{
  "type": "Feature",
  "properties": {
    "gn:admin1_code":"53",
    "gn:admin2_code":"56",
    "gn:admin3_code":"562",
    "gn:admin4_code":"56178",
    "gn:asciiname":"Sainte-Trephin",
    "gn:country_code":"FR",
    "gn:dem":121,
    "gn:feature_class":"P",
    "gn:feature_code":"PPL",
    "gn:name":"Sainte-Tr\u00e9phin",
    "gn:population":0,
    "gn:timezone":"Europe/Paris",
    "iso:country":"FR",
    "name:und_x_variant":[
        "Sainte-Tr\u00e9phine",
        "Sainte-Tr\u00e9phin"
    ],
    "wof:name":"Sainte-Trephin",
    "wof:placetype":"locality"
},
  "geometry": {"coordinates":[-2.98646,48.06446],"type":"Point"}
}