{
  "type": "Feature",
  "properties": {
    "iso:country":"FR",
    "wof:name":"Amme",
    "wof:placetype":"neighbourhood"
},
  "geometry": {"coordinates":[7.69981022435255,48.58977480657077],"type":"Point"}
}