{
  "type": "Feature",
  "properties": {
    "iso:country":"FR",
    "name:ceb_x_preferred":[
        "Amme J\u00f5gi"
    ],
    "name:chv_x_preferred":[
        "\u0410\u043c\u043c\u0435"
    ],
    "name:deu_x_preferred":[
        "Amme"
    ],
    "name:est_x_preferred":[
        "Amme j\u00f5gi"
    ],
    "name:glg_x_preferred":[
        "R\u00edo Amme"
    ],
    "name:lit_x_preferred":[
        "Am\u0117"
    ],
    "name:pol_x_preferred":[
        "Amme"
    ],
    "name:por_x_preferred":[
        "Rio Amme"
    ],
    "name:rus_x_preferred":[
        "\u0410\u043c\u043c\u0435"
    ],
    "name:srp_x_preferred":[
        "\u0410\u043c\u0435"
    ],
    "name:swe_x_preferred":[
        "Amme j\u00f5gi"
    ],
    "name:zho_x_preferred":[
        "\u963f\u6885\u6cb3"
    ],
    "wof:name":"Amme",
    "wof:placetype":"neighbourhood"
},
  "geometry": {"coordinates":[7.69981022435255,48.58977480657077],"type":"Point"}
}