{
  "type": "Feature",
  "properties": {
    "gn:admin1_code":"93",
    "gn:admin2_code":"05",
    "gn:admin3_code":"052",
    "gn:admin4_code":"05086",
    "gn:asciiname":"Vaucluse",
    "gn:country_code":"FR",
    "gn:dem":929,
    "gn:feature_class":"P",
    "gn:feature_code":"PPL",
    "gn:name":"Vaucluse",
    "gn:population":0,
    "gn:timezone":"Europe/Paris",
    "iso:country":"FR",
    "wof:name":"Vaucluse",
    "wof:placetype":"locality"
},
  "geometry": {"coordinates":[5.61142,44.3773],"type":"Point"}
}