{
  "type": "Feature",
  "properties": {
    "gn:admin1_code":"84",
    "gn:admin2_code":"38",
    "gn:admin3_code":"382",
    "gn:admin4_code":"38222",
    "gn:asciiname":"La Daviere",
    "gn:country_code":"FR",
    "gn:dem":463,
    "gn:feature_class":"P",
    "gn:feature_code":"PPL",
    "gn:name":"La Davi\u00e8re",
    "gn:population":0,
    "gn:timezone":"Europe/Paris",
    "iso:country":"FR",
    "wof:name":"La Daviere",
    "wof:placetype":"locality"
},
  "geometry": {"coordinates":[5.61276,45.43523],"type":"Point"}
}