{
  "type": "Feature",
  "properties": {
    "gn:admin1_code":"94",
    "gn:admin2_code":"2B",
    "gn:admin3_code":"2B3",
    "gn:admin4_code":"2B135",
    "gn:asciiname":"Altiani",
    "gn:country_code":"FR",
    "gn:dem":542,
    "gn:feature_class":"P",
    "gn:feature_code":"PPL",
    "gn:name":"Altiani",
    "gn:population":0,
    "gn:timezone":"Europe/Paris",
    "iso:country":"FR",
    "name:cat_x_preferred":[
        "Altiani"
    ],
    "name:ceb_x_preferred":[
        "Altiani"
    ],
    "name:cos_x_preferred":[
        "Altiani"
    ],
    "name:deu_x_preferred":[
        "Altiani"
    ],
    "name:eus_x_preferred":[
        "Altiani"
    ],
    "name:fas_x_preferred":[
        "\u0627\u0644\u062a\u06cc\u0627\u0646\u06cc"
    ],
    "name:fra_x_preferred":[
        "Altiani"
    ],
    "name:hun_x_preferred":[
        "Altiani"
    ],
    "name:ita_x_preferred":[
        "Altiani"
    ],
    "name:kaz_x_preferred":[
        "\u0410\u043b\u044c\u0442\u0438\u0430\u043d\u0438"
    ],
    "name:lat_x_preferred":[
        "Altiani"
    ],
    "name:lmo_x_preferred":[
        "Altiani"
    ],
    "name:mlg_x_preferred":[
        "Altiani"
    ],
    "name:msa_x_preferred":[
        "Altiani"
    ],
    "name:nld_x_preferred":[
        "Altiani"
    ],
    "name:nor_x_preferred":[
        "Altiani"
    ],
    "name:oci_x_preferred":[
        "Altiani"
    ],
    "name:pol_x_preferred":[
        "Altiani"
    ],
    "name:por_x_preferred":[
        "Altiani"
    ],
    "name:rus_x_preferred":[
        "\u0410\u043b\u044c\u0442\u0438\u0430\u043d\u0438"
    ],
    "name:slk_x_preferred":[
        "Altiani"
    ],
    "name:slv_x_preferred":[
        "Altiani"
    ],
    "name:spa_x_preferred":[
        "Altiani"
    ],
    "name:srp_x_preferred":[
        "\u0410\u043b\u0442\u0438\u0458\u0430\u043d\u0438"
    ],
    "name:swe_x_preferred":[
        "Altiani"
    ],
    "name:ukr_x_preferred":[
        "\u0410\u043b\u044c\u0442\u0456\u0430\u043d\u0456"
    ],
    "name:und_x_variant":[
        "Acciani"
    ],
    "name:vie_x_preferred":[
        "Altiani"
    ],
    "name:vol_x_preferred":[
        "Altiani"
    ],
    "name:war_x_preferred":[
        "Altiani"
    ],
    "wof:name":"Altiani",
    "wof:placetype":"locality"
},
  "geometry": {"coordinates":[9.29498,42.01095],"type":"Point"}
}