{
  "type": "Feature",
  "properties": {
    "gn:admin1_code":"84",
    "gn:admin2_code":"63",
    "gn:admin3_code":"634",
    "gn:admin4_code":"63187",
    "gn:asciiname":"Laval",
    "gn:country_code":"FR",
    "gn:dem":509,
    "gn:feature_class":"P",
    "gn:feature_code":"PPL",
    "gn:name":"Laval",
    "gn:population":0,
    "gn:timezone":"Europe/Paris",
    "iso:country":"FR",
    "wof:name":"Laval",
    "wof:placetype":"locality"
},
  "geometry": {"coordinates":[2.86319,46.25209],"type":"Point"}
}