{
  "type": "Feature",
  "properties": {
    "gn:admin1_code":"75",
    "gn:admin2_code":"19",
    "gn:admin3_code":"193",
    "gn:admin4_code":"19071",
    "gn:asciiname":"Rouffiat",
    "gn:country_code":"FR",
    "gn:dem":807,
    "gn:feature_class":"P",
    "gn:feature_code":"PPL",
    "gn:name":"Rouffiat",
    "gn:population":0,
    "gn:timezone":"Europe/Paris",
    "iso:country":"FR",
    "wof:name":"Rouffiat",
    "wof:placetype":"locality"
},
  "geometry": {"coordinates":[2.06071,45.50489],"type":"Point"}
}