{
  "type": "Feature",
  "properties": {
    "gn:admin1_code":"53",
    "gn:admin2_code":"29",
    "gn:admin3_code":"293",
    "gn:admin4_code":"29199",
    "gn:asciiname":"Quilidien",
    "gn:country_code":"FR",
    "gn:dem":162,
    "gn:feature_class":"P",
    "gn:feature_code":"PPL",
    "gn:name":"Quilidien",
    "gn:population":0,
    "gn:timezone":"Europe/Paris",
    "iso:country":"FR",
    "wof:name":"Quilidien",
    "wof:placetype":"locality"
},
  "geometry": {"coordinates":[-3.68333,48.56667],"type":"Point"}
}