{
  "type": "Feature",
  "properties": {
    "gn:admin1_code":"75",
    "gn:admin2_code":"23",
    "gn:admin3_code":"232",
    "gn:admin4_code":"23139",
    "gn:asciiname":"Laboutant",
    "gn:country_code":"FR",
    "gn:dem":315,
    "gn:feature_class":"P",
    "gn:feature_code":"PPL",
    "gn:name":"Laboutant",
    "gn:population":0,
    "gn:timezone":"Europe/Paris",
    "iso:country":"FR",
    "wof:name":"Laboutant",
    "wof:placetype":"locality"
},
  "geometry": {"coordinates":[1.9616,46.36274],"type":"Point"}
}