{
  "type": "Feature",
  "properties": {
    "gn:admin1_code":"84",
    "gn:admin2_code":"03",
    "gn:admin3_code":"031",
    "gn:admin4_code":"03206",
    "gn:asciiname":"Le Peux",
    "gn:country_code":"FR",
    "gn:dem":482,
    "gn:feature_class":"P",
    "gn:feature_code":"PPL",
    "gn:name":"Le Peux",
    "gn:population":0,
    "gn:timezone":"Europe/Paris",
    "iso:country":"FR",
    "wof:name":"Le Peux",
    "wof:placetype":"locality"
},
  "geometry": {"coordinates":[2.57037,46.18898],"type":"Point"}
}