{
  "type": "Feature",
  "properties": {
    "gn:admin1_code":"53",
    "gn:admin2_code":"56",
    "gn:admin3_code":"561",
    "gn:admin4_code":"56121",
    "gn:asciiname":"Keryvaland",
    "gn:country_code":"FR",
    "gn:dem":23,
    "gn:feature_class":"P",
    "gn:feature_code":"PPL",
    "gn:name":"Keryvaland",
    "gn:population":0,
    "gn:timezone":"Europe/Paris",
    "iso:country":"FR",
    "wof:name":"Keryvaland",
    "wof:placetype":"locality"
},
  "geometry": {"coordinates":[-3.38834,47.73993],"type":"Point"}
}