{
  "type": "Feature",
  "properties": {
    "gn:admin1_code":"84",
    "gn:admin2_code":"15",
    "gn:admin3_code":"153",
    "gn:admin4_code":"15105.0",
    "gn:asciiname":"Combaliboeuf",
    "gn:country_code":"FR",
    "gn:dem":1064,
    "gn:feature_class":"P",
    "gn:feature_code":"PPL",
    "gn:name":"Combaliboeuf",
    "gn:population":0,
    "gn:timezone":"Europe/Paris",
    "iso:country":"FR",
    "wof:name":"Combaliboeuf",
    "wof:placetype":"locality"
},
  "geometry": {"coordinates":[3.07745,45.33057],"type":"Point"}
}