{
  "type": "Feature",
  "properties": {
    "gn:country":"FR",
    "gn:fcode":"PPL",
    "gn:population":295,
    "iso:country":"FR",
    "name:ceb_x_preferred":[
        "Espinasse"
    ],
    "name:deu_x_preferred":[
        "Espinasse"
    ],
    "name:fra_x_preferred":[
        "Espinasse"
    ],
    "name:ita_x_preferred":[
        "Espinasse"
    ],
    "name:nds_x_preferred":[
        "Espinasse"
    ],
    "name:nld_x_preferred":[
        "Espinasse"
    ],
    "name:oci_x_preferred":[
        "Espinassa"
    ],
    "name:pms_x_preferred":[
        "Espinasse"
    ],
    "name:pol_x_preferred":[
        "Espinasse"
    ],
    "name:por_x_preferred":[
        "Espinasse"
    ],
    "name:rus_x_preferred":[
        "\u042d\u0441\u043f\u0438\u043d\u0430\u0441"
    ],
    "name:slk_x_preferred":[
        "Espinasse"
    ],
    "name:spa_x_preferred":[
        "Espinasse"
    ],
    "name:swe_x_preferred":[
        "Espinasse"
    ],
    "name:ukr_x_preferred":[
        "\u0415\u0441\u043f\u0456\u043d\u0430\u0441\u0441"
    ],
    "qs_pg:aaroncc":"FR",
    "qs_pg:gn_country":"FR",
    "qs_pg:gn_fcode":"PPL",
    "qs_pg:gn_pop":295,
    "qs_pg:name":"Espinasse",
    "qs_pg:photos_9r":0,
    "qs_pg:photos_sr":0,
    "qs_pg:pop_sr":2,
    "qs_pg:qs_pg_placetype":"locality",
    "wof:name":"Espinasse",
    "wof:placetype":"neighbourhood",
    "wof:population":295
},
  "geometry": {"coordinates":[3.61314,45.53057],"type":"Point"}
}