{
  "type": "Feature",
  "properties": {
    "gn:admin1_code":"28",
    "gn:admin2_code":"76",
    "gn:admin3_code":"763",
    "gn:admin4_code":"76020",
    "gn:asciiname":"La Greve",
    "gn:country_code":"FR",
    "gn:dem":5,
    "gn:feature_class":"P",
    "gn:feature_code":"PPL",
    "gn:name":"La Gr\u00e8ve",
    "gn:population":0,
    "gn:timezone":"Europe/Paris",
    "iso:country":"FR",
    "wof:name":"La Greve",
    "wof:placetype":"locality"
},
  "geometry": {"coordinates":[0.88492,49.437],"type":"Point"}
}