{
  "type": "Feature",
  "properties": {
    "gn:admin1_code":"28",
    "gn:admin2_code":"76",
    "gn:admin3_code":"761",
    "gn:admin4_code":"76655",
    "gn:asciiname":"Saint-Leger",
    "gn:country_code":"FR",
    "gn:dem":32,
    "gn:feature_class":"P",
    "gn:feature_code":"PPL",
    "gn:name":"Saint-L\u00e9ger",
    "gn:population":0,
    "gn:timezone":"Europe/Paris",
    "iso:country":"FR",
    "name:und_x_variant":[
        "Saint-L\u00e9ger"
    ],
    "wof:name":"Saint-Leger",
    "wof:placetype":"locality"
},
  "geometry": {"coordinates":[0.6983,49.86784],"type":"Point"}
}