{
  "type": "Feature",
  "properties": {
    "gn:admin1_code":"52",
    "gn:admin2_code":"44",
    "gn:admin3_code":"443",
    "gn:admin4_code":"44154",
    "gn:asciiname":"Le Fief",
    "gn:country_code":"FR",
    "gn:dem":17,
    "gn:feature_class":"P",
    "gn:feature_code":"PPL",
    "gn:name":"Le Fief",
    "gn:population":0,
    "gn:timezone":"Europe/Paris",
    "iso:country":"FR",
    "wof:name":"Le Fief",
    "wof:placetype":"locality"
},
  "geometry": {"coordinates":[-2.16496,47.23227],"type":"Point"}
}