{
  "type": "Feature",
  "properties": {
    "gn:admin1_code":"53",
    "gn:admin2_code":"56",
    "gn:admin3_code":"562",
    "gn:admin4_code":"56102",
    "gn:asciiname":"Bogas",
    "gn:country_code":"FR",
    "gn:dem":88,
    "gn:feature_class":"P",
    "gn:feature_code":"PPL",
    "gn:name":"Bogas",
    "gn:population":0,
    "gn:timezone":"Europe/Paris",
    "iso:country":"FR",
    "wof:name":"Bogas",
    "wof:placetype":"locality"
},
  "geometry": {"coordinates":[-2.59188,48.00101],"type":"Point"}
}