{
  "type": "Feature",
  "properties": {
    "gn:admin1_code":"76",
    "gn:admin2_code":"30",
    "gn:admin3_code":"301",
    "gn:admin4_code":"30077",
    "gn:asciiname":"Malataverne",
    "gn:country_code":"FR",
    "gn:dem":155,
    "gn:feature_class":"P",
    "gn:feature_code":"PPL",
    "gn:name":"Malataverne",
    "gn:population":0,
    "gn:timezone":"Europe/Paris",
    "iso:country":"FR",
    "wof:name":"Malataverne",
    "wof:placetype":"locality"
},
  "geometry": {"coordinates":[4.03126,44.15692],"type":"Point"}
}