{
  "type": "Feature",
  "properties": {
    "gn:admin1_code":"76",
    "gn:admin2_code":"30",
    "gn:admin3_code":"301",
    "gn:admin4_code":"30077",
    "gn:asciiname":"Malataverne",
    "gn:country_code":"FR",
    "gn:dem":155,
    "gn:feature_class":"P",
    "gn:feature_code":"PPL",
    "gn:name":"Malataverne",
    "gn:population":0,
    "gn:timezone":"Europe/Paris",
    "iso:country":"FR",
    "name:bug_x_preferred":[
        "Malataverne"
    ],
    "name:cat_x_preferred":[
        "Malatav\u00e8rna"
    ],
    "name:ceb_x_preferred":[
        "Malataverne"
    ],
    "name:deu_x_preferred":[
        "Malataverne"
    ],
    "name:eus_x_preferred":[
        "Malataverne"
    ],
    "name:fra_x_preferred":[
        "Malataverne"
    ],
    "name:hun_x_preferred":[
        "Malataverne"
    ],
    "name:ita_x_preferred":[
        "Malataverne"
    ],
    "name:lat_x_preferred":[
        "Malataverne"
    ],
    "name:lmo_x_preferred":[
        "Malataverne"
    ],
    "name:ltz_x_preferred":[
        "Malataverne"
    ],
    "name:mlg_x_preferred":[
        "Malataverne"
    ],
    "name:msa_x_preferred":[
        "Malataverne"
    ],
    "name:nld_x_preferred":[
        "Malataverne"
    ],
    "name:oci_x_preferred":[
        "Malatav\u00e8rna"
    ],
    "name:pms_x_preferred":[
        "Malataverne"
    ],
    "name:pol_x_preferred":[
        "Malataverne"
    ],
    "name:por_x_preferred":[
        "Malataverne"
    ],
    "name:ron_x_preferred":[
        "Malataverne"
    ],
    "name:slk_x_preferred":[
        "Malataverne"
    ],
    "name:spa_x_preferred":[
        "Malataverne"
    ],
    "name:swe_x_preferred":[
        "Malataverne"
    ],
    "name:ukr_x_preferred":[
        "\u041c\u0430\u043b\u0430\u0442\u0430\u0432\u0435\u0440\u043d"
    ],
    "name:uzb_x_preferred":[
        "Malataverne"
    ],
    "name:vie_x_preferred":[
        "Malataverne"
    ],
    "name:vol_x_preferred":[
        "Malataverne"
    ],
    "name:war_x_preferred":[
        "Malataverne"
    ],
    "name:zho_x_preferred":[
        "\u9a6c\u62c9\u5854\u97e6\u5c14\u8bb7"
    ],
    "wof:name":"Malataverne",
    "wof:placetype":"locality"
},
  "geometry": {"coordinates":[4.03126,44.15692],"type":"Point"}
}