{
  "type": "Feature",
  "properties": {
    "gn:admin1_code":"75",
    "gn:admin2_code":"24",
    "gn:admin3_code":"241",
    "gn:admin4_code":"24445",
    "gn:asciiname":"Vignettes",
    "gn:country_code":"FR",
    "gn:dem":147,
    "gn:feature_class":"P",
    "gn:feature_code":"PPL",
    "gn:name":"Vignettes",
    "gn:population":0,
    "gn:timezone":"Europe/Paris",
    "iso:country":"FR",
    "wof:name":"Vignettes",
    "wof:placetype":"locality"
},
  "geometry": {"coordinates":[0.68707,44.89716],"type":"Point"}
}