{
  "type": "Feature",
  "properties": {
    "gn:admin1_code":"53",
    "gn:admin2_code":"22",
    "gn:admin3_code":"224",
    "gn:admin4_code":"22173",
    "gn:asciiname":"La Cotentin",
    "gn:country_code":"FR",
    "gn:dem":56,
    "gn:feature_class":"P",
    "gn:feature_code":"PPL",
    "gn:name":"La Cotentin",
    "gn:population":0,
    "gn:timezone":"Europe/Paris",
    "iso:country":"FR",
    "name:und_x_variant":[
        "Cotentin",
        "Le Cotentin",
        "La Cotentin"
    ],
    "wof:name":"La Cotentin",
    "wof:placetype":"locality"
},
  "geometry": {"coordinates":[-2.59209,48.55475],"type":"Point"}
}