{
  "type": "Feature",
  "properties": {
    "gn:admin1_code":"75",
    "gn:admin2_code":"24",
    "gn:admin3_code":"244",
    "gn:admin4_code":"24117",
    "gn:asciiname":"Contezat",
    "gn:country_code":"FR",
    "gn:dem":301,
    "gn:feature_class":"P",
    "gn:feature_code":"PPL",
    "gn:name":"Contezat",
    "gn:population":0,
    "gn:timezone":"Europe/Paris",
    "iso:country":"FR",
    "wof:name":"Contezat",
    "wof:placetype":"locality"
},
  "geometry": {"coordinates":[1.34584,45.09219],"type":"Point"}
}