{
  "type": "Feature",
  "properties": {
    "gn:admin1_code":"84",
    "gn:admin2_code":"03",
    "gn:admin3_code":"031",
    "gn:admin4_code":"03070",
    "gn:asciiname":"Mauvisse",
    "gn:country_code":"FR",
    "gn:dem":333,
    "gn:feature_class":"P",
    "gn:feature_code":"PPL",
    "gn:name":"Mauvisse",
    "gn:population":0,
    "gn:timezone":"Europe/Paris",
    "iso:country":"FR",
    "name:und_x_variant":[
        "Mauvise",
        "Mauvisse"
    ],
    "wof:name":"Mauvisse",
    "wof:placetype":"locality"
},
  "geometry": {"coordinates":[2.9361,46.42772],"type":"Point"}
}