{
  "type": "Feature",
  "properties": {
    "gn:admin1_code":"75",
    "gn:admin2_code":"23",
    "gn:admin3_code":"232",
    "gn:admin4_code":"23258",
    "gn:asciiname":"Vareilles",
    "gn:country_code":"FR",
    "gn:dem":364,
    "gn:feature_class":"P",
    "gn:feature_code":"PPL",
    "gn:name":"Vareilles",
    "gn:population":264,
    "gn:timezone":"Europe/Paris",
    "iso:country":"FR",
    "wof:name":"Vareilles",
    "wof:placetype":"locality",
    "wof:population":264
},
  "geometry": {"coordinates":[1.47753,46.29991],"type":"Point"}
}