{
  "type": "Feature",
  "properties": {
    "gn:admin1_code":"75",
    "gn:admin2_code":"23",
    "gn:admin3_code":"232",
    "gn:admin4_code":"23258",
    "gn:asciiname":"Vareilles",
    "gn:country_code":"FR",
    "gn:dem":364,
    "gn:feature_class":"P",
    "gn:feature_code":"PPL",
    "gn:name":"Vareilles",
    "gn:population":264,
    "gn:timezone":"Europe/Paris",
    "iso:country":"FR",
    "name:ceb_x_preferred":[
        "Vareilles"
    ],
    "name:deu_x_preferred":[
        "Vareilles"
    ],
    "name:epo_x_preferred":[
        "Vareilles"
    ],
    "name:fra_x_preferred":[
        "Vareilles"
    ],
    "name:ita_x_preferred":[
        "Vareilles"
    ],
    "name:nds_x_preferred":[
        "Vareilles"
    ],
    "name:nld_x_preferred":[
        "Vareilles"
    ],
    "name:oci_x_preferred":[
        "Vareilles"
    ],
    "name:pms_x_preferred":[
        "Vareilles"
    ],
    "name:pol_x_preferred":[
        "Vareilles"
    ],
    "name:slk_x_preferred":[
        "Vareilles"
    ],
    "name:spa_x_preferred":[
        "Vareilles"
    ],
    "name:swe_x_preferred":[
        "Vareilles"
    ],
    "name:ukr_x_preferred":[
        "\u0412\u0430\u0440\u0435\u0439"
    ],
    "wof:name":"Vareilles",
    "wof:placetype":"locality",
    "wof:population":264
},
  "geometry": {"coordinates":[1.47753,46.29991],"type":"Point"}
}