{
  "type": "Feature",
  "properties": {
    "frgov:code_epci":"200067510",
    "frgov:insee_arr":"2",
    "frgov:insee_com":"23258",
    "frgov:insee_dep":"23",
    "frgov:insee_reg":"75",
    "frgov:nom_com":"Vareilles",
    "frgov:nom_com_m":"VAREILLES",
    "frgov:nom_dep":"CREUSE",
    "frgov:nom_reg":"NOUVELLE-AQUITAINE",
    "frgov:statut":"Commune simple",
    "gn:admin1_code":"75",
    "gn:admin2_code":"23",
    "gn:admin3_code":"232",
    "gn:admin4_code":"23258",
    "gn:asciiname":"Vareilles",
    "gn:country_code":"FR",
    "gn:dem":364,
    "gn:feature_class":"P",
    "gn:feature_code":"PPL",
    "gn:name":"Vareilles",
    "gn:population":264,
    "gn:timezone":"Europe/Paris",
    "iso:country":"FR",
    "name:cat_x_preferred":[
        "Varelhas e Boch\u00e9s"
    ],
    "name:ceb_x_preferred":[
        "Vareilles"
    ],
    "name:deu_x_preferred":[
        "Vareilles"
    ],
    "name:epo_x_preferred":[
        "Vareilles"
    ],
    "name:fas_x_preferred":[
        "\u0648\u0631\u06cc\u0644\u0633\u060c \u06a9\u0631\u0648\u0633"
    ],
    "name:fra_x_preferred":[
        "Vareilles"
    ],
    "name:ita_x_preferred":[
        "Vareilles"
    ],
    "name:kaz_x_preferred":[
        "\u0412\u0430\u0440\u0435\u0439"
    ],
    "name:nds_x_preferred":[
        "Vareilles"
    ],
    "name:nld_x_preferred":[
        "Vareilles"
    ],
    "name:oci_x_preferred":[
        "Vareilles"
    ],
    "name:oci_x_variant":[
        "Vareilles"
    ],
    "name:pms_x_preferred":[
        "Vareilles"
    ],
    "name:pol_x_preferred":[
        "Vareilles"
    ],
    "name:rus_x_preferred":[
        "\u0412\u0430\u0440\u0435\u0439"
    ],
    "name:slk_x_preferred":[
        "Vareilles"
    ],
    "name:spa_x_preferred":[
        "Vareilles"
    ],
    "name:swe_x_preferred":[
        "Vareilles"
    ],
    "name:ukr_x_preferred":[
        "\u0412\u0430\u0440\u0435\u0439"
    ],
    "name:zho_x_preferred":[
        "\u74e6\u96f7\u83b1"
    ],
    "qs:a0":"France",
    "qs:a1":"CREUSE",
    "qs:a1_lc":"23",
    "qs:a1r":"LIMOUSIN",
    "qs:a1r_lc":"74",
    "qs:a2_lc":"25",
    "qs:a2r_lc":"2",
    "qs:adm0":"France",
    "qs:adm0_a3":"FRA",
    "qs:la":"VAREILLES",
    "qs:la_lc":"23258",
    "qs:level":"localadmin",
    "qs:type":"Commune simple",
    "wof:coterminous":[
        404367639
    ],
    "wof:name":"Vareilles",
    "wof:placetype":"locality",
    "wof:placetype_local":"Commune simple",
    "wof:population":264
},
  "geometry": {"coordinates":[1.47753,46.29991],"type":"Point"}
}