{
  "type": "Feature",
  "properties": {
    "frgov:code_epci":"200072643",
    "frgov:insee_arr":"2",
    "frgov:insee_com":"31398",
    "frgov:insee_dep":"31",
    "frgov:insee_reg":"76",
    "frgov:nom_com":"Nizan-Gesse",
    "frgov:nom_com_m":"NIZAN-GESSE",
    "frgov:nom_dep":"HAUTE-GARONNE",
    "frgov:nom_reg":"OCCITANIE",
    "frgov:statut":"Commune simple",
    "gn:admin1_code":"76",
    "gn:admin2_code":"31",
    "gn:admin3_code":"312",
    "gn:admin4_code":"31398",
    "gn:asciiname":"Nizan-Gesse",
    "gn:country_code":"FR",
    "gn:dem":375,
    "gn:feature_class":"P",
    "gn:feature_code":"PPL",
    "gn:name":"Nizan-Gesse",
    "gn:population":0,
    "gn:timezone":"Europe/Paris",
    "iso:country":"FR",
    "name:bug_x_preferred":[
        "Nizan-Gesse"
    ],
    "name:ceb_x_preferred":[
        "Nizan-Gesse"
    ],
    "name:deu_x_preferred":[
        "Nizan-Gesse"
    ],
    "name:eus_x_preferred":[
        "Nizan-Gesse"
    ],
    "name:fra_x_preferred":[
        "Nizan-Gesse"
    ],
    "name:hun_x_preferred":[
        "Nizan-Gesse"
    ],
    "name:ind_x_preferred":[
        "Nizan-Gesse"
    ],
    "name:ita_x_preferred":[
        "Nizan-Gesse"
    ],
    "name:lat_x_preferred":[
        "Nizan-Gesse"
    ],
    "name:msa_x_preferred":[
        "Nizan-Gesse"
    ],
    "name:nld_x_preferred":[
        "Nizan-Gesse"
    ],
    "name:pol_x_preferred":[
        "Nizan-Gesse"
    ],
    "name:ron_x_preferred":[
        "Nizan-Gesse"
    ],
    "name:rus_x_preferred":[
        "\u041d\u0438\u0437\u0430\u043d-\u0416\u0435\u0441"
    ],
    "name:slk_x_preferred":[
        "Nizan-Gesse"
    ],
    "name:spa_x_preferred":[
        "Nizan-Gesse"
    ],
    "name:swe_x_preferred":[
        "Nizan-Gesse"
    ],
    "name:ukr_x_preferred":[
        "\u041d\u0456\u0437\u0430\u043d-\u0416\u0435\u0441\u0441"
    ],
    "name:und_x_variant":[
        "Nizan-sur-Gesse",
        "Nizan",
        "Nizan-Gesse"
    ],
    "name:vie_x_preferred":[
        "Nizan-Gesse"
    ],
    "name:vol_x_preferred":[
        "Nizan-Gesse"
    ],
    "name:war_x_preferred":[
        "Nizan-Gesse"
    ],
    "name:zho_x_preferred":[
        "\u5c3c\u85cf\u70ed\u65af"
    ],
    "qs:a0":"France",
    "qs:a1":"HAUTE-GARONNE",
    "qs:a1_lc":"31",
    "qs:a1r":"MIDI-PYRENEES",
    "qs:a1r_lc":"73",
    "qs:a2_lc":"06",
    "qs:a2r_lc":"2",
    "qs:adm0":"France",
    "qs:adm0_a3":"FRA",
    "qs:la":"NIZAN-GESSE",
    "qs:la_lc":"31398",
    "qs:level":"localadmin",
    "qs:type":"Commune simple",
    "wof:coterminous":[
        404414471
    ],
    "wof:name":"Nizan-Gesse",
    "wof:placetype":"locality",
    "wof:placetype_local":"Commune simple"
},
  "geometry": {"coordinates":[0.59581,43.23229],"type":"Point"}
}