{
  "type": "Feature",
  "properties": {
    "gn:admin1_code":"76",
    "gn:admin2_code":"31",
    "gn:admin3_code":"312",
    "gn:admin4_code":"31398",
    "gn:asciiname":"Nizan-Gesse",
    "gn:country_code":"FR",
    "gn:dem":375,
    "gn:feature_class":"P",
    "gn:feature_code":"PPL",
    "gn:name":"Nizan-Gesse",
    "gn:population":0,
    "gn:timezone":"Europe/Paris",
    "iso:country":"FR",
    "name:und_x_variant":[
        "Nizan-sur-Gesse",
        "Nizan",
        "Nizan-Gesse"
    ],
    "wof:name":"Nizan-Gesse",
    "wof:placetype":"locality"
},
  "geometry": {"coordinates":[0.59581,43.23229],"type":"Point"}
}