{
  "type": "Feature",
  "properties": {
    "gn:admin1_code":"24",
    "gn:admin2_code":"18",
    "gn:admin3_code":"181",
    "gn:admin4_code":"18144",
    "gn:asciiname":"Le Petit Poisson",
    "gn:country_code":"FR",
    "gn:dem":316,
    "gn:feature_class":"P",
    "gn:feature_code":"PPL",
    "gn:name":"Le Petit Poisson",
    "gn:population":0,
    "gn:timezone":"Europe/Paris",
    "iso:country":"FR",
    "wof:name":"Le Petit Poisson",
    "wof:placetype":"locality"
},
  "geometry": {"coordinates":[2.74562,47.37057],"type":"Point"}
}