{
  "type": "Feature",
  "properties": {
    "gn:admin1_code":"53",
    "gn:asciiname":"Talavouron",
    "gn:country_code":"FR",
    "gn:dem":-9999,
    "gn:feature_class":"P",
    "gn:feature_code":"PPL",
    "gn:name":"Talavouron",
    "gn:population":0,
    "gn:timezone":"Europe/Paris",
    "iso:country":"FR",
    "wof:name":"Talavouron",
    "wof:placetype":"locality"
},
  "geometry": {"coordinates":[-4.41667,48.33333],"type":"Point"}
}