{
  "type": "Feature",
  "properties": {
    "gn:admin1_code":"84",
    "gn:admin2_code":"63",
    "gn:admin3_code":"633",
    "gn:admin4_code":"63054",
    "gn:asciiname":"Lavord",
    "gn:country_code":"FR",
    "gn:dem":375,
    "gn:feature_class":"P",
    "gn:feature_code":"PPL",
    "gn:name":"Lavord",
    "gn:population":0,
    "gn:timezone":"Europe/Paris",
    "iso:country":"FR",
    "wof:name":"Lavord",
    "wof:placetype":"locality"
},
  "geometry": {"coordinates":[3.27092,45.52097],"type":"Point"}
}