{
  "type": "Feature",
  "properties": {
    "frgov:code_epci":"243600343",
    "frgov:insee_arr":"1",
    "frgov:insee_com":"36246",
    "frgov:insee_dep":"36",
    "frgov:insee_reg":"24",
    "frgov:nom_com":"Villiers",
    "frgov:nom_com_m":"VILLIERS",
    "frgov:nom_dep":"INDRE",
    "frgov:nom_reg":"CENTRE-VAL DE LOIRE",
    "frgov:statut":"Commune simple",
    "gn:admin1_code":"24",
    "gn:admin2_code":"36",
    "gn:admin3_code":"361",
    "gn:admin4_code":"36246",
    "gn:asciiname":"Villiers",
    "gn:country_code":"FR",
    "gn:dem":146,
    "gn:feature_class":"P",
    "gn:feature_code":"PPL",
    "gn:name":"Villiers",
    "gn:population":0,
    "gn:timezone":"Europe/Paris",
    "iso:country":"FR",
    "name:als_x_preferred":[
        "Villiers"
    ],
    "name:bre_x_preferred":[
        "Villiers"
    ],
    "name:ceb_x_preferred":[
        "Villiers"
    ],
    "name:deu_x_preferred":[
        "Villiers"
    ],
    "name:epo_x_preferred":[
        "Villiers"
    ],
    "name:fra_x_preferred":[
        "Villiers"
    ],
    "name:ita_x_preferred":[
        "Villiers"
    ],
    "name:jpn_x_preferred":[
        "\u30f4\u30a3\u30ea\u30a2\u30fc\u30ba"
    ],
    "name:nds_x_preferred":[
        "Villiers"
    ],
    "name:nld_x_preferred":[
        "Villiers"
    ],
    "name:pms_x_preferred":[
        "Villiers"
    ],
    "name:pol_x_preferred":[
        "Villiers"
    ],
    "name:por_x_preferred":[
        "Villiers"
    ],
    "name:ron_x_preferred":[
        "Villiers"
    ],
    "name:rus_x_preferred":[
        "\u0412\u0438\u043b\u044c\u0435"
    ],
    "name:slk_x_preferred":[
        "Villiers"
    ],
    "name:spa_x_preferred":[
        "Villiers"
    ],
    "name:swe_x_preferred":[
        "Villiers"
    ],
    "name:ukr_x_preferred":[
        "\u0412\u0456\u043b\u044c\u0454"
    ],
    "name:zho_x_preferred":[
        "\u7ef4\u5229\u8036\u5c14"
    ],
    "qs:a0":"France",
    "qs:a1":"INDRE",
    "qs:a1_lc":"36",
    "qs:a1r":"CENTRE",
    "qs:a1r_lc":"24",
    "qs:a2_lc":"15",
    "qs:a2r_lc":"1",
    "qs:adm0":"France",
    "qs:adm0_a3":"FRA",
    "qs:la":"VILLIERS",
    "qs:la_lc":"36246",
    "qs:level":"localadmin",
    "qs:type":"Commune simple",
    "wof:coterminous":[
        404425761
    ],
    "wof:name":"Villiers",
    "wof:placetype":"locality",
    "wof:placetype_local":"Commune simple"
},
  "geometry": {"coordinates":[1.1849,46.88758],"type":"Point"}
}