{
  "type": "Feature",
  "properties": {
    "gn:gn_country":"FR",
    "gn:gn_fcode":"PPL",
    "gn:gn_pop":226,
    "gn:population":226,
    "iso:country":"FR",
    "name:baq_x_preferred":[
        "V\u00e9rigny"
    ],
    "name:bug_x_preferred":[
        "V\u00e9rigny"
    ],
    "name:cat_x_preferred":[
        "V\u00e9rigny"
    ],
    "name:chi_x_preferred":[
        "\u97e6\u91cc\u5c3c"
    ],
    "name:dut_x_preferred":[
        "V\u00e9rigny"
    ],
    "name:eng_x_preferred":[
        "V\u00e9rigny"
    ],
    "name:fre_x_preferred":[
        "V\u00e9rigny"
    ],
    "name:ger_x_preferred":[
        "V\u00e9rigny"
    ],
    "name:hun_x_preferred":[
        "V\u00e9rigny"
    ],
    "name:ind_x_preferred":[
        "V\u00e9rigny"
    ],
    "name:ita_x_preferred":[
        "V\u00e9rigny"
    ],
    "name:lat_x_preferred":[
        "V\u00e9rigny"
    ],
    "name:may_x_preferred":[
        "V\u00e9rigny"
    ],
    "name:mlg_x_preferred":[
        "V\u00e9rigny"
    ],
    "name:nan_x_preferred":[
        "V\u00e9rigny"
    ],
    "name:oci_x_preferred":[
        "V\u00e9rigny"
    ],
    "name:pms_x_preferred":[
        "V\u00e9rigny"
    ],
    "name:pol_x_preferred":[
        "V\u00e9rigny"
    ],
    "name:por_x_preferred":[
        "V\u00e9rigny"
    ],
    "name:rum_x_preferred":[
        "V\u00e9rigny"
    ],
    "name:slo_x_preferred":[
        "V\u00e9rigny"
    ],
    "name:spa_x_preferred":[
        "V\u00e9rigny"
    ],
    "name:swe_x_preferred":[
        "V\u00e9rigny"
    ],
    "name:ukr_x_preferred":[
        "\u0412\u0435\u0440\u0438\u043d\u044c\u0457"
    ],
    "name:uzb_x_preferred":[
        "V\u00e9rigny"
    ],
    "name:vie_x_preferred":[
        "V\u00e9rigny"
    ],
    "name:vol_x_preferred":[
        "V\u00e9rigny"
    ],
    "name:war_x_preferred":[
        "V\u00e9rigny"
    ],
    "qs_pg:aaroncc":"FR",
    "qs_pg:gn_country":"FR",
    "qs_pg:gn_fcode":"PPL",
    "qs_pg:gn_pop":226,
    "qs_pg:name":"V\u00e9rigny",
    "qs_pg:name_adm0":"France",
    "qs_pg:name_adm1":"Centre",
    "qs_pg:photos_9k":1,
    "qs_pg:photos_9r":1,
    "qs_pg:photos_all":2,
    "qs_pg:photos_sr":0,
    "qs_pg:pop_sr":2,
    "qs_pg:qs_pg_placetype":"locality",
    "qs_pg:qs_pg_placetype_gp":"Town",
    "qs_pg:woe_adm0":23424819,
    "woe:adm0_id":23424819,
    "woe:name_adm0":"France",
    "woe:name_adm1":"Centre",
    "woe:placetype":"Town",
    "wof:name":"V\u00e9rigny",
    "wof:placetype":"neighbourhood",
    "wof:population":226
},
  "geometry": {"coordinates":[1.3231,48.51973],"type":"Point"}
}