{
  "type": "Feature",
  "properties": {
    "frgov:code_epci":"200067361",
    "frgov:insee_arr":"2",
    "frgov:insee_com":"46034",
    "frgov:insee_dep":"46",
    "frgov:insee_reg":"76",
    "frgov:nom_com":"Le Bourg",
    "frgov:nom_com_m":"LE BOURG",
    "frgov:nom_dep":"LOT",
    "frgov:nom_reg":"OCCITANIE",
    "frgov:statut":"Commune simple",
    "gn:admin1_code":"76",
    "gn:admin2_code":"46",
    "gn:admin3_code":"462",
    "gn:admin4_code":"46034",
    "gn:asciiname":"Le Bourg",
    "gn:country_code":"FR",
    "gn:dem":353,
    "gn:feature_class":"P",
    "gn:feature_code":"PPL",
    "gn:name":"Le Bourg",
    "gn:population":264,
    "gn:timezone":"Europe/Paris",
    "iso:country":"FR",
    "name:cat_x_preferred":[
        "Lo Borg"
    ],
    "name:ceb_x_preferred":[
        "Le Bourg"
    ],
    "name:deu_x_preferred":[
        "Le Bourg"
    ],
    "name:eus_x_preferred":[
        "Le Bourg"
    ],
    "name:fas_x_preferred":[
        "\u0644 \u0628\u0648\u0631\u06af"
    ],
    "name:fin_x_preferred":[
        "Le Bourg"
    ],
    "name:fra_x_preferred":[
        "Le Bourg"
    ],
    "name:hbs_x_preferred":[
        "Bourg"
    ],
    "name:hun_x_preferred":[
        "Le Bourg"
    ],
    "name:ita_x_preferred":[
        "Le Bourg"
    ],
    "name:lat_x_preferred":[
        "Le Bourg"
    ],
    "name:msa_x_preferred":[
        "Le Bourg"
    ],
    "name:nld_x_preferred":[
        "Le Bourg"
    ],
    "name:oci_x_preferred":[
        "Lo Borg"
    ],
    "name:pms_x_preferred":[
        "Le Bourg"
    ],
    "name:pol_x_preferred":[
        "Le Bourg"
    ],
    "name:por_x_preferred":[
        "Le Bourg"
    ],
    "name:ron_x_preferred":[
        "Le Bourg"
    ],
    "name:slk_x_preferred":[
        "Le Bourg"
    ],
    "name:spa_x_preferred":[
        "Le Bourg"
    ],
    "name:srp_x_preferred":[
        "\u0411\u0443\u0440"
    ],
    "name:swe_x_preferred":[
        "Le Bourg"
    ],
    "name:ukr_x_preferred":[
        "\u041b\u0435-\u0411\u0443\u0440"
    ],
    "name:vie_x_preferred":[
        "Le Bourg"
    ],
    "name:vol_x_preferred":[
        "Le Bourg"
    ],
    "name:war_x_preferred":[
        "Le Bourg"
    ],
    "name:zho_x_preferred":[
        "\u52d2\u5e03\u5c14"
    ],
    "qs:a0":"France",
    "qs:a1":"LOT",
    "qs:a1_lc":"46",
    "qs:a1r":"MIDI-PYRENEES",
    "qs:a1r_lc":"73",
    "qs:a2_lc":"13",
    "qs:a2r_lc":"2",
    "qs:adm0":"France",
    "qs:adm0_a3":"FRA",
    "qs:la":"LE BOURG",
    "qs:la_lc":"46034",
    "qs:level":"localadmin",
    "qs:type":"Commune simple",
    "wof:coterminous":[
        404354121
    ],
    "wof:name":"Le Bourg",
    "wof:placetype":"locality",
    "wof:placetype_local":"Commune simple",
    "wof:population":264
},
  "geometry": {"coordinates":[1.90429,44.70953],"type":"Point"}
}