{
  "type": "Feature",
  "properties": {
    "gn:admin1_code":"76",
    "gn:admin2_code":"46",
    "gn:admin3_code":"462",
    "gn:admin4_code":"46034",
    "gn:asciiname":"Le Bourg",
    "gn:country_code":"FR",
    "gn:dem":353,
    "gn:feature_class":"P",
    "gn:feature_code":"PPL",
    "gn:name":"Le Bourg",
    "gn:population":264,
    "gn:timezone":"Europe/Paris",
    "iso:country":"FR",
    "name:cat_x_preferred":[
        "Lo Borg"
    ],
    "name:fas_x_preferred":[
        "\u0644 \u0628\u0648\u0631\u06af"
    ],
    "name:hbs_x_preferred":[
        "Bourg"
    ],
    "name:oci_x_preferred":[
        "Lo Borg"
    ],
    "name:srp_x_preferred":[
        "\u0411\u0443\u0440"
    ],
    "name:ukr_x_preferred":[
        "\u041b\u0435-\u0411\u0443\u0440"
    ],
    "name:zho_x_preferred":[
        "\u52d2\u5e03\u5c14"
    ],
    "wof:name":"Le Bourg",
    "wof:placetype":"locality",
    "wof:population":264
},
  "geometry": {"coordinates":[1.90429,44.70953],"type":"Point"}
}