{
  "type": "Feature",
  "properties": {
    "gn:admin1_code":"24",
    "gn:admin2_code":"28",
    "gn:admin3_code":"282",
    "gn:admin4_code":"28012",
    "gn:asciiname":"Beauvoir",
    "gn:country_code":"FR",
    "gn:dem":167,
    "gn:feature_class":"P",
    "gn:feature_code":"PPL",
    "gn:name":"Beauvoir",
    "gn:population":0,
    "gn:timezone":"Europe/Paris",
    "iso:country":"FR",
    "name:bre_x_preferred":[
        "Beauvoir"
    ],
    "name:cat_x_preferred":[
        "Beauvoir"
    ],
    "name:ceb_x_preferred":[
        "Beauvoir"
    ],
    "name:ces_x_preferred":[
        "Beauvoir"
    ],
    "name:deu_x_preferred":[
        "Beauvoir"
    ],
    "name:fra_x_preferred":[
        "Beauvoir"
    ],
    "name:ita_x_preferred":[
        "Beauvoir"
    ],
    "name:jpn_x_preferred":[
        "\u30dc\u30fc\u30f4\u30a9\u30ef\u30fc\u30eb"
    ],
    "name:nds_x_preferred":[
        "Beauvoir"
    ],
    "name:nld_x_preferred":[
        "Beauvoir"
    ],
    "name:oci_x_preferred":[
        "Beauvoir"
    ],
    "name:pms_x_preferred":[
        "Beauvoir"
    ],
    "name:pol_x_preferred":[
        "Beauvoir"
    ],
    "name:por_x_preferred":[
        "Beauvoir"
    ],
    "name:ron_x_preferred":[
        "Beauvoir"
    ],
    "name:rus_x_preferred":[
        "\u0411\u043e\u0432\u0443\u0430\u0440"
    ],
    "name:slk_x_preferred":[
        "Beauvoir"
    ],
    "name:spa_x_preferred":[
        "Beauvoir"
    ],
    "name:srp_x_preferred":[
        "\u0411\u043e\u0432\u043e\u0430\u0440"
    ],
    "name:swe_x_preferred":[
        "Beauvoir"
    ],
    "name:tur_x_preferred":[
        "Beauvoir"
    ],
    "name:ukr_x_preferred":[
        "\u0411\u043e\u0432\u0443\u0430\u0440"
    ],
    "wof:name":"Beauvoir",
    "wof:placetype":"locality"
},
  "geometry": {"coordinates":[1.21147,48.1312],"type":"Point"}
}