{
  "type": "Feature",
  "properties": {
    "gn:admin1_code":"84",
    "gn:admin2_code":"38",
    "gn:admin3_code":"381",
    "gn:admin4_code":"38565.0",
    "gn:asciiname":"Morletiere",
    "gn:country_code":"FR",
    "gn:dem":203,
    "gn:feature_class":"P",
    "gn:feature_code":"PPL",
    "gn:name":"Morleti\u00e8re",
    "gn:population":0,
    "gn:timezone":"Europe/Paris",
    "iso:country":"FR",
    "name:und_x_variant":[
        "Morteli\u00e8re",
        "Morleti\u00e8re"
    ],
    "wof:name":"Morletiere",
    "wof:placetype":"locality"
},
  "geometry": {"coordinates":[5.64647,45.27731],"type":"Point"}
}