{
  "type": "Feature",
  "properties": {
    "gn:admin1_code":"75",
    "gn:admin2_code":"19",
    "gn:admin3_code":"191",
    "gn:admin4_code":"19066",
    "gn:asciiname":"Le Rieux",
    "gn:cc2":"FR",
    "gn:country_code":"FR",
    "gn:dem":220,
    "gn:feature_class":"P",
    "gn:feature_code":"PPL",
    "gn:name":"Le Rieux",
    "gn:population":0,
    "gn:timezone":"Europe/Paris",
    "iso:country":"FR",
    "name:und_x_variant":[
        "Le Rieu"
    ],
    "wof:name":"Le Rieux",
    "wof:placetype":"locality"
},
  "geometry": {"coordinates":[1.31802,45.15662],"type":"Point"}
}