{
  "type": "Feature",
  "properties": {
    "gn:admin1_code":"75",
    "gn:admin2_code":"24",
    "gn:admin3_code":"244",
    "gn:admin4_code":"24217",
    "gn:asciiname":"Laturache",
    "gn:country_code":"FR",
    "gn:dem":194,
    "gn:feature_class":"P",
    "gn:feature_code":"PPL",
    "gn:name":"Laturache",
    "gn:population":0,
    "gn:timezone":"Europe/Paris",
    "iso:country":"FR",
    "wof:name":"Laturache",
    "wof:placetype":"locality"
},
  "geometry": {"coordinates":[0.90317,44.9653],"type":"Point"}
}