{
  "type": "Feature",
  "properties": {
    "gn:admin1_code":"84",
    "gn:admin2_code":"15",
    "gn:admin3_code":"153",
    "gn:admin4_code":"15119",
    "gn:asciiname":"Bousselorgue",
    "gn:country_code":"FR",
    "gn:dem":548,
    "gn:feature_class":"P",
    "gn:feature_code":"PPL",
    "gn:name":"Bousselorgue",
    "gn:population":0,
    "gn:timezone":"Europe/Paris",
    "iso:country":"FR",
    "wof:name":"Bousselorgue",
    "wof:placetype":"locality"
},
  "geometry": {"coordinates":[3.18668,45.24237],"type":"Point"}
}