{
  "type": "Feature",
  "properties": {
    "gn:admin1_code":"11",
    "gn:admin2_code":"77",
    "gn:admin3_code":"772",
    "gn:admin4_code":"77010",
    "gn:asciiname":"Bagneaux",
    "gn:country_code":"FR",
    "gn:dem":113,
    "gn:feature_class":"P",
    "gn:feature_code":"PPL",
    "gn:name":"Bagneaux",
    "gn:population":0,
    "gn:timezone":"Europe/Paris",
    "iso:country":"FR",
    "wof:name":"Bagneaux",
    "wof:placetype":"locality"
},
  "geometry": {"coordinates":[2.93663,48.6004],"type":"Point"}
}