{
  "type": "Feature",
  "properties": {
    "gn:admin1_code":"11",
    "gn:admin2_code":"77",
    "gn:admin3_code":"772",
    "gn:admin4_code":"77010",
    "gn:asciiname":"Bagneaux",
    "gn:country_code":"FR",
    "gn:dem":113,
    "gn:feature_class":"P",
    "gn:feature_code":"PPL",
    "gn:name":"Bagneaux",
    "gn:population":0,
    "gn:timezone":"Europe/Paris",
    "iso:country":"FR",
    "name:bug_x_preferred":[
        "Bagneaux"
    ],
    "name:cat_x_preferred":[
        "Bagneaux"
    ],
    "name:ceb_x_preferred":[
        "Bagneaux"
    ],
    "name:deu_x_preferred":[
        "Bagneaux"
    ],
    "name:epo_x_preferred":[
        "Bagneaux"
    ],
    "name:eus_x_preferred":[
        "Bagneaux"
    ],
    "name:fra_x_preferred":[
        "Bagneaux"
    ],
    "name:hun_x_preferred":[
        "Bagneaux"
    ],
    "name:ita_x_preferred":[
        "Bagneaux"
    ],
    "name:kaz_x_preferred":[
        "\u0411\u0430\u043d\u044c\u043e"
    ],
    "name:lat_x_preferred":[
        "Bagneaux"
    ],
    "name:msa_x_preferred":[
        "Bagneaux"
    ],
    "name:nld_x_preferred":[
        "Bagneaux"
    ],
    "name:oci_x_preferred":[
        "Bagneaux"
    ],
    "name:pms_x_preferred":[
        "Bagneaux"
    ],
    "name:pol_x_preferred":[
        "Bagneaux"
    ],
    "name:por_x_preferred":[
        "Bagneaux"
    ],
    "name:ron_x_preferred":[
        "Bagneaux"
    ],
    "name:slk_x_preferred":[
        "Bagneaux"
    ],
    "name:spa_x_preferred":[
        "Bagneaux"
    ],
    "name:sqi_x_preferred":[
        "Bagneaux"
    ],
    "name:srp_x_preferred":[
        "\u0411\u0430\u045a\u043e"
    ],
    "name:swe_x_preferred":[
        "Bagneaux"
    ],
    "name:ukr_x_preferred":[
        "\u0411\u0430\u043d\u044c\u043e"
    ],
    "name:uzb_x_preferred":[
        "Bagneaux"
    ],
    "name:vie_x_preferred":[
        "Bagneaux"
    ],
    "name:vol_x_preferred":[
        "Bagneaux"
    ],
    "name:war_x_preferred":[
        "Bagneaux"
    ],
    "name:zho_x_preferred":[
        "\u5df4\u5c3c\u6b27"
    ],
    "wof:name":"Bagneaux",
    "wof:placetype":"locality"
},
  "geometry": {"coordinates":[2.93663,48.6004],"type":"Point"}
}