{
  "type": "Feature",
  "properties": {
    "gn:admin1_code":"84",
    "gn:admin2_code":"73",
    "gn:admin3_code":"731",
    "gn:admin4_code":"73196",
    "gn:asciiname":"Pallud",
    "gn:country_code":"FR",
    "gn:dem":501,
    "gn:feature_class":"P",
    "gn:feature_code":"PPL",
    "gn:name":"Pallud",
    "gn:population":652,
    "gn:timezone":"Europe/Paris",
    "iso:country":"FR",
    "name:rus_x_preferred":[
        "\u041f\u0430\u043b\u043b\u044e"
    ],
    "name:ukr_x_preferred":[
        "\u041f\u0430\u043b\u043b\u044e"
    ],
    "wof:name":"Pallud",
    "wof:placetype":"locality",
    "wof:population":652
},
  "geometry": {"coordinates":[6.38836,45.68398],"type":"Point"}
}