{
  "type": "Feature",
  "properties": {
    "gn:admin1_code":"84",
    "gn:admin2_code":"73",
    "gn:admin3_code":"731",
    "gn:admin4_code":"73196",
    "gn:asciiname":"Pallud",
    "gn:country_code":"FR",
    "gn:dem":501,
    "gn:feature_class":"P",
    "gn:feature_code":"PPL",
    "gn:name":"Pallud",
    "gn:population":652,
    "gn:timezone":"Europe/Paris",
    "iso:country":"FR",
    "name:cat_x_preferred":[
        "Pallud"
    ],
    "name:ceb_x_preferred":[
        "Pallud"
    ],
    "name:deu_x_preferred":[
        "Pallud"
    ],
    "name:eus_x_preferred":[
        "Pallud"
    ],
    "name:fra_x_preferred":[
        "Pallud"
    ],
    "name:hun_x_preferred":[
        "Pallud"
    ],
    "name:ita_x_preferred":[
        "Pallud"
    ],
    "name:lat_x_preferred":[
        "Palus"
    ],
    "name:lmo_x_preferred":[
        "Pallud"
    ],
    "name:msa_x_preferred":[
        "Pallud"
    ],
    "name:nld_x_preferred":[
        "Pallud"
    ],
    "name:oci_x_preferred":[
        "Pallud"
    ],
    "name:pol_x_preferred":[
        "Pallud"
    ],
    "name:ron_x_preferred":[
        "Pallud"
    ],
    "name:rus_x_preferred":[
        "\u041f\u0430\u043b\u043b\u044e"
    ],
    "name:slk_x_preferred":[
        "Pallud"
    ],
    "name:spa_x_preferred":[
        "Pallud"
    ],
    "name:swe_x_preferred":[
        "Pallud"
    ],
    "name:ukr_x_preferred":[
        "\u041f\u0430\u043b\u043b\u044e"
    ],
    "name:uzb_x_preferred":[
        "Pallud"
    ],
    "name:vie_x_preferred":[
        "Pallud"
    ],
    "name:vol_x_preferred":[
        "Pallud"
    ],
    "name:war_x_preferred":[
        "Pallud"
    ],
    "wof:name":"Pallud",
    "wof:placetype":"locality",
    "wof:population":652
},
  "geometry": {"coordinates":[6.38836,45.68398],"type":"Point"}
}