{
  "type": "Feature",
  "properties": {
    "gn:admin1_code":"75",
    "gn:admin2_code":"23",
    "gn:admin3_code":"232",
    "gn:admin4_code":"23174",
    "gn:asciiname":"Chateux",
    "gn:country_code":"FR",
    "gn:dem":419,
    "gn:feature_class":"P",
    "gn:feature_code":"PPL",
    "gn:name":"Chateux",
    "gn:population":0,
    "gn:timezone":"Europe/Paris",
    "iso:country":"FR",
    "wof:name":"Chateux",
    "wof:placetype":"locality"
},
  "geometry": {"coordinates":[2.31667,46.31667],"type":"Point"}
}