{
  "type": "Feature",
  "properties": {
    "gn:admin1_code":"84",
    "gn:admin2_code":"43",
    "gn:admin3_code":"431",
    "gn:admin4_code":"43178",
    "gn:asciiname":"Chevissiere",
    "gn:country_code":"FR",
    "gn:dem":826,
    "gn:feature_class":"P",
    "gn:feature_code":"PPL",
    "gn:name":"Chevissi\u00e8re",
    "gn:population":0,
    "gn:timezone":"Europe/Paris",
    "iso:country":"FR",
    "wof:name":"Chevissiere",
    "wof:placetype":"locality"
},
  "geometry": {"coordinates":[3.56814,45.27727],"type":"Point"}
}