{
  "type": "Feature",
  "properties": {
    "gn:admin1_code":"84",
    "gn:admin2_code":"03",
    "gn:admin3_code":"033",
    "gn:admin4_code":"03021",
    "gn:asciiname":"La Serre",
    "gn:country_code":"FR",
    "gn:dem":493,
    "gn:feature_class":"P",
    "gn:feature_code":"PPL",
    "gn:name":"La Serre",
    "gn:population":0,
    "gn:timezone":"Europe/Paris",
    "iso:country":"FR",
    "name:bre_x_preferred":[
        "La Serre"
    ],
    "name:cat_x_preferred":[
        "La S\u00e8rra"
    ],
    "name:ceb_x_preferred":[
        "La Serre"
    ],
    "name:deu_x_preferred":[
        "La Serre"
    ],
    "name:eus_x_preferred":[
        "La Serre"
    ],
    "name:fas_x_preferred":[
        "\u0644\u0627 \u0633\u0631"
    ],
    "name:fra_x_preferred":[
        "La Serre"
    ],
    "name:hun_x_preferred":[
        "La Serre"
    ],
    "name:hye_x_preferred":[
        "\u053c\u0561 \u054d\u0565\u0580"
    ],
    "name:ita_x_preferred":[
        "La Serre"
    ],
    "name:lat_x_preferred":[
        "La Serre"
    ],
    "name:msa_x_preferred":[
        "La Serre"
    ],
    "name:nld_x_preferred":[
        "La Serre"
    ],
    "name:oci_x_preferred":[
        "La S\u00e8rra"
    ],
    "name:pms_x_preferred":[
        "La Serre"
    ],
    "name:pol_x_preferred":[
        "La Serre"
    ],
    "name:por_x_preferred":[
        "La Serre"
    ],
    "name:ron_x_preferred":[
        "La Serre"
    ],
    "name:rus_x_preferred":[
        "\u041b\u0430-\u0421\u0435\u0440"
    ],
    "name:slk_x_preferred":[
        "La Serre"
    ],
    "name:spa_x_preferred":[
        "La Serre"
    ],
    "name:swe_x_preferred":[
        "La Serre"
    ],
    "name:ukr_x_preferred":[
        "\u041b\u0430-\u0421\u0435\u0440\u0440"
    ],
    "name:urd_x_preferred":[
        "\u0644\u0627 \u0633\u06cc\u0631\u06cc"
    ],
    "name:vie_x_preferred":[
        "La Serre"
    ],
    "name:vol_x_preferred":[
        "La Serre"
    ],
    "name:war_x_preferred":[
        "La Serre"
    ],
    "name:zho_x_preferred":[
        "\u62c9\u585e\u5c14"
    ],
    "wof:name":"La Serre",
    "wof:placetype":"locality"
},
  "geometry": {"coordinates":[3.14774,46.11167],"type":"Point"}
}