{
  "type": "Feature",
  "properties": {
    "gn:admin1_code":"28",
    "gn:admin2_code":"76",
    "gn:admin3_code":"763",
    "gn:admin4_code":"76253",
    "gn:asciiname":"Etainemare",
    "gn:country_code":"FR",
    "gn:dem":134,
    "gn:feature_class":"P",
    "gn:feature_code":"PPL",
    "gn:name":"\u00c9tainemare",
    "gn:population":0,
    "gn:timezone":"Europe/Paris",
    "iso:country":"FR",
    "name:und_x_variant":[
        "Etennemare",
        "\u00c9tainemare"
    ],
    "wof:name":"Etainemare",
    "wof:placetype":"locality"
},
  "geometry": {"coordinates":[0.77504,49.66816],"type":"Point"}
}