{
  "type": "Feature",
  "properties": {
    "gn:admin1_code":"53",
    "gn:admin2_code":"35",
    "gn:admin3_code":"351",
    "gn:admin4_code":"35161",
    "gn:asciiname":"Les Chenais",
    "gn:country_code":"FR",
    "gn:dem":73,
    "gn:feature_class":"P",
    "gn:feature_code":"PPL",
    "gn:name":"Les Chenais",
    "gn:population":0,
    "gn:timezone":"Europe/Paris",
    "iso:country":"FR",
    "wof:name":"Les Chenais",
    "wof:placetype":"locality"
},
  "geometry": {"coordinates":[-1.34529,48.06119],"type":"Point"}
}