{
  "type": "Feature",
  "properties": {
    "gn:admin1_code":"32",
    "gn:admin2_code":"62",
    "gn:admin3_code":"625",
    "gn:admin4_code":"62327.0",
    "gn:asciiname":"Pippemont",
    "gn:country_code":"FR",
    "gn:dem":120,
    "gn:feature_class":"P",
    "gn:feature_code":"PPL",
    "gn:name":"Pippemont",
    "gn:population":0,
    "gn:timezone":"Europe/Paris",
    "iso:country":"FR",
    "wof:name":"Pippemont",
    "wof:placetype":"locality"
},
  "geometry": {"coordinates":[2.308,50.55579],"type":"Point"}
}