{
  "type": "Feature",
  "properties": {
    "frgov:code_epci":"200034874",
    "frgov:insee_arr":"2",
    "frgov:insee_com":"55530",
    "frgov:insee_dep":"55",
    "frgov:insee_reg":"44",
    "frgov:nom_com":"Valbois",
    "frgov:nom_com_m":"VALBOIS",
    "frgov:nom_dep":"MEUSE",
    "frgov:nom_reg":"GRAND EST",
    "frgov:statut":"Commune simple",
    "gn:admin1_code":"44",
    "gn:admin2_code":"55",
    "gn:admin3_code":"552",
    "gn:admin4_code":"55530",
    "gn:asciiname":"Valbois",
    "gn:country_code":"FR",
    "gn:dem":263,
    "gn:feature_class":"P",
    "gn:feature_code":"PPL",
    "gn:name":"Valbois",
    "gn:population":0,
    "gn:timezone":"Europe/Paris",
    "iso:country":"FR",
    "name:cat_x_preferred":[
        "Valbois"
    ],
    "name:ceb_x_preferred":[
        "Valbois"
    ],
    "name:eus_x_preferred":[
        "Valbois"
    ],
    "name:fra_x_preferred":[
        "Valbois"
    ],
    "name:hun_x_preferred":[
        "Valbois"
    ],
    "name:ita_x_preferred":[
        "Valbois"
    ],
    "name:kaz_x_preferred":[
        "\u0412\u0430\u043b\u044c\u0431\u0443\u0430"
    ],
    "name:lat_x_preferred":[
        "Valbois"
    ],
    "name:ltz_x_preferred":[
        "Valbois"
    ],
    "name:msa_x_preferred":[
        "Valbois"
    ],
    "name:nld_x_preferred":[
        "Valbois"
    ],
    "name:oci_x_preferred":[
        "Valbois"
    ],
    "name:pms_x_preferred":[
        "Valbois"
    ],
    "name:pol_x_preferred":[
        "Valbois"
    ],
    "name:por_x_preferred":[
        "Valbois"
    ],
    "name:ron_x_preferred":[
        "Valbois"
    ],
    "name:slk_x_preferred":[
        "Valbois"
    ],
    "name:spa_x_preferred":[
        "Valbois"
    ],
    "name:swe_x_preferred":[
        "Valbois"
    ],
    "name:ukr_x_preferred":[
        "\u0412\u0430\u043b\u044c\u0431\u0443\u0430"
    ],
    "name:und_x_variant":[
        "Varvinay"
    ],
    "name:uzb_x_preferred":[
        "Valbois"
    ],
    "name:vie_x_preferred":[
        "Valbois"
    ],
    "name:vol_x_preferred":[
        "Valbois"
    ],
    "name:war_x_preferred":[
        "Valbois"
    ],
    "name:zho_x_preferred":[
        "\u74e6\u5c14\u5e03\u74e6"
    ],
    "qs:a0":"France",
    "qs:a1":"MEUSE",
    "qs:a1_lc":"55",
    "qs:a1r":"LORRAINE",
    "qs:a1r_lc":"41",
    "qs:a2_lc":"27",
    "qs:a2r_lc":"2",
    "qs:adm0":"France",
    "qs:adm0_a3":"FRA",
    "qs:la":"VALBOIS",
    "qs:la_lc":"55530",
    "qs:level":"localadmin",
    "qs:type":"Commune simple",
    "wof:coterminous":[
        404389047
    ],
    "wof:name":"Valbois",
    "wof:placetype":"locality",
    "wof:placetype_local":"Commune simple"
},
  "geometry": {"coordinates":[5.61667,48.93333],"type":"Point"}
}