{
  "type": "Feature",
  "properties": {
    "gn:admin1_code":"93",
    "gn:admin2_code":"04",
    "gn:admin3_code":"042",
    "gn:admin4_code":"04173",
    "gn:asciiname":"Meouilles",
    "gn:country_code":"FR",
    "gn:dem":897,
    "gn:feature_class":"P",
    "gn:feature_code":"PPL",
    "gn:name":"M\u00e9ouilles",
    "gn:population":0,
    "gn:timezone":"Europe/Paris",
    "iso:country":"FR",
    "wof:name":"Meouilles",
    "wof:placetype":"locality"
},
  "geometry": {"coordinates":[6.51939,43.95143],"type":"Point"}
}