{
  "type": "Feature",
  "properties": {
    "gn:admin1_code":"32",
    "gn:admin2_code":"60",
    "gn:admin3_code":"601",
    "gn:admin4_code":"60235",
    "gn:asciiname":"La Tremblee",
    "gn:country_code":"FR",
    "gn:dem":139,
    "gn:feature_class":"P",
    "gn:feature_code":"PPL",
    "gn:name":"La Trembl\u00e9e",
    "gn:population":0,
    "gn:timezone":"Europe/Paris",
    "iso:country":"FR",
    "wof:name":"La Tremblee",
    "wof:placetype":"locality"
},
  "geometry": {"coordinates":[1.82962,49.33826],"type":"Point"}
}