{
  "type": "Feature",
  "properties": {
    "gn:admin1_code":"32",
    "gn:admin2_code":"62",
    "gn:admin3_code":"623",
    "gn:admin4_code":"62894",
    "gn:asciiname":"L'Ermitage",
    "gn:country_code":"FR",
    "gn:dem":110,
    "gn:feature_class":"P",
    "gn:feature_code":"PPL",
    "gn:name":"L\u2019Ermitage",
    "gn:population":0,
    "gn:timezone":"Europe/Paris",
    "iso:country":"FR",
    "wof:name":"L'Ermitage",
    "wof:placetype":"locality"
},
  "geometry": {"coordinates":[1.67109,50.74171],"type":"Point"}
}