{
  "type": "Feature",
  "properties": {
    "gn:admin1_code":"53",
    "gn:admin2_code":"29",
    "gn:admin3_code":"294",
    "gn:admin4_code":"29215",
    "gn:asciiname":"Brunphuez",
    "gn:country_code":"FR",
    "gn:dem":39,
    "gn:feature_class":"P",
    "gn:feature_code":"PPL",
    "gn:name":"Brunphuez",
    "gn:population":0,
    "gn:timezone":"Europe/Paris",
    "iso:country":"FR",
    "wof:name":"Brunphuez",
    "wof:placetype":"locality"
},
  "geometry": {"coordinates":[-4.43601,47.97746],"type":"Point"}
}