{
  "type": "Feature",
  "properties": {
    "gn:admin1_code":"53",
    "gn:admin2_code":"29",
    "gn:admin3_code":"294",
    "gn:admin4_code":"29284",
    "gn:asciiname":"Letty",
    "gn:country_code":"FR",
    "gn:dem":15,
    "gn:feature_class":"P",
    "gn:feature_code":"PPL",
    "gn:name":"Letty",
    "gn:population":0,
    "gn:timezone":"Europe/Paris",
    "iso:country":"FR",
    "name:fra_x_preferred":[
        "Letty"
    ],
    "name:jpn_x_preferred":[
        "\u30ec\u30c6\u30a3"
    ],
    "wof:name":"Letty",
    "wof:placetype":"locality"
},
  "geometry": {"coordinates":[-4.25201,47.80856],"type":"Point"}
}