{
  "type": "Feature",
  "properties": {
    "gn:admin1_code":"44",
    "gn:admin2_code":"52",
    "gn:admin3_code":"522",
    "gn:admin4_code":"52332",
    "gn:asciiname":"Provencheres-sur-Meuse",
    "gn:country_code":"FR",
    "gn:dem":341,
    "gn:feature_class":"P",
    "gn:feature_code":"PPL",
    "gn:name":"Provench\u00e8res-sur-Meuse",
    "gn:population":0,
    "gn:timezone":"Europe/Paris",
    "iso:country":"FR",
    "name:und_x_variant":[
        "Provench\u00e8res",
        "Provench\u00e8res-sur-Meuse"
    ],
    "wof:name":"Provencheres-sur-Meuse",
    "wof:placetype":"locality"
},
  "geometry": {"coordinates":[5.53129,48.01054],"type":"Point"}
}