{
  "type": "Feature",
  "properties": {
    "iso:country":"FR",
    "qs_pg:aaroncc":"FR",
    "qs_pg:name":"Monroc",
    "qs_pg:name_adm0":"Guadeloupe",
    "qs_pg:name_adm1":"Pointe-\u00c0-Pitre",
    "qs_pg:photos":21,
    "qs_pg:photos_1k":4,
    "qs_pg:photos_9k":1,
    "qs_pg:photos_9r":1,
    "qs_pg:photos_all":21,
    "qs_pg:photos_sr":1,
    "qs_pg:pop_sr":0,
    "qs_pg:qs_pg_placetype":"locality",
    "qs_pg:qs_pg_placetype_gp":"Town",
    "qs_pg:woe_adm0":23424831,
    "woe:adm0_id":23424831,
    "woe:name_adm0":"Guadeloupe",
    "woe:name_adm1":"Pointe-\u00c0-Pitre",
    "woe:placetype":"Town",
    "wof:name":"Monroc",
    "wof:placetype":"neighbourhood"
},
  "geometry": {"coordinates":[-61.494083,16.380097],"type":"Point"}
}