{
  "type": "Feature",
  "properties": {
    "gn:admin1_code":"84",
    "gn:admin2_code":"07",
    "gn:admin3_code":"073",
    "gn:admin4_code":"07086",
    "gn:asciiname":"Trollat",
    "gn:country_code":"FR",
    "gn:dem":439,
    "gn:feature_class":"P",
    "gn:feature_code":"PPL",
    "gn:name":"Trollat",
    "gn:population":0,
    "gn:timezone":"Europe/Paris",
    "iso:country":"FR",
    "wof:name":"Trollat",
    "wof:placetype":"locality"
},
  "geometry": {"coordinates":[4.74727,45.09534],"type":"Point"}
}