{
  "type": "Feature",
  "properties": {
    "gn:admin1_code":"27",
    "gn:admin2_code":"58",
    "gn:admin3_code":"583",
    "gn:admin4_code":"58233",
    "gn:asciiname":"La Mignonnerie",
    "gn:country_code":"FR",
    "gn:dem":318,
    "gn:feature_class":"P",
    "gn:feature_code":"PPL",
    "gn:name":"La Mignonnerie",
    "gn:population":0,
    "gn:timezone":"Europe/Paris",
    "iso:country":"FR",
    "wof:name":"La Mignonnerie",
    "wof:placetype":"locality"
},
  "geometry": {"coordinates":[3.41486,47.10742],"type":"Point"}
}