{
  "type": "Feature",
  "properties": {
    "gn:admin1_code":"84",
    "gn:admin2_code":"38",
    "gn:admin3_code":"381",
    "gn:admin4_code":"38469",
    "gn:asciiname":"Dorciere",
    "gn:country_code":"FR",
    "gn:dem":1374,
    "gn:feature_class":"P",
    "gn:feature_code":"PPL",
    "gn:name":"Dorci\u00e8re",
    "gn:population":0,
    "gn:timezone":"Europe/Paris",
    "iso:country":"FR",
    "name:und_x_variant":[
        "Dourci\u00e8res",
        "Dorci\u00e8re"
    ],
    "wof:name":"Dorciere",
    "wof:placetype":"locality"
},
  "geometry": {"coordinates":[5.97584,44.85077],"type":"Point"}
}