{
  "type": "Feature",
  "properties": {
    "gn:admin1_code":"75",
    "gn:admin2_code":"24",
    "gn:admin3_code":"242",
    "gn:admin4_code":"24133",
    "gn:asciiname":"Vergne-Libert",
    "gn:country_code":"FR",
    "gn:dem":296,
    "gn:feature_class":"P",
    "gn:feature_code":"PPL",
    "gn:name":"Vergne-Libert",
    "gn:population":0,
    "gn:timezone":"Europe/Paris",
    "iso:country":"FR",
    "wof:name":"Vergne-Libert",
    "wof:placetype":"locality"
},
  "geometry": {"coordinates":[0.93346,45.53097],"type":"Point"}
}