{
  "type": "Feature",
  "properties": {
    "gn:admin1_code":"44",
    "gn:admin2_code":"88",
    "gn:admin3_code":"881",
    "gn:admin4_code":"88197",
    "gn:asciiname":"Gerbamont",
    "gn:country_code":"FR",
    "gn:dem":534,
    "gn:feature_class":"P",
    "gn:feature_code":"PPL",
    "gn:name":"Gerbamont",
    "gn:population":0,
    "gn:timezone":"Europe/Paris",
    "iso:country":"FR",
    "wof:name":"Gerbamont",
    "wof:placetype":"locality"
},
  "geometry": {"coordinates":[6.75556,48.0044],"type":"Point"}
}