{
  "type": "Feature",
  "properties": {
    "frgov:code_epci":"200071157",
    "frgov:insee_arr":"1",
    "frgov:insee_com":"88197",
    "frgov:insee_dep":"88",
    "frgov:insee_reg":"44",
    "frgov:nom_com":"Gerbamont",
    "frgov:nom_com_m":"GERBAMONT",
    "frgov:nom_dep":"VOSGES",
    "frgov:nom_reg":"GRAND EST",
    "frgov:statut":"Commune simple",
    "gn:admin1_code":"44",
    "gn:admin2_code":"88",
    "gn:admin3_code":"881",
    "gn:admin4_code":"88197",
    "gn:asciiname":"Gerbamont",
    "gn:country_code":"FR",
    "gn:dem":534,
    "gn:feature_class":"P",
    "gn:feature_code":"PPL",
    "gn:name":"Gerbamont",
    "gn:population":0,
    "gn:timezone":"Europe/Paris",
    "iso:country":"FR",
    "name:bug_x_preferred":[
        "Gerbamont"
    ],
    "name:cat_x_preferred":[
        "Gerbamont"
    ],
    "name:ceb_x_preferred":[
        "Gerbamont"
    ],
    "name:deu_x_preferred":[
        "Gerbamont"
    ],
    "name:eus_x_preferred":[
        "Gerbamont"
    ],
    "name:fra_x_preferred":[
        "Gerbamont"
    ],
    "name:hun_x_preferred":[
        "Gerbamont"
    ],
    "name:ind_x_preferred":[
        "Gerbamont"
    ],
    "name:ita_x_preferred":[
        "Gerbamont"
    ],
    "name:kaz_x_preferred":[
        "\u0416\u0435\u0440\u0431\u0430\u043c\u043e\u043d"
    ],
    "name:ltz_x_preferred":[
        "Gerbamont"
    ],
    "name:msa_x_preferred":[
        "Gerbamont"
    ],
    "name:nld_x_preferred":[
        "Gerbamont"
    ],
    "name:oci_x_preferred":[
        "Gerbamont"
    ],
    "name:pol_x_preferred":[
        "Gerbamont"
    ],
    "name:slk_x_preferred":[
        "Gerbamont"
    ],
    "name:spa_x_preferred":[
        "Gerbamont"
    ],
    "name:swe_x_preferred":[
        "Gerbamont"
    ],
    "name:ukr_x_preferred":[
        "\u0416\u0435\u0440\u0431\u0430\u043c\u043e\u043d"
    ],
    "name:uzb_x_preferred":[
        "Gerbamont"
    ],
    "name:vie_x_preferred":[
        "Gerbamont"
    ],
    "name:vol_x_preferred":[
        "Gerbamont"
    ],
    "name:war_x_preferred":[
        "Gerbamont"
    ],
    "name:zho_x_preferred":[
        "\u70ed\u5c14\u5df4\u8499"
    ],
    "qs:a0":"France",
    "qs:a1":"VOSGES",
    "qs:a1_lc":"88",
    "qs:a1r":"LORRAINE",
    "qs:a1r_lc":"41",
    "qs:a2_lc":"25",
    "qs:a2r_lc":"1",
    "qs:adm0":"France",
    "qs:adm0_a3":"FRA",
    "qs:la":"GERBAMONT",
    "qs:la_lc":"88197",
    "qs:level":"localadmin",
    "qs:type":"Commune simple",
    "wof:coterminous":[
        404403979
    ],
    "wof:name":"Gerbamont",
    "wof:placetype":"locality",
    "wof:placetype_local":"Commune simple"
},
  "geometry": {"coordinates":[6.75556,48.0044],"type":"Point"}
}