{
  "type": "Feature",
  "properties": {
    "gn:admin1_code":"44",
    "gn:admin2_code":"88",
    "gn:admin3_code":"881",
    "gn:admin4_code":"88197",
    "gn:asciiname":"Gerbamont",
    "gn:country_code":"FR",
    "gn:dem":534,
    "gn:feature_class":"P",
    "gn:feature_code":"PPL",
    "gn:name":"Gerbamont",
    "gn:population":0,
    "gn:timezone":"Europe/Paris",
    "iso:country":"FR",
    "name:bug_x_preferred":[
        "Gerbamont"
    ],
    "name:cat_x_preferred":[
        "Gerbamont"
    ],
    "name:ceb_x_preferred":[
        "Gerbamont"
    ],
    "name:deu_x_preferred":[
        "Gerbamont"
    ],
    "name:eus_x_preferred":[
        "Gerbamont"
    ],
    "name:fra_x_preferred":[
        "Gerbamont"
    ],
    "name:hun_x_preferred":[
        "Gerbamont"
    ],
    "name:ind_x_preferred":[
        "Gerbamont"
    ],
    "name:ita_x_preferred":[
        "Gerbamont"
    ],
    "name:kaz_x_preferred":[
        "\u0416\u0435\u0440\u0431\u0430\u043c\u043e\u043d"
    ],
    "name:ltz_x_preferred":[
        "Gerbamont"
    ],
    "name:msa_x_preferred":[
        "Gerbamont"
    ],
    "name:nld_x_preferred":[
        "Gerbamont"
    ],
    "name:oci_x_preferred":[
        "Gerbamont"
    ],
    "name:pol_x_preferred":[
        "Gerbamont"
    ],
    "name:slk_x_preferred":[
        "Gerbamont"
    ],
    "name:spa_x_preferred":[
        "Gerbamont"
    ],
    "name:swe_x_preferred":[
        "Gerbamont"
    ],
    "name:ukr_x_preferred":[
        "\u0416\u0435\u0440\u0431\u0430\u043c\u043e\u043d"
    ],
    "name:uzb_x_preferred":[
        "Gerbamont"
    ],
    "name:vie_x_preferred":[
        "Gerbamont"
    ],
    "name:vol_x_preferred":[
        "Gerbamont"
    ],
    "name:war_x_preferred":[
        "Gerbamont"
    ],
    "name:zho_x_preferred":[
        "\u70ed\u5c14\u5df4\u8499"
    ],
    "wof:name":"Gerbamont",
    "wof:placetype":"locality"
},
  "geometry": {"coordinates":[6.75556,48.0044],"type":"Point"}
}