{
  "type": "Feature",
  "properties": {
    "gn:admin1_code":"84",
    "gn:admin2_code":"07",
    "gn:admin3_code":"073",
    "gn:admin4_code":"07080",
    "gn:asciiname":"La Vialette",
    "gn:country_code":"FR",
    "gn:dem":1066,
    "gn:feature_class":"P",
    "gn:feature_code":"PPL",
    "gn:name":"La Vialette",
    "gn:population":0,
    "gn:timezone":"Europe/Paris",
    "iso:country":"FR",
    "wof:name":"La Vialette",
    "wof:placetype":"locality"
},
  "geometry": {"coordinates":[4.42512,45.11351],"type":"Point"}
}