{
  "type": "Feature",
  "properties": {
    "gn:gn_country":"FO",
    "gn:gn_fcode":"PPL",
    "gn:gn_pop":854,
    "gn:population":854,
    "iso:country":"FO",
    "name:ces_x_preferred":[
        "Strendur"
    ],
    "name:dan_x_preferred":[
        "Strendur"
    ],
    "name:deu_x_preferred":[
        "Strendur"
    ],
    "name:eng_x_preferred":[
        "Strendur"
    ],
    "name:fao_x_preferred":[
        "Strendur"
    ],
    "name:fra_x_preferred":[
        "Strendur"
    ],
    "name:glv_x_preferred":[
        "Strendur"
    ],
    "name:hun_x_preferred":[
        "Strendur"
    ],
    "name:isl_x_preferred":[
        "Strendur"
    ],
    "name:ita_x_preferred":[
        "Strendur"
    ],
    "name:lit_x_preferred":[
        "Strenduras"
    ],
    "name:nld_x_preferred":[
        "Strendur"
    ],
    "name:nob_x_preferred":[
        "Strendur"
    ],
    "name:nor_x_preferred":[
        "Strendur"
    ],
    "name:pol_x_preferred":[
        "Strendur"
    ],
    "name:ron_x_preferred":[
        "Strendur"
    ],
    "name:spa_x_preferred":[
        "Strendur"
    ],
    "name:swe_x_preferred":[
        "Strendur"
    ],
    "name:unk_x_variant":[
        "Str\u00e6nder"
    ],
    "qs:a0":"Foroyar#F\u00e6r\u00f8erne",
    "qs:a1":"*",
    "qs:a1r":"0",
    "qs:adm0":"Foroyar#F\u00e6r\u00f8erne",
    "qs:la_lc":"*",
    "qs:level":"locality",
    "qs:loc":"Strendur",
    "qs:loc_alt":"Strendur",
    "qs:pop":0,
    "qs:type":"buffered point",
    "qs_pg:aaroncc":"FO",
    "qs_pg:gn_country":"FO",
    "qs_pg:gn_fcode":"PPL",
    "qs_pg:gn_pop":854,
    "qs_pg:name":"Strendur",
    "qs_pg:name_adm0":"F\u00e6r\u00f8erne",
    "qs_pg:name_adm1":"Sy\u00f0ra Eysturoy",
    "qs_pg:photos_9k":1,
    "qs_pg:photos_9r":1,
    "qs_pg:photos_all":4,
    "qs_pg:photos_sr":0,
    "qs_pg:pop_sr":2,
    "qs_pg:qs_pg_placetype":"locality",
    "qs_pg:qs_pg_placetype_gp":"Town",
    "qs_pg:woe_adm0":23424816,
    "wd:wordcount":78,
    "wof:name":"Strendur",
    "wof:placetype":"locality",
    "wof:population":854
},
  "geometry": {"coordinates":[-6.759497,62.109726],"type":"Point"}
}