{
  "type": "Feature",
  "properties": {
    "iso:country":"FR",
    "name:eng_x_preferred":[
        "Canteleu"
    ],
    "name:fra_x_preferred":[
        "Canteleu"
    ],
    "wof:name":"Canteleu",
    "wof:placetype":"neighbourhood"
},
  "geometry": {"coordinates":[3.0211053044775,50.63820710258716],"type":"Point"}
}