{
  "type": "Feature",
  "properties": {
    "gn:admin1_code":"52",
    "gn:admin2_code":"44",
    "gn:admin3_code":"443",
    "gn:admin4_code":"44135",
    "gn:asciiname":"Penchateau",
    "gn:country_code":"FR",
    "gn:dem":6,
    "gn:feature_class":"P",
    "gn:feature_code":"PPL",
    "gn:name":"Pench\u00e2teau",
    "gn:population":0,
    "gn:timezone":"Europe/Paris",
    "iso:country":"FR",
    "wof:name":"Penchateau",
    "wof:placetype":"locality"
},
  "geometry": {"coordinates":[-2.41973,47.2636],"type":"Point"}
}