{
  "type": "Feature",
  "properties": {
    "gn:admin1_code":"52",
    "gn:admin2_code":"85",
    "gn:admin3_code":"851",
    "gn:admin4_code":"85115",
    "gn:asciiname":"Pareds",
    "gn:country_code":"FR",
    "gn:dem":69,
    "gn:feature_class":"P",
    "gn:feature_code":"PPL",
    "gn:name":"Pareds",
    "gn:population":0,
    "gn:timezone":"Europe/Paris",
    "iso:country":"FR",
    "wof:name":"Pareds",
    "wof:placetype":"locality"
},
  "geometry": {"coordinates":[-0.95451,46.6619],"type":"Point"}
}