{
  "type": "Feature",
  "properties": {
    "gn:admin1_code":"28",
    "gn:admin2_code":"61",
    "gn:admin3_code":"613",
    "gn:admin4_code":"61300",
    "gn:asciiname":"Freulemont",
    "gn:country_code":"FR",
    "gn:dem":175,
    "gn:feature_class":"P",
    "gn:feature_code":"PPL",
    "gn:name":"Freulemont",
    "gn:population":0,
    "gn:timezone":"Europe/Paris",
    "iso:country":"FR",
    "wof:name":"Freulemont",
    "wof:placetype":"locality"
},
  "geometry": {"coordinates":[0.81649,48.45274000000001],"type":"Point"}
}