{
  "type": "Feature",
  "properties": {
    "gn:admin1_code":"76",
    "gn:admin2_code":"65",
    "gn:admin3_code":"652",
    "gn:admin4_code":"65127",
    "gn:asciiname":"Capvern-les-Bains",
    "gn:country_code":"FR",
    "gn:dem":486,
    "gn:feature_class":"P",
    "gn:feature_code":"PPL",
    "gn:name":"Capvern-les-Bains",
    "gn:population":0,
    "gn:timezone":"Europe/Paris",
    "iso:country":"FR",
    "wof:name":"Capvern-les-Bains",
    "wof:placetype":"locality"
},
  "geometry": {"coordinates":[0.30839,43.12063],"type":"Point"}
}