{
  "type": "Feature",
  "properties": {
    "gn:admin1_code":"24",
    "gn:admin2_code":"18",
    "gn:admin3_code":"183",
    "gn:admin4_code":"18148",
    "gn:asciiname":"Autry",
    "gn:country_code":"FR",
    "gn:dem":123,
    "gn:feature_class":"P",
    "gn:feature_code":"PPL",
    "gn:name":"Autry",
    "gn:population":0,
    "gn:timezone":"Europe/Paris",
    "iso:country":"FR",
    "wof:name":"Autry",
    "wof:placetype":"locality"
},
  "geometry": {"coordinates":[2.05267,47.19848],"type":"Point"}
}