{
  "type": "Feature",
  "properties": {
    "gn:admin1_code":"24",
    "gn:admin2_code":"18",
    "gn:admin3_code":"183",
    "gn:admin4_code":"18148",
    "gn:asciiname":"Autry",
    "gn:country_code":"FR",
    "gn:dem":123,
    "gn:feature_class":"P",
    "gn:feature_code":"PPL",
    "gn:name":"Autry",
    "gn:population":0,
    "gn:timezone":"Europe/Paris",
    "iso:country":"FR",
    "name:bug_x_preferred":[
        "Autry"
    ],
    "name:cat_x_preferred":[
        "Autry"
    ],
    "name:ceb_x_preferred":[
        "Autry"
    ],
    "name:ces_x_preferred":[
        "Autry"
    ],
    "name:deu_x_preferred":[
        "Autry"
    ],
    "name:eus_x_preferred":[
        "Autry"
    ],
    "name:fas_x_preferred":[
        "\u0627\u062a\u0631\u06cc"
    ],
    "name:fra_x_preferred":[
        "Autry"
    ],
    "name:hun_x_preferred":[
        "Autry"
    ],
    "name:hye_x_preferred":[
        "\u0555\u057f\u0580\u056b"
    ],
    "name:ita_x_preferred":[
        "Autry"
    ],
    "name:lat_x_preferred":[
        "Autry"
    ],
    "name:ltz_x_preferred":[
        "Autry"
    ],
    "name:mlg_x_preferred":[
        "Autry"
    ],
    "name:msa_x_preferred":[
        "Autry"
    ],
    "name:nld_x_preferred":[
        "Autry"
    ],
    "name:oci_x_preferred":[
        "Autry"
    ],
    "name:pam_x_preferred":[
        "Autry"
    ],
    "name:pms_x_preferred":[
        "Autry"
    ],
    "name:pol_x_preferred":[
        "Autry"
    ],
    "name:por_x_preferred":[
        "Autry"
    ],
    "name:ron_x_preferred":[
        "Autry"
    ],
    "name:rus_x_preferred":[
        "\u041e\u0442\u0440\u0438"
    ],
    "name:slk_x_preferred":[
        "Autry"
    ],
    "name:spa_x_preferred":[
        "Autry"
    ],
    "name:sqi_x_preferred":[
        "Autry"
    ],
    "name:srp_x_preferred":[
        "\u041e\u0442\u0440\u0438"
    ],
    "name:swe_x_preferred":[
        "Autry"
    ],
    "name:ukr_x_preferred":[
        "\u041e\u0442\u0440\u0456"
    ],
    "name:vie_x_preferred":[
        "Autry"
    ],
    "name:vol_x_preferred":[
        "Autry"
    ],
    "name:war_x_preferred":[
        "Autry"
    ],
    "name:zho_x_preferred":[
        "\u6b27\u7279\u91cc"
    ],
    "wof:name":"Autry",
    "wof:placetype":"locality"
},
  "geometry": {"coordinates":[2.05267,47.19848],"type":"Point"}
}