{
  "type": "Feature",
  "properties": {
    "gn:admin1_code":"75",
    "gn:admin2_code":"87",
    "gn:admin3_code":"872",
    "gn:admin4_code":"87159",
    "gn:asciiname":"Le Mazeaud",
    "gn:country_code":"FR",
    "gn:dem":471,
    "gn:feature_class":"P",
    "gn:feature_code":"PPL",
    "gn:name":"Le Mazeaud",
    "gn:population":0,
    "gn:timezone":"Europe/Paris",
    "iso:country":"FR",
    "wof:name":"Le Mazeaud",
    "wof:placetype":"locality"
},
  "geometry": {"coordinates":[1.38333,46.03333],"type":"Point"}
}