{
  "type": "Feature",
  "properties": {
    "gn:admin1_code":"44",
    "gn:admin2_code":"88",
    "gn:admin3_code":"881",
    "gn:admin4_code":"88069",
    "gn:asciiname":"Bouxieres-aux-Bois",
    "gn:country_code":"FR",
    "gn:dem":372,
    "gn:feature_class":"P",
    "gn:feature_code":"PPL",
    "gn:name":"Bouxi\u00e8res-aux-Bois",
    "gn:population":0,
    "gn:timezone":"Europe/Paris",
    "iso:country":"FR",
    "name:und_x_variant":[
        "Bouxi\u00e8res",
        "Bouxi\u00e8res-aux-Bois"
    ],
    "wof:name":"Bouxieres-aux-Bois",
    "wof:placetype":"locality"
},
  "geometry": {"coordinates":[6.3171,48.26297],"type":"Point"}
}