{
  "type": "Feature",
  "properties": {
    "gn:admin1_code":"84",
    "gn:admin2_code":"07",
    "gn:admin3_code":"073",
    "gn:admin4_code":"07258",
    "gn:asciiname":"La Chanal",
    "gn:country_code":"FR",
    "gn:dem":613,
    "gn:feature_class":"P",
    "gn:feature_code":"PPL",
    "gn:name":"La Chanal",
    "gn:population":0,
    "gn:timezone":"Europe/Paris",
    "iso:country":"FR",
    "wof:name":"La Chanal",
    "wof:placetype":"locality"
},
  "geometry": {"coordinates":[4.51156,45.18164],"type":"Point"}
}