{
  "type": "Feature",
  "properties": {
    "gn:admin1_code":"94",
    "gn:admin2_code":"2B",
    "gn:admin3_code":"2B3",
    "gn:admin4_code":"2B147",
    "gn:asciiname":"Poggio",
    "gn:country_code":"FR",
    "gn:dem":1051,
    "gn:feature_class":"P",
    "gn:feature_code":"PPL",
    "gn:name":"Poggio",
    "gn:population":0,
    "gn:timezone":"Europe/Paris",
    "iso:country":"FR",
    "wof:name":"Poggio",
    "wof:placetype":"locality"
},
  "geometry": {"coordinates":[8.98865,42.33682],"type":"Point"}
}