{
  "type": "Feature",
  "properties": {
    "gn:admin1_code":"94",
    "gn:admin2_code":"2B",
    "gn:admin3_code":"2B3",
    "gn:admin4_code":"2B147",
    "gn:asciiname":"Poggio",
    "gn:country_code":"FR",
    "gn:dem":1051,
    "gn:feature_class":"P",
    "gn:feature_code":"PPL",
    "gn:name":"Poggio",
    "gn:population":0,
    "gn:timezone":"Europe/Paris",
    "iso:country":"FR",
    "name:ceb_x_preferred":[
        "Poggio"
    ],
    "name:ces_x_preferred":[
        "Poggio"
    ],
    "name:deu_x_preferred":[
        "Poggio"
    ],
    "name:fas_x_preferred":[
        "\u067e\u0648\u062c\u06cc\u0648"
    ],
    "name:fra_x_preferred":[
        "Poggio"
    ],
    "name:ita_x_preferred":[
        "Poggio"
    ],
    "name:pol_x_preferred":[
        "Poggio"
    ],
    "name:por_x_preferred":[
        "Poggio"
    ],
    "name:rus_x_preferred":[
        "\u041f\u043e\u0434\u0436\u0438\u043e"
    ],
    "name:spa_x_preferred":[
        "Poggio"
    ],
    "name:srp_x_preferred":[
        "\u041f\u043e\u0452\u043e"
    ],
    "name:swe_x_preferred":[
        "Poggio"
    ],
    "name:ukr_x_preferred":[
        "\u041f\u043e\u0434\u0436\u0456\u043e"
    ],
    "wof:name":"Poggio",
    "wof:placetype":"locality"
},
  "geometry": {"coordinates":[8.98865,42.33682],"type":"Point"}
}