{
  "type": "Feature",
  "properties": {
    "gn:admin1_code":"24",
    "gn:admin2_code":"18",
    "gn:admin3_code":"182",
    "gn:admin4_code":"18199",
    "gn:asciiname":"La Veve",
    "gn:country_code":"FR",
    "gn:dem":165,
    "gn:feature_class":"P",
    "gn:feature_code":"PPL",
    "gn:name":"La V\u00e8ve",
    "gn:population":0,
    "gn:timezone":"Europe/Paris",
    "iso:country":"FR",
    "wof:name":"La Veve",
    "wof:placetype":"locality"
},
  "geometry": {"coordinates":[2.18269,46.83697],"type":"Point"}
}