{
  "type": "Feature",
  "properties": {
    "gn:admin1_code":"24",
    "gn:admin2_code":"45",
    "gn:admin3_code":"452",
    "gn:admin4_code":"45333",
    "gn:asciiname":"Le Grand Charmoy",
    "gn:country_code":"FR",
    "gn:dem":124,
    "gn:feature_class":"P",
    "gn:feature_code":"PPL",
    "gn:name":"Le Grand Charmoy",
    "gn:population":0,
    "gn:timezone":"Europe/Paris",
    "iso:country":"FR",
    "wof:name":"Le Grand Charmoy",
    "wof:placetype":"locality"
},
  "geometry": {"coordinates":[2.06921,47.96595],"type":"Point"}
}