{
  "type": "Feature",
  "properties": {
    "gn:admin1_code":"27",
    "gn:admin2_code":"70",
    "gn:admin3_code":"702",
    "gn:admin4_code":"70559",
    "gn:asciiname":"Villeparois",
    "gn:country_code":"FR",
    "gn:dem":228,
    "gn:feature_class":"P",
    "gn:feature_code":"PPL",
    "gn:name":"Villeparois",
    "gn:population":0,
    "gn:timezone":"Europe/Paris",
    "iso:country":"FR",
    "name:bug_x_preferred":[
        "Villeparois"
    ],
    "name:cat_x_preferred":[
        "Villeparois"
    ],
    "name:ceb_x_preferred":[
        "Villeparois"
    ],
    "name:deu_x_preferred":[
        "Villeparois"
    ],
    "name:eus_x_preferred":[
        "Villeparois"
    ],
    "name:fra_x_preferred":[
        "Villeparois"
    ],
    "name:hun_x_preferred":[
        "Villeparois"
    ],
    "name:ita_x_preferred":[
        "Villeparois"
    ],
    "name:lat_x_preferred":[
        "Villeparois"
    ],
    "name:msa_x_preferred":[
        "Villeparois"
    ],
    "name:nld_x_preferred":[
        "Villeparois"
    ],
    "name:oci_x_preferred":[
        "Villeparois"
    ],
    "name:pms_x_preferred":[
        "Villeparois"
    ],
    "name:pol_x_preferred":[
        "Villeparois"
    ],
    "name:por_x_preferred":[
        "Villeparois"
    ],
    "name:rus_x_preferred":[
        "\u0412\u0438\u043b\u044c\u043f\u0430\u0440\u0443\u0430"
    ],
    "name:slk_x_preferred":[
        "Villeparois"
    ],
    "name:spa_x_preferred":[
        "Villeparois"
    ],
    "name:swe_x_preferred":[
        "Villeparois"
    ],
    "name:ukr_x_preferred":[
        "\u0412\u0456\u043b\u044c\u043f\u0430\u0440\u0443\u0430"
    ],
    "name:uzb_x_preferred":[
        "Villeparois"
    ],
    "name:vie_x_preferred":[
        "Villeparois"
    ],
    "name:vol_x_preferred":[
        "Villeparois"
    ],
    "name:war_x_preferred":[
        "Villeparois"
    ],
    "wof:name":"Villeparois",
    "wof:placetype":"locality"
},
  "geometry": {"coordinates":[6.18171,47.65578],"type":"Point"}
}