{
  "type": "Feature",
  "properties": {
    "gn:admin1_code":"27",
    "gn:admin2_code":"70",
    "gn:admin3_code":"702",
    "gn:admin4_code":"70559",
    "gn:asciiname":"Villeparois",
    "gn:country_code":"FR",
    "gn:dem":228,
    "gn:feature_class":"P",
    "gn:feature_code":"PPL",
    "gn:name":"Villeparois",
    "gn:population":0,
    "gn:timezone":"Europe/Paris",
    "iso:country":"FR",
    "wof:name":"Villeparois",
    "wof:placetype":"locality"
},
  "geometry": {"coordinates":[6.18171,47.65578],"type":"Point"}
}