{
  "type": "Feature",
  "properties": {
    "frgov:code_epci":"200070811",
    "frgov:insee_arr":"1",
    "frgov:insee_com":"65411",
    "frgov:insee_dep":"65",
    "frgov:insee_reg":"76",
    "frgov:nom_com":"Sassis",
    "frgov:nom_com_m":"SASSIS",
    "frgov:nom_dep":"HAUTES-PYRENEES",
    "frgov:nom_reg":"OCCITANIE",
    "frgov:statut":"Commune simple",
    "gn:admin1_code":"76",
    "gn:admin2_code":"65",
    "gn:admin3_code":"651",
    "gn:admin4_code":"65411",
    "gn:asciiname":"Sassis",
    "gn:country_code":"FR",
    "gn:dem":876,
    "gn:feature_class":"P",
    "gn:feature_code":"PPL",
    "gn:name":"Sassis",
    "gn:population":63,
    "gn:timezone":"Europe/Paris",
    "iso:country":"FR",
    "name:arg_x_preferred":[
        "Sass\u00eds"
    ],
    "name:bug_x_preferred":[
        "Sassis"
    ],
    "name:cat_x_preferred":[
        "Sass\u00eds"
    ],
    "name:ceb_x_preferred":[
        "Sassis"
    ],
    "name:deu_x_preferred":[
        "Sassis"
    ],
    "name:eus_x_preferred":[
        "Sassis"
    ],
    "name:fra_x_preferred":[
        "Sassis"
    ],
    "name:hun_x_preferred":[
        "Sassis"
    ],
    "name:ind_x_preferred":[
        "Sassis"
    ],
    "name:ita_x_preferred":[
        "Sassis"
    ],
    "name:lat_x_preferred":[
        "Sassis"
    ],
    "name:msa_x_preferred":[
        "Sassis"
    ],
    "name:nld_x_preferred":[
        "Sassis"
    ],
    "name:oci_x_preferred":[
        "Sass\u00eds"
    ],
    "name:pms_x_preferred":[
        "Sassis"
    ],
    "name:pol_x_preferred":[
        "Sassis"
    ],
    "name:por_x_preferred":[
        "Sassis"
    ],
    "name:ron_x_preferred":[
        "Sassis"
    ],
    "name:rus_x_preferred":[
        "\u0421\u0430\u0441\u0438\u0441"
    ],
    "name:slk_x_preferred":[
        "Sassis"
    ],
    "name:spa_x_preferred":[
        "Sassis"
    ],
    "name:swe_x_preferred":[
        "Sassis"
    ],
    "name:ukr_x_preferred":[
        "\u0421\u0430\u0441\u0441\u0456"
    ],
    "name:vie_x_preferred":[
        "Sassis"
    ],
    "name:vol_x_preferred":[
        "Sassis"
    ],
    "name:war_x_preferred":[
        "Sassis"
    ],
    "name:zho_x_preferred":[
        "\u8428\u897f"
    ],
    "qs:a0":"France",
    "qs:a1":"HAUTES-PYRENEES",
    "qs:a1_lc":"65",
    "qs:a1r":"MIDI-PYRENEES",
    "qs:a1r_lc":"73",
    "qs:a2_lc":"13",
    "qs:a2r_lc":"1",
    "qs:adm0":"France",
    "qs:adm0_a3":"FRA",
    "qs:la":"SASSIS",
    "qs:la_lc":"65411",
    "qs:level":"localadmin",
    "qs:type":"Commune simple",
    "wof:coterminous":[
        404367431
    ],
    "wof:name":"Sassis",
    "wof:placetype":"locality",
    "wof:placetype_local":"Commune simple",
    "wof:population":63
},
  "geometry": {"coordinates":[-0.01667,42.86667],"type":"Point"}
}