{
  "type": "Feature",
  "properties": {
    "gn:admin1_code":"76",
    "gn:admin2_code":"65",
    "gn:admin3_code":"651",
    "gn:admin4_code":"65411",
    "gn:asciiname":"Sassis",
    "gn:country_code":"FR",
    "gn:dem":876,
    "gn:feature_class":"P",
    "gn:feature_code":"PPL",
    "gn:name":"Sassis",
    "gn:population":63,
    "gn:timezone":"Europe/Paris",
    "iso:country":"FR",
    "wof:name":"Sassis",
    "wof:placetype":"locality",
    "wof:population":63
},
  "geometry": {"coordinates":[-0.01667,42.86667],"type":"Point"}
}