{
  "type": "Feature",
  "properties": {
    "gn:admin1_code":"75",
    "gn:admin2_code":"24",
    "gn:admin3_code":"244",
    "gn:admin4_code":"24172",
    "gn:asciiname":"Tayac",
    "gn:country_code":"FR",
    "gn:dem":65,
    "gn:feature_class":"P",
    "gn:feature_code":"PPL",
    "gn:name":"Tayac",
    "gn:population":0,
    "gn:timezone":"Europe/Paris",
    "iso:country":"FR",
    "name:bug_x_preferred":[
        "Tayac"
    ],
    "name:cat_x_preferred":[
        "Taiac"
    ],
    "name:ceb_x_preferred":[
        "Tayac"
    ],
    "name:deu_x_preferred":[
        "Tayac"
    ],
    "name:eus_x_preferred":[
        "Tayac"
    ],
    "name:fra_x_preferred":[
        "Tayac"
    ],
    "name:hun_x_preferred":[
        "Tayac"
    ],
    "name:ind_x_preferred":[
        "Tayac"
    ],
    "name:ita_x_preferred":[
        "Tayac"
    ],
    "name:kaz_x_preferred":[
        "\u0422\u0430\u044f\u043a"
    ],
    "name:lat_x_preferred":[
        "Tayac"
    ],
    "name:mlg_x_preferred":[
        "Tayac"
    ],
    "name:msa_x_preferred":[
        "Tayac"
    ],
    "name:nld_x_preferred":[
        "Tayac"
    ],
    "name:oci_x_preferred":[
        "Taiac"
    ],
    "name:pms_x_preferred":[
        "Tayac"
    ],
    "name:pol_x_preferred":[
        "Tayac"
    ],
    "name:por_x_preferred":[
        "Tayac"
    ],
    "name:ron_x_preferred":[
        "Tayac"
    ],
    "name:slk_x_preferred":[
        "Tayac"
    ],
    "name:spa_x_preferred":[
        "Tayac"
    ],
    "name:swe_x_preferred":[
        "Tayac"
    ],
    "name:ukr_x_preferred":[
        "\u0422\u0430\u044f\u043a"
    ],
    "name:uzb_x_preferred":[
        "Tayac"
    ],
    "name:vie_x_preferred":[
        "Tayac"
    ],
    "name:vol_x_preferred":[
        "Tayac"
    ],
    "name:war_x_preferred":[
        "Tayac"
    ],
    "name:zho_x_preferred":[
        "\u6cf0\u963f\u514b"
    ],
    "wof:name":"Tayac",
    "wof:placetype":"locality"
},
  "geometry": {"coordinates":[1.00568,44.94269],"type":"Point"}
}