{
  "type": "Feature",
  "properties": {
    "gn:admin1_code":"75",
    "gn:admin2_code":"24",
    "gn:admin3_code":"244",
    "gn:admin4_code":"24172",
    "gn:asciiname":"Tayac",
    "gn:country_code":"FR",
    "gn:dem":65,
    "gn:feature_class":"P",
    "gn:feature_code":"PPL",
    "gn:name":"Tayac",
    "gn:population":0,
    "gn:timezone":"Europe/Paris",
    "iso:country":"FR",
    "wof:name":"Tayac",
    "wof:placetype":"locality"
},
  "geometry": {"coordinates":[1.00568,44.94269],"type":"Point"}
}