{
  "type": "Feature",
  "properties": {
    "iso:country":"FR",
    "name:eng_x_preferred":[
        "Saint-Pierre-des-Corps-Blanqui"
    ],
    "name:fra_x_preferred":[
        "Saint-Pierre-des-Corps-Blanqui"
    ],
    "wof:name":"Saint-Pierre-des-Corps-Blanqui",
    "wof:placetype":"neighbourhood"
},
  "geometry": {"coordinates":[0.69945986677803,47.39665567388902],"type":"Point"}
}