{
  "type": "Feature",
  "properties": {
    "iso:country":"FR",
    "name:eng_x_preferred":[
        "Hautes Noues"
    ],
    "name:fra_x_preferred":[
        "Hautes Noues"
    ],
    "wof:name":"Hautes Noues",
    "wof:placetype":"neighbourhood"
},
  "geometry": {"coordinates":[2.53856806101447,48.83376935903084],"type":"Point"}
}