{
  "type": "Feature",
  "properties": {
    "gn:admin1_code":"27",
    "gn:admin2_code":"89",
    "gn:admin3_code":"891",
    "gn:admin4_code":"89419",
    "gn:asciiname":"Champeaux",
    "gn:country_code":"FR",
    "gn:dem":187,
    "gn:feature_class":"P",
    "gn:feature_code":"PPL",
    "gn:name":"Champeaux",
    "gn:population":0,
    "gn:timezone":"Europe/Paris",
    "iso:country":"FR",
    "name:bre_x_preferred":[
        "Champeaux"
    ],
    "name:ceb_x_preferred":[
        "Champeaux"
    ],
    "name:deu_x_preferred":[
        "Champeaux"
    ],
    "name:fra_x_preferred":[
        "Champeaux"
    ],
    "name:ita_x_preferred":[
        "Champeaux"
    ],
    "name:nds_x_preferred":[
        "Champeaux"
    ],
    "name:nld_x_preferred":[
        "Champeaux"
    ],
    "name:pms_x_preferred":[
        "Champeaux"
    ],
    "name:pol_x_preferred":[
        "Champeaux"
    ],
    "name:slk_x_preferred":[
        "Champeaux"
    ],
    "name:spa_x_preferred":[
        "Champeaux"
    ],
    "name:swe_x_preferred":[
        "Champeaux"
    ],
    "name:ukr_x_preferred":[
        "\u0428\u0430\u043c\u043f\u043e"
    ],
    "wof:name":"Champeaux",
    "wof:placetype":"locality"
},
  "geometry": {"coordinates":[3.26971,47.75100000000001],"type":"Point"}
}