{
  "type": "Feature",
  "properties": {
    "gn:admin1_code":"27",
    "gn:admin2_code":"39",
    "gn:admin3_code":"392",
    "gn:admin4_code":"39010",
    "gn:asciiname":"Morval",
    "gn:country_code":"FR",
    "gn:dem":443,
    "gn:feature_class":"P",
    "gn:feature_code":"PPL",
    "gn:name":"Morval",
    "gn:population":0,
    "gn:timezone":"Europe/Paris",
    "iso:country":"FR",
    "wof:name":"Morval",
    "wof:placetype":"locality"
},
  "geometry": {"coordinates":[5.43823,46.41638],"type":"Point"}
}