{
  "type": "Feature",
  "properties": {
    "gn:admin1_code":"27",
    "gn:admin2_code":"39",
    "gn:admin3_code":"392",
    "gn:admin4_code":"39010",
    "gn:asciiname":"Morval",
    "gn:country_code":"FR",
    "gn:dem":443,
    "gn:feature_class":"P",
    "gn:feature_code":"PPL",
    "gn:name":"Morval",
    "gn:population":0,
    "gn:timezone":"Europe/Paris",
    "iso:country":"FR",
    "name:ara_x_preferred":[
        "\u0645\u0648\u0631\u0641\u0627\u0644"
    ],
    "name:bre_x_preferred":[
        "Morval"
    ],
    "name:cat_x_preferred":[
        "Morval"
    ],
    "name:ceb_x_preferred":[
        "Morval"
    ],
    "name:deu_x_preferred":[
        "Morval"
    ],
    "name:eus_x_preferred":[
        "Morval"
    ],
    "name:fra_x_preferred":[
        "Morval"
    ],
    "name:hun_x_preferred":[
        "Morval"
    ],
    "name:ind_x_preferred":[
        "Morval"
    ],
    "name:ita_x_preferred":[
        "Morval"
    ],
    "name:kaz_x_preferred":[
        "\u041c\u043e\u0440\u0432\u0430\u043b\u044c"
    ],
    "name:lat_x_preferred":[
        "Morval"
    ],
    "name:ltz_x_preferred":[
        "Morval"
    ],
    "name:mlg_x_preferred":[
        "Morval"
    ],
    "name:msa_x_preferred":[
        "Morval"
    ],
    "name:nld_x_preferred":[
        "Morval"
    ],
    "name:pcd_x_preferred":[
        "Mourval"
    ],
    "name:pms_x_preferred":[
        "Morval"
    ],
    "name:pol_x_preferred":[
        "Morval"
    ],
    "name:por_x_preferred":[
        "Morval"
    ],
    "name:ron_x_preferred":[
        "Morval"
    ],
    "name:rus_x_preferred":[
        "\u041c\u043e\u0440\u0432\u0430\u043b\u044c"
    ],
    "name:slk_x_preferred":[
        "Morval"
    ],
    "name:spa_x_preferred":[
        "Morval"
    ],
    "name:swe_x_preferred":[
        "Morval"
    ],
    "name:ukr_x_preferred":[
        "\u041c\u043e\u0440\u0432\u0430\u043b\u044c"
    ],
    "name:vie_x_preferred":[
        "Morval"
    ],
    "name:vol_x_preferred":[
        "Morval"
    ],
    "name:war_x_preferred":[
        "Morval"
    ],
    "name:zho_x_preferred":[
        "\u83ab\u74e6\u5c14"
    ],
    "wof:name":"Morval",
    "wof:placetype":"locality"
},
  "geometry": {"coordinates":[5.43823,46.41638],"type":"Point"}
}