{
  "type": "Feature",
  "properties": {
    "gn:admin1_code":"76",
    "gn:admin2_code":"48",
    "gn:admin3_code":"482",
    "gn:admin4_code":"48004",
    "gn:asciiname":"Combret",
    "gn:country_code":"FR",
    "gn:dem":785,
    "gn:feature_class":"P",
    "gn:feature_code":"PPL",
    "gn:name":"Combret",
    "gn:population":0,
    "gn:timezone":"Europe/Paris",
    "iso:country":"FR",
    "wof:name":"Combret",
    "wof:placetype":"locality"
},
  "geometry": {"coordinates":[3.88893,44.46446],"type":"Point"}
}