{
  "type": "Feature",
  "properties": {
    "gn:admin1_code":"76",
    "gn:admin2_code":"48",
    "gn:admin3_code":"482",
    "gn:admin4_code":"48004",
    "gn:asciiname":"Combret",
    "gn:country_code":"FR",
    "gn:dem":785,
    "gn:feature_class":"P",
    "gn:feature_code":"PPL",
    "gn:name":"Combret",
    "gn:population":0,
    "gn:timezone":"Europe/Paris",
    "iso:country":"FR",
    "name:cat_x_preferred":[
        "Combret"
    ],
    "name:ceb_x_preferred":[
        "Combret"
    ],
    "name:deu_x_preferred":[
        "Combret"
    ],
    "name:eus_x_preferred":[
        "Combret"
    ],
    "name:fra_x_preferred":[
        "Combret"
    ],
    "name:hun_x_preferred":[
        "Combret"
    ],
    "name:hye_x_preferred":[
        "\u053f\u0578\u0574\u0562\u0580\u0565"
    ],
    "name:ita_x_preferred":[
        "Combret"
    ],
    "name:lat_x_preferred":[
        "Combret"
    ],
    "name:msa_x_preferred":[
        "Combret"
    ],
    "name:nld_x_preferred":[
        "Combret"
    ],
    "name:oci_x_preferred":[
        "Combret"
    ],
    "name:pam_x_preferred":[
        "Combret"
    ],
    "name:pms_x_preferred":[
        "Combret"
    ],
    "name:pol_x_preferred":[
        "Combret"
    ],
    "name:por_x_preferred":[
        "Combret"
    ],
    "name:ron_x_preferred":[
        "Combret"
    ],
    "name:rus_x_preferred":[
        "\u041a\u043e\u043c\u0431\u0440\u0435"
    ],
    "name:slk_x_preferred":[
        "Combret"
    ],
    "name:spa_x_preferred":[
        "Combret"
    ],
    "name:srp_x_preferred":[
        "\u041a\u043e\u043c\u0431\u0440\u0435"
    ],
    "name:swe_x_preferred":[
        "Combret"
    ],
    "name:ukr_x_preferred":[
        "\u041a\u043e\u043c\u0431\u0440\u0435"
    ],
    "name:vie_x_preferred":[
        "Combret"
    ],
    "name:vol_x_preferred":[
        "Combret"
    ],
    "name:war_x_preferred":[
        "Combret"
    ],
    "name:zho_x_preferred":[
        "\u5b54\u5e03\u96f7"
    ],
    "wof:name":"Combret",
    "wof:placetype":"locality"
},
  "geometry": {"coordinates":[3.88893,44.46446],"type":"Point"}
}