{
  "type": "Feature",
  "properties": {
    "gn:admin1_code":"32",
    "gn:asciiname":"Le Clipon",
    "gn:country_code":"FR",
    "gn:dem":2,
    "gn:feature_class":"P",
    "gn:feature_code":"PPL",
    "gn:name":"Le Clipon",
    "gn:population":0,
    "gn:timezone":"Europe/Paris",
    "iso:country":"FR",
    "wof:name":"Le Clipon",
    "wof:placetype":"locality"
},
  "geometry": {"coordinates":[2.21667,51.03333],"type":"Point"}
}