{
  "type": "Feature",
  "properties": {
    "frgov:code_epci":"200071181",
    "frgov:insee_arr":"2",
    "frgov:insee_com":"80455",
    "frgov:insee_dep":"80",
    "frgov:insee_reg":"32",
    "frgov:nom_com":"Lachapelle",
    "frgov:nom_com_m":"LACHAPELLE",
    "frgov:nom_dep":"SOMME",
    "frgov:nom_reg":"HAUTS-DE-FRANCE",
    "frgov:statut":"Commune simple",
    "gn:admin1_code":"32",
    "gn:admin2_code":"80",
    "gn:admin3_code":"802",
    "gn:admin4_code":"80455",
    "gn:asciiname":"Lachapelle",
    "gn:cc2":"FR",
    "gn:country_code":"FR",
    "gn:dem":160,
    "gn:feature_class":"P",
    "gn:feature_code":"PPL",
    "gn:name":"Lachapelle",
    "gn:population":0,
    "gn:timezone":"Europe/Paris",
    "iso:country":"FR",
    "name:ceb_x_preferred":[
        "Lachapelle"
    ],
    "name:deu_x_preferred":[
        "Lachapelle"
    ],
    "name:fra_x_preferred":[
        "Lachapelle"
    ],
    "name:ita_x_preferred":[
        "Lachapelle"
    ],
    "name:nds_x_preferred":[
        "Lachapelle"
    ],
    "name:nld_x_preferred":[
        "Lachapelle"
    ],
    "name:oci_x_preferred":[
        "Lachapelle"
    ],
    "name:pms_x_preferred":[
        "Lachapelle"
    ],
    "name:pol_x_preferred":[
        "Lachapelle"
    ],
    "name:rus_x_preferred":[
        "\u041b\u0430\u0448\u0430\u043f\u0435\u043b\u044c"
    ],
    "name:scn_x_preferred":[
        "Lachapelle"
    ],
    "name:slk_x_preferred":[
        "Lachapelle"
    ],
    "name:spa_x_preferred":[
        "Lachapelle"
    ],
    "name:swe_x_preferred":[
        "Lachapelle"
    ],
    "name:ukr_x_preferred":[
        "\u041b\u0430\u0448\u0430\u043f\u0435\u043b\u044c"
    ],
    "name:und_x_variant":[
        "Lachapelle-sur-Poix"
    ],
    "qs:a0":"France",
    "qs:a1":"SOMME",
    "qs:a1_lc":"80",
    "qs:a1r":"PICARDIE",
    "qs:a1r_lc":"22",
    "qs:a2_lc":"35",
    "qs:a2r_lc":"2",
    "qs:adm0":"France",
    "qs:adm0_a3":"FRA",
    "qs:la":"LACHAPELLE",
    "qs:la_lc":"80455",
    "qs:level":"localadmin",
    "qs:type":"Commune simple",
    "wof:coterminous":[
        404380671
    ],
    "wof:name":"Lachapelle",
    "wof:placetype":"locality",
    "wof:placetype_local":"Commune simple"
},
  "geometry": {"coordinates":[1.95,49.76667],"type":"Point"}
}