{
  "type": "Feature",
  "properties": {
    "gn:admin1_code":"32",
    "gn:admin2_code":"80",
    "gn:admin3_code":"802",
    "gn:admin4_code":"80455",
    "gn:asciiname":"Lachapelle",
    "gn:cc2":"FR",
    "gn:country_code":"FR",
    "gn:dem":160,
    "gn:feature_class":"P",
    "gn:feature_code":"PPL",
    "gn:name":"Lachapelle",
    "gn:population":0,
    "gn:timezone":"Europe/Paris",
    "iso:country":"FR",
    "name:und_x_variant":[
        "Lachapelle-sur-Poix"
    ],
    "wof:name":"Lachapelle",
    "wof:placetype":"locality"
},
  "geometry": {"coordinates":[1.95,49.76667],"type":"Point"}
}