{
  "type": "Feature",
  "properties": {
    "gn:gn_country":"FR",
    "gn:gn_fcode":"PPL",
    "gn:gn_pop":0,
    "iso:country":"FR",
    "name:arg_x_preferred":[
        "Aigas Caudas"
    ],
    "name:cat_x_preferred":[
        "Aigas Caudas"
    ],
    "name:eng_x_preferred":[
        "Eaux-Chaudes"
    ],
    "name:fra_x_preferred":[
        "Eaux-Chaudes"
    ],
    "name:nld_x_preferred":[
        "Eaux-Chaudes"
    ],
    "name:zho_x_preferred":[
        "\u6bd4\u5229\u725b\u65af\u5927\u897f\u6d0b\u6e29\u6cc9"
    ],
    "qs_pg:aaroncc":"FR",
    "qs_pg:gn_country":"FR",
    "qs_pg:gn_fcode":"PPL",
    "qs_pg:gn_pop":0,
    "qs_pg:name":"Eaux Chaudes",
    "qs_pg:name_adm0":"France",
    "qs_pg:name_adm1":"Aquitaine",
    "qs_pg:photos":71,
    "qs_pg:photos_1k":14,
    "qs_pg:photos_9k":1,
    "qs_pg:photos_9r":2,
    "qs_pg:photos_all":71,
    "qs_pg:photos_sr":2,
    "qs_pg:pop_sr":0,
    "qs_pg:qs_pg_placetype":"locality",
    "qs_pg:qs_pg_placetype_gp":"Town",
    "qs_pg:woe_adm0":23424819,
    "woe:adm0_id":23424819,
    "woe:name_adm0":"France",
    "woe:name_adm1":"Aquitaine",
    "woe:placetype":"Town",
    "wof:name":"Eaux Chaudes",
    "wof:placetype":"neighbourhood"
},
  "geometry": {"coordinates":[-0.4395,42.95375],"type":"Point"}
}