{
  "type": "Feature",
  "properties": {
    "gn:admin1_code":"84",
    "gn:admin2_code":"43",
    "gn:admin3_code":"433",
    "gn:admin4_code":"43212",
    "gn:asciiname":"Saint-Pal-de-Chalencon",
    "gn:cc2":"FR",
    "gn:country_code":"FR",
    "gn:dem":886,
    "gn:feature_class":"P",
    "gn:feature_code":"PPL",
    "gn:name":"Saint-Pal-de-Chalencon",
    "gn:population":0,
    "gn:timezone":"Europe/Paris",
    "iso:country":"FR",
    "name:und_x_variant":[
        "Saint-Pal"
    ],
    "wof:name":"Saint-Pal-de-Chalencon",
    "wof:placetype":"locality"
},
  "geometry": {"coordinates":[3.95,45.35],"type":"Point"}
}