{
  "type": "Feature",
  "properties": {
    "gn:admin1_code":"75",
    "gn:admin2_code":"23",
    "gn:admin3_code":"232",
    "gn:admin4_code":"23006",
    "gn:asciiname":"La Ronze",
    "gn:country_code":"FR",
    "gn:dem":446,
    "gn:feature_class":"P",
    "gn:feature_code":"PPL",
    "gn:name":"La Ronze",
    "gn:population":0,
    "gn:timezone":"Europe/Paris",
    "iso:country":"FR",
    "wof:name":"La Ronze",
    "wof:placetype":"locality"
},
  "geometry": {"coordinates":[1.57362,46.06283],"type":"Point"}
}