{
  "type": "Feature",
  "properties": {
    "gn:admin1_code":"93",
    "gn:admin2_code":"04",
    "gn:admin3_code":"043",
    "gn:admin4_code":"04024",
    "gn:asciiname":"Giraud",
    "gn:country_code":"FR",
    "gn:dem":1359,
    "gn:feature_class":"P",
    "gn:feature_code":"PPL",
    "gn:name":"Giraud",
    "gn:population":0,
    "gn:timezone":"Europe/Paris",
    "iso:country":"FR",
    "wof:name":"Giraud",
    "wof:placetype":"locality"
},
  "geometry": {"coordinates":[6.41667,44.23333],"type":"Point"}
}