{
  "type": "Feature",
  "properties": {
    "gn:admin1_code":"27",
    "gn:admin2_code":"21",
    "gn:admin3_code":"213",
    "gn:admin4_code":"21685",
    "gn:asciiname":"Chalvosson",
    "gn:country_code":"FR",
    "gn:dem":357,
    "gn:feature_class":"P",
    "gn:feature_code":"PPL",
    "gn:name":"Chalvosson",
    "gn:population":0,
    "gn:timezone":"Europe/Paris",
    "iso:country":"FR",
    "name:und_x_variant":[
        "Chalvasson",
        "Chalvosson"
    ],
    "wof:name":"Chalvosson",
    "wof:placetype":"locality"
},
  "geometry": {"coordinates":[4.56548,47.67548],"type":"Point"}
}