{
  "type": "Feature",
  "properties": {
    "gn:admin1_code":"84",
    "gn:admin2_code":"73",
    "gn:admin3_code":"732",
    "gn:admin4_code":"73274",
    "gn:asciiname":"Les Courriers",
    "gn:country_code":"FR",
    "gn:dem":763,
    "gn:feature_class":"P",
    "gn:feature_code":"PPL",
    "gn:name":"Les Courriers",
    "gn:population":0,
    "gn:timezone":"Europe/Paris",
    "iso:country":"FR",
    "wof:name":"Les Courriers",
    "wof:placetype":"locality"
},
  "geometry": {"coordinates":[5.86915,45.43279],"type":"Point"}
}