{
  "type": "Feature",
  "properties": {
    "frgov:code_epci":"200070068",
    "frgov:insee_arr":"1",
    "frgov:insee_com":"76399",
    "frgov:insee_dep":"76",
    "frgov:insee_reg":"28",
    "frgov:nom_com":"Lucy",
    "frgov:nom_com_m":"LUCY",
    "frgov:nom_dep":"SEINE-MARITIME",
    "frgov:nom_reg":"NORMANDIE",
    "frgov:statut":"Commune simple",
    "gn:admin1_code":"28",
    "gn:admin2_code":"76",
    "gn:admin3_code":"761",
    "gn:admin4_code":"76399",
    "gn:asciiname":"Lucy",
    "gn:country_code":"FR",
    "gn:dem":112,
    "gn:feature_class":"P",
    "gn:feature_code":"PPL",
    "gn:name":"Lucy",
    "gn:population":146,
    "gn:timezone":"Europe/Paris",
    "iso:country":"FR",
    "name:deu_x_preferred":[
        "Lucy"
    ],
    "name:est_x_preferred":[
        "Lucy"
    ],
    "name:fra_x_preferred":[
        "Lucy"
    ],
    "name:nld_x_preferred":[
        "Lucy"
    ],
    "name:nor_x_preferred":[
        "Lucy"
    ],
    "qs:a0":"France",
    "qs:a1":"SEINE-MARITIME",
    "qs:a1_lc":"76",
    "qs:a1r":"HAUTE-NORMANDIE",
    "qs:a1r_lc":"23",
    "qs:a2_lc":"38",
    "qs:a2r_lc":"1",
    "qs:adm0":"France",
    "qs:adm0_a3":"FRA",
    "qs:la":"LUCY",
    "qs:la_lc":"76399",
    "qs:level":"localadmin",
    "qs:type":"Commune simple",
    "wof:coterminous":[
        404423945
    ],
    "wof:name":"Lucy",
    "wof:placetype":"locality",
    "wof:placetype_local":"Commune simple",
    "wof:population":146
},
  "geometry": {"coordinates":[1.45599,49.7837],"type":"Point"}
}