{
  "type": "Feature",
  "properties": {
    "gn:admin1_code":"28",
    "gn:admin2_code":"76",
    "gn:admin3_code":"761",
    "gn:admin4_code":"76399",
    "gn:asciiname":"Lucy",
    "gn:country_code":"FR",
    "gn:dem":112,
    "gn:feature_class":"P",
    "gn:feature_code":"PPL",
    "gn:name":"Lucy",
    "gn:population":146,
    "gn:timezone":"Europe/Paris",
    "iso:country":"FR",
    "name:deu_x_preferred":[
        "Lucy"
    ],
    "name:est_x_preferred":[
        "Lucy"
    ],
    "name:fra_x_preferred":[
        "Lucy"
    ],
    "name:nld_x_preferred":[
        "Lucy"
    ],
    "name:nor_x_preferred":[
        "Lucy"
    ],
    "wof:name":"Lucy",
    "wof:placetype":"locality",
    "wof:population":146
},
  "geometry": {"coordinates":[1.45599,49.7837],"type":"Point"}
}