{
  "type": "Feature",
  "properties": {
    "gn:admin1_code":"84",
    "gn:admin2_code":"26",
    "gn:admin3_code":"262",
    "gn:admin4_code":"26089",
    "gn:asciiname":"Les Nauds",
    "gn:country_code":"FR",
    "gn:dem":700,
    "gn:feature_class":"P",
    "gn:feature_code":"PPL",
    "gn:name":"Les Nauds",
    "gn:population":0,
    "gn:timezone":"Europe/Paris",
    "iso:country":"FR",
    "wof:name":"Les Nauds",
    "wof:placetype":"locality"
},
  "geometry": {"coordinates":[5.21758,44.47732],"type":"Point"}
}