{
  "type": "Feature",
  "properties": {
    "gn:admin1_code":"11",
    "gn:admin2_code":"77",
    "gn:admin3_code":"772",
    "gn:admin4_code":"77034",
    "gn:asciiname":"Blandy",
    "gn:country_code":"FR",
    "gn:dem":85,
    "gn:feature_class":"P",
    "gn:feature_code":"PPL",
    "gn:name":"Blandy",
    "gn:population":785,
    "gn:timezone":"Europe/Paris",
    "iso:country":"FR",
    "name:und_x_variant":[
        "Blandy-les-Tours",
        "Blandy"
    ],
    "wof:name":"Blandy",
    "wof:placetype":"locality",
    "wof:population":785
},
  "geometry": {"coordinates":[2.78178,48.56718],"type":"Point"}
}