{
  "type": "Feature",
  "properties": {
    "gn:admin1_code":"24",
    "gn:admin2_code":"45",
    "gn:admin3_code":"451",
    "gn:admin4_code":"45328.0",
    "gn:asciiname":"Chaisnois",
    "gn:country_code":"FR",
    "gn:dem":95,
    "gn:feature_class":"P",
    "gn:feature_code":"PPL",
    "gn:name":"Chaisnois",
    "gn:population":0,
    "gn:timezone":"Europe/Paris",
    "iso:country":"FR",
    "name:und_x_variant":[
        "Le Ch\u00eanoi",
        "Chaisnois"
    ],
    "wof:name":"Chaisnois",
    "wof:placetype":"locality"
},
  "geometry": {"coordinates":[2.66156,48.09211],"type":"Point"}
}