{
  "type": "Feature",
  "properties": {
    "gn:admin1_code":"44",
    "gn:admin2_code":"10",
    "gn:admin3_code":"103",
    "gn:admin4_code":"10099",
    "gn:asciiname":"Loge-Borgne",
    "gn:country_code":"FR",
    "gn:dem":138,
    "gn:feature_class":"P",
    "gn:feature_code":"PPL",
    "gn:name":"Loge-Borgne",
    "gn:population":0,
    "gn:timezone":"Europe/Paris",
    "iso:country":"FR",
    "wof:name":"Loge-Borgne",
    "wof:placetype":"locality"
},
  "geometry": {"coordinates":[3.92448,47.99882],"type":"Point"}
}