{
  "type": "Feature",
  "properties": {
    "frgov:code_epci":"200040210",
    "frgov:insee_arr":"1",
    "frgov:insee_com":"83020",
    "frgov:insee_dep":"83",
    "frgov:insee_reg":"93",
    "frgov:nom_com":"Le Bourguet",
    "frgov:nom_com_m":"LE BOURGUET",
    "frgov:nom_dep":"VAR",
    "frgov:nom_reg":"PROVENCE-ALPES-COTE D'AZUR",
    "frgov:statut":"Commune simple",
    "gn:admin1_code":"93",
    "gn:admin2_code":"83",
    "gn:admin3_code":"831",
    "gn:admin4_code":"83020",
    "gn:asciiname":"Le Bourguet",
    "gn:country_code":"FR",
    "gn:dem":845,
    "gn:feature_class":"P",
    "gn:feature_code":"PPL",
    "gn:name":"Le Bourguet",
    "gn:population":0,
    "gn:timezone":"Europe/Paris",
    "iso:country":"FR",
    "name:cat_x_preferred":[
        "Sant P\u00e8ire de Bagarri"
    ],
    "name:ceb_x_preferred":[
        "Le Bourguet"
    ],
    "name:deu_x_preferred":[
        "Le Bourguet"
    ],
    "name:eus_x_preferred":[
        "Le Bourguet"
    ],
    "name:fra_x_preferred":[
        "Le Bourguet"
    ],
    "name:hbs_x_preferred":[
        "Bourguet"
    ],
    "name:hun_x_preferred":[
        "Le Bourguet"
    ],
    "name:ita_x_preferred":[
        "Le Bourguet"
    ],
    "name:lmo_x_preferred":[
        "Le Bourguet"
    ],
    "name:mlg_x_preferred":[
        "Le Bourguet"
    ],
    "name:msa_x_preferred":[
        "Le Bourguet"
    ],
    "name:nld_x_preferred":[
        "Le Bourguet"
    ],
    "name:oci_x_preferred":[
        "Lo Borguet"
    ],
    "name:pms_x_preferred":[
        "Le Bourguet"
    ],
    "name:pol_x_preferred":[
        "Le Bourguet"
    ],
    "name:por_x_preferred":[
        "Le Bourguet"
    ],
    "name:ron_x_preferred":[
        "Le Bourguet"
    ],
    "name:rus_x_preferred":[
        "\u041b\u0435-\u0411\u0443\u0440\u0433\u0435"
    ],
    "name:slk_x_preferred":[
        "Le Bourguet"
    ],
    "name:spa_x_preferred":[
        "Le Bourguet"
    ],
    "name:srp_x_preferred":[
        "\u0411\u0443\u0440\u0433\u0435"
    ],
    "name:swe_x_preferred":[
        "Le Bourguet"
    ],
    "name:ukr_x_preferred":[
        "\u041b\u0435-\u0411\u0443\u0440\u0433\u0435"
    ],
    "name:vie_x_preferred":[
        "Le Bourguet"
    ],
    "name:vol_x_preferred":[
        "Le Bourguet"
    ],
    "name:war_x_preferred":[
        "Le Bourguet"
    ],
    "name:zho_x_preferred":[
        "\u83b1\u5e03\u5c14\u5c45\u5384"
    ],
    "name:zho_x_variant":[
        "\u52d2\u5e03\u5c14\u76d6"
    ],
    "qs:a0":"France",
    "qs:a1":"VAR",
    "qs:a1_lc":"83",
    "qs:a1r":"PROVENCE-ALPES-COTE D'AZUR",
    "qs:a1r_lc":"93",
    "qs:a2_lc":"08",
    "qs:a2r_lc":"1",
    "qs:adm0":"France",
    "qs:adm0_a3":"FRA",
    "qs:la":"LE BOURGUET",
    "qs:la_lc":"83020",
    "qs:level":"localadmin",
    "qs:type":"Commune simple",
    "wof:coterminous":[
        404359273
    ],
    "wof:name":"Le Bourguet",
    "wof:placetype":"locality",
    "wof:placetype_local":"Commune simple"
},
  "geometry": {"coordinates":[6.51872,43.7833],"type":"Point"}
}