{
  "type": "Feature",
  "properties": {
    "gn:admin1_code":"93",
    "gn:admin2_code":"83",
    "gn:admin3_code":"831",
    "gn:admin4_code":"83020",
    "gn:asciiname":"Le Bourguet",
    "gn:country_code":"FR",
    "gn:dem":845,
    "gn:feature_class":"P",
    "gn:feature_code":"PPL",
    "gn:name":"Le Bourguet",
    "gn:population":0,
    "gn:timezone":"Europe/Paris",
    "iso:country":"FR",
    "name:cat_x_preferred":[
        "Sant P\u00e8ire de Bagarri"
    ],
    "name:ceb_x_preferred":[
        "Le Bourguet"
    ],
    "name:deu_x_preferred":[
        "Le Bourguet"
    ],
    "name:eus_x_preferred":[
        "Le Bourguet"
    ],
    "name:fra_x_preferred":[
        "Le Bourguet"
    ],
    "name:hbs_x_preferred":[
        "Bourguet"
    ],
    "name:hun_x_preferred":[
        "Le Bourguet"
    ],
    "name:ita_x_preferred":[
        "Le Bourguet"
    ],
    "name:lmo_x_preferred":[
        "Le Bourguet"
    ],
    "name:mlg_x_preferred":[
        "Le Bourguet"
    ],
    "name:msa_x_preferred":[
        "Le Bourguet"
    ],
    "name:nld_x_preferred":[
        "Le Bourguet"
    ],
    "name:oci_x_preferred":[
        "Lo Borguet"
    ],
    "name:pms_x_preferred":[
        "Le Bourguet"
    ],
    "name:pol_x_preferred":[
        "Le Bourguet"
    ],
    "name:por_x_preferred":[
        "Le Bourguet"
    ],
    "name:ron_x_preferred":[
        "Le Bourguet"
    ],
    "name:rus_x_preferred":[
        "\u041b\u0435-\u0411\u0443\u0440\u0433\u0435"
    ],
    "name:slk_x_preferred":[
        "Le Bourguet"
    ],
    "name:spa_x_preferred":[
        "Le Bourguet"
    ],
    "name:srp_x_preferred":[
        "\u0411\u0443\u0440\u0433\u0435"
    ],
    "name:swe_x_preferred":[
        "Le Bourguet"
    ],
    "name:ukr_x_preferred":[
        "\u041b\u0435-\u0411\u0443\u0440\u0433\u0435"
    ],
    "name:vie_x_preferred":[
        "Le Bourguet"
    ],
    "name:vol_x_preferred":[
        "Le Bourguet"
    ],
    "name:war_x_preferred":[
        "Le Bourguet"
    ],
    "name:zho_x_preferred":[
        "\u83b1\u5e03\u5c14\u5c45\u5384"
    ],
    "name:zho_x_variant":[
        "\u52d2\u5e03\u5c14\u76d6"
    ],
    "wof:name":"Le Bourguet",
    "wof:placetype":"locality"
},
  "geometry": {"coordinates":[6.51872,43.7833],"type":"Point"}
}