{
  "type": "Feature",
  "properties": {
    "gn:admin1_code":"24",
    "gn:admin2_code":"45",
    "gn:admin3_code":"451",
    "gn:admin4_code":"45332",
    "gn:asciiname":"Lieux des Champs",
    "gn:country_code":"FR",
    "gn:dem":112,
    "gn:feature_class":"P",
    "gn:feature_code":"PPL",
    "gn:name":"Lieux des Champs",
    "gn:population":0,
    "gn:timezone":"Europe/Paris",
    "iso:country":"FR",
    "wof:name":"Lieux des Champs",
    "wof:placetype":"locality"
},
  "geometry": {"coordinates":[2.68123,47.86958],"type":"Point"}
}