{
  "type": "Feature",
  "properties": {
    "gn:admin1_code":"27",
    "gn:admin2_code":"58",
    "gn:admin3_code":"583",
    "gn:admin4_code":"58254",
    "gn:asciiname":"Le Gue-d'Heuillon",
    "gn:country_code":"FR",
    "gn:dem":188,
    "gn:feature_class":"P",
    "gn:feature_code":"PPL",
    "gn:name":"Le Gu\u00e9-d\u2019Heuillon",
    "gn:population":0,
    "gn:timezone":"Europe/Paris",
    "iso:country":"FR",
    "wof:name":"Le Gue-d'Heuillon",
    "wof:placetype":"locality"
},
  "geometry": {"coordinates":[3.21313,47.04559],"type":"Point"}
}