{
  "type": "Feature",
  "properties": {
    "gn:admin1_code":"84",
    "gn:admin2_code":"43",
    "gn:admin3_code":"433",
    "gn:admin4_code":"43162.0",
    "gn:asciiname":"Retournaque",
    "gn:country_code":"FR",
    "gn:dem":537,
    "gn:feature_class":"P",
    "gn:feature_code":"PPL",
    "gn:name":"Retournaque",
    "gn:population":0,
    "gn:timezone":"Europe/Paris",
    "iso:country":"FR",
    "name:und_x_variant":[
        "Retournaquet",
        "Retournaque"
    ],
    "wof:name":"Retournaque",
    "wof:placetype":"locality"
},
  "geometry": {"coordinates":[4.03107,45.19728],"type":"Point"}
}