{
  "type": "Feature",
  "properties": {
    "iso:country":"FR",
    "wof:name":"La Confluence",
    "wof:placetype":"neighbourhood"
},
  "geometry": {"coordinates":[4.8182236751455,45.73816707725761],"type":"Point"}
}