{
  "type": "Feature",
  "properties": {
    "gn:admin1_code":"84",
    "gn:admin2_code":"69",
    "gn:admin3_code":"692",
    "gn:admin4_code":"69200",
    "gn:asciiname":"La Favrotiere",
    "gn:country_code":"FR",
    "gn:dem":619,
    "gn:feature_class":"P",
    "gn:feature_code":"PPL",
    "gn:name":"La Favroti\u00e8re",
    "gn:population":0,
    "gn:timezone":"Europe/Paris",
    "iso:country":"FR",
    "wof:name":"La Favrotiere",
    "wof:placetype":"locality"
},
  "geometry": {"coordinates":[4.46737,45.83347],"type":"Point"}
}