{
  "type": "Feature",
  "properties": {
    "gn:admin1_code":"27",
    "gn:admin2_code":"39",
    "gn:admin3_code":"392",
    "gn:admin4_code":"39397",
    "gn:asciiname":"Sezeria",
    "gn:country_code":"FR",
    "gn:dem":495,
    "gn:feature_class":"P",
    "gn:feature_code":"PPL",
    "gn:name":"S\u00e9z\u00e9ria",
    "gn:population":0,
    "gn:timezone":"Europe/Paris",
    "iso:country":"FR",
    "name:und_x_variant":[
        "S\u00e9z\u00e9ria"
    ],
    "wof:name":"Sezeria",
    "wof:placetype":"locality"
},
  "geometry": {"coordinates":[5.58147,46.5156],"type":"Point"}
}