{
  "type": "Feature",
  "properties": {
    "gn:admin1_code":"84",
    "gn:admin2_code":"01",
    "gn:admin3_code":"014",
    "gn:admin4_code":"01189",
    "gn:asciiname":"Craz",
    "gn:country_code":"FR",
    "gn:dem":665,
    "gn:feature_class":"P",
    "gn:feature_code":"PPL",
    "gn:name":"Craz",
    "gn:population":0,
    "gn:timezone":"Europe/Paris",
    "iso:country":"FR",
    "wof:name":"Craz",
    "wof:placetype":"locality"
},
  "geometry": {"coordinates":[5.75648,46.04178],"type":"Point"}
}