{
  "type": "Feature",
  "properties": {
    "gn:admin1_code":"93",
    "gn:admin2_code":"06",
    "gn:admin3_code":"062",
    "gn:admin4_code":"06146",
    "gn:asciiname":"La Courbaisse",
    "gn:country_code":"FR",
    "gn:dem":229,
    "gn:feature_class":"P",
    "gn:feature_code":"PPL",
    "gn:name":"La Courbaisse",
    "gn:population":0,
    "gn:timezone":"Europe/Paris",
    "iso:country":"FR",
    "name:und_x_variant":[
        "Corbaissa",
        "La Courbaisse"
    ],
    "wof:name":"La Courbaisse",
    "wof:placetype":"locality"
},
  "geometry": {"coordinates":[7.18565,43.92246],"type":"Point"}
}