{
  "type": "Feature",
  "properties": {
    "gn:admin1_code":"28",
    "gn:admin2_code":"76",
    "gn:admin3_code":"762",
    "gn:admin4_code":"76499.0",
    "gn:asciiname":"Les Nouettes",
    "gn:country_code":"FR",
    "gn:dem":3,
    "gn:feature_class":"P",
    "gn:feature_code":"PPL",
    "gn:name":"Les Nouettes",
    "gn:population":0,
    "gn:timezone":"Europe/Paris",
    "iso:country":"FR",
    "wof:name":"Les Nouettes",
    "wof:placetype":"locality"
},
  "geometry": {"coordinates":[0.6052,49.43842],"type":"Point"}
}