{
  "type": "Feature",
  "properties": {
    "gn:admin1_code":"93",
    "gn:admin2_code":"83",
    "gn:admin3_code":"831",
    "gn:admin4_code":"83004",
    "gn:asciiname":"Pomples",
    "gn:country_code":"FR",
    "gn:dem":178,
    "gn:feature_class":"P",
    "gn:feature_code":"PPL",
    "gn:name":"Pomples",
    "gn:population":0,
    "gn:timezone":"Europe/Paris",
    "iso:country":"FR",
    "wof:name":"Pomples",
    "wof:placetype":"locality"
},
  "geometry": {"coordinates":[6.53333,43.43333],"type":"Point"}
}