{
  "type": "Feature",
  "properties": {
    "gn:admin1_code":"76",
    "gn:admin2_code":"12",
    "gn:admin3_code":"122",
    "gn:admin4_code":"12214",
    "gn:asciiname":"Saint-Chely-d'Aubrac",
    "gn:country_code":"FR",
    "gn:dem":803,
    "gn:feature_class":"P",
    "gn:feature_code":"PPL",
    "gn:name":"Saint-Ch\u00e9ly-d\u2019Aubrac",
    "gn:population":0,
    "gn:timezone":"Europe/Paris",
    "iso:country":"FR",
    "name:ceb_x_preferred":[
        "Saint-Ch\u00e9ly-d'Aubrac"
    ],
    "name:deu_x_preferred":[
        "Saint-Ch\u00e9ly-d\u2019Aubrac"
    ],
    "name:eus_x_preferred":[
        "Saint-Ch\u00e9ly-d'Aubrac"
    ],
    "name:fin_x_preferred":[
        "Saint-Ch\u00e9ly-d\u2019Aubrac"
    ],
    "name:fra_x_preferred":[
        "Saint-Ch\u00e9ly-d'Aubrac"
    ],
    "name:hun_x_preferred":[
        "Saint-Ch\u00e9ly-d\u2019Aubrac"
    ],
    "name:ita_x_preferred":[
        "Saint-Ch\u00e9ly-d'Aubrac"
    ],
    "name:jpn_x_preferred":[
        "\u30b5\u30f3\uff1d\u30b7\u30a7\u30ea\uff1d\u30c9\u30d6\u30e9\u30c3\u30af"
    ],
    "name:lat_x_preferred":[
        "Saint-Ch\u00e9ly-d'Aubrac"
    ],
    "name:mlg_x_preferred":[
        "Saint-Ch\u00e9ly-d'Aubrac"
    ],
    "name:msa_x_preferred":[
        "Saint-Ch\u00e9ly-d'Aubrac"
    ],
    "name:nld_x_preferred":[
        "Saint-Ch\u00e9ly-d'Aubrac"
    ],
    "name:pol_x_preferred":[
        "Saint-Ch\u00e9ly-d\u2019Aubrac"
    ],
    "name:por_x_preferred":[
        "Saint-Ch\u00e9ly-d'Aubrac"
    ],
    "name:ron_x_preferred":[
        "Saint-Ch\u00e9ly-d'Aubrac"
    ],
    "name:rus_x_preferred":[
        "\u0421\u0435\u043d-\u0428\u0435\u043b\u0438-\u0434\u2019\u041e\u0431\u0440\u0430\u043a"
    ],
    "name:slk_x_preferred":[
        "Saint-Ch\u00e9ly-d\u2019Aubrac"
    ],
    "name:slv_x_preferred":[
        "Saint-Ch\u00e9ly-d'Aubrac"
    ],
    "name:spa_x_preferred":[
        "Saint-Ch\u00e9ly-d'Aubrac"
    ],
    "name:swe_x_preferred":[
        "Saint-Ch\u00e9ly-d'Aubrac"
    ],
    "name:ukr_x_preferred":[
        "\u0421\u0435\u043d-\u0428\u0435\u043b\u0456-\u0434'\u041e\u0431\u0440\u0430\u043a"
    ],
    "name:und_x_variant":[
        "Saint-Ch\u00e9ly"
    ],
    "name:urd_x_preferred":[
        "\u0633\u06cc\u0646\u0679-\u0686\u0644\u06d2-\u062f\u0648\u0628\u0631\u06a9"
    ],
    "name:vie_x_preferred":[
        "Saint-Ch\u00e9ly-d'Aubrac"
    ],
    "name:vol_x_preferred":[
        "Saint-Ch\u00e9ly-d'Aubrac"
    ],
    "name:war_x_preferred":[
        "Saint-Ch\u00e9ly-d'Aubrac"
    ],
    "name:zho_x_preferred":[
        "\u5723\u8c22\u5229\u591a\u5e03\u62c9\u514b"
    ],
    "wof:name":"Saint-Chely-d'Aubrac",
    "wof:placetype":"locality"
},
  "geometry": {"coordinates":[2.92469,44.59102],"type":"Point"}
}