{
  "type": "Feature",
  "properties": {
    "gn:admin1_code":"53",
    "gn:admin2_code":"35",
    "gn:admin3_code":"351",
    "gn:admin4_code":"35272",
    "gn:asciiname":"Le Vivier",
    "gn:country_code":"FR",
    "gn:dem":84,
    "gn:feature_class":"P",
    "gn:feature_code":"PPL",
    "gn:name":"Le Vivier",
    "gn:population":0,
    "gn:timezone":"Europe/Paris",
    "iso:country":"FR",
    "name:arg_x_preferred":[
        "Lo Vivi\u00e8r"
    ],
    "name:bug_x_preferred":[
        "Le Vivier"
    ],
    "name:cat_x_preferred":[
        "El Viver"
    ],
    "name:ceb_x_preferred":[
        "Le Vivier"
    ],
    "name:dan_x_preferred":[
        "Le Vivier"
    ],
    "name:deu_x_preferred":[
        "Le Vivier"
    ],
    "name:eus_x_preferred":[
        "Le Vivier"
    ],
    "name:fra_x_preferred":[
        "Le Vivier"
    ],
    "name:hun_x_preferred":[
        "Le Vivier"
    ],
    "name:ita_x_preferred":[
        "Le Vivier"
    ],
    "name:kaz_x_preferred":[
        "\u041b\u0435-\u0412\u0438\u0432\u044c\u0435"
    ],
    "name:lat_x_preferred":[
        "Le Vivier"
    ],
    "name:lmo_x_preferred":[
        "Le Vivier"
    ],
    "name:msa_x_preferred":[
        "Le Vivier"
    ],
    "name:nld_x_preferred":[
        "Le Vivier"
    ],
    "name:oci_x_preferred":[
        "Lo Vivi\u00e8r"
    ],
    "name:pol_x_preferred":[
        "Vivier"
    ],
    "name:ron_x_preferred":[
        "Le Vivier"
    ],
    "name:slk_x_preferred":[
        "Le Vivier"
    ],
    "name:spa_x_preferred":[
        "Le Vivier"
    ],
    "name:swe_x_preferred":[
        "Le Vivier"
    ],
    "name:ukr_x_preferred":[
        "\u041b\u0435-\u0412\u0456\u0432'\u0454"
    ],
    "name:vie_x_preferred":[
        "Le Vivier"
    ],
    "name:vol_x_preferred":[
        "Le Vivier"
    ],
    "name:war_x_preferred":[
        "Le Vivier"
    ],
    "name:zho_x_preferred":[
        "\u52d2\u7ef4\u7ef4\u8036"
    ],
    "wof:name":"Le Vivier",
    "wof:placetype":"locality"
},
  "geometry": {"coordinates":[-1.17258,48.00275],"type":"Point"}
}