{
  "type": "Feature",
  "properties": {
    "gn:admin1_code":"53",
    "gn:admin2_code":"35",
    "gn:admin3_code":"351",
    "gn:admin4_code":"35272",
    "gn:asciiname":"Le Vivier",
    "gn:country_code":"FR",
    "gn:dem":84,
    "gn:feature_class":"P",
    "gn:feature_code":"PPL",
    "gn:name":"Le Vivier",
    "gn:population":0,
    "gn:timezone":"Europe/Paris",
    "iso:country":"FR",
    "wof:name":"Le Vivier",
    "wof:placetype":"locality"
},
  "geometry": {"coordinates":[-1.17258,48.00275],"type":"Point"}
}