{
  "type": "Feature",
  "properties": {
    "gn:admin1_code":"76",
    "gn:asciiname":"Cave de la Pinede",
    "gn:country_code":"FR",
    "gn:dem":2,
    "gn:feature_class":"P",
    "gn:feature_code":"PPL",
    "gn:name":"Cave de la Pin\u00e8de",
    "gn:population":0,
    "gn:timezone":"Europe/Paris",
    "iso:country":"FR",
    "wof:name":"Cave de la Pinede",
    "wof:placetype":"locality"
},
  "geometry": {"coordinates":[4.33017,43.4715],"type":"Point"}
}