{
  "type": "Feature",
  "properties": {
    "iso:country":"FR",
    "name:eng_x_preferred":[
        "Centre-Ville-Gare"
    ],
    "name:fra_x_preferred":[
        "Centre-Ville-Gare"
    ],
    "wof:name":"Centre-Ville-Gare",
    "wof:placetype":"neighbourhood"
},
  "geometry": {"coordinates":[2.46056392898705,48.89359643444419],"type":"Point"}
}