{
  "type": "Feature",
  "properties": {
    "gn:admin1_code":"52",
    "gn:admin2_code":"44",
    "gn:admin3_code":"444",
    "gn:admin4_code":"44115",
    "gn:asciiname":"Blanche-Lande",
    "gn:country_code":"FR",
    "gn:dem":64,
    "gn:feature_class":"P",
    "gn:feature_code":"PPL",
    "gn:name":"Blanche-Lande",
    "gn:population":0,
    "gn:timezone":"Europe/Paris",
    "iso:country":"FR",
    "wof:name":"Blanche-Lande",
    "wof:placetype":"locality"
},
  "geometry": {"coordinates":[-1.2569,47.35369],"type":"Point"}
}