{
  "type": "Feature",
  "properties": {
    "gn:admin1_code":"84",
    "gn:admin2_code":"26",
    "gn:admin3_code":"262",
    "gn:admin4_code":"26220",
    "gn:asciiname":"Le Rieu",
    "gn:country_code":"FR",
    "gn:dem":325,
    "gn:feature_class":"P",
    "gn:feature_code":"PPL",
    "gn:name":"Le Rieu",
    "gn:population":0,
    "gn:timezone":"Europe/Paris",
    "iso:country":"FR",
    "wof:name":"Le Rieu",
    "wof:placetype":"locality"
},
  "geometry": {"coordinates":[5.1544,44.35856],"type":"Point"}
}