{
  "type": "Feature",
  "properties": {
    "gn:admin1_code":"75",
    "gn:admin2_code":"79",
    "gn:admin3_code":"792",
    "gn:admin4_code":"79136",
    "gn:asciiname":"Loize",
    "gn:country_code":"FR",
    "gn:dem":148,
    "gn:feature_class":"P",
    "gn:feature_code":"PPL",
    "gn:name":"Loiz\u00e9",
    "gn:population":0,
    "gn:timezone":"Europe/Paris",
    "iso:country":"FR",
    "name:und_x_variant":[
        "Loiz\u00e9"
    ],
    "wof:name":"Loize",
    "wof:placetype":"locality"
},
  "geometry": {"coordinates":[-0.03834,46.13247],"type":"Point"}
}