{
  "type": "Feature",
  "properties": {
    "gn:admin1_code":"93",
    "gn:admin2_code":"05",
    "gn:admin3_code":"052",
    "gn:admin4_code":"05144",
    "gn:asciiname":"Lachaup",
    "gn:country_code":"FR",
    "gn:dem":925,
    "gn:feature_class":"P",
    "gn:feature_code":"PPL",
    "gn:name":"Lachaup",
    "gn:population":0,
    "gn:timezone":"Europe/Paris",
    "iso:country":"FR",
    "name:und_x_variant":[
        "La Chalp",
        "Lachaup"
    ],
    "wof:name":"Lachaup",
    "wof:placetype":"locality"
},
  "geometry": {"coordinates":[6.0857,44.79279],"type":"Point"}
}