{
  "type": "Feature",
  "properties": {
    "gn:admin1_code":"75",
    "gn:admin2_code":"86",
    "gn:admin3_code":"863",
    "gn:admin4_code":"86222",
    "gn:asciiname":"Aille",
    "gn:country_code":"FR",
    "gn:dem":71,
    "gn:feature_class":"P",
    "gn:feature_code":"PPL",
    "gn:name":"Aill\u00e9",
    "gn:population":0,
    "gn:timezone":"Europe/Paris",
    "iso:country":"FR",
    "wof:name":"Aille",
    "wof:placetype":"locality"
},
  "geometry": {"coordinates":[0.41145,46.69033],"type":"Point"}
}