{
  "type": "Feature",
  "properties": {
    "gn:admin1_code":"84",
    "gn:admin2_code":"42",
    "gn:admin3_code":"421",
    "gn:admin4_code":"42264",
    "gn:asciiname":"Guillarme",
    "gn:country_code":"FR",
    "gn:dem":600,
    "gn:feature_class":"P",
    "gn:feature_code":"PPL",
    "gn:name":"Guillarme",
    "gn:population":0,
    "gn:timezone":"Europe/Paris",
    "iso:country":"FR",
    "wof:name":"Guillarme",
    "wof:placetype":"locality"
},
  "geometry": {"coordinates":[4.37059,45.58029000000001],"type":"Point"}
}