{
  "type": "Feature",
  "properties": {
    "gn:admin1_code":"27",
    "gn:admin2_code":"25",
    "gn:admin3_code":"252",
    "gn:admin4_code":"25519.0",
    "gn:asciiname":"Mouillevillers",
    "gn:country_code":"FR",
    "gn:dem":547,
    "gn:feature_class":"P",
    "gn:feature_code":"PPL",
    "gn:name":"Mouillevillers",
    "gn:population":0,
    "gn:timezone":"Europe/Paris",
    "iso:country":"FR",
    "wof:name":"Mouillevillers",
    "wof:placetype":"locality"
},
  "geometry": {"coordinates":[6.79981,47.29533],"type":"Point"}
}