{
  "type": "Feature",
  "properties": {
    "gn:admin1_code":"75",
    "gn:admin2_code":"79",
    "gn:admin3_code":"791",
    "gn:admin4_code":"79079",
    "gn:asciiname":"La Chapelle-Largeau",
    "gn:country_code":"FR",
    "gn:dem":169,
    "gn:feature_class":"P",
    "gn:feature_code":"PPL",
    "gn:name":"La Chapelle-Largeau",
    "gn:population":0,
    "gn:timezone":"Europe/Paris",
    "iso:country":"FR",
    "name:und_x_variant":[
        "La Chapelle",
        "La Chapelle-Largeau"
    ],
    "wof:name":"La Chapelle-Largeau",
    "wof:placetype":"locality"
},
  "geometry": {"coordinates":[-0.83762,46.94655],"type":"Point"}
}