{
  "type": "Feature",
  "properties": {
    "gn:admin1_code":"94",
    "gn:admin2_code":"2B",
    "gn:admin3_code":"2B3",
    "gn:admin4_code":"2B095",
    "gn:asciiname":"Cavallaracce",
    "gn:country_code":"FR",
    "gn:dem":859,
    "gn:feature_class":"P",
    "gn:feature_code":"PPL",
    "gn:name":"Cavallaracce",
    "gn:population":0,
    "gn:timezone":"Europe/Paris",
    "iso:country":"FR",
    "wof:name":"Cavallaracce",
    "wof:placetype":"locality"
},
  "geometry": {"coordinates":[9.03992,42.35386],"type":"Point"}
}