{
  "type": "Feature",
  "properties": {
    "gn:admin1_code":"24",
    "gn:admin2_code":"18",
    "gn:admin3_code":"183",
    "gn:admin4_code":"18037",
    "gn:asciiname":"Les Brosses",
    "gn:country_code":"FR",
    "gn:dem":150,
    "gn:feature_class":"P",
    "gn:feature_code":"PPL",
    "gn:name":"Les Brosses",
    "gn:population":0,
    "gn:timezone":"Europe/Paris",
    "iso:country":"FR",
    "wof:name":"Les Brosses",
    "wof:placetype":"locality"
},
  "geometry": {"coordinates":[2.24686,47.60057000000001],"type":"Point"}
}