{
  "type": "Feature",
  "properties": {
    "gn:admin1_code":"27",
    "gn:admin2_code":"89",
    "gn:admin3_code":"891",
    "gn:admin4_code":"89086",
    "gn:asciiname":"La Mothe-aux-Aulnaies",
    "gn:country_code":"FR",
    "gn:dem":129,
    "gn:feature_class":"P",
    "gn:feature_code":"PPL",
    "gn:name":"La Mothe-aux-Aulnaies",
    "gn:population":0,
    "gn:timezone":"Europe/Paris",
    "iso:country":"FR",
    "wof:name":"La Mothe-aux-Aulnaies",
    "wof:placetype":"locality"
},
  "geometry": {"coordinates":[3.08828,47.90592],"type":"Point"}
}