{
  "type": "Feature",
  "properties": {
    "gn:admin1_code":"28",
    "gn:admin2_code":"61",
    "gn:admin3_code":"613",
    "gn:admin4_code":"61230",
    "gn:asciiname":"Le Val du Tellier",
    "gn:country_code":"FR",
    "gn:dem":215,
    "gn:feature_class":"P",
    "gn:feature_code":"PPL",
    "gn:name":"Le Val du Tellier",
    "gn:population":0,
    "gn:timezone":"Europe/Paris",
    "iso:country":"FR",
    "wof:name":"Le Val du Tellier",
    "wof:placetype":"locality"
},
  "geometry": {"coordinates":[0.78392,48.53939],"type":"Point"}
}