{
  "type": "Feature",
  "properties": {
    "gn:admin1_code":"84",
    "gn:admin2_code":"63",
    "gn:admin3_code":"633",
    "gn:admin4_code":"63340",
    "gn:asciiname":"Dijoly",
    "gn:country_code":"FR",
    "gn:dem":712,
    "gn:feature_class":"P",
    "gn:feature_code":"PPL",
    "gn:name":"Dijoly",
    "gn:population":0,
    "gn:timezone":"Europe/Paris",
    "iso:country":"FR",
    "wof:name":"Dijoly",
    "wof:placetype":"locality"
},
  "geometry": {"coordinates":[3.40258,45.50043],"type":"Point"}
}