{
  "type": "Feature",
  "properties": {
    "gn:admin1_code":"24",
    "gn:admin2_code":"41",
    "gn:admin3_code":"413",
    "gn:admin4_code":"41232.0",
    "gn:asciiname":"Le Ruisseau",
    "gn:country_code":"FR",
    "gn:dem":117,
    "gn:feature_class":"P",
    "gn:feature_code":"PPL",
    "gn:name":"Le Ruisseau",
    "gn:population":0,
    "gn:timezone":"Europe/Paris",
    "iso:country":"FR",
    "wof:name":"Le Ruisseau",
    "wof:placetype":"locality"
},
  "geometry": {"coordinates":[2.07962,47.44143],"type":"Point"}
}