{
  "type": "Feature",
  "properties": {
    "gn:admin1_code":"52",
    "gn:admin2_code":"44",
    "gn:admin3_code":"441",
    "gn:admin4_code":"44149",
    "gn:asciiname":"Pichon",
    "gn:country_code":"FR",
    "gn:dem":36,
    "gn:feature_class":"P",
    "gn:feature_code":"PPL",
    "gn:name":"Pichon",
    "gn:population":0,
    "gn:timezone":"Europe/Paris",
    "iso:country":"FR",
    "wof:name":"Pichon",
    "wof:placetype":"locality"
},
  "geometry": {"coordinates":[-1.55773,47.51072],"type":"Point"}
}