{
  "type": "Feature",
  "properties": {
    "gn:admin1_code":"93",
    "gn:admin2_code":"05",
    "gn:admin3_code":"052",
    "gn:admin4_code":"05017",
    "gn:asciiname":"Les Espagnes",
    "gn:country_code":"FR",
    "gn:dem":1022,
    "gn:feature_class":"P",
    "gn:feature_code":"PPL",
    "gn:name":"Les Espagnes",
    "gn:population":0,
    "gn:timezone":"Europe/Paris",
    "iso:country":"FR",
    "wof:name":"Les Espagnes",
    "wof:placetype":"locality"
},
  "geometry": {"coordinates":[6.25,44.56667],"type":"Point"}
}