{
  "type": "Feature",
  "properties": {
    "gn:admin1_code":"32",
    "gn:admin2_code":"60",
    "gn:admin3_code":"601",
    "gn:admin4_code":"60089",
    "gn:asciiname":"Le Fayel",
    "gn:country_code":"FR",
    "gn:dem":122,
    "gn:feature_class":"P",
    "gn:feature_code":"PPL",
    "gn:name":"Le Fayel",
    "gn:population":0,
    "gn:timezone":"Europe/Paris",
    "iso:country":"FR",
    "wof:name":"Le Fayel",
    "wof:placetype":"locality"
},
  "geometry": {"coordinates":[1.86283,49.20576],"type":"Point"}
}