{
  "type": "Feature",
  "properties": {
    "gn:admin1_code":"32",
    "gn:admin2_code":"60",
    "gn:admin3_code":"601",
    "gn:admin4_code":"60089",
    "gn:asciiname":"Le Fayel",
    "gn:country_code":"FR",
    "gn:dem":122,
    "gn:feature_class":"P",
    "gn:feature_code":"PPL",
    "gn:name":"Le Fayel",
    "gn:population":0,
    "gn:timezone":"Europe/Paris",
    "iso:country":"FR",
    "name:cat_x_preferred":[
        "Le Fayel"
    ],
    "name:ceb_x_preferred":[
        "Le Fayel"
    ],
    "name:deu_x_preferred":[
        "Le Fayel"
    ],
    "name:eus_x_preferred":[
        "Le Fayel"
    ],
    "name:fra_x_preferred":[
        "Le Fayel"
    ],
    "name:hun_x_preferred":[
        "Le Fayel"
    ],
    "name:ind_x_preferred":[
        "Le Fayel"
    ],
    "name:ita_x_preferred":[
        "Le Fayel"
    ],
    "name:lat_x_preferred":[
        "Le Fayel"
    ],
    "name:mlg_x_preferred":[
        "Le Fayel"
    ],
    "name:msa_x_preferred":[
        "Le Fayel"
    ],
    "name:nld_x_preferred":[
        "Le Fayel"
    ],
    "name:oci_x_preferred":[
        "Le Fayel"
    ],
    "name:pms_x_preferred":[
        "Le Fayel"
    ],
    "name:pol_x_preferred":[
        "Le Fayel"
    ],
    "name:por_x_preferred":[
        "Le Fayel"
    ],
    "name:ron_x_preferred":[
        "Le Fayel"
    ],
    "name:slk_x_preferred":[
        "Le Fayel"
    ],
    "name:spa_x_preferred":[
        "Le Fayel"
    ],
    "name:swe_x_preferred":[
        "Le Fayel"
    ],
    "name:ukr_x_preferred":[
        "\u041b\u0435-\u0424\u0430\u0454\u043b\u044c"
    ],
    "name:uzb_x_preferred":[
        "Le Fayel"
    ],
    "name:vie_x_preferred":[
        "Le Fayel"
    ],
    "name:vol_x_preferred":[
        "Le Fayel"
    ],
    "name:war_x_preferred":[
        "Le Fayel"
    ],
    "name:zho_x_preferred":[
        "\u52d2\u8d39\u57c3"
    ],
    "wof:name":"Le Fayel",
    "wof:placetype":"locality"
},
  "geometry": {"coordinates":[1.86283,49.20576],"type":"Point"}
}