{
  "type": "Feature",
  "properties": {
    "gn:admin1_code":"84",
    "gn:admin2_code":"07",
    "gn:admin3_code":"071",
    "gn:admin4_code":"07203",
    "gn:asciiname":"Sagnes-et-Goudoulet",
    "gn:country_code":"FR",
    "gn:dem":1213,
    "gn:feature_class":"P",
    "gn:feature_code":"PPL",
    "gn:name":"Sagnes-et-Goudoulet",
    "gn:population":0,
    "gn:timezone":"Europe/Paris",
    "iso:country":"FR",
    "name:bug_x_preferred":[
        "Sagnes-et-Goudoulet"
    ],
    "name:ceb_x_preferred":[
        "Sagnes-et-Goudoulet"
    ],
    "name:deu_x_preferred":[
        "Sagnes-et-Goudoulet"
    ],
    "name:eus_x_preferred":[
        "Sagnes-et-Goudoulet"
    ],
    "name:fin_x_preferred":[
        "Sagnes-et-Goudoulet"
    ],
    "name:fra_x_preferred":[
        "Sagnes-et-Goudoulet"
    ],
    "name:hun_x_preferred":[
        "Sagnes-et-Goudoulet"
    ],
    "name:ita_x_preferred":[
        "Sagnes-et-Goudoulet"
    ],
    "name:lat_x_preferred":[
        "Sagnes-et-Goudoulet"
    ],
    "name:lmo_x_preferred":[
        "Sagnes-et-Goudoulet"
    ],
    "name:msa_x_preferred":[
        "Sagnes-et-Goudoulet"
    ],
    "name:nld_x_preferred":[
        "Sagnes-et-Goudoulet"
    ],
    "name:pms_x_preferred":[
        "Sagnes-et-Goudoulet"
    ],
    "name:pol_x_preferred":[
        "Sagnes-et-Goudoulet"
    ],
    "name:por_x_preferred":[
        "Sagnes-et-Goudoulet"
    ],
    "name:ron_x_preferred":[
        "Sagnes-et-Goudoulet"
    ],
    "name:rus_x_preferred":[
        "\u0421\u0430\u043d\u044c-\u044d-\u0413\u0443\u0434\u0443\u043b\u0435"
    ],
    "name:slk_x_preferred":[
        "Sagnes-et-Goudoulet"
    ],
    "name:spa_x_preferred":[
        "Sagnes-et-Goudoulet"
    ],
    "name:sqi_x_preferred":[
        "Sagnes-et-Goudoulet"
    ],
    "name:swe_x_preferred":[
        "Sagnes-et-Goudoulet"
    ],
    "name:ukr_x_preferred":[
        "\u0421\u0430\u043d\u044c-\u0435-\u0413\u0443\u0434\u0443\u043b\u0435"
    ],
    "name:urd_x_preferred":[
        "\u0633\u06af\u0646\u0633-\u06cc\u062a-\u06af\u0648\u062f\u0648\u0644\u062a"
    ],
    "name:uzb_x_preferred":[
        "Sagnes-et-Goudoulet"
    ],
    "name:vie_x_preferred":[
        "Sagnes-et-Goudoulet"
    ],
    "name:vol_x_preferred":[
        "Sagnes-et-Goudoulet"
    ],
    "name:war_x_preferred":[
        "Sagnes-et-Goudoulet"
    ],
    "name:zho_x_preferred":[
        "\u8428\u76d6\u548c\u53e4\u675c\u83b1"
    ],
    "wof:name":"Sagnes-et-Goudoulet",
    "wof:placetype":"locality"
},
  "geometry": {"coordinates":[4.21667,44.78333],"type":"Point"}
}