{
  "type": "Feature",
  "properties": {
    "gn:admin1_code":"28",
    "gn:admin2_code":"76",
    "gn:admin3_code":"762",
    "gn:admin4_code":"76490",
    "gn:asciiname":"Mont-Edard",
    "gn:country_code":"FR",
    "gn:dem":91,
    "gn:feature_class":"P",
    "gn:feature_code":"PPL",
    "gn:name":"Mont-\u00c9dard",
    "gn:population":0,
    "gn:timezone":"Europe/Paris",
    "iso:country":"FR",
    "wof:name":"Mont-Edard",
    "wof:placetype":"locality"
},
  "geometry": {"coordinates":[0.61571,49.74168],"type":"Point"}
}