{
  "type": "Feature",
  "properties": {
    "gn:admin1_code":"75",
    "gn:admin2_code":"19",
    "gn:admin3_code":"193",
    "gn:admin4_code":"19027",
    "gn:asciiname":"Florentin",
    "gn:country_code":"FR",
    "gn:dem":834,
    "gn:feature_class":"P",
    "gn:feature_code":"PPL",
    "gn:name":"Florentin",
    "gn:population":0,
    "gn:timezone":"Europe/Paris",
    "iso:country":"FR",
    "wof:name":"Florentin",
    "wof:placetype":"locality"
},
  "geometry": {"coordinates":[1.99775,45.50016],"type":"Point"}
}