{
  "type": "Feature",
  "properties": {
    "gn:admin1_code":"44",
    "gn:admin2_code":"51",
    "gn:admin3_code":"511",
    "gn:admin4_code":"51244",
    "gn:asciiname":"Vesigneul-sur-Coole",
    "gn:country_code":"FR",
    "gn:dem":133,
    "gn:feature_class":"P",
    "gn:feature_code":"PPL",
    "gn:name":"V\u00e9signeul-sur-Coole",
    "gn:population":0,
    "gn:timezone":"Europe/Paris",
    "iso:country":"FR",
    "name:und_x_variant":[
        "V\u00e9signeul",
        "V\u00e9signeul-sur-Coole"
    ],
    "wof:name":"Vesigneul-sur-Coole",
    "wof:placetype":"locality"
},
  "geometry": {"coordinates":[4.39397,48.7856],"type":"Point"}
}