{
  "type": "Feature",
  "properties": {
    "gn:admin1_code":"44",
    "gn:admin2_code":"57",
    "gn:admin3_code":"577",
    "gn:admin4_code":"57388",
    "gn:asciiname":"Scheuerwald",
    "gn:country_code":"FR",
    "gn:dem":395,
    "gn:feature_class":"P",
    "gn:feature_code":"PPL",
    "gn:name":"Scheuerwald",
    "gn:population":0,
    "gn:timezone":"Europe/Paris",
    "iso:country":"FR",
    "wof:name":"Scheuerwald",
    "wof:placetype":"locality"
},
  "geometry": {"coordinates":[6.4924,49.44843],"type":"Point"}
}