{
  "type": "Feature",
  "properties": {
    "gn:admin1_code":"93",
    "gn:admin2_code":"06",
    "gn:admin3_code":"062",
    "gn:admin4_code":"06162",
    "gn:asciiname":"Morignolo",
    "gn:country_code":"FR",
    "gn:dem":2322,
    "gn:feature_class":"P",
    "gn:feature_code":"PPL",
    "gn:name":"Morignolo",
    "gn:population":0,
    "gn:timezone":"Europe/Paris",
    "iso:country":"FR",
    "name:und_x_variant":[
        "Morignol",
        "Morignole",
        "Morignolo"
    ],
    "wof:name":"Morignolo",
    "wof:placetype":"locality"
},
  "geometry": {"coordinates":[7.6782,44.11563],"type":"Point"}
}