{
  "type": "Feature",
  "properties": {
    "gn:admin1_code":"27",
    "gn:admin2_code":"58",
    "gn:admin3_code":"583",
    "gn:admin4_code":"58212",
    "gn:asciiname":"Chaillant",
    "gn:country_code":"FR",
    "gn:dem":222,
    "gn:feature_class":"P",
    "gn:feature_code":"PPL",
    "gn:name":"Chaillant",
    "gn:population":0,
    "gn:timezone":"Europe/Paris",
    "iso:country":"FR",
    "wof:name":"Chaillant",
    "wof:placetype":"locality"
},
  "geometry": {"coordinates":[3.26334,47.12009000000001],"type":"Point"}
}