{
  "type": "Feature",
  "properties": {
    "gn:admin1_code":"94",
    "gn:admin2_code":"2B",
    "gn:admin3_code":"2B3",
    "gn:admin4_code":"2B137",
    "gn:asciiname":"Lano",
    "gn:country_code":"FR",
    "gn:dem":603,
    "gn:feature_class":"P",
    "gn:feature_code":"PPL",
    "gn:name":"Lano",
    "gn:population":0,
    "gn:timezone":"Europe/Paris",
    "iso:country":"FR",
    "name:ceb_x_preferred":[
        "Lano"
    ],
    "name:ces_x_preferred":[
        "Lano"
    ],
    "name:deu_x_preferred":[
        "Lano"
    ],
    "name:fra_x_preferred":[
        "Lano"
    ],
    "name:nld_x_preferred":[
        "Lano"
    ],
    "name:slk_x_preferred":[
        "Lano"
    ],
    "name:spa_x_preferred":[
        "Lano"
    ],
    "name:srp_x_preferred":[
        "\u041b\u0430\u043d\u043e"
    ],
    "wof:name":"Lano",
    "wof:placetype":"locality"
},
  "geometry": {"coordinates":[9.248,42.38217],"type":"Point"}
}