{
  "type": "Feature",
  "properties": {
    "frgov:code_epci":"200073138",
    "frgov:insee_arr":"3",
    "frgov:insee_com":"2B137",
    "frgov:insee_dep":"2B",
    "frgov:insee_reg":"94",
    "frgov:nom_com":"Lano",
    "frgov:nom_com_m":"LANO",
    "frgov:nom_dep":"HAUTE-CORSE",
    "frgov:nom_reg":"CORSE",
    "frgov:statut":"Commune simple",
    "gn:admin1_code":"94",
    "gn:admin2_code":"2B",
    "gn:admin3_code":"2B3",
    "gn:admin4_code":"2B137",
    "gn:asciiname":"Lano",
    "gn:country_code":"FR",
    "gn:dem":603,
    "gn:feature_class":"P",
    "gn:feature_code":"PPL",
    "gn:name":"Lano",
    "gn:population":0,
    "gn:timezone":"Europe/Paris",
    "iso:country":"FR",
    "name:ceb_x_preferred":[
        "Lano"
    ],
    "name:ces_x_preferred":[
        "Lano"
    ],
    "name:cos_x_preferred":[
        "Lanu"
    ],
    "name:deu_x_preferred":[
        "Lano"
    ],
    "name:fra_x_preferred":[
        "Lano"
    ],
    "name:kaz_x_preferred":[
        "\u041b\u0430\u043d\u043e"
    ],
    "name:nld_x_preferred":[
        "Lano"
    ],
    "name:rus_x_preferred":[
        "\u041b\u0430\u043d\u043e"
    ],
    "name:slk_x_preferred":[
        "Lano"
    ],
    "name:spa_x_preferred":[
        "Lano"
    ],
    "name:srp_x_preferred":[
        "\u041b\u0430\u043d\u043e"
    ],
    "name:ukr_x_preferred":[
        "\u041b\u0430\u043d\u043e"
    ],
    "qs:a0":"France",
    "qs:a1":"HAUTE-CORSE",
    "qs:a1_lc":"2B",
    "qs:a1r":"CORSE",
    "qs:a1r_lc":"94",
    "qs:a2_lc":"54",
    "qs:a2r_lc":"3",
    "qs:adm0":"France",
    "qs:adm0_a3":"FRA",
    "qs:la":"LANO",
    "qs:la_lc":"2B137",
    "qs:level":"localadmin",
    "qs:type":"Commune simple",
    "wof:coterminous":[
        404382813
    ],
    "wof:name":"Lano",
    "wof:placetype":"locality",
    "wof:placetype_local":"Commune simple"
},
  "geometry": {"coordinates":[9.248,42.38217],"type":"Point"}
}