{
  "type": "Feature",
  "properties": {
    "gn:admin1_code":"84",
    "gn:admin2_code":"43",
    "gn:admin3_code":"433",
    "gn:admin4_code":"43020",
    "gn:asciiname":"Lavoux",
    "gn:country_code":"FR",
    "gn:dem":795,
    "gn:feature_class":"P",
    "gn:feature_code":"PPL",
    "gn:name":"Lavoux",
    "gn:population":0,
    "gn:timezone":"Europe/Paris",
    "iso:country":"FR",
    "wof:name":"Lavoux",
    "wof:placetype":"locality"
},
  "geometry": {"coordinates":[4.09547,45.35282],"type":"Point"}
}