{
  "type": "Feature",
  "properties": {
    "gn:admin1_code":"84",
    "gn:admin2_code":"43",
    "gn:admin3_code":"433",
    "gn:admin4_code":"43020",
    "gn:asciiname":"Lavoux",
    "gn:country_code":"FR",
    "gn:dem":795,
    "gn:feature_class":"P",
    "gn:feature_code":"PPL",
    "gn:name":"Lavoux",
    "gn:population":0,
    "gn:timezone":"Europe/Paris",
    "iso:country":"FR",
    "name:cat_x_preferred":[
        "Lavoux"
    ],
    "name:ceb_x_preferred":[
        "Lavoux"
    ],
    "name:deu_x_preferred":[
        "Lavoux"
    ],
    "name:eus_x_preferred":[
        "Lavoux"
    ],
    "name:fra_x_preferred":[
        "Lavoux"
    ],
    "name:hun_x_preferred":[
        "Lavoux"
    ],
    "name:ita_x_preferred":[
        "Lavoux"
    ],
    "name:lat_x_preferred":[
        "Lavatorium"
    ],
    "name:mlg_x_preferred":[
        "Lavoux"
    ],
    "name:msa_x_preferred":[
        "Lavoux"
    ],
    "name:nld_x_preferred":[
        "Lavoux"
    ],
    "name:oci_x_preferred":[
        "Lavoux"
    ],
    "name:pms_x_preferred":[
        "Lavoux"
    ],
    "name:pol_x_preferred":[
        "Lavoux"
    ],
    "name:por_x_preferred":[
        "Lavoux"
    ],
    "name:ron_x_preferred":[
        "Lavoux"
    ],
    "name:slk_x_preferred":[
        "Lavoux"
    ],
    "name:spa_x_preferred":[
        "Lavoux"
    ],
    "name:swe_x_preferred":[
        "Lavoux"
    ],
    "name:ukr_x_preferred":[
        "\u041b\u0430\u0432\u0443"
    ],
    "name:vie_x_preferred":[
        "Lavoux"
    ],
    "name:vol_x_preferred":[
        "Lavoux"
    ],
    "name:war_x_preferred":[
        "Lavoux"
    ],
    "wof:name":"Lavoux",
    "wof:placetype":"locality"
},
  "geometry": {"coordinates":[4.09547,45.35282],"type":"Point"}
}