{
  "type": "Feature",
  "properties": {
    "gn:admin1_code":"27",
    "gn:admin2_code":"21",
    "gn:admin3_code":"211",
    "gn:admin4_code":"21363",
    "gn:asciiname":"Fontaine",
    "gn:country_code":"FR",
    "gn:dem":413,
    "gn:feature_class":"P",
    "gn:feature_code":"PPL",
    "gn:name":"Fontaine",
    "gn:population":0,
    "gn:timezone":"Europe/Paris",
    "iso:country":"FR",
    "wof:name":"Fontaine",
    "wof:placetype":"locality"
},
  "geometry": {"coordinates":[4.45,47.11667],"type":"Point"}
}