{
  "type": "Feature",
  "properties": {
    "iso:country":"FR",
    "name:eng_x_preferred":[
        "Clos Saint-Vincent"
    ],
    "name:fra_x_preferred":[
        "Clos Saint-Vincent"
    ],
    "wof:name":"Clos Saint-Vincent",
    "wof:placetype":"neighbourhood"
},
  "geometry": {"coordinates":[2.55438407125508,48.84518880399491],"type":"Point"}
}