{
  "type": "Feature",
  "properties": {
    "gn:admin1_code":"84",
    "gn:admin2_code":"63",
    "gn:admin3_code":"632",
    "gn:admin4_code":"63449",
    "gn:asciiname":"Saignes",
    "gn:country_code":"FR",
    "gn:dem":1064,
    "gn:feature_class":"P",
    "gn:feature_code":"PPL",
    "gn:name":"Saignes",
    "gn:population":0,
    "gn:timezone":"Europe/Paris",
    "iso:country":"FR",
    "name:ceb_x_preferred":[
        "Saignes"
    ],
    "name:deu_x_preferred":[
        "Saignes"
    ],
    "name:fra_x_preferred":[
        "Saignes"
    ],
    "name:ita_x_preferred":[
        "Saignes"
    ],
    "name:nds_x_preferred":[
        "Saignes"
    ],
    "name:nld_x_preferred":[
        "Saignes"
    ],
    "name:pms_x_preferred":[
        "Saignes"
    ],
    "name:pol_x_preferred":[
        "Saignes"
    ],
    "name:por_x_preferred":[
        "Saignes"
    ],
    "name:rus_x_preferred":[
        "\u0421\u0435\u043d\u044c"
    ],
    "name:scn_x_preferred":[
        "Saignes"
    ],
    "name:slk_x_preferred":[
        "Saignes"
    ],
    "name:spa_x_preferred":[
        "Saignes"
    ],
    "name:swe_x_preferred":[
        "Saignes"
    ],
    "name:ukr_x_preferred":[
        "\u0421\u0435\u043d\u044c"
    ],
    "wof:name":"Saignes",
    "wof:placetype":"locality"
},
  "geometry": {"coordinates":[2.93183,45.60886],"type":"Point"}
}