{
  "type": "Feature",
  "properties": {
    "gn:admin1_code":"24",
    "gn:admin2_code":"36",
    "gn:admin3_code":"362",
    "gn:admin4_code":"36107.0",
    "gn:asciiname":"Basses Vallees",
    "gn:country_code":"FR",
    "gn:dem":112,
    "gn:feature_class":"P",
    "gn:feature_code":"PPL",
    "gn:name":"Basses Vall\u00e9es",
    "gn:population":0,
    "gn:timezone":"Europe/Paris",
    "iso:country":"FR",
    "wof:name":"Basses Vallees",
    "wof:placetype":"locality"
},
  "geometry": {"coordinates":[1.42357,47.22001],"type":"Point"}
}