{
  "type": "Feature",
  "properties": {
    "gn:admin1_code":"53",
    "gn:admin2_code":"22",
    "gn:admin3_code":"221",
    "gn:admin4_code":"22201",
    "gn:asciiname":"Ville Hery",
    "gn:country_code":"FR",
    "gn:dem":60,
    "gn:feature_class":"P",
    "gn:feature_code":"PPL",
    "gn:name":"Ville H\u00e9ry",
    "gn:population":0,
    "gn:timezone":"Europe/Paris",
    "iso:country":"FR",
    "wof:name":"Ville Hery",
    "wof:placetype":"locality"
},
  "geometry": {"coordinates":[-2.31667,48.65],"type":"Point"}
}