{
  "type": "Feature",
  "properties": {
    "gn:admin1_code":"84",
    "gn:admin2_code":"63",
    "gn:admin3_code":"631",
    "gn:admin4_code":"63394",
    "gn:asciiname":"La Besse",
    "gn:country_code":"FR",
    "gn:dem":1119,
    "gn:feature_class":"P",
    "gn:feature_code":"PPL",
    "gn:name":"La Besse",
    "gn:population":0,
    "gn:timezone":"Europe/Paris",
    "iso:country":"FR",
    "name:und_x_variant":[
        "Besse",
        "La Besse"
    ],
    "wof:name":"La Besse",
    "wof:placetype":"locality"
},
  "geometry": {"coordinates":[3.88193,45.50239000000001],"type":"Point"}
}