{
  "type": "Feature",
  "properties": {
    "gn:admin1_code":"27",
    "gn:admin2_code":"71",
    "gn:admin3_code":"712",
    "gn:admin4_code":"71436",
    "gn:asciiname":"Bois Bretoux",
    "gn:country_code":"FR",
    "gn:dem":308,
    "gn:feature_class":"P",
    "gn:feature_code":"PPL",
    "gn:name":"Bois Bretoux",
    "gn:population":0,
    "gn:timezone":"Europe/Paris",
    "iso:country":"FR",
    "name:und_x_variant":[
        "Le Bois Bretoux",
        "Bois Bretoux"
    ],
    "wof:name":"Bois Bretoux",
    "wof:placetype":"locality"
},
  "geometry": {"coordinates":[4.48024,46.7344],"type":"Point"}
}