{
  "type": "Feature",
  "properties": {
    "gn:admin1_code":"32",
    "gn:admin2_code":"62",
    "gn:admin3_code":"625",
    "gn:admin4_code":"62760.0",
    "gn:asciiname":"Willametz",
    "gn:country_code":"FR",
    "gn:dem":85,
    "gn:feature_class":"P",
    "gn:feature_code":"PPL",
    "gn:name":"Willametz",
    "gn:population":0,
    "gn:timezone":"Europe/Paris",
    "iso:country":"FR",
    "wof:name":"Willametz",
    "wof:placetype":"locality"
},
  "geometry": {"coordinates":[2.08964,50.61367],"type":"Point"}
}