{
  "type": "Feature",
  "properties": {
    "gn:admin1_code":"27",
    "gn:admin2_code":"89",
    "gn:admin3_code":"892",
    "gn:admin4_code":"89423.0",
    "gn:asciiname":"L'Isle",
    "gn:country_code":"FR",
    "gn:dem":132,
    "gn:feature_class":"P",
    "gn:feature_code":"PPL",
    "gn:name":"L'Isle",
    "gn:population":0,
    "gn:timezone":"Europe/Paris",
    "iso:country":"FR",
    "wof:name":"L'Isle",
    "wof:placetype":"locality"
},
  "geometry": {"coordinates":[3.92504,47.92687],"type":"Point"}
}