{
  "type": "Feature",
  "properties": {
    "gn:admin1_code":"27",
    "gn:admin2_code":"89",
    "gn:admin3_code":"892",
    "gn:admin4_code":"89423.0",
    "gn:asciiname":"L'Isle",
    "gn:country_code":"FR",
    "gn:dem":132,
    "gn:feature_class":"P",
    "gn:feature_code":"PPL",
    "gn:name":"L'Isle",
    "gn:population":0,
    "gn:timezone":"Europe/Paris",
    "iso:country":"FR",
    "name:als_x_preferred":[
        "L\u2019Isle"
    ],
    "name:ceb_x_preferred":[
        "L'Isle"
    ],
    "name:deu_x_preferred":[
        "L\u2019Isle"
    ],
    "name:epo_x_preferred":[
        "L'Isle"
    ],
    "name:eus_x_preferred":[
        "L'Isle"
    ],
    "name:fra_x_preferred":[
        "L'Isle"
    ],
    "name:ita_x_preferred":[
        "L'Isle"
    ],
    "name:lmo_x_preferred":[
        "L'Isle"
    ],
    "name:msa_x_preferred":[
        "L'Isle"
    ],
    "name:nld_x_preferred":[
        "L'Isle"
    ],
    "name:nno_x_preferred":[
        "L'Isle"
    ],
    "name:roh_x_preferred":[
        "L'Isle"
    ],
    "name:spa_x_preferred":[
        "L'Isle"
    ],
    "name:swe_x_preferred":[
        "L'Isle"
    ],
    "name:vec_x_preferred":[
        "L'Isle"
    ],
    "name:vol_x_preferred":[
        "L'Isle"
    ],
    "name:war_x_preferred":[
        "L\u2019Isle"
    ],
    "wof:name":"L'Isle",
    "wof:placetype":"locality"
},
  "geometry": {"coordinates":[3.92504,47.92687],"type":"Point"}
}