{
  "type": "Feature",
  "properties": {
    "gn:admin1_code":"76",
    "gn:admin2_code":"11",
    "gn:admin3_code":"112",
    "gn:admin4_code":"11015",
    "gn:asciiname":"Arques",
    "gn:country_code":"FR",
    "gn:dem":360,
    "gn:feature_class":"P",
    "gn:feature_code":"PPL",
    "gn:name":"Arques",
    "gn:population":213,
    "gn:timezone":"Europe/Paris",
    "iso:country":"FR",
    "name:cat_x_preferred":[
        "Arcas"
    ],
    "name:eus_x_preferred":[
        "Arcas"
    ],
    "name:kaz_x_preferred":[
        "\u0410\u0440\u043a"
    ],
    "name:oci_x_preferred":[
        "Arcas"
    ],
    "name:rus_x_preferred":[
        "\u0410\u0440\u043a"
    ],
    "name:srp_x_preferred":[
        "\u0410\u0440\u043a"
    ],
    "name:ukr_x_preferred":[
        "\u0410\u0440\u043a"
    ],
    "name:zho_x_preferred":[
        "\u963f\u5c14\u5c48\u57c3"
    ],
    "wof:name":"Arques",
    "wof:placetype":"locality",
    "wof:population":213
},
  "geometry": {"coordinates":[2.37502,42.95236],"type":"Point"}
}