{
  "type": "Feature",
  "properties": {
    "frgov:code_epci":"200071926",
    "frgov:insee_arr":"2",
    "frgov:insee_com":"11015",
    "frgov:insee_dep":"11",
    "frgov:insee_reg":"76",
    "frgov:nom_com":"Arques",
    "frgov:nom_com_m":"ARQUES",
    "frgov:nom_dep":"AUDE",
    "frgov:nom_reg":"OCCITANIE",
    "frgov:statut":"Commune simple",
    "gn:admin1_code":"76",
    "gn:admin2_code":"11",
    "gn:admin3_code":"112",
    "gn:admin4_code":"11015",
    "gn:asciiname":"Arques",
    "gn:country_code":"FR",
    "gn:dem":360,
    "gn:feature_class":"P",
    "gn:feature_code":"PPL",
    "gn:name":"Arques",
    "gn:population":213,
    "gn:timezone":"Europe/Paris",
    "iso:country":"FR",
    "name:bre_x_preferred":[
        "Arques"
    ],
    "name:cat_x_preferred":[
        "Arcas"
    ],
    "name:ceb_x_preferred":[
        "Arques"
    ],
    "name:deu_x_preferred":[
        "Arques"
    ],
    "name:est_x_preferred":[
        "Arques"
    ],
    "name:eus_x_preferred":[
        "Arcas"
    ],
    "name:fra_x_preferred":[
        "Arques"
    ],
    "name:hun_x_preferred":[
        "Arques"
    ],
    "name:hye_x_preferred":[
        "\u0531\u0580\u0584"
    ],
    "name:ita_x_preferred":[
        "Arques"
    ],
    "name:kaz_x_preferred":[
        "\u0410\u0440\u043a"
    ],
    "name:lat_x_preferred":[
        "Arques"
    ],
    "name:ltz_x_preferred":[
        "Arques"
    ],
    "name:msa_x_preferred":[
        "Arques"
    ],
    "name:nds_x_preferred":[
        "Arques"
    ],
    "name:nld_x_preferred":[
        "Arques"
    ],
    "name:oci_x_preferred":[
        "Arcas"
    ],
    "name:pms_x_preferred":[
        "Arques"
    ],
    "name:pol_x_preferred":[
        "Arques"
    ],
    "name:por_x_preferred":[
        "Arques"
    ],
    "name:ron_x_preferred":[
        "Arques"
    ],
    "name:rus_x_preferred":[
        "\u0410\u0440\u043a"
    ],
    "name:slk_x_preferred":[
        "Arques"
    ],
    "name:spa_x_preferred":[
        "Arques"
    ],
    "name:sqi_x_preferred":[
        "Arques"
    ],
    "name:srp_x_preferred":[
        "\u0410\u0440\u043a"
    ],
    "name:swe_x_preferred":[
        "Arques"
    ],
    "name:ukr_x_preferred":[
        "\u0410\u0440\u043a"
    ],
    "name:vie_x_preferred":[
        "Arques"
    ],
    "name:vol_x_preferred":[
        "Arques"
    ],
    "name:war_x_preferred":[
        "Arques"
    ],
    "name:zho_x_preferred":[
        "\u963f\u5c14\u5c48\u57c3"
    ],
    "name:zho_x_variant":[
        "\u963f\u5c14\u514b"
    ],
    "qs:a0":"France",
    "qs:a1":"AUDE",
    "qs:a1_lc":"11",
    "qs:a1r":"LANGUEDOC-ROUSSILLON",
    "qs:a1r_lc":"91",
    "qs:a2_lc":"13",
    "qs:a2r_lc":"2",
    "qs:adm0":"France",
    "qs:adm0_a3":"FRA",
    "qs:la":"ARQUES",
    "qs:la_lc":"11015",
    "qs:level":"localadmin",
    "qs:type":"Commune simple",
    "wof:coterminous":[
        404411727
    ],
    "wof:name":"Arques",
    "wof:placetype":"locality",
    "wof:placetype_local":"Commune simple",
    "wof:population":213
},
  "geometry": {"coordinates":[2.37502,42.95236],"type":"Point"}
}