{
  "type": "Feature",
  "properties": {
    "gn:admin1_code":"75",
    "gn:admin2_code":"86",
    "gn:admin3_code":"861",
    "gn:admin4_code":"86092",
    "gn:asciiname":"Les Bacheliers",
    "gn:country_code":"FR",
    "gn:dem":98,
    "gn:feature_class":"P",
    "gn:feature_code":"PPL",
    "gn:name":"Les Bacheliers",
    "gn:population":0,
    "gn:timezone":"Europe/Paris",
    "iso:country":"FR",
    "wof:name":"Les Bacheliers",
    "wof:placetype":"locality"
},
  "geometry": {"coordinates":[0.61585,46.90573],"type":"Point"}
}