{
  "type": "Feature",
  "properties": {
    "gn:admin1_code":"44",
    "gn:admin2_code":"52",
    "gn:admin3_code":"523",
    "gn:admin4_code":"52411",
    "gn:asciiname":"Les Sellieres",
    "gn:country_code":"FR",
    "gn:dem":135,
    "gn:feature_class":"P",
    "gn:feature_code":"PPL",
    "gn:name":"Les Selli\u00e8res",
    "gn:population":0,
    "gn:timezone":"Europe/Paris",
    "iso:country":"FR",
    "wof:name":"Les Sellieres",
    "wof:placetype":"locality"
},
  "geometry": {"coordinates":[4.69848,48.46536],"type":"Point"}
}