{
  "type": "Feature",
  "properties": {
    "gn:admin1_code":"27",
    "gn:admin2_code":"89",
    "gn:admin3_code":"892",
    "gn:admin4_code":"89197",
    "gn:asciiname":"Perigny",
    "gn:country_code":"FR",
    "gn:dem":207,
    "gn:feature_class":"P",
    "gn:feature_code":"PPL",
    "gn:name":"P\u00e9rigny",
    "gn:population":0,
    "gn:timezone":"Europe/Paris",
    "iso:country":"FR",
    "wof:name":"Perigny",
    "wof:placetype":"locality"
},
  "geometry": {"coordinates":[4.07441,47.54334],"type":"Point"}
}