{
  "type": "Feature",
  "properties": {
    "gn:admin1_code":"27",
    "gn:admin2_code":"58",
    "gn:admin3_code":"583",
    "gn:admin4_code":"58204",
    "gn:asciiname":"Nion",
    "gn:country_code":"FR",
    "gn:dem":281,
    "gn:feature_class":"P",
    "gn:feature_code":"PPL",
    "gn:name":"Nion",
    "gn:population":0,
    "gn:timezone":"Europe/Paris",
    "iso:country":"FR",
    "wof:name":"Nion",
    "wof:placetype":"locality"
},
  "geometry": {"coordinates":[3.30438,47.08219],"type":"Point"}
}