{
  "type": "Feature",
  "properties": {
    "gn:admin1_code":"84",
    "gn:admin2_code":"63",
    "gn:admin3_code":"633",
    "gn:admin4_code":"63299",
    "gn:asciiname":"Le Fromental",
    "gn:country_code":"FR",
    "gn:dem":826,
    "gn:feature_class":"P",
    "gn:feature_code":"PPL",
    "gn:name":"Le Fromental",
    "gn:population":0,
    "gn:timezone":"Europe/Paris",
    "iso:country":"FR",
    "wof:name":"Le Fromental",
    "wof:placetype":"locality"
},
  "geometry": {"coordinates":[3.13642,45.42371],"type":"Point"}
}