{
  "type": "Feature",
  "properties": {
    "gn:admin1_code":"84",
    "gn:admin2_code":"63",
    "gn:admin3_code":"631",
    "gn:admin4_code":"63211",
    "gn:asciiname":"Suargue",
    "gn:country_code":"FR",
    "gn:dem":552,
    "gn:feature_class":"P",
    "gn:feature_code":"PPL",
    "gn:name":"Suargue",
    "gn:population":0,
    "gn:timezone":"Europe/Paris",
    "iso:country":"FR",
    "wof:name":"Suargue",
    "wof:placetype":"locality"
},
  "geometry": {"coordinates":[3.73783,45.45926],"type":"Point"}
}