{
  "type": "Feature",
  "properties": {
    "gn:admin1_code":"11",
    "gn:admin2_code":"78",
    "gn:admin3_code":"782",
    "gn:admin4_code":"78307",
    "gn:asciiname":"Les Gros Taillis",
    "gn:country_code":"FR",
    "gn:dem":163,
    "gn:feature_class":"P",
    "gn:feature_code":"PPL",
    "gn:name":"Les Gros Taillis",
    "gn:population":0,
    "gn:timezone":"Europe/Paris",
    "iso:country":"FR",
    "name:und_x_variant":[
        "Le Gros Taillis",
        "Les Gros Taillis"
    ],
    "wof:name":"Les Gros Taillis",
    "wof:placetype":"locality"
},
  "geometry": {"coordinates":[1.6931,48.66667],"type":"Point"}
}