{
  "type": "Feature",
  "properties": {
    "gn:admin1_code":"84",
    "gn:admin2_code":"38",
    "gn:admin3_code":"382",
    "gn:admin4_code":"38464",
    "gn:asciiname":"Chateau de Vallin",
    "gn:country_code":"FR",
    "gn:dem":503,
    "gn:feature_class":"P",
    "gn:feature_code":"PPL",
    "gn:name":"Ch\u00e2teau de Vallin",
    "gn:population":0,
    "gn:timezone":"Europe/Paris",
    "iso:country":"FR",
    "name:und_x_variant":[
        "Vallin",
        "Ch\u00e2teau de Villan",
        "Ch\u00e2teau de Vallin"
    ],
    "wof:name":"Chateau de Vallin",
    "wof:placetype":"locality"
},
  "geometry": {"coordinates":[5.38636,45.53224],"type":"Point"}
}