{
  "type": "Feature",
  "properties": {
    "gn:admin1_code":"27",
    "gn:admin2_code":"58",
    "gn:admin3_code":"582",
    "gn:admin4_code":"58229",
    "gn:asciiname":"Les Meulots",
    "gn:country_code":"FR",
    "gn:dem":283,
    "gn:feature_class":"P",
    "gn:feature_code":"PPL",
    "gn:name":"Les Meulots",
    "gn:population":0,
    "gn:timezone":"Europe/Paris",
    "iso:country":"FR",
    "wof:name":"Les Meulots",
    "wof:placetype":"locality"
},
  "geometry": {"coordinates":[3.86171,47.3834],"type":"Point"}
}