{
  "type": "Feature",
  "properties": {
    "gn:admin1_code":"84",
    "gn:admin2_code":"43",
    "gn:admin3_code":"431",
    "gn:admin4_code":"43016",
    "gn:asciiname":"Lugeac",
    "gn:country_code":"FR",
    "gn:dem":441,
    "gn:feature_class":"P",
    "gn:feature_code":"PPL",
    "gn:name":"Lugeac",
    "gn:population":0,
    "gn:timezone":"Europe/Paris",
    "iso:country":"FR",
    "wof:name":"Lugeac",
    "wof:placetype":"locality"
},
  "geometry": {"coordinates":[3.3521,45.38541],"type":"Point"}
}