{
  "type": "Feature",
  "properties": {
    "gn:admin1_code":"11",
    "gn:admin2_code":"77",
    "gn:admin3_code":"772",
    "gn:admin4_code":"77211",
    "gn:asciiname":"Grandpuits-Bailly-Carrois",
    "gn:country_code":"FR",
    "gn:dem":114,
    "gn:feature_class":"P",
    "gn:feature_code":"PPL",
    "gn:name":"Grandpuits-Bailly-Carrois",
    "gn:population":0,
    "gn:timezone":"Europe/Paris",
    "iso:country":"FR",
    "name:cat_x_preferred":[
        "Grandpuits-Bailly-Carrois"
    ],
    "name:ceb_x_preferred":[
        "Grandpuits-Bailly-Carrois"
    ],
    "name:deu_x_preferred":[
        "Grandpuits-Bailly-Carrois"
    ],
    "name:eus_x_preferred":[
        "Grandpuits-Bailly-Carrois"
    ],
    "name:fra_x_preferred":[
        "Grandpuits-Bailly-Carrois"
    ],
    "name:hun_x_preferred":[
        "Grandpuits-Bailly-Carrois"
    ],
    "name:ind_x_preferred":[
        "Grandpuits-Bailly-Carrois"
    ],
    "name:ita_x_preferred":[
        "Grandpuits-Bailly-Carrois"
    ],
    "name:kaz_x_preferred":[
        "\u0413\u0440\u0430\u043d\u043f\u044e\u0438-\u0411\u0430\u0438-\u041a\u0430\u0440\u0440\u0443\u0430"
    ],
    "name:lat_x_preferred":[
        "Grandpuits-Bailly-Carrois"
    ],
    "name:msa_x_preferred":[
        "Grandpuits-Bailly-Carrois"
    ],
    "name:nld_x_preferred":[
        "Grandpuits-Bailly-Carrois"
    ],
    "name:oci_x_preferred":[
        "Grandpuits-Bailly-Carrois"
    ],
    "name:pms_x_preferred":[
        "Grandpuits-Bailly-Carrois"
    ],
    "name:pol_x_preferred":[
        "Grandpuits-Bailly-Carrois"
    ],
    "name:por_x_preferred":[
        "Grandpuits-Bailly-Carrois"
    ],
    "name:slk_x_preferred":[
        "Grandpuits-Bailly-Carrois"
    ],
    "name:spa_x_preferred":[
        "Grandpuits-Bailly-Carrois"
    ],
    "name:swe_x_preferred":[
        "Grandpuits-Bailly-Carrois"
    ],
    "name:ukr_x_preferred":[
        "\u0413\u0440\u0430\u043d\u043f\u044e\u0457-\u0411\u0430\u0457-\u041a\u0430\u0440\u0440\u0443\u0430"
    ],
    "name:vie_x_preferred":[
        "Grandpuits-Bailly-Carrois"
    ],
    "name:vol_x_preferred":[
        "Grandpuits-Bailly-Carrois"
    ],
    "name:war_x_preferred":[
        "Grandpuits-Bailly-Carrois"
    ],
    "wof:name":"Grandpuits-Bailly-Carrois",
    "wof:placetype":"locality"
},
  "geometry": {"coordinates":[2.96667,48.58333],"type":"Point"}
}