{
  "type": "Feature",
  "properties": {
    "gn:admin1_code":"27",
    "gn:admin2_code":"71",
    "gn:admin3_code":"712",
    "gn:admin4_code":"71443",
    "gn:asciiname":"Bout d'Amont",
    "gn:country_code":"FR",
    "gn:dem":200,
    "gn:feature_class":"P",
    "gn:feature_code":"PPL",
    "gn:name":"Bout d\u2019Amont",
    "gn:population":0,
    "gn:timezone":"Europe/Paris",
    "iso:country":"FR",
    "wof:name":"Bout d'Amont",
    "wof:placetype":"locality"
},
  "geometry": {"coordinates":[4.90392,46.9379],"type":"Point"}
}