{
  "type": "Feature",
  "properties": {
    "gn:admin1_code":"28",
    "gn:admin2_code":"76",
    "gn:admin3_code":"763",
    "gn:admin4_code":"76100",
    "gn:asciiname":"Gruchy",
    "gn:country_code":"FR",
    "gn:dem":160,
    "gn:feature_class":"P",
    "gn:feature_code":"PPL",
    "gn:name":"Gruchy",
    "gn:population":0,
    "gn:timezone":"Europe/Paris",
    "iso:country":"FR",
    "wof:name":"Gruchy",
    "wof:placetype":"locality"
},
  "geometry": {"coordinates":[1.27062,49.50276],"type":"Point"}
}