{
  "type": "Feature",
  "properties": {
    "gn:admin1_code":"75",
    "gn:admin2_code":"17",
    "gn:admin3_code":"172",
    "gn:admin4_code":"17385",
    "gn:asciiname":"La Vieille Perrotine",
    "gn:country_code":"FR",
    "gn:dem":2,
    "gn:feature_class":"P",
    "gn:feature_code":"PPL",
    "gn:name":"La Vieille Perrotine",
    "gn:population":0,
    "gn:timezone":"Europe/Paris",
    "iso:country":"FR",
    "wof:name":"La Vieille Perrotine",
    "wof:placetype":"locality"
},
  "geometry": {"coordinates":[-1.2495,45.95228],"type":"Point"}
}