{
  "type": "Feature",
  "properties": {
    "gn:admin1_code":"75",
    "gn:admin2_code":"33",
    "gn:admin3_code":"335",
    "gn:admin4_code":"33028",
    "gn:asciiname":"Baron",
    "gn:country_code":"FR",
    "gn:dem":50,
    "gn:feature_class":"P",
    "gn:feature_code":"PPL",
    "gn:name":"Baron",
    "gn:population":938,
    "gn:timezone":"Europe/Paris",
    "iso:country":"FR",
    "wof:name":"Baron",
    "wof:placetype":"locality",
    "wof:population":938
},
  "geometry": {"coordinates":[-0.31233,44.82182],"type":"Point"}
}