{
  "type": "Feature",
  "properties": {
    "gn:admin1_code":"52",
    "gn:admin2_code":"85",
    "gn:admin3_code":"851",
    "gn:admin4_code":"85094",
    "gn:asciiname":"Payre-sur-Vendee",
    "gn:country_code":"FR",
    "gn:dem":78,
    "gn:feature_class":"P",
    "gn:feature_code":"PPL",
    "gn:name":"Payr\u00e9-sur-Vend\u00e9e",
    "gn:population":0,
    "gn:timezone":"Europe/Paris",
    "iso:country":"FR",
    "name:und_x_variant":[
        "Payr\u00e9",
        "Payr\u00e9-sur-Vend\u00e9e"
    ],
    "wof:name":"Payre-sur-Vendee",
    "wof:placetype":"locality"
},
  "geometry": {"coordinates":[-0.67608,46.51225],"type":"Point"}
}