{
  "type": "Feature",
  "properties": {
    "gn:admin1_code":"11",
    "gn:admin2_code":"91",
    "gn:admin3_code":"911",
    "gn:admin4_code":"91315",
    "gn:asciiname":"Aubin",
    "gn:country_code":"FR",
    "gn:dem":66,
    "gn:feature_class":"P",
    "gn:feature_code":"PPL",
    "gn:name":"Aubin",
    "gn:population":0,
    "gn:timezone":"Europe/Paris",
    "iso:country":"FR",
    "name:bre_x_preferred":[
        "Aubin"
    ],
    "name:ceb_x_preferred":[
        "Aubin"
    ],
    "name:deu_x_preferred":[
        "Aubin"
    ],
    "name:fra_x_preferred":[
        "Aubin"
    ],
    "name:ita_x_preferred":[
        "Aubin"
    ],
    "name:nds_x_preferred":[
        "Aubin"
    ],
    "name:nld_x_preferred":[
        "Aubin"
    ],
    "name:pms_x_preferred":[
        "Aubin"
    ],
    "name:pol_x_preferred":[
        "Aubin"
    ],
    "name:por_x_preferred":[
        "Aubin"
    ],
    "name:rus_x_preferred":[
        "\u041e\u0431\u0435\u043d"
    ],
    "name:slk_x_preferred":[
        "Aubin"
    ],
    "name:spa_x_preferred":[
        "Aubin"
    ],
    "name:swe_x_preferred":[
        "Aubin"
    ],
    "name:ukr_x_preferred":[
        "\u041e\u0431\u0435\u043d"
    ],
    "name:und_x_variant":[
        "Saint-Aubin"
    ],
    "wof:name":"Aubin",
    "wof:placetype":"locality"
},
  "geometry": {"coordinates":[2.35918,48.50974],"type":"Point"}
}