{
  "type": "Feature",
  "properties": {
    "gn:admin1_code":"93",
    "gn:admin2_code":"83",
    "gn:admin3_code":"832",
    "gn:admin4_code":"83126",
    "gn:asciiname":"Fabregas",
    "gn:country_code":"FR",
    "gn:dem":24,
    "gn:feature_class":"P",
    "gn:feature_code":"PPL",
    "gn:name":"Fabregas",
    "gn:population":0,
    "gn:timezone":"Europe/Paris",
    "iso:country":"FR",
    "wof:name":"Fabregas",
    "wof:placetype":"locality"
},
  "geometry": {"coordinates":[5.87189,43.07174000000001],"type":"Point"}
}