{
  "type": "Feature",
  "properties": {
    "gn:admin1_code":"11",
    "gn:admin2_code":"91",
    "gn:admin3_code":"913",
    "gn:admin4_code":"91471.0",
    "gn:asciiname":"Mondetour",
    "gn:country_code":"FR",
    "gn:dem":157,
    "gn:feature_class":"P",
    "gn:feature_code":"PPL",
    "gn:name":"Mond\u00e9tour",
    "gn:population":0,
    "gn:timezone":"Europe/Paris",
    "iso:country":"FR",
    "wof:name":"Mondetour",
    "wof:placetype":"locality"
},
  "geometry": {"coordinates":[2.18103,48.68049],"type":"Point"}
}