{
  "type": "Feature",
  "properties": {
    "gn:admin1_code":"75",
    "gn:admin2_code":"17",
    "gn:admin3_code":"175",
    "gn:admin4_code":"17397",
    "gn:asciiname":"Coulonge-sur-Charente",
    "gn:country_code":"FR",
    "gn:dem":10,
    "gn:feature_class":"P",
    "gn:feature_code":"PPL",
    "gn:name":"Coulong\u00e9-sur-Charente",
    "gn:population":0,
    "gn:timezone":"Europe/Paris",
    "iso:country":"FR",
    "wof:name":"Coulonge-sur-Charente",
    "wof:placetype":"locality"
},
  "geometry": {"coordinates":[-0.68447,45.85462],"type":"Point"}
}