{
  "type": "Feature",
  "properties": {
    "gn:admin1_code":"24",
    "gn:admin2_code":"45",
    "gn:admin3_code":"451",
    "gn:admin4_code":"45029",
    "gn:asciiname":"L'Etang",
    "gn:country_code":"FR",
    "gn:dem":138,
    "gn:feature_class":"P",
    "gn:feature_code":"PPL",
    "gn:name":"L\u2019\u00c9tang",
    "gn:population":0,
    "gn:timezone":"Europe/Paris",
    "iso:country":"FR",
    "name:und_x_variant":[
        "L\u2019\u00c9tang"
    ],
    "wof:name":"L'Etang",
    "wof:placetype":"locality"
},
  "geometry": {"coordinates":[2.80352,47.56],"type":"Point"}
}