{
  "type": "Feature",
  "properties": {
    "gn:admin1_code":"76",
    "gn:admin2_code":"11",
    "gn:admin3_code":"112",
    "gn:admin4_code":"11046",
    "gn:asciiname":"Tournebouix",
    "gn:country_code":"FR",
    "gn:dem":439,
    "gn:feature_class":"P",
    "gn:feature_code":"PPL",
    "gn:name":"Tournebouix",
    "gn:population":0,
    "gn:timezone":"Europe/Paris",
    "iso:country":"FR",
    "wof:name":"Tournebouix",
    "wof:placetype":"locality"
},
  "geometry": {"coordinates":[2.11615,42.9816],"type":"Point"}
}