{
  "type": "Feature",
  "properties": {
    "gn:admin1_code":"53",
    "gn:admin2_code":"56",
    "gn:admin3_code":"561",
    "gn:admin4_code":"56062",
    "gn:asciiname":"Ban-Gavres",
    "gn:country_code":"FR",
    "gn:dem":3,
    "gn:feature_class":"P",
    "gn:feature_code":"PPL",
    "gn:name":"Ban-G\u00e2vres",
    "gn:population":0,
    "gn:timezone":"Europe/Paris",
    "iso:country":"FR",
    "name:und_x_variant":[
        "Ban G\u00e2vre",
        "Ban-G\u00e2vres"
    ],
    "wof:name":"Ban-Gavres",
    "wof:placetype":"locality"
},
  "geometry": {"coordinates":[-3.35157,47.69863],"type":"Point"}
}