{
  "type": "Feature",
  "properties": {
    "gn:admin1_code":"32",
    "gn:admin2_code":"62",
    "gn:admin3_code":"624",
    "gn:admin4_code":"62183",
    "gn:asciiname":"La Houssoye",
    "gn:country_code":"FR",
    "gn:dem":70,
    "gn:feature_class":"P",
    "gn:feature_code":"PPL",
    "gn:name":"La Houssoye",
    "gn:population":0,
    "gn:timezone":"Europe/Paris",
    "iso:country":"FR",
    "wof:name":"La Houssoye",
    "wof:placetype":"locality"
},
  "geometry": {"coordinates":[1.81418,50.38637],"type":"Point"}
}