{
  "type": "Feature",
  "properties": {
    "gn:admin1_code":"32",
    "gn:admin2_code":"62",
    "gn:admin3_code":"624",
    "gn:admin4_code":"62183",
    "gn:asciiname":"La Houssoye",
    "gn:country_code":"FR",
    "gn:dem":70,
    "gn:feature_class":"P",
    "gn:feature_code":"PPL",
    "gn:name":"La Houssoye",
    "gn:population":0,
    "gn:timezone":"Europe/Paris",
    "iso:country":"FR",
    "name:cat_x_preferred":[
        "La Houssoye"
    ],
    "name:ceb_x_preferred":[
        "La Houssoye"
    ],
    "name:ces_x_preferred":[
        "La Houssoye"
    ],
    "name:deu_x_preferred":[
        "La Houssoye"
    ],
    "name:eus_x_preferred":[
        "La Houssoye"
    ],
    "name:fra_x_preferred":[
        "La Houssoye"
    ],
    "name:hun_x_preferred":[
        "La Houssoye"
    ],
    "name:ind_x_preferred":[
        "La Houssoye"
    ],
    "name:ita_x_preferred":[
        "La Houssoye"
    ],
    "name:lat_x_preferred":[
        "La Houssoye"
    ],
    "name:mlg_x_preferred":[
        "La Houssoye"
    ],
    "name:msa_x_preferred":[
        "La Houssoye"
    ],
    "name:nld_x_preferred":[
        "La Houssoye"
    ],
    "name:oci_x_preferred":[
        "La Houssoye"
    ],
    "name:pms_x_preferred":[
        "La Houssoye"
    ],
    "name:pol_x_preferred":[
        "La Houssoye"
    ],
    "name:por_x_preferred":[
        "La Houssoye"
    ],
    "name:ron_x_preferred":[
        "La Houssoye"
    ],
    "name:slk_x_preferred":[
        "La Houssoye"
    ],
    "name:spa_x_preferred":[
        "La Houssoye"
    ],
    "name:swe_x_preferred":[
        "La Houssoye"
    ],
    "name:ukr_x_preferred":[
        "\u041b\u0430-\u0423\u0441\u0441\u0443\u0430"
    ],
    "name:urd_x_preferred":[
        "\u0644\u0627 \u06c1\u0648\u0633\u0648\u06cc"
    ],
    "name:uzb_x_preferred":[
        "La Houssoye"
    ],
    "name:vie_x_preferred":[
        "La Houssoye"
    ],
    "name:vol_x_preferred":[
        "La Houssoye"
    ],
    "name:war_x_preferred":[
        "La Houssoye"
    ],
    "name:zho_x_preferred":[
        "\u6d1b\u82cf\u74e6\u57c3"
    ],
    "wof:name":"La Houssoye",
    "wof:placetype":"locality"
},
  "geometry": {"coordinates":[1.81418,50.38637],"type":"Point"}
}