{
  "type": "Feature",
  "properties": {
    "gn:admin1_code":"11",
    "gn:admin2_code":"77",
    "gn:admin3_code":"773",
    "gn:admin4_code":"77423",
    "gn:asciiname":"Saint-Martin-des-Champs",
    "gn:country_code":"FR",
    "gn:dem":141,
    "gn:feature_class":"P",
    "gn:feature_code":"PPL",
    "gn:name":"Saint-Martin-des-Champs",
    "gn:population":604,
    "gn:timezone":"Europe/Paris",
    "iso:country":"FR",
    "name:bre_x_preferred":[
        "Saint-Martin-des-Champs"
    ],
    "name:ceb_x_preferred":[
        "Saint-Martin-des-Champs"
    ],
    "name:deu_x_preferred":[
        "Saint-Martin-des-Champs"
    ],
    "name:fra_x_preferred":[
        "Saint-Martin-des-Champs"
    ],
    "name:ita_x_preferred":[
        "Saint-Martin-des-Champs"
    ],
    "name:nds_x_preferred":[
        "Saint-Martin-des-Champs"
    ],
    "name:nld_x_preferred":[
        "Saint-Martin-des-Champs"
    ],
    "name:oci_x_preferred":[
        "Saint-Martin-des-Champs"
    ],
    "name:pms_x_preferred":[
        "Saint-Martin-des-Champs"
    ],
    "name:pol_x_preferred":[
        "Saint-Martin-des-Champs"
    ],
    "name:por_x_preferred":[
        "Saint-Martin-des-Champs"
    ],
    "name:rus_x_preferred":[
        "\u0421\u0435\u043d-\u041c\u0430\u0440\u0442\u0435\u043d-\u0434\u0435-\u0428\u0430\u043d"
    ],
    "name:slk_x_preferred":[
        "Saint-Martin-des-Champs"
    ],
    "name:spa_x_preferred":[
        "Saint-Martin-des-Champs"
    ],
    "name:swe_x_preferred":[
        "Saint-Martin-des-Champs"
    ],
    "name:ukr_x_preferred":[
        "\u0421\u0435\u043d-\u041c\u0430\u0440\u0442\u0435\u043d-\u0434\u0435-\u0428\u0430\u043c"
    ],
    "name:und_x_variant":[
        "Saint-Martin"
    ],
    "wof:name":"Saint-Martin-des-Champs",
    "wof:placetype":"locality",
    "wof:population":604
},
  "geometry": {"coordinates":[3.33461,48.77848],"type":"Point"}
}