{
  "type": "Feature",
  "properties": {
    "gn:admin1_code":"11",
    "gn:admin2_code":"77",
    "gn:admin3_code":"773",
    "gn:admin4_code":"77423",
    "gn:asciiname":"Saint-Martin-des-Champs",
    "gn:country_code":"FR",
    "gn:dem":141,
    "gn:feature_class":"P",
    "gn:feature_code":"PPL",
    "gn:name":"Saint-Martin-des-Champs",
    "gn:population":604,
    "gn:timezone":"Europe/Paris",
    "iso:country":"FR",
    "name:und_x_variant":[
        "Saint-Martin"
    ],
    "wof:name":"Saint-Martin-des-Champs",
    "wof:placetype":"locality",
    "wof:population":604
},
  "geometry": {"coordinates":[3.33461,48.77848],"type":"Point"}
}