{
  "type": "Feature",
  "properties": {
    "gn:admin1_code":"75",
    "gn:admin2_code":"64",
    "gn:admin3_code":"642",
    "gn:admin4_code":"64214",
    "gn:asciiname":"Undurein",
    "gn:country_code":"FR",
    "gn:dem":115,
    "gn:feature_class":"P",
    "gn:feature_code":"PPL",
    "gn:name":"Undurein",
    "gn:population":0,
    "gn:timezone":"Europe/Paris",
    "iso:country":"FR",
    "name:eus_x_preferred":[
        "\u00dcnd\u00fcreine"
    ],
    "name:fra_x_preferred":[
        "Undurein"
    ],
    "wof:name":"Undurein",
    "wof:placetype":"locality"
},
  "geometry": {"coordinates":[-0.87881,43.28301],"type":"Point"}
}