{
  "type": "Feature",
  "properties": {
    "gn:admin1_code":"76",
    "gn:admin2_code":"46",
    "gn:admin3_code":"462",
    "gn:admin4_code":"46237",
    "gn:asciiname":"Puy Blanc",
    "gn:country_code":"FR",
    "gn:dem":328,
    "gn:feature_class":"P",
    "gn:feature_code":"PPL",
    "gn:name":"Puy Blanc",
    "gn:population":0,
    "gn:timezone":"Europe/Paris",
    "iso:country":"FR",
    "wof:name":"Puy Blanc",
    "wof:placetype":"locality"
},
  "geometry": {"coordinates":[1.92596,44.63476],"type":"Point"}
}