{
  "type": "Feature",
  "properties": {
    "gn:admin1_code":"84",
    "gn:admin2_code":"03",
    "gn:admin3_code":"031",
    "gn:admin4_code":"03308",
    "gn:asciiname":"Villard",
    "gn:country_code":"FR",
    "gn:dem":448,
    "gn:feature_class":"P",
    "gn:feature_code":"PPL",
    "gn:name":"Villard",
    "gn:population":0,
    "gn:timezone":"Europe/Paris",
    "iso:country":"FR",
    "name:bre_x_preferred":[
        "Villard"
    ],
    "name:cat_x_preferred":[
        "Villard"
    ],
    "name:ceb_x_preferred":[
        "Villard"
    ],
    "name:deu_x_preferred":[
        "Villard"
    ],
    "name:epo_x_preferred":[
        "Villard"
    ],
    "name:fra_x_preferred":[
        "Villard"
    ],
    "name:ita_x_preferred":[
        "Villard"
    ],
    "name:nds_x_preferred":[
        "Villard"
    ],
    "name:nld_x_preferred":[
        "Villard"
    ],
    "name:pol_x_preferred":[
        "Villard"
    ],
    "name:por_x_preferred":[
        "Villard"
    ],
    "name:rus_x_preferred":[
        "\u0412\u0438\u043b\u043b\u0430\u0440\u0434"
    ],
    "name:slk_x_preferred":[
        "Villard"
    ],
    "name:spa_x_preferred":[
        "Villard"
    ],
    "name:swe_x_preferred":[
        "Villard"
    ],
    "name:ukr_x_preferred":[
        "\u0412\u0456\u043b\u043b\u0430\u0440"
    ],
    "wof:name":"Villard",
    "wof:placetype":"locality"
},
  "geometry": {"coordinates":[2.98661,46.25253],"type":"Point"}
}