{
  "type": "Feature",
  "properties": {
    "gn:admin1_code":"75",
    "gn:admin2_code":"33",
    "gn:admin3_code":"333",
    "gn:admin4_code":"33175",
    "gn:asciiname":"Sallebruneau",
    "gn:country_code":"FR",
    "gn:dem":76,
    "gn:feature_class":"P",
    "gn:feature_code":"PPL",
    "gn:name":"Sallebruneau",
    "gn:population":0,
    "gn:timezone":"Europe/Paris",
    "iso:country":"FR",
    "wof:name":"Sallebruneau",
    "wof:placetype":"locality"
},
  "geometry": {"coordinates":[-0.11785,44.72539],"type":"Point"}
}