{
  "type": "Feature",
  "properties": {
    "gn:admin1_code":"52",
    "gn:admin2_code":"44",
    "gn:admin3_code":"441",
    "gn:admin4_code":"44015",
    "gn:asciiname":"La Fraudais",
    "gn:country_code":"FR",
    "gn:dem":27,
    "gn:feature_class":"P",
    "gn:feature_code":"PPL",
    "gn:name":"La Fraudais",
    "gn:population":0,
    "gn:timezone":"Europe/Paris",
    "iso:country":"FR",
    "wof:name":"La Fraudais",
    "wof:placetype":"locality"
},
  "geometry": {"coordinates":[-1.73678,47.49798],"type":"Point"}
}