{
  "type": "Feature",
  "properties": {
    "gn:admin1_code":"84",
    "gn:admin2_code":"38",
    "gn:admin3_code":"381",
    "gn:admin4_code":"38155",
    "gn:asciiname":"Montcelet",
    "gn:country_code":"FR",
    "gn:dem":396,
    "gn:feature_class":"P",
    "gn:feature_code":"PPL",
    "gn:name":"Montcelet",
    "gn:population":0,
    "gn:timezone":"Europe/Paris",
    "iso:country":"FR",
    "wof:name":"Montcelet",
    "wof:placetype":"locality"
},
  "geometry": {"coordinates":[5.75727,45.42999],"type":"Point"}
}