{
  "type": "Feature",
  "properties": {
    "gn:admin1_code":"84",
    "gn:admin2_code":"42",
    "gn:admin3_code":"421",
    "gn:admin4_code":"42318",
    "gn:asciiname":"La Breure",
    "gn:country_code":"FR",
    "gn:dem":898,
    "gn:feature_class":"P",
    "gn:feature_code":"PPL",
    "gn:name":"La Breure",
    "gn:population":0,
    "gn:timezone":"Europe/Paris",
    "iso:country":"FR",
    "wof:name":"La Breure",
    "wof:placetype":"locality"
},
  "geometry": {"coordinates":[3.9154,45.40024],"type":"Point"}
}