{
  "type": "Feature",
  "properties": {
    "gn:admin1_code":"28",
    "gn:admin2_code":"76",
    "gn:admin3_code":"763",
    "gn:admin4_code":"76311",
    "gn:asciiname":"Les Souches",
    "gn:country_code":"FR",
    "gn:dem":148,
    "gn:feature_class":"P",
    "gn:feature_code":"PPL",
    "gn:name":"Les Souches",
    "gn:population":0,
    "gn:timezone":"Europe/Paris",
    "iso:country":"FR",
    "wof:name":"Les Souches",
    "wof:placetype":"locality"
},
  "geometry": {"coordinates":[0.99808,49.58585],"type":"Point"}
}