{
  "type": "Feature",
  "properties": {
    "gn:admin1_code":"24",
    "gn:admin2_code":"28",
    "gn:admin3_code":"282",
    "gn:admin4_code":"28103",
    "gn:asciiname":"Le Mee",
    "gn:country_code":"FR",
    "gn:dem":124,
    "gn:feature_class":"P",
    "gn:feature_code":"PPL",
    "gn:name":"Le M\u00e9e",
    "gn:population":219,
    "gn:timezone":"Europe/Paris",
    "iso:country":"FR",
    "name:und_x_variant":[
        "Le M\u00e9e"
    ],
    "wof:name":"Le Mee",
    "wof:placetype":"locality",
    "wof:population":219
},
  "geometry": {"coordinates":[1.41631,47.98572],"type":"Point"}
}