{
  "type": "Feature",
  "properties": {
    "gn:admin1_code":"75",
    "gn:admin2_code":"23",
    "gn:admin3_code":"232",
    "gn:admin4_code":"23141",
    "gn:asciiname":"Les Villettes",
    "gn:country_code":"FR",
    "gn:dem":366,
    "gn:feature_class":"P",
    "gn:feature_code":"PPL",
    "gn:name":"Les Villettes",
    "gn:population":0,
    "gn:timezone":"Europe/Paris",
    "iso:country":"FR",
    "wof:name":"Les Villettes",
    "wof:placetype":"locality"
},
  "geometry": {"coordinates":[1.65241,46.24231],"type":"Point"}
}