{
  "type": "Feature",
  "properties": {
    "gn:admin1_code":"75",
    "gn:admin2_code":"23",
    "gn:admin3_code":"232",
    "gn:admin4_code":"23141",
    "gn:asciiname":"Les Villettes",
    "gn:country_code":"FR",
    "gn:dem":366,
    "gn:feature_class":"P",
    "gn:feature_code":"PPL",
    "gn:name":"Les Villettes",
    "gn:population":0,
    "gn:timezone":"Europe/Paris",
    "iso:country":"FR",
    "name:bug_x_preferred":[
        "Les Villettes"
    ],
    "name:cat_x_preferred":[
        "Las Viletas"
    ],
    "name:ceb_x_preferred":[
        "Les Villettes"
    ],
    "name:deu_x_preferred":[
        "Les Villettes"
    ],
    "name:eus_x_preferred":[
        "Les Villettes"
    ],
    "name:fra_x_preferred":[
        "Les Villettes"
    ],
    "name:hun_x_preferred":[
        "Les Villettes"
    ],
    "name:ind_x_preferred":[
        "Les Villettes"
    ],
    "name:ita_x_preferred":[
        "Les Villettes"
    ],
    "name:kaz_x_preferred":[
        "\u041b\u0435-\u0412\u0438\u043b\u044c\u0442\u0442\u0435\u0441"
    ],
    "name:lat_x_preferred":[
        "Les Villettes"
    ],
    "name:ltz_x_preferred":[
        "Les Villettes"
    ],
    "name:msa_x_preferred":[
        "Les Villettes"
    ],
    "name:nld_x_preferred":[
        "Les Villettes"
    ],
    "name:oci_x_preferred":[
        "Las Vialetas"
    ],
    "name:pms_x_preferred":[
        "Les Villettes"
    ],
    "name:pol_x_preferred":[
        "Les Villettes"
    ],
    "name:por_x_preferred":[
        "Les Villettes"
    ],
    "name:ron_x_preferred":[
        "Les Villettes"
    ],
    "name:slk_x_preferred":[
        "Les Villettes"
    ],
    "name:spa_x_preferred":[
        "Les Villettes"
    ],
    "name:swe_x_preferred":[
        "Les Villettes"
    ],
    "name:ukr_x_preferred":[
        "\u041b\u0435-\u0412\u0456\u043b\u044c\u0442\u0442\u0435\u0441"
    ],
    "name:uzb_x_preferred":[
        "Les Villettes"
    ],
    "name:vie_x_preferred":[
        "Les Villettes"
    ],
    "name:vol_x_preferred":[
        "Les Villettes"
    ],
    "name:war_x_preferred":[
        "Les Villettes"
    ],
    "name:zho_x_preferred":[
        "\u83b1\u7ef4\u83b1\u7279"
    ],
    "wof:name":"Les Villettes",
    "wof:placetype":"locality"
},
  "geometry": {"coordinates":[1.65241,46.24231],"type":"Point"}
}