{
  "type": "Feature",
  "properties": {
    "gn:admin1_code":"52",
    "gn:admin2_code":"49",
    "gn:admin3_code":"493",
    "gn:admin4_code":"49228",
    "gn:asciiname":"Lasse",
    "gn:country_code":"FR",
    "gn:dem":80,
    "gn:feature_class":"P",
    "gn:feature_code":"PPL",
    "gn:name":"Lasse",
    "gn:population":261,
    "gn:timezone":"Europe/Paris",
    "iso:country":"FR",
    "name:deu_x_preferred":[
        "Lasse"
    ],
    "name:fin_x_preferred":[
        "Lasse"
    ],
    "name:jpn_x_preferred":[
        "\u30e9\u30c3\u30bb"
    ],
    "name:nno_x_preferred":[
        "Lasse"
    ],
    "name:nor_x_preferred":[
        "Lasse"
    ],
    "name:ukr_x_preferred":[
        "\u041b\u0430\u0441\u0441\u0435"
    ],
    "wof:name":"Lasse",
    "wof:placetype":"locality",
    "wof:population":261
},
  "geometry": {"coordinates":[0.01038,47.53638],"type":"Point"}
}