{
  "type": "Feature",
  "properties": {
    "gn:admin1_code":"44",
    "gn:admin2_code":"10",
    "gn:admin3_code":"102",
    "gn:admin4_code":"10259",
    "gn:asciiname":"Freparoy",
    "gn:country_code":"FR",
    "gn:dem":60,
    "gn:feature_class":"P",
    "gn:feature_code":"PPL",
    "gn:name":"Fr\u00e9paroy",
    "gn:population":0,
    "gn:timezone":"Europe/Paris",
    "iso:country":"FR",
    "wof:name":"Freparoy",
    "wof:placetype":"locality"
},
  "geometry": {"coordinates":[3.45579,48.47546],"type":"Point"}
}