{
  "type": "Feature",
  "properties": {
    "gn:admin1_code":"28",
    "gn:admin2_code":"76",
    "gn:admin3_code":"762",
    "gn:admin4_code":"76361.0",
    "gn:asciiname":"Epaville",
    "gn:country_code":"FR",
    "gn:dem":96,
    "gn:feature_class":"P",
    "gn:feature_code":"PPL",
    "gn:name":"\u00c9paville",
    "gn:population":0,
    "gn:timezone":"Europe/Paris",
    "iso:country":"FR",
    "wof:name":"Epaville",
    "wof:placetype":"locality"
},
  "geometry": {"coordinates":[0.17074,49.61679],"type":"Point"}
}