{
  "type": "Feature",
  "properties": {
    "gn:admin1_code":"27",
    "gn:admin2_code":"89",
    "gn:admin3_code":"891",
    "gn:admin4_code":"89007",
    "gn:asciiname":"Ferrieres",
    "gn:country_code":"FR",
    "gn:dem":229,
    "gn:feature_class":"P",
    "gn:feature_code":"PPL",
    "gn:name":"Ferri\u00e8res",
    "gn:population":0,
    "gn:timezone":"Europe/Paris",
    "iso:country":"FR",
    "name:und_x_variant":[
        "Ferri\u00e8re",
        "Ferri\u00e8res"
    ],
    "wof:name":"Ferrieres",
    "wof:placetype":"locality"
},
  "geometry": {"coordinates":[3.42715,47.51905],"type":"Point"}
}