{
  "type": "Feature",
  "properties": {
    "gn:admin1_code":"84",
    "gn:admin2_code":"63",
    "gn:admin3_code":"633",
    "gn:admin4_code":"63247",
    "gn:asciiname":"Beaune",
    "gn:country_code":"FR",
    "gn:dem":1038,
    "gn:feature_class":"P",
    "gn:feature_code":"PPL",
    "gn:name":"Beaune",
    "gn:population":0,
    "gn:timezone":"Europe/Paris",
    "iso:country":"FR",
    "wof:name":"Beaune",
    "wof:placetype":"locality"
},
  "geometry": {"coordinates":[2.91832,45.58989],"type":"Point"}
}