{
  "type": "Feature",
  "properties": {
    "gn:admin1_code":"84",
    "gn:admin2_code":"63",
    "gn:admin3_code":"633",
    "gn:admin4_code":"63247",
    "gn:asciiname":"Beaune",
    "gn:country_code":"FR",
    "gn:dem":1038,
    "gn:feature_class":"P",
    "gn:feature_code":"PPL",
    "gn:name":"Beaune",
    "gn:population":0,
    "gn:timezone":"Europe/Paris",
    "iso:country":"FR",
    "name:ara_x_preferred":[
        "\u0628\u0648\u0648\u0646"
    ],
    "name:bel_x_preferred":[
        "\u0411\u043e\u043d"
    ],
    "name:bre_x_preferred":[
        "Beaune"
    ],
    "name:bug_x_preferred":[
        "Beaune"
    ],
    "name:bul_x_preferred":[
        "\u0411\u043e\u043d"
    ],
    "name:cat_x_preferred":[
        "Beaune"
    ],
    "name:ceb_x_preferred":[
        "Beaune"
    ],
    "name:ces_x_preferred":[
        "Beaune"
    ],
    "name:deu_x_preferred":[
        "Beaune"
    ],
    "name:epo_x_preferred":[
        "Beaune"
    ],
    "name:eus_x_preferred":[
        "Beaune"
    ],
    "name:fas_x_preferred":[
        "\u0628\u0648\u0646"
    ],
    "name:fra_x_preferred":[
        "Beaune"
    ],
    "name:hun_x_preferred":[
        "Beaune"
    ],
    "name:ind_x_preferred":[
        "Beaune"
    ],
    "name:ita_x_preferred":[
        "Beaune"
    ],
    "name:jpn_x_preferred":[
        "\u30dc\u30fc\u30cc"
    ],
    "name:kaz_x_preferred":[
        "\u0411\u043e\u043d"
    ],
    "name:kor_x_preferred":[
        "\ubcf8"
    ],
    "name:lat_x_preferred":[
        "Belna"
    ],
    "name:lit_x_preferred":[
        "Bonas"
    ],
    "name:ltz_x_preferred":[
        "Beaune"
    ],
    "name:mlg_x_preferred":[
        "Beaune"
    ],
    "name:msa_x_preferred":[
        "Beaune"
    ],
    "name:mzn_x_preferred":[
        "\u0628\u0648\u0646"
    ],
    "name:nld_x_preferred":[
        "Beaune"
    ],
    "name:nno_x_preferred":[
        "Beaune"
    ],
    "name:nor_x_preferred":[
        "Beaune"
    ],
    "name:oci_x_preferred":[
        "Beaune"
    ],
    "name:pms_x_preferred":[
        "Beaune"
    ],
    "name:pol_x_preferred":[
        "Beaune"
    ],
    "name:por_x_preferred":[
        "Beaune"
    ],
    "name:ron_x_preferred":[
        "Beaune"
    ],
    "name:rus_x_preferred":[
        "\u0411\u043e\u043d"
    ],
    "name:sco_x_preferred":[
        "Beaune"
    ],
    "name:slk_x_preferred":[
        "Beaune"
    ],
    "name:slv_x_preferred":[
        "Beaune"
    ],
    "name:spa_x_preferred":[
        "Beaune"
    ],
    "name:sqi_x_preferred":[
        "Beaune"
    ],
    "name:srp_x_preferred":[
        "\u0411\u043e\u043d"
    ],
    "name:swa_x_preferred":[
        "Beaune"
    ],
    "name:swe_x_preferred":[
        "Beaune"
    ],
    "name:szl_x_preferred":[
        "Beaune"
    ],
    "name:tur_x_preferred":[
        "Beaune"
    ],
    "name:ukr_x_preferred":[
        "\u0411\u043e\u043d"
    ],
    "name:uzb_x_preferred":[
        "Beaune"
    ],
    "name:vie_x_preferred":[
        "Beaune"
    ],
    "name:vol_x_preferred":[
        "Beaune"
    ],
    "name:war_x_preferred":[
        "Beaune"
    ],
    "wof:name":"Beaune",
    "wof:placetype":"locality"
},
  "geometry": {"coordinates":[2.91832,45.58989],"type":"Point"}
}