{
  "type": "Feature",
  "properties": {
    "gn:admin1_code":"75",
    "gn:admin2_code":"24",
    "gn:admin3_code":"243",
    "gn:admin4_code":"24156",
    "gn:asciiname":"La Deuil",
    "gn:country_code":"FR",
    "gn:dem":231,
    "gn:feature_class":"P",
    "gn:feature_code":"PPL",
    "gn:name":"La Deuil",
    "gn:population":0,
    "gn:timezone":"Europe/Paris",
    "iso:country":"FR",
    "wof:name":"La Deuil",
    "wof:placetype":"locality"
},
  "geometry": {"coordinates":[0.87792,45.0546],"type":"Point"}
}