{
  "type": "Feature",
  "properties": {
    "gn:admin1_code":"53",
    "gn:admin2_code":"29",
    "gn:admin3_code":"291",
    "gn:admin4_code":"29212",
    "gn:asciiname":"La Trinite",
    "gn:country_code":"FR",
    "gn:dem":92,
    "gn:feature_class":"P",
    "gn:feature_code":"PPL",
    "gn:name":"La Trinit\u00e9",
    "gn:population":0,
    "gn:timezone":"Europe/Paris",
    "iso:country":"FR",
    "name:und_x_variant":[
        "Trinit\u00e9",
        "La Trinit\u00e9"
    ],
    "wof:name":"La Trinite",
    "wof:placetype":"locality"
},
  "geometry": {"coordinates":[-4.58883,48.37133],"type":"Point"}
}