{
  "type": "Feature",
  "properties": {
    "frgov:code_epci":"200040905",
    "frgov:insee_arr":"1",
    "frgov:insee_com":"81275",
    "frgov:insee_dep":"81",
    "frgov:insee_reg":"76",
    "frgov:nom_com":"Salles",
    "frgov:nom_com_m":"SALLES",
    "frgov:nom_dep":"TARN",
    "frgov:nom_reg":"OCCITANIE",
    "frgov:statut":"Commune simple",
    "gn:admin1_code":"76",
    "gn:admin2_code":"81",
    "gn:admin3_code":"811",
    "gn:admin4_code":"81275",
    "gn:asciiname":"Salles",
    "gn:country_code":"FR",
    "gn:dem":198,
    "gn:feature_class":"P",
    "gn:feature_code":"PPL",
    "gn:name":"Salles",
    "gn:population":187,
    "gn:timezone":"Europe/Paris",
    "iso:country":"FR",
    "name:cat_x_preferred":[
        "Salas"
    ],
    "name:ceb_x_preferred":[
        "Salles"
    ],
    "name:deu_x_preferred":[
        "Salles"
    ],
    "name:fra_x_preferred":[
        "Salles"
    ],
    "name:ita_x_preferred":[
        "Salles"
    ],
    "name:nds_x_preferred":[
        "Salles"
    ],
    "name:nld_x_preferred":[
        "Salles"
    ],
    "name:oci_x_preferred":[
        "Salas"
    ],
    "name:pms_x_preferred":[
        "Salles"
    ],
    "name:pol_x_preferred":[
        "Salles"
    ],
    "name:por_x_preferred":[
        "Salles"
    ],
    "name:rus_x_preferred":[
        "\u0421\u0430\u043b\u044c"
    ],
    "name:slk_x_preferred":[
        "Salles"
    ],
    "name:spa_x_preferred":[
        "Salles"
    ],
    "name:swe_x_preferred":[
        "Salles"
    ],
    "name:ukr_x_preferred":[
        "\u0421\u0430\u043b\u044c"
    ],
    "name:zho_x_preferred":[
        "\u8428\u83b1"
    ],
    "qs:a0":"France",
    "qs:a1":"TARN",
    "qs:a1_lc":"81",
    "qs:a1r":"MIDI-PYRENEES",
    "qs:a1r_lc":"73",
    "qs:a2_lc":"20",
    "qs:a2r_lc":"1",
    "qs:adm0":"France",
    "qs:adm0_a3":"FRA",
    "qs:la":"SALLES",
    "qs:la_lc":"81275",
    "qs:level":"localadmin",
    "qs:type":"Commune simple",
    "wof:coterminous":[
        404384399
    ],
    "wof:name":"Salles",
    "wof:placetype":"locality",
    "wof:placetype_local":"Commune simple",
    "wof:population":187
},
  "geometry": {"coordinates":[2.03584,44.0725],"type":"Point"}
}