{
  "type": "Feature",
  "properties": {
    "gn:admin1_code":"76",
    "gn:admin2_code":"81",
    "gn:admin3_code":"811",
    "gn:admin4_code":"81275",
    "gn:asciiname":"Salles",
    "gn:country_code":"FR",
    "gn:dem":198,
    "gn:feature_class":"P",
    "gn:feature_code":"PPL",
    "gn:name":"Salles",
    "gn:population":187,
    "gn:timezone":"Europe/Paris",
    "iso:country":"FR",
    "wof:name":"Salles",
    "wof:placetype":"locality",
    "wof:population":187
},
  "geometry": {"coordinates":[2.03584,44.0725],"type":"Point"}
}