{
  "type": "Feature",
  "properties": {
    "gn:admin1_code":"76",
    "gn:admin2_code":"81",
    "gn:admin3_code":"811",
    "gn:admin4_code":"81275",
    "gn:asciiname":"Salles",
    "gn:country_code":"FR",
    "gn:dem":198,
    "gn:feature_class":"P",
    "gn:feature_code":"PPL",
    "gn:name":"Salles",
    "gn:population":187,
    "gn:timezone":"Europe/Paris",
    "iso:country":"FR",
    "name:ceb_x_preferred":[
        "Salles"
    ],
    "name:deu_x_preferred":[
        "Salles"
    ],
    "name:fra_x_preferred":[
        "Salles"
    ],
    "name:ita_x_preferred":[
        "Salles"
    ],
    "name:nds_x_preferred":[
        "Salles"
    ],
    "name:nld_x_preferred":[
        "Salles"
    ],
    "name:pms_x_preferred":[
        "Salles"
    ],
    "name:pol_x_preferred":[
        "Salles"
    ],
    "name:por_x_preferred":[
        "Salles"
    ],
    "name:rus_x_preferred":[
        "\u0421\u0430\u043b\u044c"
    ],
    "name:slk_x_preferred":[
        "Salles"
    ],
    "name:spa_x_preferred":[
        "Salles"
    ],
    "name:swe_x_preferred":[
        "Salles"
    ],
    "name:ukr_x_preferred":[
        "\u0421\u0430\u043b\u044c"
    ],
    "wof:name":"Salles",
    "wof:placetype":"locality",
    "wof:population":187
},
  "geometry": {"coordinates":[2.03584,44.0725],"type":"Point"}
}