{
  "type": "Feature",
  "properties": {
    "gn:admin1_code":"53",
    "gn:admin2_code":"29",
    "gn:admin3_code":"291",
    "gn:admin4_code":"29075",
    "gn:asciiname":"Seiter",
    "gn:country_code":"FR",
    "gn:dem":71,
    "gn:feature_class":"P",
    "gn:feature_code":"PPL",
    "gn:name":"Seiter",
    "gn:population":0,
    "gn:timezone":"Europe/Paris",
    "iso:country":"FR",
    "wof:name":"Seiter",
    "wof:placetype":"locality"
},
  "geometry": {"coordinates":[-4.36667,48.43333],"type":"Point"}
}