{
  "type": "Feature",
  "properties": {
    "gn:admin1_code":"84",
    "gn:admin2_code":"26",
    "gn:admin3_code":"262",
    "gn:admin4_code":"26135.0",
    "gn:asciiname":"Ferrassieres-de-Barret",
    "gn:country_code":"FR",
    "gn:dem":1171,
    "gn:feature_class":"P",
    "gn:feature_code":"PPL",
    "gn:name":"Ferrassi\u00e8res-de-Barret",
    "gn:population":0,
    "gn:timezone":"Europe/Paris",
    "iso:country":"FR",
    "wof:name":"Ferrassieres-de-Barret",
    "wof:placetype":"locality"
},
  "geometry": {"coordinates":[5.52745,44.14069],"type":"Point"}
}