{
  "type": "Feature",
  "properties": {
    "gn:admin1_code":"24",
    "gn:admin2_code":"18",
    "gn:admin3_code":"181",
    "gn:admin4_code":"18166",
    "gn:asciiname":"Bellevue",
    "gn:country_code":"FR",
    "gn:dem":165,
    "gn:feature_class":"P",
    "gn:feature_code":"PPL",
    "gn:name":"Bellevue",
    "gn:population":0,
    "gn:timezone":"Europe/Paris",
    "iso:country":"FR",
    "name:bar_x_preferred":[
        "Bellevue"
    ],
    "name:bre_x_preferred":[
        "Bellevue"
    ],
    "name:bul_x_preferred":[
        "\u0411\u0435\u043b\u0432\u044e"
    ],
    "name:cat_x_preferred":[
        "Bellevue"
    ],
    "name:ceb_x_preferred":[
        "Bellevue"
    ],
    "name:dan_x_preferred":[
        "Bellevue"
    ],
    "name:deu_x_preferred":[
        "Bellevue"
    ],
    "name:epo_x_preferred":[
        "Bellevue"
    ],
    "name:eus_x_preferred":[
        "Bellevue"
    ],
    "name:fas_x_preferred":[
        "\u0628\u0644\u0648\u06cc\u0648"
    ],
    "name:fin_x_preferred":[
        "Bellevue"
    ],
    "name:fra_x_preferred":[
        "Bellevue"
    ],
    "name:ita_x_preferred":[
        "Bellevue"
    ],
    "name:jpn_x_preferred":[
        "\u30d9\u30eb\u30d3\u30e5\u30fc"
    ],
    "name:nld_x_preferred":[
        "Bellevue"
    ],
    "name:nor_x_preferred":[
        "Bellevue"
    ],
    "name:pol_x_preferred":[
        "Bellevue"
    ],
    "name:por_x_preferred":[
        "Bellevue"
    ],
    "name:rus_x_preferred":[
        "\u0411\u0435\u043b\u044c\u0432\u044e"
    ],
    "name:spa_x_preferred":[
        "Bellevue"
    ],
    "name:swe_x_preferred":[
        "Bellevue"
    ],
    "name:ukr_x_preferred":[
        "\u0411\u0435\u043b\u044c\u0432\u044e"
    ],
    "name:vol_x_preferred":[
        "Bellevue"
    ],
    "name:zho_x_preferred":[
        "\u8d1d\u5c14\u7ef4\u5c24"
    ],
    "wof:name":"Bellevue",
    "wof:placetype":"locality"
},
  "geometry": {"coordinates":[2.56762,47.10782],"type":"Point"}
}