{
  "type": "Feature",
  "properties": {
    "gn:admin1_code":"24",
    "gn:admin2_code":"18",
    "gn:admin3_code":"181",
    "gn:admin4_code":"18166",
    "gn:asciiname":"Bellevue",
    "gn:country_code":"FR",
    "gn:dem":165,
    "gn:feature_class":"P",
    "gn:feature_code":"PPL",
    "gn:name":"Bellevue",
    "gn:population":0,
    "gn:timezone":"Europe/Paris",
    "iso:country":"FR",
    "wof:name":"Bellevue",
    "wof:placetype":"locality"
},
  "geometry": {"coordinates":[2.56762,47.10782],"type":"Point"}
}