{
  "type": "Feature",
  "properties": {
    "gn:admin1_code":"27",
    "gn:admin2_code":"89",
    "gn:admin3_code":"891",
    "gn:admin4_code":"89344",
    "gn:asciiname":"Les Bordes",
    "gn:country_code":"FR",
    "gn:dem":216,
    "gn:feature_class":"P",
    "gn:feature_code":"PPL",
    "gn:name":"Les Bordes",
    "gn:population":0,
    "gn:timezone":"Europe/Paris",
    "iso:country":"FR",
    "name:ceb_x_preferred":[
        "Les Bordes"
    ],
    "name:ces_x_preferred":[
        "Les Bordes"
    ],
    "name:deu_x_preferred":[
        "Les Bordes"
    ],
    "name:epo_x_preferred":[
        "Les Bordes"
    ],
    "name:fra_x_preferred":[
        "Les Bordes"
    ],
    "name:ita_x_preferred":[
        "Les Bordes"
    ],
    "name:nds_x_preferred":[
        "Les Bordes"
    ],
    "name:nld_x_preferred":[
        "Les Bordes"
    ],
    "name:oci_x_preferred":[
        "Les Bordes"
    ],
    "name:pms_x_preferred":[
        "Les Bordes"
    ],
    "name:pol_x_preferred":[
        "Les Bordes"
    ],
    "name:por_x_preferred":[
        "Les Bordes"
    ],
    "name:rus_x_preferred":[
        "\u041b\u0435-\u0411\u043e\u0440\u0434"
    ],
    "name:slk_x_preferred":[
        "Les Bordes"
    ],
    "name:spa_x_preferred":[
        "Les Bordes"
    ],
    "name:swe_x_preferred":[
        "Les Bordes"
    ],
    "name:ukr_x_preferred":[
        "\u041b\u0435-\u0411\u043e\u0440\u0434"
    ],
    "wof:name":"Les Bordes",
    "wof:placetype":"locality"
},
  "geometry": {"coordinates":[3.09915,47.67758],"type":"Point"}
}