{
  "type": "Feature",
  "properties": {
    "gn:admin1_code":"24",
    "gn:admin2_code":"18",
    "gn:admin3_code":"181",
    "gn:admin4_code":"18189.0",
    "gn:asciiname":"Les Bardy",
    "gn:country_code":"FR",
    "gn:dem":235,
    "gn:feature_class":"P",
    "gn:feature_code":"PPL",
    "gn:name":"Les Bardy",
    "gn:population":0,
    "gn:timezone":"Europe/Paris",
    "iso:country":"FR",
    "wof:name":"Les Bardy",
    "wof:placetype":"locality"
},
  "geometry": {"coordinates":[2.44372,47.25514],"type":"Point"}
}