{
  "type": "Feature",
  "properties": {
    "gn:admin1_code":"84",
    "gn:admin2_code":"03",
    "gn:admin3_code":"033",
    "gn:admin4_code":"03298",
    "gn:asciiname":"Chazeuil",
    "gn:country_code":"FR",
    "gn:dem":266,
    "gn:feature_class":"P",
    "gn:feature_code":"PPL",
    "gn:name":"Chazeuil",
    "gn:population":0,
    "gn:timezone":"Europe/Paris",
    "iso:country":"FR",
    "name:und_x_variant":[
        "Chaseuil",
        "Chazeuil"
    ],
    "wof:name":"Chazeuil",
    "wof:placetype":"locality"
},
  "geometry": {"coordinates":[3.38769,46.33138],"type":"Point"}
}