{
  "type": "Feature",
  "properties": {
    "gn:admin1_code":"84",
    "gn:admin2_code":"03",
    "gn:admin3_code":"033",
    "gn:admin4_code":"03298",
    "gn:asciiname":"Chazeuil",
    "gn:country_code":"FR",
    "gn:dem":266,
    "gn:feature_class":"P",
    "gn:feature_code":"PPL",
    "gn:name":"Chazeuil",
    "gn:population":0,
    "gn:timezone":"Europe/Paris",
    "iso:country":"FR",
    "name:ceb_x_preferred":[
        "Chazeuil"
    ],
    "name:deu_x_preferred":[
        "Chazeuil"
    ],
    "name:fra_x_preferred":[
        "Chazeuil"
    ],
    "name:ita_x_preferred":[
        "Chazeuil"
    ],
    "name:nds_x_preferred":[
        "Chazeuil"
    ],
    "name:nld_x_preferred":[
        "Chazeuil"
    ],
    "name:oci_x_preferred":[
        "Chazeuil"
    ],
    "name:pms_x_preferred":[
        "Chazeuil"
    ],
    "name:pol_x_preferred":[
        "Chazeuil"
    ],
    "name:por_x_preferred":[
        "Chazeuil"
    ],
    "name:slk_x_preferred":[
        "Chazeuil"
    ],
    "name:spa_x_preferred":[
        "Chazeuil"
    ],
    "name:swe_x_preferred":[
        "Chazeuil"
    ],
    "name:ukr_x_preferred":[
        "\u0428\u0430\u0437\u0435\u0439"
    ],
    "name:und_x_variant":[
        "Chaseuil"
    ],
    "wof:name":"Chazeuil",
    "wof:placetype":"locality"
},
  "geometry": {"coordinates":[3.38769,46.33138],"type":"Point"}
}