{
  "type": "Feature",
  "properties": {
    "gn:admin1_code":"75",
    "gn:admin2_code":"23",
    "gn:admin3_code":"232",
    "gn:admin4_code":"23243",
    "gn:asciiname":"Montaguillaume",
    "gn:country_code":"FR",
    "gn:dem":454,
    "gn:feature_class":"P",
    "gn:feature_code":"PPL",
    "gn:name":"Montaguillaume",
    "gn:population":0,
    "gn:timezone":"Europe/Paris",
    "iso:country":"FR",
    "wof:name":"Montaguillaume",
    "wof:placetype":"locality"
},
  "geometry": {"coordinates":[2.19109,46.24601],"type":"Point"}
}