{
  "type": "Feature",
  "properties": {
    "frgov:code_epci":"200069615",
    "frgov:insee_arr":"2",
    "frgov:insee_com":"39140",
    "frgov:insee_dep":"39",
    "frgov:insee_reg":"27",
    "frgov:nom_com":"Ch\u00eane-Sec",
    "frgov:nom_com_m":"CHENE-SEC",
    "frgov:nom_dep":"JURA",
    "frgov:nom_reg":"BOURGOGNE-FRANCHE-COMTE",
    "frgov:statut":"Commune simple",
    "gn:admin1_code":"27",
    "gn:admin2_code":"39",
    "gn:admin3_code":"392",
    "gn:admin4_code":"39140",
    "gn:asciiname":"Chene-Sec",
    "gn:country_code":"FR",
    "gn:dem":211,
    "gn:feature_class":"P",
    "gn:feature_code":"PPL",
    "gn:name":"Ch\u00eane-Sec",
    "gn:population":0,
    "gn:timezone":"Europe/Paris",
    "iso:country":"FR",
    "name:fra_x_preferred":[
        "Ch\u00eane-Sec"
    ],
    "name:und_x_variant":[
        "Ch\u00eane-Sec"
    ],
    "qs:a0":"France",
    "qs:a1":"JURA",
    "qs:a1_lc":"39",
    "qs:a1r":"FRANCHE-COMTE",
    "qs:a1r_lc":"43",
    "qs:a2_lc":"07",
    "qs:a2r_lc":"2",
    "qs:adm0":"France",
    "qs:adm0_a3":"FRA",
    "qs:la":"CHENE-SEC",
    "qs:la_lc":"39140",
    "qs:level":"localadmin",
    "qs:type":"Commune simple",
    "wof:coterminous":[
        404409649
    ],
    "wof:name":"Chene-Sec",
    "wof:placetype":"locality",
    "wof:placetype_local":"Commune simple"
},
  "geometry": {"coordinates":[5.44349,46.85266],"type":"Point"}
}