{
  "type": "Feature",
  "properties": {
    "gn:admin1_code":"27",
    "gn:admin2_code":"39",
    "gn:admin3_code":"392",
    "gn:admin4_code":"39140",
    "gn:asciiname":"Chene-Sec",
    "gn:country_code":"FR",
    "gn:dem":211,
    "gn:feature_class":"P",
    "gn:feature_code":"PPL",
    "gn:name":"Ch\u00eane-Sec",
    "gn:population":0,
    "gn:timezone":"Europe/Paris",
    "iso:country":"FR",
    "name:und_x_variant":[
        "Ch\u00eane-Sec"
    ],
    "wof:name":"Chene-Sec",
    "wof:placetype":"locality"
},
  "geometry": {"coordinates":[5.44349,46.85266],"type":"Point"}
}