{
  "type": "Feature",
  "properties": {
    "gn:admin1_code":"94",
    "gn:admin2_code":"2B",
    "gn:admin3_code":"2B3",
    "gn:admin4_code":"2B234",
    "gn:asciiname":"Piobetta",
    "gn:country_code":"FR",
    "gn:dem":822,
    "gn:feature_class":"P",
    "gn:feature_code":"PPL",
    "gn:name":"Piobetta",
    "gn:population":0,
    "gn:timezone":"Europe/Paris",
    "iso:country":"FR",
    "wof:name":"Piobetta",
    "wof:placetype":"locality"
},
  "geometry": {"coordinates":[9.38333,42.33333],"type":"Point"}
}