{
  "type": "Feature",
  "properties": {
    "gn:admin1_code":"27",
    "gn:admin2_code":"89",
    "gn:admin3_code":"891",
    "gn:admin4_code":"89367.0",
    "gn:asciiname":"Le Grand Banny",
    "gn:country_code":"FR",
    "gn:dem":292,
    "gn:feature_class":"P",
    "gn:feature_code":"PPL",
    "gn:name":"Le Grand Banny",
    "gn:population":0,
    "gn:timezone":"Europe/Paris",
    "iso:country":"FR",
    "name:und_x_variant":[
        "Grand Banny",
        "Le Grand Banny"
    ],
    "wof:name":"Le Grand Banny",
    "wof:placetype":"locality"
},
  "geometry": {"coordinates":[3.28533,47.60911],"type":"Point"}
}