{
  "type": "Feature",
  "properties": {
    "gn:admin1_code":"75",
    "gn:admin2_code":"87",
    "gn:admin3_code":"872",
    "gn:admin4_code":"87051",
    "gn:asciiname":"Amboiras",
    "gn:country_code":"FR",
    "gn:dem":504,
    "gn:feature_class":"P",
    "gn:feature_code":"PPL",
    "gn:name":"Amboiras",
    "gn:population":0,
    "gn:timezone":"Europe/Paris",
    "iso:country":"FR",
    "wof:name":"Amboiras",
    "wof:placetype":"locality"
},
  "geometry": {"coordinates":[1.58086,45.6481],"type":"Point"}
}