{
  "type": "Feature",
  "properties": {
    "gn:admin1_code":"75",
    "gn:admin2_code":"23",
    "gn:admin3_code":"232",
    "gn:admin4_code":"23191",
    "gn:asciiname":"Saint-Eloi",
    "gn:country_code":"FR",
    "gn:dem":547,
    "gn:feature_class":"P",
    "gn:feature_code":"PPL",
    "gn:name":"Saint-\u00c9loi",
    "gn:population":173,
    "gn:timezone":"Europe/Paris",
    "iso:country":"FR",
    "name:und_x_variant":[
        "Saint-\u00c9loi"
    ],
    "wof:name":"Saint-Eloi",
    "wof:placetype":"locality",
    "wof:population":173
},
  "geometry": {"coordinates":[1.83324,46.07326],"type":"Point"}
}