{
  "type": "Feature",
  "properties": {
    "frgov:code_epci":"200034825",
    "frgov:insee_arr":"2",
    "frgov:insee_com":"23191",
    "frgov:insee_dep":"23",
    "frgov:insee_reg":"75",
    "frgov:nom_com":"Saint-\u00c9loi",
    "frgov:nom_com_m":"SAINT-ELOI",
    "frgov:nom_dep":"CREUSE",
    "frgov:nom_reg":"NOUVELLE-AQUITAINE",
    "frgov:statut":"Commune simple",
    "gn:admin1_code":"75",
    "gn:admin2_code":"23",
    "gn:admin3_code":"232",
    "gn:admin4_code":"23191",
    "gn:asciiname":"Saint-Eloi",
    "gn:country_code":"FR",
    "gn:dem":547,
    "gn:feature_class":"P",
    "gn:feature_code":"PPL",
    "gn:name":"Saint-\u00c9loi",
    "gn:population":173,
    "gn:timezone":"Europe/Paris",
    "iso:country":"FR",
    "name:fra_x_preferred":[
        "Saint-\u00c9loi"
    ],
    "name:und_x_variant":[
        "Saint-\u00c9loi"
    ],
    "qs:a0":"France",
    "qs:a1":"CREUSE",
    "qs:a1_lc":"23",
    "qs:a1r":"LIMOUSIN",
    "qs:a1r_lc":"74",
    "qs:a2_lc":"21",
    "qs:a2r_lc":"2",
    "qs:adm0":"France",
    "qs:adm0_a3":"FRA",
    "qs:la":"SAINT-ELOI",
    "qs:la_lc":"23191",
    "qs:level":"localadmin",
    "qs:type":"Commune simple",
    "wof:coterminous":[
        404424763
    ],
    "wof:name":"Saint-Eloi",
    "wof:placetype":"locality",
    "wof:placetype_local":"Commune simple",
    "wof:population":173
},
  "geometry": {"coordinates":[1.83324,46.07326],"type":"Point"}
}