{
  "type": "Feature",
  "properties": {
    "gn:admin1_code":"53",
    "gn:admin2_code":"29",
    "gn:admin3_code":"291",
    "gn:admin4_code":"29195",
    "gn:asciiname":"Kerizoc",
    "gn:country_code":"FR",
    "gn:dem":54,
    "gn:feature_class":"P",
    "gn:feature_code":"PPL",
    "gn:name":"Kerizoc",
    "gn:population":0,
    "gn:timezone":"Europe/Paris",
    "iso:country":"FR",
    "wof:name":"Kerizoc",
    "wof:placetype":"locality"
},
  "geometry": {"coordinates":[-4.46245,48.62300000000001],"type":"Point"}
}