{
  "type": "Feature",
  "properties": {
    "gn:admin1_code":"84",
    "gn:admin2_code":"43",
    "gn:admin3_code":"433",
    "gn:admin4_code":"43130",
    "gn:asciiname":"Salettes",
    "gn:country_code":"FR",
    "gn:dem":900,
    "gn:feature_class":"P",
    "gn:feature_code":"PPL",
    "gn:name":"Salettes",
    "gn:population":0,
    "gn:timezone":"Europe/Paris",
    "iso:country":"FR",
    "name:ceb_x_preferred":[
        "Salettes"
    ],
    "name:deu_x_preferred":[
        "Salettes"
    ],
    "name:fra_x_preferred":[
        "Salettes"
    ],
    "name:ita_x_preferred":[
        "Salettes"
    ],
    "name:nds_x_preferred":[
        "Salettes"
    ],
    "name:nld_x_preferred":[
        "Salettes"
    ],
    "name:pms_x_preferred":[
        "Salettes"
    ],
    "name:pol_x_preferred":[
        "Salettes"
    ],
    "name:slk_x_preferred":[
        "Salettes"
    ],
    "name:spa_x_preferred":[
        "Salettes"
    ],
    "name:swe_x_preferred":[
        "Salettes"
    ],
    "name:ukr_x_preferred":[
        "\u0421\u0430\u043b\u0435\u0442\u0442"
    ],
    "wof:name":"Salettes",
    "wof:placetype":"locality"
},
  "geometry": {"coordinates":[4.28342,45.075],"type":"Point"}
}