{
  "type": "Feature",
  "properties": {
    "gn:admin1_code":"84",
    "gn:admin2_code":"43",
    "gn:admin3_code":"433",
    "gn:admin4_code":"43130",
    "gn:asciiname":"Salettes",
    "gn:country_code":"FR",
    "gn:dem":900,
    "gn:feature_class":"P",
    "gn:feature_code":"PPL",
    "gn:name":"Salettes",
    "gn:population":0,
    "gn:timezone":"Europe/Paris",
    "iso:country":"FR",
    "wof:name":"Salettes",
    "wof:placetype":"locality"
},
  "geometry": {"coordinates":[4.28342,45.075],"type":"Point"}
}