{
  "type": "Feature",
  "properties": {
    "iso:country":"FR",
    "name:eng_x_preferred":[
        "Quartier des Arts-et-Metiers"
    ],
    "name:fra_x_preferred":[
        "Quartier des Arts-et-M\u00e9tiers"
    ],
    "wof:name":"Quartier des Arts-et-Metiers",
    "wof:placetype":"neighbourhood"
},
  "geometry": {"coordinates":[2.3566641303777,48.86662142506199],"type":"Point"}
}