{
  "type": "Feature",
  "properties": {
    "gn:admin1_code":"24",
    "gn:admin2_code":"45",
    "gn:admin3_code":"453",
    "gn:admin4_code":"45030",
    "gn:asciiname":"Orme",
    "gn:country_code":"FR",
    "gn:dem":105,
    "gn:feature_class":"P",
    "gn:feature_code":"PPL",
    "gn:name":"Orme",
    "gn:population":0,
    "gn:timezone":"Europe/Paris",
    "iso:country":"FR",
    "wof:name":"Orme",
    "wof:placetype":"locality"
},
  "geometry": {"coordinates":[2.41587,48.06326],"type":"Point"}
}