{
  "type": "Feature",
  "properties": {
    "gn:admin1_code":"84",
    "gn:admin2_code":"63",
    "gn:admin3_code":"632",
    "gn:admin4_code":"63368",
    "gn:asciiname":"Les Coins",
    "gn:country_code":"FR",
    "gn:dem":421,
    "gn:feature_class":"P",
    "gn:feature_code":"PPL",
    "gn:name":"Les Coins",
    "gn:population":0,
    "gn:timezone":"Europe/Paris",
    "iso:country":"FR",
    "wof:name":"Les Coins",
    "wof:placetype":"locality"
},
  "geometry": {"coordinates":[3.33454,45.69857],"type":"Point"}
}