{
  "type": "Feature",
  "properties": {
    "gn:admin1_code":"27",
    "gn:admin2_code":"89",
    "gn:admin3_code":"892",
    "gn:admin4_code":"89336",
    "gn:asciiname":"Villiers-les-Nonains",
    "gn:country_code":"FR",
    "gn:dem":353,
    "gn:feature_class":"P",
    "gn:feature_code":"PPL",
    "gn:name":"Villiers-les-Nonains",
    "gn:population":0,
    "gn:timezone":"Europe/Paris",
    "iso:country":"FR",
    "wof:name":"Villiers-les-Nonains",
    "wof:placetype":"locality"
},
  "geometry": {"coordinates":[3.98571,47.44226],"type":"Point"}
}