{
  "type": "Feature",
  "properties": {
    "gn:admin1_code":"24",
    "gn:admin2_code":"45",
    "gn:admin3_code":"452",
    "gn:admin4_code":"45277.0",
    "gn:asciiname":"Les Rossignols",
    "gn:country_code":"FR",
    "gn:dem":149,
    "gn:feature_class":"P",
    "gn:feature_code":"PPL",
    "gn:name":"Les Rossignols",
    "gn:population":0,
    "gn:timezone":"Europe/Paris",
    "iso:country":"FR",
    "wof:name":"Les Rossignols",
    "wof:placetype":"locality"
},
  "geometry": {"coordinates":[2.50514,47.68038],"type":"Point"}
}