{
  "type": "Feature",
  "properties": {
    "gn:gn_country":"FR",
    "gn:gn_fcode":"PPL",
    "gn:gn_pop":137,
    "gn:population":137,
    "iso:country":"FR",
    "name:bul_x_preferred":[
        "\u0412\u0438\u0437\u0430\u0432\u043e\u043d\u0430"
    ],
    "name:ces_x_preferred":[
        "Vizzavona"
    ],
    "name:deu_x_preferred":[
        "Vizzavona"
    ],
    "name:eng_x_preferred":[
        "Vizzavona"
    ],
    "name:fra_x_preferred":[
        "Vizzavona"
    ],
    "name:ita_x_preferred":[
        "Vizzavona"
    ],
    "name:nan_x_preferred":[
        "Vizzavona"
    ],
    "name:nld_x_preferred":[
        "Vizzavona"
    ],
    "name:rus_x_preferred":[
        "\u0412\u0438\u0437\u0430\u0432\u043e\u043d\u0430"
    ],
    "qs_pg:aaroncc":"FR",
    "qs_pg:gn_country":"FR",
    "qs_pg:gn_fcode":"PPL",
    "qs_pg:gn_pop":137,
    "qs_pg:name":"Vizzavona",
    "qs_pg:name_adm0":"France",
    "qs_pg:name_adm1":"Corse",
    "qs_pg:photos":133,
    "qs_pg:photos_1k":27,
    "qs_pg:photos_9k":1,
    "qs_pg:photos_9r":3,
    "qs_pg:photos_all":133,
    "qs_pg:photos_sr":3,
    "qs_pg:pop_sr":1,
    "qs_pg:qs_pg_placetype":"locality",
    "qs_pg:qs_pg_placetype_gp":"Town",
    "qs_pg:woe_adm0":23424819,
    "woe:adm0_id":23424819,
    "woe:name_adm0":"France",
    "woe:name_adm1":"Corse",
    "woe:placetype":"Town",
    "wof:name":"Vizzavona",
    "wof:placetype":"neighbourhood",
    "wof:population":137
},
  "geometry": {"coordinates":[9.13393,42.12793],"type":"Point"}
}