{
  "type": "Feature",
  "properties": {
    "gn:admin1_code":"75",
    "gn:admin2_code":"23",
    "gn:admin3_code":"231",
    "gn:admin4_code":"23114",
    "gn:asciiname":"Le Teillet",
    "gn:country_code":"FR",
    "gn:dem":438,
    "gn:feature_class":"P",
    "gn:feature_code":"PPL",
    "gn:name":"Le Teillet",
    "gn:population":0,
    "gn:timezone":"Europe/Paris",
    "iso:country":"FR",
    "wof:name":"Le Teillet",
    "wof:placetype":"locality"
},
  "geometry": {"coordinates":[2.33562,46.15648],"type":"Point"}
}