{
  "type": "Feature",
  "properties": {
    "gn:admin1_code":"44",
    "gn:admin2_code":"68",
    "gn:admin3_code":"685",
    "gn:admin4_code":"68298",
    "gn:asciiname":"Echery",
    "gn:country_code":"FR",
    "gn:dem":427,
    "gn:feature_class":"P",
    "gn:feature_code":"PPL",
    "gn:name":"\u00c9chery",
    "gn:population":0,
    "gn:timezone":"Europe/Paris",
    "iso:country":"FR",
    "name:und_x_variant":[
        "\u00c9chery"
    ],
    "wof:name":"Echery",
    "wof:placetype":"locality"
},
  "geometry": {"coordinates":[7.1625,48.23132],"type":"Point"}
}