{
  "type": "Feature",
  "properties": {
    "gn:admin1_code":"93",
    "gn:admin2_code":"06",
    "gn:admin3_code":"062",
    "gn:admin4_code":"06023",
    "gn:asciiname":"Piene",
    "gn:country_code":"FR",
    "gn:dem":222,
    "gn:feature_class":"P",
    "gn:feature_code":"PPL",
    "gn:name":"Piene",
    "gn:population":0,
    "gn:timezone":"Europe/Paris",
    "iso:country":"FR",
    "name:und_x_variant":[
        "Piene-Haute",
        "Pienne-Haute",
        "Piena",
        "Piene"
    ],
    "wof:name":"Piene",
    "wof:placetype":"locality"
},
  "geometry": {"coordinates":[7.51927,43.90845],"type":"Point"}
}