{
  "type": "Feature",
  "properties": {
    "gn:admin1_code":"84",
    "gn:admin2_code":"43",
    "gn:admin3_code":"431",
    "gn:admin4_code":"43173",
    "gn:asciiname":"Saint-Christophe-d'Allier",
    "gn:country_code":"FR",
    "gn:dem":976,
    "gn:feature_class":"P",
    "gn:feature_code":"PPL",
    "gn:name":"Saint-Christophe-d\u2019Allier",
    "gn:population":0,
    "gn:timezone":"Europe/Paris",
    "iso:country":"FR",
    "name:bug_x_preferred":[
        "Saint-Christophe-d'Allier"
    ],
    "name:ceb_x_preferred":[
        "Saint-Christophe-d'Allier"
    ],
    "name:deu_x_preferred":[
        "Saint-Christophe-d\u2019Allier"
    ],
    "name:eus_x_preferred":[
        "Saint-Christophe-d'Allier"
    ],
    "name:fra_x_preferred":[
        "Saint-Christophe-d'Allier"
    ],
    "name:hun_x_preferred":[
        "Saint-Christophe-d\u2019Allier"
    ],
    "name:ita_x_preferred":[
        "Saint-Christophe-d'Allier"
    ],
    "name:kaz_x_preferred":[
        "\u0421\u0435\u043d-\u041a\u0440\u0438\u0441\u0442\u043e\u0444-\u0434'\u0410\u043b\u044c\u0435"
    ],
    "name:lat_x_preferred":[
        "Saint-Christophe-d'Allier"
    ],
    "name:ltz_x_preferred":[
        "Saint-Christophe-d'Allier"
    ],
    "name:msa_x_preferred":[
        "Saint-Christophe-d'Allier"
    ],
    "name:nld_x_preferred":[
        "Saint-Christophe-d'Allier"
    ],
    "name:pms_x_preferred":[
        "Saint-Christophe-d'Allier"
    ],
    "name:pol_x_preferred":[
        "Saint-Christophe-d\u2019Allier"
    ],
    "name:por_x_preferred":[
        "Saint-Christophe-d'Allier"
    ],
    "name:ron_x_preferred":[
        "Saint-Christophe-d'Allier"
    ],
    "name:slk_x_preferred":[
        "Saint-Christophe-d\u2019Allier"
    ],
    "name:spa_x_preferred":[
        "Saint-Christophe-d'Allier"
    ],
    "name:swe_x_preferred":[
        "Saint-Christophe-d'Allier"
    ],
    "name:ukr_x_preferred":[
        "\u0421\u0435\u043d-\u041a\u0440\u0438\u0441\u0442\u043e\u0444-\u0434'\u0410\u043b\u044c\u0454"
    ],
    "name:und_x_variant":[
        "Saint-Christophe",
        "Saint-Christophe-d\u2019Allier"
    ],
    "name:urd_x_preferred":[
        "\u0633\u06cc\u0646\u0679-\u06a9\u0631\u0648\u0633\u0679\u0648\u0641\u06d2-\u062f\u0644\u0626\u06cc\u0631"
    ],
    "name:uzb_x_preferred":[
        "Saint-Christophe-d'Allier"
    ],
    "name:vie_x_preferred":[
        "Saint-Christophe-d'Allier"
    ],
    "name:vol_x_preferred":[
        "Saint-Christophe-d'Allier"
    ],
    "name:war_x_preferred":[
        "Saint-Christophe-d'Allier"
    ],
    "name:zho_x_preferred":[
        "\u5723\u514b\u91cc\u65af\u6258\u592b\u8fbe\u5229\u8036"
    ],
    "wof:name":"Saint-Christophe-d'Allier",
    "wof:placetype":"locality"
},
  "geometry": {"coordinates":[3.70426,44.85654],"type":"Point"}
}