{
  "type": "Feature",
  "properties": {
    "gn:admin1_code":"84",
    "gn:admin2_code":"43",
    "gn:admin3_code":"431",
    "gn:admin4_code":"43173",
    "gn:asciiname":"Saint-Christophe-d'Allier",
    "gn:country_code":"FR",
    "gn:dem":976,
    "gn:feature_class":"P",
    "gn:feature_code":"PPL",
    "gn:name":"Saint-Christophe-d\u2019Allier",
    "gn:population":0,
    "gn:timezone":"Europe/Paris",
    "iso:country":"FR",
    "name:und_x_variant":[
        "Saint-Christophe",
        "Saint-Christophe-d\u2019Allier"
    ],
    "wof:name":"Saint-Christophe-d'Allier",
    "wof:placetype":"locality"
},
  "geometry": {"coordinates":[3.70426,44.85654],"type":"Point"}
}