{
  "type": "Feature",
  "properties": {
    "gn:admin1_code":"24",
    "gn:admin2_code":"36",
    "gn:admin3_code":"363",
    "gn:admin4_code":"36143",
    "gn:asciiname":"Vicq",
    "gn:country_code":"FR",
    "gn:dem":235,
    "gn:feature_class":"P",
    "gn:feature_code":"PPL",
    "gn:name":"Vicq",
    "gn:population":0,
    "gn:timezone":"Europe/Paris",
    "iso:country":"FR",
    "wof:name":"Vicq",
    "wof:placetype":"locality"
},
  "geometry": {"coordinates":[1.95991,46.63885],"type":"Point"}
}