{
  "type": "Feature",
  "properties": {
    "gn:admin1_code":"44",
    "gn:admin2_code":"51",
    "gn:admin3_code":"513",
    "gn:admin4_code":"51440",
    "gn:asciiname":"Moronvilliers",
    "gn:country_code":"FR",
    "gn:dem":193,
    "gn:feature_class":"P",
    "gn:feature_code":"PPLL",
    "gn:name":"Moronvilliers",
    "gn:population":0,
    "gn:timezone":"Europe/Paris",
    "iso:country":"FR",
    "name:fra_x_preferred":[
        "Moronvilliers"
    ],
    "wof:name":"Moronvilliers",
    "wof:placetype":"locality"
},
  "geometry": {"coordinates":[4.31385,49.23593],"type":"Point"}
}