{
  "type": "Feature",
  "properties": {
    "iso:country":"FR",
    "name:eng_x_preferred":[
        "Quartier de la Plaine-de-Monceau"
    ],
    "name:fra_x_preferred":[
        "Quartier de la Plaine-de-Monceau"
    ],
    "wof:name":"Quartier de la Plaine-de-Monceau",
    "wof:placetype":"neighbourhood"
},
  "geometry": {"coordinates":[2.30184690308923,48.88555098763624],"type":"Point"}
}