{
  "type": "Feature",
  "properties": {
    "gn:admin1_code":"44",
    "gn:admin2_code":"55",
    "gn:admin3_code":"553",
    "gn:admin4_code":"55174",
    "gn:asciiname":"Ivoiry",
    "gn:country_code":"FR",
    "gn:dem":215,
    "gn:feature_class":"P",
    "gn:feature_code":"PPL",
    "gn:name":"Ivoiry",
    "gn:population":0,
    "gn:timezone":"Europe/Paris",
    "iso:country":"FR",
    "wof:name":"Ivoiry",
    "wof:placetype":"locality"
},
  "geometry": {"coordinates":[5.09751,49.27537],"type":"Point"}
}