{
  "type": "Feature",
  "properties": {
    "gn:admin1_code":"27",
    "gn:admin2_code":"21",
    "gn:admin3_code":"213",
    "gn:admin4_code":"21563.0",
    "gn:asciiname":"Corcelotte-en-Montagne",
    "gn:country_code":"FR",
    "gn:dem":481,
    "gn:feature_class":"P",
    "gn:feature_code":"PPL",
    "gn:name":"Corcelotte-en-Montagne",
    "gn:population":0,
    "gn:timezone":"Europe/Paris",
    "iso:country":"FR",
    "wof:name":"Corcelotte-en-Montagne",
    "wof:placetype":"locality"
},
  "geometry": {"coordinates":[4.62465,47.33476],"type":"Point"}
}