{
  "type": "Feature",
  "properties": {
    "gn:admin1_code":"27",
    "gn:admin2_code":"89",
    "gn:admin3_code":"891",
    "gn:admin4_code":"89334.0",
    "gn:asciiname":"Sur Ocre",
    "gn:country_code":"FR",
    "gn:dem":153,
    "gn:feature_class":"P",
    "gn:feature_code":"PPL",
    "gn:name":"Sur Ocre",
    "gn:population":0,
    "gn:timezone":"Europe/Paris",
    "iso:country":"FR",
    "wof:name":"Sur Ocre",
    "wof:placetype":"locality"
},
  "geometry": {"coordinates":[3.34047,47.82708],"type":"Point"}
}