{
  "type": "Feature",
  "properties": {
    "gn:admin1_code":"32",
    "gn:admin2_code":"59",
    "gn:admin3_code":"593",
    "gn:admin4_code":"59105",
    "gn:asciiname":"Le Marais",
    "gn:country_code":"FR",
    "gn:dem":17,
    "gn:feature_class":"P",
    "gn:feature_code":"PPL",
    "gn:name":"Le Marais",
    "gn:population":0,
    "gn:timezone":"Europe/Paris",
    "iso:country":"FR",
    "name:und_x_variant":[
        "Le Marals",
        "Le Marais"
    ],
    "wof:name":"Le Marais",
    "wof:placetype":"locality"
},
  "geometry": {"coordinates":[3.24382,50.42208],"type":"Point"}
}