{
  "type": "Feature",
  "properties": {
    "gn:admin1_code":"32",
    "gn:admin2_code":"59",
    "gn:admin3_code":"593",
    "gn:admin4_code":"59105",
    "gn:asciiname":"Le Marais",
    "gn:country_code":"FR",
    "gn:dem":17,
    "gn:feature_class":"P",
    "gn:feature_code":"PPL",
    "gn:name":"Le Marais",
    "gn:population":0,
    "gn:timezone":"Europe/Paris",
    "iso:country":"FR",
    "name:ara_x_preferred":[
        "\u062d\u064a \u0645\u0627\u0631\u064a\u0647"
    ],
    "name:bel_x_preferred":[
        "\u041c\u0430\u0440\u044d"
    ],
    "name:bul_x_preferred":[
        "\u041c\u0430\u0440\u0435"
    ],
    "name:ces_x_preferred":[
        "Le Marais"
    ],
    "name:deu_x_preferred":[
        "Marais"
    ],
    "name:ell_x_preferred":[
        "\u039b\u03b5 \u039c\u03b1\u03c1\u03b1\u03af"
    ],
    "name:epo_x_preferred":[
        "Le Marais"
    ],
    "name:eus_x_preferred":[
        "Le Marais"
    ],
    "name:fas_x_preferred":[
        "\u0645\u062d\u0644\u0647 \u0644\u0648\u0645\u0631\u06cc"
    ],
    "name:fin_x_preferred":[
        "Le Marais"
    ],
    "name:fra_x_preferred":[
        "Le Marais"
    ],
    "name:heb_x_preferred":[
        "\u05d4\u05de\u05d0\u05e8\u05d4"
    ],
    "name:ita_x_preferred":[
        "Le Marais"
    ],
    "name:jpn_x_preferred":[
        "\u30eb\u30fb\u30de\u30ec"
    ],
    "name:kat_x_preferred":[
        "\u10db\u10d0\u10e0\u10d4"
    ],
    "name:nld_x_preferred":[
        "Le Marais"
    ],
    "name:nor_x_preferred":[
        "Le Marais"
    ],
    "name:pol_x_preferred":[
        "Le Marais"
    ],
    "name:por_x_preferred":[
        "Marais"
    ],
    "name:rus_x_preferred":[
        "\u041c\u0430\u0440\u0435"
    ],
    "name:slk_x_preferred":[
        "Le Marais"
    ],
    "name:spa_x_preferred":[
        "Le Marais"
    ],
    "name:swe_x_preferred":[
        "Marais"
    ],
    "name:ukr_x_preferred":[
        "\u041c\u0430\u0440\u0435"
    ],
    "name:und_x_variant":[
        "Le Marals",
        "Le Marais"
    ],
    "name:vie_x_preferred":[
        "Le Marais"
    ],
    "name:zho_x_preferred":[
        "\u739b\u9ed1\u533a"
    ],
    "wof:name":"Le Marais",
    "wof:placetype":"locality"
},
  "geometry": {"coordinates":[3.24382,50.42208],"type":"Point"}
}