{
  "type": "Feature",
  "properties": {
    "gn:admin1_code":"84",
    "gn:admin2_code":"69",
    "gn:admin3_code":"691",
    "gn:admin4_code":"69288.0",
    "gn:asciiname":"Poulieu",
    "gn:country_code":"FR",
    "gn:dem":287,
    "gn:feature_class":"P",
    "gn:feature_code":"PPL",
    "gn:name":"Poulieu",
    "gn:population":0,
    "gn:timezone":"Europe/Paris",
    "iso:country":"FR",
    "wof:name":"Poulieu",
    "wof:placetype":"locality"
},
  "geometry": {"coordinates":[5.05885,45.67574000000001],"type":"Point"}
}