{
  "type": "Feature",
  "properties": {
    "iso:country":"FR",
    "name:eng_x_preferred":[
        "La Defense"
    ],
    "name:fra_x_preferred":[
        "La D\u00e9fense"
    ],
    "wof:name":"La Defense",
    "wof:placetype":"neighbourhood"
},
  "geometry": {"coordinates":[2.24158124430708,48.89072846037752],"type":"Point"}
}