{
  "type": "Feature",
  "properties": {
    "gn:admin1_code":"28",
    "gn:admin2_code":"27",
    "gn:admin3_code":"271",
    "gn:admin4_code":"27213",
    "gn:asciiname":"La Villeneuve",
    "gn:country_code":"FR",
    "gn:dem":124,
    "gn:feature_class":"P",
    "gn:feature_code":"PPL",
    "gn:name":"La Villeneuve",
    "gn:population":0,
    "gn:timezone":"Europe/Paris",
    "iso:country":"FR",
    "wof:name":"La Villeneuve",
    "wof:placetype":"locality"
},
  "geometry": {"coordinates":[1.63705,49.14100000000001],"type":"Point"}
}