{
  "type": "Feature",
  "properties": {
    "gn:admin1_code":"11",
    "gn:admin2_code":"78",
    "gn:admin3_code":"782",
    "gn:admin4_code":"78506",
    "gn:asciiname":"Gourville",
    "gn:country_code":"FR",
    "gn:dem":138,
    "gn:feature_class":"P",
    "gn:feature_code":"PPL",
    "gn:name":"Gourville",
    "gn:population":0,
    "gn:timezone":"Europe/Paris",
    "iso:country":"FR",
    "name:cat_x_preferred":[
        "Gourville"
    ],
    "name:ceb_x_preferred":[
        "Gourville"
    ],
    "name:deu_x_preferred":[
        "Gourville"
    ],
    "name:eus_x_preferred":[
        "Gourville"
    ],
    "name:fra_x_preferred":[
        "Gourville"
    ],
    "name:hun_x_preferred":[
        "Gourville"
    ],
    "name:hye_x_preferred":[
        "\u0533\u0578\u0582\u0580\u057e\u056b\u056c"
    ],
    "name:ita_x_preferred":[
        "Gourville"
    ],
    "name:lat_x_preferred":[
        "Gourville"
    ],
    "name:msa_x_preferred":[
        "Gourville"
    ],
    "name:nld_x_preferred":[
        "Gourville"
    ],
    "name:oci_x_preferred":[
        "Gourville"
    ],
    "name:pms_x_preferred":[
        "Gourville"
    ],
    "name:pol_x_preferred":[
        "Gourville"
    ],
    "name:por_x_preferred":[
        "Gourville"
    ],
    "name:ron_x_preferred":[
        "Gourville"
    ],
    "name:rus_x_preferred":[
        "\u0413\u0443\u0440\u0432\u0438\u043b\u044c"
    ],
    "name:slk_x_preferred":[
        "Gourville"
    ],
    "name:spa_x_preferred":[
        "Gourville"
    ],
    "name:swe_x_preferred":[
        "Gourville"
    ],
    "name:ukr_x_preferred":[
        "\u0413\u0443\u0440\u0432\u0456\u043b\u044c"
    ],
    "name:vie_x_preferred":[
        "Gourville"
    ],
    "name:vol_x_preferred":[
        "Gourville"
    ],
    "name:war_x_preferred":[
        "Gourville"
    ],
    "name:zho_x_preferred":[
        "\u53e4\u5c14\u7ef4\u5c14"
    ],
    "wof:name":"Gourville",
    "wof:placetype":"locality"
},
  "geometry": {"coordinates":[1.79194,48.51378],"type":"Point"}
}