{
  "type": "Feature",
  "properties": {
    "gn:admin1_code":"44",
    "gn:admin2_code":"55",
    "gn:admin3_code":"553",
    "gn:admin4_code":"55253",
    "gn:asciiname":"Senades",
    "gn:country_code":"FR",
    "gn:dem":168,
    "gn:feature_class":"P",
    "gn:feature_code":"PPL",
    "gn:name":"Senades",
    "gn:population":0,
    "gn:timezone":"Europe/Paris",
    "iso:country":"FR",
    "wof:name":"Senades",
    "wof:placetype":"locality"
},
  "geometry": {"coordinates":[4.99915,49.09789],"type":"Point"}
}