{
  "type": "Feature",
  "properties": {
    "gn:admin1_code":"44",
    "gn:admin2_code":"10",
    "gn:admin3_code":"103",
    "gn:admin4_code":"10349",
    "gn:asciiname":"Grange-l'Eveque",
    "gn:country_code":"FR",
    "gn:dem":148,
    "gn:feature_class":"P",
    "gn:feature_code":"PPL",
    "gn:name":"Grange-l'\u00c9v\u00eaque",
    "gn:population":0,
    "gn:timezone":"Europe/Paris",
    "iso:country":"FR",
    "name:und_x_variant":[
        "La Grange-l'Ev\u00eaque",
        "Grange-l'\u00c9v\u00eaque"
    ],
    "wof:name":"Grange-l'Eveque",
    "wof:placetype":"locality"
},
  "geometry": {"coordinates":[3.94572,48.3227],"type":"Point"}
}