{
  "type": "Feature",
  "properties": {
    "gn:admin1_code":"28",
    "gn:admin2_code":"76",
    "gn:admin3_code":"762",
    "gn:admin4_code":"76481.0",
    "gn:asciiname":"Saint-Barthelemy",
    "gn:country_code":"FR",
    "gn:dem":74,
    "gn:feature_class":"P",
    "gn:feature_code":"PPL",
    "gn:name":"Saint-Barth\u00e9lemy",
    "gn:population":0,
    "gn:timezone":"Europe/Paris",
    "iso:country":"FR",
    "wof:name":"Saint-Barthelemy",
    "wof:placetype":"locality"
},
  "geometry": {"coordinates":[0.14892,49.56552],"type":"Point"}
}