{
  "type": "Feature",
  "properties": {
    "gn:admin1_code":"84",
    "gn:admin2_code":"63",
    "gn:admin3_code":"632",
    "gn:admin4_code":"63225.0",
    "gn:asciiname":"Le Fraisse",
    "gn:country_code":"FR",
    "gn:dem":724,
    "gn:feature_class":"P",
    "gn:feature_code":"PPL",
    "gn:name":"Le Fraisse",
    "gn:population":0,
    "gn:timezone":"Europe/Paris",
    "iso:country":"FR",
    "wof:name":"Le Fraisse",
    "wof:placetype":"locality"
},
  "geometry": {"coordinates":[2.48962,45.61977],"type":"Point"}
}