{
  "type": "Feature",
  "properties": {
    "gn:admin1_code":"44",
    "gn:admin2_code":"88",
    "gn:admin3_code":"882",
    "gn:admin4_code":"88004",
    "gn:asciiname":"Ainvelle",
    "gn:country_code":"FR",
    "gn:dem":298,
    "gn:feature_class":"P",
    "gn:feature_code":"PPL",
    "gn:name":"Ainvelle",
    "gn:population":149,
    "gn:timezone":"Europe/Paris",
    "iso:country":"FR",
    "wof:name":"Ainvelle",
    "wof:placetype":"locality",
    "wof:population":149
},
  "geometry": {"coordinates":[5.8284,47.99658],"type":"Point"}
}