{
  "type": "Feature",
  "properties": {
    "gn:admin1_code":"75",
    "gn:admin2_code":"19",
    "gn:admin3_code":"193",
    "gn:admin4_code":"19226",
    "gn:asciiname":"Fournol",
    "gn:country_code":"FR",
    "gn:dem":786,
    "gn:feature_class":"P",
    "gn:feature_code":"PPL",
    "gn:name":"Fournol",
    "gn:population":0,
    "gn:timezone":"Europe/Paris",
    "iso:country":"FR",
    "wof:name":"Fournol",
    "wof:placetype":"locality"
},
  "geometry": {"coordinates":[1.99181,45.619],"type":"Point"}
}