{
  "type": "Feature",
  "properties": {
    "gn:admin1_code":"27",
    "gn:admin2_code":"71",
    "gn:admin3_code":"711",
    "gn:admin4_code":"71537",
    "gn:asciiname":"Chevigny",
    "gn:country_code":"FR",
    "gn:dem":272,
    "gn:feature_class":"P",
    "gn:feature_code":"PPL",
    "gn:name":"Chevigny",
    "gn:population":0,
    "gn:timezone":"Europe/Paris",
    "iso:country":"FR",
    "wof:name":"Chevigny",
    "wof:placetype":"locality"
},
  "geometry": {"coordinates":[4.10119,46.79047],"type":"Point"}
}