{
  "type": "Feature",
  "properties": {
    "gn:admin1_code":"27",
    "gn:admin2_code":"71",
    "gn:admin3_code":"711",
    "gn:admin4_code":"71537",
    "gn:asciiname":"Chevigny",
    "gn:country_code":"FR",
    "gn:dem":272,
    "gn:feature_class":"P",
    "gn:feature_code":"PPL",
    "gn:name":"Chevigny",
    "gn:population":0,
    "gn:timezone":"Europe/Paris",
    "iso:country":"FR",
    "name:cat_x_preferred":[
        "Chevigny"
    ],
    "name:ceb_x_preferred":[
        "Chevigny"
    ],
    "name:deu_x_preferred":[
        "Chevigny"
    ],
    "name:eus_x_preferred":[
        "Chevigny"
    ],
    "name:fra_x_preferred":[
        "Chevigny"
    ],
    "name:hun_x_preferred":[
        "Chevigny"
    ],
    "name:ita_x_preferred":[
        "Chevigny"
    ],
    "name:lat_x_preferred":[
        "Chevigny"
    ],
    "name:msa_x_preferred":[
        "Chevigny"
    ],
    "name:nld_x_preferred":[
        "Chevigny"
    ],
    "name:oci_x_preferred":[
        "Chevigny"
    ],
    "name:pms_x_preferred":[
        "Chevigny"
    ],
    "name:pol_x_preferred":[
        "Chevigny"
    ],
    "name:por_x_preferred":[
        "Chevigny"
    ],
    "name:slk_x_preferred":[
        "Chevigny"
    ],
    "name:spa_x_preferred":[
        "Chevigny"
    ],
    "name:srp_x_preferred":[
        "\u0428\u0435\u0432\u0438\u045a\u0438"
    ],
    "name:swe_x_preferred":[
        "Chevigny"
    ],
    "name:ukr_x_preferred":[
        "\u0428\u0435\u0432\u0456\u043d\u044c\u0457"
    ],
    "name:uzb_x_preferred":[
        "Chevigny"
    ],
    "name:vie_x_preferred":[
        "Chevigny"
    ],
    "name:vol_x_preferred":[
        "Chevigny"
    ],
    "name:war_x_preferred":[
        "Chevigny"
    ],
    "name:zho_x_preferred":[
        "\u8c22\u7ef4\u5c3c"
    ],
    "wof:name":"Chevigny",
    "wof:placetype":"locality"
},
  "geometry": {"coordinates":[4.10119,46.79047],"type":"Point"}
}