{
  "type": "Feature",
  "properties": {
    "gn:admin1_code":"84",
    "gn:admin2_code":"63",
    "gn:admin3_code":"634",
    "gn:admin4_code":"63233",
    "gn:asciiname":"Montaigut-en-Combraille",
    "gn:country_code":"FR",
    "gn:dem":625,
    "gn:feature_class":"P",
    "gn:feature_code":"PPL",
    "gn:name":"Montaigut-en-Combraille",
    "gn:population":1047,
    "gn:timezone":"Europe/Paris",
    "iso:country":"FR",
    "name:und_x_variant":[
        "Montaigut-en-Combrailles",
        "Montaigut",
        "Montaigut-en-Combraille"
    ],
    "wof:name":"Montaigut-en-Combraille",
    "wof:placetype":"locality",
    "wof:population":1047
},
  "geometry": {"coordinates":[2.80847,46.17984000000001],"type":"Point"}
}