{
  "type": "Feature",
  "properties": {
    "gn:admin1_code":"75",
    "gn:admin2_code":"19",
    "gn:admin3_code":"192",
    "gn:admin4_code":"19040",
    "gn:asciiname":"Le Teil",
    "gn:country_code":"FR",
    "gn:dem":485,
    "gn:feature_class":"P",
    "gn:feature_code":"PPL",
    "gn:name":"Le Teil",
    "gn:population":0,
    "gn:timezone":"Europe/Paris",
    "iso:country":"FR",
    "wof:name":"Le Teil",
    "wof:placetype":"locality"
},
  "geometry": {"coordinates":[1.93565,45.18239000000001],"type":"Point"}
}