{
  "type": "Feature",
  "properties": {
    "gn:admin1_code":"75",
    "gn:admin2_code":"19",
    "gn:admin3_code":"192",
    "gn:admin4_code":"19040",
    "gn:asciiname":"Le Teil",
    "gn:country_code":"FR",
    "gn:dem":485,
    "gn:feature_class":"P",
    "gn:feature_code":"PPL",
    "gn:name":"Le Teil",
    "gn:population":0,
    "gn:timezone":"Europe/Paris",
    "iso:country":"FR",
    "name:bre_x_preferred":[
        "Le Teil"
    ],
    "name:bug_x_preferred":[
        "Le Teil"
    ],
    "name:cat_x_preferred":[
        "Lo Telh"
    ],
    "name:ceb_x_preferred":[
        "Le Teil"
    ],
    "name:deu_x_preferred":[
        "Le Teil"
    ],
    "name:eus_x_preferred":[
        "Le Teil"
    ],
    "name:fra_x_preferred":[
        "Le Teil"
    ],
    "name:hun_x_preferred":[
        "Le Teil"
    ],
    "name:hye_x_preferred":[
        "\u053c\u0568 \u054f\u0565\u0575"
    ],
    "name:ita_x_preferred":[
        "Le Teil"
    ],
    "name:lat_x_preferred":[
        "Le Teil"
    ],
    "name:lmo_x_preferred":[
        "Le Teil"
    ],
    "name:msa_x_preferred":[
        "Le Teil"
    ],
    "name:nld_x_preferred":[
        "Le Teil"
    ],
    "name:oci_x_preferred":[
        "Lo Telh"
    ],
    "name:pam_x_preferred":[
        "Le Teil"
    ],
    "name:pms_x_preferred":[
        "Le Teil"
    ],
    "name:pol_x_preferred":[
        "Le Teil"
    ],
    "name:por_x_preferred":[
        "Le Teil"
    ],
    "name:ron_x_preferred":[
        "Le Teil"
    ],
    "name:rus_x_preferred":[
        "\u041b\u0435-\u0422\u0435\u0439"
    ],
    "name:slk_x_preferred":[
        "Le Teil"
    ],
    "name:spa_x_preferred":[
        "Le Teil"
    ],
    "name:sqi_x_preferred":[
        "Le Teil"
    ],
    "name:swe_x_preferred":[
        "Le Teil"
    ],
    "name:ukr_x_preferred":[
        "\u041b\u0435-\u0422\u0435\u0439"
    ],
    "name:uzb_x_preferred":[
        "Le Teil"
    ],
    "name:vie_x_preferred":[
        "Le Teil"
    ],
    "name:vol_x_preferred":[
        "Le Teil"
    ],
    "name:war_x_preferred":[
        "Le Teil"
    ],
    "name:zho_x_preferred":[
        "\u52d2\u6cf0\u4f0a"
    ],
    "wof:name":"Le Teil",
    "wof:placetype":"locality"
},
  "geometry": {"coordinates":[1.93565,45.18239000000001],"type":"Point"}
}