{
  "type": "Feature",
  "properties": {
    "gn:admin1_code":"84",
    "gn:admin2_code":"01",
    "gn:admin3_code":"011",
    "gn:admin4_code":"01073",
    "gn:asciiname":"Aignoz",
    "gn:cc2":"FR",
    "gn:country_code":"FR",
    "gn:dem":242,
    "gn:feature_class":"P",
    "gn:feature_code":"PPL",
    "gn:name":"Aignoz",
    "gn:population":0,
    "gn:timezone":"Europe/Paris",
    "iso:country":"FR",
    "name:und_x_variant":[
        "Aignot"
    ],
    "wof:name":"Aignoz",
    "wof:placetype":"locality"
},
  "geometry": {"coordinates":[5.74396,45.83167],"type":"Point"}
}