{
  "type": "Feature",
  "properties": {
    "gn:admin1_code":"11",
    "gn:admin2_code":"77",
    "gn:admin3_code":"774",
    "gn:admin4_code":"77088",
    "gn:asciiname":"Bessonville",
    "gn:country_code":"FR",
    "gn:dem":132,
    "gn:feature_class":"P",
    "gn:feature_code":"PPL",
    "gn:name":"Bessonville",
    "gn:population":0,
    "gn:timezone":"Europe/Paris",
    "iso:country":"FR",
    "wof:name":"Bessonville",
    "wof:placetype":"locality"
},
  "geometry": {"coordinates":[2.59649,48.32201],"type":"Point"}
}