{
  "type": "Feature",
  "properties": {
    "gn:admin1_code":"75",
    "gn:admin2_code":"33",
    "gn:admin3_code":"335",
    "gn:admin4_code":"33210",
    "gn:asciiname":"Juillac",
    "gn:country_code":"FR",
    "gn:dem":84,
    "gn:feature_class":"P",
    "gn:feature_code":"PPL",
    "gn:name":"Juillac",
    "gn:population":225,
    "gn:timezone":"Europe/Paris",
    "iso:country":"FR",
    "wof:name":"Juillac",
    "wof:placetype":"locality",
    "wof:population":225
},
  "geometry": {"coordinates":[0.04054,44.81135],"type":"Point"}
}