{
  "type": "Feature",
  "properties": {
    "frgov:code_epci":"243301454",
    "frgov:insee_arr":"5",
    "frgov:insee_com":"33210",
    "frgov:insee_dep":"33",
    "frgov:insee_reg":"75",
    "frgov:nom_com":"Juillac",
    "frgov:nom_com_m":"JUILLAC",
    "frgov:nom_dep":"GIRONDE",
    "frgov:nom_reg":"NOUVELLE-AQUITAINE",
    "frgov:statut":"Commune simple",
    "gn:admin1_code":"75",
    "gn:admin2_code":"33",
    "gn:admin3_code":"335",
    "gn:admin4_code":"33210",
    "gn:asciiname":"Juillac",
    "gn:country_code":"FR",
    "gn:dem":84,
    "gn:feature_class":"P",
    "gn:feature_code":"PPL",
    "gn:name":"Juillac",
    "gn:population":225,
    "gn:timezone":"Europe/Paris",
    "iso:country":"FR",
    "name:cat_x_preferred":[
        "Julhac"
    ],
    "name:ceb_x_preferred":[
        "Juillac"
    ],
    "name:ces_x_preferred":[
        "Juillac"
    ],
    "name:deu_x_preferred":[
        "Juillac"
    ],
    "name:epo_x_preferred":[
        "Juillac"
    ],
    "name:fra_x_preferred":[
        "Juillac"
    ],
    "name:ita_x_preferred":[
        "Juillac"
    ],
    "name:nds_x_preferred":[
        "Juillac"
    ],
    "name:nld_x_preferred":[
        "Juillac"
    ],
    "name:oci_x_preferred":[
        "Julhac"
    ],
    "name:pms_x_preferred":[
        "Juillac"
    ],
    "name:pol_x_preferred":[
        "Juillac"
    ],
    "name:por_x_preferred":[
        "Juillac"
    ],
    "name:rus_x_preferred":[
        "\u0416\u044e\u0439\u0430\u043a"
    ],
    "name:slk_x_preferred":[
        "Juillac"
    ],
    "name:spa_x_preferred":[
        "Juillac"
    ],
    "name:swe_x_preferred":[
        "Juillac"
    ],
    "name:ukr_x_preferred":[
        "\u0416\u0443\u0456\u044f\u043a"
    ],
    "name:ukr_x_variant":[
        "\u0416\u0443\u0456\u044f\u043a"
    ],
    "name:zho_x_preferred":[
        "\u745e\u4f0a\u62c9\u514b"
    ],
    "qs:a0":"France",
    "qs:a1":"GIRONDE",
    "qs:a1_lc":"33",
    "qs:a1r":"AQUITAINE",
    "qs:a1r_lc":"72",
    "qs:a2_lc":"37",
    "qs:a2r_lc":"5",
    "qs:adm0":"France",
    "qs:adm0_a3":"FRA",
    "qs:la":"JUILLAC",
    "qs:la_lc":"33210",
    "qs:level":"localadmin",
    "qs:type":"Commune simple",
    "wof:coterminous":[
        404354697
    ],
    "wof:name":"Juillac",
    "wof:placetype":"locality",
    "wof:placetype_local":"Commune simple",
    "wof:population":225
},
  "geometry": {"coordinates":[0.04054,44.81135],"type":"Point"}
}