{
  "type": "Feature",
  "properties": {
    "gn:admin1_code":"27",
    "gn:admin2_code":"21",
    "gn:admin3_code":"212",
    "gn:admin4_code":"21614.0",
    "gn:asciiname":"Spoy",
    "gn:country_code":"FR",
    "gn:dem":243,
    "gn:feature_class":"P",
    "gn:feature_code":"PPL",
    "gn:name":"Spoy",
    "gn:population":256,
    "gn:timezone":"Europe/Paris",
    "iso:country":"FR",
    "wof:name":"Spoy",
    "wof:placetype":"locality",
    "wof:population":256
},
  "geometry": {"coordinates":[5.18977,47.44505],"type":"Point"}
}