{
  "type": "Feature",
  "properties": {
    "gn:admin1_code":"28",
    "gn:admin2_code":"61",
    "gn:admin3_code":"612",
    "gn:admin4_code":"61221",
    "gn:asciiname":"Landigou",
    "gn:country_code":"FR",
    "gn:dem":253,
    "gn:feature_class":"P",
    "gn:feature_code":"PPL",
    "gn:name":"Landigou",
    "gn:population":446,
    "gn:timezone":"Europe/Paris",
    "iso:country":"FR",
    "wof:name":"Landigou",
    "wof:placetype":"locality",
    "wof:population":446
},
  "geometry": {"coordinates":[-0.47098,48.74578],"type":"Point"}
}