{
  "type": "Feature",
  "properties": {
    "frgov:code_epci":"200035814",
    "frgov:insee_arr":"2",
    "frgov:insee_com":"61221",
    "frgov:insee_dep":"61",
    "frgov:insee_reg":"28",
    "frgov:nom_com":"Landigou",
    "frgov:nom_com_m":"LANDIGOU",
    "frgov:nom_dep":"ORNE",
    "frgov:nom_reg":"NORMANDIE",
    "frgov:statut":"Commune simple",
    "gn:admin1_code":"28",
    "gn:admin2_code":"61",
    "gn:admin3_code":"612",
    "gn:admin4_code":"61221",
    "gn:asciiname":"Landigou",
    "gn:country_code":"FR",
    "gn:dem":253,
    "gn:feature_class":"P",
    "gn:feature_code":"PPL",
    "gn:name":"Landigou",
    "gn:population":446,
    "gn:timezone":"Europe/Paris",
    "iso:country":"FR",
    "name:cat_x_preferred":[
        "Landigou"
    ],
    "name:ceb_x_preferred":[
        "Landigou"
    ],
    "name:deu_x_preferred":[
        "Landigou"
    ],
    "name:eus_x_preferred":[
        "Landigou"
    ],
    "name:fra_x_preferred":[
        "Landigou"
    ],
    "name:hun_x_preferred":[
        "Landigou"
    ],
    "name:ind_x_preferred":[
        "Landigou"
    ],
    "name:ita_x_preferred":[
        "Landigou"
    ],
    "name:kaz_x_preferred":[
        "\u041b\u0430\u043d\u0434\u0438\u0433\u0443"
    ],
    "name:lat_x_preferred":[
        "Landigou"
    ],
    "name:mlg_x_preferred":[
        "Landigou"
    ],
    "name:msa_x_preferred":[
        "Landigou"
    ],
    "name:nld_x_preferred":[
        "Landigou"
    ],
    "name:oci_x_preferred":[
        "Landigou"
    ],
    "name:pms_x_preferred":[
        "Landigou"
    ],
    "name:pol_x_preferred":[
        "Landigou"
    ],
    "name:por_x_preferred":[
        "Landigou"
    ],
    "name:ron_x_preferred":[
        "Landigou"
    ],
    "name:slk_x_preferred":[
        "Landigou"
    ],
    "name:spa_x_preferred":[
        "Landigou"
    ],
    "name:swe_x_preferred":[
        "Landigou"
    ],
    "name:ukr_x_preferred":[
        "\u041b\u0430\u043d\u0434\u0456\u0433\u0443"
    ],
    "name:urd_x_preferred":[
        "\u0644\u0627\u0646\u0688\u06cc\u06af\u0648"
    ],
    "name:uzb_x_preferred":[
        "Landigou"
    ],
    "name:vie_x_preferred":[
        "Landigou"
    ],
    "name:vol_x_preferred":[
        "Landigou"
    ],
    "name:war_x_preferred":[
        "Landigou"
    ],
    "name:zho_x_preferred":[
        "\u6717\u8fea\u53e4"
    ],
    "qs:a0":"France",
    "qs:a1":"ORNE",
    "qs:a1_lc":"61",
    "qs:a1r":"BASSE-NORMANDIE",
    "qs:a1r_lc":"25",
    "qs:a2_lc":"40",
    "qs:a2r_lc":"2",
    "qs:adm0":"France",
    "qs:adm0_a3":"FRA",
    "qs:la":"LANDIGOU",
    "qs:la_lc":"61221",
    "qs:level":"localadmin",
    "qs:type":"Commune simple",
    "wof:coterminous":[
        404426069
    ],
    "wof:name":"Landigou",
    "wof:placetype":"locality",
    "wof:placetype_local":"Commune simple",
    "wof:population":446
},
  "geometry": {"coordinates":[-0.47098,48.74578],"type":"Point"}
}