{
  "type": "Feature",
  "properties": {
    "gn:admin1_code":"28",
    "gn:admin2_code":"76",
    "gn:admin3_code":"763",
    "gn:admin4_code":"76401",
    "gn:asciiname":"Le Fayel",
    "gn:country_code":"FR",
    "gn:dem":28,
    "gn:feature_class":"P",
    "gn:feature_code":"PPL",
    "gn:name":"Le Fayel",
    "gn:population":0,
    "gn:timezone":"Europe/Paris",
    "iso:country":"FR",
    "name:und_x_variant":[
        "Le Fayet",
        "Le Fayel"
    ],
    "wof:name":"Le Fayel",
    "wof:placetype":"locality"
},
  "geometry": {"coordinates":[0.72252,49.50031],"type":"Point"}
}