{
  "type": "Feature",
  "properties": {
    "gn:admin1_code":"76",
    "gn:admin2_code":"12",
    "gn:admin3_code":"121",
    "gn:admin4_code":"12270",
    "gn:asciiname":"Pomairols",
    "gn:country_code":"FR",
    "gn:dem":751,
    "gn:feature_class":"P",
    "gn:feature_code":"PPL",
    "gn:name":"Pomairols",
    "gn:population":0,
    "gn:timezone":"Europe/Paris",
    "iso:country":"FR",
    "wof:name":"Pomairols",
    "wof:placetype":"locality"
},
  "geometry": {"coordinates":[3.02454,44.29348],"type":"Point"}
}