{
  "type": "Feature",
  "properties": {
    "gn:admin1_code":"11",
    "gn:admin2_code":"77",
    "gn:admin3_code":"773",
    "gn:admin4_code":"77026",
    "gn:asciiname":"Bonsac",
    "gn:country_code":"FR",
    "gn:dem":144,
    "gn:feature_class":"P",
    "gn:feature_code":"PPL",
    "gn:name":"Bonsac",
    "gn:population":0,
    "gn:timezone":"Europe/Paris",
    "iso:country":"FR",
    "wof:name":"Bonsac",
    "wof:placetype":"locality"
},
  "geometry": {"coordinates":[3.43195,48.5999],"type":"Point"}
}