{
  "type": "Feature",
  "properties": {
    "gn:admin1_code":"84",
    "gn:admin2_code":"03",
    "gn:admin3_code":"032",
    "gn:admin4_code":"03292",
    "gn:asciiname":"Les Bourses",
    "gn:country_code":"FR",
    "gn:dem":428,
    "gn:feature_class":"P",
    "gn:feature_code":"PPL",
    "gn:name":"Les Bourses",
    "gn:population":0,
    "gn:timezone":"Europe/Paris",
    "iso:country":"FR",
    "wof:name":"Les Bourses",
    "wof:placetype":"locality"
},
  "geometry": {"coordinates":[3.07371,46.40307],"type":"Point"}
}