{
  "type": "Feature",
  "properties": {
    "gn:admin1_code":"84",
    "gn:admin2_code":"74",
    "gn:admin3_code":"741",
    "gn:admin4_code":"74135.0",
    "gn:asciiname":"Bourjal",
    "gn:country_code":"FR",
    "gn:dem":503,
    "gn:feature_class":"P",
    "gn:feature_code":"PPL",
    "gn:name":"Bourjal",
    "gn:population":0,
    "gn:timezone":"Europe/Paris",
    "iso:country":"FR",
    "name:und_x_variant":[
        "Bourgeal",
        "Bourjal"
    ],
    "wof:name":"Bourjal",
    "wof:placetype":"locality"
},
  "geometry": {"coordinates":[6.2522,45.75116],"type":"Point"}
}