{
  "type": "Feature",
  "properties": {
    "gn:admin1_code":"44",
    "gn:admin2_code":"55",
    "gn:admin3_code":"551",
    "gn:admin4_code":"55040",
    "gn:asciiname":"Seraucourt",
    "gn:country_code":"FR",
    "gn:dem":250,
    "gn:feature_class":"P",
    "gn:feature_code":"PPL",
    "gn:name":"Seraucourt",
    "gn:population":0,
    "gn:timezone":"Europe/Paris",
    "iso:country":"FR",
    "wof:name":"Seraucourt",
    "wof:placetype":"locality"
},
  "geometry": {"coordinates":[5.23936,48.96328],"type":"Point"}
}