{
  "type": "Feature",
  "properties": {
    "gn:admin1_code":"27",
    "gn:admin2_code":"89",
    "gn:admin3_code":"891",
    "gn:admin4_code":"89088",
    "gn:asciiname":"Petit Chaumont",
    "gn:country_code":"FR",
    "gn:dem":138,
    "gn:feature_class":"P",
    "gn:feature_code":"PPL",
    "gn:name":"Petit Chaumont",
    "gn:population":0,
    "gn:timezone":"Europe/Paris",
    "iso:country":"FR",
    "name:und_x_variant":[
        "Chaumont",
        "Petit Chaumont"
    ],
    "wof:name":"Petit Chaumont",
    "wof:placetype":"locality"
},
  "geometry": {"coordinates":[3.33367,47.85225],"type":"Point"}
}