{
  "type": "Feature",
  "properties": {
    "gn:admin1_code":"76",
    "gn:admin2_code":"48",
    "gn:admin3_code":"482",
    "gn:admin4_code":"48045",
    "gn:asciiname":"Fouzillac",
    "gn:country_code":"FR",
    "gn:dem":1220,
    "gn:feature_class":"P",
    "gn:feature_code":"PPL",
    "gn:name":"Fouzillac",
    "gn:population":0,
    "gn:timezone":"Europe/Paris",
    "iso:country":"FR",
    "name:und_x_variant":[
        "Fouzilhac",
        "Fouzillac"
    ],
    "wof:name":"Fouzillac",
    "wof:placetype":"locality"
},
  "geometry": {"coordinates":[3.78708,44.66357],"type":"Point"}
}