{
  "type": "Feature",
  "properties": {
    "gn:admin1_code":"24",
    "gn:admin2_code":"36",
    "gn:admin3_code":"364",
    "gn:admin4_code":"36205.0",
    "gn:asciiname":"Pay",
    "gn:country_code":"FR",
    "gn:dem":129,
    "gn:feature_class":"P",
    "gn:feature_code":"PPL",
    "gn:name":"Pay",
    "gn:population":0,
    "gn:timezone":"Europe/Paris",
    "iso:country":"FR",
    "name:ceb_x_preferred":[
        "Pay"
    ],
    "name:deu_x_preferred":[
        "Pay"
    ],
    "name:tgl_x_preferred":[
        "Pay"
    ],
    "name:uzb_x_preferred":[
        "Pay"
    ],
    "wof:name":"Pay",
    "wof:placetype":"locality"
},
  "geometry": {"coordinates":[1.99085,47.10924],"type":"Point"}
}