{
  "type": "Feature",
  "properties": {
    "gn:admin1_code":"24",
    "gn:admin2_code":"18",
    "gn:admin3_code":"183",
    "gn:admin4_code":"18149",
    "gn:asciiname":"Le Bechignol",
    "gn:country_code":"FR",
    "gn:dem":200,
    "gn:feature_class":"P",
    "gn:feature_code":"PPL",
    "gn:name":"Le B\u00e9chignol",
    "gn:population":0,
    "gn:timezone":"Europe/Paris",
    "iso:country":"FR",
    "wof:name":"Le Bechignol",
    "wof:placetype":"locality"
},
  "geometry": {"coordinates":[2.34467,47.29943],"type":"Point"}
}