{
  "type": "Feature",
  "properties": {
    "gn:admin1_code":"93",
    "gn:admin2_code":"06",
    "gn:admin3_code":"062",
    "gn:admin4_code":"06071",
    "gn:asciiname":"Barzes",
    "gn:cc2":"FR",
    "gn:country_code":"FR",
    "gn:dem":1261,
    "gn:feature_class":"P",
    "gn:feature_code":"PPL",
    "gn:name":"Barzes",
    "gn:population":0,
    "gn:timezone":"Europe/Paris",
    "iso:country":"FR",
    "name:und_x_variant":[
        "Les Barz\u00e8s",
        "Barzes"
    ],
    "wof:name":"Barzes",
    "wof:placetype":"locality"
},
  "geometry": {"coordinates":[6.9119,44.07695],"type":"Point"}
}