{
  "type": "Feature",
  "properties": {
    "gn:admin1_code":"75",
    "gn:admin2_code":"24",
    "gn:admin3_code":"243",
    "gn:admin4_code":"24147",
    "gn:asciiname":"La Forge-d'Ans",
    "gn:country_code":"FR",
    "gn:dem":125,
    "gn:feature_class":"P",
    "gn:feature_code":"PPL",
    "gn:name":"La Forge-d\u2019Ans",
    "gn:population":0,
    "gn:timezone":"Europe/Paris",
    "iso:country":"FR",
    "wof:name":"La Forge-d'Ans",
    "wof:placetype":"locality"
},
  "geometry": {"coordinates":[0.98716,45.22799000000001],"type":"Point"}
}