{
  "type": "Feature",
  "properties": {
    "gn:admin1_code":"84",
    "gn:admin2_code":"43",
    "gn:admin3_code":"432",
    "gn:admin4_code":"43010",
    "gn:asciiname":"Bouzols",
    "gn:country_code":"FR",
    "gn:dem":747,
    "gn:feature_class":"P",
    "gn:feature_code":"PPL",
    "gn:name":"Bouzols",
    "gn:population":0,
    "gn:timezone":"Europe/Paris",
    "iso:country":"FR",
    "wof:name":"Bouzols",
    "wof:placetype":"locality"
},
  "geometry": {"coordinates":[3.93633,45.00031],"type":"Point"}
}