{
  "type": "Feature",
  "properties": {
    "gn:admin1_code":"24",
    "gn:admin2_code":"36",
    "gn:admin3_code":"364",
    "gn:admin4_code":"36199",
    "gn:asciiname":"Villiers",
    "gn:country_code":"FR",
    "gn:dem":145,
    "gn:feature_class":"P",
    "gn:feature_code":"PPL",
    "gn:name":"Villiers",
    "gn:population":0,
    "gn:timezone":"Europe/Paris",
    "iso:country":"FR",
    "name:als_x_preferred":[
        "Villiers"
    ],
    "name:bre_x_preferred":[
        "Villiers"
    ],
    "name:ceb_x_preferred":[
        "Villiers"
    ],
    "name:deu_x_preferred":[
        "Villiers"
    ],
    "name:epo_x_preferred":[
        "Villiers"
    ],
    "name:fra_x_preferred":[
        "Villiers"
    ],
    "name:ita_x_preferred":[
        "Villiers"
    ],
    "name:jpn_x_preferred":[
        "\u30f4\u30a3\u30ea\u30a2\u30fc\u30ba"
    ],
    "name:nds_x_preferred":[
        "Villiers"
    ],
    "name:nld_x_preferred":[
        "Villiers"
    ],
    "name:pms_x_preferred":[
        "Villiers"
    ],
    "name:pol_x_preferred":[
        "Villiers"
    ],
    "name:por_x_preferred":[
        "Villiers"
    ],
    "name:ron_x_preferred":[
        "Villiers"
    ],
    "name:rus_x_preferred":[
        "\u0412\u0438\u043b\u044c\u0435"
    ],
    "name:slk_x_preferred":[
        "Villiers"
    ],
    "name:spa_x_preferred":[
        "Villiers"
    ],
    "name:swe_x_preferred":[
        "Villiers"
    ],
    "name:ukr_x_preferred":[
        "\u0412\u0456\u043b\u044c\u0454"
    ],
    "wof:name":"Villiers",
    "wof:placetype":"locality"
},
  "geometry": {"coordinates":[2.00525,46.99123],"type":"Point"}
}