{
  "type": "Feature",
  "properties": {
    "frgov:code_epci":"200034049",
    "frgov:insee_arr":"1",
    "frgov:insee_com":"81233",
    "frgov:insee_dep":"81",
    "frgov:insee_reg":"76",
    "frgov:nom_com":"Roum\u00e9goux",
    "frgov:nom_com_m":"ROUMEGOUX",
    "frgov:nom_dep":"TARN",
    "frgov:nom_reg":"OCCITANIE",
    "frgov:statut":"Commune simple",
    "gn:admin1_code":"76",
    "gn:admin2_code":"81",
    "gn:admin3_code":"811",
    "gn:admin4_code":"81233",
    "gn:asciiname":"Roumegoux",
    "gn:country_code":"FR",
    "gn:dem":335,
    "gn:feature_class":"P",
    "gn:feature_code":"PPL",
    "gn:name":"Roum\u00e9goux",
    "gn:population":194,
    "gn:timezone":"Europe/Paris",
    "iso:country":"FR",
    "name:fra_x_preferred":[
        "Roum\u00e9goux"
    ],
    "name:und_x_variant":[
        "Roum\u00e9goux"
    ],
    "qs:a0":"France",
    "qs:a1":"TARN",
    "qs:a1_lc":"81",
    "qs:a1r":"MIDI-PYRENEES",
    "qs:a1r_lc":"73",
    "qs:a2_lc":"26",
    "qs:a2r_lc":"1",
    "qs:adm0":"France",
    "qs:adm0_a3":"FRA",
    "qs:la":"ROUMEGOUX",
    "qs:la_lc":"81233",
    "qs:level":"localadmin",
    "qs:type":"Commune simple",
    "wof:coterminous":[
        404391041
    ],
    "wof:name":"Roumegoux",
    "wof:placetype":"locality",
    "wof:placetype_local":"Commune simple",
    "wof:population":194
},
  "geometry": {"coordinates":[2.26172,43.80387],"type":"Point"}
}