{
  "type": "Feature",
  "properties": {
    "gn:admin1_code":"76",
    "gn:admin2_code":"81",
    "gn:admin3_code":"811",
    "gn:admin4_code":"81233",
    "gn:asciiname":"Roumegoux",
    "gn:country_code":"FR",
    "gn:dem":335,
    "gn:feature_class":"P",
    "gn:feature_code":"PPL",
    "gn:name":"Roum\u00e9goux",
    "gn:population":194,
    "gn:timezone":"Europe/Paris",
    "iso:country":"FR",
    "name:und_x_variant":[
        "Roum\u00e9goux"
    ],
    "wof:name":"Roumegoux",
    "wof:placetype":"locality",
    "wof:population":194
},
  "geometry": {"coordinates":[2.26172,43.80387],"type":"Point"}
}