{
  "type": "Feature",
  "properties": {
    "gn:admin1_code":"84",
    "gn:admin2_code":"43",
    "gn:admin3_code":"431",
    "gn:admin4_code":"43256",
    "gn:asciiname":"Sauzet",
    "gn:country_code":"FR",
    "gn:dem":1124,
    "gn:feature_class":"P",
    "gn:feature_code":"PPL",
    "gn:name":"Sauzet",
    "gn:population":0,
    "gn:timezone":"Europe/Paris",
    "iso:country":"FR",
    "name:ceb_x_preferred":[
        "Sauzet"
    ],
    "name:deu_x_preferred":[
        "Sauzet"
    ],
    "name:fra_x_preferred":[
        "Sauzet"
    ],
    "name:ita_x_preferred":[
        "Sauzet"
    ],
    "name:lmo_x_preferred":[
        "Sauzet"
    ],
    "name:nds_x_preferred":[
        "Sauzet"
    ],
    "name:nld_x_preferred":[
        "Sauzet"
    ],
    "name:oci_x_preferred":[
        "Sauset"
    ],
    "name:pms_x_preferred":[
        "Sauzet"
    ],
    "name:pol_x_preferred":[
        "Sauzet"
    ],
    "name:por_x_preferred":[
        "Sauzet"
    ],
    "name:rus_x_preferred":[
        "\u0421\u043e\u0437\u0435"
    ],
    "name:slk_x_preferred":[
        "Sauzet"
    ],
    "name:spa_x_preferred":[
        "Sauzet"
    ],
    "name:swe_x_preferred":[
        "Sauzet"
    ],
    "name:ukr_x_preferred":[
        "\u0421\u043e\u0437\u0435"
    ],
    "wof:name":"Sauzet",
    "wof:placetype":"locality"
},
  "geometry": {"coordinates":[3.45944,44.98715],"type":"Point"}
}