{
  "type": "Feature",
  "properties": {
    "gn:admin1_code":"84",
    "gn:admin2_code":"43",
    "gn:admin3_code":"431",
    "gn:admin4_code":"43256",
    "gn:asciiname":"Sauzet",
    "gn:country_code":"FR",
    "gn:dem":1124,
    "gn:feature_class":"P",
    "gn:feature_code":"PPL",
    "gn:name":"Sauzet",
    "gn:population":0,
    "gn:timezone":"Europe/Paris",
    "iso:country":"FR",
    "wof:name":"Sauzet",
    "wof:placetype":"locality"
},
  "geometry": {"coordinates":[3.45944,44.98715],"type":"Point"}
}