{
  "type": "Feature",
  "properties": {
    "iso:country":"FR",
    "name:eng_x_preferred":[
        "Plateau-Mont-Valerien"
    ],
    "name:fra_x_preferred":[
        "Plateau- Mont-Val\u00e9rien"
    ],
    "wof:name":"Plateau-Mont-Valerien",
    "wof:placetype":"neighbourhood"
},
  "geometry": {"coordinates":[2.20833614090982,48.88151015068547],"type":"Point"}
}