{
  "type": "Feature",
  "properties": {
    "gn:admin1_code":"24",
    "gn:admin2_code":"36",
    "gn:admin3_code":"363",
    "gn:admin4_code":"36143",
    "gn:asciiname":"Beaupin",
    "gn:country_code":"FR",
    "gn:dem":185,
    "gn:feature_class":"P",
    "gn:feature_code":"PPL",
    "gn:name":"Beaupin",
    "gn:population":0,
    "gn:timezone":"Europe/Paris",
    "iso:country":"FR",
    "wof:name":"Beaupin",
    "wof:placetype":"locality"
},
  "geometry": {"coordinates":[1.93896,46.63619],"type":"Point"}
}