{
  "type": "Feature",
  "properties": {
    "gn:admin1_code":"84",
    "gn:admin2_code":"01",
    "gn:admin3_code":"011",
    "gn:admin4_code":"1414.0",
    "gn:asciiname":"Fitignieu",
    "gn:country_code":"FR",
    "gn:dem":554,
    "gn:feature_class":"P",
    "gn:feature_code":"PPL",
    "gn:name":"Fitignieu",
    "gn:population":0,
    "gn:timezone":"Europe/Paris",
    "iso:country":"FR",
    "wof:name":"Fitignieu",
    "wof:placetype":"locality"
},
  "geometry": {"coordinates":[5.66483,45.92781],"type":"Point"}
}