{
  "type": "Feature",
  "properties": {
    "gn:admin1_code":"11",
    "gn:admin2_code":"78",
    "gn:admin3_code":"784",
    "gn:admin4_code":"78423.0",
    "gn:asciiname":"Le Manet",
    "gn:country_code":"FR",
    "gn:dem":169,
    "gn:feature_class":"P",
    "gn:feature_code":"PPL",
    "gn:name":"Le Manet",
    "gn:population":0,
    "gn:timezone":"Europe/Paris",
    "iso:country":"FR",
    "wof:name":"Le Manet",
    "wof:placetype":"locality"
},
  "geometry": {"coordinates":[2.01667,48.76667],"type":"Point"}
}