{
  "type": "Feature",
  "properties": {
    "gn:admin1_code":"27",
    "gn:admin2_code":"58",
    "gn:admin3_code":"583",
    "gn:admin4_code":"58223",
    "gn:asciiname":"Le Tailly",
    "gn:country_code":"FR",
    "gn:dem":280,
    "gn:feature_class":"P",
    "gn:feature_code":"PPL",
    "gn:name":"Le Tailly",
    "gn:population":0,
    "gn:timezone":"Europe/Paris",
    "iso:country":"FR",
    "name:und_x_variant":[
        "Le Taillis",
        "Le Tailly"
    ],
    "wof:name":"Le Tailly",
    "wof:placetype":"locality"
},
  "geometry": {"coordinates":[3.52914,47.04518],"type":"Point"}
}