{
  "type": "Feature",
  "properties": {
    "gn:admin1_code":"75",
    "gn:admin2_code":"24",
    "gn:admin3_code":"244",
    "gn:admin4_code":"24341",
    "gn:asciiname":"Temniac",
    "gn:country_code":"FR",
    "gn:dem":176,
    "gn:feature_class":"P",
    "gn:feature_code":"PPL",
    "gn:name":"Temniac",
    "gn:population":0,
    "gn:timezone":"Europe/Paris",
    "iso:country":"FR",
    "wof:name":"Temniac",
    "wof:placetype":"locality"
},
  "geometry": {"coordinates":[1.23333,44.91667],"type":"Point"}
}