{
  "type": "Feature",
  "properties": {
    "gn:admin1_code":"84",
    "gn:admin2_code":"43",
    "gn:admin3_code":"432",
    "gn:admin4_code":"43071",
    "gn:asciiname":"Arzon",
    "gn:country_code":"FR",
    "gn:dem":704,
    "gn:feature_class":"P",
    "gn:feature_code":"PPL",
    "gn:name":"Arzon",
    "gn:population":0,
    "gn:timezone":"Europe/Paris",
    "iso:country":"FR",
    "name:als_x_preferred":[
        "Arzon"
    ],
    "name:bre_x_preferred":[
        "Arzhon-Rewiz"
    ],
    "name:cat_x_preferred":[
        "Arzon"
    ],
    "name:ceb_x_preferred":[
        "Arzon"
    ],
    "name:cym_x_preferred":[
        "Arzhon-Rewiz"
    ],
    "name:deu_x_preferred":[
        "Arzon"
    ],
    "name:eus_x_preferred":[
        "Arzon"
    ],
    "name:fra_x_preferred":[
        "Arzon"
    ],
    "name:glg_x_preferred":[
        "Arzon"
    ],
    "name:hun_x_preferred":[
        "Arzon"
    ],
    "name:ita_x_preferred":[
        "Arzon"
    ],
    "name:jpn_x_preferred":[
        "\u30a2\u30eb\u30be\u30f3"
    ],
    "name:kaz_x_preferred":[
        "\u0410\u0440\u0437\u043e\u043d"
    ],
    "name:lat_x_preferred":[
        "Arzo"
    ],
    "name:msa_x_preferred":[
        "Arzon"
    ],
    "name:nld_x_preferred":[
        "Arzon"
    ],
    "name:oci_x_preferred":[
        "Arzhon-Rewiz"
    ],
    "name:pms_x_preferred":[
        "Arzon"
    ],
    "name:pol_x_preferred":[
        "Arzon"
    ],
    "name:por_x_preferred":[
        "Arzon"
    ],
    "name:ron_x_preferred":[
        "Arzon"
    ],
    "name:rus_x_preferred":[
        "\u0410\u0440\u0437\u043e\u043d"
    ],
    "name:slk_x_preferred":[
        "Arzon"
    ],
    "name:spa_x_preferred":[
        "Arzon"
    ],
    "name:sqi_x_preferred":[
        "Arzon"
    ],
    "name:srp_x_preferred":[
        "\u0410\u0440\u0437\u043e\u043d"
    ],
    "name:swe_x_preferred":[
        "Arzon"
    ],
    "name:ukr_x_preferred":[
        "\u0410\u0440\u0437\u043e\u043d"
    ],
    "name:uzb_x_preferred":[
        "Arzon"
    ],
    "name:vie_x_preferred":[
        "Arzon"
    ],
    "name:vol_x_preferred":[
        "Arzon"
    ],
    "name:war_x_preferred":[
        "Arzon"
    ],
    "name:zho_x_preferred":[
        "\u963f\u5c14\u5b97"
    ],
    "wof:name":"Arzon",
    "wof:placetype":"locality"
},
  "geometry": {"coordinates":[3.85556,45.23597],"type":"Point"}
}