{
  "type": "Feature",
  "properties": {
    "gn:admin1_code":"84",
    "gn:admin2_code":"43",
    "gn:admin3_code":"432",
    "gn:admin4_code":"43071",
    "gn:asciiname":"Arzon",
    "gn:country_code":"FR",
    "gn:dem":704,
    "gn:feature_class":"P",
    "gn:feature_code":"PPL",
    "gn:name":"Arzon",
    "gn:population":0,
    "gn:timezone":"Europe/Paris",
    "iso:country":"FR",
    "wof:name":"Arzon",
    "wof:placetype":"locality"
},
  "geometry": {"coordinates":[3.85556,45.23597],"type":"Point"}
}