{
  "type": "Feature",
  "properties": {
    "gn:admin1_code":"53",
    "gn:admin2_code":"29",
    "gn:admin3_code":"293",
    "gn:admin4_code":"29202",
    "gn:asciiname":"Guirhoen",
    "gn:country_code":"FR",
    "gn:dem":254,
    "gn:feature_class":"P",
    "gn:feature_code":"PPL",
    "gn:name":"Guirho\u00ebn",
    "gn:population":0,
    "gn:timezone":"Europe/Paris",
    "iso:country":"FR",
    "wof:name":"Guirhoen",
    "wof:placetype":"locality"
},
  "geometry": {"coordinates":[-3.88142,48.43833],"type":"Point"}
}