{
  "type": "Feature",
  "properties": {
    "gn:admin1_code":"93",
    "gn:admin2_code":"13",
    "gn:admin3_code":"132",
    "gn:admin4_code":"13058",
    "gn:asciiname":"Les Flechons",
    "gn:country_code":"FR",
    "gn:dem":101,
    "gn:feature_class":"P",
    "gn:feature_code":"PPL",
    "gn:name":"Les Fl\u00e9chons",
    "gn:population":0,
    "gn:timezone":"Europe/Paris",
    "iso:country":"FR",
    "wof:name":"Les Flechons",
    "wof:placetype":"locality"
},
  "geometry": {"coordinates":[4.86988,43.71988],"type":"Point"}
}