{
  "type": "Feature",
  "properties": {
    "gn:admin1_code":"84",
    "gn:admin2_code":"38",
    "gn:admin3_code":"381",
    "gn:admin4_code":"38446",
    "gn:asciiname":"Les Arragons",
    "gn:country_code":"FR",
    "gn:dem":998,
    "gn:feature_class":"P",
    "gn:feature_code":"PPL",
    "gn:name":"Les Arragons",
    "gn:population":0,
    "gn:timezone":"Europe/Paris",
    "iso:country":"FR",
    "wof:name":"Les Arragons",
    "wof:placetype":"locality"
},
  "geometry": {"coordinates":[5.84374,45.38227],"type":"Point"}
}