{
  "type": "Feature",
  "properties": {
    "gn:admin1_code":"93",
    "gn:admin2_code":"04",
    "gn:admin3_code":"041",
    "gn:admin4_code":"04120",
    "gn:asciiname":"Fontvive",
    "gn:country_code":"FR",
    "gn:dem":1986,
    "gn:feature_class":"P",
    "gn:feature_code":"PPL",
    "gn:name":"Fontvive",
    "gn:population":0,
    "gn:timezone":"Europe/Paris",
    "iso:country":"FR",
    "wof:name":"Fontvive",
    "wof:placetype":"locality"
},
  "geometry": {"coordinates":[6.81667,44.48333],"type":"Point"}
}