{
  "type": "Feature",
  "properties": {
    "gn:admin1_code":"53",
    "gn:admin2_code":"29",
    "gn:admin3_code":"294",
    "gn:admin4_code":"29220",
    "gn:asciiname":"Bringal",
    "gn:country_code":"FR",
    "gn:dem":24,
    "gn:feature_class":"P",
    "gn:feature_code":"PPL",
    "gn:name":"Bringal",
    "gn:population":0,
    "gn:timezone":"Europe/Paris",
    "iso:country":"FR",
    "wof:name":"Bringal",
    "wof:placetype":"locality"
},
  "geometry": {"coordinates":[-4.22141,47.88327],"type":"Point"}
}