{
  "type": "Feature",
  "properties": {
    "gn:admin1_code":"75",
    "gn:admin2_code":"79",
    "gn:admin3_code":"792",
    "gn:admin4_code":"79137",
    "gn:asciiname":"Gript",
    "gn:country_code":"FR",
    "gn:dem":34,
    "gn:feature_class":"P",
    "gn:feature_code":"PPL",
    "gn:name":"Gript",
    "gn:population":0,
    "gn:timezone":"Europe/Paris",
    "iso:country":"FR",
    "wof:name":"Gript",
    "wof:placetype":"locality"
},
  "geometry": {"coordinates":[-0.46941,46.2143],"type":"Point"}
}