{
  "type": "Feature",
  "properties": {
    "gn:admin1_code":"44",
    "gn:admin2_code":"57",
    "gn:admin3_code":"572",
    "gn:admin4_code":"57490",
    "gn:asciiname":"Salival",
    "gn:country_code":"FR",
    "gn:dem":200,
    "gn:feature_class":"P",
    "gn:feature_code":"PPL",
    "gn:name":"Salival",
    "gn:population":0,
    "gn:timezone":"Europe/Paris",
    "iso:country":"FR",
    "name:deu_x_preferred":[
        "Salival"
    ],
    "name:fin_x_preferred":[
        "Salival"
    ],
    "name:fra_x_preferred":[
        "Salival"
    ],
    "name:glg_x_preferred":[
        "Salival"
    ],
    "name:ita_x_preferred":[
        "Salival"
    ],
    "name:nld_x_preferred":[
        "Salival"
    ],
    "name:pol_x_preferred":[
        "Salival"
    ],
    "name:por_x_preferred":[
        "Salival"
    ],
    "name:spa_x_preferred":[
        "Salival"
    ],
    "name:swe_x_preferred":[
        "Salival"
    ],
    "wof:name":"Salival",
    "wof:placetype":"locality"
},
  "geometry": {"coordinates":[6.56667,48.78333],"type":"Point"}
}