{
  "type": "Feature",
  "properties": {
    "gn:admin1_code":"24",
    "gn:admin2_code":"28",
    "gn:admin3_code":"284",
    "gn:admin4_code":"28378.0",
    "gn:asciiname":"Les Herissieres",
    "gn:country_code":"FR",
    "gn:dem":191,
    "gn:feature_class":"P",
    "gn:feature_code":"PPL",
    "gn:name":"Les H\u00e9rissi\u00e8res",
    "gn:population":0,
    "gn:timezone":"Europe/Paris",
    "iso:country":"FR",
    "wof:name":"Les Herissieres",
    "wof:placetype":"locality"
},
  "geometry": {"coordinates":[0.82142,48.27561],"type":"Point"}
}