{
  "type": "Feature",
  "properties": {
    "iso:country":"FR",
    "name:eng_x_preferred":[
        "Pasteur"
    ],
    "name:fra_x_preferred":[
        "Pasteur"
    ],
    "wof:name":"Pasteur",
    "wof:placetype":"neighbourhood"
},
  "geometry": {"coordinates":[7.2828658676646,43.72268554342436],"type":"Point"}
}