{
  "type": "Feature",
  "properties": {
    "gn:admin1_code":"27",
    "gn:admin2_code":"70",
    "gn:admin3_code":"701",
    "gn:admin4_code":"70031",
    "gn:asciiname":"Etroitefontaine",
    "gn:country_code":"FR",
    "gn:dem":283,
    "gn:feature_class":"P",
    "gn:feature_code":"PPL",
    "gn:name":"\u00c9troitefontaine",
    "gn:population":0,
    "gn:timezone":"Europe/Paris",
    "iso:country":"FR",
    "name:und_x_variant":[
        "\u00c9troitefontaine"
    ],
    "wof:name":"Etroitefontaine",
    "wof:placetype":"locality"
},
  "geometry": {"coordinates":[6.49618,47.5791],"type":"Point"}
}