{
  "type": "Feature",
  "properties": {
    "gn:admin1_code":"75",
    "gn:admin2_code":"87",
    "gn:admin3_code":"871",
    "gn:admin4_code":"87089",
    "gn:asciiname":"Les Grandes Forges",
    "gn:country_code":"FR",
    "gn:dem":301,
    "gn:feature_class":"P",
    "gn:feature_code":"PPL",
    "gn:name":"Les Grandes Forges",
    "gn:population":0,
    "gn:timezone":"Europe/Paris",
    "iso:country":"FR",
    "wof:name":"Les Grandes Forges",
    "wof:placetype":"locality"
},
  "geometry": {"coordinates":[1.22171,46.24467],"type":"Point"}
}