{
  "type": "Feature",
  "properties": {
    "gn:gn_country":"FR",
    "gn:gn_fcode":"PPL",
    "gn:gn_pop":295,
    "gn:population":295,
    "iso:country":"FR",
    "name:unk_x_variant":[
        "Sancourt"
    ],
    "qs_pg:aaroncc":"FR",
    "qs_pg:gn_country":"FR",
    "qs_pg:gn_fcode":"PPL",
    "qs_pg:gn_pop":295,
    "qs_pg:name":"Missancourt",
    "qs_pg:name_adm0":"France",
    "qs_pg:name_adm1":"Picardie",
    "qs_pg:photos_9r":0,
    "qs_pg:photos_sr":0,
    "qs_pg:pop_sr":2,
    "qs_pg:qs_pg_placetype":"locality",
    "qs_pg:qs_pg_placetype_gp":"Town",
    "qs_pg:woe_adm0":23424819,
    "woe:adm0_id":23424819,
    "woe:name_adm0":"France",
    "woe:name_adm1":"Picardie",
    "woe:placetype":"Town",
    "wof:name":"Missancourt",
    "wof:placetype":"neighbourhood",
    "wof:population":295
},
  "geometry": {"coordinates":[3.03826,49.77355],"type":"Point"}
}