{
  "type": "Feature",
  "properties": {
    "gn:admin1_code":"75",
    "gn:admin2_code":"79",
    "gn:admin3_code":"791",
    "gn:admin4_code":"79123",
    "gn:asciiname":"Montigny",
    "gn:country_code":"FR",
    "gn:dem":177,
    "gn:feature_class":"P",
    "gn:feature_code":"PPL",
    "gn:name":"Montigny",
    "gn:population":0,
    "gn:timezone":"Europe/Paris",
    "iso:country":"FR",
    "name:bre_x_preferred":[
        "Montigny"
    ],
    "name:cat_x_preferred":[
        "Montigny"
    ],
    "name:ceb_x_preferred":[
        "Montigny"
    ],
    "name:ces_x_preferred":[
        "Montigny"
    ],
    "name:deu_x_preferred":[
        "Montigny"
    ],
    "name:epo_x_preferred":[
        "Montigny"
    ],
    "name:fas_x_preferred":[
        "\u0645\u0648\u0646\u062a\u06cc\u0646\u06cc\u0647"
    ],
    "name:fra_x_preferred":[
        "Montigny"
    ],
    "name:hun_x_preferred":[
        "Montigny"
    ],
    "name:ita_x_preferred":[
        "Montigny"
    ],
    "name:jpn_x_preferred":[
        "\u30e2\u30f3\u30c6\u30a3\u30cb\u30fc"
    ],
    "name:nds_x_preferred":[
        "Montigny"
    ],
    "name:nld_x_preferred":[
        "Montigny"
    ],
    "name:oci_x_preferred":[
        "Montigny"
    ],
    "name:pms_x_preferred":[
        "Montigny"
    ],
    "name:pol_x_preferred":[
        "Montigny"
    ],
    "name:por_x_preferred":[
        "Montigny"
    ],
    "name:rus_x_preferred":[
        "\u041c\u043e\u043d\u0442\u0438\u043d\u044c\u0438"
    ],
    "name:sco_x_preferred":[
        "Montigny"
    ],
    "name:slk_x_preferred":[
        "Montigny"
    ],
    "name:spa_x_preferred":[
        "Montigny"
    ],
    "name:swe_x_preferred":[
        "Montigny"
    ],
    "name:ukr_x_preferred":[
        "\u041c\u043e\u043d\u0442\u0456\u043d\u044c\u0457"
    ],
    "wof:name":"Montigny",
    "wof:placetype":"locality"
},
  "geometry": {"coordinates":[-0.64238,46.7981],"type":"Point"}
}