{
  "type": "Feature",
  "properties": {
    "gn:admin1_code":"75",
    "gn:admin2_code":"79",
    "gn:admin3_code":"791",
    "gn:admin4_code":"79123",
    "gn:asciiname":"Montigny",
    "gn:country_code":"FR",
    "gn:dem":177,
    "gn:feature_class":"P",
    "gn:feature_code":"PPL",
    "gn:name":"Montigny",
    "gn:population":0,
    "gn:timezone":"Europe/Paris",
    "iso:country":"FR",
    "wof:name":"Montigny",
    "wof:placetype":"locality"
},
  "geometry": {"coordinates":[-0.64238,46.7981],"type":"Point"}
}