{
  "type": "Feature",
  "properties": {
    "gn:admin1_code":"84",
    "gn:admin2_code":"73",
    "gn:admin3_code":"732",
    "gn:admin4_code":"73210",
    "gn:asciiname":"Marle",
    "gn:country_code":"FR",
    "gn:dem":691,
    "gn:feature_class":"P",
    "gn:feature_code":"PPL",
    "gn:name":"Marle",
    "gn:population":0,
    "gn:timezone":"Europe/Paris",
    "iso:country":"FR",
    "name:und_x_variant":[
        "Marlieu",
        "Marles",
        "Marle"
    ],
    "wof:name":"Marle",
    "wof:placetype":"locality"
},
  "geometry": {"coordinates":[6.02277,45.57318],"type":"Point"}
}