{
  "type": "Feature",
  "properties": {
    "gn:admin1_code":"84",
    "gn:admin2_code":"43",
    "gn:admin3_code":"431",
    "gn:admin4_code":"43131",
    "gn:asciiname":"La Brequeille",
    "gn:country_code":"FR",
    "gn:dem":645,
    "gn:feature_class":"P",
    "gn:feature_code":"PPL",
    "gn:name":"La Brequeille",
    "gn:population":0,
    "gn:timezone":"Europe/Paris",
    "iso:country":"FR",
    "name:und_x_variant":[
        "La Br\u00e9queuille",
        "La Brequeille"
    ],
    "wof:name":"La Brequeille",
    "wof:placetype":"locality"
},
  "geometry": {"coordinates":[3.5685,45.17676],"type":"Point"}
}