{
  "type": "Feature",
  "properties": {
    "gn:admin1_code":"76",
    "gn:admin2_code":"66",
    "gn:admin3_code":"661",
    "gn:admin4_code":"66106",
    "gn:asciiname":"la Selva",
    "gn:country_code":"FR",
    "gn:dem":591,
    "gn:feature_class":"P",
    "gn:feature_code":"PPL",
    "gn:name":"la Selva",
    "gn:population":0,
    "gn:timezone":"Europe/Paris",
    "iso:country":"FR",
    "name:cat_x_preferred":[
        "la Selva"
    ],
    "name:ceb_x_preferred":[
        "La Selva"
    ],
    "name:deu_x_preferred":[
        "La Selva"
    ],
    "name:fra_x_preferred":[
        "la Selva"
    ],
    "name:srp_x_preferred":[
        "La Selva"
    ],
    "name:swe_x_preferred":[
        "La Selva"
    ],
    "wof:name":"la Selva",
    "wof:placetype":"locality"
},
  "geometry": {"coordinates":[2.78057,42.44208],"type":"Point"}
}