{
  "type": "Feature",
  "properties": {
    "gn:admin1_code":"84",
    "gn:admin2_code":"43",
    "gn:admin3_code":"433",
    "gn:admin4_code":"43199",
    "gn:asciiname":"Les Moulins",
    "gn:country_code":"FR",
    "gn:dem":970,
    "gn:feature_class":"P",
    "gn:feature_code":"PPL",
    "gn:name":"Les Moulins",
    "gn:population":0,
    "gn:timezone":"Europe/Paris",
    "iso:country":"FR",
    "name:bre_x_preferred":[
        "Plezeved"
    ],
    "name:deu_x_preferred":[
        "Pl\u00e9met"
    ],
    "name:fra_x_preferred":[
        "Pl\u00e9met"
    ],
    "name:ita_x_preferred":[
        "Les Moulins"
    ],
    "name:pol_x_preferred":[
        "Les Moulins"
    ],
    "name:spa_x_preferred":[
        "Pl\u00e9met"
    ],
    "wof:name":"Les Moulins",
    "wof:placetype":"locality"
},
  "geometry": {"coordinates":[4.2228,45.10397],"type":"Point"}
}