{
  "type": "Feature",
  "properties": {
    "gn:admin1_code":"84",
    "gn:admin2_code":"42",
    "gn:admin3_code":"421",
    "gn:admin4_code":"42318",
    "gn:asciiname":"Fresse Rival",
    "gn:country_code":"FR",
    "gn:dem":848,
    "gn:feature_class":"P",
    "gn:feature_code":"PPL",
    "gn:name":"Fresse Rival",
    "gn:population":0,
    "gn:timezone":"Europe/Paris",
    "iso:country":"FR",
    "wof:name":"Fresse Rival",
    "wof:placetype":"locality"
},
  "geometry": {"coordinates":[3.90126,45.38746],"type":"Point"}
}