{
  "type": "Feature",
  "properties": {
    "gn:admin1_code":"93",
    "gn:admin2_code":"06",
    "gn:admin3_code":"062",
    "gn:admin4_code":"06149",
    "gn:asciiname":"Laghet",
    "gn:country_code":"FR",
    "gn:dem":389,
    "gn:feature_class":"P",
    "gn:feature_code":"PPL",
    "gn:name":"Laghet",
    "gn:population":0,
    "gn:timezone":"Europe/Paris",
    "iso:country":"FR",
    "wof:name":"Laghet",
    "wof:placetype":"locality"
},
  "geometry": {"coordinates":[7.38535,43.75198],"type":"Point"}
}