{
  "type": "Feature",
  "properties": {
    "gn:admin1_code":"84",
    "gn:admin2_code":"03",
    "gn:admin3_code":"031",
    "gn:admin4_code":"03077",
    "gn:asciiname":"Chamboirat",
    "gn:country_code":"FR",
    "gn:dem":461,
    "gn:feature_class":"P",
    "gn:feature_code":"PPL",
    "gn:name":"Chamboirat",
    "gn:population":0,
    "gn:timezone":"Europe/Paris",
    "iso:country":"FR",
    "wof:name":"Chamboirat",
    "wof:placetype":"locality"
},
  "geometry": {"coordinates":[3.0109,46.23195],"type":"Point"}
}