{
  "type": "Feature",
  "properties": {
    "gn:admin1_code":"84",
    "gn:admin2_code":"43",
    "gn:admin3_code":"431",
    "gn:admin4_code":"43106",
    "gn:asciiname":"Chastenuel",
    "gn:country_code":"FR",
    "gn:dem":1037,
    "gn:feature_class":"P",
    "gn:feature_code":"PPL",
    "gn:name":"Chastenuel",
    "gn:population":0,
    "gn:timezone":"Europe/Paris",
    "iso:country":"FR",
    "name:und_x_variant":[
        "Chastanuel",
        "Chastannel",
        "Chastenuel"
    ],
    "wof:name":"Chastenuel",
    "wof:placetype":"locality"
},
  "geometry": {"coordinates":[3.63106,45.1577],"type":"Point"}
}