{
  "type": "Feature",
  "properties": {
    "gn:admin1_code":"52",
    "gn:admin2_code":"44",
    "gn:admin3_code":"442",
    "gn:admin4_code":"44217",
    "gn:asciiname":"La Roche",
    "gn:country_code":"FR",
    "gn:dem":70,
    "gn:feature_class":"P",
    "gn:feature_code":"PPL",
    "gn:name":"La Roche",
    "gn:population":0,
    "gn:timezone":"Europe/Paris",
    "iso:country":"FR",
    "wof:name":"La Roche",
    "wof:placetype":"locality"
},
  "geometry": {"coordinates":[-1.7244,47.30059],"type":"Point"}
}