{
  "type": "Feature",
  "properties": {
    "gn:admin1_code":"24",
    "gn:admin2_code":"28",
    "gn:admin3_code":"281",
    "gn:admin4_code":"28344",
    "gn:asciiname":"Goimpy",
    "gn:country_code":"FR",
    "gn:dem":154,
    "gn:feature_class":"P",
    "gn:feature_code":"PPL",
    "gn:name":"Goimpy",
    "gn:population":0,
    "gn:timezone":"Europe/Paris",
    "iso:country":"FR",
    "wof:name":"Goimpy",
    "wof:placetype":"locality"
},
  "geometry": {"coordinates":[1.75276,48.42183],"type":"Point"}
}