{
  "type": "Feature",
  "properties": {
    "iso:country":"FR",
    "wof:name":"Saint-Menet",
    "wof:placetype":"neighbourhood"
},
  "geometry": {"coordinates":[5.5021594827891,43.29017150399233],"type":"Point"}
}