{
  "type": "Feature",
  "properties": {
    "gn:admin1_code":"84",
    "gn:admin2_code":"15",
    "gn:admin3_code":"152",
    "gn:admin4_code":"15046",
    "gn:asciiname":"Cussac",
    "gn:country_code":"FR",
    "gn:dem":623,
    "gn:feature_class":"P",
    "gn:feature_code":"PPL",
    "gn:name":"Cussac",
    "gn:population":0,
    "gn:timezone":"Europe/Paris",
    "iso:country":"FR",
    "name:ceb_x_preferred":[
        "Cussac"
    ],
    "name:deu_x_preferred":[
        "Cussac"
    ],
    "name:fra_x_preferred":[
        "Cussac"
    ],
    "name:hun_x_preferred":[
        "Cussac"
    ],
    "name:ita_x_preferred":[
        "Cussac"
    ],
    "name:nds_x_preferred":[
        "Cussac"
    ],
    "name:nld_x_preferred":[
        "Cussac"
    ],
    "name:pms_x_preferred":[
        "Cussac"
    ],
    "name:pol_x_preferred":[
        "Cussac"
    ],
    "name:rus_x_preferred":[
        "\u041a\u044e\u0441\u0441\u0430\u043a"
    ],
    "name:slk_x_preferred":[
        "Cussac"
    ],
    "name:spa_x_preferred":[
        "Cussac"
    ],
    "name:srp_x_preferred":[
        "\u041a\u0438\u0441\u0430\u043a"
    ],
    "name:swe_x_preferred":[
        "Cussac"
    ],
    "name:ukr_x_preferred":[
        "\u041a\u044e\u0441\u0441\u0430\u043a"
    ],
    "wof:name":"Cussac",
    "wof:placetype":"locality"
},
  "geometry": {"coordinates":[2.26667,45.18333],"type":"Point"}
}