{
  "type": "Feature",
  "properties": {
    "gn:admin1_code":"52",
    "gn:admin2_code":"85",
    "gn:admin3_code":"852",
    "gn:admin4_code":"85109",
    "gn:asciiname":"Petit-Bourg-des-Herbiers",
    "gn:country_code":"FR",
    "gn:dem":106,
    "gn:feature_class":"P",
    "gn:feature_code":"PPL",
    "gn:name":"Petit-Bourg-des-Herbiers",
    "gn:population":0,
    "gn:timezone":"Europe/Paris",
    "iso:country":"FR",
    "name:und_x_variant":[
        "Petit Bourg",
        "Petit-Bourg-des-Herbiers"
    ],
    "wof:name":"Petit-Bourg-des-Herbiers",
    "wof:placetype":"locality"
},
  "geometry": {"coordinates":[-1.00274,46.87036],"type":"Point"}
}