{
  "type": "Feature",
  "properties": {
    "gn:admin1_code":"53",
    "gn:admin2_code":"29",
    "gn:admin3_code":"292",
    "gn:admin4_code":"29302",
    "gn:asciiname":"Kerhuel",
    "gn:country_code":"FR",
    "gn:dem":121,
    "gn:feature_class":"P",
    "gn:feature_code":"PPL",
    "gn:name":"Kerhuel",
    "gn:population":0,
    "gn:timezone":"Europe/Paris",
    "iso:country":"FR",
    "name:und_x_variant":[
        "Kerhaul",
        "Kerhuel"
    ],
    "wof:name":"Kerhuel",
    "wof:placetype":"locality"
},
  "geometry": {"coordinates":[-4.13067,48.27501],"type":"Point"}
}