{
  "type": "Feature",
  "properties": {
    "gn:admin1_code":"28",
    "gn:admin2_code":"76",
    "gn:admin3_code":"762",
    "gn:admin4_code":"76715",
    "gn:asciiname":"Le Mesnil au Coffe",
    "gn:country_code":"FR",
    "gn:dem":150,
    "gn:feature_class":"P",
    "gn:feature_code":"PPL",
    "gn:name":"Le Mesnil au Coffe",
    "gn:population":0,
    "gn:timezone":"Europe/Paris",
    "iso:country":"FR",
    "name:und_x_variant":[
        "Le Mesnil",
        "Le Mesnil au Coffe"
    ],
    "wof:name":"Le Mesnil au Coffe",
    "wof:placetype":"locality"
},
  "geometry": {"coordinates":[0.62001,49.59307],"type":"Point"}
}