{
  "type": "Feature",
  "properties": {
    "gn:admin1_code":"84",
    "gn:admin2_code":"43",
    "gn:admin3_code":"433",
    "gn:admin4_code":"43137",
    "gn:asciiname":"Antonianes",
    "gn:country_code":"FR",
    "gn:dem":602,
    "gn:feature_class":"P",
    "gn:feature_code":"PPL",
    "gn:name":"Antonianes",
    "gn:population":0,
    "gn:timezone":"Europe/Paris",
    "iso:country":"FR",
    "wof:name":"Antonianes",
    "wof:placetype":"locality"
},
  "geometry": {"coordinates":[4.19331,45.31662],"type":"Point"}
}