{
  "type": "Feature",
  "properties": {
    "gn:admin1_code":"84",
    "gn:admin2_code":"63",
    "gn:admin3_code":"632",
    "gn:admin4_code":"63163",
    "gn:asciiname":"La Narse",
    "gn:country_code":"FR",
    "gn:dem":862,
    "gn:feature_class":"P",
    "gn:feature_code":"PPL",
    "gn:name":"La Narse",
    "gn:population":0,
    "gn:timezone":"Europe/Paris",
    "iso:country":"FR",
    "wof:name":"La Narse",
    "wof:placetype":"locality"
},
  "geometry": {"coordinates":[2.74059,45.76699],"type":"Point"}
}