{
  "type": "Feature",
  "properties": {
    "gn:admin1_code":"28",
    "gn:admin2_code":"76",
    "gn:admin3_code":"763",
    "gn:admin4_code":"76727",
    "gn:asciiname":"La Neuville",
    "gn:country_code":"FR",
    "gn:dem":12,
    "gn:feature_class":"P",
    "gn:feature_code":"PPLL",
    "gn:name":"La Neuville",
    "gn:population":0,
    "gn:timezone":"Europe/Paris",
    "iso:country":"FR",
    "wof:name":"La Neuville",
    "wof:placetype":"locality"
},
  "geometry": {"coordinates":[0.67817,49.47563],"type":"Point"}
}