{
  "type": "Feature",
  "properties": {
    "gn:admin1_code":"94",
    "gn:admin2_code":"2A",
    "gn:admin3_code":"2A1",
    "gn:admin4_code":"2A345",
    "gn:asciiname":"Calzatoja",
    "gn:country_code":"FR",
    "gn:dem":245,
    "gn:feature_class":"P",
    "gn:feature_code":"PPL",
    "gn:name":"Calzatoja",
    "gn:population":0,
    "gn:timezone":"Europe/Paris",
    "iso:country":"FR",
    "wof:name":"Calzatoja",
    "wof:placetype":"locality"
},
  "geometry": {"coordinates":[8.93333,42.05],"type":"Point"}
}