{
  "type": "Feature",
  "properties": {
    "gn:admin1_code":"53",
    "gn:admin2_code":"35",
    "gn:admin3_code":"352",
    "gn:admin4_code":"35106",
    "gn:asciiname":"Le Crope",
    "gn:country_code":"FR",
    "gn:dem":73,
    "gn:feature_class":"P",
    "gn:feature_code":"PPL",
    "gn:name":"Le Crop\u00e9",
    "gn:population":0,
    "gn:timezone":"Europe/Paris",
    "iso:country":"FR",
    "name:und_x_variant":[
        "Crope",
        "Croppee",
        "Le Crop\u00e9"
    ],
    "wof:name":"Le Crope",
    "wof:placetype":"locality"
},
  "geometry": {"coordinates":[-1.57562,47.81048],"type":"Point"}
}