{
  "type": "Feature",
  "properties": {
    "gn:admin1_code":"53",
    "gn:admin2_code":"56",
    "gn:admin3_code":"561",
    "gn:admin4_code":"56094",
    "gn:asciiname":"Le Bonhomme",
    "gn:country_code":"FR",
    "gn:dem":26,
    "gn:feature_class":"P",
    "gn:feature_code":"PPLL",
    "gn:name":"Le Bonhomme",
    "gn:population":0,
    "gn:timezone":"Europe/Paris",
    "iso:country":"FR",
    "name:als_x_preferred":[
        "Le Bonhomme"
    ],
    "name:bug_x_preferred":[
        "Le Bonhomme"
    ],
    "name:cat_x_preferred":[
        "Le Bonhomme"
    ],
    "name:ceb_x_preferred":[
        "Le Bonhomme"
    ],
    "name:ces_x_preferred":[
        "Le Bonhomme"
    ],
    "name:deu_x_preferred":[
        "Le Bonhomme"
    ],
    "name:eus_x_preferred":[
        "Le Bonhomme"
    ],
    "name:fra_x_preferred":[
        "Le Bonhomme"
    ],
    "name:hun_x_preferred":[
        "Le Bonhomme"
    ],
    "name:ita_x_preferred":[
        "Le Bonhomme"
    ],
    "name:kaz_x_preferred":[
        "\u041b\u0435-\u0411\u043e\u043d\u043e\u043c\u043c"
    ],
    "name:lat_x_preferred":[
        "Le Bonhomme"
    ],
    "name:ltz_x_preferred":[
        "Le Bonhomme"
    ],
    "name:msa_x_preferred":[
        "Le Bonhomme"
    ],
    "name:nld_x_preferred":[
        "Le Bonhomme"
    ],
    "name:oci_x_preferred":[
        "Le Bonhomme"
    ],
    "name:pfl_x_preferred":[
        "Le Bonhomme"
    ],
    "name:pms_x_preferred":[
        "Le Bonhomme"
    ],
    "name:pol_x_preferred":[
        "Le Bonhomme"
    ],
    "name:por_x_preferred":[
        "Bonhomme"
    ],
    "name:ron_x_preferred":[
        "Le Bonhomme"
    ],
    "name:rus_x_preferred":[
        "\u041b\u0435-\u0411\u043e\u043d\u043e\u043c"
    ],
    "name:slk_x_preferred":[
        "Le Bonhomme"
    ],
    "name:spa_x_preferred":[
        "Le Bonhomme"
    ],
    "name:swe_x_preferred":[
        "Le Bonhomme"
    ],
    "name:ukr_x_preferred":[
        "\u041b\u0435-\u0411\u043e\u043d\u043e\u043c\u043c"
    ],
    "name:uzb_x_preferred":[
        "Le Bonhomme"
    ],
    "name:vie_x_preferred":[
        "Le Bonhomme"
    ],
    "name:vol_x_preferred":[
        "Le Bonhomme"
    ],
    "name:war_x_preferred":[
        "Le Bonhomme"
    ],
    "name:zho_x_preferred":[
        "\u52d2\u535a\u8bfa\u59c6"
    ],
    "wof:name":"Le Bonhomme",
    "wof:placetype":"locality"
},
  "geometry": {"coordinates":[-3.29714,47.76557],"type":"Point"}
}