{
  "type": "Feature",
  "properties": {
    "gn:admin1_code":"52",
    "gn:admin2_code":"44",
    "gn:admin3_code":"443",
    "gn:admin4_code":"44129",
    "gn:asciiname":"Saint-Guillaume",
    "gn:country_code":"FR",
    "gn:dem":13,
    "gn:feature_class":"P",
    "gn:feature_code":"PPL",
    "gn:name":"Saint-Guillaume",
    "gn:population":0,
    "gn:timezone":"Europe/Paris",
    "iso:country":"FR",
    "name:cat_x_preferred":[
        "Sant Guilhaume"
    ],
    "name:ceb_x_preferred":[
        "Saint-Guillaume"
    ],
    "name:deu_x_preferred":[
        "Saint-Guillaume"
    ],
    "name:eus_x_preferred":[
        "Saint-Guillaume"
    ],
    "name:fas_x_preferred":[
        "\u0633\u0646-\u06af\u06cc\u0648\u0645"
    ],
    "name:fra_x_preferred":[
        "Saint-Guillaume"
    ],
    "name:hun_x_preferred":[
        "Saint-Guillaume"
    ],
    "name:ita_x_preferred":[
        "Saint-Guillaume"
    ],
    "name:lat_x_preferred":[
        "Saint-Guillaume"
    ],
    "name:mlg_x_preferred":[
        "Saint-Guillaume"
    ],
    "name:msa_x_preferred":[
        "Saint-Guillaume"
    ],
    "name:nld_x_preferred":[
        "Saint-Guillaume"
    ],
    "name:oci_x_preferred":[
        "Saint-Guillaume"
    ],
    "name:pol_x_preferred":[
        "Saint-Guillaume"
    ],
    "name:por_x_preferred":[
        "Saint-Guillaume"
    ],
    "name:ron_x_preferred":[
        "Saint-Guillaume"
    ],
    "name:rus_x_preferred":[
        "\u0421\u0435\u043d-\u0413\u0438\u0439\u043e\u043c"
    ],
    "name:slk_x_preferred":[
        "Saint-Guillaume"
    ],
    "name:spa_x_preferred":[
        "Saint-Guillaume"
    ],
    "name:swe_x_preferred":[
        "Saint-Guillaume"
    ],
    "name:ukr_x_preferred":[
        "\u0421\u0435\u043d-\u0413\u0456\u0439\u043e\u043c"
    ],
    "name:urd_x_preferred":[
        "\u0633\u06cc\u0646\u0679-\u06af\u06cc\u0644\u0648\u0645\u06d2"
    ],
    "name:uzb_x_preferred":[
        "Saint-Guillaume"
    ],
    "name:vie_x_preferred":[
        "Saint-Guillaume"
    ],
    "name:vol_x_preferred":[
        "Saint-Guillaume"
    ],
    "name:war_x_preferred":[
        "Saint-Guillaume"
    ],
    "name:zho_x_preferred":[
        "\u5723\u5409\u6d1b\u59c6"
    ],
    "wof:name":"Saint-Guillaume",
    "wof:placetype":"locality"
},
  "geometry": {"coordinates":[-2.1194,47.42202],"type":"Point"}
}