{
  "type": "Feature",
  "properties": {
    "gn:admin1_code":"52",
    "gn:admin2_code":"44",
    "gn:admin3_code":"443",
    "gn:admin4_code":"44129",
    "gn:asciiname":"Saint-Guillaume",
    "gn:country_code":"FR",
    "gn:dem":13,
    "gn:feature_class":"P",
    "gn:feature_code":"PPL",
    "gn:name":"Saint-Guillaume",
    "gn:population":0,
    "gn:timezone":"Europe/Paris",
    "iso:country":"FR",
    "wof:name":"Saint-Guillaume",
    "wof:placetype":"locality"
},
  "geometry": {"coordinates":[-2.1194,47.42202],"type":"Point"}
}