{
  "type": "Feature",
  "properties": {
    "gn:admin1_code":"28",
    "gn:admin2_code":"76",
    "gn:admin3_code":"763",
    "gn:admin4_code":"76675",
    "gn:asciiname":"Le Grand-Hamel",
    "gn:country_code":"FR",
    "gn:dem":176,
    "gn:feature_class":"P",
    "gn:feature_code":"PPL",
    "gn:name":"Le Grand-Hamel",
    "gn:population":0,
    "gn:timezone":"Europe/Paris",
    "iso:country":"FR",
    "wof:name":"Le Grand-Hamel",
    "wof:placetype":"locality"
},
  "geometry": {"coordinates":[1.02998,49.60527],"type":"Point"}
}