{
  "type": "Feature",
  "properties": {
    "iso:country":"FR",
    "name:eng_x_preferred":[
        "Plateau d'Avron"
    ],
    "name:fra_x_preferred":[
        "Plateau d'Avron"
    ],
    "wof:name":"Plateau d'Avron",
    "wof:placetype":"neighbourhood"
},
  "geometry": {"coordinates":[2.51077490700958,48.87212953117236],"type":"Point"}
}