{
  "type": "Feature",
  "properties": {
    "iso:country":"FR",
    "name:eng_x_preferred":[
        "Pervenches-Val Content"
    ],
    "name:fra_x_preferred":[
        "Pervenches-Val Content"
    ],
    "wof:name":"Pervenches-Val Content",
    "wof:placetype":"neighbourhood"
},
  "geometry": {"coordinates":[2.27950412257995,48.79224696287606],"type":"Point"}
}