{
  "type": "Feature",
  "properties": {
    "frgov:code_epci":"200072635",
    "frgov:insee_arr":"2",
    "frgov:insee_com":"31335",
    "frgov:insee_dep":"31",
    "frgov:insee_reg":"76",
    "frgov:nom_com":"Mayr\u00e8gne",
    "frgov:nom_com_m":"MAYREGNE",
    "frgov:nom_dep":"HAUTE-GARONNE",
    "frgov:nom_reg":"OCCITANIE",
    "frgov:statut":"Commune simple",
    "gn:admin1_code":"76",
    "gn:admin2_code":"31",
    "gn:admin3_code":"312",
    "gn:admin4_code":"31335",
    "gn:asciiname":"Mayregne",
    "gn:country_code":"FR",
    "gn:dem":1207,
    "gn:feature_class":"P",
    "gn:feature_code":"PPL",
    "gn:name":"Mayr\u00e8gne",
    "gn:population":0,
    "gn:timezone":"Europe/Paris",
    "iso:country":"FR",
    "name:fra_x_preferred":[
        "Mayr\u00e8gne"
    ],
    "name:und_x_variant":[
        "Mayr\u00e8gne"
    ],
    "qs:a0":"France",
    "qs:a1":"HAUTE-GARONNE",
    "qs:a1_lc":"31",
    "qs:a1r":"MIDI-PYRENEES",
    "qs:a1r_lc":"73",
    "qs:a2_lc":"04",
    "qs:a2r_lc":"2",
    "qs:adm0":"France",
    "qs:adm0_a3":"FRA",
    "qs:la":"MAYREGNE",
    "qs:la_lc":"31335",
    "qs:level":"localadmin",
    "qs:type":"Commune simple",
    "wof:coterminous":[
        404410843
    ],
    "wof:name":"Mayregne",
    "wof:placetype":"locality",
    "wof:placetype_local":"Commune simple"
},
  "geometry": {"coordinates":[0.53991,42.84376],"type":"Point"}
}