{
  "type": "Feature",
  "properties": {
    "gn:admin1_code":"76",
    "gn:admin2_code":"31",
    "gn:admin3_code":"312",
    "gn:admin4_code":"31335",
    "gn:asciiname":"Mayregne",
    "gn:country_code":"FR",
    "gn:dem":1207,
    "gn:feature_class":"P",
    "gn:feature_code":"PPL",
    "gn:name":"Mayr\u00e8gne",
    "gn:population":0,
    "gn:timezone":"Europe/Paris",
    "iso:country":"FR",
    "name:und_x_variant":[
        "Mayr\u00e8gne"
    ],
    "wof:name":"Mayregne",
    "wof:placetype":"locality"
},
  "geometry": {"coordinates":[0.53991,42.84376],"type":"Point"}
}