{
  "type": "Feature",
  "properties": {
    "gn:country":"FR",
    "gn:fcode":"PPL",
    "gn:population":158,
    "iso:country":"FR",
    "name:und_x_variant":[
        "Saint-Bazile"
    ],
    "qs_pg:aaroncc":"FR",
    "qs_pg:gn_country":"FR",
    "qs_pg:gn_fcode":"PPL",
    "qs_pg:gn_pop":158,
    "qs_pg:name":"St.-Bazile-de-la-Roche",
    "qs_pg:name_adm0":"France",
    "qs_pg:name_adm1":"Limousin",
    "qs_pg:photos_9r":0,
    "qs_pg:photos_sr":0,
    "qs_pg:pop_sr":1,
    "qs_pg:qs_pg_placetype":"locality",
    "qs_pg:qs_pg_placetype_gp":"Town",
    "qs_pg:woe_adm0":23424819,
    "woe:adm0_id":23424819,
    "woe:name_adm0":"France",
    "woe:name_adm1":"Limousin",
    "woe:placetype":"Town",
    "wof:name":"St.-Bazile-de-la-Roche",
    "wof:placetype":"neighbourhood",
    "wof:population":158
},
  "geometry": {"coordinates":[1.95359,45.15135],"type":"Point"}
}