{
  "type": "Feature",
  "properties": {
    "gn:admin1_code":"84",
    "gn:admin2_code":"63",
    "gn:admin3_code":"631",
    "gn:admin4_code":"63139",
    "gn:asciiname":"Collanges",
    "gn:country_code":"FR",
    "gn:dem":620,
    "gn:feature_class":"P",
    "gn:feature_code":"PPL",
    "gn:name":"Collanges",
    "gn:population":0,
    "gn:timezone":"Europe/Paris",
    "iso:country":"FR",
    "name:cat_x_preferred":[
        "Colanjas"
    ],
    "name:ceb_x_preferred":[
        "Collanges"
    ],
    "name:deu_x_preferred":[
        "Collanges"
    ],
    "name:eus_x_preferred":[
        "Collanges"
    ],
    "name:fra_x_preferred":[
        "Collanges"
    ],
    "name:hun_x_preferred":[
        "Collanges"
    ],
    "name:ita_x_preferred":[
        "Collanges"
    ],
    "name:kaz_x_preferred":[
        "\u041a\u043e\u043b\u043b\u0430\u043d\u0436"
    ],
    "name:lat_x_preferred":[
        "Collanges"
    ],
    "name:mlg_x_preferred":[
        "Collanges"
    ],
    "name:msa_x_preferred":[
        "Collanges"
    ],
    "name:nld_x_preferred":[
        "Collanges"
    ],
    "name:oci_x_preferred":[
        "Colanjas"
    ],
    "name:pms_x_preferred":[
        "Collanges"
    ],
    "name:pol_x_preferred":[
        "Collanges"
    ],
    "name:por_x_preferred":[
        "Collanges"
    ],
    "name:ron_x_preferred":[
        "Collanges"
    ],
    "name:slk_x_preferred":[
        "Collanges"
    ],
    "name:spa_x_preferred":[
        "Collanges"
    ],
    "name:srp_x_preferred":[
        "\u041a\u043e\u043b\u0430\u043d\u0436"
    ],
    "name:swe_x_preferred":[
        "Collanges"
    ],
    "name:ukr_x_preferred":[
        "\u041a\u043e\u043b\u043b\u0430\u043d\u0436"
    ],
    "name:uzb_x_preferred":[
        "Collanges"
    ],
    "name:vie_x_preferred":[
        "Collanges"
    ],
    "name:vol_x_preferred":[
        "Collanges"
    ],
    "name:war_x_preferred":[
        "Collanges"
    ],
    "name:zho_x_preferred":[
        "\u79d1\u6717\u70ed"
    ],
    "wof:name":"Collanges",
    "wof:placetype":"locality"
},
  "geometry": {"coordinates":[3.77089,45.40201],"type":"Point"}
}