{
  "type": "Feature",
  "properties": {
    "gn:admin1_code":"84",
    "gn:admin2_code":"63",
    "gn:admin3_code":"631",
    "gn:admin4_code":"63139",
    "gn:asciiname":"Collanges",
    "gn:country_code":"FR",
    "gn:dem":620,
    "gn:feature_class":"P",
    "gn:feature_code":"PPL",
    "gn:name":"Collanges",
    "gn:population":0,
    "gn:timezone":"Europe/Paris",
    "iso:country":"FR",
    "wof:name":"Collanges",
    "wof:placetype":"locality"
},
  "geometry": {"coordinates":[3.77089,45.40201],"type":"Point"}
}