{
  "type": "Feature",
  "properties": {
    "gn:admin1_code":"84",
    "gn:admin2_code":"73",
    "gn:admin3_code":"732",
    "gn:admin4_code":"73084",
    "gn:asciiname":"Tormery",
    "gn:country_code":"FR",
    "gn:dem":351,
    "gn:feature_class":"P",
    "gn:feature_code":"PPL",
    "gn:name":"Torm\u00e9ry",
    "gn:population":0,
    "gn:timezone":"Europe/Paris",
    "iso:country":"FR",
    "name:und_x_variant":[
        "Torm\u00e9ry"
    ],
    "wof:name":"Tormery",
    "wof:placetype":"locality"
},
  "geometry": {"coordinates":[6.01809,45.51626],"type":"Point"}
}