{
  "type": "Feature",
  "properties": {
    "gn:admin1_code":"27",
    "gn:admin2_code":"89",
    "gn:admin3_code":"892",
    "gn:admin4_code":"89336",
    "gn:asciiname":"Auxon",
    "gn:country_code":"FR",
    "gn:dem":367,
    "gn:feature_class":"P",
    "gn:feature_code":"PPL",
    "gn:name":"Auxon",
    "gn:population":0,
    "gn:timezone":"Europe/Paris",
    "iso:country":"FR",
    "wof:name":"Auxon",
    "wof:placetype":"locality"
},
  "geometry": {"coordinates":[3.97107,47.41643],"type":"Point"}
}