{
  "type": "Feature",
  "properties": {
    "gn:admin1_code":"27",
    "gn:admin2_code":"89",
    "gn:admin3_code":"892",
    "gn:admin4_code":"89336",
    "gn:asciiname":"Auxon",
    "gn:country_code":"FR",
    "gn:dem":367,
    "gn:feature_class":"P",
    "gn:feature_code":"PPL",
    "gn:name":"Auxon",
    "gn:population":0,
    "gn:timezone":"Europe/Paris",
    "iso:country":"FR",
    "name:cat_x_preferred":[
        "Auxon"
    ],
    "name:ceb_x_preferred":[
        "Auxon"
    ],
    "name:ces_x_preferred":[
        "Auxon"
    ],
    "name:deu_x_preferred":[
        "Auxon"
    ],
    "name:fra_x_preferred":[
        "Auxon"
    ],
    "name:ita_x_preferred":[
        "Auxon"
    ],
    "name:nds_x_preferred":[
        "Auxon"
    ],
    "name:nld_x_preferred":[
        "Auxon"
    ],
    "name:pms_x_preferred":[
        "Auxon"
    ],
    "name:pol_x_preferred":[
        "Auxon"
    ],
    "name:por_x_preferred":[
        "Auxon"
    ],
    "name:rus_x_preferred":[
        "\u041e\u0441\u043e\u043d"
    ],
    "name:scn_x_preferred":[
        "Auxon"
    ],
    "name:slk_x_preferred":[
        "Auxon"
    ],
    "name:spa_x_preferred":[
        "Auxon"
    ],
    "name:swe_x_preferred":[
        "Auxon"
    ],
    "name:ukr_x_preferred":[
        "\u041e\u043a\u0441\u043e\u043d"
    ],
    "wof:name":"Auxon",
    "wof:placetype":"locality"
},
  "geometry": {"coordinates":[3.97107,47.41643],"type":"Point"}
}