{
  "type": "Feature",
  "properties": {
    "gn:admin1_code":"52",
    "gn:admin2_code":"44",
    "gn:admin3_code":"441",
    "gn:admin4_code":"44036",
    "gn:asciiname":"La Ville Marie",
    "gn:country_code":"FR",
    "gn:dem":70,
    "gn:feature_class":"P",
    "gn:feature_code":"PPL",
    "gn:name":"La Ville Marie",
    "gn:population":0,
    "gn:timezone":"Europe/Paris",
    "iso:country":"FR",
    "wof:name":"La Ville Marie",
    "wof:placetype":"locality"
},
  "geometry": {"coordinates":[-1.38744,47.72996],"type":"Point"}
}