{
  "type": "Feature",
  "properties": {
    "gn:admin1_code":"52",
    "gn:admin2_code":"44",
    "gn:admin3_code":"442",
    "gn:admin4_code":"44101",
    "gn:asciiname":"La Montagne",
    "gn:country_code":"FR",
    "gn:dem":31,
    "gn:feature_class":"P",
    "gn:feature_code":"PPL",
    "gn:name":"La Montagne",
    "gn:population":6012,
    "gn:timezone":"Europe/Paris",
    "iso:country":"FR",
    "name:bre_x_preferred":[
        "Ar Menez"
    ],
    "name:fra_x_preferred":[
        "La Montagne"
    ],
    "wof:name":"La Montagne",
    "wof:placetype":"locality",
    "wof:population":6012
},
  "geometry": {"coordinates":[-1.68272,47.18651],"type":"Point"}
}