{
  "type": "Feature",
  "properties": {
    "gn:admin1_code":"84",
    "gn:admin2_code":"26",
    "gn:admin3_code":"263",
    "gn:admin4_code":"26143",
    "gn:asciiname":"Saint-Julien",
    "gn:country_code":"FR",
    "gn:dem":427,
    "gn:feature_class":"P",
    "gn:feature_code":"PPL",
    "gn:name":"Saint-Julien",
    "gn:population":0,
    "gn:timezone":"Europe/Paris",
    "iso:country":"FR",
    "name:bre_x_preferred":[
        "Saint-Julien"
    ],
    "name:ceb_x_preferred":[
        "Saint-Julien"
    ],
    "name:ces_x_preferred":[
        "Saint-Julien"
    ],
    "name:deu_x_preferred":[
        "Saint-Julien"
    ],
    "name:fra_x_preferred":[
        "Saint-Julien"
    ],
    "name:ita_x_preferred":[
        "Saint-Julien"
    ],
    "name:jpn_x_preferred":[
        "\u30b5\u30f3\uff1d\u30b8\u30e5\u30ea\u30a2\u30f3"
    ],
    "name:lmo_x_preferred":[
        "Saint-Julien"
    ],
    "name:nds_x_preferred":[
        "Saint-Julien"
    ],
    "name:nld_x_preferred":[
        "Saint-Julien"
    ],
    "name:oci_x_preferred":[
        "Saint-Julien"
    ],
    "name:pms_x_preferred":[
        "Saint-Julien"
    ],
    "name:pol_x_preferred":[
        "Saint-Julien"
    ],
    "name:por_x_preferred":[
        "Saint-Julien"
    ],
    "name:rus_x_preferred":[
        "\u0421\u0435\u043d-\u0416\u044e\u043b\u044c\u0435\u043d"
    ],
    "name:slk_x_preferred":[
        "Saint-Julien"
    ],
    "name:spa_x_preferred":[
        "Saint-Julien"
    ],
    "name:swe_x_preferred":[
        "Saint-Julien"
    ],
    "name:ukr_x_preferred":[
        "\u0421\u0435\u043d-\u0416\u0443\u043b\u044c\u0454\u043d"
    ],
    "wof:name":"Saint-Julien",
    "wof:placetype":"locality"
},
  "geometry": {"coordinates":[5.09591,45.22764],"type":"Point"}
}