{
  "type": "Feature",
  "properties": {
    "gn:admin1_code":"84",
    "gn:admin2_code":"26",
    "gn:admin3_code":"263",
    "gn:admin4_code":"26143",
    "gn:asciiname":"Saint-Julien",
    "gn:country_code":"FR",
    "gn:dem":427,
    "gn:feature_class":"P",
    "gn:feature_code":"PPL",
    "gn:name":"Saint-Julien",
    "gn:population":0,
    "gn:timezone":"Europe/Paris",
    "iso:country":"FR",
    "wof:name":"Saint-Julien",
    "wof:placetype":"locality"
},
  "geometry": {"coordinates":[5.09591,45.22764],"type":"Point"}
}