{
  "type": "Feature",
  "properties": {
    "gn:admin1_code":"75",
    "gn:admin2_code":"64",
    "gn:admin3_code":"642",
    "gn:admin4_code":"64403",
    "gn:asciiname":"Montfort",
    "gn:country_code":"FR",
    "gn:dem":129,
    "gn:feature_class":"P",
    "gn:feature_code":"PPL",
    "gn:name":"Montfort",
    "gn:population":191,
    "gn:timezone":"Europe/Paris",
    "iso:country":"FR",
    "wof:name":"Montfort",
    "wof:placetype":"locality",
    "wof:population":191
},
  "geometry": {"coordinates":[-0.84725,43.36824],"type":"Point"}
}