{
  "type": "Feature",
  "properties": {
    "gn:admin1_code":"84",
    "gn:admin2_code":"26",
    "gn:admin3_code":"263",
    "gn:admin4_code":"26298",
    "gn:asciiname":"Charaix",
    "gn:country_code":"FR",
    "gn:dem":450,
    "gn:feature_class":"P",
    "gn:feature_code":"PPL",
    "gn:name":"Charaix",
    "gn:population":0,
    "gn:timezone":"Europe/Paris",
    "iso:country":"FR",
    "wof:name":"Charaix",
    "wof:placetype":"locality"
},
  "geometry": {"coordinates":[5.04845,45.21749000000001],"type":"Point"}
}