{
  "type": "Feature",
  "properties": {
    "gn:admin1_code":"24",
    "gn:admin2_code":"28",
    "gn:admin3_code":"281",
    "gn:admin4_code":"28021",
    "gn:asciiname":"Hauville",
    "gn:country_code":"FR",
    "gn:dem":170,
    "gn:feature_class":"P",
    "gn:feature_code":"PPL",
    "gn:name":"Hauville",
    "gn:population":0,
    "gn:timezone":"Europe/Paris",
    "iso:country":"FR",
    "name:bug_x_preferred":[
        "Hauville"
    ],
    "name:cat_x_preferred":[
        "Hauville"
    ],
    "name:ceb_x_preferred":[
        "Hauville"
    ],
    "name:deu_x_preferred":[
        "Hauville"
    ],
    "name:eus_x_preferred":[
        "Hauville"
    ],
    "name:fra_x_preferred":[
        "Hauville"
    ],
    "name:hun_x_preferred":[
        "Hauville"
    ],
    "name:ind_x_preferred":[
        "Hauville"
    ],
    "name:ita_x_preferred":[
        "Hauville"
    ],
    "name:kaz_x_preferred":[
        "\u041e\u0432\u0438\u043b\u044c"
    ],
    "name:lat_x_preferred":[
        "Alta Villa"
    ],
    "name:msa_x_preferred":[
        "Hauville"
    ],
    "name:nld_x_preferred":[
        "Hauville"
    ],
    "name:oci_x_preferred":[
        "Hauville"
    ],
    "name:pms_x_preferred":[
        "Hauville"
    ],
    "name:pol_x_preferred":[
        "Hauville"
    ],
    "name:por_x_preferred":[
        "Hauville"
    ],
    "name:ron_x_preferred":[
        "Hauville"
    ],
    "name:slk_x_preferred":[
        "Hauville"
    ],
    "name:spa_x_preferred":[
        "Hauville"
    ],
    "name:srp_x_preferred":[
        "\u041e\u0432\u0438\u043b"
    ],
    "name:swe_x_preferred":[
        "Hauville"
    ],
    "name:ukr_x_preferred":[
        "\u041e\u0432\u0456\u043b\u044c"
    ],
    "name:vie_x_preferred":[
        "Hauville"
    ],
    "name:vol_x_preferred":[
        "Hauville"
    ],
    "name:war_x_preferred":[
        "Hauville"
    ],
    "wof:name":"Hauville",
    "wof:placetype":"locality"
},
  "geometry": {"coordinates":[1.34411,48.36865],"type":"Point"}
}