{
  "type": "Feature",
  "properties": {
    "gn:admin1_code":"24",
    "gn:admin2_code":"28",
    "gn:admin3_code":"281",
    "gn:admin4_code":"28021",
    "gn:asciiname":"Hauville",
    "gn:country_code":"FR",
    "gn:dem":170,
    "gn:feature_class":"P",
    "gn:feature_code":"PPL",
    "gn:name":"Hauville",
    "gn:population":0,
    "gn:timezone":"Europe/Paris",
    "iso:country":"FR",
    "wof:name":"Hauville",
    "wof:placetype":"locality"
},
  "geometry": {"coordinates":[1.34411,48.36865],"type":"Point"}
}