{
  "type": "Feature",
  "properties": {
    "gn:admin1_code":"28",
    "gn:admin2_code":"76",
    "gn:admin3_code":"761",
    "gn:admin4_code":"76321",
    "gn:asciiname":"Orival",
    "gn:country_code":"FR",
    "gn:dem":161,
    "gn:feature_class":"P",
    "gn:feature_code":"PPL",
    "gn:name":"Orival",
    "gn:population":0,
    "gn:timezone":"Europe/Paris",
    "iso:country":"FR",
    "wof:name":"Orival",
    "wof:placetype":"locality"
},
  "geometry": {"coordinates":[1.21777,49.79441],"type":"Point"}
}