{
  "type": "Feature",
  "properties": {
    "gn:admin1_code":"53",
    "gn:admin2_code":"22",
    "gn:admin3_code":"221",
    "gn:admin4_code":"22208",
    "gn:asciiname":"Lantran",
    "gn:country_code":"FR",
    "gn:dem":108,
    "gn:feature_class":"P",
    "gn:feature_code":"PPL",
    "gn:name":"Lantran",
    "gn:population":0,
    "gn:timezone":"Europe/Paris",
    "iso:country":"FR",
    "wof:name":"Lantran",
    "wof:placetype":"locality"
},
  "geometry": {"coordinates":[-1.96694,48.31267],"type":"Point"}
}