{
  "type": "Feature",
  "properties": {
    "gn:admin1_code":"24",
    "gn:admin2_code":"36",
    "gn:admin3_code":"362",
    "gn:admin4_code":"36231.0",
    "gn:asciiname":"La Madrolle",
    "gn:country_code":"FR",
    "gn:dem":150,
    "gn:feature_class":"P",
    "gn:feature_code":"PPL",
    "gn:name":"La Madrolle",
    "gn:population":0,
    "gn:timezone":"Europe/Paris",
    "iso:country":"FR",
    "name:und_x_variant":[
        "Madrolle",
        "La Madrolle"
    ],
    "wof:name":"La Madrolle",
    "wof:placetype":"locality"
},
  "geometry": {"coordinates":[1.61768,46.71442],"type":"Point"}
}