{
  "type": "Feature",
  "properties": {
    "gn:gn_country":"FR",
    "gn:gn_fcode":"PPL",
    "gn:gn_pop":12955,
    "gn:population":12955,
    "iso:country":"FR",
    "name:cat_x_preferred":[
        "Ambar\u00e9s e la Grava"
    ],
    "name:fas_x_preferred":[
        "\u0627\u0645\u0628\u0627\u0631\u0633-\u0627\u062a-\u0644\u0627\u06af\u0631\u0627\u0648\u0627"
    ],
    "name:kaz_x_preferred":[
        "\u0410\u043c\u0431\u0430\u0440\u0435\u0437-\u0435-\u041b\u0430\u0433\u0440\u0430\u0432"
    ],
    "name:oci_x_preferred":[
        "Ambar\u00e9s e La Grava"
    ],
    "name:srp_x_preferred":[
        "\u0410\u043c\u0431\u0430\u0440\u0435\u0441-\u0435-\u041b\u0430\u0433\u0440\u0430\u0432"
    ],
    "name:ukr_x_preferred":[
        "\u0410\u043c\u0431\u0430\u0440\u0435\u0437-\u0435-\u041b\u0430\u0433\u0440\u0430\u0432"
    ],
    "name:unk_x_variant":[
        "Amoar\u00e8s"
    ],
    "name:zho_x_preferred":[
        "\u6602\u5df4\u96f7\u548c\u62c9\u683c\u62c9\u592b"
    ],
    "qs_pg:aaroncc":"FR",
    "qs_pg:gn_country":"FR",
    "qs_pg:gn_fcode":"PPL",
    "qs_pg:gn_pop":12955,
    "qs_pg:name":"Ambar\u00e8s-et-Lagrave",
    "qs_pg:name_adm0":"France",
    "qs_pg:name_adm1":"Aquitaine",
    "qs_pg:photos":377,
    "qs_pg:photos_1k":76,
    "qs_pg:photos_9k":2,
    "qs_pg:photos_9r":5,
    "qs_pg:photos_all":377,
    "qs_pg:photos_sr":6,
    "qs_pg:pop_sr":6,
    "qs_pg:qs_pg_placetype":"neighbourhood",
    "qs_pg:qs_pg_placetype_gp":"Suburb",
    "qs_pg:woe_adm0":23424819,
    "woe:adm0_id":23424819,
    "woe:name_adm0":"France",
    "woe:name_adm1":"Aquitaine",
    "woe:placetype":"Suburb",
    "wof:name":"Ambar\u00e8s-et-Lagrave",
    "wof:placetype":"neighbourhood",
    "wof:population":12955
},
  "geometry": {"coordinates":[-0.48333,44.91667],"type":"Point"}
}