{
  "type": "Feature",
  "properties": {
    "gn:admin1_code":"94",
    "gn:admin2_code":"2B",
    "gn:admin3_code":"2B3",
    "gn:admin4_code":"2B059",
    "gn:asciiname":"Monticelli",
    "gn:country_code":"FR",
    "gn:dem":317,
    "gn:feature_class":"P",
    "gn:feature_code":"PPL",
    "gn:name":"Monticelli",
    "gn:population":0,
    "gn:timezone":"Europe/Paris",
    "iso:country":"FR",
    "name:ceb_x_preferred":[
        "Monticelli"
    ],
    "name:deu_x_preferred":[
        "Monticelli"
    ],
    "name:fra_x_preferred":[
        "Monticelli"
    ],
    "name:ita_x_preferred":[
        "Monticelli"
    ],
    "name:por_x_preferred":[
        "Monticelli"
    ],
    "name:rus_x_preferred":[
        "\u041c\u043e\u043d\u0442\u0438\u0447\u0435\u043b\u043b\u0438"
    ],
    "name:srp_x_preferred":[
        "Monti\u010deli"
    ],
    "name:swe_x_preferred":[
        "Monticelli"
    ],
    "wof:name":"Monticelli",
    "wof:placetype":"locality"
},
  "geometry": {"coordinates":[9.24247,42.47693],"type":"Point"}
}