{
  "type": "Feature",
  "properties": {
    "gn:admin1_code":"94",
    "gn:admin2_code":"2B",
    "gn:admin3_code":"2B3",
    "gn:admin4_code":"2B059",
    "gn:asciiname":"Monticelli",
    "gn:country_code":"FR",
    "gn:dem":317,
    "gn:feature_class":"P",
    "gn:feature_code":"PPL",
    "gn:name":"Monticelli",
    "gn:population":0,
    "gn:timezone":"Europe/Paris",
    "iso:country":"FR",
    "wof:name":"Monticelli",
    "wof:placetype":"locality"
},
  "geometry": {"coordinates":[9.24247,42.47693],"type":"Point"}
}