{
  "type": "Feature",
  "properties": {
    "gn:admin1_code":"75",
    "gn:admin2_code":"19",
    "gn:admin3_code":"193",
    "gn:admin4_code":"19002",
    "gn:asciiname":"Bonnefond-Sigale",
    "gn:country_code":"FR",
    "gn:dem":847,
    "gn:feature_class":"P",
    "gn:feature_code":"PPL",
    "gn:name":"Bonnefond-Sigale",
    "gn:population":0,
    "gn:timezone":"Europe/Paris",
    "iso:country":"FR",
    "wof:name":"Bonnefond-Sigale",
    "wof:placetype":"locality"
},
  "geometry": {"coordinates":[2.36667,45.61667],"type":"Point"}
}