{
  "type": "Feature",
  "properties": {
    "gn:admin1_code":"84",
    "gn:admin2_code":"69",
    "gn:admin3_code":"691",
    "gn:admin4_code":"69136",
    "gn:asciiname":"Sourzy",
    "gn:country_code":"FR",
    "gn:dem":275,
    "gn:feature_class":"P",
    "gn:feature_code":"PPL",
    "gn:name":"Sourzy",
    "gn:population":0,
    "gn:timezone":"Europe/Paris",
    "iso:country":"FR",
    "wof:name":"Sourzy",
    "wof:placetype":"locality"
},
  "geometry": {"coordinates":[4.74929,45.6218],"type":"Point"}
}