{
  "type": "Feature",
  "properties": {
    "gn:admin1_code":"27",
    "gn:admin2_code":"58",
    "gn:admin3_code":"583",
    "gn:admin4_code":"58275",
    "gn:asciiname":"Pornas",
    "gn:country_code":"FR",
    "gn:dem":297,
    "gn:feature_class":"P",
    "gn:feature_code":"PPL",
    "gn:name":"Pornas",
    "gn:population":0,
    "gn:timezone":"Europe/Paris",
    "iso:country":"FR",
    "name:und_x_variant":[
        "Pornat",
        "Pornas"
    ],
    "wof:name":"Pornas",
    "wof:placetype":"locality"
},
  "geometry": {"coordinates":[3.4755,47.06417],"type":"Point"}
}