{
  "type": "Feature",
  "properties": {
    "gn:admin1_code":"28",
    "gn:admin2_code":"76",
    "gn:admin3_code":"763",
    "gn:admin4_code":"76418.0",
    "gn:asciiname":"Sainte-Gertrude",
    "gn:country_code":"FR",
    "gn:dem":10,
    "gn:feature_class":"P",
    "gn:feature_code":"PPL",
    "gn:name":"Sainte-Gertrude",
    "gn:population":0,
    "gn:timezone":"Europe/Paris",
    "iso:country":"FR",
    "wof:name":"Sainte-Gertrude",
    "wof:placetype":"locality"
},
  "geometry": {"coordinates":[0.7057,49.54474],"type":"Point"}
}