{
  "type": "Feature",
  "properties": {
    "gn:admin1_code":"53",
    "gn:admin2_code":"22",
    "gn:admin3_code":"222",
    "gn:admin4_code":"22024",
    "gn:asciiname":"La Haye",
    "gn:country_code":"FR",
    "gn:dem":263,
    "gn:feature_class":"P",
    "gn:feature_code":"PPL",
    "gn:name":"La Haye",
    "gn:population":0,
    "gn:timezone":"Europe/Paris",
    "iso:country":"FR",
    "wof:name":"La Haye",
    "wof:placetype":"locality"
},
  "geometry": {"coordinates":[-3.49341,48.43941],"type":"Point"}
}