{
  "type": "Feature",
  "properties": {
    "gn:admin1_code":"53",
    "gn:admin2_code":"22",
    "gn:admin3_code":"222",
    "gn:admin4_code":"22024",
    "gn:asciiname":"La Haye",
    "gn:country_code":"FR",
    "gn:dem":263,
    "gn:feature_class":"P",
    "gn:feature_code":"PPL",
    "gn:name":"La Haye",
    "gn:population":0,
    "gn:timezone":"Europe/Paris",
    "iso:country":"FR",
    "name:ceb_x_preferred":[
        "La Haye"
    ],
    "name:deu_x_preferred":[
        "La Haye"
    ],
    "name:ita_x_preferred":[
        "La Haye"
    ],
    "name:nds_x_preferred":[
        "La Haye"
    ],
    "name:nld_x_preferred":[
        "La Haye"
    ],
    "name:pms_x_preferred":[
        "La Haye"
    ],
    "name:pol_x_preferred":[
        "La Haye"
    ],
    "name:por_x_preferred":[
        "La Haye"
    ],
    "name:scn_x_preferred":[
        "La Haye"
    ],
    "name:slk_x_preferred":[
        "La Haye"
    ],
    "name:spa_x_preferred":[
        "La Haye"
    ],
    "name:swe_x_preferred":[
        "La Haye"
    ],
    "name:ukr_x_preferred":[
        "\u041b\u0430-\u0415"
    ],
    "wof:name":"La Haye",
    "wof:placetype":"locality"
},
  "geometry": {"coordinates":[-3.49341,48.43941],"type":"Point"}
}