{
  "type": "Feature",
  "properties": {
    "gn:admin1_code":"52",
    "gn:admin2_code":"44",
    "gn:admin3_code":"443",
    "gn:admin4_code":"44030",
    "gn:asciiname":"Mayun",
    "gn:country_code":"FR",
    "gn:dem":6,
    "gn:feature_class":"P",
    "gn:feature_code":"PPL",
    "gn:name":"Mayun",
    "gn:population":0,
    "gn:timezone":"Europe/Paris",
    "iso:country":"FR",
    "wof:name":"Mayun",
    "wof:placetype":"locality"
},
  "geometry": {"coordinates":[-2.26227,47.44095],"type":"Point"}
}