{
  "type": "Feature",
  "properties": {
    "gn:admin1_code":"28",
    "gn:admin2_code":"76",
    "gn:admin3_code":"761",
    "gn:admin4_code":"76209",
    "gn:asciiname":"Beuvreil",
    "gn:country_code":"FR",
    "gn:dem":105,
    "gn:feature_class":"P",
    "gn:feature_code":"PPL",
    "gn:name":"Beuvreil",
    "gn:population":0,
    "gn:timezone":"Europe/Paris",
    "iso:country":"FR",
    "wof:name":"Beuvreil",
    "wof:placetype":"locality"
},
  "geometry": {"coordinates":[1.68621,49.53216],"type":"Point"}
}