{
  "type": "Feature",
  "properties": {
    "gn:admin1_code":"93",
    "gn:admin2_code":"06",
    "gn:admin3_code":"062",
    "gn:admin4_code":"06071",
    "gn:asciiname":"Le Lavigne",
    "gn:country_code":"FR",
    "gn:dem":1497,
    "gn:feature_class":"P",
    "gn:feature_code":"PPL",
    "gn:name":"Le Lavigne",
    "gn:population":0,
    "gn:timezone":"Europe/Paris",
    "iso:country":"FR",
    "name:und_x_variant":[
        "Lavigne",
        "Le Lavigne"
    ],
    "wof:name":"Le Lavigne",
    "wof:placetype":"locality"
},
  "geometry": {"coordinates":[6.90032,44.04716],"type":"Point"}
}