{
  "type": "Feature",
  "properties": {
    "gn:admin1_code":"28",
    "gn:admin2_code":"14",
    "gn:admin3_code":"142",
    "gn:admin4_code":"14066",
    "gn:asciiname":"Bernieres-sur-Mer",
    "gn:country_code":"FR",
    "gn:dem":7,
    "gn:feature_class":"P",
    "gn:feature_code":"PPL",
    "gn:name":"Berni\u00e8res-sur-Mer",
    "gn:population":1972,
    "gn:timezone":"Europe/Paris",
    "iso:country":"FR",
    "name:kaz_x_preferred":[
        "\u0411\u0435\u0440\u043d\u044c\u0435\u0440-\u0441\u044e\u0440-\u041c\u0435\u0440"
    ],
    "name:rus_x_preferred":[
        "\u0411\u0435\u0440\u043d\u044c\u0435\u0440-\u0441\u044e\u0440-\u041c\u0435\u0440"
    ],
    "name:srp_x_preferred":[
        "\u0411\u0435\u0440\u043d\u0438\u0458\u0435\u0440 \u043d\u0430 \u041c\u043e\u0440\u0443"
    ],
    "name:ukr_x_preferred":[
        "\u0411\u0435\u0440\u043d\u044c\u0454\u0440-\u0441\u044e\u0440-\u041c\u0435\u0440"
    ],
    "name:und_x_variant":[
        "Berni\u00e8res",
        "Berni\u00e8res-sur-Mer"
    ],
    "name:zho_x_preferred":[
        "\u6ee8\u6d77\u8d1d\u5c14\u5c3c\u57c3"
    ],
    "wof:name":"Bernieres-sur-Mer",
    "wof:placetype":"locality",
    "wof:population":1972
},
  "geometry": {"coordinates":[-0.42299,49.33057],"type":"Point"}
}