{
  "type": "Feature",
  "properties": {
    "gn:admin1_code":"28",
    "gn:admin2_code":"14",
    "gn:admin3_code":"142",
    "gn:admin4_code":"14066",
    "gn:asciiname":"Bernieres-sur-Mer",
    "gn:country_code":"FR",
    "gn:dem":7,
    "gn:feature_class":"P",
    "gn:feature_code":"PPL",
    "gn:name":"Berni\u00e8res-sur-Mer",
    "gn:population":1972,
    "gn:timezone":"Europe/Paris",
    "iso:country":"FR",
    "name:bre_x_preferred":[
        "Berni\u00e8res-sur-Mer"
    ],
    "name:cat_x_preferred":[
        "Berni\u00e8res-sur-Mer"
    ],
    "name:ceb_x_preferred":[
        "Berni\u00e8res-sur-Mer"
    ],
    "name:deu_x_preferred":[
        "Berni\u00e8res-sur-Mer"
    ],
    "name:epo_x_preferred":[
        "Berni\u00e8res-sur-Mer"
    ],
    "name:eus_x_preferred":[
        "Berni\u00e8res-sur-Mer"
    ],
    "name:fas_x_preferred":[
        "\u0628\u0631\u0646\u06cc\u0631-\u0633\u0648\u0631-\u0645\u0631"
    ],
    "name:fin_x_preferred":[
        "Berni\u00e8res-sur-Mer"
    ],
    "name:fra_x_preferred":[
        "Berni\u00e8res-sur-Mer"
    ],
    "name:hun_x_preferred":[
        "Berni\u00e8res-sur-Mer"
    ],
    "name:ind_x_preferred":[
        "Berni\u00e8res-sur-Mer"
    ],
    "name:ita_x_preferred":[
        "Berni\u00e8res-sur-Mer"
    ],
    "name:kaz_x_preferred":[
        "\u0411\u0435\u0440\u043d\u044c\u0435\u0440-\u0441\u044e\u0440-\u041c\u0435\u0440"
    ],
    "name:lat_x_preferred":[
        "Berni\u00e8res-sur-Mer"
    ],
    "name:msa_x_preferred":[
        "Berni\u00e8res-sur-Mer"
    ],
    "name:nld_x_preferred":[
        "Berni\u00e8res-sur-Mer"
    ],
    "name:oci_x_preferred":[
        "Berni\u00e8res-sur-Mer"
    ],
    "name:pam_x_preferred":[
        "Berni\u00e8res-sur-Mer"
    ],
    "name:pms_x_preferred":[
        "Berni\u00e8res-sur-Mer"
    ],
    "name:pol_x_preferred":[
        "Berni\u00e8res-sur-Mer"
    ],
    "name:por_x_preferred":[
        "Berni\u00e8res-sur-Mer"
    ],
    "name:ron_x_preferred":[
        "Berni\u00e8res-sur-Mer"
    ],
    "name:rus_x_preferred":[
        "\u0411\u0435\u0440\u043d\u044c\u0435\u0440-\u0441\u044e\u0440-\u041c\u0435\u0440"
    ],
    "name:slk_x_preferred":[
        "Berni\u00e8res-sur-Mer"
    ],
    "name:spa_x_preferred":[
        "Berni\u00e8res-sur-Mer"
    ],
    "name:srp_x_preferred":[
        "\u0411\u0435\u0440\u043d\u0438\u0458\u0435\u0440 \u043d\u0430 \u041c\u043e\u0440\u0443"
    ],
    "name:swe_x_preferred":[
        "Berni\u00e8res-sur-Mer"
    ],
    "name:ukr_x_preferred":[
        "\u0411\u0435\u0440\u043d\u044c\u0454\u0440-\u0441\u044e\u0440-\u041c\u0435\u0440"
    ],
    "name:und_x_variant":[
        "Berni\u00e8res"
    ],
    "name:uzb_x_preferred":[
        "Berni\u00e8res-sur-Mer"
    ],
    "name:vie_x_preferred":[
        "Berni\u00e8res-sur-Mer"
    ],
    "name:vol_x_preferred":[
        "Berni\u00e8res-sur-Mer"
    ],
    "name:war_x_preferred":[
        "Berni\u00e8res-sur-Mer"
    ],
    "name:zho_x_preferred":[
        "\u6ee8\u6d77\u8d1d\u5c14\u5c3c\u57c3"
    ],
    "wof:name":"Bernieres-sur-Mer",
    "wof:placetype":"locality",
    "wof:population":1972
},
  "geometry": {"coordinates":[-0.42299,49.33057],"type":"Point"}
}