{
  "type": "Feature",
  "properties": {
    "gn:admin1_code":"24",
    "gn:admin2_code":"36",
    "gn:admin3_code":"361",
    "gn:admin4_code":"36172",
    "gn:asciiname":"Les Brunets",
    "gn:country_code":"FR",
    "gn:dem":140,
    "gn:feature_class":"P",
    "gn:feature_code":"PPL",
    "gn:name":"Les Brunets",
    "gn:population":0,
    "gn:timezone":"Europe/Paris",
    "iso:country":"FR",
    "wof:name":"Les Brunets",
    "wof:placetype":"locality"
},
  "geometry": {"coordinates":[1.37313,46.62721],"type":"Point"}
}