{
  "type": "Feature",
  "properties": {
    "gn:admin1_code":"84",
    "gn:admin2_code":"43",
    "gn:admin3_code":"432",
    "gn:admin4_code":"43005",
    "gn:asciiname":"Pourcharesse",
    "gn:country_code":"FR",
    "gn:dem":1036,
    "gn:feature_class":"P",
    "gn:feature_code":"PPL",
    "gn:name":"Pourcharesse",
    "gn:population":0,
    "gn:timezone":"Europe/Paris",
    "iso:country":"FR",
    "name:und_x_variant":[
        "Pourcheresse",
        "Pourcharesse"
    ],
    "wof:name":"Pourcharesse",
    "wof:placetype":"locality"
},
  "geometry": {"coordinates":[3.66139,44.89031],"type":"Point"}
}