{
  "type": "Feature",
  "properties": {
    "gn:admin1_code":"84",
    "gn:admin2_code":"15",
    "gn:admin3_code":"153",
    "gn:admin4_code":"15001",
    "gn:asciiname":"Roche Haut",
    "gn:country_code":"FR",
    "gn:dem":1031,
    "gn:feature_class":"P",
    "gn:feature_code":"PPL",
    "gn:name":"Roche Haut",
    "gn:population":0,
    "gn:timezone":"Europe/Paris",
    "iso:country":"FR",
    "name:und_x_variant":[
        "Roche",
        "Roche Haut"
    ],
    "wof:name":"Roche Haut",
    "wof:placetype":"locality"
},
  "geometry": {"coordinates":[2.95342,45.20597],"type":"Point"}
}