{
  "type": "Feature",
  "properties": {
    "gn:admin1_code":"75",
    "gn:admin2_code":"19",
    "gn:admin3_code":"191",
    "gn:admin4_code":"19005",
    "gn:asciiname":"Le Puy",
    "gn:country_code":"FR",
    "gn:dem":186,
    "gn:feature_class":"P",
    "gn:feature_code":"PPL",
    "gn:name":"Le Puy",
    "gn:population":0,
    "gn:timezone":"Europe/Paris",
    "iso:country":"FR",
    "wof:name":"Le Puy",
    "wof:placetype":"locality"
},
  "geometry": {"coordinates":[1.43921,45.26148],"type":"Point"}
}