{
  "type": "Feature",
  "properties": {
    "gn:admin1_code":"93",
    "gn:admin2_code":"05",
    "gn:admin3_code":"051",
    "gn:admin4_code":"05151",
    "gn:asciiname":"Queyrieres",
    "gn:country_code":"FR",
    "gn:dem":1230,
    "gn:feature_class":"P",
    "gn:feature_code":"PPL",
    "gn:name":"Queyri\u00e8res",
    "gn:population":0,
    "gn:timezone":"Europe/Paris",
    "iso:country":"FR",
    "name:und_x_variant":[
        "Queri\u00e8res",
        "Queyri\u00e8res"
    ],
    "wof:name":"Queyrieres",
    "wof:placetype":"locality"
},
  "geometry": {"coordinates":[6.58043,44.82527],"type":"Point"}
}