{
  "type": "Feature",
  "properties": {
    "gn:admin1_code":"84",
    "gn:admin2_code":"43",
    "gn:admin3_code":"432",
    "gn:admin4_code":"43221",
    "gn:asciiname":"Varennes",
    "gn:country_code":"FR",
    "gn:dem":1037,
    "gn:feature_class":"P",
    "gn:feature_code":"PPL",
    "gn:name":"Varennes",
    "gn:population":0,
    "gn:timezone":"Europe/Paris",
    "iso:country":"FR",
    "wof:name":"Varennes",
    "wof:placetype":"locality"
},
  "geometry": {"coordinates":[3.68665,45.02476],"type":"Point"}
}