{
  "type": "Feature",
  "properties": {
    "gn:admin1_code":"75",
    "gn:admin2_code":"33",
    "gn:admin3_code":"334",
    "gn:admin4_code":"33314",
    "gn:asciiname":"Padarnac",
    "gn:country_code":"FR",
    "gn:dem":12,
    "gn:feature_class":"P",
    "gn:feature_code":"PPL",
    "gn:name":"Padarnac",
    "gn:population":0,
    "gn:timezone":"Europe/Paris",
    "iso:country":"FR",
    "wof:name":"Padarnac",
    "wof:placetype":"locality"
},
  "geometry": {"coordinates":[-0.75867,45.21021],"type":"Point"}
}