{
  "type": "Feature",
  "properties": {
    "gn:admin1_code":"52",
    "gn:admin2_code":"44",
    "gn:admin3_code":"444",
    "gn:admin4_code":"44082",
    "gn:asciiname":"La Haie de Ligne",
    "gn:country_code":"FR",
    "gn:dem":38,
    "gn:feature_class":"P",
    "gn:feature_code":"PPL",
    "gn:name":"La Haie de Lign\u00e9",
    "gn:population":0,
    "gn:timezone":"Europe/Paris",
    "iso:country":"FR",
    "name:und_x_variant":[
        "La Haie",
        "La Haie de Lign\u00e9"
    ],
    "wof:name":"La Haie de Ligne",
    "wof:placetype":"locality"
},
  "geometry": {"coordinates":[-1.40476,47.39845],"type":"Point"}
}