{
  "type": "Feature",
  "properties": {
    "gn:admin1_code":"24",
    "gn:admin2_code":"18",
    "gn:admin3_code":"182",
    "gn:admin4_code":"18009.0",
    "gn:asciiname":"Les Boutillats",
    "gn:country_code":"FR",
    "gn:dem":203,
    "gn:feature_class":"P",
    "gn:feature_code":"PPL",
    "gn:name":"Les Boutillats",
    "gn:population":0,
    "gn:timezone":"Europe/Paris",
    "iso:country":"FR",
    "wof:name":"Les Boutillats",
    "wof:placetype":"locality"
},
  "geometry": {"coordinates":[2.42991,46.68609],"type":"Point"}
}