{
  "type": "Feature",
  "properties": {
    "gn:admin1_code":"76",
    "gn:admin2_code":"48",
    "gn:admin3_code":"481",
    "gn:admin4_code":"48096",
    "gn:asciiname":"Salvensac",
    "gn:country_code":"FR",
    "gn:dem":775,
    "gn:feature_class":"P",
    "gn:feature_code":"PPL",
    "gn:name":"Salvensac",
    "gn:population":0,
    "gn:timezone":"Europe/Paris",
    "iso:country":"FR",
    "name:und_x_variant":[
        "Salvinsac",
        "Salvensac"
    ],
    "wof:name":"Salvensac",
    "wof:placetype":"locality"
},
  "geometry": {"coordinates":[3.45074,44.19557],"type":"Point"}
}