{
  "type": "Feature",
  "properties": {
    "gn:admin1_code":"27",
    "gn:admin2_code":"58",
    "gn:admin3_code":"583",
    "gn:admin4_code":"58137.0",
    "gn:asciiname":"Nogent",
    "gn:country_code":"FR",
    "gn:dem":200,
    "gn:feature_class":"P",
    "gn:feature_code":"PPL",
    "gn:name":"Nogent",
    "gn:population":0,
    "gn:timezone":"Europe/Paris",
    "iso:country":"FR",
    "name:bre_x_preferred":[
        "Nogent"
    ],
    "name:deu_x_preferred":[
        "Nogent"
    ],
    "name:epo_x_preferred":[
        "Nogent"
    ],
    "name:fra_x_preferred":[
        "Nogent"
    ],
    "name:jpn_x_preferred":[
        "\u30ce\u30b8\u30e3\u30f3"
    ],
    "name:nld_x_preferred":[
        "Nogent"
    ],
    "name:oci_x_preferred":[
        "Nogent"
    ],
    "name:swe_x_preferred":[
        "Nogent"
    ],
    "wof:name":"Nogent",
    "wof:placetype":"locality"
},
  "geometry": {"coordinates":[3.55892,46.76107],"type":"Point"}
}