{
  "type": "Feature",
  "properties": {
    "gn:admin1_code":"32",
    "gn:admin2_code":"62",
    "gn:admin3_code":"626",
    "gn:admin4_code":"62193.0",
    "gn:asciiname":"Le Chalet Beutin",
    "gn:country_code":"FR",
    "gn:dem":8,
    "gn:feature_class":"P",
    "gn:feature_code":"PPLL",
    "gn:name":"Le Chalet Beutin",
    "gn:population":0,
    "gn:timezone":"Europe/Paris",
    "iso:country":"FR",
    "wof:name":"Le Chalet Beutin",
    "wof:placetype":"locality"
},
  "geometry": {"coordinates":[1.91139,50.97071],"type":"Point"}
}