{
  "type": "Feature",
  "properties": {
    "gn:admin1_code":"44",
    "gn:admin2_code":"51",
    "gn:admin3_code":"513",
    "gn:admin4_code":"51571",
    "gn:asciiname":"Courmelois",
    "gn:country_code":"FR",
    "gn:dem":90,
    "gn:feature_class":"P",
    "gn:feature_code":"PPL",
    "gn:name":"Courmelois",
    "gn:population":0,
    "gn:timezone":"Europe/Paris",
    "iso:country":"FR",
    "wof:name":"Courmelois",
    "wof:placetype":"locality"
},
  "geometry": {"coordinates":[4.21677,49.16479],"type":"Point"}
}