{
  "type": "Feature",
  "properties": {
    "gn:admin1_code":"28",
    "gn:admin2_code":"27",
    "gn:admin3_code":"272",
    "gn:admin4_code":"27518",
    "gn:asciiname":"Le Grand Saint-Aubin",
    "gn:country_code":"FR",
    "gn:dem":4,
    "gn:feature_class":"P",
    "gn:feature_code":"PPL",
    "gn:name":"Le Grand Saint-Aubin",
    "gn:population":0,
    "gn:timezone":"Europe/Paris",
    "iso:country":"FR",
    "wof:name":"Le Grand Saint-Aubin",
    "wof:placetype":"locality"
},
  "geometry": {"coordinates":[0.53667,49.44741],"type":"Point"}
}