{
  "type": "Feature",
  "properties": {
    "gn:admin1_code":"32",
    "gn:admin2_code":"62",
    "gn:admin3_code":"623",
    "gn:admin4_code":"62251",
    "gn:asciiname":"Sacriquier",
    "gn:country_code":"FR",
    "gn:dem":188,
    "gn:feature_class":"P",
    "gn:feature_code":"PPL",
    "gn:name":"Sacriquier",
    "gn:population":0,
    "gn:timezone":"Europe/Paris",
    "iso:country":"FR",
    "wof:name":"Sacriquier",
    "wof:placetype":"locality"
},
  "geometry": {"coordinates":[1.87112,50.64503],"type":"Point"}
}