{
  "type": "Feature",
  "properties": {
    "gn:admin1_code":"53",
    "gn:admin2_code":"29",
    "gn:admin3_code":"293",
    "gn:admin4_code":"29097",
    "gn:asciiname":"Roc'hfily",
    "gn:country_code":"FR",
    "gn:dem":110,
    "gn:feature_class":"P",
    "gn:feature_code":"PPL",
    "gn:name":"Roc\u2019hfily",
    "gn:population":0,
    "gn:timezone":"Europe/Paris",
    "iso:country":"FR",
    "wof:name":"Roc'hfily",
    "wof:placetype":"locality"
},
  "geometry": {"coordinates":[-4.06667,48.48333],"type":"Point"}
}