{
  "type": "Feature",
  "properties": {
    "gn:admin1_code":"44",
    "gn:admin2_code":"08",
    "gn:admin3_code":"083",
    "gn:admin4_code":"08194",
    "gn:asciiname":"Iges",
    "gn:country_code":"FR",
    "gn:dem":165,
    "gn:feature_class":"P",
    "gn:feature_code":"PPL",
    "gn:name":"Iges",
    "gn:population":0,
    "gn:timezone":"Europe/Paris",
    "iso:country":"FR",
    "wof:name":"Iges",
    "wof:placetype":"locality"
},
  "geometry": {"coordinates":[4.9081,49.73033],"type":"Point"}
}