{
  "type": "Feature",
  "properties": {
    "gn:admin1_code":"44",
    "gn:admin2_code":"08",
    "gn:admin3_code":"081",
    "gn:admin4_code":"08218",
    "gn:asciiname":"Linchamps",
    "gn:country_code":"FR",
    "gn:dem":209,
    "gn:feature_class":"P",
    "gn:feature_code":"PPL",
    "gn:name":"Linchamps",
    "gn:population":0,
    "gn:timezone":"Europe/Paris",
    "iso:country":"FR",
    "wof:name":"Linchamps",
    "wof:placetype":"locality"
},
  "geometry": {"coordinates":[4.83778,49.91365],"type":"Point"}
}