{
  "type": "Feature",
  "properties": {
    "gn:country":"FR",
    "iso:country":"FR",
    "qs_pg:aaroncc":"FR",
    "qs_pg:gn_country":"FR",
    "qs_pg:name":"L'Am\u00e9lie-sur-Mer",
    "qs_pg:name_adm0":"France",
    "qs_pg:name_adm1":"Aquitaine",
    "qs_pg:photos":59,
    "qs_pg:photos_1k":12,
    "qs_pg:photos_9k":1,
    "qs_pg:photos_9r":2,
    "qs_pg:photos_all":59,
    "qs_pg:photos_sr":2,
    "qs_pg:pop_sr":0,
    "qs_pg:qs_pg_placetype":"locality",
    "qs_pg:qs_pg_placetype_gp":"Town",
    "qs_pg:woe_adm0":23424819,
    "woe:adm0_id":23424819,
    "woe:name_adm0":"France",
    "woe:name_adm1":"Aquitaine",
    "woe:placetype":"Town",
    "wof:name":"L'Am\u00e9lie-sur-Mer",
    "wof:placetype":"neighbourhood"
},
  "geometry": {"coordinates":[-1.141805,45.484326],"type":"Point"}
}