{
  "type": "Feature",
  "properties": {
    "gn:admin1_code":"53",
    "gn:admin2_code":"29",
    "gn:admin3_code":"292",
    "gn:admin4_code":"29062",
    "gn:asciiname":"Treguron",
    "gn:country_code":"FR",
    "gn:dem":89,
    "gn:feature_class":"P",
    "gn:feature_code":"PPL",
    "gn:name":"Treguron",
    "gn:population":0,
    "gn:timezone":"Europe/Paris",
    "iso:country":"FR",
    "wof:name":"Treguron",
    "wof:placetype":"locality"
},
  "geometry": {"coordinates":[-3.95,48.16667],"type":"Point"}
}