{
  "type": "Feature",
  "properties": {
    "iso:country":"FR",
    "name:eng_x_preferred":[
        "Cassagnes-B\u00e9gonh\u00e8s Airport"
    ],
    "name:msa_x_preferred":[
        "Lapangan Terbang Cassagnes-Begonhes"
    ],
    "oa:elevation_ft":"2024",
    "oa:type":"small_airport",
    "woe:hierarchy":{
        "country_id":23424819,
        "county_id":12597173,
        "localadmin_id":12658414,
        "planet_id":1,
        "state_id":7153323
    },
    "wof:name":"Cassagnes Begonhes Airport",
    "wof:placetype":"campus"
},
  "geometry": {"coordinates":[2.51778,44.1783],"type":"Point"}
}