{
  "type": "Feature",
  "properties": {
    "gn:admin1_code":"75",
    "gn:admin2_code":"24",
    "gn:admin3_code":"241",
    "gn:admin4_code":"24045",
    "gn:asciiname":"Le Cler",
    "gn:country_code":"FR",
    "gn:dem":178,
    "gn:feature_class":"P",
    "gn:feature_code":"PPL",
    "gn:name":"Le Cler",
    "gn:population":0,
    "gn:timezone":"Europe/Paris",
    "iso:country":"FR",
    "wof:name":"Le Cler",
    "wof:placetype":"locality"
},
  "geometry": {"coordinates":[0.66122,44.72372],"type":"Point"}
}