{
  "type": "Feature",
  "properties": {
    "gn:admin1_code":"44",
    "gn:admin2_code":"57",
    "gn:admin3_code":"577",
    "gn:admin4_code":"57672",
    "gn:asciiname":"Beuvange-sous-Saint-Michel",
    "gn:country_code":"FR",
    "gn:dem":204,
    "gn:feature_class":"P",
    "gn:feature_code":"PPL",
    "gn:name":"Beuvange-sous-Saint-Michel",
    "gn:population":0,
    "gn:timezone":"Europe/Paris",
    "iso:country":"FR",
    "name:und_x_variant":[
        "Beuvange",
        "Beuvange sous Saint-Michel"
    ],
    "wof:name":"Beuvange-sous-Saint-Michel",
    "wof:placetype":"locality"
},
  "geometry": {"coordinates":[6.08304,49.36593],"type":"Point"}
}