{
  "type": "Feature",
  "properties": {
    "gn:admin1_code":"93",
    "gn:admin2_code":"04",
    "gn:admin3_code":"041",
    "gn:admin4_code":"04033",
    "gn:asciiname":"La Garde",
    "gn:country_code":"FR",
    "gn:dem":1085,
    "gn:feature_class":"P",
    "gn:feature_code":"PPL",
    "gn:name":"La Garde",
    "gn:population":0,
    "gn:timezone":"Europe/Paris",
    "iso:country":"FR",
    "name:ceb_x_preferred":[
        "La Garde"
    ],
    "name:deu_x_preferred":[
        "La Garde"
    ],
    "name:epo_x_preferred":[
        "La Garde"
    ],
    "name:fra_x_preferred":[
        "La Garde"
    ],
    "name:ita_x_preferred":[
        "La Garde"
    ],
    "name:lmo_x_preferred":[
        "La Garde"
    ],
    "name:nds_x_preferred":[
        "La Garde"
    ],
    "name:nld_x_preferred":[
        "La Garde"
    ],
    "name:oci_x_preferred":[
        "La Garda"
    ],
    "name:pms_x_preferred":[
        "La Garde"
    ],
    "name:por_x_preferred":[
        "La Garde"
    ],
    "name:ron_x_preferred":[
        "La Garde"
    ],
    "name:rus_x_preferred":[
        "\u041b\u0430-\u0413\u0430\u0440\u0434"
    ],
    "name:slk_x_preferred":[
        "La Garde"
    ],
    "name:spa_x_preferred":[
        "La Garde"
    ],
    "name:swe_x_preferred":[
        "La Garde"
    ],
    "name:ukr_x_preferred":[
        "\u041b\u0430-\u0413\u0430\u0440\u0434"
    ],
    "wof:name":"La Garde",
    "wof:placetype":"locality"
},
  "geometry": {"coordinates":[6.26667,44.43333],"type":"Point"}
}