{
  "type": "Feature",
  "properties": {
    "gn:admin1_code":"44",
    "gn:admin2_code":"57",
    "gn:admin3_code":"574",
    "gn:admin4_code":"57751",
    "gn:asciiname":"Saint-Remy",
    "gn:country_code":"FR",
    "gn:dem":164,
    "gn:feature_class":"P",
    "gn:feature_code":"PPL",
    "gn:name":"Saint-R\u00e9my",
    "gn:population":0,
    "gn:timezone":"Europe/Paris",
    "iso:country":"FR",
    "wof:name":"Saint-Remy",
    "wof:placetype":"locality"
},
  "geometry": {"coordinates":[6.16192,49.17494],"type":"Point"}
}