{
  "type": "Feature",
  "properties": {
    "gn:admin1_code":"75",
    "gn:admin2_code":"23",
    "gn:admin3_code":"232",
    "gn:admin4_code":"23068",
    "gn:asciiname":"Le Poirier",
    "gn:country_code":"FR",
    "gn:dem":509,
    "gn:feature_class":"P",
    "gn:feature_code":"PPL",
    "gn:name":"Le Poirier",
    "gn:population":0,
    "gn:timezone":"Europe/Paris",
    "iso:country":"FR",
    "wof:name":"Le Poirier",
    "wof:placetype":"locality"
},
  "geometry": {"coordinates":[2.11515,46.14364000000001],"type":"Point"}
}