{
  "type": "Feature",
  "properties": {
    "gn:admin1_code":"28",
    "gn:admin2_code":"76",
    "gn:admin3_code":"761",
    "gn:admin4_code":"76345",
    "gn:asciiname":"Fricourt",
    "gn:country_code":"FR",
    "gn:dem":140,
    "gn:feature_class":"P",
    "gn:feature_code":"PPL",
    "gn:name":"Fricourt",
    "gn:population":0,
    "gn:timezone":"Europe/Paris",
    "iso:country":"FR",
    "name:bug_x_preferred":[
        "Fricourt"
    ],
    "name:cat_x_preferred":[
        "Fricourt"
    ],
    "name:ceb_x_preferred":[
        "Fricourt"
    ],
    "name:deu_x_preferred":[
        "Fricourt"
    ],
    "name:eus_x_preferred":[
        "Fricourt"
    ],
    "name:fra_x_preferred":[
        "Fricourt"
    ],
    "name:hun_x_preferred":[
        "Fricourt"
    ],
    "name:hye_x_preferred":[
        "\u0556\u0580\u056b\u056f\u0578\u0582\u0580"
    ],
    "name:ita_x_preferred":[
        "Fricourt"
    ],
    "name:lat_x_preferred":[
        "Fricourt"
    ],
    "name:mlg_x_preferred":[
        "Fricourt"
    ],
    "name:msa_x_preferred":[
        "Fricourt"
    ],
    "name:nld_x_preferred":[
        "Fricourt"
    ],
    "name:oci_x_preferred":[
        "Fricourt"
    ],
    "name:pcd_x_preferred":[
        "Fricourt"
    ],
    "name:pms_x_preferred":[
        "Fricourt"
    ],
    "name:pol_x_preferred":[
        "Fricourt"
    ],
    "name:por_x_preferred":[
        "Fricourt"
    ],
    "name:ron_x_preferred":[
        "Fricourt"
    ],
    "name:slk_x_preferred":[
        "Fricourt"
    ],
    "name:spa_x_preferred":[
        "Fricourt"
    ],
    "name:swe_x_preferred":[
        "Fricourt"
    ],
    "name:ukr_x_preferred":[
        "\u0424\u0440\u0438\u043a\u0443\u0440"
    ],
    "name:uzb_x_preferred":[
        "Fricourt"
    ],
    "name:vie_x_preferred":[
        "Fricourt"
    ],
    "name:vol_x_preferred":[
        "Fricourt"
    ],
    "name:war_x_preferred":[
        "Fricourt"
    ],
    "name:zho_x_preferred":[
        "\u5f17\u91cc\u5e93\u5c14"
    ],
    "wof:name":"Fricourt",
    "wof:placetype":"locality"
},
  "geometry": {"coordinates":[1.65633,49.59205],"type":"Point"}
}