{
  "type": "Feature",
  "properties": {
    "gn:admin1_code":"84",
    "gn:admin2_code":"63",
    "gn:admin3_code":"633",
    "gn:admin4_code":"63442",
    "gn:asciiname":"Chambrefaite",
    "gn:country_code":"FR",
    "gn:dem":712,
    "gn:feature_class":"P",
    "gn:feature_code":"PPL",
    "gn:name":"Chambrefaite",
    "gn:population":0,
    "gn:timezone":"Europe/Paris",
    "iso:country":"FR",
    "wof:name":"Chambrefaite",
    "wof:placetype":"locality"
},
  "geometry": {"coordinates":[3.43452,45.43335],"type":"Point"}
}