{
  "type": "Feature",
  "properties": {
    "gn:admin1_code":"75",
    "gn:admin2_code":"86",
    "gn:admin3_code":"861",
    "gn:admin4_code":"86137",
    "gn:asciiname":"Veniers",
    "gn:country_code":"FR",
    "gn:dem":66,
    "gn:feature_class":"P",
    "gn:feature_code":"PPL",
    "gn:name":"V\u00e9niers",
    "gn:population":0,
    "gn:timezone":"Europe/Paris",
    "iso:country":"FR",
    "wof:name":"Veniers",
    "wof:placetype":"locality"
},
  "geometry": {"coordinates":[0.08686,47.03474],"type":"Point"}
}