{
  "type": "Feature",
  "properties": {
    "gn:admin1_code":"84",
    "gn:admin2_code":"63",
    "gn:admin3_code":"632",
    "gn:admin4_code":"63084",
    "gn:asciiname":"Jussat",
    "gn:country_code":"FR",
    "gn:dem":548,
    "gn:feature_class":"P",
    "gn:feature_code":"PPL",
    "gn:name":"Jussat",
    "gn:population":0,
    "gn:timezone":"Europe/Paris",
    "iso:country":"FR",
    "wof:name":"Jussat",
    "wof:placetype":"locality"
},
  "geometry": {"coordinates":[3.10798,45.70201],"type":"Point"}
}