{
  "type": "Feature",
  "properties": {
    "gn:admin1_code":"84",
    "gn:admin2_code":"03",
    "gn:admin3_code":"032",
    "gn:admin4_code":"03254",
    "gn:asciiname":"Cregnards",
    "gn:country_code":"FR",
    "gn:dem":228,
    "gn:feature_class":"P",
    "gn:feature_code":"PPL",
    "gn:name":"Cregnards",
    "gn:population":0,
    "gn:timezone":"Europe/Paris",
    "iso:country":"FR",
    "wof:name":"Cregnards",
    "wof:placetype":"locality"
},
  "geometry": {"coordinates":[3.34032,46.3209],"type":"Point"}
}