{
  "type": "Feature",
  "properties": {
    "gn:admin1_code":"84",
    "gn:admin2_code":"03",
    "gn:admin3_code":"032",
    "gn:admin4_code":"03046",
    "gn:asciiname":"Fradonniere",
    "gn:country_code":"FR",
    "gn:dem":375,
    "gn:feature_class":"P",
    "gn:feature_code":"PPL",
    "gn:name":"Fradonni\u00e8re",
    "gn:population":0,
    "gn:timezone":"Europe/Paris",
    "iso:country":"FR",
    "wof:name":"Fradonniere",
    "wof:placetype":"locality"
},
  "geometry": {"coordinates":[2.98019,46.45247],"type":"Point"}
}