{
  "type": "Feature",
  "properties": {
    "gn:admin1_code":"27",
    "gn:admin2_code":"58",
    "gn:admin3_code":"584",
    "gn:admin4_code":"58007",
    "gn:asciiname":"Les Girardins",
    "gn:country_code":"FR",
    "gn:dem":191,
    "gn:feature_class":"P",
    "gn:feature_code":"PPL",
    "gn:name":"Les Girardins",
    "gn:population":0,
    "gn:timezone":"Europe/Paris",
    "iso:country":"FR",
    "wof:name":"Les Girardins",
    "wof:placetype":"locality"
},
  "geometry": {"coordinates":[2.94419,47.54657],"type":"Point"}
}