{
  "type": "Feature",
  "properties": {
    "gn:admin1_code":"75",
    "gn:admin2_code":"19",
    "gn:admin3_code":"191",
    "gn:admin4_code":"19068",
    "gn:asciiname":"Coignac",
    "gn:country_code":"FR",
    "gn:dem":246,
    "gn:feature_class":"P",
    "gn:feature_code":"PPL",
    "gn:name":"Coignac",
    "gn:population":0,
    "gn:timezone":"Europe/Paris",
    "iso:country":"FR",
    "wof:name":"Coignac",
    "wof:placetype":"locality"
},
  "geometry": {"coordinates":[1.63333,45.16667],"type":"Point"}
}