{
  "type": "Feature",
  "properties": {
    "gn:admin1_code":"84",
    "gn:admin2_code":"73",
    "gn:admin3_code":"731",
    "gn:admin4_code":"73257",
    "gn:asciiname":"Beranger",
    "gn:cc2":"FR",
    "gn:country_code":"FR",
    "gn:dem":1569,
    "gn:feature_class":"P",
    "gn:feature_code":"PPL",
    "gn:name":"B\u00e9ranger",
    "gn:population":0,
    "gn:timezone":"Europe/Paris",
    "iso:country":"FR",
    "name:und_x_variant":[
        "B\u00e9renger"
    ],
    "wof:name":"Beranger",
    "wof:placetype":"locality"
},
  "geometry": {"coordinates":[6.50579,45.4093],"type":"Point"}
}