{
  "type": "Feature",
  "properties": {
    "gn:admin1_code":"44",
    "gn:admin2_code":"68",
    "gn:admin3_code":"685",
    "gn:admin4_code":"68269",
    "gn:asciiname":"Petite-Verrerie",
    "gn:country_code":"FR",
    "gn:dem":664,
    "gn:feature_class":"P",
    "gn:feature_code":"PPL",
    "gn:name":"Petite-Verrerie",
    "gn:population":0,
    "gn:timezone":"Europe/Paris",
    "iso:country":"FR",
    "name:und_x_variant":[
        "La Petite Verrerie",
        "Petite-Verrerie"
    ],
    "wof:name":"Petite-Verrerie",
    "wof:placetype":"locality"
},
  "geometry": {"coordinates":[7.2512,48.22322],"type":"Point"}
}