{
  "type": "Feature",
  "properties": {
    "gn:admin1_code":"76",
    "gn:admin2_code":"32",
    "gn:admin3_code":"322",
    "gn:admin4_code":"32274",
    "gn:asciiname":"Monlezun-d'Armagnac",
    "gn:country_code":"FR",
    "gn:dem":111,
    "gn:feature_class":"P",
    "gn:feature_code":"PPL",
    "gn:name":"Monlezun-d\u2019Armagnac",
    "gn:population":0,
    "gn:timezone":"Europe/Paris",
    "iso:country":"FR",
    "name:arg_x_preferred":[
        "Montlasun d'Armanhac"
    ],
    "name:bug_x_preferred":[
        "Monlezun-d'Armagnac"
    ],
    "name:cat_x_preferred":[
        "Montlasun"
    ],
    "name:ceb_x_preferred":[
        "Monlezun-d'Armagnac"
    ],
    "name:deu_x_preferred":[
        "Monlezun-d\u2019Armagnac"
    ],
    "name:eus_x_preferred":[
        "Monlezun-d'Armagnac"
    ],
    "name:fra_x_preferred":[
        "Monlezun-d'Armagnac"
    ],
    "name:hun_x_preferred":[
        "Monlezun-d\u2019Armagnac"
    ],
    "name:ita_x_preferred":[
        "Monlezun-d'Armagnac"
    ],
    "name:lat_x_preferred":[
        "Monlezun-d'Armagnac"
    ],
    "name:mlg_x_preferred":[
        "Monlezun-d'Armagnac"
    ],
    "name:msa_x_preferred":[
        "Monlezun-d'Armagnac"
    ],
    "name:nld_x_preferred":[
        "Monlezun-d'Armagnac"
    ],
    "name:oci_x_preferred":[
        "Montlesun d'Armanhac"
    ],
    "name:pms_x_preferred":[
        "Monlezun-d'Armagnac"
    ],
    "name:pol_x_preferred":[
        "Monlezun-d\u2019Armagnac"
    ],
    "name:por_x_preferred":[
        "Monlezun-d'Armagnac"
    ],
    "name:ron_x_preferred":[
        "Monlezun-d'Armagnac"
    ],
    "name:rus_x_preferred":[
        "\u041c\u043e\u043d\u043b\u0435\u0437\u0451\u043d-\u0434\u2019\u0410\u0440\u043c\u0430\u043d\u044c\u044f\u043a"
    ],
    "name:slk_x_preferred":[
        "Monlezun-d\u2019Armagnac"
    ],
    "name:spa_x_preferred":[
        "Monlezun-d'Armagnac"
    ],
    "name:swe_x_preferred":[
        "Monlezun-d'Armagnac"
    ],
    "name:ukr_x_preferred":[
        "\u041c\u043e\u043d\u043b\u0435\u0437\u0435\u043d-\u0434'\u0410\u0440\u043c\u0430\u043d\u044c\u044f\u043a"
    ],
    "name:und_x_variant":[
        "Monlezun"
    ],
    "name:vie_x_preferred":[
        "Monlezun-d'Armagnac"
    ],
    "name:vol_x_preferred":[
        "Monlezun-d'Armagnac"
    ],
    "name:war_x_preferred":[
        "Monlezun-d'Armagnac"
    ],
    "name:zho_x_preferred":[
        "\u8499\u52d2\u8d5e\u8fbe\u5c14\u9a6c\u5c3c\u4e9a\u514b"
    ],
    "wof:name":"Monlezun-d'Armagnac",
    "wof:placetype":"locality"
},
  "geometry": {"coordinates":[-0.14689,43.82437],"type":"Point"}
}