{
  "type": "Feature",
  "properties": {
    "gn:admin1_code":"75",
    "gn:admin2_code":"17",
    "gn:admin3_code":"175",
    "gn:admin4_code":"17150",
    "gn:asciiname":"Les Eglises-d'Argenteuil",
    "gn:country_code":"FR",
    "gn:dem":30,
    "gn:feature_class":"P",
    "gn:feature_code":"PPL",
    "gn:name":"Les \u00c9glises-d\u2019Argenteuil",
    "gn:population":0,
    "gn:timezone":"Europe/Paris",
    "iso:country":"FR",
    "name:und_x_variant":[
        "Les \u00c9glises",
        "Les \u00c9glises-d\u2019Argenteuil"
    ],
    "wof:name":"Les Eglises-d'Argenteuil",
    "wof:placetype":"locality"
},
  "geometry": {"coordinates":[-0.43244,45.97304000000001],"type":"Point"}
}