{
  "type": "Feature",
  "properties": {
    "gn:admin1_code":"75",
    "gn:admin2_code":"24",
    "gn:admin3_code":"242",
    "gn:admin4_code":"24180",
    "gn:asciiname":"Pauliac",
    "gn:country_code":"FR",
    "gn:dem":355,
    "gn:feature_class":"P",
    "gn:feature_code":"PPL",
    "gn:name":"Pauliac",
    "gn:population":0,
    "gn:timezone":"Europe/Paris",
    "iso:country":"FR",
    "name:und_x_variant":[
        "Paulhiac",
        "Pauliac"
    ],
    "wof:name":"Pauliac",
    "wof:placetype":"locality"
},
  "geometry": {"coordinates":[0.92792,45.59704],"type":"Point"}
}