{
  "type": "Feature",
  "properties": {
    "gn:admin1_code":"84",
    "gn:admin2_code":"15",
    "gn:admin3_code":"152",
    "gn:admin4_code":"15015",
    "gn:asciiname":"Varleix",
    "gn:country_code":"FR",
    "gn:dem":834,
    "gn:feature_class":"P",
    "gn:feature_code":"PPL",
    "gn:name":"Varleix",
    "gn:population":0,
    "gn:timezone":"Europe/Paris",
    "iso:country":"FR",
    "wof:name":"Varleix",
    "wof:placetype":"locality"
},
  "geometry": {"coordinates":[2.47553,45.26734],"type":"Point"}
}