{
  "type": "Feature",
  "properties": {
    "gn:admin1_code":"27",
    "gn:admin2_code":"21",
    "gn:admin3_code":"213",
    "gn:admin4_code":"21025",
    "gn:asciiname":"La Carolue",
    "gn:country_code":"FR",
    "gn:dem":309,
    "gn:feature_class":"P",
    "gn:feature_code":"PPL",
    "gn:name":"La Carolue",
    "gn:population":0,
    "gn:timezone":"Europe/Paris",
    "iso:country":"FR",
    "wof:name":"La Carolue",
    "wof:placetype":"locality"
},
  "geometry": {"coordinates":[4.34386,47.7008],"type":"Point"}
}