{
  "type": "Feature",
  "properties": {
    "gn:admin1_code":"76",
    "gn:admin2_code":"81",
    "gn:admin3_code":"811",
    "gn:admin4_code":"81094",
    "gn:asciiname":"Fraissines",
    "gn:country_code":"FR",
    "gn:dem":356,
    "gn:feature_class":"P",
    "gn:feature_code":"PPL",
    "gn:name":"Fraissines",
    "gn:population":0,
    "gn:timezone":"Europe/Paris",
    "iso:country":"FR",
    "name:cat_x_preferred":[
        "Fraissinhas"
    ],
    "name:ceb_x_preferred":[
        "Fraissines"
    ],
    "name:deu_x_preferred":[
        "Fraissines"
    ],
    "name:eus_x_preferred":[
        "Fraissines"
    ],
    "name:fra_x_preferred":[
        "Fraissines"
    ],
    "name:hun_x_preferred":[
        "Fraissines"
    ],
    "name:ita_x_preferred":[
        "Fraissines"
    ],
    "name:lat_x_preferred":[
        "Fraissines"
    ],
    "name:msa_x_preferred":[
        "Fraissines"
    ],
    "name:nld_x_preferred":[
        "Fraissines"
    ],
    "name:oci_x_preferred":[
        "Fraissinhas"
    ],
    "name:pol_x_preferred":[
        "Fraissines"
    ],
    "name:ron_x_preferred":[
        "Fraissines"
    ],
    "name:rus_x_preferred":[
        "\u0424\u0440\u0435\u0441\u0441\u0438\u043d"
    ],
    "name:slk_x_preferred":[
        "Fraissines"
    ],
    "name:spa_x_preferred":[
        "Fraissines"
    ],
    "name:srp_x_preferred":[
        "\u0424\u0440\u0435\u0441\u0438\u043d"
    ],
    "name:swe_x_preferred":[
        "Fraissines"
    ],
    "name:ukr_x_preferred":[
        "\u0424\u0440\u0435\u0441\u0441\u0456\u043d"
    ],
    "name:vie_x_preferred":[
        "Fraissines"
    ],
    "name:vol_x_preferred":[
        "Fraissines"
    ],
    "name:war_x_preferred":[
        "Fraissines"
    ],
    "name:zho_x_preferred":[
        "\u5f17\u8d56\u897f\u7eb3"
    ],
    "wof:name":"Fraissines",
    "wof:placetype":"locality"
},
  "geometry": {"coordinates":[2.51667,43.96667],"type":"Point"}
}