{
  "type": "Feature",
  "properties": {
    "gn:admin1_code":"84",
    "gn:admin2_code":"63",
    "gn:admin3_code":"632",
    "gn:admin4_code":"63239",
    "gn:asciiname":"Montmorin",
    "gn:country_code":"FR",
    "gn:dem":588,
    "gn:feature_class":"P",
    "gn:feature_code":"PPL",
    "gn:name":"Montmorin",
    "gn:population":0,
    "gn:timezone":"Europe/Paris",
    "iso:country":"FR",
    "name:ceb_x_preferred":[
        "Montmorin"
    ],
    "name:deu_x_preferred":[
        "Montmorin"
    ],
    "name:fra_x_preferred":[
        "Montmorin"
    ],
    "name:hun_x_preferred":[
        "Montmorin"
    ],
    "name:ita_x_preferred":[
        "Montmorin"
    ],
    "name:nds_x_preferred":[
        "Montmorin"
    ],
    "name:nld_x_preferred":[
        "Montmorin"
    ],
    "name:pms_x_preferred":[
        "Montmorin"
    ],
    "name:pol_x_preferred":[
        "Montmorin"
    ],
    "name:por_x_preferred":[
        "Montmorin"
    ],
    "name:rus_x_preferred":[
        "\u041c\u043e\u043d\u043c\u043e\u0440\u0435\u043d"
    ],
    "name:slk_x_preferred":[
        "Montmorin"
    ],
    "name:spa_x_preferred":[
        "Montmorin"
    ],
    "name:swe_x_preferred":[
        "Montmorin"
    ],
    "name:ukr_x_preferred":[
        "\u041c\u043e\u043d\u043c\u043e\u0440\u0435\u043d"
    ],
    "wof:name":"Montmorin",
    "wof:placetype":"locality"
},
  "geometry": {"coordinates":[3.36094,45.69576],"type":"Point"}
}