{
  "type": "Feature",
  "properties": {
    "frgov:code_epci":"200067627",
    "frgov:insee_arr":"2",
    "frgov:insee_com":"63239",
    "frgov:insee_dep":"63",
    "frgov:insee_reg":"84",
    "frgov:nom_com":"Montmorin",
    "frgov:nom_com_m":"MONTMORIN",
    "frgov:nom_dep":"PUY-DE-DOME",
    "frgov:nom_reg":"AUVERGNE-RHONE-ALPES",
    "frgov:statut":"Commune simple",
    "gn:admin1_code":"84",
    "gn:admin2_code":"63",
    "gn:admin3_code":"632",
    "gn:admin4_code":"63239",
    "gn:asciiname":"Montmorin",
    "gn:country_code":"FR",
    "gn:dem":588,
    "gn:feature_class":"P",
    "gn:feature_code":"PPL",
    "gn:name":"Montmorin",
    "gn:population":0,
    "gn:timezone":"Europe/Paris",
    "iso:country":"FR",
    "name:cat_x_preferred":[
        "Montmaurin"
    ],
    "name:ceb_x_preferred":[
        "Montmorin"
    ],
    "name:deu_x_preferred":[
        "Montmorin"
    ],
    "name:fra_x_preferred":[
        "Montmorin"
    ],
    "name:hun_x_preferred":[
        "Montmorin"
    ],
    "name:ita_x_preferred":[
        "Montmorin"
    ],
    "name:kaz_x_preferred":[
        "\u041c\u043e\u043d\u043c\u043e\u0440\u0435\u043d"
    ],
    "name:nds_x_preferred":[
        "Montmorin"
    ],
    "name:nld_x_preferred":[
        "Montmorin"
    ],
    "name:pms_x_preferred":[
        "Montmorin"
    ],
    "name:pol_x_preferred":[
        "Montmorin"
    ],
    "name:por_x_preferred":[
        "Montmorin"
    ],
    "name:rus_x_preferred":[
        "\u041c\u043e\u043d\u043c\u043e\u0440\u0435\u043d"
    ],
    "name:slk_x_preferred":[
        "Montmorin"
    ],
    "name:spa_x_preferred":[
        "Montmorin"
    ],
    "name:swe_x_preferred":[
        "Montmorin"
    ],
    "name:ukr_x_preferred":[
        "\u041c\u043e\u043d\u043c\u043e\u0440\u0435\u043d"
    ],
    "name:zho_x_preferred":[
        "\u8499\u7279\u83ab\u5170"
    ],
    "qs:a0":"France",
    "qs:a1":"PUY-DE-DOME",
    "qs:a1_lc":"63",
    "qs:a1r":"AUVERGNE",
    "qs:a1r_lc":"83",
    "qs:a2_lc":"06",
    "qs:a2r_lc":"2",
    "qs:adm0":"France",
    "qs:adm0_a3":"FRA",
    "qs:la":"MONTMORIN",
    "qs:la_lc":"63239",
    "qs:level":"localadmin",
    "qs:type":"Commune simple",
    "wof:coterminous":[
        404363387
    ],
    "wof:name":"Montmorin",
    "wof:placetype":"locality",
    "wof:placetype_local":"Commune simple"
},
  "geometry": {"coordinates":[3.36094,45.69576],"type":"Point"}
}