{
  "type": "Feature",
  "properties": {
    "gn:admin1_code":"84",
    "gn:admin2_code":"63",
    "gn:admin3_code":"632",
    "gn:admin4_code":"63239",
    "gn:asciiname":"Montmorin",
    "gn:country_code":"FR",
    "gn:dem":588,
    "gn:feature_class":"P",
    "gn:feature_code":"PPL",
    "gn:name":"Montmorin",
    "gn:population":0,
    "gn:timezone":"Europe/Paris",
    "iso:country":"FR",
    "wof:name":"Montmorin",
    "wof:placetype":"locality"
},
  "geometry": {"coordinates":[3.36094,45.69576],"type":"Point"}
}