{
  "type": "Feature",
  "properties": {
    "gn:admin1_code":"84",
    "gn:admin2_code":"63",
    "gn:admin3_code":"635",
    "gn:admin4_code":"63393",
    "gn:asciiname":"Fracard",
    "gn:country_code":"FR",
    "gn:dem":605,
    "gn:feature_class":"P",
    "gn:feature_code":"PPL",
    "gn:name":"Fracard",
    "gn:population":0,
    "gn:timezone":"Europe/Paris",
    "iso:country":"FR",
    "wof:name":"Fracard",
    "wof:placetype":"locality"
},
  "geometry": {"coordinates":[3.54954,45.88928],"type":"Point"}
}