{
  "type": "Feature",
  "properties": {
    "iso:country":"FR",
    "name:ceb_x_preferred":[
        "Sainte-Marthe"
    ],
    "name:deu_x_preferred":[
        "Sainte-Marthe"
    ],
    "name:fra_x_preferred":[
        "Sainte-Marthe"
    ],
    "name:ita_x_preferred":[
        "Sainte-Marthe"
    ],
    "name:nds_x_preferred":[
        "Sainte-Marthe"
    ],
    "name:nld_x_preferred":[
        "Sainte-Marthe"
    ],
    "name:oci_x_preferred":[
        "Sainte-Marthe"
    ],
    "name:pms_x_preferred":[
        "Sainte-Marthe"
    ],
    "name:pol_x_preferred":[
        "Sainte-Marthe"
    ],
    "name:por_x_preferred":[
        "Sainte-Marthe"
    ],
    "name:rus_x_preferred":[
        "\u0421\u0435\u043d\u0442-\u041c\u0430\u0440\u0442"
    ],
    "name:slk_x_preferred":[
        "Sainte-Marthe"
    ],
    "name:spa_x_preferred":[
        "Sainte-Marthe"
    ],
    "name:swe_x_preferred":[
        "Sainte-Marthe"
    ],
    "name:ukr_x_preferred":[
        "\u0421\u0435\u043d\u0442-\u041c\u0430\u0440\u0442"
    ],
    "wof:name":"Sainte-Marthe",
    "wof:placetype":"neighbourhood"
},
  "geometry": {"coordinates":[5.39384109943106,43.34092195868201],"type":"Point"}
}