{
  "type": "Feature",
  "properties": {
    "gn:admin1_code":"84",
    "gn:admin2_code":"38",
    "gn:admin3_code":"381",
    "gn:admin4_code":"38226",
    "gn:asciiname":"Saint-Genis",
    "gn:country_code":"FR",
    "gn:dem":875,
    "gn:feature_class":"P",
    "gn:feature_code":"PPL",
    "gn:name":"Saint-Genis",
    "gn:population":0,
    "gn:timezone":"Europe/Paris",
    "iso:country":"FR",
    "name:deu_x_preferred":[
        "Saint-Genis"
    ],
    "name:fra_x_preferred":[
        "Saint-Genis"
    ],
    "name:nld_x_preferred":[
        "Saint-Genis"
    ],
    "name:swe_x_preferred":[
        "Saint-Genis"
    ],
    "wof:name":"Saint-Genis",
    "wof:placetype":"locality"
},
  "geometry": {"coordinates":[5.77038,44.82155],"type":"Point"}
}