{
  "type": "Feature",
  "properties": {
    "gn:admin1_code":"84",
    "gn:admin2_code":"63",
    "gn:admin3_code":"632",
    "gn:admin4_code":"63449",
    "gn:asciiname":"Mareuge",
    "gn:country_code":"FR",
    "gn:dem":1044,
    "gn:feature_class":"P",
    "gn:feature_code":"PPL",
    "gn:name":"Mareuge",
    "gn:population":0,
    "gn:timezone":"Europe/Paris",
    "iso:country":"FR",
    "wof:name":"Mareuge",
    "wof:placetype":"locality"
},
  "geometry": {"coordinates":[2.9284,45.62316],"type":"Point"}
}