{
  "type": "Feature",
  "properties": {
    "gn:admin1_code":"27",
    "gn:admin2_code":"58",
    "gn:admin3_code":"584",
    "gn:admin4_code":"58007.0",
    "gn:asciiname":"Sermaize",
    "gn:country_code":"FR",
    "gn:dem":184,
    "gn:feature_class":"P",
    "gn:feature_code":"PPL",
    "gn:name":"Sermaize",
    "gn:population":0,
    "gn:timezone":"Europe/Paris",
    "iso:country":"FR",
    "name:bre_x_preferred":[
        "Sermaize"
    ],
    "name:cat_x_preferred":[
        "Sermaize"
    ],
    "name:ceb_x_preferred":[
        "Sermaize"
    ],
    "name:deu_x_preferred":[
        "Sermaize"
    ],
    "name:eus_x_preferred":[
        "Sermaize"
    ],
    "name:fra_x_preferred":[
        "Sermaize"
    ],
    "name:hun_x_preferred":[
        "Sermaize"
    ],
    "name:ind_x_preferred":[
        "Sermaize"
    ],
    "name:ita_x_preferred":[
        "Sermaize"
    ],
    "name:lat_x_preferred":[
        "Sermaize"
    ],
    "name:mlg_x_preferred":[
        "Sermaize"
    ],
    "name:msa_x_preferred":[
        "Sermaize"
    ],
    "name:nld_x_preferred":[
        "Sermaize"
    ],
    "name:oci_x_preferred":[
        "Sermaize"
    ],
    "name:pms_x_preferred":[
        "Sermaize"
    ],
    "name:pol_x_preferred":[
        "Sermaize"
    ],
    "name:por_x_preferred":[
        "Sermaize"
    ],
    "name:ron_x_preferred":[
        "Sermaize"
    ],
    "name:slk_x_preferred":[
        "Sermaize"
    ],
    "name:spa_x_preferred":[
        "Sermaize"
    ],
    "name:swe_x_preferred":[
        "Sermaize"
    ],
    "name:ukr_x_preferred":[
        "\u0421\u0435\u0440\u043c\u0435\u0437"
    ],
    "name:uzb_x_preferred":[
        "Sermaize"
    ],
    "name:vie_x_preferred":[
        "Sermaize"
    ],
    "name:vol_x_preferred":[
        "Sermaize"
    ],
    "name:war_x_preferred":[
        "Sermaize"
    ],
    "name:zho_x_preferred":[
        "\u585e\u5c14\u8fc8\u5179"
    ],
    "wof:name":"Sermaize",
    "wof:placetype":"locality"
},
  "geometry": {"coordinates":[2.92028,47.56058],"type":"Point"}
}