{
  "type": "Feature",
  "properties": {
    "gn:admin1_code":"44",
    "gn:admin2_code":"08",
    "gn:admin3_code":"083",
    "gn:admin4_code":"08349",
    "gn:asciiname":"Messempre",
    "gn:country_code":"FR",
    "gn:dem":189,
    "gn:feature_class":"P",
    "gn:feature_code":"PPL",
    "gn:name":"Messempr\u00e9",
    "gn:population":0,
    "gn:timezone":"Europe/Paris",
    "iso:country":"FR",
    "name:und_x_variant":[
        "Messempr\u00e9"
    ],
    "wof:name":"Messempre",
    "wof:placetype":"locality"
},
  "geometry": {"coordinates":[5.16409,49.6774],"type":"Point"}
}