{
  "type": "Feature",
  "properties": {
    "gn:admin1_code":"53",
    "gn:admin2_code":"35",
    "gn:admin3_code":"354",
    "gn:admin4_code":"35288",
    "gn:asciiname":"Intra Muros",
    "gn:country_code":"FR",
    "gn:dem":26,
    "gn:elevation":"24.0",
    "gn:feature_class":"P",
    "gn:feature_code":"PPL",
    "gn:name":"Intra Muros",
    "gn:population":0,
    "gn:timezone":"Europe/Paris",
    "iso:country":"FR",
    "wof:name":"Intra Muros",
    "wof:placetype":"locality"
},
  "geometry": {"coordinates":[-2.02573,48.64845],"type":"Point"}
}