{
  "type": "Feature",
  "properties": {
    "gn:admin1_code":"75",
    "gn:admin2_code":"19",
    "gn:admin3_code":"192",
    "gn:admin4_code":"19039",
    "gn:asciiname":"Feix",
    "gn:country_code":"FR",
    "gn:dem":551,
    "gn:feature_class":"P",
    "gn:feature_code":"PPL",
    "gn:name":"Feix",
    "gn:population":0,
    "gn:timezone":"Europe/Paris",
    "iso:country":"FR",
    "wof:name":"Feix",
    "wof:placetype":"locality"
},
  "geometry": {"coordinates":[1.98874,45.28628],"type":"Point"}
}