{
  "type": "Feature",
  "properties": {
    "gn:admin1_code":"44",
    "gn:admin2_code":"08",
    "gn:admin3_code":"084",
    "gn:admin4_code":"08045",
    "gn:asciiname":"La Noue-Adam",
    "gn:country_code":"FR",
    "gn:dem":148,
    "gn:feature_class":"P",
    "gn:feature_code":"PPL",
    "gn:name":"La Nou\u00e9-Adam",
    "gn:population":0,
    "gn:timezone":"Europe/Paris",
    "iso:country":"FR",
    "wof:name":"La Noue-Adam",
    "wof:placetype":"locality"
},
  "geometry": {"coordinates":[4.75965,49.42116],"type":"Point"}
}