{
  "type": "Feature",
  "properties": {
    "gn:admin1_code":"84",
    "gn:admin2_code":"07",
    "gn:admin3_code":"073",
    "gn:admin4_code":"07054",
    "gn:asciiname":"Bois Lantal",
    "gn:country_code":"FR",
    "gn:dem":804,
    "gn:feature_class":"P",
    "gn:feature_code":"PPL",
    "gn:name":"Bois Lantal",
    "gn:population":0,
    "gn:timezone":"Europe/Paris",
    "iso:country":"FR",
    "wof:name":"Bois Lantal",
    "wof:placetype":"locality"
},
  "geometry": {"coordinates":[4.29506,44.92294],"type":"Point"}
}