{
  "type": "Feature",
  "properties": {
    "iso:country":"FR",
    "name:eng_x_preferred":[
        "Lapalisse - P\u00e9rigny Airport"
    ],
    "name:msa_x_preferred":[
        "Lapangan Terbang Perigny"
    ],
    "oa:elevation_ft":"1040",
    "oa:type":"small_airport",
    "woe:hierarchy":{
        "country_id":23424819,
        "county_id":12597131,
        "localadmin_id":22755181,
        "planet_id":1,
        "state_id":7153310
    },
    "wof:name":"A\u00e9rodrome de Lapalisse-p\u00e9rigny",
    "wof:placetype":"campus"
},
  "geometry": {"coordinates":[3.5875,46.2531],"type":"Point"}
}