{
  "type": "Feature",
  "properties": {
    "gn:admin1_code":"52",
    "gn:admin2_code":"72",
    "gn:admin3_code":"722",
    "gn:admin4_code":"72300",
    "gn:asciiname":"La Chenaie",
    "gn:country_code":"FR",
    "gn:dem":75,
    "gn:feature_class":"P",
    "gn:feature_code":"PPL",
    "gn:name":"La Chenaie",
    "gn:population":0,
    "gn:timezone":"Europe/Paris",
    "iso:country":"FR",
    "wof:name":"La Chenaie",
    "wof:placetype":"locality"
},
  "geometry": {"coordinates":[0.36501,48.04682],"type":"Point"}
}