{
  "type": "Feature",
  "properties": {
    "gn:admin1_code":"93",
    "gn:admin2_code":"13",
    "gn:admin3_code":"131",
    "gn:admin4_code":"13001",
    "gn:asciiname":"Les Platrieres",
    "gn:country_code":"FR",
    "gn:dem":323,
    "gn:feature_class":"P",
    "gn:feature_code":"PPL",
    "gn:name":"Les Platri\u00e8res",
    "gn:population":0,
    "gn:timezone":"Europe/Paris",
    "iso:country":"FR",
    "wof:name":"Les Platrieres",
    "wof:placetype":"locality"
},
  "geometry": {"coordinates":[5.43333,43.55],"type":"Point"}
}