{
  "type": "Feature",
  "properties": {
    "gn:admin1_code":"84",
    "gn:admin2_code":"73",
    "gn:admin3_code":"731",
    "gn:admin4_code":"73227",
    "gn:asciiname":"Courchevel 1650",
    "gn:country_code":"FR",
    "gn:dem":1566,
    "gn:feature_class":"P",
    "gn:feature_code":"PPL",
    "gn:name":"Courchevel 1650",
    "gn:population":0,
    "gn:timezone":"Europe/Paris",
    "iso:country":"FR",
    "name:fra_x_preferred":[
        "Courchevel Moriond"
    ],
    "name:und_x_variant":[
        "Courchevel Moriond"
    ],
    "wof:name":"Courchevel 1650",
    "wof:placetype":"locality"
},
  "geometry": {"coordinates":[6.65068,45.41683],"type":"Point"}
}