{
  "type": "Feature",
  "properties": {
    "gn:admin1_code":"27",
    "gn:admin2_code":"89",
    "gn:admin3_code":"892",
    "gn:admin4_code":"89061",
    "gn:asciiname":"La Chaussee",
    "gn:country_code":"FR",
    "gn:dem":110,
    "gn:feature_class":"P",
    "gn:feature_code":"PPL",
    "gn:name":"La Chauss\u00e9e",
    "gn:population":0,
    "gn:timezone":"Europe/Paris",
    "iso:country":"FR",
    "wof:name":"La Chaussee",
    "wof:placetype":"locality"
},
  "geometry": {"coordinates":[3.83294,47.99718],"type":"Point"}
}