{
  "type": "Feature",
  "properties": {
    "gn:admin1_code":"84",
    "gn:admin2_code":"03",
    "gn:admin3_code":"031",
    "gn:admin4_code":"03158",
    "gn:asciiname":"Verigny",
    "gn:country_code":"FR",
    "gn:dem":238,
    "gn:feature_class":"P",
    "gn:feature_code":"PPL",
    "gn:name":"V\u00e9rigny",
    "gn:population":0,
    "gn:timezone":"Europe/Paris",
    "iso:country":"FR",
    "wof:name":"Verigny",
    "wof:placetype":"locality"
},
  "geometry": {"coordinates":[2.63305,46.48914],"type":"Point"}
}