{
  "type": "Feature",
  "properties": {
    "gn:admin1_code":"11",
    "gn:admin2_code":"77",
    "gn:admin3_code":"775",
    "gn:admin4_code":"77350",
    "gn:asciiname":"Doutre",
    "gn:country_code":"FR",
    "gn:dem":108,
    "gn:feature_class":"P",
    "gn:feature_code":"PPL",
    "gn:name":"Doutre",
    "gn:population":0,
    "gn:timezone":"Europe/Paris",
    "iso:country":"FR",
    "wof:name":"Doutre",
    "wof:placetype":"locality"
},
  "geometry": {"coordinates":[2.6708,48.76967],"type":"Point"}
}