{
  "type": "Feature",
  "properties": {
    "frgov:code_epci":"200040137",
    "frgov:insee_arr":"1",
    "frgov:insee_com":"10315",
    "frgov:insee_dep":"10",
    "frgov:insee_reg":"44",
    "frgov:nom_com":"Rances",
    "frgov:nom_com_m":"RANCES",
    "frgov:nom_dep":"AUBE",
    "frgov:nom_reg":"GRAND EST",
    "frgov:statut":"Commune simple",
    "gn:admin1_code":"44",
    "gn:admin2_code":"10",
    "gn:admin3_code":"101",
    "gn:admin4_code":"10315",
    "gn:asciiname":"Rances",
    "gn:country_code":"FR",
    "gn:dem":113,
    "gn:feature_class":"P",
    "gn:feature_code":"PPL",
    "gn:name":"Rances",
    "gn:population":46,
    "gn:timezone":"Europe/Paris",
    "iso:country":"FR",
    "name:als_x_preferred":[
        "Rances"
    ],
    "name:ceb_x_preferred":[
        "Rances"
    ],
    "name:deu_x_preferred":[
        "Rances"
    ],
    "name:epo_x_preferred":[
        "Rances"
    ],
    "name:eus_x_preferred":[
        "Rances"
    ],
    "name:fra_x_preferred":[
        "Rances"
    ],
    "name:ita_x_preferred":[
        "Rances"
    ],
    "name:lmo_x_preferred":[
        "Rances"
    ],
    "name:msa_x_preferred":[
        "Rances"
    ],
    "name:nld_x_preferred":[
        "Rances"
    ],
    "name:nno_x_preferred":[
        "Rances"
    ],
    "name:por_x_preferred":[
        "Rances"
    ],
    "name:roh_x_preferred":[
        "Rances"
    ],
    "name:spa_x_preferred":[
        "Rances"
    ],
    "name:swe_x_preferred":[
        "Rances"
    ],
    "name:vie_x_preferred":[
        "Rances"
    ],
    "name:vol_x_preferred":[
        "Rances"
    ],
    "qs:a0":"France",
    "qs:a1":"AUBE",
    "qs:a1_lc":"10",
    "qs:a1r":"CHAMPAGNE-ARDENNE",
    "qs:a1r_lc":"21",
    "qs:a2_lc":"06",
    "qs:a2r_lc":"1",
    "qs:adm0":"France",
    "qs:adm0_a3":"FRA",
    "qs:la":"RANCES",
    "qs:la_lc":"10315",
    "qs:level":"localadmin",
    "qs:type":"Commune simple",
    "wof:coterminous":[
        404404985
    ],
    "wof:name":"Rances",
    "wof:placetype":"locality",
    "wof:placetype_local":"Commune simple",
    "wof:population":46
},
  "geometry": {"coordinates":[4.54661,48.46615],"type":"Point"}
}