{
  "type": "Feature",
  "properties": {
    "gn:admin1_code":"44",
    "gn:admin2_code":"10",
    "gn:admin3_code":"101",
    "gn:admin4_code":"10315",
    "gn:asciiname":"Rances",
    "gn:country_code":"FR",
    "gn:dem":113,
    "gn:feature_class":"P",
    "gn:feature_code":"PPL",
    "gn:name":"Rances",
    "gn:population":46,
    "gn:timezone":"Europe/Paris",
    "iso:country":"FR",
    "name:als_x_preferred":[
        "Rances"
    ],
    "name:ceb_x_preferred":[
        "Rances"
    ],
    "name:deu_x_preferred":[
        "Rances"
    ],
    "name:epo_x_preferred":[
        "Rances"
    ],
    "name:eus_x_preferred":[
        "Rances"
    ],
    "name:fra_x_preferred":[
        "Rances"
    ],
    "name:ita_x_preferred":[
        "Rances"
    ],
    "name:lmo_x_preferred":[
        "Rances"
    ],
    "name:msa_x_preferred":[
        "Rances"
    ],
    "name:nld_x_preferred":[
        "Rances"
    ],
    "name:nno_x_preferred":[
        "Rances"
    ],
    "name:por_x_preferred":[
        "Rances"
    ],
    "name:roh_x_preferred":[
        "Rances"
    ],
    "name:spa_x_preferred":[
        "Rances"
    ],
    "name:swe_x_preferred":[
        "Rances"
    ],
    "name:vie_x_preferred":[
        "Rances"
    ],
    "name:vol_x_preferred":[
        "Rances"
    ],
    "wof:name":"Rances",
    "wof:placetype":"locality",
    "wof:population":46
},
  "geometry": {"coordinates":[4.54661,48.46615],"type":"Point"}
}