{
  "type": "Feature",
  "properties": {
    "gn:admin1_code":"24",
    "gn:admin2_code":"45",
    "gn:admin3_code":"451",
    "gn:admin4_code":"45222.0",
    "gn:asciiname":"Villiers",
    "gn:country_code":"FR",
    "gn:dem":99,
    "gn:feature_class":"P",
    "gn:feature_code":"PPL",
    "gn:name":"Villiers",
    "gn:population":0,
    "gn:timezone":"Europe/Paris",
    "iso:country":"FR",
    "wof:name":"Villiers",
    "wof:placetype":"locality"
},
  "geometry": {"coordinates":[2.72636,48.11414],"type":"Point"}
}