{
  "type": "Feature",
  "properties": {
    "gn:admin1_code":"84",
    "gn:admin2_code":"73",
    "gn:admin3_code":"731",
    "gn:admin4_code":"73132",
    "gn:asciiname":"Les Pres",
    "gn:country_code":"FR",
    "gn:dem":1211,
    "gn:feature_class":"P",
    "gn:feature_code":"PPL",
    "gn:name":"Les Pr\u00e9s",
    "gn:population":0,
    "gn:timezone":"Europe/Paris",
    "iso:country":"FR",
    "name:und_x_variant":[
        "Le Pr\u00e9",
        "Les Pr\u00e9s"
    ],
    "wof:name":"Les Pres",
    "wof:placetype":"locality"
},
  "geometry": {"coordinates":[6.61391,45.76347],"type":"Point"}
}