{
  "type": "Feature",
  "properties": {
    "gn:admin1_code":"84",
    "gn:admin2_code":"63",
    "gn:admin3_code":"632",
    "gn:admin4_code":"63417",
    "gn:asciiname":"Argnat",
    "gn:country_code":"FR",
    "gn:dem":614,
    "gn:feature_class":"P",
    "gn:feature_code":"PPL",
    "gn:name":"Argnat",
    "gn:population":0,
    "gn:timezone":"Europe/Paris",
    "iso:country":"FR",
    "wof:name":"Argnat",
    "wof:placetype":"locality"
},
  "geometry": {"coordinates":[3.03454,45.84587],"type":"Point"}
}