{
  "type": "Feature",
  "properties": {
    "gn:admin1_code":"84",
    "gn:admin2_code":"43",
    "gn:admin3_code":"432",
    "gn:admin4_code":"43023",
    "gn:asciiname":"Cheyrac-l'Aigue",
    "gn:country_code":"FR",
    "gn:dem":920,
    "gn:feature_class":"P",
    "gn:feature_code":"PPL",
    "gn:name":"Cheyrac-l\u2019Aigue",
    "gn:population":0,
    "gn:timezone":"Europe/Paris",
    "iso:country":"FR",
    "wof:name":"Cheyrac-l'Aigue",
    "wof:placetype":"locality"
},
  "geometry": {"coordinates":[3.80976,45.29331],"type":"Point"}
}