{
  "type": "Feature",
  "properties": {
    "gn:admin1_code":"27",
    "gn:admin2_code":"58",
    "gn:admin3_code":"581",
    "gn:admin4_code":"58135",
    "gn:asciiname":"Isenay",
    "gn:country_code":"FR",
    "gn:dem":242,
    "gn:feature_class":"P",
    "gn:feature_code":"PPL",
    "gn:name":"Isenay",
    "gn:population":0,
    "gn:timezone":"Europe/Paris",
    "iso:country":"FR",
    "name:cat_x_preferred":[
        "Isenay"
    ],
    "name:ceb_x_preferred":[
        "Isenay"
    ],
    "name:deu_x_preferred":[
        "Isenay"
    ],
    "name:eus_x_preferred":[
        "Isenay"
    ],
    "name:fra_x_preferred":[
        "Isenay"
    ],
    "name:hun_x_preferred":[
        "Isenay"
    ],
    "name:ita_x_preferred":[
        "Isenay"
    ],
    "name:kaz_x_preferred":[
        "\u0418\u0437\u043d\u0435"
    ],
    "name:lat_x_preferred":[
        "Ysenaium"
    ],
    "name:msa_x_preferred":[
        "Isenay"
    ],
    "name:nld_x_preferred":[
        "Isenay"
    ],
    "name:oci_x_preferred":[
        "Isenay"
    ],
    "name:pms_x_preferred":[
        "Isenay"
    ],
    "name:pol_x_preferred":[
        "Isenay"
    ],
    "name:por_x_preferred":[
        "Isenay"
    ],
    "name:ron_x_preferred":[
        "Isenay"
    ],
    "name:slk_x_preferred":[
        "Isenay"
    ],
    "name:spa_x_preferred":[
        "Isenay"
    ],
    "name:swe_x_preferred":[
        "Isenay"
    ],
    "name:ukr_x_preferred":[
        "\u0406\u0437\u043d\u0435"
    ],
    "name:uzb_x_preferred":[
        "Isenay"
    ],
    "name:vie_x_preferred":[
        "Isenay"
    ],
    "name:vol_x_preferred":[
        "Isenay"
    ],
    "name:war_x_preferred":[
        "Isenay"
    ],
    "name:zho_x_preferred":[
        "\u4f0a\u745f\u5948"
    ],
    "wof:name":"Isenay",
    "wof:placetype":"locality"
},
  "geometry": {"coordinates":[3.70548,46.90184],"type":"Point"}
}