{
  "type": "Feature",
  "properties": {
    "frgov:code_epci":"200067882",
    "frgov:insee_arr":"1",
    "frgov:insee_com":"58135",
    "frgov:insee_dep":"58",
    "frgov:insee_reg":"27",
    "frgov:nom_com":"Isenay",
    "frgov:nom_com_m":"ISENAY",
    "frgov:nom_dep":"NIEVRE",
    "frgov:nom_reg":"BOURGOGNE-FRANCHE-COMTE",
    "frgov:statut":"Commune simple",
    "gn:admin1_code":"27",
    "gn:admin2_code":"58",
    "gn:admin3_code":"581",
    "gn:admin4_code":"58135",
    "gn:asciiname":"Isenay",
    "gn:country_code":"FR",
    "gn:dem":242,
    "gn:feature_class":"P",
    "gn:feature_code":"PPL",
    "gn:name":"Isenay",
    "gn:population":0,
    "gn:timezone":"Europe/Paris",
    "iso:country":"FR",
    "name:cat_x_preferred":[
        "Isenay"
    ],
    "name:ceb_x_preferred":[
        "Isenay"
    ],
    "name:deu_x_preferred":[
        "Isenay"
    ],
    "name:eus_x_preferred":[
        "Isenay"
    ],
    "name:fra_x_preferred":[
        "Isenay"
    ],
    "name:hun_x_preferred":[
        "Isenay"
    ],
    "name:ita_x_preferred":[
        "Isenay"
    ],
    "name:kaz_x_preferred":[
        "\u0418\u0437\u043d\u0435"
    ],
    "name:lat_x_preferred":[
        "Ysenaium"
    ],
    "name:msa_x_preferred":[
        "Isenay"
    ],
    "name:nld_x_preferred":[
        "Isenay"
    ],
    "name:oci_x_preferred":[
        "Isenay"
    ],
    "name:pms_x_preferred":[
        "Isenay"
    ],
    "name:pol_x_preferred":[
        "Isenay"
    ],
    "name:por_x_preferred":[
        "Isenay"
    ],
    "name:ron_x_preferred":[
        "Isenay"
    ],
    "name:slk_x_preferred":[
        "Isenay"
    ],
    "name:spa_x_preferred":[
        "Isenay"
    ],
    "name:swe_x_preferred":[
        "Isenay"
    ],
    "name:ukr_x_preferred":[
        "\u0406\u0437\u043d\u0435"
    ],
    "name:uzb_x_preferred":[
        "Isenay"
    ],
    "name:vie_x_preferred":[
        "Isenay"
    ],
    "name:vol_x_preferred":[
        "Isenay"
    ],
    "name:war_x_preferred":[
        "Isenay"
    ],
    "name:zho_x_preferred":[
        "\u4f0a\u745f\u5948"
    ],
    "qs:a0":"France",
    "qs:a1":"NIEVRE",
    "qs:a1_lc":"58",
    "qs:a1r":"BOURGOGNE",
    "qs:a1r_lc":"26",
    "qs:a2_lc":"15",
    "qs:a2r_lc":"1",
    "qs:adm0":"France",
    "qs:adm0_a3":"FRA",
    "qs:la":"ISENAY",
    "qs:la_lc":"58135",
    "qs:level":"localadmin",
    "qs:type":"Commune simple",
    "wof:coterminous":[
        404363581
    ],
    "wof:name":"Isenay",
    "wof:placetype":"locality",
    "wof:placetype_local":"Commune simple"
},
  "geometry": {"coordinates":[3.70548,46.90184],"type":"Point"}
}