{
  "type": "Feature",
  "properties": {
    "gn:admin1_code":"11",
    "gn:admin2_code":"78",
    "gn:admin3_code":"781",
    "gn:admin4_code":"78089",
    "gn:asciiname":"Morvent",
    "gn:country_code":"FR",
    "gn:dem":113,
    "gn:feature_class":"P",
    "gn:feature_code":"PPL",
    "gn:name":"Morvent",
    "gn:population":0,
    "gn:timezone":"Europe/Paris",
    "iso:country":"FR",
    "wof:name":"Morvent",
    "wof:placetype":"locality"
},
  "geometry": {"coordinates":[1.56906,49.01823],"type":"Point"}
}