{
  "type": "Feature",
  "properties": {
    "gn:admin1_code":"75",
    "gn:admin2_code":"17",
    "gn:admin3_code":"172",
    "gn:admin4_code":"17375",
    "gn:asciiname":"Lupin",
    "gn:country_code":"FR",
    "gn:dem":4,
    "gn:feature_class":"P",
    "gn:feature_code":"PPL",
    "gn:name":"Lupin",
    "gn:population":0,
    "gn:timezone":"Europe/Paris",
    "iso:country":"FR",
    "name:und_x_variant":[
        "Le Passage",
        "Lupin"
    ],
    "wof:name":"Lupin",
    "wof:placetype":"locality"
},
  "geometry": {"coordinates":[-1.03445,45.95294000000001],"type":"Point"}
}