{
  "type": "Feature",
  "properties": {
    "gn:admin1_code":"28",
    "gn:admin2_code":"76",
    "gn:admin3_code":"761",
    "gn:admin4_code":"76567.0",
    "gn:asciiname":"Les Craffeux",
    "gn:country_code":"FR",
    "gn:dem":226,
    "gn:feature_class":"P",
    "gn:feature_code":"PPL",
    "gn:name":"Les Craffeux",
    "gn:population":0,
    "gn:timezone":"Europe/Paris",
    "iso:country":"FR",
    "wof:name":"Les Craffeux",
    "wof:placetype":"locality"
},
  "geometry": {"coordinates":[1.53973,49.78187],"type":"Point"}
}