{
  "type": "Feature",
  "properties": {
    "gn:admin1_code":"32",
    "gn:admin2_code":"80",
    "gn:admin3_code":"804",
    "gn:admin4_code":"80555",
    "gn:asciiname":"Montecourt",
    "gn:country_code":"FR",
    "gn:dem":62,
    "gn:feature_class":"P",
    "gn:feature_code":"PPL",
    "gn:name":"Montecourt",
    "gn:population":0,
    "gn:timezone":"Europe/Paris",
    "iso:country":"FR",
    "wof:name":"Montecourt",
    "wof:placetype":"locality"
},
  "geometry": {"coordinates":[3.03694,49.85483],"type":"Point"}
}