{
  "type": "Feature",
  "properties": {
    "gn:admin1_code":"84",
    "gn:admin2_code":"43",
    "gn:admin3_code":"431",
    "gn:admin4_code":"43151",
    "gn:asciiname":"Boisserette",
    "gn:country_code":"FR",
    "gn:dem":942,
    "gn:feature_class":"P",
    "gn:feature_code":"PPL",
    "gn:name":"Boisserette",
    "gn:population":0,
    "gn:timezone":"Europe/Paris",
    "iso:country":"FR",
    "wof:name":"Boisserette",
    "wof:placetype":"locality"
},
  "geometry": {"coordinates":[3.42682,45.06757],"type":"Point"}
}