{
  "type": "Feature",
  "properties": {
    "gn:admin1_code":"75",
    "gn:admin2_code":"19",
    "gn:admin3_code":"193",
    "gn:admin4_code":"19055",
    "gn:asciiname":"Eyboulet",
    "gn:country_code":"FR",
    "gn:dem":634,
    "gn:feature_class":"P",
    "gn:feature_code":"PPL",
    "gn:name":"Eyboulet",
    "gn:population":0,
    "gn:timezone":"Europe/Paris",
    "iso:country":"FR",
    "wof:name":"Eyboulet",
    "wof:placetype":"locality"
},
  "geometry": {"coordinates":[2.33333,45.45],"type":"Point"}
}