{
  "type": "Feature",
  "properties": {
    "gn:admin1_code":"76",
    "gn:admin2_code":"66",
    "gn:admin3_code":"661",
    "gn:admin4_code":"66106",
    "gn:asciiname":"Riunoguers",
    "gn:country_code":"FR",
    "gn:dem":348,
    "gn:feature_class":"P",
    "gn:feature_code":"PPL",
    "gn:name":"Riunoguers",
    "gn:population":0,
    "gn:timezone":"Europe/Paris",
    "iso:country":"FR",
    "name:cat_x_preferred":[
        "Riunoguers"
    ],
    "name:fra_x_preferred":[
        "Riunogu\u00e8s"
    ],
    "wof:name":"Riunoguers",
    "wof:placetype":"locality"
},
  "geometry": {"coordinates":[2.81997,42.46203],"type":"Point"}
}