{
  "type": "Feature",
  "properties": {
    "gn:admin1_code":"52",
    "gn:admin2_code":"44",
    "gn:admin3_code":"444",
    "gn:admin4_code":"44082",
    "gn:asciiname":"Prefoure",
    "gn:country_code":"FR",
    "gn:dem":16,
    "gn:feature_class":"P",
    "gn:feature_code":"PPL",
    "gn:name":"Pr\u00e9foure",
    "gn:population":0,
    "gn:timezone":"Europe/Paris",
    "iso:country":"FR",
    "wof:name":"Prefoure",
    "wof:placetype":"locality"
},
  "geometry": {"coordinates":[-1.41441,47.41584],"type":"Point"}
}