{
  "type": "Feature",
  "properties": {
    "gn:admin1_code":"53",
    "gn:admin2_code":"29",
    "gn:admin3_code":"291",
    "gn:admin4_code":"29117",
    "gn:asciiname":"Kerdrein",
    "gn:country_code":"FR",
    "gn:dem":46,
    "gn:feature_class":"P",
    "gn:feature_code":"PPL",
    "gn:name":"Kerdrein",
    "gn:population":0,
    "gn:timezone":"Europe/Paris",
    "iso:country":"FR",
    "wof:name":"Kerdrein",
    "wof:placetype":"locality"
},
  "geometry": {"coordinates":[-4.49033,48.55833],"type":"Point"}
}