{
  "type": "Feature",
  "properties": {
    "gn:admin1_code":"52",
    "gn:admin2_code":"72",
    "gn:admin3_code":"722",
    "gn:admin4_code":"72251",
    "gn:asciiname":"Verriere",
    "gn:country_code":"FR",
    "gn:dem":82,
    "gn:feature_class":"P",
    "gn:feature_code":"PPL",
    "gn:name":"Verri\u00e8re",
    "gn:population":0,
    "gn:timezone":"Europe/Paris",
    "iso:country":"FR",
    "wof:name":"Verriere",
    "wof:placetype":"locality"
},
  "geometry": {"coordinates":[0.21876,48.26044],"type":"Point"}
}