{
  "type": "Feature",
  "properties": {
    "gn:admin1_code":"24",
    "gn:admin2_code":"18",
    "gn:admin3_code":"181",
    "gn:admin4_code":"18004",
    "gn:asciiname":"Grand Millanfroid",
    "gn:country_code":"FR",
    "gn:dem":232,
    "gn:feature_class":"P",
    "gn:feature_code":"PPL",
    "gn:name":"Grand Millanfroid",
    "gn:population":0,
    "gn:timezone":"Europe/Paris",
    "iso:country":"FR",
    "wof:name":"Grand Millanfroid",
    "wof:placetype":"locality"
},
  "geometry": {"coordinates":[2.30295,47.27171],"type":"Point"}
}