{
  "type": "Feature",
  "properties": {
    "gn:admin1_code":"93",
    "gn:admin2_code":"83",
    "gn:admin3_code":"831",
    "gn:admin4_code":"83124",
    "gn:asciiname":"Broves en Seillans",
    "gn:country_code":"FR",
    "gn:dem":266,
    "gn:feature_class":"P",
    "gn:feature_code":"PPL",
    "gn:name":"Broves en Seillans",
    "gn:population":0,
    "gn:timezone":"Europe/Paris",
    "iso:country":"FR",
    "wof:name":"Broves en Seillans",
    "wof:placetype":"locality"
},
  "geometry": {"coordinates":[6.64274,43.5867],"type":"Point"}
}