{
  "type": "Feature",
  "properties": {
    "gn:admin1_code":"44",
    "gn:admin2_code":"52",
    "gn:admin3_code":"522",
    "gn:admin4_code":"52383",
    "gn:asciiname":"Vieux Moulins",
    "gn:country_code":"FR",
    "gn:dem":373,
    "gn:feature_class":"P",
    "gn:feature_code":"PPL",
    "gn:name":"Vieux Moulins",
    "gn:population":0,
    "gn:timezone":"Europe/Paris",
    "iso:country":"FR",
    "wof:name":"Vieux Moulins",
    "wof:placetype":"locality"
},
  "geometry": {"coordinates":[5.25624,47.8496],"type":"Point"}
}