{
  "type": "Feature",
  "properties": {
    "iso:country":"FR",
    "name:eng_x_preferred":[
        "Mermoz-Victor-Hugo-Argenteuil"
    ],
    "name:fra_x_preferred":[
        "Mermoz-Victor-Hugo-Argenteuil"
    ],
    "wof:name":"Mermoz-Victor-Hugo-Argenteuil",
    "wof:placetype":"neighbourhood"
},
  "geometry": {"coordinates":[2.27227288343738,48.92182303572876],"type":"Point"}
}