{
  "type": "Feature",
  "properties": {
    "gn:admin1_code":"24",
    "gn:admin2_code":"28",
    "gn:admin3_code":"283",
    "gn:admin4_code":"28239",
    "gn:asciiname":"Blainville",
    "gn:country_code":"FR",
    "gn:dem":129,
    "gn:feature_class":"P",
    "gn:feature_code":"PPL",
    "gn:name":"Blainville",
    "gn:population":0,
    "gn:timezone":"Europe/Paris",
    "iso:country":"FR",
    "name:azb_x_preferred":[
        "\u0628\u0644\u0646\u0648\u06cc\u0644"
    ],
    "name:ceb_x_preferred":[
        "Blainville"
    ],
    "name:deu_x_preferred":[
        "Blainville"
    ],
    "name:fra_x_preferred":[
        "Blainville"
    ],
    "name:ita_x_preferred":[
        "Blainville"
    ],
    "name:jpn_x_preferred":[
        "\u30d6\u30e9\u30f3\u30f4\u30a3\u30eb"
    ],
    "name:spa_x_preferred":[
        "Blainville"
    ],
    "name:swe_x_preferred":[
        "Blainville"
    ],
    "wof:name":"Blainville",
    "wof:placetype":"locality"
},
  "geometry": {"coordinates":[1.39595,48.69793],"type":"Point"}
}