{
  "type": "Feature",
  "properties": {
    "gn:admin1_code":"75",
    "gn:admin2_code":"40",
    "gn:admin3_code":"402",
    "gn:admin4_code":"40200",
    "gn:asciiname":"Biganon",
    "gn:country_code":"FR",
    "gn:dem":48,
    "gn:feature_class":"P",
    "gn:feature_code":"PPL",
    "gn:name":"Biganon",
    "gn:population":0,
    "gn:timezone":"Europe/Paris",
    "iso:country":"FR",
    "wof:name":"Biganon",
    "wof:placetype":"locality"
},
  "geometry": {"coordinates":[-0.75297,44.41298],"type":"Point"}
}