{
  "type": "Feature",
  "properties": {
    "gn:admin1_code":"53",
    "gn:admin2_code":"35",
    "gn:admin3_code":"353",
    "gn:admin4_code":"35211",
    "gn:asciiname":"Pertuis Nanti",
    "gn:country_code":"FR",
    "gn:dem":151,
    "gn:feature_class":"P",
    "gn:feature_code":"PPL",
    "gn:name":"Pertuis Nanti",
    "gn:population":0,
    "gn:timezone":"Europe/Paris",
    "iso:country":"FR",
    "wof:name":"Pertuis Nanti",
    "wof:placetype":"locality"
},
  "geometry": {"coordinates":[-2.27895,48.02181],"type":"Point"}
}