{
  "type": "Feature",
  "properties": {
    "gn:admin1_code":"75",
    "gn:admin2_code":"19",
    "gn:admin3_code":"193",
    "gn:admin4_code":"19027",
    "gn:asciiname":"Chatemichy",
    "gn:country_code":"FR",
    "gn:dem":819,
    "gn:feature_class":"P",
    "gn:feature_code":"PPL",
    "gn:name":"Chatemichy",
    "gn:population":0,
    "gn:timezone":"Europe/Paris",
    "iso:country":"FR",
    "name:und_x_variant":[
        "La Chatemichy",
        "Chatemichy"
    ],
    "wof:name":"Chatemichy",
    "wof:placetype":"locality"
},
  "geometry": {"coordinates":[1.94295,45.53296],"type":"Point"}
}