{
  "type": "Feature",
  "properties": {
    "gn:admin1_code":"53",
    "gn:admin2_code":"56",
    "gn:admin3_code":"562",
    "gn:admin4_code":"56198",
    "gn:asciiname":"Saint-Samson",
    "gn:country_code":"FR",
    "gn:dem":67,
    "gn:feature_class":"P",
    "gn:feature_code":"PPL",
    "gn:name":"Saint-Samson",
    "gn:population":0,
    "gn:timezone":"Europe/Paris",
    "iso:country":"FR",
    "name:bre_x_preferred":[
        "Saint-Samson"
    ],
    "name:ceb_x_preferred":[
        "Saint-Samson"
    ],
    "name:deu_x_preferred":[
        "Saint-Samson"
    ],
    "name:fra_x_preferred":[
        "Saint-Samson"
    ],
    "name:ita_x_preferred":[
        "Saint-Samson"
    ],
    "name:jpn_x_preferred":[
        "\u30b5\u30f3\uff1d\u30b5\u30f3\u30bd\u30f3"
    ],
    "name:nds_x_preferred":[
        "Saint-Samson"
    ],
    "name:nld_x_preferred":[
        "Saint-Samson"
    ],
    "name:oci_x_preferred":[
        "Saint-Samson"
    ],
    "name:pms_x_preferred":[
        "Saint-Samson"
    ],
    "name:pol_x_preferred":[
        "Saint-Samson"
    ],
    "name:por_x_preferred":[
        "Saint-Samson"
    ],
    "name:slk_x_preferred":[
        "Saint-Samson"
    ],
    "name:spa_x_preferred":[
        "Saint-Samson"
    ],
    "name:swe_x_preferred":[
        "Saint-Samson"
    ],
    "name:ukr_x_preferred":[
        "\u0421\u0435\u043d-\u0421\u0430\u043c\u0441\u043e\u043d"
    ],
    "wof:name":"Saint-Samson",
    "wof:placetype":"locality"
},
  "geometry": {"coordinates":[-2.76549,48.08694000000001],"type":"Point"}
}