{
  "type": "Feature",
  "properties": {
    "gn:admin1_code":"93",
    "gn:admin2_code":"05",
    "gn:admin3_code":"052",
    "gn:admin4_code":"05033",
    "gn:asciiname":"Les Courtilles",
    "gn:country_code":"FR",
    "gn:dem":822,
    "gn:feature_class":"P",
    "gn:feature_code":"PPL",
    "gn:name":"Les Courtilles",
    "gn:population":0,
    "gn:timezone":"Europe/Paris",
    "iso:country":"FR",
    "name:und_x_variant":[
        "Courtilles",
        "Les Courtilles"
    ],
    "wof:name":"Les Courtilles",
    "wof:placetype":"locality"
},
  "geometry": {"coordinates":[5.65102,44.37758],"type":"Point"}
}