{
  "type": "Feature",
  "properties": {
    "gn:admin1_code":"75",
    "gn:admin2_code":"87",
    "gn:admin3_code":"872",
    "gn:admin4_code":"87082",
    "gn:asciiname":"La Grenerie",
    "gn:country_code":"FR",
    "gn:dem":400,
    "gn:feature_class":"P",
    "gn:feature_code":"PPL",
    "gn:name":"La Grenerie",
    "gn:population":0,
    "gn:timezone":"Europe/Paris",
    "iso:country":"FR",
    "wof:name":"La Grenerie",
    "wof:placetype":"locality"
},
  "geometry": {"coordinates":[1.13452,45.61294],"type":"Point"}
}