{
  "type": "Feature",
  "properties": {
    "frgov:code_epci":"200072049",
    "frgov:insee_arr":"3",
    "frgov:insee_com":"16239",
    "frgov:insee_dep":"16",
    "frgov:insee_reg":"75",
    "frgov:nom_com":"Mouzon",
    "frgov:nom_com_m":"MOUZON",
    "frgov:nom_dep":"CHARENTE",
    "frgov:nom_reg":"NOUVELLE-AQUITAINE",
    "frgov:statut":"Commune simple",
    "gn:admin1_code":"75",
    "gn:admin2_code":"16",
    "gn:admin3_code":"163",
    "gn:admin4_code":"16239",
    "gn:asciiname":"Mouzon",
    "gn:country_code":"FR",
    "gn:dem":277,
    "gn:feature_class":"P",
    "gn:feature_code":"PPL",
    "gn:name":"Mouzon",
    "gn:population":0,
    "gn:timezone":"Europe/Paris",
    "iso:country":"FR",
    "name:cat_x_preferred":[
        "Mausom"
    ],
    "name:ceb_x_preferred":[
        "Mouzon"
    ],
    "name:deu_x_preferred":[
        "Mouzon"
    ],
    "name:fra_x_preferred":[
        "Mouzon"
    ],
    "name:hun_x_preferred":[
        "Mouzon"
    ],
    "name:ita_x_preferred":[
        "Mouzon"
    ],
    "name:ltz_x_preferred":[
        "Mouzon"
    ],
    "name:nds_x_preferred":[
        "Mouzon"
    ],
    "name:nld_x_preferred":[
        "Mouzon"
    ],
    "name:pms_x_preferred":[
        "Mouzon"
    ],
    "name:pol_x_preferred":[
        "Mouzon"
    ],
    "name:por_x_preferred":[
        "Mouzon"
    ],
    "name:rus_x_preferred":[
        "\u041c\u0443\u0437\u043e\u043d"
    ],
    "name:slk_x_preferred":[
        "Mouzon"
    ],
    "name:spa_x_preferred":[
        "Mouzon"
    ],
    "name:sqi_x_preferred":[
        "Mouzon"
    ],
    "name:swe_x_preferred":[
        "Mouzon"
    ],
    "name:ukr_x_preferred":[
        "\u041c\u0443\u0437\u043e\u043d"
    ],
    "name:zho_x_preferred":[
        "\u7a46\u5b97"
    ],
    "qs:a0":"France",
    "qs:a1":"CHARENTE",
    "qs:a1_lc":"16",
    "qs:a1r":"POITOU-CHARENTES",
    "qs:a1r_lc":"54",
    "qs:a2_lc":"20",
    "qs:a2r_lc":"3",
    "qs:adm0":"France",
    "qs:adm0_a3":"FRA",
    "qs:la":"MOUZON",
    "qs:la_lc":"16239",
    "qs:level":"localadmin",
    "qs:type":"Commune simple",
    "wof:coterminous":[
        404417327
    ],
    "wof:name":"Mouzon",
    "wof:placetype":"locality",
    "wof:placetype_local":"Commune simple"
},
  "geometry": {"coordinates":[0.61473,45.80564],"type":"Point"}
}