{
  "type": "Feature",
  "properties": {
    "gn:admin1_code":"75",
    "gn:admin2_code":"16",
    "gn:admin3_code":"163",
    "gn:admin4_code":"16239",
    "gn:asciiname":"Mouzon",
    "gn:country_code":"FR",
    "gn:dem":277,
    "gn:feature_class":"P",
    "gn:feature_code":"PPL",
    "gn:name":"Mouzon",
    "gn:population":0,
    "gn:timezone":"Europe/Paris",
    "iso:country":"FR",
    "name:ceb_x_preferred":[
        "Mouzon"
    ],
    "name:deu_x_preferred":[
        "Mouzon"
    ],
    "name:fra_x_preferred":[
        "Mouzon"
    ],
    "name:hun_x_preferred":[
        "Mouzon"
    ],
    "name:ita_x_preferred":[
        "Mouzon"
    ],
    "name:ltz_x_preferred":[
        "Mouzon"
    ],
    "name:nds_x_preferred":[
        "Mouzon"
    ],
    "name:nld_x_preferred":[
        "Mouzon"
    ],
    "name:pms_x_preferred":[
        "Mouzon"
    ],
    "name:pol_x_preferred":[
        "Mouzon"
    ],
    "name:por_x_preferred":[
        "Mouzon"
    ],
    "name:rus_x_preferred":[
        "\u041c\u0443\u0437\u043e\u043d"
    ],
    "name:slk_x_preferred":[
        "Mouzon"
    ],
    "name:spa_x_preferred":[
        "Mouzon"
    ],
    "name:sqi_x_preferred":[
        "Mouzon"
    ],
    "name:swe_x_preferred":[
        "Mouzon"
    ],
    "name:ukr_x_preferred":[
        "\u041c\u0443\u0437\u043e\u043d"
    ],
    "wof:name":"Mouzon",
    "wof:placetype":"locality"
},
  "geometry": {"coordinates":[0.61473,45.80564],"type":"Point"}
}