{
  "type": "Feature",
  "properties": {
    "gn:admin1_code":"75",
    "gn:admin2_code":"16",
    "gn:admin3_code":"163",
    "gn:admin4_code":"16239",
    "gn:asciiname":"Mouzon",
    "gn:country_code":"FR",
    "gn:dem":277,
    "gn:feature_class":"P",
    "gn:feature_code":"PPL",
    "gn:name":"Mouzon",
    "gn:population":0,
    "gn:timezone":"Europe/Paris",
    "iso:country":"FR",
    "wof:name":"Mouzon",
    "wof:placetype":"locality"
},
  "geometry": {"coordinates":[0.61473,45.80564],"type":"Point"}
}