{
  "type": "Feature",
  "properties": {
    "gn:admin1_code":"52",
    "gn:admin2_code":"44",
    "gn:admin3_code":"443",
    "gn:admin4_code":"44152",
    "gn:asciiname":"Pocazet",
    "gn:country_code":"FR",
    "gn:dem":21,
    "gn:feature_class":"P",
    "gn:feature_code":"PPL",
    "gn:name":"Pocazet",
    "gn:population":0,
    "gn:timezone":"Europe/Paris",
    "iso:country":"FR",
    "wof:name":"Pocazet",
    "wof:placetype":"locality"
},
  "geometry": {"coordinates":[-2.01238,47.43548],"type":"Point"}
}