{
  "type": "Feature",
  "properties": {
    "iso:country":"FR",
    "name:eng_x_preferred":[
        "Fontaine Michalon"
    ],
    "name:fra_x_preferred":[
        "Fontaine Michalon"
    ],
    "wof:name":"Fontaine Michalon",
    "wof:placetype":"neighbourhood"
},
  "geometry": {"coordinates":[2.29723532122922,48.74322248005524],"type":"Point"}
}