{
  "type": "Feature",
  "properties": {
    "gn:admin1_code":"84",
    "gn:admin2_code":"03",
    "gn:admin3_code":"032",
    "gn:admin4_code":"3121.0",
    "gn:asciiname":"Les Driats",
    "gn:country_code":"FR",
    "gn:dem":247,
    "gn:feature_class":"P",
    "gn:feature_code":"PPL",
    "gn:name":"Les Driats",
    "gn:population":0,
    "gn:timezone":"Europe/Paris",
    "iso:country":"FR",
    "wof:name":"Les Driats",
    "wof:placetype":"locality"
},
  "geometry": {"coordinates":[3.43447,46.63982],"type":"Point"}
}