{
  "type": "Feature",
  "properties": {
    "gn:admin1_code":"28",
    "gn:admin2_code":"14",
    "gn:admin3_code":"141",
    "gn:admin4_code":"14078",
    "gn:asciiname":"Blay",
    "gn:country_code":"FR",
    "gn:dem":36,
    "gn:feature_class":"P",
    "gn:feature_code":"PPL",
    "gn:name":"Blay",
    "gn:population":281,
    "gn:timezone":"Europe/Paris",
    "iso:country":"FR",
    "name:bre_x_preferred":[
        "Blay"
    ],
    "name:cat_x_preferred":[
        "Blay"
    ],
    "name:ceb_x_preferred":[
        "Blay"
    ],
    "name:deu_x_preferred":[
        "Blay"
    ],
    "name:eus_x_preferred":[
        "Blay"
    ],
    "name:fra_x_preferred":[
        "Blay"
    ],
    "name:hun_x_preferred":[
        "Blay"
    ],
    "name:hye_x_preferred":[
        "\u0532\u056c\u0565"
    ],
    "name:ind_x_preferred":[
        "Blay"
    ],
    "name:ita_x_preferred":[
        "Blay"
    ],
    "name:kaz_x_preferred":[
        "\u0411\u043b\u0435"
    ],
    "name:lat_x_preferred":[
        "Blay"
    ],
    "name:msa_x_preferred":[
        "Blay"
    ],
    "name:nld_x_preferred":[
        "Blay"
    ],
    "name:oci_x_preferred":[
        "Blay"
    ],
    "name:pam_x_preferred":[
        "Blay"
    ],
    "name:pms_x_preferred":[
        "Blay"
    ],
    "name:pol_x_preferred":[
        "Blay"
    ],
    "name:por_x_preferred":[
        "Blay"
    ],
    "name:ron_x_preferred":[
        "Blay"
    ],
    "name:rus_x_preferred":[
        "\u0411\u043b\u0435"
    ],
    "name:slk_x_preferred":[
        "Blay"
    ],
    "name:spa_x_preferred":[
        "Blay"
    ],
    "name:srp_x_preferred":[
        "\u0411\u043b\u0435"
    ],
    "name:swe_x_preferred":[
        "Blay"
    ],
    "name:ukr_x_preferred":[
        "\u0411\u043b\u0435"
    ],
    "name:uzb_x_preferred":[
        "Blay"
    ],
    "name:vie_x_preferred":[
        "Blay"
    ],
    "name:vol_x_preferred":[
        "Blay"
    ],
    "name:war_x_preferred":[
        "Blay"
    ],
    "name:zho_x_preferred":[
        "\u5e03\u83b1"
    ],
    "wof:name":"Blay",
    "wof:placetype":"locality",
    "wof:population":281
},
  "geometry": {"coordinates":[-0.83968,49.2706],"type":"Point"}
}