{
  "type": "Feature",
  "properties": {
    "frgov:code_epci":"200066801",
    "frgov:insee_arr":"1",
    "frgov:insee_com":"14078",
    "frgov:insee_dep":"14",
    "frgov:insee_reg":"28",
    "frgov:nom_com":"Blay",
    "frgov:nom_com_m":"BLAY",
    "frgov:nom_dep":"CALVADOS",
    "frgov:nom_reg":"NORMANDIE",
    "frgov:statut":"Commune simple",
    "gn:admin1_code":"28",
    "gn:admin2_code":"14",
    "gn:admin3_code":"141",
    "gn:admin4_code":"14078",
    "gn:asciiname":"Blay",
    "gn:country_code":"FR",
    "gn:dem":36,
    "gn:feature_class":"P",
    "gn:feature_code":"PPL",
    "gn:name":"Blay",
    "gn:population":281,
    "gn:timezone":"Europe/Paris",
    "iso:country":"FR",
    "name:bre_x_preferred":[
        "Blay"
    ],
    "name:cat_x_preferred":[
        "Blay"
    ],
    "name:ceb_x_preferred":[
        "Blay"
    ],
    "name:deu_x_preferred":[
        "Blay"
    ],
    "name:eus_x_preferred":[
        "Blay"
    ],
    "name:fra_x_preferred":[
        "Blay"
    ],
    "name:hun_x_preferred":[
        "Blay"
    ],
    "name:hye_x_preferred":[
        "\u0532\u056c\u0565"
    ],
    "name:ind_x_preferred":[
        "Blay"
    ],
    "name:ita_x_preferred":[
        "Blay"
    ],
    "name:kaz_x_preferred":[
        "\u0411\u043b\u0435"
    ],
    "name:lat_x_preferred":[
        "Blay"
    ],
    "name:msa_x_preferred":[
        "Blay"
    ],
    "name:nld_x_preferred":[
        "Blay"
    ],
    "name:oci_x_preferred":[
        "Blay"
    ],
    "name:pam_x_preferred":[
        "Blay"
    ],
    "name:pms_x_preferred":[
        "Blay"
    ],
    "name:pol_x_preferred":[
        "Blay"
    ],
    "name:por_x_preferred":[
        "Blay"
    ],
    "name:ron_x_preferred":[
        "Blay"
    ],
    "name:rus_x_preferred":[
        "\u0411\u043b\u0435"
    ],
    "name:slk_x_preferred":[
        "Blay"
    ],
    "name:spa_x_preferred":[
        "Blay"
    ],
    "name:srp_x_preferred":[
        "\u0411\u043b\u0435"
    ],
    "name:swe_x_preferred":[
        "Blay"
    ],
    "name:ukr_x_preferred":[
        "\u0411\u043b\u0435"
    ],
    "name:uzb_x_preferred":[
        "Blay"
    ],
    "name:vie_x_preferred":[
        "Blay"
    ],
    "name:vol_x_preferred":[
        "Blay"
    ],
    "name:war_x_preferred":[
        "Blay"
    ],
    "name:zho_x_preferred":[
        "\u5e03\u83b1"
    ],
    "qs:a0":"France",
    "qs:a1":"CALVADOS",
    "qs:a1_lc":"14",
    "qs:a1r":"BASSE-NORMANDIE",
    "qs:a1r_lc":"25",
    "qs:a2_lc":"33",
    "qs:a2r_lc":"1",
    "qs:adm0":"France",
    "qs:adm0_a3":"FRA",
    "qs:la":"BLAY",
    "qs:la_lc":"14078",
    "qs:level":"localadmin",
    "qs:type":"Commune simple",
    "wof:coterminous":[
        404390975
    ],
    "wof:name":"Blay",
    "wof:placetype":"locality",
    "wof:placetype_local":"Commune simple",
    "wof:population":281
},
  "geometry": {"coordinates":[-0.83968,49.2706],"type":"Point"}
}