{
  "type": "Feature",
  "properties": {
    "gn:admin1_code":"75",
    "gn:admin2_code":"79",
    "gn:admin3_code":"792",
    "gn:admin4_code":"79061",
    "gn:asciiname":"Montigne",
    "gn:country_code":"FR",
    "gn:dem":69,
    "gn:feature_class":"P",
    "gn:feature_code":"PPL",
    "gn:name":"Montign\u00e9",
    "gn:population":0,
    "gn:timezone":"Europe/Paris",
    "iso:country":"FR",
    "name:und_x_variant":[
        "Montign\u00e9"
    ],
    "wof:name":"Montigne",
    "wof:placetype":"locality"
},
  "geometry": {"coordinates":[-0.23897,46.21361],"type":"Point"}
}