{
  "type": "Feature",
  "properties": {
    "gn:admin1_code":"24",
    "gn:admin2_code":"28",
    "gn:admin3_code":"281",
    "gn:admin4_code":"28034",
    "gn:asciiname":"Bercheres-la-Maingot",
    "gn:country_code":"FR",
    "gn:dem":161,
    "gn:feature_class":"P",
    "gn:feature_code":"PPL",
    "gn:name":"Berch\u00e8res-la-Maingot",
    "gn:population":0,
    "gn:timezone":"Europe/Paris",
    "iso:country":"FR",
    "name:und_x_variant":[
        "Berch\u00e8res",
        "Berch\u00e8res-la-Maingot"
    ],
    "wof:name":"Bercheres-la-Maingot",
    "wof:placetype":"locality"
},
  "geometry": {"coordinates":[1.48202,48.53392],"type":"Point"}
}