{
  "type": "Feature",
  "properties": {
    "iso:country":"FR",
    "name:eng_x_preferred":[
        "La Boule-Champs-Pierreux"
    ],
    "name:fra_x_preferred":[
        "La Boule-Champs-Pierreux"
    ],
    "wof:name":"La Boule-Champs-Pierreux",
    "wof:placetype":"neighbourhood"
},
  "geometry": {"coordinates":[2.21039607846972,48.88888493896152],"type":"Point"}
}