{
  "type": "Feature",
  "properties": {
    "gn:admin1_code":"27",
    "gn:admin2_code":"89",
    "gn:admin3_code":"891",
    "gn:admin4_code":"89438",
    "gn:asciiname":"La Chapelle",
    "gn:country_code":"FR",
    "gn:dem":203,
    "gn:feature_class":"P",
    "gn:feature_code":"PPL",
    "gn:name":"La Chapelle",
    "gn:population":0,
    "gn:timezone":"Europe/Paris",
    "iso:country":"FR",
    "wof:name":"La Chapelle",
    "wof:placetype":"locality"
},
  "geometry": {"coordinates":[3.62874,47.81746],"type":"Point"}
}