{
  "type": "Feature",
  "properties": {
    "iso:country":"FR",
    "name:eng_x_preferred":[
        "Quartier de la Folie-Mericourt"
    ],
    "name:fra_x_preferred":[
        "Quartier de la Folie-M\u00e9ricourt"
    ],
    "wof:name":"Quartier de la Folie-Mericourt",
    "wof:placetype":"neighbourhood"
},
  "geometry": {"coordinates":[2.37280030793025,48.86761888693039],"type":"Point"}
}