{
  "type": "Feature",
  "properties": {
    "gn:admin1_code":"93",
    "gn:admin2_code":"04",
    "gn:admin3_code":"042",
    "gn:admin4_code":"04006",
    "gn:asciiname":"Bas Villard",
    "gn:country_code":"FR",
    "gn:dem":1701,
    "gn:feature_class":"P",
    "gn:feature_code":"PPL",
    "gn:name":"Bas Villard",
    "gn:population":0,
    "gn:timezone":"Europe/Paris",
    "iso:country":"FR",
    "name:und_x_variant":[
        "Villard Bas",
        "Bas Villard"
    ],
    "wof:name":"Bas Villard",
    "wof:placetype":"locality"
},
  "geometry": {"coordinates":[6.64647,44.24004],"type":"Point"}
}