{
  "type": "Feature",
  "properties": {
    "gn:admin1_code":"44",
    "gn:admin2_code":"54",
    "gn:admin3_code":"542",
    "gn:admin4_code":"54422",
    "gn:asciiname":"Pettonville",
    "gn:country_code":"FR",
    "gn:dem":255,
    "gn:feature_class":"P",
    "gn:feature_code":"PPL",
    "gn:name":"Pettonville",
    "gn:population":0,
    "gn:timezone":"Europe/Paris",
    "iso:country":"FR",
    "wof:name":"Pettonville",
    "wof:placetype":"locality"
},
  "geometry": {"coordinates":[6.74134,48.53023],"type":"Point"}
}