{
  "type": "Feature",
  "properties": {
    "gn:admin1_code":"44",
    "gn:admin2_code":"54",
    "gn:admin3_code":"542",
    "gn:admin4_code":"54422",
    "gn:asciiname":"Pettonville",
    "gn:country_code":"FR",
    "gn:dem":255,
    "gn:feature_class":"P",
    "gn:feature_code":"PPL",
    "gn:name":"Pettonville",
    "gn:population":0,
    "gn:timezone":"Europe/Paris",
    "iso:country":"FR",
    "name:cat_x_preferred":[
        "Pettonville"
    ],
    "name:ceb_x_preferred":[
        "Pettonville"
    ],
    "name:deu_x_preferred":[
        "Pettonville"
    ],
    "name:eus_x_preferred":[
        "Pettonville"
    ],
    "name:fra_x_preferred":[
        "Pettonville"
    ],
    "name:hun_x_preferred":[
        "Pettonville"
    ],
    "name:ita_x_preferred":[
        "Pettonville"
    ],
    "name:kaz_x_preferred":[
        "\u041f\u0435\u0442\u0442\u043e\u043d\u0432\u0438\u043b\u044c"
    ],
    "name:lat_x_preferred":[
        "Pettonville"
    ],
    "name:ltz_x_preferred":[
        "Pettonville"
    ],
    "name:mlg_x_preferred":[
        "Pettonville"
    ],
    "name:msa_x_preferred":[
        "Pettonville"
    ],
    "name:nld_x_preferred":[
        "Pettonville"
    ],
    "name:oci_x_preferred":[
        "Pettonville"
    ],
    "name:pms_x_preferred":[
        "Pettonville"
    ],
    "name:pol_x_preferred":[
        "Pettonville"
    ],
    "name:por_x_preferred":[
        "Pettonville"
    ],
    "name:rus_x_preferred":[
        "\u041f\u0435\u0442\u0442\u043e\u043d\u0432\u0438\u043b\u044c"
    ],
    "name:slk_x_preferred":[
        "Pettonville"
    ],
    "name:spa_x_preferred":[
        "Pettonville"
    ],
    "name:swe_x_preferred":[
        "Pettonville"
    ],
    "name:ukr_x_preferred":[
        "\u041f\u0435\u0442\u0442\u043e\u043d\u0432\u0456\u043b\u044c"
    ],
    "name:uzb_x_preferred":[
        "Pettonville"
    ],
    "name:vie_x_preferred":[
        "Pettonville"
    ],
    "name:vol_x_preferred":[
        "Pettonville"
    ],
    "name:war_x_preferred":[
        "Pettonville"
    ],
    "name:zho_x_preferred":[
        "\u4f69\u901a\u7ef4\u5c14"
    ],
    "wof:name":"Pettonville",
    "wof:placetype":"locality"
},
  "geometry": {"coordinates":[6.74134,48.53023],"type":"Point"}
}