{
  "type": "Feature",
  "properties": {
    "gn:admin1_code":"28",
    "gn:admin2_code":"76",
    "gn:admin3_code":"763",
    "gn:admin4_code":"76580",
    "gn:asciiname":"Le Varat",
    "gn:country_code":"FR",
    "gn:dem":152,
    "gn:feature_class":"P",
    "gn:feature_code":"PPL",
    "gn:name":"Le Varat",
    "gn:population":0,
    "gn:timezone":"Europe/Paris",
    "iso:country":"FR",
    "wof:name":"Le Varat",
    "wof:placetype":"locality"
},
  "geometry": {"coordinates":[1.19437,49.5608],"type":"Point"}
}