{
  "type": "Feature",
  "properties": {
    "gn:admin1_code":"84",
    "gn:admin2_code":"07",
    "gn:admin3_code":"073",
    "gn:admin4_code":"07265",
    "gn:asciiname":"Ecuville",
    "gn:country_code":"FR",
    "gn:dem":533,
    "gn:feature_class":"P",
    "gn:feature_code":"PPL",
    "gn:name":"\u00c9cuville",
    "gn:population":0,
    "gn:timezone":"Europe/Paris",
    "iso:country":"FR",
    "wof:name":"Ecuville",
    "wof:placetype":"locality"
},
  "geometry": {"coordinates":[4.63883,45.30281],"type":"Point"}
}