{
  "type": "Feature",
  "properties": {
    "gn:admin1_code":"27",
    "gn:admin2_code":"89",
    "gn:admin3_code":"893",
    "gn:admin4_code":"89142",
    "gn:asciiname":"Pimancon",
    "gn:cc2":"FR",
    "gn:country_code":"FR",
    "gn:dem":236,
    "gn:feature_class":"P",
    "gn:feature_code":"PPL",
    "gn:name":"Piman\u00e7on",
    "gn:population":0,
    "gn:timezone":"Europe/Paris",
    "iso:country":"FR",
    "name:und_x_variant":[
        "Pimanson",
        "Piman\u00e7on"
    ],
    "wof:name":"Pimancon",
    "wof:placetype":"locality"
},
  "geometry": {"coordinates":[3.46241,48.10365],"type":"Point"}
}