{
  "type": "Feature",
  "properties": {
    "gn:admin1_code":"75",
    "gn:admin2_code":"24",
    "gn:admin3_code":"241",
    "gn:admin4_code":"24231",
    "gn:asciiname":"Lavalade",
    "gn:country_code":"FR",
    "gn:dem":199,
    "gn:feature_class":"P",
    "gn:feature_code":"PPL",
    "gn:name":"Lavalade",
    "gn:population":0,
    "gn:timezone":"Europe/Paris",
    "iso:country":"FR",
    "name:bug_x_preferred":[
        "Lavalade"
    ],
    "name:cat_x_preferred":[
        "La Valada"
    ],
    "name:ceb_x_preferred":[
        "Lavalade"
    ],
    "name:deu_x_preferred":[
        "Lavalade"
    ],
    "name:eus_x_preferred":[
        "Lavalade"
    ],
    "name:fra_x_preferred":[
        "Lavalade"
    ],
    "name:hun_x_preferred":[
        "Lavalade"
    ],
    "name:ita_x_preferred":[
        "Lavalade"
    ],
    "name:kaz_x_preferred":[
        "\u041b\u0430\u0432\u0430\u043b\u0430\u0434"
    ],
    "name:lat_x_preferred":[
        "Lavalade"
    ],
    "name:mlg_x_preferred":[
        "Lavalade"
    ],
    "name:msa_x_preferred":[
        "Lavalade"
    ],
    "name:nld_x_preferred":[
        "Lavalade"
    ],
    "name:oci_x_preferred":[
        "La Valada"
    ],
    "name:pms_x_preferred":[
        "Lavalade"
    ],
    "name:pol_x_preferred":[
        "Lavalade"
    ],
    "name:por_x_preferred":[
        "Lavalade"
    ],
    "name:ron_x_preferred":[
        "Lavalade"
    ],
    "name:slk_x_preferred":[
        "Lavalade"
    ],
    "name:spa_x_preferred":[
        "Lavalade"
    ],
    "name:swe_x_preferred":[
        "Lavalade"
    ],
    "name:ukr_x_preferred":[
        "\u041b\u0430\u0432\u0430\u043b\u0430\u0434"
    ],
    "name:uzb_x_preferred":[
        "Lavalade"
    ],
    "name:vie_x_preferred":[
        "Lavalade"
    ],
    "name:vol_x_preferred":[
        "Lavalade"
    ],
    "name:war_x_preferred":[
        "Lavalade"
    ],
    "name:zho_x_preferred":[
        "\u62c9\u74e6\u62c9\u5fb7"
    ],
    "wof:name":"Lavalade",
    "wof:placetype":"locality"
},
  "geometry": {"coordinates":[0.86368,44.69531],"type":"Point"}
}