{
  "type": "Feature",
  "properties": {
    "frgov:code_epci":"200034833",
    "frgov:insee_arr":"1",
    "frgov:insee_com":"24231",
    "frgov:insee_dep":"24",
    "frgov:insee_reg":"75",
    "frgov:nom_com":"Lavalade",
    "frgov:nom_com_m":"LAVALADE",
    "frgov:nom_dep":"DORDOGNE",
    "frgov:nom_reg":"NOUVELLE-AQUITAINE",
    "frgov:statut":"Commune simple",
    "gn:admin1_code":"75",
    "gn:admin2_code":"24",
    "gn:admin3_code":"241",
    "gn:admin4_code":"24231",
    "gn:asciiname":"Lavalade",
    "gn:country_code":"FR",
    "gn:dem":199,
    "gn:feature_class":"P",
    "gn:feature_code":"PPL",
    "gn:name":"Lavalade",
    "gn:population":0,
    "gn:timezone":"Europe/Paris",
    "iso:country":"FR",
    "name:bug_x_preferred":[
        "Lavalade"
    ],
    "name:cat_x_preferred":[
        "La Valada"
    ],
    "name:ceb_x_preferred":[
        "Lavalade"
    ],
    "name:deu_x_preferred":[
        "Lavalade"
    ],
    "name:eus_x_preferred":[
        "Lavalade"
    ],
    "name:fra_x_preferred":[
        "Lavalade"
    ],
    "name:hun_x_preferred":[
        "Lavalade"
    ],
    "name:ita_x_preferred":[
        "Lavalade"
    ],
    "name:kaz_x_preferred":[
        "\u041b\u0430\u0432\u0430\u043b\u0430\u0434"
    ],
    "name:lat_x_preferred":[
        "Lavalade"
    ],
    "name:mlg_x_preferred":[
        "Lavalade"
    ],
    "name:msa_x_preferred":[
        "Lavalade"
    ],
    "name:nld_x_preferred":[
        "Lavalade"
    ],
    "name:oci_x_preferred":[
        "La Valada"
    ],
    "name:pms_x_preferred":[
        "Lavalade"
    ],
    "name:pol_x_preferred":[
        "Lavalade"
    ],
    "name:por_x_preferred":[
        "Lavalade"
    ],
    "name:ron_x_preferred":[
        "Lavalade"
    ],
    "name:slk_x_preferred":[
        "Lavalade"
    ],
    "name:spa_x_preferred":[
        "Lavalade"
    ],
    "name:swe_x_preferred":[
        "Lavalade"
    ],
    "name:ukr_x_preferred":[
        "\u041b\u0430\u0432\u0430\u043b\u0430\u0434"
    ],
    "name:uzb_x_preferred":[
        "Lavalade"
    ],
    "name:vie_x_preferred":[
        "Lavalade"
    ],
    "name:vol_x_preferred":[
        "Lavalade"
    ],
    "name:war_x_preferred":[
        "Lavalade"
    ],
    "name:zho_x_preferred":[
        "\u62c9\u74e6\u62c9\u5fb7"
    ],
    "qs:a0":"France",
    "qs:a1":"DORDOGNE",
    "qs:a1_lc":"24",
    "qs:a1r":"AQUITAINE",
    "qs:a1r_lc":"72",
    "qs:a2_lc":"20",
    "qs:a2r_lc":"1",
    "qs:adm0":"France",
    "qs:adm0_a3":"FRA",
    "qs:la":"LAVALADE",
    "qs:la_lc":"24231",
    "qs:level":"localadmin",
    "qs:type":"Commune simple",
    "wof:coterminous":[
        404409613
    ],
    "wof:name":"Lavalade",
    "wof:placetype":"locality",
    "wof:placetype_local":"Commune simple"
},
  "geometry": {"coordinates":[0.86368,44.69531],"type":"Point"}
}