{
  "type": "Feature",
  "properties": {
    "gn:admin1_code":"11",
    "gn:admin2_code":"78",
    "gn:admin3_code":"782",
    "gn:admin4_code":"78506",
    "gn:asciiname":"La Chapelle",
    "gn:country_code":"FR",
    "gn:dem":157,
    "gn:feature_class":"P",
    "gn:feature_code":"PPL",
    "gn:name":"La Chapelle",
    "gn:population":0,
    "gn:timezone":"Europe/Paris",
    "iso:country":"FR",
    "wof:name":"La Chapelle",
    "wof:placetype":"locality"
},
  "geometry": {"coordinates":[1.80331,48.50072],"type":"Point"}
}