{
  "type": "Feature",
  "properties": {
    "gn:admin1_code":"93",
    "gn:asciiname":"Port Santa-Lucia",
    "gn:cc2":"FR",
    "gn:country_code":"FR",
    "gn:dem":-9999,
    "gn:feature_class":"P",
    "gn:feature_code":"PPL",
    "gn:name":"Port Santa-Lucia",
    "gn:population":0,
    "gn:timezone":"Europe/Paris",
    "iso:country":"FR",
    "name:und_x_variant":[
        "Port de Santa Lucia",
        "Port Santa-Lucia"
    ],
    "wof:name":"Port Santa-Lucia",
    "wof:placetype":"locality"
},
  "geometry": {"coordinates":[6.77917,43.4125],"type":"Point"}
}