{
  "type": "Feature",
  "properties": {
    "gn:admin1_code":"52",
    "gn:admin2_code":"44",
    "gn:admin3_code":"441",
    "gn:admin4_code":"44007",
    "gn:asciiname":"Ronde Bruere",
    "gn:country_code":"FR",
    "gn:dem":33,
    "gn:feature_class":"P",
    "gn:feature_code":"PPL",
    "gn:name":"Ronde Bru\u00e8re",
    "gn:population":0,
    "gn:timezone":"Europe/Paris",
    "iso:country":"FR",
    "wof:name":"Ronde Bruere",
    "wof:placetype":"locality"
},
  "geometry": {"coordinates":[-1.98324,47.60657],"type":"Point"}
}