{
  "type": "Feature",
  "properties": {
    "gn:admin1_code":"24",
    "gn:admin2_code":"45",
    "gn:admin3_code":"451",
    "gn:admin4_code":"45343.0",
    "gn:asciiname":"Le Bignon",
    "gn:country_code":"FR",
    "gn:dem":93,
    "gn:feature_class":"P",
    "gn:feature_code":"PPL",
    "gn:name":"Le Bignon",
    "gn:population":0,
    "gn:timezone":"Europe/Paris",
    "iso:country":"FR",
    "name:aka_x_preferred":[
        "Le Bignon"
    ],
    "name:ast_x_preferred":[
        "Le Bignon"
    ],
    "name:bam_x_preferred":[
        "Le Bignon"
    ],
    "name:bre_x_preferred":[
        "Bignon"
    ],
    "name:cat_x_preferred":[
        "Le Bignon"
    ],
    "name:ceb_x_preferred":[
        "Le Bignon"
    ],
    "name:cym_x_preferred":[
        "Bignon"
    ],
    "name:deu_x_preferred":[
        "Le Bignon"
    ],
    "name:eus_x_preferred":[
        "Le Bignon"
    ],
    "name:fra_x_preferred":[
        "Le Bignon"
    ],
    "name:hun_x_preferred":[
        "Le Bignon"
    ],
    "name:ita_x_preferred":[
        "Le Bignon"
    ],
    "name:lat_x_preferred":[
        "Bugnonium"
    ],
    "name:mlg_x_preferred":[
        "Le Bignon"
    ],
    "name:msa_x_preferred":[
        "Le Bignon"
    ],
    "name:nld_x_preferred":[
        "Le Bignon"
    ],
    "name:nrm_x_preferred":[
        "Le Bignon"
    ],
    "name:oci_x_preferred":[
        "Le Binyon"
    ],
    "name:pms_x_preferred":[
        "Le Bignon"
    ],
    "name:pol_x_preferred":[
        "Le Bignon"
    ],
    "name:por_x_preferred":[
        "Le Bignon"
    ],
    "name:ron_x_preferred":[
        "Le Bignon"
    ],
    "name:slk_x_preferred":[
        "Le Bignon"
    ],
    "name:slv_x_preferred":[
        "Le Bignon"
    ],
    "name:spa_x_preferred":[
        "Le Bignon"
    ],
    "name:srp_x_preferred":[
        "\u0411\u0438\u045a\u043e\u043d"
    ],
    "name:swe_x_preferred":[
        "Le Bignon"
    ],
    "name:ukr_x_preferred":[
        "\u041b\u0435-\u0411\u0456\u043d\u044c\u043e\u043d"
    ],
    "name:vie_x_preferred":[
        "Le Bignon"
    ],
    "name:vol_x_preferred":[
        "Le Bignon"
    ],
    "name:war_x_preferred":[
        "Le Bignon"
    ],
    "name:zho_x_preferred":[
        "\u52d2\u6bd4\u5c3c\u7fc1"
    ],
    "wof:name":"Le Bignon",
    "wof:placetype":"locality"
},
  "geometry": {"coordinates":[2.61742,48.02895],"type":"Point"}
}