{
  "type": "Feature",
  "properties": {
    "gn:admin1_code":"24",
    "gn:admin2_code":"45",
    "gn:admin3_code":"451",
    "gn:admin4_code":"45343.0",
    "gn:asciiname":"Le Bignon",
    "gn:country_code":"FR",
    "gn:dem":93,
    "gn:feature_class":"P",
    "gn:feature_code":"PPL",
    "gn:name":"Le Bignon",
    "gn:population":0,
    "gn:timezone":"Europe/Paris",
    "iso:country":"FR",
    "wof:name":"Le Bignon",
    "wof:placetype":"locality"
},
  "geometry": {"coordinates":[2.61742,48.02895],"type":"Point"}
}