{
  "type": "Feature",
  "properties": {
    "gn:admin1_code":"53",
    "gn:admin2_code":"22",
    "gn:admin3_code":"222",
    "gn:admin4_code":"22023",
    "gn:asciiname":"Kermarc'h",
    "gn:country_code":"FR",
    "gn:dem":261,
    "gn:feature_class":"P",
    "gn:feature_code":"PPL",
    "gn:name":"Kermarc\u2019h",
    "gn:population":0,
    "gn:timezone":"Europe/Paris",
    "iso:country":"FR",
    "wof:name":"Kermarc'h",
    "wof:placetype":"locality"
},
  "geometry": {"coordinates":[-3.31793,48.42878],"type":"Point"}
}