{
  "type": "Feature",
  "properties": {
    "gn:admin1_code":"75",
    "gn:admin2_code":"19",
    "gn:admin3_code":"193",
    "gn:admin4_code":"19006",
    "gn:asciiname":"Ceppe",
    "gn:country_code":"FR",
    "gn:dem":725,
    "gn:feature_class":"P",
    "gn:feature_code":"PPL",
    "gn:name":"Ceppe",
    "gn:population":0,
    "gn:timezone":"Europe/Paris",
    "iso:country":"FR",
    "wof:name":"Ceppe",
    "wof:placetype":"locality"
},
  "geometry": {"coordinates":[2.23333,45.56667],"type":"Point"}
}