{
  "type": "Feature",
  "properties": {
    "gn:admin1_code":"76",
    "gn:admin2_code":"82",
    "gn:admin3_code":"822",
    "gn:admin4_code":"82137",
    "gn:asciiname":"Parisot",
    "gn:country_code":"FR",
    "gn:dem":376,
    "gn:feature_class":"P",
    "gn:feature_code":"PPL",
    "gn:name":"Parisot",
    "gn:population":0,
    "gn:timezone":"Europe/Paris",
    "iso:country":"FR",
    "name:ceb_x_preferred":[
        "Parisot"
    ],
    "name:deu_x_preferred":[
        "Parisot"
    ],
    "name:fra_x_preferred":[
        "Parisot"
    ],
    "name:ita_x_preferred":[
        "Parisot"
    ],
    "name:nds_x_preferred":[
        "Parisot"
    ],
    "name:nld_x_preferred":[
        "Parisot"
    ],
    "name:oci_x_preferred":[
        "Paris\u00f2t"
    ],
    "name:pms_x_preferred":[
        "Parisot"
    ],
    "name:pol_x_preferred":[
        "Parisot"
    ],
    "name:por_x_preferred":[
        "Parisot"
    ],
    "name:rus_x_preferred":[
        "\u041f\u0430\u0440\u0438\u0437\u043e"
    ],
    "name:slk_x_preferred":[
        "Parisot"
    ],
    "name:spa_x_preferred":[
        "Parisot"
    ],
    "name:swe_x_preferred":[
        "Parisot"
    ],
    "name:ukr_x_preferred":[
        "\u041f\u0430\u0440\u0438\u0437\u043e"
    ],
    "wof:name":"Parisot",
    "wof:placetype":"locality"
},
  "geometry": {"coordinates":[1.85761,44.265],"type":"Point"}
}