{
  "type": "Feature",
  "properties": {
    "frgov:code_epci":"248200107",
    "frgov:insee_arr":"2",
    "frgov:insee_com":"82137",
    "frgov:insee_dep":"82",
    "frgov:insee_reg":"76",
    "frgov:nom_com":"Parisot",
    "frgov:nom_com_m":"PARISOT",
    "frgov:nom_dep":"TARN-ET-GARONNE",
    "frgov:nom_reg":"OCCITANIE",
    "frgov:statut":"Commune simple",
    "gn:admin1_code":"76",
    "gn:admin2_code":"82",
    "gn:admin3_code":"822",
    "gn:admin4_code":"82137",
    "gn:asciiname":"Parisot",
    "gn:country_code":"FR",
    "gn:dem":376,
    "gn:feature_class":"P",
    "gn:feature_code":"PPL",
    "gn:name":"Parisot",
    "gn:population":0,
    "gn:timezone":"Europe/Paris",
    "iso:country":"FR",
    "name:ceb_x_preferred":[
        "Parisot"
    ],
    "name:deu_x_preferred":[
        "Parisot"
    ],
    "name:fra_x_preferred":[
        "Parisot"
    ],
    "name:ita_x_preferred":[
        "Parisot"
    ],
    "name:nds_x_preferred":[
        "Parisot"
    ],
    "name:nld_x_preferred":[
        "Parisot"
    ],
    "name:oci_x_preferred":[
        "Paris\u00f2t"
    ],
    "name:pms_x_preferred":[
        "Parisot"
    ],
    "name:pol_x_preferred":[
        "Parisot"
    ],
    "name:por_x_preferred":[
        "Parisot"
    ],
    "name:rus_x_preferred":[
        "\u041f\u0430\u0440\u0438\u0437\u043e"
    ],
    "name:slk_x_preferred":[
        "Parisot"
    ],
    "name:spa_x_preferred":[
        "Parisot"
    ],
    "name:swe_x_preferred":[
        "Parisot"
    ],
    "name:ukr_x_preferred":[
        "\u041f\u0430\u0440\u0438\u0437\u043e"
    ],
    "qs:a0":"France",
    "qs:a1":"TARN-ET-GARONNE",
    "qs:a1_lc":"82",
    "qs:a1r":"MIDI-PYRENEES",
    "qs:a1r_lc":"73",
    "qs:a2_lc":"20",
    "qs:a2r_lc":"2",
    "qs:adm0":"France",
    "qs:adm0_a3":"FRA",
    "qs:la":"PARISOT",
    "qs:la_lc":"82137",
    "qs:level":"localadmin",
    "qs:type":"Commune simple",
    "wof:coterminous":[
        404362987
    ],
    "wof:name":"Parisot",
    "wof:placetype":"locality",
    "wof:placetype_local":"Commune simple"
},
  "geometry": {"coordinates":[1.85761,44.265],"type":"Point"}
}