{
  "type": "Feature",
  "properties": {
    "gn:admin1_code":"76",
    "gn:admin2_code":"82",
    "gn:admin3_code":"822",
    "gn:admin4_code":"82137",
    "gn:asciiname":"Parisot",
    "gn:country_code":"FR",
    "gn:dem":376,
    "gn:feature_class":"P",
    "gn:feature_code":"PPL",
    "gn:name":"Parisot",
    "gn:population":0,
    "gn:timezone":"Europe/Paris",
    "iso:country":"FR",
    "wof:name":"Parisot",
    "wof:placetype":"locality"
},
  "geometry": {"coordinates":[1.85761,44.265],"type":"Point"}
}