{
  "type": "Feature",
  "properties": {
    "gn:admin1_code":"32",
    "gn:admin2_code":"62",
    "gn:admin3_code":"624",
    "gn:admin4_code":"62832",
    "gn:asciiname":"Courteville",
    "gn:country_code":"FR",
    "gn:dem":18,
    "gn:feature_class":"P",
    "gn:feature_code":"PPL",
    "gn:name":"Courteville",
    "gn:population":0,
    "gn:timezone":"Europe/Paris",
    "iso:country":"FR",
    "wof:name":"Courteville",
    "wof:placetype":"locality"
},
  "geometry": {"coordinates":[1.69171,50.53002],"type":"Point"}
}