{
  "type": "Feature",
  "properties": {
    "gn:admin1_code":"27",
    "gn:admin2_code":"58",
    "gn:admin3_code":"581",
    "gn:admin4_code":"58309",
    "gn:asciiname":"Les Fossas",
    "gn:country_code":"FR",
    "gn:dem":470,
    "gn:feature_class":"P",
    "gn:feature_code":"PPL",
    "gn:name":"Les Fossas",
    "gn:population":0,
    "gn:timezone":"Europe/Paris",
    "iso:country":"FR",
    "wof:name":"Les Fossas",
    "wof:placetype":"locality"
},
  "geometry": {"coordinates":[3.91229,46.90848],"type":"Point"}
}