{
  "type": "Feature",
  "properties": {
    "gn:admin1_code":"44",
    "gn:admin2_code":"52",
    "gn:admin3_code":"521",
    "gn:admin4_code":"52254",
    "gn:asciiname":"Bas-Pre",
    "gn:country_code":"FR",
    "gn:dem":323,
    "gn:feature_class":"P",
    "gn:feature_code":"PPL",
    "gn:name":"Bas-Pr\u00e9",
    "gn:population":0,
    "gn:timezone":"Europe/Paris",
    "iso:country":"FR",
    "wof:name":"Bas-Pre",
    "wof:placetype":"locality"
},
  "geometry": {"coordinates":[4.96667,48.21667],"type":"Point"}
}