{
  "type": "Feature",
  "properties": {
    "gn:admin1_code":"76",
    "gn:admin2_code":"81",
    "gn:admin3_code":"812",
    "gn:admin4_code":"81086",
    "gn:asciiname":"Prades",
    "gn:country_code":"FR",
    "gn:dem":600,
    "gn:feature_class":"P",
    "gn:feature_code":"PPL",
    "gn:name":"Prades",
    "gn:population":0,
    "gn:timezone":"Europe/Paris",
    "iso:country":"FR",
    "wof:name":"Prades",
    "wof:placetype":"locality"
},
  "geometry": {"coordinates":[2.54552,43.70446],"type":"Point"}
}