{
  "type": "Feature",
  "properties": {
    "gn:admin1_code":"84",
    "gn:admin2_code":"26",
    "gn:admin3_code":"263",
    "gn:admin4_code":"26212",
    "gn:asciiname":"Les Auleas",
    "gn:country_code":"FR",
    "gn:dem":282,
    "gn:feature_class":"P",
    "gn:feature_code":"PPL",
    "gn:name":"Les Aul\u00e9as",
    "gn:population":0,
    "gn:timezone":"Europe/Paris",
    "iso:country":"FR",
    "wof:name":"Les Auleas",
    "wof:placetype":"locality"
},
  "geometry": {"coordinates":[5.03333,44.85],"type":"Point"}
}