{
  "type": "Feature",
  "properties": {
    "gn:admin1_code":"24",
    "gn:admin2_code":"37",
    "gn:admin3_code":"371",
    "gn:admin4_code":"37264",
    "gn:asciiname":"Le Hay",
    "gn:country_code":"FR",
    "gn:dem":46,
    "gn:feature_class":"P",
    "gn:feature_code":"PPL",
    "gn:name":"Le Hay",
    "gn:population":0,
    "gn:timezone":"Europe/Paris",
    "iso:country":"FR",
    "wof:name":"Le Hay",
    "wof:placetype":"locality"
},
  "geometry": {"coordinates":[0.45581,47.31483],"type":"Point"}
}