{
  "type": "Feature",
  "properties": {
    "gn:admin1_code":"84",
    "gn:admin2_code":"07",
    "gn:admin3_code":"071",
    "gn:admin4_code":"07050",
    "gn:asciiname":"Marvignes",
    "gn:country_code":"FR",
    "gn:dem":167,
    "gn:feature_class":"P",
    "gn:feature_code":"PPL",
    "gn:name":"Marvignes",
    "gn:population":0,
    "gn:timezone":"Europe/Paris",
    "iso:country":"FR",
    "name:und_x_variant":[
        "Marvigne",
        "Marvignes"
    ],
    "wof:name":"Marvignes",
    "wof:placetype":"locality"
},
  "geometry": {"coordinates":[4.11492,44.42352],"type":"Point"}
}