{
  "type": "Feature",
  "properties": {
    "gn:admin1_code":"84",
    "gn:admin2_code":"63",
    "gn:admin3_code":"631",
    "gn:admin4_code":"63056",
    "gn:asciiname":"Le Coupat",
    "gn:country_code":"FR",
    "gn:dem":667,
    "gn:feature_class":"P",
    "gn:feature_code":"PPL",
    "gn:name":"Le Coupat",
    "gn:population":0,
    "gn:timezone":"Europe/Paris",
    "iso:country":"FR",
    "name:und_x_variant":[
        "Coupat",
        "Le Coupat"
    ],
    "wof:name":"Le Coupat",
    "wof:placetype":"locality"
},
  "geometry": {"coordinates":[3.4672,45.61405],"type":"Point"}
}