{
  "type": "Feature",
  "properties": {
    "gn:admin1_code":"75",
    "gn:admin2_code":"33",
    "gn:admin3_code":"335",
    "gn:admin4_code":"33356",
    "gn:asciiname":"Tressac",
    "gn:country_code":"FR",
    "gn:dem":1,
    "gn:feature_class":"P",
    "gn:feature_code":"PPL",
    "gn:name":"Tressac",
    "gn:population":0,
    "gn:timezone":"Europe/Paris",
    "iso:country":"FR",
    "wof:name":"Tressac",
    "wof:placetype":"locality"
},
  "geometry": {"coordinates":[-0.31667,44.93333],"type":"Point"}
}