{
  "type": "Feature",
  "properties": {
    "gn:admin1_code":"28",
    "gn:admin2_code":"76",
    "gn:admin3_code":"763",
    "gn:admin4_code":"76325",
    "gn:asciiname":"Cotte-Cotte",
    "gn:country_code":"FR",
    "gn:dem":142,
    "gn:feature_class":"P",
    "gn:feature_code":"PPL",
    "gn:name":"Cotte-Cotte",
    "gn:population":0,
    "gn:timezone":"Europe/Paris",
    "iso:country":"FR",
    "wof:name":"Cotte-Cotte",
    "wof:placetype":"locality"
},
  "geometry": {"coordinates":[0.82633,49.66034000000001],"type":"Point"}
}