{
  "type": "Feature",
  "properties": {
    "gn:admin1_code":"84",
    "gn:admin2_code":"63",
    "gn:admin3_code":"634",
    "gn:admin4_code":"63462",
    "gn:asciiname":"Virlet",
    "gn:country_code":"FR",
    "gn:dem":533,
    "gn:feature_class":"P",
    "gn:feature_code":"PPL",
    "gn:name":"Virlet",
    "gn:population":0,
    "gn:timezone":"Europe/Paris",
    "iso:country":"FR",
    "wof:name":"Virlet",
    "wof:placetype":"locality"
},
  "geometry": {"coordinates":[2.6979,46.15544000000001],"type":"Point"}
}