{
  "type": "Feature",
  "properties": {
    "frgov:code_epci":"200072080",
    "frgov:insee_arr":"4",
    "frgov:insee_com":"63462",
    "frgov:insee_dep":"63",
    "frgov:insee_reg":"84",
    "frgov:nom_com":"Virlet",
    "frgov:nom_com_m":"VIRLET",
    "frgov:nom_dep":"PUY-DE-DOME",
    "frgov:nom_reg":"AUVERGNE-RHONE-ALPES",
    "frgov:statut":"Commune simple",
    "gn:admin1_code":"84",
    "gn:admin2_code":"63",
    "gn:admin3_code":"634",
    "gn:admin4_code":"63462",
    "gn:asciiname":"Virlet",
    "gn:country_code":"FR",
    "gn:dem":533,
    "gn:feature_class":"P",
    "gn:feature_code":"PPL",
    "gn:name":"Virlet",
    "gn:population":0,
    "gn:timezone":"Europe/Paris",
    "iso:country":"FR",
    "name:cat_x_preferred":[
        "Virlac"
    ],
    "name:ceb_x_preferred":[
        "Virlet"
    ],
    "name:deu_x_preferred":[
        "Virlet"
    ],
    "name:eus_x_preferred":[
        "Virlet"
    ],
    "name:fra_x_preferred":[
        "Virlet"
    ],
    "name:hun_x_preferred":[
        "Virlet"
    ],
    "name:ita_x_preferred":[
        "Virlet"
    ],
    "name:lat_x_preferred":[
        "Virlet"
    ],
    "name:mlg_x_preferred":[
        "Virlet"
    ],
    "name:msa_x_preferred":[
        "Virlet"
    ],
    "name:nld_x_preferred":[
        "Virlet"
    ],
    "name:oci_x_preferred":[
        "Virlet"
    ],
    "name:pms_x_preferred":[
        "Virlet"
    ],
    "name:pol_x_preferred":[
        "Virlet"
    ],
    "name:por_x_preferred":[
        "Virlet"
    ],
    "name:ron_x_preferred":[
        "Virlet"
    ],
    "name:slk_x_preferred":[
        "Virlet"
    ],
    "name:spa_x_preferred":[
        "Virlet"
    ],
    "name:swe_x_preferred":[
        "Virlet"
    ],
    "name:ukr_x_preferred":[
        "\u0412\u0456\u0440\u043b\u0435"
    ],
    "name:uzb_x_preferred":[
        "Virlet"
    ],
    "name:vie_x_preferred":[
        "Virlet"
    ],
    "name:vol_x_preferred":[
        "Virlet"
    ],
    "name:war_x_preferred":[
        "Virlet"
    ],
    "name:zho_x_preferred":[
        "\u7ef4\u5c14\u83b1"
    ],
    "qs:a0":"France",
    "qs:a1":"PUY-DE-DOME",
    "qs:a1_lc":"63",
    "qs:a1r":"AUVERGNE",
    "qs:a1r_lc":"83",
    "qs:a2_lc":"26",
    "qs:a2r_lc":"4",
    "qs:adm0":"France",
    "qs:adm0_a3":"FRA",
    "qs:la":"VIRLET",
    "qs:la_lc":"63462",
    "qs:level":"localadmin",
    "qs:type":"Commune simple",
    "wof:coterminous":[
        404366377
    ],
    "wof:name":"Virlet",
    "wof:placetype":"locality",
    "wof:placetype_local":"Commune simple"
},
  "geometry": {"coordinates":[2.6979,46.15544],"type":"Point"}
}