{
  "type": "Feature",
  "properties": {
    "gn:admin1_code":"75",
    "gn:admin2_code":"19",
    "gn:admin3_code":"193",
    "gn:admin4_code":"19028",
    "gn:asciiname":"Chantery",
    "gn:country_code":"FR",
    "gn:dem":640,
    "gn:feature_class":"P",
    "gn:feature_code":"PPL",
    "gn:name":"Chantery",
    "gn:population":0,
    "gn:timezone":"Europe/Paris",
    "iso:country":"FR",
    "wof:name":"Chantery",
    "wof:placetype":"locality"
},
  "geometry": {"coordinates":[2.47596,45.38736],"type":"Point"}
}