{
  "type": "Feature",
  "properties": {
    "frgov:code_epci":"240800920",
    "frgov:insee_arr":"4",
    "frgov:insee_com":"08431",
    "frgov:insee_dep":"08",
    "frgov:insee_reg":"44",
    "frgov:nom_com":"Sugny",
    "frgov:nom_com_m":"SUGNY",
    "frgov:nom_dep":"ARDENNES",
    "frgov:nom_reg":"GRAND EST",
    "frgov:statut":"Commune simple",
    "gn:admin1_code":"44",
    "gn:admin2_code":"08",
    "gn:admin3_code":"084",
    "gn:admin4_code":"08431",
    "gn:asciiname":"Sugny",
    "gn:country_code":"FR",
    "gn:dem":107,
    "gn:feature_class":"P",
    "gn:feature_code":"PPL",
    "gn:name":"Sugny",
    "gn:population":0,
    "gn:timezone":"Europe/Paris",
    "iso:country":"FR",
    "name:bug_x_preferred":[
        "Sugny"
    ],
    "name:cat_x_preferred":[
        "Sugny"
    ],
    "name:ceb_x_preferred":[
        "Sugny"
    ],
    "name:deu_x_preferred":[
        "Sugny"
    ],
    "name:eus_x_preferred":[
        "Sugny"
    ],
    "name:fra_x_preferred":[
        "Sugny"
    ],
    "name:hun_x_preferred":[
        "Sugny"
    ],
    "name:hye_x_preferred":[
        "\u054d\u0578\u0582\u0576\u056b"
    ],
    "name:ita_x_preferred":[
        "Sugny"
    ],
    "name:lat_x_preferred":[
        "Sugny"
    ],
    "name:ltz_x_preferred":[
        "Sugny"
    ],
    "name:mlg_x_preferred":[
        "Sugny"
    ],
    "name:msa_x_preferred":[
        "Sugny"
    ],
    "name:nld_x_preferred":[
        "Sugny"
    ],
    "name:oci_x_preferred":[
        "Sugny"
    ],
    "name:pms_x_preferred":[
        "Sugny"
    ],
    "name:pol_x_preferred":[
        "Sugny"
    ],
    "name:por_x_preferred":[
        "Sugny"
    ],
    "name:ron_x_preferred":[
        "Sugny"
    ],
    "name:rus_x_preferred":[
        "\u0421\u044e\u043d\u044c\u0438"
    ],
    "name:slk_x_preferred":[
        "Sugny"
    ],
    "name:spa_x_preferred":[
        "Sugny"
    ],
    "name:sqi_x_preferred":[
        "Sugny"
    ],
    "name:swe_x_preferred":[
        "Sugny"
    ],
    "name:ukr_x_preferred":[
        "\u0421\u044e\u043d\u044c\u0457"
    ],
    "name:vie_x_preferred":[
        "Sugny"
    ],
    "name:vol_x_preferred":[
        "Sugny"
    ],
    "name:war_x_preferred":[
        "Sugny"
    ],
    "qs:a0":"France",
    "qs:a1":"ARDENNES",
    "qs:a1_lc":"08",
    "qs:a1r":"CHAMPAGNE-ARDENNE",
    "qs:a1r_lc":"21",
    "qs:a2_lc":"17",
    "qs:a2r_lc":"4",
    "qs:adm0":"France",
    "qs:adm0_a3":"FRA",
    "qs:la":"SUGNY",
    "qs:la_lc":"08431",
    "qs:level":"localadmin",
    "qs:type":"Commune simple",
    "wof:coterminous":[
        404411873
    ],
    "wof:name":"Sugny",
    "wof:placetype":"locality",
    "wof:placetype_local":"Commune simple"
},
  "geometry": {"coordinates":[4.65557,49.35786],"type":"Point"}
}