{
  "type": "Feature",
  "properties": {
    "iso:country":"FR",
    "name:eng_x_preferred":[
        "Maroc"
    ],
    "name:fra_x_preferred":[
        "Maroc"
    ],
    "wof:name":"Maroc",
    "wof:placetype":"neighbourhood"
},
  "geometry": {"coordinates":[2.49167587128285,48.81515931939002],"type":"Point"}
}