{
  "type": "Feature",
  "properties": {
    "gn:admin1_code":"75",
    "gn:admin2_code":"24",
    "gn:admin3_code":"244",
    "gn:admin4_code":"24206",
    "gn:asciiname":"Le Breuil",
    "gn:country_code":"FR",
    "gn:dem":207,
    "gn:feature_class":"P",
    "gn:feature_code":"PPL",
    "gn:name":"Le Breuil",
    "gn:population":0,
    "gn:timezone":"Europe/Paris",
    "iso:country":"FR",
    "wof:name":"Le Breuil",
    "wof:placetype":"locality"
},
  "geometry": {"coordinates":[1.08535,44.75914],"type":"Point"}
}