{
  "type": "Feature",
  "properties": {
    "gn:admin1_code":"75",
    "gn:admin2_code":"24",
    "gn:admin3_code":"244",
    "gn:admin4_code":"24206",
    "gn:asciiname":"Le Breuil",
    "gn:country_code":"FR",
    "gn:dem":207,
    "gn:feature_class":"P",
    "gn:feature_code":"PPL",
    "gn:name":"Le Breuil",
    "gn:population":0,
    "gn:timezone":"Europe/Paris",
    "iso:country":"FR",
    "name:ceb_x_preferred":[
        "Le Breuil"
    ],
    "name:deu_x_preferred":[
        "Le Breuil"
    ],
    "name:fra_x_preferred":[
        "Le Breuil"
    ],
    "name:ita_x_preferred":[
        "Le Breuil"
    ],
    "name:lmo_x_preferred":[
        "Le Breuil"
    ],
    "name:nds_x_preferred":[
        "Le Breuil"
    ],
    "name:nld_x_preferred":[
        "Le Breuil"
    ],
    "name:pms_x_preferred":[
        "Le Breuil"
    ],
    "name:pol_x_preferred":[
        "Le Breuil"
    ],
    "name:por_x_preferred":[
        "Le Breuil"
    ],
    "name:rus_x_preferred":[
        "\u041b\u0435-\u0411\u0440\u0451\u0439"
    ],
    "name:slk_x_preferred":[
        "Le Breuil"
    ],
    "name:spa_x_preferred":[
        "Le Breuil"
    ],
    "name:sqi_x_preferred":[
        "Le Breuil"
    ],
    "name:swe_x_preferred":[
        "Le Breuil"
    ],
    "name:ukr_x_preferred":[
        "\u041b\u0435-\u0411\u0440\u0435\u0439"
    ],
    "wof:name":"Le Breuil",
    "wof:placetype":"locality"
},
  "geometry": {"coordinates":[1.08535,44.75914],"type":"Point"}
}