{
  "type": "Feature",
  "properties": {
    "gn:admin1_code":"44",
    "gn:admin2_code":"54",
    "gn:admin3_code":"541",
    "gn:admin4_code":"54011",
    "gn:asciiname":"La Malmaison",
    "gn:country_code":"FR",
    "gn:dem":365,
    "gn:feature_class":"P",
    "gn:feature_code":"PPL",
    "gn:name":"La Malmaison",
    "gn:population":0,
    "gn:timezone":"Europe/Paris",
    "iso:country":"FR",
    "name:bug_x_preferred":[
        "La Malmaison"
    ],
    "name:cat_x_preferred":[
        "La Malmaison"
    ],
    "name:ceb_x_preferred":[
        "La Malmaison"
    ],
    "name:deu_x_preferred":[
        "La Malmaison"
    ],
    "name:eus_x_preferred":[
        "La Malmaison"
    ],
    "name:fra_x_preferred":[
        "La Malmaison"
    ],
    "name:hun_x_preferred":[
        "La Malmaison"
    ],
    "name:hye_x_preferred":[
        "\u053c\u0561 \u0544\u0561\u056c\u0574\u0565\u0566\u0578\u0576"
    ],
    "name:ind_x_preferred":[
        "La Malmaison"
    ],
    "name:ita_x_preferred":[
        "La Malmaison"
    ],
    "name:lat_x_preferred":[
        "La Malmaison"
    ],
    "name:ltz_x_preferred":[
        "La Malmaison"
    ],
    "name:mlg_x_preferred":[
        "La Malmaison"
    ],
    "name:msa_x_preferred":[
        "La Malmaison"
    ],
    "name:nld_x_preferred":[
        "La Malmaison"
    ],
    "name:oci_x_preferred":[
        "La Malmaison"
    ],
    "name:pms_x_preferred":[
        "La Malmaison"
    ],
    "name:pol_x_preferred":[
        "La Malmaison"
    ],
    "name:por_x_preferred":[
        "La Malmaison"
    ],
    "name:ron_x_preferred":[
        "La Malmaison"
    ],
    "name:rus_x_preferred":[
        "\u041b\u0430-\u041c\u0430\u043b\u044c\u043c\u0435\u0437\u043e\u043d"
    ],
    "name:slk_x_preferred":[
        "La Malmaison"
    ],
    "name:spa_x_preferred":[
        "La Malmaison"
    ],
    "name:sqi_x_preferred":[
        "La Malmaison"
    ],
    "name:swe_x_preferred":[
        "La Malmaison"
    ],
    "name:ukr_x_preferred":[
        "\u041b\u0430-\u041c\u0430\u043b\u044c\u043c\u0435\u0437\u043e\u043d"
    ],
    "name:urd_x_preferred":[
        "\u0644\u0627 \u0645\u0627\u0644\u0645\u0627\u06cc\u0633\u0648\u0646"
    ],
    "name:uzb_x_preferred":[
        "La Malmaison"
    ],
    "name:vie_x_preferred":[
        "La Malmaison"
    ],
    "name:vol_x_preferred":[
        "La Malmaison"
    ],
    "name:war_x_preferred":[
        "La Malmaison"
    ],
    "name:zea_x_preferred":[
        "La Malmaison"
    ],
    "name:zho_x_preferred":[
        "\u62c9\u9a6c\u5c14\u8fc8\u677e"
    ],
    "wof:name":"La Malmaison",
    "wof:placetype":"locality"
},
  "geometry": {"coordinates":[5.58108,49.51562],"type":"Point"}
}