{
  "type": "Feature",
  "properties": {
    "iso:country":"FR",
    "name:ast_x_preferred":[
        "Val-Cenis"
    ],
    "name:cat_x_preferred":[
        "Val-Cenis"
    ],
    "name:deu_x_preferred":[
        "Val-Cenis"
    ],
    "name:ell_x_preferred":[
        "\u0392\u03b1\u03bb-\u03a3\u03b5\u03bd\u03af"
    ],
    "name:eng_x_preferred":[
        "Val-Cenis"
    ],
    "name:epo_x_preferred":[
        "Val-Cenis"
    ],
    "name:fin_x_preferred":[
        "Val-Cenis"
    ],
    "name:fra_x_preferred":[
        "Val-Cenis"
    ],
    "name:frp_x_preferred":[
        "V\u00e2l-Cenis"
    ],
    "name:gle_x_preferred":[
        "Val-Cenis"
    ],
    "name:ita_x_preferred":[
        "Val-Cenis"
    ],
    "name:jpn_x_preferred":[
        "\u30f4\u30a1\u30eb\uff1d\u30b9\u30cb"
    ],
    "name:lld_x_preferred":[
        "Val-Cenis"
    ],
    "name:nld_x_preferred":[
        "Val-Cenis"
    ],
    "name:oci_x_preferred":[
        "Val-Cenis"
    ],
    "name:pol_x_preferred":[
        "Val-Cenis"
    ],
    "name:por_x_preferred":[
        "Val-Cenis"
    ],
    "name:spa_x_preferred":[
        "Val-Cenis"
    ],
    "name:swe_x_preferred":[
        "Val-Cenis"
    ],
    "name:ukr_x_preferred":[
        "\u0412\u0430\u043b\u044c-\u0421\u0435\u043d\u0456"
    ],
    "name:vec_x_preferred":[
        "Val-Cenis"
    ],
    "name:zho_x_preferred":[
        "\u745f\u5c3c\u8c37"
    ],
    "name:zho_x_variant":[
        "\u74e6\u52d2\u745f\u5c3c"
    ],
    "qs_pg:aaroncc":"FR",
    "qs_pg:name":"Val Cenis",
    "qs_pg:name_adm0":"France",
    "qs_pg:name_adm1":"Rh\u00f4ne-Alpes",
    "qs_pg:photos":153,
    "qs_pg:photos_1k":31,
    "qs_pg:photos_9k":1,
    "qs_pg:photos_9r":4,
    "qs_pg:photos_all":153,
    "qs_pg:photos_sr":4,
    "qs_pg:pop_sr":0,
    "qs_pg:qs_pg_placetype":"locality",
    "qs_pg:qs_pg_placetype_gp":"Town",
    "qs_pg:woe_adm0":23424819,
    "woe:adm0_id":23424819,
    "woe:name_adm0":"France",
    "woe:name_adm1":"Rh\u00f4ne-Alpes",
    "woe:placetype":"Town",
    "wof:name":"Val Cenis",
    "wof:placetype":"neighbourhood"
},
  "geometry": {"coordinates":[6.903076,45.269268],"type":"Point"}
}