{
  "type": "Feature",
  "properties": {
    "gn:admin1_code":"28",
    "gn:admin2_code":"76",
    "gn:admin3_code":"761",
    "gn:admin4_code":"76166",
    "gn:asciiname":"Sainte-Beuve-aux-Champs",
    "gn:country_code":"FR",
    "gn:dem":227,
    "gn:feature_class":"P",
    "gn:feature_code":"PPL",
    "gn:name":"Sainte-Beuve-aux-Champs",
    "gn:population":0,
    "gn:timezone":"Europe/Paris",
    "iso:country":"FR",
    "name:und_x_variant":[
        "Sainte-Beuve",
        "Sainte-Beuve-aux-Champs"
    ],
    "wof:name":"Sainte-Beuve-aux-Champs",
    "wof:placetype":"locality"
},
  "geometry": {"coordinates":[1.60652,49.76972],"type":"Point"}
}