{
  "type": "Feature",
  "properties": {
    "gn:admin1_code":"75",
    "gn:admin2_code":"23",
    "gn:admin3_code":"232",
    "gn:admin4_code":"23230",
    "gn:asciiname":"Les Quoirs",
    "gn:country_code":"FR",
    "gn:dem":434,
    "gn:feature_class":"P",
    "gn:feature_code":"PPL",
    "gn:name":"Les Quoirs",
    "gn:population":0,
    "gn:timezone":"Europe/Paris",
    "iso:country":"FR",
    "wof:name":"Les Quoirs",
    "wof:placetype":"locality"
},
  "geometry": {"coordinates":[1.63122,45.95867],"type":"Point"}
}