{
  "type": "Feature",
  "properties": {
    "gn:admin1_code":"94",
    "gn:admin2_code":"2B",
    "gn:admin3_code":"2B3",
    "gn:admin4_code":"2B135",
    "gn:asciiname":"Pietrapola",
    "gn:country_code":"FR",
    "gn:dem":230,
    "gn:feature_class":"P",
    "gn:feature_code":"PPL",
    "gn:name":"Pietrapola",
    "gn:population":0,
    "gn:timezone":"Europe/Paris",
    "iso:country":"FR",
    "wof:name":"Pietrapola",
    "wof:placetype":"locality"
},
  "geometry": {"coordinates":[9.30015,41.98881],"type":"Point"}
}