{
  "type": "Feature",
  "properties": {
    "gn:admin1_code":"84",
    "gn:admin2_code":"63",
    "gn:admin3_code":"634",
    "gn:admin4_code":"63118",
    "gn:asciiname":"Le Cheval-Blanc",
    "gn:country_code":"FR",
    "gn:dem":720,
    "gn:feature_class":"P",
    "gn:feature_code":"PPL",
    "gn:name":"Le Cheval-Blanc",
    "gn:population":0,
    "gn:timezone":"Europe/Paris",
    "iso:country":"FR",
    "wof:name":"Le Cheval-Blanc",
    "wof:placetype":"locality"
},
  "geometry": {"coordinates":[2.56667,45.86667],"type":"Point"}
}