{
  "type": "Feature",
  "properties": {
    "gn:admin1_code":"24",
    "gn:admin2_code":"36",
    "gn:admin3_code":"362",
    "gn:admin4_code":"36128",
    "gn:asciiname":"Les Villerais",
    "gn:country_code":"FR",
    "gn:dem":165,
    "gn:feature_class":"P",
    "gn:feature_code":"PPL",
    "gn:name":"Les Villerais",
    "gn:population":0,
    "gn:timezone":"Europe/Paris",
    "iso:country":"FR",
    "wof:name":"Les Villerais",
    "wof:placetype":"locality"
},
  "geometry": {"coordinates":[1.77514,46.88904],"type":"Point"}
}