{
  "type": "Feature",
  "properties": {
    "gn:admin1_code":"84",
    "gn:admin2_code":"43",
    "gn:admin3_code":"433",
    "gn:admin4_code":"43212",
    "gn:asciiname":"Bost-Buisson",
    "gn:country_code":"FR",
    "gn:dem":918,
    "gn:feature_class":"P",
    "gn:feature_code":"PPL",
    "gn:name":"Bost-Buisson",
    "gn:population":0,
    "gn:timezone":"Europe/Paris",
    "iso:country":"FR",
    "wof:name":"Bost-Buisson",
    "wof:placetype":"locality"
},
  "geometry": {"coordinates":[3.9487,45.36854],"type":"Point"}
}