{
  "type": "Feature",
  "properties": {
    "gn:admin1_code":"76",
    "gn:admin2_code":"48",
    "gn:admin3_code":"481",
    "gn:admin4_code":"48146",
    "gn:asciiname":"Le Mas Andre",
    "gn:country_code":"FR",
    "gn:dem":924,
    "gn:feature_class":"P",
    "gn:feature_code":"PPL",
    "gn:name":"Le Mas Andr\u00e9",
    "gn:population":0,
    "gn:timezone":"Europe/Paris",
    "iso:country":"FR",
    "wof:name":"Le Mas Andre",
    "wof:placetype":"locality"
},
  "geometry": {"coordinates":[3.50773,44.36041],"type":"Point"}
}