{
  "type": "Feature",
  "properties": {
    "iso:country":"FR",
    "name:eng_x_preferred":[
        "Saint-Junien Airport"
    ],
    "name:msa_x_preferred":[
        "Lapangan Terbang St Junien"
    ],
    "oa:elevation_ft":"902",
    "oa:type":"small_airport",
    "woe:hierarchy":{
        "country_id":23424819,
        "county_id":12597196,
        "localadmin_id":12657808,
        "planet_id":1,
        "state_id":7153321
    },
    "wof:name":"A\u00e9rodrome de Saint-junien",
    "wof:placetype":"campus"
},
  "geometry": {"coordinates":[0.91889,45.9025],"type":"Point"}
}