{
  "type": "Feature",
  "properties": {
    "gn:admin1_code":"32",
    "gn:admin2_code":"59",
    "gn:admin3_code":"596",
    "gn:admin4_code":"59484",
    "gn:asciiname":"Blanc-Misseron",
    "gn:cc2":"FR",
    "gn:country_code":"FR",
    "gn:dem":28,
    "gn:feature_class":"P",
    "gn:feature_code":"PPL",
    "gn:name":"Blanc-Misseron",
    "gn:population":0,
    "gn:timezone":"Europe/Paris",
    "iso:country":"FR",
    "name:und_x_variant":[
        "Blanc-Misserom"
    ],
    "wof:name":"Blanc-Misseron",
    "wof:placetype":"locality"
},
  "geometry": {"coordinates":[3.67347,50.40266],"type":"Point"}
}