{
  "type": "Feature",
  "properties": {
    "gn:admin1_code":"84",
    "gn:admin2_code":"74",
    "gn:admin3_code":"742",
    "gn:admin4_code":"74250",
    "gn:asciiname":"Saint-Maurice-de-Rumilly",
    "gn:country_code":"FR",
    "gn:dem":481,
    "gn:feature_class":"P",
    "gn:feature_code":"PPL",
    "gn:name":"Saint-Maurice-de-Rumilly",
    "gn:population":0,
    "gn:timezone":"Europe/Paris",
    "iso:country":"FR",
    "name:und_x_variant":[
        "Saint-Maurice",
        "Saint-Maurice-de-Rumilly"
    ],
    "wof:name":"Saint-Maurice-de-Rumilly",
    "wof:placetype":"locality"
},
  "geometry": {"coordinates":[6.3561,46.05922],"type":"Point"}
}