{
  "type": "Feature",
  "properties": {
    "gn:admin1_code":"84",
    "gn:admin2_code":"63",
    "gn:admin3_code":"634",
    "gn:admin4_code":"63165",
    "gn:asciiname":"Villevergne",
    "gn:country_code":"FR",
    "gn:dem":751,
    "gn:feature_class":"P",
    "gn:feature_code":"PPL",
    "gn:name":"Villevergne",
    "gn:population":0,
    "gn:timezone":"Europe/Paris",
    "iso:country":"FR",
    "wof:name":"Villevergne",
    "wof:placetype":"locality"
},
  "geometry": {"coordinates":[2.44134,45.77359000000001],"type":"Point"}
}