{
  "type": "Feature",
  "properties": {
    "gn:admin1_code":"75",
    "gn:admin2_code":"19",
    "gn:admin3_code":"193",
    "gn:admin4_code":"19033",
    "gn:asciiname":"Mourieras",
    "gn:country_code":"FR",
    "gn:dem":717,
    "gn:feature_class":"P",
    "gn:feature_code":"PPL",
    "gn:name":"Mouri\u00e9ras",
    "gn:population":0,
    "gn:timezone":"Europe/Paris",
    "iso:country":"FR",
    "wof:name":"Mourieras",
    "wof:placetype":"locality"
},
  "geometry": {"coordinates":[1.92877,45.61657],"type":"Point"}
}