{
  "type": "Feature",
  "properties": {
    "gn:admin1_code":"75",
    "gn:admin2_code":"87",
    "gn:admin3_code":"871",
    "gn:admin4_code":"87136",
    "gn:asciiname":"Puycatelin",
    "gn:country_code":"FR",
    "gn:dem":231,
    "gn:feature_class":"P",
    "gn:feature_code":"PPL",
    "gn:name":"Puycatelin",
    "gn:population":0,
    "gn:timezone":"Europe/Paris",
    "iso:country":"FR",
    "name:und_x_variant":[
        "Le Puy-Catelin",
        "Puycatelin"
    ],
    "wof:name":"Puycatelin",
    "wof:placetype":"locality"
},
  "geometry": {"coordinates":[0.87056,46.20964],"type":"Point"}
}