{
  "type": "Feature",
  "properties": {
    "gn:admin1_code":"75",
    "gn:admin2_code":"24",
    "gn:admin3_code":"242",
    "gn:admin4_code":"24253",
    "gn:asciiname":"Pommier",
    "gn:country_code":"FR",
    "gn:dem":177,
    "gn:feature_class":"P",
    "gn:feature_code":"PPL",
    "gn:name":"Pommier",
    "gn:population":0,
    "gn:timezone":"Europe/Paris",
    "iso:country":"FR",
    "name:ara_x_preferred":[
        "\u0628\u0648\u0645\u064a\u064a\u0631"
    ],
    "name:cat_x_preferred":[
        "Pommier"
    ],
    "name:ceb_x_preferred":[
        "Pommier"
    ],
    "name:ces_x_preferred":[
        "Pommier"
    ],
    "name:deu_x_preferred":[
        "Pommier"
    ],
    "name:eus_x_preferred":[
        "Pommier"
    ],
    "name:fra_x_preferred":[
        "Pommier"
    ],
    "name:hun_x_preferred":[
        "Pommier"
    ],
    "name:ind_x_preferred":[
        "Pommier"
    ],
    "name:ita_x_preferred":[
        "Pommier"
    ],
    "name:kaz_x_preferred":[
        "\u041f\u043e\u043c\u043c\u044c\u0435"
    ],
    "name:lat_x_preferred":[
        "Pommier"
    ],
    "name:ltz_x_preferred":[
        "Pommier"
    ],
    "name:mlg_x_preferred":[
        "Pommier"
    ],
    "name:msa_x_preferred":[
        "Pommier"
    ],
    "name:nld_x_preferred":[
        "Pommier"
    ],
    "name:pms_x_preferred":[
        "Pommier"
    ],
    "name:pol_x_preferred":[
        "Pommier"
    ],
    "name:por_x_preferred":[
        "Pommier"
    ],
    "name:ron_x_preferred":[
        "Pommier"
    ],
    "name:slk_x_preferred":[
        "Pommier"
    ],
    "name:spa_x_preferred":[
        "Pommier"
    ],
    "name:swe_x_preferred":[
        "Pommier"
    ],
    "name:ukr_x_preferred":[
        "\u041f\u043e\u043c\u043c'\u0454"
    ],
    "name:vie_x_preferred":[
        "Pommier"
    ],
    "name:vol_x_preferred":[
        "Pommier"
    ],
    "name:war_x_preferred":[
        "Pommier"
    ],
    "name:zho_x_preferred":[
        "\u6ce2\u7c73\u8036"
    ],
    "wof:name":"Pommier",
    "wof:placetype":"locality"
},
  "geometry": {"coordinates":[0.55,45.46575],"type":"Point"}
}