{
  "type": "Feature",
  "properties": {
    "gn:admin1_code":"24",
    "gn:admin2_code":"18",
    "gn:admin3_code":"182",
    "gn:admin4_code":"18040",
    "gn:asciiname":"Cilly",
    "gn:country_code":"FR",
    "gn:dem":191,
    "gn:feature_class":"P",
    "gn:feature_code":"PPL",
    "gn:name":"Cilly",
    "gn:population":0,
    "gn:timezone":"Europe/Paris",
    "iso:country":"FR",
    "wof:name":"Cilly",
    "wof:placetype":"locality"
},
  "geometry": {"coordinates":[2.63787,46.88462],"type":"Point"}
}