{
  "type": "Feature",
  "properties": {
    "gn:admin1_code":"53",
    "gn:admin2_code":"56",
    "gn:admin3_code":"561",
    "gn:admin4_code":"56220",
    "gn:asciiname":"Sainte-Helene",
    "gn:country_code":"FR",
    "gn:dem":8,
    "gn:feature_class":"P",
    "gn:feature_code":"PPL",
    "gn:name":"Sainte-H\u00e9l\u00e8ne",
    "gn:population":1050,
    "gn:timezone":"Europe/Paris",
    "iso:country":"FR",
    "name:bre_x_preferred":[
        "Santez-Elen"
    ],
    "name:fra_x_preferred":[
        "Sainte-H\u00e9l\u00e8ne"
    ],
    "wof:name":"Sainte-Helene",
    "wof:placetype":"locality",
    "wof:population":1050
},
  "geometry": {"coordinates":[-3.20359,47.71976],"type":"Point"}
}