{
  "type": "Feature",
  "properties": {
    "frgov:code_epci":"245600440",
    "frgov:insee_arr":"1",
    "frgov:insee_com":"56220",
    "frgov:insee_dep":"56",
    "frgov:insee_reg":"53",
    "frgov:nom_com":"Sainte-H\u00e9l\u00e8ne",
    "frgov:nom_com_m":"SAINTE-HELENE",
    "frgov:nom_dep":"MORBIHAN",
    "frgov:nom_reg":"BRETAGNE",
    "frgov:statut":"Commune simple",
    "gn:admin1_code":"53",
    "gn:admin2_code":"56",
    "gn:admin3_code":"561",
    "gn:admin4_code":"56220",
    "gn:asciiname":"Sainte-Helene",
    "gn:country_code":"FR",
    "gn:dem":8,
    "gn:feature_class":"P",
    "gn:feature_code":"PPL",
    "gn:name":"Sainte-H\u00e9l\u00e8ne",
    "gn:population":1050,
    "gn:timezone":"Europe/Paris",
    "iso:country":"FR",
    "name:bre_x_preferred":[
        "Santez-Elen"
    ],
    "name:fra_x_preferred":[
        "Sainte-H\u00e9l\u00e8ne"
    ],
    "name:und_x_variant":[
        "Sainte-H\u00e9l\u00e8ne"
    ],
    "qs:a0":"France",
    "qs:a1":"MORBIHAN",
    "qs:a1_lc":"56",
    "qs:a1r":"BRETAGNE",
    "qs:a1r_lc":"53",
    "qs:a2_lc":"28",
    "qs:a2r_lc":"1",
    "qs:adm0":"France",
    "qs:adm0_a3":"FRA",
    "qs:la":"SAINTE-HELENE",
    "qs:la_lc":"56220",
    "qs:level":"localadmin",
    "qs:type":"Commune simple",
    "wof:coterminous":[
        404425451
    ],
    "wof:name":"Sainte-Helene",
    "wof:placetype":"locality",
    "wof:placetype_local":"Commune simple",
    "wof:population":1050
},
  "geometry": {"coordinates":[-3.20359,47.71976],"type":"Point"}
}