{
  "type": "Feature",
  "properties": {
    "gn:gn_country":"GP",
    "gn:gn_fcode":"PPL",
    "gn:gn_pop":1716,
    "gn:population":1716,
    "iso:country":"FR",
    "name:fra_x_preferred":[
        "Beaus\u00e9jour"
    ],
    "name:unk_x_variant":[
        "La Grande Anse"
    ],
    "qs_pg:aaroncc":"FR",
    "qs_pg:gn_country":"GP",
    "qs_pg:gn_fcode":"PPL",
    "qs_pg:gn_pop":1716,
    "qs_pg:name":"Grande Anse",
    "qs_pg:name_adm0":"Guadeloupe",
    "qs_pg:name_adm1":"Pointe-\u00c0-Pitre",
    "qs_pg:photos":29,
    "qs_pg:photos_1k":6,
    "qs_pg:photos_9k":1,
    "qs_pg:photos_9r":2,
    "qs_pg:photos_all":29,
    "qs_pg:photos_sr":2,
    "qs_pg:pop_sr":3,
    "qs_pg:qs_pg_placetype":"locality",
    "qs_pg:qs_pg_placetype_gp":"Town",
    "qs_pg:woe_adm0":23424831,
    "woe:adm0_id":23424831,
    "woe:name_adm0":"Guadeloupe",
    "woe:name_adm1":"Pointe-\u00c0-Pitre",
    "woe:placetype":"Town",
    "wof:name":"Grande Anse",
    "wof:placetype":"neighbourhood",
    "wof:population":1716
},
  "geometry": {"coordinates":[-61.07406,16.30351],"type":"Point"}
}