{
  "type": "Feature",
  "properties": {
    "gn:admin1_code":"24",
    "gn:admin2_code":"28",
    "gn:admin3_code":"283",
    "gn:admin4_code":"28064",
    "gn:asciiname":"Les Vignes",
    "gn:country_code":"FR",
    "gn:dem":131,
    "gn:feature_class":"P",
    "gn:feature_code":"PPL",
    "gn:name":"Les Vignes",
    "gn:population":0,
    "gn:timezone":"Europe/Paris",
    "iso:country":"FR",
    "name:cat_x_preferred":[
        "Las Vinhas"
    ],
    "name:ceb_x_preferred":[
        "Les Vignes"
    ],
    "name:ces_x_preferred":[
        "Les Vignes"
    ],
    "name:deu_x_preferred":[
        "Les Vignes"
    ],
    "name:eus_x_preferred":[
        "Les Vignes"
    ],
    "name:fra_x_preferred":[
        "Les Vignes"
    ],
    "name:hun_x_preferred":[
        "Les Vignes"
    ],
    "name:ita_x_preferred":[
        "Les Vignes"
    ],
    "name:kaz_x_preferred":[
        "\u041b\u0435-\u0412\u0438\u043d\u044c"
    ],
    "name:lat_x_preferred":[
        "Les Vignes"
    ],
    "name:lmo_x_preferred":[
        "Les Vignes"
    ],
    "name:msa_x_preferred":[
        "Les Vignes"
    ],
    "name:nld_x_preferred":[
        "Les Vignes"
    ],
    "name:oci_x_preferred":[
        "Las Vinhas"
    ],
    "name:pms_x_preferred":[
        "Les Vignes"
    ],
    "name:pol_x_preferred":[
        "Les Vignes"
    ],
    "name:por_x_preferred":[
        "Les Vignes"
    ],
    "name:ron_x_preferred":[
        "Les Vignes"
    ],
    "name:slk_x_preferred":[
        "Les Vignes"
    ],
    "name:spa_x_preferred":[
        "Les Vignes"
    ],
    "name:swe_x_preferred":[
        "Les Vignes"
    ],
    "name:ukr_x_preferred":[
        "\u041b\u0435-\u0412\u0456\u043d\u044c"
    ],
    "name:vie_x_preferred":[
        "Les Vignes"
    ],
    "name:vol_x_preferred":[
        "Les Vignes"
    ],
    "name:war_x_preferred":[
        "Les Vignes"
    ],
    "name:zho_x_preferred":[
        "\u83b1\u7ef4\u6d85"
    ],
    "wof:name":"Les Vignes",
    "wof:placetype":"locality"
},
  "geometry": {"coordinates":[1.508,48.80111],"type":"Point"}
}