{
  "type": "Feature",
  "properties": {
    "gn:admin1_code":"75",
    "gn:admin2_code":"23",
    "gn:admin3_code":"232",
    "gn:admin4_code":"23176",
    "gn:asciiname":"La Bussiere-Madeleine",
    "gn:country_code":"FR",
    "gn:dem":358,
    "gn:feature_class":"P",
    "gn:feature_code":"PPL",
    "gn:name":"La Bussi\u00e8re-Madeleine",
    "gn:population":0,
    "gn:timezone":"Europe/Paris",
    "iso:country":"FR",
    "wof:name":"La Bussiere-Madeleine",
    "wof:placetype":"locality"
},
  "geometry": {"coordinates":[1.43752,46.25469],"type":"Point"}
}