{
  "type": "Feature",
  "properties": {
    "gn:admin1_code":"84",
    "gn:admin2_code":"73",
    "gn:admin3_code":"732",
    "gn:admin4_code":"73020",
    "gn:asciiname":"Montagny",
    "gn:country_code":"FR",
    "gn:dem":802,
    "gn:feature_class":"P",
    "gn:feature_code":"PPL",
    "gn:name":"Montagny",
    "gn:population":0,
    "gn:timezone":"Europe/Paris",
    "iso:country":"FR",
    "name:ceb_x_preferred":[
        "Montagny"
    ],
    "name:deu_x_preferred":[
        "Montagny"
    ],
    "name:epo_x_preferred":[
        "Montagny"
    ],
    "name:fra_x_preferred":[
        "Montagny"
    ],
    "name:ita_x_preferred":[
        "Montagny"
    ],
    "name:lmo_x_preferred":[
        "Montagny"
    ],
    "name:nds_x_preferred":[
        "Montagny"
    ],
    "name:nld_x_preferred":[
        "Montagny"
    ],
    "name:pms_x_preferred":[
        "Montagny"
    ],
    "name:pol_x_preferred":[
        "Montagny"
    ],
    "name:por_x_preferred":[
        "Montagny"
    ],
    "name:slk_x_preferred":[
        "Montagny"
    ],
    "name:spa_x_preferred":[
        "Montagny"
    ],
    "name:swe_x_preferred":[
        "Montagny"
    ],
    "name:ukr_x_preferred":[
        "\u041c\u043e\u043d\u0442\u0430\u043d\u044c\u0457"
    ],
    "wof:name":"Montagny",
    "wof:placetype":"locality"
},
  "geometry": {"coordinates":[6.07455,45.71981],"type":"Point"}
}