{
  "type": "Feature",
  "properties": {
    "gn:admin1_code":"75",
    "gn:admin2_code":"19",
    "gn:admin3_code":"193",
    "gn:admin4_code":"19263",
    "gn:asciiname":"Robert",
    "gn:country_code":"FR",
    "gn:dem":613,
    "gn:feature_class":"P",
    "gn:feature_code":"PPL",
    "gn:name":"Robert",
    "gn:population":0,
    "gn:timezone":"Europe/Paris",
    "iso:country":"FR",
    "name:ara_x_preferred":[
        "\u0631\u0648\u0628\u0631\u062a"
    ],
    "name:aze_x_preferred":[
        "Robert"
    ],
    "name:bre_x_preferred":[
        "Robert"
    ],
    "name:ces_x_preferred":[
        "Robert"
    ],
    "name:dan_x_preferred":[
        "Robert"
    ],
    "name:deu_x_preferred":[
        "Robert"
    ],
    "name:diq_x_preferred":[
        "Robert"
    ],
    "name:epo_x_preferred":[
        "Robert"
    ],
    "name:est_x_preferred":[
        "Robert"
    ],
    "name:fin_x_preferred":[
        "Robert"
    ],
    "name:fra_x_preferred":[
        "Robert"
    ],
    "name:hun_x_preferred":[
        "R\u00f3bert"
    ],
    "name:jpn_x_preferred":[
        "\u30ed\u30d9\u30eb\u30c8"
    ],
    "name:lav_x_preferred":[
        "Roberts"
    ],
    "name:nld_x_preferred":[
        "Robert"
    ],
    "name:nno_x_preferred":[
        "Robert"
    ],
    "name:nor_x_preferred":[
        "Robert"
    ],
    "name:pol_x_preferred":[
        "Robert"
    ],
    "name:slv_x_preferred":[
        "Robert"
    ],
    "name:swe_x_preferred":[
        "Robert"
    ],
    "name:tel_x_preferred":[
        "\u0c30\u0c3e\u0c2c\u0c30\u0c4d\u0c1f\u0c4d"
    ],
    "name:vie_x_preferred":[
        "Robert"
    ],
    "name:zho_x_preferred":[
        "\u7f57\u4f2f\u7279"
    ],
    "wof:name":"Robert",
    "wof:placetype":"locality"
},
  "geometry": {"coordinates":[2.0471,45.42991],"type":"Point"}
}