{
  "type": "Feature",
  "properties": {
    "gn:admin1_code":"75",
    "gn:admin2_code":"19",
    "gn:admin3_code":"193",
    "gn:admin4_code":"19263",
    "gn:asciiname":"Robert",
    "gn:country_code":"FR",
    "gn:dem":613,
    "gn:feature_class":"P",
    "gn:feature_code":"PPL",
    "gn:name":"Robert",
    "gn:population":0,
    "gn:timezone":"Europe/Paris",
    "iso:country":"FR",
    "wof:name":"Robert",
    "wof:placetype":"locality"
},
  "geometry": {"coordinates":[2.0471,45.42991],"type":"Point"}
}