{
  "type": "Feature",
  "properties": {
    "iso:country":"FR",
    "name:ceb_x_preferred":[
        "Cap Gris-Nez"
    ],
    "name:ces_x_preferred":[
        "Gris Nez"
    ],
    "name:deu_x_preferred":[
        "Cap Gris-Nez"
    ],
    "name:epo_x_preferred":[
        "Kabo Gris-Nez"
    ],
    "name:eus_x_preferred":[
        "Cap Gris Nez"
    ],
    "name:fra_x_preferred":[
        "Cap Gris-Nez"
    ],
    "name:hun_x_preferred":[
        "Cap Gris-Nez"
    ],
    "name:ita_x_preferred":[
        "Cap Gris-Nez"
    ],
    "name:nld_x_preferred":[
        "Cap Gris-Nez"
    ],
    "name:nno_x_preferred":[
        "Cap Gris-Nez"
    ],
    "name:nor_x_preferred":[
        "Cap Gris-Nez"
    ],
    "name:por_x_preferred":[
        "Cabo Gris-Nez"
    ],
    "name:spa_x_preferred":[
        "Cabo Gris-Nez"
    ],
    "name:vls_x_preferred":[
        "Koap Zwartenesse"
    ],
    "qs_pg:aaroncc":"FR",
    "qs_pg:name":"Cap Gris-Nez",
    "qs_pg:name_adm0":"France",
    "qs_pg:name_adm1":"Nord-Pas-de-Calais",
    "qs_pg:photos":248,
    "qs_pg:photos_1k":50,
    "qs_pg:photos_9k":1,
    "qs_pg:photos_9r":4,
    "qs_pg:photos_all":248,
    "qs_pg:photos_sr":4,
    "qs_pg:pop_sr":0,
    "qs_pg:qs_pg_placetype":"locality",
    "qs_pg:qs_pg_placetype_gp":"Town",
    "qs_pg:woe_adm0":23424819,
    "woe:adm0_id":23424819,
    "woe:name_adm0":"France",
    "woe:name_adm1":"Nord-Pas-de-Calais",
    "woe:placetype":"Town",
    "wof:name":"Cap Gris-Nez",
    "wof:placetype":"neighbourhood"
},
  "geometry": {"coordinates":[1.590532,50.868378],"type":"Point"}
}