{
  "type": "Feature",
  "properties": {
    "gn:admin1_code":"84",
    "gn:admin2_code":"26",
    "gn:admin3_code":"261",
    "gn:admin4_code":"26183",
    "gn:asciiname":"Blacons",
    "gn:country_code":"FR",
    "gn:dem":230,
    "gn:feature_class":"P",
    "gn:feature_code":"PPL",
    "gn:name":"Blacons",
    "gn:population":0,
    "gn:timezone":"Europe/Paris",
    "iso:country":"FR",
    "wof:name":"Blacons",
    "wof:placetype":"locality"
},
  "geometry": {"coordinates":[5.09153,44.71084000000001],"type":"Point"}
}