{
  "type": "Feature",
  "properties": {
    "gn:admin1_code":"84",
    "gn:admin2_code":"42",
    "gn:admin3_code":"421",
    "gn:admin4_code":"42094",
    "gn:asciiname":"Randan",
    "gn:country_code":"FR",
    "gn:dem":326,
    "gn:feature_class":"P",
    "gn:feature_code":"PPL",
    "gn:name":"Randan",
    "gn:population":0,
    "gn:timezone":"Europe/Paris",
    "iso:country":"FR",
    "name:pol_x_preferred":[
        "Randan"
    ],
    "name:zho_x_preferred":[
        "\u6717\u5f53"
    ],
    "wof:name":"Randan",
    "wof:placetype":"locality"
},
  "geometry": {"coordinates":[4.21667,45.73333],"type":"Point"}
}