{
  "type": "Feature",
  "properties": {
    "frgov:code_epci":"200043263",
    "frgov:insee_arr":"1",
    "frgov:insee_com":"59169",
    "frgov:insee_dep":"59",
    "frgov:insee_reg":"32",
    "frgov:nom_com":"Damousies",
    "frgov:nom_com_m":"DAMOUSIES",
    "frgov:nom_dep":"NORD",
    "frgov:nom_reg":"HAUTS-DE-FRANCE",
    "frgov:statut":"Commune simple",
    "gn:admin1_code":"32",
    "gn:admin2_code":"59",
    "gn:admin3_code":"591",
    "gn:admin4_code":"59169",
    "gn:asciiname":"Damousies",
    "gn:country_code":"FR",
    "gn:dem":153,
    "gn:feature_class":"P",
    "gn:feature_code":"PPL",
    "gn:name":"Damousies",
    "gn:population":0,
    "gn:timezone":"Europe/Paris",
    "iso:country":"FR",
    "name:bre_x_preferred":[
        "Damousies"
    ],
    "name:cat_x_preferred":[
        "Damousies"
    ],
    "name:ceb_x_preferred":[
        "Damousies"
    ],
    "name:deu_x_preferred":[
        "Damousies"
    ],
    "name:epo_x_preferred":[
        "Damousies"
    ],
    "name:eus_x_preferred":[
        "Damousies"
    ],
    "name:fra_x_preferred":[
        "Damousies"
    ],
    "name:hun_x_preferred":[
        "Damousies"
    ],
    "name:ind_x_preferred":[
        "Damousies"
    ],
    "name:ita_x_preferred":[
        "Damousies"
    ],
    "name:kaz_x_preferred":[
        "\u0414\u0430\u043c\u0443\u0437\u0438"
    ],
    "name:lat_x_preferred":[
        "Damousies"
    ],
    "name:mlg_x_preferred":[
        "Damousies"
    ],
    "name:msa_x_preferred":[
        "Damousies"
    ],
    "name:nld_x_preferred":[
        "Damousies"
    ],
    "name:oci_x_preferred":[
        "Damousies"
    ],
    "name:pol_x_preferred":[
        "Damousies"
    ],
    "name:ron_x_preferred":[
        "Damousies"
    ],
    "name:slk_x_preferred":[
        "Damousies"
    ],
    "name:spa_x_preferred":[
        "Damousies"
    ],
    "name:srp_x_preferred":[
        "\u0414\u0430\u043c\u0443\u0437\u0438"
    ],
    "name:swe_x_preferred":[
        "Damousies"
    ],
    "name:ukr_x_preferred":[
        "\u0414\u0430\u043c\u0443\u0437\u0456"
    ],
    "name:vie_x_preferred":[
        "Damousies"
    ],
    "name:vol_x_preferred":[
        "Damousies"
    ],
    "name:war_x_preferred":[
        "Damousies"
    ],
    "name:zho_x_preferred":[
        "\u8fbe\u7a46\u897f"
    ],
    "qs:a0":"France",
    "qs:a1":"NORD",
    "qs:a1_lc":"59",
    "qs:a1r":"NORD-PAS-DE-CALAIS",
    "qs:a1r_lc":"31",
    "qs:a2_lc":"45",
    "qs:a2r_lc":"1",
    "qs:adm0":"France",
    "qs:adm0_a3":"FRA",
    "qs:la":"DAMOUSIES",
    "qs:la_lc":"59169",
    "qs:level":"localadmin",
    "qs:type":"Commune simple",
    "wof:coterminous":[
        404415397
    ],
    "wof:name":"Damousies",
    "wof:placetype":"locality",
    "wof:placetype_local":"Commune simple"
},
  "geometry": {"coordinates":[4.01341,50.21959],"type":"Point"}
}