{
  "type": "Feature",
  "properties": {
    "gn:admin1_code":"27",
    "gn:admin2_code":"58",
    "gn:admin3_code":"583",
    "gn:admin4_code":"58092",
    "gn:asciiname":"Ligny",
    "gn:country_code":"FR",
    "gn:dem":291,
    "gn:feature_class":"P",
    "gn:feature_code":"PPL",
    "gn:name":"Ligny",
    "gn:population":0,
    "gn:timezone":"Europe/Paris",
    "iso:country":"FR",
    "name:cat_x_preferred":[
        "Ligny"
    ],
    "name:deu_x_preferred":[
        "Ligny"
    ],
    "name:est_x_preferred":[
        "Ligny"
    ],
    "name:fas_x_preferred":[
        "\u0644\u06cc\u06af\u0646\u06cc"
    ],
    "name:fra_x_preferred":[
        "Ligny"
    ],
    "name:jpn_x_preferred":[
        "\u30ea\u30cb\u30fc"
    ],
    "name:lmo_x_preferred":[
        "Ligny"
    ],
    "name:nld_x_preferred":[
        "Ligny"
    ],
    "name:pol_x_preferred":[
        "Ligny"
    ],
    "name:spa_x_preferred":[
        "Ligny"
    ],
    "name:swe_x_preferred":[
        "Ligny"
    ],
    "name:wln_x_preferred":[
        "Lign\u00e8"
    ],
    "wof:name":"Ligny",
    "wof:placetype":"locality"
},
  "geometry": {"coordinates":[3.50926,47.14359],"type":"Point"}
}