{
  "type": "Feature",
  "properties": {
    "gn:admin1_code":"27",
    "gn:admin2_code":"89",
    "gn:admin3_code":"893",
    "gn:admin4_code":"89483.0",
    "gn:asciiname":"Les Basses Bergeries",
    "gn:country_code":"FR",
    "gn:dem":174,
    "gn:feature_class":"P",
    "gn:feature_code":"PPL",
    "gn:name":"Les Basses Bergeries",
    "gn:population":0,
    "gn:timezone":"Europe/Paris",
    "iso:country":"FR",
    "wof:name":"Les Basses Bergeries",
    "wof:placetype":"locality"
},
  "geometry": {"coordinates":[3.44114,48.25636],"type":"Point"}
}