{
  "type": "Feature",
  "properties": {
    "gn:admin1_code":"27",
    "gn:admin2_code":"25",
    "gn:admin3_code":"251",
    "gn:admin4_code":"25171",
    "gn:asciiname":"Courcelles",
    "gn:country_code":"FR",
    "gn:dem":360,
    "gn:feature_class":"P",
    "gn:feature_code":"PPL",
    "gn:name":"Courcelles",
    "gn:population":66,
    "gn:timezone":"Europe/Paris",
    "iso:country":"FR",
    "name:und_x_variant":[
        "Courcelles-l\u00e8s-Quingey",
        "Courcelles"
    ],
    "wof:name":"Courcelles",
    "wof:placetype":"locality",
    "wof:population":66
},
  "geometry": {"coordinates":[5.95558,47.09425],"type":"Point"}
}