{
  "type": "Feature",
  "properties": {
    "frgov:code_epci":"200068070",
    "frgov:insee_arr":"1",
    "frgov:insee_com":"25171",
    "frgov:insee_dep":"25",
    "frgov:insee_reg":"27",
    "frgov:nom_com":"Courcelles",
    "frgov:nom_com_m":"COURCELLES",
    "frgov:nom_dep":"DOUBS",
    "frgov:nom_reg":"BOURGOGNE-FRANCHE-COMTE",
    "frgov:statut":"Commune simple",
    "gn:admin1_code":"27",
    "gn:admin2_code":"25",
    "gn:admin3_code":"251",
    "gn:admin4_code":"25171",
    "gn:asciiname":"Courcelles",
    "gn:country_code":"FR",
    "gn:dem":360,
    "gn:feature_class":"P",
    "gn:feature_code":"PPL",
    "gn:name":"Courcelles",
    "gn:population":66,
    "gn:timezone":"Europe/Paris",
    "iso:country":"FR",
    "name:cat_x_preferred":[
        "Courcelles"
    ],
    "name:ceb_x_preferred":[
        "Courcelles"
    ],
    "name:ces_x_preferred":[
        "Courcelles"
    ],
    "name:deu_x_preferred":[
        "Courcelles"
    ],
    "name:epo_x_preferred":[
        "Courcelles"
    ],
    "name:fra_x_preferred":[
        "Courcelles"
    ],
    "name:ita_x_preferred":[
        "Courcelles"
    ],
    "name:nds_x_preferred":[
        "Courcelles"
    ],
    "name:nld_x_preferred":[
        "Courcelles"
    ],
    "name:pms_x_preferred":[
        "Courcelles"
    ],
    "name:pol_x_preferred":[
        "Courcelles"
    ],
    "name:por_x_preferred":[
        "Courcelles"
    ],
    "name:rus_x_preferred":[
        "\u041a\u0443\u0440\u0441\u0435\u043b\u044c"
    ],
    "name:slk_x_preferred":[
        "Courcelles"
    ],
    "name:spa_x_preferred":[
        "Courcelles"
    ],
    "name:swe_x_preferred":[
        "Courcelles"
    ],
    "name:ukr_x_preferred":[
        "\u041a\u0443\u0440\u0441\u0435\u043b\u044c"
    ],
    "name:und_x_variant":[
        "Courcelles-l\u00e8s-Quingey",
        "Courcelles"
    ],
    "qs:a0":"France",
    "qs:a1":"DOUBS",
    "qs:a1_lc":"25",
    "qs:a1r":"FRANCHE-COMTE",
    "qs:a1r_lc":"43",
    "qs:a2_lc":"22",
    "qs:a2r_lc":"1",
    "qs:adm0":"France",
    "qs:adm0_a3":"FRA",
    "qs:la":"COURCELLES",
    "qs:la_lc":"25171",
    "qs:level":"localadmin",
    "qs:type":"Commune simple",
    "wof:coterminous":[
        404395417
    ],
    "wof:name":"Courcelles",
    "wof:placetype":"locality",
    "wof:placetype_local":"Commune simple",
    "wof:population":66
},
  "geometry": {"coordinates":[5.95558,47.09425],"type":"Point"}
}