{
  "type": "Feature",
  "properties": {
    "gn:admin1_code":"27",
    "gn:admin2_code":"58",
    "gn:admin3_code":"582",
    "gn:admin4_code":"58206.0",
    "gn:asciiname":"Serres",
    "gn:country_code":"FR",
    "gn:dem":236,
    "gn:feature_class":"P",
    "gn:feature_code":"PPL",
    "gn:name":"Serres",
    "gn:population":0,
    "gn:timezone":"Europe/Paris",
    "iso:country":"FR",
    "wof:name":"Serres",
    "wof:placetype":"locality"
},
  "geometry": {"coordinates":[3.45333,47.33893],"type":"Point"}
}