{
  "type": "Feature",
  "properties": {
    "gn:admin1_code":"84",
    "gn:admin2_code":"38",
    "gn:admin3_code":"382",
    "gn:admin4_code":"38001",
    "gn:asciiname":"Laregnier",
    "gn:country_code":"FR",
    "gn:dem":376,
    "gn:feature_class":"P",
    "gn:feature_code":"PPL",
    "gn:name":"Laregnier",
    "gn:population":0,
    "gn:timezone":"Europe/Paris",
    "iso:country":"FR",
    "wof:name":"Laregnier",
    "wof:placetype":"locality"
},
  "geometry": {"coordinates":[5.57529,45.5508],"type":"Point"}
}