{
  "type": "Feature",
  "properties": {
    "gn:admin1_code":"28",
    "gn:admin2_code":"61",
    "gn:admin3_code":"613",
    "gn:admin4_code":"61323",
    "gn:asciiname":"La Martiniere",
    "gn:country_code":"FR",
    "gn:dem":226,
    "gn:feature_class":"P",
    "gn:feature_code":"PPL",
    "gn:name":"La Martini\u00e8re",
    "gn:population":0,
    "gn:timezone":"Europe/Paris",
    "iso:country":"FR",
    "wof:name":"La Martiniere",
    "wof:placetype":"locality"
},
  "geometry": {"coordinates":[0.91468,48.50314],"type":"Point"}
}