{
  "type": "Feature",
  "properties": {
    "gn:admin1_code":"52",
    "gn:admin2_code":"44",
    "gn:admin3_code":"441",
    "gn:admin4_code":"44146",
    "gn:asciiname":"La Pisiere",
    "gn:country_code":"FR",
    "gn:dem":92,
    "gn:feature_class":"P",
    "gn:feature_code":"PPL",
    "gn:name":"La Pisi\u00e8re",
    "gn:population":0,
    "gn:timezone":"Europe/Paris",
    "iso:country":"FR",
    "wof:name":"La Pisiere",
    "wof:placetype":"locality"
},
  "geometry": {"coordinates":[-1.37744,47.77111],"type":"Point"}
}