{
  "type": "Feature",
  "properties": {
    "gn:admin1_code":"76",
    "gn:admin2_code":"30",
    "gn:admin3_code":"303",
    "gn:admin4_code":"30064",
    "gn:asciiname":"Campestre-et-Luc",
    "gn:country_code":"FR",
    "gn:dem":782,
    "gn:feature_class":"P",
    "gn:feature_code":"PPL",
    "gn:name":"Campestre-et-Luc",
    "gn:population":0,
    "gn:timezone":"Europe/Paris",
    "iso:country":"FR",
    "name:bug_x_preferred":[
        "Campestre-et-Luc"
    ],
    "name:ceb_x_preferred":[
        "Campestre-et-Luc"
    ],
    "name:deu_x_preferred":[
        "Campestre-et-Luc"
    ],
    "name:fra_x_preferred":[
        "Campestre-et-Luc"
    ],
    "name:hun_x_preferred":[
        "Campestre-et-Luc"
    ],
    "name:ita_x_preferred":[
        "Campestre-et-Luc"
    ],
    "name:kaz_x_preferred":[
        "\u041a\u0430\u043c\u043f\u0435\u0441\u0442\u0440-\u0435-\u041b\u044e\u043a"
    ],
    "name:lat_x_preferred":[
        "Campestre-et-Luc"
    ],
    "name:lmo_x_preferred":[
        "Campestre-et-Luc"
    ],
    "name:mlg_x_preferred":[
        "Campestre-et-Luc"
    ],
    "name:msa_x_preferred":[
        "Campestre-et-Luc"
    ],
    "name:nld_x_preferred":[
        "Campestre-et-Luc"
    ],
    "name:pms_x_preferred":[
        "Campestre-et-Luc"
    ],
    "name:pol_x_preferred":[
        "Campestre-et-Luc"
    ],
    "name:por_x_preferred":[
        "Campestre-et-Luc"
    ],
    "name:ron_x_preferred":[
        "Campestre-et-Luc"
    ],
    "name:slk_x_preferred":[
        "Campestre-et-Luc"
    ],
    "name:spa_x_preferred":[
        "Campestre-et-Luc"
    ],
    "name:swe_x_preferred":[
        "Campestre-et-Luc"
    ],
    "name:ukr_x_preferred":[
        "\u041a\u0430\u043c\u043f\u0435\u0441\u0442\u0440-\u0435-\u041b\u044e\u043a"
    ],
    "name:und_x_variant":[
        "Campestre",
        "Campestre-et-Luc"
    ],
    "name:vie_x_preferred":[
        "Campestre-et-Luc"
    ],
    "name:vol_x_preferred":[
        "Campestre-et-Luc"
    ],
    "name:war_x_preferred":[
        "Campestre-et-Luc"
    ],
    "name:zho_x_preferred":[
        "\u5eb7\u4f69\u65af\u7279\u5c14\u548c\u5415\u514b"
    ],
    "wof:name":"Campestre-et-Luc",
    "wof:placetype":"locality"
},
  "geometry": {"coordinates":[3.42045,43.95295],"type":"Point"}
}