{
  "type": "Feature",
  "properties": {
    "gn:admin1_code":"76",
    "gn:admin2_code":"30",
    "gn:admin3_code":"303",
    "gn:admin4_code":"30064",
    "gn:asciiname":"Campestre-et-Luc",
    "gn:country_code":"FR",
    "gn:dem":782,
    "gn:feature_class":"P",
    "gn:feature_code":"PPL",
    "gn:name":"Campestre-et-Luc",
    "gn:population":0,
    "gn:timezone":"Europe/Paris",
    "iso:country":"FR",
    "name:und_x_variant":[
        "Campestre",
        "Campestre-et-Luc"
    ],
    "wof:name":"Campestre-et-Luc",
    "wof:placetype":"locality"
},
  "geometry": {"coordinates":[3.42045,43.95295],"type":"Point"}
}