{
  "type": "Feature",
  "properties": {
    "gn:admin1_code":"27",
    "gn:admin2_code":"89",
    "gn:admin3_code":"891",
    "gn:admin4_code":"89340",
    "gn:asciiname":"Le Buisson",
    "gn:country_code":"FR",
    "gn:dem":325,
    "gn:feature_class":"P",
    "gn:feature_code":"PPL",
    "gn:name":"Le Buisson",
    "gn:population":0,
    "gn:timezone":"Europe/Paris",
    "iso:country":"FR",
    "name:ceb_x_preferred":[
        "Le Buisson"
    ],
    "name:deu_x_preferred":[
        "Le Buisson"
    ],
    "name:fra_x_preferred":[
        "Le Buisson"
    ],
    "name:hun_x_preferred":[
        "Le Buisson"
    ],
    "name:ita_x_preferred":[
        "Le Buisson"
    ],
    "name:nds_x_preferred":[
        "Le Buisson"
    ],
    "name:oci_x_preferred":[
        "Le Buisson"
    ],
    "name:por_x_preferred":[
        "Le Buisson"
    ],
    "name:slk_x_preferred":[
        "Le Buisson"
    ],
    "name:spa_x_preferred":[
        "Le Buisson"
    ],
    "name:swe_x_preferred":[
        "Le Buisson"
    ],
    "name:ukr_x_preferred":[
        "\u041b\u0435-\u0411\u044e\u0457\u0441\u0441\u043e\u043d"
    ],
    "wof:name":"Le Buisson",
    "wof:placetype":"locality"
},
  "geometry": {"coordinates":[3.25297,47.58476],"type":"Point"}
}