{
  "type": "Feature",
  "properties": {
    "gn:admin1_code":"24",
    "gn:admin2_code":"45",
    "gn:admin3_code":"452",
    "gn:admin4_code":"45342",
    "gn:asciiname":"Les Bordes-Latrees",
    "gn:country_code":"FR",
    "gn:dem":128,
    "gn:feature_class":"P",
    "gn:feature_code":"PPL",
    "gn:name":"Les Bordes-Latr\u00e9es",
    "gn:population":0,
    "gn:timezone":"Europe/Paris",
    "iso:country":"FR",
    "wof:name":"Les Bordes-Latrees",
    "wof:placetype":"locality"
},
  "geometry": {"coordinates":[2.01401,48.07524],"type":"Point"}
}