{
  "type": "Feature",
  "properties": {
    "gn:admin1_code":"27",
    "gn:admin2_code":"21",
    "gn:admin3_code":"212",
    "gn:admin4_code":"21254.0",
    "gn:asciiname":"L'Etang-Vergy",
    "gn:country_code":"FR",
    "gn:dem":310,
    "gn:feature_class":"P",
    "gn:feature_code":"PPL",
    "gn:name":"L\u2019\u00c9tang-Vergy",
    "gn:population":0,
    "gn:timezone":"Europe/Paris",
    "iso:country":"FR",
    "name:und_x_variant":[
        "L\u2019\u00c9tang",
        "L\u2019\u00c9tang-Vergy"
    ],
    "wof:name":"L'Etang-Vergy",
    "wof:placetype":"locality"
},
  "geometry": {"coordinates":[4.87836,47.17762000000001],"type":"Point"}
}