{
  "type": "Feature",
  "properties": {
    "frgov:code_epci":"200070894",
    "frgov:insee_arr":"1",
    "frgov:insee_com":"21254",
    "frgov:insee_dep":"21",
    "frgov:insee_reg":"27",
    "frgov:nom_com":"L'\u00c9tang-Vergy",
    "frgov:nom_com_m":"L'ETANG-VERGY",
    "frgov:nom_dep":"COTE-D'OR",
    "frgov:nom_reg":"BOURGOGNE-FRANCHE-COMTE",
    "frgov:statut":"Commune simple",
    "gn:admin1_code":"27",
    "gn:admin2_code":"21",
    "gn:admin3_code":"212",
    "gn:admin4_code":"21254.0",
    "gn:asciiname":"L'Etang-Vergy",
    "gn:country_code":"FR",
    "gn:dem":310,
    "gn:feature_class":"P",
    "gn:feature_code":"PPL",
    "gn:name":"L\u2019\u00c9tang-Vergy",
    "gn:population":0,
    "gn:timezone":"Europe/Paris",
    "iso:country":"FR",
    "name:fra_x_preferred":[
        "L'\u00c9tang-Vergy"
    ],
    "name:und_x_variant":[
        "L\u2019\u00c9tang",
        "L\u2019\u00c9tang-Vergy"
    ],
    "qs:a0":"France",
    "qs:a1":"COTE-D'OR",
    "qs:a1_lc":"21",
    "qs:a1r":"BOURGOGNE",
    "qs:a1r_lc":"26",
    "qs:a2_lc":"15",
    "qs:a2r_lc":"2",
    "qs:adm0":"France",
    "qs:adm0_a3":"FRA",
    "qs:la":"L'ETANG-VERGY",
    "qs:la_lc":"21254",
    "qs:level":"localadmin",
    "qs:type":"Commune simple",
    "wof:coterminous":[
        404407727
    ],
    "wof:name":"L'Etang-Vergy",
    "wof:placetype":"locality",
    "wof:placetype_local":"Commune simple"
},
  "geometry": {"coordinates":[4.87836,47.17762],"type":"Point"}
}