{
  "type": "Feature",
  "properties": {
    "gn:admin1_code":"52",
    "gn:admin2_code":"44",
    "gn:admin3_code":"443",
    "gn:admin4_code":"44050",
    "gn:asciiname":"Le Gue",
    "gn:country_code":"FR",
    "gn:dem":5,
    "gn:feature_class":"P",
    "gn:feature_code":"PPL",
    "gn:name":"Le Gu\u00e9",
    "gn:population":0,
    "gn:timezone":"Europe/Paris",
    "iso:country":"FR",
    "wof:name":"Le Gue",
    "wof:placetype":"locality"
},
  "geometry": {"coordinates":[-2.12211,47.38967],"type":"Point"}
}