{
  "type": "Feature",
  "properties": {
    "gn:admin1_code":"93",
    "gn:admin2_code":"05",
    "gn:admin3_code":"052",
    "gn:admin4_code":"05084",
    "gn:asciiname":"Les Jourdans",
    "gn:country_code":"FR",
    "gn:dem":953,
    "gn:feature_class":"P",
    "gn:feature_code":"PPL",
    "gn:name":"Les Jourdans",
    "gn:population":0,
    "gn:timezone":"Europe/Paris",
    "iso:country":"FR",
    "wof:name":"Les Jourdans",
    "wof:placetype":"locality"
},
  "geometry": {"coordinates":[6.21667,44.53333],"type":"Point"}
}