{
  "type": "Feature",
  "properties": {
    "gn:admin1_code":"27",
    "gn:admin2_code":"25",
    "gn:admin3_code":"251",
    "gn:admin4_code":"25215",
    "gn:asciiname":"L'Ecouvotte",
    "gn:country_code":"FR",
    "gn:dem":336,
    "gn:feature_class":"P",
    "gn:feature_code":"PPL",
    "gn:name":"L\u2019\u00c9couvotte",
    "gn:population":0,
    "gn:timezone":"Europe/Paris",
    "iso:country":"FR",
    "name:und_x_variant":[
        "L\u2019\u00c9couvotte"
    ],
    "wof:name":"L'Ecouvotte",
    "wof:placetype":"locality"
},
  "geometry": {"coordinates":[6.24967,47.34005],"type":"Point"}
}