{
  "type": "Feature",
  "properties": {
    "frgov:code_epci":"242504447",
    "frgov:insee_arr":"1",
    "frgov:insee_com":"25215",
    "frgov:insee_dep":"25",
    "frgov:insee_reg":"27",
    "frgov:nom_com":"L'\u00c9couvotte",
    "frgov:nom_com_m":"L'ECOUVOTTE",
    "frgov:nom_dep":"DOUBS",
    "frgov:nom_reg":"BOURGOGNE-FRANCHE-COMTE",
    "frgov:statut":"Commune simple",
    "gn:admin1_code":"27",
    "gn:admin2_code":"25",
    "gn:admin3_code":"251",
    "gn:admin4_code":"25215",
    "gn:asciiname":"L'Ecouvotte",
    "gn:country_code":"FR",
    "gn:dem":336,
    "gn:feature_class":"P",
    "gn:feature_code":"PPL",
    "gn:name":"L\u2019\u00c9couvotte",
    "gn:population":0,
    "gn:timezone":"Europe/Paris",
    "iso:country":"FR",
    "name:cat_x_preferred":[
        "L'\u00c9couvotte"
    ],
    "name:ceb_x_preferred":[
        "L'\u00c9couvotte"
    ],
    "name:deu_x_preferred":[
        "L\u2019\u00c9couvotte"
    ],
    "name:eus_x_preferred":[
        "L'\u00c9couvotte"
    ],
    "name:fra_x_preferred":[
        "L'\u00c9couvotte"
    ],
    "name:hun_x_preferred":[
        "L\u2019\u00c9couvotte"
    ],
    "name:ita_x_preferred":[
        "L'\u00c9couvotte"
    ],
    "name:lat_x_preferred":[
        "L'\u00c9couvotte"
    ],
    "name:msa_x_preferred":[
        "L'\u00c9couvotte"
    ],
    "name:nld_x_preferred":[
        "L'\u00c9couvotte"
    ],
    "name:oci_x_preferred":[
        "L'\u00c9couvotte"
    ],
    "name:pms_x_preferred":[
        "L'\u00c9couvotte"
    ],
    "name:pol_x_preferred":[
        "L\u2019\u00c9couvotte"
    ],
    "name:por_x_preferred":[
        "L'\u00c9couvotte"
    ],
    "name:slk_x_preferred":[
        "L\u2019\u00c9couvotte"
    ],
    "name:spa_x_preferred":[
        "L'\u00c9couvotte"
    ],
    "name:swe_x_preferred":[
        "L'\u00c9couvotte"
    ],
    "name:ukr_x_preferred":[
        "\u041b'\u0415\u043a\u0443\u0432\u043e\u0442\u0442"
    ],
    "name:und_x_variant":[
        "L\u2019\u00c9couvotte"
    ],
    "name:uzb_x_preferred":[
        "L'\u00c9couvotte"
    ],
    "name:vie_x_preferred":[
        "L'\u00c9couvotte"
    ],
    "name:vol_x_preferred":[
        "L'\u00c9couvotte"
    ],
    "name:war_x_preferred":[
        "L'\u00c9couvotte"
    ],
    "name:zho_x_preferred":[
        "\u83b1\u5e93\u6c83\u7279"
    ],
    "qs:a0":"France",
    "qs:a1":"DOUBS",
    "qs:a1_lc":"25",
    "qs:a1r":"FRANCHE-COMTE",
    "qs:a1r_lc":"43",
    "qs:a2_lc":"24",
    "qs:a2r_lc":"1",
    "qs:adm0":"France",
    "qs:adm0_a3":"FRA",
    "qs:la":"L'ECOUVOTTE",
    "qs:la_lc":"25215",
    "qs:level":"localadmin",
    "qs:type":"Commune simple",
    "wof:coterminous":[
        404383119
    ],
    "wof:name":"L'Ecouvotte",
    "wof:placetype":"locality",
    "wof:placetype_local":"Commune simple"
},
  "geometry": {"coordinates":[6.24967,47.34005],"type":"Point"}
}