{
  "type": "Feature",
  "properties": {
    "gn:admin1_code":"27",
    "gn:admin2_code":"25",
    "gn:admin3_code":"251",
    "gn:admin4_code":"25215",
    "gn:asciiname":"L'Ecouvotte",
    "gn:country_code":"FR",
    "gn:dem":336,
    "gn:feature_class":"P",
    "gn:feature_code":"PPL",
    "gn:name":"L\u2019\u00c9couvotte",
    "gn:population":0,
    "gn:timezone":"Europe/Paris",
    "iso:country":"FR",
    "name:cat_x_preferred":[
        "L'\u00c9couvotte"
    ],
    "name:ceb_x_preferred":[
        "L'\u00c9couvotte"
    ],
    "name:deu_x_preferred":[
        "L\u2019\u00c9couvotte"
    ],
    "name:eus_x_preferred":[
        "L'\u00c9couvotte"
    ],
    "name:fra_x_preferred":[
        "L'\u00c9couvotte"
    ],
    "name:hun_x_preferred":[
        "L\u2019\u00c9couvotte"
    ],
    "name:ita_x_preferred":[
        "L'\u00c9couvotte"
    ],
    "name:lat_x_preferred":[
        "L'\u00c9couvotte"
    ],
    "name:msa_x_preferred":[
        "L'\u00c9couvotte"
    ],
    "name:nld_x_preferred":[
        "L'\u00c9couvotte"
    ],
    "name:oci_x_preferred":[
        "L'\u00c9couvotte"
    ],
    "name:pms_x_preferred":[
        "L'\u00c9couvotte"
    ],
    "name:pol_x_preferred":[
        "L\u2019\u00c9couvotte"
    ],
    "name:por_x_preferred":[
        "L'\u00c9couvotte"
    ],
    "name:slk_x_preferred":[
        "L\u2019\u00c9couvotte"
    ],
    "name:spa_x_preferred":[
        "L'\u00c9couvotte"
    ],
    "name:swe_x_preferred":[
        "L'\u00c9couvotte"
    ],
    "name:ukr_x_preferred":[
        "\u041b'\u0415\u043a\u0443\u0432\u043e\u0442\u0442"
    ],
    "name:uzb_x_preferred":[
        "L'\u00c9couvotte"
    ],
    "name:vie_x_preferred":[
        "L'\u00c9couvotte"
    ],
    "name:vol_x_preferred":[
        "L'\u00c9couvotte"
    ],
    "name:war_x_preferred":[
        "L'\u00c9couvotte"
    ],
    "name:zho_x_preferred":[
        "\u83b1\u5e93\u6c83\u7279"
    ],
    "wof:name":"L'Ecouvotte",
    "wof:placetype":"locality"
},
  "geometry": {"coordinates":[6.24967,47.34005],"type":"Point"}
}