{
  "type": "Feature",
  "properties": {
    "iso:country":"FR",
    "name:eng_x_preferred":[
        "Tilleuls"
    ],
    "name:fra_x_preferred":[
        "Tilleuls"
    ],
    "wof:name":"Tilleuls",
    "wof:placetype":"neighbourhood"
},
  "geometry": {"coordinates":[2.4081911796191,48.74794182554952],"type":"Point"}
}