{
  "type": "Feature",
  "properties": {
    "gn:admin1_code":"76",
    "gn:admin2_code":"66",
    "gn:admin3_code":"661",
    "gn:admin4_code":"66003",
    "gn:asciiname":"Montalba",
    "gn:cc2":"FR",
    "gn:country_code":"FR",
    "gn:dem":536,
    "gn:feature_class":"P",
    "gn:feature_code":"PPL",
    "gn:name":"Montalb\u00e0",
    "gn:population":0,
    "gn:timezone":"Europe/Paris",
    "iso:country":"FR",
    "name:cat_x_preferred":[
        "Montalb\u00e0"
    ],
    "name:cat_x_variant":[
        "Montalb\u00e0 de Paracolls"
    ],
    "name:deu_x_preferred":[
        "Montalba"
    ],
    "name:fra_x_preferred":[
        "Montalba-d'Am\u00e9lie"
    ],
    "name:fra_x_variant":[
        "Montalba"
    ],
    "wof:name":"Montalba",
    "wof:placetype":"locality"
},
  "geometry": {"coordinates":[2.68409,42.44503],"type":"Point"}
}