{
  "type": "Feature",
  "properties": {
    "gn:admin1_code":"94",
    "gn:admin2_code":"2A",
    "gn:admin3_code":"2A1",
    "gn:admin4_code":"2A312",
    "gn:asciiname":"Santa-Maria-Siche",
    "gn:country_code":"FR",
    "gn:dem":501,
    "gn:feature_class":"P",
    "gn:feature_code":"PPL",
    "gn:name":"Santa-Maria-Sich\u00e9",
    "gn:population":369,
    "gn:timezone":"Europe/Paris",
    "iso:country":"FR",
    "name:und_x_variant":[
        "Sainte-Marie-Sicche",
        "Sainte-Marie",
        "Santa-Maria-Sich\u00e9"
    ],
    "wof:name":"Santa-Maria-Siche",
    "wof:placetype":"locality",
    "wof:population":369
},
  "geometry": {"coordinates":[8.97666,41.87675],"type":"Point"}
}