{
  "type": "Feature",
  "properties": {
    "gn:admin1_code":"84",
    "gn:admin2_code":"74",
    "gn:admin3_code":"742",
    "gn:admin4_code":"74099.0",
    "gn:asciiname":"Ormaret",
    "gn:country_code":"FR",
    "gn:dem":1141,
    "gn:feature_class":"P",
    "gn:feature_code":"PPL",
    "gn:name":"Ormaret",
    "gn:population":0,
    "gn:timezone":"Europe/Paris",
    "iso:country":"FR",
    "wof:name":"Ormaret",
    "wof:placetype":"locality"
},
  "geometry": {"coordinates":[6.63272,45.8834],"type":"Point"}
}