{
  "type": "Feature",
  "properties": {
    "gn:admin1_code":"44",
    "gn:admin2_code":"08",
    "gn:admin3_code":"081",
    "gn:admin4_code":"08214",
    "gn:asciiname":"Les Vieux Moulins d'Hargnies",
    "gn:country_code":"FR",
    "gn:dem":488,
    "gn:feature_class":"P",
    "gn:feature_code":"PPL",
    "gn:name":"Les Vieux Moulins d\u2019Hargnies",
    "gn:population":0,
    "gn:timezone":"Europe/Paris",
    "iso:country":"FR",
    "wof:name":"Les Vieux Moulins d'Hargnies",
    "wof:placetype":"locality"
},
  "geometry": {"coordinates":[4.78087,49.94711],"type":"Point"}
}