{
  "type": "Feature",
  "properties": {
    "gn:admin1_code":"44",
    "gn:admin2_code":"51",
    "gn:admin3_code":"513",
    "gn:admin4_code":"51267",
    "gn:asciiname":"Germigny",
    "gn:country_code":"FR",
    "gn:dem":141,
    "gn:feature_class":"P",
    "gn:feature_code":"PPL",
    "gn:name":"Germigny",
    "gn:population":210,
    "gn:timezone":"Europe/Paris",
    "iso:country":"FR",
    "wof:name":"Germigny",
    "wof:placetype":"locality",
    "wof:population":210
},
  "geometry": {"coordinates":[3.86607,49.245],"type":"Point"}
}