{
  "type": "Feature",
  "properties": {
    "gn:admin1_code":"44",
    "gn:admin2_code":"51",
    "gn:admin3_code":"513",
    "gn:admin4_code":"51267",
    "gn:asciiname":"Germigny",
    "gn:country_code":"FR",
    "gn:dem":141,
    "gn:feature_class":"P",
    "gn:feature_code":"PPL",
    "gn:name":"Germigny",
    "gn:population":210,
    "gn:timezone":"Europe/Paris",
    "iso:country":"FR",
    "name:cat_x_preferred":[
        "Germigny"
    ],
    "name:ceb_x_preferred":[
        "Germigny"
    ],
    "name:deu_x_preferred":[
        "Germigny"
    ],
    "name:fra_x_preferred":[
        "Germigny"
    ],
    "name:ita_x_preferred":[
        "Germigny"
    ],
    "name:nds_x_preferred":[
        "Germigny"
    ],
    "name:nld_x_preferred":[
        "Germigny"
    ],
    "name:oci_x_preferred":[
        "Germigny"
    ],
    "name:pol_x_preferred":[
        "Germigny"
    ],
    "name:por_x_preferred":[
        "Germigny"
    ],
    "name:rus_x_preferred":[
        "\u0416\u0435\u0440\u043c\u0438\u043d\u044c\u0438"
    ],
    "name:slk_x_preferred":[
        "Germigny"
    ],
    "name:spa_x_preferred":[
        "Germigny"
    ],
    "name:srp_x_preferred":[
        "\u0416\u0435\u0440\u043c\u0438\u045a\u0438"
    ],
    "name:swe_x_preferred":[
        "Germigny"
    ],
    "name:ukr_x_preferred":[
        "\u0416\u0435\u0440\u043c\u0456\u043d\u044c\u0457"
    ],
    "wof:name":"Germigny",
    "wof:placetype":"locality",
    "wof:population":210
},
  "geometry": {"coordinates":[3.86607,49.245],"type":"Point"}
}