{
  "type": "Feature",
  "properties": {
    "frgov:code_epci":"200067213",
    "frgov:insee_arr":"3",
    "frgov:insee_com":"51267",
    "frgov:insee_dep":"51",
    "frgov:insee_reg":"44",
    "frgov:nom_com":"Germigny",
    "frgov:nom_com_m":"GERMIGNY",
    "frgov:nom_dep":"MARNE",
    "frgov:nom_reg":"GRAND EST",
    "frgov:statut":"Commune simple",
    "gn:admin1_code":"44",
    "gn:admin2_code":"51",
    "gn:admin3_code":"513",
    "gn:admin4_code":"51267",
    "gn:asciiname":"Germigny",
    "gn:country_code":"FR",
    "gn:dem":141,
    "gn:feature_class":"P",
    "gn:feature_code":"PPL",
    "gn:name":"Germigny",
    "gn:population":210,
    "gn:timezone":"Europe/Paris",
    "iso:country":"FR",
    "name:cat_x_preferred":[
        "Germigny"
    ],
    "name:ceb_x_preferred":[
        "Germigny"
    ],
    "name:deu_x_preferred":[
        "Germigny"
    ],
    "name:fra_x_preferred":[
        "Germigny"
    ],
    "name:ita_x_preferred":[
        "Germigny"
    ],
    "name:nds_x_preferred":[
        "Germigny"
    ],
    "name:nld_x_preferred":[
        "Germigny"
    ],
    "name:oci_x_preferred":[
        "Germigny"
    ],
    "name:pol_x_preferred":[
        "Germigny"
    ],
    "name:por_x_preferred":[
        "Germigny"
    ],
    "name:rus_x_preferred":[
        "\u0416\u0435\u0440\u043c\u0438\u043d\u044c\u0438"
    ],
    "name:slk_x_preferred":[
        "Germigny"
    ],
    "name:spa_x_preferred":[
        "Germigny"
    ],
    "name:srp_x_preferred":[
        "\u0416\u0435\u0440\u043c\u0438\u045a\u0438"
    ],
    "name:swe_x_preferred":[
        "Germigny"
    ],
    "name:ukr_x_preferred":[
        "\u0416\u0435\u0440\u043c\u0456\u043d\u044c\u0457"
    ],
    "qs:a0":"France",
    "qs:a1":"MARNE",
    "qs:a1_lc":"51",
    "qs:a1r":"CHAMPAGNE-ARDENNE",
    "qs:a1r_lc":"21",
    "qs:a2_lc":"31",
    "qs:a2r_lc":"3",
    "qs:adm0":"France",
    "qs:adm0_a3":"FRA",
    "qs:la":"GERMIGNY",
    "qs:la_lc":"51267",
    "qs:level":"localadmin",
    "qs:type":"Commune simple",
    "wof:coterminous":[
        404411033
    ],
    "wof:name":"Germigny",
    "wof:placetype":"locality",
    "wof:placetype_local":"Commune simple",
    "wof:population":210
},
  "geometry": {"coordinates":[3.86607,49.245],"type":"Point"}
}