{
  "type": "Feature",
  "properties": {
    "gn:admin1_code":"75",
    "gn:admin2_code":"64",
    "gn:admin3_code":"641",
    "gn:admin4_code":"64377",
    "gn:asciiname":"La Place",
    "gn:country_code":"FR",
    "gn:dem":146,
    "gn:feature_class":"P",
    "gn:feature_code":"PPL",
    "gn:name":"La Place",
    "gn:population":0,
    "gn:timezone":"Europe/Paris",
    "iso:country":"FR",
    "name:fra_x_preferred":[
        "La Place"
    ],
    "name:spa_x_preferred":[
        "Plaza"
    ],
    "wof:name":"La Place",
    "wof:placetype":"locality"
},
  "geometry": {"coordinates":[-1.27463,43.34667],"type":"Point"}
}