{
  "type": "Feature",
  "properties": {
    "gn:admin1_code":"84",
    "gn:admin2_code":"26",
    "gn:admin3_code":"262",
    "gn:admin4_code":"26304",
    "gn:asciiname":"Le Monestier",
    "gn:country_code":"FR",
    "gn:dem":447,
    "gn:feature_class":"P",
    "gn:feature_code":"PPL",
    "gn:name":"Le Monestier",
    "gn:population":0,
    "gn:timezone":"Europe/Paris",
    "iso:country":"FR",
    "name:cat_x_preferred":[
        "Lo Monesti\u00e8r"
    ],
    "name:ceb_x_preferred":[
        "Le Monestier"
    ],
    "name:deu_x_preferred":[
        "Le Monestier"
    ],
    "name:eus_x_preferred":[
        "Le Monestier"
    ],
    "name:fra_x_preferred":[
        "Le Monestier"
    ],
    "name:hun_x_preferred":[
        "Le Monestier"
    ],
    "name:ita_x_preferred":[
        "Le Monestier"
    ],
    "name:kaz_x_preferred":[
        "\u041b\u0435-\u041c\u043e\u043d\u0435\u0442\u044c\u0435"
    ],
    "name:lat_x_preferred":[
        "Le Monestier"
    ],
    "name:msa_x_preferred":[
        "Le Monestier"
    ],
    "name:nld_x_preferred":[
        "Le Monestier"
    ],
    "name:oci_x_preferred":[
        "Le Monestier"
    ],
    "name:pol_x_preferred":[
        "Monestier"
    ],
    "name:ron_x_preferred":[
        "Le Monestier"
    ],
    "name:slk_x_preferred":[
        "Le Monestier"
    ],
    "name:spa_x_preferred":[
        "Le Monestier"
    ],
    "name:swe_x_preferred":[
        "Le Monestier"
    ],
    "name:ukr_x_preferred":[
        "\u041b\u0435-\u041c\u043e\u043d\u0435\u0442\u044c\u0454"
    ],
    "name:uzb_x_preferred":[
        "Le Monestier"
    ],
    "name:vie_x_preferred":[
        "Le Monestier"
    ],
    "name:vol_x_preferred":[
        "Le Monestier"
    ],
    "name:war_x_preferred":[
        "Le Monestier"
    ],
    "name:zho_x_preferred":[
        "\u52d2\u83ab\u5185\u65af\u6377"
    ],
    "wof:name":"Le Monestier",
    "wof:placetype":"locality"
},
  "geometry": {"coordinates":[5.23146,44.43296],"type":"Point"}
}