{
  "type": "Feature",
  "properties": {
    "gn:admin1_code":"76",
    "gn:admin2_code":"48",
    "gn:admin3_code":"482",
    "gn:admin4_code":"48016",
    "gn:asciiname":"Julliers",
    "gn:country_code":"FR",
    "gn:dem":708,
    "gn:feature_class":"P",
    "gn:feature_code":"PPL",
    "gn:name":"Julliers",
    "gn:population":0,
    "gn:timezone":"Europe/Paris",
    "iso:country":"FR",
    "wof:name":"Julliers",
    "wof:placetype":"locality"
},
  "geometry": {"coordinates":[3.46013,44.48119000000001],"type":"Point"}
}