{
  "type": "Feature",
  "properties": {
    "gn:admin1_code":"84",
    "gn:admin2_code":"43",
    "gn:admin3_code":"432",
    "gn:admin4_code":"43216.0",
    "gn:asciiname":"Marcilhac",
    "gn:country_code":"FR",
    "gn:dem":816,
    "gn:feature_class":"P",
    "gn:feature_code":"PPL",
    "gn:name":"Marcilhac",
    "gn:population":0,
    "gn:timezone":"Europe/Paris",
    "iso:country":"FR",
    "wof:name":"Marcilhac",
    "wof:placetype":"locality"
},
  "geometry": {"coordinates":[3.79086,45.11839000000001],"type":"Point"}
}