{
  "type": "Feature",
  "properties": {
    "gn:country":"FR",
    "gn:fcode":"PPL",
    "gn:population":220,
    "iso:country":"FR",
    "name:cat_x_preferred":[
        "Beauvau"
    ],
    "name:ceb_x_preferred":[
        "Beauvau"
    ],
    "name:deu_x_preferred":[
        "Beauvau"
    ],
    "name:eng_x_preferred":[
        "Beauvau"
    ],
    "name:eus_x_preferred":[
        "Beauvau"
    ],
    "name:fra_x_preferred":[
        "Beauvau"
    ],
    "name:hun_x_preferred":[
        "Beauvau"
    ],
    "name:ita_x_preferred":[
        "Beauvau"
    ],
    "name:lat_x_preferred":[
        "Beauvau"
    ],
    "name:mlg_x_preferred":[
        "Beauvau"
    ],
    "name:msa_x_preferred":[
        "Beauvau"
    ],
    "name:nan_x_preferred":[
        "Beauvau"
    ],
    "name:nld_x_preferred":[
        "Beauvau"
    ],
    "name:oci_x_preferred":[
        "Beauvau"
    ],
    "name:pms_x_preferred":[
        "Beauvau"
    ],
    "name:pol_x_preferred":[
        "Beauvau"
    ],
    "name:por_x_preferred":[
        "Beauvau"
    ],
    "name:ron_x_preferred":[
        "Beauvau"
    ],
    "name:slk_x_preferred":[
        "Beauvau"
    ],
    "name:spa_x_preferred":[
        "Beauvau"
    ],
    "name:sqi_x_preferred":[
        "Beauvau"
    ],
    "name:srp_x_preferred":[
        "\u0411\u043e\u0432\u043e"
    ],
    "name:swe_x_preferred":[
        "Beauvau"
    ],
    "name:ukr_x_preferred":[
        "\u0411\u043e\u0432\u043e"
    ],
    "name:vie_x_preferred":[
        "Beauvau"
    ],
    "name:vol_x_preferred":[
        "Beauvau"
    ],
    "name:war_x_preferred":[
        "Beauvau"
    ],
    "name:zho_x_preferred":[
        "\u535a\u6c83"
    ],
    "qs_pg:aaroncc":"FR",
    "qs_pg:gn_country":"FR",
    "qs_pg:gn_fcode":"PPL",
    "qs_pg:gn_pop":220,
    "qs_pg:name":"Beauvau",
    "qs_pg:name_adm0":"France",
    "qs_pg:name_adm1":"Pays de la Loire",
    "qs_pg:photos_9r":0,
    "qs_pg:photos_sr":0,
    "qs_pg:pop_sr":2,
    "qs_pg:qs_pg_placetype":"locality",
    "qs_pg:qs_pg_placetype_gp":"Town",
    "qs_pg:woe_adm0":23424819,
    "woe:adm0_id":23424819,
    "woe:name_adm0":"France",
    "woe:name_adm1":"Pays de la Loire",
    "woe:placetype":"Town",
    "wof:name":"Beauvau",
    "wof:placetype":"neighbourhood",
    "wof:population":220
},
  "geometry": {"coordinates":[-0.2546,47.58039],"type":"Point"}
}