{
  "type": "Feature",
  "properties": {
    "gn:admin1_code":"84",
    "gn:admin2_code":"07",
    "gn:admin3_code":"073",
    "gn:admin4_code":"07256",
    "gn:asciiname":"Les Sauzets",
    "gn:country_code":"FR",
    "gn:dem":485,
    "gn:feature_class":"P",
    "gn:feature_code":"PPL",
    "gn:name":"Les Sauzets",
    "gn:population":0,
    "gn:timezone":"Europe/Paris",
    "iso:country":"FR",
    "wof:name":"Les Sauzets",
    "wof:placetype":"locality"
},
  "geometry": {"coordinates":[4.49007,44.90439],"type":"Point"}
}