{
  "type": "Feature",
  "properties": {
    "gn:admin1_code":"24",
    "gn:admin2_code":"36",
    "gn:admin3_code":"361",
    "gn:admin4_code":"36165",
    "gn:asciiname":"Aze",
    "gn:country_code":"FR",
    "gn:dem":108,
    "gn:feature_class":"P",
    "gn:feature_code":"PPL",
    "gn:name":"Az\u00e9",
    "gn:population":0,
    "gn:timezone":"Europe/Paris",
    "iso:country":"FR",
    "wof:name":"Aze",
    "wof:placetype":"locality"
},
  "geometry": {"coordinates":[1.09879,46.67012],"type":"Point"}
}