{
  "type": "Feature",
  "properties": {
    "iso:country":"FR",
    "name:eng_x_preferred":[
        "Carnot Gambetta"
    ],
    "name:fra_x_preferred":[
        "Carnot Gambetta"
    ],
    "wof:name":"Carnot Gambetta",
    "wof:placetype":"neighbourhood"
},
  "geometry": {"coordinates":[2.23020867236181,48.87412016177248],"type":"Point"}
}