{
  "type": "Feature",
  "properties": {
    "gn:admin1_code":"75",
    "gn:admin2_code":"40",
    "gn:admin3_code":"402",
    "gn:admin4_code":"40169",
    "gn:asciiname":"La Legue",
    "gn:country_code":"FR",
    "gn:dem":137,
    "gn:feature_class":"P",
    "gn:feature_code":"PPL",
    "gn:name":"La L\u00e9gue",
    "gn:population":0,
    "gn:timezone":"Europe/Paris",
    "iso:country":"FR",
    "wof:name":"La Legue",
    "wof:placetype":"locality"
},
  "geometry": {"coordinates":[-0.21201,44.20895],"type":"Point"}
}