{
  "type": "Feature",
  "properties": {
    "gn:admin1_code":"93",
    "gn:admin2_code":"83",
    "gn:admin3_code":"831",
    "gn:admin4_code":"83003",
    "gn:asciiname":"Lentier",
    "gn:country_code":"FR",
    "gn:dem":341,
    "gn:feature_class":"P",
    "gn:feature_code":"PPL",
    "gn:name":"Lentier",
    "gn:population":0,
    "gn:timezone":"Europe/Paris",
    "iso:country":"FR",
    "wof:name":"Lentier",
    "wof:placetype":"locality"
},
  "geometry": {"coordinates":[6.41353,43.56495],"type":"Point"}
}