{
  "type": "Feature",
  "properties": {
    "iso:country":"FR",
    "name:fra_x_variant":[
        "Les Izards-3 Cocus",
        "3 Cocus",
        "Trois Cocus"
    ],
    "wof:name":"Les Izards",
    "wof:placetype":"neighbourhood"
},
  "geometry": {"coordinates":[1.44416686640014,43.63883324084524],"type":"Point"}
}