{
  "type": "Feature",
  "properties": {
    "gn:admin1_code":"53",
    "gn:admin2_code":"56",
    "gn:admin3_code":"562",
    "gn:admin4_code":"56199",
    "gn:asciiname":"Penhoat",
    "gn:country_code":"FR",
    "gn:dem":140,
    "gn:feature_class":"P",
    "gn:feature_code":"PPL",
    "gn:name":"Penhoat",
    "gn:population":0,
    "gn:timezone":"Europe/Paris",
    "iso:country":"FR",
    "wof:name":"Penhoat",
    "wof:placetype":"locality"
},
  "geometry": {"coordinates":[-3.66667,48.13333],"type":"Point"}
}