{
  "type": "Feature",
  "properties": {
    "gn:admin1_code":"24",
    "gn:admin2_code":"36",
    "gn:admin3_code":"364",
    "gn:admin4_code":"36088",
    "gn:asciiname":"Saint-Denis-de-Jouhet",
    "gn:country_code":"FR",
    "gn:dem":128,
    "gn:feature_class":"P",
    "gn:feature_code":"PPL",
    "gn:name":"Saint-Denis-de-Jouhet",
    "gn:population":0,
    "gn:timezone":"Europe/Paris",
    "iso:country":"FR",
    "name:und_x_variant":[
        "Saint-Denis",
        "Saint-Denis-de-Jouhet"
    ],
    "wof:name":"Saint-Denis-de-Jouhet",
    "wof:placetype":"locality"
},
  "geometry": {"coordinates":[1.98828,46.96037000000001],"type":"Point"}
}