{
  "type": "Feature",
  "properties": {
    "gn:admin1_code":"24",
    "gn:admin2_code":"36",
    "gn:admin3_code":"364",
    "gn:admin4_code":"36088",
    "gn:asciiname":"Saint-Denis-de-Jouhet",
    "gn:country_code":"FR",
    "gn:dem":128,
    "gn:feature_class":"P",
    "gn:feature_code":"PPL",
    "gn:name":"Saint-Denis-de-Jouhet",
    "gn:population":0,
    "gn:timezone":"Europe/Paris",
    "iso:country":"FR",
    "name:cat_x_preferred":[
        "Saint-Denis-de-Jouhet"
    ],
    "name:ceb_x_preferred":[
        "Saint-Denis-de-Jouhet"
    ],
    "name:deu_x_preferred":[
        "Saint-Denis-de-Jouhet"
    ],
    "name:eus_x_preferred":[
        "Saint-Denis-de-Jouhet"
    ],
    "name:fas_x_preferred":[
        "\u0633\u0646\u062a-\u062f\u0646\u06cc\u0633-\u062f\u0647-\u0698\u0648\u0647\u062a"
    ],
    "name:fra_x_preferred":[
        "Saint-Denis-de-Jouhet"
    ],
    "name:hun_x_preferred":[
        "Saint-Denis-de-Jouhet"
    ],
    "name:ita_x_preferred":[
        "Saint-Denis-de-Jouhet"
    ],
    "name:lat_x_preferred":[
        "Saint-Denis-de-Jouhet"
    ],
    "name:mlg_x_preferred":[
        "Saint-Denis-de-Jouhet"
    ],
    "name:msa_x_preferred":[
        "Saint-Denis-de-Jouhet"
    ],
    "name:nld_x_preferred":[
        "Saint-Denis-de-Jouhet"
    ],
    "name:oci_x_preferred":[
        "Saint-Denis-de-Jouhet"
    ],
    "name:pms_x_preferred":[
        "Saint-Denis-de-Jouhet"
    ],
    "name:pol_x_preferred":[
        "Saint-Denis-de-Jouhet"
    ],
    "name:por_x_preferred":[
        "Saint-Denis-de-Jouhet"
    ],
    "name:ron_x_preferred":[
        "Saint-Denis-de-Jouhet"
    ],
    "name:rus_x_preferred":[
        "\u0421\u0435\u043d-\u0414\u0435\u043d\u0438-\u0434\u0435-\u0416\u0443\u044d"
    ],
    "name:slk_x_preferred":[
        "Saint-Denis-de-Jouhet"
    ],
    "name:spa_x_preferred":[
        "Saint-Denis-de-Jouhet"
    ],
    "name:swe_x_preferred":[
        "Saint-Denis-de-Jouhet"
    ],
    "name:ukr_x_preferred":[
        "\u0421\u0435\u043d-\u0414\u0435\u043d\u0456-\u0434\u0435-\u0416\u0443\u0435"
    ],
    "name:und_x_variant":[
        "Saint-Denis",
        "Saint-Denis-de-Jouhet"
    ],
    "name:urd_x_preferred":[
        "\u0633\u06cc\u0646\u0679-\u0688\u06cc\u0646\u0633-\u062f\u06d2-\u062c\u0648\u06be\u06cc\u062a"
    ],
    "name:uzb_x_preferred":[
        "Saint-Denis-de-Jouhet"
    ],
    "name:vie_x_preferred":[
        "Saint-Denis-de-Jouhet"
    ],
    "name:vol_x_preferred":[
        "Saint-Denis-de-Jouhet"
    ],
    "name:war_x_preferred":[
        "Saint-Denis-de-Jouhet"
    ],
    "name:zho_x_preferred":[
        "\u5723\u4f46\u5c3c\u5fb7\u8339\u57c3"
    ],
    "wof:name":"Saint-Denis-de-Jouhet",
    "wof:placetype":"locality"
},
  "geometry": {"coordinates":[1.98828,46.96037000000001],"type":"Point"}
}