{
  "type": "Feature",
  "properties": {
    "gn:admin1_code":"75",
    "gn:admin2_code":"16",
    "gn:admin3_code":"161",
    "gn:admin4_code":"16209",
    "gn:asciiname":"La Vallade",
    "gn:country_code":"FR",
    "gn:dem":118,
    "gn:feature_class":"P",
    "gn:feature_code":"PPL",
    "gn:name":"La Vallade",
    "gn:population":0,
    "gn:timezone":"Europe/Paris",
    "iso:country":"FR",
    "wof:name":"La Vallade",
    "wof:placetype":"locality"
},
  "geometry": {"coordinates":[0.43653,45.71544],"type":"Point"}
}