{
  "type": "Feature",
  "properties": {
    "gn:admin1_code":"84",
    "gn:admin2_code":"26",
    "gn:admin3_code":"263",
    "gn:admin4_code":"26107",
    "gn:asciiname":"Mont de Verroux",
    "gn:country_code":"FR",
    "gn:dem":423,
    "gn:feature_class":"P",
    "gn:feature_code":"PPL",
    "gn:name":"Mont de Verroux",
    "gn:population":0,
    "gn:timezone":"Europe/Paris",
    "iso:country":"FR",
    "wof:name":"Mont de Verroux",
    "wof:placetype":"locality"
},
  "geometry": {"coordinates":[5.06363,45.17984000000001],"type":"Point"}
}