{
  "type": "Feature",
  "properties": {
    "gn:admin1_code":"76",
    "gn:admin2_code":"32",
    "gn:admin3_code":"323",
    "gn:admin4_code":"32167",
    "gn:asciiname":"Laas",
    "gn:country_code":"FR",
    "gn:dem":243,
    "gn:feature_class":"P",
    "gn:feature_code":"PPL",
    "gn:name":"Laas",
    "gn:population":290,
    "gn:timezone":"Europe/Paris",
    "iso:country":"FR",
    "name:arg_x_preferred":[
        "Laas"
    ],
    "name:ceb_x_preferred":[
        "Laas"
    ],
    "name:deu_x_preferred":[
        "Laas"
    ],
    "name:fra_x_preferred":[
        "Laas"
    ],
    "name:ita_x_preferred":[
        "Laas"
    ],
    "name:nds_x_preferred":[
        "Laas"
    ],
    "name:nld_x_preferred":[
        "Laas"
    ],
    "name:oci_x_preferred":[
        "La\u00e0s"
    ],
    "name:pms_x_preferred":[
        "Laas"
    ],
    "name:pol_x_preferred":[
        "Laas"
    ],
    "name:por_x_preferred":[
        "Laas"
    ],
    "name:rus_x_preferred":[
        "\u041b\u0430\u0430\u0441"
    ],
    "name:slk_x_preferred":[
        "Laas"
    ],
    "name:spa_x_preferred":[
        "Laas"
    ],
    "name:swe_x_preferred":[
        "Laas"
    ],
    "name:ukr_x_preferred":[
        "\u041b\u0430\u0430\u0441"
    ],
    "wof:name":"Laas",
    "wof:placetype":"locality",
    "wof:population":290
},
  "geometry": {"coordinates":[0.30733,43.46928],"type":"Point"}
}