{
  "type": "Feature",
  "properties": {
    "frgov:code_epci":"243200425",
    "frgov:insee_arr":"3",
    "frgov:insee_com":"32167",
    "frgov:insee_dep":"32",
    "frgov:insee_reg":"76",
    "frgov:nom_com":"Laas",
    "frgov:nom_com_m":"LAAS",
    "frgov:nom_dep":"GERS",
    "frgov:nom_reg":"OCCITANIE",
    "frgov:statut":"Commune simple",
    "gn:admin1_code":"76",
    "gn:admin2_code":"32",
    "gn:admin3_code":"323",
    "gn:admin4_code":"32167",
    "gn:asciiname":"Laas",
    "gn:country_code":"FR",
    "gn:dem":243,
    "gn:feature_class":"P",
    "gn:feature_code":"PPL",
    "gn:name":"Laas",
    "gn:population":290,
    "gn:timezone":"Europe/Paris",
    "iso:country":"FR",
    "name:arg_x_preferred":[
        "Laas"
    ],
    "name:ceb_x_preferred":[
        "Laas"
    ],
    "name:deu_x_preferred":[
        "Laas"
    ],
    "name:fra_x_preferred":[
        "Laas"
    ],
    "name:ita_x_preferred":[
        "Laas"
    ],
    "name:nds_x_preferred":[
        "Laas"
    ],
    "name:nld_x_preferred":[
        "Laas"
    ],
    "name:oci_x_preferred":[
        "La\u00e0s"
    ],
    "name:pms_x_preferred":[
        "Laas"
    ],
    "name:pol_x_preferred":[
        "Laas"
    ],
    "name:por_x_preferred":[
        "Laas"
    ],
    "name:rus_x_preferred":[
        "\u041b\u0430\u0430\u0441"
    ],
    "name:slk_x_preferred":[
        "Laas"
    ],
    "name:spa_x_preferred":[
        "Laas"
    ],
    "name:swe_x_preferred":[
        "Laas"
    ],
    "name:ukr_x_preferred":[
        "\u041b\u0430\u0430\u0441"
    ],
    "qs:a0":"France",
    "qs:a1":"GERS",
    "qs:a1_lc":"32",
    "qs:a1r":"MIDI-PYRENEES",
    "qs:a1r_lc":"73",
    "qs:a2_lc":"19",
    "qs:a2r_lc":"3",
    "qs:adm0":"France",
    "qs:adm0_a3":"FRA",
    "qs:la":"LAAS",
    "qs:la_lc":"32167",
    "qs:level":"localadmin",
    "qs:type":"Commune simple",
    "wof:coterminous":[
        404391437
    ],
    "wof:name":"Laas",
    "wof:placetype":"locality",
    "wof:placetype_local":"Commune simple",
    "wof:population":290
},
  "geometry": {"coordinates":[0.30733,43.46928],"type":"Point"}
}