{
  "type": "Feature",
  "properties": {
    "gn:admin1_code":"93",
    "gn:admin2_code":"05",
    "gn:admin3_code":"052",
    "gn:admin4_code":"05029",
    "gn:asciiname":"La Plaine",
    "gn:country_code":"FR",
    "gn:dem":1060,
    "gn:feature_class":"P",
    "gn:feature_code":"PPL",
    "gn:name":"La Plaine",
    "gn:population":0,
    "gn:timezone":"Europe/Paris",
    "iso:country":"FR",
    "name:ceb_x_preferred":[
        "La Plaine"
    ],
    "name:deu_x_preferred":[
        "La Plaine"
    ],
    "name:ell_x_preferred":[
        "\u039b\u03b1 \u03a0\u03bb\u03b1\u03b9\u03bd"
    ],
    "name:ita_x_preferred":[
        "La Plaine"
    ],
    "name:nld_x_preferred":[
        "La Plaine"
    ],
    "name:por_x_preferred":[
        "La Plaine"
    ],
    "name:spa_x_preferred":[
        "La Plaine"
    ],
    "name:swe_x_preferred":[
        "La Plaine"
    ],
    "wof:name":"La Plaine",
    "wof:placetype":"locality"
},
  "geometry": {"coordinates":[6.16667,44.65],"type":"Point"}
}