{
  "type": "Feature",
  "properties": {
    "gn:admin1_code":"93",
    "gn:admin2_code":"05",
    "gn:admin3_code":"052",
    "gn:admin4_code":"05029",
    "gn:asciiname":"La Plaine",
    "gn:country_code":"FR",
    "gn:dem":1060,
    "gn:feature_class":"P",
    "gn:feature_code":"PPL",
    "gn:name":"La Plaine",
    "gn:population":0,
    "gn:timezone":"Europe/Paris",
    "iso:country":"FR",
    "wof:name":"La Plaine",
    "wof:placetype":"locality"
},
  "geometry": {"coordinates":[6.16667,44.65],"type":"Point"}
}