{
  "type": "Feature",
  "properties": {
    "frgov:code_epci":"200040277",
    "frgov:insee_arr":"3",
    "frgov:insee_com":"28090",
    "frgov:insee_dep":"28",
    "frgov:insee_reg":"24",
    "frgov:nom_com":"Les Ch\u00e2telets",
    "frgov:nom_com_m":"LES CHATELETS",
    "frgov:nom_dep":"EURE-ET-LOIR",
    "frgov:nom_reg":"CENTRE-VAL DE LOIRE",
    "frgov:statut":"Commune simple",
    "gn:admin1_code":"24",
    "gn:admin2_code":"28",
    "gn:admin3_code":"283",
    "gn:admin4_code":"28090",
    "gn:asciiname":"Les Chatelets",
    "gn:country_code":"FR",
    "gn:dem":178,
    "gn:feature_class":"P",
    "gn:feature_code":"PPL",
    "gn:name":"Les Ch\u00e2telets",
    "gn:population":0,
    "gn:timezone":"Europe/Paris",
    "iso:country":"FR",
    "name:fra_x_preferred":[
        "Les Ch\u00e2telets"
    ],
    "name:und_x_variant":[
        "Les Ch\u00e2telets"
    ],
    "qs:a0":"France",
    "qs:a1":"EURE-ET-LOIR",
    "qs:a1_lc":"28",
    "qs:a1r":"CENTRE",
    "qs:a1r_lc":"24",
    "qs:a2_lc":"05",
    "qs:a2r_lc":"3",
    "qs:adm0":"France",
    "qs:adm0_a3":"FRA",
    "qs:la":"LES CHATELETS",
    "qs:la_lc":"28090",
    "qs:level":"localadmin",
    "qs:type":"Commune simple",
    "wof:coterminous":[
        404364797
    ],
    "wof:name":"Les Chatelets",
    "wof:placetype":"locality",
    "wof:placetype_local":"Commune simple"
},
  "geometry": {"coordinates":[1.01178,48.65073],"type":"Point"}
}