{
  "type": "Feature",
  "properties": {
    "gn:admin1_code":"24",
    "gn:admin2_code":"28",
    "gn:admin3_code":"283",
    "gn:admin4_code":"28090",
    "gn:asciiname":"Les Chatelets",
    "gn:country_code":"FR",
    "gn:dem":178,
    "gn:feature_class":"P",
    "gn:feature_code":"PPL",
    "gn:name":"Les Ch\u00e2telets",
    "gn:population":0,
    "gn:timezone":"Europe/Paris",
    "iso:country":"FR",
    "name:und_x_variant":[
        "Les Ch\u00e2telets"
    ],
    "wof:name":"Les Chatelets",
    "wof:placetype":"locality"
},
  "geometry": {"coordinates":[1.01178,48.65073],"type":"Point"}
}