{
  "type": "Feature",
  "properties": {
    "gn:admin1_code":"32",
    "gn:admin2_code":"62",
    "gn:admin3_code":"623",
    "gn:admin4_code":"62604",
    "gn:asciiname":"Le Croquelet",
    "gn:country_code":"FR",
    "gn:dem":53,
    "gn:feature_class":"P",
    "gn:feature_code":"PPL",
    "gn:name":"Le Croquelet",
    "gn:population":0,
    "gn:timezone":"Europe/Paris",
    "iso:country":"FR",
    "wof:name":"Le Croquelet",
    "wof:placetype":"locality"
},
  "geometry": {"coordinates":[1.63291,50.61884000000001],"type":"Point"}
}