{
  "type": "Feature",
  "properties": {
    "gn:admin1_code":"53",
    "gn:admin2_code":"56",
    "gn:admin3_code":"561",
    "gn:admin4_code":"56162",
    "gn:asciiname":"Kerbernes",
    "gn:country_code":"FR",
    "gn:dem":21,
    "gn:feature_class":"P",
    "gn:feature_code":"PPLL",
    "gn:name":"Kerbern\u00e8s",
    "gn:population":0,
    "gn:timezone":"Europe/Paris",
    "iso:country":"FR",
    "wof:name":"Kerbernes",
    "wof:placetype":"locality"
},
  "geometry": {"coordinates":[-3.39889,47.73806],"type":"Point"}
}