{
  "type": "Feature",
  "properties": {
    "gn:admin1_code":"28",
    "gn:admin2_code":"27",
    "gn:admin3_code":"273",
    "gn:admin4_code":"27038",
    "gn:asciiname":"La Foret",
    "gn:country_code":"FR",
    "gn:dem":196,
    "gn:feature_class":"P",
    "gn:feature_code":"PPL",
    "gn:name":"La For\u00eat",
    "gn:population":0,
    "gn:timezone":"Europe/Paris",
    "iso:country":"FR",
    "wof:name":"La Foret",
    "wof:placetype":"locality"
},
  "geometry": {"coordinates":[0.81353,48.72301],"type":"Point"}
}