{
  "type": "Feature",
  "properties": {
    "gn:admin1_code":"28",
    "gn:admin2_code":"76",
    "gn:admin3_code":"761",
    "gn:admin4_code":"76666",
    "gn:asciiname":"Abancourt",
    "gn:country_code":"FR",
    "gn:dem":153,
    "gn:feature_class":"P",
    "gn:feature_code":"PPL",
    "gn:name":"Abancourt",
    "gn:population":0,
    "gn:timezone":"Europe/Paris",
    "iso:country":"FR",
    "name:bre_x_preferred":[
        "Abancourt"
    ],
    "name:ceb_x_preferred":[
        "Abancourt"
    ],
    "name:ces_x_preferred":[
        "Abancourt"
    ],
    "name:deu_x_preferred":[
        "Abancourt"
    ],
    "name:est_x_preferred":[
        "Abancourt"
    ],
    "name:eus_x_preferred":[
        "Abancourt"
    ],
    "name:fra_x_preferred":[
        "Abancourt"
    ],
    "name:ita_x_preferred":[
        "Abancourt"
    ],
    "name:nds_x_preferred":[
        "Abancourt"
    ],
    "name:nld_x_preferred":[
        "Abancourt"
    ],
    "name:oci_x_preferred":[
        "Abancourt"
    ],
    "name:pol_x_preferred":[
        "Abancourt"
    ],
    "name:ron_x_preferred":[
        "Abancourt"
    ],
    "name:rus_x_preferred":[
        "\u0410\u0431\u0430\u043d\u043a\u0443\u0440"
    ],
    "name:sco_x_preferred":[
        "Abancourt"
    ],
    "name:slk_x_preferred":[
        "Abancourt"
    ],
    "name:spa_x_preferred":[
        "Abancourt"
    ],
    "name:swe_x_preferred":[
        "Abancourt"
    ],
    "name:ukr_x_preferred":[
        "\u0410\u0431\u0430\u043d\u043a\u0443\u0440"
    ],
    "wof:name":"Abancourt",
    "wof:placetype":"locality"
},
  "geometry": {"coordinates":[1.62327,49.591],"type":"Point"}
}