{
  "type": "Feature",
  "properties": {
    "gn:admin1_code":"84",
    "gn:admin2_code":"43",
    "gn:admin3_code":"431",
    "gn:admin4_code":"43239",
    "gn:asciiname":"Montplot",
    "gn:country_code":"FR",
    "gn:dem":881,
    "gn:feature_class":"P",
    "gn:feature_code":"PPL",
    "gn:name":"Montplot",
    "gn:population":0,
    "gn:timezone":"Europe/Paris",
    "iso:country":"FR",
    "wof:name":"Montplot",
    "wof:placetype":"locality"
},
  "geometry": {"coordinates":[3.60427,45.07162],"type":"Point"}
}