{
  "type": "Feature",
  "properties": {
    "gn:admin1_code":"84",
    "gn:admin2_code":"43",
    "gn:admin3_code":"432",
    "gn:admin4_code":"43160",
    "gn:asciiname":"Arquejols",
    "gn:country_code":"FR",
    "gn:dem":1008,
    "gn:feature_class":"P",
    "gn:feature_code":"PPL",
    "gn:name":"Arquejols",
    "gn:population":0,
    "gn:timezone":"Europe/Paris",
    "iso:country":"FR",
    "name:und_x_variant":[
        "Arquejol",
        "Arquejols"
    ],
    "wof:name":"Arquejols",
    "wof:placetype":"locality"
},
  "geometry": {"coordinates":[3.82289,44.80748],"type":"Point"}
}