{
  "type": "Feature",
  "properties": {
    "gn:admin1_code":"84",
    "gn:admin2_code":"63",
    "gn:admin3_code":"631",
    "gn:admin4_code":"63211",
    "gn:asciiname":"Chadernolles",
    "gn:country_code":"FR",
    "gn:dem":570,
    "gn:feature_class":"P",
    "gn:feature_code":"PPL",
    "gn:name":"Chadernolles",
    "gn:population":0,
    "gn:timezone":"Europe/Paris",
    "iso:country":"FR",
    "name:und_x_variant":[
        "Chademolle",
        "Chadernolle",
        "Chadernolles"
    ],
    "wof:name":"Chadernolles",
    "wof:placetype":"locality"
},
  "geometry": {"coordinates":[3.76384,45.47424],"type":"Point"}
}