{
  "type": "Feature",
  "properties": {
    "gn:admin1_code":"84",
    "gn:admin2_code":"43",
    "gn:admin3_code":"433",
    "gn:admin4_code":"43025",
    "gn:asciiname":"Pirolles",
    "gn:country_code":"FR",
    "gn:dem":542,
    "gn:feature_class":"P",
    "gn:feature_code":"PPL",
    "gn:name":"Pirolles",
    "gn:population":0,
    "gn:timezone":"Europe/Paris",
    "iso:country":"FR",
    "wof:name":"Pirolles",
    "wof:placetype":"locality"
},
  "geometry": {"coordinates":[4.11483,45.27183],"type":"Point"}
}