{
  "type": "Feature",
  "properties": {
    "gn:admin1_code":"93",
    "gn:admin2_code":"05",
    "gn:admin3_code":"051",
    "gn:admin4_code":"05093",
    "gn:asciiname":"Chalets du Jadis",
    "gn:cc2":"FR",
    "gn:country_code":"FR",
    "gn:dem":1872,
    "gn:feature_class":"P",
    "gn:feature_code":"PPL",
    "gn:name":"Chalets du Jadis",
    "gn:population":0,
    "gn:timezone":"Europe/Paris",
    "iso:country":"FR",
    "name:und_x_variant":[
        "Le Jadis"
    ],
    "wof:name":"Chalets du Jadis",
    "wof:placetype":"locality"
},
  "geometry": {"coordinates":[6.54047,45.04096],"type":"Point"}
}