{
  "type": "Feature",
  "properties": {
    "gn:admin1_code":"76",
    "gn:admin2_code":"46",
    "gn:admin3_code":"463",
    "gn:admin4_code":"46087",
    "gn:asciiname":"Saint-Avit",
    "gn:country_code":"FR",
    "gn:dem":215,
    "gn:feature_class":"P",
    "gn:feature_code":"PPL",
    "gn:name":"Saint-Avit",
    "gn:population":0,
    "gn:timezone":"Europe/Paris",
    "iso:country":"FR",
    "name:cat_x_preferred":[
        "Saint-Avit"
    ],
    "name:ceb_x_preferred":[
        "Saint-Avit"
    ],
    "name:deu_x_preferred":[
        "Saint-Avit"
    ],
    "name:fra_x_preferred":[
        "Saint-Avit"
    ],
    "name:ita_x_preferred":[
        "Saint-Avit"
    ],
    "name:nds_x_preferred":[
        "Saint-Avit"
    ],
    "name:nld_x_preferred":[
        "Saint-Avit"
    ],
    "name:oci_x_preferred":[
        "Sent Avit"
    ],
    "name:pms_x_preferred":[
        "Saint-Avit"
    ],
    "name:pol_x_preferred":[
        "Saint-Avit"
    ],
    "name:por_x_preferred":[
        "Saint-Avit"
    ],
    "name:slk_x_preferred":[
        "Saint-Avit"
    ],
    "name:spa_x_preferred":[
        "Saint-Avit"
    ],
    "name:swe_x_preferred":[
        "Saint-Avit"
    ],
    "name:ukr_x_preferred":[
        "\u0421\u0435\u043d\u0442-\u0410\u0432\u0456"
    ],
    "wof:name":"Saint-Avit",
    "wof:placetype":"locality"
},
  "geometry": {"coordinates":[1.30238,44.66828],"type":"Point"}
}