{
  "type": "Feature",
  "properties": {
    "gn:admin1_code":"84",
    "gn:admin2_code":"03",
    "gn:admin3_code":"031",
    "gn:admin4_code":"03262",
    "gn:asciiname":"Varennes",
    "gn:country_code":"FR",
    "gn:dem":223,
    "gn:feature_class":"P",
    "gn:feature_code":"PPL",
    "gn:name":"Varennes",
    "gn:population":0,
    "gn:timezone":"Europe/Paris",
    "iso:country":"FR",
    "wof:name":"Varennes",
    "wof:placetype":"locality"
},
  "geometry": {"coordinates":[2.61391,46.3742],"type":"Point"}
}