{
  "type": "Feature",
  "properties": {
    "gn:admin1_code":"24",
    "gn:admin2_code":"45",
    "gn:admin3_code":"452",
    "gn:admin4_code":"45188",
    "gn:asciiname":"Les Bernieres",
    "gn:country_code":"FR",
    "gn:dem":130,
    "gn:feature_class":"P",
    "gn:feature_code":"PPL",
    "gn:name":"Les Berni\u00e8res",
    "gn:population":0,
    "gn:timezone":"Europe/Paris",
    "iso:country":"FR",
    "wof:name":"Les Bernieres",
    "wof:placetype":"locality"
},
  "geometry": {"coordinates":[2.07158,48.00185],"type":"Point"}
}