{
  "type": "Feature",
  "properties": {
    "gn:admin1_code":"84",
    "gn:admin2_code":"38",
    "gn:admin3_code":"382",
    "gn:admin4_code":"38532",
    "gn:asciiname":"La Chanas",
    "gn:country_code":"FR",
    "gn:dem":223,
    "gn:feature_class":"P",
    "gn:feature_code":"PPL",
    "gn:name":"La Chanas",
    "gn:population":0,
    "gn:timezone":"Europe/Paris",
    "iso:country":"FR",
    "name:und_x_variant":[
        "Chanas",
        "La Chanas"
    ],
    "wof:name":"La Chanas",
    "wof:placetype":"locality"
},
  "geometry": {"coordinates":[5.27065,45.65521],"type":"Point"}
}