{
  "type": "Feature",
  "properties": {
    "gn:admin1_code":"84",
    "gn:admin2_code":"63",
    "gn:admin3_code":"633",
    "gn:admin4_code":"63401",
    "gn:asciiname":"Jassat",
    "gn:country_code":"FR",
    "gn:dem":872,
    "gn:feature_class":"P",
    "gn:feature_code":"PPL",
    "gn:name":"Jassat",
    "gn:population":0,
    "gn:timezone":"Europe/Paris",
    "iso:country":"FR",
    "wof:name":"Jassat",
    "wof:placetype":"locality"
},
  "geometry": {"coordinates":[2.93125,45.56164],"type":"Point"}
}