{
  "type": "Feature",
  "properties": {
    "iso:country":"FR",
    "name:eng_x_preferred":[
        "Saint-Isidore"
    ],
    "name:fra_x_preferred":[
        "Saint-Isidore"
    ],
    "wof:name":"Saint-Isidore",
    "wof:placetype":"neighbourhood"
},
  "geometry": {"coordinates":[7.19354468624792,43.70427034553316],"type":"Point"}
}