{
  "type": "Feature",
  "properties": {
    "gn:admin1_code":"84",
    "gn:admin2_code":"03",
    "gn:admin3_code":"031",
    "gn:admin4_code":"03243",
    "gn:asciiname":"Les Tais",
    "gn:country_code":"FR",
    "gn:dem":464,
    "gn:feature_class":"P",
    "gn:feature_code":"PPL",
    "gn:name":"Les Tais",
    "gn:population":0,
    "gn:timezone":"Europe/Paris",
    "iso:country":"FR",
    "wof:name":"Les Tais",
    "wof:placetype":"locality"
},
  "geometry": {"coordinates":[2.99467,46.34105],"type":"Point"}
}