{
  "type": "Feature",
  "properties": {
    "gn:admin1_code":"76",
    "gn:admin2_code":"46",
    "gn:admin3_code":"462",
    "gn:admin4_code":"46124",
    "gn:asciiname":"Glanes",
    "gn:country_code":"FR",
    "gn:dem":249,
    "gn:feature_class":"P",
    "gn:feature_code":"PPL",
    "gn:name":"Glanes",
    "gn:population":267,
    "gn:timezone":"Europe/Paris",
    "iso:country":"FR",
    "wof:name":"Glanes",
    "wof:placetype":"locality",
    "wof:population":267
},
  "geometry": {"coordinates":[1.87833,44.92197],"type":"Point"}
}