{
  "type": "Feature",
  "properties": {
    "gn:admin1_code":"84",
    "gn:admin2_code":"63",
    "gn:admin3_code":"634",
    "gn:admin4_code":"63281",
    "gn:asciiname":"Le Puy",
    "gn:country_code":"FR",
    "gn:dem":555,
    "gn:feature_class":"P",
    "gn:feature_code":"PPL",
    "gn:name":"Le Puy",
    "gn:population":0,
    "gn:timezone":"Europe/Paris",
    "iso:country":"FR",
    "name:ceb_x_preferred":[
        "Le Puy"
    ],
    "name:deu_x_preferred":[
        "Le Puy"
    ],
    "name:fra_x_preferred":[
        "Le Puy"
    ],
    "name:ita_x_preferred":[
        "Le Puy"
    ],
    "name:jpn_x_preferred":[
        "\u30eb\u30fb\u30d4\u30e5\u30a4"
    ],
    "name:nds_x_preferred":[
        "Le Puy"
    ],
    "name:nld_x_preferred":[
        "Le Puy"
    ],
    "name:por_x_preferred":[
        "Le Puy"
    ],
    "name:slk_x_preferred":[
        "Le Puy"
    ],
    "name:spa_x_preferred":[
        "Le Puy"
    ],
    "name:swe_x_preferred":[
        "Le Puy"
    ],
    "name:ukr_x_preferred":[
        "\u041b\u0435-\u041f\u044e\u0457"
    ],
    "name:vie_x_preferred":[
        "Le Puy"
    ],
    "wof:name":"Le Puy",
    "wof:placetype":"locality"
},
  "geometry": {"coordinates":[2.69528,46.10162],"type":"Point"}
}