{
  "type": "Feature",
  "properties": {
    "gn:admin1_code":"94",
    "gn:admin2_code":"2B",
    "gn:admin3_code":"2B2",
    "gn:admin4_code":"2B086",
    "gn:asciiname":"Casevecchie",
    "gn:country_code":"FR",
    "gn:dem":192,
    "gn:feature_class":"P",
    "gn:feature_code":"PPL",
    "gn:name":"Casevecchie",
    "gn:population":0,
    "gn:timezone":"Europe/Paris",
    "iso:country":"FR",
    "wof:name":"Casevecchie",
    "wof:placetype":"locality"
},
  "geometry": {"coordinates":[9.36667,42.96667],"type":"Point"}
}