{
  "type": "Feature",
  "properties": {
    "gn:admin1_code":"94",
    "gn:admin2_code":"2B",
    "gn:admin3_code":"2B2",
    "gn:admin4_code":"2B086",
    "gn:asciiname":"Casevecchie",
    "gn:country_code":"FR",
    "gn:dem":192,
    "gn:feature_class":"P",
    "gn:feature_code":"PPL",
    "gn:name":"Casevecchie",
    "gn:population":0,
    "gn:timezone":"Europe/Paris",
    "iso:country":"FR",
    "name:cat_x_preferred":[
        "Casevecchie"
    ],
    "name:ceb_x_preferred":[
        "Casevecchie"
    ],
    "name:cos_x_preferred":[
        "Casevechje"
    ],
    "name:deu_x_preferred":[
        "Casevecchie"
    ],
    "name:eus_x_preferred":[
        "Casevecchie"
    ],
    "name:fra_x_preferred":[
        "Casevecchie"
    ],
    "name:hun_x_preferred":[
        "Casevecchie"
    ],
    "name:ita_x_preferred":[
        "Casevecchie"
    ],
    "name:kaz_x_preferred":[
        "\u041a\u0430\u0437\u0435\u0432\u0435\u043a\u043a\u044c\u0435"
    ],
    "name:lat_x_preferred":[
        "Casevecchie"
    ],
    "name:lmo_x_preferred":[
        "Casevecchie"
    ],
    "name:mlg_x_preferred":[
        "Casevecchie"
    ],
    "name:msa_x_preferred":[
        "Casevecchie"
    ],
    "name:nld_x_preferred":[
        "Casevecchie"
    ],
    "name:oci_x_preferred":[
        "Casevecchie"
    ],
    "name:pol_x_preferred":[
        "Casevecchie"
    ],
    "name:por_x_preferred":[
        "Casevecchie"
    ],
    "name:rus_x_preferred":[
        "\u041a\u0430\u0437\u0435\u0432\u0435\u043a\u043a\u044c\u0435"
    ],
    "name:slk_x_preferred":[
        "Casevecchie"
    ],
    "name:slv_x_preferred":[
        "Casevecchie"
    ],
    "name:spa_x_preferred":[
        "Casevecchie"
    ],
    "name:srp_x_preferred":[
        "\u041a\u0430\u0437\u0435\u0432\u0435\u043a\u0438\u0458\u0435"
    ],
    "name:swe_x_preferred":[
        "Casevecchie"
    ],
    "name:ukr_x_preferred":[
        "\u041a\u0430\u0437\u0435\u0432\u0435\u043a\u043a'\u0454"
    ],
    "name:vie_x_preferred":[
        "Casevecchie"
    ],
    "name:vol_x_preferred":[
        "Casevecchie"
    ],
    "name:war_x_preferred":[
        "Casevecchie"
    ],
    "wof:name":"Casevecchie",
    "wof:placetype":"locality"
},
  "geometry": {"coordinates":[9.36667,42.96667],"type":"Point"}
}