{
  "type": "Feature",
  "properties": {
    "iso:country":"FR",
    "name:eng_x_preferred":[
        "Mutualite"
    ],
    "name:fra_x_preferred":[
        "Mutualit\u00e9"
    ],
    "wof:name":"Mutualite",
    "wof:placetype":"neighbourhood"
},
  "geometry": {"coordinates":[5.73588869937559,45.18918413714756],"type":"Point"}
}