{
  "type": "Feature",
  "properties": {
    "gn:admin1_code":"84",
    "gn:admin2_code":"03",
    "gn:admin3_code":"032",
    "gn:admin4_code":"03092",
    "gn:asciiname":"Le Bout Petit",
    "gn:country_code":"FR",
    "gn:dem":446,
    "gn:feature_class":"P",
    "gn:feature_code":"PPL",
    "gn:name":"Le Bout Petit",
    "gn:population":0,
    "gn:timezone":"Europe/Paris",
    "iso:country":"FR",
    "wof:name":"Le Bout Petit",
    "wof:placetype":"locality"
},
  "geometry": {"coordinates":[3.12916,46.43498],"type":"Point"}
}