{
  "type": "Feature",
  "properties": {
    "gn:admin1_code":"93",
    "gn:admin2_code":"83",
    "gn:admin3_code":"832",
    "gn:admin4_code":"83137",
    "gn:asciiname":"Les Routes",
    "gn:country_code":"FR",
    "gn:dem":30,
    "gn:feature_class":"P",
    "gn:feature_code":"PPL",
    "gn:name":"Les Routes",
    "gn:population":0,
    "gn:timezone":"Europe/Paris",
    "iso:country":"FR",
    "wof:name":"Les Routes",
    "wof:placetype":"locality"
},
  "geometry": {"coordinates":[5.90104,43.13817],"type":"Point"}
}