{
  "type": "Feature",
  "properties": {
    "gn:admin1_code":"75",
    "gn:admin2_code":"64",
    "gn:admin3_code":"641",
    "gn:admin4_code":"64260",
    "gn:asciiname":"Hendaye-Plage",
    "gn:country_code":"FR",
    "gn:dem":24,
    "gn:feature_class":"P",
    "gn:feature_code":"PPL",
    "gn:name":"Hendaye-Plage",
    "gn:population":0,
    "gn:timezone":"Europe/Paris",
    "iso:country":"FR",
    "wof:name":"Hendaye-Plage",
    "wof:placetype":"locality"
},
  "geometry": {"coordinates":[-1.76868,43.35845],"type":"Point"}
}