{
  "type": "Feature",
  "properties": {
    "gn:admin1_code":"28",
    "gn:admin2_code":"50",
    "gn:admin3_code":"504",
    "gn:admin4_code":"50292",
    "gn:asciiname":"La Driauderie",
    "gn:country_code":"FR",
    "gn:dem":47,
    "gn:feature_class":"P",
    "gn:feature_code":"PPL",
    "gn:name":"La Driauderie",
    "gn:population":0,
    "gn:timezone":"Europe/Paris",
    "iso:country":"FR",
    "name:und_x_variant":[
        "Dreauderie",
        "La Driauderie"
    ],
    "wof:name":"La Driauderie",
    "wof:placetype":"locality"
},
  "geometry": {"coordinates":[-1.26679,49.10857],"type":"Point"}
}