{
  "type": "Feature",
  "properties": {
    "gn:gn_country":"FR",
    "iso:country":"FR",
    "qs_pg:aaroncc":"FR",
    "qs_pg:gn_country":"FR",
    "qs_pg:name":"A Bucca Ll'oru",
    "qs_pg:name_adm0":"France",
    "qs_pg:name_adm1":"Corse",
    "qs_pg:photos":328,
    "qs_pg:photos_1k":66,
    "qs_pg:photos_9k":1,
    "qs_pg:photos_9r":5,
    "qs_pg:photos_all":328,
    "qs_pg:photos_sr":5,
    "qs_pg:pop_sr":0,
    "qs_pg:qs_pg_placetype":"locality",
    "qs_pg:qs_pg_placetype_gp":"Town",
    "qs_pg:woe_adm0":23424819,
    "woe:adm0_id":23424819,
    "woe:name_adm0":"France",
    "woe:name_adm1":"Corse",
    "woe:placetype":"Town",
    "wof:name":"A Bucca Ll'oru",
    "wof:placetype":"neighbourhood"
},
  "geometry": {"coordinates":[9.307823,41.548167],"type":"Point"}
}