{
  "type": "Feature",
  "properties": {
    "gn:admin1_code":"53",
    "gn:admin2_code":"22",
    "gn:admin3_code":"221",
    "gn:admin4_code":"22046",
    "gn:asciiname":"Le Gouray",
    "gn:country_code":"FR",
    "gn:dem":138,
    "gn:feature_class":"P",
    "gn:feature_code":"PPL",
    "gn:name":"Le Gouray",
    "gn:population":983,
    "gn:timezone":"Europe/Paris",
    "iso:country":"FR",
    "name:bre_x_preferred":[
        "Gorre"
    ],
    "name:fra_x_preferred":[
        "Le Gouray"
    ],
    "wof:name":"Le Gouray",
    "wof:placetype":"locality",
    "wof:population":983
},
  "geometry": {"coordinates":[-2.48807,48.32757],"type":"Point"}
}