{
  "type": "Feature",
  "properties": {
    "gn:admin1_code":"11",
    "gn:admin2_code":"78",
    "gn:admin3_code":"781",
    "gn:admin4_code":"78444.0",
    "gn:asciiname":"L'Aunaie",
    "gn:country_code":"FR",
    "gn:dem":134,
    "gn:feature_class":"P",
    "gn:feature_code":"PPL",
    "gn:name":"L\u2019Aunaie",
    "gn:population":0,
    "gn:timezone":"Europe/Paris",
    "iso:country":"FR",
    "wof:name":"L'Aunaie",
    "wof:placetype":"locality"
},
  "geometry": {"coordinates":[1.55216,48.93285],"type":"Point"}
}