{
  "type": "Feature",
  "properties": {
    "gn:admin1_code":"53",
    "gn:admin2_code":"29",
    "gn:admin3_code":"294",
    "gn:admin4_code":"29241",
    "gn:asciiname":"Quistinit",
    "gn:country_code":"FR",
    "gn:dem":138,
    "gn:feature_class":"P",
    "gn:feature_code":"PPL",
    "gn:name":"Quistinit",
    "gn:population":0,
    "gn:timezone":"Europe/Paris",
    "iso:country":"FR",
    "wof:name":"Quistinit",
    "wof:placetype":"locality"
},
  "geometry": {"coordinates":[-3.76667,47.98333],"type":"Point"}
}