{
  "type": "Feature",
  "properties": {
    "gn:country":"FR",
    "gn:fcode":"PPL",
    "gn:population":0,
    "iso:country":"FR",
    "name:ara_x_preferred":[
        "\u0643\u0627\u0645\u064a\u0631\u0648\u0646"
    ],
    "name:bel_x_preferred":[
        "\u041a\u044d\u043c\u0435\u0440\u0430\u043d"
    ],
    "name:cat_x_preferred":[
        "Cameron"
    ],
    "name:ceb_x_preferred":[
        "Cameron"
    ],
    "name:ces_x_preferred":[
        "Cameron"
    ],
    "name:dan_x_preferred":[
        "Cameron"
    ],
    "name:deu_x_preferred":[
        "Cameron"
    ],
    "name:ell_x_preferred":[
        "\u039a\u03ac\u03bc\u03b5\u03c1\u03bf\u03bd"
    ],
    "name:fra_x_preferred":[
        "Cameron"
    ],
    "name:heb_x_preferred":[
        "\u05e7\u05de\u05e8\u05d5\u05df"
    ],
    "name:hun_x_preferred":[
        "Cameron"
    ],
    "name:ita_x_preferred":[
        "Cameron"
    ],
    "name:jpn_x_preferred":[
        "\u30ad\u30e3\u30e1\u30ed\u30f3"
    ],
    "name:kor_x_preferred":[
        "\uce90\uba38\ub7f0"
    ],
    "name:lav_x_preferred":[
        "Kemerons"
    ],
    "name:nld_x_preferred":[
        "Cameron"
    ],
    "name:pol_x_preferred":[
        "Cameron"
    ],
    "name:por_x_preferred":[
        "Cameron"
    ],
    "name:ron_x_preferred":[
        "Cameron"
    ],
    "name:rus_x_preferred":[
        "\u041a\u0430\u043c\u0435\u0440\u043e\u043d"
    ],
    "name:spa_x_preferred":[
        "Cameron"
    ],
    "name:srp_x_preferred":[
        "\u041a\u0430\u043c\u0435\u0440\u043e\u043d"
    ],
    "name:swe_x_preferred":[
        "Cameron"
    ],
    "name:tha_x_preferred":[
        "\u0e04\u0e32\u0e40\u0e21\u0e23\u0e2d\u0e19"
    ],
    "name:ukr_x_preferred":[
        "\u041a\u0430\u043c\u0435\u0440\u043e\u043d"
    ],
    "name:und_x_variant":[
        "Camerun"
    ],
    "name:urd_x_preferred":[
        "\u06a9\u06cc\u0645\u0631\u0648\u0646"
    ],
    "name:vol_x_preferred":[
        "Cameron"
    ],
    "qs_pg:aaroncc":"FR",
    "qs_pg:gn_country":"FR",
    "qs_pg:gn_fcode":"PPL",
    "qs_pg:gn_pop":0,
    "qs_pg:name":"Cameron",
    "qs_pg:name_adm0":"France",
    "qs_pg:name_adm1":"Pays de la Loire",
    "qs_pg:photos":35,
    "qs_pg:photos_1k":7,
    "qs_pg:photos_9k":1,
    "qs_pg:photos_9r":2,
    "qs_pg:photos_all":35,
    "qs_pg:photos_sr":2,
    "qs_pg:pop_sr":0,
    "qs_pg:qs_pg_placetype":"locality",
    "qs_pg:qs_pg_placetype_gp":"Town",
    "qs_pg:woe_adm0":23424819,
    "woe:adm0_id":23424819,
    "woe:name_adm0":"France",
    "woe:name_adm1":"Pays de la Loire",
    "woe:placetype":"Town",
    "wof:name":"Cameron",
    "wof:placetype":"neighbourhood"
},
  "geometry": {"coordinates":[-2.235,47.42],"type":"Point"}
}