{
  "type": "Feature",
  "properties": {
    "frgov:code_epci":"200069730",
    "frgov:insee_arr":"1",
    "frgov:insee_com":"76450",
    "frgov:insee_dep":"76",
    "frgov:insee_reg":"28",
    "frgov:nom_com":"Montroty",
    "frgov:nom_com_m":"MONTROTY",
    "frgov:nom_dep":"SEINE-MARITIME",
    "frgov:nom_reg":"NORMANDIE",
    "frgov:statut":"Commune simple",
    "gn:admin1_code":"28",
    "gn:admin2_code":"76",
    "gn:admin3_code":"761",
    "gn:admin4_code":"76450",
    "gn:asciiname":"Montroty",
    "gn:country_code":"FR",
    "gn:dem":196,
    "gn:feature_class":"P",
    "gn:feature_code":"PPL",
    "gn:name":"Montroty",
    "gn:population":0,
    "gn:timezone":"Europe/Paris",
    "iso:country":"FR",
    "name:cat_x_preferred":[
        "Montroty"
    ],
    "name:ceb_x_preferred":[
        "Montroty"
    ],
    "name:deu_x_preferred":[
        "Montroty"
    ],
    "name:eus_x_preferred":[
        "Montroty"
    ],
    "name:fra_x_preferred":[
        "Montroty"
    ],
    "name:hun_x_preferred":[
        "Montroty"
    ],
    "name:ita_x_preferred":[
        "Montroty"
    ],
    "name:kaz_x_preferred":[
        "\u041c\u043e\u043d\u0440\u043e\u0442\u0438"
    ],
    "name:lat_x_preferred":[
        "Montroty"
    ],
    "name:mlg_x_preferred":[
        "Montroty"
    ],
    "name:msa_x_preferred":[
        "Montroty"
    ],
    "name:nld_x_preferred":[
        "Montroty"
    ],
    "name:oci_x_preferred":[
        "Montroty"
    ],
    "name:pms_x_preferred":[
        "Montroty"
    ],
    "name:pol_x_preferred":[
        "Montroty"
    ],
    "name:por_x_preferred":[
        "Montroty"
    ],
    "name:ron_x_preferred":[
        "Montroty"
    ],
    "name:slk_x_preferred":[
        "Montroty"
    ],
    "name:spa_x_preferred":[
        "Montroty"
    ],
    "name:swe_x_preferred":[
        "Montroty"
    ],
    "name:ukr_x_preferred":[
        "\u041c\u043e\u043d\u0440\u043e\u0442\u0456"
    ],
    "name:vie_x_preferred":[
        "Montroty"
    ],
    "name:vol_x_preferred":[
        "Montroty"
    ],
    "name:war_x_preferred":[
        "Montroty"
    ],
    "qs:a0":"France",
    "qs:a1":"SEINE-MARITIME",
    "qs:a1_lc":"76",
    "qs:a1r":"HAUTE-NORMANDIE",
    "qs:a1r_lc":"23",
    "qs:a2_lc":"25",
    "qs:a2r_lc":"1",
    "qs:adm0":"France",
    "qs:adm0_a3":"FRA",
    "qs:la":"MONTROTY",
    "qs:la_lc":"76450",
    "qs:level":"localadmin",
    "qs:type":"Commune simple",
    "wof:coterminous":[
        404390671
    ],
    "wof:name":"Montroty",
    "wof:placetype":"locality",
    "wof:placetype_local":"Commune simple"
},
  "geometry": {"coordinates":[1.66512,49.43956],"type":"Point"}
}