{
  "type": "Feature",
  "properties": {
    "gn:admin1_code":"28",
    "gn:admin2_code":"76",
    "gn:admin3_code":"761",
    "gn:admin4_code":"76450",
    "gn:asciiname":"Montroty",
    "gn:country_code":"FR",
    "gn:dem":196,
    "gn:feature_class":"P",
    "gn:feature_code":"PPL",
    "gn:name":"Montroty",
    "gn:population":0,
    "gn:timezone":"Europe/Paris",
    "iso:country":"FR",
    "wof:name":"Montroty",
    "wof:placetype":"locality"
},
  "geometry": {"coordinates":[1.66512,49.43956],"type":"Point"}
}