{
  "type": "Feature",
  "properties": {
    "gn:admin1_code":"24",
    "gn:admin2_code":"37",
    "gn:admin3_code":"373",
    "gn:admin4_code":"37111",
    "gn:asciiname":"Logny",
    "gn:country_code":"FR",
    "gn:dem":121,
    "gn:feature_class":"P",
    "gn:feature_code":"PPL",
    "gn:name":"Logny",
    "gn:population":0,
    "gn:timezone":"Europe/Paris",
    "iso:country":"FR",
    "name:fra_x_preferred":[
        "Logny"
    ],
    "name:nld_x_preferred":[
        "Logny"
    ],
    "name:pol_x_preferred":[
        "Logny"
    ],
    "name:ukr_x_preferred":[
        "\u041b\u043e\u043d\u044c\u0457"
    ],
    "wof:name":"Logny",
    "wof:placetype":"locality"
},
  "geometry": {"coordinates":[1.12284,47.1542],"type":"Point"}
}