{
  "type": "Feature",
  "properties": {
    "iso:country":"FR",
    "name:eng_x_preferred":[
        "La Binquenais"
    ],
    "name:fra_x_preferred":[
        "La Binquenais"
    ],
    "wof:name":"La Binquenais",
    "wof:placetype":"neighbourhood"
},
  "geometry": {"coordinates":[-1.67015361875203,48.09034436254997],"type":"Point"}
}