{
  "type": "Feature",
  "properties": {
    "gn:admin1_code":"24",
    "gn:admin2_code":"28",
    "gn:admin3_code":"282",
    "gn:admin4_code":"28330",
    "gn:asciiname":"Valliere",
    "gn:country_code":"FR",
    "gn:dem":115,
    "gn:feature_class":"P",
    "gn:feature_code":"PPL",
    "gn:name":"Valli\u00e8re",
    "gn:population":0,
    "gn:timezone":"Europe/Paris",
    "iso:country":"FR",
    "wof:name":"Valliere",
    "wof:placetype":"locality"
},
  "geometry": {"coordinates":[1.4817,48.10643],"type":"Point"}
}