{
  "type": "Feature",
  "properties": {
    "gn:admin1_code":"28",
    "gn:admin2_code":"76",
    "gn:admin3_code":"761",
    "gn:admin4_code":"76652",
    "gn:asciiname":"Equiqueville",
    "gn:country_code":"FR",
    "gn:dem":41,
    "gn:feature_class":"P",
    "gn:feature_code":"PPL",
    "gn:name":"\u00c9quiqueville",
    "gn:population":0,
    "gn:timezone":"Europe/Paris",
    "iso:country":"FR",
    "wof:name":"Equiqueville",
    "wof:placetype":"locality"
},
  "geometry": {"coordinates":[1.25404,49.8163],"type":"Point"}
}