{
  "type": "Feature",
  "properties": {
    "gn:admin1_code":"32",
    "gn:admin2_code":"59",
    "gn:admin3_code":"591",
    "gn:admin4_code":"59225",
    "gn:asciiname":"Roeux",
    "gn:country_code":"FR",
    "gn:dem":153,
    "gn:feature_class":"P",
    "gn:feature_code":"PPL",
    "gn:name":"Roeux",
    "gn:population":0,
    "gn:timezone":"Europe/Paris",
    "iso:country":"FR",
    "wof:name":"Roeux",
    "wof:placetype":"locality"
},
  "geometry": {"coordinates":[3.8971,50.2965],"type":"Point"}
}