{
  "type": "Feature",
  "properties": {
    "gn:admin1_code":"27",
    "gn:admin2_code":"58",
    "gn:admin3_code":"582",
    "gn:admin4_code":"58029",
    "gn:asciiname":"La Roche",
    "gn:country_code":"FR",
    "gn:dem":194,
    "gn:feature_class":"P",
    "gn:feature_code":"PPL",
    "gn:name":"La Roche",
    "gn:population":0,
    "gn:timezone":"Europe/Paris",
    "iso:country":"FR",
    "name:als_x_preferred":[
        "La Roche"
    ],
    "name:bre_x_preferred":[
        "La Roche"
    ],
    "name:ceb_x_preferred":[
        "La Roche"
    ],
    "name:deu_x_preferred":[
        "La Roche"
    ],
    "name:epo_x_preferred":[
        "La Roche"
    ],
    "name:eus_x_preferred":[
        "La Roche"
    ],
    "name:fra_x_preferred":[
        "La Roche"
    ],
    "name:ita_x_preferred":[
        "La Roche"
    ],
    "name:jpn_x_preferred":[
        "\u30e9\u30fb\u30ed\u30c3\u30b7\u30e5"
    ],
    "name:nld_x_preferred":[
        "La Roche"
    ],
    "name:pol_x_preferred":[
        "La Roche"
    ],
    "name:ron_x_preferred":[
        "La Roche"
    ],
    "name:swe_x_preferred":[
        "La Roche"
    ],
    "wof:name":"La Roche",
    "wof:placetype":"locality"
},
  "geometry": {"coordinates":[3.49509,47.33904],"type":"Point"}
}