{
  "type": "Feature",
  "properties": {
    "gn:admin1_code":"27",
    "gn:admin2_code":"58",
    "gn:admin3_code":"582",
    "gn:admin4_code":"58029",
    "gn:asciiname":"La Roche",
    "gn:country_code":"FR",
    "gn:dem":194,
    "gn:feature_class":"P",
    "gn:feature_code":"PPL",
    "gn:name":"La Roche",
    "gn:population":0,
    "gn:timezone":"Europe/Paris",
    "iso:country":"FR",
    "wof:name":"La Roche",
    "wof:placetype":"locality"
},
  "geometry": {"coordinates":[3.49509,47.33904],"type":"Point"}
}