{
  "type": "Feature",
  "properties": {
    "gn:admin1_code":"93",
    "gn:admin2_code":"05",
    "gn:admin3_code":"052",
    "gn:admin4_code":"05095",
    "gn:asciiname":"Lacoue",
    "gn:country_code":"FR",
    "gn:dem":947,
    "gn:feature_class":"P",
    "gn:feature_code":"PPL",
    "gn:name":"Lacoue",
    "gn:population":0,
    "gn:timezone":"Europe/Paris",
    "iso:country":"FR",
    "name:und_x_variant":[
        "Lacaue",
        "Lacoue"
    ],
    "wof:name":"Lacoue",
    "wof:placetype":"locality"
},
  "geometry": {"coordinates":[6.0038,44.72684],"type":"Point"}
}