{
  "type": "Feature",
  "properties": {
    "gn:admin1_code":"44",
    "gn:admin2_code":"10",
    "gn:admin3_code":"102",
    "gn:admin4_code":"10370",
    "gn:asciiname":"Le Vallon",
    "gn:country_code":"FR",
    "gn:dem":89,
    "gn:feature_class":"P",
    "gn:feature_code":"PPL",
    "gn:name":"Le Vallon",
    "gn:population":0,
    "gn:timezone":"Europe/Paris",
    "iso:country":"FR",
    "wof:name":"Le Vallon",
    "wof:placetype":"locality"
},
  "geometry": {"coordinates":[3.52156,48.40784],"type":"Point"}
}