{
  "type": "Feature",
  "properties": {
    "gn:admin1_code":"75",
    "gn:admin2_code":"23",
    "gn:admin3_code":"232",
    "gn:admin4_code":"23104",
    "gn:asciiname":"Bordessoulles",
    "gn:cc2":"FR",
    "gn:country_code":"FR",
    "gn:dem":476,
    "gn:feature_class":"P",
    "gn:feature_code":"PPL",
    "gn:name":"Bordessoulles",
    "gn:population":0,
    "gn:timezone":"Europe/Paris",
    "iso:country":"FR",
    "name:und_x_variant":[
        "Bordessoulle",
        "Bordessoulles"
    ],
    "wof:name":"Bordessoulles",
    "wof:placetype":"locality"
},
  "geometry": {"coordinates":[2.26396,46.28842],"type":"Point"}
}