{
  "type": "Feature",
  "properties": {
    "gn:admin1_code":"53",
    "gn:admin2_code":"22",
    "gn:admin3_code":"223",
    "gn:admin4_code":"22198",
    "gn:asciiname":"Barnabanec",
    "gn:country_code":"FR",
    "gn:dem":93,
    "gn:feature_class":"P",
    "gn:feature_code":"PPL",
    "gn:name":"Barnabanec",
    "gn:population":0,
    "gn:timezone":"Europe/Paris",
    "iso:country":"FR",
    "wof:name":"Barnabanec",
    "wof:placetype":"locality"
},
  "geometry": {"coordinates":[-3.48475,48.79174],"type":"Point"}
}