{
  "type": "Feature",
  "properties": {
    "gn:admin1_code":"44",
    "gn:admin2_code":"68",
    "gn:admin3_code":"684",
    "gn:admin4_code":"68121",
    "gn:asciiname":"Hagenthal-le-Haut",
    "gn:country_code":"FR",
    "gn:dem":381,
    "gn:feature_class":"P",
    "gn:feature_code":"PPL",
    "gn:name":"Hagenthal-le-Haut",
    "gn:population":0,
    "gn:timezone":"Europe/Paris",
    "iso:country":"FR",
    "wof:name":"Hagenthal-le-Haut",
    "wof:placetype":"locality"
},
  "geometry": {"coordinates":[7.46667,47.51667],"type":"Point"}
}