{
  "type": "Feature",
  "properties": {
    "iso:country":"FR",
    "name:eng_x_preferred":[
        "Montceleux-Pont-Blanc"
    ],
    "name:fra_x_preferred":[
        "Montceleux-Pont-Blanc"
    ],
    "wof:name":"Montceleux-Pont-Blanc",
    "wof:placetype":"neighbourhood"
},
  "geometry": {"coordinates":[2.53525336224087,48.94852071225391],"type":"Point"}
}