{
  "type": "Feature",
  "properties": {
    "gn:admin1_code":"24",
    "gn:admin2_code":"45",
    "gn:admin3_code":"453",
    "gn:admin4_code":"45030.0",
    "gn:asciiname":"Jarrisoi",
    "gn:country_code":"FR",
    "gn:dem":111,
    "gn:feature_class":"P",
    "gn:feature_code":"PPL",
    "gn:name":"Jarrisoi",
    "gn:population":0,
    "gn:timezone":"Europe/Paris",
    "iso:country":"FR",
    "name:und_x_variant":[
        "Jarrissoy",
        "Jarrisoi"
    ],
    "wof:name":"Jarrisoi",
    "wof:placetype":"locality"
},
  "geometry": {"coordinates":[2.43113,48.06041],"type":"Point"}
}