{
  "type": "Feature",
  "properties": {
    "gn:admin1_code":"44",
    "gn:admin2_code":"67",
    "gn:admin3_code":"674",
    "gn:admin4_code":"67372",
    "gn:asciiname":"La Walck",
    "gn:country_code":"FR",
    "gn:dem":189,
    "gn:feature_class":"P",
    "gn:feature_code":"PPL",
    "gn:name":"La Walck",
    "gn:population":0,
    "gn:timezone":"Europe/Paris",
    "iso:country":"FR",
    "wof:name":"La Walck",
    "wof:placetype":"locality"
},
  "geometry": {"coordinates":[7.61053,48.8501],"type":"Point"}
}