{
  "type": "Feature",
  "properties": {
    "gn:admin1_code":"44",
    "gn:admin2_code":"67",
    "gn:admin3_code":"674",
    "gn:admin4_code":"67372",
    "gn:asciiname":"La Walck",
    "gn:country_code":"FR",
    "gn:dem":189,
    "gn:feature_class":"P",
    "gn:feature_code":"PPL",
    "gn:name":"La Walck",
    "gn:population":0,
    "gn:timezone":"Europe/Paris",
    "iso:country":"FR",
    "name:als_x_preferred":[
        "Walk"
    ],
    "name:ara_x_preferred":[
        "\u0644\u0627 \u0648\u0627\u0644\u0643"
    ],
    "name:cat_x_preferred":[
        "La Walck"
    ],
    "name:ceb_x_preferred":[
        "La Walck"
    ],
    "name:deu_x_preferred":[
        "La Walck"
    ],
    "name:eus_x_preferred":[
        "La Walck"
    ],
    "name:fas_x_preferred":[
        "\u0644\u0627\u0648\u0627\u0644\u06a9"
    ],
    "name:fra_x_preferred":[
        "La Walck"
    ],
    "name:hun_x_preferred":[
        "La Walck"
    ],
    "name:hye_x_preferred":[
        "\u053c\u0561 \u054e\u0561\u056c\u056f"
    ],
    "name:ita_x_preferred":[
        "La Walck"
    ],
    "name:kaz_x_preferred":[
        "\u041b\u0430-\u0412\u0430\u043b\u044c\u043a"
    ],
    "name:lat_x_preferred":[
        "La Walck"
    ],
    "name:mlg_x_preferred":[
        "La Walck"
    ],
    "name:msa_x_preferred":[
        "La Walck"
    ],
    "name:nld_x_preferred":[
        "La Walck"
    ],
    "name:oci_x_preferred":[
        "La Walck"
    ],
    "name:pfl_x_preferred":[
        "Walk"
    ],
    "name:pms_x_preferred":[
        "Walck"
    ],
    "name:pol_x_preferred":[
        "La Walck"
    ],
    "name:por_x_preferred":[
        "La Walck"
    ],
    "name:ron_x_preferred":[
        "La Walck"
    ],
    "name:rus_x_preferred":[
        "\u041b\u0430-\u0412\u0430\u043b\u044c\u043a"
    ],
    "name:slk_x_preferred":[
        "La Walck"
    ],
    "name:spa_x_preferred":[
        "La Walck"
    ],
    "name:swe_x_preferred":[
        "La Walck"
    ],
    "name:ukr_x_preferred":[
        "\u041b\u0430-\u0412\u0430\u043b\u044c\u043a"
    ],
    "name:urd_x_preferred":[
        "\u0644\u0627 \u0648\u0627\u0644\u06a9"
    ],
    "name:uzb_x_preferred":[
        "La Walck"
    ],
    "name:vie_x_preferred":[
        "La Walck"
    ],
    "name:vol_x_preferred":[
        "La Walck"
    ],
    "name:war_x_preferred":[
        "La Walck"
    ],
    "name:zho_x_preferred":[
        "\u62c9\u74e6\u5c14\u514b"
    ],
    "wof:name":"La Walck",
    "wof:placetype":"locality"
},
  "geometry": {"coordinates":[7.61053,48.8501],"type":"Point"}
}