{
  "type": "Feature",
  "properties": {
    "gn:admin1_code":"84",
    "gn:admin2_code":"38",
    "gn:admin3_code":"381",
    "gn:admin4_code":"38342",
    "gn:asciiname":"Maissenas",
    "gn:country_code":"FR",
    "gn:dem":772,
    "gn:feature_class":"P",
    "gn:feature_code":"PPL",
    "gn:name":"Maissenas",
    "gn:population":0,
    "gn:timezone":"Europe/Paris",
    "iso:country":"FR",
    "wof:name":"Maissenas",
    "wof:placetype":"locality"
},
  "geometry": {"coordinates":[5.65451,44.87712],"type":"Point"}
}