{
  "type": "Feature",
  "properties": {
    "gn:country":"FR",
    "gn:fcode":"PPL",
    "gn:population":401,
    "iso:country":"FR",
    "name:und_x_variant":[
        "Saint-Maur-sur Loir"
    ],
    "qs_pg:aaroncc":"FR",
    "qs_pg:gn_country":"FR",
    "qs_pg:gn_fcode":"PPL",
    "qs_pg:gn_pop":401,
    "qs_pg:name":"St.-Maur-sur-le-Loir",
    "qs_pg:name_adm0":"France",
    "qs_pg:name_adm1":"Centre",
    "qs_pg:photos":1,
    "qs_pg:photos_1k":1,
    "qs_pg:photos_9k":1,
    "qs_pg:photos_9r":1,
    "qs_pg:photos_all":1,
    "qs_pg:photos_sr":1,
    "qs_pg:pop_sr":2,
    "qs_pg:qs_pg_placetype":"locality",
    "qs_pg:qs_pg_placetype_gp":"Town",
    "qs_pg:woe_adm0":23424819,
    "woe:adm0_id":23424819,
    "woe:name_adm0":"France",
    "woe:name_adm1":"Centre",
    "woe:placetype":"Town",
    "wof:name":"St.-Maur-sur-le-Loir",
    "wof:placetype":"neighbourhood",
    "wof:population":401
},
  "geometry": {"coordinates":[1.41973,48.15309],"type":"Point"}
}