{
  "type": "Feature",
  "properties": {
    "gn:admin1_code":"75",
    "gn:admin2_code":"23",
    "gn:admin3_code":"232",
    "gn:admin4_code":"23245",
    "gn:asciiname":"Chamilloux",
    "gn:country_code":"FR",
    "gn:dem":412,
    "gn:feature_class":"P",
    "gn:feature_code":"PPL",
    "gn:name":"Chamilloux",
    "gn:population":0,
    "gn:timezone":"Europe/Paris",
    "iso:country":"FR",
    "wof:name":"Chamilloux",
    "wof:placetype":"locality"
},
  "geometry": {"coordinates":[1.8354,46.18821],"type":"Point"}
}