{
  "type": "Feature",
  "properties": {
    "frgov:code_epci":"200068757",
    "frgov:insee_arr":"1",
    "frgov:insee_com":"88388",
    "frgov:insee_dep":"88",
    "frgov:insee_reg":"44",
    "frgov:nom_com":"Renauvoid",
    "frgov:nom_com_m":"RENAUVOID",
    "frgov:nom_dep":"VOSGES",
    "frgov:nom_reg":"GRAND EST",
    "frgov:statut":"Commune simple",
    "gn:admin1_code":"44",
    "gn:admin2_code":"88",
    "gn:admin3_code":"881",
    "gn:admin4_code":"88388",
    "gn:asciiname":"Renauvoid",
    "gn:country_code":"FR",
    "gn:dem":417,
    "gn:feature_class":"P",
    "gn:feature_code":"PPL",
    "gn:name":"Renauvoid",
    "gn:population":0,
    "gn:timezone":"Europe/Paris",
    "iso:country":"FR",
    "name:bug_x_preferred":[
        "Renauvoid"
    ],
    "name:cat_x_preferred":[
        "Renauvoid"
    ],
    "name:ceb_x_preferred":[
        "Renauvoid"
    ],
    "name:deu_x_preferred":[
        "Renauvoid"
    ],
    "name:eus_x_preferred":[
        "Renauvoid"
    ],
    "name:fra_x_preferred":[
        "Renauvoid"
    ],
    "name:hun_x_preferred":[
        "Renauvoid"
    ],
    "name:ind_x_preferred":[
        "Renauvoid"
    ],
    "name:ita_x_preferred":[
        "Renauvoid"
    ],
    "name:kaz_x_preferred":[
        "\u0420\u0435\u043d\u043e\u0432\u0443\u0430"
    ],
    "name:mlg_x_preferred":[
        "Renauvoid"
    ],
    "name:msa_x_preferred":[
        "Renauvoid"
    ],
    "name:nld_x_preferred":[
        "Renauvoid"
    ],
    "name:oci_x_preferred":[
        "Renauvoid"
    ],
    "name:pol_x_preferred":[
        "Renauvoid"
    ],
    "name:slk_x_preferred":[
        "Renauvoid"
    ],
    "name:spa_x_preferred":[
        "Renauvoid"
    ],
    "name:swe_x_preferred":[
        "Renauvoid"
    ],
    "name:ukr_x_preferred":[
        "\u0420\u0435\u043d\u043e\u0432\u0443\u0430"
    ],
    "name:uzb_x_preferred":[
        "Renauvoid"
    ],
    "name:vie_x_preferred":[
        "Renauvoid"
    ],
    "name:vol_x_preferred":[
        "Renauvoid"
    ],
    "name:war_x_preferred":[
        "Renauvoid"
    ],
    "name:zho_x_preferred":[
        "\u96f7\u8bfa\u74e6"
    ],
    "qs:a0":"France",
    "qs:a1":"VOSGES",
    "qs:a1_lc":"88",
    "qs:a1r":"LORRAINE",
    "qs:a1r_lc":"41",
    "qs:a2_lc":"30",
    "qs:a2r_lc":"1",
    "qs:adm0":"France",
    "qs:adm0_a3":"FRA",
    "qs:la":"RENAUVOID",
    "qs:la_lc":"88388",
    "qs:level":"localadmin",
    "qs:type":"Commune simple",
    "wof:coterminous":[
        404396827
    ],
    "wof:name":"Renauvoid",
    "wof:placetype":"locality",
    "wof:placetype_local":"Commune simple"
},
  "geometry": {"coordinates":[6.3836,48.1437],"type":"Point"}
}