{
  "type": "Feature",
  "properties": {
    "gn:admin1_code":"75",
    "gn:admin2_code":"16",
    "gn:admin3_code":"161",
    "gn:admin4_code":"16093",
    "gn:asciiname":"Treille",
    "gn:cc2":"FR",
    "gn:country_code":"FR",
    "gn:dem":118,
    "gn:feature_class":"P",
    "gn:feature_code":"PPL",
    "gn:name":"Treille",
    "gn:population":0,
    "gn:timezone":"Europe/Paris",
    "iso:country":"FR",
    "name:deu_x_preferred":[
        "Treille"
    ],
    "name:fra_x_preferred":[
        "Treille"
    ],
    "name:und_x_variant":[
        "Treilles",
        "Treille"
    ],
    "wof:name":"Treille",
    "wof:placetype":"locality"
},
  "geometry": {"coordinates":[0.33333,45.65],"type":"Point"}
}