{
  "type": "Feature",
  "properties": {
    "gn:admin1_code":"93",
    "gn:admin2_code":"83",
    "gn:admin3_code":"831",
    "gn:admin4_code":"83011",
    "gn:asciiname":"Les Condamines",
    "gn:country_code":"FR",
    "gn:dem":886,
    "gn:feature_class":"P",
    "gn:feature_code":"PPL",
    "gn:name":"Les Condamines",
    "gn:population":0,
    "gn:timezone":"Europe/Paris",
    "iso:country":"FR",
    "wof:name":"Les Condamines",
    "wof:placetype":"locality"
},
  "geometry": {"coordinates":[6.51184,43.65178],"type":"Point"}
}