{
  "type": "Feature",
  "properties": {
    "gn:admin1_code":"24",
    "gn:admin2_code":"18",
    "gn:admin3_code":"181",
    "gn:admin4_code":"18288",
    "gn:asciiname":"Chailleux",
    "gn:country_code":"FR",
    "gn:dem":180,
    "gn:feature_class":"P",
    "gn:feature_code":"PPL",
    "gn:name":"Chailleux",
    "gn:population":0,
    "gn:timezone":"Europe/Paris",
    "iso:country":"FR",
    "name:und_x_variant":[
        "Le Chailleux",
        "Chailleux"
    ],
    "wof:name":"Chailleux",
    "wof:placetype":"locality"
},
  "geometry": {"coordinates":[2.46093,46.93564],"type":"Point"}
}