{
  "type": "Feature",
  "properties": {
    "gn:admin1_code":"93",
    "gn:admin2_code":"05",
    "gn:admin3_code":"052",
    "gn:admin4_code":"05114",
    "gn:asciiname":"Le Villard",
    "gn:country_code":"FR",
    "gn:dem":1431,
    "gn:feature_class":"P",
    "gn:feature_code":"PPL",
    "gn:name":"Le Villard",
    "gn:population":0,
    "gn:timezone":"Europe/Paris",
    "iso:country":"FR",
    "name:und_x_variant":[
        "Le Villara",
        "Le Villard"
    ],
    "wof:name":"Le Villard",
    "wof:placetype":"locality"
},
  "geometry": {"coordinates":[6.34587,44.60067],"type":"Point"}
}