{
  "type": "Feature",
  "properties": {
    "gn:admin1_code":"24",
    "gn:admin2_code":"28",
    "gn:admin3_code":"282",
    "gn:admin4_code":"28398",
    "gn:asciiname":"La Haudotiere",
    "gn:country_code":"FR",
    "gn:dem":179,
    "gn:feature_class":"P",
    "gn:feature_code":"PPL",
    "gn:name":"La Haudoti\u00e8re",
    "gn:population":0,
    "gn:timezone":"Europe/Paris",
    "iso:country":"FR",
    "wof:name":"La Haudotiere",
    "wof:placetype":"locality"
},
  "geometry": {"coordinates":[1.10138,48.17066],"type":"Point"}
}