{
  "type": "Feature",
  "properties": {
    "gn:admin1_code":"84",
    "gn:admin2_code":"42",
    "gn:admin3_code":"421",
    "gn:admin4_code":"42251",
    "gn:asciiname":"Maigneu-le-Gabion",
    "gn:country_code":"FR",
    "gn:dem":351,
    "gn:feature_class":"P",
    "gn:feature_code":"PPL",
    "gn:name":"Maigneu-le-Gabion",
    "gn:population":0,
    "gn:timezone":"Europe/Paris",
    "iso:country":"FR",
    "name:und_x_variant":[
        "Maigneu",
        "Maigneux-le-Gabion",
        "Maigneu-le-Gabion"
    ],
    "wof:name":"Maigneu-le-Gabion",
    "wof:placetype":"locality"
},
  "geometry": {"coordinates":[4.25162,45.68452],"type":"Point"}
}