{
  "type": "Feature",
  "properties": {
    "gn:admin1_code":"52",
    "gn:admin2_code":"49",
    "gn:admin3_code":"492",
    "gn:admin4_code":"49260",
    "gn:asciiname":"La Terreliere",
    "gn:country_code":"FR",
    "gn:dem":113,
    "gn:feature_class":"P",
    "gn:feature_code":"PPL",
    "gn:name":"La Terreli\u00e8re",
    "gn:population":0,
    "gn:timezone":"Europe/Paris",
    "iso:country":"FR",
    "wof:name":"La Terreliere",
    "wof:placetype":"locality"
},
  "geometry": {"coordinates":[-1.01084,47.05286],"type":"Point"}
}