{
  "type": "Feature",
  "properties": {
    "gn:admin1_code":"75",
    "gn:admin2_code":"86",
    "gn:admin3_code":"863",
    "gn:admin4_code":"86293",
    "gn:asciiname":"Villepesant",
    "gn:country_code":"FR",
    "gn:dem":125,
    "gn:feature_class":"P",
    "gn:feature_code":"PPL",
    "gn:name":"Villepesant",
    "gn:population":0,
    "gn:timezone":"Europe/Paris",
    "iso:country":"FR",
    "wof:name":"Villepesant",
    "wof:placetype":"locality"
},
  "geometry": {"coordinates":[0.26975,46.3998],"type":"Point"}
}