{
  "type": "Feature",
  "properties": {
    "gn:admin1_code":"84",
    "gn:admin2_code":"69",
    "gn:admin3_code":"691",
    "gn:admin4_code":"69268",
    "gn:asciiname":"Les Sept Chemins",
    "gn:country_code":"FR",
    "gn:dem":205,
    "gn:feature_class":"P",
    "gn:feature_code":"PPL",
    "gn:name":"Les Sept Chemins",
    "gn:population":0,
    "gn:timezone":"Europe/Paris",
    "iso:country":"FR",
    "name:und_x_variant":[
        "Les 7 Chemins",
        "Les Sept Chemins"
    ],
    "wof:name":"Les Sept Chemins",
    "wof:placetype":"locality"
},
  "geometry": {"coordinates":[4.75164,45.65215],"type":"Point"}
}