{
  "type": "Feature",
  "properties": {
    "gn:admin1_code":"11",
    "gn:admin2_code":"91",
    "gn:admin3_code":"911",
    "gn:admin4_code":"91130",
    "gn:asciiname":"Le Veau",
    "gn:country_code":"FR",
    "gn:dem":102,
    "gn:feature_class":"P",
    "gn:feature_code":"PPL",
    "gn:name":"Le Veau",
    "gn:population":0,
    "gn:timezone":"Europe/Paris",
    "iso:country":"FR",
    "wof:name":"Le Veau",
    "wof:placetype":"locality"
},
  "geometry": {"coordinates":[2.05334,48.41441],"type":"Point"}
}