{
  "type": "Feature",
  "properties": {
    "gn:admin1_code":"84",
    "gn:admin2_code":"63",
    "gn:admin3_code":"632",
    "gn:admin4_code":"63040.0",
    "gn:asciiname":"Tinlhat",
    "gn:country_code":"FR",
    "gn:dem":397,
    "gn:feature_class":"P",
    "gn:feature_code":"PPL",
    "gn:name":"Tinlhat",
    "gn:population":0,
    "gn:timezone":"Europe/Paris",
    "iso:country":"FR",
    "name:und_x_variant":[
        "Tinlhalt",
        "Tinlhat"
    ],
    "wof:name":"Tinlhat",
    "wof:placetype":"locality"
},
  "geometry": {"coordinates":[3.30614,45.73181],"type":"Point"}
}