{
  "type": "Feature",
  "properties": {
    "gn:admin1_code":"93",
    "gn:admin2_code":"06",
    "gn:admin3_code":"062",
    "gn:admin4_code":"06075",
    "gn:asciiname":"Les Traverses",
    "gn:country_code":"FR",
    "gn:dem":500,
    "gn:feature_class":"P",
    "gn:feature_code":"PPL",
    "gn:name":"Les Traverses",
    "gn:population":0,
    "gn:timezone":"Europe/Paris",
    "iso:country":"FR",
    "wof:name":"Les Traverses",
    "wof:placetype":"locality"
},
  "geometry": {"coordinates":[7.22939,43.85661],"type":"Point"}
}