{
  "type": "Feature",
  "properties": {
    "iso:country":"FR",
    "name:fra_x_preferred":[
        "Baille"
    ],
    "name:nld_x_preferred":[
        "Baille"
    ],
    "wof:name":"Baille",
    "wof:placetype":"neighbourhood"
},
  "geometry": {"coordinates":[5.39906246894056,43.28854712281379],"type":"Point"}
}