{
  "type": "Feature",
  "properties": {
    "gn:admin1_code":"84",
    "gn:admin2_code":"43",
    "gn:admin3_code":"433",
    "gn:admin4_code":"43204",
    "gn:asciiname":"Souvignet",
    "gn:country_code":"FR",
    "gn:dem":987,
    "gn:feature_class":"P",
    "gn:feature_code":"PPL",
    "gn:name":"Souvignet",
    "gn:population":0,
    "gn:timezone":"Europe/Paris",
    "iso:country":"FR",
    "wof:name":"Souvignet",
    "wof:placetype":"locality"
},
  "geometry": {"coordinates":[4.40582,45.18224],"type":"Point"}
}