{
  "type": "Feature",
  "properties": {
    "gn:admin1_code":"75",
    "gn:admin2_code":"23",
    "gn:admin3_code":"232",
    "gn:admin4_code":"23193",
    "gn:asciiname":"Charsat",
    "gn:country_code":"FR",
    "gn:dem":396,
    "gn:feature_class":"P",
    "gn:feature_code":"PPL",
    "gn:name":"Charsat",
    "gn:population":0,
    "gn:timezone":"Europe/Paris",
    "iso:country":"FR",
    "wof:name":"Charsat",
    "wof:placetype":"locality"
},
  "geometry": {"coordinates":[1.90111,46.17465],"type":"Point"}
}