{
  "type": "Feature",
  "properties": {
    "gn:admin1_code":"28",
    "gn:admin2_code":"76",
    "gn:admin3_code":"761",
    "gn:admin4_code":"76703",
    "gn:asciiname":"Touffreville-sur-Eu",
    "gn:country_code":"FR",
    "gn:dem":14,
    "gn:feature_class":"P",
    "gn:feature_code":"PPL",
    "gn:name":"Touffreville-sur-Eu",
    "gn:population":0,
    "gn:timezone":"Europe/Paris",
    "iso:country":"FR",
    "name:und_x_variant":[
        "Touffreville",
        "Touffreville-sur-Eu"
    ],
    "wof:name":"Touffreville-sur-Eu",
    "wof:placetype":"locality"
},
  "geometry": {"coordinates":[1.32461,50.00135],"type":"Point"}
}