{
  "type": "Feature",
  "properties": {
    "gn:admin1_code":"28",
    "gn:admin2_code":"76",
    "gn:admin3_code":"761",
    "gn:admin4_code":"76703",
    "gn:asciiname":"Touffreville-sur-Eu",
    "gn:country_code":"FR",
    "gn:dem":14,
    "gn:feature_class":"P",
    "gn:feature_code":"PPL",
    "gn:name":"Touffreville-sur-Eu",
    "gn:population":0,
    "gn:timezone":"Europe/Paris",
    "iso:country":"FR",
    "name:cat_x_preferred":[
        "Touffreville-sur-Eu"
    ],
    "name:ceb_x_preferred":[
        "Touffreville-sur-Eu"
    ],
    "name:deu_x_preferred":[
        "Touffreville-sur-Eu"
    ],
    "name:eus_x_preferred":[
        "Touffreville-sur-Eu"
    ],
    "name:fra_x_preferred":[
        "Touffreville-sur-Eu"
    ],
    "name:hun_x_preferred":[
        "Touffreville-sur-Eu"
    ],
    "name:ita_x_preferred":[
        "Touffreville-sur-Eu"
    ],
    "name:kaz_x_preferred":[
        "\u0422\u0443\u0444\u0444\u0440\u0435\u0432\u0438\u043b\u044c-\u0441\u044e\u0440-\u0415"
    ],
    "name:lat_x_preferred":[
        "Touffreville-sur-Eu"
    ],
    "name:msa_x_preferred":[
        "Touffreville-sur-Eu"
    ],
    "name:nld_x_preferred":[
        "Touffreville-sur-Eu"
    ],
    "name:oci_x_preferred":[
        "Touffreville-sur-Eu"
    ],
    "name:pms_x_preferred":[
        "Touffreville-sur-Eu"
    ],
    "name:pol_x_preferred":[
        "Touffreville-sur-Eu"
    ],
    "name:por_x_preferred":[
        "Touffreville-sur-Eu"
    ],
    "name:ron_x_preferred":[
        "Touffreville-sur-Eu"
    ],
    "name:slk_x_preferred":[
        "Touffreville-sur-Eu"
    ],
    "name:spa_x_preferred":[
        "Touffreville-sur-Eu"
    ],
    "name:swe_x_preferred":[
        "Touffreville-sur-Eu"
    ],
    "name:ukr_x_preferred":[
        "\u0422\u0443\u0444\u0444\u0440\u0435\u0432\u0456\u043b\u044c-\u0441\u044e\u0440-\u0415"
    ],
    "name:und_x_variant":[
        "Touffreville",
        "Touffreville-sur-Eu"
    ],
    "name:vie_x_preferred":[
        "Touffreville-sur-Eu"
    ],
    "name:vol_x_preferred":[
        "Touffreville-sur-Eu"
    ],
    "name:war_x_preferred":[
        "Touffreville-sur-Eu"
    ],
    "wof:name":"Touffreville-sur-Eu",
    "wof:placetype":"locality"
},
  "geometry": {"coordinates":[1.32461,50.00135],"type":"Point"}
}