{
  "type": "Feature",
  "properties": {
    "gn:admin1_code":"75",
    "gn:admin2_code":"17",
    "gn:admin3_code":"174",
    "gn:admin4_code":"17248",
    "gn:asciiname":"La Rive",
    "gn:country_code":"FR",
    "gn:dem":3,
    "gn:feature_class":"P",
    "gn:feature_code":"PPL",
    "gn:name":"La Rive",
    "gn:population":0,
    "gn:timezone":"Europe/Paris",
    "iso:country":"FR",
    "wof:name":"La Rive",
    "wof:placetype":"locality"
},
  "geometry": {"coordinates":[-0.79374,45.47733],"type":"Point"}
}