{
  "type": "Feature",
  "properties": {
    "gn:admin1_code":"53",
    "gn:admin2_code":"22",
    "gn:admin3_code":"223",
    "gn:admin4_code":"22034",
    "gn:asciiname":"Kerstephan",
    "gn:country_code":"FR",
    "gn:dem":74,
    "gn:feature_class":"P",
    "gn:feature_code":"PPL",
    "gn:name":"Kerst\u00e9phan",
    "gn:population":0,
    "gn:timezone":"Europe/Paris",
    "iso:country":"FR",
    "wof:name":"Kerstephan",
    "wof:placetype":"locality"
},
  "geometry": {"coordinates":[-3.37439,48.68689000000001],"type":"Point"}
}