{
  "type": "Feature",
  "properties": {
    "gn:admin1_code":"84",
    "gn:admin2_code":"43",
    "gn:admin3_code":"432",
    "gn:admin4_code":"43201",
    "gn:asciiname":"Saint-Julien-d'Ance",
    "gn:country_code":"FR",
    "gn:dem":771,
    "gn:feature_class":"P",
    "gn:feature_code":"PPL",
    "gn:name":"Saint-Julien-d\u2019Ance",
    "gn:population":0,
    "gn:timezone":"Europe/Paris",
    "iso:country":"FR",
    "name:bug_x_preferred":[
        "Saint-Julien-d'Ance"
    ],
    "name:ceb_x_preferred":[
        "Saint-Julien-d'Ance"
    ],
    "name:deu_x_preferred":[
        "Saint-Julien-d\u2019Ance"
    ],
    "name:eus_x_preferred":[
        "Saint-Julien-d'Ance"
    ],
    "name:fra_x_preferred":[
        "Saint-Julien-d'Ance"
    ],
    "name:hun_x_preferred":[
        "Saint-Julien-d\u2019Ance"
    ],
    "name:ind_x_preferred":[
        "Saint-Julien-d'Ance"
    ],
    "name:ita_x_preferred":[
        "Saint-Julien-d'Ance"
    ],
    "name:kaz_x_preferred":[
        "\u0421\u0435\u043d-\u0416\u0443\u043b\u044c\u0435\u043d-\u0434'\u0410\u043d\u0441"
    ],
    "name:lat_x_preferred":[
        "Saint-Julien-d'Ance"
    ],
    "name:ltz_x_preferred":[
        "Saint-Julien-d'Ance"
    ],
    "name:msa_x_preferred":[
        "Saint-Julien-d'Ance"
    ],
    "name:nld_x_preferred":[
        "Saint-Julien-d'Ance"
    ],
    "name:pms_x_preferred":[
        "Saint-Julien-d'Ance"
    ],
    "name:pol_x_preferred":[
        "Saint-Julien-d\u2019Ance"
    ],
    "name:por_x_preferred":[
        "Saint-Julien-d'Ance"
    ],
    "name:ron_x_preferred":[
        "Saint-Julien-d'Ance"
    ],
    "name:slk_x_preferred":[
        "Saint-Julien-d\u2019Ance"
    ],
    "name:spa_x_preferred":[
        "Saint-Julien-d'Ance"
    ],
    "name:swe_x_preferred":[
        "Saint-Julien-d'Ance"
    ],
    "name:ukr_x_preferred":[
        "\u0421\u0435\u043d-\u0416\u0443\u043b\u044c\u0454\u043d-\u0434'\u0410\u043d\u0441"
    ],
    "name:und_x_variant":[
        "Saint Julien",
        "Saint-Julien-d\u2019Ance"
    ],
    "name:urd_x_preferred":[
        "\u0633\u06cc\u0646\u0679-\u062c\u0644\u06cc\u06ba -\u062f\u0646\u06a9\u06d2"
    ],
    "name:uzb_x_preferred":[
        "Saint-Julien-d'Ance"
    ],
    "name:vie_x_preferred":[
        "Saint-Julien-d'Ance"
    ],
    "name:vol_x_preferred":[
        "Saint-Julien-d'Ance"
    ],
    "name:war_x_preferred":[
        "Saint-Julien-d'Ance"
    ],
    "name:zho_x_preferred":[
        "\u5723\u6731\u5229\u5b89\u5f53\u65af"
    ],
    "wof:name":"Saint-Julien-d'Ance",
    "wof:placetype":"locality"
},
  "geometry": {"coordinates":[3.91317,45.30384],"type":"Point"}
}