{
  "type": "Feature",
  "properties": {
    "gn:admin1_code":"84",
    "gn:admin2_code":"74",
    "gn:admin3_code":"743",
    "gn:admin4_code":"74029",
    "gn:asciiname":"Les Metral",
    "gn:country_code":"FR",
    "gn:dem":400,
    "gn:feature_class":"P",
    "gn:feature_code":"PPL",
    "gn:name":"Les M\u00e9tral",
    "gn:population":0,
    "gn:timezone":"Europe/Paris",
    "iso:country":"FR",
    "wof:name":"Les Metral",
    "wof:placetype":"locality"
},
  "geometry": {"coordinates":[5.82032,45.99805],"type":"Point"}
}