{
  "type": "Feature",
  "properties": {
    "gn:admin1_code":"44",
    "gn:admin2_code":"51",
    "gn:admin3_code":"512",
    "gn:admin4_code":"51243",
    "gn:asciiname":"Fresnay",
    "gn:country_code":"FR",
    "gn:dem":88,
    "gn:feature_class":"P",
    "gn:feature_code":"PPL",
    "gn:name":"Fresnay",
    "gn:population":0,
    "gn:timezone":"Europe/Paris",
    "iso:country":"FR",
    "name:cat_x_preferred":[
        "Fresnay"
    ],
    "name:ceb_x_preferred":[
        "Fresnay"
    ],
    "name:eus_x_preferred":[
        "Fresnay"
    ],
    "name:fra_x_preferred":[
        "Fresnay"
    ],
    "name:hun_x_preferred":[
        "Fresnay"
    ],
    "name:hye_x_preferred":[
        "\u0556\u0580\u0565\u0576\u0565"
    ],
    "name:ita_x_preferred":[
        "Fresnay"
    ],
    "name:jpn_x_preferred":[
        "\u30d5\u30ec\u30cd\u30a4"
    ],
    "name:lat_x_preferred":[
        "Fresnay"
    ],
    "name:msa_x_preferred":[
        "Fresnay"
    ],
    "name:nld_x_preferred":[
        "Fresnay"
    ],
    "name:oci_x_preferred":[
        "Fresnay"
    ],
    "name:pms_x_preferred":[
        "Fresnay"
    ],
    "name:pol_x_preferred":[
        "Fresnay"
    ],
    "name:por_x_preferred":[
        "Fresnay"
    ],
    "name:ron_x_preferred":[
        "Fresnay"
    ],
    "name:rus_x_preferred":[
        "\u0424\u0440\u0435\u043d\u0435"
    ],
    "name:slk_x_preferred":[
        "Fresnay"
    ],
    "name:spa_x_preferred":[
        "Fresnay"
    ],
    "name:swe_x_preferred":[
        "Fresnay"
    ],
    "name:ukr_x_preferred":[
        "\u0424\u0440\u0435\u043d\u0435"
    ],
    "name:vie_x_preferred":[
        "Fresnay"
    ],
    "name:vol_x_preferred":[
        "Fresnay"
    ],
    "name:war_x_preferred":[
        "Fresnay"
    ],
    "name:zho_x_preferred":[
        "\u5f17\u96f7\u65af\u5948"
    ],
    "wof:name":"Fresnay",
    "wof:placetype":"locality"
},
  "geometry": {"coordinates":[3.93302,48.65719],"type":"Point"}
}