{
  "type": "Feature",
  "properties": {
    "gn:admin1_code":"44",
    "gn:admin2_code":"51",
    "gn:admin3_code":"512",
    "gn:admin4_code":"51243",
    "gn:asciiname":"Fresnay",
    "gn:country_code":"FR",
    "gn:dem":88,
    "gn:feature_class":"P",
    "gn:feature_code":"PPL",
    "gn:name":"Fresnay",
    "gn:population":0,
    "gn:timezone":"Europe/Paris",
    "iso:country":"FR",
    "wof:name":"Fresnay",
    "wof:placetype":"locality"
},
  "geometry": {"coordinates":[3.93302,48.65719],"type":"Point"}
}