{
  "type": "Feature",
  "properties": {
    "gn:admin1_code":"84",
    "gn:admin2_code":"38",
    "gn:admin3_code":"382",
    "gn:admin4_code":"38065",
    "gn:asciiname":"Le Lac",
    "gn:country_code":"FR",
    "gn:dem":513,
    "gn:feature_class":"P",
    "gn:feature_code":"PPL",
    "gn:name":"Le Lac",
    "gn:population":0,
    "gn:timezone":"Europe/Paris",
    "iso:country":"FR",
    "name:ceb_x_preferred":[
        "Le Lac"
    ],
    "name:fra_x_preferred":[
        "Le Lac"
    ],
    "name:swe_x_preferred":[
        "Le Lac"
    ],
    "name:und_x_variant":[
        "Lac"
    ],
    "wof:name":"Le Lac",
    "wof:placetype":"locality"
},
  "geometry": {"coordinates":[5.41539,45.43031],"type":"Point"}
}