{
  "type": "Feature",
  "properties": {
    "iso:country":"FR",
    "name:eng_x_preferred":[
        "Saint-Roman-de-Bellet"
    ],
    "name:fra_x_preferred":[
        "Saint-Roman-de-Bellet"
    ],
    "name:fra_x_variant":[
        "Saint-Roman"
    ],
    "wof:name":"Saint-Roman-de-Bellet",
    "wof:placetype":"neighbourhood"
},
  "geometry": {"coordinates":[7.21106846062897,43.74313105111965],"type":"Point"}
}