{
  "type": "Feature",
  "properties": {
    "gn:admin1_code":"84",
    "gn:admin2_code":"26",
    "gn:admin3_code":"263",
    "gn:admin4_code":"26207",
    "gn:asciiname":"Chamelin",
    "gn:country_code":"FR",
    "gn:dem":332,
    "gn:feature_class":"P",
    "gn:feature_code":"PPL",
    "gn:name":"Chamelin",
    "gn:population":0,
    "gn:timezone":"Europe/Paris",
    "iso:country":"FR",
    "wof:name":"Chamelin",
    "wof:placetype":"locality"
},
  "geometry": {"coordinates":[5.18333,45.15],"type":"Point"}
}