{
  "type": "Feature",
  "properties": {
    "gn:admin1_code":"75",
    "gn:admin2_code":"19",
    "gn:admin3_code":"192",
    "gn:admin4_code":"19073",
    "gn:asciiname":"Le Bouchard",
    "gn:country_code":"FR",
    "gn:dem":601,
    "gn:feature_class":"P",
    "gn:feature_code":"PPL",
    "gn:name":"Le Bouchard",
    "gn:population":0,
    "gn:timezone":"Europe/Paris",
    "iso:country":"FR",
    "wof:name":"Le Bouchard",
    "wof:placetype":"locality"
},
  "geometry": {"coordinates":[2.06214,45.4098],"type":"Point"}
}