{
  "type": "Feature",
  "properties": {
    "gn:admin1_code":"84",
    "gn:admin2_code":"38",
    "gn:admin3_code":"381",
    "gn:admin4_code":"38436",
    "gn:asciiname":"Meinget",
    "gn:country_code":"FR",
    "gn:dem":322,
    "gn:feature_class":"P",
    "gn:feature_code":"PPL",
    "gn:name":"Meinget",
    "gn:population":0,
    "gn:timezone":"Europe/Paris",
    "iso:country":"FR",
    "wof:name":"Meinget",
    "wof:placetype":"locality"
},
  "geometry": {"coordinates":[5.65946,45.07938],"type":"Point"}
}