{
  "type": "Feature",
  "properties": {
    "gn:admin1_code":"84",
    "gn:admin2_code":"15",
    "gn:admin3_code":"151",
    "gn:admin4_code":"15113",
    "gn:asciiname":"Saint-Julien-de-Jordanne",
    "gn:country_code":"FR",
    "gn:dem":895,
    "gn:feature_class":"P",
    "gn:feature_code":"PPL",
    "gn:name":"Saint-Julien-de-Jordanne",
    "gn:population":0,
    "gn:timezone":"Europe/Paris",
    "iso:country":"FR",
    "name:und_x_variant":[
        "Saint-Julien",
        "Saint-Julien-de-Jordanne"
    ],
    "wof:name":"Saint-Julien-de-Jordanne",
    "wof:placetype":"locality"
},
  "geometry": {"coordinates":[2.63785,45.06302],"type":"Point"}
}