{
  "type": "Feature",
  "properties": {
    "gn:admin1_code":"24",
    "gn:admin2_code":"36",
    "gn:admin3_code":"363",
    "gn:admin4_code":"36186.0",
    "gn:asciiname":"Bouchenoire",
    "gn:country_code":"FR",
    "gn:dem":240,
    "gn:feature_class":"P",
    "gn:feature_code":"PPL",
    "gn:name":"Bouchenoire",
    "gn:population":0,
    "gn:timezone":"Europe/Paris",
    "iso:country":"FR",
    "wof:name":"Bouchenoire",
    "wof:placetype":"locality"
},
  "geometry": {"coordinates":[2.10924,46.65343],"type":"Point"}
}