{
  "type": "Feature",
  "properties": {
    "gn:admin1_code":"24",
    "gn:admin2_code":"18",
    "gn:admin3_code":"181",
    "gn:admin4_code":"18286",
    "gn:asciiname":"Villers",
    "gn:country_code":"FR",
    "gn:dem":178,
    "gn:feature_class":"P",
    "gn:feature_code":"PPL",
    "gn:name":"Villers",
    "gn:population":0,
    "gn:timezone":"Europe/Paris",
    "iso:country":"FR",
    "name:bre_x_preferred":[
        "Villers"
    ],
    "name:ceb_x_preferred":[
        "Villers"
    ],
    "name:deu_x_preferred":[
        "Villers"
    ],
    "name:fra_x_preferred":[
        "Villers"
    ],
    "name:ita_x_preferred":[
        "Villers"
    ],
    "name:nds_x_preferred":[
        "Villers"
    ],
    "name:nld_x_preferred":[
        "Villers"
    ],
    "name:pol_x_preferred":[
        "Villers"
    ],
    "name:por_x_preferred":[
        "Villers"
    ],
    "name:rus_x_preferred":[
        "\u0412\u0438\u043b\u043b\u0435\u0440"
    ],
    "name:slk_x_preferred":[
        "Villers"
    ],
    "name:spa_x_preferred":[
        "Villers"
    ],
    "name:swe_x_preferred":[
        "Villers"
    ],
    "name:ukr_x_preferred":[
        "\u0412\u0456\u043b\u043b\u0435\u0440"
    ],
    "wof:name":"Villers",
    "wof:placetype":"locality"
},
  "geometry": {"coordinates":[2.82163,47.09028],"type":"Point"}
}