{
  "type": "Feature",
  "properties": {
    "gn:admin1_code":"75",
    "gn:admin2_code":"87",
    "gn:admin3_code":"872",
    "gn:admin4_code":"87002",
    "gn:asciiname":"Le Vieux",
    "gn:country_code":"FR",
    "gn:dem":433,
    "gn:feature_class":"P",
    "gn:feature_code":"PPL",
    "gn:name":"Le Vieux",
    "gn:population":0,
    "gn:timezone":"Europe/Paris",
    "iso:country":"FR",
    "name:und_x_variant":[
        "Vieux",
        "Le Vieux"
    ],
    "wof:name":"Le Vieux",
    "wof:placetype":"locality"
},
  "geometry": {"coordinates":[1.41396,45.98874],"type":"Point"}
}