{
  "type": "Feature",
  "properties": {
    "iso:country":"FR",
    "name:eng_x_preferred":[
        "Zone d'Activite Nord"
    ],
    "name:fra_x_preferred":[
        "Zone d'Activit\u00e9 Nord"
    ],
    "wof:name":"Zone d'Activite Nord",
    "wof:placetype":"neighbourhood"
},
  "geometry": {"coordinates":[-1.68502379301256,48.13188322684729],"type":"Point"}
}