{
  "type": "Feature",
  "properties": {
    "gn:admin1_code":"75",
    "gn:admin2_code":"47",
    "gn:admin3_code":"472",
    "gn:admin4_code":"47112",
    "gn:asciiname":"Saint-Gayrand",
    "gn:country_code":"FR",
    "gn:dem":165,
    "gn:feature_class":"P",
    "gn:feature_code":"PPL",
    "gn:name":"Saint-Gayrand",
    "gn:population":0,
    "gn:timezone":"Europe/Paris",
    "iso:country":"FR",
    "wof:name":"Saint-Gayrand",
    "wof:placetype":"locality"
},
  "geometry": {"coordinates":[0.39611,44.40232],"type":"Point"}
}