{
  "type": "Feature",
  "properties": {
    "gn:admin1_code":"76",
    "gn:admin2_code":"30",
    "gn:admin3_code":"301",
    "gn:admin4_code":"30216",
    "gn:asciiname":"Le Buis",
    "gn:country_code":"FR",
    "gn:dem":168,
    "gn:feature_class":"P",
    "gn:feature_code":"PPL",
    "gn:name":"Le Buis",
    "gn:population":0,
    "gn:timezone":"Europe/Paris",
    "iso:country":"FR",
    "name:cat_x_preferred":[
        "Lo Bois"
    ],
    "name:ceb_x_preferred":[
        "Le Buis"
    ],
    "name:deu_x_preferred":[
        "Le Buis"
    ],
    "name:epo_x_preferred":[
        "Le Buis"
    ],
    "name:eus_x_preferred":[
        "Le Buis"
    ],
    "name:fra_x_preferred":[
        "Le Buis"
    ],
    "name:hun_x_preferred":[
        "Le Buis"
    ],
    "name:ind_x_preferred":[
        "Le Buis"
    ],
    "name:ita_x_preferred":[
        "Le Buis"
    ],
    "name:kaz_x_preferred":[
        "\u041b\u0435-\u0411\u044e\u0438"
    ],
    "name:lat_x_preferred":[
        "Le Buis"
    ],
    "name:mlg_x_preferred":[
        "Le Buis"
    ],
    "name:msa_x_preferred":[
        "Le Buis"
    ],
    "name:nld_x_preferred":[
        "Le Buis"
    ],
    "name:oci_x_preferred":[
        "Lu Bois"
    ],
    "name:pms_x_preferred":[
        "Le Buis"
    ],
    "name:pol_x_preferred":[
        "Le Buis"
    ],
    "name:por_x_preferred":[
        "Le Buis"
    ],
    "name:ron_x_preferred":[
        "Le Buis"
    ],
    "name:slk_x_preferred":[
        "Le Buis"
    ],
    "name:spa_x_preferred":[
        "Le Buis"
    ],
    "name:srp_x_preferred":[
        "\u0411\u0438"
    ],
    "name:swe_x_preferred":[
        "Le Buis"
    ],
    "name:szl_x_preferred":[
        "Le Buis"
    ],
    "name:ukr_x_preferred":[
        "\u041b\u0435-\u0411\u044e\u0457"
    ],
    "name:uzb_x_preferred":[
        "Le Buis"
    ],
    "name:vie_x_preferred":[
        "Le Buis"
    ],
    "name:vol_x_preferred":[
        "Le Buis"
    ],
    "name:war_x_preferred":[
        "Le Buis"
    ],
    "name:zho_x_preferred":[
        "\u52d2\u6bd4\u4f0a"
    ],
    "wof:name":"Le Buis",
    "wof:placetype":"locality"
},
  "geometry": {"coordinates":[4.12007,44.2812],"type":"Point"}
}