{
  "type": "Feature",
  "properties": {
    "gn:admin1_code":"75",
    "gn:admin2_code":"23",
    "gn:admin3_code":"231",
    "gn:admin4_code":"23220",
    "gn:asciiname":"Le Monteil Rebillon",
    "gn:country_code":"FR",
    "gn:dem":563,
    "gn:feature_class":"P",
    "gn:feature_code":"PPLF",
    "gn:name":"Le Monteil R\u00e9billon",
    "gn:population":0,
    "gn:timezone":"Europe/Paris",
    "iso:country":"FR",
    "wof:name":"Le Monteil Rebillon",
    "wof:placetype":"locality"
},
  "geometry": {"coordinates":[2.19157,46.02896],"type":"Point"}
}