{
  "type": "Feature",
  "properties": {
    "gn:admin1_code":"53",
    "gn:admin2_code":"29",
    "gn:admin3_code":"294",
    "gn:admin4_code":"29002",
    "gn:asciiname":"La Villeneuve",
    "gn:country_code":"FR",
    "gn:dem":78,
    "gn:feature_class":"P",
    "gn:feature_code":"PPL",
    "gn:name":"La Villeneuve",
    "gn:population":0,
    "gn:timezone":"Europe/Paris",
    "iso:country":"FR",
    "wof:name":"La Villeneuve",
    "wof:placetype":"locality"
},
  "geometry": {"coordinates":[-3.43253,47.92269],"type":"Point"}
}