{
  "type": "Feature",
  "properties": {
    "gn:admin1_code":"52",
    "gn:admin2_code":"44",
    "gn:admin3_code":"442",
    "gn:admin4_code":"44026",
    "gn:asciiname":"La petorie",
    "gn:country_code":"FR",
    "gn:dem":66,
    "gn:elevation":"73.0",
    "gn:feature_class":"P",
    "gn:feature_code":"PPL",
    "gn:name":"La p\u00e8torie",
    "gn:population":0,
    "gn:timezone":"Europe/Paris",
    "iso:country":"FR",
    "wof:name":"La petorie",
    "wof:placetype":"locality"
},
  "geometry": {"coordinates":[-1.42623,47.30644],"type":"Point"}
}