{
  "type": "Feature",
  "properties": {
    "gn:admin1_code":"93",
    "gn:admin2_code":"83",
    "gn:admin3_code":"831",
    "gn:admin4_code":"83068",
    "gn:asciiname":"L'Avelan",
    "gn:country_code":"FR",
    "gn:dem":53,
    "gn:feature_class":"P",
    "gn:feature_code":"PPL",
    "gn:name":"L\u2019Avelan",
    "gn:population":0,
    "gn:timezone":"Europe/Paris",
    "iso:country":"FR",
    "wof:name":"L'Avelan",
    "wof:placetype":"locality"
},
  "geometry": {"coordinates":[6.55,43.28333],"type":"Point"}
}