{
  "type": "Feature",
  "properties": {
    "gn:admin1_code":"75",
    "gn:admin2_code":"87",
    "gn:admin3_code":"873",
    "gn:admin4_code":"87034",
    "gn:asciiname":"Le Mazet",
    "gn:country_code":"FR",
    "gn:dem":320,
    "gn:feature_class":"P",
    "gn:feature_code":"PPL",
    "gn:name":"Le Mazet",
    "gn:population":0,
    "gn:timezone":"Europe/Paris",
    "iso:country":"FR",
    "wof:name":"Le Mazet",
    "wof:placetype":"locality"
},
  "geometry": {"coordinates":[0.93197,45.7282],"type":"Point"}
}