{
  "type": "Feature",
  "properties": {
    "gn:admin1_code":"84",
    "gn:admin2_code":"07",
    "gn:admin3_code":"073",
    "gn:admin4_code":"07085",
    "gn:asciiname":"Le Mont",
    "gn:country_code":"FR",
    "gn:dem":581,
    "gn:feature_class":"P",
    "gn:feature_code":"PPL",
    "gn:name":"Le Mont",
    "gn:population":0,
    "gn:timezone":"Europe/Paris",
    "iso:country":"FR",
    "name:deu_x_preferred":[
        "Le Mont"
    ],
    "name:epo_x_preferred":[
        "Le Mont"
    ],
    "name:fra_x_preferred":[
        "Le Mont"
    ],
    "name:ita_x_preferred":[
        "Le Mont"
    ],
    "name:nld_x_preferred":[
        "Le Mont"
    ],
    "name:por_x_preferred":[
        "Le Mont"
    ],
    "name:spa_x_preferred":[
        "Le Mont"
    ],
    "name:swe_x_preferred":[
        "Le Mont"
    ],
    "wof:name":"Le Mont",
    "wof:placetype":"locality"
},
  "geometry": {"coordinates":[4.58333,45.03333],"type":"Point"}
}