{
  "type": "Feature",
  "properties": {
    "frgov:code_epci":"200069128",
    "frgov:insee_arr":"2",
    "frgov:insee_com":"48081",
    "frgov:insee_dep":"48",
    "frgov:insee_reg":"76",
    "frgov:nom_com":"Lanu\u00e9jols",
    "frgov:nom_com_m":"LANUEJOLS",
    "frgov:nom_dep":"LOZERE",
    "frgov:nom_reg":"OCCITANIE",
    "frgov:statut":"Commune simple",
    "gn:admin1_code":"76",
    "gn:admin2_code":"48",
    "gn:admin3_code":"482",
    "gn:admin4_code":"48081",
    "gn:asciiname":"Lanuejols",
    "gn:country_code":"FR",
    "gn:dem":852,
    "gn:feature_class":"P",
    "gn:feature_code":"PPL",
    "gn:name":"Lanu\u00e9jols",
    "gn:population":0,
    "gn:timezone":"Europe/Paris",
    "iso:country":"FR",
    "name:fra_x_preferred":[
        "Lanu\u00e9jols"
    ],
    "name:und_x_variant":[
        "Lanu\u00e9jols"
    ],
    "qs:a0":"France",
    "qs:a1":"LOZERE",
    "qs:a1_lc":"48",
    "qs:a1r":"LANGUEDOC-ROUSSILLON",
    "qs:a1r_lc":"91",
    "qs:a2_lc":"25",
    "qs:a2r_lc":"2",
    "qs:adm0":"France",
    "qs:adm0_a3":"FRA",
    "qs:la":"LANUEJOLS",
    "qs:la_lc":"48081",
    "qs:level":"localadmin",
    "qs:type":"Commune simple",
    "wof:coterminous":[
        404382837
    ],
    "wof:name":"Lanuejols",
    "wof:placetype":"locality",
    "wof:placetype_local":"Commune simple"
},
  "geometry": {"coordinates":[3.57296,44.50068],"type":"Point"}
}