{
  "type": "Feature",
  "properties": {
    "gn:admin1_code":"76",
    "gn:admin2_code":"48",
    "gn:admin3_code":"482",
    "gn:admin4_code":"48081",
    "gn:asciiname":"Lanuejols",
    "gn:country_code":"FR",
    "gn:dem":852,
    "gn:feature_class":"P",
    "gn:feature_code":"PPL",
    "gn:name":"Lanu\u00e9jols",
    "gn:population":0,
    "gn:timezone":"Europe/Paris",
    "iso:country":"FR",
    "name:und_x_variant":[
        "Lanu\u00e9jols"
    ],
    "wof:name":"Lanuejols",
    "wof:placetype":"locality"
},
  "geometry": {"coordinates":[3.57296,44.50068],"type":"Point"}
}