{
  "type": "Feature",
  "properties": {
    "gn:admin1_code":"76",
    "gn:admin2_code":"12",
    "gn:admin3_code":"122",
    "gn:admin4_code":"12056",
    "gn:asciiname":"La Borie",
    "gn:cc2":"FR",
    "gn:country_code":"FR",
    "gn:dem":688,
    "gn:feature_class":"P",
    "gn:feature_code":"PPL",
    "gn:name":"La Borie",
    "gn:population":0,
    "gn:timezone":"Europe/Paris",
    "iso:country":"FR",
    "name:und_x_variant":[
        "La Borie-Noble",
        "La Borie"
    ],
    "wof:name":"La Borie",
    "wof:placetype":"locality"
},
  "geometry": {"coordinates":[2.48333,44.31667],"type":"Point"}
}