{
  "type": "Feature",
  "properties": {
    "gn:admin1_code":"84",
    "gn:admin2_code":"38",
    "gn:admin3_code":"382",
    "gn:admin4_code":"38434",
    "gn:asciiname":"Brennier",
    "gn:country_code":"FR",
    "gn:dem":404,
    "gn:feature_class":"P",
    "gn:feature_code":"PPL",
    "gn:name":"Brennier",
    "gn:population":0,
    "gn:timezone":"Europe/Paris",
    "iso:country":"FR",
    "name:und_x_variant":[
        "Brenier",
        "Brennier"
    ],
    "wof:name":"Brennier",
    "wof:placetype":"locality"
},
  "geometry": {"coordinates":[5.52425,45.51099],"type":"Point"}
}