{
  "type": "Feature",
  "properties": {
    "gn:admin1_code":"84",
    "gn:admin2_code":"07",
    "gn:admin3_code":"073",
    "gn:admin4_code":"07039",
    "gn:asciiname":"Bosas",
    "gn:country_code":"FR",
    "gn:dem":547,
    "gn:feature_class":"P",
    "gn:feature_code":"PPL",
    "gn:name":"Bosas",
    "gn:population":0,
    "gn:timezone":"Europe/Paris",
    "iso:country":"FR",
    "wof:name":"Bosas",
    "wof:placetype":"locality"
},
  "geometry": {"coordinates":[4.65055,45.05535],"type":"Point"}
}