{
  "type": "Feature",
  "properties": {
    "gn:admin1_code":"75",
    "gn:admin2_code":"23",
    "gn:admin3_code":"232",
    "gn:admin4_code":"23039",
    "gn:asciiname":"Puy-Manteau",
    "gn:country_code":"FR",
    "gn:dem":307,
    "gn:feature_class":"P",
    "gn:feature_code":"PPL",
    "gn:name":"Puy-Manteau",
    "gn:population":0,
    "gn:timezone":"Europe/Paris",
    "iso:country":"FR",
    "wof:name":"Puy-Manteau",
    "wof:placetype":"locality"
},
  "geometry": {"coordinates":[1.76667,46.33333],"type":"Point"}
}