{
  "type": "Feature",
  "properties": {
    "gn:admin1_code":"52",
    "gn:admin2_code":"44",
    "gn:admin3_code":"441",
    "gn:admin4_code":"44086",
    "gn:asciiname":"La Chaussee",
    "gn:country_code":"FR",
    "gn:dem":59,
    "gn:feature_class":"P",
    "gn:feature_code":"PPL",
    "gn:name":"La Chauss\u00e9e",
    "gn:population":0,
    "gn:timezone":"Europe/Paris",
    "iso:country":"FR",
    "wof:name":"La Chaussee",
    "wof:placetype":"locality"
},
  "geometry": {"coordinates":[-1.596,47.67162],"type":"Point"}
}