{
  "type": "Feature",
  "properties": {
    "gn:admin1_code":"24",
    "gn:admin2_code":"18",
    "gn:admin3_code":"181",
    "gn:admin4_code":"18092",
    "gn:asciiname":"Bel-Air",
    "gn:country_code":"FR",
    "gn:dem":164,
    "gn:feature_class":"P",
    "gn:feature_code":"PPL",
    "gn:name":"Bel-Air",
    "gn:population":0,
    "gn:timezone":"Europe/Paris",
    "iso:country":"FR",
    "wof:name":"Bel-Air",
    "wof:placetype":"locality"
},
  "geometry": {"coordinates":[2.63333,47.07629],"type":"Point"}
}