{
  "type": "Feature",
  "properties": {
    "gn:admin1_code":"44",
    "gn:admin2_code":"52",
    "gn:admin3_code":"523",
    "gn:admin4_code":"52331",
    "gn:asciiname":"La Bouverie",
    "gn:country_code":"FR",
    "gn:dem":141,
    "gn:feature_class":"P",
    "gn:feature_code":"PPL",
    "gn:name":"La Bouverie",
    "gn:population":0,
    "gn:timezone":"Europe/Paris",
    "iso:country":"FR",
    "wof:name":"La Bouverie",
    "wof:placetype":"locality"
},
  "geometry": {"coordinates":[4.78088,48.46787],"type":"Point"}
}