{
  "type": "Feature",
  "properties": {
    "gn:admin1_code":"75",
    "gn:admin2_code":"24",
    "gn:admin3_code":"241",
    "gn:admin4_code":"24532",
    "gn:asciiname":"Monguyard",
    "gn:country_code":"FR",
    "gn:dem":107,
    "gn:feature_class":"P",
    "gn:feature_code":"PPL",
    "gn:name":"Monguyard",
    "gn:population":0,
    "gn:timezone":"Europe/Paris",
    "iso:country":"FR",
    "wof:name":"Monguyard",
    "wof:placetype":"locality"
},
  "geometry": {"coordinates":[0.4314,44.69108],"type":"Point"}
}