{
  "type": "Feature",
  "properties": {
    "gn:admin1_code":"44",
    "gn:admin2_code":"55",
    "gn:admin3_code":"552",
    "gn:admin4_code":"55012",
    "gn:asciiname":"Marbotte",
    "gn:country_code":"FR",
    "gn:dem":249,
    "gn:feature_class":"P",
    "gn:feature_code":"PPL",
    "gn:name":"Marbotte",
    "gn:population":0,
    "gn:timezone":"Europe/Paris",
    "iso:country":"FR",
    "wof:name":"Marbotte",
    "wof:placetype":"locality"
},
  "geometry": {"coordinates":[5.58338,48.83471],"type":"Point"}
}