{
  "type": "Feature",
  "properties": {
    "gn:admin1_code":"84",
    "gn:admin2_code":"15",
    "gn:admin3_code":"153",
    "gn:admin4_code":"15209.0",
    "gn:asciiname":"La Roche-Canillac",
    "gn:country_code":"FR",
    "gn:dem":1050,
    "gn:feature_class":"P",
    "gn:feature_code":"PPL",
    "gn:name":"La Roche-Canillac",
    "gn:population":0,
    "gn:timezone":"Europe/Paris",
    "iso:country":"FR",
    "name:und_x_variant":[
        "La Roche-Conillac",
        "La Roche-Canillac"
    ],
    "wof:name":"La Roche-Canillac",
    "wof:placetype":"locality"
},
  "geometry": {"coordinates":[3.02547,44.75095],"type":"Point"}
}