{
  "type": "Feature",
  "properties": {
    "gn:admin1_code":"84",
    "gn:admin2_code":"15",
    "gn:admin3_code":"153",
    "gn:admin4_code":"15209.0",
    "gn:asciiname":"La Roche-Canillac",
    "gn:country_code":"FR",
    "gn:dem":1050,
    "gn:feature_class":"P",
    "gn:feature_code":"PPL",
    "gn:name":"La Roche-Canillac",
    "gn:population":0,
    "gn:timezone":"Europe/Paris",
    "iso:country":"FR",
    "name:bug_x_preferred":[
        "La Roche-Canillac"
    ],
    "name:ceb_x_preferred":[
        "La Roche-Canillac"
    ],
    "name:deu_x_preferred":[
        "La Roche-Canillac"
    ],
    "name:eus_x_preferred":[
        "La Roche-Canillac"
    ],
    "name:fra_x_preferred":[
        "La Roche-Canillac"
    ],
    "name:hun_x_preferred":[
        "La Roche-Canillac"
    ],
    "name:ind_x_preferred":[
        "La Roche-Canillac"
    ],
    "name:ita_x_preferred":[
        "La Roche-Canillac"
    ],
    "name:jpn_x_preferred":[
        "\u30e9\u30fb\u30ed\u30c3\u30b7\u30e5\uff1d\u30ab\u30cb\u30e4\u30c3\u30af"
    ],
    "name:kaz_x_preferred":[
        "\u041b\u0430-\u0420\u043e\u0448-\u041a\u0430\u043d\u0438\u044f\u043a"
    ],
    "name:lat_x_preferred":[
        "La Roche-Canillac"
    ],
    "name:msa_x_preferred":[
        "La Roche-Canillac"
    ],
    "name:nld_x_preferred":[
        "La Roche-Canillac"
    ],
    "name:nov_x_preferred":[
        "La Roche-Canillac"
    ],
    "name:oci_x_preferred":[
        "La R\u00f2cha Canilhac"
    ],
    "name:pms_x_preferred":[
        "La Roche-Canillac"
    ],
    "name:pol_x_preferred":[
        "La Roche-Canillac"
    ],
    "name:por_x_preferred":[
        "La Roche-Canillac"
    ],
    "name:ron_x_preferred":[
        "La Roche-Canillac"
    ],
    "name:rus_x_preferred":[
        "\u041b\u0430-\u0420\u043e\u0448-\u041a\u0430\u043d\u0438\u0439\u0430\u043a"
    ],
    "name:slk_x_preferred":[
        "La Roche-Canillac"
    ],
    "name:slv_x_preferred":[
        "La Roche-Canillac"
    ],
    "name:spa_x_preferred":[
        "La Roche-Canillac"
    ],
    "name:swe_x_preferred":[
        "La Roche-Canillac"
    ],
    "name:ukr_x_preferred":[
        "\u041b\u0430-\u0420\u043e\u0448-\u041a\u0430\u043d\u0456\u044f\u043a"
    ],
    "name:und_x_variant":[
        "La Roche-Conillac",
        "La Roche-Canillac"
    ],
    "name:urd_x_preferred":[
        "\u0644\u0627 \u0631\u0648\u0634\u06d2-\u06a9\u0627\u0646\u06cc\u0644\u0627\u06a9"
    ],
    "name:uzb_x_preferred":[
        "La Roche-Canillac"
    ],
    "name:vie_x_preferred":[
        "La Roche-Canillac"
    ],
    "name:vol_x_preferred":[
        "La Roche-Canillac"
    ],
    "name:war_x_preferred":[
        "La Roche-Canillac"
    ],
    "name:zho_x_preferred":[
        "\u62c9\u7f57\u4ec0\u5361\u5c3c\u4e9a\u514b"
    ],
    "wof:name":"La Roche-Canillac",
    "wof:placetype":"locality"
},
  "geometry": {"coordinates":[3.02547,44.75095],"type":"Point"}
}