{
  "type": "Feature",
  "properties": {
    "iso:country":"FR",
    "name:eng_x_preferred":[
        "Plaine"
    ],
    "name:fra_x_preferred":[
        "Plaine"
    ],
    "name:fra_x_variant":[
        "Cit\u00e9 de la Plaine"
    ],
    "wof:name":"Plaine",
    "wof:placetype":"neighbourhood"
},
  "geometry": {"coordinates":[2.24471406601276,48.78500874015018],"type":"Point"}
}