{
  "type": "Feature",
  "properties": {
    "gn:admin1_code":"44",
    "gn:admin2_code":"67",
    "gn:admin3_code":"673",
    "gn:admin4_code":"67448",
    "gn:asciiname":"Vacquenoux",
    "gn:country_code":"FR",
    "gn:dem":438,
    "gn:feature_class":"P",
    "gn:feature_code":"PPL",
    "gn:name":"Vacquenoux",
    "gn:population":0,
    "gn:timezone":"Europe/Paris",
    "iso:country":"FR",
    "wof:name":"Vacquenoux",
    "wof:placetype":"locality"
},
  "geometry": {"coordinates":[7.1812,48.484],"type":"Point"}
}