{
  "type": "Feature",
  "properties": {
    "gn:admin1_code":"84",
    "gn:admin2_code":"15",
    "gn:admin3_code":"153",
    "gn:admin4_code":"15259",
    "gn:asciiname":"Le Soul",
    "gn:country_code":"FR",
    "gn:dem":996,
    "gn:feature_class":"P",
    "gn:feature_code":"PPL",
    "gn:name":"Le Soul",
    "gn:population":0,
    "gn:timezone":"Europe/Paris",
    "iso:country":"FR",
    "wof:name":"Le Soul",
    "wof:placetype":"locality"
},
  "geometry": {"coordinates":[3.12835,45.13592],"type":"Point"}
}