{
  "type": "Feature",
  "properties": {
    "gn:admin1_code":"11",
    "gn:admin2_code":"91",
    "gn:admin3_code":"913",
    "gn:admin4_code":"91338",
    "gn:asciiname":"Roussigny",
    "gn:country_code":"FR",
    "gn:dem":171,
    "gn:feature_class":"P",
    "gn:feature_code":"PPL",
    "gn:name":"Roussigny",
    "gn:population":0,
    "gn:timezone":"Europe/Paris",
    "iso:country":"FR",
    "wof:name":"Roussigny",
    "wof:placetype":"locality"
},
  "geometry": {"coordinates":[2.10581,48.64756],"type":"Point"}
}