{
  "type": "Feature",
  "properties": {
    "gn:admin1_code":"75",
    "gn:admin2_code":"24",
    "gn:admin3_code":"241",
    "gn:admin4_code":"24167",
    "gn:asciiname":"Les Roux",
    "gn:country_code":"FR",
    "gn:dem":121,
    "gn:feature_class":"P",
    "gn:feature_code":"PPL",
    "gn:name":"Les Roux",
    "gn:population":0,
    "gn:timezone":"Europe/Paris",
    "iso:country":"FR",
    "wof:name":"Les Roux",
    "wof:placetype":"locality"
},
  "geometry": {"coordinates":[0.37807,44.68456],"type":"Point"}
}