{
  "type": "Feature",
  "properties": {
    "gn:admin1_code":"53",
    "gn:admin2_code":"35",
    "gn:admin3_code":"354",
    "gn:admin4_code":"35288",
    "gn:asciiname":"La Cite",
    "gn:country_code":"FR",
    "gn:dem":17,
    "gn:elevation":"18.0",
    "gn:feature_class":"P",
    "gn:feature_code":"PPL",
    "gn:name":"La Cit\u00e9",
    "gn:population":0,
    "gn:timezone":"Europe/Paris",
    "iso:country":"FR",
    "wof:name":"La Cite",
    "wof:placetype":"locality"
},
  "geometry": {"coordinates":[-2.02625,48.63583],"type":"Point"}
}