{
  "type": "Feature",
  "properties": {
    "gn:admin1_code":"93",
    "gn:admin2_code":"13",
    "gn:admin3_code":"131",
    "gn:admin4_code":"13080",
    "gn:asciiname":"La Cride",
    "gn:country_code":"FR",
    "gn:dem":251,
    "gn:feature_class":"P",
    "gn:feature_code":"PPL",
    "gn:name":"La Cride",
    "gn:population":0,
    "gn:timezone":"Europe/Paris",
    "iso:country":"FR",
    "wof:name":"La Cride",
    "wof:placetype":"locality"
},
  "geometry": {"coordinates":[5.42349,43.648],"type":"Point"}
}