{
  "type": "Feature",
  "properties": {
    "gn:admin1_code":"75",
    "gn:admin2_code":"24",
    "gn:admin3_code":"242",
    "gn:admin4_code":"24227",
    "gn:asciiname":"La Durantie",
    "gn:country_code":"FR",
    "gn:dem":309,
    "gn:feature_class":"P",
    "gn:feature_code":"PPL",
    "gn:name":"La Durantie",
    "gn:population":0,
    "gn:timezone":"Europe/Paris",
    "iso:country":"FR",
    "wof:name":"La Durantie",
    "wof:placetype":"locality"
},
  "geometry": {"coordinates":[1.11715,45.39681],"type":"Point"}
}