{
  "type": "Feature",
  "properties": {
    "gn:admin1_code":"75",
    "gn:admin2_code":"24",
    "gn:admin3_code":"242",
    "gn:admin4_code":"24271",
    "gn:asciiname":"Mazerou",
    "gn:country_code":"FR",
    "gn:dem":296,
    "gn:feature_class":"P",
    "gn:feature_code":"PPL",
    "gn:name":"Mazerou",
    "gn:population":0,
    "gn:timezone":"Europe/Paris",
    "iso:country":"FR",
    "wof:name":"Mazerou",
    "wof:placetype":"locality"
},
  "geometry": {"coordinates":[0.81459,45.48627000000001],"type":"Point"}
}