{
  "type": "Feature",
  "properties": {
    "gn:admin1_code":"76",
    "gn:admin2_code":"48",
    "gn:admin3_code":"482",
    "gn:admin4_code":"48010",
    "gn:asciiname":"Florac",
    "gn:country_code":"FR",
    "gn:dem":1027,
    "gn:feature_class":"P",
    "gn:feature_code":"PPL",
    "gn:name":"Florac",
    "gn:population":0,
    "gn:timezone":"Europe/Paris",
    "iso:country":"FR",
    "wof:name":"Florac",
    "wof:placetype":"locality"
},
  "geometry": {"coordinates":[3.74845,44.7484],"type":"Point"}
}