{
  "type": "Feature",
  "properties": {
    "gn:admin1_code":"76",
    "gn:admin2_code":"48",
    "gn:admin3_code":"482",
    "gn:admin4_code":"48010",
    "gn:asciiname":"Florac",
    "gn:country_code":"FR",
    "gn:dem":1027,
    "gn:feature_class":"P",
    "gn:feature_code":"PPL",
    "gn:name":"Florac",
    "gn:population":0,
    "gn:timezone":"Europe/Paris",
    "iso:country":"FR",
    "name:bre_x_preferred":[
        "Florac"
    ],
    "name:cat_x_preferred":[
        "Florac"
    ],
    "name:ceb_x_preferred":[
        "Florac"
    ],
    "name:cym_x_preferred":[
        "Florac"
    ],
    "name:deu_x_preferred":[
        "Florac"
    ],
    "name:epo_x_preferred":[
        "Florac"
    ],
    "name:eus_x_preferred":[
        "Florac"
    ],
    "name:fas_x_preferred":[
        "\u0641\u0644\u0631\u0627\u06a9"
    ],
    "name:fra_x_preferred":[
        "Florac"
    ],
    "name:hun_x_preferred":[
        "Florac"
    ],
    "name:ind_x_preferred":[
        "Florac"
    ],
    "name:ita_x_preferred":[
        "Florac"
    ],
    "name:jpn_x_preferred":[
        "\u30d5\u30ed\u30e9\u30c3\u30af"
    ],
    "name:kaz_x_preferred":[
        "\u0424\u043b\u043e\u0440\u0430\u043a"
    ],
    "name:lat_x_preferred":[
        "Florac"
    ],
    "name:lmo_x_preferred":[
        "Florac"
    ],
    "name:msa_x_preferred":[
        "Florac"
    ],
    "name:nld_x_preferred":[
        "Florac"
    ],
    "name:nno_x_preferred":[
        "Florac"
    ],
    "name:nor_x_preferred":[
        "Florac"
    ],
    "name:oci_x_preferred":[
        "Florac"
    ],
    "name:pms_x_preferred":[
        "Florac"
    ],
    "name:pol_x_preferred":[
        "Florac"
    ],
    "name:por_x_preferred":[
        "Florac"
    ],
    "name:ron_x_preferred":[
        "Florac"
    ],
    "name:slk_x_preferred":[
        "Florac"
    ],
    "name:slv_x_preferred":[
        "Florac"
    ],
    "name:spa_x_preferred":[
        "Florac"
    ],
    "name:swe_x_preferred":[
        "Florac"
    ],
    "name:ukr_x_preferred":[
        "\u0424\u043b\u043e\u0440\u0430\u043a"
    ],
    "name:vie_x_preferred":[
        "Florac"
    ],
    "name:vol_x_preferred":[
        "Florac"
    ],
    "name:war_x_preferred":[
        "Florac"
    ],
    "name:zho_x_preferred":[
        "\u5f17\u6d1b\u62c9\u514b"
    ],
    "wof:name":"Florac",
    "wof:placetype":"locality"
},
  "geometry": {"coordinates":[3.74845,44.7484],"type":"Point"}
}