{
  "type": "Feature",
  "properties": {
    "gn:admin1_code":"84",
    "gn:admin2_code":"43",
    "gn:admin3_code":"431",
    "gn:admin4_code":"43128",
    "gn:asciiname":"Malcros",
    "gn:country_code":"FR",
    "gn:dem":995,
    "gn:feature_class":"P",
    "gn:feature_code":"PPL",
    "gn:name":"Malcros",
    "gn:population":0,
    "gn:timezone":"Europe/Paris",
    "iso:country":"FR",
    "wof:name":"Malcros",
    "wof:placetype":"locality"
},
  "geometry": {"coordinates":[3.72777,45.33079],"type":"Point"}
}