{
  "type": "Feature",
  "properties": {
    "frgov:code_epci":"200073419",
    "frgov:insee_arr":"2",
    "frgov:insee_com":"43030",
    "frgov:insee_dep":"43",
    "frgov:insee_reg":"84",
    "frgov:nom_com":"Blanzac",
    "frgov:nom_com_m":"BLANZAC",
    "frgov:nom_dep":"HAUTE-LOIRE",
    "frgov:nom_reg":"AUVERGNE-RHONE-ALPES",
    "frgov:statut":"Commune simple",
    "gn:admin1_code":"84",
    "gn:admin2_code":"43",
    "gn:admin3_code":"432",
    "gn:admin4_code":"43030",
    "gn:asciiname":"Blanzac",
    "gn:country_code":"FR",
    "gn:dem":705,
    "gn:feature_class":"P",
    "gn:feature_code":"PPL",
    "gn:name":"Blanzac",
    "gn:population":289,
    "gn:timezone":"Europe/Paris",
    "iso:country":"FR",
    "name:ceb_x_preferred":[
        "Blanzac"
    ],
    "name:deu_x_preferred":[
        "Blanzac"
    ],
    "name:epo_x_preferred":[
        "Blanzac"
    ],
    "name:fra_x_preferred":[
        "Blanzac"
    ],
    "name:ita_x_preferred":[
        "Blanzac"
    ],
    "name:nds_x_preferred":[
        "Blanzac"
    ],
    "name:nld_x_preferred":[
        "Blanzac"
    ],
    "name:pms_x_preferred":[
        "Blanzac"
    ],
    "name:pol_x_preferred":[
        "Blanzac"
    ],
    "name:por_x_preferred":[
        "Blanzac"
    ],
    "name:slk_x_preferred":[
        "Blanzac"
    ],
    "name:spa_x_preferred":[
        "Blanzac"
    ],
    "name:srp_x_preferred":[
        "\u0411\u043b\u0430\u043d\u0437\u0430\u043a"
    ],
    "name:swe_x_preferred":[
        "Blanzac"
    ],
    "name:ukr_x_preferred":[
        "\u0411\u043b\u0430\u043d\u0437\u0430\u043a"
    ],
    "qs:a0":"France",
    "qs:a1":"HAUTE-LOIRE",
    "qs:a1_lc":"43",
    "qs:a1r":"AUVERGNE",
    "qs:a1r_lc":"83",
    "qs:a2_lc":"24",
    "qs:a2r_lc":"2",
    "qs:adm0":"France",
    "qs:adm0_a3":"FRA",
    "qs:la":"BLANZAC",
    "qs:la_lc":"43030",
    "qs:level":"localadmin",
    "qs:type":"Commune simple",
    "wof:coterminous":[
        404396201
    ],
    "wof:name":"Blanzac",
    "wof:placetype":"locality",
    "wof:placetype_local":"Commune simple",
    "wof:population":289
},
  "geometry": {"coordinates":[3.84252,45.10852],"type":"Point"}
}