{
  "type": "Feature",
  "properties": {
    "gn:admin1_code":"84",
    "gn:admin2_code":"43",
    "gn:admin3_code":"432",
    "gn:admin4_code":"43030",
    "gn:asciiname":"Blanzac",
    "gn:country_code":"FR",
    "gn:dem":705,
    "gn:feature_class":"P",
    "gn:feature_code":"PPL",
    "gn:name":"Blanzac",
    "gn:population":289,
    "gn:timezone":"Europe/Paris",
    "iso:country":"FR",
    "wof:name":"Blanzac",
    "wof:placetype":"locality",
    "wof:population":289
},
  "geometry": {"coordinates":[3.84252,45.10852],"type":"Point"}
}