{
  "type": "Feature",
  "properties": {
    "gn:admin1_code":"84",
    "gn:admin2_code":"43",
    "gn:admin3_code":"432",
    "gn:admin4_code":"43030",
    "gn:asciiname":"Blanzac",
    "gn:country_code":"FR",
    "gn:dem":705,
    "gn:feature_class":"P",
    "gn:feature_code":"PPL",
    "gn:name":"Blanzac",
    "gn:population":289,
    "gn:timezone":"Europe/Paris",
    "iso:country":"FR",
    "name:ceb_x_preferred":[
        "Blanzac"
    ],
    "name:deu_x_preferred":[
        "Blanzac"
    ],
    "name:epo_x_preferred":[
        "Blanzac"
    ],
    "name:fra_x_preferred":[
        "Blanzac"
    ],
    "name:ita_x_preferred":[
        "Blanzac"
    ],
    "name:nds_x_preferred":[
        "Blanzac"
    ],
    "name:nld_x_preferred":[
        "Blanzac"
    ],
    "name:pms_x_preferred":[
        "Blanzac"
    ],
    "name:pol_x_preferred":[
        "Blanzac"
    ],
    "name:por_x_preferred":[
        "Blanzac"
    ],
    "name:slk_x_preferred":[
        "Blanzac"
    ],
    "name:spa_x_preferred":[
        "Blanzac"
    ],
    "name:srp_x_preferred":[
        "\u0411\u043b\u0430\u043d\u0437\u0430\u043a"
    ],
    "name:swe_x_preferred":[
        "Blanzac"
    ],
    "name:ukr_x_preferred":[
        "\u0411\u043b\u0430\u043d\u0437\u0430\u043a"
    ],
    "wof:name":"Blanzac",
    "wof:placetype":"locality",
    "wof:population":289
},
  "geometry": {"coordinates":[3.84252,45.10852],"type":"Point"}
}