{
  "type": "Feature",
  "properties": {
    "gn:admin1_code":"75",
    "gn:admin2_code":"87",
    "gn:admin3_code":"872",
    "gn:admin4_code":"87083",
    "gn:asciiname":"La Couriere",
    "gn:cc2":"FR",
    "gn:country_code":"FR",
    "gn:dem":544,
    "gn:feature_class":"P",
    "gn:feature_code":"PPL",
    "gn:name":"La Couri\u00e8re",
    "gn:population":0,
    "gn:timezone":"Europe/Paris",
    "iso:country":"FR",
    "name:und_x_variant":[
        "Couri\u00e8re",
        "La Couri\u00e8re"
    ],
    "wof:name":"La Couriere",
    "wof:placetype":"locality"
},
  "geometry": {"coordinates":[1.51667,46.05],"type":"Point"}
}