{
  "type": "Feature",
  "properties": {
    "gn:admin1_code":"75",
    "gn:admin2_code":"23",
    "gn:admin3_code":"232",
    "gn:admin4_code":"23217",
    "gn:asciiname":"La Varache",
    "gn:country_code":"FR",
    "gn:dem":394,
    "gn:feature_class":"P",
    "gn:feature_code":"PPL",
    "gn:name":"La Varache",
    "gn:population":0,
    "gn:timezone":"Europe/Paris",
    "iso:country":"FR",
    "wof:name":"La Varache",
    "wof:placetype":"locality"
},
  "geometry": {"coordinates":[1.59197,45.94828],"type":"Point"}
}