{
  "type": "Feature",
  "properties": {
    "gn:admin1_code":"24",
    "gn:admin2_code":"18",
    "gn:admin3_code":"182",
    "gn:admin4_code":"18076",
    "gn:asciiname":"Touzel",
    "gn:country_code":"FR",
    "gn:dem":183,
    "gn:feature_class":"P",
    "gn:feature_code":"PPL",
    "gn:name":"Touzel",
    "gn:population":0,
    "gn:timezone":"Europe/Paris",
    "iso:country":"FR",
    "wof:name":"Touzel",
    "wof:placetype":"locality"
},
  "geometry": {"coordinates":[2.58462,46.69759000000001],"type":"Point"}
}