{
  "type": "Feature",
  "properties": {
    "gn:admin1_code":"52",
    "gn:admin2_code":"44",
    "gn:admin3_code":"441",
    "gn:admin4_code":"44085",
    "gn:asciiname":"La Riolais",
    "gn:country_code":"FR",
    "gn:dem":64,
    "gn:feature_class":"P",
    "gn:feature_code":"PPL",
    "gn:name":"La Riolais",
    "gn:population":0,
    "gn:timezone":"Europe/Paris",
    "iso:country":"FR",
    "name:und_x_variant":[
        "La Riclais",
        "La Riolais"
    ],
    "wof:name":"La Riolais",
    "wof:placetype":"locality"
},
  "geometry": {"coordinates":[-1.41933,47.66434],"type":"Point"}
}