{
  "type": "Feature",
  "properties": {
    "gn:admin1_code":"52",
    "gn:admin2_code":"44",
    "gn:admin3_code":"441",
    "gn:admin4_code":"44199",
    "gn:asciiname":"Le Dougilard",
    "gn:country_code":"FR",
    "gn:dem":95,
    "gn:feature_class":"P",
    "gn:feature_code":"PPL",
    "gn:name":"Le Dougilard",
    "gn:population":0,
    "gn:timezone":"Europe/Paris",
    "iso:country":"FR",
    "wof:name":"Le Dougilard",
    "wof:placetype":"locality"
},
  "geometry": {"coordinates":[-1.27466,47.74256],"type":"Point"}
}