{
  "type": "Feature",
  "properties": {
    "iso:country":"FR",
    "name:eng_x_preferred":[
        "Tarbes - Laloub\u00e8re Airport"
    ],
    "name:eng_x_variant":[
        "LFDT"
    ],
    "name:msa_x_preferred":[
        "Lapangan Terbang Laloubere"
    ],
    "oa:elevation_ft":"1076",
    "oa:type":"small_airport",
    "woe:hierarchy":{
        "country_id":23424819,
        "county_id":12597169,
        "localadmin_id":12667769,
        "planet_id":1,
        "state_id":7153323
    },
    "wof:name":"A\u00e9rodrome de Tarbes-laloub\u00e8re",
    "wof:placetype":"campus"
},
  "geometry": {"coordinates":[0.0775,43.215],"type":"Point"}
}