{
  "type": "Feature",
  "properties": {
    "gn:admin1_code":"84",
    "gn:admin2_code":"43",
    "gn:admin3_code":"431",
    "gn:admin4_code":"43202.0",
    "gn:asciiname":"Le Monteil",
    "gn:country_code":"FR",
    "gn:dem":758,
    "gn:feature_class":"P",
    "gn:feature_code":"PPL",
    "gn:name":"Le Monteil",
    "gn:population":0,
    "gn:timezone":"Europe/Paris",
    "iso:country":"FR",
    "name:ceb_x_preferred":[
        "Le Monteil"
    ],
    "name:deu_x_preferred":[
        "Le Monteil"
    ],
    "name:fra_x_preferred":[
        "Le Monteil"
    ],
    "name:ita_x_preferred":[
        "Le Monteil"
    ],
    "name:nds_x_preferred":[
        "Le Monteil"
    ],
    "name:nld_x_preferred":[
        "Le Monteil"
    ],
    "name:pol_x_preferred":[
        "Le Monteil"
    ],
    "name:por_x_preferred":[
        "Le Monteil"
    ],
    "name:rus_x_preferred":[
        "\u041b\u0435-\u041c\u043e\u043d\u0442\u0435\u0439"
    ],
    "name:scn_x_preferred":[
        "Le Monteil"
    ],
    "name:slk_x_preferred":[
        "Le Monteil"
    ],
    "name:spa_x_preferred":[
        "Le Monteil"
    ],
    "name:swe_x_preferred":[
        "Le Monteil"
    ],
    "name:ukr_x_preferred":[
        "\u041b\u0435-\u041c\u043e\u043d\u0442\u0435\u0439"
    ],
    "name:und_x_variant":[
        "Monteil",
        "Le Monteil"
    ],
    "wof:name":"Le Monteil",
    "wof:placetype":"locality"
},
  "geometry": {"coordinates":[3.56659,45.0504],"type":"Point"}
}