{
  "type": "Feature",
  "properties": {
    "gn:admin1_code":"75",
    "gn:admin2_code":"17",
    "gn:admin3_code":"173",
    "gn:admin4_code":"17264",
    "gn:asciiname":"Le Treuil Baton",
    "gn:country_code":"FR",
    "gn:dem":25,
    "gn:feature_class":"P",
    "gn:feature_code":"PPL",
    "gn:name":"Le Treuil B\u00e2ton",
    "gn:population":0,
    "gn:timezone":"Europe/Paris",
    "iso:country":"FR",
    "wof:name":"Le Treuil Baton",
    "wof:placetype":"locality"
},
  "geometry": {"coordinates":[-1.16001,46.19921],"type":"Point"}
}