{
  "type": "Feature",
  "properties": {
    "gn:admin1_code":"84",
    "gn:admin2_code":"03",
    "gn:admin3_code":"031",
    "gn:admin4_code":"3222.0",
    "gn:asciiname":"Les Noix",
    "gn:country_code":"FR",
    "gn:dem":379,
    "gn:feature_class":"P",
    "gn:feature_code":"PPL",
    "gn:name":"Les Noix",
    "gn:population":0,
    "gn:timezone":"Europe/Paris",
    "iso:country":"FR",
    "wof:name":"Les Noix",
    "wof:placetype":"locality"
},
  "geometry": {"coordinates":[2.75038,46.56438],"type":"Point"}
}