{
  "type": "Feature",
  "properties": {
    "gn:admin1_code":"84",
    "gn:admin2_code":"43",
    "gn:admin3_code":"432",
    "gn:admin4_code":"43241",
    "gn:asciiname":"Montagnac",
    "gn:country_code":"FR",
    "gn:dem":971,
    "gn:feature_class":"P",
    "gn:feature_code":"PPL",
    "gn:name":"Montagnac",
    "gn:population":0,
    "gn:timezone":"Europe/Paris",
    "iso:country":"FR",
    "wof:name":"Montagnac",
    "wof:placetype":"locality"
},
  "geometry": {"coordinates":[3.84419,44.96107],"type":"Point"}
}