{
  "type": "Feature",
  "properties": {
    "gn:admin1_code":"84",
    "gn:admin2_code":"43",
    "gn:admin3_code":"432",
    "gn:admin4_code":"43241",
    "gn:asciiname":"Montagnac",
    "gn:country_code":"FR",
    "gn:dem":971,
    "gn:feature_class":"P",
    "gn:feature_code":"PPL",
    "gn:name":"Montagnac",
    "gn:population":0,
    "gn:timezone":"Europe/Paris",
    "iso:country":"FR",
    "name:ceb_x_preferred":[
        "Montagnac"
    ],
    "name:deu_x_preferred":[
        "Montagnac"
    ],
    "name:fra_x_preferred":[
        "Montagnac"
    ],
    "name:ita_x_preferred":[
        "Montagnac"
    ],
    "name:lmo_x_preferred":[
        "Montagnac"
    ],
    "name:nds_x_preferred":[
        "Montagnac"
    ],
    "name:nld_x_preferred":[
        "Montagnac"
    ],
    "name:oci_x_preferred":[
        "Montanhac"
    ],
    "name:pol_x_preferred":[
        "Montagnac"
    ],
    "name:scn_x_preferred":[
        "Montagnac"
    ],
    "name:slk_x_preferred":[
        "Montagnac"
    ],
    "name:spa_x_preferred":[
        "Montagnac"
    ],
    "name:swe_x_preferred":[
        "Montagnac"
    ],
    "name:ukr_x_preferred":[
        "\u041c\u043e\u043d\u0442\u0430\u043d\u044c\u044f\u043a"
    ],
    "wof:name":"Montagnac",
    "wof:placetype":"locality"
},
  "geometry": {"coordinates":[3.84419,44.96107],"type":"Point"}
}