{
  "type": "Feature",
  "properties": {
    "gn:admin1_code":"84",
    "gn:admin2_code":"38",
    "gn:admin3_code":"383",
    "gn:admin4_code":"38069.0",
    "gn:asciiname":"Gerbuat",
    "gn:country_code":"FR",
    "gn:dem":592,
    "gn:feature_class":"P",
    "gn:feature_code":"PPL",
    "gn:name":"Gerbuat",
    "gn:population":0,
    "gn:timezone":"Europe/Paris",
    "iso:country":"FR",
    "wof:name":"Gerbuat",
    "wof:placetype":"locality"
},
  "geometry": {"coordinates":[5.28267,45.4765],"type":"Point"}
}