{
  "type": "Feature",
  "properties": {
    "gn:admin1_code":"24",
    "gn:admin2_code":"28",
    "gn:admin3_code":"284",
    "gn:admin4_code":"28376",
    "gn:asciiname":"Les Emonderies",
    "gn:country_code":"FR",
    "gn:dem":232,
    "gn:feature_class":"P",
    "gn:feature_code":"PPL",
    "gn:name":"Les \u00c9monderies",
    "gn:population":0,
    "gn:timezone":"Europe/Paris",
    "iso:country":"FR",
    "wof:name":"Les Emonderies",
    "wof:placetype":"locality"
},
  "geometry": {"coordinates":[0.88333,48.18333],"type":"Point"}
}