{
  "type": "Feature",
  "properties": {
    "gn:admin1_code":"84",
    "gn:admin2_code":"43",
    "gn:admin3_code":"432",
    "gn:admin4_code":"43026",
    "gn:asciiname":"Uffour",
    "gn:country_code":"FR",
    "gn:dem":960,
    "gn:feature_class":"P",
    "gn:feature_code":"PPL",
    "gn:name":"Uffour",
    "gn:population":0,
    "gn:timezone":"Europe/Paris",
    "iso:country":"FR",
    "wof:name":"Uffour",
    "wof:placetype":"locality"
},
  "geometry": {"coordinates":[3.81925,45.19297],"type":"Point"}
}