{
  "type": "Feature",
  "properties": {
    "gn:admin1_code":"24",
    "gn:admin2_code":"18",
    "gn:admin3_code":"183",
    "gn:admin4_code":"18036",
    "gn:asciiname":"Verdaux",
    "gn:country_code":"FR",
    "gn:dem":118,
    "gn:feature_class":"P",
    "gn:feature_code":"PPL",
    "gn:name":"Verdaux",
    "gn:population":0,
    "gn:timezone":"Europe/Paris",
    "iso:country":"FR",
    "wof:name":"Verdaux",
    "wof:placetype":"locality"
},
  "geometry": {"coordinates":[2.10858,47.19114],"type":"Point"}
}