{
  "type": "Feature",
  "properties": {
    "iso:country":"FR",
    "name:eng_x_preferred":[
        "Rosiers"
    ],
    "name:fra_x_preferred":[
        "Rosiers"
    ],
    "wof:name":"Rosiers",
    "wof:placetype":"neighbourhood"
},
  "geometry": {"coordinates":[2.23241166114114,48.88900251287455],"type":"Point"}
}