{
  "type": "Feature",
  "properties": {
    "gn:admin1_code":"84",
    "gn:admin2_code":"03",
    "gn:admin3_code":"031",
    "gn:admin4_code":"03072",
    "gn:asciiname":"Coutine",
    "gn:country_code":"FR",
    "gn:dem":295,
    "gn:feature_class":"P",
    "gn:feature_code":"PPL",
    "gn:name":"Coutine",
    "gn:population":0,
    "gn:timezone":"Europe/Paris",
    "iso:country":"FR",
    "wof:name":"Coutine",
    "wof:placetype":"locality"
},
  "geometry": {"coordinates":[2.50504,46.46228],"type":"Point"}
}