{
  "type": "Feature",
  "properties": {
    "gn:admin1_code":"93",
    "gn:admin2_code":"04",
    "gn:admin3_code":"044",
    "gn:admin4_code":"04095",
    "gn:asciiname":"L'Hospitalet",
    "gn:country_code":"FR",
    "gn:dem":894,
    "gn:feature_class":"P",
    "gn:feature_code":"PPL",
    "gn:name":"L\u2019Hospitalet",
    "gn:population":0,
    "gn:timezone":"Europe/Paris",
    "iso:country":"FR",
    "name:und_x_variant":[
        "L\u2019Hospitalet"
    ],
    "wof:name":"L'Hospitalet",
    "wof:placetype":"locality"
},
  "geometry": {"coordinates":[5.70156,44.08785],"type":"Point"}
}