{
  "type": "Feature",
  "properties": {
    "gn:admin1_code":"93",
    "gn:admin2_code":"04",
    "gn:admin3_code":"044",
    "gn:admin4_code":"04095",
    "gn:asciiname":"L'Hospitalet",
    "gn:country_code":"FR",
    "gn:dem":894,
    "gn:feature_class":"P",
    "gn:feature_code":"PPL",
    "gn:name":"L\u2019Hospitalet",
    "gn:population":0,
    "gn:timezone":"Europe/Paris",
    "iso:country":"FR",
    "name:bug_x_preferred":[
        "L'Hospitalet"
    ],
    "name:ceb_x_preferred":[
        "L'Hospitalet"
    ],
    "name:deu_x_preferred":[
        "L\u2019Hospitalet"
    ],
    "name:eus_x_preferred":[
        "L'Hospitalet"
    ],
    "name:fra_x_preferred":[
        "L'Hospitalet"
    ],
    "name:hun_x_preferred":[
        "L\u2019Hospitalet"
    ],
    "name:hye_x_preferred":[
        "\u053c\u2019\u0555\u057d\u057a\u056b\u057f\u0561\u056c\u0565"
    ],
    "name:ita_x_preferred":[
        "L'Hospitalet"
    ],
    "name:jpn_x_preferred":[
        "\u30ed\u30b9\u30d4\u30bf\u30ec"
    ],
    "name:lat_x_preferred":[
        "L'Hospitalet"
    ],
    "name:lmo_x_preferred":[
        "L'Hospitalet"
    ],
    "name:ltz_x_preferred":[
        "L'Hospitalet"
    ],
    "name:msa_x_preferred":[
        "L'Hospitalet"
    ],
    "name:nld_x_preferred":[
        "L'Hospitalet"
    ],
    "name:oci_x_preferred":[
        "L'Espitalet"
    ],
    "name:pms_x_preferred":[
        "L'Hospitalet"
    ],
    "name:pol_x_preferred":[
        "L\u2019Hospitalet"
    ],
    "name:por_x_preferred":[
        "L'Hospitalet"
    ],
    "name:rus_x_preferred":[
        "\u041b\u2019\u041e\u0441\u043f\u0438\u0442\u0430\u043b\u0435"
    ],
    "name:sco_x_preferred":[
        "L'Hospitalet"
    ],
    "name:slk_x_preferred":[
        "L\u2019Hospitalet"
    ],
    "name:swe_x_preferred":[
        "L'Hospitalet"
    ],
    "name:ukr_x_preferred":[
        "\u041b'\u041e\u0441\u043f\u0456\u0442\u0430\u043b\u0435"
    ],
    "name:und_x_variant":[
        "L\u2019Hospitalet"
    ],
    "name:vie_x_preferred":[
        "L'Hospitalet"
    ],
    "name:vol_x_preferred":[
        "L'Hospitalet"
    ],
    "name:war_x_preferred":[
        "L'Hospitalet"
    ],
    "name:zea_x_preferred":[
        "L'Hospitalet"
    ],
    "name:zho_x_preferred":[
        "\u7ea6\u65af\u76ae\u5854\u83b1"
    ],
    "wof:name":"L'Hospitalet",
    "wof:placetype":"locality"
},
  "geometry": {"coordinates":[5.70156,44.08785],"type":"Point"}
}