{
  "type": "Feature",
  "properties": {
    "gn:admin1_code":"32",
    "gn:admin2_code":"59",
    "gn:admin3_code":"595",
    "gn:admin4_code":"59411",
    "gn:asciiname":"Loffrande",
    "gn:country_code":"FR",
    "gn:dem":49,
    "gn:feature_class":"P",
    "gn:feature_code":"PPL",
    "gn:name":"Loffrande",
    "gn:population":0,
    "gn:timezone":"Europe/Paris",
    "iso:country":"FR",
    "wof:name":"Loffrande",
    "wof:placetype":"locality"
},
  "geometry": {"coordinates":[3.08212,50.49031],"type":"Point"}
}