{
  "type": "Feature",
  "properties": {
    "gn:admin1_code":"32",
    "gn:admin2_code":"60",
    "gn:admin3_code":"601",
    "gn:admin4_code":"60594.0",
    "gn:asciiname":"Hyancourt",
    "gn:country_code":"FR",
    "gn:dem":114,
    "gn:feature_class":"P",
    "gn:feature_code":"PPL",
    "gn:name":"Hyancourt",
    "gn:population":0,
    "gn:timezone":"Europe/Paris",
    "iso:country":"FR",
    "wof:name":"Hyancourt",
    "wof:placetype":"locality"
},
  "geometry": {"coordinates":[1.727,49.50821],"type":"Point"}
}