{
  "type": "Feature",
  "properties": {
    "frgov:code_epci":"243200425",
    "frgov:insee_arr":"3",
    "frgov:insee_com":"32238",
    "frgov:insee_dep":"32",
    "frgov:insee_reg":"76",
    "frgov:nom_com":"Marseillan",
    "frgov:nom_com_m":"MARSEILLAN",
    "frgov:nom_dep":"GERS",
    "frgov:nom_reg":"OCCITANIE",
    "frgov:statut":"Commune simple",
    "gn:admin1_code":"76",
    "gn:admin2_code":"32",
    "gn:admin3_code":"323",
    "gn:admin4_code":"32238",
    "gn:asciiname":"Marseillan",
    "gn:country_code":"FR",
    "gn:dem":223,
    "gn:feature_class":"P",
    "gn:feature_code":"PPL",
    "gn:name":"Marseillan",
    "gn:population":0,
    "gn:timezone":"Europe/Paris",
    "iso:country":"FR",
    "name:arg_x_preferred":[
        "Marcelhan"
    ],
    "name:ceb_x_preferred":[
        "Marseillan"
    ],
    "name:deu_x_preferred":[
        "Marseillan"
    ],
    "name:est_x_preferred":[
        "Marseillan"
    ],
    "name:fra_x_preferred":[
        "Marseillan"
    ],
    "name:ita_x_preferred":[
        "Marseillan"
    ],
    "name:nds_x_preferred":[
        "Marseillan"
    ],
    "name:nld_x_preferred":[
        "Marseillan"
    ],
    "name:oci_x_preferred":[
        "Marcelhan"
    ],
    "name:pms_x_preferred":[
        "Marseillan"
    ],
    "name:pol_x_preferred":[
        "Marseillan"
    ],
    "name:por_x_preferred":[
        "Marseillan"
    ],
    "name:rus_x_preferred":[
        "\u041c\u0430\u0440\u0441\u0435\u0439\u0430\u043d"
    ],
    "name:slk_x_preferred":[
        "Marseillan"
    ],
    "name:spa_x_preferred":[
        "Marseillan"
    ],
    "name:swe_x_preferred":[
        "Marseillan"
    ],
    "name:ukr_x_preferred":[
        "\u041c\u0430\u0440\u0441\u0435\u044f\u043d"
    ],
    "qs:a0":"France",
    "qs:a1":"GERS",
    "qs:a1_lc":"32",
    "qs:a1r":"MIDI-PYRENEES",
    "qs:a1r_lc":"73",
    "qs:a2_lc":"19",
    "qs:a2r_lc":"3",
    "qs:adm0":"France",
    "qs:adm0_a3":"FRA",
    "qs:la":"MARSEILLAN",
    "qs:la_lc":"32238",
    "qs:level":"localadmin",
    "qs:type":"Commune simple",
    "wof:coterminous":[
        404372263
    ],
    "wof:name":"Marseillan",
    "wof:placetype":"locality",
    "wof:placetype_local":"Commune simple"
},
  "geometry": {"coordinates":[0.31579,43.48682],"type":"Point"}
}