{
  "type": "Feature",
  "properties": {
    "gn:admin1_code":"76",
    "gn:admin2_code":"32",
    "gn:admin3_code":"323",
    "gn:admin4_code":"32238",
    "gn:asciiname":"Marseillan",
    "gn:country_code":"FR",
    "gn:dem":223,
    "gn:feature_class":"P",
    "gn:feature_code":"PPL",
    "gn:name":"Marseillan",
    "gn:population":0,
    "gn:timezone":"Europe/Paris",
    "iso:country":"FR",
    "name:arg_x_preferred":[
        "Marcelhan"
    ],
    "name:ceb_x_preferred":[
        "Marseillan"
    ],
    "name:deu_x_preferred":[
        "Marseillan"
    ],
    "name:est_x_preferred":[
        "Marseillan"
    ],
    "name:fra_x_preferred":[
        "Marseillan"
    ],
    "name:ita_x_preferred":[
        "Marseillan"
    ],
    "name:nds_x_preferred":[
        "Marseillan"
    ],
    "name:nld_x_preferred":[
        "Marseillan"
    ],
    "name:oci_x_preferred":[
        "Marcelhan"
    ],
    "name:pms_x_preferred":[
        "Marseillan"
    ],
    "name:pol_x_preferred":[
        "Marseillan"
    ],
    "name:por_x_preferred":[
        "Marseillan"
    ],
    "name:rus_x_preferred":[
        "\u041c\u0430\u0440\u0441\u0435\u0439\u0430\u043d"
    ],
    "name:slk_x_preferred":[
        "Marseillan"
    ],
    "name:spa_x_preferred":[
        "Marseillan"
    ],
    "name:swe_x_preferred":[
        "Marseillan"
    ],
    "name:ukr_x_preferred":[
        "\u041c\u0430\u0440\u0441\u0435\u044f\u043d"
    ],
    "wof:name":"Marseillan",
    "wof:placetype":"locality"
},
  "geometry": {"coordinates":[0.31579,43.48682],"type":"Point"}
}