{
  "type": "Feature",
  "properties": {
    "gn:admin1_code":"76",
    "gn:admin2_code":"32",
    "gn:admin3_code":"323",
    "gn:admin4_code":"32238",
    "gn:asciiname":"Marseillan",
    "gn:country_code":"FR",
    "gn:dem":223,
    "gn:feature_class":"P",
    "gn:feature_code":"PPL",
    "gn:name":"Marseillan",
    "gn:population":0,
    "gn:timezone":"Europe/Paris",
    "iso:country":"FR",
    "wof:name":"Marseillan",
    "wof:placetype":"locality"
},
  "geometry": {"coordinates":[0.31579,43.48682],"type":"Point"}
}