{
  "type": "Feature",
  "properties": {
    "gn:admin1_code":"75",
    "gn:admin2_code":"19",
    "gn:admin3_code":"191",
    "gn:admin4_code":"19031",
    "gn:asciiname":"Labrousse",
    "gn:country_code":"FR",
    "gn:dem":202,
    "gn:feature_class":"P",
    "gn:feature_code":"PPL",
    "gn:name":"Labrousse",
    "gn:population":0,
    "gn:timezone":"Europe/Paris",
    "iso:country":"FR",
    "name:cat_x_preferred":[
        "Labrossa"
    ],
    "name:ceb_x_preferred":[
        "Labrousse"
    ],
    "name:deu_x_preferred":[
        "Labrousse"
    ],
    "name:eus_x_preferred":[
        "Labrousse"
    ],
    "name:fra_x_preferred":[
        "Labrousse"
    ],
    "name:hun_x_preferred":[
        "Labrousse"
    ],
    "name:hye_x_preferred":[
        "\u053c\u0561\u0562\u0580\u0578\u0582\u057d"
    ],
    "name:ita_x_preferred":[
        "Labrousse"
    ],
    "name:kaz_x_preferred":[
        "\u041b\u0430\u0431\u0440\u0443\u0441\u0441"
    ],
    "name:lat_x_preferred":[
        "Labrousse"
    ],
    "name:ltz_x_preferred":[
        "Labrousse"
    ],
    "name:mlg_x_preferred":[
        "Labrousse"
    ],
    "name:msa_x_preferred":[
        "Labrousse"
    ],
    "name:nld_x_preferred":[
        "Labrousse"
    ],
    "name:oci_x_preferred":[
        "La Brossa"
    ],
    "name:pms_x_preferred":[
        "Labrousse"
    ],
    "name:pol_x_preferred":[
        "Labrousse"
    ],
    "name:por_x_preferred":[
        "Labrousse"
    ],
    "name:ron_x_preferred":[
        "Labrousse"
    ],
    "name:rus_x_preferred":[
        "\u041b\u0430\u0431\u0440\u0443\u0441"
    ],
    "name:slk_x_preferred":[
        "Labrousse"
    ],
    "name:spa_x_preferred":[
        "Labrousse"
    ],
    "name:swe_x_preferred":[
        "Labrousse"
    ],
    "name:ukr_x_preferred":[
        "\u041b\u0430\u0431\u0440\u0443\u0441\u0441"
    ],
    "name:urd_x_preferred":[
        "\u0644\u0627\u0628\u0631\u0648\u0633\u06cc"
    ],
    "name:uzb_x_preferred":[
        "Labrousse"
    ],
    "name:vie_x_preferred":[
        "Labrousse"
    ],
    "name:vol_x_preferred":[
        "Labrousse"
    ],
    "name:war_x_preferred":[
        "Labrousse"
    ],
    "name:zho_x_preferred":[
        "\u62c9\u5e03\u9c81\u65af"
    ],
    "wof:name":"Labrousse",
    "wof:placetype":"locality"
},
  "geometry": {"coordinates":[1.49797,45.12109],"type":"Point"}
}