{
  "type": "Feature",
  "properties": {
    "gn:admin1_code":"75",
    "gn:admin2_code":"86",
    "gn:admin3_code":"861",
    "gn:admin4_code":"86224",
    "gn:asciiname":"Avrigny",
    "gn:country_code":"FR",
    "gn:dem":83,
    "gn:feature_class":"P",
    "gn:feature_code":"PPL",
    "gn:name":"Avrigny",
    "gn:population":0,
    "gn:timezone":"Europe/Paris",
    "iso:country":"FR",
    "name:cat_x_preferred":[
        "Avrigny"
    ],
    "name:ceb_x_preferred":[
        "Avrigny"
    ],
    "name:deu_x_preferred":[
        "Avrigny"
    ],
    "name:eus_x_preferred":[
        "Avrigny"
    ],
    "name:fra_x_preferred":[
        "Avrigny"
    ],
    "name:hun_x_preferred":[
        "Avrigny"
    ],
    "name:ind_x_preferred":[
        "Avrigny"
    ],
    "name:ita_x_preferred":[
        "Avrigny"
    ],
    "name:lat_x_preferred":[
        "Avrigny"
    ],
    "name:mlg_x_preferred":[
        "Avrigny"
    ],
    "name:msa_x_preferred":[
        "Avrigny"
    ],
    "name:nld_x_preferred":[
        "Avrigny"
    ],
    "name:oci_x_preferred":[
        "Avrigny"
    ],
    "name:pms_x_preferred":[
        "Avrigny"
    ],
    "name:pol_x_preferred":[
        "Avrigny"
    ],
    "name:por_x_preferred":[
        "Avrigny"
    ],
    "name:ron_x_preferred":[
        "Avrigny"
    ],
    "name:slk_x_preferred":[
        "Avrigny"
    ],
    "name:spa_x_preferred":[
        "Avrigny"
    ],
    "name:sqi_x_preferred":[
        "Avrigny"
    ],
    "name:srp_x_preferred":[
        "\u0410\u0432\u0440\u0438\u045a\u0438"
    ],
    "name:swe_x_preferred":[
        "Avrigny"
    ],
    "name:ukr_x_preferred":[
        "\u0410\u0432\u0440\u0438\u043d\u044c\u0457"
    ],
    "name:uzb_x_preferred":[
        "Avrigny"
    ],
    "name:vie_x_preferred":[
        "Avrigny"
    ],
    "name:vol_x_preferred":[
        "Avrigny"
    ],
    "name:war_x_preferred":[
        "Avrigny"
    ],
    "name:zho_x_preferred":[
        "\u963f\u592b\u91cc\u5c3c"
    ],
    "wof:name":"Avrigny",
    "wof:placetype":"locality"
},
  "geometry": {"coordinates":[0.40819,46.89242],"type":"Point"}
}