{
  "type": "Feature",
  "properties": {
    "iso:country":"FR",
    "name:bre_x_preferred":[
        "Brigitte"
    ],
    "name:deu_x_preferred":[
        "Brigitte"
    ],
    "name:fra_x_preferred":[
        "Brigitte"
    ],
    "name:nor_x_preferred":[
        "Brigitte"
    ],
    "name:spa_x_preferred":[
        "Brigitte"
    ],
    "wof:name":"Brigitte",
    "wof:placetype":"neighbourhood"
},
  "geometry": {"coordinates":[7.70078297264473,48.59236734497115],"type":"Point"}
}