{
  "type": "Feature",
  "properties": {
    "gn:admin1_code":"24",
    "gn:admin2_code":"28",
    "gn:admin3_code":"284",
    "gn:admin4_code":"28112.0",
    "gn:asciiname":"Saint-Hilaire",
    "gn:country_code":"FR",
    "gn:dem":185,
    "gn:feature_class":"P",
    "gn:feature_code":"PPL",
    "gn:name":"Saint-Hilaire",
    "gn:population":0,
    "gn:timezone":"Europe/Paris",
    "iso:country":"FR",
    "name:bre_x_preferred":[
        "Saint-Hilaire"
    ],
    "name:ceb_x_preferred":[
        "Saint-Hilaire"
    ],
    "name:deu_x_preferred":[
        "Saint-Hilaire"
    ],
    "name:fra_x_preferred":[
        "Saint-Hilaire"
    ],
    "name:hun_x_preferred":[
        "Saint-Hilaire"
    ],
    "name:ita_x_preferred":[
        "Saint-Hilaire"
    ],
    "name:jpn_x_preferred":[
        "\u30b5\u30f3\u30c6\u30a3\u30ec\u30fc\u30eb"
    ],
    "name:lmo_x_preferred":[
        "Saint-Hilaire"
    ],
    "name:nds_x_preferred":[
        "Saint-Hilaire"
    ],
    "name:nld_x_preferred":[
        "Saint-Hilaire"
    ],
    "name:pms_x_preferred":[
        "Saint-Hilaire"
    ],
    "name:pol_x_preferred":[
        "Saint-Hilaire"
    ],
    "name:por_x_preferred":[
        "Saint-Hilaire"
    ],
    "name:ron_x_preferred":[
        "Saint-Hilaire"
    ],
    "name:rus_x_preferred":[
        "\u0421\u0435\u043d\u0442-\u0418\u043b\u0435\u0440"
    ],
    "name:slk_x_preferred":[
        "Saint-Hilaire"
    ],
    "name:spa_x_preferred":[
        "Saint-Hilaire"
    ],
    "name:sqi_x_preferred":[
        "Saint-Hilaire"
    ],
    "name:ukr_x_preferred":[
        "\u0421\u0435\u043d-\u0406\u043b\u0435\u0440"
    ],
    "wof:name":"Saint-Hilaire",
    "wof:placetype":"locality"
},
  "geometry": {"coordinates":[0.95226,48.34517],"type":"Point"}
}