{
  "type": "Feature",
  "properties": {
    "gn:admin1_code":"24",
    "gn:admin2_code":"28",
    "gn:admin3_code":"284",
    "gn:admin4_code":"28112.0",
    "gn:asciiname":"Saint-Hilaire",
    "gn:country_code":"FR",
    "gn:dem":185,
    "gn:feature_class":"P",
    "gn:feature_code":"PPL",
    "gn:name":"Saint-Hilaire",
    "gn:population":0,
    "gn:timezone":"Europe/Paris",
    "iso:country":"FR",
    "wof:name":"Saint-Hilaire",
    "wof:placetype":"locality"
},
  "geometry": {"coordinates":[0.95226,48.34517],"type":"Point"}
}