{
  "type": "Feature",
  "properties": {
    "gn:gn_country":"FR",
    "gn:gn_fcode":"PPL",
    "gn:gn_pop":0,
    "iso:country":"FR",
    "name:unk_x_variant":[
        "Sainte-Aigule"
    ],
    "qs_pg:aaroncc":"FR",
    "qs_pg:gn_country":"FR",
    "qs_pg:gn_fcode":"PPL",
    "qs_pg:gn_pop":0,
    "qs_pg:name":"St. Aygulf",
    "qs_pg:name_adm0":"France",
    "qs_pg:name_adm1":"Provence-Alpes-C\u00f4te d'Azur",
    "qs_pg:photos":224,
    "qs_pg:photos_1k":45,
    "qs_pg:photos_9k":1,
    "qs_pg:photos_9r":4,
    "qs_pg:photos_all":224,
    "qs_pg:photos_sr":4,
    "qs_pg:pop_sr":0,
    "qs_pg:qs_pg_placetype":"locality",
    "qs_pg:qs_pg_placetype_gp":"Town",
    "qs_pg:woe_adm0":23424819,
    "woe:adm0_id":23424819,
    "woe:name_adm0":"France",
    "woe:name_adm1":"Provence-Alpes-C\u00f4te d'Azur",
    "woe:placetype":"Town",
    "wof:name":"St. Aygulf",
    "wof:placetype":"neighbourhood"
},
  "geometry": {"coordinates":[6.721,43.381],"type":"Point"}
}