{
  "type": "Feature",
  "properties": {
    "gn:admin1_code":"94",
    "gn:admin2_code":"2B",
    "gn:admin3_code":"2B2",
    "gn:admin4_code":"2B107",
    "gn:asciiname":"Gualdo",
    "gn:country_code":"FR",
    "gn:dem":260,
    "gn:feature_class":"P",
    "gn:feature_code":"PPL",
    "gn:name":"Gualdo",
    "gn:population":0,
    "gn:timezone":"Europe/Paris",
    "iso:country":"FR",
    "name:ceb_x_preferred":[
        "Gualdo"
    ],
    "name:deu_x_preferred":[
        "Gualdo"
    ],
    "name:ita_x_preferred":[
        "Gualdo"
    ],
    "name:lat_x_preferred":[
        "Gualdum"
    ],
    "name:srp_x_preferred":[
        "Gvaldo"
    ],
    "name:swe_x_preferred":[
        "Gualdo"
    ],
    "wof:name":"Gualdo",
    "wof:placetype":"locality"
},
  "geometry": {"coordinates":[9.37375,42.97552],"type":"Point"}
}