{
  "type": "Feature",
  "properties": {
    "iso:country":"FR",
    "name:eng_x_preferred":[
        "Quartier du Montparnasse"
    ],
    "name:fra_x_preferred":[
        "Quartier du Montparnasse"
    ],
    "wof:name":"Quartier du Montparnasse",
    "wof:placetype":"neighbourhood"
},
  "geometry": {"coordinates":[2.33120101331782,48.83830780407824],"type":"Point"}
}