{
  "type": "Feature",
  "properties": {
    "gn:admin1_code":"24",
    "gn:admin2_code":"18",
    "gn:admin3_code":"182",
    "gn:admin4_code":"18114.0",
    "gn:asciiname":"Le Trait d'Aujonc",
    "gn:country_code":"FR",
    "gn:dem":172,
    "gn:feature_class":"P",
    "gn:feature_code":"PPL",
    "gn:name":"Le Trait d\u2019Aujonc",
    "gn:population":0,
    "gn:timezone":"Europe/Paris",
    "iso:country":"FR",
    "wof:name":"Le Trait d'Aujonc",
    "wof:placetype":"locality"
},
  "geometry": {"coordinates":[2.31334,46.75581],"type":"Point"}
}