{
  "type": "Feature",
  "properties": {
    "gn:admin1_code":"27",
    "gn:admin2_code":"89",
    "gn:admin3_code":"891",
    "gn:admin4_code":"89397",
    "gn:asciiname":"La Rue des Merles",
    "gn:country_code":"FR",
    "gn:dem":209,
    "gn:feature_class":"P",
    "gn:feature_code":"PPL",
    "gn:name":"La Rue des Merles",
    "gn:population":0,
    "gn:timezone":"Europe/Paris",
    "iso:country":"FR",
    "wof:name":"La Rue des Merles",
    "wof:placetype":"locality"
},
  "geometry": {"coordinates":[3.24424,47.83138],"type":"Point"}
}