{
  "type": "Feature",
  "properties": {
    "gn:admin1_code":"93",
    "gn:admin2_code":"04",
    "gn:admin3_code":"043",
    "gn:admin4_code":"04205",
    "gn:asciiname":"Grand Chardavon",
    "gn:country_code":"FR",
    "gn:dem":1154,
    "gn:feature_class":"P",
    "gn:feature_code":"PPL",
    "gn:name":"Grand Chardavon",
    "gn:population":0,
    "gn:timezone":"Europe/Paris",
    "iso:country":"FR",
    "wof:name":"Grand Chardavon",
    "wof:placetype":"locality"
},
  "geometry": {"coordinates":[6.32584,44.34411],"type":"Point"}
}