{
  "type": "Feature",
  "properties": {
    "gn:admin1_code":"84",
    "gn:admin2_code":"03",
    "gn:admin3_code":"032",
    "gn:admin4_code":"03059",
    "gn:asciiname":"Rosier",
    "gn:country_code":"FR",
    "gn:dem":266,
    "gn:feature_class":"P",
    "gn:feature_code":"PPL",
    "gn:name":"Rosier",
    "gn:population":0,
    "gn:timezone":"Europe/Paris",
    "iso:country":"FR",
    "name:deu_x_preferred":[
        "Rosier"
    ],
    "name:fra_x_preferred":[
        "Rosier"
    ],
    "name:nld_x_preferred":[
        "Rosier"
    ],
    "name:ron_x_preferred":[
        "Rosier"
    ],
    "name:rus_x_preferred":[
        "\u0420\u043e\u0437\u044c\u0435"
    ],
    "wof:name":"Rosier",
    "wof:placetype":"locality"
},
  "geometry": {"coordinates":[3.23708,46.27507],"type":"Point"}
}