{
  "type": "Feature",
  "properties": {
    "gn:admin1_code":"84",
    "gn:admin2_code":"07",
    "gn:admin3_code":"073",
    "gn:admin4_code":"07170",
    "gn:asciiname":"Moliere",
    "gn:country_code":"FR",
    "gn:dem":680,
    "gn:feature_class":"P",
    "gn:feature_code":"PPL",
    "gn:name":"Moli\u00e8re",
    "gn:population":0,
    "gn:timezone":"Europe/Paris",
    "iso:country":"FR",
    "wof:name":"Moliere",
    "wof:placetype":"locality"
},
  "geometry": {"coordinates":[4.50972,45.05527],"type":"Point"}
}