{
  "type": "Feature",
  "properties": {
    "iso:country":"FR",
    "name:eng_x_preferred":[
        "Coteaux-Bords de Seine"
    ],
    "name:fra_x_preferred":[
        "Coteaux-Bords de Seine"
    ],
    "wof:name":"Coteaux-Bords de Seine",
    "wof:placetype":"neighbourhood"
},
  "geometry": {"coordinates":[2.22000912041592,48.85369440756971],"type":"Point"}
}