{
  "type": "Feature",
  "properties": {
    "gn:admin1_code":"75",
    "gn:admin2_code":"19",
    "gn:admin3_code":"192",
    "gn:admin4_code":"19251",
    "gn:asciiname":"Roufiat",
    "gn:country_code":"FR",
    "gn:dem":556,
    "gn:feature_class":"P",
    "gn:feature_code":"PPL",
    "gn:name":"Roufiat",
    "gn:population":0,
    "gn:timezone":"Europe/Paris",
    "iso:country":"FR",
    "wof:name":"Roufiat",
    "wof:placetype":"locality"
},
  "geometry": {"coordinates":[1.90113,45.40357],"type":"Point"}
}