{
  "type": "Feature",
  "properties": {
    "gn:admin1_code":"24",
    "gn:admin2_code":"37",
    "gn:admin3_code":"371",
    "gn:admin4_code":"37228",
    "gn:asciiname":"Le Port Guyet",
    "gn:country_code":"FR",
    "gn:dem":34,
    "gn:feature_class":"P",
    "gn:feature_code":"PPL",
    "gn:name":"Le Port Guyet",
    "gn:population":0,
    "gn:timezone":"Europe/Paris",
    "iso:country":"FR",
    "wof:name":"Le Port Guyet",
    "wof:placetype":"locality"
},
  "geometry": {"coordinates":[0.11716,47.28045],"type":"Point"}
}