{
  "type": "Feature",
  "properties": {
    "gn:admin1_code":"84",
    "gn:admin2_code":"63",
    "gn:admin3_code":"631",
    "gn:admin4_code":"63328",
    "gn:asciiname":"Pinet",
    "gn:country_code":"FR",
    "gn:dem":869,
    "gn:feature_class":"P",
    "gn:feature_code":"PPL",
    "gn:name":"Pinet",
    "gn:population":0,
    "gn:timezone":"Europe/Paris",
    "iso:country":"FR",
    "name:cat_x_preferred":[
        "Pinet"
    ],
    "name:ceb_x_preferred":[
        "Pinet"
    ],
    "name:deu_x_preferred":[
        "Pinet"
    ],
    "name:eus_x_preferred":[
        "Pinet"
    ],
    "name:fra_x_preferred":[
        "Pinet"
    ],
    "name:glg_x_preferred":[
        "Pinet"
    ],
    "name:hun_x_preferred":[
        "Pinet"
    ],
    "name:ita_x_preferred":[
        "Pinet"
    ],
    "name:msa_x_preferred":[
        "Pinet"
    ],
    "name:nld_x_preferred":[
        "Pinet"
    ],
    "name:oci_x_preferred":[
        "Pinet"
    ],
    "name:pol_x_preferred":[
        "Pinet"
    ],
    "name:por_x_preferred":[
        "Pinet"
    ],
    "name:rus_x_preferred":[
        "\u041f\u0438\u043d\u0435"
    ],
    "name:swe_x_preferred":[
        "Pinet"
    ],
    "name:vie_x_preferred":[
        "Pinet"
    ],
    "name:war_x_preferred":[
        "Pinet"
    ],
    "wof:name":"Pinet",
    "wof:placetype":"locality"
},
  "geometry": {"coordinates":[3.47711,45.45302],"type":"Point"}
}