{
  "type": "Feature",
  "properties": {
    "gn:admin1_code":"84",
    "gn:admin2_code":"38",
    "gn:admin3_code":"381",
    "gn:admin4_code":"38140",
    "gn:asciiname":"Montfort",
    "gn:country_code":"FR",
    "gn:dem":244,
    "gn:feature_class":"P",
    "gn:feature_code":"PPL",
    "gn:name":"Montfort",
    "gn:population":0,
    "gn:timezone":"Europe/Paris",
    "iso:country":"FR",
    "name:afr_x_preferred":[
        "Montfort"
    ],
    "name:bre_x_preferred":[
        "Montfort"
    ],
    "name:cat_x_preferred":[
        "Montfort"
    ],
    "name:ceb_x_preferred":[
        "Montfort"
    ],
    "name:ces_x_preferred":[
        "Montfort"
    ],
    "name:deu_x_preferred":[
        "Montfort"
    ],
    "name:fra_x_preferred":[
        "Montfort"
    ],
    "name:heb_x_preferred":[
        "\u05de\u05d5\u05e0\u05e4\u05d5\u05e8"
    ],
    "name:hun_x_preferred":[
        "Montfort"
    ],
    "name:ita_x_preferred":[
        "Montfort"
    ],
    "name:lim_x_preferred":[
        "Mofert"
    ],
    "name:ltz_x_preferred":[
        "Montfort"
    ],
    "name:nds_x_preferred":[
        "Montfort"
    ],
    "name:nld_x_preferred":[
        "Montfort"
    ],
    "name:pms_x_preferred":[
        "Montfort"
    ],
    "name:pol_x_preferred":[
        "Montfort"
    ],
    "name:por_x_preferred":[
        "Montfort"
    ],
    "name:rus_x_preferred":[
        "\u041c\u043e\u043d\u0444\u043e\u0440"
    ],
    "name:scn_x_preferred":[
        "Montfort"
    ],
    "name:slk_x_preferred":[
        "Montfort"
    ],
    "name:spa_x_preferred":[
        "Montfort"
    ],
    "name:swe_x_preferred":[
        "Montfort"
    ],
    "name:ukr_x_preferred":[
        "\u041c\u043e\u043d\u0444\u043e\u0440"
    ],
    "wof:name":"Montfort",
    "wof:placetype":"locality"
},
  "geometry": {"coordinates":[5.90034,45.29748],"type":"Point"}
}