{
  "type": "Feature",
  "properties": {
    "gn:admin1_code":"84",
    "gn:admin2_code":"38",
    "gn:admin3_code":"381",
    "gn:admin4_code":"38140",
    "gn:asciiname":"Montfort",
    "gn:country_code":"FR",
    "gn:dem":244,
    "gn:feature_class":"P",
    "gn:feature_code":"PPL",
    "gn:name":"Montfort",
    "gn:population":0,
    "gn:timezone":"Europe/Paris",
    "iso:country":"FR",
    "wof:name":"Montfort",
    "wof:placetype":"locality"
},
  "geometry": {"coordinates":[5.90034,45.29748],"type":"Point"}
}