{
  "type": "Feature",
  "properties": {
    "gn:admin1_code":"28",
    "gn:admin2_code":"76",
    "gn:admin3_code":"761",
    "gn:admin4_code":"76372",
    "gn:asciiname":"Cuignet",
    "gn:country_code":"FR",
    "gn:dem":225,
    "gn:feature_class":"P",
    "gn:feature_code":"PPL",
    "gn:name":"Cuignet",
    "gn:population":0,
    "gn:timezone":"Europe/Paris",
    "iso:country":"FR",
    "wof:name":"Cuignet",
    "wof:placetype":"locality"
},
  "geometry": {"coordinates":[1.655,49.7525],"type":"Point"}
}