{
  "type": "Feature",
  "properties": {
    "gn:admin1_code":"75",
    "gn:admin2_code":"86",
    "gn:admin3_code":"862",
    "gn:admin4_code":"86264",
    "gn:asciiname":"Bernai",
    "gn:country_code":"FR",
    "gn:dem":128,
    "gn:feature_class":"P",
    "gn:feature_code":"PPL",
    "gn:name":"Bernai",
    "gn:population":0,
    "gn:timezone":"Europe/Paris",
    "iso:country":"FR",
    "wof:name":"Bernai",
    "wof:placetype":"locality"
},
  "geometry": {"coordinates":[0.39414,46.27332],"type":"Point"}
}