{
  "type": "Feature",
  "properties": {
    "gn:admin1_code":"84",
    "gn:admin2_code":"63",
    "gn:admin3_code":"632",
    "gn:admin4_code":"63239",
    "gn:asciiname":"Oriol",
    "gn:country_code":"FR",
    "gn:dem":461,
    "gn:feature_class":"P",
    "gn:feature_code":"PPL",
    "gn:name":"Oriol",
    "gn:population":0,
    "gn:timezone":"Europe/Paris",
    "iso:country":"FR",
    "wof:name":"Oriol",
    "wof:placetype":"locality"
},
  "geometry": {"coordinates":[3.36091,45.70624],"type":"Point"}
}