{
  "type": "Feature",
  "properties": {
    "gn:admin1_code":"53",
    "gn:admin2_code":"29",
    "gn:admin3_code":"291",
    "gn:admin4_code":"29019",
    "gn:asciiname":"Kerinou",
    "gn:country_code":"FR",
    "gn:dem":31,
    "gn:feature_class":"P",
    "gn:feature_code":"PPL",
    "gn:name":"K\u00e9rinou",
    "gn:population":0,
    "gn:timezone":"Europe/Paris",
    "iso:country":"FR",
    "wof:name":"Kerinou",
    "wof:placetype":"locality"
},
  "geometry": {"coordinates":[-4.48808,48.40258],"type":"Point"}
}