{
  "type": "Feature",
  "properties": {
    "gn:admin1_code":"84",
    "gn:admin2_code":"26",
    "gn:admin3_code":"261",
    "gn:admin4_code":"26136",
    "gn:asciiname":"Le Pilhon",
    "gn:country_code":"FR",
    "gn:dem":1093,
    "gn:feature_class":"P",
    "gn:feature_code":"PPL",
    "gn:name":"Le Pilhon",
    "gn:population":0,
    "gn:timezone":"Europe/Paris",
    "iso:country":"FR",
    "wof:name":"Le Pilhon",
    "wof:placetype":"locality"
},
  "geometry": {"coordinates":[5.60148,44.59356],"type":"Point"}
}