{
  "type": "Feature",
  "properties": {
    "gn:admin1_code":"44",
    "gn:admin2_code":"57",
    "gn:admin3_code":"576",
    "gn:admin4_code":"57513",
    "gn:asciiname":"Dollenbach",
    "gn:country_code":"FR",
    "gn:dem":314,
    "gn:feature_class":"P",
    "gn:feature_code":"PPL",
    "gn:name":"Dollenbach",
    "gn:population":0,
    "gn:timezone":"Europe/Paris",
    "iso:country":"FR",
    "name:und_x_variant":[
        "Dollendach",
        "Dollenbach"
    ],
    "wof:name":"Dollenbach",
    "wof:placetype":"locality"
},
  "geometry": {"coordinates":[7.35981,49.10286],"type":"Point"}
}