{
  "type": "Feature",
  "properties": {
    "gn:admin1_code":"28",
    "gn:admin2_code":"27",
    "gn:admin3_code":"271",
    "gn:admin4_code":"27417",
    "gn:asciiname":"La Lande-Perrin",
    "gn:country_code":"FR",
    "gn:dem":134,
    "gn:feature_class":"P",
    "gn:feature_code":"PPL",
    "gn:name":"La Lande-Perrin",
    "gn:population":0,
    "gn:timezone":"Europe/Paris",
    "iso:country":"FR",
    "name:und_x_variant":[
        "la Lande",
        "La Lande-Perrin"
    ],
    "wof:name":"La Lande-Perrin",
    "wof:placetype":"locality"
},
  "geometry": {"coordinates":[1.58657,49.3711],"type":"Point"}
}