{
  "type": "Feature",
  "properties": {
    "gn:admin1_code":"24",
    "gn:admin2_code":"45",
    "gn:admin3_code":"453",
    "gn:admin4_code":"45054.0",
    "gn:asciiname":"Buisseau",
    "gn:country_code":"FR",
    "gn:dem":90,
    "gn:feature_class":"P",
    "gn:feature_code":"PPL",
    "gn:name":"Buisseau",
    "gn:population":0,
    "gn:timezone":"Europe/Paris",
    "iso:country":"FR",
    "wof:name":"Buisseau",
    "wof:placetype":"locality"
},
  "geometry": {"coordinates":[2.43707,48.23149],"type":"Point"}
}