{
  "type": "Feature",
  "properties": {
    "gn:admin1_code":"75",
    "gn:admin2_code":"19",
    "gn:admin3_code":"192",
    "gn:admin4_code":"19171",
    "gn:asciiname":"Luzege",
    "gn:country_code":"FR",
    "gn:dem":457,
    "gn:feature_class":"P",
    "gn:feature_code":"PPL",
    "gn:name":"Luz\u00e8ge",
    "gn:population":0,
    "gn:timezone":"Europe/Paris",
    "iso:country":"FR",
    "wof:name":"Luzege",
    "wof:placetype":"locality"
},
  "geometry": {"coordinates":[1.90403,45.02749],"type":"Point"}
}