{
  "type": "Feature",
  "properties": {
    "gn:admin1_code":"76",
    "gn:admin2_code":"48",
    "gn:admin3_code":"482",
    "gn:admin4_code":"48063",
    "gn:asciiname":"Chabanes Planes",
    "gn:country_code":"FR",
    "gn:dem":1019,
    "gn:feature_class":"P",
    "gn:feature_code":"PPL",
    "gn:name":"Chabanes Planes",
    "gn:population":0,
    "gn:timezone":"Europe/Paris",
    "iso:country":"FR",
    "wof:name":"Chabanes Planes",
    "wof:placetype":"locality"
},
  "geometry": {"coordinates":[3.35624,44.7608],"type":"Point"}
}