{
  "type": "Feature",
  "properties": {
    "gn:admin1_code":"75",
    "gn:admin2_code":"33",
    "gn:admin3_code":"336",
    "gn:admin4_code":"33555",
    "gn:asciiname":"Croix d'Hins",
    "gn:country_code":"FR",
    "gn:dem":62,
    "gn:feature_class":"P",
    "gn:feature_code":"PPL",
    "gn:name":"Croix d\u2019Hins",
    "gn:population":0,
    "gn:timezone":"Europe/Paris",
    "iso:country":"FR",
    "name:und_x_variant":[
        "La Croix d\u2019Hins",
        "Croix d\u2019Hins"
    ],
    "wof:name":"Croix d'Hins",
    "wof:placetype":"locality"
},
  "geometry": {"coordinates":[-0.81556,44.71138],"type":"Point"}
}