{
  "type": "Feature",
  "properties": {
    "gn:admin1_code":"93",
    "gn:admin2_code":"13",
    "gn:admin3_code":"133",
    "gn:admin4_code":"13055",
    "gn:asciiname":"Marseille 01",
    "gn:country_code":"FR",
    "gn:dem":32,
    "gn:feature_class":"P",
    "gn:feature_code":"PPL",
    "gn:name":"Marseille 01",
    "gn:population":40919,
    "gn:timezone":"Europe/Paris",
    "iso:country":"FR",
    "name:urd_x_preferred":[
        "\u0645\u0627\u0631\u0633\u06cc\u0644 \u06a9\u0627\u067e\u06c1\u0644\u0627 \u0627\u0631\u0627\u0624\u0646\u0688\u0688\u0633\u0645\u0646\u0679"
    ],
    "wof:name":"Marseille 01",
    "wof:placetype":"locality",
    "wof:population":40919
},
  "geometry": {"coordinates":[5.38407,43.29814],"type":"Point"}
}