{
  "type": "Feature",
  "properties": {
    "gn:admin1_code":"93",
    "gn:admin2_code":"13",
    "gn:admin3_code":"133",
    "gn:admin4_code":"13055",
    "gn:asciiname":"Marseille 01",
    "gn:country_code":"FR",
    "gn:dem":32,
    "gn:feature_class":"P",
    "gn:feature_code":"PPL",
    "gn:name":"Marseille 01",
    "gn:population":40919,
    "gn:timezone":"Europe/Paris",
    "iso:country":"FR",
    "wof:name":"Marseille 01",
    "wof:placetype":"locality",
    "wof:population":40919
},
  "geometry": {"coordinates":[5.38407,43.29814],"type":"Point"}
}