{
  "type": "Feature",
  "properties": {
    "gn:admin1_code":"32",
    "gn:admin2_code":"80",
    "gn:admin3_code":"801",
    "gn:admin4_code":"80809.0",
    "gn:asciiname":"Viammeville",
    "gn:country_code":"FR",
    "gn:dem":113,
    "gn:feature_class":"P",
    "gn:feature_code":"PPL",
    "gn:name":"Viammeville",
    "gn:population":0,
    "gn:timezone":"Europe/Paris",
    "iso:country":"FR",
    "name:und_x_variant":[
        "Wiammeville",
        "Viammeville"
    ],
    "wof:name":"Viammeville",
    "wof:placetype":"locality"
},
  "geometry": {"coordinates":[1.65452,49.99055],"type":"Point"}
}