{
  "type": "Feature",
  "properties": {
    "gn:admin1_code":"24",
    "gn:admin2_code":"18",
    "gn:admin3_code":"182",
    "gn:admin4_code":"18234",
    "gn:asciiname":"Moulin Foulet",
    "gn:country_code":"FR",
    "gn:dem":383,
    "gn:feature_class":"P",
    "gn:feature_code":"PPL",
    "gn:name":"Moulin Foulet",
    "gn:population":0,
    "gn:timezone":"Europe/Paris",
    "iso:country":"FR",
    "wof:name":"Moulin Foulet",
    "wof:placetype":"locality"
},
  "geometry": {"coordinates":[2.2598,46.49171],"type":"Point"}
}