{
  "type": "Feature",
  "properties": {
    "gn:admin1_code":"84",
    "gn:admin2_code":"42",
    "gn:admin3_code":"421",
    "gn:admin4_code":"42256",
    "gn:asciiname":"Verines",
    "gn:country_code":"FR",
    "gn:dem":425,
    "gn:feature_class":"P",
    "gn:feature_code":"PPL",
    "gn:name":"V\u00e9rines",
    "gn:population":0,
    "gn:timezone":"Europe/Paris",
    "iso:country":"FR",
    "wof:name":"Verines",
    "wof:placetype":"locality"
},
  "geometry": {"coordinates":[4.13446,45.49105],"type":"Point"}
}