{
  "type": "Feature",
  "properties": {
    "gn:admin1_code":"93",
    "gn:admin2_code":"83",
    "gn:asciiname":"Porquerolles",
    "gn:country_code":"FR",
    "gn:dem":5,
    "gn:feature_class":"P",
    "gn:feature_code":"PPL",
    "gn:name":"Porquerolles",
    "gn:population":0,
    "gn:timezone":"Europe/Paris",
    "iso:country":"FR",
    "name:bre_x_preferred":[
        "Porcair\u00f2la"
    ],
    "name:cat_x_preferred":[
        "P\u00f2rcar\u00f2las"
    ],
    "name:dan_x_preferred":[
        "Porquerolles"
    ],
    "name:deu_x_preferred":[
        "Porquerolles"
    ],
    "name:ell_x_preferred":[
        "\u03a0\u03bf\u03c1\u03ba\u03b5\u03c1\u03cc\u03bb"
    ],
    "name:ita_x_preferred":[
        "Porquerolles"
    ],
    "name:ltz_x_preferred":[
        "Porquerolles"
    ],
    "name:nld_x_preferred":[
        "Porquerolles"
    ],
    "name:oci_x_preferred":[
        "Porcair\u00f2la"
    ],
    "name:pms_x_preferred":[
        "Porquerolles"
    ],
    "name:por_x_preferred":[
        "Porquerolles"
    ],
    "name:rus_x_preferred":[
        "\u041f\u043e\u0440\u043a\u0435\u0440\u043e\u043b\u044c"
    ],
    "name:spa_x_preferred":[
        "Porquerolles"
    ],
    "name:ukr_x_preferred":[
        "\u041f\u043e\u0440\u043a\u0435\u0440\u043e\u043b\u044c"
    ],
    "name:zho_x_preferred":[
        "\u6ce2\u514b\u7f85\u52d2\u5cf6"
    ],
    "wof:name":"Porquerolles",
    "wof:placetype":"locality"
},
  "geometry": {"coordinates":[6.20265,43.00116],"type":"Point"}
}