{
  "type": "Feature",
  "properties": {
    "gn:admin1_code":"84",
    "gn:admin2_code":"03",
    "gn:admin3_code":"032",
    "gn:admin4_code":"03180",
    "gn:asciiname":"La Faye",
    "gn:country_code":"FR",
    "gn:dem":265,
    "gn:feature_class":"P",
    "gn:feature_code":"PPL",
    "gn:name":"La Faye",
    "gn:population":0,
    "gn:timezone":"Europe/Paris",
    "iso:country":"FR",
    "name:cat_x_preferred":[
        "La Faye"
    ],
    "name:ceb_x_preferred":[
        "La Faye"
    ],
    "name:deu_x_preferred":[
        "La Faye"
    ],
    "name:eus_x_preferred":[
        "La Faye"
    ],
    "name:fas_x_preferred":[
        "\u0644\u0627 \u0641\u06cc"
    ],
    "name:fra_x_preferred":[
        "La Faye"
    ],
    "name:hun_x_preferred":[
        "La Faye"
    ],
    "name:hye_x_preferred":[
        "\u053c\u0561 \u0556\u0565\u0575"
    ],
    "name:ita_x_preferred":[
        "La Faye"
    ],
    "name:lat_x_preferred":[
        "La Faye"
    ],
    "name:msa_x_preferred":[
        "La Faye"
    ],
    "name:nld_x_preferred":[
        "La Faye"
    ],
    "name:oci_x_preferred":[
        "La Faye"
    ],
    "name:pms_x_preferred":[
        "La Faye"
    ],
    "name:pol_x_preferred":[
        "La Faye"
    ],
    "name:por_x_preferred":[
        "La Faye"
    ],
    "name:ron_x_preferred":[
        "La Faye"
    ],
    "name:rus_x_preferred":[
        "\u041b\u0430-\u0424\u0435\u0439"
    ],
    "name:slk_x_preferred":[
        "La Faye"
    ],
    "name:spa_x_preferred":[
        "La Faye"
    ],
    "name:swe_x_preferred":[
        "La Faye"
    ],
    "name:ukr_x_preferred":[
        "\u041b\u0430-\u0424\u0435"
    ],
    "name:urd_x_preferred":[
        "\u0644\u0627 \u0641\u0627\u0626\u06d2"
    ],
    "name:vie_x_preferred":[
        "La Faye"
    ],
    "name:vol_x_preferred":[
        "La Faye"
    ],
    "name:war_x_preferred":[
        "La Faye"
    ],
    "name:zho_x_preferred":[
        "\u62c9\u8d39\u57c3"
    ],
    "wof:name":"La Faye",
    "wof:placetype":"locality"
},
  "geometry": {"coordinates":[3.46685,46.52566],"type":"Point"}
}