{
  "type": "Feature",
  "properties": {
    "gn:admin1_code":"24",
    "gn:admin2_code":"28",
    "gn:admin3_code":"281",
    "gn:admin4_code":"28274",
    "gn:asciiname":"Moutiers",
    "gn:country_code":"FR",
    "gn:dem":151,
    "gn:feature_class":"P",
    "gn:feature_code":"PPL",
    "gn:name":"Moutiers",
    "gn:population":224,
    "gn:timezone":"Europe/Paris",
    "iso:country":"FR",
    "name:bre_x_preferred":[
        "Moutiers"
    ],
    "name:ceb_x_preferred":[
        "Moutiers"
    ],
    "name:deu_x_preferred":[
        "Moutiers"
    ],
    "name:fra_x_preferred":[
        "Moutiers"
    ],
    "name:hun_x_preferred":[
        "Moutiers"
    ],
    "name:ita_x_preferred":[
        "Moutiers"
    ],
    "name:nds_x_preferred":[
        "Moutiers"
    ],
    "name:nld_x_preferred":[
        "Moutiers"
    ],
    "name:oci_x_preferred":[
        "Moutiers"
    ],
    "name:pms_x_preferred":[
        "Moutiers"
    ],
    "name:pol_x_preferred":[
        "Moutiers"
    ],
    "name:rus_x_preferred":[
        "\u041c\u0443\u0442\u044c\u0435"
    ],
    "name:slk_x_preferred":[
        "Moutiers"
    ],
    "name:spa_x_preferred":[
        "Moutiers"
    ],
    "name:swe_x_preferred":[
        "Moutiers"
    ],
    "name:ukr_x_preferred":[
        "\u041c\u0443\u0442\u044c\u0454"
    ],
    "name:und_x_variant":[
        "Moutiers-en-Beauce"
    ],
    "wof:name":"Moutiers",
    "wof:placetype":"locality",
    "wof:population":224
},
  "geometry": {"coordinates":[1.77611,48.29734000000001],"type":"Point"}
}