{
  "type": "Feature",
  "properties": {
    "gn:admin1_code":"84",
    "gn:admin2_code":"01",
    "gn:admin3_code":"011",
    "gn:admin4_code":"01185",
    "gn:asciiname":"Nantuy",
    "gn:country_code":"FR",
    "gn:dem":736,
    "gn:feature_class":"P",
    "gn:feature_code":"PPL",
    "gn:name":"Nantuy",
    "gn:population":0,
    "gn:timezone":"Europe/Paris",
    "iso:country":"FR",
    "wof:name":"Nantuy",
    "wof:placetype":"locality"
},
  "geometry": {"coordinates":[5.57633,45.96923],"type":"Point"}
}