{
  "type": "Feature",
  "properties": {
    "gn:admin1_code":"84",
    "gn:admin2_code":"43",
    "gn:admin3_code":"431",
    "gn:admin4_code":"43013",
    "gn:asciiname":"Sorlhac",
    "gn:country_code":"FR",
    "gn:dem":915,
    "gn:feature_class":"P",
    "gn:feature_code":"PPL",
    "gn:name":"Sorlhac",
    "gn:population":0,
    "gn:timezone":"Europe/Paris",
    "iso:country":"FR",
    "wof:name":"Sorlhac",
    "wof:placetype":"locality"
},
  "geometry": {"coordinates":[3.64184,45.11048],"type":"Point"}
}