{
  "type": "Feature",
  "properties": {
    "gn:admin1_code":"28",
    "gn:admin2_code":"50",
    "gn:admin3_code":"502",
    "gn:admin4_code":"50382",
    "gn:asciiname":"L'Heleinerie",
    "gn:country_code":"FR",
    "gn:dem":112,
    "gn:feature_class":"P",
    "gn:feature_code":"PPLL",
    "gn:name":"L\u2019H\u00e9leinerie",
    "gn:population":0,
    "gn:timezone":"Europe/Paris",
    "iso:country":"FR",
    "wof:name":"L'Heleinerie",
    "wof:placetype":"locality"
},
  "geometry": {"coordinates":[-1.68819,49.62612],"type":"Point"}
}