{
  "type": "Feature",
  "properties": {
    "gn:admin1_code":"93",
    "gn:admin2_code":"05",
    "gn:admin3_code":"052",
    "gn:admin4_code":"05036",
    "gn:asciiname":"Saint-Marcellin",
    "gn:country_code":"FR",
    "gn:dem":1032,
    "gn:feature_class":"P",
    "gn:feature_code":"PPL",
    "gn:name":"Saint-Marcellin",
    "gn:population":0,
    "gn:timezone":"Europe/Paris",
    "iso:country":"FR",
    "name:cat_x_preferred":[
        "Saint-marcellin"
    ],
    "name:deu_x_preferred":[
        "Saint-Marcellin"
    ],
    "name:fra_x_preferred":[
        "Saint-marcellin"
    ],
    "name:ind_x_preferred":[
        "Saint Marcellin"
    ],
    "name:nld_x_preferred":[
        "Saint-Marcellin"
    ],
    "name:pol_x_preferred":[
        "Saint-Marcellin"
    ],
    "name:spa_x_preferred":[
        "Saint-Marcellin"
    ],
    "name:und_x_variant":[
        "Vi\u00e8re"
    ],
    "wof:name":"Saint-Marcellin",
    "wof:placetype":"locality"
},
  "geometry": {"coordinates":[6.51723,44.61497],"type":"Point"}
}