{
  "type": "Feature",
  "properties": {
    "gn:admin1_code":"76",
    "gn:admin2_code":"46",
    "gn:admin3_code":"461",
    "gn:admin4_code":"46201",
    "gn:asciiname":"Sainte-Croix",
    "gn:country_code":"FR",
    "gn:dem":198,
    "gn:feature_class":"P",
    "gn:feature_code":"PPL",
    "gn:name":"Sainte-Croix",
    "gn:population":0,
    "gn:timezone":"Europe/Paris",
    "iso:country":"FR",
    "name:ceb_x_preferred":[
        "Sainte-Croix"
    ],
    "name:ces_x_preferred":[
        "Sainte-Croix"
    ],
    "name:deu_x_preferred":[
        "Sainte-Croix"
    ],
    "name:epo_x_preferred":[
        "Sainte-Croix"
    ],
    "name:fra_x_preferred":[
        "Sainte-Croix"
    ],
    "name:hun_x_preferred":[
        "Sainte-Croix"
    ],
    "name:ita_x_preferred":[
        "Sainte-Croix"
    ],
    "name:nds_x_preferred":[
        "Sainte-Croix"
    ],
    "name:nld_x_preferred":[
        "Sainte-Croix"
    ],
    "name:pms_x_preferred":[
        "Sainte-Croix"
    ],
    "name:pol_x_preferred":[
        "Sainte-Croix"
    ],
    "name:por_x_preferred":[
        "Sainte-Croix"
    ],
    "name:ron_x_preferred":[
        "Sainte-Croix"
    ],
    "name:rus_x_preferred":[
        "\u0421\u0435\u043d\u0442-\u041a\u0440\u0443\u0430"
    ],
    "name:slk_x_preferred":[
        "Sainte-Croix"
    ],
    "name:spa_x_preferred":[
        "Sainte-Croix"
    ],
    "name:swe_x_preferred":[
        "Sainte-Croix"
    ],
    "name:ukr_x_preferred":[
        "\u0421\u0435\u043d\u0442-\u041a\u0440\u0443\u0430"
    ],
    "wof:name":"Sainte-Croix",
    "wof:placetype":"locality"
},
  "geometry": {"coordinates":[1.16601,44.34081],"type":"Point"}
}