{
  "type": "Feature",
  "properties": {
    "gn:admin1_code":"76",
    "gn:admin2_code":"48",
    "gn:admin3_code":"482",
    "gn:admin4_code":"48151",
    "gn:asciiname":"Saint-Frezal-d'Albuges",
    "gn:country_code":"FR",
    "gn:dem":1210,
    "gn:feature_class":"P",
    "gn:feature_code":"PPL",
    "gn:name":"Saint-Fr\u00e9zal-d\u2019Albuges",
    "gn:population":0,
    "gn:timezone":"Europe/Paris",
    "iso:country":"FR",
    "name:und_x_variant":[
        "Saint-Fr\u00e9zal",
        "Saint-Fr\u00e9zal-d\u2019Albuges"
    ],
    "wof:name":"Saint-Frezal-d'Albuges",
    "wof:placetype":"locality"
},
  "geometry": {"coordinates":[3.76849,44.563],"type":"Point"}
}