{
  "type": "Feature",
  "properties": {
    "gn:admin1_code":"75",
    "gn:admin2_code":"19",
    "gn:admin3_code":"193",
    "gn:admin4_code":"19136",
    "gn:asciiname":"Celle",
    "gn:country_code":"FR",
    "gn:dem":887,
    "gn:feature_class":"P",
    "gn:feature_code":"PPL",
    "gn:name":"Celle",
    "gn:population":0,
    "gn:timezone":"Europe/Paris",
    "iso:country":"FR",
    "wof:name":"Celle",
    "wof:placetype":"locality"
},
  "geometry": {"coordinates":[2.0649,45.58875],"type":"Point"}
}