{
  "type": "Feature",
  "properties": {
    "gn:admin1_code":"76",
    "gn:admin2_code":"48",
    "gn:admin3_code":"482",
    "gn:admin4_code":"48048",
    "gn:asciiname":"Laubarnes",
    "gn:country_code":"FR",
    "gn:dem":1171,
    "gn:feature_class":"P",
    "gn:feature_code":"PPLL",
    "gn:name":"Laubarn\u00e8s",
    "gn:population":0,
    "gn:timezone":"Europe/Paris",
    "iso:country":"FR",
    "name:fra_x_preferred":[
        "Laubernes"
    ],
    "wof:name":"Laubarnes",
    "wof:placetype":"locality"
},
  "geometry": {"coordinates":[3.80831,44.65834],"type":"Point"}
}