{
  "type": "Feature",
  "properties": {
    "frgov:code_epci":"200035632",
    "frgov:insee_arr":"3",
    "frgov:insee_com":"32093",
    "frgov:insee_dep":"32",
    "frgov:insee_reg":"76",
    "frgov:nom_com":"Caumont",
    "frgov:nom_com_m":"CAUMONT",
    "frgov:nom_dep":"GERS",
    "frgov:nom_reg":"OCCITANIE",
    "frgov:statut":"Commune simple",
    "gn:admin1_code":"76",
    "gn:admin2_code":"32",
    "gn:admin3_code":"323",
    "gn:admin4_code":"32093",
    "gn:asciiname":"Caumont",
    "gn:country_code":"FR",
    "gn:dem":137,
    "gn:feature_class":"P",
    "gn:feature_code":"PPL",
    "gn:name":"Caumont",
    "gn:population":0,
    "gn:timezone":"Europe/Paris",
    "iso:country":"FR",
    "name:bre_x_preferred":[
        "Caumont"
    ],
    "name:cat_x_preferred":[
        "Caumont"
    ],
    "name:ceb_x_preferred":[
        "Caumont"
    ],
    "name:deu_x_preferred":[
        "Caumont"
    ],
    "name:fra_x_preferred":[
        "Caumont"
    ],
    "name:hye_x_preferred":[
        "\u053f\u0578\u0574\u0578\u0576"
    ],
    "name:ita_x_preferred":[
        "Caumont"
    ],
    "name:nds_x_preferred":[
        "Caumont"
    ],
    "name:nld_x_preferred":[
        "Caumont"
    ],
    "name:oci_x_preferred":[
        "Calmont/Caumont/Chaumont"
    ],
    "name:pms_x_preferred":[
        "Caumont"
    ],
    "name:pol_x_preferred":[
        "Caumont"
    ],
    "name:rus_x_preferred":[
        "\u041a\u043e\u043c\u043e\u043d"
    ],
    "name:rus_x_variant":[
        "\u041a\u043e\u043c\u043e\u043d"
    ],
    "name:slk_x_preferred":[
        "Caumont"
    ],
    "name:spa_x_preferred":[
        "Caumont"
    ],
    "name:srp_x_preferred":[
        "\u041a\u043e\u043c\u043e\u043d"
    ],
    "name:swe_x_preferred":[
        "Caumont"
    ],
    "name:ukr_x_preferred":[
        "\u041a\u043e\u043c\u043e\u043d"
    ],
    "name:zho_x_preferred":[
        "\u79d1\u8499"
    ],
    "qs:a0":"France",
    "qs:a1":"GERS",
    "qs:a1_lc":"32",
    "qs:a1r":"MIDI-PYRENEES",
    "qs:a1r_lc":"73",
    "qs:a2_lc":"24",
    "qs:a2r_lc":"3",
    "qs:adm0":"France",
    "qs:adm0_a3":"FRA",
    "qs:la":"CAUMONT",
    "qs:la_lc":"32093",
    "qs:level":"localadmin",
    "qs:type":"Commune simple",
    "wof:coterminous":[
        404370637
    ],
    "wof:name":"Caumont",
    "wof:placetype":"locality",
    "wof:placetype_local":"Commune simple"
},
  "geometry": {"coordinates":[-0.11041,43.68847],"type":"Point"}
}