{
  "type": "Feature",
  "properties": {
    "gn:admin1_code":"76",
    "gn:admin2_code":"32",
    "gn:admin3_code":"323",
    "gn:admin4_code":"32093",
    "gn:asciiname":"Caumont",
    "gn:country_code":"FR",
    "gn:dem":137,
    "gn:feature_class":"P",
    "gn:feature_code":"PPL",
    "gn:name":"Caumont",
    "gn:population":0,
    "gn:timezone":"Europe/Paris",
    "iso:country":"FR",
    "wof:name":"Caumont",
    "wof:placetype":"locality"
},
  "geometry": {"coordinates":[-0.11041,43.68847],"type":"Point"}
}