{
  "type": "Feature",
  "properties": {
    "gn:admin1_code":"76",
    "gn:admin2_code":"81",
    "gn:admin3_code":"811",
    "gn:admin4_code":"81206",
    "gn:asciiname":"Penne-du-Tarn",
    "gn:country_code":"FR",
    "gn:dem":463,
    "gn:feature_class":"P",
    "gn:feature_code":"PPL",
    "gn:name":"Penne-du-Tarn",
    "gn:population":0,
    "gn:timezone":"Europe/Paris",
    "iso:country":"FR",
    "wof:name":"Penne-du-Tarn",
    "wof:placetype":"locality"
},
  "geometry": {"coordinates":[1.76481,44.05647],"type":"Point"}
}