{
  "type": "Feature",
  "properties": {
    "gn:admin1_code":"93",
    "gn:admin2_code":"05",
    "gn:admin3_code":"052",
    "gn:admin4_code":"05039",
    "gn:asciiname":"Aubessagne",
    "gn:country_code":"FR",
    "gn:dem":934,
    "gn:feature_class":"P",
    "gn:feature_code":"PPL",
    "gn:name":"Aubessagne",
    "gn:population":0,
    "gn:timezone":"Europe/Paris",
    "iso:country":"FR",
    "name:deu_x_preferred":[
        "Aubessagne"
    ],
    "name:fra_x_preferred":[
        "Aubessagne"
    ],
    "name:ltz_x_preferred":[
        "Aubessagne"
    ],
    "name:pol_x_preferred":[
        "Aubessagne"
    ],
    "name:spa_x_preferred":[
        "Aubessagne"
    ],
    "wof:name":"Aubessagne",
    "wof:placetype":"locality"
},
  "geometry": {"coordinates":[6.01293,44.75349],"type":"Point"}
}