{
  "type": "Feature",
  "properties": {
    "gn:admin1_code":"27",
    "gn:admin2_code":"25",
    "gn:admin3_code":"253",
    "gn:admin4_code":"25601",
    "gn:asciiname":"Villedieu-le-Camp",
    "gn:country_code":"FR",
    "gn:dem":645,
    "gn:feature_class":"P",
    "gn:feature_code":"PPLL",
    "gn:name":"Villedieu-le-Camp",
    "gn:population":0,
    "gn:timezone":"Europe/Paris",
    "iso:country":"FR",
    "wof:name":"Villedieu-le-Camp",
    "wof:placetype":"locality"
},
  "geometry": {"coordinates":[6.39177,47.18767],"type":"Point"}
}