{
  "type": "Feature",
  "properties": {
    "gn:admin1_code":"76",
    "gn:admin2_code":"81",
    "gn:admin3_code":"812",
    "gn:admin4_code":"81049",
    "gn:asciiname":"Cahuzac",
    "gn:country_code":"FR",
    "gn:dem":271,
    "gn:feature_class":"P",
    "gn:feature_code":"PPL",
    "gn:name":"Cahuzac",
    "gn:population":282,
    "gn:timezone":"Europe/Paris",
    "iso:country":"FR",
    "name:ceb_x_preferred":[
        "Cahuzac"
    ],
    "name:deu_x_preferred":[
        "Cahuzac"
    ],
    "name:fra_x_preferred":[
        "Cahuzac"
    ],
    "name:ita_x_preferred":[
        "Cahuzac"
    ],
    "name:nds_x_preferred":[
        "Cahuzac"
    ],
    "name:nld_x_preferred":[
        "Cahuzac"
    ],
    "name:oci_x_preferred":[
        "Ca\u00fcsac"
    ],
    "name:pms_x_preferred":[
        "Cahuzac"
    ],
    "name:pol_x_preferred":[
        "Cahuzac"
    ],
    "name:por_x_preferred":[
        "Cahuzac"
    ],
    "name:rus_x_preferred":[
        "\u041a\u0430\u044e\u0437\u0430\u043a"
    ],
    "name:slk_x_preferred":[
        "Cahuzac"
    ],
    "name:spa_x_preferred":[
        "Cahuzac"
    ],
    "name:srp_x_preferred":[
        "\u041a\u0430\u0438\u0437\u0430\u043a"
    ],
    "name:swe_x_preferred":[
        "Cahuzac"
    ],
    "name:ukr_x_preferred":[
        "\u041a\u0430\u044e\u0437\u0430\u043a"
    ],
    "wof:name":"Cahuzac",
    "wof:placetype":"locality",
    "wof:population":282
},
  "geometry": {"coordinates":[2.08015,43.46919000000001],"type":"Point"}
}