{
  "type": "Feature",
  "properties": {
    "frgov:code_epci":"243100567",
    "frgov:insee_arr":"2",
    "frgov:insee_com":"81049",
    "frgov:insee_dep":"81",
    "frgov:insee_reg":"76",
    "frgov:nom_com":"Cahuzac",
    "frgov:nom_com_m":"CAHUZAC",
    "frgov:nom_dep":"TARN",
    "frgov:nom_reg":"OCCITANIE",
    "frgov:statut":"Commune simple",
    "gn:admin1_code":"76",
    "gn:admin2_code":"81",
    "gn:admin3_code":"812",
    "gn:admin4_code":"81049",
    "gn:asciiname":"Cahuzac",
    "gn:country_code":"FR",
    "gn:dem":271,
    "gn:feature_class":"P",
    "gn:feature_code":"PPL",
    "gn:name":"Cahuzac",
    "gn:population":282,
    "gn:timezone":"Europe/Paris",
    "iso:country":"FR",
    "name:ceb_x_preferred":[
        "Cahuzac"
    ],
    "name:deu_x_preferred":[
        "Cahuzac"
    ],
    "name:fra_x_preferred":[
        "Cahuzac"
    ],
    "name:ita_x_preferred":[
        "Cahuzac"
    ],
    "name:nds_x_preferred":[
        "Cahuzac"
    ],
    "name:nld_x_preferred":[
        "Cahuzac"
    ],
    "name:oci_x_preferred":[
        "Ca\u00fcsac"
    ],
    "name:pms_x_preferred":[
        "Cahuzac"
    ],
    "name:pol_x_preferred":[
        "Cahuzac"
    ],
    "name:por_x_preferred":[
        "Cahuzac"
    ],
    "name:rus_x_preferred":[
        "\u041a\u0430\u044e\u0437\u0430\u043a"
    ],
    "name:slk_x_preferred":[
        "Cahuzac"
    ],
    "name:spa_x_preferred":[
        "Cahuzac"
    ],
    "name:srp_x_preferred":[
        "\u041a\u0430\u0438\u0437\u0430\u043a"
    ],
    "name:swe_x_preferred":[
        "Cahuzac"
    ],
    "name:ukr_x_preferred":[
        "\u041a\u0430\u044e\u0437\u0430\u043a"
    ],
    "qs:a0":"France",
    "qs:a1":"TARN",
    "qs:a1_lc":"81",
    "qs:a1r":"MIDI-PYRENEES",
    "qs:a1r_lc":"73",
    "qs:a2_lc":"11",
    "qs:a2r_lc":"2",
    "qs:adm0":"France",
    "qs:adm0_a3":"FRA",
    "qs:la":"CAHUZAC",
    "qs:la_lc":"81049",
    "qs:level":"localadmin",
    "qs:type":"Commune simple",
    "wof:coterminous":[
        404391479
    ],
    "wof:name":"Cahuzac",
    "wof:placetype":"locality",
    "wof:placetype_local":"Commune simple",
    "wof:population":282
},
  "geometry": {"coordinates":[2.08015,43.46919],"type":"Point"}
}