{
  "type": "Feature",
  "properties": {
    "gn:admin1_code":"28",
    "gn:admin2_code":"61",
    "gn:admin3_code":"613",
    "gn:admin4_code":"61440",
    "gn:asciiname":"La Raciniere",
    "gn:country_code":"FR",
    "gn:dem":225,
    "gn:feature_class":"P",
    "gn:feature_code":"PPL",
    "gn:name":"La Racini\u00e8re",
    "gn:population":0,
    "gn:timezone":"Europe/Paris",
    "iso:country":"FR",
    "wof:name":"La Raciniere",
    "wof:placetype":"locality"
},
  "geometry": {"coordinates":[0.66919,48.73094],"type":"Point"}
}