{
  "type": "Feature",
  "properties": {
    "gn:admin1_code":"24",
    "gn:admin2_code":"28",
    "gn:admin3_code":"281",
    "gn:admin4_code":"28339.0",
    "gn:asciiname":"Le Plessis-le-Franc",
    "gn:country_code":"FR",
    "gn:dem":180,
    "gn:feature_class":"P",
    "gn:feature_code":"PPL",
    "gn:name":"Le Plessis-le-Franc",
    "gn:population":0,
    "gn:timezone":"Europe/Paris",
    "iso:country":"FR",
    "name:und_x_variant":[
        "Le Plessis",
        "Le Plessis-le-Franc"
    ],
    "wof:name":"Le Plessis-le-Franc",
    "wof:placetype":"locality"
},
  "geometry": {"coordinates":[1.25083,48.41307000000001],"type":"Point"}
}