{
  "type": "Feature",
  "properties": {
    "gn:admin1_code":"27",
    "gn:admin2_code":"21",
    "gn:admin3_code":"213",
    "gn:admin4_code":"21641",
    "gn:asciiname":"Les Malmaisons",
    "gn:country_code":"FR",
    "gn:dem":364,
    "gn:feature_class":"P",
    "gn:feature_code":"PPL",
    "gn:name":"Les Malmaisons",
    "gn:population":0,
    "gn:timezone":"Europe/Paris",
    "iso:country":"FR",
    "wof:name":"Les Malmaisons",
    "wof:placetype":"locality"
},
  "geometry": {"coordinates":[4.4368,47.65425],"type":"Point"}
}