{
  "type": "Feature",
  "properties": {
    "gn:admin1_code":"32",
    "gn:admin2_code":"02",
    "gn:admin3_code":"022",
    "gn:admin4_code":"2140.0",
    "gn:asciiname":"Marivaux",
    "gn:country_code":"FR",
    "gn:dem":74,
    "gn:feature_class":"P",
    "gn:feature_code":"PPL",
    "gn:name":"Marivaux",
    "gn:population":0,
    "gn:timezone":"Europe/Paris",
    "iso:country":"FR",
    "wof:name":"Marivaux",
    "wof:placetype":"locality"
},
  "geometry": {"coordinates":[3.12289,49.51933],"type":"Point"}
}