{
  "type": "Feature",
  "properties": {
    "iso:country":"FR",
    "name:eng_x_preferred":[
        "Italie"
    ],
    "name:fra_x_preferred":[
        "Italie"
    ],
    "wof:name":"Italie",
    "wof:placetype":"neighbourhood"
},
  "geometry": {"coordinates":[-1.66784602376848,48.08549844313342],"type":"Point"}
}