{
  "type": "Feature",
  "properties": {
    "gn:admin1_code":"24",
    "gn:admin2_code":"28",
    "gn:admin3_code":"282",
    "gn:admin4_code":"28019.0",
    "gn:asciiname":"Baigneaux",
    "gn:country_code":"FR",
    "gn:dem":132,
    "gn:feature_class":"P",
    "gn:feature_code":"PPL",
    "gn:name":"Baigneaux",
    "gn:population":0,
    "gn:timezone":"Europe/Paris",
    "iso:country":"FR",
    "name:ceb_x_preferred":[
        "Baigneaux"
    ],
    "name:deu_x_preferred":[
        "Baigneaux"
    ],
    "name:fra_x_preferred":[
        "Baigneaux"
    ],
    "name:ita_x_preferred":[
        "Baigneaux"
    ],
    "name:ltz_x_preferred":[
        "Baigneaux"
    ],
    "name:nds_x_preferred":[
        "Baigneaux"
    ],
    "name:nld_x_preferred":[
        "Baigneaux"
    ],
    "name:pms_x_preferred":[
        "Baigneaux"
    ],
    "name:pol_x_preferred":[
        "Baigneaux"
    ],
    "name:por_x_preferred":[
        "Baigneaux"
    ],
    "name:ron_x_preferred":[
        "Baigneaux"
    ],
    "name:rus_x_preferred":[
        "\u0411\u0435\u043d\u044c\u0451"
    ],
    "name:slk_x_preferred":[
        "Baigneaux"
    ],
    "name:spa_x_preferred":[
        "Baigneaux"
    ],
    "name:swe_x_preferred":[
        "Baigneaux"
    ],
    "wof:name":"Baigneaux",
    "wof:placetype":"locality"
},
  "geometry": {"coordinates":[1.60872,48.18409000000001],"type":"Point"}
}