{
  "type": "Feature",
  "properties": {
    "iso:country":"FR",
    "name:eng_x_preferred":[
        "Les Varennes"
    ],
    "name:fra_x_preferred":[
        "Les Varennes"
    ],
    "wof:name":"Les Varennes",
    "wof:placetype":"neighbourhood"
},
  "geometry": {"coordinates":[2.28199321379816,48.82921346223421],"type":"Point"}
}