{
  "type": "Feature",
  "properties": {
    "gn:admin1_code":"53",
    "gn:admin2_code":"29",
    "gn:admin3_code":"293",
    "gn:admin4_code":"29163",
    "gn:asciiname":"Kervenarhant",
    "gn:country_code":"FR",
    "gn:dem":122,
    "gn:feature_class":"P",
    "gn:feature_code":"PPL",
    "gn:name":"Kerv\u00e9narhant",
    "gn:population":0,
    "gn:timezone":"Europe/Paris",
    "iso:country":"FR",
    "wof:name":"Kervenarhant",
    "wof:placetype":"locality"
},
  "geometry": {"coordinates":[-3.87533,48.533],"type":"Point"}
}