{
  "type": "Feature",
  "properties": {
    "gn:admin1_code":"75",
    "gn:admin2_code":"16",
    "gn:admin3_code":"163",
    "gn:admin4_code":"16253",
    "gn:asciiname":"Embourie",
    "gn:country_code":"FR",
    "gn:dem":123,
    "gn:feature_class":"P",
    "gn:feature_code":"PPL",
    "gn:name":"Embourie",
    "gn:population":0,
    "gn:timezone":"Europe/Paris",
    "iso:country":"FR",
    "wof:name":"Embourie",
    "wof:placetype":"locality"
},
  "geometry": {"coordinates":[0.0408,46.03999],"type":"Point"}
}