{
  "type": "Feature",
  "properties": {
    "gn:admin1_code":"93",
    "gn:admin2_code":"05",
    "gn:admin3_code":"051",
    "gn:admin4_code":"05151",
    "gn:asciiname":"Sachas",
    "gn:country_code":"FR",
    "gn:dem":1381,
    "gn:feature_class":"P",
    "gn:feature_code":"PPL",
    "gn:name":"Sachas",
    "gn:population":0,
    "gn:timezone":"Europe/Paris",
    "iso:country":"FR",
    "wof:name":"Sachas",
    "wof:placetype":"locality"
},
  "geometry": {"coordinates":[6.58785,44.87029],"type":"Point"}
}