{
  "type": "Feature",
  "properties": {
    "iso:country":"FR",
    "name:eng_x_preferred":[
        "Baud-Chardonnet"
    ],
    "name:fra_x_preferred":[
        "Baud-Chardonnet"
    ],
    "wof:name":"Baud-Chardonnet",
    "wof:placetype":"neighbourhood"
},
  "geometry": {"coordinates":[-1.64853410914443,48.10875278192102],"type":"Point"}
}