{
  "type": "Feature",
  "properties": {
    "gn:admin1_code":"24",
    "gn:admin2_code":"28",
    "gn:admin3_code":"281",
    "gn:admin4_code":"28290",
    "gn:asciiname":"Jorand",
    "gn:country_code":"FR",
    "gn:dem":181,
    "gn:feature_class":"P",
    "gn:feature_code":"PPL",
    "gn:name":"Jorand",
    "gn:population":0,
    "gn:timezone":"Europe/Paris",
    "iso:country":"FR",
    "wof:name":"Jorand",
    "wof:placetype":"locality"
},
  "geometry": {"coordinates":[1.24917,48.39464],"type":"Point"}
}