{
  "type": "Feature",
  "properties": {
    "gn:admin1_code":"24",
    "gn:admin2_code":"18",
    "gn:admin3_code":"181",
    "gn:admin4_code":"18256",
    "gn:asciiname":"Les Cottereaux",
    "gn:country_code":"FR",
    "gn:dem":237,
    "gn:feature_class":"P",
    "gn:feature_code":"PPL",
    "gn:name":"Les Cottereaux",
    "gn:population":0,
    "gn:timezone":"Europe/Paris",
    "iso:country":"FR",
    "wof:name":"Les Cottereaux",
    "wof:placetype":"locality"
},
  "geometry": {"coordinates":[2.72486,47.41086],"type":"Point"}
}