{
  "type": "Feature",
  "properties": {
    "gn:admin1_code":"24",
    "gn:admin2_code":"45",
    "gn:admin3_code":"452",
    "gn:admin4_code":"45335",
    "gn:asciiname":"Les Quatre Vents",
    "gn:country_code":"FR",
    "gn:dem":125,
    "gn:feature_class":"P",
    "gn:feature_code":"PPL",
    "gn:name":"Les Quatre Vents",
    "gn:population":0,
    "gn:timezone":"Europe/Paris",
    "iso:country":"FR",
    "name:und_x_variant":[
        "Les 4 Vents",
        "Les Quatre Vents"
    ],
    "wof:name":"Les Quatre Vents",
    "wof:placetype":"locality"
},
  "geometry": {"coordinates":[2.11952,47.74104000000001],"type":"Point"}
}