{
  "type": "Feature",
  "properties": {
    "gn:admin1_code":"75",
    "gn:admin2_code":"47",
    "gn:admin3_code":"472",
    "gn:admin4_code":"47151",
    "gn:asciiname":"Bernac",
    "gn:country_code":"FR",
    "gn:dem":156,
    "gn:feature_class":"P",
    "gn:feature_code":"PPL",
    "gn:name":"Bernac",
    "gn:population":0,
    "gn:timezone":"Europe/Paris",
    "iso:country":"FR",
    "name:ceb_x_preferred":[
        "Bernac"
    ],
    "name:deu_x_preferred":[
        "Bernac"
    ],
    "name:fra_x_preferred":[
        "Bernac"
    ],
    "name:ita_x_preferred":[
        "Bernac"
    ],
    "name:nds_x_preferred":[
        "Bernac"
    ],
    "name:nld_x_preferred":[
        "Bernac"
    ],
    "name:oci_x_preferred":[
        "Bernac"
    ],
    "name:pol_x_preferred":[
        "Bernac"
    ],
    "name:por_x_preferred":[
        "Bernac"
    ],
    "name:rus_x_preferred":[
        "\u0411\u0435\u0440\u043d\u0430\u043a"
    ],
    "name:scn_x_preferred":[
        "Bernac"
    ],
    "name:slk_x_preferred":[
        "Bernac"
    ],
    "name:spa_x_preferred":[
        "Bernac"
    ],
    "name:srp_x_preferred":[
        "\u0411\u0435\u0440\u043d\u0430\u043a"
    ],
    "name:swe_x_preferred":[
        "Bernac"
    ],
    "name:ukr_x_preferred":[
        "\u0411\u0435\u0440\u043d\u0430\u043a"
    ],
    "wof:name":"Bernac",
    "wof:placetype":"locality"
},
  "geometry": {"coordinates":[0.32922,44.72188],"type":"Point"}
}