{
  "type": "Feature",
  "properties": {
    "gn:admin1_code":"75",
    "gn:admin2_code":"47",
    "gn:admin3_code":"472",
    "gn:admin4_code":"47151",
    "gn:asciiname":"Bernac",
    "gn:country_code":"FR",
    "gn:dem":156,
    "gn:feature_class":"P",
    "gn:feature_code":"PPL",
    "gn:name":"Bernac",
    "gn:population":0,
    "gn:timezone":"Europe/Paris",
    "iso:country":"FR",
    "wof:name":"Bernac",
    "wof:placetype":"locality"
},
  "geometry": {"coordinates":[0.32922,44.72188],"type":"Point"}
}