{
  "type": "Feature",
  "properties": {
    "gn:admin1_code":"53",
    "gn:admin2_code":"35",
    "gn:admin3_code":"354",
    "gn:admin4_code":"35288",
    "gn:asciiname":"Bellevue - La Madeleine",
    "gn:country_code":"FR",
    "gn:dem":29,
    "gn:elevation":"30.0",
    "gn:feature_class":"P",
    "gn:feature_code":"PPL",
    "gn:name":"Bellevue - La Madeleine",
    "gn:population":0,
    "gn:timezone":"Europe/Paris",
    "iso:country":"FR",
    "wof:name":"Bellevue - La Madeleine",
    "wof:placetype":"locality"
},
  "geometry": {"coordinates":[-1.99428,48.62613],"type":"Point"}
}