{
  "type": "Feature",
  "properties": {
    "gn:admin1_code":"93",
    "gn:admin2_code":"05",
    "gn:admin3_code":"052",
    "gn:admin4_code":"05165",
    "gn:asciiname":"Les Arnauds",
    "gn:country_code":"FR",
    "gn:dem":767,
    "gn:feature_class":"P",
    "gn:feature_code":"PPL",
    "gn:name":"Les Arnauds",
    "gn:population":0,
    "gn:timezone":"Europe/Paris",
    "iso:country":"FR",
    "wof:name":"Les Arnauds",
    "wof:placetype":"locality"
},
  "geometry": {"coordinates":[5.8146,44.4126],"type":"Point"}
}