{
  "type": "Feature",
  "properties": {
    "gn:admin1_code":"76",
    "gn:admin2_code":"30",
    "gn:admin3_code":"303",
    "gn:admin4_code":"30139",
    "gn:asciiname":"Montjardin",
    "gn:country_code":"FR",
    "gn:dem":920,
    "gn:feature_class":"P",
    "gn:feature_code":"PPL",
    "gn:name":"Montjardin",
    "gn:population":0,
    "gn:timezone":"Europe/Paris",
    "iso:country":"FR",
    "wof:name":"Montjardin",
    "wof:placetype":"locality"
},
  "geometry": {"coordinates":[3.39428,44.12442],"type":"Point"}
}