{
  "type": "Feature",
  "properties": {
    "gn:admin1_code":"76",
    "gn:admin2_code":"30",
    "gn:admin3_code":"303",
    "gn:admin4_code":"30139",
    "gn:asciiname":"Montjardin",
    "gn:country_code":"FR",
    "gn:dem":920,
    "gn:feature_class":"P",
    "gn:feature_code":"PPL",
    "gn:name":"Montjardin",
    "gn:population":0,
    "gn:timezone":"Europe/Paris",
    "iso:country":"FR",
    "name:cat_x_preferred":[
        "Montjardin"
    ],
    "name:ceb_x_preferred":[
        "Montjardin"
    ],
    "name:deu_x_preferred":[
        "Montjardin"
    ],
    "name:eus_x_preferred":[
        "Montjardin"
    ],
    "name:fra_x_preferred":[
        "Montjardin"
    ],
    "name:hun_x_preferred":[
        "Montjardin"
    ],
    "name:hye_x_preferred":[
        "\u0544\u0578\u0576\u056a\u0561\u0580\u0564\u0565\u0576"
    ],
    "name:ita_x_preferred":[
        "Montjardin"
    ],
    "name:kaz_x_preferred":[
        "\u041c\u043e\u043d\u0436\u0430\u0440\u0434\u0435\u043d"
    ],
    "name:lat_x_preferred":[
        "Montjardin"
    ],
    "name:lmo_x_preferred":[
        "Montjardin"
    ],
    "name:mlg_x_preferred":[
        "Montjardin"
    ],
    "name:msa_x_preferred":[
        "Montjardin"
    ],
    "name:nld_x_preferred":[
        "Montjardin"
    ],
    "name:oci_x_preferred":[
        "Montjardin"
    ],
    "name:pms_x_preferred":[
        "Montjardin"
    ],
    "name:pol_x_preferred":[
        "Montjardin"
    ],
    "name:por_x_preferred":[
        "Montjardin"
    ],
    "name:ron_x_preferred":[
        "Montjardin"
    ],
    "name:rus_x_preferred":[
        "\u041c\u043e\u043d\u0436\u0430\u0440\u0434\u0435\u043d"
    ],
    "name:slk_x_preferred":[
        "Montjardin"
    ],
    "name:spa_x_preferred":[
        "Montjardin"
    ],
    "name:swe_x_preferred":[
        "Montjardin"
    ],
    "name:ukr_x_preferred":[
        "\u041c\u043e\u043d\u0436\u0430\u0440\u0434\u0435\u043d"
    ],
    "name:vie_x_preferred":[
        "Montjardin"
    ],
    "name:vol_x_preferred":[
        "Montjardin"
    ],
    "name:war_x_preferred":[
        "Montjardin"
    ],
    "name:zho_x_preferred":[
        "\u8499\u96c5\u5c14\u4e39"
    ],
    "wof:name":"Montjardin",
    "wof:placetype":"locality"
},
  "geometry": {"coordinates":[3.39428,44.12442],"type":"Point"}
}