{
  "type": "Feature",
  "properties": {
    "gn:admin1_code":"11",
    "gn:admin2_code":"77",
    "gn:admin3_code":"773",
    "gn:admin4_code":"77272",
    "gn:asciiname":"Landoy",
    "gn:country_code":"FR",
    "gn:dem":134,
    "gn:feature_class":"P",
    "gn:feature_code":"PPL",
    "gn:name":"Landoy",
    "gn:population":0,
    "gn:timezone":"Europe/Paris",
    "iso:country":"FR",
    "wof:name":"Landoy",
    "wof:placetype":"locality"
},
  "geometry": {"coordinates":[3.16675,48.54009],"type":"Point"}
}