{
  "type": "Feature",
  "properties": {
    "gn:admin1_code":"32",
    "gn:admin2_code":"62",
    "gn:admin3_code":"623",
    "gn:admin4_code":"62105",
    "gn:asciiname":"Houllefort",
    "gn:country_code":"FR",
    "gn:dem":40,
    "gn:feature_class":"P",
    "gn:feature_code":"PPL",
    "gn:name":"Houllefort",
    "gn:population":0,
    "gn:timezone":"Europe/Paris",
    "iso:country":"FR",
    "wof:name":"Houllefort",
    "wof:placetype":"locality"
},
  "geometry": {"coordinates":[1.77309,50.75921],"type":"Point"}
}