{
  "type": "Feature",
  "properties": {
    "gn:admin1_code":"84",
    "gn:admin2_code":"15",
    "gn:admin3_code":"151",
    "gn:admin4_code":"15167.0",
    "gn:asciiname":"Le Sartre",
    "gn:country_code":"FR",
    "gn:dem":547,
    "gn:feature_class":"P",
    "gn:feature_code":"PPL",
    "gn:name":"Le Sartre",
    "gn:population":0,
    "gn:timezone":"Europe/Paris",
    "iso:country":"FR",
    "wof:name":"Le Sartre",
    "wof:placetype":"locality"
},
  "geometry": {"coordinates":[2.21225,44.805],"type":"Point"}
}