{
  "type": "Feature",
  "properties": {
    "gn:admin1_code":"94",
    "gn:admin2_code":"2B",
    "gn:admin3_code":"2B2",
    "gn:admin4_code":"2B281",
    "gn:asciiname":"Crosciano",
    "gn:country_code":"FR",
    "gn:dem":68,
    "gn:feature_class":"P",
    "gn:feature_code":"PPL",
    "gn:name":"Crosciano",
    "gn:population":0,
    "gn:timezone":"Europe/Paris",
    "iso:country":"FR",
    "wof:name":"Crosciano",
    "wof:placetype":"locality"
},
  "geometry": {"coordinates":[9.46795,42.81493],"type":"Point"}
}