{
  "type": "Feature",
  "properties": {
    "gn:admin1_code":"27",
    "gn:admin2_code":"58",
    "gn:admin3_code":"583",
    "gn:admin4_code":"58095",
    "gn:asciiname":"Saixy",
    "gn:country_code":"FR",
    "gn:dem":192,
    "gn:feature_class":"P",
    "gn:feature_code":"PPL",
    "gn:name":"Saixy",
    "gn:population":0,
    "gn:timezone":"Europe/Paris",
    "iso:country":"FR",
    "name:und_x_variant":[
        "Saizy",
        "Saixy"
    ],
    "wof:name":"Saixy",
    "wof:placetype":"locality"
},
  "geometry": {"coordinates":[3.50361,46.801],"type":"Point"}
}