{
  "type": "Feature",
  "properties": {
    "gn:admin1_code":"75",
    "gn:admin2_code":"19",
    "gn:admin3_code":"193",
    "gn:admin4_code":"19256",
    "gn:asciiname":"Janconie",
    "gn:cc2":"FR",
    "gn:country_code":"FR",
    "gn:dem":598,
    "gn:feature_class":"P",
    "gn:feature_code":"PPL",
    "gn:name":"Janconie",
    "gn:population":0,
    "gn:timezone":"Europe/Paris",
    "iso:country":"FR",
    "name:und_x_variant":[
        "La Janconnie",
        "Janconie"
    ],
    "wof:name":"Janconie",
    "wof:placetype":"locality"
},
  "geometry": {"coordinates":[2.31667,45.35],"type":"Point"}
}