{
  "type": "Feature",
  "properties": {
    "gn:admin1_code":"27",
    "gn:admin2_code":"58",
    "gn:admin3_code":"583",
    "gn:admin4_code":"58207",
    "gn:asciiname":"Pinay",
    "gn:country_code":"FR",
    "gn:dem":249,
    "gn:feature_class":"P",
    "gn:feature_code":"PPL",
    "gn:name":"Pinay",
    "gn:population":0,
    "gn:timezone":"Europe/Paris",
    "iso:country":"FR",
    "name:deu_x_preferred":[
        "Pinay"
    ],
    "name:jpn_x_preferred":[
        "\u30d4\u30cd\u30fc"
    ],
    "name:nds_x_preferred":[
        "Pinay"
    ],
    "name:ukr_x_preferred":[
        "\u041f\u0456\u043d\u0435"
    ],
    "wof:name":"Pinay",
    "wof:placetype":"locality"
},
  "geometry": {"coordinates":[3.13528,47.10273],"type":"Point"}
}