{
  "type": "Feature",
  "properties": {
    "gn:admin1_code":"75",
    "gn:admin2_code":"16",
    "gn:admin3_code":"162",
    "gn:admin4_code":"16339",
    "gn:asciiname":"Saint-Medard",
    "gn:country_code":"FR",
    "gn:dem":103,
    "gn:feature_class":"P",
    "gn:feature_code":"PPL",
    "gn:name":"Saint-M\u00e9dard",
    "gn:population":0,
    "gn:timezone":"Europe/Paris",
    "iso:country":"FR",
    "name:und_x_variant":[
        "Saint-M\u00e9dard-de-Rouillac",
        "Saint-M\u00e9dard"
    ],
    "wof:name":"Saint-Medard",
    "wof:placetype":"locality"
},
  "geometry": {"coordinates":[-0.09639,45.85128],"type":"Point"}
}