{
  "type": "Feature",
  "properties": {
    "gn:admin1_code":"27",
    "gn:admin2_code":"58",
    "gn:admin3_code":"583",
    "gn:admin4_code":"58095",
    "gn:asciiname":"Brain",
    "gn:country_code":"FR",
    "gn:dem":219,
    "gn:feature_class":"P",
    "gn:feature_code":"PPL",
    "gn:name":"Brain",
    "gn:population":0,
    "gn:timezone":"Europe/Paris",
    "iso:country":"FR",
    "wof:name":"Brain",
    "wof:placetype":"locality"
},
  "geometry": {"coordinates":[3.4975,46.81827],"type":"Point"}
}