{
  "type": "Feature",
  "properties": {
    "gn:admin1_code":"75",
    "gn:admin2_code":"86",
    "gn:admin3_code":"861",
    "gn:admin4_code":"86151",
    "gn:asciiname":"La Brise",
    "gn:country_code":"FR",
    "gn:dem":69,
    "gn:feature_class":"P",
    "gn:feature_code":"PPL",
    "gn:name":"La Brise",
    "gn:population":0,
    "gn:timezone":"Europe/Paris",
    "iso:country":"FR",
    "wof:name":"La Brise",
    "wof:placetype":"locality"
},
  "geometry": {"coordinates":[0.25,46.96667],"type":"Point"}
}