{
  "type": "Feature",
  "properties": {
    "gn:admin1_code":"24",
    "gn:admin2_code":"36",
    "gn:admin3_code":"361",
    "gn:admin4_code":"36173",
    "gn:asciiname":"Haut Coudreau",
    "gn:country_code":"FR",
    "gn:dem":111,
    "gn:feature_class":"P",
    "gn:feature_code":"PPL",
    "gn:name":"Haut Coudreau",
    "gn:population":0,
    "gn:timezone":"Europe/Paris",
    "iso:country":"FR",
    "wof:name":"Haut Coudreau",
    "wof:placetype":"locality"
},
  "geometry": {"coordinates":[1.2557,46.6949],"type":"Point"}
}