{
  "type": "Feature",
  "properties": {
    "gn:admin1_code":"75",
    "gn:admin2_code":"24",
    "gn:admin3_code":"243",
    "gn:admin4_code":"24401",
    "gn:asciiname":"Sainte-Eulalie-d'Ans",
    "gn:country_code":"FR",
    "gn:dem":136,
    "gn:feature_class":"P",
    "gn:feature_code":"PPL",
    "gn:name":"Sainte-Eulalie-d\u2019Ans",
    "gn:population":0,
    "gn:timezone":"Europe/Paris",
    "iso:country":"FR",
    "name:bug_x_preferred":[
        "Sainte-Eulalie-d'Ans"
    ],
    "name:ceb_x_preferred":[
        "Sainte-Eulalie-d'Ans"
    ],
    "name:deu_x_preferred":[
        "Sainte-Eulalie-d\u2019Ans"
    ],
    "name:eng_x_preferred":[
        "Sainte-Eulalie-dAns"
    ],
    "name:eus_x_preferred":[
        "Sainte-Eulalie-d'Ans"
    ],
    "name:fra_x_preferred":[
        "Sainte-Eulalie-d'Ans"
    ],
    "name:hun_x_preferred":[
        "Sainte-Eulalie-d\u2019Ans"
    ],
    "name:ita_x_preferred":[
        "Sainte-Eulalie-d'Ans"
    ],
    "name:kaz_x_preferred":[
        "\u0421\u0435\u043d\u0442-\u0415\u043b\u0430\u043b\u0438-\u0434'\u0410\u043d"
    ],
    "name:lat_x_preferred":[
        "Sainte-Eulalie-d'Ans"
    ],
    "name:ltz_x_preferred":[
        "Sainte-Eulalie-d'Ans"
    ],
    "name:mlg_x_preferred":[
        "Sainte-Eulalie-d'Ans"
    ],
    "name:msa_x_preferred":[
        "Sainte-Eulalie-d'Ans"
    ],
    "name:nld_x_preferred":[
        "Sainte-Eulalie-d'Ans"
    ],
    "name:pms_x_preferred":[
        "Sainte-Eulalie-d'Ans"
    ],
    "name:pol_x_preferred":[
        "Sainte-Eulalie-d\u2019Ans"
    ],
    "name:por_x_preferred":[
        "Sainte-Eulalie-d'Ans"
    ],
    "name:ron_x_preferred":[
        "Sainte-Eulalie-d'Ans"
    ],
    "name:rus_x_preferred":[
        "\u0421\u0435\u043d\u0442-\u042d\u043b\u0430\u043b\u0438-\u0434\u2019\u0410\u043d\u0441"
    ],
    "name:slk_x_preferred":[
        "Sainte-Eulalie-d\u2019Ans"
    ],
    "name:spa_x_preferred":[
        "Sainte-Eulalie-d'Ans"
    ],
    "name:swe_x_preferred":[
        "Sainte-Eulalie-d'Ans"
    ],
    "name:ukr_x_preferred":[
        "\u0421\u0435\u043d\u0442-\u0415\u043b\u0430\u043b\u0456-\u0434'\u0410\u043d"
    ],
    "name:und_x_variant":[
        "Sainte-Eulalie"
    ],
    "name:urd_x_preferred":[
        "\u0633\u06cc\u0646-\u06cc\u0644\u06d2-\u062f\u0646\u0633"
    ],
    "name:uzb_x_preferred":[
        "Sainte-Eulalie-d'Ans"
    ],
    "name:vie_x_preferred":[
        "Sainte-Eulalie-d'Ans"
    ],
    "name:vol_x_preferred":[
        "Sainte-Eulalie-d'Ans"
    ],
    "name:war_x_preferred":[
        "Sainte-Eulalie-d'Ans"
    ],
    "name:zho_x_preferred":[
        "\u5723\u5384\u62c9\u5229\u8036\u5f53"
    ],
    "wof:name":"Sainte-Eulalie-d'Ans",
    "wof:placetype":"locality"
},
  "geometry": {"coordinates":[1.02069,45.24569],"type":"Point"}
}