{
  "type": "Feature",
  "properties": {
    "gn:admin1_code":"75",
    "gn:admin2_code":"24",
    "gn:admin3_code":"243",
    "gn:admin4_code":"24401",
    "gn:asciiname":"Sainte-Eulalie-d'Ans",
    "gn:country_code":"FR",
    "gn:dem":136,
    "gn:feature_class":"P",
    "gn:feature_code":"PPL",
    "gn:name":"Sainte-Eulalie-d\u2019Ans",
    "gn:population":0,
    "gn:timezone":"Europe/Paris",
    "iso:country":"FR",
    "name:eng_x_preferred":[
        "Sainte-Eulalie-dAns"
    ],
    "name:und_x_variant":[
        "Sainte-Eulalie",
        "Sainte-Eulalie-d\u2019Ans"
    ],
    "name:zho_x_preferred":[
        "\u5723\u5384\u62c9\u5229\u8036\u5f53"
    ],
    "wof:name":"Sainte-Eulalie-d'Ans",
    "wof:placetype":"locality"
},
  "geometry": {"coordinates":[1.02069,45.24569],"type":"Point"}
}