{
  "type": "Feature",
  "properties": {
    "gn:admin1_code":"11",
    "gn:admin2_code":"91",
    "gn:admin3_code":"911",
    "gn:admin4_code":"91533",
    "gn:asciiname":"Gittonville",
    "gn:country_code":"FR",
    "gn:dem":95,
    "gn:feature_class":"P",
    "gn:feature_code":"PPL",
    "gn:name":"Gittonville",
    "gn:population":0,
    "gn:timezone":"Europe/Paris",
    "iso:country":"FR",
    "wof:name":"Gittonville",
    "wof:placetype":"locality"
},
  "geometry": {"coordinates":[2.11079,48.35198],"type":"Point"}
}