{
  "type": "Feature",
  "properties": {
    "gn:admin1_code":"84",
    "gn:admin2_code":"63",
    "gn:admin3_code":"631",
    "gn:admin4_code":"63331",
    "gn:asciiname":"Les Berniche",
    "gn:country_code":"FR",
    "gn:dem":1090,
    "gn:feature_class":"P",
    "gn:feature_code":"PPL",
    "gn:name":"Les Berniche",
    "gn:population":0,
    "gn:timezone":"Europe/Paris",
    "iso:country":"FR",
    "wof:name":"Les Berniche",
    "wof:placetype":"locality"
},
  "geometry": {"coordinates":[3.93648,45.49416],"type":"Point"}
}