{
  "type": "Feature",
  "properties": {
    "gn:admin1_code":"93",
    "gn:admin2_code":"13",
    "gn:admin3_code":"131",
    "gn:admin4_code":"13001",
    "gn:asciiname":"Dioulouffet",
    "gn:country_code":"FR",
    "gn:dem":304,
    "gn:feature_class":"P",
    "gn:feature_code":"PPL",
    "gn:name":"Dioulouffet",
    "gn:population":0,
    "gn:timezone":"Europe/Paris",
    "iso:country":"FR",
    "wof:name":"Dioulouffet",
    "wof:placetype":"locality"
},
  "geometry": {"coordinates":[5.4249,43.56501],"type":"Point"}
}