{
  "type": "Feature",
  "properties": {
    "gn:admin1_code":"44",
    "gn:admin2_code":"10",
    "gn:admin3_code":"102",
    "gn:admin4_code":"10351",
    "gn:asciiname":"Bossenay",
    "gn:country_code":"FR",
    "gn:dem":101,
    "gn:feature_class":"P",
    "gn:feature_code":"PPL",
    "gn:name":"Bossenay",
    "gn:population":0,
    "gn:timezone":"Europe/Paris",
    "iso:country":"FR",
    "wof:name":"Bossenay",
    "wof:placetype":"locality"
},
  "geometry": {"coordinates":[3.67406,48.43609],"type":"Point"}
}