{
  "type": "Feature",
  "properties": {
    "gn:admin1_code":"76",
    "gn:admin2_code":"12",
    "gn:admin3_code":"123",
    "gn:admin4_code":"12256",
    "gn:asciiname":"Saint-Clair-de-Marque",
    "gn:country_code":"FR",
    "gn:dem":344,
    "gn:feature_class":"P",
    "gn:feature_code":"PPL",
    "gn:name":"Saint-Clair-de-Marque",
    "gn:population":0,
    "gn:timezone":"Europe/Paris",
    "iso:country":"FR",
    "name:und_x_variant":[
        "Saint-Clan-de-Marque",
        "Saint-Clair-de-Marques",
        "Saint-Clair-de-Marque"
    ],
    "wof:name":"Saint-Clair-de-Marque",
    "wof:placetype":"locality"
},
  "geometry": {"coordinates":[1.88334,44.43167],"type":"Point"}
}