{
  "type": "Feature",
  "properties": {
    "gn:country":"FR",
    "gn:fcode":"PPL",
    "gn:population":1722,
    "iso:country":"FR",
    "name:und_x_variant":[
        "Gouville"
    ],
    "qs_pg:aaroncc":"FR",
    "qs_pg:gn_country":"FR",
    "qs_pg:gn_fcode":"PPL",
    "qs_pg:gn_pop":1722,
    "qs_pg:name":"Gouville-sur-mer-plage",
    "qs_pg:name_adm0":"France",
    "qs_pg:name_adm1":"Basse-Normandie",
    "qs_pg:photos":75,
    "qs_pg:photos_1k":15,
    "qs_pg:photos_9k":1,
    "qs_pg:photos_9r":2,
    "qs_pg:photos_all":75,
    "qs_pg:photos_sr":2,
    "qs_pg:pop_sr":3,
    "qs_pg:qs_pg_placetype":"locality",
    "qs_pg:qs_pg_placetype_gp":"Town",
    "qs_pg:woe_adm0":23424819,
    "woe:adm0_id":23424819,
    "woe:name_adm0":"France",
    "woe:name_adm1":"Basse-Normandie",
    "woe:placetype":"Town",
    "wof:name":"Gouville-sur-mer-plage",
    "wof:placetype":"neighbourhood",
    "wof:population":1722
},
  "geometry": {"coordinates":[-1.57908,49.09611],"type":"Point"}
}