{
  "type": "Feature",
  "properties": {
    "frgov:code_epci":"200070431",
    "frgov:insee_arr":"1",
    "frgov:insee_com":"38004",
    "frgov:insee_dep":"38",
    "frgov:insee_reg":"84",
    "frgov:nom_com":"L'Albenc",
    "frgov:nom_com_m":"L'ALBENC",
    "frgov:nom_dep":"ISERE",
    "frgov:nom_reg":"AUVERGNE-RHONE-ALPES",
    "frgov:statut":"Commune simple",
    "gn:admin1_code":"84",
    "gn:admin2_code":"38",
    "gn:admin3_code":"381",
    "gn:admin4_code":"38004",
    "gn:asciiname":"L'Albenc",
    "gn:country_code":"FR",
    "gn:dem":255,
    "gn:feature_class":"P",
    "gn:feature_code":"PPL",
    "gn:name":"L\u2019Albenc",
    "gn:population":0,
    "gn:timezone":"Europe/Paris",
    "iso:country":"FR",
    "name:cat_x_preferred":[
        "L'Albenc"
    ],
    "name:ceb_x_preferred":[
        "L'Albenc"
    ],
    "name:deu_x_preferred":[
        "L\u2019Albenc"
    ],
    "name:eus_x_preferred":[
        "L'Albenc"
    ],
    "name:fra_x_preferred":[
        "L'Albenc"
    ],
    "name:hun_x_preferred":[
        "L\u2019Albenc"
    ],
    "name:ita_x_preferred":[
        "L'Albenc"
    ],
    "name:lat_x_preferred":[
        "L'Albenc"
    ],
    "name:lmo_x_preferred":[
        "L'Albenc"
    ],
    "name:mlg_x_preferred":[
        "L'Albenc"
    ],
    "name:msa_x_preferred":[
        "L'Albenc"
    ],
    "name:nld_x_preferred":[
        "L'Albenc"
    ],
    "name:oci_x_preferred":[
        "L'Albenc"
    ],
    "name:pms_x_preferred":[
        "L'Albenc"
    ],
    "name:pol_x_preferred":[
        "L\u2019Albenc"
    ],
    "name:por_x_preferred":[
        "L'Albenc"
    ],
    "name:ron_x_preferred":[
        "L'Albenc"
    ],
    "name:rus_x_preferred":[
        "\u041b\u2019\u0410\u043b\u044c\u0431\u0435\u043d\u043a"
    ],
    "name:slk_x_preferred":[
        "L\u2019Albenc"
    ],
    "name:spa_x_preferred":[
        "L'Albenc"
    ],
    "name:srp_x_preferred":[
        "\u0410\u043b\u0431\u0430\u043d"
    ],
    "name:swe_x_preferred":[
        "L'Albenc"
    ],
    "name:ukr_x_preferred":[
        "\u041b'\u0410\u043b\u044c\u0431\u0430\u043d\u043a"
    ],
    "name:und_x_variant":[
        "L\u2019Albenc"
    ],
    "name:urd_x_preferred":[
        "\u0644\u0627\u0644\u0628\u06cc\u0646\u06a9"
    ],
    "name:uzb_x_preferred":[
        "L'Albenc"
    ],
    "name:vie_x_preferred":[
        "L'Albenc"
    ],
    "name:vol_x_preferred":[
        "L'Albenc"
    ],
    "name:war_x_preferred":[
        "L'Albenc"
    ],
    "name:zho_x_preferred":[
        "\u62c9\u5c14\u90a6\u514b"
    ],
    "qs:a0":"France",
    "qs:a1":"ISERE",
    "qs:a1_lc":"38",
    "qs:a1r":"RHONE-ALPES",
    "qs:a1r_lc":"82",
    "qs:a2_lc":"42",
    "qs:a2r_lc":"1",
    "qs:adm0":"France",
    "qs:adm0_a3":"FRA",
    "qs:la":"L'ALBENC",
    "qs:la_lc":"38004",
    "qs:level":"localadmin",
    "qs:type":"Commune simple",
    "wof:coterminous":[
        404404593
    ],
    "wof:name":"L'Albenc",
    "wof:placetype":"locality",
    "wof:placetype_local":"Commune simple"
},
  "geometry": {"coordinates":[5.44013,45.22526],"type":"Point"}
}