{
  "type": "Feature",
  "properties": {
    "gn:admin1_code":"24",
    "gn:admin2_code":"37",
    "gn:admin3_code":"372",
    "gn:admin4_code":"37085",
    "gn:asciiname":"Petit Rouvre",
    "gn:country_code":"FR",
    "gn:dem":90,
    "gn:feature_class":"P",
    "gn:feature_code":"PPL",
    "gn:name":"Petit Rouvre",
    "gn:population":0,
    "gn:timezone":"Europe/Paris",
    "iso:country":"FR",
    "name:und_x_variant":[
        "Le Petit Rouvre",
        "Petit Rouvre"
    ],
    "wof:name":"Petit Rouvre",
    "wof:placetype":"locality"
},
  "geometry": {"coordinates":[0.86856,47.24133],"type":"Point"}
}