{
  "type": "Feature",
  "properties": {
    "iso:country":"FR",
    "name:eng_x_preferred":[
        "Les Cevennes"
    ],
    "name:fra_x_preferred":[
        "Les C\u00e9vennes"
    ],
    "wof:name":"Les Cevennes",
    "wof:placetype":"neighbourhood"
},
  "geometry": {"coordinates":[3.84820799758811,43.61350698626573],"type":"Point"}
}