{
  "type": "Feature",
  "properties": {
    "gn:admin1_code":"75",
    "gn:admin2_code":"19",
    "gn:admin3_code":"192",
    "gn:admin4_code":"19039",
    "gn:asciiname":"Nussannes",
    "gn:country_code":"FR",
    "gn:dem":572,
    "gn:feature_class":"P",
    "gn:feature_code":"PPL",
    "gn:name":"Nussannes",
    "gn:population":0,
    "gn:timezone":"Europe/Paris",
    "iso:country":"FR",
    "wof:name":"Nussannes",
    "wof:placetype":"locality"
},
  "geometry": {"coordinates":[2.01147,45.29147],"type":"Point"}
}