{
  "type": "Feature",
  "properties": {
    "gn:admin1_code":"52",
    "gn:admin2_code":"53",
    "gn:admin3_code":"532",
    "gn:admin4_code":"53209",
    "gn:asciiname":"Hardoniere",
    "gn:country_code":"FR",
    "gn:dem":146,
    "gn:feature_class":"P",
    "gn:feature_code":"PPL",
    "gn:name":"Hardoni\u00e8re",
    "gn:population":0,
    "gn:timezone":"Europe/Paris",
    "iso:country":"FR",
    "name:und_x_variant":[
        "La Hardoni\u00e8re",
        "Hardoni\u00e8re"
    ],
    "wof:name":"Hardoniere",
    "wof:placetype":"locality"
},
  "geometry": {"coordinates":[-1.01701,48.05655],"type":"Point"}
}