{
  "type": "Feature",
  "properties": {
    "gn:admin1_code":"53",
    "gn:admin2_code":"22",
    "gn:admin3_code":"221",
    "gn:admin4_code":"22282",
    "gn:asciiname":"La Ville Norme",
    "gn:country_code":"FR",
    "gn:dem":44,
    "gn:feature_class":"P",
    "gn:feature_code":"PPL",
    "gn:name":"La Ville Norme",
    "gn:population":0,
    "gn:timezone":"Europe/Paris",
    "iso:country":"FR",
    "wof:name":"La Ville Norme",
    "wof:placetype":"locality"
},
  "geometry": {"coordinates":[-2.27621,48.63277],"type":"Point"}
}