{
  "type": "Feature",
  "properties": {
    "gn:admin1_code":"28",
    "gn:admin2_code":"76",
    "gn:admin3_code":"761",
    "gn:admin4_code":"76262",
    "gn:asciiname":"La Vieuville",
    "gn:country_code":"FR",
    "gn:dem":151,
    "gn:feature_class":"P",
    "gn:feature_code":"PPL",
    "gn:name":"La Vieuville",
    "gn:population":0,
    "gn:timezone":"Europe/Paris",
    "iso:country":"FR",
    "wof:name":"La Vieuville",
    "wof:placetype":"locality"
},
  "geometry": {"coordinates":[1.49609,49.80562000000001],"type":"Point"}
}