{
  "type": "Feature",
  "properties": {
    "gn:admin1_code":"27",
    "gn:admin2_code":"25",
    "gn:admin3_code":"252",
    "gn:admin4_code":"25463",
    "gn:asciiname":"Vermondans",
    "gn:country_code":"FR",
    "gn:dem":362,
    "gn:feature_class":"P",
    "gn:feature_code":"PPL",
    "gn:name":"Vermondans",
    "gn:population":0,
    "gn:timezone":"Europe/Paris",
    "iso:country":"FR",
    "wof:name":"Vermondans",
    "wof:placetype":"locality"
},
  "geometry": {"coordinates":[6.75542,47.38983],"type":"Point"}
}