{
  "type": "Feature",
  "properties": {
    "gn:admin1_code":"75",
    "gn:admin2_code":"86",
    "gn:admin3_code":"861",
    "gn:admin4_code":"86137",
    "gn:asciiname":"Rossay",
    "gn:country_code":"FR",
    "gn:dem":91,
    "gn:feature_class":"P",
    "gn:feature_code":"PPL",
    "gn:name":"Rossay",
    "gn:population":0,
    "gn:timezone":"Europe/Paris",
    "iso:country":"FR",
    "wof:name":"Rossay",
    "wof:placetype":"locality"
},
  "geometry": {"coordinates":[0.14331,46.98408],"type":"Point"}
}