{
  "type": "Feature",
  "properties": {
    "iso:country":"FR",
    "wof:name":"Belfort",
    "wof:placetype":"neighbourhood"
},
  "geometry": {"coordinates":[1.45085509079595,43.60848343286313],"type":"Point"}
}