{
  "type": "Feature",
  "properties": {
    "gn:admin1_code":"93",
    "gn:admin2_code":"04",
    "gn:admin3_code":"044",
    "gn:admin4_code":"04208",
    "gn:asciiname":"Chavon",
    "gn:country_code":"FR",
    "gn:dem":828,
    "gn:feature_class":"P",
    "gn:feature_code":"PPL",
    "gn:name":"Chavon",
    "gn:population":0,
    "gn:timezone":"Europe/Paris",
    "iso:country":"FR",
    "wof:name":"Chavon",
    "wof:placetype":"locality"
},
  "geometry": {"coordinates":[5.55,44.01667],"type":"Point"}
}