{
  "type": "Feature",
  "properties": {
    "gn:admin1_code":"24",
    "gn:admin2_code":"28",
    "gn:admin3_code":"281",
    "gn:admin4_code":"28254",
    "gn:asciiname":"Affonville",
    "gn:country_code":"FR",
    "gn:dem":229,
    "gn:feature_class":"P",
    "gn:feature_code":"PPL",
    "gn:name":"Affonville",
    "gn:population":0,
    "gn:timezone":"Europe/Paris",
    "iso:country":"FR",
    "wof:name":"Affonville",
    "wof:placetype":"locality"
},
  "geometry": {"coordinates":[1.31109,48.53082],"type":"Point"}
}