{
  "type": "Feature",
  "properties": {
    "gn:admin1_code":"24",
    "gn:admin2_code":"36",
    "gn:admin3_code":"363",
    "gn:admin4_code":"36133",
    "gn:asciiname":"Les Loges de Bonavois",
    "gn:country_code":"FR",
    "gn:dem":236,
    "gn:feature_class":"P",
    "gn:feature_code":"PPL",
    "gn:name":"Les Loges de Bonavois",
    "gn:population":0,
    "gn:timezone":"Europe/Paris",
    "iso:country":"FR",
    "wof:name":"Les Loges de Bonavois",
    "wof:placetype":"locality"
},
  "geometry": {"coordinates":[1.75991,46.57677],"type":"Point"}
}