{
  "type": "Feature",
  "properties": {
    "gn:admin1_code":"11",
    "gn:admin2_code":"77",
    "gn:admin3_code":"773",
    "gn:admin4_code":"77072",
    "gn:asciiname":"Puits-Jolly",
    "gn:country_code":"FR",
    "gn:dem":151,
    "gn:feature_class":"P",
    "gn:feature_code":"PPL",
    "gn:name":"Puits-Jolly",
    "gn:population":0,
    "gn:timezone":"Europe/Paris",
    "iso:country":"FR",
    "wof:name":"Puits-Jolly",
    "wof:placetype":"locality"
},
  "geometry": {"coordinates":[3.45241,48.56514],"type":"Point"}
}