{
  "type": "Feature",
  "properties": {
    "gn:admin1_code":"84",
    "gn:admin2_code":"07",
    "gn:admin3_code":"071",
    "gn:admin4_code":"07334",
    "gn:asciiname":"Chassagnes",
    "gn:country_code":"FR",
    "gn:dem":206,
    "gn:feature_class":"P",
    "gn:feature_code":"PPL",
    "gn:name":"Chassagnes",
    "gn:population":0,
    "gn:timezone":"Europe/Paris",
    "iso:country":"FR",
    "name:bug_x_preferred":[
        "Chassagnes"
    ],
    "name:cat_x_preferred":[
        "Chassanha"
    ],
    "name:ceb_x_preferred":[
        "Chassagnes"
    ],
    "name:deu_x_preferred":[
        "Chassagnes"
    ],
    "name:eus_x_preferred":[
        "Chassagnes"
    ],
    "name:fra_x_preferred":[
        "Chassagnes"
    ],
    "name:hun_x_preferred":[
        "Chassagnes"
    ],
    "name:ita_x_preferred":[
        "Chassagnes"
    ],
    "name:kaz_x_preferred":[
        "\u0428\u0430\u0441\u0441\u0430\u043d\u044c"
    ],
    "name:lat_x_preferred":[
        "Chassagnes"
    ],
    "name:ltz_x_preferred":[
        "Chassagnes"
    ],
    "name:mlg_x_preferred":[
        "Chassagnes"
    ],
    "name:msa_x_preferred":[
        "Chassagnes"
    ],
    "name:nld_x_preferred":[
        "Chassagnes"
    ],
    "name:oci_x_preferred":[
        "Chassanha"
    ],
    "name:pms_x_preferred":[
        "Chassagnes"
    ],
    "name:pol_x_preferred":[
        "Chassagnes"
    ],
    "name:por_x_preferred":[
        "Chassagnes"
    ],
    "name:ron_x_preferred":[
        "Chassagnes"
    ],
    "name:slk_x_preferred":[
        "Chassagnes"
    ],
    "name:spa_x_preferred":[
        "Chassagnes"
    ],
    "name:srp_x_preferred":[
        "\u0428\u0430\u0441\u0430\u045a"
    ],
    "name:swe_x_preferred":[
        "Chassagnes"
    ],
    "name:ukr_x_preferred":[
        "\u0428\u0430\u0441\u0441\u0430\u043d\u044c"
    ],
    "name:uzb_x_preferred":[
        "Chassagnes"
    ],
    "name:vie_x_preferred":[
        "Chassagnes"
    ],
    "name:vol_x_preferred":[
        "Chassagnes"
    ],
    "name:war_x_preferred":[
        "Chassagnes"
    ],
    "name:zho_x_preferred":[
        "\u6c99\u8428\u76d6"
    ],
    "wof:name":"Chassagnes",
    "wof:placetype":"locality"
},
  "geometry": {"coordinates":[4.16566,44.40466],"type":"Point"}
}