{
  "type": "Feature",
  "properties": {
    "gn:admin1_code":"27",
    "gn:admin2_code":"39",
    "gn:admin3_code":"392",
    "gn:admin4_code":"39461.0",
    "gn:asciiname":"Rix",
    "gn:country_code":"FR",
    "gn:dem":779,
    "gn:feature_class":"P",
    "gn:feature_code":"PPL",
    "gn:name":"Rix",
    "gn:population":78,
    "gn:timezone":"Europe/Paris",
    "iso:country":"FR",
    "name:ceb_x_preferred":[
        "Rix"
    ],
    "name:deu_x_preferred":[
        "Rix"
    ],
    "name:fra_x_preferred":[
        "Rix"
    ],
    "name:nld_x_preferred":[
        "Rix"
    ],
    "name:oci_x_preferred":[
        "Rix"
    ],
    "name:pms_x_preferred":[
        "Rix"
    ],
    "name:pol_x_preferred":[
        "Rix"
    ],
    "name:por_x_preferred":[
        "Rix"
    ],
    "name:rus_x_preferred":[
        "\u0420\u0438\u043a\u0441"
    ],
    "name:scn_x_preferred":[
        "Rix"
    ],
    "name:slk_x_preferred":[
        "Rix"
    ],
    "name:spa_x_preferred":[
        "Rix"
    ],
    "name:swe_x_preferred":[
        "Rix"
    ],
    "name:ukr_x_preferred":[
        "\u0420\u0438\u043a\u0441"
    ],
    "wof:name":"Rix",
    "wof:placetype":"locality",
    "wof:population":78
},
  "geometry": {"coordinates":[6.05254,46.76649000000001],"type":"Point"}
}