{
  "type": "Feature",
  "properties": {
    "frgov:code_epci":"200069623",
    "frgov:insee_arr":"2",
    "frgov:insee_com":"39461",
    "frgov:insee_dep":"39",
    "frgov:insee_reg":"27",
    "frgov:nom_com":"Rix",
    "frgov:nom_com_m":"RIX",
    "frgov:nom_dep":"JURA",
    "frgov:nom_reg":"BOURGOGNE-FRANCHE-COMTE",
    "frgov:statut":"Commune simple",
    "gn:admin1_code":"27",
    "gn:admin2_code":"39",
    "gn:admin3_code":"392",
    "gn:admin4_code":"39461.0",
    "gn:asciiname":"Rix",
    "gn:country_code":"FR",
    "gn:dem":779,
    "gn:feature_class":"P",
    "gn:feature_code":"PPL",
    "gn:name":"Rix",
    "gn:population":78,
    "gn:timezone":"Europe/Paris",
    "iso:country":"FR",
    "name:ceb_x_preferred":[
        "Rix"
    ],
    "name:deu_x_preferred":[
        "Rix"
    ],
    "name:fra_x_preferred":[
        "Rix"
    ],
    "name:nld_x_preferred":[
        "Rix"
    ],
    "name:oci_x_preferred":[
        "Rix"
    ],
    "name:pms_x_preferred":[
        "Rix"
    ],
    "name:pol_x_preferred":[
        "Rix"
    ],
    "name:por_x_preferred":[
        "Rix"
    ],
    "name:rus_x_preferred":[
        "\u0420\u0438\u043a\u0441"
    ],
    "name:scn_x_preferred":[
        "Rix"
    ],
    "name:slk_x_preferred":[
        "Rix"
    ],
    "name:spa_x_preferred":[
        "Rix"
    ],
    "name:swe_x_preferred":[
        "Rix"
    ],
    "name:ukr_x_preferred":[
        "\u0420\u0438\u043a\u0441"
    ],
    "name:zho_x_preferred":[
        "\u91cc\u9547"
    ],
    "qs:a0":"France",
    "qs:a1":"JURA",
    "qs:a1_lc":"39",
    "qs:a1r":"FRANCHE-COMTE",
    "qs:a1r_lc":"43",
    "qs:a2_lc":"20",
    "qs:a2r_lc":"2",
    "qs:adm0":"France",
    "qs:adm0_a3":"FRA",
    "qs:la":"RIX",
    "qs:la_lc":"39461",
    "qs:level":"localadmin",
    "qs:type":"Commune simple",
    "wof:coterminous":[
        404350621
    ],
    "wof:name":"Rix",
    "wof:placetype":"locality",
    "wof:placetype_local":"Commune simple",
    "wof:population":78
},
  "geometry": {"coordinates":[6.05254,46.76649],"type":"Point"}
}