{
  "type": "Feature",
  "properties": {
    "iso:country":"FR",
    "name:eng_x_preferred":[
        "Freinville"
    ],
    "name:fra_x_preferred":[
        "Freinville"
    ],
    "wof:name":"Freinville",
    "wof:placetype":"neighbourhood"
},
  "geometry": {"coordinates":[2.51904565907861,48.92730296780805],"type":"Point"}
}