{
  "type": "Feature",
  "properties": {
    "gn:admin1_code":"53",
    "gn:admin2_code":"29",
    "gn:admin3_code":"294",
    "gn:admin4_code":"29170",
    "gn:asciiname":"Saint-Roch",
    "gn:country_code":"FR",
    "gn:dem":60,
    "gn:feature_class":"P",
    "gn:feature_code":"PPL",
    "gn:name":"Saint-Roch",
    "gn:population":0,
    "gn:timezone":"Europe/Paris",
    "iso:country":"FR",
    "name:deu_x_preferred":[
        "Saint-Roch"
    ],
    "name:fra_x_preferred":[
        "Saint-Roch"
    ],
    "name:nld_x_preferred":[
        "Saint-Roch"
    ],
    "name:spa_x_preferred":[
        "Saint-Roch"
    ],
    "wof:name":"Saint-Roch",
    "wof:placetype":"locality"
},
  "geometry": {"coordinates":[-4.16667,47.91667],"type":"Point"}
}