{
  "type": "Feature",
  "properties": {
    "gn:admin1_code":"84",
    "gn:admin2_code":"26",
    "gn:admin3_code":"261",
    "gn:admin4_code":"26067",
    "gn:asciiname":"Chamanche",
    "gn:country_code":"FR",
    "gn:dem":941,
    "gn:feature_class":"P",
    "gn:feature_code":"PPL",
    "gn:name":"Chamanche",
    "gn:population":0,
    "gn:timezone":"Europe/Paris",
    "iso:country":"FR",
    "wof:name":"Chamanche",
    "wof:placetype":"locality"
},
  "geometry": {"coordinates":[5.32411,44.51658],"type":"Point"}
}