{
  "type": "Feature",
  "properties": {
    "gn:admin1_code":"44",
    "gn:admin2_code":"55",
    "gn:admin3_code":"551",
    "gn:admin4_code":"55532",
    "gn:asciiname":"Bourgogne",
    "gn:country_code":"FR",
    "gn:dem":207,
    "gn:feature_class":"P",
    "gn:feature_code":"PPL",
    "gn:name":"Bourgogne",
    "gn:population":0,
    "gn:timezone":"Europe/Paris",
    "iso:country":"FR",
    "wof:name":"Bourgogne",
    "wof:placetype":"locality"
},
  "geometry": {"coordinates":[5.10697,48.93569],"type":"Point"}
}