{
  "type": "Feature",
  "properties": {
    "gn:admin1_code":"27",
    "gn:admin2_code":"58",
    "gn:admin3_code":"583",
    "gn:admin4_code":"58051.0",
    "gn:asciiname":"Aglan",
    "gn:country_code":"FR",
    "gn:dem":247,
    "gn:feature_class":"P",
    "gn:feature_code":"PPL",
    "gn:name":"Aglan",
    "gn:population":0,
    "gn:timezone":"Europe/Paris",
    "iso:country":"FR",
    "wof:name":"Aglan",
    "wof:placetype":"locality"
},
  "geometry": {"coordinates":[3.12999,46.92096],"type":"Point"}
}