{
  "type": "Feature",
  "properties": {
    "gn:admin1_code":"24",
    "gn:admin2_code":"18",
    "gn:admin3_code":"182",
    "gn:admin4_code":"18212",
    "gn:asciiname":"Baranthaume",
    "gn:country_code":"FR",
    "gn:dem":170,
    "gn:feature_class":"P",
    "gn:feature_code":"PPL",
    "gn:name":"Baranthaume",
    "gn:population":0,
    "gn:timezone":"Europe/Paris",
    "iso:country":"FR",
    "wof:name":"Baranthaume",
    "wof:placetype":"locality"
},
  "geometry": {"coordinates":[2.43844,46.86431],"type":"Point"}
}