{
  "type": "Feature",
  "properties": {
    "gn:admin1_code":"84",
    "gn:admin2_code":"03",
    "gn:admin3_code":"031",
    "gn:admin4_code":"03041",
    "gn:asciiname":"Le May",
    "gn:country_code":"FR",
    "gn:dem":334,
    "gn:feature_class":"P",
    "gn:feature_code":"PPL",
    "gn:name":"Le May",
    "gn:population":0,
    "gn:timezone":"Europe/Paris",
    "iso:country":"FR",
    "wof:name":"Le May",
    "wof:placetype":"locality"
},
  "geometry": {"coordinates":[2.72953,46.58962],"type":"Point"}
}