{
  "type": "Feature",
  "properties": {
    "gn:admin1_code":"28",
    "gn:admin2_code":"50",
    "gn:admin3_code":"504",
    "gn:admin4_code":"50492",
    "gn:asciiname":"Rouxeville",
    "gn:country_code":"FR",
    "gn:dem":176,
    "gn:feature_class":"P",
    "gn:feature_code":"PPL",
    "gn:name":"Rouxeville",
    "gn:population":0,
    "gn:timezone":"Europe/Paris",
    "iso:country":"FR",
    "name:kaz_x_preferred":[
        "\u0420\u0443\u0441\u0435\u0432\u0438\u043b\u044c"
    ],
    "name:ukr_x_preferred":[
        "\u0420\u0443\u0441\u0435\u0432\u0456\u043b\u044c"
    ],
    "name:zho_x_preferred":[
        "\u9c81\u514b\u585e\u7ef4\u5c14"
    ],
    "wof:name":"Rouxeville",
    "wof:placetype":"locality"
},
  "geometry": {"coordinates":[-0.94534,49.10259],"type":"Point"}
}