{
  "type": "Feature",
  "properties": {
    "gn:admin1_code":"28",
    "gn:admin2_code":"50",
    "gn:admin3_code":"504",
    "gn:admin4_code":"50492",
    "gn:asciiname":"Rouxeville",
    "gn:country_code":"FR",
    "gn:dem":176,
    "gn:feature_class":"P",
    "gn:feature_code":"PPL",
    "gn:name":"Rouxeville",
    "gn:population":0,
    "gn:timezone":"Europe/Paris",
    "iso:country":"FR",
    "name:bug_x_preferred":[
        "Rouxeville"
    ],
    "name:cat_x_preferred":[
        "Rouxeville"
    ],
    "name:ceb_x_preferred":[
        "Rouxeville"
    ],
    "name:deu_x_preferred":[
        "Rouxeville"
    ],
    "name:eus_x_preferred":[
        "Rouxeville"
    ],
    "name:fra_x_preferred":[
        "Rouxeville"
    ],
    "name:hun_x_preferred":[
        "Rouxeville"
    ],
    "name:ita_x_preferred":[
        "Rouxeville"
    ],
    "name:kaz_x_preferred":[
        "\u0420\u0443\u0441\u0435\u0432\u0438\u043b\u044c"
    ],
    "name:lat_x_preferred":[
        "Rouxeville"
    ],
    "name:msa_x_preferred":[
        "Rouxeville"
    ],
    "name:nld_x_preferred":[
        "Rouxeville"
    ],
    "name:oci_x_preferred":[
        "Rouxeville"
    ],
    "name:pms_x_preferred":[
        "Rouxeville"
    ],
    "name:pol_x_preferred":[
        "Rouxeville"
    ],
    "name:por_x_preferred":[
        "Rouxeville"
    ],
    "name:ron_x_preferred":[
        "Rouxeville"
    ],
    "name:slk_x_preferred":[
        "Rouxeville"
    ],
    "name:spa_x_preferred":[
        "Rouxeville"
    ],
    "name:swe_x_preferred":[
        "Rouxeville"
    ],
    "name:ukr_x_preferred":[
        "\u0420\u0443\u0441\u0435\u0432\u0456\u043b\u044c"
    ],
    "name:uzb_x_preferred":[
        "Rouxeville"
    ],
    "name:vie_x_preferred":[
        "Rouxeville"
    ],
    "name:vol_x_preferred":[
        "Rouxeville"
    ],
    "name:war_x_preferred":[
        "Rouxeville"
    ],
    "name:zho_x_preferred":[
        "\u9c81\u514b\u585e\u7ef4\u5c14"
    ],
    "wof:name":"Rouxeville",
    "wof:placetype":"locality"
},
  "geometry": {"coordinates":[-0.94534,49.10259],"type":"Point"}
}