{
  "type": "Feature",
  "properties": {
    "gn:admin1_code":"53",
    "gn:admin2_code":"22",
    "gn:admin3_code":"223",
    "gn:admin4_code":"22226",
    "gn:asciiname":"Kervren",
    "gn:country_code":"FR",
    "gn:dem":118,
    "gn:feature_class":"P",
    "gn:feature_code":"PPL",
    "gn:name":"Kervren",
    "gn:population":0,
    "gn:timezone":"Europe/Paris",
    "iso:country":"FR",
    "wof:name":"Kervren",
    "wof:placetype":"locality"
},
  "geometry": {"coordinates":[-3.49389,48.66955],"type":"Point"}
}