{
  "type": "Feature",
  "properties": {
    "gn:admin1_code":"93",
    "gn:admin2_code":"13",
    "gn:admin3_code":"133",
    "gn:admin4_code":"13055",
    "gn:asciiname":"Marseille 15",
    "gn:country_code":"FR",
    "gn:dem":153,
    "gn:feature_class":"P",
    "gn:feature_code":"PPL",
    "gn:name":"Marseille 15",
    "gn:population":77770,
    "gn:timezone":"Europe/Paris",
    "iso:country":"FR",
    "name:urd_x_preferred":[
        "\u0645\u0627\u0631\u0633\u06cc\u0644 \u06a9\u0627\u067e\u0646\u062f\u0631\u06c1\u0648\u0627\u06ba \u0627\u0631\u0627\u0624\u0646\u0688\u0688\u0633\u0645\u0646\u0679"
    ],
    "wof:name":"Marseille 15",
    "wof:placetype":"locality",
    "wof:population":77770
},
  "geometry": {"coordinates":[5.35386,43.37224000000001],"type":"Point"}
}