{
  "type": "Feature",
  "properties": {
    "gn:admin1_code":"32",
    "gn:admin2_code":"62",
    "gn:admin3_code":"626",
    "gn:admin4_code":"62193",
    "gn:asciiname":"Cite Civry",
    "gn:country_code":"FR",
    "gn:dem":3,
    "gn:feature_class":"P",
    "gn:feature_code":"PPLL",
    "gn:name":"Cit\u00e9 Civry",
    "gn:population":0,
    "gn:timezone":"Europe/Paris",
    "iso:country":"FR",
    "wof:name":"Cite Civry",
    "wof:placetype":"locality"
},
  "geometry": {"coordinates":[1.89076,50.95725],"type":"Point"}
}