{
  "type": "Feature",
  "properties": {
    "gn:country":"FR",
    "gn:fcode":"PPL",
    "gn:population":0,
    "iso:country":"FR",
    "name:bre_x_preferred":[
        "Ploumanac'h"
    ],
    "name:deu_x_preferred":[
        "Ploumanac\u2019h"
    ],
    "name:eng_x_preferred":[
        "Ploumanac'h"
    ],
    "name:fra_x_preferred":[
        "Ploumanac'h"
    ],
    "name:ita_x_preferred":[
        "Ploumanac'h"
    ],
    "name:jpn_x_preferred":[
        "\u30d7\u30eb\u30fc\u30de\u30ca\u30c3\u30af"
    ],
    "name:nan_x_preferred":[
        "Ploumanac'h"
    ],
    "name:nld_x_preferred":[
        "Ploumanac'h"
    ],
    "qs_pg:aaroncc":"FR",
    "qs_pg:gn_country":"FR",
    "qs_pg:gn_fcode":"PPL",
    "qs_pg:gn_pop":0,
    "qs_pg:name":"Ploumanach",
    "qs_pg:name_adm0":"France",
    "qs_pg:name_adm1":"Bretagne",
    "qs_pg:photos":1302,
    "qs_pg:photos_1k":264,
    "qs_pg:photos_9k":6,
    "qs_pg:photos_9r":7,
    "qs_pg:photos_all":1302,
    "qs_pg:photos_sr":12,
    "qs_pg:pop_sr":0,
    "qs_pg:qs_pg_placetype":"locality",
    "qs_pg:qs_pg_placetype_gp":"Town",
    "qs_pg:woe_adm0":23424819,
    "woe:adm0_id":23424819,
    "woe:name_adm0":"France",
    "woe:name_adm1":"Bretagne",
    "woe:placetype":"Town",
    "wof:name":"Ploumanach",
    "wof:placetype":"neighbourhood"
},
  "geometry": {"coordinates":[-3.48473,48.82806],"type":"Point"}
}