{
  "type": "Feature",
  "properties": {
    "iso:country":"FR",
    "name:eng_x_preferred":[
        "Clagny-Glatigny"
    ],
    "name:fra_x_preferred":[
        "Clagny-Glatigny"
    ],
    "wof:name":"Clagny-Glatigny",
    "wof:placetype":"neighbourhood"
},
  "geometry": {"coordinates":[2.14299034387081,48.81617844001624],"type":"Point"}
}