{
  "type": "Feature",
  "properties": {
    "gn:admin1_code":"75",
    "gn:admin2_code":"24",
    "gn:admin3_code":"241",
    "gn:admin4_code":"24223",
    "gn:asciiname":"Sauve-Boeuf",
    "gn:country_code":"FR",
    "gn:dem":45,
    "gn:feature_class":"P",
    "gn:feature_code":"PPL",
    "gn:name":"Sauve-B\u0153uf",
    "gn:population":0,
    "gn:timezone":"Europe/Paris",
    "iso:country":"FR",
    "wof:name":"Sauve-Boeuf",
    "wof:placetype":"locality"
},
  "geometry": {"coordinates":[0.78333,44.85],"type":"Point"}
}