{
  "type": "Feature",
  "properties": {
    "gn:admin1_code":"53",
    "gn:asciiname":"Kervigorn",
    "gn:country_code":"FR",
    "gn:dem":23,
    "gn:feature_class":"P",
    "gn:feature_code":"PPL",
    "gn:name":"Kervigorn",
    "gn:population":0,
    "gn:timezone":"Europe/Paris",
    "iso:country":"FR",
    "wof:name":"Kervigorn",
    "wof:placetype":"locality"
},
  "geometry": {"coordinates":[-4.61575,48.57475],"type":"Point"}
}