{
  "type": "Feature",
  "properties": {
    "iso:country":"FR",
    "name:eng_x_preferred":[
        "PVC-Les Sablons"
    ],
    "name:fra_x_preferred":[
        "PVC-Les Sablons"
    ],
    "wof:name":"PVC-Les Sablons",
    "wof:placetype":"neighbourhood"
},
  "geometry": {"coordinates":[2.44802548960334,48.90749984901345],"type":"Point"}
}