{
  "type": "Feature",
  "properties": {
    "gn:admin1_code":"84",
    "gn:admin2_code":"63",
    "gn:admin3_code":"632",
    "gn:admin4_code":"63368",
    "gn:asciiname":"Lassias",
    "gn:country_code":"FR",
    "gn:dem":564,
    "gn:feature_class":"P",
    "gn:feature_code":"PPL",
    "gn:name":"Lassias",
    "gn:population":0,
    "gn:timezone":"Europe/Paris",
    "iso:country":"FR",
    "wof:name":"Lassias",
    "wof:placetype":"locality"
},
  "geometry": {"coordinates":[3.29781,45.68349],"type":"Point"}
}