{
  "type": "Feature",
  "properties": {
    "gn:admin1_code":"84",
    "gn:admin2_code":"26",
    "gn:admin3_code":"263",
    "gn:admin4_code":"26034",
    "gn:asciiname":"Les Massotiers",
    "gn:country_code":"FR",
    "gn:dem":195,
    "gn:feature_class":"P",
    "gn:feature_code":"PPL",
    "gn:name":"Les Massotiers",
    "gn:population":0,
    "gn:timezone":"Europe/Paris",
    "iso:country":"FR",
    "wof:name":"Les Massotiers",
    "wof:placetype":"locality"
},
  "geometry": {"coordinates":[5.23265,45.06696],"type":"Point"}
}