{
  "type": "Feature",
  "properties": {
    "gn:admin1_code":"84",
    "gn:admin2_code":"63",
    "gn:admin3_code":"635",
    "gn:admin4_code":"63364",
    "gn:asciiname":"Chez Valladier",
    "gn:country_code":"FR",
    "gn:dem":369,
    "gn:feature_class":"P",
    "gn:feature_code":"PPL",
    "gn:name":"Chez Valladier",
    "gn:population":0,
    "gn:timezone":"Europe/Paris",
    "iso:country":"FR",
    "wof:name":"Chez Valladier",
    "wof:placetype":"locality"
},
  "geometry": {"coordinates":[3.44171,45.82516],"type":"Point"}
}