{
  "type": "Feature",
  "properties": {
    "gn:admin1_code":"84",
    "gn:admin2_code":"63",
    "gn:admin3_code":"632",
    "gn:admin4_code":"63370",
    "gn:asciiname":"Pierrefitte",
    "gn:country_code":"FR",
    "gn:dem":927,
    "gn:feature_class":"P",
    "gn:feature_code":"PPL",
    "gn:name":"Pierrefitte",
    "gn:population":0,
    "gn:timezone":"Europe/Paris",
    "iso:country":"FR",
    "name:ceb_x_preferred":[
        "Pierrefitte"
    ],
    "name:deu_x_preferred":[
        "Pierrefitte"
    ],
    "name:epo_x_preferred":[
        "Pierrefitte"
    ],
    "name:fra_x_preferred":[
        "Pierrefitte"
    ],
    "name:glg_x_preferred":[
        "Pierrefitte"
    ],
    "name:ita_x_preferred":[
        "Pierrefitte"
    ],
    "name:nds_x_preferred":[
        "Pierrefitte"
    ],
    "name:nld_x_preferred":[
        "Pierrefitte"
    ],
    "name:oci_x_preferred":[
        "P\u00e8irafita"
    ],
    "name:pms_x_preferred":[
        "Pierrefitte"
    ],
    "name:pol_x_preferred":[
        "Pierrefitte"
    ],
    "name:por_x_preferred":[
        "Pierrefitte"
    ],
    "name:rus_x_preferred":[
        "\u041f\u044c\u0435\u0440\u0444\u0438\u0442"
    ],
    "name:slk_x_preferred":[
        "Pierrefitte"
    ],
    "name:spa_x_preferred":[
        "Pierrefitte"
    ],
    "name:swe_x_preferred":[
        "Pierrefitte"
    ],
    "name:ukr_x_preferred":[
        "\u041f'\u0454\u0440\u0440\u0444\u0456\u0442\u0442"
    ],
    "wof:name":"Pierrefitte",
    "wof:placetype":"locality"
},
  "geometry": {"coordinates":[2.65612,45.64558],"type":"Point"}
}