{
  "type": "Feature",
  "properties": {
    "gn:admin1_code":"84",
    "gn:admin2_code":"63",
    "gn:admin3_code":"632",
    "gn:admin4_code":"63370",
    "gn:asciiname":"Pierrefitte",
    "gn:country_code":"FR",
    "gn:dem":927,
    "gn:feature_class":"P",
    "gn:feature_code":"PPL",
    "gn:name":"Pierrefitte",
    "gn:population":0,
    "gn:timezone":"Europe/Paris",
    "iso:country":"FR",
    "wof:name":"Pierrefitte",
    "wof:placetype":"locality"
},
  "geometry": {"coordinates":[2.65612,45.64558],"type":"Point"}
}