{
  "type": "Feature",
  "properties": {
    "gn:admin1_code":"75",
    "gn:admin2_code":"23",
    "gn:admin3_code":"232",
    "gn:admin4_code":"23154",
    "gn:asciiname":"Les Forgettes",
    "gn:country_code":"FR",
    "gn:dem":519,
    "gn:feature_class":"P",
    "gn:feature_code":"PPL",
    "gn:name":"Les Forgettes",
    "gn:population":0,
    "gn:timezone":"Europe/Paris",
    "iso:country":"FR",
    "wof:name":"Les Forgettes",
    "wof:placetype":"locality"
},
  "geometry": {"coordinates":[2.04634,46.17692],"type":"Point"}
}