{
  "type": "Feature",
  "properties": {
    "gn:admin1_code":"84",
    "gn:admin2_code":"38",
    "gn:admin3_code":"381",
    "gn:admin4_code":"38151",
    "gn:asciiname":"Les Granges",
    "gn:country_code":"FR",
    "gn:dem":227,
    "gn:feature_class":"P",
    "gn:feature_code":"PPL",
    "gn:name":"Les Granges",
    "gn:population":0,
    "gn:timezone":"Europe/Paris",
    "iso:country":"FR",
    "wof:name":"Les Granges",
    "wof:placetype":"locality"
},
  "geometry": {"coordinates":[5.72631,45.15544000000001],"type":"Point"}
}