{
  "type": "Feature",
  "properties": {
    "gn:admin1_code":"84",
    "gn:admin2_code":"63",
    "gn:admin3_code":"634",
    "gn:admin4_code":"63243",
    "gn:asciiname":"La Lubiere",
    "gn:country_code":"FR",
    "gn:dem":623,
    "gn:feature_class":"P",
    "gn:feature_code":"PPL",
    "gn:name":"La Lubi\u00e8re",
    "gn:population":0,
    "gn:timezone":"Europe/Paris",
    "iso:country":"FR",
    "wof:name":"La Lubiere",
    "wof:placetype":"locality"
},
  "geometry": {"coordinates":[2.89497,46.15049000000001],"type":"Point"}
}