{
  "type": "Feature",
  "properties": {
    "gn:admin1_code":"32",
    "gn:admin2_code":"80",
    "gn:admin3_code":"802",
    "gn:admin4_code":"80443.0",
    "gn:asciiname":"Orival",
    "gn:country_code":"FR",
    "gn:dem":188,
    "gn:feature_class":"P",
    "gn:feature_code":"PPL",
    "gn:name":"Orival",
    "gn:population":0,
    "gn:timezone":"Europe/Paris",
    "iso:country":"FR",
    "name:ceb_x_preferred":[
        "Orival"
    ],
    "name:deu_x_preferred":[
        "Orival"
    ],
    "name:fra_x_preferred":[
        "Orival"
    ],
    "name:ita_x_preferred":[
        "Orival"
    ],
    "name:nds_x_preferred":[
        "Orival"
    ],
    "name:nld_x_preferred":[
        "Orival"
    ],
    "name:oci_x_preferred":[
        "Orival"
    ],
    "name:pms_x_preferred":[
        "Orival"
    ],
    "name:pol_x_preferred":[
        "Orival"
    ],
    "name:por_x_preferred":[
        "Orival"
    ],
    "name:rus_x_preferred":[
        "\u041e\u0440\u0438\u0432\u0430\u043b\u044c"
    ],
    "name:slk_x_preferred":[
        "Orival"
    ],
    "name:spa_x_preferred":[
        "Orival"
    ],
    "name:swe_x_preferred":[
        "Orival"
    ],
    "name:ukr_x_preferred":[
        "\u041e\u0440\u0438\u0432\u0430\u043b\u044c"
    ],
    "wof:name":"Orival",
    "wof:placetype":"locality"
},
  "geometry": {"coordinates":[1.84496,49.80339],"type":"Point"}
}