{
  "type": "Feature",
  "properties": {
    "gn:admin1_code":"75",
    "gn:admin2_code":"33",
    "gn:admin3_code":"335",
    "gn:admin4_code":"33303",
    "gn:asciiname":"Mongiron",
    "gn:country_code":"FR",
    "gn:dem":69,
    "gn:feature_class":"P",
    "gn:feature_code":"PPL",
    "gn:name":"Mongiron",
    "gn:population":0,
    "gn:timezone":"Europe/Paris",
    "iso:country":"FR",
    "wof:name":"Mongiron",
    "wof:placetype":"locality"
},
  "geometry": {"coordinates":[-0.29132,44.84651],"type":"Point"}
}