{
  "type": "Feature",
  "properties": {
    "gn:admin1_code":"84",
    "gn:admin2_code":"38",
    "gn:admin3_code":"382",
    "gn:admin4_code":"38053",
    "gn:asciiname":"Le Molard",
    "gn:country_code":"FR",
    "gn:dem":249,
    "gn:feature_class":"P",
    "gn:feature_code":"PPL",
    "gn:name":"Le Molard",
    "gn:population":0,
    "gn:timezone":"Europe/Paris",
    "iso:country":"FR",
    "name:und_x_variant":[
        "Le Mollard et Bourselas",
        "Le Mollard",
        "Le Molard"
    ],
    "wof:name":"Le Molard",
    "wof:placetype":"locality"
},
  "geometry": {"coordinates":[5.27526,45.60182],"type":"Point"}
}