{
  "type": "Feature",
  "properties": {
    "gn:admin1_code":"24",
    "gn:admin2_code":"18",
    "gn:admin3_code":"181",
    "gn:admin4_code":"18289",
    "gn:asciiname":"La Suee",
    "gn:country_code":"FR",
    "gn:dem":158,
    "gn:feature_class":"P",
    "gn:feature_code":"PPL",
    "gn:name":"La Su\u00e9e",
    "gn:population":0,
    "gn:timezone":"Europe/Paris",
    "iso:country":"FR",
    "wof:name":"La Suee",
    "wof:placetype":"locality"
},
  "geometry": {"coordinates":[2.61238,46.98362],"type":"Point"}
}