{
  "type": "Feature",
  "properties": {
    "gn:admin1_code":"93",
    "gn:admin2_code":"05",
    "gn:admin3_code":"051",
    "gn:admin4_code":"05180",
    "gn:asciiname":"Eyssarvia",
    "gn:cc2":"FR",
    "gn:country_code":"FR",
    "gn:dem":1361,
    "gn:feature_class":"P",
    "gn:feature_code":"PPL",
    "gn:name":"Eyssarvia",
    "gn:population":0,
    "gn:timezone":"Europe/Paris",
    "iso:country":"FR",
    "name:und_x_variant":[
        "L\u2019Eyssarvia",
        "Eyssarvia"
    ],
    "wof:name":"Eyssarvia",
    "wof:placetype":"locality"
},
  "geometry": {"coordinates":[6.53333,44.81667],"type":"Point"}
}