{
  "type": "Feature",
  "properties": {
    "gn:admin1_code":"84",
    "gn:admin2_code":"43",
    "gn:admin3_code":"433",
    "gn:admin4_code":"43244",
    "gn:asciiname":"Mazeaux",
    "gn:country_code":"FR",
    "gn:dem":916,
    "gn:feature_class":"P",
    "gn:feature_code":"PPL",
    "gn:name":"Mazeaux",
    "gn:population":0,
    "gn:timezone":"Europe/Paris",
    "iso:country":"FR",
    "name:und_x_variant":[
        "Les Mazeaux",
        "Mazeaux"
    ],
    "wof:name":"Mazeaux",
    "wof:placetype":"locality"
},
  "geometry": {"coordinates":[4.31717,45.11537],"type":"Point"}
}