{
  "type": "Feature",
  "properties": {
    "gn:admin1_code":"53",
    "gn:admin2_code":"56",
    "gn:admin3_code":"561",
    "gn:admin4_code":"56107",
    "gn:asciiname":"Les Quatre Chemins",
    "gn:country_code":"FR",
    "gn:dem":29,
    "gn:feature_class":"P",
    "gn:feature_code":"PPLL",
    "gn:name":"Les Quatre Chemins",
    "gn:population":0,
    "gn:timezone":"Europe/Paris",
    "iso:country":"FR",
    "wof:name":"Les Quatre Chemins",
    "wof:placetype":"locality"
},
  "geometry": {"coordinates":[-3.38638,47.71687],"type":"Point"}
}