{
  "type": "Feature",
  "properties": {
    "gn:admin1_code":"75",
    "gn:admin2_code":"24",
    "gn:admin3_code":"243",
    "gn:admin4_code":"24339",
    "gn:asciiname":"Preyssac-d'Excideuil",
    "gn:country_code":"FR",
    "gn:dem":251,
    "gn:feature_class":"P",
    "gn:feature_code":"PPL",
    "gn:name":"Preyssac-d\u2019Excideuil",
    "gn:population":0,
    "gn:timezone":"Europe/Paris",
    "iso:country":"FR",
    "name:und_x_variant":[
        "Preyssac",
        "Preyssac-d\u2019Excideuil"
    ],
    "wof:name":"Preyssac-d'Excideuil",
    "wof:placetype":"locality"
},
  "geometry": {"coordinates":[1.10356,45.33727],"type":"Point"}
}