{
  "type": "Feature",
  "properties": {
    "gn:admin1_code":"75",
    "gn:admin2_code":"24",
    "gn:admin3_code":"243",
    "gn:admin4_code":"24339",
    "gn:asciiname":"Preyssac-d'Excideuil",
    "gn:country_code":"FR",
    "gn:dem":251,
    "gn:feature_class":"P",
    "gn:feature_code":"PPL",
    "gn:name":"Preyssac-d\u2019Excideuil",
    "gn:population":0,
    "gn:timezone":"Europe/Paris",
    "iso:country":"FR",
    "name:bug_x_preferred":[
        "Preyssac-d'Excideuil"
    ],
    "name:cat_x_preferred":[
        "Preissac d'Eissiduelh"
    ],
    "name:ceb_x_preferred":[
        "Preyssac-d'Excideuil"
    ],
    "name:deu_x_preferred":[
        "Preyssac-d\u2019Excideuil"
    ],
    "name:eus_x_preferred":[
        "Preyssac-d'Excideuil"
    ],
    "name:fra_x_preferred":[
        "Preyssac-d'Excideuil"
    ],
    "name:hun_x_preferred":[
        "Preyssac-d\u2019Excideuil"
    ],
    "name:ita_x_preferred":[
        "Preyssac-d'Excideuil"
    ],
    "name:kaz_x_preferred":[
        "\u041f\u0440\u0435\u0441\u0441\u0430\u043a-\u0434'\u0415\u043a\u0441\u0441\u0438\u0434\u0435\u0439"
    ],
    "name:lat_x_preferred":[
        "Preyssac-d'Excideuil"
    ],
    "name:mlg_x_preferred":[
        "Preyssac-d'Excideuil"
    ],
    "name:msa_x_preferred":[
        "Preyssac-d'Excideuil"
    ],
    "name:nld_x_preferred":[
        "Preyssac-d'Excideuil"
    ],
    "name:oci_x_preferred":[
        "Preissac d'Eissiduelh"
    ],
    "name:pms_x_preferred":[
        "Preyssac-d'Excideuil"
    ],
    "name:pol_x_preferred":[
        "Preyssac-d\u2019Excideuil"
    ],
    "name:por_x_preferred":[
        "Preyssac-d'Excideuil"
    ],
    "name:ron_x_preferred":[
        "Preyssac-d'Excideuil"
    ],
    "name:rus_x_preferred":[
        "\u041f\u0440\u0435\u0441\u0430\u043a-\u0434\u2019\u042d\u043a\u0441\u0438\u0434\u0451\u0439"
    ],
    "name:slk_x_preferred":[
        "Preyssac-d\u2019Excideuil"
    ],
    "name:spa_x_preferred":[
        "Preyssac-d'Excideuil"
    ],
    "name:swe_x_preferred":[
        "Preyssac-d'Excideuil"
    ],
    "name:ukr_x_preferred":[
        "\u041f\u0440\u0435\u0441\u0441\u0430\u043a-\u0434'\u0415\u043a\u0441\u0441\u0456\u0434\u0435\u0439"
    ],
    "name:und_x_variant":[
        "Preyssac"
    ],
    "name:uzb_x_preferred":[
        "Preyssac-d'Excideuil"
    ],
    "name:vie_x_preferred":[
        "Preyssac-d'Excideuil"
    ],
    "name:vol_x_preferred":[
        "Preyssac-d'Excideuil"
    ],
    "name:war_x_preferred":[
        "Preyssac-d'Excideuil"
    ],
    "name:zho_x_preferred":[
        "\u666e\u96f7\u8428\u514b\u4ee3\u514b\u65af\u897f\u5fb7\u4f0a"
    ],
    "wof:name":"Preyssac-d'Excideuil",
    "wof:placetype":"locality"
},
  "geometry": {"coordinates":[1.10356,45.33727],"type":"Point"}
}