{
  "type": "Feature",
  "properties": {
    "iso:country":"FR",
    "name:eng_x_preferred":[
        "Les Tourettes"
    ],
    "name:fra_x_preferred":[
        "Les Tourettes"
    ],
    "wof:name":"Les Tourettes",
    "wof:placetype":"neighbourhood"
},
  "geometry": {"coordinates":[0.69410975117107,47.41299389099304],"type":"Point"}
}