{
  "type": "Feature",
  "properties": {
    "gn:admin1_code":"24",
    "gn:admin2_code":"28",
    "gn:admin3_code":"283",
    "gn:admin4_code":"28374",
    "gn:asciiname":"Borville",
    "gn:cc2":"FR",
    "gn:country_code":"FR",
    "gn:dem":152,
    "gn:feature_class":"P",
    "gn:feature_code":"PPL",
    "gn:name":"Borville",
    "gn:population":0,
    "gn:timezone":"Europe/Paris",
    "iso:country":"FR",
    "wof:name":"Borville",
    "wof:placetype":"locality"
},
  "geometry": {"coordinates":[1.46616,48.60959],"type":"Point"}
}