{
  "type": "Feature",
  "properties": {
    "gn:admin1_code":"24",
    "gn:admin2_code":"28",
    "gn:admin3_code":"283",
    "gn:admin4_code":"28374",
    "gn:asciiname":"Borville",
    "gn:cc2":"FR",
    "gn:country_code":"FR",
    "gn:dem":152,
    "gn:feature_class":"P",
    "gn:feature_code":"PPL",
    "gn:name":"Borville",
    "gn:population":0,
    "gn:timezone":"Europe/Paris",
    "iso:country":"FR",
    "name:cat_x_preferred":[
        "Borville"
    ],
    "name:ceb_x_preferred":[
        "Borville"
    ],
    "name:deu_x_preferred":[
        "Borville"
    ],
    "name:eus_x_preferred":[
        "Borville"
    ],
    "name:fra_x_preferred":[
        "Borville"
    ],
    "name:hun_x_preferred":[
        "Borville"
    ],
    "name:ita_x_preferred":[
        "Borville"
    ],
    "name:kaz_x_preferred":[
        "\u0411\u043e\u0440\u0432\u0438\u043b\u044c"
    ],
    "name:lat_x_preferred":[
        "Borville"
    ],
    "name:ltz_x_preferred":[
        "Borville"
    ],
    "name:mlg_x_preferred":[
        "Borville"
    ],
    "name:msa_x_preferred":[
        "Borville"
    ],
    "name:nap_x_preferred":[
        "Borville"
    ],
    "name:nld_x_preferred":[
        "Borville"
    ],
    "name:nor_x_preferred":[
        "Borville"
    ],
    "name:oci_x_preferred":[
        "Borville"
    ],
    "name:pms_x_preferred":[
        "Borville"
    ],
    "name:pol_x_preferred":[
        "Borville"
    ],
    "name:por_x_preferred":[
        "Borville"
    ],
    "name:rus_x_preferred":[
        "\u0411\u043e\u0440\u0432\u0438\u043b\u044c"
    ],
    "name:slk_x_preferred":[
        "Borville"
    ],
    "name:spa_x_preferred":[
        "Borville"
    ],
    "name:srp_x_preferred":[
        "\u0411\u043e\u0440\u0432\u0438\u043b\u0435"
    ],
    "name:swe_x_preferred":[
        "Borville"
    ],
    "name:ukr_x_preferred":[
        "\u0411\u043e\u0440\u0432\u0456\u043b\u044c"
    ],
    "name:uzb_x_preferred":[
        "Borville"
    ],
    "name:vie_x_preferred":[
        "Borville"
    ],
    "name:vol_x_preferred":[
        "Borville"
    ],
    "name:war_x_preferred":[
        "Borville"
    ],
    "wof:name":"Borville",
    "wof:placetype":"locality"
},
  "geometry": {"coordinates":[1.46616,48.60959],"type":"Point"}
}