{
  "type": "Feature",
  "properties": {
    "frgov:code_epci":"200069169",
    "frgov:insee_arr":"3",
    "frgov:insee_com":"63183",
    "frgov:insee_dep":"63",
    "frgov:insee_reg":"84",
    "frgov:nom_com":"Labessette",
    "frgov:nom_com_m":"LABESSETTE",
    "frgov:nom_dep":"PUY-DE-DOME",
    "frgov:nom_reg":"AUVERGNE-RHONE-ALPES",
    "frgov:statut":"Commune simple",
    "gn:admin1_code":"84",
    "gn:admin2_code":"63",
    "gn:admin3_code":"633",
    "gn:admin4_code":"63183",
    "gn:asciiname":"Labessette",
    "gn:country_code":"FR",
    "gn:dem":763,
    "gn:feature_class":"P",
    "gn:feature_code":"PPL",
    "gn:name":"Labessette",
    "gn:population":0,
    "gn:timezone":"Europe/Paris",
    "iso:country":"FR",
    "name:cat_x_preferred":[
        "La Beceta"
    ],
    "name:ceb_x_preferred":[
        "Labessette"
    ],
    "name:deu_x_preferred":[
        "Labessette"
    ],
    "name:eus_x_preferred":[
        "Labessette"
    ],
    "name:fra_x_preferred":[
        "Labessette"
    ],
    "name:hun_x_preferred":[
        "Labessette"
    ],
    "name:ita_x_preferred":[
        "Labessette"
    ],
    "name:kaz_x_preferred":[
        "\u041b\u0430\u0431\u0435\u0441\u0441\u0435\u0442\u0442"
    ],
    "name:lat_x_preferred":[
        "Labessette"
    ],
    "name:msa_x_preferred":[
        "Labessette"
    ],
    "name:nld_x_preferred":[
        "Labessette"
    ],
    "name:oci_x_preferred":[
        "La Beceta"
    ],
    "name:pms_x_preferred":[
        "Labessette"
    ],
    "name:pol_x_preferred":[
        "Labessette"
    ],
    "name:por_x_preferred":[
        "Labessette"
    ],
    "name:ron_x_preferred":[
        "Labessette"
    ],
    "name:slk_x_preferred":[
        "Labessette"
    ],
    "name:spa_x_preferred":[
        "Labessette"
    ],
    "name:swe_x_preferred":[
        "Labessette"
    ],
    "name:ukr_x_preferred":[
        "\u041b\u0430\u0431\u0435\u0441\u0441\u0435\u0442\u0442"
    ],
    "name:urd_x_preferred":[
        "\u0644\u0627\u0628\u06cc\u0633\u06cc\u062a\u06cc"
    ],
    "name:uzb_x_preferred":[
        "Labessette"
    ],
    "name:vie_x_preferred":[
        "Labessette"
    ],
    "name:vol_x_preferred":[
        "Labessette"
    ],
    "name:war_x_preferred":[
        "Labessette"
    ],
    "name:zho_x_preferred":[
        "\u62c9\u8d1d\u585e\u7279"
    ],
    "qs:a0":"France",
    "qs:a1":"PUY-DE-DOME",
    "qs:a1_lc":"63",
    "qs:a1r":"AUVERGNE",
    "qs:a1r_lc":"83",
    "qs:a2_lc":"45",
    "qs:a2r_lc":"3",
    "qs:adm0":"France",
    "qs:adm0_a3":"FRA",
    "qs:la":"LABESSETTE",
    "qs:la_lc":"63183",
    "qs:level":"localadmin",
    "qs:type":"Commune simple",
    "wof:coterminous":[
        404381795
    ],
    "wof:name":"Labessette",
    "wof:placetype":"locality",
    "wof:placetype_local":"Commune simple"
},
  "geometry": {"coordinates":[2.53333,45.5],"type":"Point"}
}