{
  "type": "Feature",
  "properties": {
    "gn:admin1_code":"84",
    "gn:admin2_code":"26",
    "gn:admin3_code":"261",
    "gn:admin4_code":"26074",
    "gn:asciiname":"Revoulat",
    "gn:country_code":"FR",
    "gn:dem":1106,
    "gn:feature_class":"P",
    "gn:feature_code":"PPL",
    "gn:name":"Revoulat",
    "gn:population":0,
    "gn:timezone":"Europe/Paris",
    "iso:country":"FR",
    "wof:name":"Revoulat",
    "wof:placetype":"locality"
},
  "geometry": {"coordinates":[5.39,44.99668],"type":"Point"}
}