{
  "type": "Feature",
  "properties": {
    "gn:admin1_code":"27",
    "gn:admin2_code":"89",
    "gn:admin3_code":"892",
    "gn:admin4_code":"89431",
    "gn:asciiname":"Vassy-sous-Pisy",
    "gn:cc2":"FR",
    "gn:country_code":"FR",
    "gn:dem":325,
    "gn:feature_class":"P",
    "gn:feature_code":"PPL",
    "gn:name":"Vassy-sous-Pisy",
    "gn:population":0,
    "gn:timezone":"Europe/Paris",
    "iso:country":"FR",
    "name:bug_x_preferred":[
        "Vassy"
    ],
    "name:cat_x_preferred":[
        "Vassy-sous-Pisy"
    ],
    "name:ceb_x_preferred":[
        "Vassy"
    ],
    "name:deu_x_preferred":[
        "Vassy-sous-Pisy"
    ],
    "name:epo_x_preferred":[
        "Vassy-sous-Pisy"
    ],
    "name:eus_x_preferred":[
        "Vassy-sous-Pisy"
    ],
    "name:fas_x_preferred":[
        "\u0648\u0633\u06cc"
    ],
    "name:fra_x_preferred":[
        "Vassy-sous-Pisy"
    ],
    "name:hun_x_preferred":[
        "Vassy"
    ],
    "name:ita_x_preferred":[
        "Vassy-sous-Pisy"
    ],
    "name:kaz_x_preferred":[
        "\u0412\u0430\u0441\u0441\u0438"
    ],
    "name:lat_x_preferred":[
        "Vassy-sous-Pisy"
    ],
    "name:msa_x_preferred":[
        "Vassy"
    ],
    "name:nld_x_preferred":[
        "Vassy-sous-Pisy"
    ],
    "name:oci_x_preferred":[
        "Vassy-sous-Pisy"
    ],
    "name:pms_x_preferred":[
        "Vassy"
    ],
    "name:pol_x_preferred":[
        "Vassy"
    ],
    "name:por_x_preferred":[
        "Vassy"
    ],
    "name:ron_x_preferred":[
        "Vassy"
    ],
    "name:slk_x_preferred":[
        "Vassy-sous-Pisy"
    ],
    "name:spa_x_preferred":[
        "Vassy-sous-Pisy"
    ],
    "name:swe_x_preferred":[
        "Vassy-sous-Pisy"
    ],
    "name:ukr_x_preferred":[
        "\u0412\u0430\u0441\u0441\u0456-\u0441\u0443-\u041f\u0456\u0437\u0456"
    ],
    "name:uzb_x_preferred":[
        "Vassy"
    ],
    "name:vie_x_preferred":[
        "Vassy"
    ],
    "name:vol_x_preferred":[
        "Vassy"
    ],
    "name:war_x_preferred":[
        "Vassy"
    ],
    "name:zho_x_preferred":[
        "\u74e6\u897f\u82cf\u76ae\u897f"
    ],
    "wof:name":"Vassy-sous-Pisy",
    "wof:placetype":"locality"
},
  "geometry": {"coordinates":[4.1687,47.5695],"type":"Point"}
}