{
  "type": "Feature",
  "properties": {
    "gn:admin1_code":"27",
    "gn:admin2_code":"89",
    "gn:admin3_code":"892",
    "gn:admin4_code":"89431",
    "gn:asciiname":"Vassy-sous-Pisy",
    "gn:cc2":"FR",
    "gn:country_code":"FR",
    "gn:dem":325,
    "gn:feature_class":"P",
    "gn:feature_code":"PPL",
    "gn:name":"Vassy-sous-Pisy",
    "gn:population":0,
    "gn:timezone":"Europe/Paris",
    "iso:country":"FR",
    "wof:name":"Vassy-sous-Pisy",
    "wof:placetype":"locality"
},
  "geometry": {"coordinates":[4.1687,47.5695],"type":"Point"}
}