{
  "type": "Feature",
  "properties": {
    "gn:admin1_code":"44",
    "gn:admin2_code":"08",
    "gn:admin3_code":"084",
    "gn:admin4_code":"08392",
    "gn:asciiname":"Corbon",
    "gn:country_code":"FR",
    "gn:dem":109,
    "gn:feature_class":"P",
    "gn:feature_code":"PPL",
    "gn:name":"Corbon",
    "gn:population":0,
    "gn:timezone":"Europe/Paris",
    "iso:country":"FR",
    "name:bre_x_preferred":[
        "Corbon"
    ],
    "name:cat_x_preferred":[
        "Corbon"
    ],
    "name:ceb_x_preferred":[
        "Corbon"
    ],
    "name:deu_x_preferred":[
        "Corbon"
    ],
    "name:fra_x_preferred":[
        "Corbon"
    ],
    "name:ind_x_preferred":[
        "Corbon"
    ],
    "name:ita_x_preferred":[
        "Corbon"
    ],
    "name:nds_x_preferred":[
        "Corbon"
    ],
    "name:nld_x_preferred":[
        "Corbon"
    ],
    "name:oci_x_preferred":[
        "Corbon"
    ],
    "name:pms_x_preferred":[
        "Corbon"
    ],
    "name:pol_x_preferred":[
        "Corbon"
    ],
    "name:por_x_preferred":[
        "Corbon"
    ],
    "name:rus_x_preferred":[
        "\u041a\u043e\u0440\u0431\u043e\u043d"
    ],
    "name:scn_x_preferred":[
        "Corbon"
    ],
    "name:slk_x_preferred":[
        "Corbon"
    ],
    "name:spa_x_preferred":[
        "Corbon"
    ],
    "name:srp_x_preferred":[
        "\u041a\u043e\u0440\u0431\u043e\u043d"
    ],
    "name:swe_x_preferred":[
        "Corbon"
    ],
    "name:ukr_x_preferred":[
        "\u041a\u043e\u0440\u0431\u043e\u043d"
    ],
    "wof:name":"Corbon",
    "wof:placetype":"locality"
},
  "geometry": {"coordinates":[4.6867,49.32949],"type":"Point"}
}