{
  "type": "Feature",
  "properties": {
    "gn:admin1_code":"44",
    "gn:admin2_code":"08",
    "gn:admin3_code":"084",
    "gn:admin4_code":"08392",
    "gn:asciiname":"Corbon",
    "gn:country_code":"FR",
    "gn:dem":109,
    "gn:feature_class":"P",
    "gn:feature_code":"PPL",
    "gn:name":"Corbon",
    "gn:population":0,
    "gn:timezone":"Europe/Paris",
    "iso:country":"FR",
    "wof:name":"Corbon",
    "wof:placetype":"locality"
},
  "geometry": {"coordinates":[4.6867,49.32949],"type":"Point"}
}