{
  "type": "Feature",
  "properties": {
    "gn:admin1_code":"24",
    "gn:admin2_code":"41",
    "gn:admin3_code":"413",
    "gn:admin4_code":"41258",
    "gn:asciiname":"La Pichonniere",
    "gn:country_code":"FR",
    "gn:dem":66,
    "gn:feature_class":"P",
    "gn:feature_code":"PPL",
    "gn:name":"La Pichonni\u00e8re",
    "gn:population":0,
    "gn:timezone":"Europe/Paris",
    "iso:country":"FR",
    "wof:name":"La Pichonniere",
    "wof:placetype":"locality"
},
  "geometry": {"coordinates":[1.3288,47.30138],"type":"Point"}
}