{
  "type": "Feature",
  "properties": {
    "gn:admin1_code":"53",
    "gn:admin2_code":"22",
    "gn:admin3_code":"222",
    "gn:admin4_code":"22216",
    "gn:asciiname":"Kergoguen",
    "gn:country_code":"FR",
    "gn:dem":218,
    "gn:feature_class":"P",
    "gn:feature_code":"PPL",
    "gn:name":"Kergoguen",
    "gn:population":0,
    "gn:timezone":"Europe/Paris",
    "iso:country":"FR",
    "wof:name":"Kergoguen",
    "wof:placetype":"locality"
},
  "geometry": {"coordinates":[-3.40168,48.47453],"type":"Point"}
}