{
  "type": "Feature",
  "properties": {
    "gn:admin1_code":"75",
    "gn:admin2_code":"23",
    "gn:admin3_code":"231",
    "gn:admin4_code":"23203",
    "gn:asciiname":"Les Bordes",
    "gn:country_code":"FR",
    "gn:dem":478,
    "gn:feature_class":"P",
    "gn:feature_code":"PPL",
    "gn:name":"Les Bordes",
    "gn:population":0,
    "gn:timezone":"Europe/Paris",
    "iso:country":"FR",
    "wof:name":"Les Bordes",
    "wof:placetype":"locality"
},
  "geometry": {"coordinates":[2.47299,46.15852],"type":"Point"}
}