{
  "type": "Feature",
  "properties": {
    "gn:admin1_code":"53",
    "gn:admin2_code":"29",
    "gn:admin3_code":"292",
    "gn:admin4_code":"29042",
    "gn:asciiname":"Bouis",
    "gn:country_code":"FR",
    "gn:dem":29,
    "gn:feature_class":"P",
    "gn:feature_code":"PPL",
    "gn:name":"Bouis",
    "gn:population":0,
    "gn:timezone":"Europe/Paris",
    "iso:country":"FR",
    "wof:name":"Bouis",
    "wof:placetype":"locality"
},
  "geometry": {"coordinates":[-4.52356,48.22219000000001],"type":"Point"}
}