{
  "type": "Feature",
  "properties": {
    "gn:admin1_code":"84",
    "gn:admin2_code":"43",
    "gn:admin3_code":"433",
    "gn:admin4_code":"43114",
    "gn:asciiname":"Verne",
    "gn:country_code":"FR",
    "gn:dem":873,
    "gn:feature_class":"P",
    "gn:feature_code":"PPL",
    "gn:name":"Verne",
    "gn:population":0,
    "gn:timezone":"Europe/Paris",
    "iso:country":"FR",
    "name:bul_x_preferred":[
        "\u0412\u0435\u0440\u043d"
    ],
    "name:ceb_x_preferred":[
        "Verne"
    ],
    "name:deu_x_preferred":[
        "Verne"
    ],
    "name:fra_x_preferred":[
        "Verne"
    ],
    "name:ita_x_preferred":[
        "Jules Verne"
    ],
    "name:nds_x_preferred":[
        "Verne"
    ],
    "name:nld_x_preferred":[
        "Verne"
    ],
    "name:pol_x_preferred":[
        "Verne"
    ],
    "name:por_x_preferred":[
        "Verne"
    ],
    "name:rus_x_preferred":[
        "\u0412\u0435\u0440\u043d"
    ],
    "name:slk_x_preferred":[
        "Verne"
    ],
    "name:spa_x_preferred":[
        "Verne"
    ],
    "name:srp_x_preferred":[
        "Verne"
    ],
    "name:swe_x_preferred":[
        "Verne"
    ],
    "name:ukr_x_preferred":[
        "\u0412\u0435\u0440\u043d"
    ],
    "wof:name":"Verne",
    "wof:placetype":"locality"
},
  "geometry": {"coordinates":[4.25372,45.16863],"type":"Point"}
}