{
  "type": "Feature",
  "properties": {
    "gn:admin1_code":"52",
    "gn:admin2_code":"72",
    "gn:admin3_code":"722",
    "gn:admin4_code":"72067",
    "gn:asciiname":"Les Picaudieres",
    "gn:country_code":"FR",
    "gn:dem":91,
    "gn:feature_class":"P",
    "gn:feature_code":"PPL",
    "gn:name":"Les Picaudi\u00e8res",
    "gn:population":0,
    "gn:timezone":"Europe/Paris",
    "iso:country":"FR",
    "wof:name":"Les Picaudieres",
    "wof:placetype":"locality"
},
  "geometry": {"coordinates":[0.44732,48.09234],"type":"Point"}
}