{
  "type": "Feature",
  "properties": {
    "gn:admin1_code":"84",
    "gn:admin2_code":"07",
    "gn:admin3_code":"071",
    "gn:admin4_code":"07343",
    "gn:asciiname":"Vinezac",
    "gn:country_code":"FR",
    "gn:dem":249,
    "gn:feature_class":"P",
    "gn:feature_code":"PPL",
    "gn:name":"Vinezac",
    "gn:population":0,
    "gn:timezone":"Europe/Paris",
    "iso:country":"FR",
    "name:cat_x_preferred":[
        "Vinesac"
    ],
    "name:hye_x_preferred":[
        "\u054e\u056b\u0576\u0566\u0561\u056f"
    ],
    "name:rus_x_preferred":[
        "\u0412\u0438\u043d\u0437\u0430\u043a"
    ],
    "name:ukr_x_preferred":[
        "\u0412\u0456\u043d\u0437\u0430\u043a"
    ],
    "name:zho_x_preferred":[
        "\u7ef4\u5185\u624e\u514b"
    ],
    "wof:name":"Vinezac",
    "wof:placetype":"locality"
},
  "geometry": {"coordinates":[4.32449,44.53947],"type":"Point"}
}