{
  "type": "Feature",
  "properties": {
    "frgov:code_epci":"200073245",
    "frgov:insee_arr":"1",
    "frgov:insee_com":"07343",
    "frgov:insee_dep":"07",
    "frgov:insee_reg":"84",
    "frgov:nom_com":"Vinezac",
    "frgov:nom_com_m":"VINEZAC",
    "frgov:nom_dep":"ARDECHE",
    "frgov:nom_reg":"AUVERGNE-RHONE-ALPES",
    "frgov:statut":"Commune simple",
    "gn:admin1_code":"84",
    "gn:admin2_code":"07",
    "gn:admin3_code":"071",
    "gn:admin4_code":"07343",
    "gn:asciiname":"Vinezac",
    "gn:country_code":"FR",
    "gn:dem":249,
    "gn:feature_class":"P",
    "gn:feature_code":"PPL",
    "gn:name":"Vinezac",
    "gn:population":0,
    "gn:timezone":"Europe/Paris",
    "iso:country":"FR",
    "name:bug_x_preferred":[
        "Vinezac"
    ],
    "name:cat_x_preferred":[
        "Vinesac"
    ],
    "name:ceb_x_preferred":[
        "Vinezac"
    ],
    "name:deu_x_preferred":[
        "Vinezac"
    ],
    "name:eus_x_preferred":[
        "Vinezac"
    ],
    "name:fra_x_preferred":[
        "Vinezac"
    ],
    "name:hun_x_preferred":[
        "Vinezac"
    ],
    "name:hye_x_preferred":[
        "\u054e\u056b\u0576\u0566\u0561\u056f"
    ],
    "name:ita_x_preferred":[
        "Vinezac"
    ],
    "name:lat_x_preferred":[
        "Vinezac"
    ],
    "name:lmo_x_preferred":[
        "Vinezac"
    ],
    "name:msa_x_preferred":[
        "Vinezac"
    ],
    "name:nld_x_preferred":[
        "Vinezac"
    ],
    "name:oci_x_preferred":[
        "Vinasac"
    ],
    "name:pms_x_preferred":[
        "Vinezac"
    ],
    "name:pol_x_preferred":[
        "Vinezac"
    ],
    "name:por_x_preferred":[
        "Vinezac"
    ],
    "name:ron_x_preferred":[
        "Vinezac"
    ],
    "name:rus_x_preferred":[
        "\u0412\u0438\u043d\u0437\u0430\u043a"
    ],
    "name:slk_x_preferred":[
        "Vinezac"
    ],
    "name:spa_x_preferred":[
        "Vinezac"
    ],
    "name:sqi_x_preferred":[
        "Vinezac"
    ],
    "name:swe_x_preferred":[
        "Vinezac"
    ],
    "name:ukr_x_preferred":[
        "\u0412\u0456\u043d\u0437\u0430\u043a"
    ],
    "name:uzb_x_preferred":[
        "Vinezac"
    ],
    "name:vie_x_preferred":[
        "Vinezac"
    ],
    "name:vol_x_preferred":[
        "Vinezac"
    ],
    "name:war_x_preferred":[
        "Vinezac"
    ],
    "name:zho_x_preferred":[
        "\u7ef4\u5185\u624e\u514b"
    ],
    "qs:a0":"France",
    "qs:a1":"ARDECHE",
    "qs:a1_lc":"07",
    "qs:a1r":"RHONE-ALPES",
    "qs:a1r_lc":"82",
    "qs:a2_lc":"11",
    "qs:a2r_lc":"1",
    "qs:adm0":"France",
    "qs:adm0_a3":"FRA",
    "qs:la":"VINEZAC",
    "qs:la_lc":"07343",
    "qs:level":"localadmin",
    "qs:type":"Commune simple",
    "wof:coterminous":[
        404364979
    ],
    "wof:name":"Vinezac",
    "wof:placetype":"locality",
    "wof:placetype_local":"Commune simple"
},
  "geometry": {"coordinates":[4.32449,44.53947],"type":"Point"}
}