{
  "type": "Feature",
  "properties": {
    "gn:admin1_code":"75",
    "gn:admin2_code":"23",
    "gn:admin3_code":"231",
    "gn:admin4_code":"23144",
    "gn:asciiname":"Le Chiroux",
    "gn:country_code":"FR",
    "gn:dem":723,
    "gn:feature_class":"P",
    "gn:feature_code":"PPL",
    "gn:name":"Le Chiroux",
    "gn:population":0,
    "gn:timezone":"Europe/Paris",
    "iso:country":"FR",
    "wof:name":"Le Chiroux",
    "wof:placetype":"locality"
},
  "geometry": {"coordinates":[2.07151,45.82714],"type":"Point"}
}