{
  "type": "Feature",
  "properties": {
    "gn:admin1_code":"75",
    "gn:admin2_code":"86",
    "gn:admin3_code":"863",
    "gn:admin4_code":"86281",
    "gn:asciiname":"Signy",
    "gn:country_code":"FR",
    "gn:dem":83,
    "gn:feature_class":"P",
    "gn:feature_code":"PPL",
    "gn:name":"Signy",
    "gn:population":0,
    "gn:timezone":"Europe/Paris",
    "iso:country":"FR",
    "name:dan_x_preferred":[
        "Signe"
    ],
    "name:deu_x_preferred":[
        "Signy"
    ],
    "name:fas_x_preferred":[
        "\u0632\u06cc\u06af\u0646\u06cc"
    ],
    "name:fra_x_preferred":[
        "Sign\u00fd"
    ],
    "name:ita_x_preferred":[
        "Signe"
    ],
    "name:jpn_x_preferred":[
        "\u30b7\u30b0\u30cb\u30e5\u30fc"
    ],
    "name:kor_x_preferred":[
        "\uc2dc\uadf8\ub258"
    ],
    "name:por_x_preferred":[
        "Signy"
    ],
    "name:spa_x_preferred":[
        "Signy"
    ],
    "name:swe_x_preferred":[
        "Signe"
    ],
    "wof:name":"Signy",
    "wof:placetype":"locality"
},
  "geometry": {"coordinates":[0.32931,46.75469],"type":"Point"}
}