{
  "type": "Feature",
  "properties": {
    "gn:admin1_code":"75",
    "gn:admin2_code":"16",
    "gn:admin3_code":"163",
    "gn:admin4_code":"16149",
    "gn:asciiname":"La Garde",
    "gn:cc2":"FR",
    "gn:country_code":"FR",
    "gn:dem":222,
    "gn:feature_class":"P",
    "gn:feature_code":"PPL",
    "gn:name":"La Garde",
    "gn:population":0,
    "gn:timezone":"Europe/Paris",
    "iso:country":"FR",
    "name:und_x_variant":[
        "Garde",
        "La Garde"
    ],
    "wof:name":"La Garde",
    "wof:placetype":"locality"
},
  "geometry": {"coordinates":[0.56159,45.84764000000001],"type":"Point"}
}