{
  "type": "Feature",
  "properties": {
    "gn:admin1_code":"28",
    "gn:admin2_code":"61",
    "gn:admin3_code":"612",
    "gn:admin4_code":"61188.0",
    "gn:asciiname":"Taloney",
    "gn:country_code":"FR",
    "gn:dem":217,
    "gn:feature_class":"P",
    "gn:feature_code":"PPL",
    "gn:name":"Taloney",
    "gn:population":0,
    "gn:timezone":"Europe/Paris",
    "iso:country":"FR",
    "wof:name":"Taloney",
    "wof:placetype":"locality"
},
  "geometry": {"coordinates":[0.29038,48.68125],"type":"Point"}
}