{
  "type": "Feature",
  "properties": {
    "gn:admin1_code":"27",
    "gn:admin2_code":"58",
    "gn:admin3_code":"583",
    "gn:admin4_code":"58264.0",
    "gn:asciiname":"Marcigny",
    "gn:country_code":"FR",
    "gn:dem":214,
    "gn:feature_class":"P",
    "gn:feature_code":"PPL",
    "gn:name":"Marcigny",
    "gn:population":0,
    "gn:timezone":"Europe/Paris",
    "iso:country":"FR",
    "name:cat_x_preferred":[
        "Marcigny"
    ],
    "name:ceb_x_preferred":[
        "Marcigny"
    ],
    "name:deu_x_preferred":[
        "Marcigny"
    ],
    "name:eus_x_preferred":[
        "Marcigny"
    ],
    "name:fra_x_preferred":[
        "Marcigny"
    ],
    "name:hun_x_preferred":[
        "Marcigny"
    ],
    "name:ita_x_preferred":[
        "Marcigny"
    ],
    "name:kaz_x_preferred":[
        "\u041c\u0430\u0440\u0441\u0438\u043d\u044c\u0438"
    ],
    "name:lat_x_preferred":[
        "Marcigny"
    ],
    "name:msa_x_preferred":[
        "Marcigny"
    ],
    "name:nld_x_preferred":[
        "Marcigny"
    ],
    "name:oci_x_preferred":[
        "Marcigny"
    ],
    "name:pms_x_preferred":[
        "Marcigny"
    ],
    "name:pol_x_preferred":[
        "Marcigny"
    ],
    "name:por_x_preferred":[
        "Marcigny"
    ],
    "name:ron_x_preferred":[
        "Marcigny"
    ],
    "name:slk_x_preferred":[
        "Marcigny"
    ],
    "name:spa_x_preferred":[
        "Marcigny"
    ],
    "name:swe_x_preferred":[
        "Marcigny"
    ],
    "name:ukr_x_preferred":[
        "\u041c\u0430\u0440\u0441\u0456\u043d\u044c\u0457"
    ],
    "name:uzb_x_preferred":[
        "Marcigny"
    ],
    "name:vie_x_preferred":[
        "Marcigny"
    ],
    "name:vol_x_preferred":[
        "Marcigny"
    ],
    "name:war_x_preferred":[
        "Marcigny"
    ],
    "wof:name":"Marcigny",
    "wof:placetype":"locality"
},
  "geometry": {"coordinates":[3.0961,46.78657000000001],"type":"Point"}
}