{
  "type": "Feature",
  "properties": {
    "gn:admin1_code":"75",
    "gn:admin2_code":"24",
    "gn:admin3_code":"241",
    "gn:admin4_code":"24168",
    "gn:asciiname":"Falgueyrat",
    "gn:country_code":"FR",
    "gn:dem":83,
    "gn:feature_class":"P",
    "gn:feature_code":"PPL",
    "gn:name":"Falgueyrat",
    "gn:population":0,
    "gn:timezone":"Europe/Paris",
    "iso:country":"FR",
    "wof:name":"Falgueyrat",
    "wof:placetype":"locality"
},
  "geometry": {"coordinates":[0.5373,44.6783],"type":"Point"}
}