{
  "type": "Feature",
  "properties": {
    "gn:admin1_code":"84",
    "gn:admin2_code":"43",
    "gn:admin3_code":"432",
    "gn:admin4_code":"43164",
    "gn:asciiname":"Chamboulive",
    "gn:country_code":"FR",
    "gn:dem":532,
    "gn:feature_class":"P",
    "gn:feature_code":"PPL",
    "gn:name":"Chamboulive",
    "gn:population":0,
    "gn:timezone":"Europe/Paris",
    "iso:country":"FR",
    "name:bug_x_preferred":[
        "Chamboulive"
    ],
    "name:cat_x_preferred":[
        "Chamboliva"
    ],
    "name:ceb_x_preferred":[
        "Chamboulive"
    ],
    "name:deu_x_preferred":[
        "Chamboulive"
    ],
    "name:eus_x_preferred":[
        "Chamboliva"
    ],
    "name:fra_x_preferred":[
        "Chamboulive"
    ],
    "name:hun_x_preferred":[
        "Chamboulive"
    ],
    "name:ind_x_preferred":[
        "Chamboulive"
    ],
    "name:ita_x_preferred":[
        "Chamboulive"
    ],
    "name:kaz_x_preferred":[
        "\u0428\u0430\u043c\u0431\u0443\u043b\u0438\u0432"
    ],
    "name:lat_x_preferred":[
        "Chamboulive"
    ],
    "name:mlg_x_preferred":[
        "Chamboulive"
    ],
    "name:msa_x_preferred":[
        "Chamboulive"
    ],
    "name:nld_x_preferred":[
        "Chamboulive"
    ],
    "name:oci_x_preferred":[
        "Chamboliva"
    ],
    "name:pms_x_preferred":[
        "Chamboulive"
    ],
    "name:pol_x_preferred":[
        "Chamboulive"
    ],
    "name:por_x_preferred":[
        "Chamboulive"
    ],
    "name:ron_x_preferred":[
        "Chamboulive"
    ],
    "name:rus_x_preferred":[
        "\u0428\u0430\u043c\u0431\u0443\u043b\u0438\u0432"
    ],
    "name:slk_x_preferred":[
        "Chamboulive"
    ],
    "name:spa_x_preferred":[
        "Chamboulive"
    ],
    "name:srp_x_preferred":[
        "\u0428\u0430\u043c\u0431\u0443\u043b\u0438\u0432"
    ],
    "name:swe_x_preferred":[
        "Chamboulive"
    ],
    "name:ukr_x_preferred":[
        "\u0428\u0430\u043c\u0431\u0443\u043b\u0456\u0432"
    ],
    "name:uzb_x_preferred":[
        "Chamboulive"
    ],
    "name:vie_x_preferred":[
        "Chamboulive"
    ],
    "name:vol_x_preferred":[
        "Chamboulive"
    ],
    "name:war_x_preferred":[
        "Chamboulive"
    ],
    "name:zho_x_preferred":[
        "\u5c1a\u5e03\u5229\u592b"
    ],
    "wof:name":"Chamboulive",
    "wof:placetype":"locality"
},
  "geometry": {"coordinates":[3.96639,45.19982],"type":"Point"}
}