{
  "type": "Feature",
  "properties": {
    "gn:admin1_code":"84",
    "gn:admin2_code":"43",
    "gn:admin3_code":"432",
    "gn:admin4_code":"43164",
    "gn:asciiname":"Chamboulive",
    "gn:country_code":"FR",
    "gn:dem":532,
    "gn:feature_class":"P",
    "gn:feature_code":"PPL",
    "gn:name":"Chamboulive",
    "gn:population":0,
    "gn:timezone":"Europe/Paris",
    "iso:country":"FR",
    "wof:name":"Chamboulive",
    "wof:placetype":"locality"
},
  "geometry": {"coordinates":[3.96639,45.19982],"type":"Point"}
}