{
  "type": "Feature",
  "properties": {
    "gn:admin1_code":"84",
    "gn:admin2_code":"73",
    "gn:admin3_code":"731",
    "gn:admin4_code":"73034",
    "gn:asciiname":"Les Sauces",
    "gn:country_code":"FR",
    "gn:dem":1643,
    "gn:feature_class":"P",
    "gn:feature_code":"PPL",
    "gn:name":"Les Sauces",
    "gn:population":0,
    "gn:timezone":"Europe/Paris",
    "iso:country":"FR",
    "wof:name":"Les Sauces",
    "wof:placetype":"locality"
},
  "geometry": {"coordinates":[6.65784,45.69611],"type":"Point"}
}