{
  "type": "Feature",
  "properties": {
    "gn:admin1_code":"24",
    "gn:admin2_code":"28",
    "gn:admin3_code":"281",
    "gn:admin4_code":"28397",
    "gn:asciiname":"Breez",
    "gn:country_code":"FR",
    "gn:dem":154,
    "gn:feature_class":"P",
    "gn:feature_code":"PPL",
    "gn:name":"Br\u00e9ez",
    "gn:population":0,
    "gn:timezone":"Europe/Paris",
    "iso:country":"FR",
    "wof:name":"Breez",
    "wof:placetype":"locality"
},
  "geometry": {"coordinates":[1.65166,48.45595],"type":"Point"}
}