{
  "type": "Feature",
  "properties": {
    "gn:admin1_code":"53",
    "gn:admin2_code":"56",
    "gn:admin3_code":"561",
    "gn:admin4_code":"56098",
    "gn:asciiname":"Saint-Nudec",
    "gn:country_code":"FR",
    "gn:dem":24,
    "gn:feature_class":"P",
    "gn:feature_code":"PPL",
    "gn:name":"Saint-Nudec",
    "gn:population":0,
    "gn:timezone":"Europe/Paris",
    "iso:country":"FR",
    "wof:name":"Saint-Nudec",
    "wof:placetype":"locality"
},
  "geometry": {"coordinates":[-3.29909,47.7917],"type":"Point"}
}