{
  "type": "Feature",
  "properties": {
    "gn:admin1_code":"27",
    "gn:admin2_code":"89",
    "gn:admin3_code":"891",
    "gn:admin4_code":"89205",
    "gn:asciiname":"La Tuilerie",
    "gn:country_code":"FR",
    "gn:dem":121,
    "gn:feature_class":"P",
    "gn:feature_code":"PPL",
    "gn:name":"La Tuilerie",
    "gn:population":0,
    "gn:timezone":"Europe/Paris",
    "iso:country":"FR",
    "wof:name":"La Tuilerie",
    "wof:placetype":"locality"
},
  "geometry": {"coordinates":[3.78801,47.95385],"type":"Point"}
}