{
  "type": "Feature",
  "properties": {
    "gn:admin1_code":"27",
    "gn:admin2_code":"71",
    "gn:admin3_code":"713",
    "gn:admin4_code":"71176",
    "gn:asciiname":"Vigny-les-Paray",
    "gn:country_code":"FR",
    "gn:dem":257,
    "gn:feature_class":"P",
    "gn:feature_code":"PPL",
    "gn:name":"Vigny-l\u00e8s-Paray",
    "gn:population":0,
    "gn:timezone":"Europe/Paris",
    "iso:country":"FR",
    "name:und_x_variant":[
        "Vigny",
        "Vigny-l\u00e8s-Paray"
    ],
    "wof:name":"Vigny-les-Paray",
    "wof:placetype":"locality"
},
  "geometry": {"coordinates":[4.08306,46.5026],"type":"Point"}
}