{
  "type": "Feature",
  "properties": {
    "gn:admin1_code":"28",
    "gn:admin2_code":"14",
    "gn:admin3_code":"142",
    "gn:admin4_code":"14721.0",
    "gn:asciiname":"Neuilly-le-Malherbe",
    "gn:country_code":"FR",
    "gn:dem":93,
    "gn:feature_class":"P",
    "gn:feature_code":"PPL",
    "gn:name":"Neuilly-le-Malherbe",
    "gn:population":0,
    "gn:timezone":"Europe/Paris",
    "iso:country":"FR",
    "name:und_x_variant":[
        "Neuilly",
        "Neuilly-le-Malherbe"
    ],
    "wof:name":"Neuilly-le-Malherbe",
    "wof:placetype":"locality"
},
  "geometry": {"coordinates":[-0.53738,49.09766],"type":"Point"}
}