{
  "type": "Feature",
  "properties": {
    "iso:country":"FR",
    "name:eng_x_preferred":[
        "Saint-Augustin"
    ],
    "name:fra_x_preferred":[
        "Saint-Augustin"
    ],
    "wof:name":"Saint-Augustin",
    "wof:placetype":"neighbourhood"
},
  "geometry": {"coordinates":[7.20636207550951,43.67854578755092],"type":"Point"}
}