{
  "type": "Feature",
  "properties": {
    "gn:admin1_code":"76",
    "gn:admin2_code":"12",
    "gn:admin3_code":"121",
    "gn:admin4_code":"12260",
    "gn:asciiname":"La Roujarie",
    "gn:country_code":"FR",
    "gn:dem":802,
    "gn:feature_class":"P",
    "gn:feature_code":"PPL",
    "gn:name":"La Roujarie",
    "gn:population":0,
    "gn:timezone":"Europe/Paris",
    "iso:country":"FR",
    "wof:name":"La Roujarie",
    "wof:placetype":"locality"
},
  "geometry": {"coordinates":[3.41206,43.99163],"type":"Point"}
}