{
  "type": "Feature",
  "properties": {
    "gn:admin1_code":"84",
    "gn:admin2_code":"43",
    "gn:admin3_code":"433",
    "gn:admin4_code":"43268",
    "gn:asciiname":"Marnhac",
    "gn:country_code":"FR",
    "gn:dem":815,
    "gn:feature_class":"P",
    "gn:feature_code":"PPL",
    "gn:name":"Marnhac",
    "gn:population":0,
    "gn:timezone":"Europe/Paris",
    "iso:country":"FR",
    "wof:name":"Marnhac",
    "wof:placetype":"locality"
},
  "geometry": {"coordinates":[4.0913,45.16393],"type":"Point"}
}