{
  "type": "Feature",
  "properties": {
    "gn:admin1_code":"84",
    "gn:admin2_code":"63",
    "gn:admin3_code":"634",
    "gn:admin4_code":"63170",
    "gn:asciiname":"Ballot",
    "gn:country_code":"FR",
    "gn:dem":770,
    "gn:feature_class":"P",
    "gn:feature_code":"PPL",
    "gn:name":"Ballot",
    "gn:population":0,
    "gn:timezone":"Europe/Paris",
    "iso:country":"FR",
    "wof:name":"Ballot",
    "wof:placetype":"locality"
},
  "geometry": {"coordinates":[2.72305,45.83503],"type":"Point"}
}