{
  "type": "Feature",
  "properties": {
    "gn:admin1_code":"84",
    "gn:admin2_code":"63",
    "gn:admin3_code":"634",
    "gn:admin4_code":"63170",
    "gn:asciiname":"Ballot",
    "gn:country_code":"FR",
    "gn:dem":770,
    "gn:feature_class":"P",
    "gn:feature_code":"PPL",
    "gn:name":"Ballot",
    "gn:population":0,
    "gn:timezone":"Europe/Paris",
    "iso:country":"FR",
    "name:ara_x_preferred":[
        "\u0648\u0631\u0642\u0629 \u0627\u0642\u062a\u0631\u0627\u0639"
    ],
    "name:aze_x_preferred":[
        "Se\u00e7ki v\u0259r\u0259q\u0259si"
    ],
    "name:bel_x_preferred":[
        "\u0412\u044b\u0431\u0430\u0440\u0447\u044b \u0431\u044e\u043b\u0435\u0442\u044d\u043d\u044c"
    ],
    "name:cat_x_preferred":[
        "Papereta electoral"
    ],
    "name:chr_x_preferred":[
        "\u13a7\u13c1\u13e8\u13a2"
    ],
    "name:cym_x_preferred":[
        "Balod"
    ],
    "name:dan_x_preferred":[
        "Stemmeseddel"
    ],
    "name:deu_x_preferred":[
        "Stimmzettel"
    ],
    "name:epo_x_preferred":[
        "Balotilo"
    ],
    "name:eus_x_preferred":[
        "Boto-txartel"
    ],
    "name:fas_x_preferred":[
        "\u062a\u0639\u0631\u0641\u0647 \u0627\u0646\u062a\u062e\u0627\u0628\u0627\u062a\u06cc"
    ],
    "name:heb_x_preferred":[
        "\u05e4\u05ea\u05e7 \u05d4\u05e6\u05d1\u05e2\u05d4"
    ],
    "name:hrv_x_preferred":[
        "Glasa\u010dki listi\u0107"
    ],
    "name:ind_x_preferred":[
        "Surat suara"
    ],
    "name:ita_x_preferred":[
        "Scheda elettorale"
    ],
    "name:kaz_x_preferred":[
        "\u0411\u044e\u043b\u043b\u0435\u0442\u0435\u043d\u044c"
    ],
    "name:kor_x_preferred":[
        "\ud22c\ud45c\uc6a9\uc9c0"
    ],
    "name:lmo_x_preferred":[
        "Scheda elettorala"
    ],
    "name:msa_x_preferred":[
        "Kertas undi"
    ],
    "name:nld_x_preferred":[
        "Stembiljet"
    ],
    "name:nor_x_preferred":[
        "Stemmeseddel"
    ],
    "name:pan_x_preferred":[
        "\u0a1a\u0a4b\u0a23 \u0a2a\u0a30\u0a1a\u0a40"
    ],
    "name:por_x_preferred":[
        "C\u00e9dula eleitoral"
    ],
    "name:rus_x_preferred":[
        "\u0418\u0437\u0431\u0438\u0440\u0430\u0442\u0435\u043b\u044c\u043d\u044b\u0439 \u0431\u044e\u043b\u043b\u0435\u0442\u0435\u043d\u044c"
    ],
    "name:sin_x_preferred":[
        "\u0da1\u0db1\u0dca\u0daf \u0db4\u0dad\u0dca\u200d\u0dbb\u0dd2\u0d9a\u0dcf"
    ],
    "name:snd_x_preferred":[
        "\u0628\u064a\u0644\u067d \u067e\u064a\u067e\u0631"
    ],
    "name:spa_x_preferred":[
        "Boleta electoral"
    ],
    "name:swa_x_preferred":[
        "Kura"
    ],
    "name:swe_x_preferred":[
        "Valsedel"
    ],
    "name:tur_x_preferred":[
        "Oy pusulas\u0131"
    ],
    "name:ukr_x_preferred":[
        "\u0412\u0438\u0431\u043e\u0440\u0447\u0438\u0439 \u0431\u044e\u043b\u0435\u0442\u0435\u043d\u044c"
    ],
    "wof:name":"Ballot",
    "wof:placetype":"locality"
},
  "geometry": {"coordinates":[2.72305,45.83503],"type":"Point"}
}