{
  "type": "Feature",
  "properties": {
    "gn:admin1_code":"94",
    "gn:admin2_code":"2B",
    "gn:admin3_code":"2B3",
    "gn:admin4_code":"2B009",
    "gn:asciiname":"Casabianda",
    "gn:country_code":"FR",
    "gn:dem":36,
    "gn:feature_class":"P",
    "gn:feature_code":"PPL",
    "gn:name":"Casabianda",
    "gn:population":0,
    "gn:timezone":"Europe/Paris",
    "iso:country":"FR",
    "wof:name":"Casabianda",
    "wof:placetype":"locality"
},
  "geometry": {"coordinates":[9.50307,42.09466],"type":"Point"}
}