{
  "type": "Feature",
  "properties": {
    "iso:country":"FR",
    "name:eng_x_preferred":[
        "Comedie"
    ],
    "name:fra_x_preferred":[
        "Com\u00e9die"
    ],
    "wof:name":"Comedie",
    "wof:placetype":"neighbourhood"
},
  "geometry": {"coordinates":[3.88050896293708,43.60915687177086],"type":"Point"}
}