{
  "type": "Feature",
  "properties": {
    "iso:country":"FR",
    "name:eng_x_preferred":[
        "River-de-Seine-Gallieni"
    ],
    "name:fra_x_preferred":[
        "River-de-Seine-Gallieni"
    ],
    "wof:name":"River-de-Seine-Gallieni",
    "wof:placetype":"neighbourhood"
},
  "geometry": {"coordinates":[2.33294090560078,48.93276781778412],"type":"Point"}
}