{
  "type": "Feature",
  "properties": {
    "iso:country":"FR",
    "name:eng_x_preferred":[
        "Fosse de l'Aumone\n"
    ],
    "name:fra_x_preferred":[
        "Foss\u00e9 de l'Aum\u00f4ne\n"
    ],
    "wof:name":"Fosse de l'Aumone\n",
    "wof:placetype":"neighbourhood"
},
  "geometry": {"coordinates":[2.28936750416015,48.92063395617004],"type":"Point"}
}