{
  "type": "Feature",
  "properties": {
    "iso:country":"FR",
    "name:eng_x_preferred":[
        "Fosse de l'Aumone"
    ],
    "name:fra_x_preferred":[
        "Foss\u00e9 de l'Aum\u00f4ne"
    ],
    "wof:name":"Fosse de l'Aumone\n",
    "wof:placetype":"neighbourhood"
},
  "geometry": {"coordinates":[2.289368,48.920634],"type":"Point"}
}