{
  "type": "Feature",
  "properties": {
    "frgov:code_epci":"200069730",
    "frgov:insee_arr":"1",
    "frgov:insee_com":"27392",
    "frgov:insee_dep":"27",
    "frgov:insee_reg":"28",
    "frgov:nom_com":"Martagny",
    "frgov:nom_com_m":"MARTAGNY",
    "frgov:nom_dep":"EURE",
    "frgov:nom_reg":"NORMANDIE",
    "frgov:statut":"Commune simple",
    "gn:admin1_code":"28",
    "gn:admin2_code":"27",
    "gn:admin3_code":"271",
    "gn:admin4_code":"27392",
    "gn:asciiname":"Martagny",
    "gn:country_code":"FR",
    "gn:dem":127,
    "gn:feature_class":"P",
    "gn:feature_code":"PPL",
    "gn:name":"Martagny",
    "gn:population":0,
    "gn:timezone":"Europe/Paris",
    "iso:country":"FR",
    "name:bug_x_preferred":[
        "Martagny"
    ],
    "name:cat_x_preferred":[
        "Martagny"
    ],
    "name:ceb_x_preferred":[
        "Martagny"
    ],
    "name:deu_x_preferred":[
        "Martagny"
    ],
    "name:eus_x_preferred":[
        "Martagny"
    ],
    "name:fra_x_preferred":[
        "Martagny"
    ],
    "name:hun_x_preferred":[
        "Martagny"
    ],
    "name:ita_x_preferred":[
        "Martagny"
    ],
    "name:kaz_x_preferred":[
        "\u041c\u0430\u0440\u0442\u0430\u043d\u044c\u0438"
    ],
    "name:lat_x_preferred":[
        "Martagny"
    ],
    "name:mlg_x_preferred":[
        "Martagny"
    ],
    "name:msa_x_preferred":[
        "Martagny"
    ],
    "name:nld_x_preferred":[
        "Martagny"
    ],
    "name:oci_x_preferred":[
        "Martagny"
    ],
    "name:pms_x_preferred":[
        "Martagny"
    ],
    "name:pol_x_preferred":[
        "Martagny"
    ],
    "name:por_x_preferred":[
        "Martagny"
    ],
    "name:slk_x_preferred":[
        "Martagny"
    ],
    "name:spa_x_preferred":[
        "Martagny"
    ],
    "name:swe_x_preferred":[
        "Martagny"
    ],
    "name:ukr_x_preferred":[
        "\u041c\u0430\u0440\u0442\u0430\u043d\u044c\u0457"
    ],
    "name:vie_x_preferred":[
        "Martagny"
    ],
    "name:vol_x_preferred":[
        "Martagny"
    ],
    "name:war_x_preferred":[
        "Martagny"
    ],
    "name:zho_x_preferred":[
        "\u9a6c\u5c14\u5854\u5c3c"
    ],
    "qs:a0":"France",
    "qs:a1":"EURE",
    "qs:a1_lc":"27",
    "qs:a1r":"HAUTE-NORMANDIE",
    "qs:a1r_lc":"23",
    "qs:a2_lc":"20",
    "qs:a2r_lc":"1",
    "qs:adm0":"France",
    "qs:adm0_a3":"FRA",
    "qs:la":"MARTAGNY",
    "qs:la_lc":"27392",
    "qs:level":"localadmin",
    "qs:type":"Commune simple",
    "wof:coterminous":[
        404412771
    ],
    "wof:name":"Martagny",
    "wof:placetype":"locality",
    "wof:placetype_local":"Commune simple"
},
  "geometry": {"coordinates":[1.6604,49.3947],"type":"Point"}
}