{
  "type": "Feature",
  "properties": {
    "gn:admin1_code":"53",
    "gn:admin2_code":"35",
    "gn:admin3_code":"353",
    "gn:admin4_code":"35041",
    "gn:asciiname":"Le Beauchene",
    "gn:country_code":"FR",
    "gn:dem":81,
    "gn:feature_class":"P",
    "gn:feature_code":"PPL",
    "gn:name":"Le Beauch\u00eane",
    "gn:population":0,
    "gn:timezone":"Europe/Paris",
    "iso:country":"FR",
    "wof:name":"Le Beauchene",
    "wof:placetype":"locality"
},
  "geometry": {"coordinates":[-1.56705,47.95781],"type":"Point"}
}