{
  "type": "Feature",
  "properties": {
    "gn:admin1_code":"84",
    "gn:admin2_code":"74",
    "gn:admin3_code":"741",
    "gn:admin4_code":"74072",
    "gn:asciiname":"Marseau",
    "gn:country_code":"FR",
    "gn:dem":517,
    "gn:feature_class":"P",
    "gn:feature_code":"PPL",
    "gn:name":"Marseau",
    "gn:population":0,
    "gn:timezone":"Europe/Paris",
    "iso:country":"FR",
    "wof:name":"Marseau",
    "wof:placetype":"locality"
},
  "geometry": {"coordinates":[6.21667,45.76667],"type":"Point"}
}