{
  "type": "Feature",
  "properties": {
    "gn:admin1_code":"28",
    "gn:admin2_code":"61",
    "gn:admin3_code":"612",
    "gn:admin4_code":"61167",
    "gn:asciiname":"Marnefer",
    "gn:country_code":"FR",
    "gn:dem":225,
    "gn:feature_class":"P",
    "gn:feature_code":"PPL",
    "gn:name":"Marnefer",
    "gn:population":0,
    "gn:timezone":"Europe/Paris",
    "iso:country":"FR",
    "wof:name":"Marnefer",
    "wof:placetype":"locality"
},
  "geometry": {"coordinates":[0.57489,48.88294000000001],"type":"Point"}
}