{
  "type": "Feature",
  "properties": {
    "gn:admin1_code":"28",
    "gn:admin2_code":"76",
    "gn:admin3_code":"761",
    "gn:admin4_code":"76427",
    "gn:asciiname":"Isembertheville",
    "gn:country_code":"FR",
    "gn:dem":57,
    "gn:feature_class":"P",
    "gn:feature_code":"PPL",
    "gn:name":"Isembertheville",
    "gn:population":0,
    "gn:timezone":"Europe/Paris",
    "iso:country":"FR",
    "wof:name":"Isembertheville",
    "wof:placetype":"locality"
},
  "geometry": {"coordinates":[1.35889,49.77208],"type":"Point"}
}