{
  "type": "Feature",
  "properties": {
    "gn:admin1_code":"84",
    "gn:admin2_code":"43",
    "gn:admin3_code":"433",
    "gn:admin4_code":"43224",
    "gn:asciiname":"Le Pinet",
    "gn:country_code":"FR",
    "gn:dem":782,
    "gn:feature_class":"P",
    "gn:feature_code":"PPL",
    "gn:name":"Le Pinet",
    "gn:population":0,
    "gn:timezone":"Europe/Paris",
    "iso:country":"FR",
    "wof:name":"Le Pinet",
    "wof:placetype":"locality"
},
  "geometry": {"coordinates":[4.23712,45.2289],"type":"Point"}
}