{
  "type": "Feature",
  "properties": {
    "iso:country":"FR",
    "qs_pg:aaroncc":"FR",
    "qs_pg:name":"Laschamp",
    "qs_pg:name_adm0":"France",
    "qs_pg:name_adm1":"Auvergne",
    "qs_pg:photos":309,
    "qs_pg:photos_1k":63,
    "qs_pg:photos_9k":1,
    "qs_pg:photos_9r":5,
    "qs_pg:photos_all":309,
    "qs_pg:photos_sr":5,
    "qs_pg:pop_sr":0,
    "qs_pg:qs_pg_placetype":"locality",
    "qs_pg:qs_pg_placetype_gp":"Town",
    "qs_pg:woe_adm0":23424819,
    "woe:adm0_id":23424819,
    "woe:name_adm0":"France",
    "woe:name_adm1":"Auvergne",
    "woe:placetype":"Town",
    "wof:name":"Laschamp",
    "wof:placetype":"neighbourhood"
},
  "geometry": {"coordinates":[2.964076,45.772252],"type":"Point"}
}