{
  "type": "Feature",
  "properties": {
    "gn:admin1_code":"84",
    "gn:admin2_code":"38",
    "gn:admin3_code":"383",
    "gn:admin4_code":"38072",
    "gn:asciiname":"Herpieux",
    "gn:country_code":"FR",
    "gn:dem":188,
    "gn:feature_class":"P",
    "gn:feature_code":"PPL",
    "gn:name":"Herpieux",
    "gn:population":0,
    "gn:timezone":"Europe/Paris",
    "iso:country":"FR",
    "wof:name":"Herpieux",
    "wof:placetype":"locality"
},
  "geometry": {"coordinates":[4.84918,45.31809000000001],"type":"Point"}
}