{
  "type": "Feature",
  "properties": {
    "gn:admin1_code":"84",
    "gn:admin2_code":"26",
    "gn:admin3_code":"263",
    "gn:admin4_code":"26295",
    "gn:asciiname":"Marnas",
    "gn:country_code":"FR",
    "gn:dem":200,
    "gn:feature_class":"P",
    "gn:feature_code":"PPL",
    "gn:name":"Marnas",
    "gn:population":0,
    "gn:timezone":"Europe/Paris",
    "iso:country":"FR",
    "wof:name":"Marnas",
    "wof:placetype":"locality"
},
  "geometry": {"coordinates":[4.88226,45.16067],"type":"Point"}
}