{
  "type": "Feature",
  "properties": {
    "gn:admin1_code":"75",
    "gn:admin2_code":"19",
    "gn:admin3_code":"192",
    "gn:admin4_code":"19145",
    "gn:asciiname":"Souny",
    "gn:country_code":"FR",
    "gn:dem":587,
    "gn:feature_class":"P",
    "gn:feature_code":"PPL",
    "gn:name":"Souny",
    "gn:population":0,
    "gn:timezone":"Europe/Paris",
    "iso:country":"FR",
    "wof:name":"Souny",
    "wof:placetype":"locality"
},
  "geometry": {"coordinates":[2.07939,45.39985],"type":"Point"}
}