{
  "type": "Feature",
  "properties": {
    "gn:admin1_code":"75",
    "gn:admin2_code":"19",
    "gn:admin3_code":"191",
    "gn:admin4_code":"19116",
    "gn:asciiname":"Vicary",
    "gn:country_code":"FR",
    "gn:dem":211,
    "gn:feature_class":"P",
    "gn:feature_code":"PPL",
    "gn:name":"Vicary",
    "gn:population":0,
    "gn:timezone":"Europe/Paris",
    "iso:country":"FR",
    "wof:name":"Vicary",
    "wof:placetype":"locality"
},
  "geometry": {"coordinates":[1.81126,44.94276],"type":"Point"}
}