{
  "type": "Feature",
  "properties": {
    "gn:admin1_code":"24",
    "gn:admin2_code":"45",
    "gn:admin3_code":"451",
    "gn:admin4_code":"45129",
    "gn:asciiname":"Les Guillaumes",
    "gn:country_code":"FR",
    "gn:dem":181,
    "gn:feature_class":"P",
    "gn:feature_code":"PPL",
    "gn:name":"Les Guillaumes",
    "gn:population":0,
    "gn:timezone":"Europe/Paris",
    "iso:country":"FR",
    "wof:name":"Les Guillaumes",
    "wof:placetype":"locality"
},
  "geometry": {"coordinates":[3.0951,47.99324],"type":"Point"}
}