{
  "type": "Feature",
  "properties": {
    "gn:admin1_code":"24",
    "gn:admin2_code":"36",
    "gn:admin3_code":"363",
    "gn:admin4_code":"36240.0",
    "gn:asciiname":"La Rigaudiere",
    "gn:country_code":"FR",
    "gn:dem":397,
    "gn:feature_class":"P",
    "gn:feature_code":"PPL",
    "gn:name":"La Rigaudi\u00e8re",
    "gn:population":0,
    "gn:timezone":"Europe/Paris",
    "iso:country":"FR",
    "wof:name":"La Rigaudiere",
    "wof:placetype":"locality"
},
  "geometry": {"coordinates":[2.10428,46.41849000000001],"type":"Point"}
}