{
  "type": "Feature",
  "properties": {
    "gn:admin1_code":"84",
    "gn:admin2_code":"43",
    "gn:admin3_code":"432",
    "gn:admin4_code":"43228",
    "gn:asciiname":"Cheyrac",
    "gn:country_code":"FR",
    "gn:dem":957,
    "gn:feature_class":"P",
    "gn:feature_code":"PPL",
    "gn:name":"Cheyrac",
    "gn:population":0,
    "gn:timezone":"Europe/Paris",
    "iso:country":"FR",
    "wof:name":"Cheyrac",
    "wof:placetype":"locality"
},
  "geometry": {"coordinates":[3.79843,45.33326],"type":"Point"}
}