{
  "type": "Feature",
  "properties": {
    "gn:admin1_code":"84",
    "gn:admin2_code":"01",
    "gn:admin3_code":"011",
    "gn:admin4_code":"01216",
    "gn:asciiname":"Trieux",
    "gn:country_code":"FR",
    "gn:dem":418,
    "gn:feature_class":"P",
    "gn:feature_code":"PPL",
    "gn:name":"Trieux",
    "gn:population":0,
    "gn:timezone":"Europe/Paris",
    "iso:country":"FR",
    "wof:name":"Trieux",
    "wof:placetype":"locality"
},
  "geometry": {"coordinates":[5.55742,45.73376],"type":"Point"}
}