{
  "type": "Feature",
  "properties": {
    "gn:admin1_code":"84",
    "gn:admin2_code":"01",
    "gn:admin3_code":"011",
    "gn:admin4_code":"01216",
    "gn:asciiname":"Trieux",
    "gn:country_code":"FR",
    "gn:dem":418,
    "gn:feature_class":"P",
    "gn:feature_code":"PPL",
    "gn:name":"Trieux",
    "gn:population":0,
    "gn:timezone":"Europe/Paris",
    "iso:country":"FR",
    "name:ceb_x_preferred":[
        "Trieux"
    ],
    "name:deu_x_preferred":[
        "Trieux"
    ],
    "name:eus_x_preferred":[
        "Trieux"
    ],
    "name:fra_x_preferred":[
        "Trieux"
    ],
    "name:hun_x_preferred":[
        "Trieux"
    ],
    "name:ita_x_preferred":[
        "Trieux"
    ],
    "name:kaz_x_preferred":[
        "\u0422\u0440\u0438\u0435"
    ],
    "name:lat_x_preferred":[
        "Trieux"
    ],
    "name:ltz_x_preferred":[
        "Trieux"
    ],
    "name:msa_x_preferred":[
        "Trieux"
    ],
    "name:nld_x_preferred":[
        "Trieux"
    ],
    "name:oci_x_preferred":[
        "Trieux"
    ],
    "name:pms_x_preferred":[
        "Trieux"
    ],
    "name:pol_x_preferred":[
        "Trieux"
    ],
    "name:por_x_preferred":[
        "Trieux"
    ],
    "name:rus_x_preferred":[
        "\u0422\u0440\u0438\u0451"
    ],
    "name:slk_x_preferred":[
        "Trieux"
    ],
    "name:spa_x_preferred":[
        "Trieux"
    ],
    "name:swe_x_preferred":[
        "Trieux"
    ],
    "name:ukr_x_preferred":[
        "\u0422\u0440\u0456\u0454"
    ],
    "name:uzb_x_preferred":[
        "Trieux"
    ],
    "name:vie_x_preferred":[
        "Trieux"
    ],
    "name:vol_x_preferred":[
        "Trieux"
    ],
    "name:war_x_preferred":[
        "Trieux"
    ],
    "name:zho_x_preferred":[
        "\u7279\u91cc\u5384"
    ],
    "wof:name":"Trieux",
    "wof:placetype":"locality"
},
  "geometry": {"coordinates":[5.55742,45.73376],"type":"Point"}
}