{
  "type": "Feature",
  "properties": {
    "gn:admin1_code":"44",
    "gn:admin2_code":"55",
    "gn:admin3_code":"552",
    "gn:admin4_code":"55472",
    "gn:asciiname":"Vaux-la-Grande",
    "gn:country_code":"FR",
    "gn:dem":310,
    "gn:feature_class":"P",
    "gn:feature_code":"PPL",
    "gn:name":"Vaux-la-Grande",
    "gn:population":0,
    "gn:timezone":"Europe/Paris",
    "iso:country":"FR",
    "name:und_x_variant":[
        "Vaux",
        "Vaux-la-Grande"
    ],
    "wof:name":"Vaux-la-Grande",
    "wof:placetype":"locality"
},
  "geometry": {"coordinates":[5.44687,48.68389000000001],"type":"Point"}
}