{
  "type": "Feature",
  "properties": {
    "gn:admin1_code":"32",
    "gn:admin2_code":"59",
    "gn:admin3_code":"593",
    "gn:admin4_code":"59551",
    "gn:asciiname":"Vieux Conde",
    "gn:country_code":"FR",
    "gn:dem":27,
    "gn:feature_class":"P",
    "gn:feature_code":"PPL",
    "gn:name":"Vieux Cond\u00e9",
    "gn:population":0,
    "gn:timezone":"Europe/Paris",
    "iso:country":"FR",
    "name:und_x_variant":[
        "Vieux Cond\u00e9"
    ],
    "wof:name":"Vieux Conde",
    "wof:placetype":"locality"
},
  "geometry": {"coordinates":[3.32793,50.48084],"type":"Point"}
}