{
  "type": "Feature",
  "properties": {
    "gn:admin1_code":"75",
    "gn:admin2_code":"23",
    "gn:admin3_code":"232",
    "gn:admin4_code":"23064",
    "gn:asciiname":"Le Theix",
    "gn:country_code":"FR",
    "gn:dem":405,
    "gn:feature_class":"P",
    "gn:feature_code":"PPL",
    "gn:name":"Le Theix",
    "gn:population":0,
    "gn:timezone":"Europe/Paris",
    "iso:country":"FR",
    "wof:name":"Le Theix",
    "wof:placetype":"locality"
},
  "geometry": {"coordinates":[2.15641,46.30911],"type":"Point"}
}