{
  "type": "Feature",
  "properties": {
    "gn:admin1_code":"53",
    "gn:admin2_code":"22",
    "gn:admin3_code":"223",
    "gn:admin4_code":"22090",
    "gn:asciiname":"Kerimel",
    "gn:country_code":"FR",
    "gn:dem":91,
    "gn:feature_class":"P",
    "gn:feature_code":"PPL",
    "gn:name":"Kerimel",
    "gn:population":0,
    "gn:timezone":"Europe/Paris",
    "iso:country":"FR",
    "wof:name":"Kerimel",
    "wof:placetype":"locality"
},
  "geometry": {"coordinates":[-3.39735,48.76568],"type":"Point"}
}