{
  "type": "Feature",
  "properties": {
    "gn:admin1_code":"32",
    "gn:admin2_code":"02",
    "gn:admin3_code":"022",
    "gn:admin4_code":"02738",
    "gn:asciiname":"Fargniers",
    "gn:country_code":"FR",
    "gn:dem":55,
    "gn:feature_class":"P",
    "gn:feature_code":"PPL",
    "gn:name":"Fargniers",
    "gn:population":0,
    "gn:timezone":"Europe/Paris",
    "iso:country":"FR",
    "name:fra_x_preferred":[
        "Fargniers"
    ],
    "name:sqi_x_preferred":[
        "Fargniers"
    ],
    "wof:name":"Fargniers",
    "wof:placetype":"locality"
},
  "geometry": {"coordinates":[3.31476,49.65761],"type":"Point"}
}