{
  "type": "Feature",
  "properties": {
    "gn:admin1_code":"84",
    "gn:admin2_code":"63",
    "gn:admin3_code":"633",
    "gn:admin4_code":"63357",
    "gn:asciiname":"Haut Rouherent",
    "gn:country_code":"FR",
    "gn:dem":808,
    "gn:feature_class":"P",
    "gn:feature_code":"PPL",
    "gn:name":"Haut Rouherent",
    "gn:population":0,
    "gn:timezone":"Europe/Paris",
    "iso:country":"FR",
    "wof:name":"Haut Rouherent",
    "wof:placetype":"locality"
},
  "geometry": {"coordinates":[3.11909,45.46746],"type":"Point"}
}