{
  "type": "Feature",
  "properties": {
    "gn:admin1_code":"28",
    "gn:admin2_code":"50",
    "gn:admin3_code":"501",
    "gn:admin4_code":"50532.0",
    "gn:asciiname":"Saint-Pair-sur-Mer",
    "gn:country_code":"FR",
    "gn:dem":22,
    "gn:feature_class":"P",
    "gn:feature_code":"PPL",
    "gn:name":"Saint-Pair-sur-Mer",
    "gn:population":3741,
    "gn:timezone":"Europe/Paris",
    "iso:country":"FR",
    "name:kaz_x_preferred":[
        "\u0421\u0435\u043d-\u041f\u0435\u0440-\u0441\u044e\u0440-\u041c\u0435\u0440"
    ],
    "name:ukr_x_preferred":[
        "\u0421\u0435\u043d-\u041f\u0435\u0440-\u0441\u044e\u0440-\u041c\u0435\u0440"
    ],
    "name:und_x_variant":[
        "Saint-Pair",
        "Saint-Pair-sur-Mer"
    ],
    "name:urd_x_preferred":[
        "\u0633\u06cc\u0646\u0679-\u067e\u06cc\u0631-\u0633\u0631-\u0645\u0631"
    ],
    "name:zho_x_preferred":[
        "\u6ee8\u6d77\u5723\u4f69"
    ],
    "wof:name":"Saint-Pair-sur-Mer",
    "wof:placetype":"locality",
    "wof:population":3741
},
  "geometry": {"coordinates":[-1.56761,48.81455],"type":"Point"}
}