{
  "type": "Feature",
  "properties": {
    "gn:admin1_code":"44",
    "gn:admin2_code":"52",
    "gn:admin3_code":"522",
    "gn:admin4_code":"52332",
    "gn:asciiname":"Ravennefontaines",
    "gn:country_code":"FR",
    "gn:dem":365,
    "gn:feature_class":"P",
    "gn:feature_code":"PPL",
    "gn:name":"Ravennefontaines",
    "gn:population":0,
    "gn:timezone":"Europe/Paris",
    "iso:country":"FR",
    "wof:name":"Ravennefontaines",
    "wof:placetype":"locality"
},
  "geometry": {"coordinates":[5.60527,48.03544],"type":"Point"}
}