{
  "type": "Feature",
  "properties": {
    "gn:admin1_code":"28",
    "gn:admin2_code":"76",
    "gn:admin3_code":"763",
    "gn:admin4_code":"76705",
    "gn:asciiname":"Bedanne",
    "gn:country_code":"FR",
    "gn:dem":8,
    "gn:feature_class":"P",
    "gn:feature_code":"PPL",
    "gn:name":"B\u00e9danne",
    "gn:population":0,
    "gn:timezone":"Europe/Paris",
    "iso:country":"FR",
    "wof:name":"Bedanne",
    "wof:placetype":"locality"
},
  "geometry": {"coordinates":[1.0699,49.32664000000001],"type":"Point"}
}