{
  "type": "Feature",
  "properties": {
    "gn:admin1_code":"75",
    "gn:admin2_code":"24",
    "gn:admin3_code":"241",
    "gn:admin4_code":"24005",
    "gn:asciiname":"Fourques",
    "gn:country_code":"FR",
    "gn:dem":77,
    "gn:feature_class":"P",
    "gn:feature_code":"PPL",
    "gn:name":"Fourques",
    "gn:population":0,
    "gn:timezone":"Europe/Paris",
    "iso:country":"FR",
    "wof:name":"Fourques",
    "wof:placetype":"locality"
},
  "geometry": {"coordinates":[0.88333,44.86667],"type":"Point"}
}