{
  "type": "Feature",
  "properties": {
    "gn:admin1_code":"76",
    "gn:admin2_code":"12",
    "gn:admin3_code":"122",
    "gn:admin4_code":"12096",
    "gn:asciiname":"Biounac",
    "gn:country_code":"FR",
    "gn:dem":634,
    "gn:feature_class":"P",
    "gn:feature_code":"PPL",
    "gn:name":"Biounac",
    "gn:population":0,
    "gn:timezone":"Europe/Paris",
    "iso:country":"FR",
    "wof:name":"Biounac",
    "wof:placetype":"locality"
},
  "geometry": {"coordinates":[2.76449,44.48806],"type":"Point"}
}