{
  "type": "Feature",
  "properties": {
    "gn:admin1_code":"84",
    "gn:admin2_code":"38",
    "gn:admin3_code":"381",
    "gn:admin4_code":"38413",
    "gn:asciiname":"Chalmeane",
    "gn:country_code":"FR",
    "gn:dem":990,
    "gn:feature_class":"P",
    "gn:feature_code":"PPL",
    "gn:name":"Chalm\u00e9ane",
    "gn:population":0,
    "gn:timezone":"Europe/Paris",
    "iso:country":"FR",
    "wof:name":"Chalmeane",
    "wof:placetype":"locality"
},
  "geometry": {"coordinates":[5.85901,44.8816],"type":"Point"}
}