{
  "type": "Feature",
  "properties": {
    "gn:admin1_code":"28",
    "gn:admin2_code":"76",
    "gn:admin3_code":"763",
    "gn:admin4_code":"76099.0",
    "gn:asciiname":"La Pierre",
    "gn:country_code":"FR",
    "gn:dem":118,
    "gn:feature_class":"P",
    "gn:feature_code":"PPL",
    "gn:name":"La Pierre",
    "gn:population":0,
    "gn:timezone":"Europe/Paris",
    "iso:country":"FR",
    "name:cat_x_preferred":[
        "La Pierre"
    ],
    "name:ceb_x_preferred":[
        "La Pierre"
    ],
    "name:deu_x_preferred":[
        "La Pierre"
    ],
    "name:eus_x_preferred":[
        "La Pierre"
    ],
    "name:fas_x_preferred":[
        "\u0644\u0627 \u067e\u06cc\u06cc\u0631"
    ],
    "name:fra_x_preferred":[
        "La Pierre"
    ],
    "name:hun_x_preferred":[
        "La Pierre"
    ],
    "name:ita_x_preferred":[
        "La Pierre"
    ],
    "name:lat_x_preferred":[
        "La Pierre"
    ],
    "name:lmo_x_preferred":[
        "La Pierre"
    ],
    "name:msa_x_preferred":[
        "La Pierre"
    ],
    "name:nld_x_preferred":[
        "La Pierre"
    ],
    "name:oci_x_preferred":[
        "La Pierre"
    ],
    "name:pol_x_preferred":[
        "La Pierre"
    ],
    "name:por_x_preferred":[
        "La Pierre"
    ],
    "name:ron_x_preferred":[
        "La Pierre"
    ],
    "name:rus_x_preferred":[
        "\u041b\u0430-\u041f\u044c\u0435\u0440"
    ],
    "name:slk_x_preferred":[
        "La Pierre"
    ],
    "name:spa_x_preferred":[
        "La Pierre"
    ],
    "name:swe_x_preferred":[
        "La Pierre"
    ],
    "name:ukr_x_preferred":[
        "\u041b\u0430-\u041f'\u0454\u0440\u0440"
    ],
    "name:urd_x_preferred":[
        "\u0644\u0627 \u067e\u06cc\u0631\u06cc"
    ],
    "name:uzb_x_preferred":[
        "La Pierre"
    ],
    "name:vie_x_preferred":[
        "La Pierre"
    ],
    "name:vol_x_preferred":[
        "La Pierre"
    ],
    "name:war_x_preferred":[
        "La Pierre"
    ],
    "name:zho_x_preferred":[
        "\u62c9\u76ae\u8036\u5c14"
    ],
    "wof:name":"La Pierre",
    "wof:placetype":"locality"
},
  "geometry": {"coordinates":[0.84672,49.54811],"type":"Point"}
}