{
  "type": "Feature",
  "properties": {
    "gn:admin1_code":"76",
    "gn:admin2_code":"32",
    "gn:admin3_code":"321",
    "gn:admin4_code":"32038",
    "gn:asciiname":"Beaupuy",
    "gn:country_code":"FR",
    "gn:dem":189,
    "gn:feature_class":"P",
    "gn:feature_code":"PPL",
    "gn:name":"Beaupuy",
    "gn:population":0,
    "gn:timezone":"Europe/Paris",
    "iso:country":"FR",
    "wof:name":"Beaupuy",
    "wof:placetype":"locality"
},
  "geometry": {"coordinates":[1.00654,43.64421],"type":"Point"}
}