{
  "type": "Feature",
  "properties": {
    "frgov:code_epci":"200023620",
    "frgov:insee_arr":"1",
    "frgov:insee_com":"32038",
    "frgov:insee_dep":"32",
    "frgov:insee_reg":"76",
    "frgov:nom_com":"Beaupuy",
    "frgov:nom_com_m":"BEAUPUY",
    "frgov:nom_dep":"GERS",
    "frgov:nom_reg":"OCCITANIE",
    "frgov:statut":"Commune simple",
    "gn:admin1_code":"76",
    "gn:admin2_code":"32",
    "gn:admin3_code":"321",
    "gn:admin4_code":"32038",
    "gn:asciiname":"Beaupuy",
    "gn:country_code":"FR",
    "gn:dem":189,
    "gn:feature_class":"P",
    "gn:feature_code":"PPL",
    "gn:name":"Beaupuy",
    "gn:population":0,
    "gn:timezone":"Europe/Paris",
    "iso:country":"FR",
    "name:arg_x_preferred":[
        "B\u00e8thpoi"
    ],
    "name:cat_x_preferred":[
        "B\u00e8thpoi"
    ],
    "name:ceb_x_preferred":[
        "Beaupuy"
    ],
    "name:deu_x_preferred":[
        "Beaupuy"
    ],
    "name:eus_x_preferred":[
        "B\u00e8thpoi"
    ],
    "name:fra_x_preferred":[
        "Beaupuy"
    ],
    "name:ita_x_preferred":[
        "Beaupuy"
    ],
    "name:nds_x_preferred":[
        "Beaupuy"
    ],
    "name:nld_x_preferred":[
        "Beaupuy"
    ],
    "name:oci_x_preferred":[
        "B\u00e8lpu\u00e8g"
    ],
    "name:oci_x_variant":[
        "B\u00e8lpu\u00e8g"
    ],
    "name:pms_x_preferred":[
        "Beaupuy"
    ],
    "name:pol_x_preferred":[
        "Beaupuy"
    ],
    "name:por_x_preferred":[
        "Beaupuy"
    ],
    "name:rus_x_preferred":[
        "\u0411\u043e\u043f\u044e\u0438"
    ],
    "name:slk_x_preferred":[
        "Beaupuy"
    ],
    "name:spa_x_preferred":[
        "Beaupuy"
    ],
    "name:srp_x_preferred":[
        "\u0411\u043e\u043f\u0438\u0458"
    ],
    "name:swe_x_preferred":[
        "Beaupuy"
    ],
    "name:ukr_x_preferred":[
        "\u0411\u043e\u043f\u044e\u0457"
    ],
    "name:zho_x_preferred":[
        "\u535a\u76ae\u4f0a"
    ],
    "qs:a0":"France",
    "qs:a1":"GERS",
    "qs:a1_lc":"32",
    "qs:a1r":"MIDI-PYRENEES",
    "qs:a1r_lc":"73",
    "qs:a2_lc":"10",
    "qs:a2r_lc":"1",
    "qs:adm0":"France",
    "qs:adm0_a3":"FRA",
    "qs:la":"BEAUPUY",
    "qs:la_lc":"32038",
    "qs:level":"localadmin",
    "qs:type":"Commune simple",
    "wof:coterminous":[
        404420105
    ],
    "wof:name":"Beaupuy",
    "wof:placetype":"locality",
    "wof:placetype_local":"Commune simple"
},
  "geometry": {"coordinates":[1.00654,43.64421],"type":"Point"}
}