{
  "type": "Feature",
  "properties": {
    "gn:admin1_code":"76",
    "gn:admin2_code":"32",
    "gn:admin3_code":"321",
    "gn:admin4_code":"32038",
    "gn:asciiname":"Beaupuy",
    "gn:country_code":"FR",
    "gn:dem":189,
    "gn:feature_class":"P",
    "gn:feature_code":"PPL",
    "gn:name":"Beaupuy",
    "gn:population":0,
    "gn:timezone":"Europe/Paris",
    "iso:country":"FR",
    "name:ceb_x_preferred":[
        "Beaupuy"
    ],
    "name:deu_x_preferred":[
        "Beaupuy"
    ],
    "name:fra_x_preferred":[
        "Beaupuy"
    ],
    "name:ita_x_preferred":[
        "Beaupuy"
    ],
    "name:nds_x_preferred":[
        "Beaupuy"
    ],
    "name:nld_x_preferred":[
        "Beaupuy"
    ],
    "name:oci_x_preferred":[
        "B\u00e8lpu\u00e8g"
    ],
    "name:pms_x_preferred":[
        "Beaupuy"
    ],
    "name:pol_x_preferred":[
        "Beaupuy"
    ],
    "name:por_x_preferred":[
        "Beaupuy"
    ],
    "name:rus_x_preferred":[
        "\u0411\u043e\u043f\u044e\u0438"
    ],
    "name:slk_x_preferred":[
        "Beaupuy"
    ],
    "name:spa_x_preferred":[
        "Beaupuy"
    ],
    "name:srp_x_preferred":[
        "\u0411\u043e\u043f\u0438\u0458"
    ],
    "name:swe_x_preferred":[
        "Beaupuy"
    ],
    "name:ukr_x_preferred":[
        "\u0411\u043e\u043f\u044e\u0457"
    ],
    "wof:name":"Beaupuy",
    "wof:placetype":"locality"
},
  "geometry": {"coordinates":[1.00654,43.64421],"type":"Point"}
}