{
  "type": "Feature",
  "properties": {
    "gn:admin1_code":"44",
    "gn:admin2_code":"54",
    "gn:admin3_code":"542",
    "gn:admin4_code":"54170",
    "gn:asciiname":"Domptail-en-l'Air",
    "gn:cc2":"FR",
    "gn:country_code":"FR",
    "gn:dem":323,
    "gn:feature_class":"P",
    "gn:feature_code":"PPL",
    "gn:name":"Domptail-en-l'Air",
    "gn:population":0,
    "gn:timezone":"Europe/Paris",
    "iso:country":"FR",
    "name:und_x_variant":[
        "Domptail"
    ],
    "wof:name":"Domptail-en-l'Air",
    "wof:placetype":"locality"
},
  "geometry": {"coordinates":[6.33333,48.51667],"type":"Point"}
}