{
  "type": "Feature",
  "properties": {
    "gn:admin1_code":"44",
    "gn:admin2_code":"54",
    "gn:admin3_code":"542",
    "gn:admin4_code":"54170",
    "gn:asciiname":"Domptail-en-l'Air",
    "gn:cc2":"FR",
    "gn:country_code":"FR",
    "gn:dem":323,
    "gn:feature_class":"P",
    "gn:feature_code":"PPL",
    "gn:name":"Domptail-en-l'Air",
    "gn:population":0,
    "gn:timezone":"Europe/Paris",
    "iso:country":"FR",
    "name:cat_x_preferred":[
        "Domptail-en-l'Air"
    ],
    "name:ceb_x_preferred":[
        "Domptail-en-l'Air"
    ],
    "name:deu_x_preferred":[
        "Domptail-en-l\u2019Air"
    ],
    "name:eus_x_preferred":[
        "Domptail-en-l'Air"
    ],
    "name:fin_x_preferred":[
        "Domptail-en-l\u2019Air"
    ],
    "name:fra_x_preferred":[
        "Domptail-en-l'Air"
    ],
    "name:hun_x_preferred":[
        "Domptail-en-l\u2019Air"
    ],
    "name:ita_x_preferred":[
        "Domptail-en-l'Air"
    ],
    "name:kaz_x_preferred":[
        "\u0414\u043e\u043c\u0442\u0430\u0439-\u0430\u043d-\u043b'\u0415\u0440"
    ],
    "name:lat_x_preferred":[
        "Domptail-en-l'Air"
    ],
    "name:ltz_x_preferred":[
        "Domptail-en-l'Air"
    ],
    "name:mlg_x_preferred":[
        "Domptail-en-l'Air"
    ],
    "name:msa_x_preferred":[
        "Domptail-en-l'Air"
    ],
    "name:nap_x_preferred":[
        "Domptail-en-l'Air"
    ],
    "name:nld_x_preferred":[
        "Domptail-en-l'Air"
    ],
    "name:nor_x_preferred":[
        "Domptail-en-l'Air"
    ],
    "name:oci_x_preferred":[
        "Domptail-en-l'Air"
    ],
    "name:pms_x_preferred":[
        "Domptail-en-l'Air"
    ],
    "name:pol_x_preferred":[
        "Domptail-en-l\u2019Air"
    ],
    "name:por_x_preferred":[
        "Domptail-en-l'Air"
    ],
    "name:rus_x_preferred":[
        "\u0414\u043e\u043d\u0442\u0430\u0439-\u0430\u043d-\u043b\u2019\u042d\u0440"
    ],
    "name:slk_x_preferred":[
        "Domptail-en-l\u2019Air"
    ],
    "name:spa_x_preferred":[
        "Domptail-en-l'Air"
    ],
    "name:swe_x_preferred":[
        "Domptail-en-l'Air"
    ],
    "name:ukr_x_preferred":[
        "\u0414\u043e\u043c\u0442\u0430\u0439-\u0430\u043d-\u043b'\u0415\u0440"
    ],
    "name:und_x_variant":[
        "Domptail"
    ],
    "name:uzb_x_preferred":[
        "Domptail-en-l'Air"
    ],
    "name:vie_x_preferred":[
        "Domptail-en-l'Air"
    ],
    "name:vol_x_preferred":[
        "Domptail-en-l'Air"
    ],
    "name:war_x_preferred":[
        "Domptail-en-l'Air"
    ],
    "name:zho_x_preferred":[
        "\u83b1\u5730\u533a\u4e1c\u666e\u6cf0"
    ],
    "wof:name":"Domptail-en-l'Air",
    "wof:placetype":"locality"
},
  "geometry": {"coordinates":[6.33333,48.51667],"type":"Point"}
}