{
  "type": "Feature",
  "properties": {
    "iso:country":"FR",
    "wof:name":"La Cubucelle",
    "wof:placetype":"neighbourhood"
},
  "geometry": {"coordinates":[5.36139708286265,43.33347233196269],"type":"Point"}
}