{
  "type": "Feature",
  "properties": {
    "frgov:code_epci":"200072312",
    "frgov:insee_arr":"1",
    "frgov:insee_com":"27331",
    "frgov:insee_dep":"27",
    "frgov:insee_reg":"28",
    "frgov:nom_com":"Heub\u00e9court-Haricourt",
    "frgov:nom_com_m":"HEUBECOURT-HARICOURT",
    "frgov:nom_dep":"EURE",
    "frgov:nom_reg":"NORMANDIE",
    "frgov:statut":"Commune simple",
    "gn:admin1_code":"28",
    "gn:admin2_code":"27",
    "gn:admin3_code":"271",
    "gn:admin4_code":"27331",
    "gn:asciiname":"Heubecourt-Haricourt",
    "gn:country_code":"FR",
    "gn:dem":131,
    "gn:feature_class":"P",
    "gn:feature_code":"PPL",
    "gn:name":"Heub\u00e9court-Haricourt",
    "gn:population":0,
    "gn:timezone":"Europe/Paris",
    "iso:country":"FR",
    "name:fra_x_preferred":[
        "Heub\u00e9court-Haricourt"
    ],
    "qs:a0":"France",
    "qs:a1":"EURE",
    "qs:a1_lc":"27",
    "qs:a1r":"HAUTE-NORMANDIE",
    "qs:a1r_lc":"23",
    "qs:a2_lc":"14",
    "qs:a2r_lc":"1",
    "qs:adm0":"France",
    "qs:adm0_a3":"FRA",
    "qs:la":"HEUBECOURT-HARICOURT",
    "qs:la_lc":"27331",
    "qs:level":"localadmin",
    "qs:type":"Commune simple",
    "wof:coterminous":[
        404378945
    ],
    "wof:name":"Heubecourt-Haricourt",
    "wof:placetype":"locality",
    "wof:placetype_local":"Commune simple"
},
  "geometry": {"coordinates":[1.56667,49.13333],"type":"Point"}
}