{
  "type": "Feature",
  "properties": {
    "gn:admin1_code":"28",
    "gn:admin2_code":"27",
    "gn:admin3_code":"271",
    "gn:admin4_code":"27331",
    "gn:asciiname":"Heubecourt-Haricourt",
    "gn:country_code":"FR",
    "gn:dem":131,
    "gn:feature_class":"P",
    "gn:feature_code":"PPL",
    "gn:name":"Heub\u00e9court-Haricourt",
    "gn:population":0,
    "gn:timezone":"Europe/Paris",
    "iso:country":"FR",
    "wof:name":"Heubecourt-Haricourt",
    "wof:placetype":"locality"
},
  "geometry": {"coordinates":[1.56667,49.13333],"type":"Point"}
}