{
  "type": "Feature",
  "properties": {
    "gn:admin1_code":"75",
    "gn:admin2_code":"24",
    "gn:admin3_code":"241",
    "gn:admin4_code":"24167",
    "gn:asciiname":"Rouquette",
    "gn:country_code":"FR",
    "gn:dem":97,
    "gn:feature_class":"P",
    "gn:feature_code":"PPL",
    "gn:name":"Rouquette",
    "gn:population":0,
    "gn:timezone":"Europe/Paris",
    "iso:country":"FR",
    "wof:name":"Rouquette",
    "wof:placetype":"locality"
},
  "geometry": {"coordinates":[0.39716,44.6786],"type":"Point"}
}