{
  "type": "Feature",
  "properties": {
    "gn:admin1_code":"84",
    "gn:admin2_code":"43",
    "gn:admin3_code":"431",
    "gn:admin4_code":"43013",
    "gn:asciiname":"Vissac",
    "gn:country_code":"FR",
    "gn:dem":844,
    "gn:feature_class":"P",
    "gn:feature_code":"PPLL",
    "gn:name":"Vissac",
    "gn:population":0,
    "gn:timezone":"Europe/Paris",
    "iso:country":"FR",
    "wof:name":"Vissac",
    "wof:placetype":"locality"
},
  "geometry": {"coordinates":[3.59952,45.10433],"type":"Point"}
}