{
  "type": "Feature",
  "properties": {
    "gn:admin1_code":"24",
    "gn:admin2_code":"28",
    "gn:admin3_code":"282",
    "gn:admin4_code":"28106",
    "gn:asciiname":"Molitard",
    "gn:country_code":"FR",
    "gn:dem":114,
    "gn:feature_class":"P",
    "gn:feature_code":"PPL",
    "gn:name":"Molitard",
    "gn:population":0,
    "gn:timezone":"Europe/Paris",
    "iso:country":"FR",
    "wof:name":"Molitard",
    "wof:placetype":"locality"
},
  "geometry": {"coordinates":[1.42635,48.1112],"type":"Point"}
}