{
  "type": "Feature",
  "properties": {
    "gn:admin1_code":"52",
    "gn:admin2_code":"53",
    "gn:admin3_code":"531",
    "gn:admin4_code":"53184",
    "gn:asciiname":"Preaux",
    "gn:country_code":"FR",
    "gn:dem":77,
    "gn:feature_class":"P",
    "gn:feature_code":"PPL",
    "gn:name":"Pr\u00e9aux",
    "gn:population":167,
    "gn:timezone":"Europe/Paris",
    "iso:country":"FR",
    "name:und_x_variant":[
        "Pr\u00e9aux"
    ],
    "wof:name":"Preaux",
    "wof:placetype":"locality",
    "wof:population":167
},
  "geometry": {"coordinates":[-0.47056,47.93463],"type":"Point"}
}