{
  "type": "Feature",
  "properties": {
    "frgov:code_epci":"245300223",
    "frgov:insee_arr":"1",
    "frgov:insee_com":"53184",
    "frgov:insee_dep":"53",
    "frgov:insee_reg":"52",
    "frgov:nom_com":"Pr\u00e9aux",
    "frgov:nom_com_m":"PREAUX",
    "frgov:nom_dep":"MAYENNE",
    "frgov:nom_reg":"PAYS DE LA LOIRE",
    "frgov:statut":"Commune simple",
    "gn:admin1_code":"52",
    "gn:admin2_code":"53",
    "gn:admin3_code":"531",
    "gn:admin4_code":"53184",
    "gn:asciiname":"Preaux",
    "gn:country_code":"FR",
    "gn:dem":77,
    "gn:feature_class":"P",
    "gn:feature_code":"PPL",
    "gn:name":"Pr\u00e9aux",
    "gn:population":167,
    "gn:timezone":"Europe/Paris",
    "iso:country":"FR",
    "name:fra_x_preferred":[
        "Pr\u00e9aux"
    ],
    "name:und_x_variant":[
        "Pr\u00e9aux"
    ],
    "qs:a0":"France",
    "qs:a1":"MAYENNE",
    "qs:a1_lc":"53",
    "qs:a1r":"PAYS DE LA LOIRE",
    "qs:a1r_lc":"52",
    "qs:a2_lc":"13",
    "qs:a2r_lc":"1",
    "qs:adm0":"France",
    "qs:adm0_a3":"FRA",
    "qs:la":"PREAUX",
    "qs:la_lc":"53184",
    "qs:level":"localadmin",
    "qs:type":"Commune simple",
    "wof:coterminous":[
        404412927
    ],
    "wof:name":"Preaux",
    "wof:placetype":"locality",
    "wof:placetype_local":"Commune simple",
    "wof:population":167
},
  "geometry": {"coordinates":[-0.47056,47.93463],"type":"Point"}
}