{
  "type": "Feature",
  "properties": {
    "gn:gn_country":"FR",
    "gn:gn_fcode":"PPL",
    "gn:gn_pop":24,
    "gn:population":24,
    "iso:country":"FR",
    "name:baq_x_preferred":[
        "Florentia"
    ],
    "name:cat_x_preferred":[
        "Florentia"
    ],
    "name:chi_x_preferred":[
        "\u5f17\u6d1b\u6717\u8482\u963f"
    ],
    "name:dut_x_preferred":[
        "Florentia"
    ],
    "name:eng_x_preferred":[
        "Florentia"
    ],
    "name:fre_x_preferred":[
        "Florentia"
    ],
    "name:ger_x_preferred":[
        "Florentia"
    ],
    "name:hun_x_preferred":[
        "Florentia"
    ],
    "name:ita_x_preferred":[
        "Florentia"
    ],
    "name:may_x_preferred":[
        "Florentia"
    ],
    "name:nan_x_preferred":[
        "Florentia"
    ],
    "name:oci_x_preferred":[
        "Florentia"
    ],
    "name:pms_x_preferred":[
        "Florentia"
    ],
    "name:pol_x_preferred":[
        "Florentia"
    ],
    "name:por_x_preferred":[
        "Florentia"
    ],
    "name:slo_x_preferred":[
        "Florentia"
    ],
    "name:spa_x_preferred":[
        "Florentia"
    ],
    "name:swe_x_preferred":[
        "Florentia"
    ],
    "name:ukr_x_preferred":[
        "\u0424\u043b\u043e\u0440\u0430\u043d\u0442\u0456\u044f"
    ],
    "name:uzb_x_preferred":[
        "Florentia"
    ],
    "name:vie_x_preferred":[
        "Florentia"
    ],
    "name:vol_x_preferred":[
        "Florentia"
    ],
    "name:war_x_preferred":[
        "Florentia"
    ],
    "qs_pg:aaroncc":"FR",
    "qs_pg:gn_country":"FR",
    "qs_pg:gn_fcode":"PPL",
    "qs_pg:gn_pop":24,
    "qs_pg:name":"Florentia",
    "qs_pg:name_adm0":"France",
    "qs_pg:name_adm1":"Franche-Comt\u00e9",
    "qs_pg:photos_9r":0,
    "qs_pg:photos_sr":0,
    "qs_pg:pop_sr":1,
    "qs_pg:qs_pg_placetype":"locality",
    "qs_pg:qs_pg_placetype_gp":"Town",
    "qs_pg:woe_adm0":23424819,
    "woe:adm0_id":23424819,
    "woe:name_adm0":"France",
    "woe:name_adm1":"Franche-Comt\u00e9",
    "woe:placetype":"Town",
    "wof:name":"Florentia",
    "wof:placetype":"neighbourhood",
    "wof:population":24
},
  "geometry": {"coordinates":[5.42527,46.39513],"type":"Point"}
}