{
  "type": "Feature",
  "properties": {
    "iso:country":"FR",
    "name:ces_x_preferred":[
        "Quartier des Batignolles"
    ],
    "name:deu_x_preferred":[
        "Quartier des Batignolles"
    ],
    "name:eng_x_preferred":[
        "Batignolles"
    ],
    "name:eus_x_preferred":[
        "Batignolles"
    ],
    "name:fra_x_preferred":[
        "Quartier des Batignolles"
    ],
    "name:fra_x_variant":[
        "Batignolles"
    ],
    "name:ita_x_preferred":[
        "Batignolles"
    ],
    "name:jpn_x_preferred":[
        "\u30d0\u30c6\u30a3\u30cb\u30e7\u30fc\u30eb"
    ],
    "name:jpn_x_variant":[
        "\u30d0\u30c6\u30a3\u30cb\u30e7\u30fc\u30eb\u5730\u533a"
    ],
    "name:ltz_x_preferred":[
        "Batignolles"
    ],
    "name:nld_x_preferred":[
        "Batignolles"
    ],
    "name:slk_x_preferred":[
        "Quartier des Batignolles"
    ],
    "name:zho_x_preferred":[
        "\u5df4\u8482\u8afe\u723e"
    ],
    "wd:wordcount":324,
    "wof:name":"Batignolles",
    "wof:placetype":"neighbourhood"
},
  "geometry": {"coordinates":[2.313853,48.887878],"type":"Point"}
}