{
  "type": "Feature",
  "properties": {
    "gn:gn_country":"FR",
    "iso:country":"FR",
    "name:deu_x_preferred":[
        "Mont Noir"
    ],
    "name:fra_x_preferred":[
        "Mont Noir"
    ],
    "name:nld_x_preferred":[
        "Zwarteberg"
    ],
    "name:vls_x_preferred":[
        "Zwortnberg"
    ],
    "qs_pg:aaroncc":"FR",
    "qs_pg:gn_country":"FR",
    "qs_pg:name":"Mont Noir",
    "qs_pg:name_adm0":"France",
    "qs_pg:name_adm1":"Nord-Pas-de-Calais",
    "qs_pg:photos":58,
    "qs_pg:photos_1k":12,
    "qs_pg:photos_9k":1,
    "qs_pg:photos_9r":2,
    "qs_pg:photos_all":58,
    "qs_pg:photos_sr":2,
    "qs_pg:pop_sr":0,
    "qs_pg:qs_pg_placetype":"locality",
    "qs_pg:qs_pg_placetype_gp":"Town",
    "qs_pg:woe_adm0":23424819,
    "woe:adm0_id":23424819,
    "woe:name_adm0":"France",
    "woe:name_adm1":"Nord-Pas-de-Calais",
    "woe:placetype":"Town",
    "wof:name":"Mont Noir",
    "wof:placetype":"neighbourhood"
},
  "geometry": {"coordinates":[2.732377,50.779932],"type":"Point"}
}