{
  "type": "Feature",
  "properties": {
    "gn:admin1_code":"76",
    "gn:admin2_code":"12",
    "gn:admin3_code":"122",
    "gn:admin4_code":"12241",
    "gn:asciiname":"Inieres",
    "gn:country_code":"FR",
    "gn:dem":629,
    "gn:feature_class":"P",
    "gn:feature_code":"PPL",
    "gn:name":"Ini\u00e8res",
    "gn:population":0,
    "gn:timezone":"Europe/Paris",
    "iso:country":"FR",
    "wof:name":"Inieres",
    "wof:placetype":"locality"
},
  "geometry": {"coordinates":[2.6556,44.30678],"type":"Point"}
}