{
  "type": "Feature",
  "properties": {
    "gn:admin1_code":"32",
    "gn:admin2_code":"62",
    "gn:admin3_code":"627",
    "gn:admin4_code":"62637",
    "gn:asciiname":"Oignies",
    "gn:country_code":"FR",
    "gn:dem":29,
    "gn:feature_class":"P",
    "gn:feature_code":"PPL",
    "gn:name":"Oignies",
    "gn:population":10609,
    "gn:timezone":"Europe/Paris",
    "iso:country":"FR",
    "wof:name":"Oignies",
    "wof:placetype":"locality",
    "wof:population":10609
},
  "geometry": {"coordinates":[2.99376,50.46331],"type":"Point"}
}