{
  "type": "Feature",
  "properties": {
    "gn:admin1_code":"84",
    "gn:admin2_code":"01",
    "gn:admin3_code":"011",
    "gn:admin4_code":"01058",
    "gn:asciiname":"La Bruyere",
    "gn:country_code":"FR",
    "gn:dem":229,
    "gn:feature_class":"P",
    "gn:feature_code":"PPL",
    "gn:name":"La Bruy\u00e8re",
    "gn:population":0,
    "gn:timezone":"Europe/Paris",
    "iso:country":"FR",
    "wof:name":"La Bruyere",
    "wof:placetype":"locality"
},
  "geometry": {"coordinates":[5.62476,45.64127],"type":"Point"}
}