{
  "type": "Feature",
  "properties": {
    "iso:country":"FR",
    "name:eng_x_preferred":[
        "La Mare"
    ],
    "name:fra_x_preferred":[
        "La Mare"
    ],
    "wof:name":"La Mare",
    "wof:placetype":"neighbourhood"
},
  "geometry": {"coordinates":[2.45305613155212,48.91552501409974],"type":"Point"}
}