{
  "type": "Feature",
  "properties": {
    "gn:admin1_code":"84",
    "gn:admin2_code":"07",
    "gn:admin3_code":"073",
    "gn:admin4_code":"07192",
    "gn:asciiname":"La Valette",
    "gn:country_code":"FR",
    "gn:dem":956,
    "gn:feature_class":"P",
    "gn:feature_code":"PPL",
    "gn:name":"La Valette",
    "gn:population":0,
    "gn:timezone":"Europe/Paris",
    "iso:country":"FR",
    "name:cat_x_preferred":[
        "La Valette"
    ],
    "name:ceb_x_preferred":[
        "La Valette"
    ],
    "name:deu_x_preferred":[
        "La Valette"
    ],
    "name:eus_x_preferred":[
        "La Valette"
    ],
    "name:fra_x_preferred":[
        "La Valette"
    ],
    "name:hun_x_preferred":[
        "La Valette"
    ],
    "name:hye_x_preferred":[
        "\u053c\u0561-\u054e\u0561\u056c\u0565\u057f\u057f"
    ],
    "name:ind_x_preferred":[
        "La Valette"
    ],
    "name:ita_x_preferred":[
        "La Valette"
    ],
    "name:lat_x_preferred":[
        "La Valette"
    ],
    "name:ltz_x_preferred":[
        "La Valette"
    ],
    "name:mlg_x_preferred":[
        "La Valette"
    ],
    "name:msa_x_preferred":[
        "La Valette"
    ],
    "name:nld_x_preferred":[
        "La Valette"
    ],
    "name:oci_x_preferred":[
        "La Valette"
    ],
    "name:pms_x_preferred":[
        "La Valette"
    ],
    "name:pol_x_preferred":[
        "La Valette"
    ],
    "name:por_x_preferred":[
        "La Valette"
    ],
    "name:ron_x_preferred":[
        "La Valette"
    ],
    "name:rus_x_preferred":[
        "\u041b\u0430-\u0412\u0430\u043b\u0435\u0442\u0442"
    ],
    "name:slk_x_preferred":[
        "La Valette"
    ],
    "name:spa_x_preferred":[
        "La Valette"
    ],
    "name:swe_x_preferred":[
        "La Valette"
    ],
    "name:ukr_x_preferred":[
        "\u041b\u0430-\u0412\u0430\u043b\u0435\u0442\u0442"
    ],
    "name:urd_x_preferred":[
        "\u0644\u0627 \u0648\u06cc\u0644\u06cc\u062a"
    ],
    "name:uzb_x_preferred":[
        "La Valette"
    ],
    "name:vie_x_preferred":[
        "La Valette"
    ],
    "name:vol_x_preferred":[
        "La Valette"
    ],
    "name:war_x_preferred":[
        "La Valette"
    ],
    "name:zho_x_preferred":[
        "\u62c9\u74e6\u83b1\u7279"
    ],
    "wof:name":"La Valette",
    "wof:placetype":"locality"
},
  "geometry": {"coordinates":[4.41502,45.07551],"type":"Point"}
}