{
  "type": "Feature",
  "properties": {
    "gn:admin1_code":"84",
    "gn:admin2_code":"07",
    "gn:admin3_code":"073",
    "gn:admin4_code":"07192",
    "gn:asciiname":"La Valette",
    "gn:country_code":"FR",
    "gn:dem":956,
    "gn:feature_class":"P",
    "gn:feature_code":"PPL",
    "gn:name":"La Valette",
    "gn:population":0,
    "gn:timezone":"Europe/Paris",
    "iso:country":"FR",
    "wof:name":"La Valette",
    "wof:placetype":"locality"
},
  "geometry": {"coordinates":[4.41502,45.07551],"type":"Point"}
}