{
  "type": "Feature",
  "properties": {
    "iso:country":"FR",
    "name:fra_x_preferred":[
        "Pr\u00e9fecture"
    ],
    "wof:name":"Prefecture",
    "wof:placetype":"neighbourhood"
},
  "geometry": {"coordinates":[4.84284674648912,45.7591206585719],"type":"Point"}
}