{
  "type": "Feature",
  "properties": {
    "iso:country":"FR",
    "name:afr_x_preferred":[
        "Prefektuur"
    ],
    "name:ara_x_preferred":[
        "\u0639\u0645\u0627\u0644\u0629"
    ],
    "name:arg_x_preferred":[
        "Prefectura"
    ],
    "name:ast_x_preferred":[
        "Prefectura"
    ],
    "name:aze_x_preferred":[
        "Ostan"
    ],
    "name:bre_x_preferred":[
        "Prefeti"
    ],
    "name:cat_x_preferred":[
        "Prefectura"
    ],
    "name:dan_x_preferred":[
        "Pr\u00e6fektur"
    ],
    "name:deu_x_preferred":[
        "Pr\u00e4fektur"
    ],
    "name:ell_x_preferred":[
        "\u039d\u03bf\u03bc\u03cc\u03c2"
    ],
    "name:epo_x_preferred":[
        "Prefektlando"
    ],
    "name:eus_x_preferred":[
        "Prefektura"
    ],
    "name:fin_x_preferred":[
        "Prefektuuri"
    ],
    "name:fra_x_preferred":[
        "Pr\u00e9fecture"
    ],
    "name:glg_x_preferred":[
        "Prefectura"
    ],
    "name:haw_x_preferred":[
        "P\u016bahah\u014dua"
    ],
    "name:ind_x_preferred":[
        "Prefektur"
    ],
    "name:kat_x_preferred":[
        "\u10de\u10e0\u10d4\u10e4\u10d4\u10e5\u10e2\u10e3\u10e0\u10d0"
    ],
    "name:kaz_x_preferred":[
        "\u041f\u0440\u0435\u0444\u0435\u043a\u0442\u0443\u0440\u0430"
    ],
    "name:kor_x_preferred":[
        "\ud604"
    ],
    "name:lat_x_preferred":[
        "Praefectura"
    ],
    "name:ltz_x_preferred":[
        "Prefecture"
    ],
    "name:msa_x_preferred":[
        "Prefektur"
    ],
    "name:oci_x_preferred":[
        "Prefectura"
    ],
    "name:pol_x_preferred":[
        "Prefektura"
    ],
    "name:por_x_preferred":[
        "Prefeitura"
    ],
    "name:rus_x_preferred":[
        "\u041f\u0440\u0435\u0444\u0435\u043a\u0442\u0443\u0440\u0430"
    ],
    "name:slv_x_preferred":[
        "Prefektura"
    ],
    "name:spa_x_preferred":[
        "Prefectura"
    ],
    "name:srp_x_preferred":[
        "\u041f\u0440\u0435\u0444\u0435\u043a\u0442\u0443\u0440\u0430"
    ],
    "name:sun_x_preferred":[
        "Pr\u00e9f\u00e9ktur"
    ],
    "name:tat_x_preferred":[
        "\u041f\u0440\u0435\u0444\u0435\u043a\u0442\u0443\u0440\u0430"
    ],
    "name:tur_x_preferred":[
        "Prefekt\u00f6rl\u00fck"
    ],
    "name:ukr_x_preferred":[
        "\u041f\u0440\u0435\u0444\u0435\u043a\u0442\u0443\u0440\u0430"
    ],
    "name:urd_x_preferred":[
        "\u067e\u0631\u06cc\u0641\u06cc\u06a9\u0686\u0648\u0631"
    ],
    "name:vie_x_preferred":[
        "Huy\u1ec7n"
    ],
    "name:xmf_x_preferred":[
        "\u10de\u10e0\u10d4\u10e4\u10d4\u10e5\u10e2\u10e3\u10e0\u10d0"
    ],
    "wof:name":"Prefecture",
    "wof:placetype":"neighbourhood"
},
  "geometry": {"coordinates":[4.84284674648912,45.7591206585719],"type":"Point"}
}