{
  "type": "Feature",
  "properties": {
    "gn:admin1_code":"24",
    "gn:admin2_code":"18",
    "gn:admin3_code":"182",
    "gn:admin4_code":"18065",
    "gn:asciiname":"Dampierre-en-Lignieres",
    "gn:country_code":"FR",
    "gn:dem":150,
    "gn:feature_class":"P",
    "gn:feature_code":"PPL",
    "gn:name":"Dampierre-en-Ligni\u00e8res",
    "gn:population":0,
    "gn:timezone":"Europe/Paris",
    "iso:country":"FR",
    "name:und_x_variant":[
        "Dampierre",
        "Dampierre-en-Ligni\u00e8res"
    ],
    "wof:name":"Dampierre-en-Lignieres",
    "wof:placetype":"locality"
},
  "geometry": {"coordinates":[2.11667,46.85],"type":"Point"}
}