{
  "type": "Feature",
  "properties": {
    "gn:admin1_code":"75",
    "gn:admin2_code":"33",
    "gn:admin3_code":"331",
    "gn:admin4_code":"33100",
    "gn:asciiname":"Coudeau",
    "gn:country_code":"FR",
    "gn:dem":63,
    "gn:feature_class":"P",
    "gn:feature_code":"PPL",
    "gn:name":"Coudeau",
    "gn:population":0,
    "gn:timezone":"Europe/Paris",
    "iso:country":"FR",
    "wof:name":"Coudeau",
    "wof:placetype":"locality"
},
  "geometry": {"coordinates":[-0.61553,45.12111],"type":"Point"}
}