{
  "type": "Feature",
  "properties": {
    "gn:admin1_code":"27",
    "gn:admin2_code":"58",
    "gn:admin3_code":"583",
    "gn:admin4_code":"58223",
    "gn:asciiname":"Conseuille",
    "gn:country_code":"FR",
    "gn:dem":253,
    "gn:feature_class":"P",
    "gn:feature_code":"PPL",
    "gn:name":"Conseuille",
    "gn:population":0,
    "gn:timezone":"Europe/Paris",
    "iso:country":"FR",
    "wof:name":"Conseuille",
    "wof:placetype":"locality"
},
  "geometry": {"coordinates":[3.50908,47.01765],"type":"Point"}
}