{
  "type": "Feature",
  "properties": {
    "gn:country":"FR",
    "gn:fcode":"PPL",
    "gn:population":5698,
    "iso:country":"FR",
    "name:kaz_x_preferred":[
        "\u0421\u0435\u043d\u0442-\u0410\u0440\u043d\u0443-\u0430\u043d-\u0418\u0432\u0435\u043b\u0438\u043d"
    ],
    "name:rus_x_preferred":[
        "\u0421\u0435\u043d\u0442-\u0410\u0440\u043d\u0443-\u0430\u043d-\u0418\u0432\u0435\u043b\u0438\u043d"
    ],
    "name:ukr_x_preferred":[
        "\u0421\u0435\u043d\u0442-\u0410\u0440\u043d\u0443-\u0430\u043d-\u0406\u0432\u043b\u0456\u043d"
    ],
    "name:und_x_variant":[
        "Saint-Arnoult"
    ],
    "name:urd_x_preferred":[
        "\u0633\u06cc\u0646\u0679-\u0627\u0631\u0646\u0648\u0644\u0679-\u0627\u06cc\u0646 -\u06cc\u0648\u0644\u0646\u0633"
    ],
    "qs_pg:aaroncc":"FR",
    "qs_pg:gn_country":"FR",
    "qs_pg:gn_fcode":"PPL",
    "qs_pg:gn_pop":5698,
    "qs_pg:name":"Saint-quentin-en-yvelines",
    "qs_pg:name_adm0":"France",
    "qs_pg:name_adm1":"\u00cele-de-France",
    "qs_pg:photos":91,
    "qs_pg:photos_1k":18,
    "qs_pg:photos_9k":1,
    "qs_pg:photos_9r":3,
    "qs_pg:photos_all":91,
    "qs_pg:photos_sr":3,
    "qs_pg:pop_sr":5,
    "qs_pg:qs_pg_placetype":"locality",
    "qs_pg:qs_pg_placetype_gp":"Town",
    "qs_pg:woe_adm0":23424819,
    "woe:adm0_id":23424819,
    "woe:name_adm0":"France",
    "woe:name_adm1":"\u00cele-de-France",
    "woe:placetype":"Town",
    "wof:name":"Saint-quentin-en-yvelines",
    "wof:placetype":"neighbourhood",
    "wof:population":5698
},
  "geometry": {"coordinates":[1.9395,48.57111],"type":"Point"}
}