{
  "type": "Feature",
  "properties": {
    "iso:country":"FR",
    "name:eng_x_preferred":[
        "Hector Berlioz"
    ],
    "name:fra_x_preferred":[
        "Hector Berlioz"
    ],
    "name:fra_x_variant":[
        "Cit\u00e9 Hector Berlioz"
    ],
    "wof:name":"Hector Berlioz",
    "wof:placetype":"neighbourhood"
},
  "geometry": {"coordinates":[2.45374753838084,48.90571335691308],"type":"Point"}
}