{
  "type": "Feature",
  "properties": {
    "gn:admin1_code":"84",
    "gn:admin2_code":"73",
    "gn:admin3_code":"733",
    "gn:admin4_code":"73235",
    "gn:asciiname":"Les Sapeys",
    "gn:country_code":"FR",
    "gn:dem":1529,
    "gn:feature_class":"P",
    "gn:feature_code":"PPL",
    "gn:name":"Les Sapeys",
    "gn:population":0,
    "gn:timezone":"Europe/Paris",
    "iso:country":"FR",
    "wof:name":"Les Sapeys",
    "wof:placetype":"locality"
},
  "geometry": {"coordinates":[6.31147,45.39935],"type":"Point"}
}