{
  "type": "Feature",
  "properties": {
    "gn:admin1_code":"75",
    "gn:admin2_code":"33",
    "gn:admin3_code":"334",
    "gn:admin4_code":"33220",
    "gn:asciiname":"Poujeaux",
    "gn:country_code":"FR",
    "gn:dem":19,
    "gn:feature_class":"P",
    "gn:feature_code":"PPL",
    "gn:name":"Poujeaux",
    "gn:population":0,
    "gn:timezone":"Europe/Paris",
    "iso:country":"FR",
    "wof:name":"Poujeaux",
    "wof:placetype":"locality"
},
  "geometry": {"coordinates":[-0.73333,45.08333],"type":"Point"}
}