{
  "type": "Feature",
  "properties": {
    "gn:admin1_code":"28",
    "gn:admin2_code":"76",
    "gn:admin3_code":"761",
    "gn:admin4_code":"76209.0",
    "gn:asciiname":"Dampierre-en-Bray",
    "gn:country_code":"FR",
    "gn:dem":125,
    "gn:feature_class":"P",
    "gn:feature_code":"PPL",
    "gn:name":"Dampierre-en-Bray",
    "gn:population":0,
    "gn:timezone":"Europe/Paris",
    "iso:country":"FR",
    "name:cat_x_preferred":[
        "Dampierre-en-Bray"
    ],
    "name:ceb_x_preferred":[
        "Dampierre-en-Bray"
    ],
    "name:deu_x_preferred":[
        "Dampierre-en-Bray"
    ],
    "name:eus_x_preferred":[
        "Dampierre-en-Bray"
    ],
    "name:fra_x_preferred":[
        "Dampierre-en-Bray"
    ],
    "name:hun_x_preferred":[
        "Dampierre-en-Bray"
    ],
    "name:ita_x_preferred":[
        "Dampierre-en-Bray"
    ],
    "name:kaz_x_preferred":[
        "\u0414\u0430\u043c\u043f\u044c\u0435\u0440\u0440-\u0430\u043d-\u0411\u0440\u0435"
    ],
    "name:lat_x_preferred":[
        "Dampierre-en-Bray"
    ],
    "name:mlg_x_preferred":[
        "Dampierre-en-Bray"
    ],
    "name:msa_x_preferred":[
        "Dampierre-en-Bray"
    ],
    "name:nld_x_preferred":[
        "Dampierre-en-Bray"
    ],
    "name:oci_x_preferred":[
        "Dampierre-en-Bray"
    ],
    "name:pms_x_preferred":[
        "Dampierre-en-Bray"
    ],
    "name:pol_x_preferred":[
        "Dampierre-en-Bray"
    ],
    "name:por_x_preferred":[
        "Dampierre-en-Bray"
    ],
    "name:ron_x_preferred":[
        "Dampierre-en-Bray"
    ],
    "name:slk_x_preferred":[
        "Dampierre-en-Bray"
    ],
    "name:spa_x_preferred":[
        "Dampierre-en-Bray"
    ],
    "name:srp_x_preferred":[
        "\u0414\u0430\u043c\u043f\u0458\u0435\u0440 \u0430\u043d \u0411\u0440\u0435"
    ],
    "name:swe_x_preferred":[
        "Dampierre-en-Bray"
    ],
    "name:ukr_x_preferred":[
        "\u0414\u0430\u043c\u043f\u0454\u0440\u0440-\u0430\u043d-\u0411\u0440\u0435"
    ],
    "name:ukr_x_variant":[
        "\u0414\u0430\u043c\u043f'\u0454\u0440\u0440-\u0430\u043d-\u0411\u0440\u0435"
    ],
    "name:vie_x_preferred":[
        "Dampierre-en-Bray"
    ],
    "name:vol_x_preferred":[
        "Dampierre-en-Bray"
    ],
    "name:war_x_preferred":[
        "Dampierre-en-Bray"
    ],
    "wof:name":"Dampierre-en-Bray",
    "wof:placetype":"locality"
},
  "geometry": {"coordinates":[1.66667,49.53333],"type":"Point"}
}