{
  "type": "Feature",
  "properties": {
    "gn:admin1_code":"28",
    "gn:admin2_code":"76",
    "gn:admin3_code":"761",
    "gn:admin4_code":"76209.0",
    "gn:asciiname":"Dampierre-en-Bray",
    "gn:country_code":"FR",
    "gn:dem":125,
    "gn:feature_class":"P",
    "gn:feature_code":"PPL",
    "gn:name":"Dampierre-en-Bray",
    "gn:population":0,
    "gn:timezone":"Europe/Paris",
    "iso:country":"FR",
    "name:kaz_x_preferred":[
        "\u0414\u0430\u043c\u043f\u044c\u0435\u0440\u0440-\u0430\u043d-\u0411\u0440\u0435"
    ],
    "name:srp_x_preferred":[
        "\u0414\u0430\u043c\u043f\u0458\u0435\u0440 \u0430\u043d \u0411\u0440\u0435"
    ],
    "name:ukr_x_preferred":[
        "\u0414\u0430\u043c\u043f\u0454\u0440\u0440-\u0430\u043d-\u0411\u0440\u0435"
    ],
    "wof:name":"Dampierre-en-Bray",
    "wof:placetype":"locality"
},
  "geometry": {"coordinates":[1.66667,49.53333],"type":"Point"}
}