{
  "type": "Feature",
  "properties": {
    "gn:admin1_code":"53",
    "gn:admin2_code":"56",
    "gn:admin3_code":"562",
    "gn:admin4_code":"56066",
    "gn:asciiname":"Saint-Nicolas",
    "gn:country_code":"FR",
    "gn:dem":170,
    "gn:feature_class":"P",
    "gn:feature_code":"PPL",
    "gn:name":"Saint-Nicolas",
    "gn:population":0,
    "gn:timezone":"Europe/Paris",
    "iso:country":"FR",
    "wof:name":"Saint-Nicolas",
    "wof:placetype":"locality"
},
  "geometry": {"coordinates":[-3.55,48.15],"type":"Point"}
}