{
  "type": "Feature",
  "properties": {
    "gn:admin1_code":"84",
    "gn:admin2_code":"38",
    "gn:admin3_code":"382",
    "gn:admin4_code":"38374",
    "gn:asciiname":"Arcisse",
    "gn:country_code":"FR",
    "gn:dem":266,
    "gn:feature_class":"P",
    "gn:feature_code":"PPL",
    "gn:name":"Arcisse",
    "gn:population":0,
    "gn:timezone":"Europe/Paris",
    "iso:country":"FR",
    "wof:name":"Arcisse",
    "wof:placetype":"locality"
},
  "geometry": {"coordinates":[5.38286,45.63906],"type":"Point"}
}