{
  "type": "Feature",
  "properties": {
    "gn:admin1_code":"84",
    "gn:admin2_code":"43",
    "gn:admin3_code":"432",
    "gn:admin4_code":"43138",
    "gn:asciiname":"Moissac",
    "gn:country_code":"FR",
    "gn:dem":1018,
    "gn:feature_class":"P",
    "gn:feature_code":"PPL",
    "gn:name":"Moissac",
    "gn:population":0,
    "gn:timezone":"Europe/Paris",
    "iso:country":"FR",
    "wof:name":"Moissac",
    "wof:placetype":"locality"
},
  "geometry": {"coordinates":[3.74985,45.22287],"type":"Point"}
}