{
  "type": "Feature",
  "properties": {
    "gn:admin1_code":"84",
    "gn:admin2_code":"43",
    "gn:admin3_code":"432",
    "gn:admin4_code":"43138",
    "gn:asciiname":"Moissac",
    "gn:country_code":"FR",
    "gn:dem":1018,
    "gn:feature_class":"P",
    "gn:feature_code":"PPL",
    "gn:name":"Moissac",
    "gn:population":0,
    "gn:timezone":"Europe/Paris",
    "iso:country":"FR",
    "name:cat_x_preferred":[
        "Moissac"
    ],
    "name:ceb_x_preferred":[
        "Moissac"
    ],
    "name:dan_x_preferred":[
        "Moissac"
    ],
    "name:deu_x_preferred":[
        "Moissac"
    ],
    "name:eus_x_preferred":[
        "Moissac"
    ],
    "name:fra_x_preferred":[
        "Moissac"
    ],
    "name:hun_x_preferred":[
        "Moissac"
    ],
    "name:ind_x_preferred":[
        "Moissac"
    ],
    "name:ita_x_preferred":[
        "Moissac"
    ],
    "name:jpn_x_preferred":[
        "\u30e2\u30ef\u30b5\u30c3\u30af"
    ],
    "name:lat_x_preferred":[
        "Musciacum"
    ],
    "name:mlg_x_preferred":[
        "Moissac"
    ],
    "name:msa_x_preferred":[
        "Moissac"
    ],
    "name:nld_x_preferred":[
        "Moissac"
    ],
    "name:nor_x_preferred":[
        "Moissac"
    ],
    "name:oci_x_preferred":[
        "Moissac"
    ],
    "name:pol_x_preferred":[
        "Moissac"
    ],
    "name:ron_x_preferred":[
        "Moissac"
    ],
    "name:rus_x_preferred":[
        "\u041c\u0443\u0430\u0441\u0441\u0430\u043a"
    ],
    "name:slk_x_preferred":[
        "Moissac"
    ],
    "name:spa_x_preferred":[
        "Moissac"
    ],
    "name:swe_x_preferred":[
        "Moissac"
    ],
    "name:ukr_x_preferred":[
        "\u041c\u0443\u0430\u0441\u0441\u0430\u043a"
    ],
    "name:vie_x_preferred":[
        "Moissac"
    ],
    "name:vol_x_preferred":[
        "Moissac"
    ],
    "name:war_x_preferred":[
        "Moissac"
    ],
    "name:zho_x_preferred":[
        "\u7a46\u74e6\u8428\u514b"
    ],
    "wof:name":"Moissac",
    "wof:placetype":"locality"
},
  "geometry": {"coordinates":[3.74985,45.22287],"type":"Point"}
}