{
  "type": "Feature",
  "properties": {
    "gn:admin1_code":"93",
    "gn:admin2_code":"04",
    "gn:admin3_code":"041",
    "gn:admin4_code":"04086",
    "gn:asciiname":"Bouzoulieres",
    "gn:country_code":"FR",
    "gn:dem":1532,
    "gn:feature_class":"P",
    "gn:feature_code":"PPL",
    "gn:name":"Bouzouli\u00e8res",
    "gn:population":0,
    "gn:timezone":"Europe/Paris",
    "iso:country":"FR",
    "wof:name":"Bouzoulieres",
    "wof:placetype":"locality"
},
  "geometry": {"coordinates":[6.67937,44.40711],"type":"Point"}
}