{
  "type": "Feature",
  "properties": {
    "gn:admin1_code":"27",
    "gn:admin2_code":"39",
    "gn:admin3_code":"393",
    "gn:admin4_code":"39216",
    "gn:asciiname":"Etival",
    "gn:country_code":"FR",
    "gn:dem":816,
    "gn:feature_class":"P",
    "gn:feature_code":"PPL",
    "gn:name":"\u00c9tival",
    "gn:population":301,
    "gn:timezone":"Europe/Paris",
    "iso:country":"FR",
    "name:und_x_variant":[
        "\u00c9tival"
    ],
    "wof:name":"Etival",
    "wof:placetype":"locality",
    "wof:population":301
},
  "geometry": {"coordinates":[5.79323,46.5079],"type":"Point"}
}