{
  "type": "Feature",
  "properties": {
    "frgov:code_epci":"243900412",
    "frgov:insee_arr":"3",
    "frgov:insee_com":"39216",
    "frgov:insee_dep":"39",
    "frgov:insee_reg":"27",
    "frgov:nom_com":"\u00c9tival",
    "frgov:nom_com_m":"ETIVAL",
    "frgov:nom_dep":"JURA",
    "frgov:nom_reg":"BOURGOGNE-FRANCHE-COMTE",
    "frgov:statut":"Commune simple",
    "gn:admin1_code":"27",
    "gn:admin2_code":"39",
    "gn:admin3_code":"393",
    "gn:admin4_code":"39216",
    "gn:asciiname":"Etival",
    "gn:country_code":"FR",
    "gn:dem":816,
    "gn:feature_class":"P",
    "gn:feature_code":"PPL",
    "gn:name":"\u00c9tival",
    "gn:population":301,
    "gn:timezone":"Europe/Paris",
    "iso:country":"FR",
    "name:fra_x_preferred":[
        "\u00c9tival"
    ],
    "name:und_x_variant":[
        "\u00c9tival"
    ],
    "qs:a0":"France",
    "qs:a1":"JURA",
    "qs:a1_lc":"39",
    "qs:a1r":"FRANCHE-COMTE",
    "qs:a1r_lc":"43",
    "qs:a2_lc":"16",
    "qs:a2r_lc":"3",
    "qs:adm0":"France",
    "qs:adm0_a3":"FRA",
    "qs:la":"ETIVAL",
    "qs:la_lc":"39216",
    "qs:level":"localadmin",
    "qs:type":"Commune simple",
    "wof:coterminous":[
        404376099
    ],
    "wof:name":"Etival",
    "wof:placetype":"locality",
    "wof:placetype_local":"Commune simple",
    "wof:population":301
},
  "geometry": {"coordinates":[5.79323,46.5079],"type":"Point"}
}