{
  "type": "Feature",
  "properties": {
    "gn:admin1_code":"53",
    "gn:admin2_code":"29",
    "gn:admin3_code":"292",
    "gn:admin4_code":"29016",
    "gn:asciiname":"Le Favot",
    "gn:country_code":"FR",
    "gn:dem":116,
    "gn:feature_class":"P",
    "gn:feature_code":"PPL",
    "gn:name":"Le Favot",
    "gn:population":0,
    "gn:timezone":"Europe/Paris",
    "iso:country":"FR",
    "name:und_x_variant":[
        "Favot",
        "Le Fayot",
        "Le Favot"
    ],
    "wof:name":"Le Favot",
    "wof:placetype":"locality"
},
  "geometry": {"coordinates":[-3.99992,48.32116],"type":"Point"}
}