{
  "type": "Feature",
  "properties": {
    "gn:admin1_code":"11",
    "gn:admin2_code":"77",
    "gn:admin3_code":"773",
    "gn:admin4_code":"77403",
    "gn:asciiname":"Lugrand",
    "gn:country_code":"FR",
    "gn:dem":155,
    "gn:feature_class":"P",
    "gn:feature_code":"PPL",
    "gn:name":"Lugrand",
    "gn:population":0,
    "gn:timezone":"Europe/Paris",
    "iso:country":"FR",
    "wof:name":"Lugrand",
    "wof:placetype":"locality"
},
  "geometry": {"coordinates":[3.33076,48.57764],"type":"Point"}
}