{
  "type": "Feature",
  "properties": {
    "gn:admin1_code":"76",
    "gn:admin2_code":"66",
    "gn:admin3_code":"663",
    "gn:admin4_code":"66020",
    "gn:asciiname":"Pyrenees 2000",
    "gn:country_code":"FR",
    "gn:dem":1779,
    "gn:feature_class":"P",
    "gn:feature_code":"PPL",
    "gn:name":"Pyrenees 2000",
    "gn:population":0,
    "gn:timezone":"Europe/Paris",
    "iso:country":"FR",
    "wof:name":"Pyrenees 2000",
    "wof:placetype":"locality"
},
  "geometry": {"coordinates":[2.06161,42.52092],"type":"Point"}
}