{
  "type": "Feature",
  "properties": {
    "gn:admin1_code":"93",
    "gn:admin2_code":"13",
    "gn:admin3_code":"134",
    "gn:admin4_code":"13056",
    "gn:asciiname":"Saint-Pierre",
    "gn:country_code":"FR",
    "gn:dem":53,
    "gn:feature_class":"P",
    "gn:feature_code":"PPL",
    "gn:name":"Saint-Pierre",
    "gn:population":0,
    "gn:timezone":"Europe/Paris",
    "iso:country":"FR",
    "wof:name":"Saint-Pierre",
    "wof:placetype":"locality"
},
  "geometry": {"coordinates":[5.05324,43.37009000000001],"type":"Point"}
}