{
  "type": "Feature",
  "properties": {
    "gn:admin1_code":"24",
    "gn:admin2_code":"18",
    "gn:admin3_code":"181",
    "gn:admin4_code":"18023.0",
    "gn:asciiname":"La Loge",
    "gn:country_code":"FR",
    "gn:dem":167,
    "gn:feature_class":"P",
    "gn:feature_code":"PPL",
    "gn:name":"La Loge",
    "gn:population":0,
    "gn:timezone":"Europe/Paris",
    "iso:country":"FR",
    "wof:name":"La Loge",
    "wof:placetype":"locality"
},
  "geometry": {"coordinates":[2.68324,47.06619],"type":"Point"}
}