{
  "type": "Feature",
  "properties": {
    "gn:admin1_code":"32",
    "gn:admin2_code":"60",
    "gn:admin3_code":"601",
    "gn:admin4_code":"60248",
    "gn:asciiname":"L'Argilier",
    "gn:country_code":"FR",
    "gn:dem":207,
    "gn:feature_class":"P",
    "gn:feature_code":"PPL",
    "gn:name":"L\u2019Argilier",
    "gn:population":0,
    "gn:timezone":"Europe/Paris",
    "iso:country":"FR",
    "wof:name":"L'Argilier",
    "wof:placetype":"locality"
},
  "geometry": {"coordinates":[1.81751,49.73213],"type":"Point"}
}