{
  "type": "Feature",
  "properties": {
    "gn:admin1_code":"75",
    "gn:admin2_code":"19",
    "gn:admin3_code":"193",
    "gn:admin4_code":"19238",
    "gn:asciiname":"Le Chalard",
    "gn:country_code":"FR",
    "gn:dem":710,
    "gn:feature_class":"P",
    "gn:feature_code":"PPL",
    "gn:name":"Le Chalard",
    "gn:population":0,
    "gn:timezone":"Europe/Paris",
    "iso:country":"FR",
    "wof:name":"Le Chalard",
    "wof:placetype":"locality"
},
  "geometry": {"coordinates":[2.25,45.68333],"type":"Point"}
}