{
  "type": "Feature",
  "properties": {
    "gn:admin1_code":"75",
    "gn:admin2_code":"19",
    "gn:admin3_code":"193",
    "gn:admin4_code":"19238",
    "gn:asciiname":"Le Chalard",
    "gn:country_code":"FR",
    "gn:dem":710,
    "gn:feature_class":"P",
    "gn:feature_code":"PPL",
    "gn:name":"Le Chalard",
    "gn:population":0,
    "gn:timezone":"Europe/Paris",
    "iso:country":"FR",
    "name:cat_x_preferred":[
        "Lo Chaslar"
    ],
    "name:ceb_x_preferred":[
        "Le Chalard"
    ],
    "name:deu_x_preferred":[
        "Le Chalard"
    ],
    "name:epo_x_preferred":[
        "Le Chalard"
    ],
    "name:eus_x_preferred":[
        "Le Chalard"
    ],
    "name:fra_x_preferred":[
        "Le Chalard"
    ],
    "name:hun_x_preferred":[
        "Le Chalard"
    ],
    "name:ind_x_preferred":[
        "Le Chalard"
    ],
    "name:ita_x_preferred":[
        "Le Chalard"
    ],
    "name:kaz_x_preferred":[
        "\u041b\u0435-\u0428\u0430\u043b\u0430\u0440"
    ],
    "name:lat_x_preferred":[
        "Le Chalard"
    ],
    "name:msa_x_preferred":[
        "Le Chalard"
    ],
    "name:nld_x_preferred":[
        "Le Chalard"
    ],
    "name:oci_x_preferred":[
        "Lu Chaslar"
    ],
    "name:pms_x_preferred":[
        "Le Chalard"
    ],
    "name:pol_x_preferred":[
        "Le Chalard"
    ],
    "name:por_x_preferred":[
        "Le Chalard"
    ],
    "name:ron_x_preferred":[
        "Le Chalard"
    ],
    "name:slk_x_preferred":[
        "Le Chalard"
    ],
    "name:spa_x_preferred":[
        "Le Chalard"
    ],
    "name:srp_x_preferred":[
        "\u0428\u0430\u043b\u0430\u0440"
    ],
    "name:swe_x_preferred":[
        "Le Chalard"
    ],
    "name:ukr_x_preferred":[
        "\u041b\u0435-\u0428\u0430\u043b\u0430\u0440"
    ],
    "name:uzb_x_preferred":[
        "Le Chalard"
    ],
    "name:vie_x_preferred":[
        "Le Chalard"
    ],
    "name:vol_x_preferred":[
        "Le Chalard"
    ],
    "name:war_x_preferred":[
        "Le Chalard"
    ],
    "name:zho_x_preferred":[
        "\u52d2\u6c99\u62c9\u5c14"
    ],
    "wof:name":"Le Chalard",
    "wof:placetype":"locality"
},
  "geometry": {"coordinates":[2.25,45.68333],"type":"Point"}
}