{
  "type": "Feature",
  "properties": {
    "gn:admin1_code":"84",
    "gn:admin2_code":"73",
    "gn:admin3_code":"731",
    "gn:admin4_code":"73244",
    "gn:asciiname":"Deux Nants",
    "gn:country_code":"FR",
    "gn:dem":1485,
    "gn:feature_class":"P",
    "gn:feature_code":"PPL",
    "gn:name":"Deux Nants",
    "gn:population":0,
    "gn:timezone":"Europe/Paris",
    "iso:country":"FR",
    "wof:name":"Deux Nants",
    "wof:placetype":"locality"
},
  "geometry": {"coordinates":[6.45801,45.4102],"type":"Point"}
}