{
  "type": "Feature",
  "properties": {
    "gn:admin1_code":"84",
    "gn:admin2_code":"73",
    "gn:admin3_code":"732",
    "gn:admin4_code":"73051",
    "gn:asciiname":"Caton",
    "gn:cc2":"FR",
    "gn:country_code":"FR",
    "gn:dem":338,
    "gn:feature_class":"P",
    "gn:feature_code":"PPL",
    "gn:name":"Caton",
    "gn:population":0,
    "gn:timezone":"Europe/Paris",
    "iso:country":"FR",
    "name:bel_x_preferred":[
        "\u041a\u0430\u0442\u043e\u043d"
    ],
    "name:bul_x_preferred":[
        "\u041a\u0430\u0442\u043e\u043d"
    ],
    "name:deu_x_preferred":[
        "Caton"
    ],
    "name:fra_x_preferred":[
        "Caton"
    ],
    "name:hye_x_preferred":[
        "\u053f\u0561\u057f\u0578\u0576"
    ],
    "name:ita_x_preferred":[
        "Caton"
    ],
    "name:pol_x_preferred":[
        "Caton"
    ],
    "name:rus_x_preferred":[
        "\u041a\u0430\u0442\u043e\u043d"
    ],
    "name:spa_x_preferred":[
        "Cat\u00f3n"
    ],
    "name:ukr_x_preferred":[
        "\u041a\u0430\u0442\u043e\u043d"
    ],
    "name:und_x_variant":[
        "Le Caton"
    ],
    "wof:name":"Caton",
    "wof:placetype":"locality"
},
  "geometry": {"coordinates":[5.85,45.65],"type":"Point"}
}