{
  "type": "Feature",
  "properties": {
    "gn:admin1_code":"24",
    "gn:admin2_code":"36",
    "gn:admin3_code":"363",
    "gn:admin4_code":"36061",
    "gn:asciiname":"Rimbert",
    "gn:country_code":"FR",
    "gn:dem":384,
    "gn:feature_class":"P",
    "gn:feature_code":"PPL",
    "gn:name":"Rimbert",
    "gn:population":0,
    "gn:timezone":"Europe/Paris",
    "iso:country":"FR",
    "name:bel_x_preferred":[
        "\u0420\u044b\u043c\u0431\u0435\u0440\u0442"
    ],
    "name:dan_x_preferred":[
        "Rimbert"
    ],
    "name:deu_x_preferred":[
        "Rimbert"
    ],
    "name:fra_x_preferred":[
        "Rimbert"
    ],
    "name:ita_x_preferred":[
        "Remberto"
    ],
    "name:jpn_x_preferred":[
        "\u30ea\u30f3\u30d9\u30eb\u30c8"
    ],
    "name:lat_x_preferred":[
        "Rimbertus"
    ],
    "name:lav_x_preferred":[
        "Rimberts"
    ],
    "name:nds_x_preferred":[
        "Rimbert"
    ],
    "name:nld_x_preferred":[
        "Rembertus"
    ],
    "name:nrm_x_preferred":[
        "Saint Rembert"
    ],
    "name:pol_x_preferred":[
        "Rimbert"
    ],
    "name:rus_x_preferred":[
        "\u0420\u0438\u043c\u0431\u0435\u0440\u0442"
    ],
    "name:spa_x_preferred":[
        "Remberto"
    ],
    "name:swe_x_preferred":[
        "Rimbert"
    ],
    "wof:name":"Rimbert",
    "wof:placetype":"locality"
},
  "geometry": {"coordinates":[1.88467,46.45753],"type":"Point"}
}