{
  "type": "Feature",
  "properties": {
    "gn:admin1_code":"24",
    "gn:admin2_code":"36",
    "gn:admin3_code":"363",
    "gn:admin4_code":"36061",
    "gn:asciiname":"Rimbert",
    "gn:country_code":"FR",
    "gn:dem":384,
    "gn:feature_class":"P",
    "gn:feature_code":"PPL",
    "gn:name":"Rimbert",
    "gn:population":0,
    "gn:timezone":"Europe/Paris",
    "iso:country":"FR",
    "wof:name":"Rimbert",
    "wof:placetype":"locality"
},
  "geometry": {"coordinates":[1.88467,46.45753],"type":"Point"}
}