{
  "type": "Feature",
  "properties": {
    "gn:admin1_code":"76",
    "gn:admin2_code":"66",
    "gn:admin3_code":"663",
    "gn:admin4_code":"66005",
    "gn:asciiname":"Villeneuve-des-Escaldes",
    "gn:cc2":"FR",
    "gn:country_code":"FR",
    "gn:dem":1305,
    "gn:feature_class":"P",
    "gn:feature_code":"PPL",
    "gn:name":"Villeneuve-des-Escaldes",
    "gn:population":0,
    "gn:timezone":"Europe/Paris",
    "iso:country":"FR",
    "name:cat_x_preferred":[
        "Vilanova de les Escaldes"
    ],
    "name:cat_x_variant":[
        "Vilanova"
    ],
    "name:fra_x_preferred":[
        "Villeneuve-des Escaldas"
    ],
    "wof:name":"Villeneuve-des-Escaldes",
    "wof:placetype":"locality"
},
  "geometry": {"coordinates":[1.9525,42.47748],"type":"Point"}
}