{
  "type": "Feature",
  "properties": {
    "frgov:code_epci":"200071512",
    "frgov:insee_arr":"1",
    "frgov:insee_com":"03058",
    "frgov:insee_dep":"03",
    "frgov:insee_reg":"84",
    "frgov:nom_com":"Chappes",
    "frgov:nom_com_m":"CHAPPES",
    "frgov:nom_dep":"ALLIER",
    "frgov:nom_reg":"AUVERGNE-RHONE-ALPES",
    "frgov:statut":"Commune simple",
    "gn:admin1_code":"84",
    "gn:admin2_code":"03",
    "gn:admin3_code":"031",
    "gn:admin4_code":"03058",
    "gn:asciiname":"Chappes",
    "gn:country_code":"FR",
    "gn:dem":367,
    "gn:feature_class":"P",
    "gn:feature_code":"PPL",
    "gn:name":"Chappes",
    "gn:population":0,
    "gn:timezone":"Europe/Paris",
    "iso:country":"FR",
    "name:cat_x_preferred":[
        "Chapas"
    ],
    "name:ceb_x_preferred":[
        "Chappes"
    ],
    "name:deu_x_preferred":[
        "Chappes"
    ],
    "name:epo_x_preferred":[
        "Chappes"
    ],
    "name:fra_x_preferred":[
        "Chappes"
    ],
    "name:hun_x_preferred":[
        "Chappes"
    ],
    "name:ita_x_preferred":[
        "Chappes"
    ],
    "name:kaz_x_preferred":[
        "\u0428\u0430\u043f\u043f"
    ],
    "name:nds_x_preferred":[
        "Chappes"
    ],
    "name:nld_x_preferred":[
        "Chappes"
    ],
    "name:oci_x_preferred":[
        "Chappes"
    ],
    "name:oci_x_variant":[
        "Chappes"
    ],
    "name:pms_x_preferred":[
        "Chappes"
    ],
    "name:pol_x_preferred":[
        "Chappes"
    ],
    "name:por_x_preferred":[
        "Chappes"
    ],
    "name:rus_x_preferred":[
        "\u0428\u0430\u043f"
    ],
    "name:slk_x_preferred":[
        "Chappes"
    ],
    "name:spa_x_preferred":[
        "Chappes"
    ],
    "name:srp_x_preferred":[
        "\u0428\u0430\u043f"
    ],
    "name:swe_x_preferred":[
        "Chappes"
    ],
    "name:ukr_x_preferred":[
        "\u0428\u0430\u043f\u043f"
    ],
    "name:zho_x_preferred":[
        "\u6c99\u4f69"
    ],
    "qs:a0":"France",
    "qs:a1":"ALLIER",
    "qs:a1_lc":"03",
    "qs:a1r":"AUVERGNE",
    "qs:a1r_lc":"83",
    "qs:a2_lc":"22",
    "qs:a2r_lc":"1",
    "qs:adm0":"France",
    "qs:adm0_a3":"FRA",
    "qs:la":"CHAPPES",
    "qs:la_lc":"03058",
    "qs:level":"localadmin",
    "qs:type":"Commune simple",
    "wof:coterminous":[
        404383349
    ],
    "wof:name":"Chappes",
    "wof:placetype":"locality",
    "wof:placetype_local":"Commune simple"
},
  "geometry": {"coordinates":[2.92658,46.38782],"type":"Point"}
}