{
  "type": "Feature",
  "properties": {
    "gn:admin1_code":"84",
    "gn:admin2_code":"03",
    "gn:admin3_code":"031",
    "gn:admin4_code":"03058",
    "gn:asciiname":"Chappes",
    "gn:country_code":"FR",
    "gn:dem":367,
    "gn:feature_class":"P",
    "gn:feature_code":"PPL",
    "gn:name":"Chappes",
    "gn:population":0,
    "gn:timezone":"Europe/Paris",
    "iso:country":"FR",
    "name:ceb_x_preferred":[
        "Chappes"
    ],
    "name:deu_x_preferred":[
        "Chappes"
    ],
    "name:epo_x_preferred":[
        "Chappes"
    ],
    "name:fra_x_preferred":[
        "Chappes"
    ],
    "name:hun_x_preferred":[
        "Chappes"
    ],
    "name:ita_x_preferred":[
        "Chappes"
    ],
    "name:nds_x_preferred":[
        "Chappes"
    ],
    "name:nld_x_preferred":[
        "Chappes"
    ],
    "name:oci_x_preferred":[
        "Chappes"
    ],
    "name:pms_x_preferred":[
        "Chappes"
    ],
    "name:pol_x_preferred":[
        "Chappes"
    ],
    "name:por_x_preferred":[
        "Chappes"
    ],
    "name:rus_x_preferred":[
        "\u0428\u0430\u043f"
    ],
    "name:slk_x_preferred":[
        "Chappes"
    ],
    "name:spa_x_preferred":[
        "Chappes"
    ],
    "name:srp_x_preferred":[
        "\u0428\u0430\u043f"
    ],
    "name:swe_x_preferred":[
        "Chappes"
    ],
    "wof:name":"Chappes",
    "wof:placetype":"locality"
},
  "geometry": {"coordinates":[2.92658,46.38782],"type":"Point"}
}