{
  "type": "Feature",
  "properties": {
    "gn:admin1_code":"28",
    "gn:admin2_code":"61",
    "gn:admin3_code":"613",
    "gn:admin4_code":"61032",
    "gn:asciiname":"Launay",
    "gn:country_code":"FR",
    "gn:dem":274,
    "gn:feature_class":"P",
    "gn:feature_code":"PPL",
    "gn:name":"Launay",
    "gn:population":0,
    "gn:timezone":"Europe/Paris",
    "iso:country":"FR",
    "wof:name":"Launay",
    "wof:placetype":"locality"
},
  "geometry": {"coordinates":[0.51667,48.75],"type":"Point"}
}