{
  "type": "Feature",
  "properties": {
    "gn:admin1_code":"28",
    "gn:admin2_code":"61",
    "gn:admin3_code":"613",
    "gn:admin4_code":"61032",
    "gn:asciiname":"Launay",
    "gn:country_code":"FR",
    "gn:dem":274,
    "gn:feature_class":"P",
    "gn:feature_code":"PPL",
    "gn:name":"Launay",
    "gn:population":0,
    "gn:timezone":"Europe/Paris",
    "iso:country":"FR",
    "name:bug_x_preferred":[
        "Launay"
    ],
    "name:cat_x_preferred":[
        "Launay"
    ],
    "name:ceb_x_preferred":[
        "Launay"
    ],
    "name:deu_x_preferred":[
        "Launay"
    ],
    "name:eus_x_preferred":[
        "Launay"
    ],
    "name:fra_x_preferred":[
        "Launay"
    ],
    "name:hun_x_preferred":[
        "Launay"
    ],
    "name:ita_x_preferred":[
        "Launay"
    ],
    "name:kaz_x_preferred":[
        "\u041b\u043e\u043d\u0435"
    ],
    "name:lat_x_preferred":[
        "Launay"
    ],
    "name:msa_x_preferred":[
        "Launay"
    ],
    "name:nld_x_preferred":[
        "Launay"
    ],
    "name:oci_x_preferred":[
        "Launay"
    ],
    "name:pms_x_preferred":[
        "Launay"
    ],
    "name:pol_x_preferred":[
        "Launay"
    ],
    "name:por_x_preferred":[
        "Launay"
    ],
    "name:slk_x_preferred":[
        "Launay"
    ],
    "name:spa_x_preferred":[
        "Launay"
    ],
    "name:swe_x_preferred":[
        "Launay"
    ],
    "name:ukr_x_preferred":[
        "\u041b\u043e\u043d\u0435"
    ],
    "name:vie_x_preferred":[
        "Launay"
    ],
    "name:vol_x_preferred":[
        "Launay"
    ],
    "name:war_x_preferred":[
        "Launay"
    ],
    "wof:name":"Launay",
    "wof:placetype":"locality"
},
  "geometry": {"coordinates":[0.51667,48.75],"type":"Point"}
}