{
  "type": "Feature",
  "properties": {
    "gn:admin1_code":"52",
    "gn:admin2_code":"44",
    "gn:admin3_code":"443",
    "gn:admin4_code":"44184",
    "gn:asciiname":"Verdun",
    "gn:country_code":"FR",
    "gn:dem":31,
    "gn:feature_class":"P",
    "gn:feature_code":"PPLL",
    "gn:name":"Verdun",
    "gn:population":0,
    "gn:timezone":"Europe/Paris",
    "iso:country":"FR",
    "wof:name":"Verdun",
    "wof:placetype":"locality"
},
  "geometry": {"coordinates":[-2.28692,47.25033],"type":"Point"}
}