{
  "type": "Feature",
  "properties": {
    "gn:admin1_code":"24",
    "gn:admin2_code":"45",
    "gn:admin3_code":"453",
    "gn:admin4_code":"45253.0",
    "gn:asciiname":"Le Boulay",
    "gn:country_code":"FR",
    "gn:dem":116,
    "gn:feature_class":"P",
    "gn:feature_code":"PPL",
    "gn:name":"Le Boulay",
    "gn:population":0,
    "gn:timezone":"Europe/Paris",
    "iso:country":"FR",
    "name:cat_x_preferred":[
        "Le Boulay"
    ],
    "name:ceb_x_preferred":[
        "Le Boulay"
    ],
    "name:deu_x_preferred":[
        "Le Boulay"
    ],
    "name:eus_x_preferred":[
        "Le Boulay"
    ],
    "name:fra_x_preferred":[
        "Le Boulay"
    ],
    "name:hun_x_preferred":[
        "Le Boulay"
    ],
    "name:ita_x_preferred":[
        "Le Boulay"
    ],
    "name:lat_x_preferred":[
        "Le Boulay"
    ],
    "name:mlg_x_preferred":[
        "Le Boulay"
    ],
    "name:msa_x_preferred":[
        "Le Boulay"
    ],
    "name:nld_x_preferred":[
        "Le Boulay"
    ],
    "name:oci_x_preferred":[
        "Le Boulay"
    ],
    "name:pms_x_preferred":[
        "Le Boulay"
    ],
    "name:pol_x_preferred":[
        "Le Boulay"
    ],
    "name:por_x_preferred":[
        "Le Boulay"
    ],
    "name:ron_x_preferred":[
        "Le Boulay"
    ],
    "name:slk_x_preferred":[
        "Le Boulay"
    ],
    "name:spa_x_preferred":[
        "Le Boulay"
    ],
    "name:srp_x_preferred":[
        "\u0411\u0443\u043b\u0435"
    ],
    "name:swe_x_preferred":[
        "Le Boulay"
    ],
    "name:ukr_x_preferred":[
        "\u041b\u0435-\u0411\u0443\u043b\u0435"
    ],
    "name:uzb_x_preferred":[
        "Le Boulay"
    ],
    "name:vie_x_preferred":[
        "Le Boulay"
    ],
    "name:vol_x_preferred":[
        "Le Boulay"
    ],
    "name:war_x_preferred":[
        "Le Boulay"
    ],
    "name:zho_x_preferred":[
        "\u52d2\u5e03\u83b1"
    ],
    "wof:name":"Le Boulay",
    "wof:placetype":"locality"
},
  "geometry": {"coordinates":[2.20299,48.15245],"type":"Point"}
}