{
  "type": "Feature",
  "properties": {
    "gn:admin1_code":"32",
    "gn:admin2_code":"60",
    "gn:admin3_code":"601",
    "gn:admin4_code":"60073.0",
    "gn:asciiname":"Montreuil",
    "gn:country_code":"FR",
    "gn:dem":129,
    "gn:feature_class":"P",
    "gn:feature_code":"PPL",
    "gn:name":"Montreuil",
    "gn:population":0,
    "gn:timezone":"Europe/Paris",
    "iso:country":"FR",
    "name:azb_x_preferred":[
        "\u0645\u0648\u0646\u062a\u0631\u0648\u06cc"
    ],
    "name:bre_x_preferred":[
        "Montreuil"
    ],
    "name:cat_x_preferred":[
        "Montreuil"
    ],
    "name:ceb_x_preferred":[
        "Montreuil"
    ],
    "name:ces_x_preferred":[
        "Montreuil"
    ],
    "name:dan_x_preferred":[
        "Montreuil"
    ],
    "name:deu_x_preferred":[
        "Montreuil"
    ],
    "name:epo_x_preferred":[
        "Montreuil"
    ],
    "name:fra_x_preferred":[
        "Montreuil"
    ],
    "name:ita_x_preferred":[
        "Montreuil"
    ],
    "name:jpn_x_preferred":[
        "\u30e2\u30f3\u30c8\u30eb\u30a4\u30e6"
    ],
    "name:kor_x_preferred":[
        "\ubabd\ud2b8\ub8b0\uc720"
    ],
    "name:nds_x_preferred":[
        "Montreuil"
    ],
    "name:nld_x_preferred":[
        "Montreuil"
    ],
    "name:nor_x_preferred":[
        "Montreuil"
    ],
    "name:pms_x_preferred":[
        "Montreuil"
    ],
    "name:pol_x_preferred":[
        "Montreuil"
    ],
    "name:por_x_preferred":[
        "Montreuil"
    ],
    "name:ron_x_preferred":[
        "Montreuil"
    ],
    "name:rus_x_preferred":[
        "\u041c\u043e\u043d\u0442\u0440\u0451\u0439"
    ],
    "name:sco_x_preferred":[
        "Montreuil"
    ],
    "name:slk_x_preferred":[
        "Montreuil"
    ],
    "name:slv_x_preferred":[
        "Montreuil"
    ],
    "name:spa_x_preferred":[
        "Montreuil"
    ],
    "name:swe_x_preferred":[
        "Montreuil"
    ],
    "name:ukr_x_preferred":[
        "\u041c\u043e\u043d\u0442\u0440\u0435\u0439"
    ],
    "wof:name":"Montreuil",
    "wof:placetype":"locality"
},
  "geometry": {"coordinates":[1.84796,49.46115],"type":"Point"}
}