{
  "type": "Feature",
  "properties": {
    "gn:admin1_code":"24",
    "gn:admin2_code":"37",
    "gn:admin3_code":"373",
    "gn:admin4_code":"37080",
    "gn:asciiname":"Prouray",
    "gn:country_code":"FR",
    "gn:dem":94,
    "gn:feature_class":"P",
    "gn:feature_code":"PPL",
    "gn:name":"Prouray",
    "gn:population":0,
    "gn:timezone":"Europe/Paris",
    "iso:country":"FR",
    "wof:name":"Prouray",
    "wof:placetype":"locality"
},
  "geometry": {"coordinates":[0.68797,47.02661],"type":"Point"}
}