{
  "type": "Feature",
  "properties": {
    "gn:admin1_code":"75",
    "gn:admin2_code":"24",
    "gn:admin3_code":"241",
    "gn:admin4_code":"24028",
    "gn:asciiname":"Merle",
    "gn:country_code":"FR",
    "gn:dem":173,
    "gn:feature_class":"P",
    "gn:feature_code":"PPL",
    "gn:name":"Merle",
    "gn:population":0,
    "gn:timezone":"Europe/Paris",
    "iso:country":"FR",
    "name:deu_x_preferred":[
        "Merle"
    ],
    "name:fra_x_preferred":[
        "Merle"
    ],
    "name:por_x_preferred":[
        "Merle"
    ],
    "name:spa_x_preferred":[
        "Merle"
    ],
    "wof:name":"Merle",
    "wof:placetype":"locality"
},
  "geometry": {"coordinates":[0.78333,44.75],"type":"Point"}
}