{
  "type": "Feature",
  "properties": {
    "gn:admin1_code":"84",
    "gn:admin2_code":"03",
    "gn:admin3_code":"031",
    "gn:admin4_code":"03296",
    "gn:asciiname":"Euvy",
    "gn:country_code":"FR",
    "gn:dem":235,
    "gn:feature_class":"P",
    "gn:feature_code":"PPL",
    "gn:name":"Euvy",
    "gn:population":0,
    "gn:timezone":"Europe/Paris",
    "iso:country":"FR",
    "name:cat_x_preferred":[
        "Euvy"
    ],
    "name:ceb_x_preferred":[
        "Euvy"
    ],
    "name:eus_x_preferred":[
        "Euvy"
    ],
    "name:fra_x_preferred":[
        "Euvy"
    ],
    "name:hun_x_preferred":[
        "Euvy"
    ],
    "name:ita_x_preferred":[
        "Euvy"
    ],
    "name:lat_x_preferred":[
        "Euvy"
    ],
    "name:mlg_x_preferred":[
        "Euvy"
    ],
    "name:msa_x_preferred":[
        "Euvy"
    ],
    "name:nld_x_preferred":[
        "Euvy"
    ],
    "name:oci_x_preferred":[
        "Euvy"
    ],
    "name:pol_x_preferred":[
        "Euvy"
    ],
    "name:ron_x_preferred":[
        "Euvy"
    ],
    "name:slk_x_preferred":[
        "Euvy"
    ],
    "name:spa_x_preferred":[
        "Euvy"
    ],
    "name:srp_x_preferred":[
        "\u0415\u0432\u0438"
    ],
    "name:swe_x_preferred":[
        "Euvy"
    ],
    "name:ukr_x_preferred":[
        "\u0415\u0432\u0456"
    ],
    "name:vie_x_preferred":[
        "Euvy"
    ],
    "name:vol_x_preferred":[
        "Euvy"
    ],
    "name:war_x_preferred":[
        "Euvy"
    ],
    "wof:name":"Euvy",
    "wof:placetype":"locality"
},
  "geometry": {"coordinates":[2.84186,46.7275],"type":"Point"}
}