{
  "type": "Feature",
  "properties": {
    "frgov:code_epci":"200066918",
    "frgov:insee_arr":"1",
    "frgov:insee_com":"30072",
    "frgov:insee_dep":"30",
    "frgov:insee_reg":"76",
    "frgov:nom_com":"Castelnau-Valence",
    "frgov:nom_com_m":"CASTELNAU-VALENCE",
    "frgov:nom_dep":"GARD",
    "frgov:nom_reg":"OCCITANIE",
    "frgov:statut":"Commune simple",
    "gn:admin1_code":"76",
    "gn:admin2_code":"30",
    "gn:admin3_code":"301",
    "gn:admin4_code":"30072",
    "gn:asciiname":"Castelnau-Valence",
    "gn:country_code":"FR",
    "gn:dem":165,
    "gn:feature_class":"P",
    "gn:feature_code":"PPL",
    "gn:name":"Castelnau-Valence",
    "gn:population":0,
    "gn:timezone":"Europe/Paris",
    "iso:country":"FR",
    "name:bug_x_preferred":[
        "Castelnau-Valence"
    ],
    "name:cat_x_preferred":[
        "Cast\u00e8ln\u00f2u e Valen\u00e7a"
    ],
    "name:ceb_x_preferred":[
        "Castelnau-Valence"
    ],
    "name:deu_x_preferred":[
        "Castelnau-Valence"
    ],
    "name:eus_x_preferred":[
        "Cast\u00e8ln\u00f2u e Valen\u00e7a"
    ],
    "name:fra_x_preferred":[
        "Castelnau-Valence"
    ],
    "name:hun_x_preferred":[
        "Castelnau-Valence"
    ],
    "name:ita_x_preferred":[
        "Castelnau-Valence"
    ],
    "name:kaz_x_preferred":[
        "\u041a\u0430\u0441\u0442\u0435\u043b\u044c\u043d\u043e-\u0412\u0430\u043b\u0430\u043d\u0441"
    ],
    "name:lat_x_preferred":[
        "Castelnau-Valence"
    ],
    "name:lmo_x_preferred":[
        "Castelnau-Valence"
    ],
    "name:mlg_x_preferred":[
        "Castelnau-Valence"
    ],
    "name:msa_x_preferred":[
        "Castelnau-Valence"
    ],
    "name:nld_x_preferred":[
        "Castelnau-Valence"
    ],
    "name:oci_x_preferred":[
        "Cast\u00e8ln\u00f2u e Valen\u00e7a"
    ],
    "name:pms_x_preferred":[
        "Castelnau-Valence"
    ],
    "name:pol_x_preferred":[
        "Castelnau-Valence"
    ],
    "name:por_x_preferred":[
        "Castelnau-Valence"
    ],
    "name:ron_x_preferred":[
        "Castelnau-Valence"
    ],
    "name:slk_x_preferred":[
        "Castelnau-Valence"
    ],
    "name:spa_x_preferred":[
        "Castelnau-Valence"
    ],
    "name:srp_x_preferred":[
        "\u041a\u0430\u0441\u0442\u0435\u043b\u043d\u043e \u0412\u0430\u043b\u0430\u043d\u0441"
    ],
    "name:swe_x_preferred":[
        "Castelnau-Valence"
    ],
    "name:ukr_x_preferred":[
        "\u041a\u0430\u0441\u0442\u0435\u043b\u044c\u043d\u043e-\u0412\u0430\u043b\u0430\u043d\u0441"
    ],
    "name:vie_x_preferred":[
        "Castelnau-Valence"
    ],
    "name:vol_x_preferred":[
        "Castelnau-Valence"
    ],
    "name:war_x_preferred":[
        "Castelnau-Valence"
    ],
    "name:zho_x_preferred":[
        "\u5361\u65af\u6cf0\u5c14\u8bfa\u74e6\u6717\u514b"
    ],
    "qs:a0":"France",
    "qs:a1":"GARD",
    "qs:a1_lc":"30",
    "qs:a1r":"LANGUEDOC-ROUSSILLON",
    "qs:a1r_lc":"91",
    "qs:a2_lc":"38",
    "qs:a2r_lc":"1",
    "qs:adm0":"France",
    "qs:adm0_a3":"FRA",
    "qs:la":"CASTELNAU-VALENCE",
    "qs:la_lc":"30072",
    "qs:level":"localadmin",
    "qs:type":"Commune simple",
    "wof:coterminous":[
        404386949
    ],
    "wof:name":"Castelnau-Valence",
    "wof:placetype":"locality",
    "wof:placetype_local":"Commune simple"
},
  "geometry": {"coordinates":[4.25,44.0],"type":"Point"}
}