{
  "type": "Feature",
  "properties": {
    "gn:admin1_code":"84",
    "gn:admin2_code":"15",
    "gn:admin3_code":"152",
    "gn:admin4_code":"15036",
    "gn:asciiname":"La Forestie",
    "gn:country_code":"FR",
    "gn:dem":561,
    "gn:feature_class":"P",
    "gn:feature_code":"PPL",
    "gn:name":"La Forestie",
    "gn:population":0,
    "gn:timezone":"Europe/Paris",
    "iso:country":"FR",
    "wof:name":"La Forestie",
    "wof:placetype":"locality"
},
  "geometry": {"coordinates":[2.28112,45.25918],"type":"Point"}
}