{
  "type": "Feature",
  "properties": {
    "gn:admin1_code":"32",
    "gn:admin2_code":"60",
    "gn:admin3_code":"601",
    "gn:admin4_code":"60296",
    "gn:asciiname":"Bazincourt",
    "gn:country_code":"FR",
    "gn:dem":144,
    "gn:feature_class":"P",
    "gn:feature_code":"PPL",
    "gn:name":"Bazincourt",
    "gn:population":0,
    "gn:timezone":"Europe/Paris",
    "iso:country":"FR",
    "wof:name":"Bazincourt",
    "wof:placetype":"locality"
},
  "geometry": {"coordinates":[1.80996,49.50156],"type":"Point"}
}