{
  "type": "Feature",
  "properties": {
    "gn:admin1_code":"84",
    "gn:admin2_code":"73",
    "gn:admin3_code":"732",
    "gn:admin4_code":"73069",
    "gn:asciiname":"Villardizier",
    "gn:country_code":"FR",
    "gn:dem":319,
    "gn:feature_class":"P",
    "gn:feature_code":"PPL",
    "gn:name":"Villardizier",
    "gn:population":0,
    "gn:timezone":"Europe/Paris",
    "iso:country":"FR",
    "name:und_x_variant":[
        "Villard-Dizier",
        "Villardizier"
    ],
    "wof:name":"Villardizier",
    "wof:placetype":"locality"
},
  "geometry": {"coordinates":[6.20201,45.52517],"type":"Point"}
}