{
  "type": "Feature",
  "properties": {
    "gn:admin1_code":"75",
    "gn:admin2_code":"23",
    "gn:admin3_code":"231",
    "gn:admin4_code":"23261",
    "gn:asciiname":"Combraille",
    "gn:country_code":"FR",
    "gn:dem":444,
    "gn:feature_class":"P",
    "gn:feature_code":"PPL",
    "gn:name":"Combraille",
    "gn:population":0,
    "gn:timezone":"Europe/Paris",
    "iso:country":"FR",
    "name:und_x_variant":[
        "Combrailles",
        "Combraille"
    ],
    "wof:name":"Combraille",
    "wof:placetype":"locality"
},
  "geometry": {"coordinates":[2.41892,46.24987],"type":"Point"}
}