{
  "type": "Feature",
  "properties": {
    "gn:admin1_code":"84",
    "gn:admin2_code":"63",
    "gn:admin3_code":"633",
    "gn:admin4_code":"63380",
    "gn:asciiname":"Treizanches",
    "gn:country_code":"FR",
    "gn:dem":858,
    "gn:feature_class":"P",
    "gn:feature_code":"PPL",
    "gn:name":"Treizanches",
    "gn:population":0,
    "gn:timezone":"Europe/Paris",
    "iso:country":"FR",
    "wof:name":"Treizanches",
    "wof:placetype":"locality"
},
  "geometry": {"coordinates":[3.02576,45.59571],"type":"Point"}
}