{
  "type": "Feature",
  "properties": {
    "gn:admin1_code":"53",
    "gn:admin2_code":"22",
    "gn:admin3_code":"221",
    "gn:admin4_code":"22026",
    "gn:asciiname":"Calorguen",
    "gn:country_code":"FR",
    "gn:dem":44,
    "gn:feature_class":"P",
    "gn:feature_code":"PPL",
    "gn:name":"Calorguen",
    "gn:population":0,
    "gn:timezone":"Europe/Paris",
    "iso:country":"FR",
    "name:bre_x_preferred":[
        "Kerorgen"
    ],
    "name:bug_x_preferred":[
        "Calorguen"
    ],
    "name:cat_x_preferred":[
        "Calorguen"
    ],
    "name:ceb_x_preferred":[
        "Calorguen"
    ],
    "name:cym_x_preferred":[
        "Kerorgen"
    ],
    "name:deu_x_preferred":[
        "Calorguen"
    ],
    "name:epo_x_preferred":[
        "Calorguen"
    ],
    "name:eus_x_preferred":[
        "Calorguen"
    ],
    "name:fra_x_preferred":[
        "Calorguen"
    ],
    "name:hun_x_preferred":[
        "Calorguen"
    ],
    "name:ita_x_preferred":[
        "Calorguen"
    ],
    "name:kaz_x_preferred":[
        "\u041a\u0430\u043b\u043e\u0440\u0433\u0435\u043d"
    ],
    "name:lat_x_preferred":[
        "Calorguen"
    ],
    "name:msa_x_preferred":[
        "Calorguen"
    ],
    "name:nld_x_preferred":[
        "Calorguen"
    ],
    "name:oci_x_preferred":[
        "Calorguen"
    ],
    "name:pms_x_preferred":[
        "Calorguen"
    ],
    "name:pol_x_preferred":[
        "Calorguen"
    ],
    "name:por_x_preferred":[
        "Calorguen"
    ],
    "name:ron_x_preferred":[
        "Calorguen"
    ],
    "name:rus_x_preferred":[
        "\u041a\u0430\u043b\u043e\u0440\u0433\u0435\u043d"
    ],
    "name:slk_x_preferred":[
        "Calorguen"
    ],
    "name:spa_x_preferred":[
        "Calorguen"
    ],
    "name:srp_x_preferred":[
        "\u041a\u0430\u043b\u043e\u0440\u0433\u0430\u043d"
    ],
    "name:swe_x_preferred":[
        "Calorguen"
    ],
    "name:ukr_x_preferred":[
        "\u041a\u0430\u043b\u043e\u0440\u0433\u0435\u043d"
    ],
    "name:uzb_x_preferred":[
        "Calorguen"
    ],
    "name:vie_x_preferred":[
        "Calorguen"
    ],
    "name:vol_x_preferred":[
        "Calorguen"
    ],
    "name:war_x_preferred":[
        "Calorguen"
    ],
    "name:zho_x_preferred":[
        "\u5361\u6d1b\u5c14\u5188"
    ],
    "wof:name":"Calorguen",
    "wof:placetype":"locality"
},
  "geometry": {"coordinates":[-2.0278,48.4101],"type":"Point"}
}