{
  "type": "Feature",
  "properties": {
    "frgov:code_epci":"200068989",
    "frgov:insee_arr":"1",
    "frgov:insee_com":"22026",
    "frgov:insee_dep":"22",
    "frgov:insee_reg":"53",
    "frgov:nom_com":"Calorguen",
    "frgov:nom_com_m":"CALORGUEN",
    "frgov:nom_dep":"COTES-D'ARMOR",
    "frgov:nom_reg":"BRETAGNE",
    "frgov:statut":"Commune simple",
    "gn:admin1_code":"53",
    "gn:admin2_code":"22",
    "gn:admin3_code":"221",
    "gn:admin4_code":"22026",
    "gn:asciiname":"Calorguen",
    "gn:country_code":"FR",
    "gn:dem":44,
    "gn:feature_class":"P",
    "gn:feature_code":"PPL",
    "gn:name":"Calorguen",
    "gn:population":0,
    "gn:timezone":"Europe/Paris",
    "iso:country":"FR",
    "name:bre_x_preferred":[
        "Kerorgen"
    ],
    "name:bug_x_preferred":[
        "Calorguen"
    ],
    "name:cat_x_preferred":[
        "Calorguen"
    ],
    "name:ceb_x_preferred":[
        "Calorguen"
    ],
    "name:cym_x_preferred":[
        "Kerorgen"
    ],
    "name:deu_x_preferred":[
        "Calorguen"
    ],
    "name:epo_x_preferred":[
        "Calorguen"
    ],
    "name:eus_x_preferred":[
        "Calorguen"
    ],
    "name:fra_x_preferred":[
        "Calorguen"
    ],
    "name:hun_x_preferred":[
        "Calorguen"
    ],
    "name:ita_x_preferred":[
        "Calorguen"
    ],
    "name:kaz_x_preferred":[
        "\u041a\u0430\u043b\u043e\u0440\u0433\u0435\u043d"
    ],
    "name:lat_x_preferred":[
        "Calorguen"
    ],
    "name:msa_x_preferred":[
        "Calorguen"
    ],
    "name:nld_x_preferred":[
        "Calorguen"
    ],
    "name:oci_x_preferred":[
        "Calorguen"
    ],
    "name:pms_x_preferred":[
        "Calorguen"
    ],
    "name:pol_x_preferred":[
        "Calorguen"
    ],
    "name:por_x_preferred":[
        "Calorguen"
    ],
    "name:ron_x_preferred":[
        "Calorguen"
    ],
    "name:rus_x_preferred":[
        "\u041a\u0430\u043b\u043e\u0440\u0433\u0435\u043d"
    ],
    "name:slk_x_preferred":[
        "Calorguen"
    ],
    "name:spa_x_preferred":[
        "Calorguen"
    ],
    "name:srp_x_preferred":[
        "\u041a\u0430\u043b\u043e\u0440\u0433\u0430\u043d"
    ],
    "name:swe_x_preferred":[
        "Calorguen"
    ],
    "name:ukr_x_preferred":[
        "\u041a\u0430\u043b\u043e\u0440\u0433\u0435\u043d"
    ],
    "name:uzb_x_preferred":[
        "Calorguen"
    ],
    "name:vie_x_preferred":[
        "Calorguen"
    ],
    "name:vol_x_preferred":[
        "Calorguen"
    ],
    "name:war_x_preferred":[
        "Calorguen"
    ],
    "name:zho_x_preferred":[
        "\u5361\u6d1b\u5c14\u5188"
    ],
    "name:zho_x_variant":[
        "\u5361\u6d1b\u5c14\u5188"
    ],
    "qs:a0":"France",
    "qs:a1":"COTES-D'ARMOR",
    "qs:a1_lc":"22",
    "qs:a1r":"BRETAGNE",
    "qs:a1r_lc":"53",
    "qs:a2_lc":"12",
    "qs:a2r_lc":"1",
    "qs:adm0":"France",
    "qs:adm0_a3":"FRA",
    "qs:la":"CALORGUEN",
    "qs:la_lc":"22026",
    "qs:level":"localadmin",
    "qs:type":"Commune simple",
    "wof:coterminous":[
        404372589
    ],
    "wof:name":"Calorguen",
    "wof:placetype":"locality",
    "wof:placetype_local":"Commune simple"
},
  "geometry": {"coordinates":[-2.0278,48.4101],"type":"Point"}
}