{
  "type": "Feature",
  "properties": {
    "gn:admin1_code":"75",
    "gn:admin2_code":"64",
    "gn:admin3_code":"642",
    "gn:admin4_code":"64204",
    "gn:asciiname":"Aas",
    "gn:country_code":"FR",
    "gn:dem":779,
    "gn:feature_class":"P",
    "gn:feature_code":"PPL",
    "gn:name":"Aas",
    "gn:population":0,
    "gn:timezone":"Europe/Paris",
    "iso:country":"FR",
    "name:fra_x_preferred":[
        "Aas"
    ],
    "name:oci_x_preferred":[
        "Aas"
    ],
    "wof:name":"Aas",
    "wof:placetype":"locality"
},
  "geometry": {"coordinates":[-0.40124,42.98057],"type":"Point"}
}