{
  "type": "Feature",
  "properties": {
    "gn:admin1_code":"75",
    "gn:admin2_code":"87",
    "gn:admin3_code":"872",
    "gn:admin4_code":"87043",
    "gn:asciiname":"Villemonteix",
    "gn:country_code":"FR",
    "gn:dem":456,
    "gn:feature_class":"P",
    "gn:feature_code":"PPL",
    "gn:name":"Villemonteix",
    "gn:population":0,
    "gn:timezone":"Europe/Paris",
    "iso:country":"FR",
    "wof:name":"Villemonteix",
    "wof:placetype":"locality"
},
  "geometry": {"coordinates":[1.62467,45.83138],"type":"Point"}
}