{
  "type": "Feature",
  "properties": {
    "gn:admin1_code":"84",
    "gn:admin2_code":"15",
    "gn:admin3_code":"153",
    "gn:admin4_code":"15042",
    "gn:asciiname":"Aubevideyre",
    "gn:country_code":"FR",
    "gn:dem":843,
    "gn:feature_class":"P",
    "gn:feature_code":"PPL",
    "gn:name":"Aubevideyre",
    "gn:population":0,
    "gn:timezone":"Europe/Paris",
    "iso:country":"FR",
    "wof:name":"Aubevideyre",
    "wof:placetype":"locality"
},
  "geometry": {"coordinates":[3.22479,45.20231],"type":"Point"}
}