{
  "type": "Feature",
  "properties": {
    "gn:admin1_code":"27",
    "gn:admin2_code":"39",
    "gn:admin3_code":"392",
    "gn:admin4_code":"39424",
    "gn:asciiname":"La Perrena",
    "gn:country_code":"FR",
    "gn:dem":847,
    "gn:feature_class":"P",
    "gn:feature_code":"PPL",
    "gn:name":"La Perrena",
    "gn:population":0,
    "gn:timezone":"Europe/Paris",
    "iso:country":"FR",
    "wof:name":"La Perrena",
    "wof:placetype":"locality"
},
  "geometry": {"coordinates":[6.01013,46.67321],"type":"Point"}
}