{
  "type": "Feature",
  "properties": {
    "gn:admin1_code":"52",
    "gn:admin2_code":"53",
    "gn:admin3_code":"532",
    "gn:admin4_code":"53045",
    "gn:asciiname":"La Croix aux Vanneurs",
    "gn:country_code":"FR",
    "gn:dem":180,
    "gn:feature_class":"P",
    "gn:feature_code":"PPL",
    "gn:name":"La Croix aux Vanneurs",
    "gn:population":0,
    "gn:timezone":"Europe/Paris",
    "iso:country":"FR",
    "wof:name":"La Croix aux Vanneurs",
    "wof:placetype":"locality"
},
  "geometry": {"coordinates":[-0.97402,48.077],"type":"Point"}
}