{
  "type": "Feature",
  "properties": {
    "gn:admin1_code":"28",
    "gn:admin2_code":"27",
    "gn:admin3_code":"272",
    "gn:admin4_code":"27414",
    "gn:asciiname":"Saint-Aquilin-d'Augerons",
    "gn:cc2":"FR",
    "gn:country_code":"FR",
    "gn:dem":196,
    "gn:feature_class":"P",
    "gn:feature_code":"PPL",
    "gn:name":"Saint-Aquilin-d'Augerons",
    "gn:population":0,
    "gn:timezone":"Europe/Paris",
    "iso:country":"FR",
    "name:und_x_variant":[
        "Saint-Aquilin"
    ],
    "wof:name":"Saint-Aquilin-d'Augerons",
    "wof:placetype":"locality"
},
  "geometry": {"coordinates":[0.46323,48.92306],"type":"Point"}
}