{
  "type": "Feature",
  "properties": {
    "gn:admin1_code":"53",
    "gn:admin2_code":"35",
    "gn:admin3_code":"351",
    "gn:admin4_code":"35217",
    "gn:asciiname":"La Couture",
    "gn:country_code":"FR",
    "gn:dem":148,
    "gn:feature_class":"P",
    "gn:feature_code":"PPL",
    "gn:name":"La Couture",
    "gn:population":0,
    "gn:timezone":"Europe/Paris",
    "iso:country":"FR",
    "name:bre_x_preferred":[
        "La Couture"
    ],
    "name:ceb_x_preferred":[
        "La Couture"
    ],
    "name:deu_x_preferred":[
        "La Couture"
    ],
    "name:fra_x_preferred":[
        "La Couture"
    ],
    "name:ita_x_preferred":[
        "La Couture"
    ],
    "name:nds_x_preferred":[
        "La Couture"
    ],
    "name:nld_x_preferred":[
        "La Couture"
    ],
    "name:pms_x_preferred":[
        "La Couture"
    ],
    "name:pol_x_preferred":[
        "La Couture"
    ],
    "name:por_x_preferred":[
        "La Couture"
    ],
    "name:slk_x_preferred":[
        "La Couture"
    ],
    "name:spa_x_preferred":[
        "La Couture"
    ],
    "name:swe_x_preferred":[
        "La Couture"
    ],
    "name:szl_x_preferred":[
        "La Couture"
    ],
    "name:ukr_x_preferred":[
        "\u041b\u0430-\u041a\u0443\u0442\u044e\u0440"
    ],
    "wof:name":"La Couture",
    "wof:placetype":"locality"
},
  "geometry": {"coordinates":[-1.03886,48.04804],"type":"Point"}
}