{
  "type": "Feature",
  "properties": {
    "gn:admin1_code":"53",
    "gn:admin2_code":"35",
    "gn:admin3_code":"351",
    "gn:admin4_code":"35217",
    "gn:asciiname":"La Couture",
    "gn:country_code":"FR",
    "gn:dem":148,
    "gn:feature_class":"P",
    "gn:feature_code":"PPL",
    "gn:name":"La Couture",
    "gn:population":0,
    "gn:timezone":"Europe/Paris",
    "iso:country":"FR",
    "wof:name":"La Couture",
    "wof:placetype":"locality"
},
  "geometry": {"coordinates":[-1.03886,48.04804],"type":"Point"}
}