{
  "type": "Feature",
  "properties": {
    "iso:country":"FR",
    "name:eng_x_preferred":[
        "Les Vignes"
    ],
    "name:fra_x_preferred":[
        "Les Vignes"
    ],
    "name:fra_x_variant":[
        "Rive Droite Les Vignes"
    ],
    "wof:name":"Les Vignes",
    "wof:placetype":"neighbourhood"
},
  "geometry": {"coordinates":[2.1894247697002,48.81263654776323],"type":"Point"}
}