{
  "type": "Feature",
  "properties": {
    "gn:admin1_code":"44",
    "gn:admin2_code":"10",
    "gn:admin3_code":"101",
    "gn:admin4_code":"10228",
    "gn:asciiname":"L'Etape",
    "gn:country_code":"FR",
    "gn:dem":140,
    "gn:feature_class":"P",
    "gn:feature_code":"PPL",
    "gn:name":"L'\u00c9tape",
    "gn:population":0,
    "gn:timezone":"Europe/Paris",
    "iso:country":"FR",
    "wof:name":"L'Etape",
    "wof:placetype":"locality"
},
  "geometry": {"coordinates":[4.4632,48.35237],"type":"Point"}
}