{
  "type": "Feature",
  "properties": {
    "gn:admin1_code":"75",
    "gn:admin2_code":"16",
    "gn:admin3_code":"163",
    "gn:admin4_code":"16128",
    "gn:asciiname":"L'Age-Marenche",
    "gn:country_code":"FR",
    "gn:dem":191,
    "gn:feature_class":"P",
    "gn:feature_code":"PPL",
    "gn:name":"L\u2019Age-Marenche",
    "gn:population":0,
    "gn:timezone":"Europe/Paris",
    "iso:country":"FR",
    "wof:name":"L'Age-Marenche",
    "wof:placetype":"locality"
},
  "geometry": {"coordinates":[0.5266,46.07311],"type":"Point"}
}