{
  "type": "Feature",
  "properties": {
    "gn:country":"FR",
    "gn:fcode":"PPL",
    "gn:population":0,
    "iso:country":"FR",
    "name:cat_x_preferred":[
        "Aiguebelle"
    ],
    "name:ceb_x_preferred":[
        "Aiguebelle"
    ],
    "name:deu_x_preferred":[
        "Aiguebelle"
    ],
    "name:eus_x_preferred":[
        "Aiguebelle"
    ],
    "name:fas_x_preferred":[
        "\u0627\u06cc\u06af\u0648\u0628\u0644"
    ],
    "name:fra_x_preferred":[
        "Aiguebelle"
    ],
    "name:frp_x_preferred":[
        "\u00c9gouab\u00e8la"
    ],
    "name:hun_x_preferred":[
        "Aiguebelle"
    ],
    "name:ita_x_preferred":[
        "Aiguebelle"
    ],
    "name:lmo_x_preferred":[
        "Aiguebelle"
    ],
    "name:msa_x_preferred":[
        "Aiguebelle"
    ],
    "name:nld_x_preferred":[
        "Aiguebelle"
    ],
    "name:oci_x_preferred":[
        "Aiguebelle"
    ],
    "name:pol_x_preferred":[
        "Aiguebelle"
    ],
    "name:por_x_preferred":[
        "Aiguebelle"
    ],
    "name:ron_x_preferred":[
        "Aiguebelle"
    ],
    "name:slk_x_preferred":[
        "Aiguebelle"
    ],
    "name:spa_x_preferred":[
        "Aiguebelle"
    ],
    "name:sqi_x_preferred":[
        "Aiguebelle"
    ],
    "name:srp_x_preferred":[
        "\u0415\u0433\u0431\u0435\u043b"
    ],
    "name:swe_x_preferred":[
        "Aiguebelle"
    ],
    "name:ukr_x_preferred":[
        "\u0415\u0433\u0431\u0435\u043b\u044c"
    ],
    "name:uzb_x_preferred":[
        "Aiguebelle"
    ],
    "name:vie_x_preferred":[
        "Aiguebelle"
    ],
    "name:vol_x_preferred":[
        "Aiguebelle"
    ],
    "name:war_x_preferred":[
        "Aiguebelle"
    ],
    "qs_pg:aaroncc":"FR",
    "qs_pg:gn_country":"FR",
    "qs_pg:gn_fcode":"PPL",
    "qs_pg:gn_pop":0,
    "qs_pg:name":"Aiguebelle",
    "qs_pg:name_adm0":"France",
    "qs_pg:name_adm1":"Provence-Alpes-C\u00f4te d'Azur",
    "qs_pg:photos":31,
    "qs_pg:photos_1k":6,
    "qs_pg:photos_9k":1,
    "qs_pg:photos_9r":2,
    "qs_pg:photos_all":31,
    "qs_pg:photos_sr":2,
    "qs_pg:pop_sr":0,
    "qs_pg:qs_pg_placetype":"locality",
    "qs_pg:qs_pg_placetype_gp":"Town",
    "qs_pg:woe_adm0":23424819,
    "woe:adm0_id":23424819,
    "woe:name_adm0":"France",
    "woe:name_adm1":"Provence-Alpes-C\u00f4te d'Azur",
    "woe:placetype":"Town",
    "wof:name":"Aiguebelle",
    "wof:placetype":"neighbourhood"
},
  "geometry": {"coordinates":[6.40972,43.15221],"type":"Point"}
}