{
  "type": "Feature",
  "properties": {
    "gn:admin1_code":"75",
    "gn:admin2_code":"87",
    "gn:admin3_code":"871",
    "gn:admin4_code":"87068",
    "gn:asciiname":"La Traverse",
    "gn:country_code":"FR",
    "gn:dem":390,
    "gn:feature_class":"P",
    "gn:feature_code":"PPL",
    "gn:name":"La Traverse",
    "gn:population":0,
    "gn:timezone":"Europe/Paris",
    "iso:country":"FR",
    "wof:name":"La Traverse",
    "wof:placetype":"locality"
},
  "geometry": {"coordinates":[1.39855,46.13591],"type":"Point"}
}