{
  "type": "Feature",
  "properties": {
    "gn:admin1_code":"27",
    "gn:admin2_code":"58",
    "gn:admin3_code":"581",
    "gn:admin4_code":"58249",
    "gn:asciiname":"Poiseux",
    "gn:country_code":"FR",
    "gn:dem":409,
    "gn:feature_class":"P",
    "gn:feature_code":"PPL",
    "gn:name":"Poiseux",
    "gn:population":0,
    "gn:timezone":"Europe/Paris",
    "iso:country":"FR",
    "name:cat_x_preferred":[
        "Poiseux"
    ],
    "name:ceb_x_preferred":[
        "Poiseux"
    ],
    "name:deu_x_preferred":[
        "Poiseux"
    ],
    "name:eus_x_preferred":[
        "Poiseux"
    ],
    "name:fra_x_preferred":[
        "Poiseux"
    ],
    "name:hun_x_preferred":[
        "Poiseux"
    ],
    "name:ita_x_preferred":[
        "Poiseux"
    ],
    "name:kaz_x_preferred":[
        "\u041f\u0443\u0430\u0437\u0435"
    ],
    "name:lat_x_preferred":[
        "Poiseux"
    ],
    "name:ltz_x_preferred":[
        "Poiseux"
    ],
    "name:msa_x_preferred":[
        "Poiseux"
    ],
    "name:nld_x_preferred":[
        "Poiseux"
    ],
    "name:oci_x_preferred":[
        "Poiseux"
    ],
    "name:pms_x_preferred":[
        "Poiseux"
    ],
    "name:pol_x_preferred":[
        "Poiseux"
    ],
    "name:por_x_preferred":[
        "Poiseux"
    ],
    "name:ron_x_preferred":[
        "Poiseux"
    ],
    "name:slk_x_preferred":[
        "Poiseux"
    ],
    "name:spa_x_preferred":[
        "Poiseux"
    ],
    "name:swe_x_preferred":[
        "Poiseux"
    ],
    "name:ukr_x_preferred":[
        "\u041f\u0443\u0430\u0437\u0435"
    ],
    "name:uzb_x_preferred":[
        "Poiseux"
    ],
    "name:vie_x_preferred":[
        "Poiseux"
    ],
    "name:vol_x_preferred":[
        "Poiseux"
    ],
    "name:war_x_preferred":[
        "Poiseux"
    ],
    "name:zho_x_preferred":[
        "\u666e\u74e6\u745f"
    ],
    "wof:name":"Poiseux",
    "wof:placetype":"locality"
},
  "geometry": {"coordinates":[3.8869,46.98928],"type":"Point"}
}