{
  "type": "Feature",
  "properties": {
    "gn:admin1_code":"27",
    "gn:admin2_code":"58",
    "gn:admin3_code":"581",
    "gn:admin4_code":"58249",
    "gn:asciiname":"Poiseux",
    "gn:country_code":"FR",
    "gn:dem":409,
    "gn:feature_class":"P",
    "gn:feature_code":"PPL",
    "gn:name":"Poiseux",
    "gn:population":0,
    "gn:timezone":"Europe/Paris",
    "iso:country":"FR",
    "wof:name":"Poiseux",
    "wof:placetype":"locality"
},
  "geometry": {"coordinates":[3.8869,46.98928],"type":"Point"}
}