{
  "type": "Feature",
  "properties": {
    "iso:country":"FR",
    "name:eng_x_preferred":[
        "Centre"
    ],
    "name:fra_x_preferred":[
        "Centre"
    ],
    "wof:name":"Centre",
    "wof:placetype":"neighbourhood"
},
  "geometry": {"coordinates":[2.35580582306107,48.77168701736066],"type":"Point"}
}