{
  "type": "Feature",
  "properties": {
    "iso:country":"FR",
    "name:ben_x_preferred":[
        "\u09b8\u09c7\u09a8\u09cd\u099f\u09be\u09b0"
    ],
    "name:eng_x_preferred":[
        "Centre"
    ],
    "name:fra_x_preferred":[
        "Centre"
    ],
    "name:heb_x_preferred":[
        "\u05de\u05e8\u05db\u05d6"
    ],
    "name:hin_x_preferred":[
        "\u0938\u0947\u0902\u091f\u0930"
    ],
    "name:hun_x_preferred":[
        "K\u00f6z\u00e9p"
    ],
    "name:vie_x_preferred":[
        "Centre"
    ],
    "wof:name":"Centre",
    "wof:placetype":"neighbourhood"
},
  "geometry": {"coordinates":[2.355806,48.771687],"type":"Point"}
}