{
  "type": "Feature",
  "properties": {
    "gn:admin1_code":"52",
    "gn:admin2_code":"53",
    "gn:admin3_code":"532",
    "gn:admin4_code":"53225",
    "gn:asciiname":"Beulin",
    "gn:country_code":"FR",
    "gn:dem":120,
    "gn:feature_class":"P",
    "gn:feature_code":"PPL",
    "gn:name":"Beulin",
    "gn:population":0,
    "gn:timezone":"Europe/Paris",
    "iso:country":"FR",
    "wof:name":"Beulin",
    "wof:placetype":"locality"
},
  "geometry": {"coordinates":[-0.81207,48.21003],"type":"Point"}
}