{
  "type": "Feature",
  "properties": {
    "gn:admin1_code":"76",
    "gn:admin2_code":"46",
    "gn:admin3_code":"463",
    "gn:admin4_code":"46216",
    "gn:asciiname":"Nadaillac",
    "gn:country_code":"FR",
    "gn:dem":126,
    "gn:feature_class":"P",
    "gn:feature_code":"PPL",
    "gn:name":"Nadaillac",
    "gn:population":0,
    "gn:timezone":"Europe/Paris",
    "iso:country":"FR",
    "wof:name":"Nadaillac",
    "wof:placetype":"locality"
},
  "geometry": {"coordinates":[1.3293,44.77656],"type":"Point"}
}