{
  "type": "Feature",
  "properties": {
    "gn:admin1_code":"76",
    "gn:admin2_code":"46",
    "gn:admin3_code":"463",
    "gn:admin4_code":"46216",
    "gn:asciiname":"Nadaillac",
    "gn:country_code":"FR",
    "gn:dem":126,
    "gn:feature_class":"P",
    "gn:feature_code":"PPL",
    "gn:name":"Nadaillac",
    "gn:population":0,
    "gn:timezone":"Europe/Paris",
    "iso:country":"FR",
    "name:bug_x_preferred":[
        "Nadaillac"
    ],
    "name:cat_x_preferred":[
        "Nadalhac"
    ],
    "name:ceb_x_preferred":[
        "Nadaillac"
    ],
    "name:deu_x_preferred":[
        "Nadaillac"
    ],
    "name:eus_x_preferred":[
        "Nadaillac"
    ],
    "name:fra_x_preferred":[
        "Nadaillac"
    ],
    "name:hun_x_preferred":[
        "Nadaillac"
    ],
    "name:ita_x_preferred":[
        "Nadaillac"
    ],
    "name:kaz_x_preferred":[
        "\u041d\u0430\u0434\u0430\u044f\u043a"
    ],
    "name:lat_x_preferred":[
        "Nadaillac"
    ],
    "name:mlg_x_preferred":[
        "Nadaillac"
    ],
    "name:msa_x_preferred":[
        "Nadaillac"
    ],
    "name:nld_x_preferred":[
        "Nadaillac"
    ],
    "name:oci_x_preferred":[
        "Nadalhac"
    ],
    "name:pms_x_preferred":[
        "Nadaillac"
    ],
    "name:pol_x_preferred":[
        "Nadaillac"
    ],
    "name:por_x_preferred":[
        "Nadaillac"
    ],
    "name:ron_x_preferred":[
        "Nadaillac"
    ],
    "name:slk_x_preferred":[
        "Nadaillac"
    ],
    "name:spa_x_preferred":[
        "Nadaillac"
    ],
    "name:swe_x_preferred":[
        "Nadaillac"
    ],
    "name:ukr_x_preferred":[
        "\u041d\u0430\u0434\u0430\u044f\u043a"
    ],
    "name:uzb_x_preferred":[
        "Nadaillac"
    ],
    "name:vie_x_preferred":[
        "Nadaillac"
    ],
    "name:vol_x_preferred":[
        "Nadaillac"
    ],
    "name:war_x_preferred":[
        "Nadaillac"
    ],
    "name:zho_x_preferred":[
        "\u7eb3\u4ee3\u62c9\u514b"
    ],
    "wof:name":"Nadaillac",
    "wof:placetype":"locality"
},
  "geometry": {"coordinates":[1.3293,44.77656],"type":"Point"}
}