{
  "type": "Feature",
  "properties": {
    "gn:admin1_code":"53",
    "gn:admin2_code":"29",
    "gn:admin3_code":"291",
    "gn:admin4_code":"29019",
    "gn:asciiname":"L'arc'hantel",
    "gn:country_code":"FR",
    "gn:dem":69,
    "gn:feature_class":"P",
    "gn:feature_code":"PPL",
    "gn:name":"L'arc'hantel",
    "gn:population":0,
    "gn:timezone":"Europe/Paris",
    "iso:country":"FR",
    "wof:name":"L'arc'hantel",
    "wof:placetype":"locality"
},
  "geometry": {"coordinates":[-4.55575,48.3825],"type":"Point"}
}