{
  "type": "Feature",
  "properties": {
    "gn:admin1_code":"44",
    "gn:admin2_code":"88",
    "gn:admin3_code":"882",
    "gn:admin4_code":"88460",
    "gn:asciiname":"Fruze",
    "gn:country_code":"FR",
    "gn:dem":288,
    "gn:feature_class":"P",
    "gn:feature_code":"PPL",
    "gn:name":"Fruze",
    "gn:population":0,
    "gn:timezone":"Europe/Paris",
    "iso:country":"FR",
    "wof:name":"Fruze",
    "wof:placetype":"locality"
},
  "geometry": {"coordinates":[5.73785,48.39635],"type":"Point"}
}