{
  "type": "Feature",
  "properties": {
    "gn:admin1_code":"24",
    "gn:admin2_code":"18",
    "gn:admin3_code":"182",
    "gn:admin4_code":"18041",
    "gn:asciiname":"Les Petits Fosses",
    "gn:country_code":"FR",
    "gn:dem":223,
    "gn:feature_class":"P",
    "gn:feature_code":"PPL",
    "gn:name":"Les Petits Foss\u00e9s",
    "gn:population":0,
    "gn:timezone":"Europe/Paris",
    "iso:country":"FR",
    "wof:name":"Les Petits Fosses",
    "wof:placetype":"locality"
},
  "geometry": {"coordinates":[2.52266,46.62600000000001],"type":"Point"}
}