{
  "type": "Feature",
  "properties": {
    "gn:admin1_code":"84",
    "gn:admin2_code":"69",
    "gn:admin3_code":"691",
    "gn:admin4_code":"69219",
    "gn:asciiname":"Saint-Vincent",
    "gn:country_code":"FR",
    "gn:dem":427,
    "gn:feature_class":"P",
    "gn:feature_code":"PPL",
    "gn:name":"Saint-Vincent",
    "gn:population":0,
    "gn:timezone":"Europe/Paris",
    "iso:country":"FR",
    "wof:name":"Saint-Vincent",
    "wof:placetype":"locality"
},
  "geometry": {"coordinates":[4.67739,45.64242],"type":"Point"}
}