{
  "type": "Feature",
  "properties": {
    "iso:country":"FR",
    "name:eng_x_preferred":[
        "Paris Campagne"
    ],
    "name:fra_x_preferred":[
        "Paris Campagne"
    ],
    "wof:name":"Paris Campagne",
    "wof:placetype":"neighbourhood"
},
  "geometry": {"coordinates":[2.43411615009861,48.92774470452469],"type":"Point"}
}