{
  "type": "Feature",
  "properties": {
    "gn:admin1_code":"24",
    "gn:admin2_code":"36",
    "gn:admin3_code":"363",
    "gn:admin4_code":"36110",
    "gn:asciiname":"Les Nielloux",
    "gn:country_code":"FR",
    "gn:dem":201,
    "gn:feature_class":"P",
    "gn:feature_code":"PPL",
    "gn:name":"Les Nielloux",
    "gn:population":0,
    "gn:timezone":"Europe/Paris",
    "iso:country":"FR",
    "name:und_x_variant":[
        "Le Nielloux",
        "Les Nielloux"
    ],
    "wof:name":"Les Nielloux",
    "wof:placetype":"locality"
},
  "geometry": {"coordinates":[1.64857,46.60762],"type":"Point"}
}