{
  "type": "Feature",
  "properties": {
    "gn:admin1_code":"32",
    "gn:admin2_code":"59",
    "gn:admin3_code":"593",
    "gn:admin4_code":"59178",
    "gn:asciiname":"Dorignies",
    "gn:country_code":"FR",
    "gn:dem":24,
    "gn:feature_class":"P",
    "gn:feature_code":"PPL",
    "gn:name":"Dorignies",
    "gn:population":0,
    "gn:timezone":"Europe/Paris",
    "iso:country":"FR",
    "wof:name":"Dorignies",
    "wof:placetype":"locality"
},
  "geometry": {"coordinates":[3.09322,50.39443],"type":"Point"}
}