{
  "type": "Feature",
  "properties": {
    "gn:admin1_code":"75",
    "gn:admin2_code":"23",
    "gn:admin3_code":"232",
    "gn:admin4_code":"23236",
    "gn:asciiname":"Quinsac",
    "gn:country_code":"FR",
    "gn:dem":388,
    "gn:feature_class":"P",
    "gn:feature_code":"PPL",
    "gn:name":"Quinsac",
    "gn:population":0,
    "gn:timezone":"Europe/Paris",
    "iso:country":"FR",
    "wof:name":"Quinsac",
    "wof:placetype":"locality"
},
  "geometry": {"coordinates":[1.65725,46.19084],"type":"Point"}
}