{
  "type": "Feature",
  "properties": {
    "gn:admin1_code":"75",
    "gn:admin2_code":"23",
    "gn:admin3_code":"232",
    "gn:admin4_code":"23236",
    "gn:asciiname":"Quinsac",
    "gn:country_code":"FR",
    "gn:dem":388,
    "gn:feature_class":"P",
    "gn:feature_code":"PPL",
    "gn:name":"Quinsac",
    "gn:population":0,
    "gn:timezone":"Europe/Paris",
    "iso:country":"FR",
    "name:ceb_x_preferred":[
        "Quinsac"
    ],
    "name:deu_x_preferred":[
        "Quinsac"
    ],
    "name:fra_x_preferred":[
        "Quinsac"
    ],
    "name:ita_x_preferred":[
        "Quinsac"
    ],
    "name:nds_x_preferred":[
        "Quinsac"
    ],
    "name:nld_x_preferred":[
        "Quinsac"
    ],
    "name:oci_x_preferred":[
        "Quinsac"
    ],
    "name:pms_x_preferred":[
        "Quinsac"
    ],
    "name:pol_x_preferred":[
        "Quinsac"
    ],
    "name:por_x_preferred":[
        "Quinsac"
    ],
    "name:rus_x_preferred":[
        "\u041a\u0435\u043d\u0441\u0430\u043a"
    ],
    "name:slk_x_preferred":[
        "Quinsac"
    ],
    "name:spa_x_preferred":[
        "Quinsac"
    ],
    "name:swe_x_preferred":[
        "Quinsac"
    ],
    "name:ukr_x_preferred":[
        "\u041a\u0435\u043d\u0441\u0430\u043a"
    ],
    "wof:name":"Quinsac",
    "wof:placetype":"locality"
},
  "geometry": {"coordinates":[1.65725,46.19084],"type":"Point"}
}