{
  "type": "Feature",
  "properties": {
    "gn:admin1_code":"24",
    "gn:admin2_code":"36",
    "gn:admin3_code":"364",
    "gn:admin4_code":"36230",
    "gn:asciiname":"La Foye",
    "gn:country_code":"FR",
    "gn:dem":154,
    "gn:feature_class":"P",
    "gn:feature_code":"PPL",
    "gn:name":"La Foye",
    "gn:population":0,
    "gn:timezone":"Europe/Paris",
    "iso:country":"FR",
    "wof:name":"La Foye",
    "wof:placetype":"locality"
},
  "geometry": {"coordinates":[1.8499,47.06504],"type":"Point"}
}