{
  "type": "Feature",
  "properties": {
    "gn:admin1_code":"27",
    "gn:admin2_code":"89",
    "gn:admin3_code":"892",
    "gn:admin4_code":"89010",
    "gn:asciiname":"Moutot",
    "gn:country_code":"FR",
    "gn:dem":183,
    "gn:feature_class":"P",
    "gn:feature_code":"PPL",
    "gn:name":"Moutot",
    "gn:population":0,
    "gn:timezone":"Europe/Paris",
    "iso:country":"FR",
    "wof:name":"Moutot",
    "wof:placetype":"locality"
},
  "geometry": {"coordinates":[3.96702,47.72047],"type":"Point"}
}