{
  "type": "Feature",
  "properties": {
    "iso:country":"FR",
    "wof:name":"Coeur de Bastide",
    "wof:placetype":"neighbourhood"
},
  "geometry": {"coordinates":[-0.56095620510935,44.84376814063985],"type":"Point"}
}