{
  "type": "Feature",
  "properties": {
    "gn:admin1_code":"84",
    "gn:admin2_code":"63",
    "gn:admin3_code":"631",
    "gn:admin4_code":"63142",
    "gn:asciiname":"Buisson",
    "gn:country_code":"FR",
    "gn:dem":911,
    "gn:feature_class":"P",
    "gn:feature_code":"PPL",
    "gn:name":"Buisson",
    "gn:population":0,
    "gn:timezone":"Europe/Paris",
    "iso:country":"FR",
    "name:deu_x_preferred":[
        "Buisson"
    ],
    "name:fra_x_preferred":[
        "Buisson"
    ],
    "name:ita_x_preferred":[
        "Buisson"
    ],
    "name:nld_x_preferred":[
        "Buisson"
    ],
    "name:pol_x_preferred":[
        "Buisson"
    ],
    "name:rus_x_preferred":[
        "\u0411\u044e\u0438\u0441\u0441\u043e\u043d"
    ],
    "name:srp_x_preferred":[
        "\u0411\u0438\u0441\u043e\u043d"
    ],
    "wof:name":"Buisson",
    "wof:placetype":"locality"
},
  "geometry": {"coordinates":[3.52286,45.56444000000001],"type":"Point"}
}