{
  "type": "Feature",
  "properties": {
    "gn:admin1_code":"84",
    "gn:admin2_code":"03",
    "gn:admin3_code":"031",
    "gn:admin4_code":"03005",
    "gn:asciiname":"Le Liat",
    "gn:country_code":"FR",
    "gn:dem":372,
    "gn:feature_class":"P",
    "gn:feature_code":"PPL",
    "gn:name":"Le Liat",
    "gn:population":0,
    "gn:timezone":"Europe/Paris",
    "iso:country":"FR",
    "wof:name":"Le Liat",
    "wof:placetype":"locality"
},
  "geometry": {"coordinates":[2.4336,46.3589],"type":"Point"}
}