{
  "type": "Feature",
  "properties": {
    "gn:admin1_code":"93",
    "gn:admin2_code":"83",
    "gn:admin3_code":"833",
    "gn:admin4_code":"83114",
    "gn:asciiname":"Saint-Martin-de-Pallieres",
    "gn:country_code":"FR",
    "gn:dem":480,
    "gn:feature_class":"P",
    "gn:feature_code":"PPL",
    "gn:name":"Saint-Martin-de-Palli\u00e8res",
    "gn:population":0,
    "gn:timezone":"Europe/Paris",
    "iso:country":"FR",
    "name:cat_x_preferred":[
        "Sant Martin"
    ],
    "name:ceb_x_preferred":[
        "Saint-Martin-de-Palli\u00e8res"
    ],
    "name:deu_x_preferred":[
        "Saint-Martin-de-Palli\u00e8res"
    ],
    "name:eus_x_preferred":[
        "Saint-Martin-de-Palli\u00e8res"
    ],
    "name:fra_x_preferred":[
        "Saint-Martin-de-Palli\u00e8res"
    ],
    "name:hun_x_preferred":[
        "Saint-Martin"
    ],
    "name:ita_x_preferred":[
        "Saint-Martin-de-Palli\u00e8res"
    ],
    "name:lmo_x_preferred":[
        "Saint-Martin-de-Palli\u00e8res"
    ],
    "name:mlg_x_preferred":[
        "Saint-Martin-de-Palli\u00e8res"
    ],
    "name:msa_x_preferred":[
        "Saint-Martin-de-Palli\u00e8res"
    ],
    "name:nld_x_preferred":[
        "Saint-Martin-de-Palli\u00e8res"
    ],
    "name:oci_x_preferred":[
        "Sant Martin"
    ],
    "name:pms_x_preferred":[
        "Saint-Martin-de-Palli\u00e8res"
    ],
    "name:pol_x_preferred":[
        "Saint-Martin-de-Palli\u00e8res"
    ],
    "name:por_x_preferred":[
        "Saint-Martin-de-Palli\u00e8res"
    ],
    "name:ron_x_preferred":[
        "Saint-Martin-de-Palli\u00e8res"
    ],
    "name:rus_x_preferred":[
        "\u0421\u0435\u043d-\u041c\u0430\u0440\u0442\u0435\u043d-\u0434\u0435-\u041f\u0430\u043b\u044c\u0435\u0440"
    ],
    "name:slk_x_preferred":[
        "Saint-Martin-de-Palli\u00e8res"
    ],
    "name:spa_x_preferred":[
        "Saint-Martin-de-Palli\u00e8res"
    ],
    "name:swe_x_preferred":[
        "Saint-Martin-de-Palli\u00e9res"
    ],
    "name:swe_x_variant":[
        "Saint-Martin-de-Palli\u00e8res"
    ],
    "name:ukr_x_preferred":[
        "\u0421\u0435\u043d-\u041c\u0430\u0440\u0442\u0435\u043d"
    ],
    "name:und_x_variant":[
        "Saint-Martin-des Pallieres"
    ],
    "name:urd_x_preferred":[
        "\u0633\u06cc\u0646\u0679-\u0645\u0627\u0631\u0679\u0646-\u062f\u06d2-\u067e\u0644\u06cc\u0631\u0633"
    ],
    "name:vie_x_preferred":[
        "Saint-Martin-de-Palli\u00e8res"
    ],
    "name:vol_x_preferred":[
        "Saint-Martin-de-Palli\u00e8res"
    ],
    "name:war_x_preferred":[
        "Saint-Martin-de-Palli\u00e8res"
    ],
    "wof:name":"Saint-Martin-de-Pallieres",
    "wof:placetype":"locality"
},
  "geometry": {"coordinates":[5.88454,43.58852],"type":"Point"}
}