{
  "type": "Feature",
  "properties": {
    "gn:admin1_code":"75",
    "gn:admin2_code":"64",
    "gn:admin3_code":"643",
    "gn:admin4_code":"64369",
    "gn:asciiname":"Juillacq",
    "gn:country_code":"FR",
    "gn:dem":254,
    "gn:feature_class":"P",
    "gn:feature_code":"PPL",
    "gn:name":"Juillacq",
    "gn:population":0,
    "gn:timezone":"Europe/Paris",
    "iso:country":"FR",
    "wof:name":"Juillacq",
    "wof:placetype":"locality"
},
  "geometry": {"coordinates":[-0.13333,43.43333],"type":"Point"}
}