{
  "type": "Feature",
  "properties": {
    "gn:admin1_code":"28",
    "gn:admin2_code":"76",
    "gn:admin3_code":"761",
    "gn:admin4_code":"76487",
    "gn:asciiname":"Maintru",
    "gn:country_code":"FR",
    "gn:dem":51,
    "gn:feature_class":"P",
    "gn:feature_code":"PPL",
    "gn:name":"Maintru",
    "gn:population":0,
    "gn:timezone":"Europe/Paris",
    "iso:country":"FR",
    "wof:name":"Maintru",
    "wof:placetype":"locality"
},
  "geometry": {"coordinates":[1.30086,49.80024],"type":"Point"}
}