{
  "type": "Feature",
  "properties": {
    "gn:admin1_code":"93",
    "gn:admin2_code":"04",
    "gn:admin3_code":"044",
    "gn:admin4_code":"04016",
    "gn:asciiname":"Feissal",
    "gn:country_code":"FR",
    "gn:dem":1339,
    "gn:feature_class":"P",
    "gn:feature_code":"PPL",
    "gn:name":"Feissal",
    "gn:population":0,
    "gn:timezone":"Europe/Paris",
    "iso:country":"FR",
    "wof:name":"Feissal",
    "wof:placetype":"locality"
},
  "geometry": {"coordinates":[6.16968,44.2349],"type":"Point"}
}