{
  "type": "Feature",
  "properties": {
    "gn:admin1_code":"44",
    "gn:admin2_code":"52",
    "gn:admin3_code":"522",
    "gn:admin4_code":"52060",
    "gn:asciiname":"Villars-Saint-Marcellin",
    "gn:country_code":"FR",
    "gn:dem":262,
    "gn:feature_class":"P",
    "gn:feature_code":"PPL",
    "gn:name":"Villars-Saint-Marcellin",
    "gn:population":0,
    "gn:timezone":"Europe/Paris",
    "iso:country":"FR",
    "name:und_x_variant":[
        "Villars",
        "Villars-Saint-Marcellin"
    ],
    "wof:name":"Villars-Saint-Marcellin",
    "wof:placetype":"locality"
},
  "geometry": {"coordinates":[5.79063,47.93592],"type":"Point"}
}