{
  "type": "Feature",
  "properties": {
    "gn:admin1_code":"24",
    "gn:admin2_code":"18",
    "gn:admin3_code":"182",
    "gn:admin4_code":"18261.0",
    "gn:asciiname":"Trecon",
    "gn:country_code":"FR",
    "gn:dem":175,
    "gn:feature_class":"P",
    "gn:feature_code":"PPL",
    "gn:name":"Tr\u00e9con",
    "gn:population":0,
    "gn:timezone":"Europe/Paris",
    "iso:country":"FR",
    "wof:name":"Trecon",
    "wof:placetype":"locality"
},
  "geometry": {"coordinates":[2.66415,46.79872],"type":"Point"}
}