{
  "type": "Feature",
  "properties": {
    "iso:country":"FR",
    "name:eng_x_preferred":[
        "Fontaine des Pres"
    ],
    "name:fra_x_preferred":[
        "Fontaine des Pres"
    ],
    "wof:name":"Fontaine des Pres",
    "wof:placetype":"neighbourhood"
},
  "geometry": {"coordinates":[2.48547153787665,48.94294934315512],"type":"Point"}
}