{
  "type": "Feature",
  "properties": {
    "iso:country":"FR",
    "name:eng_x_preferred":[
        "Le Marais"
    ],
    "name:fra_x_preferred":[
        "Le Marais"
    ],
    "wof:name":"Le Marais",
    "wof:placetype":"neighbourhood"
},
  "geometry": {"coordinates":[3.00583425622156,50.62980866783984],"type":"Point"}
}