{
  "type": "Feature",
  "properties": {
    "gn:admin1_code":"24",
    "gn:admin2_code":"18",
    "gn:admin3_code":"182",
    "gn:admin4_code":"18082",
    "gn:asciiname":"Le Bec d'Allier",
    "gn:country_code":"FR",
    "gn:dem":171,
    "gn:feature_class":"P",
    "gn:feature_code":"PPL",
    "gn:name":"Le Bec d\u2019Allier",
    "gn:population":0,
    "gn:timezone":"Europe/Paris",
    "iso:country":"FR",
    "wof:name":"Le Bec d'Allier",
    "wof:placetype":"locality"
},
  "geometry": {"coordinates":[3.07515,46.95866],"type":"Point"}
}