{
  "type": "Feature",
  "properties": {
    "gn:admin1_code":"75",
    "gn:admin2_code":"19",
    "gn:admin3_code":"192",
    "gn:admin4_code":"19014",
    "gn:asciiname":"Le Mons",
    "gn:country_code":"FR",
    "gn:dem":669,
    "gn:feature_class":"P",
    "gn:feature_code":"PPL",
    "gn:name":"Le Mons",
    "gn:population":0,
    "gn:timezone":"Europe/Paris",
    "iso:country":"FR",
    "wof:name":"Le Mons",
    "wof:placetype":"locality"
},
  "geometry": {"coordinates":[2.15549,45.18305],"type":"Point"}
}