{
  "type": "Feature",
  "properties": {
    "gn:admin1_code":"84",
    "gn:admin2_code":"07",
    "gn:admin3_code":"072",
    "gn:admin4_code":"7286.0",
    "gn:asciiname":"Bachasson",
    "gn:country_code":"FR",
    "gn:dem":661,
    "gn:feature_class":"P",
    "gn:feature_code":"PPL",
    "gn:name":"Bachasson",
    "gn:population":0,
    "gn:timezone":"Europe/Paris",
    "iso:country":"FR",
    "wof:name":"Bachasson",
    "wof:placetype":"locality"
},
  "geometry": {"coordinates":[4.48333,44.81667],"type":"Point"}
}