{
  "type": "Feature",
  "properties": {
    "gn:admin1_code":"84",
    "gn:admin2_code":"42",
    "gn:admin3_code":"423",
    "gn:admin4_code":"42310",
    "gn:asciiname":"La Combe",
    "gn:country_code":"FR",
    "gn:dem":891,
    "gn:feature_class":"P",
    "gn:feature_code":"PPL",
    "gn:name":"La Combe",
    "gn:population":0,
    "gn:timezone":"Europe/Paris",
    "iso:country":"FR",
    "wof:name":"La Combe",
    "wof:placetype":"locality"
},
  "geometry": {"coordinates":[4.56549,45.33232],"type":"Point"}
}