{
  "type": "Feature",
  "properties": {
    "gn:admin1_code":"94",
    "gn:admin2_code":"2A",
    "gn:admin3_code":"2A1",
    "gn:admin4_code":"2A004",
    "gn:asciiname":"Saint-Joseph",
    "gn:country_code":"FR",
    "gn:dem":53,
    "gn:feature_class":"P",
    "gn:feature_code":"PPL",
    "gn:name":"Saint-Joseph",
    "gn:population":0,
    "gn:timezone":"Europe/Paris",
    "iso:country":"FR",
    "wof:name":"Saint-Joseph",
    "wof:placetype":"locality"
},
  "geometry": {"coordinates":[8.75994,41.93074],"type":"Point"}
}