{
  "type": "Feature",
  "properties": {
    "gn:admin1_code":"84",
    "gn:admin2_code":"43",
    "gn:admin3_code":"433",
    "gn:admin4_code":"43162",
    "gn:asciiname":"Charrees",
    "gn:country_code":"FR",
    "gn:dem":636,
    "gn:feature_class":"P",
    "gn:feature_code":"PPL",
    "gn:name":"Charr\u00e9es",
    "gn:population":0,
    "gn:timezone":"Europe/Paris",
    "iso:country":"FR",
    "wof:name":"Charrees",
    "wof:placetype":"locality"
},
  "geometry": {"coordinates":[4.01968,45.23289000000001],"type":"Point"}
}