{
  "type": "Feature",
  "properties": {
    "gn:admin1_code":"76",
    "gn:admin2_code":"11",
    "gn:admin3_code":"112",
    "gn:admin4_code":"11034",
    "gn:asciiname":"Belveze-du-Razes",
    "gn:country_code":"FR",
    "gn:dem":243,
    "gn:feature_class":"P",
    "gn:feature_code":"PPL",
    "gn:name":"Belv\u00e8ze-du-Raz\u00e8s",
    "gn:population":745,
    "gn:timezone":"Europe/Paris",
    "iso:country":"FR",
    "name:und_x_variant":[
        "Belv\u00e8ze",
        "Belv\u00e8ze-du-Raz\u00e8s"
    ],
    "wof:name":"Belveze-du-Razes",
    "wof:placetype":"locality",
    "wof:population":745
},
  "geometry": {"coordinates":[2.09536,43.12556],"type":"Point"}
}