{
  "type": "Feature",
  "properties": {
    "gn:admin1_code":"94",
    "gn:admin2_code":"2A",
    "gn:admin3_code":"2A1",
    "gn:admin4_code":"2A065",
    "gn:asciiname":"Malzone",
    "gn:country_code":"FR",
    "gn:dem":18,
    "gn:feature_class":"P",
    "gn:feature_code":"PPL",
    "gn:name":"Malzone",
    "gn:population":0,
    "gn:timezone":"Europe/Paris",
    "iso:country":"FR",
    "wof:name":"Malzone",
    "wof:placetype":"locality"
},
  "geometry": {"coordinates":[8.61667,42.18333],"type":"Point"}
}