{
  "type": "Feature",
  "properties": {
    "gn:admin1_code":"53",
    "gn:admin2_code":"29",
    "gn:admin3_code":"291",
    "gn:admin4_code":"29077",
    "gn:asciiname":"Kervaro",
    "gn:country_code":"FR",
    "gn:dem":61,
    "gn:feature_class":"P",
    "gn:feature_code":"PPL",
    "gn:name":"Kervaro",
    "gn:population":0,
    "gn:timezone":"Europe/Paris",
    "iso:country":"FR",
    "wof:name":"Kervaro",
    "wof:placetype":"locality"
},
  "geometry": {"coordinates":[-4.44545,48.61878],"type":"Point"}
}