{
  "type": "Feature",
  "properties": {
    "gn:admin1_code":"94",
    "gn:admin2_code":"2B",
    "gn:admin3_code":"2B5",
    "gn:admin4_code":"2B153",
    "gn:asciiname":"Parma",
    "gn:country_code":"FR",
    "gn:dem":874,
    "gn:feature_class":"P",
    "gn:feature_code":"PPL",
    "gn:name":"Parma",
    "gn:population":0,
    "gn:timezone":"Europe/Paris",
    "iso:country":"FR",
    "wof:name":"Parma",
    "wof:placetype":"locality"
},
  "geometry": {"coordinates":[8.7376,42.34372000000001],"type":"Point"}
}