{
  "type": "Feature",
  "properties": {
    "gn:admin1_code":"53",
    "gn:admin2_code":"22",
    "gn:admin3_code":"222",
    "gn:admin4_code":"22202",
    "gn:asciiname":"Penvenn",
    "gn:country_code":"FR",
    "gn:dem":130,
    "gn:feature_class":"P",
    "gn:feature_code":"PPL",
    "gn:name":"Penvenn",
    "gn:population":0,
    "gn:timezone":"Europe/Paris",
    "iso:country":"FR",
    "wof:name":"Penvenn",
    "wof:placetype":"locality"
},
  "geometry": {"coordinates":[-3.51667,48.25],"type":"Point"}
}