{
  "type": "Feature",
  "properties": {
    "gn:admin1_code":"84",
    "gn:admin2_code":"69",
    "gn:admin3_code":"691",
    "gn:admin4_code":"69220.0",
    "gn:asciiname":"Le Noyer",
    "gn:country_code":"FR",
    "gn:dem":614,
    "gn:feature_class":"P",
    "gn:feature_code":"PPL",
    "gn:name":"Le Noyer",
    "gn:population":0,
    "gn:timezone":"Europe/Paris",
    "iso:country":"FR",
    "wof:name":"Le Noyer",
    "wof:placetype":"locality"
},
  "geometry": {"coordinates":[4.44594,45.72362],"type":"Point"}
}