{
  "type": "Feature",
  "properties": {
    "gn:admin1_code":"84",
    "gn:admin2_code":"69",
    "gn:admin3_code":"691",
    "gn:admin4_code":"69220.0",
    "gn:asciiname":"Le Noyer",
    "gn:country_code":"FR",
    "gn:dem":614,
    "gn:feature_class":"P",
    "gn:feature_code":"PPL",
    "gn:name":"Le Noyer",
    "gn:population":0,
    "gn:timezone":"Europe/Paris",
    "iso:country":"FR",
    "name:ceb_x_preferred":[
        "Le Noyer"
    ],
    "name:deu_x_preferred":[
        "Le Noyer"
    ],
    "name:fra_x_preferred":[
        "Le Noyer"
    ],
    "name:ita_x_preferred":[
        "Le Noyer"
    ],
    "name:nds_x_preferred":[
        "Le Noyer"
    ],
    "name:nld_x_preferred":[
        "Le Noyer"
    ],
    "name:pms_x_preferred":[
        "Le Noyer"
    ],
    "name:pol_x_preferred":[
        "Le Noyer"
    ],
    "name:por_x_preferred":[
        "Le Noyer"
    ],
    "name:rus_x_preferred":[
        "\u041b\u0435-\u041d\u0443\u0430\u0439\u0435"
    ],
    "name:slk_x_preferred":[
        "Le Noyer"
    ],
    "name:spa_x_preferred":[
        "Le Noyer"
    ],
    "name:swe_x_preferred":[
        "Le Noyer"
    ],
    "name:ukr_x_preferred":[
        "\u041b\u0435-\u041d\u0443\u0430\u0454"
    ],
    "wof:name":"Le Noyer",
    "wof:placetype":"locality"
},
  "geometry": {"coordinates":[4.44594,45.72362],"type":"Point"}
}