{
  "type": "Feature",
  "properties": {
    "gn:admin1_code":"75",
    "gn:admin2_code":"24",
    "gn:admin3_code":"244",
    "gn:admin4_code":"24488",
    "gn:asciiname":"Thomas",
    "gn:country_code":"FR",
    "gn:dem":274,
    "gn:feature_class":"P",
    "gn:feature_code":"PPL",
    "gn:name":"Thomas",
    "gn:population":0,
    "gn:timezone":"Europe/Paris",
    "iso:country":"FR",
    "wof:name":"Thomas",
    "wof:placetype":"locality"
},
  "geometry": {"coordinates":[1.14141,44.69855],"type":"Point"}
}