{
  "type": "Feature",
  "properties": {
    "gn:admin1_code":"94",
    "gn:admin2_code":"2A",
    "gn:admin3_code":"2A1",
    "gn:admin4_code":"2A228",
    "gn:asciiname":"Ghiatone",
    "gn:country_code":"FR",
    "gn:dem":13,
    "gn:feature_class":"P",
    "gn:feature_code":"PPL",
    "gn:name":"Ghiatone",
    "gn:population":0,
    "gn:timezone":"Europe/Paris",
    "iso:country":"FR",
    "wof:name":"Ghiatone",
    "wof:placetype":"locality"
},
  "geometry": {"coordinates":[8.77194,41.83944],"type":"Point"}
}