{
  "type": "Feature",
  "properties": {
    "gn:admin1_code":"27",
    "gn:admin2_code":"89",
    "gn:admin3_code":"891",
    "gn:admin4_code":"89283",
    "gn:asciiname":"Chastenay",
    "gn:country_code":"FR",
    "gn:dem":259,
    "gn:feature_class":"P",
    "gn:feature_code":"PPL",
    "gn:name":"Chastenay",
    "gn:population":0,
    "gn:timezone":"Europe/Paris",
    "iso:country":"FR",
    "wof:name":"Chastenay",
    "wof:placetype":"locality"
},
  "geometry": {"coordinates":[3.38325,47.65505],"type":"Point"}
}