{
  "type": "Feature",
  "properties": {
    "gn:admin1_code":"84",
    "gn:admin2_code":"15",
    "gn:admin3_code":"152",
    "gn:admin4_code":"15038",
    "gn:asciiname":"Embort",
    "gn:country_code":"FR",
    "gn:dem":545,
    "gn:feature_class":"P",
    "gn:feature_code":"PPL",
    "gn:name":"Embort",
    "gn:population":0,
    "gn:timezone":"Europe/Paris",
    "iso:country":"FR",
    "wof:name":"Embort",
    "wof:placetype":"locality"
},
  "geometry": {"coordinates":[2.62618,45.37096],"type":"Point"}
}