{
  "type": "Feature",
  "properties": {
    "gn:admin1_code":"52",
    "gn:admin2_code":"72",
    "gn:admin3_code":"722",
    "gn:admin4_code":"72353",
    "gn:asciiname":"Grand-Morville",
    "gn:country_code":"FR",
    "gn:dem":192,
    "gn:feature_class":"P",
    "gn:feature_code":"PPL",
    "gn:name":"Grand-Morvill\u00e9",
    "gn:population":0,
    "gn:timezone":"Europe/Paris",
    "iso:country":"FR",
    "wof:name":"Grand-Morville",
    "wof:placetype":"locality"
},
  "geometry": {"coordinates":[0.76789,48.17471],"type":"Point"}
}