{
  "type": "Feature",
  "properties": {
    "gn:admin1_code":"52",
    "gn:admin2_code":"44",
    "gn:admin3_code":"443",
    "gn:admin4_code":"44080",
    "gn:asciiname":"La Barriais",
    "gn:country_code":"FR",
    "gn:dem":7,
    "gn:feature_class":"P",
    "gn:feature_code":"PPL",
    "gn:name":"La Barriais",
    "gn:population":0,
    "gn:timezone":"Europe/Paris",
    "iso:country":"FR",
    "wof:name":"La Barriais",
    "wof:placetype":"locality"
},
  "geometry": {"coordinates":[-1.94822,47.31084],"type":"Point"}
}