{
  "type": "Feature",
  "properties": {
    "gn:admin1_code":"75",
    "gn:admin2_code":"24",
    "gn:admin3_code":"241",
    "gn:admin4_code":"24257",
    "gn:asciiname":"Labarde",
    "gn:country_code":"FR",
    "gn:dem":185,
    "gn:feature_class":"P",
    "gn:feature_code":"PPL",
    "gn:name":"Labarde",
    "gn:population":0,
    "gn:timezone":"Europe/Paris",
    "iso:country":"FR",
    "name:bug_x_preferred":[
        "Labarde"
    ],
    "name:cat_x_preferred":[
        "La Barda"
    ],
    "name:ceb_x_preferred":[
        "Labarde"
    ],
    "name:deu_x_preferred":[
        "Labarde"
    ],
    "name:eus_x_preferred":[
        "Labarde"
    ],
    "name:fra_x_preferred":[
        "Labarde"
    ],
    "name:hun_x_preferred":[
        "Labarde"
    ],
    "name:ind_x_preferred":[
        "Labarde"
    ],
    "name:ita_x_preferred":[
        "Labarde"
    ],
    "name:kaz_x_preferred":[
        "\u041b\u0430\u0431\u0430\u0440\u0434"
    ],
    "name:lat_x_preferred":[
        "Labarde"
    ],
    "name:mlg_x_preferred":[
        "Labarde"
    ],
    "name:msa_x_preferred":[
        "Labarde"
    ],
    "name:nld_x_preferred":[
        "Labarde"
    ],
    "name:oci_x_preferred":[
        "La Barda"
    ],
    "name:pms_x_preferred":[
        "Labarde"
    ],
    "name:pol_x_preferred":[
        "Labarde"
    ],
    "name:por_x_preferred":[
        "Labarde"
    ],
    "name:ron_x_preferred":[
        "Labarde"
    ],
    "name:slk_x_preferred":[
        "Labarde"
    ],
    "name:spa_x_preferred":[
        "Labarde"
    ],
    "name:swe_x_preferred":[
        "Labarde"
    ],
    "name:ukr_x_preferred":[
        "\u041b\u0430\u0431\u0430\u0440\u0434"
    ],
    "name:urd_x_preferred":[
        "\u0644\u0627\u0628\u0627\u0631\u0688\u06cc"
    ],
    "name:uzb_x_preferred":[
        "Labarde"
    ],
    "name:vie_x_preferred":[
        "Labarde"
    ],
    "name:vol_x_preferred":[
        "Labarde"
    ],
    "name:war_x_preferred":[
        "Labarde"
    ],
    "name:zho_x_preferred":[
        "\u62c9\u5df4\u5c14\u5fb7"
    ],
    "wof:name":"Labarde",
    "wof:placetype":"locality"
},
  "geometry": {"coordinates":[0.87636,44.70353],"type":"Point"}
}