{
  "type": "Feature",
  "properties": {
    "gn:admin1_code":"75",
    "gn:admin2_code":"24",
    "gn:admin3_code":"241",
    "gn:admin4_code":"24257",
    "gn:asciiname":"Labarde",
    "gn:country_code":"FR",
    "gn:dem":185,
    "gn:feature_class":"P",
    "gn:feature_code":"PPL",
    "gn:name":"Labarde",
    "gn:population":0,
    "gn:timezone":"Europe/Paris",
    "iso:country":"FR",
    "wof:name":"Labarde",
    "wof:placetype":"locality"
},
  "geometry": {"coordinates":[0.87636,44.70353],"type":"Point"}
}