{
  "type": "Feature",
  "properties": {
    "gn:admin1_code":"84",
    "gn:admin2_code":"38",
    "gn:admin3_code":"382",
    "gn:admin4_code":"38343",
    "gn:asciiname":"Avaux",
    "gn:country_code":"FR",
    "gn:dem":256,
    "gn:feature_class":"P",
    "gn:feature_code":"PPL",
    "gn:name":"Avaux",
    "gn:population":0,
    "gn:timezone":"Europe/Paris",
    "iso:country":"FR",
    "name:bug_x_preferred":[
        "Avaux"
    ],
    "name:cat_x_preferred":[
        "Avaux"
    ],
    "name:ceb_x_preferred":[
        "Avaux"
    ],
    "name:ces_x_preferred":[
        "Avaux"
    ],
    "name:deu_x_preferred":[
        "Avaux"
    ],
    "name:eus_x_preferred":[
        "Avaux"
    ],
    "name:fra_x_preferred":[
        "Avaux"
    ],
    "name:hun_x_preferred":[
        "Avaux"
    ],
    "name:hye_x_preferred":[
        "\u0531\u057e\u0578"
    ],
    "name:ita_x_preferred":[
        "Avaux"
    ],
    "name:lat_x_preferred":[
        "Avaux"
    ],
    "name:ltz_x_preferred":[
        "Avaux"
    ],
    "name:mlg_x_preferred":[
        "Avaux"
    ],
    "name:msa_x_preferred":[
        "Avaux"
    ],
    "name:nld_x_preferred":[
        "Avaux"
    ],
    "name:oci_x_preferred":[
        "Avaux"
    ],
    "name:pam_x_preferred":[
        "Avaux"
    ],
    "name:pms_x_preferred":[
        "Avaux"
    ],
    "name:pol_x_preferred":[
        "Avaux"
    ],
    "name:por_x_preferred":[
        "Avaux"
    ],
    "name:ron_x_preferred":[
        "Avaux"
    ],
    "name:rus_x_preferred":[
        "\u0410\u0432\u043e"
    ],
    "name:slk_x_preferred":[
        "Avaux"
    ],
    "name:spa_x_preferred":[
        "Avaux"
    ],
    "name:sqi_x_preferred":[
        "Avaux"
    ],
    "name:srp_x_preferred":[
        "\u0410\u0432\u043e"
    ],
    "name:swe_x_preferred":[
        "Avaux"
    ],
    "name:ukr_x_preferred":[
        "\u0410\u0432\u043e"
    ],
    "name:vie_x_preferred":[
        "Avaux"
    ],
    "name:vol_x_preferred":[
        "Avaux"
    ],
    "name:war_x_preferred":[
        "Avaux"
    ],
    "wof:name":"Avaux",
    "wof:placetype":"locality"
},
  "geometry": {"coordinates":[5.66475,45.55581],"type":"Point"}
}