{
  "type": "Feature",
  "properties": {
    "gn:admin1_code":"84",
    "gn:admin2_code":"38",
    "gn:admin3_code":"382",
    "gn:admin4_code":"38343",
    "gn:asciiname":"Avaux",
    "gn:country_code":"FR",
    "gn:dem":256,
    "gn:feature_class":"P",
    "gn:feature_code":"PPL",
    "gn:name":"Avaux",
    "gn:population":0,
    "gn:timezone":"Europe/Paris",
    "iso:country":"FR",
    "wof:name":"Avaux",
    "wof:placetype":"locality"
},
  "geometry": {"coordinates":[5.66475,45.55581],"type":"Point"}
}