{
  "type": "Feature",
  "properties": {
    "gn:admin1_code":"24",
    "gn:admin2_code":"18",
    "gn:admin3_code":"182",
    "gn:admin4_code":"18161",
    "gn:asciiname":"L'Ormenay",
    "gn:country_code":"FR",
    "gn:dem":209,
    "gn:feature_class":"P",
    "gn:feature_code":"PPL",
    "gn:name":"L\u2019Ormenay",
    "gn:population":0,
    "gn:timezone":"Europe/Paris",
    "iso:country":"FR",
    "wof:name":"L'Ormenay",
    "wof:placetype":"locality"
},
  "geometry": {"coordinates":[2.8008,46.78778],"type":"Point"}
}