{
  "type": "Feature",
  "properties": {
    "gn:admin1_code":"84",
    "gn:admin2_code":"63",
    "gn:admin3_code":"634",
    "gn:admin4_code":"63320",
    "gn:asciiname":"L'Eclause",
    "gn:country_code":"FR",
    "gn:dem":692,
    "gn:feature_class":"P",
    "gn:feature_code":"PPL",
    "gn:name":"L\u2019Eclause",
    "gn:population":0,
    "gn:timezone":"Europe/Paris",
    "iso:country":"FR",
    "wof:name":"L'Eclause",
    "wof:placetype":"locality"
},
  "geometry": {"coordinates":[2.51766,45.88069],"type":"Point"}
}