{
  "type": "Feature",
  "properties": {
    "gn:admin1_code":"53",
    "gn:admin2_code":"56",
    "gn:admin3_code":"562",
    "gn:admin4_code":"56100",
    "gn:asciiname":"Kerbescontez",
    "gn:country_code":"FR",
    "gn:dem":205,
    "gn:feature_class":"P",
    "gn:feature_code":"PPL",
    "gn:name":"Kerbescontez",
    "gn:population":0,
    "gn:timezone":"Europe/Paris",
    "iso:country":"FR",
    "wof:name":"Kerbescontez",
    "wof:placetype":"locality"
},
  "geometry": {"coordinates":[-3.49383,48.1475],"type":"Point"}
}