{
  "type": "Feature",
  "properties": {
    "gn:admin1_code":"84",
    "gn:admin2_code":"43",
    "gn:admin3_code":"431",
    "gn:admin4_code":"43125",
    "gn:asciiname":"Glizeneuve",
    "gn:country_code":"FR",
    "gn:dem":911,
    "gn:feature_class":"P",
    "gn:feature_code":"PPL",
    "gn:name":"Glizeneuve",
    "gn:population":0,
    "gn:timezone":"Europe/Paris",
    "iso:country":"FR",
    "wof:name":"Glizeneuve",
    "wof:placetype":"locality"
},
  "geometry": {"coordinates":[3.27144,45.21801],"type":"Point"}
}