{
  "type": "Feature",
  "properties": {
    "gn:admin1_code":"27",
    "gn:admin2_code":"58",
    "gn:admin3_code":"583",
    "gn:admin4_code":"58092",
    "gn:asciiname":"Menetreuille",
    "gn:country_code":"FR",
    "gn:dem":273,
    "gn:feature_class":"P",
    "gn:feature_code":"PPL",
    "gn:name":"Menetreuille",
    "gn:population":0,
    "gn:timezone":"Europe/Paris",
    "iso:country":"FR",
    "wof:name":"Menetreuille",
    "wof:placetype":"locality"
},
  "geometry": {"coordinates":[3.51265,47.13717000000001],"type":"Point"}
}