{
  "type": "Feature",
  "properties": {
    "gn:admin1_code":"75",
    "gn:admin2_code":"19",
    "gn:admin3_code":"191",
    "gn:admin4_code":"19117",
    "gn:asciiname":"Le Mas",
    "gn:country_code":"FR",
    "gn:dem":202,
    "gn:feature_class":"P",
    "gn:feature_code":"PPL",
    "gn:name":"Le Mas",
    "gn:population":0,
    "gn:timezone":"Europe/Paris",
    "iso:country":"FR",
    "wof:name":"Le Mas",
    "wof:placetype":"locality"
},
  "geometry": {"coordinates":[1.44293,45.09886],"type":"Point"}
}