{
  "type": "Feature",
  "properties": {
    "gn:admin1_code":"24",
    "gn:admin2_code":"18",
    "gn:admin3_code":"181",
    "gn:admin4_code":"18018",
    "gn:asciiname":"Le Grand Aubilly",
    "gn:country_code":"FR",
    "gn:dem":184,
    "gn:feature_class":"P",
    "gn:feature_code":"PPL",
    "gn:name":"Le Grand Aubilly",
    "gn:population":0,
    "gn:timezone":"Europe/Paris",
    "iso:country":"FR",
    "wof:name":"Le Grand Aubilly",
    "wof:placetype":"locality"
},
  "geometry": {"coordinates":[2.68367,47.02193],"type":"Point"}
}