{
  "type": "Feature",
  "properties": {
    "gn:admin1_code":"24",
    "gn:admin2_code":"28",
    "gn:admin3_code":"284",
    "gn:admin4_code":"28261",
    "gn:asciiname":"Le Saussay",
    "gn:country_code":"FR",
    "gn:dem":205,
    "gn:feature_class":"P",
    "gn:feature_code":"PPL",
    "gn:name":"Le Saussay",
    "gn:population":0,
    "gn:timezone":"Europe/Paris",
    "iso:country":"FR",
    "wof:name":"Le Saussay",
    "wof:placetype":"locality"
},
  "geometry": {"coordinates":[1.1278,48.30122],"type":"Point"}
}