{
  "type": "Feature",
  "properties": {
    "gn:country":"FR",
    "gn:fcode":"PPL",
    "gn:population":0,
    "iso:country":"FR",
    "name:als_x_preferred":[
        "B\u00e4renthal"
    ],
    "name:ceb_x_preferred":[
        "B\u00e4renthal"
    ],
    "name:deu_x_preferred":[
        "B\u00e4renthal"
    ],
    "name:epo_x_preferred":[
        "B\u00e4renthal"
    ],
    "name:eus_x_preferred":[
        "B\u00e4renthal"
    ],
    "name:fas_x_preferred":[
        "\u0628\u0631\u0646\u062a\u0627\u0644"
    ],
    "name:fra_x_preferred":[
        "B\u00e4renthal"
    ],
    "name:hun_x_preferred":[
        "B\u00e4renthal"
    ],
    "name:ita_x_preferred":[
        "B\u00e4renthal"
    ],
    "name:kaz_x_preferred":[
        "\u0411\u0435\u0440\u0435\u043d\u0442\u0430\u043b\u044c"
    ],
    "name:kir_x_preferred":[
        "\u0411\u0435\u0440\u0435\u043d\u0442\u0430\u043b\u044c"
    ],
    "name:lat_x_preferred":[
        "B\u00e4renthal"
    ],
    "name:lmo_x_preferred":[
        "B\u00e4renthal"
    ],
    "name:msa_x_preferred":[
        "B\u00e4renthal"
    ],
    "name:nld_x_preferred":[
        "B\u00e4renthal"
    ],
    "name:pol_x_preferred":[
        "B\u00e4renthal"
    ],
    "name:por_x_preferred":[
        "B\u00e4renthal"
    ],
    "name:ron_x_preferred":[
        "B\u00e4renthal"
    ],
    "name:rus_x_preferred":[
        "\u0411\u0435\u0440\u0435\u043d\u0442\u0430\u043b\u044c"
    ],
    "name:spa_x_preferred":[
        "B\u00e4renthal"
    ],
    "name:srp_x_preferred":[
        "\u0411\u0435\u0440\u0435\u043d\u0442\u0430\u043b"
    ],
    "name:und_x_variant":[
        "Marienthal"
    ],
    "name:uzb_x_preferred":[
        "B\u00e4renthal"
    ],
    "name:vie_x_preferred":[
        "B\u00e4renthal"
    ],
    "name:vol_x_preferred":[
        "B\u00e4renthal"
    ],
    "name:war_x_preferred":[
        "B\u00e4renthal"
    ],
    "name:zho_x_preferred":[
        "\u8d1d\u4f26\u5854\u5c14"
    ],
    "qs_pg:aaroncc":"FR",
    "qs_pg:gn_country":"FR",
    "qs_pg:gn_fcode":"PPL",
    "qs_pg:gn_pop":0,
    "qs_pg:name":"B\u00e4renthal",
    "qs_pg:name_adm0":"Deutschland",
    "qs_pg:name_adm1":"Baden-W\u00fcrttemberg",
    "qs_pg:photos":216,
    "qs_pg:photos_1k":44,
    "qs_pg:photos_9k":1,
    "qs_pg:photos_9r":4,
    "qs_pg:photos_all":216,
    "qs_pg:photos_sr":4,
    "qs_pg:pop_sr":0,
    "qs_pg:qs_pg_placetype":"locality",
    "qs_pg:qs_pg_placetype_gp":"Town",
    "qs_pg:woe_adm0":23424829,
    "woe:adm0_id":23424829,
    "woe:name_adm0":"Deutschland",
    "woe:name_adm1":"Baden-W\u00fcrttemberg",
    "woe:placetype":"Town",
    "wof:name":"B\u00e4renthal",
    "wof:placetype":"neighbourhood"
},
  "geometry": {"coordinates":[7.81623,48.78059],"type":"Point"}
}