{
  "type": "Feature",
  "properties": {
    "frgov:code_epci":"200067437",
    "frgov:insee_arr":"3",
    "frgov:insee_com":"04122",
    "frgov:insee_dep":"04",
    "frgov:insee_reg":"93",
    "frgov:nom_com":"Mirabeau",
    "frgov:nom_com_m":"MIRABEAU",
    "frgov:nom_dep":"ALPES-DE-HAUTE-PROVENCE",
    "frgov:nom_reg":"PROVENCE-ALPES-COTE D'AZUR",
    "frgov:statut":"Commune simple",
    "gn:admin1_code":"93",
    "gn:admin2_code":"04",
    "gn:admin3_code":"043",
    "gn:admin4_code":"04122",
    "gn:asciiname":"Mirabeau",
    "gn:country_code":"FR",
    "gn:dem":628,
    "gn:feature_class":"P",
    "gn:feature_code":"PPL",
    "gn:name":"Mirabeau",
    "gn:population":0,
    "gn:timezone":"Europe/Paris",
    "iso:country":"FR",
    "name:cat_x_preferred":[
        "Mirabeau"
    ],
    "name:cat_x_variant":[
        "Mirabeau"
    ],
    "name:ceb_x_preferred":[
        "Mirabeau"
    ],
    "name:deu_x_preferred":[
        "Mirabeau"
    ],
    "name:est_x_preferred":[
        "Mirabeau"
    ],
    "name:fra_x_preferred":[
        "Mirabeau"
    ],
    "name:ita_x_preferred":[
        "Mirabeau"
    ],
    "name:jpn_x_preferred":[
        "\u30df\u30e9\u30dc\u30fc"
    ],
    "name:nds_x_preferred":[
        "Mirabeau"
    ],
    "name:nld_x_preferred":[
        "Mirabeau"
    ],
    "name:oci_x_preferred":[
        "Mirab\u00e8u"
    ],
    "name:pms_x_preferred":[
        "Mirabeau"
    ],
    "name:pol_x_preferred":[
        "Mirabeau"
    ],
    "name:por_x_preferred":[
        "Mirabeau"
    ],
    "name:rus_x_preferred":[
        "\u041c\u0438\u0440\u0430\u0431\u043e"
    ],
    "name:slk_x_preferred":[
        "Mirabeau"
    ],
    "name:spa_x_preferred":[
        "Mirabeau"
    ],
    "name:swe_x_preferred":[
        "Mirabeau"
    ],
    "name:ukr_x_preferred":[
        "\u041c\u0456\u0440\u0430\u0431\u043e"
    ],
    "name:und_x_variant":[
        "Mirateaus",
        "Mirabeau"
    ],
    "name:zho_x_preferred":[
        "\u7c73\u62c9\u535a"
    ],
    "qs:a0":"France",
    "qs:a1":"ALPES-DE-HAUTE-PROVENCE",
    "qs:a1_lc":"04",
    "qs:a1r":"PROVENCE-ALPES-COTE D'AZUR",
    "qs:a1r_lc":"93",
    "qs:a2_lc":"31",
    "qs:a2r_lc":"3",
    "qs:adm0":"France",
    "qs:adm0_a3":"FRA",
    "qs:la":"MIRABEAU",
    "qs:la_lc":"04122",
    "qs:level":"localadmin",
    "qs:type":"Commune simple",
    "wof:coterminous":[
        404425995
    ],
    "wof:name":"Mirabeau",
    "wof:placetype":"locality",
    "wof:placetype_local":"Commune simple"
},
  "geometry": {"coordinates":[6.08944,44.06368],"type":"Point"}
}