{
  "type": "Feature",
  "properties": {
    "gn:admin1_code":"93",
    "gn:admin2_code":"04",
    "gn:admin3_code":"043",
    "gn:admin4_code":"04122",
    "gn:asciiname":"Mirabeau",
    "gn:country_code":"FR",
    "gn:dem":628,
    "gn:feature_class":"P",
    "gn:feature_code":"PPL",
    "gn:name":"Mirabeau",
    "gn:population":0,
    "gn:timezone":"Europe/Paris",
    "iso:country":"FR",
    "name:und_x_variant":[
        "Mirateaus",
        "Mirabeau"
    ],
    "wof:name":"Mirabeau",
    "wof:placetype":"locality"
},
  "geometry": {"coordinates":[6.08944,44.06368],"type":"Point"}
}