{
  "type": "Feature",
  "properties": {
    "gn:admin1_code":"93",
    "gn:admin2_code":"04",
    "gn:admin3_code":"043",
    "gn:admin4_code":"04122",
    "gn:asciiname":"Mirabeau",
    "gn:country_code":"FR",
    "gn:dem":628,
    "gn:feature_class":"P",
    "gn:feature_code":"PPL",
    "gn:name":"Mirabeau",
    "gn:population":0,
    "gn:timezone":"Europe/Paris",
    "iso:country":"FR",
    "name:cat_x_preferred":[
        "Mirabeau"
    ],
    "name:ceb_x_preferred":[
        "Mirabeau"
    ],
    "name:deu_x_preferred":[
        "Mirabeau"
    ],
    "name:est_x_preferred":[
        "Mirabeau"
    ],
    "name:fra_x_preferred":[
        "Mirabeau"
    ],
    "name:ita_x_preferred":[
        "Mirabeau"
    ],
    "name:jpn_x_preferred":[
        "\u30df\u30e9\u30dc\u30fc"
    ],
    "name:nds_x_preferred":[
        "Mirabeau"
    ],
    "name:nld_x_preferred":[
        "Mirabeau"
    ],
    "name:pms_x_preferred":[
        "Mirabeau"
    ],
    "name:pol_x_preferred":[
        "Mirabeau"
    ],
    "name:por_x_preferred":[
        "Mirabeau"
    ],
    "name:rus_x_preferred":[
        "\u041c\u0438\u0440\u0430\u0431\u043e"
    ],
    "name:slk_x_preferred":[
        "Mirabeau"
    ],
    "name:spa_x_preferred":[
        "Mirabeau"
    ],
    "name:swe_x_preferred":[
        "Mirabeau"
    ],
    "name:ukr_x_preferred":[
        "\u041c\u0456\u0440\u0430\u0431\u043e"
    ],
    "name:und_x_variant":[
        "Mirateaus"
    ],
    "wof:name":"Mirabeau",
    "wof:placetype":"locality"
},
  "geometry": {"coordinates":[6.08944,44.06368],"type":"Point"}
}