{
  "type": "Feature",
  "properties": {
    "gn:admin1_code":"27",
    "gn:admin2_code":"89",
    "gn:admin3_code":"891",
    "gn:admin4_code":"89273",
    "gn:asciiname":"Les Dubois",
    "gn:country_code":"FR",
    "gn:dem":267,
    "gn:feature_class":"P",
    "gn:feature_code":"PPL",
    "gn:name":"Les Dubois",
    "gn:population":0,
    "gn:timezone":"Europe/Paris",
    "iso:country":"FR",
    "wof:name":"Les Dubois",
    "wof:placetype":"locality"
},
  "geometry": {"coordinates":[3.21262,47.59393],"type":"Point"}
}