{
  "type": "Feature",
  "properties": {
    "gn:admin1_code":"75",
    "gn:admin2_code":"87",
    "gn:admin3_code":"873",
    "gn:admin4_code":"87078",
    "gn:asciiname":"Villemonteil",
    "gn:country_code":"FR",
    "gn:dem":287,
    "gn:feature_class":"P",
    "gn:feature_code":"PPL",
    "gn:name":"Villemonteil",
    "gn:population":0,
    "gn:timezone":"Europe/Paris",
    "iso:country":"FR",
    "wof:name":"Villemonteil",
    "wof:placetype":"locality"
},
  "geometry": {"coordinates":[0.96277,45.96858],"type":"Point"}
}