{
  "type": "Feature",
  "properties": {
    "gn:admin1_code":"94",
    "gn:admin2_code":"2A",
    "gn:admin3_code":"2A4",
    "gn:admin4_code":"2A163",
    "gn:asciiname":"Giannuccio",
    "gn:country_code":"FR",
    "gn:dem":486,
    "gn:feature_class":"P",
    "gn:feature_code":"PPL",
    "gn:name":"Giannuccio",
    "gn:population":0,
    "gn:timezone":"Europe/Paris",
    "iso:country":"FR",
    "name:und_x_variant":[
        "Giannaccio",
        "Giannuccio"
    ],
    "wof:name":"Giannuccio",
    "wof:placetype":"locality"
},
  "geometry": {"coordinates":[9.04044,41.56495],"type":"Point"}
}