{
  "type": "Feature",
  "properties": {
    "gn:admin1_code":"24",
    "gn:admin2_code":"18",
    "gn:admin3_code":"182",
    "gn:admin4_code":"18231",
    "gn:asciiname":"Les Vivons",
    "gn:country_code":"FR",
    "gn:dem":195,
    "gn:feature_class":"P",
    "gn:feature_code":"PPL",
    "gn:name":"Les Vivons",
    "gn:population":0,
    "gn:timezone":"Europe/Paris",
    "iso:country":"FR",
    "name:und_x_variant":[
        "Vivons",
        "Les Vivons"
    ],
    "wof:name":"Les Vivons",
    "wof:placetype":"locality"
},
  "geometry": {"coordinates":[2.59283,46.73799],"type":"Point"}
}