{
  "type": "Feature",
  "properties": {
    "gn:admin1_code":"53",
    "gn:admin2_code":"56",
    "gn:admin3_code":"561",
    "gn:admin4_code":"56121",
    "gn:asciiname":"Kerolay",
    "gn:country_code":"FR",
    "gn:dem":9,
    "gn:feature_class":"P",
    "gn:feature_code":"PPL",
    "gn:name":"Kerolay",
    "gn:population":0,
    "gn:timezone":"Europe/Paris",
    "iso:country":"FR",
    "wof:name":"Kerolay",
    "wof:placetype":"locality"
},
  "geometry": {"coordinates":[-3.37944,47.73517],"type":"Point"}
}