{
  "type": "Feature",
  "properties": {
    "gn:admin1_code":"44",
    "gn:admin2_code":"57",
    "gn:admin3_code":"577",
    "gn:admin4_code":"57026",
    "gn:asciiname":"Belmach",
    "gn:country_code":"FR",
    "gn:dem":222,
    "gn:feature_class":"P",
    "gn:feature_code":"PPL",
    "gn:name":"Belmach",
    "gn:population":0,
    "gn:timezone":"Europe/Paris",
    "iso:country":"FR",
    "wof:name":"Belmach",
    "wof:placetype":"locality"
},
  "geometry": {"coordinates":[6.39519,49.45857],"type":"Point"}
}