{
  "type": "Feature",
  "properties": {
    "gn:admin1_code":"75",
    "gn:admin2_code":"19",
    "gn:admin3_code":"192",
    "gn:admin4_code":"19034",
    "gn:asciiname":"Belpeuch",
    "gn:country_code":"FR",
    "gn:dem":489,
    "gn:feature_class":"P",
    "gn:feature_code":"PPL",
    "gn:name":"Belpeuch",
    "gn:population":0,
    "gn:timezone":"Europe/Paris",
    "iso:country":"FR",
    "wof:name":"Belpeuch",
    "wof:placetype":"locality"
},
  "geometry": {"coordinates":[1.93622,44.97825],"type":"Point"}
}