{
  "type": "Feature",
  "properties": {
    "gn:admin1_code":"24",
    "gn:admin2_code":"37",
    "gn:admin3_code":"371",
    "gn:admin4_code":"37089",
    "gn:asciiname":"La Motte",
    "gn:country_code":"FR",
    "gn:dem":33,
    "gn:feature_class":"P",
    "gn:feature_code":"PPL",
    "gn:name":"La Motte",
    "gn:population":0,
    "gn:timezone":"Europe/Paris",
    "iso:country":"FR",
    "wof:name":"La Motte",
    "wof:placetype":"locality"
},
  "geometry": {"coordinates":[0.28537,47.15115],"type":"Point"}
}