{
  "type": "Feature",
  "properties": {
    "gn:admin1_code":"75",
    "gn:admin2_code":"87",
    "gn:admin3_code":"872",
    "gn:admin4_code":"87094",
    "gn:asciiname":"La Cote",
    "gn:country_code":"FR",
    "gn:dem":325,
    "gn:feature_class":"P",
    "gn:feature_code":"PPL",
    "gn:name":"La C\u00f4te",
    "gn:population":0,
    "gn:timezone":"Europe/Paris",
    "iso:country":"FR",
    "wof:name":"La Cote",
    "wof:placetype":"locality"
},
  "geometry": {"coordinates":[1.16667,45.71667],"type":"Point"}
}