{
  "type": "Feature",
  "properties": {
    "gn:admin1_code":"84",
    "gn:admin2_code":"38",
    "gn:admin3_code":"381",
    "gn:admin4_code":"38456",
    "gn:asciiname":"L'Echarenne",
    "gn:country_code":"FR",
    "gn:dem":726,
    "gn:feature_class":"P",
    "gn:feature_code":"PPL",
    "gn:name":"L\u2019\u00c9charenne",
    "gn:population":0,
    "gn:timezone":"Europe/Paris",
    "iso:country":"FR",
    "wof:name":"L'Echarenne",
    "wof:placetype":"locality"
},
  "geometry": {"coordinates":[5.8224,44.85696],"type":"Point"}
}