{
  "type": "Feature",
  "properties": {
    "gn:admin1_code":"53",
    "gn:admin2_code":"35",
    "gn:admin3_code":"351",
    "gn:admin4_code":"35303",
    "gn:asciiname":"Saint-Ouen-la-Rouerie",
    "gn:cc2":"FR",
    "gn:country_code":"FR",
    "gn:dem":47,
    "gn:feature_class":"P",
    "gn:feature_code":"PPL",
    "gn:name":"Saint-Ouen-la-Rou\u00ebrie",
    "gn:population":0,
    "gn:timezone":"Europe/Paris",
    "iso:country":"FR",
    "name:und_x_variant":[
        "Saint-Ouen"
    ],
    "wof:name":"Saint-Ouen-la-Rouerie",
    "wof:placetype":"locality"
},
  "geometry": {"coordinates":[-1.43333,48.46667],"type":"Point"}
}