{
  "type": "Feature",
  "properties": {
    "frgov:code_epci":"248500589",
    "frgov:insee_arr":"2",
    "frgov:insee_com":"85285",
    "frgov:insee_dep":"85",
    "frgov:insee_reg":"52",
    "frgov:nom_com":"Le Tablier",
    "frgov:nom_com_m":"LE TABLIER",
    "frgov:nom_dep":"VENDEE",
    "frgov:nom_reg":"PAYS DE LA LOIRE",
    "frgov:statut":"Commune simple",
    "gn:admin1_code":"52",
    "gn:admin2_code":"85",
    "gn:admin3_code":"852",
    "gn:admin4_code":"85285",
    "gn:asciiname":"Le Tablier",
    "gn:country_code":"FR",
    "gn:dem":52,
    "gn:feature_class":"P",
    "gn:feature_code":"PPL",
    "gn:name":"Le Tablier",
    "gn:population":0,
    "gn:timezone":"Europe/Paris",
    "iso:country":"FR",
    "name:cat_x_preferred":[
        "Le Tablier"
    ],
    "name:ceb_x_preferred":[
        "Le Tablier"
    ],
    "name:deu_x_preferred":[
        "Le Tablier"
    ],
    "name:eus_x_preferred":[
        "Le Tablier"
    ],
    "name:fra_x_preferred":[
        "Le Tablier"
    ],
    "name:hun_x_preferred":[
        "Le Tablier"
    ],
    "name:ita_x_preferred":[
        "Le Tablier"
    ],
    "name:msa_x_preferred":[
        "Le Tablier"
    ],
    "name:nld_x_preferred":[
        "Le Tablier"
    ],
    "name:oci_x_preferred":[
        "Le Tablier"
    ],
    "name:pms_x_preferred":[
        "Le Tablier"
    ],
    "name:pol_x_preferred":[
        "Le Tablier"
    ],
    "name:por_x_preferred":[
        "Le Tablier"
    ],
    "name:ron_x_preferred":[
        "Le Tablier"
    ],
    "name:slk_x_preferred":[
        "Le Tablier"
    ],
    "name:spa_x_preferred":[
        "Le Tablier"
    ],
    "name:swe_x_preferred":[
        "Le Tablier"
    ],
    "name:ukr_x_preferred":[
        "\u041b\u0435-\u0422\u0430\u0431\u043b\u044c\u0454"
    ],
    "name:vie_x_preferred":[
        "Le Tablier"
    ],
    "name:vol_x_preferred":[
        "Le Tablier"
    ],
    "name:war_x_preferred":[
        "Le Tablier"
    ],
    "name:zho_x_preferred":[
        "\u83b1\u5854\u5e03\u5229\u8036"
    ],
    "qs:a0":"France",
    "qs:a1":"VENDEE",
    "qs:a1_lc":"85",
    "qs:a1r":"PAYS DE LA LOIRE",
    "qs:a1r_lc":"52",
    "qs:a2_lc":"31",
    "qs:a2r_lc":"2",
    "qs:adm0":"France",
    "qs:adm0_a3":"FRA",
    "qs:la":"LE TABLIER",
    "qs:la_lc":"85285",
    "qs:level":"localadmin",
    "qs:type":"Commune simple",
    "wof:coterminous":[
        404402035
    ],
    "wof:name":"Le Tablier",
    "wof:placetype":"locality",
    "wof:placetype_local":"Commune simple"
},
  "geometry": {"coordinates":[-1.34445,46.5755],"type":"Point"}
}