{
  "type": "Feature",
  "properties": {
    "gn:admin1_code":"76",
    "gn:admin2_code":"48",
    "gn:admin3_code":"481",
    "gn:admin4_code":"48075",
    "gn:asciiname":"Lonjagnes",
    "gn:country_code":"FR",
    "gn:dem":682,
    "gn:feature_class":"P",
    "gn:feature_code":"PPL",
    "gn:name":"Lonjagnes",
    "gn:population":0,
    "gn:timezone":"Europe/Paris",
    "iso:country":"FR",
    "wof:name":"Lonjagnes",
    "wof:placetype":"locality"
},
  "geometry": {"coordinates":[3.55536,44.39787000000001],"type":"Point"}
}