{
  "type": "Feature",
  "properties": {
    "gn:admin1_code":"53",
    "gn:admin2_code":"29",
    "gn:admin3_code":"291",
    "gn:admin4_code":"29160",
    "gn:asciiname":"Kerangueven",
    "gn:country_code":"FR",
    "gn:dem":84,
    "gn:feature_class":"P",
    "gn:feature_code":"PPL",
    "gn:name":"Kerangu\u00e9ven",
    "gn:population":0,
    "gn:timezone":"Europe/Paris",
    "iso:country":"FR",
    "wof:name":"Kerangueven",
    "wof:placetype":"locality"
},
  "geometry": {"coordinates":[-4.36967,48.51067000000001],"type":"Point"}
}