{
  "type": "Feature",
  "properties": {
    "gn:admin1_code":"93",
    "gn:admin2_code":"05",
    "gn:admin3_code":"052",
    "gn:admin4_code":"05118",
    "gn:asciiname":"Le Plan",
    "gn:country_code":"FR",
    "gn:dem":544,
    "gn:feature_class":"P",
    "gn:feature_code":"PPL",
    "gn:name":"Le Plan",
    "gn:population":0,
    "gn:timezone":"Europe/Paris",
    "iso:country":"FR",
    "name:arg_x_preferred":[
        "Le Plan"
    ],
    "name:bug_x_preferred":[
        "Le Plan"
    ],
    "name:cat_x_preferred":[
        "Le Plan"
    ],
    "name:ceb_x_preferred":[
        "Le Plan"
    ],
    "name:deu_x_preferred":[
        "Le Plan"
    ],
    "name:eus_x_preferred":[
        "Le Plan"
    ],
    "name:fra_x_preferred":[
        "Le Plan"
    ],
    "name:hun_x_preferred":[
        "Le Plan"
    ],
    "name:ita_x_preferred":[
        "Le Plan"
    ],
    "name:lat_x_preferred":[
        "Le Plan"
    ],
    "name:msa_x_preferred":[
        "Le Plan"
    ],
    "name:nld_x_preferred":[
        "Le Plan"
    ],
    "name:oci_x_preferred":[
        "Le Plan"
    ],
    "name:pol_x_preferred":[
        "Le Plan"
    ],
    "name:ron_x_preferred":[
        "Le Plan"
    ],
    "name:rus_x_preferred":[
        "\u041b\u0435-\u041f\u043b\u0430\u043d"
    ],
    "name:slk_x_preferred":[
        "Le Plan"
    ],
    "name:spa_x_preferred":[
        "Le Plan"
    ],
    "name:swe_x_preferred":[
        "Le Plan"
    ],
    "name:ukr_x_preferred":[
        "\u041b\u0435-\u041f\u043b\u0430\u043d"
    ],
    "name:vie_x_preferred":[
        "Le Plan"
    ],
    "name:war_x_preferred":[
        "Le Plan"
    ],
    "name:zho_x_preferred":[
        "\u52d2\u666e\u6717"
    ],
    "wof:name":"Le Plan",
    "wof:placetype":"locality"
},
  "geometry": {"coordinates":[5.81212,44.27453],"type":"Point"}
}