{
  "type": "Feature",
  "properties": {
    "gn:admin1_code":"52",
    "gn:admin2_code":"72",
    "gn:admin3_code":"722",
    "gn:admin4_code":"72267",
    "gn:asciiname":"Les Mousseries",
    "gn:country_code":"FR",
    "gn:dem":133,
    "gn:feature_class":"P",
    "gn:feature_code":"PPL",
    "gn:name":"Les Mousseries",
    "gn:population":0,
    "gn:timezone":"Europe/Paris",
    "iso:country":"FR",
    "wof:name":"Les Mousseries",
    "wof:placetype":"locality"
},
  "geometry": {"coordinates":[0.58844,48.18009],"type":"Point"}
}