{
  "type": "Feature",
  "properties": {
    "gn:admin1_code":"76",
    "gn:admin2_code":"66",
    "gn:admin3_code":"661",
    "gn:admin4_code":"66008",
    "gn:asciiname":"la Platja d'Argelers",
    "gn:cc2":"FR",
    "gn:country_code":"FR",
    "gn:dem":4,
    "gn:feature_class":"P",
    "gn:feature_code":"PPL",
    "gn:name":"la Platja d'Argelers",
    "gn:population":0,
    "gn:timezone":"Europe/Paris",
    "iso:country":"FR",
    "name:cat_x_preferred":[
        "la Platja d'Argelers"
    ],
    "name:fra_x_preferred":[
        "Argel\u00e8s Plage"
    ],
    "name:nld_x_preferred":[
        "Argel\u00e8s-Plage"
    ],
    "wof:name":"la Platja d'Argelers",
    "wof:placetype":"locality"
},
  "geometry": {"coordinates":[3.04424,42.55864],"type":"Point"}
}