{
  "type": "Feature",
  "properties": {
    "iso:country":"FR",
    "name:eng_x_preferred":[
        "Centre-Sud"
    ],
    "name:fra_x_preferred":[
        "Centre-Sud"
    ],
    "wof:name":"Centre-Sud",
    "wof:placetype":"neighbourhood"
},
  "geometry": {"coordinates":[2.41947961876462,48.86364182514976],"type":"Point"}
}