{
  "type": "Feature",
  "properties": {
    "gn:admin1_code":"84",
    "gn:admin2_code":"73",
    "gn:admin3_code":"732",
    "gn:admin4_code":"73107.0",
    "gn:asciiname":"Les Girouds",
    "gn:country_code":"FR",
    "gn:dem":1053,
    "gn:feature_class":"P",
    "gn:feature_code":"PPL",
    "gn:name":"Les Girouds",
    "gn:population":0,
    "gn:timezone":"Europe/Paris",
    "iso:country":"FR",
    "wof:name":"Les Girouds",
    "wof:placetype":"locality"
},
  "geometry": {"coordinates":[5.8849,45.47337],"type":"Point"}
}