{
  "type": "Feature",
  "properties": {
    "gn:admin1_code":"53",
    "gn:admin2_code":"22",
    "gn:admin3_code":"224",
    "gn:admin4_code":"22055",
    "gn:asciiname":"La Cour",
    "gn:country_code":"FR",
    "gn:dem":72,
    "gn:feature_class":"P",
    "gn:feature_code":"PPL",
    "gn:name":"La Cour",
    "gn:population":0,
    "gn:timezone":"Europe/Paris",
    "iso:country":"FR",
    "wof:name":"La Cour",
    "wof:placetype":"locality"
},
  "geometry": {"coordinates":[-2.83052,48.6216],"type":"Point"}
}