{
  "type": "Feature",
  "properties": {
    "gn:admin1_code":"44",
    "gn:admin2_code":"08",
    "gn:admin3_code":"081",
    "gn:admin4_code":"08469",
    "gn:asciiname":"La Cassine",
    "gn:country_code":"FR",
    "gn:dem":171,
    "gn:feature_class":"P",
    "gn:feature_code":"PPL",
    "gn:name":"La Cassine",
    "gn:population":0,
    "gn:timezone":"Europe/Paris",
    "iso:country":"FR",
    "wof:name":"La Cassine",
    "wof:placetype":"locality"
},
  "geometry": {"coordinates":[4.81381,49.58047],"type":"Point"}
}