{
  "type": "Feature",
  "properties": {
    "gn:admin1_code":"93",
    "gn:admin2_code":"04",
    "gn:admin3_code":"043",
    "gn:admin4_code":"04181",
    "gn:asciiname":"Les Cardaires",
    "gn:country_code":"FR",
    "gn:dem":656,
    "gn:feature_class":"P",
    "gn:feature_code":"PPL",
    "gn:name":"Les Cardaires",
    "gn:population":0,
    "gn:timezone":"Europe/Paris",
    "iso:country":"FR",
    "wof:name":"Les Cardaires",
    "wof:placetype":"locality"
},
  "geometry": {"coordinates":[6.13145,43.97148],"type":"Point"}
}