{
  "type": "Feature",
  "properties": {
    "gn:admin1_code":"53",
    "gn:admin2_code":"56",
    "gn:admin3_code":"561",
    "gn:admin4_code":"56121",
    "gn:asciiname":"Kerforn",
    "gn:country_code":"FR",
    "gn:dem":33,
    "gn:feature_class":"P",
    "gn:feature_code":"PPLL",
    "gn:name":"Kerforn",
    "gn:population":0,
    "gn:timezone":"Europe/Paris",
    "iso:country":"FR",
    "wof:name":"Kerforn",
    "wof:placetype":"locality"
},
  "geometry": {"coordinates":[-3.3882,47.75292],"type":"Point"}
}