{
  "type": "Feature",
  "properties": {
    "gn:admin1_code":"76",
    "gn:admin2_code":"46",
    "gn:admin3_code":"463",
    "gn:admin4_code":"46220",
    "gn:asciiname":"Terregaye",
    "gn:country_code":"FR",
    "gn:dem":111,
    "gn:feature_class":"P",
    "gn:feature_code":"PPL",
    "gn:name":"Terregaye",
    "gn:population":0,
    "gn:timezone":"Europe/Paris",
    "iso:country":"FR",
    "name:und_x_variant":[
        "Terregaie",
        "Terregaye"
    ],
    "wof:name":"Terregaye",
    "wof:placetype":"locality"
},
  "geometry": {"coordinates":[1.49835,44.86151],"type":"Point"}
}