{
  "type": "Feature",
  "properties": {
    "gn:admin1_code":"32",
    "gn:admin2_code":"62",
    "gn:admin3_code":"626",
    "gn:admin4_code":"62307",
    "gn:asciiname":"Haute Escalles",
    "gn:country_code":"FR",
    "gn:dem":58,
    "gn:feature_class":"P",
    "gn:feature_code":"PPL",
    "gn:name":"Haute Escalles",
    "gn:population":0,
    "gn:timezone":"Europe/Paris",
    "iso:country":"FR",
    "wof:name":"Haute Escalles",
    "wof:placetype":"locality"
},
  "geometry": {"coordinates":[1.72444,50.91305],"type":"Point"}
}