{
  "type": "Feature",
  "properties": {
    "gn:admin1_code":"84",
    "gn:admin2_code":"03",
    "gn:admin3_code":"031",
    "gn:admin4_code":"3047.0",
    "gn:asciiname":"Chancot",
    "gn:country_code":"FR",
    "gn:dem":509,
    "gn:feature_class":"P",
    "gn:feature_code":"PPL",
    "gn:name":"Chancot",
    "gn:population":0,
    "gn:timezone":"Europe/Paris",
    "iso:country":"FR",
    "wof:name":"Chancot",
    "wof:placetype":"locality"
},
  "geometry": {"coordinates":[2.74194,46.23605],"type":"Point"}
}