{
  "type": "Feature",
  "properties": {
    "gn:admin1_code":"27",
    "gn:admin2_code":"71",
    "gn:admin3_code":"711",
    "gn:admin4_code":"71390",
    "gn:asciiname":"La Coudraye",
    "gn:country_code":"FR",
    "gn:dem":366,
    "gn:feature_class":"P",
    "gn:feature_code":"PPL",
    "gn:name":"La Coudraye",
    "gn:population":0,
    "gn:timezone":"Europe/Paris",
    "iso:country":"FR",
    "wof:name":"La Coudraye",
    "wof:placetype":"locality"
},
  "geometry": {"coordinates":[4.26417,46.71595],"type":"Point"}
}