{
  "type": "Feature",
  "properties": {
    "iso:country":"FR",
    "name:eng_x_preferred":[
        "Joinville-le-Haut"
    ],
    "name:fra_x_preferred":[
        "Joinville-le-Haut"
    ],
    "wof:name":"Joinville-le-Haut",
    "wof:placetype":"neighbourhood"
},
  "geometry": {"coordinates":[2.46655607714961,48.81730698435189],"type":"Point"}
}