{
  "type": "Feature",
  "properties": {
    "gn:admin1_code":"84",
    "gn:admin2_code":"42",
    "gn:admin3_code":"422",
    "gn:admin4_code":"42338.0",
    "gn:asciiname":"Cret d'Aiguilly",
    "gn:country_code":"FR",
    "gn:dem":326,
    "gn:feature_class":"P",
    "gn:feature_code":"PPL",
    "gn:name":"Cret d\u2019Aiguilly",
    "gn:population":0,
    "gn:timezone":"Europe/Paris",
    "iso:country":"FR",
    "wof:name":"Cret d'Aiguilly",
    "wof:placetype":"locality"
},
  "geometry": {"coordinates":[4.13913,46.07273],"type":"Point"}
}