{
  "type": "Feature",
  "properties": {
    "gn:admin1_code":"53",
    "gn:admin2_code":"56",
    "gn:admin3_code":"561",
    "gn:admin4_code":"56118",
    "gn:asciiname":"Sterbouest",
    "gn:country_code":"FR",
    "gn:dem":1,
    "gn:feature_class":"P",
    "gn:feature_code":"PPLL",
    "gn:name":"Sterbouest",
    "gn:population":0,
    "gn:timezone":"Europe/Paris",
    "iso:country":"FR",
    "wof:name":"Sterbouest",
    "wof:placetype":"locality"
},
  "geometry": {"coordinates":[-3.31449,47.74248],"type":"Point"}
}