{
  "type": "Feature",
  "properties": {
    "gn:admin1_code":"75",
    "gn:admin2_code":"24",
    "gn:admin3_code":"244",
    "gn:admin4_code":"24547",
    "gn:asciiname":"Flourgnac",
    "gn:country_code":"FR",
    "gn:dem":257,
    "gn:feature_class":"P",
    "gn:feature_code":"PPL",
    "gn:name":"Flourgnac",
    "gn:population":0,
    "gn:timezone":"Europe/Paris",
    "iso:country":"FR",
    "wof:name":"Flourgnac",
    "wof:placetype":"locality"
},
  "geometry": {"coordinates":[1.31327,45.10592000000001],"type":"Point"}
}