{
  "type": "Feature",
  "properties": {
    "gn:admin1_code":"94",
    "gn:admin2_code":"2B",
    "gn:admin3_code":"2B2",
    "gn:admin4_code":"2B033",
    "gn:asciiname":"Saint Joseph",
    "gn:country_code":"FR",
    "gn:dem":54,
    "gn:feature_class":"P",
    "gn:feature_code":"PPL",
    "gn:name":"Saint Joseph",
    "gn:population":0,
    "gn:timezone":"Europe/Paris",
    "iso:country":"FR",
    "wof:name":"Saint Joseph",
    "wof:placetype":"locality"
},
  "geometry": {"coordinates":[9.44583,42.69167],"type":"Point"}
}