{
  "type": "Feature",
  "properties": {
    "frgov:code_epci":"200040764",
    "frgov:insee_arr":"4",
    "frgov:insee_com":"2A139",
    "frgov:insee_dep":"2A",
    "frgov:insee_reg":"94",
    "frgov:nom_com":"Lecci",
    "frgov:nom_com_m":"LECCI",
    "frgov:nom_dep":"CORSE-DU-SUD",
    "frgov:nom_reg":"CORSE",
    "frgov:statut":"Commune simple",
    "gn:admin1_code":"94",
    "gn:admin2_code":"2A",
    "gn:admin3_code":"2A4",
    "gn:admin4_code":"2A139",
    "gn:asciiname":"Lecci",
    "gn:country_code":"FR",
    "gn:dem":87,
    "gn:feature_class":"P",
    "gn:feature_code":"PPL",
    "gn:name":"Lecci",
    "gn:population":0,
    "gn:timezone":"Europe/Paris",
    "iso:country":"FR",
    "name:cat_x_preferred":[
        "Lecci"
    ],
    "name:ceb_x_preferred":[
        "Lecci"
    ],
    "name:cos_x_preferred":[
        "I Licci"
    ],
    "name:deu_x_preferred":[
        "Lecci"
    ],
    "name:eus_x_preferred":[
        "Lecci"
    ],
    "name:fra_x_preferred":[
        "Lecci"
    ],
    "name:hun_x_preferred":[
        "Lecci"
    ],
    "name:hye_x_preferred":[
        "\u053c\u0565\u0579\u056b"
    ],
    "name:ind_x_preferred":[
        "Lecci"
    ],
    "name:ita_x_preferred":[
        "Lecci"
    ],
    "name:jpn_x_preferred":[
        "\u30ec\u30af\u30b7"
    ],
    "name:kaz_x_preferred":[
        "\u041b\u0435\u0447\u0447\u0438"
    ],
    "name:lat_x_preferred":[
        "Lecci"
    ],
    "name:lmo_x_preferred":[
        "Lecci"
    ],
    "name:msa_x_preferred":[
        "Lecci"
    ],
    "name:nld_x_preferred":[
        "Lecci"
    ],
    "name:nor_x_preferred":[
        "Lecci"
    ],
    "name:oci_x_preferred":[
        "Lecci"
    ],
    "name:pol_x_preferred":[
        "Lecci"
    ],
    "name:por_x_preferred":[
        "Lecci"
    ],
    "name:rus_x_preferred":[
        "\u041b\u0435\u0447\u0447\u0438"
    ],
    "name:slk_x_preferred":[
        "Lecci"
    ],
    "name:slv_x_preferred":[
        "Lecci"
    ],
    "name:spa_x_preferred":[
        "Lecci"
    ],
    "name:swe_x_preferred":[
        "Lecci"
    ],
    "name:ukr_x_preferred":[
        "\u041b\u0435\u0447\u0447\u0456"
    ],
    "name:vie_x_preferred":[
        "Lecci"
    ],
    "name:vol_x_preferred":[
        "Lecci"
    ],
    "name:war_x_preferred":[
        "Lecci"
    ],
    "qs:a0":"France",
    "qs:a1":"CORSE-DU-SUD",
    "qs:a1_lc":"2A",
    "qs:a1r":"CORSE",
    "qs:a1r_lc":"94",
    "qs:a2_lc":"40",
    "qs:a2r_lc":"4",
    "qs:adm0":"France",
    "qs:adm0_a3":"FRA",
    "qs:la":"LECCI",
    "qs:la_lc":"2A139",
    "qs:level":"localadmin",
    "qs:type":"Commune simple",
    "wof:coterminous":[
        404405521
    ],
    "wof:name":"Lecci",
    "wof:placetype":"locality",
    "wof:placetype_local":"Commune simple"
},
  "geometry": {"coordinates":[9.31572,41.68009],"type":"Point"}
}