{
  "type": "Feature",
  "properties": {
    "gn:admin1_code":"75",
    "gn:admin2_code":"24",
    "gn:admin3_code":"243",
    "gn:admin4_code":"24032",
    "gn:asciiname":"Coutancias",
    "gn:country_code":"FR",
    "gn:dem":100,
    "gn:feature_class":"P",
    "gn:feature_code":"PPL",
    "gn:name":"Coutancias",
    "gn:population":0,
    "gn:timezone":"Europe/Paris",
    "iso:country":"FR",
    "wof:name":"Coutancias",
    "wof:placetype":"locality"
},
  "geometry": {"coordinates":[0.37252,45.12152],"type":"Point"}
}