{
  "type": "Feature",
  "properties": {
    "gn:admin1_code":"32",
    "gn:admin2_code":"62",
    "gn:admin3_code":"623",
    "gn:admin4_code":"62025",
    "gn:asciiname":"Raventhun",
    "gn:country_code":"FR",
    "gn:dem":55,
    "gn:feature_class":"P",
    "gn:feature_code":"PPL",
    "gn:name":"Raventhun",
    "gn:population":0,
    "gn:timezone":"Europe/Paris",
    "iso:country":"FR",
    "name:und_x_variant":[
        "Raventhum",
        "Raventhun"
    ],
    "wof:name":"Raventhun",
    "wof:placetype":"locality"
},
  "geometry": {"coordinates":[1.62759,50.81605],"type":"Point"}
}