{
  "type": "Feature",
  "properties": {
    "gn:admin1_code":"27",
    "gn:admin2_code":"58",
    "gn:admin3_code":"584",
    "gn:admin4_code":"58307",
    "gn:asciiname":"Le Lignou",
    "gn:country_code":"FR",
    "gn:dem":191,
    "gn:feature_class":"P",
    "gn:feature_code":"PPL",
    "gn:name":"Le Lignou",
    "gn:population":0,
    "gn:timezone":"Europe/Paris",
    "iso:country":"FR",
    "wof:name":"Le Lignou",
    "wof:placetype":"locality"
},
  "geometry": {"coordinates":[3.092,47.2918],"type":"Point"}
}