{
  "type": "Feature",
  "properties": {
    "gn:admin1_code":"24",
    "gn:admin2_code":"18",
    "gn:admin3_code":"181",
    "gn:admin4_code":"18117",
    "gn:asciiname":"Le Chezal-Bedu",
    "gn:country_code":"FR",
    "gn:dem":234,
    "gn:feature_class":"P",
    "gn:feature_code":"PPL",
    "gn:name":"Le Chezal-Bedu",
    "gn:population":0,
    "gn:timezone":"Europe/Paris",
    "iso:country":"FR",
    "name:und_x_variant":[
        "Chezal-Bedu",
        "Le Chezal-Bedu"
    ],
    "wof:name":"Le Chezal-Bedu",
    "wof:placetype":"locality"
},
  "geometry": {"coordinates":[2.63705,47.39952],"type":"Point"}
}