{
  "type": "Feature",
  "properties": {
    "gn:admin1_code":"84",
    "gn:admin2_code":"43",
    "gn:admin3_code":"432",
    "gn:admin4_code":"43257.0",
    "gn:asciiname":"Archaud",
    "gn:country_code":"FR",
    "gn:dem":1000,
    "gn:feature_class":"P",
    "gn:feature_code":"PPL",
    "gn:name":"Archaud",
    "gn:population":0,
    "gn:timezone":"Europe/Paris",
    "iso:country":"FR",
    "wof:name":"Archaud",
    "wof:placetype":"locality"
},
  "geometry": {"coordinates":[3.74653,45.03096],"type":"Point"}
}