{
  "type": "Feature",
  "properties": {
    "gn:admin1_code":"24",
    "gn:admin2_code":"36",
    "gn:admin3_code":"362",
    "gn:admin4_code":"36136.0",
    "gn:asciiname":"La Cote",
    "gn:country_code":"FR",
    "gn:dem":145,
    "gn:feature_class":"P",
    "gn:feature_code":"PPL",
    "gn:name":"La C\u00f4te",
    "gn:population":0,
    "gn:timezone":"Europe/Paris",
    "iso:country":"FR",
    "wof:name":"La Cote",
    "wof:placetype":"locality"
},
  "geometry": {"coordinates":[1.17866,46.93147],"type":"Point"}
}