{
  "type": "Feature",
  "properties": {
    "iso:country":"FR",
    "qs_pg:aaroncc":"FR",
    "qs_pg:name":"Le Mas-Rouch",
    "qs_pg:name_adm0":"France",
    "qs_pg:name_adm1":"Languedoc-Roussillon",
    "qs_pg:photos":95,
    "qs_pg:photos_1k":19,
    "qs_pg:photos_9k":1,
    "qs_pg:photos_9r":3,
    "qs_pg:photos_all":95,
    "qs_pg:photos_sr":3,
    "qs_pg:pop_sr":0,
    "qs_pg:qs_pg_placetype":"locality",
    "qs_pg:qs_pg_placetype_gp":"Town",
    "qs_pg:woe_adm0":23424819,
    "woe:adm0_id":23424819,
    "woe:name_adm0":"France",
    "woe:name_adm1":"Languedoc-Roussillon",
    "woe:placetype":"Town",
    "wof:name":"Le Mas-Rouch",
    "wof:placetype":"neighbourhood"
},
  "geometry": {"coordinates":[3.248347,44.309539],"type":"Point"}
}