{
  "type": "Feature",
  "properties": {
    "gn:admin1_code":"84",
    "gn:admin2_code":"73",
    "gn:admin3_code":"731",
    "gn:admin4_code":"73034",
    "gn:asciiname":"Le Bersend",
    "gn:country_code":"FR",
    "gn:dem":1125,
    "gn:feature_class":"P",
    "gn:feature_code":"PPL",
    "gn:name":"Le Bersend",
    "gn:population":0,
    "gn:timezone":"Europe/Paris",
    "iso:country":"FR",
    "name:und_x_variant":[
        "Bersend",
        "Le Bersend"
    ],
    "wof:name":"Le Bersend",
    "wof:placetype":"locality"
},
  "geometry": {"coordinates":[6.57831,45.7081],"type":"Point"}
}