{
  "type": "Feature",
  "properties": {
    "gn:admin1_code":"84",
    "gn:admin2_code":"07",
    "gn:admin3_code":"071",
    "gn:admin4_code":"07206",
    "gn:asciiname":"Espezonne",
    "gn:country_code":"FR",
    "gn:dem":1084,
    "gn:feature_class":"P",
    "gn:feature_code":"PPLL",
    "gn:name":"Espezonne",
    "gn:population":0,
    "gn:timezone":"Europe/Paris",
    "iso:country":"FR",
    "name:fra_x_preferred":[
        "Espezone"
    ],
    "wof:name":"Espezonne",
    "wof:placetype":"locality"
},
  "geometry": {"coordinates":[3.91294,44.73143],"type":"Point"}
}