{
  "type": "Feature",
  "properties": {
    "gn:admin1_code":"76",
    "gn:admin2_code":"09",
    "gn:admin3_code":"093",
    "gn:admin4_code":"09110",
    "gn:asciiname":"Encourtiech",
    "gn:country_code":"FR",
    "gn:dem":539,
    "gn:feature_class":"P",
    "gn:feature_code":"PPL",
    "gn:name":"Encourtiech",
    "gn:population":0,
    "gn:timezone":"Europe/Paris",
    "iso:country":"FR",
    "name:bug_x_preferred":[
        "Encourtiech"
    ],
    "name:cat_x_preferred":[
        "Encorti\u00e8th"
    ],
    "name:ceb_x_preferred":[
        "Encourtiech"
    ],
    "name:eus_x_preferred":[
        "Encourtiech"
    ],
    "name:fra_x_preferred":[
        "Encourtiech"
    ],
    "name:hun_x_preferred":[
        "Encourtiech"
    ],
    "name:hye_x_preferred":[
        "\u0531\u0576\u056f\u0578\u0582\u0580\u057f\u056b\u0565\u0577"
    ],
    "name:ita_x_preferred":[
        "Encourtiech"
    ],
    "name:lat_x_preferred":[
        "Encourtiech"
    ],
    "name:mlg_x_preferred":[
        "Encourtiech"
    ],
    "name:msa_x_preferred":[
        "Encourtiech"
    ],
    "name:nld_x_preferred":[
        "Encourtiech"
    ],
    "name:oci_x_preferred":[
        "Encorti\u00e8th"
    ],
    "name:pol_x_preferred":[
        "Encourtiech"
    ],
    "name:por_x_preferred":[
        "Encourtiech"
    ],
    "name:ron_x_preferred":[
        "Encourtiech"
    ],
    "name:rus_x_preferred":[
        "\u0410\u043d\u043a\u0443\u0440\u0442\u044c\u0435\u0448"
    ],
    "name:slk_x_preferred":[
        "Encourtiech"
    ],
    "name:spa_x_preferred":[
        "Encourtiech"
    ],
    "name:swe_x_preferred":[
        "Encourtiech"
    ],
    "name:ukr_x_preferred":[
        "\u0410\u043d\u043a\u0443\u0440\u0442\u044c\u0454\u0448"
    ],
    "name:vie_x_preferred":[
        "Encourtiech"
    ],
    "name:vol_x_preferred":[
        "Encourtiech"
    ],
    "name:war_x_preferred":[
        "Encourtiech"
    ],
    "name:zho_x_preferred":[
        "\u6602\u5e93\u5c14\u8482\u8036\u514b"
    ],
    "wof:name":"Encourtiech",
    "wof:placetype":"locality"
},
  "geometry": {"coordinates":[1.1825,42.9597],"type":"Point"}
}