{
  "type": "Feature",
  "properties": {
    "gn:admin1_code":"76",
    "gn:admin2_code":"09",
    "gn:admin3_code":"093",
    "gn:admin4_code":"09110",
    "gn:asciiname":"Encourtiech",
    "gn:country_code":"FR",
    "gn:dem":539,
    "gn:feature_class":"P",
    "gn:feature_code":"PPL",
    "gn:name":"Encourtiech",
    "gn:population":0,
    "gn:timezone":"Europe/Paris",
    "iso:country":"FR",
    "wof:name":"Encourtiech",
    "wof:placetype":"locality"
},
  "geometry": {"coordinates":[1.1825,42.9597],"type":"Point"}
}