{
  "type": "Feature",
  "properties": {
    "frgov:code_epci":"200067940",
    "frgov:insee_arr":"3",
    "frgov:insee_com":"09110",
    "frgov:insee_dep":"09",
    "frgov:insee_reg":"76",
    "frgov:nom_com":"Encourtiech",
    "frgov:nom_com_m":"ENCOURTIECH",
    "frgov:nom_dep":"ARIEGE",
    "frgov:nom_reg":"OCCITANIE",
    "frgov:statut":"Commune simple",
    "gn:admin1_code":"76",
    "gn:admin2_code":"09",
    "gn:admin3_code":"093",
    "gn:admin4_code":"09110",
    "gn:asciiname":"Encourtiech",
    "gn:country_code":"FR",
    "gn:dem":539,
    "gn:feature_class":"P",
    "gn:feature_code":"PPL",
    "gn:name":"Encourtiech",
    "gn:population":0,
    "gn:timezone":"Europe/Paris",
    "iso:country":"FR",
    "name:bug_x_preferred":[
        "Encourtiech"
    ],
    "name:cat_x_preferred":[
        "Encorti\u00e8th"
    ],
    "name:ceb_x_preferred":[
        "Encourtiech"
    ],
    "name:eus_x_preferred":[
        "Encourtiech"
    ],
    "name:fra_x_preferred":[
        "Encourtiech"
    ],
    "name:hun_x_preferred":[
        "Encourtiech"
    ],
    "name:hye_x_preferred":[
        "\u0531\u0576\u056f\u0578\u0582\u0580\u057f\u056b\u0565\u0577"
    ],
    "name:ita_x_preferred":[
        "Encourtiech"
    ],
    "name:lat_x_preferred":[
        "Encourtiech"
    ],
    "name:mlg_x_preferred":[
        "Encourtiech"
    ],
    "name:msa_x_preferred":[
        "Encourtiech"
    ],
    "name:nld_x_preferred":[
        "Encourtiech"
    ],
    "name:oci_x_preferred":[
        "Encorti\u00e8th"
    ],
    "name:pol_x_preferred":[
        "Encourtiech"
    ],
    "name:por_x_preferred":[
        "Encourtiech"
    ],
    "name:ron_x_preferred":[
        "Encourtiech"
    ],
    "name:rus_x_preferred":[
        "\u0410\u043d\u043a\u0443\u0440\u0442\u044c\u0435\u0448"
    ],
    "name:slk_x_preferred":[
        "Encourtiech"
    ],
    "name:spa_x_preferred":[
        "Encourtiech"
    ],
    "name:swe_x_preferred":[
        "Encourtiech"
    ],
    "name:ukr_x_preferred":[
        "\u0410\u043d\u043a\u0443\u0440\u0442\u044c\u0454\u0448"
    ],
    "name:vie_x_preferred":[
        "Encourtiech"
    ],
    "name:vol_x_preferred":[
        "Encourtiech"
    ],
    "name:war_x_preferred":[
        "Encourtiech"
    ],
    "name:zho_x_preferred":[
        "\u6602\u5e93\u5c14\u8482\u8036\u514b"
    ],
    "qs:a0":"France",
    "qs:a1":"ARIEGE",
    "qs:a1_lc":"09",
    "qs:a1r":"MIDI-PYRENEES",
    "qs:a1r_lc":"73",
    "qs:a2_lc":"15",
    "qs:a2r_lc":"3",
    "qs:adm0":"France",
    "qs:adm0_a3":"FRA",
    "qs:la":"ENCOURTIECH",
    "qs:la_lc":"09110",
    "qs:level":"localadmin",
    "qs:type":"Commune simple",
    "wof:coterminous":[
        404411129
    ],
    "wof:name":"Encourtiech",
    "wof:placetype":"locality",
    "wof:placetype_local":"Commune simple"
},
  "geometry": {"coordinates":[1.1825,42.9597],"type":"Point"}
}