{
  "type": "Feature",
  "properties": {
    "gn:admin1_code":"53",
    "gn:admin2_code":"35",
    "gn:admin3_code":"351",
    "gn:admin4_code":"35008",
    "gn:asciiname":"Le Petit Osse",
    "gn:country_code":"FR",
    "gn:dem":78,
    "gn:feature_class":"P",
    "gn:feature_code":"PPL",
    "gn:name":"Le Petit Oss\u00e9",
    "gn:population":0,
    "gn:timezone":"Europe/Paris",
    "iso:country":"FR",
    "wof:name":"Le Petit Osse",
    "wof:placetype":"locality"
},
  "geometry": {"coordinates":[-1.17966,47.95217],"type":"Point"}
}