{
  "type": "Feature",
  "properties": {
    "gn:admin1_code":"32",
    "gn:admin2_code":"62",
    "gn:admin3_code":"622",
    "gn:admin4_code":"62512",
    "gn:asciiname":"La Tirmande",
    "gn:country_code":"FR",
    "gn:dem":67,
    "gn:feature_class":"P",
    "gn:feature_code":"PPL",
    "gn:name":"La Tirmande",
    "gn:population":0,
    "gn:timezone":"Europe/Paris",
    "iso:country":"FR",
    "name:und_x_variant":[
        "La Tirmand",
        "La Tirmande"
    ],
    "wof:name":"La Tirmande",
    "wof:placetype":"locality"
},
  "geometry": {"coordinates":[2.33768,50.57019],"type":"Point"}
}