{
  "type": "Feature",
  "properties": {
    "gn:admin1_code":"93",
    "gn:admin2_code":"84",
    "gn:admin3_code":"843",
    "gn:admin4_code":"84031",
    "gn:asciiname":"La Proto",
    "gn:cc2":"FR",
    "gn:country_code":"FR",
    "gn:dem":80,
    "gn:feature_class":"P",
    "gn:feature_code":"PPL",
    "gn:name":"La Proto",
    "gn:population":0,
    "gn:timezone":"Europe/Paris",
    "iso:country":"FR",
    "name:und_x_variant":[
        "La Prate",
        "La Prato",
        "La Proto"
    ],
    "wof:name":"La Proto",
    "wof:placetype":"locality"
},
  "geometry": {"coordinates":[5.05,44.03333],"type":"Point"}
}