{
  "type": "Feature",
  "properties": {
    "gn:admin1_code":"75",
    "gn:admin2_code":"17",
    "gn:admin3_code":"173",
    "gn:admin4_code":"17300",
    "gn:asciiname":"Laleu",
    "gn:country_code":"FR",
    "gn:dem":12,
    "gn:feature_class":"P",
    "gn:feature_code":"PPL",
    "gn:name":"Laleu",
    "gn:population":0,
    "gn:timezone":"Europe/Paris",
    "iso:country":"FR",
    "name:ceb_x_preferred":[
        "Laleu"
    ],
    "name:deu_x_preferred":[
        "Laleu"
    ],
    "name:eus_x_preferred":[
        "Laleu"
    ],
    "name:fra_x_preferred":[
        "Laleu"
    ],
    "name:ita_x_preferred":[
        "Laleu"
    ],
    "name:nds_x_preferred":[
        "Laleu"
    ],
    "name:nld_x_preferred":[
        "Laleu"
    ],
    "name:pms_x_preferred":[
        "Laleu"
    ],
    "name:pol_x_preferred":[
        "Laleu"
    ],
    "name:por_x_preferred":[
        "Laleu"
    ],
    "name:rus_x_preferred":[
        "\u041b\u0430\u043b\u0435"
    ],
    "name:scn_x_preferred":[
        "Laleu"
    ],
    "name:slk_x_preferred":[
        "Laleu"
    ],
    "name:spa_x_preferred":[
        "Laleu"
    ],
    "name:swe_x_preferred":[
        "Laleu"
    ],
    "name:ukr_x_preferred":[
        "\u041b\u0430\u043b\u0435"
    ],
    "wof:name":"Laleu",
    "wof:placetype":"locality"
},
  "geometry": {"coordinates":[-1.20069,46.17068],"type":"Point"}
}