{
  "type": "Feature",
  "properties": {
    "gn:admin1_code":"44",
    "gn:admin2_code":"55",
    "gn:admin3_code":"553",
    "gn:admin4_code":"55060",
    "gn:asciiname":"Mont-Villers",
    "gn:country_code":"FR",
    "gn:dem":264,
    "gn:feature_class":"P",
    "gn:feature_code":"PPLL",
    "gn:name":"Mont-Villers",
    "gn:population":0,
    "gn:timezone":"Europe/Paris",
    "iso:country":"FR",
    "wof:name":"Mont-Villers",
    "wof:placetype":"locality"
},
  "geometry": {"coordinates":[5.56912,49.095],"type":"Point"}
}