{
  "type": "Feature",
  "properties": {
    "gn:admin1_code":"28",
    "gn:admin2_code":"76",
    "gn:admin3_code":"761",
    "gn:admin4_code":"76147",
    "gn:asciiname":"Vauchel",
    "gn:country_code":"FR",
    "gn:dem":221,
    "gn:feature_class":"P",
    "gn:feature_code":"PPL",
    "gn:name":"Vauchel",
    "gn:population":0,
    "gn:timezone":"Europe/Paris",
    "iso:country":"FR",
    "wof:name":"Vauchel",
    "wof:placetype":"locality"
},
  "geometry": {"coordinates":[1.34607,49.71845],"type":"Point"}
}