{
  "type": "Feature",
  "properties": {
    "gn:admin1_code":"52",
    "gn:admin2_code":"72",
    "gn:admin3_code":"722",
    "gn:admin4_code":"72276",
    "gn:asciiname":"Champaissant",
    "gn:country_code":"FR",
    "gn:dem":96,
    "gn:feature_class":"P",
    "gn:feature_code":"PPL",
    "gn:name":"Champaissant",
    "gn:population":0,
    "gn:timezone":"Europe/Paris",
    "iso:country":"FR",
    "wof:name":"Champaissant",
    "wof:placetype":"locality"
},
  "geometry": {"coordinates":[0.44687,48.27363],"type":"Point"}
}