{
  "type": "Feature",
  "properties": {
    "gn:admin1_code":"52",
    "gn:admin2_code":"44",
    "gn:admin3_code":"441",
    "gn:admin4_code":"44076",
    "gn:asciiname":"Trigouet",
    "gn:country_code":"FR",
    "gn:dem":29,
    "gn:feature_class":"P",
    "gn:feature_code":"PPL",
    "gn:name":"Trigouet",
    "gn:population":0,
    "gn:timezone":"Europe/Paris",
    "iso:country":"FR",
    "wof:name":"Trigouet",
    "wof:placetype":"locality"
},
  "geometry": {"coordinates":[-1.59476,47.64324000000001],"type":"Point"}
}