{
  "type": "Feature",
  "properties": {
    "gn:admin1_code":"44",
    "gn:admin2_code":"51",
    "gn:admin3_code":"515",
    "gn:admin4_code":"51397",
    "gn:asciiname":"Bournonville",
    "gn:country_code":"FR",
    "gn:dem":179,
    "gn:feature_class":"P",
    "gn:feature_code":"PPL",
    "gn:name":"Bournonville",
    "gn:population":0,
    "gn:timezone":"Europe/Paris",
    "iso:country":"FR",
    "wof:name":"Bournonville",
    "wof:placetype":"locality"
},
  "geometry": {"coordinates":[4.92091,48.9787],"type":"Point"}
}