{
  "type": "Feature",
  "properties": {
    "gn:admin1_code":"44",
    "gn:admin2_code":"67",
    "gn:admin3_code":"672",
    "gn:admin4_code":"67497",
    "gn:asciiname":"Niederaltdorf",
    "gn:country_code":"FR",
    "gn:dem":184,
    "gn:feature_class":"P",
    "gn:feature_code":"PPL",
    "gn:name":"Niederaltdorf",
    "gn:population":0,
    "gn:timezone":"Europe/Paris",
    "iso:country":"FR",
    "wof:name":"Niederaltdorf",
    "wof:placetype":"locality"
},
  "geometry": {"coordinates":[7.66103,48.81096],"type":"Point"}
}