{
  "type": "Feature",
  "properties": {
    "gn:admin1_code":"27",
    "gn:admin2_code":"89",
    "gn:admin3_code":"893",
    "gn:admin4_code":"89018.0",
    "gn:asciiname":"Palteau",
    "gn:country_code":"FR",
    "gn:dem":180,
    "gn:feature_class":"P",
    "gn:feature_code":"PPL",
    "gn:name":"Palteau",
    "gn:population":0,
    "gn:timezone":"Europe/Paris",
    "iso:country":"FR",
    "wof:name":"Palteau",
    "wof:placetype":"locality"
},
  "geometry": {"coordinates":[3.35,48.05],"type":"Point"}
}