{
  "type": "Feature",
  "properties": {
    "iso:country":"FR",
    "name:eng_x_preferred":[
        "Les Epinettes"
    ],
    "name:fra_x_preferred":[
        "Les Epinettes"
    ],
    "wof:name":"Les Epinettes",
    "wof:placetype":"neighbourhood"
},
  "geometry": {"coordinates":[2.26242380697912,48.81666825648256],"type":"Point"}
}