{
  "type": "Feature",
  "properties": {
    "gn:admin1_code":"76",
    "gn:admin2_code":"30",
    "gn:admin3_code":"301",
    "gn:admin4_code":"30275",
    "gn:asciiname":"Vacquieres",
    "gn:country_code":"FR",
    "gn:dem":170,
    "gn:feature_class":"P",
    "gn:feature_code":"PPL",
    "gn:name":"Vacqui\u00e8res",
    "gn:population":0,
    "gn:timezone":"Europe/Paris",
    "iso:country":"FR",
    "wof:name":"Vacquieres",
    "wof:placetype":"locality"
},
  "geometry": {"coordinates":[4.23634,44.09682],"type":"Point"}
}