{
  "type": "Feature",
  "properties": {
    "gn:admin1_code":"27",
    "gn:admin2_code":"39",
    "gn:admin3_code":"392",
    "gn:admin4_code":"39209.0",
    "gn:asciiname":"Laneria",
    "gn:country_code":"FR",
    "gn:dem":377,
    "gn:feature_class":"P",
    "gn:feature_code":"PPL",
    "gn:name":"Lan\u00e9ria",
    "gn:population":0,
    "gn:timezone":"Europe/Paris",
    "iso:country":"FR",
    "wof:name":"Laneria",
    "wof:placetype":"locality"
},
  "geometry": {"coordinates":[5.39806,46.37364],"type":"Point"}
}