{
  "type": "Feature",
  "properties": {
    "iso:country":"FR",
    "name:fra_x_preferred":[
        "La Varenne Saint-hilaire"
    ],
    "name:unk_x_variant":[
        "La Varenne Saint-hilaire"
    ],
    "qs:gn_adm0_cc":"FR",
    "qs:gn_fcode":"PPL",
    "qs:gn_local":6452032,
    "qs:gn_nam_loc":"St-Maur-des-Foss\u00e9s, \u00cele-de-France, FR",
    "qs:gn_namadm1":"A8",
    "qs:gn_name":"La Varenne-Saint-Hilaire",
    "qs:local_max":467,
    "qs:local_sum":467,
    "qs:localhoods":1,
    "qs:name":"La Varenne Saint-hilaire",
    "qs:name_adm0":"France",
    "qs:name_adm1":"\u00cele-de-France",
    "qs:name_adm2":"Val-de-Marne",
    "qs:name_lau":"St.-Maur-des-Foss\u00e9s",
    "qs:name_local":"St.-Maur-des-Foss\u00e9s",
    "qs:photo_max":128,
    "qs:photo_sum":467,
    "qs:placetype":"Suburb",
    "qs:quad_count":55,
    "qs:woe_adm0":23424819,
    "qs:woe_adm1":7153319,
    "qs:woe_adm2":12597151,
    "qs:woe_lau":12646768,
    "qs:woe_local":12646768,
    "qs:woe_ver":"7.10.0",
    "wof:lang":[
        "fre"
    ],
    "wof:name":"La Varenne Saint-hilaire",
    "wof:placetype":"neighbourhood"
},
  "geometry": {"coordinates":[2.510455,48.795279],"type":"Point"}
}