{
  "type": "Feature",
  "properties": {
    "iso:country":"FR",
    "name:eng_x_preferred":[
        "Lille-Saint-Sauveur"
    ],
    "name:fra_x_preferred":[
        "Lille-Saint-Sauveur"
    ],
    "wof:name":"Lille-Saint-Sauveur",
    "wof:placetype":"neighbourhood"
},
  "geometry": {"coordinates":[3.07353357134701,50.63112179078766],"type":"Point"}
}