{
  "type": "Feature",
  "properties": {
    "gn:admin1_code":"75",
    "gn:admin2_code":"19",
    "gn:admin3_code":"191",
    "gn:admin4_code":"19023",
    "gn:asciiname":"Puy de Noix",
    "gn:country_code":"FR",
    "gn:dem":530,
    "gn:feature_class":"P",
    "gn:feature_code":"PPL",
    "gn:name":"Puy de Noix",
    "gn:population":0,
    "gn:timezone":"Europe/Paris",
    "iso:country":"FR",
    "wof:name":"Puy de Noix",
    "wof:placetype":"locality"
},
  "geometry": {"coordinates":[1.76047,45.1473],"type":"Point"}
}