{
  "type": "Feature",
  "properties": {
    "gn:admin1_code":"75",
    "gn:admin2_code":"24",
    "gn:admin3_code":"242",
    "gn:admin4_code":"24198",
    "gn:asciiname":"Boulouneix",
    "gn:country_code":"FR",
    "gn:dem":140,
    "gn:feature_class":"P",
    "gn:feature_code":"PPL",
    "gn:name":"Boulouneix",
    "gn:population":0,
    "gn:timezone":"Europe/Paris",
    "iso:country":"FR",
    "wof:name":"Boulouneix",
    "wof:placetype":"locality"
},
  "geometry": {"coordinates":[0.58044,45.37856],"type":"Point"}
}