{
  "type": "Feature",
  "properties": {
    "gn:admin1_code":"93",
    "gn:admin2_code":"04",
    "gn:admin3_code":"042",
    "gn:admin4_code":"04240",
    "gn:asciiname":"Les Sagnes",
    "gn:country_code":"FR",
    "gn:dem":1659,
    "gn:feature_class":"P",
    "gn:feature_code":"PPL",
    "gn:name":"Les Sagnes",
    "gn:population":0,
    "gn:timezone":"Europe/Paris",
    "iso:country":"FR",
    "wof:name":"Les Sagnes",
    "wof:placetype":"locality"
},
  "geometry": {"coordinates":[6.5725,44.20387],"type":"Point"}
}