{
  "type": "Feature",
  "properties": {
    "gn:admin1_code":"76",
    "gn:admin2_code":"82",
    "gn:admin3_code":"822",
    "gn:admin4_code":"82174",
    "gn:asciiname":"Saint-Vincent-d'Autejac",
    "gn:country_code":"FR",
    "gn:dem":171,
    "gn:feature_class":"P",
    "gn:feature_code":"PPL",
    "gn:name":"Saint-Vincent-d\u2019Aut\u00e9jac",
    "gn:population":313,
    "gn:timezone":"Europe/Paris",
    "iso:country":"FR",
    "name:und_x_variant":[
        "Saint-Vincent"
    ],
    "wof:name":"Saint-Vincent-d'Autejac",
    "wof:placetype":"locality",
    "wof:population":313
},
  "geometry": {"coordinates":[1.47295,44.16226],"type":"Point"}
}