{
  "type": "Feature",
  "properties": {
    "gn:admin1_code":"24",
    "gn:admin2_code":"18",
    "gn:admin3_code":"182",
    "gn:admin4_code":"18252",
    "gn:asciiname":"Les Chets",
    "gn:country_code":"FR",
    "gn:dem":289,
    "gn:feature_class":"P",
    "gn:feature_code":"PPL",
    "gn:name":"Les Chets",
    "gn:population":0,
    "gn:timezone":"Europe/Paris",
    "iso:country":"FR",
    "wof:name":"Les Chets",
    "wof:placetype":"locality"
},
  "geometry": {"coordinates":[2.334,46.51333],"type":"Point"}
}