{
  "type": "Feature",
  "properties": {
    "gn:admin1_code":"75",
    "gn:admin2_code":"24",
    "gn:admin3_code":"243",
    "gn:admin4_code":"24417",
    "gn:asciiname":"Saint-Germain-des-Pres",
    "gn:country_code":"FR",
    "gn:dem":146,
    "gn:feature_class":"P",
    "gn:feature_code":"PPL",
    "gn:name":"Saint-Germain-des-Pr\u00e9s",
    "gn:population":499,
    "gn:timezone":"Europe/Paris",
    "iso:country":"FR",
    "name:und_x_variant":[
        "Saint-Germain",
        "Saint-Germain-des-Pr\u00e9s"
    ],
    "wof:name":"Saint-Germain-des-Pres",
    "wof:placetype":"locality",
    "wof:population":499
},
  "geometry": {"coordinates":[0.99091,45.3419],"type":"Point"}
}