{
  "type": "Feature",
  "properties": {
    "gn:admin1_code":"24",
    "gn:admin2_code":"18",
    "gn:admin3_code":"181",
    "gn:admin4_code":"18151",
    "gn:asciiname":"Boiteau",
    "gn:country_code":"FR",
    "gn:dem":251,
    "gn:feature_class":"P",
    "gn:feature_code":"PPL",
    "gn:name":"Boiteau",
    "gn:population":0,
    "gn:timezone":"Europe/Paris",
    "iso:country":"FR",
    "wof:name":"Boiteau",
    "wof:placetype":"locality"
},
  "geometry": {"coordinates":[2.66448,47.23828],"type":"Point"}
}