{
  "type": "Feature",
  "properties": {
    "gn:admin1_code":"93",
    "gn:admin2_code":"84",
    "gn:admin3_code":"841",
    "gn:admin4_code":"84114",
    "gn:asciiname":"Saint-Pantaleon",
    "gn:country_code":"FR",
    "gn:dem":210,
    "gn:feature_class":"P",
    "gn:feature_code":"PPL",
    "gn:name":"Saint-Pantal\u00e9on",
    "gn:population":189,
    "gn:timezone":"Europe/Paris",
    "iso:country":"FR",
    "name:und_x_variant":[
        "Saint-Pantal\u00e9on"
    ],
    "wof:name":"Saint-Pantaleon",
    "wof:placetype":"locality",
    "wof:population":189
},
  "geometry": {"coordinates":[5.21582,43.88064],"type":"Point"}
}