{
  "type": "Feature",
  "properties": {
    "frgov:code_epci":"200040624",
    "frgov:insee_arr":"1",
    "frgov:insee_com":"84114",
    "frgov:insee_dep":"84",
    "frgov:insee_reg":"93",
    "frgov:nom_com":"Saint-Pantal\u00e9on",
    "frgov:nom_com_m":"SAINT-PANTALEON",
    "frgov:nom_dep":"VAUCLUSE",
    "frgov:nom_reg":"PROVENCE-ALPES-COTE D'AZUR",
    "frgov:statut":"Commune simple",
    "gn:admin1_code":"93",
    "gn:admin2_code":"84",
    "gn:admin3_code":"841",
    "gn:admin4_code":"84114",
    "gn:asciiname":"Saint-Pantaleon",
    "gn:country_code":"FR",
    "gn:dem":210,
    "gn:feature_class":"P",
    "gn:feature_code":"PPL",
    "gn:name":"Saint-Pantal\u00e9on",
    "gn:population":189,
    "gn:timezone":"Europe/Paris",
    "iso:country":"FR",
    "name:fra_x_preferred":[
        "Saint-Pantal\u00e9on"
    ],
    "name:und_x_variant":[
        "Saint-Pantal\u00e9on"
    ],
    "qs:a0":"France",
    "qs:a1":"VAUCLUSE",
    "qs:a1_lc":"84",
    "qs:a1r":"PROVENCE-ALPES-COTE D'AZUR",
    "qs:a1r_lc":"93",
    "qs:a2_lc":"12",
    "qs:a2r_lc":"1",
    "qs:adm0":"France",
    "qs:adm0_a3":"FRA",
    "qs:la":"SAINT-PANTALEON",
    "qs:la_lc":"84114",
    "qs:level":"localadmin",
    "qs:type":"Commune simple",
    "wof:coterminous":[
        404399559
    ],
    "wof:name":"Saint-Pantaleon",
    "wof:placetype":"locality",
    "wof:placetype_local":"Commune simple",
    "wof:population":189
},
  "geometry": {"coordinates":[5.21582,43.88064],"type":"Point"}
}