{
  "type": "Feature",
  "properties": {
    "gn:admin1_code":"84",
    "gn:admin2_code":"38",
    "gn:admin3_code":"382",
    "gn:admin4_code":"38053",
    "gn:asciiname":"Les Charbonnieres",
    "gn:country_code":"FR",
    "gn:dem":285,
    "gn:feature_class":"P",
    "gn:feature_code":"PPL",
    "gn:name":"Les Charbonni\u00e8res",
    "gn:population":0,
    "gn:timezone":"Europe/Paris",
    "iso:country":"FR",
    "name:und_x_variant":[
        "Charbonni\u00e8res",
        "Les Charbonni\u00e8res"
    ],
    "wof:name":"Les Charbonnieres",
    "wof:placetype":"locality"
},
  "geometry": {"coordinates":[5.29162,45.61412],"type":"Point"}
}