{
  "type": "Feature",
  "properties": {
    "gn:admin1_code":"53",
    "gn:admin2_code":"29",
    "gn:admin3_code":"293",
    "gn:admin4_code":"29082",
    "gn:asciiname":"Goales",
    "gn:country_code":"FR",
    "gn:dem":14,
    "gn:feature_class":"P",
    "gn:feature_code":"PPL",
    "gn:name":"Goal\u00e9s",
    "gn:population":0,
    "gn:timezone":"Europe/Paris",
    "iso:country":"FR",
    "wof:name":"Goales",
    "wof:placetype":"locality"
},
  "geometry": {"coordinates":[-4.01023,48.75089000000001],"type":"Point"}
}