{
  "type": "Feature",
  "properties": {
    "gn:admin1_code":"28",
    "gn:admin2_code":"27",
    "gn:admin3_code":"271",
    "gn:admin4_code":"27213",
    "gn:asciiname":"Le Chesnay",
    "gn:country_code":"FR",
    "gn:dem":142,
    "gn:feature_class":"P",
    "gn:feature_code":"PPL",
    "gn:name":"Le Chesnay",
    "gn:population":0,
    "gn:timezone":"Europe/Paris",
    "iso:country":"FR",
    "name:azb_x_preferred":[
        "\u0644\u0648 \u0634\u0632\u0646\u0647"
    ],
    "name:bre_x_preferred":[
        "Le Chesnay"
    ],
    "name:bug_x_preferred":[
        "Le Chesnay"
    ],
    "name:cat_x_preferred":[
        "Le Chesnay"
    ],
    "name:ceb_x_preferred":[
        "Le Chesnay"
    ],
    "name:ces_x_preferred":[
        "Le Chesnay"
    ],
    "name:deu_x_preferred":[
        "Le Chesnay"
    ],
    "name:epo_x_preferred":[
        "Le Chesnay"
    ],
    "name:eus_x_preferred":[
        "Le Chesnay"
    ],
    "name:fas_x_preferred":[
        "\u0644\u0648 \u0634\u0632\u0646\u0647"
    ],
    "name:fra_x_preferred":[
        "Le Chesnay"
    ],
    "name:hun_x_preferred":[
        "Le Chesnay"
    ],
    "name:ind_x_preferred":[
        "Le Chesnay"
    ],
    "name:ita_x_preferred":[
        "Le Chesnay"
    ],
    "name:jpn_x_preferred":[
        "\u30eb\u30fb\u30b7\u30a7\u30cd"
    ],
    "name:kaz_x_preferred":[
        "\u041b\u0435-\u0428\u0435\u043d\u0435"
    ],
    "name:kor_x_preferred":[
        "\ub974\uc170\ub124"
    ],
    "name:lat_x_preferred":[
        "Le Chesnay"
    ],
    "name:msa_x_preferred":[
        "Le Chesnay"
    ],
    "name:mzn_x_preferred":[
        "\u0644\u0648 \u0634\u0632\u0646\u0647"
    ],
    "name:nld_x_preferred":[
        "Le Chesnay"
    ],
    "name:nor_x_preferred":[
        "Le Chesnay"
    ],
    "name:oci_x_preferred":[
        "Le Chesnay"
    ],
    "name:pms_x_preferred":[
        "Le Chesnay"
    ],
    "name:pol_x_preferred":[
        "Le Chesnay"
    ],
    "name:por_x_preferred":[
        "Le Chesnay"
    ],
    "name:ron_x_preferred":[
        "Le Chesnay"
    ],
    "name:rus_x_preferred":[
        "\u041b\u0435-\u0428\u0435\u043d\u0435"
    ],
    "name:slk_x_preferred":[
        "Le Chesnay"
    ],
    "name:slv_x_preferred":[
        "Le Chesnay"
    ],
    "name:spa_x_preferred":[
        "Le Chesnay"
    ],
    "name:srp_x_preferred":[
        "\u041b\u0435 \u0428\u0435\u043d\u0435"
    ],
    "name:swa_x_preferred":[
        "Le Chesnay"
    ],
    "name:swe_x_preferred":[
        "Le Chesnay"
    ],
    "name:tur_x_preferred":[
        "Le Chesnay"
    ],
    "name:ukr_x_preferred":[
        "\u041b\u0435-\u0428\u0435\u043d\u0435"
    ],
    "name:und_x_variant":[
        "Le Chesney"
    ],
    "name:vie_x_preferred":[
        "Le Chesnay"
    ],
    "name:vol_x_preferred":[
        "Le Chesnay"
    ],
    "name:war_x_preferred":[
        "Le Chesnay"
    ],
    "name:zho_x_preferred":[
        "\u52d2\u820d\u5948"
    ],
    "wof:name":"Le Chesnay",
    "wof:placetype":"locality"
},
  "geometry": {"coordinates":[1.54485,49.19089],"type":"Point"}
}