{
  "type": "Feature",
  "properties": {
    "gn:admin1_code":"28",
    "gn:admin2_code":"27",
    "gn:admin3_code":"271",
    "gn:admin4_code":"27213",
    "gn:asciiname":"Le Chesnay",
    "gn:country_code":"FR",
    "gn:dem":142,
    "gn:feature_class":"P",
    "gn:feature_code":"PPL",
    "gn:name":"Le Chesnay",
    "gn:population":0,
    "gn:timezone":"Europe/Paris",
    "iso:country":"FR",
    "name:und_x_variant":[
        "Le Chesney",
        "Le Chesnay"
    ],
    "wof:name":"Le Chesnay",
    "wof:placetype":"locality"
},
  "geometry": {"coordinates":[1.54485,49.19089],"type":"Point"}
}