{
  "type": "Feature",
  "properties": {
    "gn:admin1_code":"24",
    "gn:admin2_code":"45",
    "gn:admin3_code":"453",
    "gn:admin4_code":"45118",
    "gn:asciiname":"Le Noizement",
    "gn:country_code":"FR",
    "gn:dem":128,
    "gn:feature_class":"P",
    "gn:feature_code":"PPL",
    "gn:name":"Le Noizement",
    "gn:population":0,
    "gn:timezone":"Europe/Paris",
    "iso:country":"FR",
    "name:und_x_variant":[
        "Le Nuisement",
        "Le Noizement"
    ],
    "wof:name":"Le Noizement",
    "wof:placetype":"locality"
},
  "geometry": {"coordinates":[2.06166,48.12083],"type":"Point"}
}