{
  "type": "Feature",
  "properties": {
    "gn:admin1_code":"84",
    "gn:admin2_code":"63",
    "gn:admin3_code":"634",
    "gn:admin4_code":"63286",
    "gn:asciiname":"Bonneuil",
    "gn:country_code":"FR",
    "gn:dem":600,
    "gn:feature_class":"P",
    "gn:feature_code":"PPL",
    "gn:name":"Bonneuil",
    "gn:population":0,
    "gn:timezone":"Europe/Paris",
    "iso:country":"FR",
    "wof:name":"Bonneuil",
    "wof:placetype":"locality"
},
  "geometry": {"coordinates":[2.96927,46.10097],"type":"Point"}
}