{
  "type": "Feature",
  "properties": {
    "gn:admin1_code":"84",
    "gn:admin2_code":"63",
    "gn:admin3_code":"634",
    "gn:admin4_code":"63286",
    "gn:asciiname":"Bonneuil",
    "gn:country_code":"FR",
    "gn:dem":600,
    "gn:feature_class":"P",
    "gn:feature_code":"PPL",
    "gn:name":"Bonneuil",
    "gn:population":0,
    "gn:timezone":"Europe/Paris",
    "iso:country":"FR",
    "name:ceb_x_preferred":[
        "Bonneuil"
    ],
    "name:deu_x_preferred":[
        "Bonneuil"
    ],
    "name:fra_x_preferred":[
        "Bonneuil"
    ],
    "name:ita_x_preferred":[
        "Bonneuil"
    ],
    "name:nds_x_preferred":[
        "Bonneuil"
    ],
    "name:nld_x_preferred":[
        "Bonneuil"
    ],
    "name:pol_x_preferred":[
        "Bonneuil"
    ],
    "name:por_x_preferred":[
        "Bonneuil"
    ],
    "name:rus_x_preferred":[
        "\u0411\u043e\u043d\u043d\u0435\u0439"
    ],
    "name:slk_x_preferred":[
        "Bonneuil"
    ],
    "name:spa_x_preferred":[
        "Bonneuil"
    ],
    "name:srp_x_preferred":[
        "\u0411\u043e\u043d\u0435\u0458"
    ],
    "name:swe_x_preferred":[
        "Bonneuil"
    ],
    "name:ukr_x_preferred":[
        "\u0411\u043e\u043d\u043d\u0435\u0439"
    ],
    "wof:name":"Bonneuil",
    "wof:placetype":"locality"
},
  "geometry": {"coordinates":[2.96927,46.10097],"type":"Point"}
}