{
  "type": "Feature",
  "properties": {
    "gn:admin1_code":"44",
    "gn:admin2_code":"57",
    "gn:admin3_code":"573",
    "gn:admin4_code":"57262",
    "gn:asciiname":"Bertring",
    "gn:country_code":"FR",
    "gn:dem":263,
    "gn:feature_class":"P",
    "gn:feature_code":"PPL",
    "gn:name":"Bertring",
    "gn:population":0,
    "gn:timezone":"Europe/Paris",
    "iso:country":"FR",
    "wof:name":"Bertring",
    "wof:placetype":"locality"
},
  "geometry": {"coordinates":[6.72844,48.97292],"type":"Point"}
}