{
  "type": "Feature",
  "properties": {
    "gn:admin1_code":"53",
    "gn:admin2_code":"29",
    "gn:admin3_code":"292",
    "gn:admin4_code":"29162",
    "gn:asciiname":"Linlouet",
    "gn:country_code":"FR",
    "gn:dem":58,
    "gn:feature_class":"P",
    "gn:feature_code":"PPL",
    "gn:name":"Linlou\u00ebt",
    "gn:population":0,
    "gn:timezone":"Europe/Paris",
    "iso:country":"FR",
    "wof:name":"Linlouet",
    "wof:placetype":"locality"
},
  "geometry": {"coordinates":[-4.0045,48.2075],"type":"Point"}
}