{
  "type": "Feature",
  "properties": {
    "gn:admin1_code":"93",
    "gn:admin2_code":"04",
    "gn:admin3_code":"043",
    "gn:admin4_code":"04237",
    "gn:asciiname":"Le Haut Vernet",
    "gn:country_code":"FR",
    "gn:dem":1312,
    "gn:feature_class":"P",
    "gn:feature_code":"PPL",
    "gn:name":"Le Haut Vernet",
    "gn:population":0,
    "gn:timezone":"Europe/Paris",
    "iso:country":"FR",
    "wof:name":"Le Haut Vernet",
    "wof:placetype":"locality"
},
  "geometry": {"coordinates":[6.38291,44.26572],"type":"Point"}
}