{
  "type": "Feature",
  "properties": {
    "gn:admin1_code":"84",
    "gn:admin2_code":"15",
    "gn:admin3_code":"153",
    "gn:admin4_code":"15061.0",
    "gn:asciiname":"Collanges",
    "gn:country_code":"FR",
    "gn:dem":1042,
    "gn:feature_class":"P",
    "gn:feature_code":"PPL",
    "gn:name":"Collanges",
    "gn:population":0,
    "gn:timezone":"Europe/Paris",
    "iso:country":"FR",
    "wof:name":"Collanges",
    "wof:placetype":"locality"
},
  "geometry": {"coordinates":[2.8204,45.1628],"type":"Point"}
}