{
  "type": "Feature",
  "properties": {
    "gn:admin1_code":"93",
    "gn:admin2_code":"04",
    "gn:admin3_code":"043",
    "gn:admin4_code":"04204",
    "gn:asciiname":"La Melle",
    "gn:country_code":"FR",
    "gn:dem":974,
    "gn:feature_class":"P",
    "gn:feature_code":"PPL",
    "gn:name":"La Melle",
    "gn:population":0,
    "gn:timezone":"Europe/Paris",
    "iso:country":"FR",
    "wof:name":"La Melle",
    "wof:placetype":"locality"
},
  "geometry": {"coordinates":[6.38333,43.91667],"type":"Point"}
}