{
  "type": "Feature",
  "properties": {
    "gn:admin1_code":"84",
    "gn:admin2_code":"63",
    "gn:admin3_code":"632",
    "gn:admin4_code":"63205",
    "gn:asciiname":"Le Chatelet",
    "gn:country_code":"FR",
    "gn:dem":602,
    "gn:feature_class":"P",
    "gn:feature_code":"PPL",
    "gn:name":"Le Ch\u00e2telet",
    "gn:population":0,
    "gn:timezone":"Europe/Paris",
    "iso:country":"FR",
    "wof:name":"Le Chatelet",
    "wof:placetype":"locality"
},
  "geometry": {"coordinates":[3.35895,45.64463],"type":"Point"}
}