{
  "type": "Feature",
  "properties": {
    "gn:admin1_code":"53",
    "gn:admin2_code":"35",
    "gn:admin3_code":"354",
    "gn:admin4_code":"35263",
    "gn:asciiname":"Saint-Vincent",
    "gn:country_code":"FR",
    "gn:dem":29,
    "gn:elevation":"28.0",
    "gn:feature_class":"P",
    "gn:feature_code":"PPL",
    "gn:name":"Saint-Vincent",
    "gn:population":0,
    "gn:timezone":"Europe/Paris",
    "iso:country":"FR",
    "wof:name":"Saint-Vincent",
    "wof:placetype":"locality"
},
  "geometry": {"coordinates":[-1.95162,48.67317],"type":"Point"}
}