{
  "type": "Feature",
  "properties": {
    "gn:admin1_code":"53",
    "gn:admin2_code":"35",
    "gn:admin3_code":"352",
    "gn:admin4_code":"35139",
    "gn:asciiname":"La Caliorne",
    "gn:country_code":"FR",
    "gn:dem":44,
    "gn:feature_class":"P",
    "gn:feature_code":"PPL",
    "gn:name":"La Caliorne",
    "gn:population":0,
    "gn:timezone":"Europe/Paris",
    "iso:country":"FR",
    "wof:name":"La Caliorne",
    "wof:placetype":"locality"
},
  "geometry": {"coordinates":[-1.70064,47.9899],"type":"Point"}
}