{
  "type": "Feature",
  "properties": {
    "gn:admin1_code":"84",
    "gn:admin2_code":"63",
    "gn:admin3_code":"633",
    "gn:admin4_code":"63357",
    "gn:asciiname":"Bas Rouherent",
    "gn:country_code":"FR",
    "gn:dem":747,
    "gn:feature_class":"P",
    "gn:feature_code":"PPL",
    "gn:name":"Bas Rouherent",
    "gn:population":0,
    "gn:timezone":"Europe/Paris",
    "iso:country":"FR",
    "wof:name":"Bas Rouherent",
    "wof:placetype":"locality"
},
  "geometry": {"coordinates":[3.11933,45.47167],"type":"Point"}
}