{
  "type": "Feature",
  "properties": {
    "gn:admin1_code":"75",
    "gn:admin2_code":"47",
    "gn:admin3_code":"473",
    "gn:admin4_code":"47283",
    "gn:asciiname":"Fontauzel",
    "gn:country_code":"FR",
    "gn:dem":102,
    "gn:feature_class":"P",
    "gn:feature_code":"PPL",
    "gn:name":"Fontauzel",
    "gn:population":0,
    "gn:timezone":"Europe/Paris",
    "iso:country":"FR",
    "wof:name":"Fontauzel",
    "wof:placetype":"locality"
},
  "geometry": {"coordinates":[0.95589,44.46919000000001],"type":"Point"}
}