{
  "type": "Feature",
  "properties": {
    "gn:admin1_code":"75",
    "gn:admin2_code":"23",
    "gn:admin3_code":"232",
    "gn:admin4_code":"23064",
    "gn:asciiname":"Doulon",
    "gn:country_code":"FR",
    "gn:dem":405,
    "gn:feature_class":"P",
    "gn:feature_code":"PPL",
    "gn:name":"Doulon",
    "gn:population":0,
    "gn:timezone":"Europe/Paris",
    "iso:country":"FR",
    "wof:name":"Doulon",
    "wof:placetype":"locality"
},
  "geometry": {"coordinates":[2.10199,46.27489],"type":"Point"}
}