{
  "type": "Feature",
  "properties": {
    "gn:admin1_code":"53",
    "gn:admin2_code":"56",
    "gn:admin3_code":"561",
    "gn:admin4_code":"56152",
    "gn:asciiname":"Bordustard",
    "gn:country_code":"FR",
    "gn:dem":49,
    "gn:feature_class":"P",
    "gn:feature_code":"PPL",
    "gn:name":"Bordustard",
    "gn:population":0,
    "gn:timezone":"Europe/Paris",
    "iso:country":"FR",
    "name:und_x_variant":[
        "Bordustern",
        "Bordustard"
    ],
    "wof:name":"Bordustard",
    "wof:placetype":"locality"
},
  "geometry": {"coordinates":[-3.18302,47.34247],"type":"Point"}
}