{
  "type": "Feature",
  "properties": {
    "gn:admin1_code":"75",
    "gn:admin2_code":"24",
    "gn:admin3_code":"244",
    "gn:admin4_code":"24012",
    "gn:asciiname":"Maisons Selves",
    "gn:country_code":"FR",
    "gn:dem":202,
    "gn:feature_class":"P",
    "gn:feature_code":"PPL",
    "gn:name":"Maisons Selves",
    "gn:population":0,
    "gn:timezone":"Europe/Paris",
    "iso:country":"FR",
    "name:und_x_variant":[
        "Maison-Selves",
        "Maisons Selves"
    ],
    "wof:name":"Maisons Selves",
    "wof:placetype":"locality"
},
  "geometry": {"coordinates":[1.25993,45.01538],"type":"Point"}
}