{
  "type": "Feature",
  "properties": {
    "gn:admin1_code":"53",
    "gn:admin2_code":"29",
    "gn:admin3_code":"292",
    "gn:admin4_code":"29054",
    "gn:asciiname":"Ruguellou",
    "gn:cc2":"FR",
    "gn:country_code":"FR",
    "gn:dem":242,
    "gn:feature_class":"P",
    "gn:feature_code":"PPL",
    "gn:name":"Ruguellou",
    "gn:population":0,
    "gn:timezone":"Europe/Paris",
    "iso:country":"FR",
    "name:und_x_variant":[
        "Ruguellon",
        "Ruguellou"
    ],
    "wof:name":"Ruguellou",
    "wof:placetype":"locality"
},
  "geometry": {"coordinates":[-3.83333,48.38333],"type":"Point"}
}