{
  "type": "Feature",
  "properties": {
    "gn:admin1_code":"24",
    "gn:admin2_code":"18",
    "gn:admin3_code":"181",
    "gn:admin4_code":"18132.0",
    "gn:asciiname":"Asnins",
    "gn:country_code":"FR",
    "gn:dem":188,
    "gn:feature_class":"P",
    "gn:feature_code":"PPL",
    "gn:name":"Asnins",
    "gn:population":0,
    "gn:timezone":"Europe/Paris",
    "iso:country":"FR",
    "wof:name":"Asnins",
    "wof:placetype":"locality"
},
  "geometry": {"coordinates":[2.84496,47.15771],"type":"Point"}
}