{
  "type": "Feature",
  "properties": {
    "gn:admin1_code":"75",
    "gn:admin2_code":"33",
    "gn:admin3_code":"334",
    "gn:admin4_code":"33038",
    "gn:asciiname":"By",
    "gn:country_code":"FR",
    "gn:dem":8,
    "gn:feature_class":"P",
    "gn:feature_code":"PPL",
    "gn:name":"By",
    "gn:population":0,
    "gn:timezone":"Europe/Paris",
    "iso:country":"FR",
    "name:ceb_x_preferred":[
        "By"
    ],
    "name:swe_x_preferred":[
        "By"
    ],
    "wof:name":"By",
    "wof:placetype":"locality"
},
  "geometry": {"coordinates":[-0.86443,45.37302],"type":"Point"}
}