{
  "type": "Feature",
  "properties": {
    "gn:gn_country":"FR",
    "gn:gn_fcode":"PPL",
    "gn:gn_pop":80,
    "gn:population":80,
    "iso:country":"FR",
    "name:ceb_x_preferred":[
        "Fontanes-du-Causse"
    ],
    "name:deu_x_preferred":[
        "Fontanes-du-Causse"
    ],
    "name:eus_x_preferred":[
        "Fontanes-du-Causse"
    ],
    "name:fra_x_preferred":[
        "Fontanes-du-Causse"
    ],
    "name:hun_x_preferred":[
        "Fontanes-du-Causse"
    ],
    "name:ita_x_preferred":[
        "Fontanes-du-Causse"
    ],
    "name:lat_x_preferred":[
        "Fontanes-du-Causse"
    ],
    "name:msa_x_preferred":[
        "Fontanes-du-Causse"
    ],
    "name:nld_x_preferred":[
        "Fontanes-du-Causse"
    ],
    "name:pms_x_preferred":[
        "Fontanes-du-Causse"
    ],
    "name:pol_x_preferred":[
        "Fontanes-du-Causse"
    ],
    "name:por_x_preferred":[
        "Fontanes-du-Causse"
    ],
    "name:ron_x_preferred":[
        "Fontanes-du-Causse"
    ],
    "name:slk_x_preferred":[
        "Fontanes-du-Causse"
    ],
    "name:spa_x_preferred":[
        "Fontanes-du-Causse"
    ],
    "name:swe_x_preferred":[
        "Fontanes-du-Causse"
    ],
    "name:ukr_x_preferred":[
        "\u0424\u043e\u043d\u0442\u0430\u043d-\u0434\u044e-\u041a\u043e\u0441\u0441"
    ],
    "name:unk_x_variant":[
        "Fontanes"
    ],
    "name:vie_x_preferred":[
        "Fontanes-du-Causse"
    ],
    "name:vol_x_preferred":[
        "Fontanes-du-Causse"
    ],
    "name:war_x_preferred":[
        "Fontanes-du-Causse"
    ],
    "name:zho_x_preferred":[
        "\u4e30\u5854\u8bb7\u8fea\u79d1\u65af"
    ],
    "qs_pg:aaroncc":"FR",
    "qs_pg:gn_country":"FR",
    "qs_pg:gn_fcode":"PPL",
    "qs_pg:gn_pop":80,
    "qs_pg:name":"Fontanes-du-Causse",
    "qs_pg:name_adm0":"France",
    "qs_pg:name_adm1":"Midi-Pyr\u00e9n\u00e9es",
    "qs_pg:photos_9k":1,
    "qs_pg:photos_9r":1,
    "qs_pg:photos_all":2,
    "qs_pg:photos_sr":0,
    "qs_pg:pop_sr":1,
    "qs_pg:qs_pg_placetype":"locality",
    "qs_pg:qs_pg_placetype_gp":"Town",
    "qs_pg:woe_adm0":23424819,
    "woe:adm0_id":23424819,
    "woe:name_adm0":"France",
    "woe:name_adm1":"Midi-Pyr\u00e9n\u00e9es",
    "woe:placetype":"Town",
    "wof:name":"Fontanes-du-Causse",
    "wof:placetype":"neighbourhood",
    "wof:population":80
},
  "geometry": {"coordinates":[1.66002,44.66645],"type":"Point"}
}