{
  "type": "Feature",
  "properties": {
    "gn:admin1_code":"27",
    "gn:admin2_code":"89",
    "gn:admin3_code":"892",
    "gn:admin4_code":"89235",
    "gn:asciiname":"Meluzien",
    "gn:country_code":"FR",
    "gn:dem":211,
    "gn:feature_class":"P",
    "gn:feature_code":"PPL",
    "gn:name":"M\u00e9luzien",
    "gn:population":0,
    "gn:timezone":"Europe/Paris",
    "iso:country":"FR",
    "wof:name":"Meluzien",
    "wof:placetype":"locality"
},
  "geometry": {"coordinates":[3.94813,47.47744],"type":"Point"}
}