{
  "type": "Feature",
  "properties": {
    "gn:admin1_code":"76",
    "gn:admin2_code":"12",
    "gn:admin3_code":"123",
    "gn:admin4_code":"12240",
    "gn:asciiname":"Les Bouygues",
    "gn:country_code":"FR",
    "gn:dem":435,
    "gn:feature_class":"P",
    "gn:feature_code":"PPL",
    "gn:name":"Les Bouygues",
    "gn:population":0,
    "gn:timezone":"Europe/Paris",
    "iso:country":"FR",
    "wof:name":"Les Bouygues",
    "wof:placetype":"locality"
},
  "geometry": {"coordinates":[2.30481,44.64044000000001],"type":"Point"}
}