{
  "type": "Feature",
  "properties": {
    "gn:admin1_code":"44",
    "gn:admin2_code":"54",
    "gn:admin3_code":"542",
    "gn:admin4_code":"54287",
    "gn:asciiname":"Lachapelle",
    "gn:country_code":"FR",
    "gn:dem":288,
    "gn:feature_class":"P",
    "gn:feature_code":"PPL",
    "gn:name":"Lachapelle",
    "gn:population":0,
    "gn:timezone":"Europe/Paris",
    "iso:country":"FR",
    "name:ceb_x_preferred":[
        "Lachapelle"
    ],
    "name:deu_x_preferred":[
        "Lachapelle"
    ],
    "name:fra_x_preferred":[
        "Lachapelle"
    ],
    "name:ita_x_preferred":[
        "Lachapelle"
    ],
    "name:nds_x_preferred":[
        "Lachapelle"
    ],
    "name:nld_x_preferred":[
        "Lachapelle"
    ],
    "name:oci_x_preferred":[
        "Lachapelle"
    ],
    "name:pms_x_preferred":[
        "Lachapelle"
    ],
    "name:pol_x_preferred":[
        "Lachapelle"
    ],
    "name:rus_x_preferred":[
        "\u041b\u0430\u0448\u0430\u043f\u0435\u043b\u044c"
    ],
    "name:scn_x_preferred":[
        "Lachapelle"
    ],
    "name:slk_x_preferred":[
        "Lachapelle"
    ],
    "name:spa_x_preferred":[
        "Lachapelle"
    ],
    "name:swe_x_preferred":[
        "Lachapelle"
    ],
    "name:ukr_x_preferred":[
        "\u041b\u0430\u0448\u0430\u043f\u0435\u043b\u044c"
    ],
    "wof:name":"Lachapelle",
    "wof:placetype":"locality"
},
  "geometry": {"coordinates":[6.78882,48.41936],"type":"Point"}
}