{
  "type": "Feature",
  "properties": {
    "frgov:code_epci":"200070324",
    "frgov:insee_arr":"2",
    "frgov:insee_com":"54287",
    "frgov:insee_dep":"54",
    "frgov:insee_reg":"44",
    "frgov:nom_com":"Lachapelle",
    "frgov:nom_com_m":"LACHAPELLE",
    "frgov:nom_dep":"MEURTHE-ET-MOSELLE",
    "frgov:nom_reg":"GRAND EST",
    "frgov:statut":"Commune simple",
    "gn:admin1_code":"44",
    "gn:admin2_code":"54",
    "gn:admin3_code":"542",
    "gn:admin4_code":"54287",
    "gn:asciiname":"Lachapelle",
    "gn:country_code":"FR",
    "gn:dem":288,
    "gn:feature_class":"P",
    "gn:feature_code":"PPL",
    "gn:name":"Lachapelle",
    "gn:population":0,
    "gn:timezone":"Europe/Paris",
    "iso:country":"FR",
    "name:ceb_x_preferred":[
        "Lachapelle"
    ],
    "name:deu_x_preferred":[
        "Lachapelle"
    ],
    "name:fra_x_preferred":[
        "Lachapelle"
    ],
    "name:ita_x_preferred":[
        "Lachapelle"
    ],
    "name:nds_x_preferred":[
        "Lachapelle"
    ],
    "name:nld_x_preferred":[
        "Lachapelle"
    ],
    "name:oci_x_preferred":[
        "Lachapelle"
    ],
    "name:pms_x_preferred":[
        "Lachapelle"
    ],
    "name:pol_x_preferred":[
        "Lachapelle"
    ],
    "name:rus_x_preferred":[
        "\u041b\u0430\u0448\u0430\u043f\u0435\u043b\u044c"
    ],
    "name:scn_x_preferred":[
        "Lachapelle"
    ],
    "name:slk_x_preferred":[
        "Lachapelle"
    ],
    "name:spa_x_preferred":[
        "Lachapelle"
    ],
    "name:swe_x_preferred":[
        "Lachapelle"
    ],
    "name:ukr_x_preferred":[
        "\u041b\u0430\u0448\u0430\u043f\u0435\u043b\u044c"
    ],
    "qs:a0":"France",
    "qs:a1":"MEURTHE-ET-MOSELLE",
    "qs:a1_lc":"54",
    "qs:a1r":"LORRAINE",
    "qs:a1r_lc":"41",
    "qs:a2_lc":"03",
    "qs:a2r_lc":"2",
    "qs:adm0":"France",
    "qs:adm0_a3":"FRA",
    "qs:la":"LACHAPELLE",
    "qs:la_lc":"54287",
    "qs:level":"localadmin",
    "qs:type":"Commune simple",
    "wof:coterminous":[
        404400257
    ],
    "wof:name":"Lachapelle",
    "wof:placetype":"locality",
    "wof:placetype_local":"Commune simple"
},
  "geometry": {"coordinates":[6.78882,48.41936],"type":"Point"}
}