{
  "type": "Feature",
  "properties": {
    "gn:admin1_code":"84",
    "gn:admin2_code":"38",
    "gn:admin3_code":"382",
    "gn:admin4_code":"38193",
    "gn:asciiname":"Saint-Germain",
    "gn:country_code":"FR",
    "gn:dem":216,
    "gn:feature_class":"P",
    "gn:feature_code":"PPL",
    "gn:name":"Saint-Germain",
    "gn:population":0,
    "gn:timezone":"Europe/Paris",
    "iso:country":"FR",
    "wof:name":"Saint-Germain",
    "wof:placetype":"locality"
},
  "geometry": {"coordinates":[5.20449,45.61526],"type":"Point"}
}