{
  "type": "Feature",
  "properties": {
    "iso:country":"FR",
    "name:fra_x_preferred":[
        "Centre-ville"
    ],
    "name:fra_x_variant":[
        "Nantes 1"
    ],
    "qs:gn_adm0_cc":"FR",
    "qs:gn_local":2990969,
    "qs:gn_nam_loc":"Nantes, Nantes, Loire-Atlantique, Pays de la Loire, FR",
    "qs:gn_namadm1":"B5",
    "qs:local_max":18650,
    "qs:local_sum":28578,
    "qs:localhoods":14,
    "qs:name":"Centre-ville",
    "qs:name_adm0":"France",
    "qs:name_adm1":"Pays de la Loire",
    "qs:name_adm2":"Loire-Atlantique",
    "qs:name_lau":"Nantes",
    "qs:name_local":"Nantes",
    "qs:photo_max":4701,
    "qs:photo_sum":18650,
    "qs:placetype":"Suburb",
    "qs:quad_count":233,
    "qs:woe_adm0":23424819,
    "qs:woe_adm1":7153325,
    "qs:woe_adm2":12597177,
    "qs:woe_lau":12662073,
    "qs:woe_local":613858,
    "qs:woe_ver":"7.10.0",
    "wof:lang":[
        "fre"
    ],
    "wof:name":"Centre-ville",
    "wof:placetype":"neighbourhood"
},
  "geometry": {"coordinates":[-1.557612,47.213827],"type":"Point"}
}