{
  "type": "Feature",
  "properties": {
    "gn:admin1_code":"75",
    "gn:admin2_code":"23",
    "gn:admin3_code":"232",
    "gn:admin4_code":"23139",
    "gn:asciiname":"Les Corets",
    "gn:country_code":"FR",
    "gn:dem":421,
    "gn:feature_class":"P",
    "gn:feature_code":"PPL",
    "gn:name":"Les C\u00f4rets",
    "gn:population":0,
    "gn:timezone":"Europe/Paris",
    "iso:country":"FR",
    "wof:name":"Les Corets",
    "wof:placetype":"locality"
},
  "geometry": {"coordinates":[1.95,46.41667],"type":"Point"}
}