{
  "type": "Feature",
  "properties": {
    "gn:admin1_code":"84",
    "gn:admin2_code":"63",
    "gn:admin3_code":"633",
    "gn:admin4_code":"63401",
    "gn:asciiname":"Roche Romaine",
    "gn:country_code":"FR",
    "gn:dem":931,
    "gn:feature_class":"P",
    "gn:feature_code":"PPL",
    "gn:name":"Roche Romaine",
    "gn:population":0,
    "gn:timezone":"Europe/Paris",
    "iso:country":"FR",
    "wof:name":"Roche Romaine",
    "wof:placetype":"locality"
},
  "geometry": {"coordinates":[2.97002,45.55999],"type":"Point"}
}