{
  "type": "Feature",
  "properties": {
    "gn:admin1_code":"44",
    "gn:admin2_code":"55",
    "gn:admin3_code":"551",
    "gn:admin4_code":"55446",
    "gn:asciiname":"Le Petit-Rumont",
    "gn:country_code":"FR",
    "gn:dem":300,
    "gn:feature_class":"P",
    "gn:feature_code":"PPL",
    "gn:name":"Le Petit-Rumont",
    "gn:population":0,
    "gn:timezone":"Europe/Paris",
    "iso:country":"FR",
    "wof:name":"Le Petit-Rumont",
    "wof:placetype":"locality"
},
  "geometry": {"coordinates":[5.27796,48.83856],"type":"Point"}
}