{
  "type": "Feature",
  "properties": {
    "gn:admin1_code":"84",
    "gn:admin2_code":"63",
    "gn:admin3_code":"634",
    "gn:admin4_code":"63419",
    "gn:asciiname":"Montignat",
    "gn:country_code":"FR",
    "gn:dem":629,
    "gn:feature_class":"P",
    "gn:feature_code":"PPL",
    "gn:name":"Montignat",
    "gn:population":0,
    "gn:timezone":"Europe/Paris",
    "iso:country":"FR",
    "wof:name":"Montignat",
    "wof:placetype":"locality"
},
  "geometry": {"coordinates":[2.92731,46.16409],"type":"Point"}
}