{
  "type": "Feature",
  "properties": {
    "gn:admin1_code":"75",
    "gn:admin2_code":"19",
    "gn:admin3_code":"191",
    "gn:admin4_code":"19031",
    "gn:asciiname":"Le Mas",
    "gn:country_code":"FR",
    "gn:dem":192,
    "gn:feature_class":"P",
    "gn:feature_code":"PPL",
    "gn:name":"Le Mas",
    "gn:population":0,
    "gn:timezone":"Europe/Paris",
    "iso:country":"FR",
    "name:ara_x_preferred":[
        "\u0644\u064a \u0645\u0627\u0633"
    ],
    "name:bug_x_preferred":[
        "Le Mas"
    ],
    "name:cat_x_preferred":[
        "Lo Mas"
    ],
    "name:ceb_x_preferred":[
        "Le Mas"
    ],
    "name:deu_x_preferred":[
        "Le Mas"
    ],
    "name:eus_x_preferred":[
        "Le Mas"
    ],
    "name:fra_x_preferred":[
        "Le Mas"
    ],
    "name:hun_x_preferred":[
        "Le Mas"
    ],
    "name:hye_x_preferred":[
        "\u053c\u0568 \u0544\u0561\u057d"
    ],
    "name:ind_x_preferred":[
        "Le Mas"
    ],
    "name:ita_x_preferred":[
        "Le Mas"
    ],
    "name:lat_x_preferred":[
        "Massium"
    ],
    "name:lmo_x_preferred":[
        "Le Mas"
    ],
    "name:msa_x_preferred":[
        "Le Mas"
    ],
    "name:nld_x_preferred":[
        "Le Mas"
    ],
    "name:oci_x_preferred":[
        "Lo Mas"
    ],
    "name:pms_x_preferred":[
        "Le Mas"
    ],
    "name:pol_x_preferred":[
        "Le Mas"
    ],
    "name:por_x_preferred":[
        "Le Mas"
    ],
    "name:ron_x_preferred":[
        "Le Mas"
    ],
    "name:rus_x_preferred":[
        "\u041b\u0435-\u041c\u0430\u0441"
    ],
    "name:slk_x_preferred":[
        "Le Mas"
    ],
    "name:spa_x_preferred":[
        "Le Mas"
    ],
    "name:sqi_x_preferred":[
        "Le Mas"
    ],
    "name:swe_x_preferred":[
        "Le Mas"
    ],
    "name:ukr_x_preferred":[
        "\u041b\u0435-\u041c\u0430"
    ],
    "name:vie_x_preferred":[
        "Le Mas"
    ],
    "name:vol_x_preferred":[
        "Le Mas"
    ],
    "name:war_x_preferred":[
        "Le Mas"
    ],
    "wof:name":"Le Mas",
    "wof:placetype":"locality"
},
  "geometry": {"coordinates":[1.50609,45.12347000000001],"type":"Point"}
}