{
  "type": "Feature",
  "properties": {
    "gn:admin1_code":"76",
    "gn:admin2_code":"12",
    "gn:admin3_code":"122",
    "gn:admin4_code":"12214",
    "gn:asciiname":"Regaussou",
    "gn:country_code":"FR",
    "gn:dem":884,
    "gn:feature_class":"P",
    "gn:feature_code":"PPL",
    "gn:name":"Regaussou",
    "gn:population":0,
    "gn:timezone":"Europe/Paris",
    "iso:country":"FR",
    "wof:name":"Regaussou",
    "wof:placetype":"locality"
},
  "geometry": {"coordinates":[2.87955,44.57653],"type":"Point"}
}