{
  "type": "Feature",
  "properties": {
    "gn:admin1_code":"93",
    "gn:admin2_code":"05",
    "gn:admin3_code":"051",
    "gn:admin4_code":"05122",
    "gn:asciiname":"Le Lauzet",
    "gn:country_code":"FR",
    "gn:dem":2106,
    "gn:feature_class":"P",
    "gn:feature_code":"PPL",
    "gn:name":"Le Lauzet",
    "gn:population":0,
    "gn:timezone":"Europe/Paris",
    "iso:country":"FR",
    "wof:name":"Le Lauzet",
    "wof:placetype":"locality"
},
  "geometry": {"coordinates":[6.61667,44.76667],"type":"Point"}
}