{
  "type": "Feature",
  "properties": {
    "gn:admin1_code":"27",
    "gn:admin2_code":"58",
    "gn:admin3_code":"584",
    "gn:admin4_code":"58218",
    "gn:asciiname":"Nentin",
    "gn:country_code":"FR",
    "gn:dem":270,
    "gn:feature_class":"P",
    "gn:feature_code":"PPL",
    "gn:name":"Nentin",
    "gn:population":0,
    "gn:timezone":"Europe/Paris",
    "iso:country":"FR",
    "wof:name":"Nentin",
    "wof:placetype":"locality"
},
  "geometry": {"coordinates":[3.34153,47.18324000000001],"type":"Point"}
}