{
  "type": "Feature",
  "properties": {
    "iso:country":"FR",
    "wof:name":"Bon Secours",
    "wof:placetype":"neighbourhood"
},
  "geometry": {"coordinates":[5.38538677236234,43.32098487458811],"type":"Point"}
}