{
  "type": "Feature",
  "properties": {
    "gn:admin1_code":"75",
    "gn:admin2_code":"23",
    "gn:admin3_code":"231",
    "gn:admin4_code":"23151",
    "gn:asciiname":"Lichiat",
    "gn:country_code":"FR",
    "gn:dem":466,
    "gn:feature_class":"P",
    "gn:feature_code":"PPL",
    "gn:name":"Lichiat",
    "gn:population":0,
    "gn:timezone":"Europe/Paris",
    "iso:country":"FR",
    "wof:name":"Lichiat",
    "wof:placetype":"locality"
},
  "geometry": {"coordinates":[2.30676,46.09815],"type":"Point"}
}