{
  "type": "Feature",
  "properties": {
    "gn:admin1_code":"28",
    "gn:admin2_code":"50",
    "gn:admin3_code":"502",
    "gn:admin4_code":"50129",
    "gn:asciiname":"Bourbourg",
    "gn:country_code":"FR",
    "gn:dem":8,
    "gn:feature_class":"P",
    "gn:feature_code":"PPLL",
    "gn:name":"Bourbourg",
    "gn:population":0,
    "gn:timezone":"Europe/Paris",
    "iso:country":"FR",
    "wof:name":"Bourbourg",
    "wof:placetype":"locality"
},
  "geometry": {"coordinates":[-1.5744,49.64824],"type":"Point"}
}