{
  "type": "Feature",
  "properties": {
    "gn:admin1_code":"28",
    "gn:admin2_code":"50",
    "gn:admin3_code":"502",
    "gn:admin4_code":"50129",
    "gn:asciiname":"Bourbourg",
    "gn:country_code":"FR",
    "gn:dem":8,
    "gn:feature_class":"P",
    "gn:feature_code":"PPLL",
    "gn:name":"Bourbourg",
    "gn:population":0,
    "gn:timezone":"Europe/Paris",
    "iso:country":"FR",
    "name:bre_x_preferred":[
        "Broekburg"
    ],
    "name:cat_x_preferred":[
        "Bourbourg"
    ],
    "name:ceb_x_preferred":[
        "Bourbourg"
    ],
    "name:ces_x_preferred":[
        "Bourbourg"
    ],
    "name:deu_x_preferred":[
        "Bourbourg"
    ],
    "name:eus_x_preferred":[
        "Bourbourg"
    ],
    "name:fra_x_preferred":[
        "Bourbourg"
    ],
    "name:hun_x_preferred":[
        "Bourbourg"
    ],
    "name:ind_x_preferred":[
        "Bourbourg"
    ],
    "name:ita_x_preferred":[
        "Bourbourg"
    ],
    "name:kaz_x_preferred":[
        "\u0411\u0443\u0440\u0431\u0443\u0440"
    ],
    "name:mlg_x_preferred":[
        "Bourbourg"
    ],
    "name:msa_x_preferred":[
        "Bourbourg"
    ],
    "name:nld_x_preferred":[
        "Bourbourg"
    ],
    "name:oci_x_preferred":[
        "Bourbourg"
    ],
    "name:pcd_x_preferred":[
        "Brouckbourq"
    ],
    "name:pol_x_preferred":[
        "Bourbourg"
    ],
    "name:ron_x_preferred":[
        "Bourbourg"
    ],
    "name:rus_x_preferred":[
        "\u0411\u0443\u0440\u0431\u0443\u0440"
    ],
    "name:slk_x_preferred":[
        "Bourbourg"
    ],
    "name:spa_x_preferred":[
        "Bourbourg"
    ],
    "name:srp_x_preferred":[
        "\u0411\u0443\u0440\u0431\u0443\u0440"
    ],
    "name:swe_x_preferred":[
        "Bourbourg"
    ],
    "name:ukr_x_preferred":[
        "\u0411\u0443\u0440\u0431\u0443\u0440"
    ],
    "name:vie_x_preferred":[
        "Bourbourg"
    ],
    "name:vls_x_preferred":[
        "Broekburg"
    ],
    "name:vol_x_preferred":[
        "Bourbourg"
    ],
    "name:war_x_preferred":[
        "Bourbourg"
    ],
    "name:zho_x_preferred":[
        "\u5e03\u5c14\u5821"
    ],
    "wof:name":"Bourbourg",
    "wof:placetype":"locality"
},
  "geometry": {"coordinates":[-1.5744,49.64824],"type":"Point"}
}