{
  "type": "Feature",
  "properties": {
    "gn:admin1_code":"24",
    "gn:admin2_code":"36",
    "gn:admin3_code":"361",
    "gn:admin4_code":"36239",
    "gn:asciiname":"Villebuxiere",
    "gn:country_code":"FR",
    "gn:dem":220,
    "gn:feature_class":"P",
    "gn:feature_code":"PPL",
    "gn:name":"Villebuxi\u00e8re",
    "gn:population":0,
    "gn:timezone":"Europe/Paris",
    "iso:country":"FR",
    "wof:name":"Villebuxiere",
    "wof:placetype":"locality"
},
  "geometry": {"coordinates":[1.47734,46.47353],"type":"Point"}
}