{
  "type": "Feature",
  "properties": {
    "gn:admin1_code":"52",
    "gn:admin2_code":"49",
    "gn:admin3_code":"492",
    "gn:admin4_code":"49371",
    "gn:asciiname":"Les Poteries",
    "gn:country_code":"FR",
    "gn:dem":183,
    "gn:feature_class":"P",
    "gn:feature_code":"PPL",
    "gn:name":"Les Poteries",
    "gn:population":0,
    "gn:timezone":"Europe/Paris",
    "iso:country":"FR",
    "wof:name":"Les Poteries",
    "wof:placetype":"locality"
},
  "geometry": {"coordinates":[-0.73452,47.09726],"type":"Point"}
}