{
  "type": "Feature",
  "properties": {
    "gn:admin1_code":"84",
    "gn:admin2_code":"26",
    "gn:admin3_code":"263",
    "gn:admin4_code":"26094",
    "gn:asciiname":"Saint-Andeol",
    "gn:country_code":"FR",
    "gn:dem":385,
    "gn:feature_class":"P",
    "gn:feature_code":"PPL",
    "gn:name":"Saint-And\u00e9ol",
    "gn:population":0,
    "gn:timezone":"Europe/Paris",
    "iso:country":"FR",
    "wof:name":"Saint-Andeol",
    "wof:placetype":"locality"
},
  "geometry": {"coordinates":[4.95504,45.16449],"type":"Point"}
}