{
  "type": "Feature",
  "properties": {
    "gn:admin1_code":"94",
    "gn:admin2_code":"2A",
    "gn:admin3_code":"2A1",
    "gn:admin4_code":"2A008",
    "gn:asciiname":"Bisinao",
    "gn:country_code":"FR",
    "gn:dem":623,
    "gn:feature_class":"P",
    "gn:feature_code":"PPL",
    "gn:name":"Bisinao",
    "gn:population":0,
    "gn:timezone":"Europe/Paris",
    "iso:country":"FR",
    "wof:name":"Bisinao",
    "wof:placetype":"locality"
},
  "geometry": {"coordinates":[8.87194,41.84196],"type":"Point"}
}