{
  "type": "Feature",
  "properties": {
    "gn:admin1_code":"93",
    "gn:admin2_code":"05",
    "gn:admin3_code":"051",
    "gn:admin4_code":"05133",
    "gn:asciiname":"Le Tronchet",
    "gn:cc2":"FR",
    "gn:country_code":"FR",
    "gn:dem":1866,
    "gn:feature_class":"P",
    "gn:feature_code":"PPL",
    "gn:name":"Le Tronchet",
    "gn:population":0,
    "gn:timezone":"Europe/Paris",
    "iso:country":"FR",
    "name:ceb_x_preferred":[
        "Le Tronchet"
    ],
    "name:deu_x_preferred":[
        "Le Tronchet"
    ],
    "name:fra_x_preferred":[
        "Le Tronchet"
    ],
    "name:ita_x_preferred":[
        "Le Tronchet"
    ],
    "name:nds_x_preferred":[
        "Le Tronchet"
    ],
    "name:nld_x_preferred":[
        "Le Tronchet"
    ],
    "name:pol_x_preferred":[
        "Le Tronchet"
    ],
    "name:por_x_preferred":[
        "Le Tronchet"
    ],
    "name:rus_x_preferred":[
        "\u041b\u0435 \u0422\u0440\u043e\u043d\u0448\u0435"
    ],
    "name:slk_x_preferred":[
        "Le Tronchet"
    ],
    "name:spa_x_preferred":[
        "Le Tronchet"
    ],
    "name:swe_x_preferred":[
        "Le Tronchet"
    ],
    "name:ukr_x_preferred":[
        "\u041b\u0435-\u0422\u0440\u043e\u043d\u0448\u0435"
    ],
    "name:und_x_variant":[
        "Le Tronchat",
        "Le Tronchet"
    ],
    "wof:name":"Le Tronchet",
    "wof:placetype":"locality"
},
  "geometry": {"coordinates":[6.59444,44.94737],"type":"Point"}
}