{
  "type": "Feature",
  "properties": {
    "gn:admin1_code":"84",
    "gn:admin2_code":"73",
    "gn:admin3_code":"733",
    "gn:admin4_code":"73290",
    "gn:asciiname":"Rivers-Derriere",
    "gn:country_code":"FR",
    "gn:dem":1995,
    "gn:feature_class":"P",
    "gn:feature_code":"PPL",
    "gn:name":"Rivers-Derri\u00e8re",
    "gn:population":0,
    "gn:timezone":"Europe/Paris",
    "iso:country":"FR",
    "wof:name":"Rivers-Derriere",
    "wof:placetype":"locality"
},
  "geometry": {"coordinates":[6.91366,45.23365],"type":"Point"}
}