{
  "type": "Feature",
  "properties": {
    "gn:admin1_code":"44",
    "gn:admin2_code":"51",
    "gn:admin3_code":"515",
    "gn:admin4_code":"51621",
    "gn:asciiname":"La Harazee",
    "gn:country_code":"FR",
    "gn:dem":140,
    "gn:feature_class":"P",
    "gn:feature_code":"PPL",
    "gn:name":"La Haraz\u00e9e",
    "gn:population":0,
    "gn:timezone":"Europe/Paris",
    "iso:country":"FR",
    "wof:name":"La Harazee",
    "wof:placetype":"locality"
},
  "geometry": {"coordinates":[4.91811,49.19456],"type":"Point"}
}