{
  "type": "Feature",
  "properties": {
    "gn:admin1_code":"28",
    "gn:admin2_code":"76",
    "gn:admin3_code":"762",
    "gn:admin4_code":"76596.0",
    "gn:asciiname":"Enanville",
    "gn:country_code":"FR",
    "gn:dem":106,
    "gn:feature_class":"P",
    "gn:feature_code":"PPL",
    "gn:name":"\u00c9nanville",
    "gn:population":0,
    "gn:timezone":"Europe/Paris",
    "iso:country":"FR",
    "wof:name":"Enanville",
    "wof:placetype":"locality"
},
  "geometry": {"coordinates":[0.28155,49.52303],"type":"Point"}
}