{
  "type": "Feature",
  "properties": {
    "gn:admin1_code":"75",
    "gn:admin2_code":"87",
    "gn:admin3_code":"873",
    "gn:admin4_code":"87126",
    "gn:asciiname":"Les Plats",
    "gn:country_code":"FR",
    "gn:dem":244,
    "gn:feature_class":"P",
    "gn:feature_code":"PPL",
    "gn:name":"Les Plats",
    "gn:population":0,
    "gn:timezone":"Europe/Paris",
    "iso:country":"FR",
    "wof:name":"Les Plats",
    "wof:placetype":"locality"
},
  "geometry": {"coordinates":[0.8548,45.84399000000001],"type":"Point"}
}