{
  "type": "Feature",
  "properties": {
    "iso:country":"FR",
    "name:eng_x_preferred":[
        "Mosson"
    ],
    "name:fra_x_preferred":[
        "Mosson"
    ],
    "wof:name":"Mosson",
    "wof:placetype":"neighbourhood"
},
  "geometry": {"coordinates":[3.82165769126052,43.62817076793966],"type":"Point"}
}