{
  "type": "Feature",
  "properties": {
    "iso:country":"FR",
    "wof:name":"Esquirol",
    "wof:placetype":"neighbourhood"
},
  "geometry": {"coordinates":[1.4471702837759,43.60059034968867],"type":"Point"}
}