{
  "type": "Feature",
  "properties": {
    "gn:admin1_code":"76",
    "gn:admin2_code":"46",
    "gn:admin3_code":"463",
    "gn:admin4_code":"46059",
    "gn:asciiname":"Rocabiliere",
    "gn:country_code":"FR",
    "gn:dem":320,
    "gn:feature_class":"P",
    "gn:feature_code":"PPL",
    "gn:name":"Rocabili\u00e8re",
    "gn:population":0,
    "gn:timezone":"Europe/Paris",
    "iso:country":"FR",
    "wof:name":"Rocabiliere",
    "wof:placetype":"locality"
},
  "geometry": {"coordinates":[1.59224,44.74717],"type":"Point"}
}