{
  "type": "Feature",
  "properties": {
    "frgov:code_epci":"200072072",
    "frgov:insee_arr":"2",
    "frgov:insee_com":"41138",
    "frgov:insee_dep":"41",
    "frgov:insee_reg":"24",
    "frgov:nom_com":"Meslay",
    "frgov:nom_com_m":"MESLAY",
    "frgov:nom_dep":"LOIR-ET-CHER",
    "frgov:nom_reg":"CENTRE-VAL DE LOIRE",
    "frgov:statut":"Commune simple",
    "gn:admin1_code":"24",
    "gn:admin2_code":"41",
    "gn:admin3_code":"412",
    "gn:admin4_code":"41138",
    "gn:asciiname":"Meslay",
    "gn:country_code":"FR",
    "gn:dem":83,
    "gn:feature_class":"P",
    "gn:feature_code":"PPL",
    "gn:name":"Meslay",
    "gn:population":310,
    "gn:timezone":"Europe/Paris",
    "iso:country":"FR",
    "name:bre_x_preferred":[
        "Meslay"
    ],
    "name:ceb_x_preferred":[
        "Meslay"
    ],
    "name:deu_x_preferred":[
        "Meslay"
    ],
    "name:fra_x_preferred":[
        "Meslay"
    ],
    "name:ita_x_preferred":[
        "Meslay"
    ],
    "name:nds_x_preferred":[
        "Meslay"
    ],
    "name:nld_x_preferred":[
        "Meslay"
    ],
    "name:oci_x_preferred":[
        "Meslay"
    ],
    "name:pms_x_preferred":[
        "Meslay"
    ],
    "name:pol_x_preferred":[
        "Meslay"
    ],
    "name:por_x_preferred":[
        "Meslay"
    ],
    "name:slk_x_preferred":[
        "Meslay"
    ],
    "name:spa_x_preferred":[
        "Meslay"
    ],
    "name:swe_x_preferred":[
        "Meslay"
    ],
    "name:ukr_x_preferred":[
        "\u041c\u0435\u0441\u043b\u0435"
    ],
    "qs:a0":"France",
    "qs:a1":"LOIR-ET-CHER",
    "qs:a1_lc":"41",
    "qs:a1r":"CENTRE",
    "qs:a1r_lc":"24",
    "qs:a2_lc":"28",
    "qs:a2r_lc":"2",
    "qs:adm0":"France",
    "qs:adm0_a3":"FRA",
    "qs:la":"MESLAY",
    "qs:la_lc":"41138",
    "qs:level":"localadmin",
    "qs:type":"Commune simple",
    "wof:coterminous":[
        404413963
    ],
    "wof:name":"Meslay",
    "wof:placetype":"locality",
    "wof:placetype_local":"Commune simple",
    "wof:population":310
},
  "geometry": {"coordinates":[1.09714,47.81085],"type":"Point"}
}