{
  "type": "Feature",
  "properties": {
    "gn:admin1_code":"24",
    "gn:admin2_code":"41",
    "gn:admin3_code":"412",
    "gn:admin4_code":"41138",
    "gn:asciiname":"Meslay",
    "gn:country_code":"FR",
    "gn:dem":83,
    "gn:feature_class":"P",
    "gn:feature_code":"PPL",
    "gn:name":"Meslay",
    "gn:population":310,
    "gn:timezone":"Europe/Paris",
    "iso:country":"FR",
    "name:bre_x_preferred":[
        "Meslay"
    ],
    "name:ceb_x_preferred":[
        "Meslay"
    ],
    "name:deu_x_preferred":[
        "Meslay"
    ],
    "name:fra_x_preferred":[
        "Meslay"
    ],
    "name:ita_x_preferred":[
        "Meslay"
    ],
    "name:nds_x_preferred":[
        "Meslay"
    ],
    "name:nld_x_preferred":[
        "Meslay"
    ],
    "name:oci_x_preferred":[
        "Meslay"
    ],
    "name:pms_x_preferred":[
        "Meslay"
    ],
    "name:pol_x_preferred":[
        "Meslay"
    ],
    "name:por_x_preferred":[
        "Meslay"
    ],
    "name:slk_x_preferred":[
        "Meslay"
    ],
    "name:spa_x_preferred":[
        "Meslay"
    ],
    "name:swe_x_preferred":[
        "Meslay"
    ],
    "name:ukr_x_preferred":[
        "\u041c\u0435\u0441\u043b\u0435"
    ],
    "wof:name":"Meslay",
    "wof:placetype":"locality",
    "wof:population":310
},
  "geometry": {"coordinates":[1.09714,47.81085],"type":"Point"}
}