{
  "type": "Feature",
  "properties": {
    "gn:admin1_code":"44",
    "gn:admin2_code":"52",
    "gn:admin3_code":"521",
    "gn:admin4_code":"52017",
    "gn:asciiname":"Valbruant",
    "gn:country_code":"FR",
    "gn:dem":305,
    "gn:feature_class":"P",
    "gn:feature_code":"PPL",
    "gn:name":"Valbruant",
    "gn:population":0,
    "gn:timezone":"Europe/Paris",
    "iso:country":"FR",
    "wof:name":"Valbruant",
    "wof:placetype":"locality"
},
  "geometry": {"coordinates":[5.04588,47.92717],"type":"Point"}
}