{
  "type": "Feature",
  "properties": {
    "gn:admin1_code":"52",
    "gn:admin2_code":"49",
    "gn:admin3_code":"492",
    "gn:admin4_code":"49244",
    "gn:asciiname":"Le Croissement",
    "gn:country_code":"FR",
    "gn:dem":22,
    "gn:feature_class":"P",
    "gn:feature_code":"PPL",
    "gn:name":"Le Croissement",
    "gn:population":0,
    "gn:timezone":"Europe/Paris",
    "iso:country":"FR",
    "wof:name":"Le Croissement",
    "wof:placetype":"locality"
},
  "geometry": {"coordinates":[-0.84609,47.38262],"type":"Point"}
}