{
  "type": "Feature",
  "properties": {
    "gn:admin1_code":"52",
    "gn:admin2_code":"53",
    "gn:admin3_code":"532",
    "gn:admin4_code":"53226",
    "gn:asciiname":"La Templerie",
    "gn:country_code":"FR",
    "gn:dem":191,
    "gn:feature_class":"P",
    "gn:feature_code":"PPL",
    "gn:name":"La Templerie",
    "gn:population":0,
    "gn:timezone":"Europe/Paris",
    "iso:country":"FR",
    "name:und_x_variant":[
        "Templerie",
        "La Templerie"
    ],
    "wof:name":"La Templerie",
    "wof:placetype":"locality"
},
  "geometry": {"coordinates":[-0.9461,48.19144],"type":"Point"}
}