{
  "type": "Feature",
  "properties": {
    "gn:admin1_code":"75",
    "gn:admin2_code":"23",
    "gn:admin3_code":"231",
    "gn:admin4_code":"23144",
    "gn:asciiname":"Les Maisons",
    "gn:country_code":"FR",
    "gn:dem":763,
    "gn:feature_class":"P",
    "gn:feature_code":"PPL",
    "gn:name":"Les Maisons",
    "gn:population":0,
    "gn:timezone":"Europe/Paris",
    "iso:country":"FR",
    "wof:name":"Les Maisons",
    "wof:placetype":"locality"
},
  "geometry": {"coordinates":[2.05457,45.82298],"type":"Point"}
}