{
  "type": "Feature",
  "properties": {
    "gn:admin1_code":"24",
    "gn:admin2_code":"28",
    "gn:admin3_code":"282",
    "gn:admin4_code":"28382",
    "gn:asciiname":"Muzelles",
    "gn:country_code":"FR",
    "gn:dem":127,
    "gn:feature_class":"P",
    "gn:feature_code":"PPL",
    "gn:name":"Muzelles",
    "gn:population":0,
    "gn:timezone":"Europe/Paris",
    "iso:country":"FR",
    "wof:name":"Muzelles",
    "wof:placetype":"locality"
},
  "geometry": {"coordinates":[1.70659,48.07106],"type":"Point"}
}