{
  "type": "Feature",
  "properties": {
    "gn:gn_country":"FR",
    "gn:gn_fcode":"PPL",
    "gn:gn_pop":0,
    "iso:country":"FR",
    "qs_pg:aaroncc":"FR",
    "qs_pg:gn_country":"FR",
    "qs_pg:gn_fcode":"PPL",
    "qs_pg:gn_pop":0,
    "qs_pg:name":"Piau Engaly",
    "qs_pg:name_adm0":"France",
    "qs_pg:name_adm1":"Midi-Pyr\u00e9n\u00e9es",
    "qs_pg:photos":677,
    "qs_pg:photos_1k":137,
    "qs_pg:photos_9k":3,
    "qs_pg:photos_9r":5,
    "qs_pg:photos_all":677,
    "qs_pg:photos_sr":8,
    "qs_pg:pop_sr":0,
    "qs_pg:qs_pg_placetype":"locality",
    "qs_pg:qs_pg_placetype_gp":"Town",
    "qs_pg:woe_adm0":23424819,
    "woe:adm0_id":23424819,
    "woe:name_adm0":"France",
    "woe:name_adm1":"Midi-Pyr\u00e9n\u00e9es",
    "woe:placetype":"Town",
    "wof:name":"Piau Engaly",
    "wof:placetype":"neighbourhood"
},
  "geometry": {"coordinates":[0.15904,42.78545],"type":"Point"}
}