{
  "type": "Feature",
  "properties": {
    "gn:admin1_code":"11",
    "gn:admin2_code":"77",
    "gn:admin3_code":"774",
    "gn:admin4_code":"77099",
    "gn:asciiname":"Fontaine",
    "gn:country_code":"FR",
    "gn:dem":88,
    "gn:feature_class":"P",
    "gn:feature_code":"PPL",
    "gn:name":"Fontaine",
    "gn:population":466,
    "gn:timezone":"Europe/Paris",
    "iso:country":"FR",
    "wof:name":"Fontaine",
    "wof:placetype":"locality",
    "wof:population":466
},
  "geometry": {"coordinates":[2.66845,48.13001],"type":"Point"}
}