{
  "type": "Feature",
  "properties": {
    "gn:admin1_code":"24",
    "gn:admin2_code":"36",
    "gn:admin3_code":"362",
    "gn:admin4_code":"36243",
    "gn:asciiname":"Breteau",
    "gn:country_code":"FR",
    "gn:dem":104,
    "gn:feature_class":"P",
    "gn:feature_code":"PPL",
    "gn:name":"Br\u00eateau",
    "gn:population":0,
    "gn:timezone":"Europe/Paris",
    "iso:country":"FR",
    "name:cat_x_preferred":[
        "Breteau"
    ],
    "name:ceb_x_preferred":[
        "Breteau"
    ],
    "name:deu_x_preferred":[
        "Breteau"
    ],
    "name:eus_x_preferred":[
        "Breteau"
    ],
    "name:fra_x_preferred":[
        "Breteau"
    ],
    "name:hun_x_preferred":[
        "Breteau"
    ],
    "name:ita_x_preferred":[
        "Breteau"
    ],
    "name:lat_x_preferred":[
        "Breteau"
    ],
    "name:msa_x_preferred":[
        "Breteau"
    ],
    "name:nld_x_preferred":[
        "Breteau"
    ],
    "name:oci_x_preferred":[
        "Breteau"
    ],
    "name:pms_x_preferred":[
        "Breteau"
    ],
    "name:pol_x_preferred":[
        "Breteau"
    ],
    "name:por_x_preferred":[
        "Breteau"
    ],
    "name:ron_x_preferred":[
        "Breteau"
    ],
    "name:slk_x_preferred":[
        "Breteau"
    ],
    "name:spa_x_preferred":[
        "Breteau"
    ],
    "name:srp_x_preferred":[
        "\u0411\u0440\u0435\u0442\u043e"
    ],
    "name:swe_x_preferred":[
        "Breteau"
    ],
    "name:ukr_x_preferred":[
        "\u0411\u0440\u0435\u0442\u043e"
    ],
    "name:und_x_variant":[
        "Br\u00eateau"
    ],
    "name:uzb_x_preferred":[
        "Breteau"
    ],
    "name:vie_x_preferred":[
        "Breteau"
    ],
    "name:vol_x_preferred":[
        "Breteau"
    ],
    "name:war_x_preferred":[
        "Breteau"
    ],
    "name:zho_x_preferred":[
        "\u5e03\u52d2\u6258"
    ],
    "wof:name":"Breteau",
    "wof:placetype":"locality"
},
  "geometry": {"coordinates":[1.38007,46.93922],"type":"Point"}
}