{
  "type": "Feature",
  "properties": {
    "gn:admin1_code":"24",
    "gn:admin2_code":"36",
    "gn:admin3_code":"362",
    "gn:admin4_code":"36243",
    "gn:asciiname":"Breteau",
    "gn:country_code":"FR",
    "gn:dem":104,
    "gn:feature_class":"P",
    "gn:feature_code":"PPL",
    "gn:name":"Br\u00eateau",
    "gn:population":0,
    "gn:timezone":"Europe/Paris",
    "iso:country":"FR",
    "name:und_x_variant":[
        "Br\u00eateau"
    ],
    "wof:name":"Breteau",
    "wof:placetype":"locality"
},
  "geometry": {"coordinates":[1.38007,46.93922],"type":"Point"}
}