{
  "type": "Feature",
  "properties": {
    "gn:admin1_code":"84",
    "gn:admin2_code":"03",
    "gn:admin3_code":"032",
    "gn:admin4_code":"3155.0",
    "gn:asciiname":"La Platriere",
    "gn:country_code":"FR",
    "gn:dem":269,
    "gn:feature_class":"P",
    "gn:feature_code":"PPL",
    "gn:name":"La Pl\u00e2tri\u00e8re",
    "gn:population":0,
    "gn:timezone":"Europe/Paris",
    "iso:country":"FR",
    "wof:name":"La Platriere",
    "wof:placetype":"locality"
},
  "geometry": {"coordinates":[2.88064,46.72572],"type":"Point"}
}