{
  "type": "Feature",
  "properties": {
    "gn:admin1_code":"75",
    "gn:admin2_code":"19",
    "gn:admin3_code":"193",
    "gn:admin4_code":"19159",
    "gn:asciiname":"Vergnolle",
    "gn:country_code":"FR",
    "gn:dem":775,
    "gn:feature_class":"P",
    "gn:feature_code":"PPL",
    "gn:name":"Vergnolle",
    "gn:population":0,
    "gn:timezone":"Europe/Paris",
    "iso:country":"FR",
    "wof:name":"Vergnolle",
    "wof:placetype":"locality"
},
  "geometry": {"coordinates":[2.03627,45.47733],"type":"Point"}
}