{
  "type": "Feature",
  "properties": {
    "gn:admin1_code":"93",
    "gn:admin2_code":"84",
    "gn:admin3_code":"841",
    "gn:admin4_code":"84102",
    "gn:asciiname":"Clavaillan",
    "gn:country_code":"FR",
    "gn:dem":236,
    "gn:feature_class":"P",
    "gn:feature_code":"PPLL",
    "gn:name":"Clavaillan",
    "gn:population":0,
    "gn:timezone":"Europe/Paris",
    "iso:country":"FR",
    "wof:name":"Clavaillan",
    "wof:placetype":"locality"
},
  "geometry": {"coordinates":[5.27775,43.92249],"type":"Point"}
}