{
  "type": "Feature",
  "properties": {
    "gn:admin1_code":"75",
    "gn:admin2_code":"16",
    "gn:admin3_code":"163",
    "gn:admin4_code":"16309",
    "gn:asciiname":"Bouliau",
    "gn:country_code":"FR",
    "gn:dem":99,
    "gn:feature_class":"P",
    "gn:feature_code":"PPL",
    "gn:name":"Bouliau",
    "gn:population":0,
    "gn:timezone":"Europe/Paris",
    "iso:country":"FR",
    "name:und_x_variant":[
        "Chez Bouillaud",
        "Bouliau"
    ],
    "wof:name":"Bouliau",
    "wof:placetype":"locality"
},
  "geometry": {"coordinates":[0.3314,45.83153],"type":"Point"}
}