{
  "type": "Feature",
  "properties": {
    "gn:admin1_code":"94",
    "gn:admin2_code":"2B",
    "gn:admin3_code":"2B2",
    "gn:admin4_code":"2B043",
    "gn:asciiname":"Poretto",
    "gn:country_code":"FR",
    "gn:dem":222,
    "gn:feature_class":"P",
    "gn:feature_code":"PPL",
    "gn:name":"Poretto",
    "gn:population":0,
    "gn:timezone":"Europe/Paris",
    "iso:country":"FR",
    "wof:name":"Poretto",
    "wof:placetype":"locality"
},
  "geometry": {"coordinates":[9.45875,42.76468],"type":"Point"}
}