{
  "type": "Feature",
  "properties": {
    "gn:admin1_code":"53",
    "gn:admin2_code":"56",
    "gn:admin3_code":"561",
    "gn:admin4_code":"56121",
    "gn:asciiname":"Kervarhic",
    "gn:cc2":"FR",
    "gn:country_code":"FR",
    "gn:dem":24,
    "gn:feature_class":"P",
    "gn:feature_code":"PPLL",
    "gn:name":"Kervarhic",
    "gn:population":0,
    "gn:timezone":"Europe/Paris",
    "iso:country":"FR",
    "name:und_x_variant":[
        "Kervaric",
        "Kervarhic"
    ],
    "wof:name":"Kervarhic",
    "wof:placetype":"locality"
},
  "geometry": {"coordinates":[-3.38389,47.74778],"type":"Point"}
}