{
  "type": "Feature",
  "properties": {
    "gn:admin1_code":"24",
    "gn:admin2_code":"28",
    "gn:admin3_code":"281",
    "gn:admin4_code":"28298.0",
    "gn:asciiname":"Boisricheux",
    "gn:country_code":"FR",
    "gn:dem":157,
    "gn:feature_class":"P",
    "gn:feature_code":"PPL",
    "gn:name":"Boisricheux",
    "gn:population":0,
    "gn:timezone":"Europe/Paris",
    "iso:country":"FR",
    "wof:name":"Boisricheux",
    "wof:placetype":"locality"
},
  "geometry": {"coordinates":[1.53455,48.57892],"type":"Point"}
}