{
  "type": "Feature",
  "properties": {
    "gn:admin1_code":"93",
    "gn:admin2_code":"04",
    "gn:admin3_code":"041",
    "gn:admin4_code":"04062",
    "gn:asciiname":"Barraques",
    "gn:cc2":"FR",
    "gn:country_code":"FR",
    "gn:dem":1485,
    "gn:feature_class":"P",
    "gn:feature_code":"PPL",
    "gn:name":"Barraques",
    "gn:population":0,
    "gn:timezone":"Europe/Paris",
    "iso:country":"FR",
    "name:und_x_variant":[
        "Baraques",
        "Barraques"
    ],
    "wof:name":"Barraques",
    "wof:placetype":"locality"
},
  "geometry": {"coordinates":[6.75,44.46667],"type":"Point"}
}