{
  "type": "Feature",
  "properties": {
    "gn:admin1_code":"28",
    "gn:admin2_code":"50",
    "gn:admin3_code":"501",
    "gn:admin4_code":"50188.0",
    "gn:asciiname":"La Besliere",
    "gn:country_code":"FR",
    "gn:dem":104,
    "gn:feature_class":"P",
    "gn:feature_code":"PPL",
    "gn:name":"La Besli\u00e8re",
    "gn:population":0,
    "gn:timezone":"Europe/Paris",
    "iso:country":"FR",
    "name:und_x_variant":[
        "La Besli\u00e8re"
    ],
    "wof:name":"La Besliere",
    "wof:placetype":"locality"
},
  "geometry": {"coordinates":[-1.42865,48.81777],"type":"Point"}
}