{
  "type": "Feature",
  "properties": {
    "gn:admin1_code":"28",
    "gn:admin2_code":"14",
    "gn:admin3_code":"141",
    "gn:admin4_code":"14312",
    "gn:asciiname":"Maisy",
    "gn:country_code":"FR",
    "gn:dem":22,
    "gn:feature_class":"P",
    "gn:feature_code":"PPL",
    "gn:name":"Maisy",
    "gn:population":0,
    "gn:timezone":"Europe/Paris",
    "iso:country":"FR",
    "name:ceb_x_preferred":[
        "Maisy"
    ],
    "name:pol_x_preferred":[
        "Mysia"
    ],
    "name:por_x_preferred":[
        "Maisy"
    ],
    "wof:name":"Maisy",
    "wof:placetype":"locality"
},
  "geometry": {"coordinates":[-1.05514,49.38194],"type":"Point"}
}