{
  "type": "Feature",
  "properties": {
    "gn:admin1_code":"84",
    "gn:admin2_code":"74",
    "gn:admin3_code":"741",
    "gn:admin4_code":"74275",
    "gn:asciiname":"Rovagny",
    "gn:country_code":"FR",
    "gn:dem":838,
    "gn:feature_class":"P",
    "gn:feature_code":"PPL",
    "gn:name":"Rovagny",
    "gn:population":0,
    "gn:timezone":"Europe/Paris",
    "iso:country":"FR",
    "wof:name":"Rovagny",
    "wof:placetype":"locality"
},
  "geometry": {"coordinates":[6.23798,45.82774000000001],"type":"Point"}
}