{
  "type": "Feature",
  "properties": {
    "gn:admin1_code":"24",
    "gn:admin2_code":"28",
    "gn:admin3_code":"281",
    "gn:admin4_code":"28025",
    "gn:asciiname":"Armonville-le-Sablon",
    "gn:country_code":"FR",
    "gn:dem":136,
    "gn:feature_class":"P",
    "gn:feature_code":"PPL",
    "gn:name":"Armonville-le-Sablon",
    "gn:population":0,
    "gn:timezone":"Europe/Paris",
    "iso:country":"FR",
    "name:und_x_variant":[
        "Armonville-Sablon",
        "Armonville-le-Sablon"
    ],
    "wof:name":"Armonville-le-Sablon",
    "wof:placetype":"locality"
},
  "geometry": {"coordinates":[1.9485,48.25379],"type":"Point"}
}