{
  "type": "Feature",
  "properties": {
    "iso:country":"FR",
    "name:bar_x_preferred":[
        "Bellevue"
    ],
    "name:bre_x_preferred":[
        "Bellevue"
    ],
    "name:bul_x_preferred":[
        "\u0411\u0435\u043b\u0432\u044e"
    ],
    "name:cat_x_preferred":[
        "Bellevue"
    ],
    "name:ceb_x_preferred":[
        "Bellevue"
    ],
    "name:dan_x_preferred":[
        "Bellevue"
    ],
    "name:deu_x_preferred":[
        "Bellevue"
    ],
    "name:epo_x_preferred":[
        "Bellevue"
    ],
    "name:eus_x_preferred":[
        "Bellevue"
    ],
    "name:fas_x_preferred":[
        "\u0628\u0644\u0648\u06cc\u0648"
    ],
    "name:fin_x_preferred":[
        "Bellevue"
    ],
    "name:fra_x_preferred":[
        "Bellevue"
    ],
    "name:ita_x_preferred":[
        "Bellevue"
    ],
    "name:jpn_x_preferred":[
        "\u30d9\u30eb\u30d3\u30e5\u30fc"
    ],
    "name:nld_x_preferred":[
        "Bellevue"
    ],
    "name:nor_x_preferred":[
        "Bellevue"
    ],
    "name:pol_x_preferred":[
        "Bellevue"
    ],
    "name:por_x_preferred":[
        "Bellevue"
    ],
    "name:rus_x_preferred":[
        "\u0411\u0435\u043b\u044c\u0432\u044e"
    ],
    "name:spa_x_preferred":[
        "Bellevue"
    ],
    "name:swe_x_preferred":[
        "Bellevue"
    ],
    "name:ukr_x_preferred":[
        "\u0411\u0435\u043b\u044c\u0432\u044e"
    ],
    "name:unk_x_variant":[
        "Bellevue"
    ],
    "name:vol_x_preferred":[
        "Bellevue"
    ],
    "name:zho_x_preferred":[
        "\u8d1d\u5c14\u7ef4\u5c24"
    ],
    "qs:gn_adm0_cc":"FR",
    "qs:gn_fcode":"PPL",
    "qs:gn_local":3030300,
    "qs:gn_nam_loc":"Brest, Brest, Finist\u00e8re, Bretagne, FR",
    "qs:gn_namadm1":"A2",
    "qs:gn_name":"Bellevue",
    "qs:local_max":9262,
    "qs:local_sum":14841,
    "qs:localhoods":7,
    "qs:name":"Bellevue",
    "qs:name_adm0":"France",
    "qs:name_adm1":"Bretagne",
    "qs:name_adm2":"Finist\u00e8re",
    "qs:name_lau":"Brest",
    "qs:name_local":"Brest",
    "qs:photo_max":1338,
    "qs:photo_sum":1802,
    "qs:placetype":"Suburb",
    "qs:quad_count":40,
    "qs:woe_adm0":23424819,
    "qs:woe_adm1":7153313,
    "qs:woe_adm2":12591797,
    "qs:woe_lau":12639848,
    "qs:woe_local":581787,
    "qs:woe_ver":"7.10.0",
    "wof:lang":[
        "fre"
    ],
    "wof:name":"Bellevue",
    "wof:placetype":"neighbourhood"
},
  "geometry": {"coordinates":[-4.523052,48.406576],"type":"Point"}
}