{
  "type": "Feature",
  "properties": {
    "gn:admin1_code":"84",
    "gn:admin2_code":"63",
    "gn:admin3_code":"631",
    "gn:admin4_code":"63230",
    "gn:asciiname":"Virenne",
    "gn:country_code":"FR",
    "gn:dem":1105,
    "gn:feature_class":"P",
    "gn:feature_code":"PPL",
    "gn:name":"Virenne",
    "gn:population":0,
    "gn:timezone":"Europe/Paris",
    "iso:country":"FR",
    "wof:name":"Virenne",
    "wof:placetype":"locality"
},
  "geometry": {"coordinates":[3.64447,45.53592],"type":"Point"}
}