{
  "type": "Feature",
  "properties": {
    "iso:country":"FR",
    "wof:name":"La Pomme",
    "wof:placetype":"neighbourhood"
},
  "geometry": {"coordinates":[5.43698534721341,43.29121275116113],"type":"Point"}
}