{
  "type": "Feature",
  "properties": {
    "iso:country":"FR",
    "qs_pg:aaroncc":"FR",
    "qs_pg:name":"Meudon-la-for\u00eat",
    "qs_pg:name_adm0":"France",
    "qs_pg:name_adm1":"\u00cele-de-France",
    "qs_pg:photos":763,
    "qs_pg:photos_1k":155,
    "qs_pg:photos_9k":3,
    "qs_pg:photos_9r":6,
    "qs_pg:photos_all":763,
    "qs_pg:photos_sr":9,
    "qs_pg:pop_sr":0,
    "qs_pg:qs_pg_placetype":"locality",
    "qs_pg:qs_pg_placetype_gp":"Town",
    "qs_pg:woe_adm0":23424819,
    "woe:adm0_id":23424819,
    "woe:name_adm0":"France",
    "woe:name_adm1":"\u00cele-de-France",
    "woe:placetype":"Town",
    "wof:name":"Meudon-la-for\u00eat",
    "wof:placetype":"neighbourhood"
},
  "geometry": {"coordinates":[2.229881,48.783953],"type":"Point"}
}