{
  "type": "Feature",
  "properties": {
    "gn:admin1_code":"24",
    "gn:admin2_code":"36",
    "gn:admin3_code":"363",
    "gn:admin4_code":"36240",
    "gn:asciiname":"La Chaume",
    "gn:country_code":"FR",
    "gn:dem":433,
    "gn:feature_class":"P",
    "gn:feature_code":"PPL",
    "gn:name":"La Chaume",
    "gn:population":0,
    "gn:timezone":"Europe/Paris",
    "iso:country":"FR",
    "name:bug_x_preferred":[
        "La Chaume"
    ],
    "name:cat_x_preferred":[
        "La Chaume"
    ],
    "name:ceb_x_preferred":[
        "La Chaume"
    ],
    "name:eus_x_preferred":[
        "La Chaume"
    ],
    "name:fra_x_preferred":[
        "La Chaume"
    ],
    "name:hun_x_preferred":[
        "La Chaume"
    ],
    "name:ind_x_preferred":[
        "La Chaume"
    ],
    "name:ita_x_preferred":[
        "La Chaume"
    ],
    "name:kaz_x_preferred":[
        "\u041b\u0430-\u0428\u043e\u043c"
    ],
    "name:lat_x_preferred":[
        "La Chaume"
    ],
    "name:mlg_x_preferred":[
        "La Chaume"
    ],
    "name:msa_x_preferred":[
        "La Chaume"
    ],
    "name:nld_x_preferred":[
        "La Chaume"
    ],
    "name:oci_x_preferred":[
        "La Chaume"
    ],
    "name:pms_x_preferred":[
        "La Chaume"
    ],
    "name:pol_x_preferred":[
        "La Chaume"
    ],
    "name:por_x_preferred":[
        "La Chaume"
    ],
    "name:ron_x_preferred":[
        "La Chaume"
    ],
    "name:rus_x_preferred":[
        "\u041b\u0430-\u0428\u043e\u043c"
    ],
    "name:slk_x_preferred":[
        "La Chaume"
    ],
    "name:spa_x_preferred":[
        "La Chaume"
    ],
    "name:srp_x_preferred":[
        "\u0428\u043e\u043c"
    ],
    "name:swe_x_preferred":[
        "La Chaume"
    ],
    "name:ukr_x_preferred":[
        "\u041b\u0430-\u0428\u043e\u043c"
    ],
    "name:urd_x_preferred":[
        "\u0644\u0627 \u0634\u0648\u0645\u06cc"
    ],
    "name:uzb_x_preferred":[
        "La Chaume"
    ],
    "name:vie_x_preferred":[
        "La Chaume"
    ],
    "name:vol_x_preferred":[
        "La Chaume"
    ],
    "name:war_x_preferred":[
        "La Chaume"
    ],
    "name:zho_x_preferred":[
        "\u62c9\u7ecd\u59c6"
    ],
    "wof:name":"La Chaume",
    "wof:placetype":"locality"
},
  "geometry": {"coordinates":[2.1465,46.43157],"type":"Point"}
}