{
  "type": "Feature",
  "properties": {
    "gn:admin1_code":"52",
    "gn:admin2_code":"72",
    "gn:admin3_code":"721",
    "gn:admin4_code":"72074",
    "gn:asciiname":"Etival",
    "gn:country_code":"FR",
    "gn:dem":136,
    "gn:feature_class":"P",
    "gn:feature_code":"PPL",
    "gn:name":"\u00c9tival",
    "gn:population":0,
    "gn:timezone":"Europe/Paris",
    "iso:country":"FR",
    "wof:name":"Etival",
    "wof:placetype":"locality"
},
  "geometry": {"coordinates":[-0.22664,48.05422],"type":"Point"}
}