{
  "type": "Feature",
  "properties": {
    "gn:admin1_code":"75",
    "gn:admin2_code":"19",
    "gn:admin3_code":"192",
    "gn:admin4_code":"19081",
    "gn:asciiname":"La Jugie",
    "gn:country_code":"FR",
    "gn:dem":592,
    "gn:feature_class":"P",
    "gn:feature_code":"PPL",
    "gn:name":"La Jugie",
    "gn:population":0,
    "gn:timezone":"Europe/Paris",
    "iso:country":"FR",
    "wof:name":"La Jugie",
    "wof:placetype":"locality"
},
  "geometry": {"coordinates":[1.95316,45.32986],"type":"Point"}
}