{
  "type": "Feature",
  "properties": {
    "gn:admin1_code":"75",
    "gn:admin2_code":"24",
    "gn:admin3_code":"243",
    "gn:admin4_code":"24026",
    "gn:asciiname":"Les Mothes",
    "gn:country_code":"FR",
    "gn:dem":249,
    "gn:feature_class":"P",
    "gn:feature_code":"PPL",
    "gn:name":"Les Mothes",
    "gn:population":0,
    "gn:timezone":"Europe/Paris",
    "iso:country":"FR",
    "wof:name":"Les Mothes",
    "wof:placetype":"locality"
},
  "geometry": {"coordinates":[0.88448,45.14558],"type":"Point"}
}