{
  "type": "Feature",
  "properties": {
    "gn:admin1_code":"84",
    "gn:admin2_code":"43",
    "gn:admin3_code":"432",
    "gn:admin4_code":"43135",
    "gn:asciiname":"L'Herm",
    "gn:country_code":"FR",
    "gn:dem":888,
    "gn:feature_class":"P",
    "gn:feature_code":"PPL",
    "gn:name":"L\u2019Herm",
    "gn:population":0,
    "gn:timezone":"Europe/Paris",
    "iso:country":"FR",
    "wof:name":"L'Herm",
    "wof:placetype":"locality"
},
  "geometry": {"coordinates":[3.9705,44.95562],"type":"Point"}
}