{
  "type": "Feature",
  "properties": {
    "gn:admin1_code":"76",
    "gn:admin2_code":"11",
    "gn:admin3_code":"111",
    "gn:admin4_code":"11156",
    "gn:asciiname":"Fraisse-Cabardes",
    "gn:cc2":"FR",
    "gn:country_code":"FR",
    "gn:dem":311,
    "gn:feature_class":"P",
    "gn:feature_code":"PPL",
    "gn:name":"Fraisse-Cabard\u00e8s",
    "gn:population":0,
    "gn:timezone":"Europe/Paris",
    "iso:country":"FR",
    "name:cat_x_preferred":[
        "Fraisse de Cabard\u00e9s"
    ],
    "name:ceb_x_preferred":[
        "Fraisse-Cabard\u00e8s"
    ],
    "name:deu_x_preferred":[
        "Fraisse-Cabard\u00e8s"
    ],
    "name:eus_x_preferred":[
        "Fraisse-Cabard\u00e8s"
    ],
    "name:fra_x_preferred":[
        "Fraisse-Cabard\u00e8s"
    ],
    "name:hun_x_preferred":[
        "Fraisse-Cabard\u00e8s"
    ],
    "name:hye_x_preferred":[
        "\u0556\u0580\u0565\u057d \u053f\u0561\u0562\u0561\u0580\u0564\u0565\u057d"
    ],
    "name:ita_x_preferred":[
        "Fraisse-Cabard\u00e8s"
    ],
    "name:kaz_x_preferred":[
        "\u0424\u0440\u0435\u0441\u0441-\u041a\u0430\u0431\u0430\u0440\u0434\u0435\u0441"
    ],
    "name:lat_x_preferred":[
        "Fraisse-Cabard\u00e8s"
    ],
    "name:lmo_x_preferred":[
        "Fraisse-Cabard\u00e8s"
    ],
    "name:mlg_x_preferred":[
        "Fraisse-Cabard\u00e8s"
    ],
    "name:msa_x_preferred":[
        "Fraisse-Cabard\u00e8s"
    ],
    "name:nld_x_preferred":[
        "Fraisse-Cabard\u00e8s"
    ],
    "name:oci_x_preferred":[
        "Fraisse Cabard\u00e9s"
    ],
    "name:pms_x_preferred":[
        "Fraisse-Cabard\u00e8s"
    ],
    "name:pol_x_preferred":[
        "Fraisse-Cabard\u00e8s"
    ],
    "name:por_x_preferred":[
        "Fraisse-Cabard\u00e8s"
    ],
    "name:ron_x_preferred":[
        "Fraisse-Cabard\u00e8s"
    ],
    "name:rus_x_preferred":[
        "\u0424\u0440\u0435\u0441-\u041a\u0430\u0431\u0430\u0440\u0434\u0435\u0441"
    ],
    "name:slk_x_preferred":[
        "Fraisse-Cabard\u00e8s"
    ],
    "name:spa_x_preferred":[
        "Fraisse-Cabard\u00e8s"
    ],
    "name:srp_x_preferred":[
        "\u0424\u0440\u0435\u0441 \u041a\u0430\u0431\u0430\u0440\u0434\u0435"
    ],
    "name:swe_x_preferred":[
        "Fraisse-Cabard\u00e8s"
    ],
    "name:ukr_x_preferred":[
        "\u0424\u0440\u0435\u0441\u0441-\u041a\u0430\u0431\u0430\u0440\u0434\u0435\u0441"
    ],
    "name:und_x_variant":[
        "Fraisse"
    ],
    "name:vie_x_preferred":[
        "Fraisse-Cabard\u00e8s"
    ],
    "name:vol_x_preferred":[
        "Fraisse-Cabard\u00e8s"
    ],
    "name:war_x_preferred":[
        "Fraisse-Cabard\u00e8s"
    ],
    "name:zho_x_preferred":[
        "\u5f17\u8d56\u65af\u5361\u5df4\u5c14\u4ee3"
    ],
    "name:zho_x_variant":[
        "\u5f17\u8d56\u65af\u5361\u5df4\u5c14\u4ee3\u65af"
    ],
    "wof:name":"Fraisse-Cabardes",
    "wof:placetype":"locality"
},
  "geometry": {"coordinates":[2.2724,43.3251],"type":"Point"}
}