{
  "type": "Feature",
  "properties": {
    "gn:admin1_code":"76",
    "gn:admin2_code":"11",
    "gn:admin3_code":"111",
    "gn:admin4_code":"11156",
    "gn:asciiname":"Fraisse-Cabardes",
    "gn:cc2":"FR",
    "gn:country_code":"FR",
    "gn:dem":311,
    "gn:feature_class":"P",
    "gn:feature_code":"PPL",
    "gn:name":"Fraisse-Cabard\u00e8s",
    "gn:population":0,
    "gn:timezone":"Europe/Paris",
    "iso:country":"FR",
    "name:cat_x_preferred":[
        "Fraisse de Cabard\u00e9s"
    ],
    "name:kaz_x_preferred":[
        "\u0424\u0440\u0435\u0441\u0441-\u041a\u0430\u0431\u0430\u0440\u0434\u0435\u0441"
    ],
    "name:oci_x_preferred":[
        "Fraisse Cabard\u00e9s"
    ],
    "name:rus_x_preferred":[
        "\u0424\u0440\u0435\u0441-\u041a\u0430\u0431\u0430\u0440\u0434\u0435\u0441"
    ],
    "name:srp_x_preferred":[
        "\u0424\u0440\u0435\u0441 \u041a\u0430\u0431\u0430\u0440\u0434\u0435"
    ],
    "name:ukr_x_preferred":[
        "\u0424\u0440\u0435\u0441\u0441-\u041a\u0430\u0431\u0430\u0440\u0434\u0435\u0441"
    ],
    "name:und_x_variant":[
        "Fraisse"
    ],
    "name:zho_x_preferred":[
        "\u5f17\u8d56\u65af\u5361\u5df4\u5c14\u4ee3"
    ],
    "wof:name":"Fraisse-Cabardes",
    "wof:placetype":"locality"
},
  "geometry": {"coordinates":[2.2724,43.3251],"type":"Point"}
}