{
  "type": "Feature",
  "properties": {
    "frgov:code_epci":"200068088",
    "frgov:insee_arr":"3",
    "frgov:insee_com":"58212",
    "frgov:insee_dep":"58",
    "frgov:insee_reg":"27",
    "frgov:nom_com":"Poiseux",
    "frgov:nom_com_m":"POISEUX",
    "frgov:nom_dep":"NIEVRE",
    "frgov:nom_reg":"BOURGOGNE-FRANCHE-COMTE",
    "frgov:statut":"Commune simple",
    "gn:admin1_code":"27",
    "gn:admin2_code":"58",
    "gn:admin3_code":"583",
    "gn:admin4_code":"58212.0",
    "gn:asciiname":"Poiseux",
    "gn:country_code":"FR",
    "gn:dem":206,
    "gn:feature_class":"P",
    "gn:feature_code":"PPL",
    "gn:name":"Poiseux",
    "gn:population":0,
    "gn:timezone":"Europe/Paris",
    "iso:country":"FR",
    "name:cat_x_preferred":[
        "Poiseux"
    ],
    "name:ceb_x_preferred":[
        "Poiseux"
    ],
    "name:deu_x_preferred":[
        "Poiseux"
    ],
    "name:eus_x_preferred":[
        "Poiseux"
    ],
    "name:fra_x_preferred":[
        "Poiseux"
    ],
    "name:hun_x_preferred":[
        "Poiseux"
    ],
    "name:ita_x_preferred":[
        "Poiseux"
    ],
    "name:kaz_x_preferred":[
        "\u041f\u0443\u0430\u0437\u0435"
    ],
    "name:lat_x_preferred":[
        "Poiseux"
    ],
    "name:ltz_x_preferred":[
        "Poiseux"
    ],
    "name:msa_x_preferred":[
        "Poiseux"
    ],
    "name:nld_x_preferred":[
        "Poiseux"
    ],
    "name:oci_x_preferred":[
        "Poiseux"
    ],
    "name:pms_x_preferred":[
        "Poiseux"
    ],
    "name:pol_x_preferred":[
        "Poiseux"
    ],
    "name:por_x_preferred":[
        "Poiseux"
    ],
    "name:ron_x_preferred":[
        "Poiseux"
    ],
    "name:slk_x_preferred":[
        "Poiseux"
    ],
    "name:spa_x_preferred":[
        "Poiseux"
    ],
    "name:swe_x_preferred":[
        "Poiseux"
    ],
    "name:ukr_x_preferred":[
        "\u041f\u0443\u0430\u0437\u0435"
    ],
    "name:uzb_x_preferred":[
        "Poiseux"
    ],
    "name:vie_x_preferred":[
        "Poiseux"
    ],
    "name:vol_x_preferred":[
        "Poiseux"
    ],
    "name:war_x_preferred":[
        "Poiseux"
    ],
    "name:zho_x_preferred":[
        "\u666e\u74e6\u745f"
    ],
    "qs:a0":"France",
    "qs:a1":"NIEVRE",
    "qs:a1_lc":"58",
    "qs:a1r":"BOURGOGNE",
    "qs:a1r_lc":"26",
    "qs:a2_lc":"26",
    "qs:a2r_lc":"3",
    "qs:adm0":"France",
    "qs:adm0_a3":"FRA",
    "qs:la":"POISEUX",
    "qs:la_lc":"58212",
    "qs:level":"localadmin",
    "qs:type":"Commune simple",
    "wof:coterminous":[
        404362613
    ],
    "wof:name":"Poiseux",
    "wof:placetype":"locality",
    "wof:placetype_local":"Commune simple"
},
  "geometry": {"coordinates":[3.23183,47.12031],"type":"Point"}
}