{
  "type": "Feature",
  "properties": {
    "gn:admin1_code":"84",
    "gn:admin2_code":"43",
    "gn:admin3_code":"432",
    "gn:admin4_code":"43192",
    "gn:asciiname":"Cros",
    "gn:country_code":"FR",
    "gn:dem":992,
    "gn:feature_class":"P",
    "gn:feature_code":"PPL",
    "gn:name":"Cros",
    "gn:population":0,
    "gn:timezone":"Europe/Paris",
    "iso:country":"FR",
    "name:ceb_x_preferred":[
        "Cros"
    ],
    "name:deu_x_preferred":[
        "Cros"
    ],
    "name:fra_x_preferred":[
        "Cros"
    ],
    "name:ita_x_preferred":[
        "Cros"
    ],
    "name:nds_x_preferred":[
        "Cros"
    ],
    "name:nld_x_preferred":[
        "Cros"
    ],
    "name:pms_x_preferred":[
        "Cros"
    ],
    "name:pol_x_preferred":[
        "Cros"
    ],
    "name:por_x_preferred":[
        "Cros"
    ],
    "name:rus_x_preferred":[
        "\u041a\u0440\u043e"
    ],
    "name:slk_x_preferred":[
        "Cros"
    ],
    "name:spa_x_preferred":[
        "Cros"
    ],
    "name:srp_x_preferred":[
        "\u041a\u0440\u043e"
    ],
    "name:swe_x_preferred":[
        "Cros"
    ],
    "name:ukr_x_preferred":[
        "\u041a\u0440\u043e\u0441"
    ],
    "name:und_x_variant":[
        "Le Cros",
        "Cros"
    ],
    "wof:name":"Cros",
    "wof:placetype":"locality"
},
  "geometry": {"coordinates":[3.73646,44.8724],"type":"Point"}
}