{
  "type": "Feature",
  "properties": {
    "gn:admin1_code":"93",
    "gn:admin2_code":"84",
    "gn:admin3_code":"843",
    "gn:admin4_code":"84067",
    "gn:asciiname":"Graminier",
    "gn:country_code":"FR",
    "gn:dem":78,
    "gn:feature_class":"P",
    "gn:feature_code":"PPL",
    "gn:name":"Graminier",
    "gn:population":0,
    "gn:timezone":"Europe/Paris",
    "iso:country":"FR",
    "wof:name":"Graminier",
    "wof:placetype":"locality"
},
  "geometry": {"coordinates":[5.01456,44.0608],"type":"Point"}
}