{
  "type": "Feature",
  "properties": {
    "gn:admin1_code":"52",
    "gn:admin2_code":"53",
    "gn:admin3_code":"532",
    "gn:admin4_code":"53048",
    "gn:asciiname":"Boyer",
    "gn:country_code":"FR",
    "gn:dem":111,
    "gn:feature_class":"P",
    "gn:feature_code":"PPL",
    "gn:name":"Boyer",
    "gn:population":0,
    "gn:timezone":"Europe/Paris",
    "iso:country":"FR",
    "name:deu_x_preferred":[
        "Boyer"
    ],
    "wof:name":"Boyer",
    "wof:placetype":"locality"
},
  "geometry": {"coordinates":[-0.89556,48.22086],"type":"Point"}
}