{
  "type": "Feature",
  "properties": {
    "gn:admin1_code":"75",
    "gn:admin2_code":"24",
    "gn:admin3_code":"244",
    "gn:admin4_code":"24516",
    "gn:asciiname":"Les Guarrigues",
    "gn:country_code":"FR",
    "gn:dem":260,
    "gn:feature_class":"P",
    "gn:feature_code":"PPL",
    "gn:name":"Les Guarrigues",
    "gn:population":0,
    "gn:timezone":"Europe/Paris",
    "iso:country":"FR",
    "wof:name":"Les Guarrigues",
    "wof:placetype":"locality"
},
  "geometry": {"coordinates":[1.31667,44.93333],"type":"Point"}
}