{
  "type": "Feature",
  "properties": {
    "gn:admin1_code":"94",
    "gn:admin2_code":"2B",
    "gn:admin3_code":"2B2",
    "gn:admin4_code":"2B281",
    "gn:asciiname":"Torrezza",
    "gn:country_code":"FR",
    "gn:dem":234,
    "gn:feature_class":"P",
    "gn:feature_code":"PPL",
    "gn:name":"Torrezza",
    "gn:population":0,
    "gn:timezone":"Europe/Paris",
    "iso:country":"FR",
    "wof:name":"Torrezza",
    "wof:placetype":"locality"
},
  "geometry": {"coordinates":[9.44744,42.80973],"type":"Point"}
}