{
  "type": "Feature",
  "properties": {
    "gn:admin1_code":"93",
    "gn:admin2_code":"04",
    "gn:admin3_code":"043",
    "gn:admin4_code":"04167",
    "gn:asciiname":"Lambert",
    "gn:country_code":"FR",
    "gn:dem":1127,
    "gn:feature_class":"P",
    "gn:feature_code":"PPL",
    "gn:name":"Lambert",
    "gn:population":0,
    "gn:timezone":"Europe/Paris",
    "iso:country":"FR",
    "wof:name":"Lambert",
    "wof:placetype":"locality"
},
  "geometry": {"coordinates":[6.22109,44.21476],"type":"Point"}
}