{
  "type": "Feature",
  "properties": {
    "gn:admin1_code":"76",
    "gn:admin2_code":"12",
    "gn:admin3_code":"122",
    "gn:admin4_code":"12036",
    "gn:asciiname":"Bussiere",
    "gn:country_code":"FR",
    "gn:dem":774,
    "gn:feature_class":"P",
    "gn:feature_code":"PPL",
    "gn:name":"Bussi\u00e8re",
    "gn:population":0,
    "gn:timezone":"Europe/Paris",
    "iso:country":"FR",
    "wof:name":"Bussiere",
    "wof:placetype":"locality"
},
  "geometry": {"coordinates":[2.69474,44.79317],"type":"Point"}
}