{
  "type": "Feature",
  "properties": {
    "iso:country":"FR",
    "name:eng_x_preferred":[
        "Pointe de Gournay"
    ],
    "name:fra_x_preferred":[
        "Pointe de Gournay"
    ],
    "wof:name":"Pointe de Gournay",
    "wof:placetype":"neighbourhood"
},
  "geometry": {"coordinates":[2.56648620441948,48.87197428118436],"type":"Point"}
}