{
  "type": "Feature",
  "properties": {
    "gn:admin1_code":"93",
    "gn:admin2_code":"13",
    "gn:admin3_code":"131",
    "gn:admin4_code":"13040",
    "gn:asciiname":"La Barque",
    "gn:country_code":"FR",
    "gn:dem":192,
    "gn:feature_class":"P",
    "gn:feature_code":"PPL",
    "gn:name":"La Barque",
    "gn:population":0,
    "gn:timezone":"Europe/Paris",
    "iso:country":"FR",
    "wof:name":"La Barque",
    "wof:placetype":"locality"
},
  "geometry": {"coordinates":[5.53827,43.47827],"type":"Point"}
}