{
  "type": "Feature",
  "properties": {
    "iso:country":"FR",
    "name:eng_x_preferred":[
        "Larue"
    ],
    "name:fra_x_preferred":[
        "Larue"
    ],
    "wof:name":"Larue",
    "wof:placetype":"neighbourhood"
},
  "geometry": {"coordinates":[2.33966964550852,48.76882083900361],"type":"Point"}
}