{
  "type": "Feature",
  "properties": {
    "gn:admin1_code":"53",
    "gn:admin2_code":"56",
    "gn:admin3_code":"561",
    "gn:admin4_code":"56241",
    "gn:asciiname":"Deuborch",
    "gn:country_code":"FR",
    "gn:dem":30,
    "gn:feature_class":"P",
    "gn:feature_code":"PPL",
    "gn:name":"Deuborch",
    "gn:population":0,
    "gn:timezone":"Europe/Paris",
    "iso:country":"FR",
    "wof:name":"Deuborch",
    "wof:placetype":"locality"
},
  "geometry": {"coordinates":[-3.23993,47.37681],"type":"Point"}
}