{
  "type": "Feature",
  "properties": {
    "gn:admin1_code":"76",
    "gn:admin2_code":"30",
    "gn:admin3_code":"302",
    "gn:admin4_code":"30184",
    "gn:asciiname":"Moussac",
    "gn:country_code":"FR",
    "gn:dem":90,
    "gn:feature_class":"P",
    "gn:feature_code":"PPL",
    "gn:name":"Moussac",
    "gn:population":1108,
    "gn:timezone":"Europe/Paris",
    "iso:country":"FR",
    "wof:name":"Moussac",
    "wof:placetype":"locality",
    "wof:population":1108
},
  "geometry": {"coordinates":[4.22647,43.98119000000001],"type":"Point"}
}