{
  "type": "Feature",
  "properties": {
    "gn:admin1_code":"52",
    "gn:admin2_code":"44",
    "gn:admin3_code":"441",
    "gn:admin4_code":"44073",
    "gn:asciiname":"La Jaunais",
    "gn:country_code":"FR",
    "gn:dem":40,
    "gn:feature_class":"P",
    "gn:feature_code":"PPL",
    "gn:name":"La Jaunais",
    "gn:population":0,
    "gn:timezone":"Europe/Paris",
    "iso:country":"FR",
    "wof:name":"La Jaunais",
    "wof:placetype":"locality"
},
  "geometry": {"coordinates":[-1.66667,47.38333],"type":"Point"}
}