{
  "type": "Feature",
  "properties": {
    "gn:admin1_code":"75",
    "gn:admin2_code":"87",
    "gn:admin3_code":"872",
    "gn:admin4_code":"87039",
    "gn:asciiname":"Belie",
    "gn:country_code":"FR",
    "gn:dem":372,
    "gn:feature_class":"P",
    "gn:feature_code":"PPL",
    "gn:name":"B\u00e9lie",
    "gn:population":0,
    "gn:timezone":"Europe/Paris",
    "iso:country":"FR",
    "wof:name":"Belie",
    "wof:placetype":"locality"
},
  "geometry": {"coordinates":[1.33059,45.63298],"type":"Point"}
}