{
  "type": "Feature",
  "properties": {
    "gn:admin1_code":"84",
    "gn:admin2_code":"73",
    "gn:admin3_code":"731",
    "gn:admin4_code":"73003",
    "gn:asciiname":"Bellecombe",
    "gn:cc2":"FR",
    "gn:country_code":"FR",
    "gn:dem":462,
    "gn:feature_class":"P",
    "gn:feature_code":"PPL",
    "gn:name":"Bellecombe",
    "gn:population":0,
    "gn:timezone":"Europe/Paris",
    "iso:country":"FR",
    "name:cat_x_preferred":[
        "Bellecombe"
    ],
    "name:ceb_x_preferred":[
        "Bellecombe"
    ],
    "name:deu_x_preferred":[
        "Bellecombe"
    ],
    "name:eus_x_preferred":[
        "Bellecombe"
    ],
    "name:fra_x_preferred":[
        "Bellecombe"
    ],
    "name:hun_x_preferred":[
        "Bellecombe"
    ],
    "name:ita_x_preferred":[
        "Bellecombe"
    ],
    "name:lat_x_preferred":[
        "Bellecombe"
    ],
    "name:msa_x_preferred":[
        "Bellecombe"
    ],
    "name:nld_x_preferred":[
        "Bellecombe"
    ],
    "name:oci_x_preferred":[
        "Bellecombe"
    ],
    "name:pms_x_preferred":[
        "Bellecombe"
    ],
    "name:pol_x_preferred":[
        "Bellecombe"
    ],
    "name:por_x_preferred":[
        "Bellecombe"
    ],
    "name:slk_x_preferred":[
        "Bellecombe"
    ],
    "name:spa_x_preferred":[
        "Bellecombe"
    ],
    "name:sqi_x_preferred":[
        "Bellecombe"
    ],
    "name:srp_x_preferred":[
        "\u0411\u0435\u043b\u043a\u043e\u043c"
    ],
    "name:swe_x_preferred":[
        "Bellecombe"
    ],
    "name:ukr_x_preferred":[
        "\u0411\u0435\u043b\u044c\u043a\u043e\u043c\u0431"
    ],
    "name:und_x_variant":[
        "Bellecombe-Tarentaise"
    ],
    "name:uzb_x_preferred":[
        "Bellecombe"
    ],
    "name:vie_x_preferred":[
        "Bellecombe"
    ],
    "name:vol_x_preferred":[
        "Bellecombe"
    ],
    "name:war_x_preferred":[
        "Bellecombe"
    ],
    "name:zho_x_preferred":[
        "\u8d1d\u83b1\u5b54\u5e03"
    ],
    "wof:name":"Bellecombe",
    "wof:placetype":"locality"
},
  "geometry": {"coordinates":[6.49704,45.50683],"type":"Point"}
}