{
  "type": "Feature",
  "properties": {
    "gn:admin1_code":"84",
    "gn:admin2_code":"73",
    "gn:admin3_code":"731",
    "gn:admin4_code":"73003",
    "gn:asciiname":"Bellecombe",
    "gn:cc2":"FR",
    "gn:country_code":"FR",
    "gn:dem":462,
    "gn:feature_class":"P",
    "gn:feature_code":"PPL",
    "gn:name":"Bellecombe",
    "gn:population":0,
    "gn:timezone":"Europe/Paris",
    "iso:country":"FR",
    "name:und_x_variant":[
        "Bellecombe-Tarentaise"
    ],
    "wof:name":"Bellecombe",
    "wof:placetype":"locality"
},
  "geometry": {"coordinates":[6.49704,45.50683],"type":"Point"}
}