{
  "type": "Feature",
  "properties": {
    "frgov:code_epci":"200043974",
    "frgov:insee_arr":"3",
    "frgov:insee_com":"33255",
    "frgov:insee_dep":"33",
    "frgov:insee_reg":"75",
    "frgov:nom_com":"Lucmau",
    "frgov:nom_com_m":"LUCMAU",
    "frgov:nom_dep":"GIRONDE",
    "frgov:nom_reg":"NOUVELLE-AQUITAINE",
    "frgov:statut":"Commune simple",
    "gn:admin1_code":"75",
    "gn:admin2_code":"33",
    "gn:admin3_code":"333",
    "gn:admin4_code":"33255",
    "gn:asciiname":"Lucmau",
    "gn:country_code":"FR",
    "gn:dem":80,
    "gn:feature_class":"P",
    "gn:feature_code":"PPL",
    "gn:name":"Lucmau",
    "gn:population":0,
    "gn:timezone":"Europe/Paris",
    "iso:country":"FR",
    "name:bug_x_preferred":[
        "Lucmau"
    ],
    "name:cat_x_preferred":[
        "Luc Mau"
    ],
    "name:cat_x_variant":[
        "Lucmau"
    ],
    "name:ceb_x_preferred":[
        "Lucmau"
    ],
    "name:deu_x_preferred":[
        "Lucmau"
    ],
    "name:eus_x_preferred":[
        "Lucmau"
    ],
    "name:fra_x_preferred":[
        "Lucmau"
    ],
    "name:hun_x_preferred":[
        "Lucmau"
    ],
    "name:ind_x_preferred":[
        "Lucmau"
    ],
    "name:ita_x_preferred":[
        "Lucmau"
    ],
    "name:kaz_x_preferred":[
        "\u041b\u044e\u043a\u043c\u043e"
    ],
    "name:lat_x_preferred":[
        "Lucmau"
    ],
    "name:mlg_x_preferred":[
        "Lucmau"
    ],
    "name:msa_x_preferred":[
        "Lucmau"
    ],
    "name:nld_x_preferred":[
        "Lucmau"
    ],
    "name:oci_x_preferred":[
        "Lucmau"
    ],
    "name:pms_x_preferred":[
        "Lucmau"
    ],
    "name:pol_x_preferred":[
        "Lucmau"
    ],
    "name:por_x_preferred":[
        "Lucmau"
    ],
    "name:ron_x_preferred":[
        "Lucmau"
    ],
    "name:slk_x_preferred":[
        "Lucmau"
    ],
    "name:spa_x_preferred":[
        "Lucmau"
    ],
    "name:swe_x_preferred":[
        "Lucmau"
    ],
    "name:ukr_x_preferred":[
        "\u041b\u044e\u043a\u043c\u043e"
    ],
    "name:uzb_x_preferred":[
        "Lucmau"
    ],
    "name:vie_x_preferred":[
        "Lucmau"
    ],
    "name:vol_x_preferred":[
        "Lucmau"
    ],
    "name:war_x_preferred":[
        "Lucmau"
    ],
    "name:zho_x_preferred":[
        "\u5415\u514b\u83ab"
    ],
    "qs:a0":"France",
    "qs:a1":"GIRONDE",
    "qs:a1_lc":"33",
    "qs:a1r":"AQUITAINE",
    "qs:a1r_lc":"72",
    "qs:a2_lc":"50",
    "qs:a2r_lc":"3",
    "qs:adm0":"France",
    "qs:adm0_a3":"FRA",
    "qs:la":"LUCMAU",
    "qs:la_lc":"33255",
    "qs:level":"localadmin",
    "qs:type":"Commune simple",
    "wof:coterminous":[
        404413265
    ],
    "wof:name":"Lucmau",
    "wof:placetype":"locality",
    "wof:placetype_local":"Commune simple"
},
  "geometry": {"coordinates":[-0.307,44.3421],"type":"Point"}
}