{
  "type": "Feature",
  "properties": {
    "gn:admin1_code":"75",
    "gn:admin2_code":"33",
    "gn:admin3_code":"333",
    "gn:admin4_code":"33255",
    "gn:asciiname":"Lucmau",
    "gn:country_code":"FR",
    "gn:dem":80,
    "gn:feature_class":"P",
    "gn:feature_code":"PPL",
    "gn:name":"Lucmau",
    "gn:population":0,
    "gn:timezone":"Europe/Paris",
    "iso:country":"FR",
    "name:cat_x_preferred":[
        "Luc Mau"
    ],
    "name:kaz_x_preferred":[
        "\u041b\u044e\u043a\u043c\u043e"
    ],
    "name:ukr_x_preferred":[
        "\u041b\u044e\u043a\u043c\u043e"
    ],
    "name:zho_x_preferred":[
        "\u5415\u514b\u83ab"
    ],
    "wof:name":"Lucmau",
    "wof:placetype":"locality"
},
  "geometry": {"coordinates":[-0.307,44.3421],"type":"Point"}
}