{
  "type": "Feature",
  "properties": {
    "gn:admin1_code":"27",
    "gn:admin2_code":"58",
    "gn:admin3_code":"583",
    "gn:admin4_code":"58291",
    "gn:asciiname":"Poisson",
    "gn:country_code":"FR",
    "gn:dem":241,
    "gn:feature_class":"P",
    "gn:feature_code":"PPL",
    "gn:name":"Poisson",
    "gn:population":0,
    "gn:timezone":"Europe/Paris",
    "iso:country":"FR",
    "name:cat_x_preferred":[
        "Poisson"
    ],
    "name:dan_x_preferred":[
        "Poisson"
    ],
    "name:deu_x_preferred":[
        "Poisson"
    ],
    "name:epo_x_preferred":[
        "Poisson"
    ],
    "name:fin_x_preferred":[
        "Poisson"
    ],
    "name:fra_x_preferred":[
        "Poisson"
    ],
    "name:heb_x_preferred":[
        "\u05e4\u05d5\u05d0\u05e1\u05d5\u05df"
    ],
    "name:hun_x_preferred":[
        "Poisson"
    ],
    "name:ita_x_preferred":[
        "Poisson"
    ],
    "name:nld_x_preferred":[
        "Poisson"
    ],
    "name:nor_x_preferred":[
        "Poisson"
    ],
    "name:pol_x_preferred":[
        "Poisson"
    ],
    "name:rus_x_preferred":[
        "\u041f\u0443\u0430\u0441\u0441\u043e\u043d"
    ],
    "name:spa_x_preferred":[
        "Poisson"
    ],
    "name:ukr_x_preferred":[
        "\u041f\u0443\u0430\u0441\u0441\u043e\u043d"
    ],
    "wof:name":"Poisson",
    "wof:placetype":"locality"
},
  "geometry": {"coordinates":[3.51105,46.91631],"type":"Point"}
}