{
  "type": "Feature",
  "properties": {
    "gn:admin1_code":"27",
    "gn:admin2_code":"58",
    "gn:admin3_code":"583",
    "gn:admin4_code":"58291",
    "gn:asciiname":"Poisson",
    "gn:country_code":"FR",
    "gn:dem":241,
    "gn:feature_class":"P",
    "gn:feature_code":"PPL",
    "gn:name":"Poisson",
    "gn:population":0,
    "gn:timezone":"Europe/Paris",
    "iso:country":"FR",
    "wof:name":"Poisson",
    "wof:placetype":"locality"
},
  "geometry": {"coordinates":[3.51105,46.91631],"type":"Point"}
}