{
  "type": "Feature",
  "properties": {
    "gn:admin1_code":"32",
    "gn:admin2_code":"62",
    "gn:admin3_code":"621",
    "gn:admin4_code":"62829",
    "gn:asciiname":"Le Transloy",
    "gn:country_code":"FR",
    "gn:dem":122,
    "gn:feature_class":"P",
    "gn:feature_code":"PPL",
    "gn:name":"Le Transloy",
    "gn:population":0,
    "gn:timezone":"Europe/Paris",
    "iso:country":"FR",
    "wof:name":"Le Transloy",
    "wof:placetype":"locality"
},
  "geometry": {"coordinates":[2.89224,50.05477],"type":"Point"}
}