{
  "type": "Feature",
  "properties": {
    "gn:admin1_code":"76",
    "gn:admin2_code":"48",
    "gn:admin3_code":"482",
    "gn:admin4_code":"48086",
    "gn:asciiname":"Espradels",
    "gn:country_code":"FR",
    "gn:dem":1169,
    "gn:feature_class":"P",
    "gn:feature_code":"PPLL",
    "gn:name":"Espradels",
    "gn:population":0,
    "gn:timezone":"Europe/Paris",
    "iso:country":"FR",
    "name:fra_x_preferred":[
        "Espradel"
    ],
    "wof:name":"Espradels",
    "wof:placetype":"locality"
},
  "geometry": {"coordinates":[3.83464,44.65319],"type":"Point"}
}