{
  "type": "Feature",
  "properties": {
    "gn:admin1_code":"44",
    "gn:admin2_code":"10",
    "gn:admin3_code":"103",
    "gn:admin4_code":"10246",
    "gn:asciiname":"Le Long-du-Bois",
    "gn:country_code":"FR",
    "gn:dem":139,
    "gn:feature_class":"P",
    "gn:feature_code":"PPL",
    "gn:name":"Le Long-du-Bois",
    "gn:population":0,
    "gn:timezone":"Europe/Paris",
    "iso:country":"FR",
    "wof:name":"Le Long-du-Bois",
    "wof:placetype":"locality"
},
  "geometry": {"coordinates":[4.16451,48.14771],"type":"Point"}
}