{
  "type": "Feature",
  "properties": {
    "gn:admin1_code":"84",
    "gn:admin2_code":"38",
    "gn:admin3_code":"383",
    "gn:admin4_code":"38160",
    "gn:asciiname":"Chaumont",
    "gn:country_code":"FR",
    "gn:dem":253,
    "gn:feature_class":"P",
    "gn:feature_code":"PPL",
    "gn:name":"Chaumont",
    "gn:population":0,
    "gn:timezone":"Europe/Paris",
    "iso:country":"FR",
    "wof:name":"Chaumont",
    "wof:placetype":"locality"
},
  "geometry": {"coordinates":[4.98079,45.49894000000001],"type":"Point"}
}