{
  "type": "Feature",
  "properties": {
    "gn:admin1_code":"84",
    "gn:admin2_code":"38",
    "gn:admin3_code":"383",
    "gn:admin4_code":"38160",
    "gn:asciiname":"Chaumont",
    "gn:country_code":"FR",
    "gn:dem":253,
    "gn:feature_class":"P",
    "gn:feature_code":"PPL",
    "gn:name":"Chaumont",
    "gn:population":0,
    "gn:timezone":"Europe/Paris",
    "iso:country":"FR",
    "name:bre_x_preferred":[
        "Chaumont"
    ],
    "name:cat_x_preferred":[
        "Chaumont"
    ],
    "name:ceb_x_preferred":[
        "Chaumont"
    ],
    "name:cym_x_preferred":[
        "Chaumont"
    ],
    "name:deu_x_preferred":[
        "Chaumont"
    ],
    "name:epo_x_preferred":[
        "Chaumont"
    ],
    "name:fra_x_preferred":[
        "Chaumont"
    ],
    "name:ita_x_preferred":[
        "Chaumont"
    ],
    "name:nds_x_preferred":[
        "Chaumont"
    ],
    "name:nld_x_preferred":[
        "Chaumont"
    ],
    "name:oci_x_preferred":[
        "Chaumont"
    ],
    "name:pms_x_preferred":[
        "Chaumont"
    ],
    "name:pol_x_preferred":[
        "Chaumont"
    ],
    "name:por_x_preferred":[
        "Chaumont"
    ],
    "name:ron_x_preferred":[
        "Chaumont"
    ],
    "name:rus_x_preferred":[
        "\u0428\u043e\u043c\u043e\u043d"
    ],
    "name:slk_x_preferred":[
        "Chaumont"
    ],
    "name:spa_x_preferred":[
        "Chaumont"
    ],
    "name:srp_x_preferred":[
        "\u0428\u043e\u043c\u043e\u043d"
    ],
    "name:swe_x_preferred":[
        "Chaumont"
    ],
    "name:ukr_x_preferred":[
        "\u0428\u043e\u043c\u043e\u043d"
    ],
    "name:vie_x_preferred":[
        "Chaumont"
    ],
    "wof:name":"Chaumont",
    "wof:placetype":"locality"
},
  "geometry": {"coordinates":[4.98079,45.49894000000001],"type":"Point"}
}