{
  "type": "Feature",
  "properties": {
    "iso:country":"FR",
    "name:eng_x_preferred":[
        "Sorano"
    ],
    "name:fra_x_preferred":[
        "Sorano"
    ],
    "wof:name":"Sorano",
    "wof:placetype":"neighbourhood"
},
  "geometry": {"coordinates":[2.44006299130978,48.85099820197217],"type":"Point"}
}