{
  "type": "Feature",
  "properties": {
    "gn:admin1_code":"44",
    "gn:admin2_code":"10",
    "gn:admin3_code":"103",
    "gn:admin4_code":"10201",
    "gn:asciiname":"Pomblin",
    "gn:country_code":"FR",
    "gn:dem":133,
    "gn:feature_class":"P",
    "gn:feature_code":"PPL",
    "gn:name":"Pomblin",
    "gn:population":0,
    "gn:timezone":"Europe/Paris",
    "iso:country":"FR",
    "name:und_x_variant":[
        "Pont-Belin",
        "Pomblin"
    ],
    "wof:name":"Pomblin",
    "wof:placetype":"locality"
},
  "geometry": {"coordinates":[4.0464,48.0618],"type":"Point"}
}