{
  "type": "Feature",
  "properties": {
    "gn:admin1_code":"76",
    "gn:admin2_code":"46",
    "gn:admin3_code":"462",
    "gn:admin4_code":"46015",
    "gn:asciiname":"Lauzeral",
    "gn:country_code":"FR",
    "gn:dem":284,
    "gn:feature_class":"P",
    "gn:feature_code":"PPL",
    "gn:name":"Lauzeral",
    "gn:population":0,
    "gn:timezone":"Europe/Paris",
    "iso:country":"FR",
    "wof:name":"Lauzeral",
    "wof:placetype":"locality"
},
  "geometry": {"coordinates":[2.14032,44.64011],"type":"Point"}
}