{
  "type": "Feature",
  "properties": {
    "iso:country":"FR",
    "name:eng_x_preferred":[
        "Centre-Ville"
    ],
    "name:fra_x_preferred":[
        "Centre-Ville"
    ],
    "wof:name":"Centre-Ville",
    "wof:placetype":"neighbourhood"
},
  "geometry": {"coordinates":[2.27135020307201,48.82488138879427],"type":"Point"}
}