{
  "type": "Feature",
  "properties": {
    "gn:admin1_code":"84",
    "gn:admin2_code":"38",
    "gn:admin3_code":"381",
    "gn:admin4_code":"38133",
    "gn:asciiname":"La Tivolliere",
    "gn:country_code":"FR",
    "gn:dem":405,
    "gn:feature_class":"P",
    "gn:feature_code":"PPL",
    "gn:name":"La Tivolli\u00e8re",
    "gn:population":0,
    "gn:timezone":"Europe/Paris",
    "iso:country":"FR",
    "name:und_x_variant":[
        "la Thivolli\u00e8re",
        "La Tivolli\u00e8re"
    ],
    "wof:name":"La Tivolliere",
    "wof:placetype":"locality"
},
  "geometry": {"coordinates":[5.61739,45.36747],"type":"Point"}
}