{
  "type": "Feature",
  "properties": {
    "gn:admin1_code":"75",
    "gn:admin2_code":"19",
    "gn:admin3_code":"191",
    "gn:admin4_code":"19198",
    "gn:asciiname":"La Ribiere",
    "gn:country_code":"FR",
    "gn:dem":348,
    "gn:feature_class":"P",
    "gn:feature_code":"PPL",
    "gn:name":"La Ribi\u00e8re",
    "gn:population":0,
    "gn:timezone":"Europe/Paris",
    "iso:country":"FR",
    "wof:name":"La Ribiere",
    "wof:placetype":"locality"
},
  "geometry": {"coordinates":[1.28569,45.45832],"type":"Point"}
}