{
  "type": "Feature",
  "properties": {
    "gn:admin1_code":"76",
    "gn:admin2_code":"12",
    "gn:admin3_code":"122",
    "gn:admin4_code":"12156",
    "gn:asciiname":"Les Bessades",
    "gn:country_code":"FR",
    "gn:dem":791,
    "gn:feature_class":"P",
    "gn:feature_code":"PPL",
    "gn:name":"Les Bessades",
    "gn:population":0,
    "gn:timezone":"Europe/Paris",
    "iso:country":"FR",
    "wof:name":"Les Bessades",
    "wof:placetype":"locality"
},
  "geometry": {"coordinates":[2.71627,44.63178],"type":"Point"}
}