{
  "type": "Feature",
  "properties": {
    "gn:gn_country":"FR",
    "gn:gn_fcode":"PPL",
    "gn:gn_pop":508,
    "gn:population":508,
    "iso:country":"FR",
    "name:cat_x_preferred":[
        "Neuilly-sur-Eure"
    ],
    "name:ceb_x_preferred":[
        "Neuilly-sur-Eure"
    ],
    "name:deu_x_preferred":[
        "Neuilly-sur-Eure"
    ],
    "name:eus_x_preferred":[
        "Neuilly-sur-Eure"
    ],
    "name:fra_x_preferred":[
        "Neuilly-sur-Eure"
    ],
    "name:hun_x_preferred":[
        "Neuilly-sur-Eure"
    ],
    "name:ind_x_preferred":[
        "Neuilly-sur-Eure"
    ],
    "name:ita_x_preferred":[
        "Neuilly-sur-Eure"
    ],
    "name:kaz_x_preferred":[
        "\u041d\u0435\u0438-\u0441\u044e\u0440-\u0415\u0440"
    ],
    "name:lat_x_preferred":[
        "Neuilly-sur-Eure"
    ],
    "name:mlg_x_preferred":[
        "Neuilly-sur-Eure"
    ],
    "name:msa_x_preferred":[
        "Neuilly-sur-Eure"
    ],
    "name:nld_x_preferred":[
        "Neuilly-sur-Eure"
    ],
    "name:oci_x_preferred":[
        "Neuilly-sur-Eure"
    ],
    "name:pms_x_preferred":[
        "Neuilly-sur-Eure"
    ],
    "name:pol_x_preferred":[
        "Neuilly-sur-Eure"
    ],
    "name:por_x_preferred":[
        "Neuilly-sur-Eure"
    ],
    "name:ron_x_preferred":[
        "Neuilly-sur-Eure"
    ],
    "name:slk_x_preferred":[
        "Neuilly-sur-Eure"
    ],
    "name:spa_x_preferred":[
        "Neuilly-sur-Eure"
    ],
    "name:swe_x_preferred":[
        "Neuilly-sur-Eure"
    ],
    "name:ukr_x_preferred":[
        "\u041d\u0435\u0457-\u0441\u044e\u0440-\u0415\u0440"
    ],
    "name:unk_x_variant":[
        "Neuilly"
    ],
    "name:uzb_x_preferred":[
        "Neuilly-sur-Eure"
    ],
    "name:vie_x_preferred":[
        "Neuilly-sur-Eure"
    ],
    "name:vol_x_preferred":[
        "Neuilly-sur-Eure"
    ],
    "name:war_x_preferred":[
        "Neuilly-sur-Eure"
    ],
    "name:zho_x_preferred":[
        "\u5384\u5c14\u6cb3\u7554\u8bb7\u4f0a"
    ],
    "qs_pg:aaroncc":"FR",
    "qs_pg:gn_country":"FR",
    "qs_pg:gn_fcode":"PPL",
    "qs_pg:gn_pop":508,
    "qs_pg:name":"Neuilly-sur-Eure",
    "qs_pg:name_adm0":"France",
    "qs_pg:name_adm1":"Basse-Normandie",
    "qs_pg:photos_9r":0,
    "qs_pg:photos_sr":0,
    "qs_pg:pop_sr":2,
    "qs_pg:qs_pg_placetype":"locality",
    "qs_pg:qs_pg_placetype_gp":"Town",
    "qs_pg:woe_adm0":23424819,
    "woe:adm0_id":23424819,
    "woe:name_adm0":"France",
    "woe:name_adm1":"Basse-Normandie",
    "woe:placetype":"Town",
    "wof:name":"Neuilly-sur-Eure",
    "wof:placetype":"neighbourhood",
    "wof:population":508
},
  "geometry": {"coordinates":[0.90403,48.54197],"type":"Point"}
}