{
  "type": "Feature",
  "properties": {
    "gn:admin1_code":"84",
    "gn:admin2_code":"38",
    "gn:admin3_code":"381",
    "gn:admin4_code":"38456",
    "gn:asciiname":"Chalanne",
    "gn:country_code":"FR",
    "gn:dem":811,
    "gn:feature_class":"P",
    "gn:feature_code":"PPL",
    "gn:name":"Chalanne",
    "gn:population":0,
    "gn:timezone":"Europe/Paris",
    "iso:country":"FR",
    "wof:name":"Chalanne",
    "wof:placetype":"locality"
},
  "geometry": {"coordinates":[5.85,44.83333],"type":"Point"}
}