{
  "type": "Feature",
  "properties": {
    "gn:admin1_code":"93",
    "gn:admin2_code":"05",
    "gn:admin3_code":"052",
    "gn:admin4_code":"05045",
    "gn:asciiname":"Le Bois",
    "gn:country_code":"FR",
    "gn:dem":1077,
    "gn:feature_class":"P",
    "gn:feature_code":"PPL",
    "gn:name":"Le Bois",
    "gn:population":0,
    "gn:timezone":"Europe/Paris",
    "iso:country":"FR",
    "wof:name":"Le Bois",
    "wof:placetype":"locality"
},
  "geometry": {"coordinates":[6.4453,44.51416],"type":"Point"}
}