{
  "type": "Feature",
  "properties": {
    "gn:admin1_code":"93",
    "gn:admin2_code":"05",
    "gn:admin3_code":"052",
    "gn:admin4_code":"05045",
    "gn:asciiname":"Le Bois",
    "gn:country_code":"FR",
    "gn:dem":1077,
    "gn:feature_class":"P",
    "gn:feature_code":"PPL",
    "gn:name":"Le Bois",
    "gn:population":0,
    "gn:timezone":"Europe/Paris",
    "iso:country":"FR",
    "name:cat_x_preferred":[
        "Le Bois"
    ],
    "name:ceb_x_preferred":[
        "Le Bois"
    ],
    "name:deu_x_preferred":[
        "Le Bois"
    ],
    "name:eus_x_preferred":[
        "Le Bois"
    ],
    "name:fas_x_preferred":[
        "\u0644 \u0628\u0648\u06cc\u0633"
    ],
    "name:fra_x_preferred":[
        "Le Bois"
    ],
    "name:hun_x_preferred":[
        "Le Bois"
    ],
    "name:ita_x_preferred":[
        "Le Bois"
    ],
    "name:lat_x_preferred":[
        "Boschus"
    ],
    "name:lmo_x_preferred":[
        "Le Bois"
    ],
    "name:msa_x_preferred":[
        "Le Bois"
    ],
    "name:nld_x_preferred":[
        "Le Bois"
    ],
    "name:oci_x_preferred":[
        "Le Bois"
    ],
    "name:pol_x_preferred":[
        "Le Bois"
    ],
    "name:ron_x_preferred":[
        "Le Bois"
    ],
    "name:slk_x_preferred":[
        "Le Bois"
    ],
    "name:spa_x_preferred":[
        "Le Bois"
    ],
    "name:srp_x_preferred":[
        "\u0411\u043e\u0430"
    ],
    "name:swe_x_preferred":[
        "Le Bois"
    ],
    "name:ukr_x_preferred":[
        "\u041b\u0435-\u0411\u0443\u0430"
    ],
    "name:uzb_x_preferred":[
        "Le Bois"
    ],
    "name:vie_x_preferred":[
        "Le Bois"
    ],
    "name:vol_x_preferred":[
        "Le Bois"
    ],
    "name:war_x_preferred":[
        "Le Bois"
    ],
    "wof:name":"Le Bois",
    "wof:placetype":"locality"
},
  "geometry": {"coordinates":[6.4453,44.51416],"type":"Point"}
}