{
  "type": "Feature",
  "properties": {
    "gn:admin1_code":"84",
    "gn:admin2_code":"63",
    "gn:admin3_code":"634",
    "gn:admin4_code":"63281",
    "gn:asciiname":"Le Mont",
    "gn:country_code":"FR",
    "gn:dem":565,
    "gn:feature_class":"P",
    "gn:feature_code":"PPL",
    "gn:name":"Le Mont",
    "gn:population":0,
    "gn:timezone":"Europe/Paris",
    "iso:country":"FR",
    "wof:name":"Le Mont",
    "wof:placetype":"locality"
},
  "geometry": {"coordinates":[2.68356,46.09936],"type":"Point"}
}