{
  "type": "Feature",
  "properties": {
    "gn:admin1_code":"75",
    "gn:admin2_code":"24",
    "gn:admin3_code":"244",
    "gn:admin4_code":"24261",
    "gn:asciiname":"Miremont",
    "gn:country_code":"FR",
    "gn:dem":134,
    "gn:feature_class":"P",
    "gn:feature_code":"PPL",
    "gn:name":"Miremont",
    "gn:population":0,
    "gn:timezone":"Europe/Paris",
    "iso:country":"FR",
    "wof:name":"Miremont",
    "wof:placetype":"locality"
},
  "geometry": {"coordinates":[0.94258,44.99343],"type":"Point"}
}