{
  "type": "Feature",
  "properties": {
    "gn:admin1_code":"75",
    "gn:admin2_code":"24",
    "gn:admin3_code":"244",
    "gn:admin4_code":"24261",
    "gn:asciiname":"Miremont",
    "gn:country_code":"FR",
    "gn:dem":134,
    "gn:feature_class":"P",
    "gn:feature_code":"PPL",
    "gn:name":"Miremont",
    "gn:population":0,
    "gn:timezone":"Europe/Paris",
    "iso:country":"FR",
    "name:arg_x_preferred":[
        "Miremont"
    ],
    "name:ceb_x_preferred":[
        "Miremont"
    ],
    "name:deu_x_preferred":[
        "Miremont"
    ],
    "name:fra_x_preferred":[
        "Miremont"
    ],
    "name:hun_x_preferred":[
        "Miremont"
    ],
    "name:ita_x_preferred":[
        "Miremont"
    ],
    "name:nds_x_preferred":[
        "Miremont"
    ],
    "name:nld_x_preferred":[
        "Miremont"
    ],
    "name:pol_x_preferred":[
        "Miremont"
    ],
    "name:por_x_preferred":[
        "Miremont"
    ],
    "name:rus_x_preferred":[
        "\u041c\u0438\u0440\u043c\u043e\u043d"
    ],
    "name:slk_x_preferred":[
        "Miremont"
    ],
    "name:spa_x_preferred":[
        "Miremont"
    ],
    "name:swe_x_preferred":[
        "Miremont"
    ],
    "name:ukr_x_preferred":[
        "\u041c\u0456\u0440\u043c\u043e\u043d"
    ],
    "wof:name":"Miremont",
    "wof:placetype":"locality"
},
  "geometry": {"coordinates":[0.94258,44.99343],"type":"Point"}
}