{
  "type": "Feature",
  "properties": {
    "gn:admin1_code":"24",
    "gn:admin2_code":"36",
    "gn:admin3_code":"362",
    "gn:admin4_code":"36235.0",
    "gn:asciiname":"Les Gauthiers",
    "gn:country_code":"FR",
    "gn:dem":127,
    "gn:feature_class":"P",
    "gn:feature_code":"PPL",
    "gn:name":"Les Gauthiers",
    "gn:population":0,
    "gn:timezone":"Europe/Paris",
    "iso:country":"FR",
    "wof:name":"Les Gauthiers",
    "wof:placetype":"locality"
},
  "geometry": {"coordinates":[1.52824,47.13472],"type":"Point"}
}