{
  "type": "Feature",
  "properties": {
    "gn:admin1_code":"75",
    "gn:admin2_code":"24",
    "gn:admin3_code":"243",
    "gn:admin4_code":"24053",
    "gn:asciiname":"Clavieras",
    "gn:country_code":"FR",
    "gn:dem":208,
    "gn:feature_class":"P",
    "gn:feature_code":"PPL",
    "gn:name":"Clavieras",
    "gn:population":0,
    "gn:timezone":"Europe/Paris",
    "iso:country":"FR",
    "wof:name":"Clavieras",
    "wof:placetype":"locality"
},
  "geometry": {"coordinates":[0.81222,45.11836],"type":"Point"}
}