{
  "type": "Feature",
  "properties": {
    "iso:country":"FR",
    "name:eng_x_preferred":[
        "Mikado"
    ],
    "name:fra_x_preferred":[
        "Mikado"
    ],
    "wof:name":"Mikado",
    "wof:placetype":"neighbourhood"
},
  "geometry": {"coordinates":[2.56594500137117,48.95385661650246],"type":"Point"}
}