{
  "type": "Feature",
  "properties": {
    "gn:admin1_code":"75",
    "gn:admin2_code":"87",
    "gn:admin3_code":"871",
    "gn:admin4_code":"87139",
    "gn:asciiname":"Pont Saint-Martin",
    "gn:country_code":"FR",
    "gn:dem":210,
    "gn:feature_class":"P",
    "gn:feature_code":"PPL",
    "gn:name":"Pont Saint-Martin",
    "gn:population":0,
    "gn:timezone":"Europe/Paris",
    "iso:country":"FR",
    "wof:name":"Pont Saint-Martin",
    "wof:placetype":"locality"
},
  "geometry": {"coordinates":[0.94529,46.18565],"type":"Point"}
}