{
  "type": "Feature",
  "properties": {
    "gn:admin1_code":"53",
    "gn:admin2_code":"35",
    "gn:admin3_code":"353",
    "gn:admin4_code":"35208",
    "gn:asciiname":"Reuzel",
    "gn:cc2":"FR",
    "gn:country_code":"FR",
    "gn:dem":106,
    "gn:feature_class":"P",
    "gn:feature_code":"PPL",
    "gn:name":"Reuzel",
    "gn:population":0,
    "gn:timezone":"Europe/Paris",
    "iso:country":"FR",
    "name:und_x_variant":[
        "Heuzel",
        "Reuzel"
    ],
    "wof:name":"Reuzel",
    "wof:placetype":"locality"
},
  "geometry": {"coordinates":[-1.68333,47.96667],"type":"Point"}
}