{
  "type": "Feature",
  "properties": {
    "gn:admin1_code":"44",
    "gn:admin2_code":"08",
    "gn:admin3_code":"084",
    "gn:admin4_code":"08045",
    "gn:asciiname":"Claire-Fontaine",
    "gn:country_code":"FR",
    "gn:dem":120,
    "gn:feature_class":"P",
    "gn:feature_code":"PPL",
    "gn:name":"Claire-Fontaine",
    "gn:population":0,
    "gn:timezone":"Europe/Paris",
    "iso:country":"FR",
    "wof:name":"Claire-Fontaine",
    "wof:placetype":"locality"
},
  "geometry": {"coordinates":[4.73918,49.42811],"type":"Point"}
}