{
  "type": "Feature",
  "properties": {
    "gn:admin1_code":"84",
    "gn:admin2_code":"43",
    "gn:admin3_code":"431",
    "gn:admin4_code":"43237",
    "gn:asciiname":"La Vernede",
    "gn:country_code":"FR",
    "gn:dem":1071,
    "gn:feature_class":"P",
    "gn:feature_code":"PPL",
    "gn:name":"La Vern\u00e8de",
    "gn:population":0,
    "gn:timezone":"Europe/Paris",
    "iso:country":"FR",
    "wof:name":"La Vernede",
    "wof:placetype":"locality"
},
  "geometry": {"coordinates":[3.70736,45.28353],"type":"Point"}
}