{
  "type": "Feature",
  "properties": {
    "gn:admin1_code":"53",
    "gn:admin2_code":"29",
    "gn:admin3_code":"291",
    "gn:admin4_code":"29019",
    "gn:asciiname":"Kervalguen",
    "gn:country_code":"FR",
    "gn:dem":94,
    "gn:feature_class":"P",
    "gn:feature_code":"PPL",
    "gn:name":"Kervalguen",
    "gn:population":0,
    "gn:timezone":"Europe/Paris",
    "iso:country":"FR",
    "wof:name":"Kervalguen",
    "wof:placetype":"locality"
},
  "geometry": {"coordinates":[-4.51075,48.44992],"type":"Point"}
}