{
  "type": "Feature",
  "properties": {
    "iso:country":"FR",
    "wof:name":"Plaine des Bouchers",
    "wof:placetype":"neighbourhood"
},
  "geometry": {"coordinates":[7.74189589311104,48.55986584498208],"type":"Point"}
}