{
  "type": "Feature",
  "properties": {
    "iso:country":"FR",
    "name:fra_x_preferred":[
        "Cavale Blanche"
    ],
    "name:unk_x_variant":[
        "Cavale Blanche"
    ],
    "qs:gn_adm0_cc":"FR",
    "qs:gn_local":3030300,
    "qs:gn_nam_loc":"Brest, Brest, Finist\u00e8re, Bretagne, FR",
    "qs:gn_namadm1":"A2",
    "qs:local_max":9262,
    "qs:local_sum":14841,
    "qs:localhoods":7,
    "qs:name":"Cavale Blanche",
    "qs:name_adm0":"France",
    "qs:name_adm1":"Bretagne",
    "qs:name_adm2":"Finist\u00e8re",
    "qs:name_lau":"Brest",
    "qs:name_local":"Brest",
    "qs:photo_max":58,
    "qs:photo_sum":177,
    "qs:placetype":"Suburb",
    "qs:quad_count":15,
    "qs:woe_adm0":23424819,
    "qs:woe_adm1":7153313,
    "qs:woe_adm2":12591797,
    "qs:woe_lau":12639848,
    "qs:woe_local":581787,
    "qs:woe_ver":"7.10.0",
    "wof:lang":[
        "fre"
    ],
    "wof:name":"Cavale Blanche",
    "wof:placetype":"neighbourhood"
},
  "geometry": {"coordinates":[-4.540767,48.403102],"type":"Point"}
}