{
  "type": "Feature",
  "properties": {
    "gn:admin1_code":"75",
    "gn:admin2_code":"87",
    "gn:admin3_code":"872",
    "gn:admin4_code":"87191",
    "gn:asciiname":"Villeneuve",
    "gn:country_code":"FR",
    "gn:dem":399,
    "gn:feature_class":"P",
    "gn:feature_code":"PPL",
    "gn:name":"Villeneuve",
    "gn:population":0,
    "gn:timezone":"Europe/Paris",
    "iso:country":"FR",
    "wof:name":"Villeneuve",
    "wof:placetype":"locality"
},
  "geometry": {"coordinates":[1.03166,45.77412],"type":"Point"}
}