{
  "type": "Feature",
  "properties": {
    "gn:admin1_code":"28",
    "gn:admin2_code":"14",
    "gn:admin3_code":"141",
    "gn:admin4_code":"14342.0",
    "gn:asciiname":"Mestry",
    "gn:country_code":"FR",
    "gn:dem":28,
    "gn:feature_class":"P",
    "gn:feature_code":"PPL",
    "gn:name":"Mestry",
    "gn:population":0,
    "gn:timezone":"Europe/Paris",
    "iso:country":"FR",
    "wof:name":"Mestry",
    "wof:placetype":"locality"
},
  "geometry": {"coordinates":[-0.99502,49.2788],"type":"Point"}
}