{
  "type": "Feature",
  "properties": {
    "gn:admin1_code":"44",
    "gn:admin2_code":"57",
    "gn:admin3_code":"575",
    "gn:admin4_code":"57680",
    "gn:asciiname":"Vallerysthal",
    "gn:country_code":"FR",
    "gn:dem":355,
    "gn:feature_class":"P",
    "gn:feature_code":"PPL",
    "gn:name":"Vall\u00e9rysthal",
    "gn:population":0,
    "gn:timezone":"Europe/Paris",
    "iso:country":"FR",
    "name:und_x_variant":[
        "Wallerysthal",
        "Valleryshal",
        "Vallerysthal-Trois-Fontaines",
        "Vallerysthal",
        "Vall\u00e9rysthal"
    ],
    "wof:name":"Vallerysthal",
    "wof:placetype":"locality"
},
  "geometry": {"coordinates":[7.12876,48.6771],"type":"Point"}
}