{
  "type": "Feature",
  "properties": {
    "gn:admin1_code":"84",
    "gn:admin2_code":"26",
    "gn:admin3_code":"261",
    "gn:admin4_code":"26178",
    "gn:asciiname":"Luzerand",
    "gn:country_code":"FR",
    "gn:dem":590,
    "gn:feature_class":"P",
    "gn:feature_code":"PPL",
    "gn:name":"Luzerand",
    "gn:population":0,
    "gn:timezone":"Europe/Paris",
    "iso:country":"FR",
    "wof:name":"Luzerand",
    "wof:placetype":"locality"
},
  "geometry": {"coordinates":[5.45718,44.65041],"type":"Point"}
}