{
  "type": "Feature",
  "properties": {
    "gn:admin1_code":"24",
    "gn:admin2_code":"36",
    "gn:admin3_code":"363",
    "gn:admin4_code":"36184",
    "gn:asciiname":"Les Blins",
    "gn:country_code":"FR",
    "gn:dem":260,
    "gn:feature_class":"P",
    "gn:feature_code":"PPL",
    "gn:name":"Les Blins",
    "gn:population":0,
    "gn:timezone":"Europe/Paris",
    "iso:country":"FR",
    "wof:name":"Les Blins",
    "wof:placetype":"locality"
},
  "geometry": {"coordinates":[1.984,46.67667],"type":"Point"}
}