{
  "type": "Feature",
  "properties": {
    "gn:country":"FR",
    "gn:fcode":"PPL",
    "gn:population":316,
    "iso:country":"FR",
    "qs_pg:aaroncc":"FR",
    "qs_pg:gn_country":"FR",
    "qs_pg:gn_fcode":"PPL",
    "qs_pg:gn_pop":316,
    "qs_pg:name":"Lutran",
    "qs_pg:name_adm0":"France",
    "qs_pg:name_adm1":"Alsace",
    "qs_pg:photos_9r":0,
    "qs_pg:photos_sr":0,
    "qs_pg:pop_sr":2,
    "qs_pg:qs_pg_placetype":"locality",
    "qs_pg:qs_pg_placetype_gp":"Town",
    "qs_pg:woe_adm0":23424819,
    "woe:adm0_id":23424819,
    "woe:name_adm0":"France",
    "woe:name_adm1":"Alsace",
    "woe:placetype":"Town",
    "wof:name":"Lutran",
    "wof:placetype":"neighbourhood",
    "wof:population":316
},
  "geometry": {"coordinates":[7.05661,47.62421],"type":"Point"}
}