{
  "type": "Feature",
  "properties": {
    "gn:admin1_code":"44",
    "gn:admin2_code":"67",
    "gn:admin3_code":"673",
    "gn:admin4_code":"67299",
    "gn:asciiname":"Meyerhof",
    "gn:country_code":"FR",
    "gn:dem":355,
    "gn:feature_class":"P",
    "gn:feature_code":"PPL",
    "gn:name":"Meyerhof",
    "gn:population":0,
    "gn:timezone":"Europe/Paris",
    "iso:country":"FR",
    "wof:name":"Meyerhof",
    "wof:placetype":"locality"
},
  "geometry": {"coordinates":[7.38379,48.49996],"type":"Point"}
}