{
  "type": "Feature",
  "properties": {
    "gn:admin1_code":"28",
    "gn:admin2_code":"76",
    "gn:admin3_code":"762",
    "gn:admin4_code":"76663.0",
    "gn:asciiname":"Le Hetre",
    "gn:country_code":"FR",
    "gn:dem":94,
    "gn:feature_class":"P",
    "gn:feature_code":"PPL",
    "gn:name":"Le H\u00eatre",
    "gn:population":0,
    "gn:timezone":"Europe/Paris",
    "iso:country":"FR",
    "wof:name":"Le Hetre",
    "wof:placetype":"locality"
},
  "geometry": {"coordinates":[0.52098,49.79098],"type":"Point"}
}