{
  "type": "Feature",
  "properties": {
    "gn:admin1_code":"53",
    "gn:admin2_code":"29",
    "gn:admin3_code":"292",
    "gn:admin4_code":"29042",
    "gn:asciiname":"St.-Norgard",
    "gn:country_code":"FR",
    "gn:dem":103,
    "gn:feature_class":"P",
    "gn:feature_code":"PPL",
    "gn:name":"St.-Norgard",
    "gn:population":0,
    "gn:timezone":"Europe/Paris",
    "iso:country":"FR",
    "wof:name":"St.-Norgard",
    "wof:placetype":"locality"
},
  "geometry": {"coordinates":[-4.52735,48.19356],"type":"Point"}
}