{
  "type": "Feature",
  "properties": {
    "gn:admin1_code":"32",
    "gn:admin2_code":"80",
    "gn:admin3_code":"802",
    "gn:admin4_code":"80066",
    "gn:asciiname":"Beaucourt-sur-l'Hallue",
    "gn:country_code":"FR",
    "gn:dem":77,
    "gn:feature_class":"P",
    "gn:feature_code":"PPL",
    "gn:name":"Beaucourt-sur-l\u2019Hallue",
    "gn:population":0,
    "gn:timezone":"Europe/Paris",
    "iso:country":"FR",
    "name:und_x_variant":[
        "Beaucourt",
        "Beaucourt-sur-l\u2019Hallue"
    ],
    "wof:name":"Beaucourt-sur-l'Hallue",
    "wof:placetype":"locality"
},
  "geometry": {"coordinates":[2.44402,49.98982],"type":"Point"}
}