{
  "type": "Feature",
  "properties": {
    "gn:admin1_code":"32",
    "gn:admin2_code":"80",
    "gn:admin3_code":"802",
    "gn:admin4_code":"80066",
    "gn:asciiname":"Beaucourt-sur-l'Hallue",
    "gn:country_code":"FR",
    "gn:dem":77,
    "gn:feature_class":"P",
    "gn:feature_code":"PPL",
    "gn:name":"Beaucourt-sur-l\u2019Hallue",
    "gn:population":0,
    "gn:timezone":"Europe/Paris",
    "iso:country":"FR",
    "name:bug_x_preferred":[
        "Beaucourt-sur-l'Hallue"
    ],
    "name:cat_x_preferred":[
        "Beaucourt-sur-l'Hallue"
    ],
    "name:ceb_x_preferred":[
        "Beaucourt-sur-l'Hallue"
    ],
    "name:deu_x_preferred":[
        "Beaucourt-sur-l\u2019Hallue"
    ],
    "name:eus_x_preferred":[
        "Beaucourt-sur-l'Hallue"
    ],
    "name:fra_x_preferred":[
        "Beaucourt-sur-l'Hallue"
    ],
    "name:hun_x_preferred":[
        "Beaucourt-sur-l\u2019Hallue"
    ],
    "name:ita_x_preferred":[
        "Beaucourt-sur-l'Hallue"
    ],
    "name:lat_x_preferred":[
        "Beaucourt-sur-l'Hallue"
    ],
    "name:mlg_x_preferred":[
        "Beaucourt-sur-l'Hallue"
    ],
    "name:msa_x_preferred":[
        "Beaucourt-sur-l'Hallue"
    ],
    "name:nld_x_preferred":[
        "Beaucourt-sur-l'Hallue"
    ],
    "name:oci_x_preferred":[
        "Beaucourt-sur-l'Hallue"
    ],
    "name:pcd_x_preferred":[
        "Bieucourt-su-l'Hallu"
    ],
    "name:pms_x_preferred":[
        "Beaucourt-sur-l'Hallue"
    ],
    "name:pol_x_preferred":[
        "Beaucourt-sur-l\u2019Hallue"
    ],
    "name:por_x_preferred":[
        "Beaucourt-sur-l'Hallue"
    ],
    "name:ron_x_preferred":[
        "Beaucourt-sur-l'Hallue"
    ],
    "name:slk_x_preferred":[
        "Beaucourt-sur-l\u2019Hallue"
    ],
    "name:spa_x_preferred":[
        "Beaucourt-sur-l'Hallue"
    ],
    "name:sqi_x_preferred":[
        "Beaucourt-sur-l'Hallue"
    ],
    "name:swe_x_preferred":[
        "Beaucourt-sur-l'Hallue"
    ],
    "name:ukr_x_preferred":[
        "\u0411\u043e\u043a\u0443\u0440-\u0441\u044e\u0440-\u043b'\u0410\u043b\u043b\u044e"
    ],
    "name:und_x_variant":[
        "Beaucourt",
        "Beaucourt-sur-l\u2019Hallue"
    ],
    "name:uzb_x_preferred":[
        "Beaucourt-sur-l'Hallue"
    ],
    "name:vie_x_preferred":[
        "Beaucourt-sur-l'Hallue"
    ],
    "name:vol_x_preferred":[
        "Beaucourt-sur-l'Hallue"
    ],
    "name:war_x_preferred":[
        "Beaucourt-sur-l'Hallue"
    ],
    "name:zho_x_preferred":[
        "\u963f\u5415\u6cb3\u7554\u535a\u5e93\u5c14"
    ],
    "wof:name":"Beaucourt-sur-l'Hallue",
    "wof:placetype":"locality"
},
  "geometry": {"coordinates":[2.44402,49.98982],"type":"Point"}
}