{
  "type": "Feature",
  "properties": {
    "gn:admin1_code":"28",
    "gn:admin2_code":"76",
    "gn:admin3_code":"762",
    "gn:admin4_code":"76543",
    "gn:asciiname":"Bielleville",
    "gn:country_code":"FR",
    "gn:dem":130,
    "gn:feature_class":"P",
    "gn:feature_code":"PPL",
    "gn:name":"Bielleville",
    "gn:population":0,
    "gn:timezone":"Europe/Paris",
    "iso:country":"FR",
    "wof:name":"Bielleville",
    "wof:placetype":"locality"
},
  "geometry": {"coordinates":[0.49944,49.64981],"type":"Point"}
}