{
  "type": "Feature",
  "properties": {
    "gn:admin1_code":"44",
    "gn:admin2_code":"88",
    "gn:admin3_code":"882",
    "gn:admin4_code":"88305",
    "gn:asciiname":"Gouecourt",
    "gn:country_code":"FR",
    "gn:dem":278,
    "gn:feature_class":"P",
    "gn:feature_code":"PPL",
    "gn:name":"Gou\u00e9court",
    "gn:population":0,
    "gn:timezone":"Europe/Paris",
    "iso:country":"FR",
    "wof:name":"Gouecourt",
    "wof:placetype":"locality"
},
  "geometry": {"coordinates":[5.70382,48.4168],"type":"Point"}
}