{
  "type": "Feature",
  "properties": {
    "gn:gn_country":"FR",
    "gn:gn_fcode":"PPL",
    "gn:gn_pop":310,
    "gn:population":310,
    "iso:country":"FR",
    "name:cat_x_preferred":[
        "\u00c9persy"
    ],
    "name:deu_x_preferred":[
        "\u00c9persy"
    ],
    "name:eng_x_preferred":[
        "\u00c9persy"
    ],
    "name:eus_x_preferred":[
        "\u00c9persy"
    ],
    "name:fra_x_preferred":[
        "\u00c9persy"
    ],
    "name:hun_x_preferred":[
        "\u00c9persy"
    ],
    "name:ita_x_preferred":[
        "\u00c9persy"
    ],
    "name:lat_x_preferred":[
        "\u00c9persy"
    ],
    "name:lmo_x_preferred":[
        "\u00c9persy"
    ],
    "name:msa_x_preferred":[
        "\u00c9persy"
    ],
    "name:nan_x_preferred":[
        "\u00c9persy"
    ],
    "name:nld_x_preferred":[
        "\u00c9persy"
    ],
    "name:oci_x_preferred":[
        "\u00c9persy"
    ],
    "name:pol_x_preferred":[
        "\u00c9persy"
    ],
    "name:ron_x_preferred":[
        "\u00c9persy"
    ],
    "name:slk_x_preferred":[
        "\u00c9persy"
    ],
    "name:spa_x_preferred":[
        "\u00c9persy"
    ],
    "name:swe_x_preferred":[
        "\u00c9persy"
    ],
    "name:ukr_x_preferred":[
        "\u0415\u043f\u0435\u0440\u0441\u0456"
    ],
    "name:uzb_x_preferred":[
        "\u00c9persy"
    ],
    "name:vie_x_preferred":[
        "\u00c9persy"
    ],
    "name:vol_x_preferred":[
        "\u00c9persy"
    ],
    "name:war_x_preferred":[
        "\u00c9persy"
    ],
    "qs_pg:aaroncc":"FR",
    "qs_pg:gn_country":"FR",
    "qs_pg:gn_fcode":"PPL",
    "qs_pg:gn_pop":310,
    "qs_pg:name":"\u00c9persy",
    "qs_pg:name_adm0":"France",
    "qs_pg:name_adm1":"Rh\u00f4ne-Alpes",
    "qs_pg:photos_9r":0,
    "qs_pg:photos_sr":0,
    "qs_pg:pop_sr":2,
    "qs_pg:qs_pg_placetype":"locality",
    "qs_pg:qs_pg_placetype_gp":"Town",
    "qs_pg:woe_adm0":23424819,
    "woe:adm0_id":23424819,
    "woe:name_adm0":"France",
    "woe:name_adm1":"Rh\u00f4ne-Alpes",
    "woe:placetype":"Town",
    "wof:name":"\u00c9persy",
    "wof:placetype":"neighbourhood",
    "wof:population":310
},
  "geometry": {"coordinates":[5.96126,45.73933],"type":"Point"}
}