{
  "type": "Feature",
  "properties": {
    "gn:admin1_code":"93",
    "gn:admin2_code":"13",
    "gn:admin3_code":"133",
    "gn:admin4_code":"13085",
    "gn:asciiname":"Roquefort",
    "gn:country_code":"FR",
    "gn:dem":321,
    "gn:feature_class":"P",
    "gn:feature_code":"PPL",
    "gn:name":"Roquefort",
    "gn:population":0,
    "gn:timezone":"Europe/Paris",
    "iso:country":"FR",
    "wof:name":"Roquefort",
    "wof:placetype":"locality"
},
  "geometry": {"coordinates":[5.62397,43.25164],"type":"Point"}
}