{
  "type": "Feature",
  "properties": {
    "gn:admin1_code":"52",
    "gn:admin2_code":"44",
    "gn:admin3_code":"441",
    "gn:admin4_code":"44091",
    "gn:asciiname":"La Calvernais",
    "gn:country_code":"FR",
    "gn:dem":74,
    "gn:feature_class":"P",
    "gn:feature_code":"PPL",
    "gn:name":"La Calvernais",
    "gn:population":0,
    "gn:timezone":"Europe/Paris",
    "iso:country":"FR",
    "wof:name":"La Calvernais",
    "wof:placetype":"locality"
},
  "geometry": {"coordinates":[-1.71196,47.57634],"type":"Point"}
}