{
  "type": "Feature",
  "properties": {
    "gn:admin1_code":"75",
    "gn:admin2_code":"23",
    "gn:admin3_code":"232",
    "gn:admin4_code":"23254",
    "gn:asciiname":"La Garde",
    "gn:country_code":"FR",
    "gn:dem":439,
    "gn:feature_class":"P",
    "gn:feature_code":"PPL",
    "gn:name":"La Garde",
    "gn:population":0,
    "gn:timezone":"Europe/Paris",
    "iso:country":"FR",
    "wof:name":"La Garde",
    "wof:placetype":"locality"
},
  "geometry": {"coordinates":[2.29829,46.28771],"type":"Point"}
}