{
  "type": "Feature",
  "properties": {
    "gn:admin1_code":"24",
    "gn:admin2_code":"37",
    "gn:admin3_code":"373",
    "gn:admin4_code":"37192",
    "gn:asciiname":"Bas Ville-Pays",
    "gn:country_code":"FR",
    "gn:dem":82,
    "gn:feature_class":"P",
    "gn:feature_code":"PPL",
    "gn:name":"Bas Ville-Pays",
    "gn:population":0,
    "gn:timezone":"Europe/Paris",
    "iso:country":"FR",
    "wof:name":"Bas Ville-Pays",
    "wof:placetype":"locality"
},
  "geometry": {"coordinates":[0.94648,47.2264],"type":"Point"}
}