{
  "type": "Feature",
  "properties": {
    "iso:country":"FR",
    "name:eng_x_preferred":[
        "Sainte-Therese-Quineleu"
    ],
    "name:fra_x_preferred":[
        "Sainte-Th\u00e9r\u00e8se - Quineleu"
    ],
    "wof:name":"Sainte-Therese-Quineleu",
    "wof:placetype":"neighbourhood"
},
  "geometry": {"coordinates":[-1.66860866558211,48.09779689434665],"type":"Point"}
}