{
  "type": "Feature",
  "properties": {
    "iso:country":"FR",
    "name:eng_x_preferred":[
        "Jean Rostand-Estienne d'Orves"
    ],
    "name:fra_x_preferred":[
        "Jean Rostand-Estienne d'Orves"
    ],
    "wof:name":"Jean Rostand-Estienne d'Orves",
    "wof:placetype":"neighbourhood"
},
  "geometry": {"coordinates":[2.45514944033133,48.90926747307044],"type":"Point"}
}