{
  "type": "Feature",
  "properties": {
    "gn:admin1_code":"27",
    "gn:admin2_code":"21",
    "gn:admin3_code":"212",
    "gn:admin4_code":"21433",
    "gn:asciiname":"La Villeneuve-sur-Vingeanne",
    "gn:country_code":"FR",
    "gn:dem":249,
    "gn:feature_class":"P",
    "gn:feature_code":"PPL",
    "gn:name":"La Villeneuve-sur-Vingeanne",
    "gn:population":0,
    "gn:timezone":"Europe/Paris",
    "iso:country":"FR",
    "name:und_x_variant":[
        "La Villeneuve",
        "La Villeneuve-sur-Vingeanne"
    ],
    "wof:name":"La Villeneuve-sur-Vingeanne",
    "wof:placetype":"locality"
},
  "geometry": {"coordinates":[5.42329,47.56314],"type":"Point"}
}