{
  "type": "Feature",
  "properties": {
    "gn:admin1_code":"76",
    "gn:admin2_code":"12",
    "gn:admin3_code":"122",
    "gn:admin4_code":"12187",
    "gn:asciiname":"Prades-d'Aubrac",
    "gn:country_code":"FR",
    "gn:dem":877,
    "gn:feature_class":"P",
    "gn:feature_code":"PPL",
    "gn:name":"Prades-d\u2019Aubrac",
    "gn:population":0,
    "gn:timezone":"Europe/Paris",
    "iso:country":"FR",
    "name:und_x_variant":[
        "Prades",
        "Prades-d\u2019Aubrac"
    ],
    "wof:name":"Prades-d'Aubrac",
    "wof:placetype":"locality"
},
  "geometry": {"coordinates":[2.93684,44.53386],"type":"Point"}
}