{
  "type": "Feature",
  "properties": {
    "gn:admin1_code":"76",
    "gn:admin2_code":"12",
    "gn:admin3_code":"122",
    "gn:admin4_code":"12187",
    "gn:asciiname":"Prades-d'Aubrac",
    "gn:country_code":"FR",
    "gn:dem":877,
    "gn:feature_class":"P",
    "gn:feature_code":"PPL",
    "gn:name":"Prades-d\u2019Aubrac",
    "gn:population":0,
    "gn:timezone":"Europe/Paris",
    "iso:country":"FR",
    "name:cat_x_preferred":[
        "Pradas d'Aubrac"
    ],
    "name:ceb_x_preferred":[
        "Prades-d'Aubrac"
    ],
    "name:deu_x_preferred":[
        "Prades-d\u2019Aubrac"
    ],
    "name:eus_x_preferred":[
        "Prades-d'Aubrac"
    ],
    "name:fra_x_preferred":[
        "Prades-d'Aubrac"
    ],
    "name:hun_x_preferred":[
        "Prades-d\u2019Aubrac"
    ],
    "name:hye_x_preferred":[
        "\u054a\u0580\u0561\u0564 \u0564'\u0555\u0562\u0580\u0561\u056f"
    ],
    "name:ita_x_preferred":[
        "Prades-d'Aubrac"
    ],
    "name:lat_x_preferred":[
        "Prades-d'Aubrac"
    ],
    "name:mlg_x_preferred":[
        "Prades-d'Aubrac"
    ],
    "name:msa_x_preferred":[
        "Prades-d'Aubrac"
    ],
    "name:nld_x_preferred":[
        "Prades-d'Aubrac"
    ],
    "name:oci_x_preferred":[
        "Pradas d'Aubrac"
    ],
    "name:pms_x_preferred":[
        "Prades-d'Aubrac"
    ],
    "name:pol_x_preferred":[
        "Prades-d\u2019Aubrac"
    ],
    "name:por_x_preferred":[
        "Prades-d'Aubrac"
    ],
    "name:ron_x_preferred":[
        "Prades-d'Aubrac"
    ],
    "name:rus_x_preferred":[
        "\u041f\u0440\u0430\u0434-\u0434\u2019\u041e\u0431\u0440\u0430\u043a"
    ],
    "name:slk_x_preferred":[
        "Prades-d\u2019Aubrac"
    ],
    "name:spa_x_preferred":[
        "Prades-d'Aubrac"
    ],
    "name:swe_x_preferred":[
        "Prades-d'Aubrac"
    ],
    "name:ukr_x_preferred":[
        "\u041f\u0440\u0430\u0434-\u0434'\u041e\u0431\u0440\u0430\u043a"
    ],
    "name:und_x_variant":[
        "Prades"
    ],
    "name:vie_x_preferred":[
        "Prades-d'Aubrac"
    ],
    "name:vol_x_preferred":[
        "Prades-d'Aubrac"
    ],
    "name:war_x_preferred":[
        "Prades-d'Aubrac"
    ],
    "name:zho_x_preferred":[
        "\u666e\u62c9\u5fb7-\u591a\u5e03\u62c9\u514b"
    ],
    "wof:name":"Prades-d'Aubrac",
    "wof:placetype":"locality"
},
  "geometry": {"coordinates":[2.93684,44.53386],"type":"Point"}
}