{
  "type": "Feature",
  "properties": {
    "gn:admin1_code":"84",
    "gn:admin2_code":"43",
    "gn:admin3_code":"431",
    "gn:admin4_code":"43011",
    "gn:asciiname":"Le Chambon",
    "gn:country_code":"FR",
    "gn:dem":502,
    "gn:feature_class":"P",
    "gn:feature_code":"PPL",
    "gn:name":"Le Chambon",
    "gn:population":0,
    "gn:timezone":"Europe/Paris",
    "iso:country":"FR",
    "wof:name":"Le Chambon",
    "wof:placetype":"locality"
},
  "geometry": {"coordinates":[3.46834,45.14176],"type":"Point"}
}