{
  "type": "Feature",
  "properties": {
    "iso:country":"FR",
    "name:eng_x_preferred":[
        "La Folie-La Cerisaie"
    ],
    "name:fra_x_preferred":[
        "La Folie-La Cerisaie"
    ],
    "wof:name":"La Folie-La Cerisaie",
    "wof:placetype":"neighbourhood"
},
  "geometry": {"coordinates":[2.43045879985643,48.90238466969731],"type":"Point"}
}