{
  "type": "Feature",
  "properties": {
    "gn:admin1_code":"27",
    "gn:admin2_code":"58",
    "gn:admin3_code":"583",
    "gn:admin4_code":"58196.0",
    "gn:asciiname":"Les Audins",
    "gn:country_code":"FR",
    "gn:dem":243,
    "gn:feature_class":"P",
    "gn:feature_code":"PPL",
    "gn:name":"Les Audins",
    "gn:population":0,
    "gn:timezone":"Europe/Paris",
    "iso:country":"FR",
    "wof:name":"Les Audins",
    "wof:placetype":"locality"
},
  "geometry": {"coordinates":[3.27895,47.13876],"type":"Point"}
}