{
  "type": "Feature",
  "properties": {
    "gn:country":"FR",
    "gn:fcode":"PPL",
    "gn:population":295,
    "iso:country":"FR",
    "name:bug_x_preferred":[
        "Thibouville"
    ],
    "name:cat_x_preferred":[
        "Thibouville"
    ],
    "name:ceb_x_preferred":[
        "Thibouville"
    ],
    "name:deu_x_preferred":[
        "Thibouville"
    ],
    "name:eus_x_preferred":[
        "Thibouville"
    ],
    "name:fra_x_preferred":[
        "Thibouville"
    ],
    "name:hun_x_preferred":[
        "Thibouville"
    ],
    "name:ind_x_preferred":[
        "Thibouville"
    ],
    "name:ita_x_preferred":[
        "Thibouville"
    ],
    "name:kaz_x_preferred":[
        "\u0422\u0438\u0431\u0443\u0432\u0438\u043b\u044c"
    ],
    "name:lat_x_preferred":[
        "Thibouville"
    ],
    "name:mlg_x_preferred":[
        "Thibouville"
    ],
    "name:msa_x_preferred":[
        "Thibouville"
    ],
    "name:nld_x_preferred":[
        "Thibouville"
    ],
    "name:oci_x_preferred":[
        "Thibouville"
    ],
    "name:pms_x_preferred":[
        "Thibouville"
    ],
    "name:pol_x_preferred":[
        "Thibouville"
    ],
    "name:por_x_preferred":[
        "Thibouville"
    ],
    "name:ron_x_preferred":[
        "Thibouville"
    ],
    "name:slk_x_preferred":[
        "Thibouville"
    ],
    "name:spa_x_preferred":[
        "Thibouville"
    ],
    "name:swe_x_preferred":[
        "Thibouville"
    ],
    "name:ukr_x_preferred":[
        "\u0422\u0456\u0431\u0443\u0432\u0456\u043b\u044c"
    ],
    "name:vie_x_preferred":[
        "Thibouville"
    ],
    "name:vol_x_preferred":[
        "Thibouville"
    ],
    "name:war_x_preferred":[
        "Thibouville"
    ],
    "name:zho_x_preferred":[
        "\u8482\u5e03\u7ef4\u52d2"
    ],
    "qs_pg:aaroncc":"FR",
    "qs_pg:gn_country":"FR",
    "qs_pg:gn_fcode":"PPL",
    "qs_pg:gn_pop":295,
    "qs_pg:name":"Thibouville",
    "qs_pg:name_adm0":"France",
    "qs_pg:name_adm1":"Haute-Normandie",
    "qs_pg:photos_9r":0,
    "qs_pg:photos_sr":0,
    "qs_pg:pop_sr":2,
    "qs_pg:qs_pg_placetype":"locality",
    "qs_pg:qs_pg_placetype_gp":"Town",
    "qs_pg:woe_adm0":23424819,
    "woe:adm0_id":23424819,
    "woe:name_adm0":"France",
    "woe:name_adm1":"Haute-Normandie",
    "woe:placetype":"Town",
    "wof:name":"Thibouville",
    "wof:placetype":"neighbourhood",
    "wof:population":295
},
  "geometry": {"coordinates":[0.7911,49.14786],"type":"Point"}
}