{
  "type": "Feature",
  "properties": {
    "gn:admin1_code":"75",
    "gn:admin2_code":"19",
    "gn:admin3_code":"192",
    "gn:admin4_code":"19249",
    "gn:asciiname":"La Goute",
    "gn:country_code":"FR",
    "gn:dem":658,
    "gn:feature_class":"P",
    "gn:feature_code":"PPL",
    "gn:name":"La Goute",
    "gn:population":0,
    "gn:timezone":"Europe/Paris",
    "iso:country":"FR",
    "wof:name":"La Goute",
    "wof:placetype":"locality"
},
  "geometry": {"coordinates":[1.94205,45.44827],"type":"Point"}
}