{
  "type": "Feature",
  "properties": {
    "gn:admin1_code":"84",
    "gn:admin2_code":"01",
    "gn:admin3_code":"012",
    "gn:admin4_code":"1349.0",
    "gn:asciiname":"Plomb",
    "gn:country_code":"FR",
    "gn:dem":293,
    "gn:feature_class":"P",
    "gn:feature_code":"PPL",
    "gn:name":"Plomb",
    "gn:population":0,
    "gn:timezone":"Europe/Paris",
    "iso:country":"FR",
    "name:bre_x_preferred":[
        "Plomb"
    ],
    "name:bug_x_preferred":[
        "Plomb"
    ],
    "name:cat_x_preferred":[
        "Plomb"
    ],
    "name:ceb_x_preferred":[
        "Plomb"
    ],
    "name:deu_x_preferred":[
        "Plomb"
    ],
    "name:eus_x_preferred":[
        "Plomb"
    ],
    "name:fra_x_preferred":[
        "Plomb"
    ],
    "name:hun_x_preferred":[
        "Plomb"
    ],
    "name:ita_x_preferred":[
        "Plomb"
    ],
    "name:kaz_x_preferred":[
        "\u041f\u043b\u043e\u043c\u0431"
    ],
    "name:lat_x_preferred":[
        "Plomb"
    ],
    "name:msa_x_preferred":[
        "Plomb"
    ],
    "name:nld_x_preferred":[
        "Plomb"
    ],
    "name:oci_x_preferred":[
        "Plomb"
    ],
    "name:pms_x_preferred":[
        "Plomb"
    ],
    "name:pol_x_preferred":[
        "Plomb"
    ],
    "name:por_x_preferred":[
        "Plomb"
    ],
    "name:ron_x_preferred":[
        "Plomb"
    ],
    "name:slk_x_preferred":[
        "Plomb"
    ],
    "name:spa_x_preferred":[
        "Plomb"
    ],
    "name:swe_x_preferred":[
        "Plomb"
    ],
    "name:ukr_x_preferred":[
        "\u041f\u043b\u043e\u043c"
    ],
    "name:und_x_variant":[
        "Mas Plomb",
        "Plomb"
    ],
    "name:uzb_x_preferred":[
        "Plomb"
    ],
    "name:vie_x_preferred":[
        "Plomb"
    ],
    "name:vol_x_preferred":[
        "Plomb"
    ],
    "name:war_x_preferred":[
        "Plomb"
    ],
    "wof:name":"Plomb",
    "wof:placetype":"locality"
},
  "geometry": {"coordinates":[5.16236,45.92331],"type":"Point"}
}