{
  "type": "Feature",
  "properties": {
    "gn:admin1_code":"84",
    "gn:admin2_code":"01",
    "gn:admin3_code":"012",
    "gn:admin4_code":"1349.0",
    "gn:asciiname":"Plomb",
    "gn:country_code":"FR",
    "gn:dem":293,
    "gn:feature_class":"P",
    "gn:feature_code":"PPL",
    "gn:name":"Plomb",
    "gn:population":0,
    "gn:timezone":"Europe/Paris",
    "iso:country":"FR",
    "name:und_x_variant":[
        "Mas Plomb",
        "Plomb"
    ],
    "wof:name":"Plomb",
    "wof:placetype":"locality"
},
  "geometry": {"coordinates":[5.16236,45.92331],"type":"Point"}
}