{
  "type": "Feature",
  "properties": {
    "gn:admin1_code":"75",
    "gn:admin2_code":"47",
    "gn:admin3_code":"473",
    "gn:admin4_code":"47152",
    "gn:asciiname":"Tourrete",
    "gn:country_code":"FR",
    "gn:dem":154,
    "gn:feature_class":"P",
    "gn:feature_code":"PPL",
    "gn:name":"Tourrete",
    "gn:population":0,
    "gn:timezone":"Europe/Paris",
    "iso:country":"FR",
    "wof:name":"Tourrete",
    "wof:placetype":"locality"
},
  "geometry": {"coordinates":[0.6458,44.58812],"type":"Point"}
}