{
  "type": "Feature",
  "properties": {
    "gn:admin1_code":"53",
    "gn:admin2_code":"22",
    "gn:admin3_code":"222",
    "gn:admin4_code":"22231",
    "gn:asciiname":"Kerderrien",
    "gn:country_code":"FR",
    "gn:dem":206,
    "gn:feature_class":"P",
    "gn:feature_code":"PPL",
    "gn:name":"Kerderrien",
    "gn:population":0,
    "gn:timezone":"Europe/Paris",
    "iso:country":"FR",
    "wof:name":"Kerderrien",
    "wof:placetype":"locality"
},
  "geometry": {"coordinates":[-3.52699,48.40311],"type":"Point"}
}