{
  "type": "Feature",
  "properties": {
    "gn:admin1_code":"24",
    "gn:admin2_code":"18",
    "gn:admin3_code":"181",
    "gn:admin4_code":"18240.0",
    "gn:asciiname":"Sarre",
    "gn:country_code":"FR",
    "gn:dem":168,
    "gn:feature_class":"P",
    "gn:feature_code":"PPL",
    "gn:name":"Sarr\u00e9",
    "gn:population":0,
    "gn:timezone":"Europe/Paris",
    "iso:country":"FR",
    "name:bre_x_preferred":[
        "Sarre"
    ],
    "name:cat_x_preferred":[
        "Sarre"
    ],
    "name:ceb_x_preferred":[
        "Sarre"
    ],
    "name:deu_x_preferred":[
        "Sarre"
    ],
    "name:fra_x_preferred":[
        "Sarre"
    ],
    "name:ita_x_preferred":[
        "Sarre"
    ],
    "name:nld_x_preferred":[
        "Sarre"
    ],
    "name:oci_x_preferred":[
        "Sarre"
    ],
    "name:pol_x_preferred":[
        "Sarre"
    ],
    "name:por_x_preferred":[
        "Sarre"
    ],
    "name:spa_x_preferred":[
        "Sarre"
    ],
    "name:swe_x_preferred":[
        "Sarre"
    ],
    "wof:name":"Sarre",
    "wof:placetype":"locality"
},
  "geometry": {"coordinates":[2.90466,47.16848],"type":"Point"}
}