{
  "type": "Feature",
  "properties": {
    "gn:admin1_code":"84",
    "gn:admin2_code":"07",
    "gn:admin3_code":"073",
    "gn:admin4_code":"07079",
    "gn:asciiname":"Maurize",
    "gn:country_code":"FR",
    "gn:dem":495,
    "gn:feature_class":"P",
    "gn:feature_code":"PPL",
    "gn:name":"Maurize",
    "gn:population":0,
    "gn:timezone":"Europe/Paris",
    "iso:country":"FR",
    "wof:name":"Maurize",
    "wof:placetype":"locality"
},
  "geometry": {"coordinates":[4.54176,44.96384000000001],"type":"Point"}
}