{
  "type": "Feature",
  "properties": {
    "gn:admin1_code":"84",
    "gn:admin2_code":"03",
    "gn:admin3_code":"031",
    "gn:admin4_code":"03158",
    "gn:asciiname":"La Palisse",
    "gn:country_code":"FR",
    "gn:dem":311,
    "gn:feature_class":"P",
    "gn:feature_code":"PPL",
    "gn:name":"La Palisse",
    "gn:population":0,
    "gn:timezone":"Europe/Paris",
    "iso:country":"FR",
    "wof:name":"La Palisse",
    "wof:placetype":"locality"
},
  "geometry": {"coordinates":[2.70095,46.468],"type":"Point"}
}