{
  "type": "Feature",
  "properties": {
    "gn:admin1_code":"28",
    "gn:admin2_code":"61",
    "gn:admin3_code":"611",
    "gn:admin4_code":"61068",
    "gn:asciiname":"Pussou",
    "gn:country_code":"FR",
    "gn:dem":173,
    "gn:feature_class":"P",
    "gn:feature_code":"PPL",
    "gn:name":"Pussou",
    "gn:population":0,
    "gn:timezone":"Europe/Paris",
    "iso:country":"FR",
    "wof:name":"Pussou",
    "wof:placetype":"locality"
},
  "geometry": {"coordinates":[0.20692,48.55401],"type":"Point"}
}