{
  "type": "Feature",
  "properties": {
    "gn:admin1_code":"84",
    "gn:admin2_code":"43",
    "gn:admin3_code":"432",
    "gn:admin4_code":"43186",
    "gn:asciiname":"La Fourette",
    "gn:country_code":"FR",
    "gn:dem":1191,
    "gn:feature_class":"P",
    "gn:feature_code":"PPL",
    "gn:name":"La Fourette",
    "gn:population":0,
    "gn:timezone":"Europe/Paris",
    "iso:country":"FR",
    "wof:name":"La Fourette",
    "wof:placetype":"locality"
},
  "geometry": {"coordinates":[4.12196,44.95413],"type":"Point"}
}