{
  "type": "Feature",
  "properties": {
    "gn:admin1_code":"76",
    "gn:admin2_code":"30",
    "gn:admin3_code":"303",
    "gn:admin4_code":"30198",
    "gn:asciiname":"Faveyrolles",
    "gn:country_code":"FR",
    "gn:dem":527,
    "gn:feature_class":"P",
    "gn:feature_code":"PPL",
    "gn:name":"Faveyrolles",
    "gn:population":0,
    "gn:timezone":"Europe/Paris",
    "iso:country":"FR",
    "name:und_x_variant":[
        "Faveyrolle",
        "Faveyrolles"
    ],
    "wof:name":"Faveyrolles",
    "wof:placetype":"locality"
},
  "geometry": {"coordinates":[3.68916,44.10923],"type":"Point"}
}