{
  "type": "Feature",
  "properties": {
    "gn:admin1_code":"75",
    "gn:admin2_code":"23",
    "gn:admin3_code":"232",
    "gn:admin4_code":"23107",
    "gn:asciiname":"Lepinas",
    "gn:country_code":"FR",
    "gn:dem":605,
    "gn:feature_class":"P",
    "gn:feature_code":"PPL",
    "gn:name":"L\u00e9pinas",
    "gn:population":0,
    "gn:timezone":"Europe/Paris",
    "iso:country":"FR",
    "name:und_x_variant":[
        "L\u00e9pinas"
    ],
    "wof:name":"Lepinas",
    "wof:placetype":"locality"
},
  "geometry": {"coordinates":[1.92754,46.07688],"type":"Point"}
}