{
  "type": "Feature",
  "properties": {
    "frgov:code_epci":"200067189",
    "frgov:insee_arr":"2",
    "frgov:insee_com":"23107",
    "frgov:insee_dep":"23",
    "frgov:insee_reg":"75",
    "frgov:nom_com":"L\u00e9pinas",
    "frgov:nom_com_m":"LEPINAS",
    "frgov:nom_dep":"CREUSE",
    "frgov:nom_reg":"NOUVELLE-AQUITAINE",
    "frgov:statut":"Commune simple",
    "gn:admin1_code":"75",
    "gn:admin2_code":"23",
    "gn:admin3_code":"232",
    "gn:admin4_code":"23107",
    "gn:asciiname":"Lepinas",
    "gn:country_code":"FR",
    "gn:dem":605,
    "gn:feature_class":"P",
    "gn:feature_code":"PPL",
    "gn:name":"L\u00e9pinas",
    "gn:population":0,
    "gn:timezone":"Europe/Paris",
    "iso:country":"FR",
    "name:fra_x_preferred":[
        "L\u00e9pinas"
    ],
    "name:und_x_variant":[
        "L\u00e9pinas"
    ],
    "qs:a0":"France",
    "qs:a1":"CREUSE",
    "qs:a1_lc":"23",
    "qs:a1r":"LIMOUSIN",
    "qs:a1r_lc":"74",
    "qs:a2_lc":"01",
    "qs:a2r_lc":"2",
    "qs:adm0":"France",
    "qs:adm0_a3":"FRA",
    "qs:la":"LEPINAS",
    "qs:la_lc":"23107",
    "qs:level":"localadmin",
    "qs:type":"Commune simple",
    "wof:coterminous":[
        404367539
    ],
    "wof:name":"Lepinas",
    "wof:placetype":"locality",
    "wof:placetype_local":"Commune simple"
},
  "geometry": {"coordinates":[1.92754,46.07688],"type":"Point"}
}