{
  "type": "Feature",
  "properties": {
    "gn:admin1_code":"24",
    "gn:admin2_code":"18",
    "gn:admin3_code":"183",
    "gn:admin4_code":"18141",
    "gn:asciiname":"Barmont",
    "gn:country_code":"FR",
    "gn:dem":113,
    "gn:feature_class":"P",
    "gn:feature_code":"PPL",
    "gn:name":"Barmont",
    "gn:population":0,
    "gn:timezone":"Europe/Paris",
    "iso:country":"FR",
    "wof:name":"Barmont",
    "wof:placetype":"locality"
},
  "geometry": {"coordinates":[2.23067,47.13305],"type":"Point"}
}