{
  "type": "Feature",
  "properties": {
    "gn:admin1_code":"93",
    "gn:admin2_code":"05",
    "gn:admin3_code":"052",
    "gn:admin4_code":"05044",
    "gn:asciiname":"Praveyral",
    "gn:country_code":"FR",
    "gn:dem":1478,
    "gn:feature_class":"P",
    "gn:feature_code":"PPL",
    "gn:name":"Praveyral",
    "gn:population":0,
    "gn:timezone":"Europe/Paris",
    "iso:country":"FR",
    "wof:name":"Praveyral",
    "wof:placetype":"locality"
},
  "geometry": {"coordinates":[6.59622,44.54956],"type":"Point"}
}