{
  "type": "Feature",
  "properties": {
    "gn:admin1_code":"84",
    "gn:admin2_code":"43",
    "gn:admin3_code":"433",
    "gn:admin4_code":"43224.0",
    "gn:asciiname":"Le Chene",
    "gn:country_code":"FR",
    "gn:dem":808,
    "gn:feature_class":"P",
    "gn:feature_code":"PPL",
    "gn:name":"Le Ch\u00eane",
    "gn:population":0,
    "gn:timezone":"Europe/Paris",
    "iso:country":"FR",
    "wof:name":"Le Chene",
    "wof:placetype":"locality"
},
  "geometry": {"coordinates":[4.25178,45.27192],"type":"Point"}
}