{
  "type": "Feature",
  "properties": {
    "frgov:code_epci":"200066124",
    "frgov:insee_arr":"1",
    "frgov:insee_com":"81061",
    "frgov:insee_dep":"81",
    "frgov:insee_reg":"76",
    "frgov:nom_com":"Castanet",
    "frgov:nom_com_m":"CASTANET",
    "frgov:nom_dep":"TARN",
    "frgov:nom_reg":"OCCITANIE",
    "frgov:statut":"Commune simple",
    "gn:admin1_code":"76",
    "gn:admin2_code":"81",
    "gn:admin3_code":"811",
    "gn:admin4_code":"81061",
    "gn:asciiname":"Castanet",
    "gn:country_code":"FR",
    "gn:dem":276,
    "gn:feature_class":"P",
    "gn:feature_code":"PPL",
    "gn:name":"Castanet",
    "gn:population":173,
    "gn:timezone":"Europe/Paris",
    "iso:country":"FR",
    "name:fra_x_preferred":[
        "Castanet"
    ],
    "qs:a0":"France",
    "qs:a1":"TARN",
    "qs:a1_lc":"81",
    "qs:a1r":"MIDI-PYRENEES",
    "qs:a1r_lc":"73",
    "qs:a2_lc":"12",
    "qs:a2r_lc":"1",
    "qs:adm0":"France",
    "qs:adm0_a3":"FRA",
    "qs:la":"CASTANET",
    "qs:la_lc":"81061",
    "qs:level":"localadmin",
    "qs:type":"Commune simple",
    "wof:coterminous":[
        404348277
    ],
    "wof:name":"Castanet",
    "wof:placetype":"locality",
    "wof:placetype_local":"Commune simple",
    "wof:population":173
},
  "geometry": {"coordinates":[2.02914,43.97514],"type":"Point"}
}