{
  "type": "Feature",
  "properties": {
    "gn:admin1_code":"76",
    "gn:admin2_code":"81",
    "gn:admin3_code":"811",
    "gn:admin4_code":"81061",
    "gn:asciiname":"Castanet",
    "gn:country_code":"FR",
    "gn:dem":276,
    "gn:feature_class":"P",
    "gn:feature_code":"PPL",
    "gn:name":"Castanet",
    "gn:population":173,
    "gn:timezone":"Europe/Paris",
    "iso:country":"FR",
    "wof:name":"Castanet",
    "wof:placetype":"locality",
    "wof:population":173
},
  "geometry": {"coordinates":[2.02914,43.97514],"type":"Point"}
}