{
  "type": "Feature",
  "properties": {
    "iso:country":"FR",
    "name:deu_x_preferred":[
        "Flughafen Fontenay-Tr\u00e9signy"
    ],
    "name:eng_x_preferred":[
        "Fontenay-Tr\u00e9signy Airport"
    ],
    "name:msa_x_preferred":[
        "Lapangan Terbang Fontenay-Tresigny"
    ],
    "oa:elevation_ft":"371",
    "oa:type":"small_airport",
    "woe:hierarchy":{
        "country_id":23424819,
        "county_id":12597137,
        "localadmin_id":12643984,
        "planet_id":1,
        "state_id":7153319
    },
    "wof:name":"A\u00e9rodrome de Fontenay-tr\u00e9signy",
    "wof:placetype":"campus"
},
  "geometry": {"coordinates":[2.9028,48.7061],"type":"Point"}
}