{
  "type": "Feature",
  "properties": {
    "gn:admin1_code":"84",
    "gn:admin2_code":"03",
    "gn:admin3_code":"032",
    "gn:admin4_code":"03169",
    "gn:asciiname":"La Roche",
    "gn:country_code":"FR",
    "gn:dem":294,
    "gn:feature_class":"P",
    "gn:feature_code":"PPL",
    "gn:name":"La Roche",
    "gn:population":0,
    "gn:timezone":"Europe/Paris",
    "iso:country":"FR",
    "wof:name":"La Roche",
    "wof:placetype":"locality"
},
  "geometry": {"coordinates":[3.25581,46.40363],"type":"Point"}
}