{
  "type": "Feature",
  "properties": {
    "gn:admin1_code":"52",
    "gn:admin2_code":"49",
    "gn:admin3_code":"493",
    "gn:admin4_code":"49018",
    "gn:asciiname":"Fougere",
    "gn:country_code":"FR",
    "gn:dem":33,
    "gn:feature_class":"P",
    "gn:feature_code":"PPL",
    "gn:name":"Fouger\u00e9",
    "gn:population":750,
    "gn:timezone":"Europe/Paris",
    "iso:country":"FR",
    "name:nld_x_preferred":[
        "Fougere"
    ],
    "name:und_x_variant":[
        "Fouger\u00e9"
    ],
    "wof:name":"Fougere",
    "wof:placetype":"locality",
    "wof:population":750
},
  "geometry": {"coordinates":[-0.14829,47.6279],"type":"Point"}
}