{
  "type": "Feature",
  "properties": {
    "gn:admin1_code":"84",
    "gn:admin2_code":"43",
    "gn:admin3_code":"431",
    "gn:admin4_code":"43093",
    "gn:asciiname":"Plagne",
    "gn:country_code":"FR",
    "gn:dem":988,
    "gn:feature_class":"P",
    "gn:feature_code":"PPL",
    "gn:name":"Plagne",
    "gn:population":0,
    "gn:timezone":"Europe/Paris",
    "iso:country":"FR",
    "name:und_x_variant":[
        "Plagnes",
        "Plagne"
    ],
    "wof:name":"Plagne",
    "wof:placetype":"locality"
},
  "geometry": {"coordinates":[3.76986,45.25772],"type":"Point"}
}