{
  "type": "Feature",
  "properties": {
    "gn:admin1_code":"84",
    "gn:admin2_code":"43",
    "gn:admin3_code":"431",
    "gn:admin4_code":"43093",
    "gn:asciiname":"Plagne",
    "gn:country_code":"FR",
    "gn:dem":988,
    "gn:feature_class":"P",
    "gn:feature_code":"PPL",
    "gn:name":"Plagne",
    "gn:population":0,
    "gn:timezone":"Europe/Paris",
    "iso:country":"FR",
    "name:arg_x_preferred":[
        "Plagne"
    ],
    "name:ceb_x_preferred":[
        "Plagne"
    ],
    "name:deu_x_preferred":[
        "Plagne"
    ],
    "name:epo_x_preferred":[
        "Plagne"
    ],
    "name:fra_x_preferred":[
        "Plagne"
    ],
    "name:hun_x_preferred":[
        "Plagne"
    ],
    "name:ita_x_preferred":[
        "Plagne"
    ],
    "name:nds_x_preferred":[
        "Plagne"
    ],
    "name:nld_x_preferred":[
        "Plagne"
    ],
    "name:pol_x_preferred":[
        "Plagne"
    ],
    "name:por_x_preferred":[
        "Plagne"
    ],
    "name:ron_x_preferred":[
        "Plagne"
    ],
    "name:rus_x_preferred":[
        "\u041f\u043b\u0430\u043d\u044c"
    ],
    "name:slk_x_preferred":[
        "Plagne"
    ],
    "name:spa_x_preferred":[
        "Plagne"
    ],
    "name:swe_x_preferred":[
        "Plagne"
    ],
    "name:ukr_x_preferred":[
        "\u041f\u043b\u0430\u043d\u044c"
    ],
    "name:und_x_variant":[
        "Plagnes"
    ],
    "wof:name":"Plagne",
    "wof:placetype":"locality"
},
  "geometry": {"coordinates":[3.76986,45.25772],"type":"Point"}
}