{
  "type": "Feature",
  "properties": {
    "gn:admin1_code":"24",
    "gn:admin2_code":"18",
    "gn:admin3_code":"182",
    "gn:admin4_code":"18087",
    "gn:asciiname":"La Perisse",
    "gn:country_code":"FR",
    "gn:dem":163,
    "gn:feature_class":"P",
    "gn:feature_code":"PPL",
    "gn:name":"La P\u00e9risse",
    "gn:population":0,
    "gn:timezone":"Europe/Paris",
    "iso:country":"FR",
    "wof:name":"La Perisse",
    "wof:placetype":"locality"
},
  "geometry": {"coordinates":[2.52138,46.88419],"type":"Point"}
}