{
  "type": "Feature",
  "properties": {
    "gn:admin1_code":"75",
    "gn:admin2_code":"19",
    "gn:admin3_code":"192",
    "gn:admin4_code":"19018",
    "gn:asciiname":"Le Mas",
    "gn:country_code":"FR",
    "gn:dem":579,
    "gn:feature_class":"P",
    "gn:feature_code":"PPL",
    "gn:name":"Le Mas",
    "gn:population":0,
    "gn:timezone":"Europe/Paris",
    "iso:country":"FR",
    "wof:name":"Le Mas",
    "wof:placetype":"locality"
},
  "geometry": {"coordinates":[2.06566,45.20034],"type":"Point"}
}