{
  "type": "Feature",
  "properties": {
    "gn:admin1_code":"76",
    "gn:admin2_code":"34",
    "gn:admin3_code":"342",
    "gn:admin4_code":"34306",
    "gn:asciiname":"Les Saulieres",
    "gn:country_code":"FR",
    "gn:dem":250,
    "gn:feature_class":"P",
    "gn:feature_code":"PPL",
    "gn:name":"Les Sauli\u00e8res",
    "gn:population":0,
    "gn:timezone":"Europe/Paris",
    "iso:country":"FR",
    "wof:name":"Les Saulieres",
    "wof:placetype":"locality"
},
  "geometry": {"coordinates":[3.33398,43.73769],"type":"Point"}
}