{
  "type": "Feature",
  "properties": {
    "gn:admin1_code":"53",
    "gn:admin2_code":"29",
    "gn:admin3_code":"292",
    "gn:admin4_code":"29054",
    "gn:asciiname":"Keranhc'roff",
    "gn:country_code":"FR",
    "gn:dem":269,
    "gn:feature_class":"P",
    "gn:feature_code":"PPL",
    "gn:name":"Keranhc\u2019roff",
    "gn:population":0,
    "gn:timezone":"Europe/Paris",
    "iso:country":"FR",
    "wof:name":"Keranhc'roff",
    "wof:placetype":"locality"
},
  "geometry": {"coordinates":[-3.84623,48.394],"type":"Point"}
}