{
  "type": "Feature",
  "properties": {
    "gn:country":"FR",
    "gn:fcode":"PPL",
    "gn:population":0,
    "iso:country":"FR",
    "name:und_x_variant":[
        "Pourville"
    ],
    "qs_pg:aaroncc":"FR",
    "qs_pg:gn_country":"FR",
    "qs_pg:gn_fcode":"PPL",
    "qs_pg:gn_pop":0,
    "qs_pg:name":"Pourville-sur-Mer",
    "qs_pg:name_adm0":"France",
    "qs_pg:name_adm1":"Haute-Normandie",
    "qs_pg:photos":439,
    "qs_pg:photos_1k":89,
    "qs_pg:photos_9k":2,
    "qs_pg:photos_9r":5,
    "qs_pg:photos_all":439,
    "qs_pg:photos_sr":6,
    "qs_pg:pop_sr":0,
    "qs_pg:qs_pg_placetype":"locality",
    "qs_pg:qs_pg_placetype_gp":"Town",
    "qs_pg:woe_adm0":23424819,
    "woe:adm0_id":23424819,
    "woe:name_adm0":"France",
    "woe:name_adm1":"Haute-Normandie",
    "woe:placetype":"Town",
    "wof:name":"Pourville-sur-Mer",
    "wof:placetype":"neighbourhood"
},
  "geometry": {"coordinates":[1.03191,49.91669],"type":"Point"}
}