{
  "type": "Feature",
  "properties": {
    "gn:country":"FR",
    "gn:fcode":"PPL",
    "gn:population":113,
    "iso:country":"FR",
    "name:ceb_x_preferred":[
        "Sommerau"
    ],
    "name:deu_x_preferred":[
        "Sommerau"
    ],
    "name:eus_x_preferred":[
        "Sommerau"
    ],
    "name:fas_x_preferred":[
        "\u0627\u0648\u0645\u0631\u06cc"
    ],
    "name:fas_x_variant":[
        "\u0633\u0648\u0645\u0631\u0627\u0648"
    ],
    "name:fra_x_preferred":[
        "Sommerau"
    ],
    "name:hun_x_preferred":[
        "Sommerau"
    ],
    "name:ita_x_preferred":[
        "Sommerau"
    ],
    "name:kat_x_preferred":[
        "\u10d6\u10dd\u10db\u10d4\u10e0\u10d0\u10e3"
    ],
    "name:kaz_x_preferred":[
        "\u041e\u043c\u043c\u0435\u0440\u0435"
    ],
    "name:msa_x_preferred":[
        "Sommerau"
    ],
    "name:nld_x_preferred":[
        "Sommerau"
    ],
    "name:pol_x_preferred":[
        "Sommerau"
    ],
    "name:por_x_preferred":[
        "Sommerau"
    ],
    "name:ron_x_preferred":[
        "Sommerau"
    ],
    "name:rus_x_preferred":[
        "\u041e\u043c\u043c\u0435\u0440\u0435\u0438"
    ],
    "name:rus_x_variant":[
        "\u0417\u043e\u043c\u043c\u0435\u0440\u0430\u0443"
    ],
    "name:spa_x_preferred":[
        "Sommerau"
    ],
    "name:srp_x_preferred":[
        "\u0417\u043e\u043c\u0435\u0440\u0430\u0443"
    ],
    "name:ukr_x_preferred":[
        "\u041e\u043c\u043c\u0435\u0440\u0435"
    ],
    "name:ukr_x_variant":[
        "\u0417\u043e\u043c\u043c\u0435\u0440\u0430\u0443"
    ],
    "name:und_x_variant":[
        "Ommeray"
    ],
    "name:uzb_x_preferred":[
        "Sommerau"
    ],
    "name:vie_x_preferred":[
        "Sommerau"
    ],
    "name:vol_x_preferred":[
        "Sommerau"
    ],
    "name:war_x_preferred":[
        "Sommerau"
    ],
    "name:zho_x_preferred":[
        "\u5965\u9ed8\u8d56"
    ],
    "name:zho_x_variant":[
        "\u7d22\u9ed8\u52b3"
    ],
    "qs_pg:aaroncc":"FR",
    "qs_pg:gn_country":"FR",
    "qs_pg:gn_fcode":"PPL",
    "qs_pg:gn_pop":113,
    "qs_pg:name":"Sommerau",
    "qs_pg:name_adm0":"Deutschland",
    "qs_pg:name_adm1":"Rheinland-Pfalz",
    "qs_pg:photos_9r":0,
    "qs_pg:photos_sr":0,
    "qs_pg:pop_sr":1,
    "qs_pg:qs_pg_placetype":"locality",
    "qs_pg:qs_pg_placetype_gp":"Town",
    "qs_pg:woe_adm0":23424829,
    "woe:adm0_id":23424829,
    "woe:name_adm0":"Deutschland",
    "woe:name_adm1":"Rheinland-Pfalz",
    "woe:placetype":"Town",
    "wof:name":"Sommerau",
    "wof:placetype":"neighbourhood",
    "wof:population":113
},
  "geometry": {"coordinates":[6.685,48.72259],"type":"Point"}
}