{
  "type": "Feature",
  "properties": {
    "gn:admin1_code":"84",
    "gn:admin2_code":"63",
    "gn:admin3_code":"631",
    "gn:admin4_code":"63056",
    "gn:asciiname":"Montboissier",
    "gn:country_code":"FR",
    "gn:dem":820,
    "gn:feature_class":"P",
    "gn:feature_code":"PPL",
    "gn:name":"Montboissier",
    "gn:population":0,
    "gn:timezone":"Europe/Paris",
    "iso:country":"FR",
    "wof:name":"Montboissier",
    "wof:placetype":"locality"
},
  "geometry": {"coordinates":[3.49123,45.58575],"type":"Point"}
}