{
  "type": "Feature",
  "properties": {
    "gn:admin1_code":"84",
    "gn:admin2_code":"63",
    "gn:admin3_code":"631",
    "gn:admin4_code":"63056",
    "gn:asciiname":"Montboissier",
    "gn:country_code":"FR",
    "gn:dem":820,
    "gn:feature_class":"P",
    "gn:feature_code":"PPL",
    "gn:name":"Montboissier",
    "gn:population":0,
    "gn:timezone":"Europe/Paris",
    "iso:country":"FR",
    "name:bug_x_preferred":[
        "Montboissier"
    ],
    "name:cat_x_preferred":[
        "Montboissier"
    ],
    "name:ceb_x_preferred":[
        "Montboissier"
    ],
    "name:deu_x_preferred":[
        "Montboissier"
    ],
    "name:eus_x_preferred":[
        "Montboissier"
    ],
    "name:fra_x_preferred":[
        "Montboissier"
    ],
    "name:hun_x_preferred":[
        "Montboissier"
    ],
    "name:ita_x_preferred":[
        "Montboissier"
    ],
    "name:lat_x_preferred":[
        "Montboissier"
    ],
    "name:mlg_x_preferred":[
        "Montboissier"
    ],
    "name:msa_x_preferred":[
        "Montboissier"
    ],
    "name:nld_x_preferred":[
        "Montboissier"
    ],
    "name:oci_x_preferred":[
        "Montboissier"
    ],
    "name:pms_x_preferred":[
        "Montboissier"
    ],
    "name:pol_x_preferred":[
        "Montboissier"
    ],
    "name:por_x_preferred":[
        "Montboissier"
    ],
    "name:ron_x_preferred":[
        "Montboissier"
    ],
    "name:slk_x_preferred":[
        "Montboissier"
    ],
    "name:spa_x_preferred":[
        "Montboissier"
    ],
    "name:swe_x_preferred":[
        "Montboissier"
    ],
    "name:ukr_x_preferred":[
        "\u041c\u043e\u043d\u0431\u0443\u0430\u0441\u044c\u0454"
    ],
    "name:uzb_x_preferred":[
        "Montboissier"
    ],
    "name:vie_x_preferred":[
        "Montboissier"
    ],
    "name:vol_x_preferred":[
        "Montboissier"
    ],
    "name:war_x_preferred":[
        "Montboissier"
    ],
    "name:zho_x_preferred":[
        "\u8499\u7279\u5e03\u74e6\u8c22"
    ],
    "wof:name":"Montboissier",
    "wof:placetype":"locality"
},
  "geometry": {"coordinates":[3.49123,45.58575],"type":"Point"}
}