{
  "type": "Feature",
  "properties": {
    "gn:admin1_code":"84",
    "gn:admin2_code":"69",
    "gn:admin3_code":"691",
    "gn:admin4_code":"69277",
    "gn:asciiname":"Quincieu",
    "gn:country_code":"FR",
    "gn:dem":219,
    "gn:feature_class":"P",
    "gn:feature_code":"PPL",
    "gn:name":"Quincieu",
    "gn:population":0,
    "gn:timezone":"Europe/Paris",
    "iso:country":"FR",
    "name:cat_x_preferred":[
        "Quincieu"
    ],
    "name:ceb_x_preferred":[
        "Quincieu"
    ],
    "name:deu_x_preferred":[
        "Quincieu"
    ],
    "name:eus_x_preferred":[
        "Quincieu"
    ],
    "name:fra_x_preferred":[
        "Quincieu"
    ],
    "name:hun_x_preferred":[
        "Quincieu"
    ],
    "name:ita_x_preferred":[
        "Quincieu"
    ],
    "name:lat_x_preferred":[
        "Quincieu"
    ],
    "name:lmo_x_preferred":[
        "Quincieu"
    ],
    "name:mlg_x_preferred":[
        "Quincieu"
    ],
    "name:msa_x_preferred":[
        "Quincieu"
    ],
    "name:nld_x_preferred":[
        "Quincieu"
    ],
    "name:oci_x_preferred":[
        "Quincieu"
    ],
    "name:pms_x_preferred":[
        "Quincieu"
    ],
    "name:pol_x_preferred":[
        "Quincieu"
    ],
    "name:por_x_preferred":[
        "Quincieu"
    ],
    "name:ron_x_preferred":[
        "Quincieu"
    ],
    "name:rus_x_preferred":[
        "\u041a\u0435\u043d\u0441\u044c\u0451"
    ],
    "name:slk_x_preferred":[
        "Quincieu"
    ],
    "name:spa_x_preferred":[
        "Quincieu"
    ],
    "name:swe_x_preferred":[
        "Quincieu"
    ],
    "name:ukr_x_preferred":[
        "\u041a\u0435\u043d\u0441\u044c\u0454"
    ],
    "name:uzb_x_preferred":[
        "Quincieu"
    ],
    "name:vie_x_preferred":[
        "Quincieu"
    ],
    "name:vol_x_preferred":[
        "Quincieu"
    ],
    "name:war_x_preferred":[
        "Quincieu"
    ],
    "wof:name":"Quincieu",
    "wof:placetype":"locality"
},
  "geometry": {"coordinates":[5.01766,45.73941],"type":"Point"}
}