{
  "type": "Feature",
  "properties": {
    "gn:admin1_code":"84",
    "gn:admin2_code":"38",
    "gn:admin3_code":"381",
    "gn:admin4_code":"38200",
    "gn:asciiname":"Les Simianes",
    "gn:country_code":"FR",
    "gn:dem":442,
    "gn:feature_class":"P",
    "gn:feature_code":"PPL",
    "gn:name":"Les Simianes",
    "gn:population":0,
    "gn:timezone":"Europe/Paris",
    "iso:country":"FR",
    "wof:name":"Les Simianes",
    "wof:placetype":"locality"
},
  "geometry": {"coordinates":[5.76667,45.11667],"type":"Point"}
}