{
  "type": "Feature",
  "properties": {
    "gn:admin1_code":"93",
    "gn:admin2_code":"04",
    "gn:admin3_code":"041",
    "gn:admin4_code":"04193",
    "gn:asciiname":"Melezen",
    "gn:country_code":"FR",
    "gn:dem":1648,
    "gn:feature_class":"P",
    "gn:feature_code":"PPL",
    "gn:name":"M\u00e9l\u00e9zen",
    "gn:population":0,
    "gn:timezone":"Europe/Paris",
    "iso:country":"FR",
    "wof:name":"Melezen",
    "wof:placetype":"locality"
},
  "geometry": {"coordinates":[6.72406,44.52521],"type":"Point"}
}