{
  "type": "Feature",
  "properties": {
    "gn:admin1_code":"24",
    "gn:admin2_code":"37",
    "gn:admin3_code":"371",
    "gn:admin4_code":"37242",
    "gn:asciiname":"Puy Rigault",
    "gn:country_code":"FR",
    "gn:dem":43,
    "gn:elevation":"43.0",
    "gn:feature_class":"P",
    "gn:feature_code":"PPL",
    "gn:name":"Puy Rigault",
    "gn:population":0,
    "gn:timezone":"Europe/Paris",
    "iso:country":"FR",
    "wof:name":"Puy Rigault",
    "wof:placetype":"locality"
},
  "geometry": {"coordinates":[0.14869,47.20883],"type":"Point"}
}