{
  "type": "Feature",
  "properties": {
    "gn:admin1_code":"24",
    "gn:admin2_code":"28",
    "gn:admin3_code":"283",
    "gn:admin4_code":"28386",
    "gn:asciiname":"La Picotiere",
    "gn:country_code":"FR",
    "gn:dem":238,
    "gn:feature_class":"P",
    "gn:feature_code":"PPL",
    "gn:name":"La Picoti\u00e8re",
    "gn:population":0,
    "gn:timezone":"Europe/Paris",
    "iso:country":"FR",
    "wof:name":"La Picotiere",
    "wof:placetype":"locality"
},
  "geometry": {"coordinates":[1.24014,48.5586],"type":"Point"}
}