{
  "type": "Feature",
  "properties": {
    "gn:admin1_code":"11",
    "gn:admin2_code":"77",
    "gn:admin3_code":"773",
    "gn:admin4_code":"77239.0",
    "gn:asciiname":"Les Orbies",
    "gn:country_code":"FR",
    "gn:dem":146,
    "gn:feature_class":"P",
    "gn:feature_code":"PPL",
    "gn:name":"Les Orbies",
    "gn:population":0,
    "gn:timezone":"Europe/Paris",
    "iso:country":"FR",
    "wof:name":"Les Orbies",
    "wof:placetype":"locality"
},
  "geometry": {"coordinates":[3.11166,48.63878],"type":"Point"}
}