{
  "type": "Feature",
  "properties": {
    "gn:admin1_code":"75",
    "gn:admin2_code":"24",
    "gn:admin3_code":"244",
    "gn:admin4_code":"24215",
    "gn:asciiname":"Laval",
    "gn:country_code":"FR",
    "gn:dem":280,
    "gn:feature_class":"P",
    "gn:feature_code":"PPL",
    "gn:name":"Laval",
    "gn:population":0,
    "gn:timezone":"Europe/Paris",
    "iso:country":"FR",
    "wof:name":"Laval",
    "wof:placetype":"locality"
},
  "geometry": {"coordinates":[1.3598,45.01789],"type":"Point"}
}