{
  "type": "Feature",
  "properties": {
    "gn:admin1_code":"75",
    "gn:admin2_code":"17",
    "gn:admin3_code":"175",
    "gn:admin4_code":"17043",
    "gn:asciiname":"Saint-Martin-de-la-Coudre",
    "gn:country_code":"FR",
    "gn:dem":32,
    "gn:feature_class":"P",
    "gn:feature_code":"PPL",
    "gn:name":"Saint-Martin-de-la-Coudre",
    "gn:population":0,
    "gn:timezone":"Europe/Paris",
    "iso:country":"FR",
    "name:und_x_variant":[
        "Saint-Martin",
        "Saint-Martin-de-la-Coudre"
    ],
    "wof:name":"Saint-Martin-de-la-Coudre",
    "wof:placetype":"locality"
},
  "geometry": {"coordinates":[-0.60363,46.06296],"type":"Point"}
}