{
  "type": "Feature",
  "properties": {
    "gn:admin1_code":"75",
    "gn:admin2_code":"24",
    "gn:admin3_code":"244",
    "gn:admin4_code":"24040",
    "gn:asciiname":"Cazenac",
    "gn:country_code":"FR",
    "gn:dem":219,
    "gn:feature_class":"P",
    "gn:feature_code":"PPL",
    "gn:name":"Cazenac",
    "gn:population":0,
    "gn:timezone":"Europe/Paris",
    "iso:country":"FR",
    "wof:name":"Cazenac",
    "wof:placetype":"locality"
},
  "geometry": {"coordinates":[1.13333,44.86667],"type":"Point"}
}