{
  "type": "Feature",
  "properties": {
    "gn:admin1_code":"84",
    "gn:admin2_code":"63",
    "gn:admin3_code":"635",
    "gn:admin4_code":"63430",
    "gn:asciiname":"Conord",
    "gn:country_code":"FR",
    "gn:dem":403,
    "gn:feature_class":"P",
    "gn:feature_code":"PPL",
    "gn:name":"Conord",
    "gn:population":0,
    "gn:timezone":"Europe/Paris",
    "iso:country":"FR",
    "wof:name":"Conord",
    "wof:placetype":"locality"
},
  "geometry": {"coordinates":[3.51479,45.89008],"type":"Point"}
}