{
  "type": "Feature",
  "properties": {
    "gn:admin1_code":"84",
    "gn:admin2_code":"43",
    "gn:admin3_code":"432",
    "gn:admin4_code":"43084",
    "gn:asciiname":"Tarreyres",
    "gn:country_code":"FR",
    "gn:dem":957,
    "gn:feature_class":"P",
    "gn:feature_code":"PPL",
    "gn:name":"Tarreyres",
    "gn:population":0,
    "gn:timezone":"Europe/Paris",
    "iso:country":"FR",
    "wof:name":"Tarreyres",
    "wof:placetype":"locality"
},
  "geometry": {"coordinates":[3.855,44.97626],"type":"Point"}
}