{
  "type": "Feature",
  "properties": {
    "gn:gn_country":"FR",
    "gn:gn_fcode":"PPL",
    "gn:gn_pop":113,
    "gn:population":113,
    "iso:country":"FR",
    "name:baq_x_preferred":[
        "Vaillac"
    ],
    "name:cat_x_preferred":[
        "Valhac"
    ],
    "name:chi_x_preferred":[
        "\u97e6\u62c9\u514b"
    ],
    "name:dut_x_preferred":[
        "Vaillac"
    ],
    "name:eng_x_preferred":[
        "Vaillac"
    ],
    "name:fre_x_preferred":[
        "Vaillac"
    ],
    "name:ger_x_preferred":[
        "Vaillac"
    ],
    "name:hun_x_preferred":[
        "Vaillac"
    ],
    "name:ita_x_preferred":[
        "Vaillac"
    ],
    "name:lat_x_preferred":[
        "Vaillac"
    ],
    "name:may_x_preferred":[
        "Vaillac"
    ],
    "name:nan_x_preferred":[
        "Vaillac"
    ],
    "name:nno_x_preferred":[
        "Vaillac"
    ],
    "name:nob_x_preferred":[
        "Vaillac"
    ],
    "name:oci_x_preferred":[
        "Valhac"
    ],
    "name:pms_x_preferred":[
        "Vaillac"
    ],
    "name:pol_x_preferred":[
        "Vaillac"
    ],
    "name:por_x_preferred":[
        "Vaillac"
    ],
    "name:rum_x_preferred":[
        "Vaillac"
    ],
    "name:slo_x_preferred":[
        "Vaillac"
    ],
    "name:spa_x_preferred":[
        "Vaillac"
    ],
    "name:swe_x_preferred":[
        "Vaillac"
    ],
    "name:ukr_x_preferred":[
        "\u0412\u0430\u044f\u043a"
    ],
    "name:vie_x_preferred":[
        "Vaillac"
    ],
    "name:vol_x_preferred":[
        "Vaillac"
    ],
    "name:war_x_preferred":[
        "Vaillac"
    ],
    "qs_pg:aaroncc":"FR",
    "qs_pg:gn_country":"FR",
    "qs_pg:gn_fcode":"PPL",
    "qs_pg:gn_pop":113,
    "qs_pg:name":"Vaillac",
    "qs_pg:name_adm0":"France",
    "qs_pg:name_adm1":"Midi-Pyr\u00e9n\u00e9es",
    "qs_pg:photos_9r":0,
    "qs_pg:photos_sr":0,
    "qs_pg:pop_sr":1,
    "qs_pg:qs_pg_placetype":"locality",
    "qs_pg:qs_pg_placetype_gp":"Town",
    "qs_pg:woe_adm0":23424819,
    "woe:adm0_id":23424819,
    "woe:name_adm0":"France",
    "woe:name_adm1":"Midi-Pyr\u00e9n\u00e9es",
    "woe:placetype":"Town",
    "wof:name":"Vaillac",
    "wof:placetype":"neighbourhood",
    "wof:population":113
},
  "geometry": {"coordinates":[1.52979,44.67429],"type":"Point"}
}