{
  "type": "Feature",
  "properties": {
    "iso:country":"FR",
    "name:eng_x_preferred":[
        "Bois Blancs"
    ],
    "name:fra_x_preferred":[
        "Bois Blancs"
    ],
    "wof:name":"Bois Blancs",
    "wof:placetype":"neighbourhood"
},
  "geometry": {"coordinates":[3.02722297586488,50.6313921376088],"type":"Point"}
}