{
  "type": "Feature",
  "properties": {
    "gn:admin1_code":"53",
    "gn:admin2_code":"29",
    "gn:admin3_code":"292",
    "gn:admin4_code":"29238",
    "gn:asciiname":"Keruzou",
    "gn:country_code":"FR",
    "gn:dem":63,
    "gn:feature_class":"P",
    "gn:feature_code":"PPL",
    "gn:name":"Keruzou",
    "gn:population":0,
    "gn:timezone":"Europe/Paris",
    "iso:country":"FR",
    "wof:name":"Keruzou",
    "wof:placetype":"locality"
},
  "geometry": {"coordinates":[-4.55276,48.32056],"type":"Point"}
}