{
  "type": "Feature",
  "properties": {
    "gn:admin1_code":"27",
    "gn:admin2_code":"89",
    "gn:admin3_code":"892",
    "gn:admin4_code":"89071",
    "gn:asciiname":"Crai",
    "gn:country_code":"FR",
    "gn:dem":208,
    "gn:feature_class":"P",
    "gn:feature_code":"PPL",
    "gn:name":"Crai",
    "gn:population":0,
    "gn:timezone":"Europe/Paris",
    "iso:country":"FR",
    "wof:name":"Crai",
    "wof:placetype":"locality"
},
  "geometry": {"coordinates":[3.65095,47.46274],"type":"Point"}
}