{
  "type": "Feature",
  "properties": {
    "gn:admin1_code":"11",
    "gn:admin2_code":"91",
    "gn:admin3_code":"911",
    "gn:admin4_code":"91109",
    "gn:asciiname":"Le Petit Brieres",
    "gn:country_code":"FR",
    "gn:dem":72,
    "gn:feature_class":"P",
    "gn:feature_code":"PPL",
    "gn:name":"Le Petit Bri\u00e8res",
    "gn:population":0,
    "gn:timezone":"Europe/Paris",
    "iso:country":"FR",
    "wof:name":"Le Petit Brieres",
    "wof:placetype":"locality"
},
  "geometry": {"coordinates":[2.14874,48.45659000000001],"type":"Point"}
}