{
  "type": "Feature",
  "properties": {
    "gn:admin1_code":"75",
    "gn:admin2_code":"23",
    "gn:admin3_code":"232",
    "gn:admin4_code":"23092",
    "gn:asciiname":"Mondoueix",
    "gn:country_code":"FR",
    "gn:dem":484,
    "gn:feature_class":"P",
    "gn:feature_code":"PPL",
    "gn:name":"Mondoueix",
    "gn:population":0,
    "gn:timezone":"Europe/Paris",
    "iso:country":"FR",
    "wof:name":"Mondoueix",
    "wof:placetype":"locality"
},
  "geometry": {"coordinates":[1.95133,46.237],"type":"Point"}
}