{
  "type": "Feature",
  "properties": {
    "gn:admin1_code":"53",
    "gn:admin2_code":"56",
    "gn:admin3_code":"563",
    "gn:admin4_code":"56002",
    "gn:asciiname":"Betahon",
    "gn:country_code":"FR",
    "gn:dem":13,
    "gn:feature_class":"P",
    "gn:feature_code":"PPL",
    "gn:name":"B\u00e9tahon",
    "gn:population":0,
    "gn:timezone":"Europe/Paris",
    "iso:country":"FR",
    "name:und_x_variant":[
        "Bellaon",
        "B\u00e9tahon"
    ],
    "wof:name":"Betahon",
    "wof:placetype":"locality"
},
  "geometry": {"coordinates":[-2.50756,47.52678],"type":"Point"}
}