{
  "type": "Feature",
  "properties": {
    "gn:admin1_code":"24",
    "gn:admin2_code":"36",
    "gn:admin3_code":"363",
    "gn:admin4_code":"36014",
    "gn:asciiname":"La Ligne",
    "gn:country_code":"FR",
    "gn:dem":271,
    "gn:feature_class":"P",
    "gn:feature_code":"PPL",
    "gn:name":"La Ligne",
    "gn:population":0,
    "gn:timezone":"Europe/Paris",
    "iso:country":"FR",
    "wof:name":"La Ligne",
    "wof:placetype":"locality"
},
  "geometry": {"coordinates":[1.52781,46.46952],"type":"Point"}
}