{
  "type": "Feature",
  "properties": {
    "frgov:code_epci":"200071140",
    "frgov:insee_arr":"2",
    "frgov:insee_com":"03162",
    "frgov:insee_dep":"03",
    "frgov:insee_reg":"84",
    "frgov:nom_com":"Marigny",
    "frgov:nom_com_m":"MARIGNY",
    "frgov:nom_dep":"ALLIER",
    "frgov:nom_reg":"AUVERGNE-RHONE-ALPES",
    "frgov:statut":"Commune simple",
    "gn:admin1_code":"84",
    "gn:admin2_code":"03",
    "gn:admin3_code":"032",
    "gn:admin4_code":"03162",
    "gn:asciiname":"Marigny",
    "gn:country_code":"FR",
    "gn:dem":259,
    "gn:feature_class":"P",
    "gn:feature_code":"PPL",
    "gn:name":"Marigny",
    "gn:population":210,
    "gn:timezone":"Europe/Paris",
    "iso:country":"FR",
    "name:bre_x_preferred":[
        "Marigny"
    ],
    "name:ceb_x_preferred":[
        "Marigny"
    ],
    "name:ces_x_preferred":[
        "Marigny"
    ],
    "name:deu_x_preferred":[
        "Marigny"
    ],
    "name:fra_x_preferred":[
        "Marigny"
    ],
    "name:ita_x_preferred":[
        "Marigny"
    ],
    "name:jpn_x_preferred":[
        "\u30de\u30ea\u30cb\u30fc"
    ],
    "name:kaz_x_preferred":[
        "\u041c\u0430\u0440\u0438\u043d\u044c\u0438"
    ],
    "name:nds_x_preferred":[
        "Marigny"
    ],
    "name:nld_x_preferred":[
        "Marigny"
    ],
    "name:pms_x_preferred":[
        "Marigny"
    ],
    "name:pol_x_preferred":[
        "Marigny"
    ],
    "name:por_x_preferred":[
        "Marigny"
    ],
    "name:rus_x_preferred":[
        "\u041c\u0430\u0440\u0438\u043d\u044c\u0438"
    ],
    "name:slk_x_preferred":[
        "Marigny"
    ],
    "name:spa_x_preferred":[
        "Marigny"
    ],
    "name:sqi_x_preferred":[
        "Marigny"
    ],
    "name:swe_x_preferred":[
        "Marigny"
    ],
    "name:ukr_x_preferred":[
        "\u041c\u0430\u0440\u0438\u043d\u044c\u0457"
    ],
    "name:zho_x_preferred":[
        "\u9a6c\u91cc\u5c3c"
    ],
    "qs:a0":"France",
    "qs:a1":"ALLIER",
    "qs:a1_lc":"03",
    "qs:a1r":"AUVERGNE",
    "qs:a1r_lc":"83",
    "qs:a2_lc":"27",
    "qs:a2r_lc":"2",
    "qs:adm0":"France",
    "qs:adm0_a3":"FRA",
    "qs:la":"MARIGNY",
    "qs:la_lc":"03162",
    "qs:level":"localadmin",
    "qs:type":"Commune simple",
    "wof:coterminous":[
        404383151
    ],
    "wof:name":"Marigny",
    "wof:placetype":"locality",
    "wof:placetype_local":"Commune simple",
    "wof:population":210
},
  "geometry": {"coordinates":[3.20914,46.5819],"type":"Point"}
}