{
  "type": "Feature",
  "properties": {
    "gn:admin1_code":"84",
    "gn:admin2_code":"03",
    "gn:admin3_code":"032",
    "gn:admin4_code":"03162",
    "gn:asciiname":"Marigny",
    "gn:country_code":"FR",
    "gn:dem":259,
    "gn:feature_class":"P",
    "gn:feature_code":"PPL",
    "gn:name":"Marigny",
    "gn:population":210,
    "gn:timezone":"Europe/Paris",
    "iso:country":"FR",
    "name:bre_x_preferred":[
        "Marigny"
    ],
    "name:ceb_x_preferred":[
        "Marigny"
    ],
    "name:ces_x_preferred":[
        "Marigny"
    ],
    "name:deu_x_preferred":[
        "Marigny"
    ],
    "name:fra_x_preferred":[
        "Marigny"
    ],
    "name:ita_x_preferred":[
        "Marigny"
    ],
    "name:jpn_x_preferred":[
        "\u30de\u30ea\u30cb\u30fc"
    ],
    "name:nds_x_preferred":[
        "Marigny"
    ],
    "name:nld_x_preferred":[
        "Marigny"
    ],
    "name:pms_x_preferred":[
        "Marigny"
    ],
    "name:pol_x_preferred":[
        "Marigny"
    ],
    "name:por_x_preferred":[
        "Marigny"
    ],
    "name:rus_x_preferred":[
        "\u041c\u0430\u0440\u0438\u043d\u044c\u0438"
    ],
    "name:slk_x_preferred":[
        "Marigny"
    ],
    "name:spa_x_preferred":[
        "Marigny"
    ],
    "name:sqi_x_preferred":[
        "Marigny"
    ],
    "name:swe_x_preferred":[
        "Marigny"
    ],
    "name:ukr_x_preferred":[
        "\u041c\u0430\u0440\u0438\u043d\u044c\u0457"
    ],
    "wof:name":"Marigny",
    "wof:placetype":"locality",
    "wof:population":210
},
  "geometry": {"coordinates":[3.20914,46.5819],"type":"Point"}
}