{
  "type": "Feature",
  "properties": {
    "gn:admin1_code":"84",
    "gn:admin2_code":"03",
    "gn:admin3_code":"032",
    "gn:admin4_code":"03162",
    "gn:asciiname":"Marigny",
    "gn:country_code":"FR",
    "gn:dem":259,
    "gn:feature_class":"P",
    "gn:feature_code":"PPL",
    "gn:name":"Marigny",
    "gn:population":210,
    "gn:timezone":"Europe/Paris",
    "iso:country":"FR",
    "wof:name":"Marigny",
    "wof:placetype":"locality",
    "wof:population":210
},
  "geometry": {"coordinates":[3.20914,46.5819],"type":"Point"}
}