{
  "type": "Feature",
  "properties": {
    "gn:admin1_code":"93",
    "gn:admin2_code":"04",
    "gn:admin3_code":"041",
    "gn:admin4_code":"04226",
    "gn:asciiname":"Les Blancs",
    "gn:cc2":"FR",
    "gn:country_code":"FR",
    "gn:dem":1366,
    "gn:feature_class":"P",
    "gn:feature_code":"PPL",
    "gn:name":"Les Blancs",
    "gn:population":0,
    "gn:timezone":"Europe/Paris",
    "iso:country":"FR",
    "name:und_x_variant":[
        "Les Blanes",
        "Les Blaues",
        "Les Blaucs",
        "Les Blancs"
    ],
    "wof:name":"Les Blancs",
    "wof:placetype":"locality"
},
  "geometry": {"coordinates":[6.61667,44.35],"type":"Point"}
}