{
  "type": "Feature",
  "properties": {
    "gn:admin1_code":"76",
    "gn:admin2_code":"12",
    "gn:admin3_code":"122",
    "gn:admin4_code":"12074",
    "gn:asciiname":"Condom-d'Aubrac",
    "gn:country_code":"FR",
    "gn:dem":948,
    "gn:feature_class":"P",
    "gn:feature_code":"PPL",
    "gn:name":"Condom-d\u2019Aubrac",
    "gn:population":0,
    "gn:timezone":"Europe/Paris",
    "iso:country":"FR",
    "name:cat_x_preferred":[
        "Condom d'Aubrac"
    ],
    "name:ceb_x_preferred":[
        "Condom-d'Aubrac"
    ],
    "name:deu_x_preferred":[
        "Condom-d\u2019Aubrac"
    ],
    "name:eus_x_preferred":[
        "Condom-d'Aubrac"
    ],
    "name:fra_x_preferred":[
        "Condom-d'Aubrac"
    ],
    "name:hun_x_preferred":[
        "Condom-d\u2019Aubrac"
    ],
    "name:hye_x_preferred":[
        "\u053f\u0578\u0576\u0564\u0578\u0574 \u0564'\u0555\u0562\u0580\u0561\u056f"
    ],
    "name:ita_x_preferred":[
        "Condom-d'Aubrac"
    ],
    "name:lat_x_preferred":[
        "Condom-d'Aubrac"
    ],
    "name:mlg_x_preferred":[
        "Condom-d'Aubrac"
    ],
    "name:msa_x_preferred":[
        "Condom-d'Aubrac"
    ],
    "name:nld_x_preferred":[
        "Condom-d'Aubrac"
    ],
    "name:oci_x_preferred":[
        "Condom d'Aubrac"
    ],
    "name:pam_x_preferred":[
        "Condom-d'Aubrac"
    ],
    "name:pms_x_preferred":[
        "Condom-d'Aubrac"
    ],
    "name:pol_x_preferred":[
        "Condom-d\u2019Aubrac"
    ],
    "name:por_x_preferred":[
        "Condom-d'Aubrac"
    ],
    "name:ron_x_preferred":[
        "Condom-d'Aubrac"
    ],
    "name:rus_x_preferred":[
        "\u041a\u043e\u043d\u0434\u043e\u043c-\u0434\u2019\u041e\u0431\u0440\u0430\u043a"
    ],
    "name:slk_x_preferred":[
        "Condom-d\u2019Aubrac"
    ],
    "name:spa_x_preferred":[
        "Condom-d'Aubrac"
    ],
    "name:srp_x_preferred":[
        "\u041a\u043e\u043d\u0434\u043e\u043c \u0434'\u041e\u0431\u0440\u0430\u043a"
    ],
    "name:swe_x_preferred":[
        "Condom-d'Aubrac"
    ],
    "name:ukr_x_preferred":[
        "\u041a\u043e\u043d\u0434\u043e\u043c-\u0434'\u041e\u0431\u0440\u0430\u043a"
    ],
    "name:und_x_variant":[
        "Condom",
        "Condom-d\u2019Aubrac"
    ],
    "name:vie_x_preferred":[
        "Condom-d'Aubrac"
    ],
    "name:vol_x_preferred":[
        "Condom-d'Aubrac"
    ],
    "name:war_x_preferred":[
        "Condom-d'Aubrac"
    ],
    "name:zho_x_preferred":[
        "\u5b54\u4e1c\u591a\u5e03\u62c9\u514b"
    ],
    "wof:name":"Condom-d'Aubrac",
    "wof:placetype":"locality"
},
  "geometry": {"coordinates":[2.86302,44.60393],"type":"Point"}
}