{
  "type": "Feature",
  "properties": {
    "gn:admin1_code":"76",
    "gn:admin2_code":"12",
    "gn:admin3_code":"122",
    "gn:admin4_code":"12074",
    "gn:asciiname":"Condom-d'Aubrac",
    "gn:country_code":"FR",
    "gn:dem":948,
    "gn:feature_class":"P",
    "gn:feature_code":"PPL",
    "gn:name":"Condom-d\u2019Aubrac",
    "gn:population":0,
    "gn:timezone":"Europe/Paris",
    "iso:country":"FR",
    "name:und_x_variant":[
        "Condom",
        "Condom-d\u2019Aubrac"
    ],
    "wof:name":"Condom-d'Aubrac",
    "wof:placetype":"locality"
},
  "geometry": {"coordinates":[2.86302,44.60393],"type":"Point"}
}