{
  "type": "Feature",
  "properties": {
    "gn:admin1_code":"24",
    "gn:admin2_code":"45",
    "gn:admin3_code":"451",
    "gn:admin4_code":"45275",
    "gn:asciiname":"Les Dulys",
    "gn:country_code":"FR",
    "gn:dem":157,
    "gn:feature_class":"P",
    "gn:feature_code":"PPL",
    "gn:name":"Les Dulys",
    "gn:population":0,
    "gn:timezone":"Europe/Paris",
    "iso:country":"FR",
    "name:und_x_variant":[
        "Les Dulis",
        "Les Dulys"
    ],
    "wof:name":"Les Dulys",
    "wof:placetype":"locality"
},
  "geometry": {"coordinates":[2.92651,47.98171],"type":"Point"}
}