{
  "type": "Feature",
  "properties": {
    "gn:admin1_code":"28",
    "gn:admin2_code":"76",
    "gn:admin3_code":"761",
    "gn:admin4_code":"76173",
    "gn:asciiname":"La Chaussee",
    "gn:country_code":"FR",
    "gn:dem":122,
    "gn:feature_class":"P",
    "gn:feature_code":"PPL",
    "gn:name":"La Chauss\u00e9e",
    "gn:population":0,
    "gn:timezone":"Europe/Paris",
    "iso:country":"FR",
    "name:und_x_variant":[
        "La Chauss\u00e9e"
    ],
    "wof:name":"La Chaussee",
    "wof:placetype":"locality"
},
  "geometry": {"coordinates":[1.11951,49.82462],"type":"Point"}
}