{
  "type": "Feature",
  "properties": {
    "gn:admin1_code":"76",
    "gn:admin2_code":"48",
    "gn:admin3_code":"482",
    "gn:admin4_code":"48009",
    "gn:asciiname":"Beauregard",
    "gn:country_code":"FR",
    "gn:dem":1157,
    "gn:feature_class":"P",
    "gn:feature_code":"PPL",
    "gn:name":"Beauregard",
    "gn:population":0,
    "gn:timezone":"Europe/Paris",
    "iso:country":"FR",
    "wof:name":"Beauregard",
    "wof:placetype":"locality"
},
  "geometry": {"coordinates":[3.22045,44.72859],"type":"Point"}
}