{
  "type": "Feature",
  "properties": {
    "gn:admin1_code":"75",
    "gn:admin2_code":"23",
    "gn:admin3_code":"232",
    "gn:admin4_code":"23072",
    "gn:asciiname":"Servieres",
    "gn:country_code":"FR",
    "gn:dem":396,
    "gn:feature_class":"P",
    "gn:feature_code":"PPL",
    "gn:name":"Servi\u00e8res",
    "gn:population":0,
    "gn:timezone":"Europe/Paris",
    "iso:country":"FR",
    "wof:name":"Servieres",
    "wof:placetype":"locality"
},
  "geometry": {"coordinates":[2.11582,46.25504],"type":"Point"}
}