{
  "type": "Feature",
  "properties": {
    "gn:admin1_code":"94",
    "gn:admin2_code":"2A",
    "gn:admin3_code":"2A1",
    "gn:admin4_code":"2A197",
    "gn:asciiname":"Tuara",
    "gn:country_code":"FR",
    "gn:dem":24,
    "gn:feature_class":"P",
    "gn:feature_code":"PPL",
    "gn:name":"Tuara",
    "gn:population":0,
    "gn:timezone":"Europe/Paris",
    "iso:country":"FR",
    "wof:name":"Tuara",
    "wof:placetype":"locality"
},
  "geometry": {"coordinates":[8.63281,42.3447],"type":"Point"}
}