{
  "type": "Feature",
  "properties": {
    "gn:admin1_code":"75",
    "gn:admin2_code":"19",
    "gn:admin3_code":"191",
    "gn:admin4_code":"19072",
    "gn:asciiname":"Travassac",
    "gn:country_code":"FR",
    "gn:dem":287,
    "gn:feature_class":"P",
    "gn:feature_code":"PPL",
    "gn:name":"Travassac",
    "gn:population":0,
    "gn:timezone":"Europe/Paris",
    "iso:country":"FR",
    "wof:name":"Travassac",
    "wof:placetype":"locality"
},
  "geometry": {"coordinates":[1.54926,45.22783],"type":"Point"}
}