{
  "type": "Feature",
  "properties": {
    "gn:admin1_code":"84",
    "gn:admin2_code":"03",
    "gn:admin3_code":"031",
    "gn:admin4_code":"03261",
    "gn:asciiname":"La Therade",
    "gn:country_code":"FR",
    "gn:dem":356,
    "gn:feature_class":"P",
    "gn:feature_code":"PPL",
    "gn:name":"La Th\u00e9rade",
    "gn:population":0,
    "gn:timezone":"Europe/Paris",
    "iso:country":"FR",
    "wof:name":"La Therade",
    "wof:placetype":"locality"
},
  "geometry": {"coordinates":[2.58333,46.25],"type":"Point"}
}