{
  "type": "Feature",
  "properties": {
    "gn:admin1_code":"11",
    "gn:admin2_code":"91",
    "gn:admin3_code":"911",
    "gn:admin4_code":"91469",
    "gn:asciiname":"Dhuilet",
    "gn:country_code":"FR",
    "gn:dem":145,
    "gn:feature_class":"P",
    "gn:feature_code":"PPL",
    "gn:name":"Dhuilet",
    "gn:population":0,
    "gn:timezone":"Europe/Paris",
    "iso:country":"FR",
    "wof:name":"Dhuilet",
    "wof:placetype":"locality"
},
  "geometry": {"coordinates":[2.1774,48.39995],"type":"Point"}
}