{
  "type": "Feature",
  "properties": {
    "gn:admin1_code":"84",
    "gn:admin2_code":"63",
    "gn:admin3_code":"634",
    "gn:admin4_code":"63419",
    "gn:asciiname":"Les Moignons",
    "gn:country_code":"FR",
    "gn:dem":556,
    "gn:feature_class":"P",
    "gn:feature_code":"PPL",
    "gn:name":"Les Moignons",
    "gn:population":0,
    "gn:timezone":"Europe/Paris",
    "iso:country":"FR",
    "wof:name":"Les Moignons",
    "wof:placetype":"locality"
},
  "geometry": {"coordinates":[2.95087,46.14684000000001],"type":"Point"}
}