{
  "type": "Feature",
  "properties": {
    "gn:admin1_code":"24",
    "gn:admin2_code":"18",
    "gn:admin3_code":"182",
    "gn:admin4_code":"18277.0",
    "gn:asciiname":"Briande",
    "gn:country_code":"FR",
    "gn:dem":168,
    "gn:feature_class":"P",
    "gn:feature_code":"PPL",
    "gn:name":"Briande",
    "gn:population":0,
    "gn:timezone":"Europe/Paris",
    "iso:country":"FR",
    "wof:name":"Briande",
    "wof:placetype":"locality"
},
  "geometry": {"coordinates":[2.60136,46.83419],"type":"Point"}
}