{
  "type": "Feature",
  "properties": {
    "gn:admin1_code":"76",
    "gn:admin2_code":"46",
    "gn:admin3_code":"462",
    "gn:admin4_code":"46183",
    "gn:asciiname":"Monteils",
    "gn:country_code":"FR",
    "gn:dem":157,
    "gn:feature_class":"P",
    "gn:feature_code":"PPL",
    "gn:name":"Monteils",
    "gn:population":0,
    "gn:timezone":"Europe/Paris",
    "iso:country":"FR",
    "name:ceb_x_preferred":[
        "Monteils"
    ],
    "name:deu_x_preferred":[
        "Monteils"
    ],
    "name:fra_x_preferred":[
        "Monteils"
    ],
    "name:ita_x_preferred":[
        "Monteils"
    ],
    "name:lmo_x_preferred":[
        "Monteils"
    ],
    "name:nds_x_preferred":[
        "Monteils"
    ],
    "name:nld_x_preferred":[
        "Monteils"
    ],
    "name:oci_x_preferred":[
        "Montelhs"
    ],
    "name:pms_x_preferred":[
        "Monteils"
    ],
    "name:pol_x_preferred":[
        "Monteils"
    ],
    "name:por_x_preferred":[
        "Monteils"
    ],
    "name:slk_x_preferred":[
        "Monteils"
    ],
    "name:spa_x_preferred":[
        "Monteils"
    ],
    "name:swe_x_preferred":[
        "Monteils"
    ],
    "name:szl_x_preferred":[
        "Monteils"
    ],
    "name:ukr_x_preferred":[
        "\u041c\u043e\u043d\u0442\u0435\u0439"
    ],
    "wof:name":"Monteils",
    "wof:placetype":"locality"
},
  "geometry": {"coordinates":[1.75327,44.53100000000001],"type":"Point"}
}