{
  "type": "Feature",
  "properties": {
    "iso:country":"FR",
    "name:fra_x_preferred":[
        "Fondaud\u00e8ge"
    ],
    "wof:name":"Fondaudege",
    "wof:placetype":"neighbourhood"
},
  "geometry": {"coordinates":[-0.58611891460843,44.84962023490705],"type":"Point"}
}