{
  "type": "Feature",
  "properties": {
    "gn:admin1_code":"93",
    "gn:admin2_code":"83",
    "gn:admin3_code":"831",
    "gn:admin4_code":"83042",
    "gn:asciiname":"Le Mourillon",
    "gn:country_code":"FR",
    "gn:dem":16,
    "gn:feature_class":"P",
    "gn:feature_code":"PPL",
    "gn:name":"Le Mourillon",
    "gn:population":0,
    "gn:timezone":"Europe/Paris",
    "iso:country":"FR",
    "name:fra_x_preferred":[
        "Le Mourillon"
    ],
    "name:oci_x_preferred":[
        "Morrilhon"
    ],
    "name:spa_x_preferred":[
        "Le Mourillon"
    ],
    "wof:name":"Le Mourillon",
    "wof:placetype":"locality"
},
  "geometry": {"coordinates":[6.53333,43.25],"type":"Point"}
}