{
  "type": "Feature",
  "properties": {
    "gn:admin1_code":"11",
    "gn:admin2_code":"77",
    "gn:admin3_code":"773",
    "gn:admin4_code":"77012.0",
    "gn:asciiname":"Corberon",
    "gn:country_code":"FR",
    "gn:dem":141,
    "gn:feature_class":"P",
    "gn:feature_code":"PPL",
    "gn:name":"Corberon",
    "gn:population":0,
    "gn:timezone":"Europe/Paris",
    "iso:country":"FR",
    "name:bug_x_preferred":[
        "Corberon"
    ],
    "name:cat_x_preferred":[
        "Corberon"
    ],
    "name:ceb_x_preferred":[
        "Corberon"
    ],
    "name:deu_x_preferred":[
        "Corberon"
    ],
    "name:epo_x_preferred":[
        "Corberon"
    ],
    "name:eus_x_preferred":[
        "Corberon"
    ],
    "name:fas_x_preferred":[
        "\u06a9\u0631\u0628\u0631\u0646\u0646"
    ],
    "name:fra_x_preferred":[
        "Corberon"
    ],
    "name:hun_x_preferred":[
        "Corberon"
    ],
    "name:ind_x_preferred":[
        "Corberon"
    ],
    "name:ita_x_preferred":[
        "Corberon"
    ],
    "name:kaz_x_preferred":[
        "\u041a\u043e\u0440\u0431\u0435\u0440\u043e\u043d"
    ],
    "name:lat_x_preferred":[
        "Corberon"
    ],
    "name:mlg_x_preferred":[
        "Corberon"
    ],
    "name:msa_x_preferred":[
        "Corberon"
    ],
    "name:nld_x_preferred":[
        "Corberon"
    ],
    "name:oci_x_preferred":[
        "Corberon"
    ],
    "name:pms_x_preferred":[
        "Corberon"
    ],
    "name:pol_x_preferred":[
        "Corberon"
    ],
    "name:por_x_preferred":[
        "Corberon"
    ],
    "name:ron_x_preferred":[
        "Corberon"
    ],
    "name:rus_x_preferred":[
        "\u041a\u043e\u0440\u0431\u0435\u0440\u043e\u043d"
    ],
    "name:slk_x_preferred":[
        "Corberon"
    ],
    "name:spa_x_preferred":[
        "Corberon"
    ],
    "name:srp_x_preferred":[
        "\u041a\u043e\u0440\u0431\u0435\u0440\u043e\u043d"
    ],
    "name:swe_x_preferred":[
        "Corberon"
    ],
    "name:ukr_x_preferred":[
        "\u041a\u043e\u0440\u0431\u0435\u0440\u043e\u043d"
    ],
    "name:uzb_x_preferred":[
        "Corberon"
    ],
    "name:vie_x_preferred":[
        "Corberon"
    ],
    "name:vol_x_preferred":[
        "Corberon"
    ],
    "name:war_x_preferred":[
        "Corberon"
    ],
    "name:zho_x_preferred":[
        "\u79d1\u5c14\u4f2f\u9f99"
    ],
    "wof:name":"Corberon",
    "wof:placetype":"locality"
},
  "geometry": {"coordinates":[3.33211,48.67599000000001],"type":"Point"}
}