{
  "type": "Feature",
  "properties": {
    "frgov:code_epci":"248400053",
    "frgov:insee_arr":"3",
    "frgov:insee_com":"84046",
    "frgov:insee_dep":"84",
    "frgov:insee_reg":"93",
    "frgov:nom_com":"Flassan",
    "frgov:nom_com_m":"FLASSAN",
    "frgov:nom_dep":"VAUCLUSE",
    "frgov:nom_reg":"PROVENCE-ALPES-COTE D'AZUR",
    "frgov:statut":"Commune simple",
    "gn:admin1_code":"93",
    "gn:admin2_code":"84",
    "gn:admin3_code":"843",
    "gn:admin4_code":"84046",
    "gn:asciiname":"Flassan",
    "gn:country_code":"FR",
    "gn:dem":436,
    "gn:feature_class":"P",
    "gn:feature_code":"PPL",
    "gn:name":"Flassan",
    "gn:population":365,
    "gn:timezone":"Europe/Paris",
    "iso:country":"FR",
    "name:cat_x_preferred":[
        "Fla\u00e7an"
    ],
    "name:ceb_x_preferred":[
        "Flassan"
    ],
    "name:deu_x_preferred":[
        "Flassan"
    ],
    "name:eus_x_preferred":[
        "Flassan"
    ],
    "name:fra_x_preferred":[
        "Flassan"
    ],
    "name:hun_x_preferred":[
        "Flassan"
    ],
    "name:hye_x_preferred":[
        "\u0556\u056c\u0561\u057d\u0561\u0576"
    ],
    "name:ita_x_preferred":[
        "Flassan"
    ],
    "name:lat_x_preferred":[
        "Flassan"
    ],
    "name:lmo_x_preferred":[
        "Flassan"
    ],
    "name:msa_x_preferred":[
        "Flassan"
    ],
    "name:nld_x_preferred":[
        "Flassan"
    ],
    "name:oci_x_preferred":[
        "Fla\u00e7an"
    ],
    "name:pms_x_preferred":[
        "Flassan"
    ],
    "name:pol_x_preferred":[
        "Flassan"
    ],
    "name:por_x_preferred":[
        "Flassan"
    ],
    "name:ron_x_preferred":[
        "Flassan"
    ],
    "name:rus_x_preferred":[
        "\u0424\u043b\u0430\u0441\u0441\u0430\u043d"
    ],
    "name:slk_x_preferred":[
        "Flassan"
    ],
    "name:spa_x_preferred":[
        "Flassan"
    ],
    "name:swe_x_preferred":[
        "Flassan"
    ],
    "name:ukr_x_preferred":[
        "\u0424\u043b\u0430\u0441\u0441\u0430\u043d"
    ],
    "name:vie_x_preferred":[
        "Flassan"
    ],
    "name:vol_x_preferred":[
        "Flassan"
    ],
    "name:war_x_preferred":[
        "Flassan"
    ],
    "name:zho_x_preferred":[
        "\u5f17\u62c9\u6851"
    ],
    "qs:a0":"France",
    "qs:a1":"VAUCLUSE",
    "qs:a1_lc":"84",
    "qs:a1r":"PROVENCE-ALPES-COTE D'AZUR",
    "qs:a1r_lc":"93",
    "qs:a2_lc":"15",
    "qs:a2r_lc":"3",
    "qs:adm0":"France",
    "qs:adm0_a3":"FRA",
    "qs:la":"FLASSAN",
    "qs:la_lc":"84046",
    "qs:level":"localadmin",
    "qs:type":"Commune simple",
    "wof:coterminous":[
        404369905
    ],
    "wof:name":"Flassan",
    "wof:placetype":"locality",
    "wof:placetype_local":"Commune simple",
    "wof:population":365
},
  "geometry": {"coordinates":[5.24148,44.09857],"type":"Point"}
}