{
  "type": "Feature",
  "properties": {
    "gn:admin1_code":"76",
    "gn:admin2_code":"12",
    "gn:admin3_code":"121",
    "gn:admin4_code":"12222",
    "gn:asciiname":"Mascourbe",
    "gn:country_code":"FR",
    "gn:dem":681,
    "gn:feature_class":"P",
    "gn:feature_code":"PPL",
    "gn:name":"Mascourbe",
    "gn:population":0,
    "gn:timezone":"Europe/Paris",
    "iso:country":"FR",
    "wof:name":"Mascourbe",
    "wof:placetype":"locality"
},
  "geometry": {"coordinates":[3.00493,43.89872],"type":"Point"}
}