{
  "type": "Feature",
  "properties": {
    "gn:admin1_code":"11",
    "gn:admin2_code":"77",
    "gn:admin3_code":"774",
    "gn:admin4_code":"77500",
    "gn:asciiname":"Passy",
    "gn:country_code":"FR",
    "gn:dem":133,
    "gn:feature_class":"P",
    "gn:feature_code":"PPL",
    "gn:name":"Passy",
    "gn:population":0,
    "gn:timezone":"Europe/Paris",
    "iso:country":"FR",
    "name:bel_x_preferred":[
        "\u041f\u0430\u0441\u0456"
    ],
    "name:cat_x_preferred":[
        "Passy"
    ],
    "name:ces_x_preferred":[
        "Passy"
    ],
    "name:deu_x_preferred":[
        "Passy"
    ],
    "name:fra_x_preferred":[
        "Passy"
    ],
    "name:ita_x_preferred":[
        "Passy"
    ],
    "name:lat_x_preferred":[
        "Passicium"
    ],
    "name:por_x_preferred":[
        "Passy"
    ],
    "name:rus_x_preferred":[
        "\u041f\u0430\u0441\u0441\u0438"
    ],
    "name:ukr_x_preferred":[
        "\u041f\u0430\u0441\u0441\u0456"
    ],
    "name:vie_x_preferred":[
        "Passy"
    ],
    "name:zho_x_preferred":[
        "\u5e15\u897f"
    ],
    "wof:name":"Passy",
    "wof:placetype":"locality"
},
  "geometry": {"coordinates":[2.91075,48.20076],"type":"Point"}
}