{
  "type": "Feature",
  "properties": {
    "gn:admin1_code":"52",
    "gn:admin2_code":"44",
    "gn:admin3_code":"441",
    "gn:admin4_code":"44015",
    "gn:asciiname":"Saint-Omer",
    "gn:country_code":"FR",
    "gn:dem":27,
    "gn:feature_class":"P",
    "gn:feature_code":"PPL",
    "gn:name":"Saint-Omer",
    "gn:population":0,
    "gn:timezone":"Europe/Paris",
    "iso:country":"FR",
    "name:ara_x_preferred":[
        "\u0633\u0627\u0646 \u0623\u0648\u0645\u064a\u0631"
    ],
    "name:bre_x_preferred":[
        "Saint-Omer"
    ],
    "name:bul_x_preferred":[
        "\u0421\u0435\u043d\u0442 \u041e\u043c\u0435\u0440"
    ],
    "name:ceb_x_preferred":[
        "Saint-Omer"
    ],
    "name:ces_x_preferred":[
        "Saint-Omer"
    ],
    "name:deu_x_preferred":[
        "Saint-Omer"
    ],
    "name:epo_x_preferred":[
        "Saint-Omer"
    ],
    "name:eus_x_preferred":[
        "Saint-Omer"
    ],
    "name:fas_x_preferred":[
        "\u0633\u0646-\u0627\u0648\u0645\u0631"
    ],
    "name:fin_x_preferred":[
        "Saint-Omer"
    ],
    "name:fra_x_preferred":[
        "Saint-Omer"
    ],
    "name:fry_x_preferred":[
        "Sint-Omaars"
    ],
    "name:glv_x_preferred":[
        "Saint-Omer"
    ],
    "name:hun_x_preferred":[
        "Saint-Omer"
    ],
    "name:ind_x_preferred":[
        "Saint-Omer"
    ],
    "name:jpn_x_preferred":[
        "\u30b5\u30f3\u30c8\u30e1\u30fc\u30eb"
    ],
    "name:kaz_x_preferred":[
        "\u0421\u0435\u043d\u0442-\u041e\u043c\u0435\u0440"
    ],
    "name:kor_x_preferred":[
        "\uc0dd\ud1a0\uba54\ub974"
    ],
    "name:lat_x_preferred":[
        "Sanctus Audomarus"
    ],
    "name:ltz_x_preferred":[
        "Saint-Omer"
    ],
    "name:mlg_x_preferred":[
        "Saint-Omer"
    ],
    "name:msa_x_preferred":[
        "Saint-Omer"
    ],
    "name:nld_x_preferred":[
        "Sint-Omaars"
    ],
    "name:nno_x_preferred":[
        "Saint-Omer"
    ],
    "name:nor_x_preferred":[
        "Saint-Omer"
    ],
    "name:pcd_x_preferred":[
        "Saint-Onm\u00e9"
    ],
    "name:pol_x_preferred":[
        "Saint-Omer"
    ],
    "name:que_x_preferred":[
        "Saint-Omer"
    ],
    "name:ron_x_preferred":[
        "Saint-Omer"
    ],
    "name:rus_x_preferred":[
        "\u0421\u0435\u043d\u0442-\u041e\u043c\u0435\u0440"
    ],
    "name:sco_x_preferred":[
        "Saint-Omer"
    ],
    "name:slk_x_preferred":[
        "Saint-Omer"
    ],
    "name:slv_x_preferred":[
        "Saint-Omer"
    ],
    "name:spa_x_preferred":[
        "Saint-Omer"
    ],
    "name:swe_x_preferred":[
        "Saint-Omer"
    ],
    "name:tur_x_preferred":[
        "Saint-Omer"
    ],
    "name:ukr_x_preferred":[
        "\u0421\u0435\u043d\u0442-\u041e\u043c\u0435\u0440"
    ],
    "name:urd_x_preferred":[
        "\u0633\u06cc\u0646\u0679-\u0627\u0645\u0631"
    ],
    "name:vie_x_preferred":[
        "Saint-Omer"
    ],
    "name:vol_x_preferred":[
        "Saint-Omer"
    ],
    "name:war_x_preferred":[
        "Saint-Omer"
    ],
    "name:zho_x_preferred":[
        "\u5723\u5965\u6885\u5c14"
    ],
    "wof:name":"Saint-Omer",
    "wof:placetype":"locality"
},
  "geometry": {"coordinates":[-1.85714,47.47381],"type":"Point"}
}