{
  "type": "Feature",
  "properties": {
    "gn:admin1_code":"52",
    "gn:admin2_code":"44",
    "gn:admin3_code":"441",
    "gn:admin4_code":"44015",
    "gn:asciiname":"Saint-Omer",
    "gn:country_code":"FR",
    "gn:dem":27,
    "gn:feature_class":"P",
    "gn:feature_code":"PPL",
    "gn:name":"Saint-Omer",
    "gn:population":0,
    "gn:timezone":"Europe/Paris",
    "iso:country":"FR",
    "wof:name":"Saint-Omer",
    "wof:placetype":"locality"
},
  "geometry": {"coordinates":[-1.85714,47.47381],"type":"Point"}
}