{
  "type": "Feature",
  "properties": {
    "gn:admin1_code":"27",
    "gn:admin2_code":"71",
    "gn:admin3_code":"711",
    "gn:admin4_code":"71015",
    "gn:asciiname":"Auxy",
    "gn:country_code":"FR",
    "gn:dem":515,
    "gn:feature_class":"P",
    "gn:feature_code":"PPL",
    "gn:name":"Auxy",
    "gn:population":1059,
    "gn:timezone":"Europe/Paris",
    "iso:country":"FR",
    "wof:name":"Auxy",
    "wof:placetype":"locality",
    "wof:population":1059
},
  "geometry": {"coordinates":[4.4044,46.9494],"type":"Point"}
}