{
  "type": "Feature",
  "properties": {
    "gn:admin1_code":"84",
    "gn:admin2_code":"26",
    "gn:admin3_code":"261",
    "gn:admin4_code":"26015",
    "gn:asciiname":"Les Mouyons",
    "gn:country_code":"FR",
    "gn:dem":558,
    "gn:feature_class":"P",
    "gn:feature_code":"PPL",
    "gn:name":"Les Mouyons",
    "gn:population":0,
    "gn:timezone":"Europe/Paris",
    "iso:country":"FR",
    "name:und_x_variant":[
        "Les Mouvons",
        "Les Mouyons"
    ],
    "wof:name":"Les Mouyons",
    "wof:placetype":"locality"
},
  "geometry": {"coordinates":[5.14707,44.6689],"type":"Point"}
}