{
  "type": "Feature",
  "properties": {
    "gn:admin1_code":"76",
    "gn:admin2_code":"12",
    "gn:admin3_code":"123",
    "gn:admin4_code":"12290",
    "gn:asciiname":"Pachins",
    "gn:country_code":"FR",
    "gn:dem":499,
    "gn:feature_class":"P",
    "gn:feature_code":"PPL",
    "gn:name":"Pachins",
    "gn:population":0,
    "gn:timezone":"Europe/Paris",
    "iso:country":"FR",
    "wof:name":"Pachins",
    "wof:placetype":"locality"
},
  "geometry": {"coordinates":[2.17723,44.4601],"type":"Point"}
}