{
  "type": "Feature",
  "properties": {
    "gn:admin1_code":"84",
    "gn:admin2_code":"63",
    "gn:admin3_code":"631",
    "gn:admin4_code":"63353",
    "gn:asciiname":"Losfond",
    "gn:country_code":"FR",
    "gn:dem":1046,
    "gn:feature_class":"P",
    "gn:feature_code":"PPL",
    "gn:name":"Losfond",
    "gn:population":0,
    "gn:timezone":"Europe/Paris",
    "iso:country":"FR",
    "wof:name":"Losfond",
    "wof:placetype":"locality"
},
  "geometry": {"coordinates":[3.56308,45.43957],"type":"Point"}
}