{
  "type": "Feature",
  "properties": {
    "gn:admin1_code":"52",
    "gn:admin2_code":"72",
    "gn:admin3_code":"722",
    "gn:admin4_code":"72112",
    "gn:asciiname":"La Cougellerie",
    "gn:country_code":"FR",
    "gn:dem":70,
    "gn:feature_class":"P",
    "gn:feature_code":"PPL",
    "gn:name":"La Cougellerie",
    "gn:population":0,
    "gn:timezone":"Europe/Paris",
    "iso:country":"FR",
    "wof:name":"La Cougellerie",
    "wof:placetype":"locality"
},
  "geometry": {"coordinates":[0.25,48.23333],"type":"Point"}
}