{
  "type": "Feature",
  "properties": {
    "iso:country":"FR",
    "name:eng_x_preferred":[
        "Joliot Curie-Lamaze-Cosmonautes"
    ],
    "name:fra_x_preferred":[
        "Joliot Curie-Lamaze-Cosmonautes"
    ],
    "wof:name":"Joliot Curie-Lamaze-Cosmonautes",
    "wof:placetype":"neighbourhood"
},
  "geometry": {"coordinates":[2.37645708655364,48.93609448336495],"type":"Point"}
}