{
  "type": "Feature",
  "properties": {
    "gn:admin1_code":"93",
    "gn:admin2_code":"05",
    "gn:admin3_code":"051",
    "gn:admin4_code":"05133",
    "gn:asciiname":"Champcella",
    "gn:country_code":"FR",
    "gn:dem":1881,
    "gn:feature_class":"P",
    "gn:feature_code":"PPL",
    "gn:name":"Champcella",
    "gn:population":0,
    "gn:timezone":"Europe/Paris",
    "iso:country":"FR",
    "name:und_x_variant":[
        "Champsella",
        "Champcella"
    ],
    "wof:name":"Champcella",
    "wof:placetype":"locality"
},
  "geometry": {"coordinates":[6.57255,44.92337],"type":"Point"}
}