{
  "type": "Feature",
  "properties": {
    "gn:admin1_code":"93",
    "gn:admin2_code":"05",
    "gn:admin3_code":"051",
    "gn:admin4_code":"05133",
    "gn:asciiname":"Champcella",
    "gn:country_code":"FR",
    "gn:dem":1881,
    "gn:feature_class":"P",
    "gn:feature_code":"PPL",
    "gn:name":"Champcella",
    "gn:population":0,
    "gn:timezone":"Europe/Paris",
    "iso:country":"FR",
    "name:bug_x_preferred":[
        "Champcella"
    ],
    "name:cat_x_preferred":[
        "Champcelat"
    ],
    "name:ceb_x_preferred":[
        "Champcella"
    ],
    "name:deu_x_preferred":[
        "Champcella"
    ],
    "name:eus_x_preferred":[
        "Champcelat"
    ],
    "name:fra_x_preferred":[
        "Champcella"
    ],
    "name:hun_x_preferred":[
        "Champcella"
    ],
    "name:ita_x_preferred":[
        "Champcella"
    ],
    "name:lat_x_preferred":[
        "Champcella"
    ],
    "name:lmo_x_preferred":[
        "Champcella"
    ],
    "name:ltz_x_preferred":[
        "Champcella"
    ],
    "name:msa_x_preferred":[
        "Champcella"
    ],
    "name:nld_x_preferred":[
        "Champcella"
    ],
    "name:oci_x_preferred":[
        "Champcelat"
    ],
    "name:pms_x_preferred":[
        "Champcella"
    ],
    "name:pol_x_preferred":[
        "Champcella"
    ],
    "name:por_x_preferred":[
        "Champcella"
    ],
    "name:ron_x_preferred":[
        "Champcella"
    ],
    "name:rus_x_preferred":[
        "\u0428\u0430\u043d\u0441\u0435\u043b\u043b\u0430"
    ],
    "name:slk_x_preferred":[
        "Champcella"
    ],
    "name:spa_x_preferred":[
        "Champcella"
    ],
    "name:sqi_x_preferred":[
        "Champcella"
    ],
    "name:srp_x_preferred":[
        "\u0428\u0430\u043d\u0441\u0435\u043b\u0430"
    ],
    "name:swe_x_preferred":[
        "Champcella"
    ],
    "name:ukr_x_preferred":[
        "\u0428\u0430\u043c\u0441\u0435\u043b\u043b\u0430"
    ],
    "name:und_x_variant":[
        "Champsella"
    ],
    "name:vie_x_preferred":[
        "Champcella"
    ],
    "name:vol_x_preferred":[
        "Champcella"
    ],
    "name:war_x_preferred":[
        "Champcella"
    ],
    "name:zho_x_preferred":[
        "\u5c1a\u666e\u745f\u62c9"
    ],
    "wof:name":"Champcella",
    "wof:placetype":"locality"
},
  "geometry": {"coordinates":[6.57255,44.92337],"type":"Point"}
}