{
  "type": "Feature",
  "properties": {
    "frgov:code_epci":"200041317",
    "frgov:insee_arr":"2",
    "frgov:insee_com":"79033",
    "frgov:insee_dep":"79",
    "frgov:insee_reg":"75",
    "frgov:nom_com":"Belleville",
    "frgov:nom_com_m":"BELLEVILLE",
    "frgov:nom_dep":"DEUX-SEVRES",
    "frgov:nom_reg":"NOUVELLE-AQUITAINE",
    "frgov:statut":"Commune simple",
    "gn:admin1_code":"75",
    "gn:admin2_code":"79",
    "gn:admin3_code":"792",
    "gn:admin4_code":"79033",
    "gn:asciiname":"Belleville",
    "gn:country_code":"FR",
    "gn:dem":52,
    "gn:feature_class":"P",
    "gn:feature_code":"PPL",
    "gn:name":"Belleville",
    "gn:population":0,
    "gn:timezone":"Europe/Paris",
    "iso:country":"FR",
    "name:azb_x_preferred":[
        "\u0628\u0644\u0648\u06cc\u0644"
    ],
    "name:ben_x_preferred":[
        "\u09ac\u09c7\u09b2\u09ad\u09bf\u09b2\u09c7"
    ],
    "name:cat_x_preferred":[
        "Belleville"
    ],
    "name:ceb_x_preferred":[
        "Belleville"
    ],
    "name:ces_x_preferred":[
        "Belleville"
    ],
    "name:deu_x_preferred":[
        "Belleville"
    ],
    "name:ell_x_preferred":[
        "\u039c\u03c0\u03b5\u03bb\u03b2\u03af\u03bb"
    ],
    "name:est_x_preferred":[
        "Belleville"
    ],
    "name:fas_x_preferred":[
        "\u0628\u0644\u0648\u06cc\u0644"
    ],
    "name:fin_x_preferred":[
        "Belleville"
    ],
    "name:fra_x_preferred":[
        "Belleville"
    ],
    "name:heb_x_preferred":[
        "\u05d1\u05dc\u05d5\u05d5\u05d9\u05dc"
    ],
    "name:hin_x_preferred":[
        "\u092c\u0947\u0932\u0947\u0935\u093f\u0932"
    ],
    "name:hun_x_preferred":[
        "Belleville"
    ],
    "name:ind_x_preferred":[
        "Belleville"
    ],
    "name:ita_x_preferred":[
        "Belleville"
    ],
    "name:jpn_x_preferred":[
        "\u30d9\u30eb\u30d3\u30eb"
    ],
    "name:lat_x_preferred":[
        "Bella Villa"
    ],
    "name:nds_x_preferred":[
        "Belleville"
    ],
    "name:nld_x_preferred":[
        "Belleville"
    ],
    "name:oci_x_preferred":[
        "Belleville"
    ],
    "name:pms_x_preferred":[
        "Belleville"
    ],
    "name:pol_x_preferred":[
        "Belleville"
    ],
    "name:por_x_preferred":[
        "Belleville"
    ],
    "name:ron_x_preferred":[
        "Belleville"
    ],
    "name:rus_x_preferred":[
        "\u0411\u0435\u043b\u044c\u0432\u0438\u043b\u044c"
    ],
    "name:slk_x_preferred":[
        "Belleville"
    ],
    "name:spa_x_preferred":[
        "Belleville"
    ],
    "name:srp_x_preferred":[
        "\u0411\u0435\u043b\u0432\u0438\u043b"
    ],
    "name:swa_x_preferred":[
        "Belleville"
    ],
    "name:swe_x_preferred":[
        "Belleville"
    ],
    "name:ukr_x_preferred":[
        "\u0411\u0435\u043b\u044c\u0432\u0456\u043b\u044c"
    ],
    "name:vol_x_preferred":[
        "Belleville"
    ],
    "name:war_x_preferred":[
        "Belleville"
    ],
    "name:zho_x_preferred":[
        "\u8c9d\u723e\u7dad\u723e"
    ],
    "qs:a0":"France",
    "qs:a1":"DEUX-SEVRES",
    "qs:a1_lc":"79",
    "qs:a1r":"POITOU-CHARENTES",
    "qs:a1r_lc":"54",
    "qs:a2_lc":"03",
    "qs:a2r_lc":"2",
    "qs:adm0":"France",
    "qs:adm0_a3":"FRA",
    "qs:la":"BELLEVILLE",
    "qs:la_lc":"79033",
    "qs:level":"localadmin",
    "qs:type":"Commune simple",
    "wof:coterminous":[
        404391617
    ],
    "wof:name":"Belleville",
    "wof:placetype":"locality",
    "wof:placetype_local":"Commune simple"
},
  "geometry": {"coordinates":[-0.49933,46.12655],"type":"Point"}
}