{
  "type": "Feature",
  "properties": {
    "gn:admin1_code":"75",
    "gn:admin2_code":"79",
    "gn:admin3_code":"792",
    "gn:admin4_code":"79033",
    "gn:asciiname":"Belleville",
    "gn:country_code":"FR",
    "gn:dem":52,
    "gn:feature_class":"P",
    "gn:feature_code":"PPL",
    "gn:name":"Belleville",
    "gn:population":0,
    "gn:timezone":"Europe/Paris",
    "iso:country":"FR",
    "wof:name":"Belleville",
    "wof:placetype":"locality"
},
  "geometry": {"coordinates":[-0.49933,46.12655],"type":"Point"}
}