{
  "type": "Feature",
  "properties": {
    "gn:admin1_code":"75",
    "gn:admin2_code":"19",
    "gn:admin3_code":"192",
    "gn:admin4_code":"19221",
    "gn:asciiname":"La Force, Saint-Martial-Entraygues",
    "gn:country_code":"FR",
    "gn:dem":485,
    "gn:feature_class":"P",
    "gn:feature_code":"PPL",
    "gn:name":"La Force, Saint-Martial-Entraygues",
    "gn:population":0,
    "gn:timezone":"Europe/Paris",
    "iso:country":"FR",
    "wof:name":"La Force, Saint-Martial-Entraygues",
    "wof:placetype":"locality"
},
  "geometry": {"coordinates":[1.97278,45.13356],"type":"Point"}
}