{
  "type": "Feature",
  "properties": {
    "gn:admin1_code":"32",
    "gn:admin2_code":"62",
    "gn:admin3_code":"625",
    "gn:admin4_code":"62153",
    "gn:asciiname":"Greuppe",
    "gn:country_code":"FR",
    "gn:dem":126,
    "gn:feature_class":"P",
    "gn:feature_code":"PPL",
    "gn:name":"Greuppe",
    "gn:population":0,
    "gn:timezone":"Europe/Paris",
    "iso:country":"FR",
    "wof:name":"Greuppe",
    "wof:placetype":"locality"
},
  "geometry": {"coordinates":[2.23085,50.55729],"type":"Point"}
}