{
  "type": "Feature",
  "properties": {
    "gn:admin1_code":"75",
    "gn:admin2_code":"16",
    "gn:admin3_code":"161",
    "gn:admin4_code":"16353",
    "gn:asciiname":"Les Chaumes",
    "gn:country_code":"FR",
    "gn:dem":114,
    "gn:feature_class":"P",
    "gn:feature_code":"PPL",
    "gn:name":"Les Chaumes",
    "gn:population":0,
    "gn:timezone":"Europe/Paris",
    "iso:country":"FR",
    "wof:name":"Les Chaumes",
    "wof:placetype":"locality"
},
  "geometry": {"coordinates":[0.42537,45.70699000000001],"type":"Point"}
}