{
  "type": "Feature",
  "properties": {
    "gn:admin1_code":"84",
    "gn:admin2_code":"03",
    "gn:admin3_code":"031",
    "gn:admin4_code":"03317",
    "gn:asciiname":"Armelle",
    "gn:country_code":"FR",
    "gn:dem":398,
    "gn:feature_class":"P",
    "gn:feature_code":"PPL",
    "gn:name":"Armelle",
    "gn:population":0,
    "gn:timezone":"Europe/Paris",
    "iso:country":"FR",
    "name:deu_x_preferred":[
        "Armelle"
    ],
    "name:fra_x_preferred":[
        "Armelle"
    ],
    "name:lat_x_preferred":[
        "Armelle Le\u015bniak"
    ],
    "wof:name":"Armelle",
    "wof:placetype":"locality"
},
  "geometry": {"coordinates":[2.40337,46.43687],"type":"Point"}
}