{
  "type": "Feature",
  "properties": {
    "gn:admin1_code":"84",
    "gn:admin2_code":"01",
    "gn:admin3_code":"011",
    "gn:admin4_code":"01122",
    "gn:asciiname":"Vaux-Saint-Sulpice",
    "gn:cc2":"FR",
    "gn:country_code":"FR",
    "gn:dem":795,
    "gn:feature_class":"P",
    "gn:feature_code":"PPL",
    "gn:name":"Vaux-Saint-Sulpice",
    "gn:population":0,
    "gn:timezone":"Europe/Paris",
    "iso:country":"FR",
    "name:und_x_variant":[
        "Vaux",
        "Vaux-Saint-Sulpice"
    ],
    "wof:name":"Vaux-Saint-Sulpice",
    "wof:placetype":"locality"
},
  "geometry": {"coordinates":[5.59444,45.93927],"type":"Point"}
}