{
  "type": "Feature",
  "properties": {
    "gn:admin1_code":"24",
    "gn:admin2_code":"45",
    "gn:admin3_code":"453",
    "gn:admin4_code":"45069.0",
    "gn:asciiname":"La Rive du Bois",
    "gn:country_code":"FR",
    "gn:dem":117,
    "gn:feature_class":"P",
    "gn:feature_code":"PPL",
    "gn:name":"La Rive du Bois",
    "gn:population":0,
    "gn:timezone":"Europe/Paris",
    "iso:country":"FR",
    "wof:name":"La Rive du Bois",
    "wof:placetype":"locality"
},
  "geometry": {"coordinates":[2.28562,48.06407],"type":"Point"}
}