{
  "type": "Feature",
  "properties": {
    "gn:admin1_code":"75",
    "gn:admin2_code":"24",
    "gn:admin3_code":"241",
    "gn:admin4_code":"24161",
    "gn:asciiname":"Grands Champs",
    "gn:country_code":"FR",
    "gn:dem":129,
    "gn:feature_class":"P",
    "gn:feature_code":"PPL",
    "gn:name":"Grands Champs",
    "gn:population":0,
    "gn:timezone":"Europe/Paris",
    "iso:country":"FR",
    "wof:name":"Grands Champs",
    "wof:placetype":"locality"
},
  "geometry": {"coordinates":[0.41566,44.99791],"type":"Point"}
}