{
  "type": "Feature",
  "properties": {
    "gn:admin1_code":"27",
    "gn:admin2_code":"21",
    "gn:admin3_code":"212",
    "gn:admin4_code":"21646.0",
    "gn:asciiname":"Fromenteau",
    "gn:country_code":"FR",
    "gn:dem":574,
    "gn:feature_class":"P",
    "gn:feature_code":"PPL",
    "gn:name":"Fromenteau",
    "gn:population":0,
    "gn:timezone":"Europe/Paris",
    "iso:country":"FR",
    "name:deu_x_preferred":[
        "Fromenteau"
    ],
    "name:fra_x_preferred":[
        "Fromenteau"
    ],
    "wof:name":"Fromenteau",
    "wof:placetype":"locality"
},
  "geometry": {"coordinates":[4.77881,47.39667],"type":"Point"}
}