{
  "type": "Feature",
  "properties": {
    "gn:admin1_code":"32",
    "gn:admin2_code":"60",
    "gn:admin3_code":"601",
    "gn:admin4_code":"60626",
    "gn:asciiname":"Les Landes",
    "gn:country_code":"FR",
    "gn:dem":175,
    "gn:feature_class":"P",
    "gn:feature_code":"PPL",
    "gn:name":"Les Landes",
    "gn:population":0,
    "gn:timezone":"Europe/Paris",
    "iso:country":"FR",
    "name:fra_x_preferred":[
        "Les Landes"
    ],
    "wof:name":"Les Landes",
    "wof:placetype":"locality"
},
  "geometry": {"coordinates":[1.75276,49.39341],"type":"Point"}
}