{
  "type": "Feature",
  "properties": {
    "gn:admin1_code":"84",
    "gn:admin2_code":"73",
    "gn:admin3_code":"731",
    "gn:admin4_code":"73296",
    "gn:asciiname":"Franchet",
    "gn:country_code":"FR",
    "gn:dem":1906,
    "gn:feature_class":"P",
    "gn:feature_code":"PPL",
    "gn:name":"Franchet",
    "gn:population":0,
    "gn:timezone":"Europe/Paris",
    "iso:country":"FR",
    "wof:name":"Franchet",
    "wof:placetype":"locality"
},
  "geometry": {"coordinates":[6.95387,45.47502],"type":"Point"}
}