{
  "type": "Feature",
  "properties": {
    "gn:admin1_code":"53",
    "gn:admin2_code":"56",
    "gn:admin3_code":"562",
    "gn:admin4_code":"56236",
    "gn:asciiname":"Saint-Goberien",
    "gn:country_code":"FR",
    "gn:dem":31,
    "gn:feature_class":"P",
    "gn:feature_code":"PPL",
    "gn:name":"Saint-Goberien",
    "gn:population":0,
    "gn:timezone":"Europe/Paris",
    "iso:country":"FR",
    "name:und_x_variant":[
        "Saint-Gobrien",
        "Saint-Goberien"
    ],
    "wof:name":"Saint-Goberien",
    "wof:placetype":"locality"
},
  "geometry": {"coordinates":[-2.51533,47.92724000000001],"type":"Point"}
}