{
  "type": "Feature",
  "properties": {
    "gn:admin1_code":"53",
    "gn:admin2_code":"29",
    "gn:admin3_code":"293",
    "gn:admin4_code":"29074",
    "gn:asciiname":"Kerroual",
    "gn:country_code":"FR",
    "gn:dem":142,
    "gn:feature_class":"P",
    "gn:feature_code":"PPL",
    "gn:name":"Kerroual",
    "gn:population":0,
    "gn:timezone":"Europe/Paris",
    "iso:country":"FR",
    "wof:name":"Kerroual",
    "wof:placetype":"locality"
},
  "geometry": {"coordinates":[-4.01209,48.46725],"type":"Point"}
}