{
  "type": "Feature",
  "properties": {
    "iso:country":"FR",
    "name:eng_x_preferred":[
        "Hotel de Ville"
    ],
    "name:fra_x_preferred":[
        "H\u00f4tel de Ville"
    ],
    "wof:name":"Hotel de Ville",
    "wof:placetype":"neighbourhood"
},
  "geometry": {"coordinates":[2.47262144885377,48.84968035777305],"type":"Point"}
}