{
  "type": "Feature",
  "properties": {
    "gn:admin1_code":"84",
    "gn:admin2_code":"07",
    "gn:admin3_code":"073",
    "gn:admin4_code":"07040",
    "gn:asciiname":"Montchal",
    "gn:country_code":"FR",
    "gn:dem":504,
    "gn:feature_class":"P",
    "gn:feature_code":"PPL",
    "gn:name":"Montchal",
    "gn:population":0,
    "gn:timezone":"Europe/Paris",
    "iso:country":"FR",
    "name:cat_x_preferred":[
        "Montchal"
    ],
    "name:ceb_x_preferred":[
        "Montchal"
    ],
    "name:deu_x_preferred":[
        "Montchal"
    ],
    "name:eus_x_preferred":[
        "Montchal"
    ],
    "name:fra_x_preferred":[
        "Montchal"
    ],
    "name:hun_x_preferred":[
        "Montchal"
    ],
    "name:ita_x_preferred":[
        "Montchal"
    ],
    "name:lat_x_preferred":[
        "Montchal"
    ],
    "name:lmo_x_preferred":[
        "Montchal"
    ],
    "name:mlg_x_preferred":[
        "Montchal"
    ],
    "name:msa_x_preferred":[
        "Montchal"
    ],
    "name:nld_x_preferred":[
        "Montchal"
    ],
    "name:oci_x_preferred":[
        "Montchal"
    ],
    "name:pms_x_preferred":[
        "Montchal"
    ],
    "name:pol_x_preferred":[
        "Montchal"
    ],
    "name:por_x_preferred":[
        "Montchal"
    ],
    "name:ron_x_preferred":[
        "Montchal"
    ],
    "name:slk_x_preferred":[
        "Montchal"
    ],
    "name:spa_x_preferred":[
        "Montchal"
    ],
    "name:swe_x_preferred":[
        "Montchal"
    ],
    "name:ukr_x_preferred":[
        "\u041c\u043e\u043d\u0448\u0430\u043b\u044c"
    ],
    "name:uzb_x_preferred":[
        "Montchal"
    ],
    "name:vie_x_preferred":[
        "Montchal"
    ],
    "name:vol_x_preferred":[
        "Montchal"
    ],
    "name:war_x_preferred":[
        "Montchal"
    ],
    "name:zho_x_preferred":[
        "\u8499\u7279\u6c99"
    ],
    "wof:name":"Montchal",
    "wof:placetype":"locality"
},
  "geometry": {"coordinates":[4.6771,45.02426],"type":"Point"}
}