{
  "type": "Feature",
  "properties": {
    "gn:admin1_code":"84",
    "gn:admin2_code":"07",
    "gn:admin3_code":"073",
    "gn:admin4_code":"07040",
    "gn:asciiname":"Montchal",
    "gn:country_code":"FR",
    "gn:dem":504,
    "gn:feature_class":"P",
    "gn:feature_code":"PPL",
    "gn:name":"Montchal",
    "gn:population":0,
    "gn:timezone":"Europe/Paris",
    "iso:country":"FR",
    "wof:name":"Montchal",
    "wof:placetype":"locality"
},
  "geometry": {"coordinates":[4.6771,45.02426],"type":"Point"}
}