{
  "type": "Feature",
  "properties": {
    "gn:admin1_code":"93",
    "gn:admin2_code":"04",
    "gn:admin3_code":"041",
    "gn:admin4_code":"04062",
    "gn:asciiname":"Sainte-Anne",
    "gn:cc2":"FR",
    "gn:country_code":"FR",
    "gn:dem":1763,
    "gn:feature_class":"P",
    "gn:feature_code":"PPL",
    "gn:name":"Sainte-Anne",
    "gn:population":0,
    "gn:timezone":"Europe/Paris",
    "iso:country":"FR",
    "name:und_x_variant":[
        "Chapelle Sainte-Anne",
        "Sainte-Anne"
    ],
    "wof:name":"Sainte-Anne",
    "wof:placetype":"locality"
},
  "geometry": {"coordinates":[6.7135,44.47863],"type":"Point"}
}