{
  "type": "Feature",
  "properties": {
    "gn:admin1_code":"75",
    "gn:admin2_code":"24",
    "gn:admin3_code":"243",
    "gn:admin4_code":"24026",
    "gn:asciiname":"Blanzac",
    "gn:country_code":"FR",
    "gn:dem":104,
    "gn:feature_class":"P",
    "gn:feature_code":"PPL",
    "gn:name":"Blanzac",
    "gn:population":0,
    "gn:timezone":"Europe/Paris",
    "iso:country":"FR",
    "name:ceb_x_preferred":[
        "Blanzac"
    ],
    "name:deu_x_preferred":[
        "Blanzac"
    ],
    "name:epo_x_preferred":[
        "Blanzac"
    ],
    "name:fra_x_preferred":[
        "Blanzac"
    ],
    "name:ita_x_preferred":[
        "Blanzac"
    ],
    "name:nds_x_preferred":[
        "Blanzac"
    ],
    "name:nld_x_preferred":[
        "Blanzac"
    ],
    "name:pms_x_preferred":[
        "Blanzac"
    ],
    "name:pol_x_preferred":[
        "Blanzac"
    ],
    "name:por_x_preferred":[
        "Blanzac"
    ],
    "name:slk_x_preferred":[
        "Blanzac"
    ],
    "name:spa_x_preferred":[
        "Blanzac"
    ],
    "name:srp_x_preferred":[
        "\u0411\u043b\u0430\u043d\u0437\u0430\u043a"
    ],
    "name:swe_x_preferred":[
        "Blanzac"
    ],
    "name:ukr_x_preferred":[
        "\u0411\u043b\u0430\u043d\u0437\u0430\u043a"
    ],
    "wof:name":"Blanzac",
    "wof:placetype":"locality"
},
  "geometry": {"coordinates":[0.86832,45.18787],"type":"Point"}
}