{
  "type": "Feature",
  "properties": {
    "gn:admin1_code":"52",
    "gn:admin2_code":"44",
    "gn:admin3_code":"441",
    "gn:admin4_code":"44149",
    "gn:asciiname":"Saffre",
    "gn:country_code":"FR",
    "gn:dem":27,
    "gn:feature_class":"P",
    "gn:feature_code":"PPL",
    "gn:name":"Saffr\u00e9",
    "gn:population":2884,
    "gn:timezone":"Europe/Paris",
    "iso:country":"FR",
    "name:aka_x_preferred":[
        "Saffr\u00e9"
    ],
    "name:ast_x_preferred":[
        "Saffr\u00e9"
    ],
    "name:bam_x_preferred":[
        "Saffr\u00e9"
    ],
    "name:bre_x_preferred":[
        "Saverieg"
    ],
    "name:cat_x_preferred":[
        "Saffr\u00e9"
    ],
    "name:ceb_x_preferred":[
        "Saffr\u00e9"
    ],
    "name:cym_x_preferred":[
        "Saverieg"
    ],
    "name:deu_x_preferred":[
        "Saffr\u00e9"
    ],
    "name:eus_x_preferred":[
        "Saffr\u00e9"
    ],
    "name:fra_x_preferred":[
        "Saffr\u00e9"
    ],
    "name:hun_x_preferred":[
        "Saffr\u00e9"
    ],
    "name:ita_x_preferred":[
        "Saffr\u00e9"
    ],
    "name:lat_x_preferred":[
        "Safriacum"
    ],
    "name:mlg_x_preferred":[
        "Saffr\u00e9"
    ],
    "name:msa_x_preferred":[
        "Saffr\u00e9"
    ],
    "name:nld_x_preferred":[
        "Saffr\u00e9"
    ],
    "name:oci_x_preferred":[
        "Saverieg"
    ],
    "name:pms_x_preferred":[
        "Saffr\u00e9"
    ],
    "name:pol_x_preferred":[
        "Saffr\u00e9"
    ],
    "name:por_x_preferred":[
        "Saffr\u00e9"
    ],
    "name:ron_x_preferred":[
        "Saffr\u00e9"
    ],
    "name:slk_x_preferred":[
        "Saffr\u00e9"
    ],
    "name:spa_x_preferred":[
        "Saffr\u00e9"
    ],
    "name:swe_x_preferred":[
        "Saffr\u00e9"
    ],
    "name:ukr_x_preferred":[
        "\u0421\u0430\u0444\u0444\u0440\u0435"
    ],
    "name:und_x_variant":[
        "Saffr\u00e9"
    ],
    "name:urd_x_preferred":[
        "\u0633\u0641\u0641\u0631\u06d2"
    ],
    "name:vie_x_preferred":[
        "Saffr\u00e9"
    ],
    "name:vol_x_preferred":[
        "Saffr\u00e9"
    ],
    "name:war_x_preferred":[
        "Saffr\u00e9"
    ],
    "name:zho_x_preferred":[
        "\u8428\u592b\u96f7"
    ],
    "wof:name":"Saffre",
    "wof:placetype":"locality",
    "wof:population":2884
},
  "geometry": {"coordinates":[-1.57856,47.50143],"type":"Point"}
}