{
  "type": "Feature",
  "properties": {
    "gn:admin1_code":"28",
    "gn:admin2_code":"76",
    "gn:admin3_code":"761",
    "gn:admin4_code":"76063.0",
    "gn:asciiname":"Bosc Renoult",
    "gn:country_code":"FR",
    "gn:dem":140,
    "gn:feature_class":"P",
    "gn:feature_code":"PPL",
    "gn:name":"Bosc Renoult",
    "gn:population":0,
    "gn:timezone":"Europe/Paris",
    "iso:country":"FR",
    "wof:name":"Bosc Renoult",
    "wof:placetype":"locality"
},
  "geometry": {"coordinates":[1.02035,49.72071],"type":"Point"}
}