{
  "type": "Feature",
  "properties": {
    "gn:admin1_code":"84",
    "gn:admin2_code":"63",
    "gn:admin3_code":"632",
    "gn:admin4_code":"63326",
    "gn:asciiname":"Villejacques",
    "gn:country_code":"FR",
    "gn:dem":821,
    "gn:feature_class":"P",
    "gn:feature_code":"PPL",
    "gn:name":"Villejacques",
    "gn:population":0,
    "gn:timezone":"Europe/Paris",
    "iso:country":"FR",
    "wof:name":"Villejacques",
    "wof:placetype":"locality"
},
  "geometry": {"coordinates":[2.8624,45.71676],"type":"Point"}
}