{
  "type": "Feature",
  "properties": {
    "iso:country":"FR",
    "name:fra_x_preferred":[
        "Haute-Indre"
    ],
    "name:unk_x_variant":[
        "Haute-Indre"
    ],
    "qs:gn_adm0_cc":"FR",
    "qs:gn_fcode":"PPL",
    "qs:gn_local":6616810,
    "qs:gn_nam_loc":"Indre, Loire-Atlantique, Pays de la Loire, FR",
    "qs:gn_namadm1":"B5",
    "qs:gn_name":"Haute-Indre",
    "qs:local_max":371,
    "qs:local_sum":371,
    "qs:localhoods":1,
    "qs:name":"Haute-Indre",
    "qs:name_adm0":"France",
    "qs:name_adm1":"Pays de la Loire",
    "qs:name_adm2":"Loire-Atlantique",
    "qs:name_lau":"Indre",
    "qs:name_local":"Indre",
    "qs:photo_max":67,
    "qs:photo_sum":371,
    "qs:placetype":"Suburb",
    "qs:quad_count":43,
    "qs:woe_adm0":23424819,
    "qs:woe_adm1":7153325,
    "qs:woe_adm2":12597177,
    "qs:woe_lau":12656339,
    "qs:woe_local":12656339,
    "qs:woe_ver":"7.10.0",
    "wof:lang":[
        "fre"
    ],
    "wof:name":"Haute-Indre",
    "wof:placetype":"neighbourhood"
},
  "geometry": {"coordinates":[-1.659226,47.201761],"type":"Point"}
}