{
  "type": "Feature",
  "properties": {
    "gn:admin1_code":"75",
    "gn:admin2_code":"86",
    "gn:admin3_code":"861",
    "gn:admin4_code":"86174",
    "gn:asciiname":"Les Barres",
    "gn:country_code":"FR",
    "gn:dem":58,
    "gn:feature_class":"P",
    "gn:feature_code":"PPL",
    "gn:name":"Les Barres",
    "gn:population":0,
    "gn:timezone":"Europe/Paris",
    "iso:country":"FR",
    "wof:name":"Les Barres",
    "wof:placetype":"locality"
},
  "geometry": {"coordinates":[0.49419,46.76495],"type":"Point"}
}