{
  "type": "Feature",
  "properties": {
    "gn:admin1_code":"84",
    "gn:admin2_code":"63",
    "gn:admin3_code":"633",
    "gn:admin4_code":"63346",
    "gn:asciiname":"La Joux",
    "gn:country_code":"FR",
    "gn:dem":1042,
    "gn:feature_class":"P",
    "gn:feature_code":"PPL",
    "gn:name":"La Joux",
    "gn:population":0,
    "gn:timezone":"Europe/Paris",
    "iso:country":"FR",
    "wof:name":"La Joux",
    "wof:placetype":"locality"
},
  "geometry": {"coordinates":[2.73606,45.44029000000001],"type":"Point"}
}