{
  "type": "Feature",
  "properties": {
    "gn:admin1_code":"84",
    "gn:admin2_code":"43",
    "gn:admin3_code":"433",
    "gn:admin4_code":"43236",
    "gn:asciiname":"Salgotier",
    "gn:country_code":"FR",
    "gn:dem":802,
    "gn:feature_class":"P",
    "gn:feature_code":"PPL",
    "gn:name":"Salgotier",
    "gn:population":0,
    "gn:timezone":"Europe/Paris",
    "iso:country":"FR",
    "wof:name":"Salgotier",
    "wof:placetype":"locality"
},
  "geometry": {"coordinates":[4.23753,45.30345],"type":"Point"}
}