{
  "type": "Feature",
  "properties": {
    "gn:admin1_code":"27",
    "gn:admin2_code":"89",
    "gn:admin3_code":"892",
    "gn:admin4_code":"89381",
    "gn:asciiname":"Le Vellerot",
    "gn:country_code":"FR",
    "gn:dem":242,
    "gn:feature_class":"P",
    "gn:feature_code":"PPL",
    "gn:name":"Le Vellerot",
    "gn:population":0,
    "gn:timezone":"Europe/Paris",
    "iso:country":"FR",
    "wof:name":"Le Vellerot",
    "wof:placetype":"locality"
},
  "geometry": {"coordinates":[4.03107,47.51631],"type":"Point"}
}