{
  "type": "Feature",
  "properties": {
    "gn:admin1_code":"24",
    "gn:admin2_code":"36",
    "gn:admin3_code":"363",
    "gn:admin4_code":"36207",
    "gn:asciiname":"Saint-Jallet",
    "gn:country_code":"FR",
    "gn:dem":301,
    "gn:feature_class":"P",
    "gn:feature_code":"PPL",
    "gn:name":"Saint-Jallet",
    "gn:population":0,
    "gn:timezone":"Europe/Paris",
    "iso:country":"FR",
    "wof:name":"Saint-Jallet",
    "wof:placetype":"locality"
},
  "geometry": {"coordinates":[1.63055,46.40166],"type":"Point"}
}