{
  "type": "Feature",
  "properties": {
    "gn:admin1_code":"84",
    "gn:admin2_code":"38",
    "gn:admin3_code":"381",
    "gn:admin4_code":"38115",
    "gn:asciiname":"Deytras",
    "gn:country_code":"FR",
    "gn:dem":732,
    "gn:feature_class":"P",
    "gn:feature_code":"PPL",
    "gn:name":"Deytras",
    "gn:population":0,
    "gn:timezone":"Europe/Paris",
    "iso:country":"FR",
    "wof:name":"Deytras",
    "wof:placetype":"locality"
},
  "geometry": {"coordinates":[5.66116,44.97072],"type":"Point"}
}