{
  "type": "Feature",
  "properties": {
    "gn:admin1_code":"84",
    "gn:admin2_code":"07",
    "gn:admin3_code":"073",
    "gn:admin4_code":"07165",
    "gn:asciiname":"Pourchoie",
    "gn:country_code":"FR",
    "gn:dem":670,
    "gn:feature_class":"P",
    "gn:feature_code":"PPL",
    "gn:name":"Pourchoie",
    "gn:population":0,
    "gn:timezone":"Europe/Paris",
    "iso:country":"FR",
    "wof:name":"Pourchoie",
    "wof:placetype":"locality"
},
  "geometry": {"coordinates":[4.47126,44.92542],"type":"Point"}
}