{
  "type": "Feature",
  "properties": {
    "gn:admin1_code":"76",
    "gn:admin2_code":"11",
    "gn:admin3_code":"112",
    "gn:admin4_code":"11263",
    "gn:asciiname":"Lafage",
    "gn:country_code":"FR",
    "gn:dem":642,
    "gn:feature_class":"P",
    "gn:feature_code":"PPL",
    "gn:name":"Lafage",
    "gn:population":0,
    "gn:timezone":"Europe/Paris",
    "iso:country":"FR",
    "name:cat_x_preferred":[
        "La Faja"
    ],
    "name:ceb_x_preferred":[
        "Lafage"
    ],
    "name:deu_x_preferred":[
        "Lafage"
    ],
    "name:eus_x_preferred":[
        "Lafage"
    ],
    "name:fra_x_preferred":[
        "Lafage"
    ],
    "name:hun_x_preferred":[
        "Lafage"
    ],
    "name:hye_x_preferred":[
        "\u053c\u0561\u0586\u0561\u056a"
    ],
    "name:ita_x_preferred":[
        "Lafage"
    ],
    "name:kaz_x_preferred":[
        "\u041b\u0430\u0444\u0430\u0436"
    ],
    "name:lat_x_preferred":[
        "Lafage"
    ],
    "name:msa_x_preferred":[
        "Lafage"
    ],
    "name:nld_x_preferred":[
        "Lafage"
    ],
    "name:oci_x_preferred":[
        "La Faja"
    ],
    "name:pms_x_preferred":[
        "Lafage"
    ],
    "name:pol_x_preferred":[
        "Lafage"
    ],
    "name:por_x_preferred":[
        "Lafage"
    ],
    "name:ron_x_preferred":[
        "Lafage"
    ],
    "name:rus_x_preferred":[
        "\u041b\u0430\u0444\u0430\u0436"
    ],
    "name:slk_x_preferred":[
        "Lafage"
    ],
    "name:spa_x_preferred":[
        "Lafage"
    ],
    "name:swe_x_preferred":[
        "Lafage"
    ],
    "name:ukr_x_preferred":[
        "\u041b\u0430\u0444\u0430\u0436"
    ],
    "name:urd_x_preferred":[
        "\u0644\u0627\u0641\u0627\u06af\u06cc"
    ],
    "name:vie_x_preferred":[
        "Lafage"
    ],
    "name:vol_x_preferred":[
        "Lafage"
    ],
    "name:war_x_preferred":[
        "Lafage"
    ],
    "name:zho_x_preferred":[
        "\u62c9\u6cd5\u683c"
    ],
    "wof:name":"Lafage",
    "wof:placetype":"locality"
},
  "geometry": {"coordinates":[2.12743,42.88042],"type":"Point"}
}