{
  "type": "Feature",
  "properties": {
    "gn:admin1_code":"84",
    "gn:admin2_code":"01",
    "gn:admin3_code":"011",
    "gn:admin4_code":"01403",
    "gn:asciiname":"Serrieres-de-Briord",
    "gn:country_code":"FR",
    "gn:dem":226,
    "gn:feature_class":"P",
    "gn:feature_code":"PPL",
    "gn:name":"Serri\u00e8res-de-Briord",
    "gn:population":1143,
    "gn:timezone":"Europe/Paris",
    "iso:country":"FR",
    "name:und_x_variant":[
        "Serri\u00e8res",
        "Serri\u00e8res-de-Briord"
    ],
    "wof:name":"Serrieres-de-Briord",
    "wof:placetype":"locality",
    "wof:population":1143
},
  "geometry": {"coordinates":[5.44831,45.80701],"type":"Point"}
}