{
  "type": "Feature",
  "properties": {
    "gn:admin1_code":"84",
    "gn:admin2_code":"03",
    "gn:admin3_code":"031",
    "gn:admin4_code":"03269",
    "gn:asciiname":"Lavault",
    "gn:country_code":"FR",
    "gn:dem":250,
    "gn:feature_class":"P",
    "gn:feature_code":"PPL",
    "gn:name":"Lavault",
    "gn:population":0,
    "gn:timezone":"Europe/Paris",
    "iso:country":"FR",
    "wof:name":"Lavault",
    "wof:placetype":"locality"
},
  "geometry": {"coordinates":[2.83333,46.45],"type":"Point"}
}