{
  "type": "Feature",
  "properties": {
    "gn:admin1_code":"24",
    "gn:admin2_code":"45",
    "gn:admin3_code":"452",
    "gn:admin4_code":"45153",
    "gn:asciiname":"Le Menil",
    "gn:country_code":"FR",
    "gn:dem":107,
    "gn:feature_class":"P",
    "gn:feature_code":"PPL",
    "gn:name":"Le M\u00e9nil",
    "gn:population":0,
    "gn:timezone":"Europe/Paris",
    "iso:country":"FR",
    "name:und_x_variant":[
        "Le Mesnil",
        "Le M\u00e9nil"
    ],
    "wof:name":"Le Menil",
    "wof:placetype":"locality"
},
  "geometry": {"coordinates":[2.2534,47.8398],"type":"Point"}
}