{
  "type": "Feature",
  "properties": {
    "gn:admin1_code":"24",
    "gn:admin2_code":"28",
    "gn:admin3_code":"281",
    "gn:admin4_code":"28183",
    "gn:asciiname":"Arnouville",
    "gn:country_code":"FR",
    "gn:dem":144,
    "gn:feature_class":"P",
    "gn:feature_code":"PPL",
    "gn:name":"Arnouville",
    "gn:population":0,
    "gn:timezone":"Europe/Paris",
    "iso:country":"FR",
    "name:aze_x_preferred":[
        "Arnuvil"
    ],
    "name:cat_x_preferred":[
        "Arnouville"
    ],
    "name:ceb_x_preferred":[
        "Arnouville"
    ],
    "name:deu_x_preferred":[
        "Arnouville"
    ],
    "name:epo_x_preferred":[
        "Arnouville"
    ],
    "name:eus_x_preferred":[
        "Arnouville"
    ],
    "name:fra_x_preferred":[
        "Arnouville"
    ],
    "name:hun_x_preferred":[
        "Arnouville"
    ],
    "name:ita_x_preferred":[
        "Arnouville"
    ],
    "name:kaz_x_preferred":[
        "\u0410\u0440\u043d\u0443\u0432\u0438\u043b\u044c"
    ],
    "name:lat_x_preferred":[
        "Arnouville"
    ],
    "name:msa_x_preferred":[
        "Arnouville"
    ],
    "name:nld_x_preferred":[
        "Arnouville"
    ],
    "name:oci_x_preferred":[
        "Arnouville"
    ],
    "name:pol_x_preferred":[
        "Arnouville"
    ],
    "name:por_x_preferred":[
        "Arnouville"
    ],
    "name:rus_x_preferred":[
        "\u0410\u0440\u043d\u0443\u0432\u0438\u043b\u044c"
    ],
    "name:slk_x_preferred":[
        "Arnouville"
    ],
    "name:spa_x_preferred":[
        "Arnouville"
    ],
    "name:sqi_x_preferred":[
        "Arnouville"
    ],
    "name:srp_x_preferred":[
        "\u0410\u0440\u043d\u0443\u0432\u0438\u043b"
    ],
    "name:swe_x_preferred":[
        "Arnouville"
    ],
    "name:ukr_x_preferred":[
        "\u0410\u0440\u043d\u0443\u0432\u0456\u043b\u044c"
    ],
    "name:vie_x_preferred":[
        "Arnouville"
    ],
    "name:vol_x_preferred":[
        "Arnouville"
    ],
    "name:war_x_preferred":[
        "Arnouville"
    ],
    "name:zho_x_preferred":[
        "\u963f\u52aa\u7ef4\u52d2"
    ],
    "wof:name":"Arnouville",
    "wof:placetype":"locality"
},
  "geometry": {"coordinates":[1.94854,48.32105],"type":"Point"}
}