{
  "type": "Feature",
  "properties": {
    "gn:admin1_code":"44",
    "gn:admin2_code":"10",
    "gn:admin3_code":"103",
    "gn:admin4_code":"10359",
    "gn:asciiname":"Foret-Chenu",
    "gn:country_code":"FR",
    "gn:dem":276,
    "gn:feature_class":"P",
    "gn:feature_code":"PPL",
    "gn:name":"For\u00eat-Chenu",
    "gn:population":0,
    "gn:timezone":"Europe/Paris",
    "iso:country":"FR",
    "wof:name":"Foret-Chenu",
    "wof:placetype":"locality"
},
  "geometry": {"coordinates":[3.93051,48.14086],"type":"Point"}
}