{
  "type": "Feature",
  "properties": {
    "gn:admin1_code":"75",
    "gn:admin2_code":"47",
    "gn:admin3_code":"474",
    "gn:admin4_code":"47222",
    "gn:asciiname":"Couthures",
    "gn:country_code":"FR",
    "gn:dem":106,
    "gn:feature_class":"P",
    "gn:feature_code":"PPL",
    "gn:name":"Couthures",
    "gn:population":0,
    "gn:timezone":"Europe/Paris",
    "iso:country":"FR",
    "wof:name":"Couthures",
    "wof:placetype":"locality"
},
  "geometry": {"coordinates":[0.10859,44.26974000000001],"type":"Point"}
}