{
  "type": "Feature",
  "properties": {
    "gn:admin1_code":"24",
    "gn:admin2_code":"37",
    "gn:admin3_code":"373",
    "gn:admin4_code":"37132",
    "gn:asciiname":"La Bouchardiere",
    "gn:country_code":"FR",
    "gn:dem":112,
    "gn:feature_class":"P",
    "gn:feature_code":"PPL",
    "gn:name":"La Bouchardi\u00e8re",
    "gn:population":0,
    "gn:timezone":"Europe/Paris",
    "iso:country":"FR",
    "wof:name":"La Bouchardiere",
    "wof:placetype":"locality"
},
  "geometry": {"coordinates":[0.9739,47.12435],"type":"Point"}
}