{
  "type": "Feature",
  "properties": {
    "iso:country":"FR",
    "name:eng_x_preferred":[
        "Poincare-Bergson-Brezin"
    ],
    "name:fra_x_preferred":[
        "Poincar\u00e9-Bergson-Br\u00e9zin"
    ],
    "wof:name":"Poincare-Bergson-Brezin",
    "wof:placetype":"neighbourhood"
},
  "geometry": {"coordinates":[2.17572046287809,48.84104235270031],"type":"Point"}
}