{
  "type": "Feature",
  "properties": {
    "gn:admin1_code":"53",
    "gn:admin2_code":"22",
    "gn:admin3_code":"224",
    "gn:admin4_code":"22063",
    "gn:asciiname":"Le Guily",
    "gn:country_code":"FR",
    "gn:dem":77,
    "gn:feature_class":"P",
    "gn:feature_code":"PPL",
    "gn:name":"Le Guily",
    "gn:population":0,
    "gn:timezone":"Europe/Paris",
    "iso:country":"FR",
    "name:und_x_variant":[
        "Le Guilly",
        "Le Guily"
    ],
    "wof:name":"Le Guily",
    "wof:placetype":"locality"
},
  "geometry": {"coordinates":[-3.06789,48.64634],"type":"Point"}
}