{
  "type": "Feature",
  "properties": {
    "gn:admin1_code":"84",
    "gn:admin2_code":"73",
    "gn:admin3_code":"732",
    "gn:admin4_code":"73021",
    "gn:asciiname":"Val Pelouse",
    "gn:country_code":"FR",
    "gn:dem":1684,
    "gn:feature_class":"P",
    "gn:feature_code":"PPL",
    "gn:name":"Val Pelouse",
    "gn:population":0,
    "gn:timezone":"Europe/Paris",
    "iso:country":"FR",
    "wof:name":"Val Pelouse",
    "wof:placetype":"locality"
},
  "geometry": {"coordinates":[6.16788,45.41921],"type":"Point"}
}