{
  "type": "Feature",
  "properties": {
    "gn:admin1_code":"84",
    "gn:admin2_code":"15",
    "gn:admin3_code":"153",
    "gn:admin4_code":"15244",
    "gn:asciiname":"Luc",
    "gn:country_code":"FR",
    "gn:dem":992,
    "gn:feature_class":"P",
    "gn:feature_code":"PPL",
    "gn:name":"Luc",
    "gn:population":0,
    "gn:timezone":"Europe/Paris",
    "iso:country":"FR",
    "wof:name":"Luc",
    "wof:placetype":"locality"
},
  "geometry": {"coordinates":[2.9753,45.06337],"type":"Point"}
}