{
  "type": "Feature",
  "properties": {
    "gn:admin1_code":"84",
    "gn:admin2_code":"15",
    "gn:admin3_code":"153",
    "gn:admin4_code":"15244",
    "gn:asciiname":"Luc",
    "gn:country_code":"FR",
    "gn:dem":992,
    "gn:feature_class":"P",
    "gn:feature_code":"PPL",
    "gn:name":"Luc",
    "gn:population":0,
    "gn:timezone":"Europe/Paris",
    "iso:country":"FR",
    "name:ceb_x_preferred":[
        "Luc"
    ],
    "name:deu_x_preferred":[
        "Luc"
    ],
    "name:fin_x_preferred":[
        "Luc"
    ],
    "name:fra_x_preferred":[
        "Luc"
    ],
    "name:hun_x_preferred":[
        "Luc"
    ],
    "name:jpn_x_preferred":[
        "\u30ea\u30e5\u30c3\u30af"
    ],
    "name:nds_x_preferred":[
        "Luc"
    ],
    "name:nld_x_preferred":[
        "Luc"
    ],
    "name:oci_x_preferred":[
        "Luc"
    ],
    "name:pms_x_preferred":[
        "Luc"
    ],
    "name:pol_x_preferred":[
        "Luc"
    ],
    "name:por_x_preferred":[
        "Luc"
    ],
    "name:ron_x_preferred":[
        "Luc"
    ],
    "name:slk_x_preferred":[
        "Luc"
    ],
    "name:spa_x_preferred":[
        "Luc"
    ],
    "name:swe_x_preferred":[
        "Luc"
    ],
    "name:ukr_x_preferred":[
        "\u041b\u044e\u043a"
    ],
    "wof:name":"Luc",
    "wof:placetype":"locality"
},
  "geometry": {"coordinates":[2.9753,45.06337],"type":"Point"}
}