{
  "type": "Feature",
  "properties": {
    "gn:admin1_code":"53",
    "gn:admin2_code":"56",
    "gn:admin3_code":"562",
    "gn:admin4_code":"56215",
    "gn:asciiname":"Hilvern",
    "gn:country_code":"FR",
    "gn:dem":135,
    "gn:feature_class":"P",
    "gn:feature_code":"PPL",
    "gn:name":"Hilvern",
    "gn:population":0,
    "gn:timezone":"Europe/Paris",
    "iso:country":"FR",
    "wof:name":"Hilvern",
    "wof:placetype":"locality"
},
  "geometry": {"coordinates":[-2.83527,48.11081],"type":"Point"}
}