{
  "type": "Feature",
  "properties": {
    "gn:admin1_code":"24",
    "gn:admin2_code":"41",
    "gn:admin3_code":"412",
    "gn:admin4_code":"41089",
    "gn:asciiname":"Les Bersinieres",
    "gn:country_code":"FR",
    "gn:dem":190,
    "gn:feature_class":"P",
    "gn:feature_code":"PPL",
    "gn:name":"Les Bersini\u00e8res",
    "gn:population":0,
    "gn:timezone":"Europe/Paris",
    "iso:country":"FR",
    "wof:name":"Les Bersinieres",
    "wof:placetype":"locality"
},
  "geometry": {"coordinates":[0.99272,48.06781],"type":"Point"}
}