{
  "type": "Feature",
  "properties": {
    "gn:admin1_code":"75",
    "gn:admin2_code":"17",
    "gn:admin3_code":"171",
    "gn:admin4_code":"17410",
    "gn:asciiname":"Saint-Thomas-de-Conac",
    "gn:cc2":"FR",
    "gn:country_code":"FR",
    "gn:dem":49,
    "gn:feature_class":"P",
    "gn:feature_code":"PPL",
    "gn:name":"Saint-Thomas-de-Conac",
    "gn:population":0,
    "gn:timezone":"Europe/Paris",
    "iso:country":"FR",
    "name:cat_x_preferred":[
        "Saint-Thomas-de-Conac"
    ],
    "name:ceb_x_preferred":[
        "Saint-Thomas-de-Conac"
    ],
    "name:deu_x_preferred":[
        "Saint-Thomas-de-Conac"
    ],
    "name:epo_x_preferred":[
        "Saint-Thomas-de-Conac"
    ],
    "name:eus_x_preferred":[
        "Saint-Thomas-de-Conac"
    ],
    "name:fra_x_preferred":[
        "Saint-Thomas-de-Conac"
    ],
    "name:hun_x_preferred":[
        "Saint-Thomas-de-Conac"
    ],
    "name:ita_x_preferred":[
        "Saint-Thomas-de-Conac"
    ],
    "name:lat_x_preferred":[
        "Saint-Thomas-de-Conac"
    ],
    "name:mlg_x_preferred":[
        "Saint-Thomas-de-Conac"
    ],
    "name:msa_x_preferred":[
        "Saint-Thomas-de-Conac"
    ],
    "name:nld_x_preferred":[
        "Saint-Thomas-de-Conac"
    ],
    "name:oci_x_preferred":[
        "Saint-Thomas-de-Conac"
    ],
    "name:pms_x_preferred":[
        "Saint-Thomas-de-Conac"
    ],
    "name:pol_x_preferred":[
        "Saint-Thomas-de-Conac"
    ],
    "name:por_x_preferred":[
        "Saint-Thomas-de-Conac"
    ],
    "name:rus_x_preferred":[
        "\u0421\u0435\u043d-\u0422\u043e\u043c\u0430-\u0434\u0435-\u041a\u043e\u043d\u0430\u043a"
    ],
    "name:slk_x_preferred":[
        "Saint-Thomas-de-Conac"
    ],
    "name:spa_x_preferred":[
        "Saint-Thomas-de-Conac"
    ],
    "name:swe_x_preferred":[
        "Saint-Thomas-de-Conac"
    ],
    "name:ukr_x_preferred":[
        "\u0421\u0435\u043d-\u0422\u043e\u043c\u0430-\u0434\u0435-\u041a\u043e\u043d\u0430\u043a"
    ],
    "name:und_x_variant":[
        "Saint-Thomas"
    ],
    "name:vie_x_preferred":[
        "Saint-Thomas-de-Conac"
    ],
    "name:vol_x_preferred":[
        "Saint-Thomas-de-Conac"
    ],
    "name:war_x_preferred":[
        "Saint-Thomas-de-Conac"
    ],
    "name:zho_x_preferred":[
        "\u5723\u6258\u9a6c\u5fb7\u79d1\u7eb3\u514b"
    ],
    "wof:name":"Saint-Thomas-de-Conac",
    "wof:placetype":"locality"
},
  "geometry": {"coordinates":[-0.68333,45.38333],"type":"Point"}
}