{
  "type": "Feature",
  "properties": {
    "gn:admin1_code":"28",
    "gn:admin2_code":"14",
    "gn:admin3_code":"141",
    "gn:admin4_code":"14377",
    "gn:asciiname":"Le Planet",
    "gn:country_code":"FR",
    "gn:dem":73,
    "gn:feature_class":"P",
    "gn:feature_code":"PPL",
    "gn:name":"Le Planet",
    "gn:population":0,
    "gn:timezone":"Europe/Paris",
    "iso:country":"FR",
    "wof:name":"Le Planet",
    "wof:placetype":"locality"
},
  "geometry": {"coordinates":[-0.71569,49.33847],"type":"Point"}
}