{
  "type": "Feature",
  "properties": {
    "gn:admin1_code":"84",
    "gn:admin2_code":"63",
    "gn:admin3_code":"631",
    "gn:admin4_code":"63371",
    "gn:asciiname":"Fontlobines",
    "gn:country_code":"FR",
    "gn:dem":954,
    "gn:feature_class":"P",
    "gn:feature_code":"PPL",
    "gn:name":"Fontlobines",
    "gn:population":0,
    "gn:timezone":"Europe/Paris",
    "iso:country":"FR",
    "wof:name":"Fontlobines",
    "wof:placetype":"locality"
},
  "geometry": {"coordinates":[3.80183,45.4488],"type":"Point"}
}