{
  "type": "Feature",
  "properties": {
    "iso:country":"FR",
    "name:eng_x_preferred":[
        "Les Bordes"
    ],
    "name:fra_x_preferred":[
        "Les Bordes"
    ],
    "wof:name":"Les Bordes",
    "wof:placetype":"neighbourhood"
},
  "geometry": {"coordinates":[2.57158428246065,48.79420534022268],"type":"Point"}
}