{
  "type": "Feature",
  "properties": {
    "gn:admin1_code":"76",
    "gn:admin2_code":"46",
    "gn:admin3_code":"461",
    "gn:admin4_code":"46040",
    "gn:asciiname":"Courbous",
    "gn:country_code":"FR",
    "gn:dem":290,
    "gn:feature_class":"P",
    "gn:feature_code":"PPL",
    "gn:name":"Courbous",
    "gn:population":0,
    "gn:timezone":"Europe/Paris",
    "iso:country":"FR",
    "wof:name":"Courbous",
    "wof:placetype":"locality"
},
  "geometry": {"coordinates":[1.65913,44.52494],"type":"Point"}
}