{
  "type": "Feature",
  "properties": {
    "gn:admin1_code":"93",
    "gn:admin2_code":"05",
    "gn:admin3_code":"052",
    "gn:admin4_code":"05132",
    "gn:asciiname":"Les Combes",
    "gn:country_code":"FR",
    "gn:dem":1254,
    "gn:feature_class":"P",
    "gn:feature_code":"PPL",
    "gn:name":"Les Combes",
    "gn:population":0,
    "gn:timezone":"Europe/Paris",
    "iso:country":"FR",
    "name:und_x_variant":[
        "Combes",
        "Les Combes"
    ],
    "wof:name":"Les Combes",
    "wof:placetype":"locality"
},
  "geometry": {"coordinates":[6.111,44.683],"type":"Point"}
}