{
  "type": "Feature",
  "properties": {
    "gn:admin1_code":"93",
    "gn:admin2_code":"05",
    "gn:admin3_code":"052",
    "gn:admin4_code":"05132",
    "gn:asciiname":"Les Combes",
    "gn:country_code":"FR",
    "gn:dem":1254,
    "gn:feature_class":"P",
    "gn:feature_code":"PPL",
    "gn:name":"Les Combes",
    "gn:population":0,
    "gn:timezone":"Europe/Paris",
    "iso:country":"FR",
    "name:cat_x_preferred":[
        "Les Combes"
    ],
    "name:ceb_x_preferred":[
        "Les Combes"
    ],
    "name:deu_x_preferred":[
        "Les Combes"
    ],
    "name:eus_x_preferred":[
        "Les Combes"
    ],
    "name:fas_x_preferred":[
        "\u0644\u0632 \u06a9\u0648\u0645\u0628\u0632"
    ],
    "name:fra_x_preferred":[
        "Les Combes"
    ],
    "name:hun_x_preferred":[
        "Les Combes"
    ],
    "name:ita_x_preferred":[
        "Les Combes"
    ],
    "name:lat_x_preferred":[
        "Les Combes"
    ],
    "name:msa_x_preferred":[
        "Les Combes"
    ],
    "name:nld_x_preferred":[
        "Les Combes"
    ],
    "name:oci_x_preferred":[
        "Les Combes"
    ],
    "name:pms_x_preferred":[
        "Les Combes"
    ],
    "name:pol_x_preferred":[
        "Les Combes"
    ],
    "name:por_x_preferred":[
        "Les Combes"
    ],
    "name:slk_x_preferred":[
        "Les Combes"
    ],
    "name:spa_x_preferred":[
        "Les Combes"
    ],
    "name:srp_x_preferred":[
        "\u041a\u043e\u043c\u0431"
    ],
    "name:swe_x_preferred":[
        "Les Combes"
    ],
    "name:ukr_x_preferred":[
        "\u041b\u0435-\u041a\u043e\u043c\u0431"
    ],
    "name:und_x_variant":[
        "Combes",
        "Les Combes"
    ],
    "name:uzb_x_preferred":[
        "Les Combes"
    ],
    "name:vie_x_preferred":[
        "Les Combes"
    ],
    "name:vol_x_preferred":[
        "Les Combes"
    ],
    "name:war_x_preferred":[
        "Les Combes"
    ],
    "name:zho_x_preferred":[
        "\u83b1\u5b54\u5e03"
    ],
    "wof:name":"Les Combes",
    "wof:placetype":"locality"
},
  "geometry": {"coordinates":[6.111,44.683],"type":"Point"}
}