{
  "type": "Feature",
  "properties": {
    "gn:admin1_code":"75",
    "gn:admin2_code":"47",
    "gn:admin3_code":"473",
    "gn:admin4_code":"47023",
    "gn:asciiname":"Les Bonnals",
    "gn:country_code":"FR",
    "gn:dem":198,
    "gn:feature_class":"P",
    "gn:feature_code":"PPL",
    "gn:name":"Les Bonnals",
    "gn:population":0,
    "gn:timezone":"Europe/Paris",
    "iso:country":"FR",
    "wof:name":"Les Bonnals",
    "wof:placetype":"locality"
},
  "geometry": {"coordinates":[0.66667,44.51667],"type":"Point"}
}