{
  "type": "Feature",
  "properties": {
    "iso:country":"FR",
    "name:eng_x_preferred":[
        "Saint-Helier"
    ],
    "name:fra_x_preferred":[
        "Saint-H\u00e9lier"
    ],
    "wof:name":"Saint-Helier",
    "wof:placetype":"neighbourhood"
},
  "geometry": {"coordinates":[-1.66904765401176,48.10680417788814],"type":"Point"}
}