{
  "type": "Feature",
  "properties": {
    "gn:admin1_code":"53",
    "gn:admin2_code":"22",
    "gn:admin3_code":"221",
    "gn:admin4_code":"22118",
    "gn:asciiname":"Tressaint",
    "gn:country_code":"FR",
    "gn:dem":56,
    "gn:feature_class":"P",
    "gn:feature_code":"PPL",
    "gn:name":"Tressaint",
    "gn:population":0,
    "gn:timezone":"Europe/Paris",
    "iso:country":"FR",
    "name:und_x_variant":[
        "Tressent",
        "Tressaint"
    ],
    "wof:name":"Tressaint",
    "wof:placetype":"locality"
},
  "geometry": {"coordinates":[-2.02408,48.43049],"type":"Point"}
}