{
  "type": "Feature",
  "properties": {
    "gn:admin1_code":"53",
    "gn:admin2_code":"22",
    "gn:admin3_code":"224",
    "gn:admin4_code":"22219",
    "gn:asciiname":"Vieux-Bourg",
    "gn:country_code":"FR",
    "gn:dem":154,
    "gn:feature_class":"P",
    "gn:feature_code":"PPL",
    "gn:name":"Vieux-Bourg",
    "gn:population":0,
    "gn:timezone":"Europe/Paris",
    "iso:country":"FR",
    "name:bre_x_preferred":[
        "Vieux-Bourg"
    ],
    "name:cat_x_preferred":[
        "Vieux-Bourg"
    ],
    "name:ceb_x_preferred":[
        "Vieux-Bourg"
    ],
    "name:deu_x_preferred":[
        "Vieux-Bourg"
    ],
    "name:eus_x_preferred":[
        "Vieux-Bourg"
    ],
    "name:fra_x_preferred":[
        "Vieux-Bourg"
    ],
    "name:hun_x_preferred":[
        "Vieux-Bourg"
    ],
    "name:hye_x_preferred":[
        "\u054e\u056b\u0565 \u0532\u0578\u0582\u0580"
    ],
    "name:ind_x_preferred":[
        "Vieux-Bourg"
    ],
    "name:ita_x_preferred":[
        "Vieux-Bourg"
    ],
    "name:kaz_x_preferred":[
        "\u0412\u044c\u0435-\u0411\u0443\u0440"
    ],
    "name:lat_x_preferred":[
        "Vieux-Bourg"
    ],
    "name:msa_x_preferred":[
        "Vieux-Bourg"
    ],
    "name:nld_x_preferred":[
        "Vieux-Bourg"
    ],
    "name:oci_x_preferred":[
        "Vieux-Bourg"
    ],
    "name:pms_x_preferred":[
        "Vieux-Bourg"
    ],
    "name:pol_x_preferred":[
        "Vieux-Bourg"
    ],
    "name:por_x_preferred":[
        "Vieux-Bourg"
    ],
    "name:ron_x_preferred":[
        "Vieux-Bourg"
    ],
    "name:rus_x_preferred":[
        "\u0412\u044c\u0451-\u0411\u0443\u0440"
    ],
    "name:slk_x_preferred":[
        "Vieux-Bourg"
    ],
    "name:spa_x_preferred":[
        "Vieux-Bourg"
    ],
    "name:swe_x_preferred":[
        "Vieux-Bourg"
    ],
    "name:ukr_x_preferred":[
        "\u0412'\u0454-\u0411\u0443\u0440"
    ],
    "name:uzb_x_preferred":[
        "Vieux-Bourg"
    ],
    "name:vie_x_preferred":[
        "Vieux-Bourg"
    ],
    "name:vol_x_preferred":[
        "Vieux-Bourg"
    ],
    "name:war_x_preferred":[
        "Vieux-Bourg"
    ],
    "name:zho_x_preferred":[
        "\u7ef4\u7ea6\u5821"
    ],
    "wof:name":"Vieux-Bourg",
    "wof:placetype":"locality"
},
  "geometry": {"coordinates":[-2.682,48.277],"type":"Point"}
}