{
  "type": "Feature",
  "properties": {
    "gn:admin1_code":"53",
    "gn:admin2_code":"22",
    "gn:admin3_code":"224",
    "gn:admin4_code":"22219",
    "gn:asciiname":"Vieux-Bourg",
    "gn:country_code":"FR",
    "gn:dem":154,
    "gn:feature_class":"P",
    "gn:feature_code":"PPL",
    "gn:name":"Vieux-Bourg",
    "gn:population":0,
    "gn:timezone":"Europe/Paris",
    "iso:country":"FR",
    "wof:name":"Vieux-Bourg",
    "wof:placetype":"locality"
},
  "geometry": {"coordinates":[-2.682,48.277],"type":"Point"}
}