{
  "type": "Feature",
  "properties": {
    "gn:admin1_code":"53",
    "gn:admin2_code":"22",
    "gn:admin3_code":"224",
    "gn:admin4_code":"22236",
    "gn:asciiname":"Kervouriou",
    "gn:country_code":"FR",
    "gn:dem":70,
    "gn:feature_class":"P",
    "gn:feature_code":"PPL",
    "gn:name":"Kervouriou",
    "gn:population":0,
    "gn:timezone":"Europe/Paris",
    "iso:country":"FR",
    "wof:name":"Kervouriou",
    "wof:placetype":"locality"
},
  "geometry": {"coordinates":[-2.968,48.66211],"type":"Point"}
}