{
  "type": "Feature",
  "properties": {
    "gn:admin1_code":"84",
    "gn:admin2_code":"03",
    "gn:admin3_code":"032",
    "gn:admin4_code":"03237",
    "gn:asciiname":"Saint-Cyprien",
    "gn:country_code":"FR",
    "gn:dem":272,
    "gn:feature_class":"P",
    "gn:feature_code":"PPL",
    "gn:name":"Saint-Cyprien",
    "gn:population":0,
    "gn:timezone":"Europe/Paris",
    "iso:country":"FR",
    "name:ceb_x_preferred":[
        "Saint-Cyprien"
    ],
    "name:deu_x_preferred":[
        "Saint-Cyprien"
    ],
    "name:epo_x_preferred":[
        "Saint-Cyprien"
    ],
    "name:fas_x_preferred":[
        "\u0633\u0646-\u0633\u06cc\u067e\u0631\u06cc\u0627\u0646"
    ],
    "name:fin_x_preferred":[
        "Saint-Cyprien"
    ],
    "name:fra_x_preferred":[
        "Saint-Cyprien"
    ],
    "name:ita_x_preferred":[
        "Saint-Cyprien"
    ],
    "name:jpn_x_preferred":[
        "\u30b5\u30f3\uff1d\u30b7\u30d7\u30ea\u30a2\u30f3"
    ],
    "name:nds_x_preferred":[
        "Saint-Cyprien"
    ],
    "name:nld_x_preferred":[
        "Saint-Cyprien"
    ],
    "name:pms_x_preferred":[
        "Saint-Cyprien"
    ],
    "name:pol_x_preferred":[
        "Saint-Cyprien"
    ],
    "name:por_x_preferred":[
        "Saint-Cyprien"
    ],
    "name:rus_x_preferred":[
        "\u0421\u0435\u043d-\u0421\u0438\u043f\u0440\u0438\u0435\u043d"
    ],
    "name:slk_x_preferred":[
        "Saint-Cyprien"
    ],
    "name:spa_x_preferred":[
        "Saint-Cyprien"
    ],
    "name:swe_x_preferred":[
        "Saint-Cyprien"
    ],
    "name:ukr_x_preferred":[
        "\u0421\u0435\u043d-\u0421\u0456\u043f\u0440\u0456\u044f\u043d"
    ],
    "wof:name":"Saint-Cyprien",
    "wof:placetype":"locality"
},
  "geometry": {"coordinates":[3.22904,46.17742],"type":"Point"}
}