{
  "type": "Feature",
  "properties": {
    "gn:admin1_code":"53",
    "gn:admin2_code":"29",
    "gn:admin3_code":"293",
    "gn:admin4_code":"29187",
    "gn:asciiname":"Kersaos",
    "gn:country_code":"FR",
    "gn:dem":98,
    "gn:feature_class":"P",
    "gn:feature_code":"PPL",
    "gn:name":"Kersaos",
    "gn:population":0,
    "gn:timezone":"Europe/Paris",
    "iso:country":"FR",
    "wof:name":"Kersaos",
    "wof:placetype":"locality"
},
  "geometry": {"coordinates":[-4.15766,48.55589000000001],"type":"Point"}
}