{
  "type": "Feature",
  "properties": {
    "iso:country":"FR",
    "name:eng_x_preferred":[
        "Avenir"
    ],
    "name:fra_x_preferred":[
        "Avenir"
    ],
    "wof:name":"Avenir",
    "wof:placetype":"neighbourhood"
},
  "geometry": {"coordinates":[2.55386193430413,48.86998421594642],"type":"Point"}
}