{
  "type": "Feature",
  "properties": {
    "gn:admin1_code":"53",
    "gn:admin2_code":"56",
    "gn:admin3_code":"563",
    "gn:admin4_code":"56211",
    "gn:asciiname":"Bellee",
    "gn:country_code":"FR",
    "gn:dem":9,
    "gn:feature_class":"P",
    "gn:feature_code":"PPL",
    "gn:name":"Bell\u00e9e",
    "gn:population":0,
    "gn:timezone":"Europe/Paris",
    "iso:country":"FR",
    "wof:name":"Bellee",
    "wof:placetype":"locality"
},
  "geometry": {"coordinates":[-2.30914,47.75029],"type":"Point"}
}