{
  "type": "Feature",
  "properties": {
    "gn:admin1_code":"53",
    "gn:admin2_code":"29",
    "gn:admin3_code":"294",
    "gn:admin4_code":"29230",
    "gn:asciiname":"Caros-Combout",
    "gn:country_code":"FR",
    "gn:dem":141,
    "gn:feature_class":"P",
    "gn:feature_code":"PPL",
    "gn:name":"Caros-Combout",
    "gn:population":0,
    "gn:timezone":"Europe/Paris",
    "iso:country":"FR",
    "wof:name":"Caros-Combout",
    "wof:placetype":"locality"
},
  "geometry": {"coordinates":[-3.50249,47.96586],"type":"Point"}
}