{
  "type": "Feature",
  "properties": {
    "gn:admin1_code":"24",
    "gn:admin2_code":"36",
    "gn:admin3_code":"361",
    "gn:admin4_code":"36196",
    "gn:asciiname":"Abloux",
    "gn:country_code":"FR",
    "gn:dem":187,
    "gn:feature_class":"P",
    "gn:feature_code":"PPL",
    "gn:name":"Abloux",
    "gn:population":0,
    "gn:timezone":"Europe/Paris",
    "iso:country":"FR",
    "wof:name":"Abloux",
    "wof:placetype":"locality"
},
  "geometry": {"coordinates":[1.44486,46.49477],"type":"Point"}
}