{
  "type": "Feature",
  "properties": {
    "gn:admin1_code":"27",
    "gn:admin2_code":"58",
    "gn:admin3_code":"582",
    "gn:admin4_code":"58093.0",
    "gn:asciiname":"Mhers",
    "gn:country_code":"FR",
    "gn:dem":193,
    "gn:feature_class":"P",
    "gn:feature_code":"PPL",
    "gn:name":"Mhers",
    "gn:population":0,
    "gn:timezone":"Europe/Paris",
    "iso:country":"FR",
    "wof:name":"Mhers",
    "wof:placetype":"locality"
},
  "geometry": {"coordinates":[3.46191,47.34869000000001],"type":"Point"}
}