{
  "type": "Feature",
  "properties": {
    "gn:admin1_code":"84",
    "gn:admin2_code":"43",
    "gn:admin3_code":"432",
    "gn:admin4_code":"43026",
    "gn:asciiname":"Ligonzac",
    "gn:country_code":"FR",
    "gn:dem":987,
    "gn:feature_class":"P",
    "gn:feature_code":"PPL",
    "gn:name":"Ligonzac",
    "gn:population":0,
    "gn:timezone":"Europe/Paris",
    "iso:country":"FR",
    "wof:name":"Ligonzac",
    "wof:placetype":"locality"
},
  "geometry": {"coordinates":[3.80099,45.23611],"type":"Point"}
}