{
  "type": "Feature",
  "properties": {
    "gn:admin1_code":"84",
    "gn:admin2_code":"07",
    "gn:admin3_code":"073",
    "gn:admin4_code":"07095",
    "gn:asciiname":"Fenier",
    "gn:country_code":"FR",
    "gn:dem":671,
    "gn:feature_class":"P",
    "gn:feature_code":"PPL",
    "gn:name":"Fenier",
    "gn:population":0,
    "gn:timezone":"Europe/Paris",
    "iso:country":"FR",
    "wof:name":"Fenier",
    "wof:placetype":"locality"
},
  "geometry": {"coordinates":[4.69477,44.97251],"type":"Point"}
}