{
  "type": "Feature",
  "properties": {
    "gn:admin1_code":"76",
    "gn:admin2_code":"12",
    "gn:admin3_code":"123",
    "gn:admin4_code":"12021",
    "gn:asciiname":"La Bastide-l'Eveque",
    "gn:country_code":"FR",
    "gn:dem":467,
    "gn:feature_class":"P",
    "gn:feature_code":"PPL",
    "gn:name":"La Bastide-l\u2019\u00c9v\u00eaque",
    "gn:population":0,
    "gn:timezone":"Europe/Paris",
    "iso:country":"FR",
    "name:und_x_variant":[
        "La Bastide",
        "La Bastide-l\u2019\u00c9v\u00eaque"
    ],
    "wof:name":"La Bastide-l'Eveque",
    "wof:placetype":"locality"
},
  "geometry": {"coordinates":[2.1362,44.34],"type":"Point"}
}