{
  "type": "Feature",
  "properties": {
    "gn:admin1_code":"27",
    "gn:admin2_code":"58",
    "gn:admin3_code":"583",
    "gn:admin4_code":"58196",
    "gn:asciiname":"Mauboux",
    "gn:country_code":"FR",
    "gn:dem":321,
    "gn:feature_class":"P",
    "gn:feature_code":"PPL",
    "gn:name":"Mauboux",
    "gn:population":0,
    "gn:timezone":"Europe/Paris",
    "iso:country":"FR",
    "wof:name":"Mauboux",
    "wof:placetype":"locality"
},
  "geometry": {"coordinates":[3.36248,47.08552],"type":"Point"}
}