{
  "type": "Feature",
  "properties": {
    "gn:admin1_code":"75",
    "gn:admin2_code":"86",
    "gn:admin3_code":"863",
    "gn:admin4_code":"86065",
    "gn:asciiname":"Baptresse",
    "gn:country_code":"FR",
    "gn:dem":102,
    "gn:feature_class":"P",
    "gn:feature_code":"PPL",
    "gn:name":"Baptresse",
    "gn:population":0,
    "gn:timezone":"Europe/Paris",
    "iso:country":"FR",
    "wof:name":"Baptresse",
    "wof:placetype":"locality"
},
  "geometry": {"coordinates":[0.28967,46.42551],"type":"Point"}
}