{
  "type": "Feature",
  "properties": {
    "gn:admin1_code":"76",
    "gn:admin2_code":"82",
    "gn:admin3_code":"822",
    "gn:admin4_code":"82188",
    "gn:asciiname":"Varennes",
    "gn:country_code":"FR",
    "gn:dem":200,
    "gn:feature_class":"P",
    "gn:feature_code":"PPL",
    "gn:name":"Varennes",
    "gn:population":483,
    "gn:timezone":"Europe/Paris",
    "iso:country":"FR",
    "wof:name":"Varennes",
    "wof:placetype":"locality",
    "wof:population":483
},
  "geometry": {"coordinates":[1.49758,43.90129],"type":"Point"}
}