{
  "type": "Feature",
  "properties": {
    "frgov:code_epci":"200066652",
    "frgov:insee_arr":"2",
    "frgov:insee_com":"82188",
    "frgov:insee_dep":"82",
    "frgov:insee_reg":"76",
    "frgov:nom_com":"Varennes",
    "frgov:nom_com_m":"VARENNES",
    "frgov:nom_dep":"TARN-ET-GARONNE",
    "frgov:nom_reg":"OCCITANIE",
    "frgov:statut":"Commune simple",
    "gn:admin1_code":"76",
    "gn:admin2_code":"82",
    "gn:admin3_code":"822",
    "gn:admin4_code":"82188",
    "gn:asciiname":"Varennes",
    "gn:country_code":"FR",
    "gn:dem":200,
    "gn:feature_class":"P",
    "gn:feature_code":"PPL",
    "gn:name":"Varennes",
    "gn:population":483,
    "gn:timezone":"Europe/Paris",
    "iso:country":"FR",
    "name:fra_x_preferred":[
        "Varennes"
    ],
    "qs:a0":"France",
    "qs:a1":"TARN-ET-GARONNE",
    "qs:a1_lc":"82",
    "qs:a1r":"MIDI-PYRENEES",
    "qs:a1r_lc":"73",
    "qs:a2_lc":"24",
    "qs:a2r_lc":"2",
    "qs:adm0":"France",
    "qs:adm0_a3":"FRA",
    "qs:la":"VARENNES",
    "qs:la_lc":"82188",
    "qs:level":"localadmin",
    "qs:type":"Commune simple",
    "wof:coterminous":[
        404354957
    ],
    "wof:name":"Varennes",
    "wof:placetype":"locality",
    "wof:placetype_local":"Commune simple",
    "wof:population":483
},
  "geometry": {"coordinates":[1.49758,43.90129],"type":"Point"}
}