{
  "type": "Feature",
  "properties": {
    "gn:admin1_code":"11",
    "gn:admin2_code":"91",
    "gn:admin3_code":"912",
    "gn:admin4_code":"91201",
    "gn:asciiname":"La Villa-Draveil",
    "gn:country_code":"FR",
    "gn:dem":33,
    "gn:feature_class":"P",
    "gn:feature_code":"PPL",
    "gn:name":"La Villa-Draveil",
    "gn:population":0,
    "gn:timezone":"Europe/Paris",
    "iso:country":"FR",
    "wof:name":"La Villa-Draveil",
    "wof:placetype":"locality"
},
  "geometry": {"coordinates":[2.39663,48.68634],"type":"Point"}
}