{
  "type": "Feature",
  "properties": {
    "iso:country":"FR",
    "wof:name":"Saint-Charles",
    "wof:placetype":"neighbourhood"
},
  "geometry": {"coordinates":[5.38744670992224,43.30474734216232],"type":"Point"}
}