{
  "type": "Feature",
  "properties": {
    "iso:country":"FR",
    "name:eng_x_preferred":[
        "Le Plateau"
    ],
    "name:fra_x_preferred":[
        "Le Plateau"
    ],
    "wof:name":"Le Plateau",
    "wof:placetype":"neighbourhood"
},
  "geometry": {"coordinates":[2.43092371631961,48.87594947002094],"type":"Point"}
}