{
  "type": "Feature",
  "properties": {
    "gn:admin1_code":"44",
    "gn:admin2_code":"10",
    "gn:admin3_code":"101",
    "gn:admin4_code":"10008",
    "gn:asciiname":"Le Chanet",
    "gn:country_code":"FR",
    "gn:dem":223,
    "gn:feature_class":"P",
    "gn:feature_code":"PPL",
    "gn:name":"Le Ch\u00e2net",
    "gn:population":0,
    "gn:timezone":"Europe/Paris",
    "iso:country":"FR",
    "wof:name":"Le Chanet",
    "wof:placetype":"locality"
},
  "geometry": {"coordinates":[4.57542,48.25832],"type":"Point"}
}