{
  "type": "Feature",
  "properties": {
    "gn:admin1_code":"32",
    "gn:admin2_code":"80",
    "gn:admin3_code":"801",
    "gn:admin4_code":"80825",
    "gn:asciiname":"Wiry-au-Val",
    "gn:country_code":"FR",
    "gn:dem":58,
    "gn:feature_class":"P",
    "gn:feature_code":"PPL",
    "gn:name":"Wiry-au-Val",
    "gn:population":0,
    "gn:timezone":"Europe/Paris",
    "iso:country":"FR",
    "wof:name":"Wiry-au-Val",
    "wof:placetype":"locality"
},
  "geometry": {"coordinates":[1.84018,49.95831],"type":"Point"}
}