{
  "type": "Feature",
  "properties": {
    "gn:admin1_code":"28",
    "gn:admin2_code":"61",
    "gn:admin3_code":"613",
    "gn:admin4_code":"61242",
    "gn:asciiname":"La Douvellerie",
    "gn:country_code":"FR",
    "gn:dem":204,
    "gn:feature_class":"P",
    "gn:feature_code":"PPL",
    "gn:name":"La Douvellerie",
    "gn:population":0,
    "gn:timezone":"Europe/Paris",
    "iso:country":"FR",
    "wof:name":"La Douvellerie",
    "wof:placetype":"locality"
},
  "geometry": {"coordinates":[0.81566,48.51369],"type":"Point"}
}