{
  "type": "Feature",
  "properties": {
    "gn:admin1_code":"84",
    "gn:admin2_code":"63",
    "gn:admin3_code":"631",
    "gn:admin4_code":"63230",
    "gn:asciiname":"Le Mayet",
    "gn:country_code":"FR",
    "gn:dem":809,
    "gn:feature_class":"P",
    "gn:feature_code":"PPL",
    "gn:name":"Le Mayet",
    "gn:population":0,
    "gn:timezone":"Europe/Paris",
    "iso:country":"FR",
    "wof:name":"Le Mayet",
    "wof:placetype":"locality"
},
  "geometry": {"coordinates":[3.68333,45.56667],"type":"Point"}
}