{
  "type": "Feature",
  "properties": {
    "gn:admin1_code":"76",
    "gn:admin2_code":"12",
    "gn:admin3_code":"122",
    "gn:admin4_code":"12076",
    "gn:asciiname":"Prayssac",
    "gn:country_code":"FR",
    "gn:dem":504,
    "gn:feature_class":"P",
    "gn:feature_code":"PPL",
    "gn:name":"Prayssac",
    "gn:population":0,
    "gn:timezone":"Europe/Paris",
    "iso:country":"FR",
    "name:cat_x_preferred":[
        "Praissac"
    ],
    "name:ceb_x_preferred":[
        "Prayssac"
    ],
    "name:deu_x_preferred":[
        "Prayssac"
    ],
    "name:eus_x_preferred":[
        "Prayssac"
    ],
    "name:fra_x_preferred":[
        "Prayssac"
    ],
    "name:hun_x_preferred":[
        "Prayssac"
    ],
    "name:ita_x_preferred":[
        "Prayssac"
    ],
    "name:lat_x_preferred":[
        "Prayssac"
    ],
    "name:mlg_x_preferred":[
        "Prayssac"
    ],
    "name:msa_x_preferred":[
        "Prayssac"
    ],
    "name:nld_x_preferred":[
        "Prayssac"
    ],
    "name:oci_x_preferred":[
        "Praissac"
    ],
    "name:pol_x_preferred":[
        "Prayssac"
    ],
    "name:ron_x_preferred":[
        "Prayssac"
    ],
    "name:slk_x_preferred":[
        "Prayssac"
    ],
    "name:spa_x_preferred":[
        "Prayssac"
    ],
    "name:swe_x_preferred":[
        "Prayssac"
    ],
    "name:ukr_x_preferred":[
        "\u041f\u0440\u0435\u0441\u0441\u0430\u043a"
    ],
    "name:vie_x_preferred":[
        "Prayssac"
    ],
    "name:vol_x_preferred":[
        "Prayssac"
    ],
    "name:war_x_preferred":[
        "Prayssac"
    ],
    "name:zho_x_preferred":[
        "\u666e\u8d56\u8428\u514b"
    ],
    "wof:name":"Prayssac",
    "wof:placetype":"locality"
},
  "geometry": {"coordinates":[2.32013,44.58148],"type":"Point"}
}