{
  "type": "Feature",
  "properties": {
    "gn:admin1_code":"44",
    "gn:admin2_code":"10",
    "gn:admin3_code":"102",
    "gn:admin4_code":"10367",
    "gn:asciiname":"Liours",
    "gn:country_code":"FR",
    "gn:dem":62,
    "gn:feature_class":"P",
    "gn:feature_code":"PPL",
    "gn:name":"Liours",
    "gn:population":0,
    "gn:timezone":"Europe/Paris",
    "iso:country":"FR",
    "wof:name":"Liours",
    "wof:placetype":"locality"
},
  "geometry": {"coordinates":[3.52088,48.53124],"type":"Point"}
}