{
  "type": "Feature",
  "properties": {
    "gn:admin1_code":"28",
    "gn:admin2_code":"76",
    "gn:admin3_code":"761",
    "gn:admin4_code":"76344",
    "gn:asciiname":"Sous-les-Quesnes",
    "gn:country_code":"FR",
    "gn:dem":180,
    "gn:feature_class":"P",
    "gn:feature_code":"PPL",
    "gn:name":"Sous-les-Quesnes",
    "gn:population":0,
    "gn:timezone":"Europe/Paris",
    "iso:country":"FR",
    "wof:name":"Sous-les-Quesnes",
    "wof:placetype":"locality"
},
  "geometry": {"coordinates":[1.68214,49.73012],"type":"Point"}
}