{
  "type": "Feature",
  "properties": {
    "gn:admin1_code":"27",
    "gn:admin2_code":"21",
    "gn:admin3_code":"213",
    "gn:admin4_code":"21069",
    "gn:asciiname":"Verchisy",
    "gn:country_code":"FR",
    "gn:dem":336,
    "gn:feature_class":"P",
    "gn:feature_code":"PPL",
    "gn:name":"Verchisy",
    "gn:population":0,
    "gn:timezone":"Europe/Paris",
    "iso:country":"FR",
    "wof:name":"Verchisy",
    "wof:placetype":"locality"
},
  "geometry": {"coordinates":[4.46595,47.35893],"type":"Point"}
}