{
  "type": "Feature",
  "properties": {
    "iso:country":"FR",
    "name:eng_x_preferred":[
        "Victor Hugo"
    ],
    "name:fra_x_preferred":[
        "Victor Hugo"
    ],
    "wof:name":"Victor Hugo",
    "wof:placetype":"neighbourhood"
},
  "geometry": {"coordinates":[2.35400450316361,48.81474608638155],"type":"Point"}
}