{
  "type": "Feature",
  "properties": {
    "gn:admin1_code":"93",
    "gn:admin2_code":"05",
    "gn:admin3_code":"051",
    "gn:admin4_code":"05161",
    "gn:asciiname":"Frejus",
    "gn:country_code":"FR",
    "gn:dem":1918,
    "gn:feature_class":"P",
    "gn:feature_code":"PPL",
    "gn:name":"Fr\u00e9jus",
    "gn:population":0,
    "gn:timezone":"Europe/Paris",
    "iso:country":"FR",
    "wof:name":"Frejus",
    "wof:placetype":"locality"
},
  "geometry": {"coordinates":[6.53716,44.93065],"type":"Point"}
}