{
  "type": "Feature",
  "properties": {
    "gn:admin1_code":"27",
    "gn:admin2_code":"21",
    "gn:admin3_code":"213",
    "gn:admin4_code":"21280",
    "gn:asciiname":"Pluvier",
    "gn:country_code":"FR",
    "gn:dem":386,
    "gn:feature_class":"P",
    "gn:feature_code":"PPL",
    "gn:name":"Pluvier",
    "gn:population":0,
    "gn:timezone":"Europe/Paris",
    "iso:country":"FR",
    "wof:name":"Pluvier",
    "wof:placetype":"locality"
},
  "geometry": {"coordinates":[4.38417,47.35714],"type":"Point"}
}