{
  "type": "Feature",
  "properties": {
    "iso:country":"FR",
    "name:eng_x_preferred":[
        "Pasteur-Magenta"
    ],
    "name:fra_x_preferred":[
        "Pasteur-Magenta"
    ],
    "wof:name":"Pasteur-Magenta",
    "wof:placetype":"neighbourhood"
},
  "geometry": {"coordinates":[2.20599010091105,48.8422097892437],"type":"Point"}
}