{
  "type": "Feature",
  "properties": {
    "gn:admin1_code":"27",
    "gn:admin2_code":"58",
    "gn:admin3_code":"583",
    "gn:admin4_code":"58306",
    "gn:asciiname":"Faye",
    "gn:country_code":"FR",
    "gn:dem":224,
    "gn:feature_class":"P",
    "gn:feature_code":"PPL",
    "gn:name":"Faye",
    "gn:population":0,
    "gn:timezone":"Europe/Paris",
    "iso:country":"FR",
    "name:ceb_x_preferred":[
        "Faye"
    ],
    "name:dan_x_preferred":[
        "Faye"
    ],
    "name:deu_x_preferred":[
        "Faye"
    ],
    "name:fra_x_preferred":[
        "Faye"
    ],
    "name:ita_x_preferred":[
        "Faye"
    ],
    "name:lit_x_preferred":[
        "Faye"
    ],
    "name:pol_x_preferred":[
        "Faye"
    ],
    "name:por_x_preferred":[
        "Faye"
    ],
    "name:rus_x_preferred":[
        "\u0424\u0430\u0439"
    ],
    "name:scn_x_preferred":[
        "Faye"
    ],
    "name:ukr_x_preferred":[
        "\u0424\u0430\u0439"
    ],
    "wof:name":"Faye",
    "wof:placetype":"locality"
},
  "geometry": {"coordinates":[3.59392,46.84023],"type":"Point"}
}