{
  "type": "Feature",
  "properties": {
    "gn:admin1_code":"84",
    "gn:admin2_code":"63",
    "gn:admin3_code":"632",
    "gn:admin4_code":"63045",
    "gn:asciiname":"Chez Bariou",
    "gn:country_code":"FR",
    "gn:dem":423,
    "gn:feature_class":"P",
    "gn:feature_code":"PPL",
    "gn:name":"Chez Bariou",
    "gn:population":0,
    "gn:timezone":"Europe/Paris",
    "iso:country":"FR",
    "name:und_x_variant":[
        "Chez Barioux",
        "Chez Bariou"
    ],
    "wof:name":"Chez Bariou",
    "wof:placetype":"locality"
},
  "geometry": {"coordinates":[3.46148,45.78868],"type":"Point"}
}