{
  "type": "Feature",
  "properties": {
    "iso:country":"FR",
    "name:eng_x_preferred":[
        "Champy"
    ],
    "name:fra_x_preferred":[
        "Champy"
    ],
    "wof:name":"Champy",
    "wof:placetype":"neighbourhood"
},
  "geometry": {"coordinates":[2.57361015514747,48.84210086895637],"type":"Point"}
}