{
  "type": "Feature",
  "properties": {
    "gn:admin1_code":"53",
    "gn:admin2_code":"22",
    "gn:admin3_code":"223",
    "gn:admin4_code":"22113",
    "gn:asciiname":"Saint-Nicodeme",
    "gn:country_code":"FR",
    "gn:dem":64,
    "gn:feature_class":"P",
    "gn:feature_code":"PPL",
    "gn:name":"Saint-Nicod\u00e8me",
    "gn:population":0,
    "gn:timezone":"Europe/Paris",
    "iso:country":"FR",
    "wof:name":"Saint-Nicodeme",
    "wof:placetype":"locality"
},
  "geometry": {"coordinates":[-3.48333,48.73333],"type":"Point"}
}