{
  "type": "Feature",
  "properties": {
    "gn:admin1_code":"84",
    "gn:admin2_code":"15",
    "gn:admin3_code":"152",
    "gn:admin4_code":"15037",
    "gn:asciiname":"Moulergues",
    "gn:country_code":"FR",
    "gn:dem":594,
    "gn:feature_class":"P",
    "gn:feature_code":"PPL",
    "gn:name":"Moulergues",
    "gn:population":0,
    "gn:timezone":"Europe/Paris",
    "iso:country":"FR",
    "wof:name":"Moulergues",
    "wof:placetype":"locality"
},
  "geometry": {"coordinates":[2.4292,45.38505],"type":"Point"}
}