{
  "type": "Feature",
  "properties": {
    "gn:admin1_code":"84",
    "gn:admin2_code":"69",
    "gn:admin3_code":"691",
    "gn:admin4_code":"69132",
    "gn:asciiname":"Baronnier",
    "gn:country_code":"FR",
    "gn:dem":484,
    "gn:feature_class":"P",
    "gn:feature_code":"PPL",
    "gn:name":"Baronnier",
    "gn:population":0,
    "gn:timezone":"Europe/Paris",
    "iso:country":"FR",
    "wof:name":"Baronnier",
    "wof:placetype":"locality"
},
  "geometry": {"coordinates":[4.40608,45.68272],"type":"Point"}
}