{
  "type": "Feature",
  "properties": {
    "gn:admin1_code":"84",
    "gn:admin2_code":"15",
    "gn:admin3_code":"153",
    "gn:admin4_code":"15001",
    "gn:asciiname":"Chastre",
    "gn:country_code":"FR",
    "gn:dem":1122,
    "gn:feature_class":"P",
    "gn:feature_code":"PPL",
    "gn:name":"Chastre",
    "gn:population":0,
    "gn:timezone":"Europe/Paris",
    "iso:country":"FR",
    "wof:name":"Chastre",
    "wof:placetype":"locality"
},
  "geometry": {"coordinates":[3.00364,45.24471],"type":"Point"}
}