{
  "type": "Feature",
  "properties": {
    "gn:admin1_code":"84",
    "gn:admin2_code":"15",
    "gn:admin3_code":"153",
    "gn:admin4_code":"15001",
    "gn:asciiname":"Chastre",
    "gn:country_code":"FR",
    "gn:dem":1122,
    "gn:feature_class":"P",
    "gn:feature_code":"PPL",
    "gn:name":"Chastre",
    "gn:population":0,
    "gn:timezone":"Europe/Paris",
    "iso:country":"FR",
    "name:bar_x_preferred":[
        "Chastre"
    ],
    "name:bre_x_preferred":[
        "Chastre"
    ],
    "name:bul_x_preferred":[
        "\u0428\u0430\u0441\u0442\u044a\u0440"
    ],
    "name:cat_x_preferred":[
        "Chastre"
    ],
    "name:ceb_x_preferred":[
        "Chastre"
    ],
    "name:deu_x_preferred":[
        "Chastre"
    ],
    "name:epo_x_preferred":[
        "Chastre"
    ],
    "name:eus_x_preferred":[
        "Chastre"
    ],
    "name:fas_x_preferred":[
        "\u0634\u0633\u062a\u0631"
    ],
    "name:fin_x_preferred":[
        "Chastre"
    ],
    "name:fra_x_preferred":[
        "Chastre"
    ],
    "name:ita_x_preferred":[
        "Chastre"
    ],
    "name:nld_x_preferred":[
        "Chastre"
    ],
    "name:nor_x_preferred":[
        "Chastre"
    ],
    "name:oci_x_preferred":[
        "Chastre"
    ],
    "name:pol_x_preferred":[
        "Chastre"
    ],
    "name:por_x_preferred":[
        "Chastre"
    ],
    "name:ron_x_preferred":[
        "Chastre"
    ],
    "name:rus_x_preferred":[
        "\u0428\u0430\u0441\u0442\u0440"
    ],
    "name:slk_x_preferred":[
        "Chastre"
    ],
    "name:spa_x_preferred":[
        "Chastre"
    ],
    "name:swe_x_preferred":[
        "Chastre"
    ],
    "name:vie_x_preferred":[
        "Chastre"
    ],
    "name:vol_x_preferred":[
        "Chastre"
    ],
    "name:war_x_preferred":[
        "Chastre"
    ],
    "name:wln_x_preferred":[
        "Tch\u00e5sse"
    ],
    "name:zho_x_preferred":[
        "\u6c99\u65af\u7279\u5c14"
    ],
    "wof:name":"Chastre",
    "wof:placetype":"locality"
},
  "geometry": {"coordinates":[3.00364,45.24471],"type":"Point"}
}