{
  "type": "Feature",
  "properties": {
    "gn:admin1_code":"24",
    "gn:admin2_code":"45",
    "gn:admin3_code":"453",
    "gn:admin4_code":"45015.0",
    "gn:asciiname":"Fromonvilliers",
    "gn:country_code":"FR",
    "gn:dem":132,
    "gn:feature_class":"P",
    "gn:feature_code":"PPL",
    "gn:name":"Fromonvilliers",
    "gn:population":0,
    "gn:timezone":"Europe/Paris",
    "iso:country":"FR",
    "wof:name":"Fromonvilliers",
    "wof:placetype":"locality"
},
  "geometry": {"coordinates":[2.0591,48.27365],"type":"Point"}
}