{
  "type": "Feature",
  "properties": {
    "gn:admin1_code":"84",
    "gn:admin2_code":"42",
    "gn:admin3_code":"422",
    "gn:admin4_code":"42141",
    "gn:asciiname":"Mars",
    "gn:country_code":"FR",
    "gn:dem":397,
    "gn:feature_class":"P",
    "gn:feature_code":"PPL",
    "gn:name":"Mars",
    "gn:population":571,
    "gn:timezone":"Europe/Paris",
    "iso:country":"FR",
    "wof:name":"Mars",
    "wof:placetype":"locality",
    "wof:population":571
},
  "geometry": {"coordinates":[4.2468,46.1545],"type":"Point"}
}