{
  "type": "Feature",
  "properties": {
    "gn:admin1_code":"75",
    "gn:admin2_code":"23",
    "gn:admin3_code":"231",
    "gn:admin4_code":"23045",
    "gn:asciiname":"Lut Petit",
    "gn:country_code":"FR",
    "gn:dem":442,
    "gn:feature_class":"P",
    "gn:feature_code":"PPL",
    "gn:name":"Lut Petit",
    "gn:population":0,
    "gn:timezone":"Europe/Paris",
    "iso:country":"FR",
    "wof:name":"Lut Petit",
    "wof:placetype":"locality"
},
  "geometry": {"coordinates":[2.43559,46.23185],"type":"Point"}
}