{
  "type": "Feature",
  "properties": {
    "gn:admin1_code":"75",
    "gn:admin2_code":"19",
    "gn:admin3_code":"193",
    "gn:admin4_code":"19256",
    "gn:asciiname":"Vernejoux",
    "gn:country_code":"FR",
    "gn:dem":568,
    "gn:feature_class":"P",
    "gn:feature_code":"PPL",
    "gn:name":"Vernejoux",
    "gn:population":0,
    "gn:timezone":"Europe/Paris",
    "iso:country":"FR",
    "wof:name":"Vernejoux",
    "wof:placetype":"locality"
},
  "geometry": {"coordinates":[2.35846,45.37241],"type":"Point"}
}