{
  "type": "Feature",
  "properties": {
    "gn:admin1_code":"27",
    "gn:admin2_code":"71",
    "gn:admin3_code":"714",
    "gn:admin4_code":"71263",
    "gn:asciiname":"Chateaurenaud",
    "gn:country_code":"FR",
    "gn:dem":188,
    "gn:feature_class":"P",
    "gn:feature_code":"PPL",
    "gn:name":"Ch\u00e2teaurenaud",
    "gn:population":0,
    "gn:timezone":"Europe/Paris",
    "iso:country":"FR",
    "name:und_x_variant":[
        "Ch\u00e2teaurenaud"
    ],
    "wof:name":"Chateaurenaud",
    "wof:placetype":"locality"
},
  "geometry": {"coordinates":[5.23155,46.63019],"type":"Point"}
}