{
  "type": "Feature",
  "properties": {
    "gn:admin1_code":"27",
    "gn:admin2_code":"58",
    "gn:admin3_code":"584",
    "gn:admin4_code":"58231",
    "gn:asciiname":"Frasnay",
    "gn:country_code":"FR",
    "gn:dem":245,
    "gn:feature_class":"P",
    "gn:feature_code":"PPL",
    "gn:name":"Frasnay",
    "gn:population":0,
    "gn:timezone":"Europe/Paris",
    "iso:country":"FR",
    "wof:name":"Frasnay",
    "wof:placetype":"locality"
},
  "geometry": {"coordinates":[3.18538,47.12868],"type":"Point"}
}