{
  "type": "Feature",
  "properties": {
    "gn:country":"FR",
    "gn:fcode":"PPL",
    "gn:population":0,
    "iso:country":"FR",
    "qs_pg:aaroncc":"FR",
    "qs_pg:gn_country":"FR",
    "qs_pg:gn_fcode":"PPL",
    "qs_pg:gn_pop":0,
    "qs_pg:name":"La Marana",
    "qs_pg:name_adm0":"France",
    "qs_pg:name_adm1":"Corse",
    "qs_pg:photos":1887,
    "qs_pg:photos_1k":382,
    "qs_pg:photos_9k":8,
    "qs_pg:photos_9r":9,
    "qs_pg:photos_all":1887,
    "qs_pg:photos_sr":15,
    "qs_pg:pop_sr":0,
    "qs_pg:qs_pg_placetype":"locality",
    "qs_pg:qs_pg_placetype_gp":"Town",
    "qs_pg:woe_adm0":23424819,
    "woe:adm0_id":23424819,
    "woe:name_adm0":"France",
    "woe:name_adm1":"Corse",
    "woe:placetype":"Town",
    "wof:name":"La Marana",
    "wof:placetype":"neighbourhood"
},
  "geometry": {"coordinates":[9.52549,42.56063],"type":"Point"}
}