{
  "type": "Feature",
  "properties": {
    "gn:admin1_code":"53",
    "gn:admin2_code":"35",
    "gn:admin3_code":"351",
    "gn:admin4_code":"35006",
    "gn:asciiname":"Cherbault",
    "gn:country_code":"FR",
    "gn:dem":104,
    "gn:feature_class":"P",
    "gn:feature_code":"PPL",
    "gn:name":"Cherbault",
    "gn:population":0,
    "gn:timezone":"Europe/Paris",
    "iso:country":"FR",
    "wof:name":"Cherbault",
    "wof:placetype":"locality"
},
  "geometry": {"coordinates":[-1.199,48.03475],"type":"Point"}
}