{
  "type": "Feature",
  "properties": {
    "gn:admin1_code":"24",
    "gn:admin2_code":"37",
    "gn:admin3_code":"373",
    "gn:admin4_code":"37192",
    "gn:asciiname":"Rochette",
    "gn:country_code":"FR",
    "gn:dem":90,
    "gn:feature_class":"P",
    "gn:feature_code":"PPL",
    "gn:name":"Rochette",
    "gn:population":0,
    "gn:timezone":"Europe/Paris",
    "iso:country":"FR",
    "name:und_x_variant":[
        "Rochet",
        "Rochette"
    ],
    "wof:name":"Rochette",
    "wof:placetype":"locality"
},
  "geometry": {"coordinates":[0.90135,47.20945],"type":"Point"}
}