{
  "type": "Feature",
  "properties": {
    "gn:admin1_code":"44",
    "gn:admin2_code":"57",
    "gn:admin3_code":"577",
    "gn:admin4_code":"57067",
    "gn:asciiname":"Imeldange",
    "gn:country_code":"FR",
    "gn:dem":170,
    "gn:feature_class":"P",
    "gn:feature_code":"PPL",
    "gn:name":"Imeldange",
    "gn:population":0,
    "gn:timezone":"Europe/Paris",
    "iso:country":"FR",
    "wof:name":"Imeldange",
    "wof:placetype":"locality"
},
  "geometry": {"coordinates":[6.19168,49.31097000000001],"type":"Point"}
}