{
  "type": "Feature",
  "properties": {
    "gn:admin1_code":"76",
    "gn:admin2_code":"34",
    "gn:admin3_code":"341",
    "gn:admin4_code":"34257",
    "gn:asciiname":"Plaisance",
    "gn:country_code":"FR",
    "gn:dem":377,
    "gn:elevation":"600.0",
    "gn:feature_class":"P",
    "gn:feature_code":"PPL",
    "gn:name":"Plaisance",
    "gn:population":30,
    "gn:timezone":"Europe/Paris",
    "iso:country":"FR",
    "wof:name":"Plaisance",
    "wof:placetype":"locality",
    "wof:population":30
},
  "geometry": {"coordinates":[3.0044,43.67195],"type":"Point"}
}