{
  "type": "Feature",
  "properties": {
    "gn:admin1_code":"76",
    "gn:admin2_code":"34",
    "gn:admin3_code":"341",
    "gn:admin4_code":"34257",
    "gn:asciiname":"Plaisance",
    "gn:country_code":"FR",
    "gn:dem":377,
    "gn:elevation":"600.0",
    "gn:feature_class":"P",
    "gn:feature_code":"PPL",
    "gn:name":"Plaisance",
    "gn:population":30,
    "gn:timezone":"Europe/Paris",
    "iso:country":"FR",
    "name:cat_x_preferred":[
        "Plaisance"
    ],
    "name:ceb_x_preferred":[
        "Plaisance"
    ],
    "name:deu_x_preferred":[
        "Plaisance"
    ],
    "name:fas_x_preferred":[
        "\u067e\u0644\u0633\u0627\u0646\u0633"
    ],
    "name:fra_x_preferred":[
        "Plaisance"
    ],
    "name:heb_x_preferred":[
        "\u05e4\u05dc\u05d0\u05d9\u05e1\u05d0\u05e0\u05e1"
    ],
    "name:hun_x_preferred":[
        "Plaisance"
    ],
    "name:ita_x_preferred":[
        "Plaisance"
    ],
    "name:nds_x_preferred":[
        "Plaisance"
    ],
    "name:nld_x_preferred":[
        "Plaisance"
    ],
    "name:pms_x_preferred":[
        "Plaisance"
    ],
    "name:pol_x_preferred":[
        "Plaisance"
    ],
    "name:por_x_preferred":[
        "Plaisance"
    ],
    "name:rus_x_preferred":[
        "\u041f\u043b\u0435\u0437\u0430\u043d\u0441"
    ],
    "name:slk_x_preferred":[
        "Plaisance"
    ],
    "name:spa_x_preferred":[
        "Plaisance"
    ],
    "name:swe_x_preferred":[
        "Plaisance"
    ],
    "name:ukr_x_preferred":[
        "\u041f\u043b\u0435\u0437\u0430\u043d\u0441"
    ],
    "wof:name":"Plaisance",
    "wof:placetype":"locality",
    "wof:population":30
},
  "geometry": {"coordinates":[3.0044,43.67195],"type":"Point"}
}