{
  "type": "Feature",
  "properties": {
    "gn:admin1_code":"11",
    "gn:admin2_code":"77",
    "gn:admin3_code":"773",
    "gn:admin4_code":"77097",
    "gn:asciiname":"Feraubry",
    "gn:country_code":"FR",
    "gn:dem":158,
    "gn:feature_class":"P",
    "gn:feature_code":"PPL",
    "gn:name":"F\u00e9raubry",
    "gn:population":0,
    "gn:timezone":"Europe/Paris",
    "iso:country":"FR",
    "wof:name":"Feraubry",
    "wof:placetype":"locality"
},
  "geometry": {"coordinates":[3.26768,48.76041],"type":"Point"}
}