{
  "type": "Feature",
  "properties": {
    "gn:admin1_code":"75",
    "gn:admin2_code":"19",
    "gn:admin3_code":"192",
    "gn:admin4_code":"19176",
    "gn:asciiname":"Pranchere",
    "gn:country_code":"FR",
    "gn:dem":613,
    "gn:feature_class":"P",
    "gn:feature_code":"PPL",
    "gn:name":"Pranch\u00e8re",
    "gn:population":0,
    "gn:timezone":"Europe/Paris",
    "iso:country":"FR",
    "wof:name":"Pranchere",
    "wof:placetype":"locality"
},
  "geometry": {"coordinates":[1.97007,45.36512000000001],"type":"Point"}
}