{
  "type": "Feature",
  "properties": {
    "gn:admin1_code":"11",
    "gn:admin2_code":"91",
    "gn:admin3_code":"913",
    "gn:admin4_code":"91249.0",
    "gn:asciiname":"Le Chardonnet",
    "gn:country_code":"FR",
    "gn:dem":162,
    "gn:feature_class":"P",
    "gn:feature_code":"PPL",
    "gn:name":"Le Chardonnet",
    "gn:population":0,
    "gn:timezone":"Europe/Paris",
    "iso:country":"FR",
    "name:und_x_variant":[
        "Chardonnet",
        "Le Chardonnet"
    ],
    "wof:name":"Le Chardonnet",
    "wof:placetype":"locality"
},
  "geometry": {"coordinates":[2.07414,48.62552],"type":"Point"}
}