{
  "type": "Feature",
  "properties": {
    "gn:admin1_code":"75",
    "gn:admin2_code":"19",
    "gn:admin3_code":"192",
    "gn:admin4_code":"19236",
    "gn:asciiname":"Pouymas Haut",
    "gn:country_code":"FR",
    "gn:dem":594,
    "gn:feature_class":"P",
    "gn:feature_code":"PPL",
    "gn:name":"Pouymas Haut",
    "gn:population":0,
    "gn:timezone":"Europe/Paris",
    "iso:country":"FR",
    "name:und_x_variant":[
        "Pouymas",
        "Pouymas Haut"
    ],
    "wof:name":"Pouymas Haut",
    "wof:placetype":"locality"
},
  "geometry": {"coordinates":[1.91994,45.29681],"type":"Point"}
}