{
  "type": "Feature",
  "properties": {
    "gn:admin1_code":"52",
    "gn:admin2_code":"44",
    "gn:admin3_code":"443",
    "gn:admin4_code":"44184",
    "gn:asciiname":"La Vecquerie",
    "gn:country_code":"FR",
    "gn:dem":34,
    "gn:feature_class":"P",
    "gn:feature_code":"PPLL",
    "gn:name":"La Vecquerie",
    "gn:population":0,
    "gn:timezone":"Europe/Paris",
    "iso:country":"FR",
    "wof:name":"La Vecquerie",
    "wof:placetype":"locality"
},
  "geometry": {"coordinates":[-2.26656,47.25526],"type":"Point"}
}