{
  "type": "Feature",
  "properties": {
    "iso:country":"FR",
    "name:bre_x_preferred":[
        "Plezeved"
    ],
    "name:deu_x_preferred":[
        "Pl\u00e9met"
    ],
    "name:fra_x_preferred":[
        "Pl\u00e9met"
    ],
    "name:ita_x_preferred":[
        "Les Moulins"
    ],
    "name:pol_x_preferred":[
        "Les Moulins"
    ],
    "name:spa_x_preferred":[
        "Pl\u00e9met"
    ],
    "qs_pg:aaroncc":"FR",
    "qs_pg:name":"Les Moulins",
    "qs_pg:name_adm0":"France",
    "qs_pg:name_adm1":"Basse-Normandie",
    "qs_pg:photos":933,
    "qs_pg:photos_1k":189,
    "qs_pg:photos_9k":4,
    "qs_pg:photos_9r":6,
    "qs_pg:photos_all":933,
    "qs_pg:photos_sr":10,
    "qs_pg:pop_sr":0,
    "qs_pg:qs_pg_placetype":"locality",
    "qs_pg:qs_pg_placetype_gp":"Town",
    "qs_pg:woe_adm0":23424819,
    "woe:adm0_id":23424819,
    "woe:name_adm0":"France",
    "woe:name_adm1":"Basse-Normandie",
    "woe:placetype":"Town",
    "wof:name":"Les Moulins",
    "wof:placetype":"neighbourhood"
},
  "geometry": {"coordinates":[-0.879834,49.370385],"type":"Point"}
}