{
  "type": "Feature",
  "properties": {
    "gn:admin1_code":"24",
    "gn:admin2_code":"18",
    "gn:admin3_code":"182",
    "gn:admin4_code":"18278",
    "gn:asciiname":"Frapon",
    "gn:country_code":"FR",
    "gn:dem":236,
    "gn:feature_class":"P",
    "gn:feature_code":"PPL",
    "gn:name":"Frapon",
    "gn:population":0,
    "gn:timezone":"Europe/Paris",
    "iso:country":"FR",
    "name:und_x_variant":[
        "Frappon",
        "Frapon"
    ],
    "wof:name":"Frapon",
    "wof:placetype":"locality"
},
  "geometry": {"coordinates":[2.44066,46.58752],"type":"Point"}
}