{
  "type": "Feature",
  "properties": {
    "gn:admin1_code":"84",
    "gn:admin2_code":"26",
    "gn:admin3_code":"261",
    "gn:admin4_code":"26128.0",
    "gn:asciiname":"Les Maillets",
    "gn:country_code":"FR",
    "gn:dem":674,
    "gn:feature_class":"P",
    "gn:feature_code":"PPL",
    "gn:name":"Les Maillets",
    "gn:population":0,
    "gn:timezone":"Europe/Paris",
    "iso:country":"FR",
    "wof:name":"Les Maillets",
    "wof:placetype":"locality"
},
  "geometry": {"coordinates":[5.22342,44.81956],"type":"Point"}
}