{
  "type": "Feature",
  "properties": {
    "gn:admin1_code":"53",
    "gn:admin2_code":"29",
    "gn:admin3_code":"294",
    "gn:admin4_code":"29230",
    "gn:asciiname":"Coatviller",
    "gn:country_code":"FR",
    "gn:dem":131,
    "gn:feature_class":"P",
    "gn:feature_code":"PPL",
    "gn:name":"Coatviller",
    "gn:population":0,
    "gn:timezone":"Europe/Paris",
    "iso:country":"FR",
    "name:und_x_variant":[
        "Coat-er-huiler",
        "Coatviller"
    ],
    "wof:name":"Coatviller",
    "wof:placetype":"locality"
},
  "geometry": {"coordinates":[-3.57189,47.9637],"type":"Point"}
}