{
  "type": "Feature",
  "properties": {
    "gn:admin1_code":"11",
    "gn:admin2_code":"77",
    "gn:admin3_code":"774",
    "gn:admin4_code":"77035.0",
    "gn:asciiname":"Maurepas",
    "gn:country_code":"FR",
    "gn:dem":161,
    "gn:feature_class":"P",
    "gn:feature_code":"PPL",
    "gn:name":"Maurepas",
    "gn:population":0,
    "gn:timezone":"Europe/Paris",
    "iso:country":"FR",
    "name:ceb_x_preferred":[
        "Maurepas"
    ],
    "name:deu_x_preferred":[
        "Maurepas"
    ],
    "name:epo_x_preferred":[
        "Maurepas"
    ],
    "name:fra_x_preferred":[
        "Maurepas"
    ],
    "name:ita_x_preferred":[
        "Maurepas"
    ],
    "name:nds_x_preferred":[
        "Maurepas"
    ],
    "name:nld_x_preferred":[
        "Maurepas"
    ],
    "name:pol_x_preferred":[
        "Maurepas"
    ],
    "name:por_x_preferred":[
        "Maurepas"
    ],
    "name:slk_x_preferred":[
        "Maurepas"
    ],
    "name:spa_x_preferred":[
        "Maurepas"
    ],
    "name:swe_x_preferred":[
        "Maurepas"
    ],
    "name:ukr_x_preferred":[
        "\u041c\u043e\u0440\u0435\u043f\u0430"
    ],
    "name:zho_x_preferred":[
        "\u83ab\u52d2\u5e15"
    ],
    "wof:name":"Maurepas",
    "wof:placetype":"locality"
},
  "geometry": {"coordinates":[3.00261,48.22427],"type":"Point"}
}