{
  "type": "Feature",
  "properties": {
    "gn:admin1_code":"93",
    "gn:admin2_code":"13",
    "gn:admin3_code":"131",
    "gn:admin4_code":"13019",
    "gn:asciiname":"Barreme",
    "gn:country_code":"FR",
    "gn:dem":151,
    "gn:feature_class":"P",
    "gn:feature_code":"PPL",
    "gn:name":"Barr\u00eame",
    "gn:population":0,
    "gn:timezone":"Europe/Paris",
    "iso:country":"FR",
    "wof:name":"Barreme",
    "wof:placetype":"locality"
},
  "geometry": {"coordinates":[5.38607,43.45452],"type":"Point"}
}