{
  "type": "Feature",
  "properties": {
    "frgov:code_epci":"240900464",
    "frgov:insee_arr":"2",
    "frgov:insee_com":"09211",
    "frgov:insee_dep":"09",
    "frgov:insee_reg":"76",
    "frgov:nom_com":"Monts\u00e9gur",
    "frgov:nom_com_m":"MONTSEGUR",
    "frgov:nom_dep":"ARIEGE",
    "frgov:nom_reg":"OCCITANIE",
    "frgov:statut":"Commune simple",
    "gn:admin1_code":"76",
    "gn:admin2_code":"09",
    "gn:admin3_code":"091",
    "gn:admin4_code":"09211",
    "gn:asciiname":"Montsegur",
    "gn:country_code":"FR",
    "gn:dem":923,
    "gn:feature_class":"P",
    "gn:feature_code":"PPL",
    "gn:name":"Monts\u00e9gur",
    "gn:population":128,
    "gn:timezone":"Europe/Paris",
    "iso:country":"FR",
    "name:bre_x_preferred":[
        "Kastell Montsegur"
    ],
    "name:ces_x_preferred":[
        "Monts\u00e9gur"
    ],
    "name:deu_x_preferred":[
        "Monts\u00e9gur"
    ],
    "name:deu_x_variant":[
        "Burg Monts\u00e9gur"
    ],
    "name:eng_x_preferred":[
        "Monts\u00e9gur"
    ],
    "name:eus_x_preferred":[
        "Montsegur gaztelua"
    ],
    "name:fra_x_preferred":[
        "Monts\u00e9gur"
    ],
    "name:hye_x_preferred":[
        "\u0544\u0578\u0576\u057d\u0565\u0563\u0575\u0578\u0582\u0580"
    ],
    "name:ita_x_preferred":[
        "Monts\u00e9gur"
    ],
    "name:nld_x_preferred":[
        "Ch\u00e2teau de Monts\u00e9gur"
    ],
    "name:pnb_x_preferred":[
        "\u0634\u062a\u0648 \u0645\u0648\u0646\u0679\u0633\u06cc\u06af\u0631"
    ],
    "name:pol_x_preferred":[
        "Monts\u00e9gur"
    ],
    "name:ron_x_preferred":[
        "Castelul Monts\u00e9gur"
    ],
    "name:rus_x_preferred":[
        "\u041c\u043e\u043d\u0441\u0435\u0433\u044e\u0440"
    ],
    "name:slk_x_preferred":[
        "Hrad Monts\u00e9gur"
    ],
    "name:spa_x_preferred":[
        "Montsegur"
    ],
    "name:swe_x_preferred":[
        "Monts\u00e9gur"
    ],
    "name:und_x_variant":[
        "Monts\u00e9gur"
    ],
    "qs:a0":"France",
    "qs:a1":"ARIEGE",
    "qs:a1_lc":"09",
    "qs:a1r":"MIDI-PYRENEES",
    "qs:a1r_lc":"73",
    "qs:a2_lc":"07",
    "qs:a2r_lc":"1",
    "qs:adm0":"France",
    "qs:adm0_a3":"FRA",
    "qs:la":"MONTSEGUR",
    "qs:la_lc":"09211",
    "qs:level":"localadmin",
    "qs:type":"Commune simple",
    "wof:coterminous":[
        404358391
    ],
    "wof:name":"Montsegur",
    "wof:placetype":"locality",
    "wof:placetype_local":"Commune simple",
    "wof:population":128
},
  "geometry": {"coordinates":[1.83234,42.87021],"type":"Point"}
}