{
  "type": "Feature",
  "properties": {
    "iso:country":"FR",
    "name:Eng_x_preferred":[
        "Coeur de ville"
    ],
    "name:Fre_x_preferred":[
        "C\u0153ur de ville"
    ],
    "name:eng_x_preferred":[
        "Coeur de ville"
    ],
    "wof:name":"Coeur de ville",
    "wof:placetype":"neighbourhood"
},
  "geometry": {"coordinates":[2.25567178942167,48.89744829945591],"type":"Point"}
}