{
  "type": "Feature",
  "properties": {
    "gn:gn_country":"FR",
    "gn:gn_fcode":"PPL",
    "gn:gn_pop":21394,
    "gn:population":21394,
    "iso:country":"FR",
    "name:bug_x_preferred":[
        "Eysines"
    ],
    "name:cat_x_preferred":[
        "Aisinas"
    ],
    "name:ceb_x_preferred":[
        "Eysines"
    ],
    "name:deu_x_preferred":[
        "Eysines"
    ],
    "name:eus_x_preferred":[
        "Eysines"
    ],
    "name:fra_x_preferred":[
        "Eysines"
    ],
    "name:hun_x_preferred":[
        "Eysines"
    ],
    "name:ind_x_preferred":[
        "Eysines"
    ],
    "name:ita_x_preferred":[
        "Eysines"
    ],
    "name:kaz_x_preferred":[
        "\u0415\u0437\u0438\u043d"
    ],
    "name:lat_x_preferred":[
        "Eysines"
    ],
    "name:mlg_x_preferred":[
        "Eysines"
    ],
    "name:msa_x_preferred":[
        "Eysines"
    ],
    "name:nld_x_preferred":[
        "Eysines"
    ],
    "name:oci_x_preferred":[
        "Aisinas"
    ],
    "name:pms_x_preferred":[
        "Eysines"
    ],
    "name:pol_x_preferred":[
        "Eysines"
    ],
    "name:por_x_preferred":[
        "Eysines"
    ],
    "name:ron_x_preferred":[
        "Eysines"
    ],
    "name:slk_x_preferred":[
        "Eysines"
    ],
    "name:spa_x_preferred":[
        "Eysines"
    ],
    "name:srp_x_preferred":[
        "\u0415\u0441\u0435\u043d"
    ],
    "name:swe_x_preferred":[
        "Eysines"
    ],
    "name:ukr_x_preferred":[
        "\u0415\u0437\u0456\u043d"
    ],
    "name:uzb_x_preferred":[
        "Eysines"
    ],
    "name:vie_x_preferred":[
        "Eysines"
    ],
    "name:vol_x_preferred":[
        "Eysines"
    ],
    "name:war_x_preferred":[
        "Eysines"
    ],
    "qs_pg:aaroncc":"FR",
    "qs_pg:gn_country":"FR",
    "qs_pg:gn_fcode":"PPL",
    "qs_pg:gn_pop":21394,
    "qs_pg:name":"Eysines",
    "qs_pg:name_adm0":"France",
    "qs_pg:name_adm1":"Aquitaine",
    "qs_pg:photos":6,
    "qs_pg:photos_1k":1,
    "qs_pg:photos_9k":1,
    "qs_pg:photos_9r":1,
    "qs_pg:photos_all":6,
    "qs_pg:photos_sr":1,
    "qs_pg:pop_sr":7,
    "qs_pg:qs_pg_placetype":"neighbourhood",
    "qs_pg:qs_pg_placetype_gp":"Suburb",
    "qs_pg:woe_adm0":23424819,
    "woe:adm0_id":23424819,
    "woe:name_adm0":"France",
    "woe:name_adm1":"Aquitaine",
    "woe:placetype":"Suburb",
    "wof:name":"Eysines",
    "wof:placetype":"neighbourhood",
    "wof:population":21394
},
  "geometry": {"coordinates":[-0.64686,44.88352],"type":"Point"}
}