{
  "type": "Feature",
  "properties": {
    "gn:admin1_code":"28",
    "gn:admin2_code":"50",
    "gn:admin3_code":"501",
    "gn:admin4_code":"50410",
    "gn:asciiname":"Cormeray",
    "gn:country_code":"FR",
    "gn:dem":56,
    "gn:feature_class":"P",
    "gn:feature_code":"PPL",
    "gn:name":"Cormeray",
    "gn:population":0,
    "gn:timezone":"Europe/Paris",
    "iso:country":"FR",
    "wof:name":"Cormeray",
    "wof:placetype":"locality"
},
  "geometry": {"coordinates":[-1.44657,48.55035],"type":"Point"}
}