{
  "type": "Feature",
  "properties": {
    "gn:admin1_code":"28",
    "gn:admin2_code":"50",
    "gn:admin3_code":"501",
    "gn:admin4_code":"50410",
    "gn:asciiname":"Cormeray",
    "gn:country_code":"FR",
    "gn:dem":56,
    "gn:feature_class":"P",
    "gn:feature_code":"PPL",
    "gn:name":"Cormeray",
    "gn:population":0,
    "gn:timezone":"Europe/Paris",
    "iso:country":"FR",
    "name:bre_x_preferred":[
        "Cormeray"
    ],
    "name:ceb_x_preferred":[
        "Cormeray"
    ],
    "name:ces_x_preferred":[
        "Cormeray"
    ],
    "name:deu_x_preferred":[
        "Cormeray"
    ],
    "name:eus_x_preferred":[
        "Cormeray"
    ],
    "name:fra_x_preferred":[
        "Cormeray"
    ],
    "name:hun_x_preferred":[
        "Cormeray"
    ],
    "name:ita_x_preferred":[
        "Cormeray"
    ],
    "name:lat_x_preferred":[
        "Cormeray"
    ],
    "name:mlg_x_preferred":[
        "Cormeray"
    ],
    "name:msa_x_preferred":[
        "Cormeray"
    ],
    "name:nld_x_preferred":[
        "Cormeray"
    ],
    "name:oci_x_preferred":[
        "Cormeray"
    ],
    "name:pms_x_preferred":[
        "Cormeray"
    ],
    "name:pol_x_preferred":[
        "Cormeray"
    ],
    "name:por_x_preferred":[
        "Cormeray"
    ],
    "name:ron_x_preferred":[
        "Cormeray"
    ],
    "name:slk_x_preferred":[
        "Cormeray"
    ],
    "name:spa_x_preferred":[
        "Cormeray"
    ],
    "name:srp_x_preferred":[
        "\u041a\u043e\u0440\u043c\u0435\u0440\u0435"
    ],
    "name:swe_x_preferred":[
        "Cormeray"
    ],
    "name:ukr_x_preferred":[
        "\u041a\u043e\u0440\u043c\u0435\u0440\u0435"
    ],
    "name:uzb_x_preferred":[
        "Cormeray"
    ],
    "name:vie_x_preferred":[
        "Cormeray"
    ],
    "name:vol_x_preferred":[
        "Cormeray"
    ],
    "name:war_x_preferred":[
        "Cormeray"
    ],
    "name:zho_x_preferred":[
        "\u79d1\u5c14\u9ed8\u8d56"
    ],
    "wof:name":"Cormeray",
    "wof:placetype":"locality"
},
  "geometry": {"coordinates":[-1.44657,48.55035],"type":"Point"}
}