{
  "type": "Feature",
  "properties": {
    "gn:admin1_code":"75",
    "gn:admin2_code":"16",
    "gn:admin3_code":"161",
    "gn:admin4_code":"16093",
    "gn:asciiname":"La Petitie",
    "gn:country_code":"FR",
    "gn:dem":120,
    "gn:feature_class":"P",
    "gn:feature_code":"PPL",
    "gn:name":"La Petitie",
    "gn:population":0,
    "gn:timezone":"Europe/Paris",
    "iso:country":"FR",
    "wof:name":"La Petitie",
    "wof:placetype":"locality"
},
  "geometry": {"coordinates":[0.35,45.63333],"type":"Point"}
}