{
  "type": "Feature",
  "properties": {
    "gn:admin1_code":"84",
    "gn:admin2_code":"69",
    "gn:admin3_code":"691",
    "gn:admin4_code":"69007",
    "gn:asciiname":"Tartara",
    "gn:country_code":"FR",
    "gn:dem":337,
    "gn:feature_class":"P",
    "gn:feature_code":"PPL",
    "gn:name":"Tartara",
    "gn:population":0,
    "gn:timezone":"Europe/Paris",
    "iso:country":"FR",
    "wof:name":"Tartara",
    "wof:placetype":"locality"
},
  "geometry": {"coordinates":[4.78863,45.4998],"type":"Point"}
}