{
  "type": "Feature",
  "properties": {
    "iso:country":"FR",
    "name:eng_x_preferred":[
        "Liberation"
    ],
    "name:fra_x_preferred":[
        "Lib\u00e9ration"
    ],
    "wof:name":"Liberation",
    "wof:placetype":"neighbourhood"
},
  "geometry": {"coordinates":[7.26123652328567,43.71346314370669],"type":"Point"}
}