{
  "type": "Feature",
  "properties": {
    "gn:admin1_code":"27",
    "gn:admin2_code":"58",
    "gn:admin3_code":"581",
    "gn:admin4_code":"58178.0",
    "gn:asciiname":"Les Coupes-de-Pouligny",
    "gn:country_code":"FR",
    "gn:dem":253,
    "gn:feature_class":"P",
    "gn:feature_code":"PPL",
    "gn:name":"Les Coupes-de-Pouligny",
    "gn:population":0,
    "gn:timezone":"Europe/Paris",
    "iso:country":"FR",
    "wof:name":"Les Coupes-de-Pouligny",
    "wof:placetype":"locality"
},
  "geometry": {"coordinates":[3.68249,46.96274],"type":"Point"}
}