{
  "type": "Feature",
  "properties": {
    "frgov:code_epci":"200068229",
    "frgov:insee_arr":"2",
    "frgov:insee_com":"26022",
    "frgov:insee_dep":"26",
    "frgov:insee_reg":"84",
    "frgov:nom_com":"Ballons",
    "frgov:nom_com_m":"BALLONS",
    "frgov:nom_dep":"DROME",
    "frgov:nom_reg":"AUVERGNE-RHONE-ALPES",
    "frgov:statut":"Commune simple",
    "gn:admin1_code":"84",
    "gn:admin2_code":"26",
    "gn:admin3_code":"262",
    "gn:admin4_code":"26022",
    "gn:asciiname":"Ballons",
    "gn:country_code":"FR",
    "gn:dem":813,
    "gn:feature_class":"P",
    "gn:feature_code":"PPL",
    "gn:name":"Ballons",
    "gn:population":73,
    "gn:timezone":"Europe/Paris",
    "iso:country":"FR",
    "name:bug_x_preferred":[
        "Ballons"
    ],
    "name:cat_x_preferred":[
        "Valons"
    ],
    "name:ceb_x_preferred":[
        "Ballons"
    ],
    "name:deu_x_preferred":[
        "Ballons"
    ],
    "name:eus_x_preferred":[
        "Ballons"
    ],
    "name:fra_x_preferred":[
        "Ballons"
    ],
    "name:hun_x_preferred":[
        "Ballons"
    ],
    "name:ita_x_preferred":[
        "Ballons"
    ],
    "name:lat_x_preferred":[
        "Ballons"
    ],
    "name:lmo_x_preferred":[
        "Ballons"
    ],
    "name:mlg_x_preferred":[
        "Ballons"
    ],
    "name:msa_x_preferred":[
        "Ballons"
    ],
    "name:nld_x_preferred":[
        "Ballons"
    ],
    "name:oci_x_preferred":[
        "Valons"
    ],
    "name:pms_x_preferred":[
        "Ballons"
    ],
    "name:pol_x_preferred":[
        "Ballons"
    ],
    "name:por_x_preferred":[
        "Ballons"
    ],
    "name:ron_x_preferred":[
        "Ballons"
    ],
    "name:slk_x_preferred":[
        "Ballons"
    ],
    "name:spa_x_preferred":[
        "Ballons"
    ],
    "name:sqi_x_preferred":[
        "Ballons"
    ],
    "name:srp_x_preferred":[
        "\u0411\u0430\u043b\u043e\u043d"
    ],
    "name:swe_x_preferred":[
        "Ballons"
    ],
    "name:ukr_x_preferred":[
        "\u0411\u0430\u043b\u043b\u043e\u043d"
    ],
    "name:uzb_x_preferred":[
        "Ballons"
    ],
    "name:vie_x_preferred":[
        "Ballons"
    ],
    "name:vol_x_preferred":[
        "Ballons"
    ],
    "name:war_x_preferred":[
        "Ballons"
    ],
    "name:zho_x_preferred":[
        "\u5df4\u9686"
    ],
    "qs:a0":"France",
    "qs:a1":"DROME",
    "qs:a1_lc":"26",
    "qs:a1r":"RHONE-ALPES",
    "qs:a1r_lc":"82",
    "qs:a2_lc":"27",
    "qs:a2r_lc":"2",
    "qs:adm0":"France",
    "qs:adm0_a3":"FRA",
    "qs:la":"BALLONS",
    "qs:la_lc":"26022",
    "qs:level":"localadmin",
    "qs:type":"Commune simple",
    "wof:coterminous":[
        404357695
    ],
    "wof:name":"Ballons",
    "wof:placetype":"locality",
    "wof:placetype_local":"Commune simple",
    "wof:population":73
},
  "geometry": {"coordinates":[5.64375,44.25562],"type":"Point"}
}