{
  "type": "Feature",
  "properties": {
    "gn:admin1_code":"84",
    "gn:admin2_code":"26",
    "gn:admin3_code":"262",
    "gn:admin4_code":"26022",
    "gn:asciiname":"Ballons",
    "gn:country_code":"FR",
    "gn:dem":813,
    "gn:feature_class":"P",
    "gn:feature_code":"PPL",
    "gn:name":"Ballons",
    "gn:population":73,
    "gn:timezone":"Europe/Paris",
    "iso:country":"FR",
    "wof:name":"Ballons",
    "wof:placetype":"locality",
    "wof:population":73
},
  "geometry": {"coordinates":[5.64375,44.25562],"type":"Point"}
}