{
  "type": "Feature",
  "properties": {
    "gn:admin1_code":"52",
    "gn:admin2_code":"85",
    "gn:admin3_code":"853",
    "gn:admin4_code":"85288",
    "gn:asciiname":"Port Bourgenay",
    "gn:country_code":"FR",
    "gn:dem":10,
    "gn:feature_class":"P",
    "gn:feature_code":"PPL",
    "gn:name":"Port Bourgenay",
    "gn:population":0,
    "gn:timezone":"Europe/Paris",
    "iso:country":"FR",
    "wof:name":"Port Bourgenay",
    "wof:placetype":"locality"
},
  "geometry": {"coordinates":[-1.67868,46.44374000000001],"type":"Point"}
}