{
  "type": "Feature",
  "properties": {
    "gn:admin1_code":"75",
    "gn:admin2_code":"24",
    "gn:admin3_code":"243",
    "gn:admin4_code":"24408",
    "gn:asciiname":"Saint-Front-d'Alemps",
    "gn:country_code":"FR",
    "gn:dem":150,
    "gn:feature_class":"P",
    "gn:feature_code":"PPL",
    "gn:name":"Saint-Front-d\u2019Alemps",
    "gn:population":0,
    "gn:timezone":"Europe/Paris",
    "iso:country":"FR",
    "name:und_x_variant":[
        "Saint-Front",
        "Saint-Front-d\u2019Alemps"
    ],
    "wof:name":"Saint-Front-d'Alemps",
    "wof:placetype":"locality"
},
  "geometry": {"coordinates":[0.78082,45.32383],"type":"Point"}
}