{
  "type": "Feature",
  "properties": {
    "gn:admin1_code":"75",
    "gn:admin2_code":"24",
    "gn:admin3_code":"243",
    "gn:admin4_code":"24408",
    "gn:asciiname":"Saint-Front-d'Alemps",
    "gn:country_code":"FR",
    "gn:dem":150,
    "gn:feature_class":"P",
    "gn:feature_code":"PPL",
    "gn:name":"Saint-Front-d\u2019Alemps",
    "gn:population":0,
    "gn:timezone":"Europe/Paris",
    "iso:country":"FR",
    "name:bug_x_preferred":[
        "Saint-Front-d'Alemps"
    ],
    "name:ceb_x_preferred":[
        "Saint-Front-d'Alemps"
    ],
    "name:deu_x_preferred":[
        "Saint-Front-d\u2019Alemps"
    ],
    "name:fra_x_preferred":[
        "Saint-Front-d'Alemps"
    ],
    "name:hun_x_preferred":[
        "Saint-Front-d\u2019Alemps"
    ],
    "name:ita_x_preferred":[
        "Saint-Front-d'Alemps"
    ],
    "name:kaz_x_preferred":[
        "\u0421\u0435\u043d-\u0424\u0440\u043e\u043d-\u0434'\u0410\u043b\u0435\u043c"
    ],
    "name:lat_x_preferred":[
        "Saint-Front-d'Alemps"
    ],
    "name:mlg_x_preferred":[
        "Saint-Front-d'Alemps"
    ],
    "name:msa_x_preferred":[
        "Saint-Front-d'Alemps"
    ],
    "name:nld_x_preferred":[
        "Saint-Front-d'Alemps"
    ],
    "name:pms_x_preferred":[
        "Saint-Front-d'Alemps"
    ],
    "name:pol_x_preferred":[
        "Saint-Front-d\u2019Alemps"
    ],
    "name:por_x_preferred":[
        "Saint-Front-d'Alemps"
    ],
    "name:ron_x_preferred":[
        "Saint-Front-d'Alemps"
    ],
    "name:rus_x_preferred":[
        "\u0421\u0435\u043d-\u0424\u0440\u043e\u043d-\u0434\u2019\u0410\u043b\u0435\u043c"
    ],
    "name:slk_x_preferred":[
        "Saint-Front-d\u2019Alemps"
    ],
    "name:spa_x_preferred":[
        "Saint-Front-d'Alemps"
    ],
    "name:swe_x_preferred":[
        "Saint-Front-d'Alemps"
    ],
    "name:ukr_x_preferred":[
        "\u0421\u0435\u043d-\u0424\u0440\u043e\u043d-\u0434'\u0410\u043b\u0435\u043c"
    ],
    "name:und_x_variant":[
        "Saint-Front",
        "Saint-Front-d\u2019Alemps"
    ],
    "name:urd_x_preferred":[
        "\u0633\u06cc\u0646\u0679-\u0641\u0631\u0646\u0679-\u062f\u0644\u0645\u067e\u0633"
    ],
    "name:uzb_x_preferred":[
        "Saint-Front-d'Alemps"
    ],
    "name:vie_x_preferred":[
        "Saint-Front-d'Alemps"
    ],
    "name:vol_x_preferred":[
        "Saint-Front-d'Alemps"
    ],
    "name:war_x_preferred":[
        "Saint-Front-d'Alemps"
    ],
    "name:zho_x_preferred":[
        "\u5723\u592b\u9f99\u8fbe\u6717\u666e"
    ],
    "wof:name":"Saint-Front-d'Alemps",
    "wof:placetype":"locality"
},
  "geometry": {"coordinates":[0.78082,45.32383],"type":"Point"}
}