{
  "type": "Feature",
  "properties": {
    "gn:admin1_code":"75",
    "gn:admin2_code":"19",
    "gn:admin3_code":"191",
    "gn:admin4_code":"19030",
    "gn:asciiname":"La Combe",
    "gn:country_code":"FR",
    "gn:dem":136,
    "gn:feature_class":"P",
    "gn:feature_code":"PPL",
    "gn:name":"La Combe",
    "gn:population":0,
    "gn:timezone":"Europe/Paris",
    "iso:country":"FR",
    "wof:name":"La Combe",
    "wof:placetype":"locality"
},
  "geometry": {"coordinates":[1.35509,45.15258],"type":"Point"}
}