{
  "type": "Feature",
  "properties": {
    "gn:admin1_code":"28",
    "gn:admin2_code":"76",
    "gn:admin3_code":"762",
    "gn:admin4_code":"76586",
    "gn:asciiname":"La Grande Rue",
    "gn:country_code":"FR",
    "gn:dem":112,
    "gn:feature_class":"P",
    "gn:feature_code":"PPL",
    "gn:name":"La Grande Rue",
    "gn:population":0,
    "gn:timezone":"Europe/Paris",
    "iso:country":"FR",
    "name:deu_x_preferred":[
        "La Grande Rue"
    ],
    "name:fra_x_preferred":[
        "La-grande-rue"
    ],
    "wof:name":"La Grande Rue",
    "wof:placetype":"locality"
},
  "geometry": {"coordinates":[0.36295,49.5752],"type":"Point"}
}