{
  "type": "Feature",
  "properties": {
    "gn:admin1_code":"84",
    "gn:admin2_code":"26",
    "gn:admin3_code":"262",
    "gn:admin4_code":"26264",
    "gn:asciiname":"Le Chambon",
    "gn:country_code":"FR",
    "gn:dem":468,
    "gn:feature_class":"P",
    "gn:feature_code":"PPL",
    "gn:name":"Le Chambon",
    "gn:population":0,
    "gn:timezone":"Europe/Paris",
    "iso:country":"FR",
    "wof:name":"Le Chambon",
    "wof:placetype":"locality"
},
  "geometry": {"coordinates":[5.35773,44.39403],"type":"Point"}
}