{
  "type": "Feature",
  "properties": {
    "gn:admin1_code":"93",
    "gn:admin2_code":"05",
    "gn:admin3_code":"051",
    "gn:admin4_code":"05007",
    "gn:asciiname":"Le Coin",
    "gn:country_code":"FR",
    "gn:dem":1577,
    "gn:feature_class":"P",
    "gn:feature_code":"PPL",
    "gn:name":"Le Coin",
    "gn:population":0,
    "gn:timezone":"Europe/Paris",
    "iso:country":"FR",
    "wof:name":"Le Coin",
    "wof:placetype":"locality"
},
  "geometry": {"coordinates":[6.73333,44.76667],"type":"Point"}
}