{
  "type": "Feature",
  "properties": {
    "gn:admin1_code":"24",
    "gn:admin2_code":"18",
    "gn:admin3_code":"182",
    "gn:admin4_code":"18031.0",
    "gn:asciiname":"Luceau",
    "gn:country_code":"FR",
    "gn:dem":216,
    "gn:feature_class":"P",
    "gn:feature_code":"PPL",
    "gn:name":"Luceau",
    "gn:population":0,
    "gn:timezone":"Europe/Paris",
    "iso:country":"FR",
    "wof:name":"Luceau",
    "wof:placetype":"locality"
},
  "geometry": {"coordinates":[2.74529,46.87934],"type":"Point"}
}