{
  "type": "Feature",
  "properties": {
    "gn:admin1_code":"24",
    "gn:admin2_code":"18",
    "gn:admin3_code":"182",
    "gn:admin4_code":"18031.0",
    "gn:asciiname":"Luceau",
    "gn:country_code":"FR",
    "gn:dem":216,
    "gn:feature_class":"P",
    "gn:feature_code":"PPL",
    "gn:name":"Luceau",
    "gn:population":0,
    "gn:timezone":"Europe/Paris",
    "iso:country":"FR",
    "name:cat_x_preferred":[
        "Luceau"
    ],
    "name:ceb_x_preferred":[
        "Luceau"
    ],
    "name:deu_x_preferred":[
        "Luceau"
    ],
    "name:eus_x_preferred":[
        "Luceau"
    ],
    "name:fra_x_preferred":[
        "Luceau"
    ],
    "name:hun_x_preferred":[
        "Luceau"
    ],
    "name:ita_x_preferred":[
        "Luceau"
    ],
    "name:lat_x_preferred":[
        "Luceau"
    ],
    "name:mlg_x_preferred":[
        "Luceau"
    ],
    "name:msa_x_preferred":[
        "Luceau"
    ],
    "name:nld_x_preferred":[
        "Luceau"
    ],
    "name:oci_x_preferred":[
        "Luceau"
    ],
    "name:pms_x_preferred":[
        "Luceau"
    ],
    "name:pol_x_preferred":[
        "Luceau"
    ],
    "name:por_x_preferred":[
        "Luceau"
    ],
    "name:ron_x_preferred":[
        "Luceau"
    ],
    "name:slk_x_preferred":[
        "Luceau"
    ],
    "name:spa_x_preferred":[
        "Luceau"
    ],
    "name:swe_x_preferred":[
        "Luceau"
    ],
    "name:ukr_x_preferred":[
        "\u041b\u044e\u0441\u043e"
    ],
    "name:vie_x_preferred":[
        "Luceau"
    ],
    "name:vol_x_preferred":[
        "Luceau"
    ],
    "name:war_x_preferred":[
        "Luceau"
    ],
    "wof:name":"Luceau",
    "wof:placetype":"locality"
},
  "geometry": {"coordinates":[2.74529,46.87934],"type":"Point"}
}