{
  "type": "Feature",
  "properties": {
    "gn:admin1_code":"24",
    "gn:admin2_code":"28",
    "gn:admin3_code":"281",
    "gn:admin4_code":"28337.0",
    "gn:asciiname":"Dolmont",
    "gn:country_code":"FR",
    "gn:dem":151,
    "gn:feature_class":"P",
    "gn:feature_code":"PPL",
    "gn:name":"Dolmont",
    "gn:population":0,
    "gn:timezone":"Europe/Paris",
    "iso:country":"FR",
    "wof:name":"Dolmont",
    "wof:placetype":"locality"
},
  "geometry": {"coordinates":[1.36193,48.42603],"type":"Point"}
}