{
  "type": "Feature",
  "properties": {
    "iso:country":"FR",
    "name:eng_x_preferred":[
        "Centre-Ville-Mairie"
    ],
    "name:fra_x_preferred":[
        "Centre-Ville-Mairie"
    ],
    "name:fra_x_variant":[
        "Centre-Ville"
    ],
    "wof:name":"Centre-Ville-Mairie",
    "wof:placetype":"neighbourhood"
},
  "geometry": {"coordinates":[2.45467021874622,48.89006001516724],"type":"Point"}
}