{
  "type": "Feature",
  "properties": {
    "iso:country":"FR",
    "name:eng_x_preferred":[
        "Limeil les Candies"
    ],
    "name:fra_x_preferred":[
        "Limeil les Candies"
    ],
    "name:fra_x_variant":[
        "Les Candies"
    ],
    "wof:name":"Limeil les Candies",
    "wof:placetype":"neighbourhood"
},
  "geometry": {"coordinates":[2.48360778250656,48.74291410025491],"type":"Point"}
}