{
  "type": "Feature",
  "properties": {
    "frgov:code_epci":"200040293",
    "frgov:insee_arr":"5",
    "frgov:insee_com":"71057",
    "frgov:insee_dep":"71",
    "frgov:insee_reg":"27",
    "frgov:nom_com":"Bray",
    "frgov:nom_com_m":"BRAY",
    "frgov:nom_dep":"SAONE-ET-LOIRE",
    "frgov:nom_reg":"BOURGOGNE-FRANCHE-COMTE",
    "frgov:statut":"Commune simple",
    "gn:admin1_code":"27",
    "gn:admin2_code":"71",
    "gn:admin3_code":"715",
    "gn:admin4_code":"71057.0",
    "gn:asciiname":"Bray",
    "gn:country_code":"FR",
    "gn:dem":304,
    "gn:feature_class":"P",
    "gn:feature_code":"PPL",
    "gn:name":"Bray",
    "gn:population":129,
    "gn:timezone":"Europe/Paris",
    "iso:country":"FR",
    "name:bre_x_preferred":[
        "Bray"
    ],
    "name:cat_x_preferred":[
        "Bray"
    ],
    "name:ceb_x_preferred":[
        "Bray"
    ],
    "name:deu_x_preferred":[
        "Bray"
    ],
    "name:eus_x_preferred":[
        "Bray"
    ],
    "name:fra_x_preferred":[
        "Bray"
    ],
    "name:heb_x_preferred":[
        "\u05d1\u05e8\u05d9\u05d9"
    ],
    "name:ita_x_preferred":[
        "Bray"
    ],
    "name:kaz_x_preferred":[
        "\u0411\u0440\u0435"
    ],
    "name:nds_x_preferred":[
        "Bray"
    ],
    "name:nld_x_preferred":[
        "Bray"
    ],
    "name:pms_x_preferred":[
        "Bray"
    ],
    "name:pol_x_preferred":[
        "Bray"
    ],
    "name:por_x_preferred":[
        "Bray"
    ],
    "name:rus_x_preferred":[
        "\u0411\u0440\u0435"
    ],
    "name:slk_x_preferred":[
        "Bray"
    ],
    "name:spa_x_preferred":[
        "Bray"
    ],
    "name:srp_x_preferred":[
        "\u0411\u0440\u0435"
    ],
    "name:swe_x_preferred":[
        "Bray"
    ],
    "name:ukr_x_preferred":[
        "\u0411\u0440\u0435"
    ],
    "name:vol_x_preferred":[
        "Bray"
    ],
    "qs:a0":"France",
    "qs:a1":"SAONE-ET-LOIRE",
    "qs:a1_lc":"71",
    "qs:a1r":"BOURGOGNE",
    "qs:a1r_lc":"26",
    "qs:a2_lc":"12",
    "qs:a2r_lc":"5",
    "qs:adm0":"France",
    "qs:adm0_a3":"FRA",
    "qs:la":"BRAY",
    "qs:la_lc":"71057",
    "qs:level":"localadmin",
    "qs:type":"Commune simple",
    "wof:coterminous":[
        404385709
    ],
    "wof:name":"Bray",
    "wof:placetype":"locality",
    "wof:placetype_local":"Commune simple",
    "wof:population":129
},
  "geometry": {"coordinates":[4.72198,46.50492],"type":"Point"}
}