{
  "type": "Feature",
  "properties": {
    "gn:admin1_code":"32",
    "gn:admin2_code":"62",
    "gn:admin3_code":"625",
    "gn:admin4_code":"62905",
    "gn:asciiname":"Cormette",
    "gn:country_code":"FR",
    "gn:dem":63,
    "gn:feature_class":"P",
    "gn:feature_code":"PPL",
    "gn:name":"Cormette",
    "gn:population":0,
    "gn:timezone":"Europe/Paris",
    "iso:country":"FR",
    "wof:name":"Cormette",
    "wof:placetype":"locality"
},
  "geometry": {"coordinates":[2.16677,50.75746],"type":"Point"}
}