{
  "type": "Feature",
  "properties": {
    "gn:admin1_code":"27",
    "gn:admin2_code":"89",
    "gn:admin3_code":"893",
    "gn:admin4_code":"89326",
    "gn:asciiname":"Rosoy",
    "gn:country_code":"FR",
    "gn:dem":74,
    "gn:feature_class":"P",
    "gn:feature_code":"PPL",
    "gn:name":"Rosoy",
    "gn:population":0,
    "gn:timezone":"Europe/Paris",
    "iso:country":"FR",
    "name:cat_x_preferred":[
        "Rosoy"
    ],
    "name:ceb_x_preferred":[
        "Rosoy"
    ],
    "name:deu_x_preferred":[
        "Rosoy"
    ],
    "name:epo_x_preferred":[
        "Rosoy"
    ],
    "name:fra_x_preferred":[
        "Rosoy"
    ],
    "name:ita_x_preferred":[
        "Rosoy"
    ],
    "name:nld_x_preferred":[
        "Rosoy"
    ],
    "name:oci_x_preferred":[
        "Rosoy"
    ],
    "name:pms_x_preferred":[
        "Rosoy"
    ],
    "name:pol_x_preferred":[
        "Rosoy"
    ],
    "name:por_x_preferred":[
        "Rosoy"
    ],
    "name:slk_x_preferred":[
        "Rosoy"
    ],
    "name:spa_x_preferred":[
        "Rosoy"
    ],
    "name:swe_x_preferred":[
        "Rosoy"
    ],
    "name:ukr_x_preferred":[
        "\u0420\u043e\u0437\u0443\u0430"
    ],
    "wof:name":"Rosoy",
    "wof:placetype":"locality"
},
  "geometry": {"coordinates":[3.31096,48.15097],"type":"Point"}
}