{
  "type": "Feature",
  "properties": {
    "frgov:code_epci":"248900334",
    "frgov:insee_arr":"3",
    "frgov:insee_com":"89326",
    "frgov:insee_dep":"89",
    "frgov:insee_reg":"27",
    "frgov:nom_com":"Rosoy",
    "frgov:nom_com_m":"ROSOY",
    "frgov:nom_dep":"YONNE",
    "frgov:nom_reg":"BOURGOGNE-FRANCHE-COMTE",
    "frgov:statut":"Commune simple",
    "gn:admin1_code":"27",
    "gn:admin2_code":"89",
    "gn:admin3_code":"893",
    "gn:admin4_code":"89326",
    "gn:asciiname":"Rosoy",
    "gn:country_code":"FR",
    "gn:dem":74,
    "gn:feature_class":"P",
    "gn:feature_code":"PPL",
    "gn:name":"Rosoy",
    "gn:population":0,
    "gn:timezone":"Europe/Paris",
    "iso:country":"FR",
    "name:cat_x_preferred":[
        "Rosoy"
    ],
    "name:ceb_x_preferred":[
        "Rosoy"
    ],
    "name:deu_x_preferred":[
        "Rosoy"
    ],
    "name:epo_x_preferred":[
        "Rosoy"
    ],
    "name:fra_x_preferred":[
        "Rosoy"
    ],
    "name:ita_x_preferred":[
        "Rosoy"
    ],
    "name:nld_x_preferred":[
        "Rosoy"
    ],
    "name:oci_x_preferred":[
        "Rosoy"
    ],
    "name:pms_x_preferred":[
        "Rosoy"
    ],
    "name:pol_x_preferred":[
        "Rosoy"
    ],
    "name:por_x_preferred":[
        "Rosoy"
    ],
    "name:slk_x_preferred":[
        "Rosoy"
    ],
    "name:spa_x_preferred":[
        "Rosoy"
    ],
    "name:swe_x_preferred":[
        "Rosoy"
    ],
    "name:ukr_x_preferred":[
        "\u0420\u043e\u0437\u0443\u0430"
    ],
    "qs:a0":"France",
    "qs:a1":"YONNE",
    "qs:a1_lc":"89",
    "qs:a1r":"BOURGOGNE",
    "qs:a1r_lc":"26",
    "qs:a2_lc":"40",
    "qs:a2r_lc":"3",
    "qs:adm0":"France",
    "qs:adm0_a3":"FRA",
    "qs:la":"ROSOY",
    "qs:la_lc":"89326",
    "qs:level":"localadmin",
    "qs:type":"Commune simple",
    "wof:coterminous":[
        404413819
    ],
    "wof:name":"Rosoy",
    "wof:placetype":"locality",
    "wof:placetype_local":"Commune simple"
},
  "geometry": {"coordinates":[3.31096,48.15097],"type":"Point"}
}