{
  "type": "Feature",
  "properties": {
    "gn:admin1_code":"27",
    "gn:admin2_code":"89",
    "gn:admin3_code":"893",
    "gn:admin4_code":"89326",
    "gn:asciiname":"Rosoy",
    "gn:country_code":"FR",
    "gn:dem":74,
    "gn:feature_class":"P",
    "gn:feature_code":"PPL",
    "gn:name":"Rosoy",
    "gn:population":0,
    "gn:timezone":"Europe/Paris",
    "iso:country":"FR",
    "wof:name":"Rosoy",
    "wof:placetype":"locality"
},
  "geometry": {"coordinates":[3.31096,48.15097],"type":"Point"}
}