{
  "type": "Feature",
  "properties": {
    "gn:admin1_code":"52",
    "gn:admin2_code":"49",
    "gn:admin3_code":"491",
    "gn:admin4_code":"49188",
    "gn:asciiname":"Marce",
    "gn:country_code":"FR",
    "gn:dem":38,
    "gn:feature_class":"P",
    "gn:feature_code":"PPL",
    "gn:name":"Marc\u00e9",
    "gn:population":0,
    "gn:timezone":"Europe/Paris",
    "iso:country":"FR",
    "name:ukr_x_preferred":[
        "\u041c\u0430\u0440\u0441\u0435"
    ],
    "name:und_x_variant":[
        "Marc\u00e9"
    ],
    "name:zho_x_preferred":[
        "\u9a6c\u5c14\u585e"
    ],
    "wof:name":"Marce",
    "wof:placetype":"locality"
},
  "geometry": {"coordinates":[-0.32461,47.58002000000001],"type":"Point"}
}