{
  "type": "Feature",
  "properties": {
    "frgov:code_epci":"200068955",
    "frgov:insee_arr":"1",
    "frgov:insee_com":"49188",
    "frgov:insee_dep":"49",
    "frgov:insee_reg":"52",
    "frgov:nom_com":"Marc\u00e9",
    "frgov:nom_com_m":"MARCE",
    "frgov:nom_dep":"MAINE-ET-LOIRE",
    "frgov:nom_reg":"PAYS DE LA LOIRE",
    "frgov:statut":"Commune simple",
    "gn:admin1_code":"52",
    "gn:admin2_code":"49",
    "gn:admin3_code":"491",
    "gn:admin4_code":"49188",
    "gn:asciiname":"Marce",
    "gn:country_code":"FR",
    "gn:dem":38,
    "gn:feature_class":"P",
    "gn:feature_code":"PPL",
    "gn:name":"Marc\u00e9",
    "gn:population":0,
    "gn:timezone":"Europe/Paris",
    "iso:country":"FR",
    "name:cat_x_preferred":[
        "Marc\u00e9"
    ],
    "name:ceb_x_preferred":[
        "Marc\u00e9"
    ],
    "name:cym_x_preferred":[
        "Marc\u00e9"
    ],
    "name:deu_x_preferred":[
        "Marc\u00e9"
    ],
    "name:eus_x_preferred":[
        "Marc\u00e9"
    ],
    "name:fra_x_preferred":[
        "Marc\u00e9"
    ],
    "name:hun_x_preferred":[
        "Marc\u00e9"
    ],
    "name:ita_x_preferred":[
        "Marc\u00e9"
    ],
    "name:lat_x_preferred":[
        "Marc\u00e9"
    ],
    "name:mlg_x_preferred":[
        "Marc\u00e9"
    ],
    "name:msa_x_preferred":[
        "Marc\u00e9"
    ],
    "name:nld_x_preferred":[
        "Marc\u00e9"
    ],
    "name:oci_x_preferred":[
        "Marc\u00e9"
    ],
    "name:pms_x_preferred":[
        "Marc\u00e9"
    ],
    "name:pol_x_preferred":[
        "Marc\u00e9"
    ],
    "name:por_x_preferred":[
        "Marc\u00e9"
    ],
    "name:ron_x_preferred":[
        "Marc\u00e9"
    ],
    "name:slk_x_preferred":[
        "Marc\u00e9"
    ],
    "name:spa_x_preferred":[
        "Marc\u00e9"
    ],
    "name:swe_x_preferred":[
        "Marc\u00e9"
    ],
    "name:ukr_x_preferred":[
        "\u041c\u0430\u0440\u0441\u0435"
    ],
    "name:und_x_variant":[
        "Marc\u00e9"
    ],
    "name:vie_x_preferred":[
        "Marc\u00e9"
    ],
    "name:vol_x_preferred":[
        "Marc\u00e9"
    ],
    "name:war_x_preferred":[
        "Marc\u00e9"
    ],
    "name:zho_x_preferred":[
        "\u9a6c\u5c14\u585e"
    ],
    "qs:a0":"France",
    "qs:a1":"MAINE-ET-LOIRE",
    "qs:a1_lc":"49",
    "qs:a1r":"PAYS DE LA LOIRE",
    "qs:a1r_lc":"52",
    "qs:a2_lc":"31",
    "qs:a2r_lc":"1",
    "qs:adm0":"France",
    "qs:adm0_a3":"FRA",
    "qs:la":"MARCE",
    "qs:la_lc":"49188",
    "qs:level":"localadmin",
    "qs:type":"Commune simple",
    "wof:coterminous":[
        404365367
    ],
    "wof:name":"Marce",
    "wof:placetype":"locality",
    "wof:placetype_local":"Commune simple"
},
  "geometry": {"coordinates":[-0.32461,47.58002],"type":"Point"}
}