{
  "type": "Feature",
  "properties": {
    "gn:admin1_code":"24",
    "gn:admin2_code":"41",
    "gn:admin3_code":"411",
    "gn:admin4_code":"41178",
    "gn:asciiname":"Le Plessis-l'Echelle",
    "gn:country_code":"FR",
    "gn:dem":131,
    "gn:feature_class":"P",
    "gn:feature_code":"PPL",
    "gn:name":"Le Plessis-l\u2019\u00c9chelle",
    "gn:population":0,
    "gn:timezone":"Europe/Paris",
    "iso:country":"FR",
    "name:und_x_variant":[
        "Le Plessis",
        "Le Plessis-l\u2019\u00c9chelle"
    ],
    "wof:name":"Le Plessis-l'Echelle",
    "wof:placetype":"locality"
},
  "geometry": {"coordinates":[1.42837,47.81377],"type":"Point"}
}