{
  "type": "Feature",
  "properties": {
    "gn:admin1_code":"24",
    "gn:admin2_code":"41",
    "gn:admin3_code":"411",
    "gn:admin4_code":"41178",
    "gn:asciiname":"Le Plessis-l'Echelle",
    "gn:country_code":"FR",
    "gn:dem":131,
    "gn:feature_class":"P",
    "gn:feature_code":"PPL",
    "gn:name":"Le Plessis-l\u2019\u00c9chelle",
    "gn:population":0,
    "gn:timezone":"Europe/Paris",
    "iso:country":"FR",
    "name:cat_x_preferred":[
        "Le Plessis-l'\u00c9chelle"
    ],
    "name:ceb_x_preferred":[
        "Le Plessis-l'\u00c9chelle"
    ],
    "name:deu_x_preferred":[
        "Le Plessis-l\u2019\u00c9chelle"
    ],
    "name:eus_x_preferred":[
        "Le Plessis-l'\u00c9chelle"
    ],
    "name:fra_x_preferred":[
        "Le Plessis-l'\u00c9chelle"
    ],
    "name:hun_x_preferred":[
        "Le Plessis-l\u2019\u00c9chelle"
    ],
    "name:ita_x_preferred":[
        "Le Plessis-l'\u00c9chelle"
    ],
    "name:lat_x_preferred":[
        "Le Plessis-l'\u00c9chelle"
    ],
    "name:msa_x_preferred":[
        "Le Plessis-l'\u00c9chelle"
    ],
    "name:nld_x_preferred":[
        "Le Plessis-l'\u00c9chelle"
    ],
    "name:oci_x_preferred":[
        "Le Plessis-l'\u00c9chelle"
    ],
    "name:pms_x_preferred":[
        "Le Plessis-l'\u00c9chelle"
    ],
    "name:pol_x_preferred":[
        "Le Plessis-l\u2019\u00c9chelle"
    ],
    "name:por_x_preferred":[
        "Le Plessis-l'\u00c9chelle"
    ],
    "name:ron_x_preferred":[
        "Le Plessis-l'\u00c9chelle"
    ],
    "name:slk_x_preferred":[
        "Le Plessis-l\u2019\u00c9chelle"
    ],
    "name:spa_x_preferred":[
        "Le Plessis-l'\u00c9chelle"
    ],
    "name:swe_x_preferred":[
        "Le Plessis-l'\u00c9chelle"
    ],
    "name:ukr_x_preferred":[
        "\u041b\u0435-\u041f\u043b\u0435\u0441\u0441\u0456-\u043b'\u0415\u0448\u0435\u043b\u044c"
    ],
    "name:und_x_variant":[
        "Le Plessis",
        "Le Plessis-l\u2019\u00c9chelle"
    ],
    "name:uzb_x_preferred":[
        "Le Plessis-l'\u00c9chelle"
    ],
    "name:vie_x_preferred":[
        "Le Plessis-l'\u00c9chelle"
    ],
    "name:vol_x_preferred":[
        "Le Plessis-l'\u00c9chelle"
    ],
    "name:war_x_preferred":[
        "Le Plessis-l'\u00c9chelle"
    ],
    "name:zho_x_preferred":[
        "\u52d2\u666e\u83b1\u897f\u83b1\u8c22\u5c14"
    ],
    "wof:name":"Le Plessis-l'Echelle",
    "wof:placetype":"locality"
},
  "geometry": {"coordinates":[1.42837,47.81377],"type":"Point"}
}