{
  "type": "Feature",
  "properties": {
    "gn:admin1_code":"75",
    "gn:admin2_code":"47",
    "gn:admin3_code":"471",
    "gn:admin4_code":"47019",
    "gn:asciiname":"Bajamont",
    "gn:country_code":"FR",
    "gn:dem":89,
    "gn:feature_class":"P",
    "gn:feature_code":"PPL",
    "gn:name":"Bajamont",
    "gn:population":0,
    "gn:timezone":"Europe/Paris",
    "iso:country":"FR",
    "wof:name":"Bajamont",
    "wof:placetype":"locality"
},
  "geometry": {"coordinates":[0.7073,44.2656],"type":"Point"}
}