{
  "type": "Feature",
  "properties": {
    "gn:admin1_code":"75",
    "gn:admin2_code":"47",
    "gn:admin3_code":"471",
    "gn:admin4_code":"47019",
    "gn:asciiname":"Bajamont",
    "gn:country_code":"FR",
    "gn:dem":89,
    "gn:feature_class":"P",
    "gn:feature_code":"PPL",
    "gn:name":"Bajamont",
    "gn:population":0,
    "gn:timezone":"Europe/Paris",
    "iso:country":"FR",
    "name:cat_x_preferred":[
        "Bajamont"
    ],
    "name:ceb_x_preferred":[
        "Bajamont"
    ],
    "name:deu_x_preferred":[
        "Bajamont"
    ],
    "name:eus_x_preferred":[
        "Bajamont"
    ],
    "name:fra_x_preferred":[
        "Bajamont"
    ],
    "name:hun_x_preferred":[
        "Bajamont"
    ],
    "name:ita_x_preferred":[
        "Bajamont"
    ],
    "name:kaz_x_preferred":[
        "\u0411\u0430\u0436\u0430\u043c\u043e\u043d"
    ],
    "name:lat_x_preferred":[
        "Bajamont"
    ],
    "name:msa_x_preferred":[
        "Bajamont"
    ],
    "name:nld_x_preferred":[
        "Bajamont"
    ],
    "name:oci_x_preferred":[
        "Bajamont"
    ],
    "name:pms_x_preferred":[
        "Bajamont"
    ],
    "name:pol_x_preferred":[
        "Bajamont"
    ],
    "name:por_x_preferred":[
        "Bajamont"
    ],
    "name:ron_x_preferred":[
        "Bajamont"
    ],
    "name:slk_x_preferred":[
        "Bajamont"
    ],
    "name:spa_x_preferred":[
        "Bajamont"
    ],
    "name:sqi_x_preferred":[
        "Bajamont"
    ],
    "name:srp_x_preferred":[
        "\u0411\u0430\u0436\u0430\u043c\u043e\u043d"
    ],
    "name:swe_x_preferred":[
        "Bajamont"
    ],
    "name:ukr_x_preferred":[
        "\u0411\u0430\u0436\u0430\u043c\u043e\u043d"
    ],
    "name:uzb_x_preferred":[
        "Bajamont"
    ],
    "name:vie_x_preferred":[
        "Bajamont"
    ],
    "name:vol_x_preferred":[
        "Bajamont"
    ],
    "name:war_x_preferred":[
        "Bajamont"
    ],
    "name:zho_x_preferred":[
        "\u5df4\u96c5\u8499"
    ],
    "wof:name":"Bajamont",
    "wof:placetype":"locality"
},
  "geometry": {"coordinates":[0.7073,44.2656],"type":"Point"}
}