{
  "type": "Feature",
  "properties": {
    "frgov:code_epci":"200035459",
    "frgov:insee_arr":"1",
    "frgov:insee_com":"47019",
    "frgov:insee_dep":"47",
    "frgov:insee_reg":"75",
    "frgov:nom_com":"Bajamont",
    "frgov:nom_com_m":"BAJAMONT",
    "frgov:nom_dep":"LOT-ET-GARONNE",
    "frgov:nom_reg":"NOUVELLE-AQUITAINE",
    "frgov:statut":"Commune simple",
    "gn:admin1_code":"75",
    "gn:admin2_code":"47",
    "gn:admin3_code":"471",
    "gn:admin4_code":"47019",
    "gn:asciiname":"Bajamont",
    "gn:country_code":"FR",
    "gn:dem":89,
    "gn:feature_class":"P",
    "gn:feature_code":"PPL",
    "gn:name":"Bajamont",
    "gn:population":0,
    "gn:timezone":"Europe/Paris",
    "iso:country":"FR",
    "name:cat_x_preferred":[
        "Bajamont"
    ],
    "name:ceb_x_preferred":[
        "Bajamont"
    ],
    "name:deu_x_preferred":[
        "Bajamont"
    ],
    "name:eus_x_preferred":[
        "Bajamont"
    ],
    "name:fra_x_preferred":[
        "Bajamont"
    ],
    "name:hun_x_preferred":[
        "Bajamont"
    ],
    "name:ita_x_preferred":[
        "Bajamont"
    ],
    "name:kaz_x_preferred":[
        "\u0411\u0430\u0436\u0430\u043c\u043e\u043d"
    ],
    "name:lat_x_preferred":[
        "Bajamont"
    ],
    "name:msa_x_preferred":[
        "Bajamont"
    ],
    "name:nld_x_preferred":[
        "Bajamont"
    ],
    "name:oci_x_preferred":[
        "Bajamont"
    ],
    "name:pms_x_preferred":[
        "Bajamont"
    ],
    "name:pol_x_preferred":[
        "Bajamont"
    ],
    "name:por_x_preferred":[
        "Bajamont"
    ],
    "name:ron_x_preferred":[
        "Bajamont"
    ],
    "name:slk_x_preferred":[
        "Bajamont"
    ],
    "name:spa_x_preferred":[
        "Bajamont"
    ],
    "name:sqi_x_preferred":[
        "Bajamont"
    ],
    "name:srp_x_preferred":[
        "\u0411\u0430\u0436\u0430\u043c\u043e\u043d"
    ],
    "name:swe_x_preferred":[
        "Bajamont"
    ],
    "name:ukr_x_preferred":[
        "\u0411\u0430\u0436\u0430\u043c\u043e\u043d"
    ],
    "name:uzb_x_preferred":[
        "Bajamont"
    ],
    "name:vie_x_preferred":[
        "Bajamont"
    ],
    "name:vol_x_preferred":[
        "Bajamont"
    ],
    "name:war_x_preferred":[
        "Bajamont"
    ],
    "name:zho_x_preferred":[
        "\u5df4\u96c5\u8499"
    ],
    "qs:a0":"France",
    "qs:a1":"LOT-ET-GARONNE",
    "qs:a1_lc":"47",
    "qs:a1r":"AQUITAINE",
    "qs:a1r_lc":"72",
    "qs:a2_lc":"02",
    "qs:a2r_lc":"1",
    "qs:adm0":"France",
    "qs:adm0_a3":"FRA",
    "qs:la":"BAJAMONT",
    "qs:la_lc":"47019",
    "qs:level":"localadmin",
    "qs:type":"Commune simple",
    "wof:coterminous":[
        404413255
    ],
    "wof:name":"Bajamont",
    "wof:placetype":"locality",
    "wof:placetype_local":"Commune simple"
},
  "geometry": {"coordinates":[0.7073,44.2656],"type":"Point"}
}