{
  "type": "Feature",
  "properties": {
    "iso:country":"FR",
    "name:eng_x_preferred":[
        "Maurepas"
    ],
    "name:fra_x_preferred":[
        "Maurepas"
    ],
    "wof:name":"Maurepas",
    "wof:placetype":"neighbourhood"
},
  "geometry": {"coordinates":[-1.66007566034267,48.12745299589723],"type":"Point"}
}