{
  "type": "Feature",
  "properties": {
    "gn:admin1_code":"93",
    "gn:admin2_code":"83",
    "gn:admin3_code":"833",
    "gn:admin4_code":"83110",
    "gn:asciiname":"Vieux Rougiers",
    "gn:country_code":"FR",
    "gn:dem":502,
    "gn:feature_class":"P",
    "gn:feature_code":"PPL",
    "gn:name":"Vieux Rougiers",
    "gn:population":0,
    "gn:timezone":"Europe/Paris",
    "iso:country":"FR",
    "wof:name":"Vieux Rougiers",
    "wof:placetype":"locality"
},
  "geometry": {"coordinates":[5.85,43.38333],"type":"Point"}
}