{
  "type": "Feature",
  "properties": {
    "gn:admin1_code":"32",
    "gn:admin2_code":"62",
    "gn:admin3_code":"625",
    "gn:admin4_code":"62053",
    "gn:asciiname":"Wandonne",
    "gn:country_code":"FR",
    "gn:dem":81,
    "gn:feature_class":"P",
    "gn:feature_code":"PPL",
    "gn:name":"Wandonne",
    "gn:population":0,
    "gn:timezone":"Europe/Paris",
    "iso:country":"FR",
    "wof:name":"Wandonne",
    "wof:placetype":"locality"
},
  "geometry": {"coordinates":[2.1264,50.56408],"type":"Point"}
}