{
  "type": "Feature",
  "properties": {
    "gn:admin1_code":"84",
    "gn:admin2_code":"43",
    "gn:admin3_code":"432",
    "gn:admin4_code":"43061",
    "gn:asciiname":"Peyredeyre",
    "gn:country_code":"FR",
    "gn:dem":595,
    "gn:feature_class":"P",
    "gn:feature_code":"PPL",
    "gn:name":"Peyredeyre",
    "gn:population":0,
    "gn:timezone":"Europe/Paris",
    "iso:country":"FR",
    "wof:name":"Peyredeyre",
    "wof:placetype":"locality"
},
  "geometry": {"coordinates":[3.91461,45.08256],"type":"Point"}
}