{
  "type": "Feature",
  "properties": {
    "gn:admin1_code":"44",
    "gn:admin2_code":"88",
    "gn:admin3_code":"883",
    "gn:admin4_code":"88361",
    "gn:asciiname":"Provencheres-sur-Fave",
    "gn:country_code":"FR",
    "gn:dem":404,
    "gn:feature_class":"P",
    "gn:feature_code":"PPL",
    "gn:name":"Provench\u00e8res-sur-Fave",
    "gn:population":768,
    "gn:timezone":"Europe/Paris",
    "iso:country":"FR",
    "name:bug_x_preferred":[
        "Provench\u00e8res-sur-Fave"
    ],
    "name:cat_x_preferred":[
        "Provench\u00e8res-sur-Fave"
    ],
    "name:ceb_x_preferred":[
        "Provench\u00e8res-sur-Fave"
    ],
    "name:deu_x_preferred":[
        "Provench\u00e8res-sur-Fave"
    ],
    "name:eus_x_preferred":[
        "Provench\u00e8res-sur-Fave"
    ],
    "name:fra_x_preferred":[
        "Provench\u00e8res-sur-Fave"
    ],
    "name:hun_x_preferred":[
        "Provench\u00e8res-sur-Fave"
    ],
    "name:ind_x_preferred":[
        "Provench\u00e8res-sur-Fave"
    ],
    "name:ita_x_preferred":[
        "Provench\u00e8res-sur-Fave"
    ],
    "name:kaz_x_preferred":[
        "\u041f\u0440\u043e\u0432\u0430\u043d\u0448\u0435\u0440-\u0441\u044e\u0440-\u0424\u0430\u0432"
    ],
    "name:ltz_x_preferred":[
        "Provench\u00e8res-sur-Fave"
    ],
    "name:mlg_x_preferred":[
        "Provench\u00e8res-sur-Fave"
    ],
    "name:msa_x_preferred":[
        "Provench\u00e8res-sur-Fave"
    ],
    "name:nld_x_preferred":[
        "Provench\u00e8res-sur-Fave"
    ],
    "name:oci_x_preferred":[
        "Provench\u00e8res-sur-Fave"
    ],
    "name:pms_x_preferred":[
        "Provench\u00e8res-sur-Fave"
    ],
    "name:pol_x_preferred":[
        "Provench\u00e8res-sur-Fave"
    ],
    "name:por_x_preferred":[
        "Provench\u00e8res-sur-Fave"
    ],
    "name:slk_x_preferred":[
        "Provench\u00e8res-sur-Fave"
    ],
    "name:spa_x_preferred":[
        "Provench\u00e8res-sur-Fave"
    ],
    "name:swe_x_preferred":[
        "Provench\u00e8res-sur-Fave"
    ],
    "name:ukr_x_preferred":[
        "\u041f\u0440\u043e\u0432\u0430\u043d\u0448\u0435\u0440-\u0441\u044e\u0440-\u0424\u0430\u0432"
    ],
    "name:und_x_variant":[
        "Provench\u00e8res"
    ],
    "name:uzb_x_preferred":[
        "Provench\u00e8res-sur-Fave"
    ],
    "name:vie_x_preferred":[
        "Provench\u00e8res-sur-Fave"
    ],
    "name:vol_x_preferred":[
        "Provench\u00e8res-sur-Fave"
    ],
    "name:war_x_preferred":[
        "Provench\u00e8res-sur-Fave"
    ],
    "name:zho_x_preferred":[
        "\u6cd5\u6c83\u6cb3\u7554\u666e\u7f57\u65fa\u8c22\u5c14"
    ],
    "wof:name":"Provencheres-sur-Fave",
    "wof:placetype":"locality",
    "wof:population":768
},
  "geometry": {"coordinates":[7.07859,48.3074],"type":"Point"}
}