{
  "type": "Feature",
  "properties": {
    "gn:admin1_code":"84",
    "gn:admin2_code":"38",
    "gn:admin3_code":"382",
    "gn:admin4_code":"38256",
    "gn:asciiname":"Le Verney",
    "gn:country_code":"FR",
    "gn:dem":557,
    "gn:feature_class":"P",
    "gn:feature_code":"PPL",
    "gn:name":"Le Verney",
    "gn:population":0,
    "gn:timezone":"Europe/Paris",
    "iso:country":"FR",
    "name:und_x_variant":[
        "Verney",
        "Le Verney"
    ],
    "wof:name":"Le Verney",
    "wof:placetype":"locality"
},
  "geometry": {"coordinates":[5.54785,45.45777],"type":"Point"}
}