{
  "type": "Feature",
  "properties": {
    "gn:admin1_code":"84",
    "gn:admin2_code":"73",
    "gn:admin3_code":"733",
    "gn:admin4_code":"73173.0",
    "gn:asciiname":"Les Karellis",
    "gn:country_code":"FR",
    "gn:dem":1575,
    "gn:feature_class":"P",
    "gn:feature_code":"PPLL",
    "gn:name":"Les Karellis",
    "gn:population":0,
    "gn:timezone":"Europe/Paris",
    "iso:country":"FR",
    "wof:name":"Les Karellis",
    "wof:placetype":"locality"
},
  "geometry": {"coordinates":[6.40627,45.22818],"type":"Point"}
}