{
  "type": "Feature",
  "properties": {
    "gn:admin1_code":"76",
    "gn:admin2_code":"11",
    "gn:admin3_code":"112",
    "gn:admin4_code":"11065",
    "gn:asciiname":"Camps-sur-l'Agly",
    "gn:country_code":"FR",
    "gn:dem":510,
    "gn:feature_class":"P",
    "gn:feature_code":"PPL",
    "gn:name":"Camps-sur-l\u2019Agly",
    "gn:population":0,
    "gn:timezone":"Europe/Paris",
    "iso:country":"FR",
    "name:cat_x_preferred":[
        "Camps"
    ],
    "name:ceb_x_preferred":[
        "Camps-sur-l'Agly"
    ],
    "name:deu_x_preferred":[
        "Camps-sur-l\u2019Agly"
    ],
    "name:eus_x_preferred":[
        "Camps d'Aglin"
    ],
    "name:fra_x_preferred":[
        "Camps-sur-l'Agly"
    ],
    "name:hun_x_preferred":[
        "Camps-sur-l\u2019Agly"
    ],
    "name:ita_x_preferred":[
        "Camps-sur-l'Agly"
    ],
    "name:kaz_x_preferred":[
        "\u041a\u0430\u043c-\u0441\u044e\u0440-\u043b'\u0410\u0433\u043b\u0438"
    ],
    "name:lat_x_preferred":[
        "Camps-sur-l\u2019Agly"
    ],
    "name:lmo_x_preferred":[
        "Camps-sur-l'Agly"
    ],
    "name:msa_x_preferred":[
        "Camps-sur-l'Agly"
    ],
    "name:nld_x_preferred":[
        "Camps-sur-l'Agly"
    ],
    "name:oci_x_preferred":[
        "Camps d'Aglin"
    ],
    "name:pms_x_preferred":[
        "Camps-sur-l'Agly"
    ],
    "name:pol_x_preferred":[
        "Camps-sur-l\u2019Agly"
    ],
    "name:por_x_preferred":[
        "Camps-sur-l'Agly"
    ],
    "name:ron_x_preferred":[
        "Camps-sur-l'Agly"
    ],
    "name:rus_x_preferred":[
        "\u041a\u0430\u043d-\u0441\u044e\u0440-\u043b\u2019\u0410\u0433\u043b\u0438"
    ],
    "name:slk_x_preferred":[
        "Camps-sur-l\u2019Agly"
    ],
    "name:spa_x_preferred":[
        "Camps-sur-l'Agly"
    ],
    "name:swe_x_preferred":[
        "Camps-sur-l'Agly"
    ],
    "name:ukr_x_preferred":[
        "\u041a\u0430\u043c-\u0441\u044e\u0440-\u043b'\u0410\u0433\u043b\u0456"
    ],
    "name:vie_x_preferred":[
        "Camps-sur-l'Agly"
    ],
    "name:vol_x_preferred":[
        "Camps-sur-l'Agly"
    ],
    "name:war_x_preferred":[
        "Camps-sur-l'Agly"
    ],
    "name:zho_x_preferred":[
        "\u963f\u683c\u5229\u6cb3\u7554\u5eb7\u6751"
    ],
    "wof:name":"Camps-sur-l'Agly",
    "wof:placetype":"locality"
},
  "geometry": {"coordinates":[2.43242,42.8586],"type":"Point"}
}