{
  "type": "Feature",
  "properties": {
    "gn:admin1_code":"76",
    "gn:admin2_code":"11",
    "gn:admin3_code":"112",
    "gn:admin4_code":"11065",
    "gn:asciiname":"Camps-sur-l'Agly",
    "gn:country_code":"FR",
    "gn:dem":510,
    "gn:feature_class":"P",
    "gn:feature_code":"PPL",
    "gn:name":"Camps-sur-l\u2019Agly",
    "gn:population":0,
    "gn:timezone":"Europe/Paris",
    "iso:country":"FR",
    "name:und_x_variant":[
        "Camps",
        "Camps-sur-l\u2019Agly"
    ],
    "wof:name":"Camps-sur-l'Agly",
    "wof:placetype":"locality"
},
  "geometry": {"coordinates":[2.43242,42.8586],"type":"Point"}
}