{
  "type": "Feature",
  "properties": {
    "gn:admin1_code":"32",
    "gn:admin2_code":"62",
    "gn:admin3_code":"621",
    "gn:admin4_code":"62609",
    "gn:asciiname":"La Targette",
    "gn:country_code":"FR",
    "gn:dem":99,
    "gn:feature_class":"P",
    "gn:feature_code":"PPL",
    "gn:name":"La Targette",
    "gn:population":0,
    "gn:timezone":"Europe/Paris",
    "iso:country":"FR",
    "wof:name":"La Targette",
    "wof:placetype":"locality"
},
  "geometry": {"coordinates":[2.75013,50.3549],"type":"Point"}
}