{
  "type": "Feature",
  "properties": {
    "gn:admin1_code":"84",
    "gn:admin2_code":"03",
    "gn:admin3_code":"032",
    "gn:admin4_code":"03169",
    "gn:asciiname":"Haute Brenne",
    "gn:country_code":"FR",
    "gn:dem":349,
    "gn:feature_class":"P",
    "gn:feature_code":"PPL",
    "gn:name":"Haute Brenne",
    "gn:population":0,
    "gn:timezone":"Europe/Paris",
    "iso:country":"FR",
    "wof:name":"Haute Brenne",
    "wof:placetype":"locality"
},
  "geometry": {"coordinates":[3.23114,46.40372],"type":"Point"}
}