{
  "type": "Feature",
  "properties": {
    "gn:admin1_code":"75",
    "gn:admin2_code":"19",
    "gn:admin3_code":"191",
    "gn:admin4_code":"19026",
    "gn:asciiname":"Les Botties",
    "gn:country_code":"FR",
    "gn:dem":244,
    "gn:feature_class":"P",
    "gn:feature_code":"PPL",
    "gn:name":"Les Botties",
    "gn:population":0,
    "gn:timezone":"Europe/Paris",
    "iso:country":"FR",
    "name:und_x_variant":[
        "Les Bothies",
        "Les Botties"
    ],
    "wof:name":"Les Botties",
    "wof:placetype":"locality"
},
  "geometry": {"coordinates":[1.79374,44.94902],"type":"Point"}
}