{
  "type": "Feature",
  "properties": {
    "gn:admin1_code":"84",
    "gn:admin2_code":"73",
    "gn:admin3_code":"732",
    "gn:admin4_code":"73270.0",
    "gn:asciiname":"Les Allues",
    "gn:country_code":"FR",
    "gn:dem":404,
    "gn:feature_class":"P",
    "gn:feature_code":"PPL",
    "gn:name":"Les Allues",
    "gn:population":0,
    "gn:timezone":"Europe/Paris",
    "iso:country":"FR",
    "name:cat_x_preferred":[
        "Les Allues"
    ],
    "name:ceb_x_preferred":[
        "Les Allues"
    ],
    "name:ces_x_preferred":[
        "Les Allues"
    ],
    "name:deu_x_preferred":[
        "Les Allues"
    ],
    "name:eus_x_preferred":[
        "Les Allues"
    ],
    "name:fra_x_preferred":[
        "Les Allues"
    ],
    "name:hun_x_preferred":[
        "Les Allues"
    ],
    "name:ita_x_preferred":[
        "Les Allues"
    ],
    "name:lat_x_preferred":[
        "Allodia"
    ],
    "name:lmo_x_preferred":[
        "Les Allues"
    ],
    "name:msa_x_preferred":[
        "Les Allues"
    ],
    "name:nld_x_preferred":[
        "Les Allues"
    ],
    "name:oci_x_preferred":[
        "Les Allues"
    ],
    "name:pol_x_preferred":[
        "Les Allues"
    ],
    "name:por_x_preferred":[
        "Les Allues"
    ],
    "name:ron_x_preferred":[
        "Les Allues"
    ],
    "name:slk_x_preferred":[
        "Les Allues"
    ],
    "name:spa_x_preferred":[
        "Les Allues"
    ],
    "name:srp_x_preferred":[
        "\u0410\u043b\u0438"
    ],
    "name:swe_x_preferred":[
        "Les Allues"
    ],
    "name:ukr_x_preferred":[
        "\u041b\u0435\u0437-\u0410\u043b\u043b\u044e"
    ],
    "name:uzb_x_preferred":[
        "Les Allues"
    ],
    "name:vie_x_preferred":[
        "Les Allues"
    ],
    "name:vol_x_preferred":[
        "Les Allues"
    ],
    "name:war_x_preferred":[
        "Les Allues"
    ],
    "wof:name":"Les Allues",
    "wof:placetype":"locality"
},
  "geometry": {"coordinates":[6.14406,45.56989],"type":"Point"}
}