{
  "type": "Feature",
  "properties": {
    "gn:admin1_code":"84",
    "gn:admin2_code":"73",
    "gn:admin3_code":"732",
    "gn:admin4_code":"73270.0",
    "gn:asciiname":"Les Allues",
    "gn:country_code":"FR",
    "gn:dem":404,
    "gn:feature_class":"P",
    "gn:feature_code":"PPL",
    "gn:name":"Les Allues",
    "gn:population":0,
    "gn:timezone":"Europe/Paris",
    "iso:country":"FR",
    "wof:name":"Les Allues",
    "wof:placetype":"locality"
},
  "geometry": {"coordinates":[6.14406,45.56989],"type":"Point"}
}