{
  "type": "Feature",
  "properties": {
    "gn:admin1_code":"84",
    "gn:admin2_code":"03",
    "gn:admin3_code":"031",
    "gn:admin4_code":"03191",
    "gn:asciiname":"Les Chez",
    "gn:country_code":"FR",
    "gn:dem":303,
    "gn:feature_class":"P",
    "gn:feature_code":"PPL",
    "gn:name":"Les Chez",
    "gn:population":0,
    "gn:timezone":"Europe/Paris",
    "iso:country":"FR",
    "wof:name":"Les Chez",
    "wof:placetype":"locality"
},
  "geometry": {"coordinates":[2.90219,46.41695],"type":"Point"}
}