{
  "type": "Feature",
  "properties": {
    "gn:admin1_code":"28",
    "gn:admin2_code":"14",
    "gn:admin3_code":"141",
    "gn:admin4_code":"14614",
    "gn:asciiname":"Baynes",
    "gn:country_code":"FR",
    "gn:dem":61,
    "gn:feature_class":"P",
    "gn:feature_code":"PPL",
    "gn:name":"Baynes",
    "gn:population":0,
    "gn:timezone":"Europe/Paris",
    "iso:country":"FR",
    "name:deu_x_preferred":[
        "Baynes"
    ],
    "name:fra_x_preferred":[
        "Baynes"
    ],
    "name:heb_x_preferred":[
        "\u05d1\u05d9\u05d9\u05e0\u05e1"
    ],
    "name:pol_x_preferred":[
        "Baynes"
    ],
    "name:swe_x_preferred":[
        "Baynes"
    ],
    "wof:name":"Baynes",
    "wof:placetype":"locality"
},
  "geometry": {"coordinates":[-0.96667,49.21667],"type":"Point"}
}