{
  "type": "Feature",
  "properties": {
    "gn:admin1_code":"84",
    "gn:admin2_code":"07",
    "gn:admin3_code":"073",
    "gn:admin4_code":"07236",
    "gn:asciiname":"Le Bosset",
    "gn:country_code":"FR",
    "gn:dem":610,
    "gn:feature_class":"P",
    "gn:feature_code":"PPL",
    "gn:name":"Le Bosset",
    "gn:population":0,
    "gn:timezone":"Europe/Paris",
    "iso:country":"FR",
    "wof:name":"Le Bosset",
    "wof:placetype":"locality"
},
  "geometry": {"coordinates":[4.60678,45.07138],"type":"Point"}
}