{
  "type": "Feature",
  "properties": {
    "gn:admin1_code":"27",
    "gn:admin2_code":"89",
    "gn:admin3_code":"891",
    "gn:admin4_code":"89408",
    "gn:asciiname":"Les Cottets",
    "gn:country_code":"FR",
    "gn:dem":201,
    "gn:feature_class":"P",
    "gn:feature_code":"PPL",
    "gn:name":"Les Cottets",
    "gn:population":0,
    "gn:timezone":"Europe/Paris",
    "iso:country":"FR",
    "wof:name":"Les Cottets",
    "wof:placetype":"locality"
},
  "geometry": {"coordinates":[3.12186,47.75544],"type":"Point"}
}