{
  "type": "Feature",
  "properties": {
    "gn:admin1_code":"93",
    "gn:admin2_code":"05",
    "gn:admin3_code":"052",
    "gn:admin4_code":"05146",
    "gn:asciiname":"Beaumugne",
    "gn:country_code":"FR",
    "gn:dem":1024,
    "gn:feature_class":"P",
    "gn:feature_code":"PPL",
    "gn:name":"Beaumugne",
    "gn:population":0,
    "gn:timezone":"Europe/Paris",
    "iso:country":"FR",
    "wof:name":"Beaumugne",
    "wof:placetype":"locality"
},
  "geometry": {"coordinates":[5.72365,44.60336],"type":"Point"}
}