{
  "type": "Feature",
  "properties": {
    "gn:admin1_code":"27",
    "gn:admin2_code":"89",
    "gn:admin3_code":"893",
    "gn:admin4_code":"89298",
    "gn:asciiname":"Les Chevres",
    "gn:country_code":"FR",
    "gn:dem":190,
    "gn:feature_class":"P",
    "gn:feature_code":"PPL",
    "gn:name":"Les Ch\u00e8vres",
    "gn:population":0,
    "gn:timezone":"Europe/Paris",
    "iso:country":"FR",
    "wof:name":"Les Chevres",
    "wof:placetype":"locality"
},
  "geometry": {"coordinates":[3.12289,48.07304],"type":"Point"}
}