{
  "type": "Feature",
  "properties": {
    "gn:admin1_code":"76",
    "gn:admin2_code":"48",
    "gn:admin3_code":"482",
    "gn:admin4_code":"48091",
    "gn:asciiname":"Rieutort",
    "gn:country_code":"FR",
    "gn:dem":1190,
    "gn:feature_class":"P",
    "gn:feature_code":"PPL",
    "gn:name":"Rieutort",
    "gn:population":0,
    "gn:timezone":"Europe/Paris",
    "iso:country":"FR",
    "name:und_x_variant":[
        "Rieutort-d\u2019Aubrac",
        "Rieutort"
    ],
    "wof:name":"Rieutort",
    "wof:placetype":"locality"
},
  "geometry": {"coordinates":[3.10394,44.66945],"type":"Point"}
}