{
  "type": "Feature",
  "properties": {
    "gn:admin1_code":"52",
    "gn:admin2_code":"44",
    "gn:admin3_code":"443",
    "gn:admin4_code":"44089",
    "gn:asciiname":"Boistuaud",
    "gn:country_code":"FR",
    "gn:dem":82,
    "gn:feature_class":"P",
    "gn:feature_code":"PPL",
    "gn:name":"Boistuaud",
    "gn:population":0,
    "gn:timezone":"Europe/Paris",
    "iso:country":"FR",
    "name:und_x_variant":[
        "Boisthuaud",
        "Boistuaud"
    ],
    "wof:name":"Boistuaud",
    "wof:placetype":"locality"
},
  "geometry": {"coordinates":[-1.86845,47.33916],"type":"Point"}
}