{
  "type": "Feature",
  "properties": {
    "gn:admin1_code":"11",
    "gn:admin2_code":"91",
    "gn:admin3_code":"913",
    "gn:admin4_code":"91319",
    "gn:asciiname":"La Brosse",
    "gn:country_code":"FR",
    "gn:dem":153,
    "gn:feature_class":"P",
    "gn:feature_code":"PPL",
    "gn:name":"La Brosse",
    "gn:population":0,
    "gn:timezone":"Europe/Paris",
    "iso:country":"FR",
    "name:deu_x_preferred":[
        "La Brosse"
    ],
    "name:fra_x_preferred":[
        "La Brosse"
    ],
    "wof:name":"La Brosse",
    "wof:placetype":"locality"
},
  "geometry": {"coordinates":[2.14233,48.66051],"type":"Point"}
}