{
  "type": "Feature",
  "properties": {
    "gn:admin1_code":"84",
    "gn:admin2_code":"73",
    "gn:admin3_code":"733",
    "gn:admin4_code":"73278",
    "gn:asciiname":"Le Replat",
    "gn:country_code":"FR",
    "gn:dem":982,
    "gn:feature_class":"P",
    "gn:feature_code":"PPL",
    "gn:name":"Le Replat",
    "gn:population":0,
    "gn:timezone":"Europe/Paris",
    "iso:country":"FR",
    "wof:name":"Le Replat",
    "wof:placetype":"locality"
},
  "geometry": {"coordinates":[6.2607,45.37221],"type":"Point"}
}