{
  "type": "Feature",
  "properties": {
    "gn:admin1_code":"93",
    "gn:admin2_code":"05",
    "gn:admin3_code":"052",
    "gn:admin4_code":"05139",
    "gn:asciiname":"Truchieres",
    "gn:country_code":"FR",
    "gn:dem":1229,
    "gn:feature_class":"P",
    "gn:feature_code":"PPL",
    "gn:name":"Truchi\u00e8res",
    "gn:population":0,
    "gn:timezone":"Europe/Paris",
    "iso:country":"FR",
    "wof:name":"Truchieres",
    "wof:placetype":"locality"
},
  "geometry": {"coordinates":[5.88865,44.72589],"type":"Point"}
}