{
  "type": "Feature",
  "properties": {
    "iso:country":"FR",
    "name:eng_x_preferred":[
        "Gabriel Peri-Estiennes d'Orves"
    ],
    "name:fra_x_preferred":[
        "Gabriel P\u00e9ri-Estiennes d'Orves"
    ],
    "wof:name":"Gabriel Peri-Estiennes d'Orves",
    "wof:placetype":"neighbourhood"
},
  "geometry": {"coordinates":[2.23919944150345,48.91561883091931],"type":"Point"}
}