{
  "type": "Feature",
  "properties": {
    "gn:admin1_code":"27",
    "gn:admin2_code":"89",
    "gn:admin3_code":"893",
    "gn:admin4_code":"89120.0",
    "gn:asciiname":"Ville Froide",
    "gn:country_code":"FR",
    "gn:dem":234,
    "gn:feature_class":"P",
    "gn:feature_code":"PPL",
    "gn:name":"Ville Froide",
    "gn:population":0,
    "gn:timezone":"Europe/Paris",
    "iso:country":"FR",
    "wof:name":"Ville Froide",
    "wof:placetype":"locality"
},
  "geometry": {"coordinates":[3.60289,48.14102000000001],"type":"Point"}
}