{
  "type": "Feature",
  "properties": {
    "gn:admin1_code":"28",
    "gn:admin2_code":"27",
    "gn:admin3_code":"273",
    "gn:admin4_code":"27114",
    "gn:asciiname":"Saint-Cheron",
    "gn:country_code":"FR",
    "gn:dem":123,
    "gn:feature_class":"P",
    "gn:feature_code":"PPL",
    "gn:name":"Saint-Ch\u00e9ron",
    "gn:population":0,
    "gn:timezone":"Europe/Paris",
    "iso:country":"FR",
    "wof:name":"Saint-Cheron",
    "wof:placetype":"locality"
},
  "geometry": {"coordinates":[1.4554,48.97027],"type":"Point"}
}