{
  "type": "Feature",
  "properties": {
    "gn:admin1_code":"75",
    "gn:admin2_code":"23",
    "gn:admin3_code":"231",
    "gn:admin4_code":"23125",
    "gn:asciiname":"Louzelergue",
    "gn:cc2":"FR",
    "gn:country_code":"FR",
    "gn:dem":780,
    "gn:feature_class":"P",
    "gn:feature_code":"PPL",
    "gn:name":"Louzelergue",
    "gn:population":0,
    "gn:timezone":"Europe/Paris",
    "iso:country":"FR",
    "name:und_x_variant":[
        "Louzelerge",
        "Louzelergue"
    ],
    "wof:name":"Louzelergue",
    "wof:placetype":"locality"
},
  "geometry": {"coordinates":[2.18333,45.75],"type":"Point"}
}