{
  "type": "Feature",
  "properties": {
    "gn:admin1_code":"24",
    "gn:admin2_code":"36",
    "gn:admin3_code":"363",
    "gn:admin4_code":"36156",
    "gn:asciiname":"Chez Comb",
    "gn:country_code":"FR",
    "gn:dem":362,
    "gn:feature_class":"P",
    "gn:feature_code":"PPL",
    "gn:name":"Chez Comb",
    "gn:population":0,
    "gn:timezone":"Europe/Paris",
    "iso:country":"FR",
    "wof:name":"Chez Comb",
    "wof:placetype":"locality"
},
  "geometry": {"coordinates":[2.13408,46.46572000000001],"type":"Point"}
}