{
  "type": "Feature",
  "properties": {
    "gn:admin1_code":"28",
    "gn:admin2_code":"76",
    "gn:admin3_code":"761",
    "gn:admin4_code":"76261.0",
    "gn:asciiname":"La Ferte-Saint-Samson",
    "gn:country_code":"FR",
    "gn:dem":188,
    "gn:feature_class":"P",
    "gn:feature_code":"PPL",
    "gn:name":"La Fert\u00e9-Saint-Samson",
    "gn:population":0,
    "gn:timezone":"Europe/Paris",
    "iso:country":"FR",
    "name:und_x_variant":[
        "La Fert\u00e9",
        "La Fert\u00e9-Saint-Samson"
    ],
    "wof:name":"La Ferte-Saint-Samson",
    "wof:placetype":"locality"
},
  "geometry": {"coordinates":[1.52423,49.5777],"type":"Point"}
}