{
  "type": "Feature",
  "properties": {
    "frgov:code_epci":"200069730",
    "frgov:insee_arr":"1",
    "frgov:insee_com":"76261",
    "frgov:insee_dep":"76",
    "frgov:insee_reg":"28",
    "frgov:nom_com":"La Fert\u00e9-Saint-Samson",
    "frgov:nom_com_m":"LA FERTE-SAINT-SAMSON",
    "frgov:nom_dep":"SEINE-MARITIME",
    "frgov:nom_reg":"NORMANDIE",
    "frgov:statut":"Commune simple",
    "gn:admin1_code":"28",
    "gn:admin2_code":"76",
    "gn:admin3_code":"761",
    "gn:admin4_code":"76261.0",
    "gn:asciiname":"La Ferte-Saint-Samson",
    "gn:country_code":"FR",
    "gn:dem":188,
    "gn:feature_class":"P",
    "gn:feature_code":"PPL",
    "gn:name":"La Fert\u00e9-Saint-Samson",
    "gn:population":0,
    "gn:timezone":"Europe/Paris",
    "iso:country":"FR",
    "name:fra_x_preferred":[
        "La Fert\u00e9-Saint-Samson"
    ],
    "name:und_x_variant":[
        "La Fert\u00e9",
        "La Fert\u00e9-Saint-Samson"
    ],
    "qs:a0":"France",
    "qs:a1":"SEINE-MARITIME",
    "qs:a1_lc":"76",
    "qs:a1r":"HAUTE-NORMANDIE",
    "qs:a1r_lc":"23",
    "qs:a2_lc":"23",
    "qs:a2r_lc":"1",
    "qs:adm0":"France",
    "qs:adm0_a3":"FRA",
    "qs:la":"LA FERTE-SAINT-SAMSON",
    "qs:la_lc":"76261",
    "qs:level":"localadmin",
    "qs:type":"Commune simple",
    "wof:coterminous":[
        404397061
    ],
    "wof:name":"La Ferte-Saint-Samson",
    "wof:placetype":"locality",
    "wof:placetype_local":"Commune simple"
},
  "geometry": {"coordinates":[1.52423,49.5777],"type":"Point"}
}