{
  "type": "Feature",
  "properties": {
    "gn:admin1_code":"84",
    "gn:admin2_code":"03",
    "gn:admin3_code":"031",
    "gn:admin4_code":"03107",
    "gn:asciiname":"Champ-Boirat",
    "gn:country_code":"FR",
    "gn:dem":310,
    "gn:feature_class":"P",
    "gn:feature_code":"PPL",
    "gn:name":"Champ-Boirat",
    "gn:population":0,
    "gn:timezone":"Europe/Paris",
    "iso:country":"FR",
    "wof:name":"Champ-Boirat",
    "wof:placetype":"locality"
},
  "geometry": {"coordinates":[3.10817,46.11478],"type":"Point"}
}