{
  "type": "Feature",
  "properties": {
    "gn:admin1_code":"84",
    "gn:admin2_code":"43",
    "gn:admin3_code":"433",
    "gn:admin4_code":"43028",
    "gn:asciiname":"Messinhac",
    "gn:country_code":"FR",
    "gn:dem":884,
    "gn:feature_class":"P",
    "gn:feature_code":"PPL",
    "gn:name":"Messinhac",
    "gn:population":0,
    "gn:timezone":"Europe/Paris",
    "iso:country":"FR",
    "wof:name":"Messinhac",
    "wof:placetype":"locality"
},
  "geometry": {"coordinates":[4.07365,45.14121],"type":"Point"}
}