{
  "type": "Feature",
  "properties": {
    "gn:admin1_code":"44",
    "gn:admin2_code":"10",
    "gn:admin3_code":"103",
    "gn:admin4_code":"10248",
    "gn:asciiname":"La Grange-au-Rez",
    "gn:country_code":"FR",
    "gn:dem":175,
    "gn:feature_class":"P",
    "gn:feature_code":"PPL",
    "gn:name":"La Grange-au-Rez",
    "gn:population":0,
    "gn:timezone":"Europe/Paris",
    "iso:country":"FR",
    "name:und_x_variant":[
        "Grange-au-Rez",
        "La Grange",
        "La Grange-au-Rez"
    ],
    "wof:name":"La Grange-au-Rez",
    "wof:placetype":"locality"
},
  "geometry": {"coordinates":[3.93228,48.28289],"type":"Point"}
}