{
  "type": "Feature",
  "properties": {
    "gn:admin1_code":"32",
    "gn:admin2_code":"80",
    "gn:admin3_code":"804",
    "gn:admin4_code":"80620",
    "gn:asciiname":"Sainte-Radegonde",
    "gn:country_code":"FR",
    "gn:dem":52,
    "gn:feature_class":"P",
    "gn:feature_code":"PPL",
    "gn:name":"Sainte-Radegonde",
    "gn:population":0,
    "gn:timezone":"Europe/Paris",
    "iso:country":"FR",
    "wof:name":"Sainte-Radegonde",
    "wof:placetype":"locality"
},
  "geometry": {"coordinates":[2.92074,49.92658],"type":"Point"}
}