{
  "type": "Feature",
  "properties": {
    "gn:admin1_code":"32",
    "gn:admin2_code":"80",
    "gn:admin3_code":"804",
    "gn:admin4_code":"80620",
    "gn:asciiname":"Sainte-Radegonde",
    "gn:country_code":"FR",
    "gn:dem":52,
    "gn:feature_class":"P",
    "gn:feature_code":"PPL",
    "gn:name":"Sainte-Radegonde",
    "gn:population":0,
    "gn:timezone":"Europe/Paris",
    "iso:country":"FR",
    "name:ceb_x_preferred":[
        "Sainte-Radegonde"
    ],
    "name:deu_x_preferred":[
        "Sainte-Radegonde"
    ],
    "name:fra_x_preferred":[
        "Sainte-Radegonde"
    ],
    "name:ita_x_preferred":[
        "Sainte-Radegonde"
    ],
    "name:jpn_x_preferred":[
        "\u30b5\u30f3\u30c8\uff1d\u30e9\u30c7\u30b4\u30f3\u30c9"
    ],
    "name:nds_x_preferred":[
        "Sainte-Radegonde"
    ],
    "name:nld_x_preferred":[
        "Sainte-Radegonde"
    ],
    "name:nor_x_preferred":[
        "Sainte-Radegonde"
    ],
    "name:oci_x_preferred":[
        "Senta Radegonda"
    ],
    "name:pms_x_preferred":[
        "Sainte-Radegonde"
    ],
    "name:pol_x_preferred":[
        "Sainte-Radegonde"
    ],
    "name:por_x_preferred":[
        "Sainte-Radegonde"
    ],
    "name:rus_x_preferred":[
        "\u0421\u0435\u043d\u0442-\u0420\u0430\u0434\u0435\u0433\u043e\u043d\u0434"
    ],
    "name:slk_x_preferred":[
        "Sainte-Radegonde"
    ],
    "name:spa_x_preferred":[
        "Sainte-Radegonde"
    ],
    "name:swe_x_preferred":[
        "Sainte-Radegonde"
    ],
    "name:ukr_x_preferred":[
        "\u0421\u0435\u043d\u0442-\u0420\u0430\u0434\u0435\u0433\u043e\u043d\u0434"
    ],
    "wof:name":"Sainte-Radegonde",
    "wof:placetype":"locality"
},
  "geometry": {"coordinates":[2.92074,49.92658],"type":"Point"}
}