{
  "type": "Feature",
  "properties": {
    "gn:admin1_code":"11",
    "gn:admin2_code":"77",
    "gn:admin3_code":"773",
    "gn:admin4_code":"77409",
    "gn:asciiname":"Gardeloup",
    "gn:country_code":"FR",
    "gn:dem":118,
    "gn:feature_class":"P",
    "gn:feature_code":"PPL",
    "gn:name":"Gardeloup",
    "gn:population":0,
    "gn:timezone":"Europe/Paris",
    "iso:country":"FR",
    "wof:name":"Gardeloup",
    "wof:placetype":"locality"
},
  "geometry": {"coordinates":[2.98564,48.41634000000001],"type":"Point"}
}