{
  "type": "Feature",
  "properties": {
    "gn:gn_country":"FR",
    "gn:gn_fcode":"PPL",
    "gn:gn_pop":0,
    "iso:country":"FR",
    "name:baq_x_preferred":[
        "Gergovia"
    ],
    "name:bel_x_preferred":[
        "\u0413\u0435\u0440\u0433\u043e\u0432\u0456\u044f"
    ],
    "name:bre_x_preferred":[
        "Gergovia"
    ],
    "name:bul_x_preferred":[
        "\u0413\u0435\u0440\u0433\u043e\u0432\u0438\u044f"
    ],
    "name:cat_x_preferred":[
        "Gerg\u00f2via"
    ],
    "name:dut_x_preferred":[
        "Gergovia"
    ],
    "name:eng_x_preferred":[
        "Gergovie"
    ],
    "name:est_x_preferred":[
        "Gergovia"
    ],
    "name:fre_x_preferred":[
        "Gergovie"
    ],
    "name:ger_x_preferred":[
        "Gergovia"
    ],
    "name:ita_x_preferred":[
        "Gergovia"
    ],
    "name:lat_x_preferred":[
        "Gergovia"
    ],
    "name:lit_x_preferred":[
        "Gergovija"
    ],
    "name:pol_x_preferred":[
        "Gergovie"
    ],
    "name:rus_x_preferred":[
        "\u0413\u0435\u0440\u0433\u043e\u0432\u0438\u044f"
    ],
    "name:spa_x_preferred":[
        "Gergovia"
    ],
    "name:swe_x_preferred":[
        "Gergovia"
    ],
    "name:tur_x_preferred":[
        "Gergovia"
    ],
    "name:unk_x_variant":[
        "Merdogne"
    ],
    "qs_pg:aaroncc":"FR",
    "qs_pg:gn_country":"FR",
    "qs_pg:gn_fcode":"PPL",
    "qs_pg:gn_pop":0,
    "qs_pg:name":"Gergovie",
    "qs_pg:name_adm0":"France",
    "qs_pg:name_adm1":"Auvergne",
    "qs_pg:photos":340,
    "qs_pg:photos_1k":69,
    "qs_pg:photos_9k":2,
    "qs_pg:photos_9r":5,
    "qs_pg:photos_all":340,
    "qs_pg:photos_sr":5,
    "qs_pg:pop_sr":0,
    "qs_pg:qs_pg_placetype":"locality",
    "qs_pg:qs_pg_placetype_gp":"Town",
    "qs_pg:woe_adm0":23424819,
    "woe:adm0_id":23424819,
    "woe:name_adm0":"France",
    "woe:name_adm1":"Auvergne",
    "woe:placetype":"Town",
    "wof:name":"Gergovie",
    "wof:placetype":"neighbourhood"
},
  "geometry": {"coordinates":[3.12582,45.71113],"type":"Point"}
}