{
  "type": "Feature",
  "properties": {
    "gn:admin1_code":"75",
    "gn:admin2_code":"87",
    "gn:admin3_code":"872",
    "gn:admin4_code":"87042",
    "gn:asciiname":"Montfayon",
    "gn:country_code":"FR",
    "gn:dem":385,
    "gn:feature_class":"P",
    "gn:feature_code":"PPL",
    "gn:name":"Montfayon",
    "gn:population":0,
    "gn:timezone":"Europe/Paris",
    "iso:country":"FR",
    "wof:name":"Montfayon",
    "wof:placetype":"locality"
},
  "geometry": {"coordinates":[1.49837,45.89054],"type":"Point"}
}