{
  "type": "Feature",
  "properties": {
    "frgov:code_epci":"247100290",
    "frgov:insee_arr":"2",
    "frgov:insee_com":"71278",
    "frgov:insee_dep":"71",
    "frgov:insee_reg":"27",
    "frgov:nom_com":"Marigny",
    "frgov:nom_com_m":"MARIGNY",
    "frgov:nom_dep":"SAONE-ET-LOIRE",
    "frgov:nom_reg":"BOURGOGNE-FRANCHE-COMTE",
    "frgov:statut":"Commune simple",
    "gn:admin1_code":"27",
    "gn:admin2_code":"71",
    "gn:admin3_code":"712",
    "gn:admin4_code":"71278",
    "gn:asciiname":"Marigny",
    "gn:country_code":"FR",
    "gn:dem":342,
    "gn:feature_class":"P",
    "gn:feature_code":"PPL",
    "gn:name":"Marigny",
    "gn:population":122,
    "gn:timezone":"Europe/Paris",
    "iso:country":"FR",
    "name:bre_x_preferred":[
        "Marigny"
    ],
    "name:ceb_x_preferred":[
        "Marigny"
    ],
    "name:ces_x_preferred":[
        "Marigny"
    ],
    "name:deu_x_preferred":[
        "Marigny"
    ],
    "name:fra_x_preferred":[
        "Marigny"
    ],
    "name:ita_x_preferred":[
        "Marigny"
    ],
    "name:jpn_x_preferred":[
        "\u30de\u30ea\u30cb\u30fc"
    ],
    "name:kaz_x_preferred":[
        "\u041c\u0430\u0440\u0438\u043d\u044c\u0438"
    ],
    "name:nds_x_preferred":[
        "Marigny"
    ],
    "name:nld_x_preferred":[
        "Marigny"
    ],
    "name:pms_x_preferred":[
        "Marigny"
    ],
    "name:pol_x_preferred":[
        "Marigny"
    ],
    "name:por_x_preferred":[
        "Marigny"
    ],
    "name:rus_x_preferred":[
        "\u041c\u0430\u0440\u0438\u043d\u044c\u0438"
    ],
    "name:slk_x_preferred":[
        "Marigny"
    ],
    "name:spa_x_preferred":[
        "Marigny"
    ],
    "name:sqi_x_preferred":[
        "Marigny"
    ],
    "name:swe_x_preferred":[
        "Marigny"
    ],
    "name:ukr_x_preferred":[
        "\u041c\u0430\u0440\u0438\u043d\u044c\u0457"
    ],
    "qs:a0":"France",
    "qs:a1":"SAONE-ET-LOIRE",
    "qs:a1_lc":"71",
    "qs:a1r":"BOURGOGNE",
    "qs:a1r_lc":"26",
    "qs:a2_lc":"36",
    "qs:a2r_lc":"2",
    "qs:adm0":"France",
    "qs:adm0_a3":"FRA",
    "qs:la":"MARIGNY",
    "qs:la_lc":"71278",
    "qs:level":"localadmin",
    "qs:type":"Commune simple",
    "wof:coterminous":[
        404354537
    ],
    "wof:name":"Marigny",
    "wof:placetype":"locality",
    "wof:placetype_local":"Commune simple",
    "wof:population":122
},
  "geometry": {"coordinates":[4.45893,46.67905],"type":"Point"}
}