{
  "type": "Feature",
  "properties": {
    "gn:admin1_code":"27",
    "gn:admin2_code":"71",
    "gn:admin3_code":"712",
    "gn:admin4_code":"71278",
    "gn:asciiname":"Marigny",
    "gn:country_code":"FR",
    "gn:dem":342,
    "gn:feature_class":"P",
    "gn:feature_code":"PPL",
    "gn:name":"Marigny",
    "gn:population":122,
    "gn:timezone":"Europe/Paris",
    "iso:country":"FR",
    "name:bre_x_preferred":[
        "Marigny"
    ],
    "name:ceb_x_preferred":[
        "Marigny"
    ],
    "name:ces_x_preferred":[
        "Marigny"
    ],
    "name:deu_x_preferred":[
        "Marigny"
    ],
    "name:fra_x_preferred":[
        "Marigny"
    ],
    "name:ita_x_preferred":[
        "Marigny"
    ],
    "name:jpn_x_preferred":[
        "\u30de\u30ea\u30cb\u30fc"
    ],
    "name:nds_x_preferred":[
        "Marigny"
    ],
    "name:nld_x_preferred":[
        "Marigny"
    ],
    "name:pms_x_preferred":[
        "Marigny"
    ],
    "name:pol_x_preferred":[
        "Marigny"
    ],
    "name:por_x_preferred":[
        "Marigny"
    ],
    "name:rus_x_preferred":[
        "\u041c\u0430\u0440\u0438\u043d\u044c\u0438"
    ],
    "name:slk_x_preferred":[
        "Marigny"
    ],
    "name:spa_x_preferred":[
        "Marigny"
    ],
    "name:sqi_x_preferred":[
        "Marigny"
    ],
    "name:swe_x_preferred":[
        "Marigny"
    ],
    "name:ukr_x_preferred":[
        "\u041c\u0430\u0440\u0438\u043d\u044c\u0457"
    ],
    "wof:name":"Marigny",
    "wof:placetype":"locality",
    "wof:population":122
},
  "geometry": {"coordinates":[4.45893,46.67905],"type":"Point"}
}