{
  "type": "Feature",
  "properties": {
    "gn:admin1_code":"27",
    "gn:admin2_code":"71",
    "gn:admin3_code":"712",
    "gn:admin4_code":"71278",
    "gn:asciiname":"Marigny",
    "gn:country_code":"FR",
    "gn:dem":342,
    "gn:feature_class":"P",
    "gn:feature_code":"PPL",
    "gn:name":"Marigny",
    "gn:population":122,
    "gn:timezone":"Europe/Paris",
    "iso:country":"FR",
    "wof:name":"Marigny",
    "wof:placetype":"locality",
    "wof:population":122
},
  "geometry": {"coordinates":[4.45893,46.67905],"type":"Point"}
}