{
  "type": "Feature",
  "properties": {
    "gn:admin1_code":"27",
    "gn:admin2_code":"21",
    "gn:admin3_code":"212",
    "gn:admin4_code":"21076",
    "gn:asciiname":"Mitreuil",
    "gn:country_code":"FR",
    "gn:dem":195,
    "gn:feature_class":"P",
    "gn:feature_code":"PPL",
    "gn:name":"Mitreuil",
    "gn:population":0,
    "gn:timezone":"Europe/Paris",
    "iso:country":"FR",
    "wof:name":"Mitreuil",
    "wof:placetype":"locality"
},
  "geometry": {"coordinates":[5.29305,47.33324],"type":"Point"}
}