{
  "type": "Feature",
  "properties": {
    "gn:admin1_code":"93",
    "gn:admin2_code":"13",
    "gn:admin3_code":"132",
    "gn:admin4_code":"13108",
    "gn:asciiname":"Saint-Michel-de-Frigolet",
    "gn:country_code":"FR",
    "gn:dem":116,
    "gn:feature_class":"P",
    "gn:feature_code":"PPL",
    "gn:name":"Saint-Michel-de-Frigolet",
    "gn:population":0,
    "gn:timezone":"Europe/Paris",
    "iso:country":"FR",
    "name:deu_x_preferred":[
        "Saint-Michel-de-Frigolet"
    ],
    "name:rus_x_preferred":[
        "\u0424\u0440\u0438\u0433\u043e\u043b\u0435"
    ],
    "wof:name":"Saint-Michel-de-Frigolet",
    "wof:placetype":"locality"
},
  "geometry": {"coordinates":[4.72613,43.85916],"type":"Point"}
}