{
  "type": "Feature",
  "properties": {
    "gn:admin1_code":"75",
    "gn:admin2_code":"16",
    "gn:admin3_code":"163",
    "gn:admin4_code":"16336",
    "gn:asciiname":"Artenac",
    "gn:country_code":"FR",
    "gn:dem":94,
    "gn:feature_class":"P",
    "gn:feature_code":"PPL",
    "gn:name":"Artenac",
    "gn:population":0,
    "gn:timezone":"Europe/Paris",
    "iso:country":"FR",
    "wof:name":"Artenac",
    "wof:placetype":"locality"
},
  "geometry": {"coordinates":[0.33548,45.84033],"type":"Point"}
}