{
  "type": "Feature",
  "properties": {
    "gn:admin1_code":"75",
    "gn:admin2_code":"47",
    "gn:admin3_code":"473",
    "gn:admin4_code":"47175",
    "gn:asciiname":"Costes",
    "gn:country_code":"FR",
    "gn:dem":103,
    "gn:feature_class":"P",
    "gn:feature_code":"PPL",
    "gn:name":"Costes",
    "gn:population":0,
    "gn:timezone":"Europe/Paris",
    "iso:country":"FR",
    "name:cat_x_preferred":[
        "Costes"
    ],
    "name:deu_x_preferred":[
        "Costes"
    ],
    "name:fra_x_preferred":[
        "Costes"
    ],
    "wof:name":"Costes",
    "wof:placetype":"locality"
},
  "geometry": {"coordinates":[0.78123,44.50293],"type":"Point"}
}