{
  "type": "Feature",
  "properties": {
    "gn:admin1_code":"93",
    "gn:admin2_code":"05",
    "gn:admin3_code":"052",
    "gn:admin4_code":"05056",
    "gn:asciiname":"Manse",
    "gn:country_code":"FR",
    "gn:dem":1168,
    "gn:feature_class":"P",
    "gn:feature_code":"PPL",
    "gn:name":"Manse",
    "gn:population":0,
    "gn:timezone":"Europe/Paris",
    "iso:country":"FR",
    "name:ara_x_preferred":[
        "\u0645\u0646\u0632\u0644 \u0627\u0644\u0642\u0633"
    ],
    "name:dan_x_preferred":[
        "Pr\u00e6steg\u00e5rd"
    ],
    "name:deu_x_preferred":[
        "Evangelisches Pfarrhaus"
    ],
    "name:jpn_x_preferred":[
        "\u7267\u5e2b\u9928"
    ],
    "name:nno_x_preferred":[
        "Prestegard"
    ],
    "name:nor_x_preferred":[
        "Presteg\u00e5rd"
    ],
    "name:swe_x_preferred":[
        "Pr\u00e4stg\u00e5rd"
    ],
    "wof:name":"Manse",
    "wof:placetype":"locality"
},
  "geometry": {"coordinates":[6.13516,44.63356],"type":"Point"}
}