{
  "type": "Feature",
  "properties": {
    "gn:admin1_code":"93",
    "gn:admin2_code":"05",
    "gn:admin3_code":"052",
    "gn:admin4_code":"05056",
    "gn:asciiname":"Manse",
    "gn:country_code":"FR",
    "gn:dem":1168,
    "gn:feature_class":"P",
    "gn:feature_code":"PPL",
    "gn:name":"Manse",
    "gn:population":0,
    "gn:timezone":"Europe/Paris",
    "iso:country":"FR",
    "wof:name":"Manse",
    "wof:placetype":"locality"
},
  "geometry": {"coordinates":[6.13516,44.63356],"type":"Point"}
}