{
  "type": "Feature",
  "properties": {
    "gn:admin1_code":"27",
    "gn:admin2_code":"58",
    "gn:admin3_code":"582",
    "gn:admin4_code":"58242",
    "gn:asciiname":"Cervenon",
    "gn:country_code":"FR",
    "gn:dem":242,
    "gn:feature_class":"P",
    "gn:feature_code":"PPL",
    "gn:name":"Cervenon",
    "gn:population":0,
    "gn:timezone":"Europe/Paris",
    "iso:country":"FR",
    "wof:name":"Cervenon",
    "wof:placetype":"locality"
},
  "geometry": {"coordinates":[3.53,47.36024000000001],"type":"Point"}
}