{
  "type": "Feature",
  "properties": {
    "gn:admin1_code":"84",
    "gn:admin2_code":"43",
    "gn:admin3_code":"431",
    "gn:admin4_code":"43207",
    "gn:asciiname":"Entremont",
    "gn:country_code":"FR",
    "gn:dem":509,
    "gn:feature_class":"P",
    "gn:feature_code":"PPL",
    "gn:name":"Entremont",
    "gn:population":0,
    "gn:timezone":"Europe/Paris",
    "iso:country":"FR",
    "name:arg_x_preferred":[
        "Entremont"
    ],
    "name:deu_x_preferred":[
        "Entremont"
    ],
    "name:fra_x_preferred":[
        "Entremont"
    ],
    "name:ita_x_preferred":[
        "Entremont"
    ],
    "name:nld_x_preferred":[
        "Entremont"
    ],
    "name:swe_x_preferred":[
        "Entremont"
    ],
    "wof:name":"Entremont",
    "wof:placetype":"locality"
},
  "geometry": {"coordinates":[3.36612,45.27428],"type":"Point"}
}