{
  "type": "Feature",
  "properties": {
    "gn:admin1_code":"24",
    "gn:admin2_code":"36",
    "gn:admin3_code":"361",
    "gn:admin4_code":"36176",
    "gn:asciiname":"Anguyenne",
    "gn:country_code":"FR",
    "gn:dem":124,
    "gn:feature_class":"P",
    "gn:feature_code":"PPL",
    "gn:name":"Anguyenne",
    "gn:population":0,
    "gn:timezone":"Europe/Paris",
    "iso:country":"FR",
    "wof:name":"Anguyenne",
    "wof:placetype":"locality"
},
  "geometry": {"coordinates":[1.21024,46.6049],"type":"Point"}
}