{
  "type": "Feature",
  "properties": {
    "gn:admin1_code":"24",
    "gn:admin2_code":"37",
    "gn:admin3_code":"373",
    "gn:admin4_code":"37049",
    "gn:asciiname":"Cornille",
    "gn:country_code":"FR",
    "gn:dem":73,
    "gn:feature_class":"P",
    "gn:feature_code":"PPL",
    "gn:name":"Cornill\u00e9",
    "gn:population":0,
    "gn:timezone":"Europe/Paris",
    "iso:country":"FR",
    "name:bug_x_preferred":[
        "Cornille"
    ],
    "name:cat_x_preferred":[
        "Cornilha"
    ],
    "name:ceb_x_preferred":[
        "Cornille"
    ],
    "name:deu_x_preferred":[
        "Cornille"
    ],
    "name:eus_x_preferred":[
        "Cornille"
    ],
    "name:fin_x_preferred":[
        "Cornille"
    ],
    "name:fra_x_preferred":[
        "Cornille"
    ],
    "name:hun_x_preferred":[
        "Cornille"
    ],
    "name:ita_x_preferred":[
        "Cornille"
    ],
    "name:kaz_x_preferred":[
        "\u041a\u043e\u0440\u043d\u0438\u0439"
    ],
    "name:lat_x_preferred":[
        "Cornille"
    ],
    "name:mlg_x_preferred":[
        "Cornille"
    ],
    "name:msa_x_preferred":[
        "Cornille"
    ],
    "name:nld_x_preferred":[
        "Cornille"
    ],
    "name:oci_x_preferred":[
        "Cornilha"
    ],
    "name:pms_x_preferred":[
        "Cornille"
    ],
    "name:pol_x_preferred":[
        "Cornille"
    ],
    "name:por_x_preferred":[
        "Cornille"
    ],
    "name:ron_x_preferred":[
        "Cornille"
    ],
    "name:slk_x_preferred":[
        "Cornille"
    ],
    "name:spa_x_preferred":[
        "Cornille"
    ],
    "name:srp_x_preferred":[
        "\u041a\u043e\u0440\u043d\u0438\u0458"
    ],
    "name:swe_x_preferred":[
        "Cornille"
    ],
    "name:ukr_x_preferred":[
        "\u041a\u043e\u0440\u043d\u0456\u0439"
    ],
    "name:uzb_x_preferred":[
        "Cornille"
    ],
    "name:vie_x_preferred":[
        "Cornille"
    ],
    "name:vol_x_preferred":[
        "Cornille"
    ],
    "name:war_x_preferred":[
        "Cornille"
    ],
    "name:zho_x_preferred":[
        "\u79d1\u5c14\u5c3c\u5c14"
    ],
    "wof:name":"Cornille",
    "wof:placetype":"locality"
},
  "geometry": {"coordinates":[0.99485,47.15796],"type":"Point"}
}