{
  "type": "Feature",
  "properties": {
    "gn:admin1_code":"28",
    "gn:admin2_code":"76",
    "gn:admin3_code":"763",
    "gn:admin4_code":"76513",
    "gn:asciiname":"Belaitre",
    "gn:country_code":"FR",
    "gn:dem":6,
    "gn:feature_class":"P",
    "gn:feature_code":"PPL",
    "gn:name":"Belaitre",
    "gn:population":0,
    "gn:timezone":"Europe/Paris",
    "iso:country":"FR",
    "wof:name":"Belaitre",
    "wof:placetype":"locality"
},
  "geometry": {"coordinates":[0.95431,49.42531],"type":"Point"}
}