{
  "type": "Feature",
  "properties": {
    "gn:admin1_code":"75",
    "gn:admin2_code":"23",
    "gn:admin3_code":"232",
    "gn:admin4_code":"23062",
    "gn:asciiname":"Here",
    "gn:country_code":"FR",
    "gn:dem":338,
    "gn:feature_class":"P",
    "gn:feature_code":"PPL",
    "gn:name":"H\u00e9r\u00e9",
    "gn:population":0,
    "gn:timezone":"Europe/Paris",
    "iso:country":"FR",
    "name:deu_x_preferred":[
        "Here"
    ],
    "name:fra_x_preferred":[
        "Here"
    ],
    "name:hun_x_preferred":[
        "Here"
    ],
    "name:ita_x_preferred":[
        "Here"
    ],
    "name:jpn_x_preferred":[
        "Here"
    ],
    "name:nld_x_preferred":[
        "Here"
    ],
    "name:rus_x_preferred":[
        "\u0417\u0434\u0435\u0441\u044c"
    ],
    "name:slk_x_preferred":[
        "Here"
    ],
    "name:war_x_preferred":[
        "Nganhi"
    ],
    "name:zho_x_preferred":[
        "Here"
    ],
    "wof:name":"Here",
    "wof:placetype":"locality"
},
  "geometry": {"coordinates":[1.85,46.33333],"type":"Point"}
}