{
  "type": "Feature",
  "properties": {
    "gn:admin1_code":"24",
    "gn:admin2_code":"36",
    "gn:admin3_code":"362",
    "gn:admin4_code":"36031",
    "gn:asciiname":"Grand Chaventon",
    "gn:country_code":"FR",
    "gn:dem":140,
    "gn:feature_class":"P",
    "gn:feature_code":"PPL",
    "gn:name":"Grand Chaventon",
    "gn:population":0,
    "gn:timezone":"Europe/Paris",
    "iso:country":"FR",
    "wof:name":"Grand Chaventon",
    "wof:placetype":"locality"
},
  "geometry": {"coordinates":[1.40402,46.84963],"type":"Point"}
}