{
  "type": "Feature",
  "properties": {
    "gn:admin1_code":"24",
    "gn:admin2_code":"45",
    "gn:admin3_code":"451",
    "gn:admin4_code":"45087",
    "gn:asciiname":"Les Menigault",
    "gn:country_code":"FR",
    "gn:dem":199,
    "gn:feature_class":"P",
    "gn:feature_code":"PPL",
    "gn:name":"Les M\u00e9nigault",
    "gn:population":0,
    "gn:timezone":"Europe/Paris",
    "iso:country":"FR",
    "name:und_x_variant":[
        "Les M\u00e9nigaults",
        "Les M\u00e9nigault"
    ],
    "wof:name":"Les Menigault",
    "wof:placetype":"locality"
},
  "geometry": {"coordinates":[2.71886,47.55542],"type":"Point"}
}