{
  "type": "Feature",
  "properties": {
    "gn:admin1_code":"32",
    "gn:admin2_code":"59",
    "gn:admin3_code":"591",
    "gn:admin4_code":"59225.0",
    "gn:asciiname":"Les Bas Vents",
    "gn:country_code":"FR",
    "gn:dem":157,
    "gn:feature_class":"P",
    "gn:feature_code":"PPL",
    "gn:name":"Les Bas Vents",
    "gn:population":0,
    "gn:timezone":"Europe/Paris",
    "iso:country":"FR",
    "wof:name":"Les Bas Vents",
    "wof:placetype":"locality"
},
  "geometry": {"coordinates":[3.90873,50.31522],"type":"Point"}
}