{
  "type": "Feature",
  "properties": {
    "gn:admin1_code":"75",
    "gn:admin2_code":"23",
    "gn:admin3_code":"231",
    "gn:admin4_code":"23232",
    "gn:asciiname":"Le Compeix",
    "gn:country_code":"FR",
    "gn:dem":660,
    "gn:feature_class":"P",
    "gn:feature_code":"PPL",
    "gn:name":"Le Compeix",
    "gn:population":0,
    "gn:timezone":"Europe/Paris",
    "iso:country":"FR",
    "wof:name":"Le Compeix",
    "wof:placetype":"locality"
},
  "geometry": {"coordinates":[1.86619,45.89682],"type":"Point"}
}