{
  "type": "Feature",
  "properties": {
    "gn:admin1_code":"84",
    "gn:admin2_code":"69",
    "gn:admin3_code":"691",
    "gn:admin4_code":"69176",
    "gn:asciiname":"Verchery",
    "gn:country_code":"FR",
    "gn:dem":352,
    "gn:feature_class":"P",
    "gn:feature_code":"PPL",
    "gn:name":"Verchery",
    "gn:population":0,
    "gn:timezone":"Europe/Paris",
    "iso:country":"FR",
    "wof:name":"Verchery",
    "wof:placetype":"locality"
},
  "geometry": {"coordinates":[4.70099,45.68347],"type":"Point"}
}