{
  "type": "Feature",
  "properties": {
    "gn:admin1_code":"84",
    "gn:admin2_code":"03",
    "gn:admin3_code":"032",
    "gn:admin4_code":"03176",
    "gn:asciiname":"Montigny",
    "gn:country_code":"FR",
    "gn:dem":295,
    "gn:feature_class":"P",
    "gn:feature_code":"PPL",
    "gn:name":"Montigny",
    "gn:population":0,
    "gn:timezone":"Europe/Paris",
    "iso:country":"FR",
    "wof:name":"Montigny",
    "wof:placetype":"locality"
},
  "geometry": {"coordinates":[3.29581,46.36819000000001],"type":"Point"}
}