{
  "type": "Feature",
  "properties": {
    "gn:admin1_code":"27",
    "gn:admin2_code":"58",
    "gn:admin3_code":"583",
    "gn:admin4_code":"58088",
    "gn:asciiname":"Villecourt",
    "gn:country_code":"FR",
    "gn:dem":204,
    "gn:feature_class":"P",
    "gn:feature_code":"PPL",
    "gn:name":"Villecourt",
    "gn:population":0,
    "gn:timezone":"Europe/Paris",
    "iso:country":"FR",
    "name:cat_x_preferred":[
        "Villecourt"
    ],
    "name:ceb_x_preferred":[
        "Villecourt"
    ],
    "name:deu_x_preferred":[
        "Villecourt"
    ],
    "name:eus_x_preferred":[
        "Villecourt"
    ],
    "name:fra_x_preferred":[
        "Villecourt"
    ],
    "name:hun_x_preferred":[
        "Villecourt"
    ],
    "name:hye_x_preferred":[
        "\u054e\u056b\u056c\u056f\u0578\u0582\u0580"
    ],
    "name:ita_x_preferred":[
        "Villecourt"
    ],
    "name:lat_x_preferred":[
        "Villecourt"
    ],
    "name:mlg_x_preferred":[
        "Villecourt"
    ],
    "name:msa_x_preferred":[
        "Villecourt"
    ],
    "name:nld_x_preferred":[
        "Villecourt"
    ],
    "name:oci_x_preferred":[
        "Villecourt"
    ],
    "name:pcd_x_preferred":[
        "Vilcourt"
    ],
    "name:pms_x_preferred":[
        "Villecourt"
    ],
    "name:pol_x_preferred":[
        "Villecourt"
    ],
    "name:por_x_preferred":[
        "Villecourt"
    ],
    "name:ron_x_preferred":[
        "Villecourt"
    ],
    "name:slk_x_preferred":[
        "Villecourt"
    ],
    "name:spa_x_preferred":[
        "Villecourt"
    ],
    "name:swe_x_preferred":[
        "Villecourt"
    ],
    "name:ukr_x_preferred":[
        "\u0412\u0456\u043b\u044c\u043a\u0443\u0440"
    ],
    "name:uzb_x_preferred":[
        "Villecourt"
    ],
    "name:vie_x_preferred":[
        "Villecourt"
    ],
    "name:vol_x_preferred":[
        "Villecourt"
    ],
    "name:war_x_preferred":[
        "Villecourt"
    ],
    "name:zho_x_preferred":[
        "\u7ef4\u5c14\u5e93\u5c14"
    ],
    "wof:name":"Villecourt",
    "wof:placetype":"locality"
},
  "geometry": {"coordinates":[3.16667,47.01667],"type":"Point"}
}