{
  "type": "Feature",
  "properties": {
    "gn:admin1_code":"27",
    "gn:admin2_code":"58",
    "gn:admin3_code":"583",
    "gn:admin4_code":"58088",
    "gn:asciiname":"Villecourt",
    "gn:country_code":"FR",
    "gn:dem":204,
    "gn:feature_class":"P",
    "gn:feature_code":"PPL",
    "gn:name":"Villecourt",
    "gn:population":0,
    "gn:timezone":"Europe/Paris",
    "iso:country":"FR",
    "wof:name":"Villecourt",
    "wof:placetype":"locality"
},
  "geometry": {"coordinates":[3.16667,47.01667],"type":"Point"}
}