{
  "type": "Feature",
  "properties": {
    "gn:admin1_code":"28",
    "gn:admin2_code":"76",
    "gn:admin3_code":"761",
    "gn:admin4_code":"76645.0",
    "gn:asciiname":"Saint-Riquier-en-Riviere",
    "gn:country_code":"FR",
    "gn:dem":89,
    "gn:feature_class":"P",
    "gn:feature_code":"PPL",
    "gn:name":"Saint-Riquier-en-Rivi\u00e8re",
    "gn:population":0,
    "gn:timezone":"Europe/Paris",
    "iso:country":"FR",
    "name:und_x_variant":[
        "Saint-Riquier",
        "Saint-Riquier-en-Rivi\u00e8re"
    ],
    "wof:name":"Saint-Riquier-en-Riviere",
    "wof:placetype":"locality"
},
  "geometry": {"coordinates":[1.55958,49.89091],"type":"Point"}
}