{
  "type": "Feature",
  "properties": {
    "gn:admin1_code":"84",
    "gn:admin2_code":"26",
    "gn:admin3_code":"262",
    "gn:admin4_code":"26374",
    "gn:asciiname":"Villebois-les-Pins",
    "gn:country_code":"FR",
    "gn:dem":873,
    "gn:feature_class":"P",
    "gn:feature_code":"PPL",
    "gn:name":"Villebois-les-Pins",
    "gn:population":0,
    "gn:timezone":"Europe/Paris",
    "iso:country":"FR",
    "name:bug_x_preferred":[
        "Villebois-les-Pins"
    ],
    "name:cat_x_preferred":[
        "Vilan\u00f2va d'Estela"
    ],
    "name:ceb_x_preferred":[
        "Villebois-les-Pins"
    ],
    "name:deu_x_preferred":[
        "Villebois-les-Pins"
    ],
    "name:eus_x_preferred":[
        "Villebois-les-Pins"
    ],
    "name:fra_x_preferred":[
        "Villebois-les-Pins"
    ],
    "name:hun_x_preferred":[
        "Villebois-les-Pins"
    ],
    "name:ita_x_preferred":[
        "Villebois-les-Pins"
    ],
    "name:lat_x_preferred":[
        "Villebois-les-Pins"
    ],
    "name:lmo_x_preferred":[
        "Villebois-les-Pins"
    ],
    "name:mlg_x_preferred":[
        "Villebois-les-Pins"
    ],
    "name:msa_x_preferred":[
        "Villebois-les-Pins"
    ],
    "name:nld_x_preferred":[
        "Villebois-les-Pins"
    ],
    "name:oci_x_preferred":[
        "Villebois-les-Pins"
    ],
    "name:pms_x_preferred":[
        "Villebois-les-Pins"
    ],
    "name:pol_x_preferred":[
        "Villebois-les-Pins"
    ],
    "name:por_x_preferred":[
        "Villebois-les-Pins"
    ],
    "name:ron_x_preferred":[
        "Villebois-les-Pins"
    ],
    "name:slk_x_preferred":[
        "Villebois-les-Pins"
    ],
    "name:spa_x_preferred":[
        "Villebois-les-Pins"
    ],
    "name:swe_x_preferred":[
        "Villebois-les-Pins"
    ],
    "name:ukr_x_preferred":[
        "\u0412\u0456\u043b\u044c\u0431\u0443\u0430-\u043b\u0435-\u041f\u0435\u043d"
    ],
    "name:und_x_variant":[
        "Villebois"
    ],
    "name:uzb_x_preferred":[
        "Villebois-les-Pins"
    ],
    "name:vie_x_preferred":[
        "Villebois-les-Pins"
    ],
    "name:vol_x_preferred":[
        "Villebois-les-Pins"
    ],
    "name:war_x_preferred":[
        "Villebois-les-Pins"
    ],
    "name:zho_x_preferred":[
        "\u7ef4\u52d2\u5e03\u74e6\u96f7\u6f58"
    ],
    "wof:name":"Villebois-les-Pins",
    "wof:placetype":"locality"
},
  "geometry": {"coordinates":[5.60934,44.31848],"type":"Point"}
}