{
  "type": "Feature",
  "properties": {
    "gn:admin1_code":"84",
    "gn:admin2_code":"26",
    "gn:admin3_code":"262",
    "gn:admin4_code":"26374",
    "gn:asciiname":"Villebois-les-Pins",
    "gn:country_code":"FR",
    "gn:dem":873,
    "gn:feature_class":"P",
    "gn:feature_code":"PPL",
    "gn:name":"Villebois-les-Pins",
    "gn:population":0,
    "gn:timezone":"Europe/Paris",
    "iso:country":"FR",
    "name:und_x_variant":[
        "Villebois",
        "Villebois-les-Pins"
    ],
    "wof:name":"Villebois-les-Pins",
    "wof:placetype":"locality"
},
  "geometry": {"coordinates":[5.60934,44.31848],"type":"Point"}
}