{
  "type": "Feature",
  "properties": {
    "gn:admin1_code":"93",
    "gn:admin2_code":"05",
    "gn:admin3_code":"052",
    "gn:admin4_code":"05139",
    "gn:asciiname":"Le Collet",
    "gn:country_code":"FR",
    "gn:dem":1280,
    "gn:feature_class":"P",
    "gn:feature_code":"PPL",
    "gn:name":"Le Collet",
    "gn:population":0,
    "gn:timezone":"Europe/Paris",
    "iso:country":"FR",
    "wof:name":"Le Collet",
    "wof:placetype":"locality"
},
  "geometry": {"coordinates":[5.92639,44.72039],"type":"Point"}
}