{
  "type": "Feature",
  "properties": {
    "frgov:code_epci":"242600534",
    "frgov:insee_arr":"1",
    "frgov:insee_com":"26254",
    "frgov:insee_dep":"26",
    "frgov:insee_reg":"84",
    "frgov:nom_com":"Pradelle",
    "frgov:nom_com_m":"PRADELLE",
    "frgov:nom_dep":"DROME",
    "frgov:nom_reg":"AUVERGNE-RHONE-ALPES",
    "frgov:statut":"Commune simple",
    "gn:admin1_code":"84",
    "gn:admin2_code":"26",
    "gn:admin3_code":"261",
    "gn:admin4_code":"26254",
    "gn:asciiname":"Pradelle",
    "gn:country_code":"FR",
    "gn:dem":519,
    "gn:feature_class":"P",
    "gn:feature_code":"PPL",
    "gn:name":"Pradelle",
    "gn:population":27,
    "gn:timezone":"Europe/Paris",
    "iso:country":"FR",
    "name:cat_x_preferred":[
        "Prad\u00e8la"
    ],
    "name:fra_x_preferred":[
        "Pradelle"
    ],
    "name:oci_x_preferred":[
        "Prad\u00e8la"
    ],
    "name:ukr_x_preferred":[
        "\u041f\u0440\u0430\u0434\u0435\u043b\u044c"
    ],
    "name:zho_x_preferred":[
        "\u666e\u62c9\u4ee3\u5c14"
    ],
    "qs:a0":"France",
    "qs:a1":"DROME",
    "qs:a1_lc":"26",
    "qs:a1r":"RHONE-ALPES",
    "qs:a1r_lc":"82",
    "qs:a2_lc":"17",
    "qs:a2r_lc":"1",
    "qs:adm0":"France",
    "qs:adm0_a3":"FRA",
    "qs:la":"PRADELLE",
    "qs:la_lc":"26254",
    "qs:level":"localadmin",
    "qs:type":"Commune simple",
    "wof:coterminous":[
        404352431
    ],
    "wof:name":"Pradelle",
    "wof:placetype":"locality",
    "wof:placetype_local":"Commune simple",
    "wof:population":27
},
  "geometry": {"coordinates":[5.29204,44.60806],"type":"Point"}
}