{
  "type": "Feature",
  "properties": {
    "gn:admin1_code":"84",
    "gn:admin2_code":"26",
    "gn:admin3_code":"261",
    "gn:admin4_code":"26254",
    "gn:asciiname":"Pradelle",
    "gn:country_code":"FR",
    "gn:dem":519,
    "gn:feature_class":"P",
    "gn:feature_code":"PPL",
    "gn:name":"Pradelle",
    "gn:population":27,
    "gn:timezone":"Europe/Paris",
    "iso:country":"FR",
    "wof:name":"Pradelle",
    "wof:placetype":"locality",
    "wof:population":27
},
  "geometry": {"coordinates":[5.29204,44.60806],"type":"Point"}
}