{
  "type": "Feature",
  "properties": {
    "gn:admin1_code":"84",
    "gn:admin2_code":"63",
    "gn:admin3_code":"634",
    "gn:admin4_code":"63170",
    "gn:asciiname":"Biot",
    "gn:country_code":"FR",
    "gn:dem":720,
    "gn:feature_class":"P",
    "gn:feature_code":"PPL",
    "gn:name":"Biot",
    "gn:population":0,
    "gn:timezone":"Europe/Paris",
    "iso:country":"FR",
    "name:cat_x_preferred":[
        "Biot"
    ],
    "name:dan_x_preferred":[
        "Biot"
    ],
    "name:deu_x_preferred":[
        "Biot"
    ],
    "name:fin_x_preferred":[
        "Biot"
    ],
    "name:fra_x_preferred":[
        "Biot"
    ],
    "name:ita_x_preferred":[
        "Biot"
    ],
    "name:nld_x_preferred":[
        "Biot"
    ],
    "name:pms_x_preferred":[
        "Biot"
    ],
    "name:pol_x_preferred":[
        "Biot"
    ],
    "name:scn_x_preferred":[
        "Biot"
    ],
    "name:sqi_x_preferred":[
        "Biot"
    ],
    "name:swe_x_preferred":[
        "Biot"
    ],
    "wof:name":"Biot",
    "wof:placetype":"locality"
},
  "geometry": {"coordinates":[2.75352,45.8708],"type":"Point"}
}