{
  "type": "Feature",
  "properties": {
    "gn:admin1_code":"93",
    "gn:admin2_code":"04",
    "gn:admin3_code":"043",
    "gn:admin4_code":"04059",
    "gn:asciiname":"Le Gion",
    "gn:country_code":"FR",
    "gn:dem":852,
    "gn:feature_class":"P",
    "gn:feature_code":"PPL",
    "gn:name":"Le Gion",
    "gn:population":0,
    "gn:timezone":"Europe/Paris",
    "iso:country":"FR",
    "wof:name":"Le Gion",
    "wof:placetype":"locality"
},
  "geometry": {"coordinates":[6.3994,44.01074000000001],"type":"Point"}
}