{
  "type": "Feature",
  "properties": {
    "gn:admin1_code":"84",
    "gn:admin2_code":"73",
    "gn:admin3_code":"732",
    "gn:admin4_code":"73107",
    "gn:asciiname":"Les Cures",
    "gn:country_code":"FR",
    "gn:dem":1010,
    "gn:feature_class":"P",
    "gn:feature_code":"PPL",
    "gn:name":"Les Cur\u00e9s",
    "gn:population":0,
    "gn:timezone":"Europe/Paris",
    "iso:country":"FR",
    "wof:name":"Les Cures",
    "wof:placetype":"locality"
},
  "geometry": {"coordinates":[5.89279,45.47473],"type":"Point"}
}