{
  "type": "Feature",
  "properties": {
    "gn:admin1_code":"75",
    "gn:admin2_code":"17",
    "gn:admin3_code":"173",
    "gn:admin4_code":"17051",
    "gn:asciiname":"Village Oceanique",
    "gn:country_code":"FR",
    "gn:dem":11,
    "gn:feature_class":"P",
    "gn:feature_code":"PPL",
    "gn:name":"Village Oc\u00e9anique",
    "gn:population":0,
    "gn:timezone":"Europe/Paris",
    "iso:country":"FR",
    "wof:name":"Village Oceanique",
    "wof:placetype":"locality"
},
  "geometry": {"coordinates":[-1.35648,46.17241],"type":"Point"}
}