{
  "type": "Feature",
  "properties": {
    "gn:admin1_code":"53",
    "gn:admin2_code":"29",
    "gn:admin3_code":"294",
    "gn:admin4_code":"29197",
    "gn:asciiname":"Lesvoualch",
    "gn:country_code":"FR",
    "gn:dem":72,
    "gn:feature_class":"P",
    "gn:feature_code":"PPL",
    "gn:name":"Lesvoualch",
    "gn:population":0,
    "gn:timezone":"Europe/Paris",
    "iso:country":"FR",
    "wof:name":"Lesvoualch",
    "wof:placetype":"locality"
},
  "geometry": {"coordinates":[-4.45648,48.01124],"type":"Point"}
}