{
  "type": "Feature",
  "properties": {
    "iso:country":"FR",
    "name:eng_x_preferred":[
        "La Sabliere"
    ],
    "name:fra_x_preferred":[
        "La Sabli\u00e8re"
    ],
    "wof:name":"La Sabliere",
    "wof:placetype":"neighbourhood"
},
  "geometry": {"coordinates":[2.48908834214287,48.89037980804836],"type":"Point"}
}