{
  "type": "Feature",
  "properties": {
    "gn:admin1_code":"76",
    "gn:admin2_code":"34",
    "gn:admin3_code":"341",
    "gn:admin4_code":"34021",
    "gn:asciiname":"Bouldoux",
    "gn:country_code":"FR",
    "gn:dem":186,
    "gn:feature_class":"P",
    "gn:feature_code":"PPL",
    "gn:name":"Bouldoux",
    "gn:population":0,
    "gn:timezone":"Europe/Paris",
    "iso:country":"FR",
    "wof:name":"Bouldoux",
    "wof:placetype":"locality"
},
  "geometry": {"coordinates":[2.91042,43.43619],"type":"Point"}
}