{
  "type": "Feature",
  "properties": {
    "gn:admin1_code":"93",
    "gn:admin2_code":"05",
    "gn:admin3_code":"051",
    "gn:admin4_code":"05151",
    "gn:asciiname":"Ratiere",
    "gn:country_code":"FR",
    "gn:dem":1800,
    "gn:feature_class":"P",
    "gn:feature_code":"PPL",
    "gn:name":"Rati\u00e8re",
    "gn:population":0,
    "gn:timezone":"Europe/Paris",
    "iso:country":"FR",
    "wof:name":"Ratiere",
    "wof:placetype":"locality"
},
  "geometry": {"coordinates":[6.57343,44.86974],"type":"Point"}
}