{
  "type": "Feature",
  "properties": {
    "gn:admin1_code":"76",
    "gn:admin2_code":"12",
    "gn:admin3_code":"122",
    "gn:admin4_code":"12277",
    "gn:asciiname":"Pierrefiche",
    "gn:country_code":"FR",
    "gn:dem":726,
    "gn:feature_class":"P",
    "gn:feature_code":"PPL",
    "gn:name":"Pierrefiche",
    "gn:population":0,
    "gn:timezone":"Europe/Paris",
    "iso:country":"FR",
    "wof:name":"Pierrefiche",
    "wof:placetype":"locality"
},
  "geometry": {"coordinates":[2.62247,44.80876],"type":"Point"}
}