{
  "type": "Feature",
  "properties": {
    "gn:admin1_code":"76",
    "gn:admin2_code":"12",
    "gn:admin3_code":"122",
    "gn:admin4_code":"12277",
    "gn:asciiname":"Pierrefiche",
    "gn:country_code":"FR",
    "gn:dem":726,
    "gn:feature_class":"P",
    "gn:feature_code":"PPL",
    "gn:name":"Pierrefiche",
    "gn:population":0,
    "gn:timezone":"Europe/Paris",
    "iso:country":"FR",
    "name:ceb_x_preferred":[
        "Pierrefiche"
    ],
    "name:deu_x_preferred":[
        "Pierrefiche"
    ],
    "name:fra_x_preferred":[
        "Pierrefiche"
    ],
    "name:hun_x_preferred":[
        "Pierrefiche"
    ],
    "name:ita_x_preferred":[
        "Pierrefiche"
    ],
    "name:nds_x_preferred":[
        "Pierrefiche"
    ],
    "name:nld_x_preferred":[
        "Pierrefiche"
    ],
    "name:pms_x_preferred":[
        "Pierrefiche"
    ],
    "name:pol_x_preferred":[
        "Pierrefiche"
    ],
    "name:por_x_preferred":[
        "Pierrefiche"
    ],
    "name:rus_x_preferred":[
        "\u041f\u044c\u0435\u0440\u0444\u0438\u0448"
    ],
    "name:slk_x_preferred":[
        "Pierrefiche"
    ],
    "name:spa_x_preferred":[
        "Pierrefiche"
    ],
    "name:swe_x_preferred":[
        "Pierrefiche"
    ],
    "name:ukr_x_preferred":[
        "\u041f'\u0454\u0440\u0440\u0444\u0456\u0448"
    ],
    "wof:name":"Pierrefiche",
    "wof:placetype":"locality"
},
  "geometry": {"coordinates":[2.62247,44.80876],"type":"Point"}
}