{
  "type": "Feature",
  "properties": {
    "gn:admin1_code":"24",
    "gn:admin2_code":"18",
    "gn:admin3_code":"181",
    "gn:admin4_code":"18125",
    "gn:asciiname":"Valise",
    "gn:country_code":"FR",
    "gn:dem":150,
    "gn:feature_class":"P",
    "gn:feature_code":"PPL",
    "gn:name":"Valise",
    "gn:population":0,
    "gn:timezone":"Europe/Paris",
    "iso:country":"FR",
    "wof:name":"Valise",
    "wof:placetype":"locality"
},
  "geometry": {"coordinates":[2.8598,47.47276],"type":"Point"}
}