{
  "type": "Feature",
  "properties": {
    "iso:country":"FR",
    "name:eng_x_preferred":[
        "Les Hautes d'Issy"
    ],
    "name:fra_x_preferred":[
        "Les Hautes d'Issy"
    ],
    "wof:name":"Les Hautes d'Issy",
    "wof:placetype":"neighbourhood"
},
  "geometry": {"coordinates":[2.27535563721626,48.8195317031251],"type":"Point"}
}