{
  "type": "Feature",
  "properties": {
    "gn:admin1_code":"84",
    "gn:admin2_code":"15",
    "gn:admin3_code":"152",
    "gn:admin4_code":"15036",
    "gn:asciiname":"Aynes",
    "gn:country_code":"FR",
    "gn:dem":271,
    "gn:feature_class":"P",
    "gn:feature_code":"PPL",
    "gn:name":"Aynes",
    "gn:population":0,
    "gn:timezone":"Europe/Paris",
    "iso:country":"FR",
    "name:und_x_variant":[
        "Aines",
        "Ayne",
        "Aynes"
    ],
    "wof:name":"Aynes",
    "wof:placetype":"locality"
},
  "geometry": {"coordinates":[2.21705,45.23337],"type":"Point"}
}