{
  "type": "Feature",
  "properties": {
    "gn:admin1_code":"84",
    "gn:admin2_code":"15",
    "gn:admin3_code":"153",
    "gn:admin4_code":"15237.0",
    "gn:asciiname":"Tiviers",
    "gn:country_code":"FR",
    "gn:dem":854,
    "gn:feature_class":"P",
    "gn:feature_code":"PPL",
    "gn:name":"Tiviers",
    "gn:population":151,
    "gn:timezone":"Europe/Paris",
    "iso:country":"FR",
    "wof:name":"Tiviers",
    "wof:placetype":"locality",
    "wof:population":151
},
  "geometry": {"coordinates":[3.15727,45.06034],"type":"Point"}
}