{
  "type": "Feature",
  "properties": {
    "frgov:code_epci":"200066660",
    "frgov:insee_arr":"3",
    "frgov:insee_com":"15237",
    "frgov:insee_dep":"15",
    "frgov:insee_reg":"84",
    "frgov:nom_com":"Tiviers",
    "frgov:nom_com_m":"TIVIERS",
    "frgov:nom_dep":"CANTAL",
    "frgov:nom_reg":"AUVERGNE-RHONE-ALPES",
    "frgov:statut":"Commune simple",
    "gn:admin1_code":"84",
    "gn:admin2_code":"15",
    "gn:admin3_code":"153",
    "gn:admin4_code":"15237.0",
    "gn:asciiname":"Tiviers",
    "gn:country_code":"FR",
    "gn:dem":854,
    "gn:feature_class":"P",
    "gn:feature_code":"PPL",
    "gn:name":"Tiviers",
    "gn:population":151,
    "gn:timezone":"Europe/Paris",
    "iso:country":"FR",
    "name:cat_x_preferred":[
        "Tivier"
    ],
    "name:ceb_x_preferred":[
        "Tiviers"
    ],
    "name:deu_x_preferred":[
        "Tiviers"
    ],
    "name:eus_x_preferred":[
        "Tiviers"
    ],
    "name:fra_x_preferred":[
        "Tiviers"
    ],
    "name:hun_x_preferred":[
        "Tiviers"
    ],
    "name:hye_x_preferred":[
        "\u054f\u056b\u057e\u056b\u0565"
    ],
    "name:ita_x_preferred":[
        "Tiviers"
    ],
    "name:kaz_x_preferred":[
        "\u0422\u0438\u0432\u044c\u0435"
    ],
    "name:lat_x_preferred":[
        "Tiviers"
    ],
    "name:mlg_x_preferred":[
        "Tiviers"
    ],
    "name:msa_x_preferred":[
        "Tiviers"
    ],
    "name:nld_x_preferred":[
        "Tiviers"
    ],
    "name:oci_x_preferred":[
        "Tivi\u00e8r"
    ],
    "name:pms_x_preferred":[
        "Tiviers"
    ],
    "name:pol_x_preferred":[
        "Tiviers"
    ],
    "name:por_x_preferred":[
        "Tiviers"
    ],
    "name:ron_x_preferred":[
        "Tiviers"
    ],
    "name:rus_x_preferred":[
        "\u0422\u0438\u0432\u044c\u0435"
    ],
    "name:slk_x_preferred":[
        "Tiviers"
    ],
    "name:spa_x_preferred":[
        "Tiviers"
    ],
    "name:swe_x_preferred":[
        "Tiviers"
    ],
    "name:ukr_x_preferred":[
        "\u0422\u0456\u0432'\u0454"
    ],
    "name:uzb_x_preferred":[
        "Tiviers"
    ],
    "name:vie_x_preferred":[
        "Tiviers"
    ],
    "name:vol_x_preferred":[
        "Tiviers"
    ],
    "name:war_x_preferred":[
        "Tiviers"
    ],
    "name:zho_x_preferred":[
        "\u8482\u7ef4\u8036\u5c14"
    ],
    "qs:a0":"France",
    "qs:a1":"CANTAL",
    "qs:a1_lc":"15",
    "qs:a1r":"AUVERGNE",
    "qs:a1r_lc":"83",
    "qs:a2_lc":"19",
    "qs:a2r_lc":"3",
    "qs:adm0":"France",
    "qs:adm0_a3":"FRA",
    "qs:la":"TIVIERS",
    "qs:la_lc":"15237",
    "qs:level":"localadmin",
    "qs:type":"Commune simple",
    "wof:coterminous":[
        404357923
    ],
    "wof:name":"Tiviers",
    "wof:placetype":"locality",
    "wof:placetype_local":"Commune simple",
    "wof:population":151
},
  "geometry": {"coordinates":[3.15727,45.06034],"type":"Point"}
}