{
  "type": "Feature",
  "properties": {
    "gn:admin1_code":"32",
    "gn:admin2_code":"60",
    "gn:admin3_code":"601",
    "gn:admin4_code":"60687",
    "gn:asciiname":"Auchy-en-Bray",
    "gn:country_code":"FR",
    "gn:dem":153,
    "gn:feature_class":"P",
    "gn:feature_code":"PPL",
    "gn:name":"Auchy-en-Bray",
    "gn:population":0,
    "gn:timezone":"Europe/Paris",
    "iso:country":"FR",
    "name:und_x_variant":[
        "Auchy",
        "Auchy-en-Bray"
    ],
    "wof:name":"Auchy-en-Bray",
    "wof:placetype":"locality"
},
  "geometry": {"coordinates":[1.77902,49.48315],"type":"Point"}
}