{
  "type": "Feature",
  "properties": {
    "gn:admin1_code":"76",
    "gn:admin2_code":"12",
    "gn:admin3_code":"121",
    "gn:admin4_code":"12147",
    "gn:asciiname":"Laval",
    "gn:country_code":"FR",
    "gn:dem":533,
    "gn:feature_class":"P",
    "gn:feature_code":"PPL",
    "gn:name":"Laval",
    "gn:population":0,
    "gn:timezone":"Europe/Paris",
    "iso:country":"FR",
    "wof:name":"Laval",
    "wof:placetype":"locality"
},
  "geometry": {"coordinates":[3.0313,43.8329],"type":"Point"}
}