{
  "type": "Feature",
  "properties": {
    "gn:admin1_code":"93",
    "gn:admin2_code":"83",
    "gn:admin3_code":"832",
    "gn:admin4_code":"83071",
    "gn:asciiname":"Saint-Clair",
    "gn:country_code":"FR",
    "gn:dem":66,
    "gn:feature_class":"P",
    "gn:feature_code":"PPL",
    "gn:name":"Saint-Clair",
    "gn:population":0,
    "gn:timezone":"Europe/Paris",
    "iso:country":"FR",
    "wof:name":"Saint-Clair",
    "wof:placetype":"locality"
},
  "geometry": {"coordinates":[6.25,43.16667],"type":"Point"}
}