{
  "type": "Feature",
  "properties": {
    "gn:admin1_code":"75",
    "gn:admin2_code":"23",
    "gn:admin3_code":"232",
    "gn:admin4_code":"23092",
    "gn:asciiname":"Moques",
    "gn:country_code":"FR",
    "gn:dem":442,
    "gn:feature_class":"P",
    "gn:feature_code":"PPL",
    "gn:name":"Moques",
    "gn:population":0,
    "gn:timezone":"Europe/Paris",
    "iso:country":"FR",
    "name:und_x_variant":[
        "Mauques",
        "Moques"
    ],
    "wof:name":"Moques",
    "wof:placetype":"locality"
},
  "geometry": {"coordinates":[1.97131,46.22834],"type":"Point"}
}