{
  "type": "Feature",
  "properties": {
    "iso:country":"FR",
    "qs_pg:aaroncc":"FR",
    "qs_pg:name":"L'Anse Caffar",
    "qs_pg:name_adm0":"Martinique",
    "qs_pg:name_adm1":"Marin",
    "qs_pg:photos":587,
    "qs_pg:photos_1k":119,
    "qs_pg:photos_9k":3,
    "qs_pg:photos_9r":5,
    "qs_pg:photos_all":587,
    "qs_pg:photos_sr":8,
    "qs_pg:pop_sr":0,
    "qs_pg:qs_pg_placetype":"locality",
    "qs_pg:qs_pg_placetype_gp":"Town",
    "qs_pg:woe_adm0":23424884,
    "woe:adm0_id":23424884,
    "woe:name_adm0":"Martinique",
    "woe:name_adm1":"Marin",
    "woe:placetype":"Town",
    "wof:name":"L'Anse Caffar",
    "wof:placetype":"neighbourhood"
},
  "geometry": {"coordinates":[-61.043472,14.468591],"type":"Point"}
}