{
  "type": "Feature",
  "properties": {
    "gn:admin1_code":"84",
    "gn:admin2_code":"43",
    "gn:admin3_code":"433",
    "gn:admin4_code":"43034",
    "gn:asciiname":"Boisset",
    "gn:country_code":"FR",
    "gn:dem":893,
    "gn:feature_class":"P",
    "gn:feature_code":"PPL",
    "gn:name":"Boisset",
    "gn:population":235,
    "gn:timezone":"Europe/Paris",
    "iso:country":"FR",
    "wof:name":"Boisset",
    "wof:placetype":"locality",
    "wof:population":235
},
  "geometry": {"coordinates":[3.98257,45.32305],"type":"Point"}
}