{
  "type": "Feature",
  "properties": {
    "gn:admin1_code":"84",
    "gn:admin2_code":"43",
    "gn:admin3_code":"433",
    "gn:admin4_code":"43034",
    "gn:asciiname":"Boisset",
    "gn:country_code":"FR",
    "gn:dem":893,
    "gn:feature_class":"P",
    "gn:feature_code":"PPL",
    "gn:name":"Boisset",
    "gn:population":235,
    "gn:timezone":"Europe/Paris",
    "iso:country":"FR",
    "name:bre_x_preferred":[
        "Boisset"
    ],
    "name:ceb_x_preferred":[
        "Boisset"
    ],
    "name:deu_x_preferred":[
        "Boisset"
    ],
    "name:fra_x_preferred":[
        "Boisset"
    ],
    "name:ita_x_preferred":[
        "Boisset"
    ],
    "name:nds_x_preferred":[
        "Boisset"
    ],
    "name:nld_x_preferred":[
        "Boisset"
    ],
    "name:pms_x_preferred":[
        "Boisset"
    ],
    "name:pol_x_preferred":[
        "Boisset"
    ],
    "name:por_x_preferred":[
        "Boisset"
    ],
    "name:rus_x_preferred":[
        "\u0411\u0443\u0430\u0441\u0435"
    ],
    "name:slk_x_preferred":[
        "Boisset"
    ],
    "name:spa_x_preferred":[
        "Boisset"
    ],
    "name:swe_x_preferred":[
        "Boisset"
    ],
    "wof:name":"Boisset",
    "wof:placetype":"locality",
    "wof:population":235
},
  "geometry": {"coordinates":[3.98257,45.32305],"type":"Point"}
}