{
  "type": "Feature",
  "properties": {
    "frgov:code_epci":"200073427",
    "frgov:insee_arr":"3",
    "frgov:insee_com":"43034",
    "frgov:insee_dep":"43",
    "frgov:insee_reg":"84",
    "frgov:nom_com":"Boisset",
    "frgov:nom_com_m":"BOISSET",
    "frgov:nom_dep":"HAUTE-LOIRE",
    "frgov:nom_reg":"AUVERGNE-RHONE-ALPES",
    "frgov:statut":"Commune simple",
    "gn:admin1_code":"84",
    "gn:admin2_code":"43",
    "gn:admin3_code":"433",
    "gn:admin4_code":"43034",
    "gn:asciiname":"Boisset",
    "gn:country_code":"FR",
    "gn:dem":893,
    "gn:feature_class":"P",
    "gn:feature_code":"PPL",
    "gn:name":"Boisset",
    "gn:population":235,
    "gn:timezone":"Europe/Paris",
    "iso:country":"FR",
    "name:bre_x_preferred":[
        "Boisset"
    ],
    "name:cat_x_preferred":[
        "Boisset de Velai"
    ],
    "name:ceb_x_preferred":[
        "Boisset"
    ],
    "name:deu_x_preferred":[
        "Boisset"
    ],
    "name:fra_x_preferred":[
        "Boisset"
    ],
    "name:ita_x_preferred":[
        "Boisset"
    ],
    "name:kaz_x_preferred":[
        "\u0411\u0443\u0430\u0441\u0441\u0435"
    ],
    "name:nds_x_preferred":[
        "Boisset"
    ],
    "name:nld_x_preferred":[
        "Boisset"
    ],
    "name:pms_x_preferred":[
        "Boisset"
    ],
    "name:pol_x_preferred":[
        "Boisset"
    ],
    "name:por_x_preferred":[
        "Boisset"
    ],
    "name:rus_x_preferred":[
        "\u0411\u0443\u0430\u0441\u0435"
    ],
    "name:slk_x_preferred":[
        "Boisset"
    ],
    "name:spa_x_preferred":[
        "Boisset"
    ],
    "name:srp_x_preferred":[
        "\u0411\u043e\u0430\u0441\u0435"
    ],
    "name:swe_x_preferred":[
        "Boisset"
    ],
    "name:ukr_x_preferred":[
        "\u0411\u0443\u0430\u0441\u0441\u0435"
    ],
    "name:zho_x_preferred":[
        "\u5e03\u74e6\u585e"
    ],
    "qs:a0":"France",
    "qs:a1":"HAUTE-LOIRE",
    "qs:a1_lc":"43",
    "qs:a1r":"AUVERGNE",
    "qs:a1r_lc":"83",
    "qs:a2_lc":"03",
    "qs:a2r_lc":"3",
    "qs:adm0":"France",
    "qs:adm0_a3":"FRA",
    "qs:la":"BOISSET",
    "qs:la_lc":"43034",
    "qs:level":"localadmin",
    "qs:type":"Commune simple",
    "wof:coterminous":[
        404391045
    ],
    "wof:name":"Boisset",
    "wof:placetype":"locality",
    "wof:placetype_local":"Commune simple",
    "wof:population":235
},
  "geometry": {"coordinates":[3.98257,45.32305],"type":"Point"}
}