{
  "type": "Feature",
  "properties": {
    "iso:country":"FR",
    "qs_pg:aaroncc":"FR",
    "qs_pg:name":"Les Bonneveaux",
    "qs_pg:name_adm0":"France",
    "qs_pg:name_adm1":"Poitou-Charentes",
    "qs_pg:photos":66,
    "qs_pg:photos_1k":13,
    "qs_pg:photos_9k":1,
    "qs_pg:photos_9r":2,
    "qs_pg:photos_all":66,
    "qs_pg:photos_sr":2,
    "qs_pg:pop_sr":0,
    "qs_pg:qs_pg_placetype":"locality",
    "qs_pg:qs_pg_placetype_gp":"Town",
    "qs_pg:woe_adm0":23424819,
    "woe:adm0_id":23424819,
    "woe:name_adm0":"France",
    "woe:name_adm1":"Poitou-Charentes",
    "woe:placetype":"Town",
    "wof:name":"Les Bonneveaux",
    "wof:placetype":"neighbourhood"
},
  "geometry": {"coordinates":[-1.08078,46.083947],"type":"Point"}
}