{
  "type": "Feature",
  "properties": {
    "gn:admin1_code":"32",
    "gn:admin2_code":"02",
    "gn:admin3_code":"024",
    "gn:admin4_code":"02008",
    "gn:asciiname":"Jouy",
    "gn:country_code":"FR",
    "gn:dem":87,
    "gn:feature_class":"P",
    "gn:feature_code":"PPL",
    "gn:name":"Jouy",
    "gn:population":0,
    "gn:timezone":"Europe/Paris",
    "iso:country":"FR",
    "name:bre_x_preferred":[
        "Jouy"
    ],
    "name:ceb_x_preferred":[
        "Jouy"
    ],
    "name:deu_x_preferred":[
        "Jouy"
    ],
    "name:epo_x_preferred":[
        "Jouy"
    ],
    "name:fra_x_preferred":[
        "Jouy"
    ],
    "name:ita_x_preferred":[
        "Jouy"
    ],
    "name:jpn_x_preferred":[
        "\u30b8\u30e5\u30a4"
    ],
    "name:nds_x_preferred":[
        "Jouy"
    ],
    "name:nld_x_preferred":[
        "Jouy"
    ],
    "name:oci_x_preferred":[
        "Jouy"
    ],
    "name:pms_x_preferred":[
        "Jouy"
    ],
    "name:pol_x_preferred":[
        "Jouy"
    ],
    "name:scn_x_preferred":[
        "Jouy"
    ],
    "name:sco_x_preferred":[
        "Jouy"
    ],
    "name:slk_x_preferred":[
        "Jouy"
    ],
    "name:spa_x_preferred":[
        "Jouy"
    ],
    "name:sqi_x_preferred":[
        "Jouy"
    ],
    "name:swe_x_preferred":[
        "Jouy"
    ],
    "name:ukr_x_preferred":[
        "\u0416\u0443\u0457"
    ],
    "wof:name":"Jouy",
    "wof:placetype":"locality"
},
  "geometry": {"coordinates":[3.51213,49.43917],"type":"Point"}
}