{
  "type": "Feature",
  "properties": {
    "gn:admin1_code":"32",
    "gn:admin2_code":"02",
    "gn:admin3_code":"024",
    "gn:admin4_code":"02008",
    "gn:asciiname":"Jouy",
    "gn:country_code":"FR",
    "gn:dem":87,
    "gn:feature_class":"P",
    "gn:feature_code":"PPL",
    "gn:name":"Jouy",
    "gn:population":0,
    "gn:timezone":"Europe/Paris",
    "iso:country":"FR",
    "wof:name":"Jouy",
    "wof:placetype":"locality"
},
  "geometry": {"coordinates":[3.51213,49.43917],"type":"Point"}
}