{
  "type": "Feature",
  "properties": {
    "gn:admin1_code":"11",
    "gn:admin2_code":"91",
    "gn:admin3_code":"911",
    "gn:admin4_code":"91593",
    "gn:asciiname":"Sermaise",
    "gn:country_code":"FR",
    "gn:dem":90,
    "gn:feature_class":"P",
    "gn:feature_code":"PPL",
    "gn:name":"Sermaise",
    "gn:population":0,
    "gn:timezone":"Europe/Paris",
    "iso:country":"FR",
    "wof:name":"Sermaise",
    "wof:placetype":"locality"
},
  "geometry": {"coordinates":[2.08074,48.53538],"type":"Point"}
}