{
  "type": "Feature",
  "properties": {
    "gn:admin1_code":"75",
    "gn:admin2_code":"47",
    "gn:admin3_code":"473",
    "gn:admin4_code":"47292",
    "gn:asciiname":"Fourquies",
    "gn:country_code":"FR",
    "gn:dem":238,
    "gn:feature_class":"P",
    "gn:feature_code":"PPL",
    "gn:name":"Fourquies",
    "gn:population":0,
    "gn:timezone":"Europe/Paris",
    "iso:country":"FR",
    "wof:name":"Fourquies",
    "wof:placetype":"locality"
},
  "geometry": {"coordinates":[1.0587,44.59165],"type":"Point"}
}