{
  "type": "Feature",
  "properties": {
    "gn:admin1_code":"28",
    "gn:admin2_code":"76",
    "gn:admin3_code":"763",
    "gn:admin4_code":"76385",
    "gn:asciiname":"Becquigny",
    "gn:country_code":"FR",
    "gn:dem":151,
    "gn:feature_class":"P",
    "gn:feature_code":"PPL",
    "gn:name":"Becquigny",
    "gn:population":0,
    "gn:timezone":"Europe/Paris",
    "iso:country":"FR",
    "name:ceb_x_preferred":[
        "Becquigny"
    ],
    "name:deu_x_preferred":[
        "Becquigny"
    ],
    "name:fra_x_preferred":[
        "Becquigny"
    ],
    "name:ita_x_preferred":[
        "Becquigny"
    ],
    "name:nds_x_preferred":[
        "Becquigny"
    ],
    "name:nld_x_preferred":[
        "Becquigny"
    ],
    "name:pms_x_preferred":[
        "Becquigny"
    ],
    "name:pol_x_preferred":[
        "Becquigny"
    ],
    "name:por_x_preferred":[
        "Becquigny"
    ],
    "name:ron_x_preferred":[
        "Becquigny"
    ],
    "name:rus_x_preferred":[
        "\u0411\u0435\u043a\u043a\u0438\u043d\u044c\u0438"
    ],
    "name:slk_x_preferred":[
        "Becquigny"
    ],
    "name:spa_x_preferred":[
        "Becquigny"
    ],
    "name:srp_x_preferred":[
        "\u0411\u0435\u043a\u0438\u045a\u0438"
    ],
    "name:swe_x_preferred":[
        "Becquigny"
    ],
    "name:ukr_x_preferred":[
        "\u0411\u0435\u043a\u0456\u043d\u044c\u0457"
    ],
    "name:und_x_variant":[
        "Bequigny"
    ],
    "wof:name":"Becquigny",
    "wof:placetype":"locality"
},
  "geometry": {"coordinates":[0.93489,49.5988],"type":"Point"}
}