{
  "type": "Feature",
  "properties": {
    "gn:admin1_code":"75",
    "gn:admin2_code":"79",
    "gn:admin3_code":"793",
    "gn:admin4_code":"79268",
    "gn:asciiname":"Lamaire",
    "gn:country_code":"FR",
    "gn:dem":148,
    "gn:feature_class":"P",
    "gn:feature_code":"PPL",
    "gn:name":"Lamaire",
    "gn:population":0,
    "gn:timezone":"Europe/Paris",
    "iso:country":"FR",
    "wof:name":"Lamaire",
    "wof:placetype":"locality"
},
  "geometry": {"coordinates":[-0.12574,46.75653],"type":"Point"}
}