{
  "type": "Feature",
  "properties": {
    "gn:admin1_code":"84",
    "gn:admin2_code":"43",
    "gn:admin3_code":"433",
    "gn:admin4_code":"43268",
    "gn:asciiname":"Echabrac",
    "gn:country_code":"FR",
    "gn:dem":837,
    "gn:feature_class":"P",
    "gn:feature_code":"PPL",
    "gn:name":"\u00c9chabrac",
    "gn:population":0,
    "gn:timezone":"Europe/Paris",
    "iso:country":"FR",
    "wof:name":"Echabrac",
    "wof:placetype":"locality"
},
  "geometry": {"coordinates":[4.09315,45.13098],"type":"Point"}
}