{
  "type": "Feature",
  "properties": {
    "gn:admin1_code":"24",
    "gn:admin2_code":"18",
    "gn:admin3_code":"182",
    "gn:admin4_code":"18187",
    "gn:asciiname":"Bouex Grand",
    "gn:country_code":"FR",
    "gn:dem":476,
    "gn:feature_class":"P",
    "gn:feature_code":"PPL",
    "gn:name":"Bouex Grand",
    "gn:population":0,
    "gn:timezone":"Europe/Paris",
    "iso:country":"FR",
    "wof:name":"Bouex Grand",
    "wof:placetype":"locality"
},
  "geometry": {"coordinates":[2.21667,46.45],"type":"Point"}
}