{
  "type": "Feature",
  "properties": {
    "gn:admin1_code":"93",
    "gn:admin2_code":"04",
    "gn:admin3_code":"044",
    "gn:admin4_code":"04026",
    "gn:asciiname":"Jurans",
    "gn:cc2":"FR",
    "gn:country_code":"FR",
    "gn:dem":844,
    "gn:feature_class":"P",
    "gn:feature_code":"PPL",
    "gn:name":"Jurans",
    "gn:population":0,
    "gn:timezone":"Europe/Paris",
    "iso:country":"FR",
    "name:und_x_variant":[
        "Les Jurans",
        "Jurans"
    ],
    "wof:name":"Jurans",
    "wof:placetype":"locality"
},
  "geometry": {"coordinates":[6.18333,44.41667],"type":"Point"}
}