{
  "type": "Feature",
  "properties": {
    "gn:admin1_code":"27",
    "gn:admin2_code":"89",
    "gn:admin3_code":"892",
    "gn:admin4_code":"89347",
    "gn:asciiname":"Vilaine",
    "gn:country_code":"FR",
    "gn:dem":356,
    "gn:feature_class":"P",
    "gn:feature_code":"PPL",
    "gn:name":"Vilaine",
    "gn:population":0,
    "gn:timezone":"Europe/Paris",
    "iso:country":"FR",
    "name:ara_x_preferred":[
        "\u0646\u0647\u0631 \u0641\u064a\u0644\u0627\u064a\u0646"
    ],
    "name:bar_x_preferred":[
        "Vilaine"
    ],
    "name:bel_x_preferred":[
        "\u0412\u0456\u043b\u0435\u043d"
    ],
    "name:bre_x_preferred":[
        "Gwilen"
    ],
    "name:cat_x_preferred":[
        "Vilaine"
    ],
    "name:ceb_x_preferred":[
        "Vilaine"
    ],
    "name:ces_x_preferred":[
        "Vilaine"
    ],
    "name:cym_x_preferred":[
        "Afon Gwilun"
    ],
    "name:deu_x_preferred":[
        "Vilaine"
    ],
    "name:ell_x_preferred":[
        "\u0392\u03b9\u03bb\u03b1\u03af\u03bd"
    ],
    "name:epo_x_preferred":[
        "Vilaine"
    ],
    "name:eus_x_preferred":[
        "Vilaine"
    ],
    "name:fas_x_preferred":[
        "\u0631\u0648\u062f \u0648\u06cc\u0644\u0646"
    ],
    "name:fra_x_preferred":[
        "Vilaine"
    ],
    "name:fry_x_preferred":[
        "Vilaine"
    ],
    "name:glg_x_preferred":[
        "R\u00edo Vilaine"
    ],
    "name:ita_x_preferred":[
        "Vilaine"
    ],
    "name:jpn_x_preferred":[
        "\u30f4\u30a3\u30ec\u30fc\u30cc\u5ddd"
    ],
    "name:kaz_x_preferred":[
        "\u0412\u0438\u043b\u0435\u043d"
    ],
    "name:kor_x_preferred":[
        "\ube4c\ub80c\uac15"
    ],
    "name:lat_x_preferred":[
        "Vicinonia"
    ],
    "name:lit_x_preferred":[
        "Vilenas"
    ],
    "name:mkd_x_preferred":[
        "\u0412\u0438\u043b\u0435\u043d"
    ],
    "name:nld_x_preferred":[
        "Vilaine"
    ],
    "name:nno_x_preferred":[
        "Vilaine"
    ],
    "name:pms_x_preferred":[
        "Vilaine"
    ],
    "name:pol_x_preferred":[
        "Vilaine"
    ],
    "name:por_x_preferred":[
        "Rio Vilaine"
    ],
    "name:ron_x_preferred":[
        "R\u00e2ul Vilaine"
    ],
    "name:rus_x_preferred":[
        "\u0412\u0438\u043b\u0435\u043d"
    ],
    "name:slv_x_preferred":[
        "Vilaine"
    ],
    "name:spa_x_preferred":[
        "R\u00edo Vilaine"
    ],
    "name:srp_x_preferred":[
        "\u0412\u0438\u043b\u0435\u043d"
    ],
    "name:swe_x_preferred":[
        "Vilaine"
    ],
    "name:ukr_x_preferred":[
        "\u0412\u0456\u043b\u0435\u043d"
    ],
    "name:zho_x_preferred":[
        "\u7ef4\u83b1\u8bb7\u6cb3"
    ],
    "wof:name":"Vilaine",
    "wof:placetype":"locality"
},
  "geometry": {"coordinates":[3.94238,47.39286],"type":"Point"}
}