{
  "type": "Feature",
  "properties": {
    "gn:admin1_code":"27",
    "gn:admin2_code":"89",
    "gn:admin3_code":"892",
    "gn:admin4_code":"89347",
    "gn:asciiname":"Vilaine",
    "gn:country_code":"FR",
    "gn:dem":356,
    "gn:feature_class":"P",
    "gn:feature_code":"PPL",
    "gn:name":"Vilaine",
    "gn:population":0,
    "gn:timezone":"Europe/Paris",
    "iso:country":"FR",
    "wof:name":"Vilaine",
    "wof:placetype":"locality"
},
  "geometry": {"coordinates":[3.94238,47.39286],"type":"Point"}
}