{
  "type": "Feature",
  "properties": {
    "gn:admin1_code":"84",
    "gn:admin2_code":"42",
    "gn:admin3_code":"423",
    "gn:admin4_code":"42234",
    "gn:asciiname":"Villemagne",
    "gn:country_code":"FR",
    "gn:dem":616,
    "gn:feature_class":"P",
    "gn:feature_code":"PPL",
    "gn:name":"Villemagne",
    "gn:population":0,
    "gn:timezone":"Europe/Paris",
    "iso:country":"FR",
    "wof:name":"Villemagne",
    "wof:placetype":"locality"
},
  "geometry": {"coordinates":[4.36667,45.51667],"type":"Point"}
}