{
  "type": "Feature",
  "properties": {
    "gn:admin1_code":"84",
    "gn:admin2_code":"42",
    "gn:admin3_code":"423",
    "gn:admin4_code":"42234",
    "gn:asciiname":"Villemagne",
    "gn:country_code":"FR",
    "gn:dem":616,
    "gn:feature_class":"P",
    "gn:feature_code":"PPL",
    "gn:name":"Villemagne",
    "gn:population":0,
    "gn:timezone":"Europe/Paris",
    "iso:country":"FR",
    "name:cat_x_preferred":[
        "Vilamanha"
    ],
    "name:ceb_x_preferred":[
        "Villemagne"
    ],
    "name:deu_x_preferred":[
        "Villemagne"
    ],
    "name:eus_x_preferred":[
        "Villemagne"
    ],
    "name:fra_x_preferred":[
        "Villemagne"
    ],
    "name:hun_x_preferred":[
        "Villemagne"
    ],
    "name:hye_x_preferred":[
        "\u054e\u056b\u056c\u0574\u0561\u0576"
    ],
    "name:ita_x_preferred":[
        "Villemagne"
    ],
    "name:kaz_x_preferred":[
        "\u0412\u0438\u043b\u044c\u043c\u0430\u043d\u044c"
    ],
    "name:lat_x_preferred":[
        "Villemagne"
    ],
    "name:lmo_x_preferred":[
        "Villemagne"
    ],
    "name:mlg_x_preferred":[
        "Villemagne"
    ],
    "name:msa_x_preferred":[
        "Villemagne"
    ],
    "name:nld_x_preferred":[
        "Villemagne"
    ],
    "name:oci_x_preferred":[
        "Vilamanha"
    ],
    "name:pms_x_preferred":[
        "Villemagne"
    ],
    "name:pol_x_preferred":[
        "Villemagne"
    ],
    "name:por_x_preferred":[
        "Villemagne"
    ],
    "name:ron_x_preferred":[
        "Villemagne"
    ],
    "name:rus_x_preferred":[
        "\u0412\u0438\u043b\u044c\u043c\u0430\u043d\u044c"
    ],
    "name:slk_x_preferred":[
        "Villemagne"
    ],
    "name:spa_x_preferred":[
        "Villemagne"
    ],
    "name:swe_x_preferred":[
        "Villemagne"
    ],
    "name:ukr_x_preferred":[
        "\u0412\u0456\u043b\u044c\u043c\u0430\u043d\u044c"
    ],
    "name:vie_x_preferred":[
        "Villemagne"
    ],
    "name:vol_x_preferred":[
        "Villemagne"
    ],
    "name:war_x_preferred":[
        "Villemagne"
    ],
    "name:zho_x_preferred":[
        "\u7ef4\u83b1\u9a6c\u5c3c"
    ],
    "wof:name":"Villemagne",
    "wof:placetype":"locality"
},
  "geometry": {"coordinates":[4.36667,45.51667],"type":"Point"}
}