{
  "type": "Feature",
  "properties": {
    "gn:admin1_code":"76",
    "gn:admin2_code":"32",
    "gn:admin3_code":"322",
    "gn:admin4_code":"32390",
    "gn:asciiname":"Saint-Martin-d'Armagnac",
    "gn:country_code":"FR",
    "gn:dem":143,
    "gn:feature_class":"P",
    "gn:feature_code":"PPL",
    "gn:name":"Saint-Martin-d\u2019Armagnac",
    "gn:population":0,
    "gn:timezone":"Europe/Paris",
    "iso:country":"FR",
    "name:bug_x_preferred":[
        "Saint-Martin-d'Armagnac"
    ],
    "name:ceb_x_preferred":[
        "Saint-Martin-d'Armagnac"
    ],
    "name:eus_x_preferred":[
        "Saint-Martin-d'Armagnac"
    ],
    "name:fra_x_preferred":[
        "Saint-Martin-d'Armagnac"
    ],
    "name:hun_x_preferred":[
        "Saint-Martin-d\u2019Armagnac"
    ],
    "name:ind_x_preferred":[
        "Saint-Martin-d'Armagnac"
    ],
    "name:ita_x_preferred":[
        "Saint-Martin-d'Armagnac"
    ],
    "name:lat_x_preferred":[
        "Saint-Martin-d'Armagnac"
    ],
    "name:mlg_x_preferred":[
        "Saint-Martin-d'Armagnac"
    ],
    "name:msa_x_preferred":[
        "Saint-Martin-d'Armagnac"
    ],
    "name:nld_x_preferred":[
        "Saint-Martin-d'Armagnac"
    ],
    "name:pms_x_preferred":[
        "Saint-Martin-d'Armagnac"
    ],
    "name:pol_x_preferred":[
        "Saint-Martin-d\u2019Armagnac"
    ],
    "name:por_x_preferred":[
        "Saint-Martin-d'Armagnac"
    ],
    "name:ron_x_preferred":[
        "Saint-Martin-d'Armagnac"
    ],
    "name:rus_x_preferred":[
        "\u0421\u0435\u043d-\u041c\u0430\u0440\u0442\u0435\u043d-\u0434\u2019\u0410\u0440\u043c\u0430\u043d\u044c\u044f\u043a"
    ],
    "name:slk_x_preferred":[
        "Saint-Martin-d\u2019Armagnac"
    ],
    "name:spa_x_preferred":[
        "Saint-Martin-d'Armagnac"
    ],
    "name:swe_x_preferred":[
        "Saint-Martin-d'Armagnac"
    ],
    "name:ukr_x_preferred":[
        "\u0421\u0435\u043d-\u041c\u0430\u0440\u0442\u0435\u043d-\u0434'\u0410\u0440\u043c\u0430\u043d\u044c\u044f\u043a"
    ],
    "name:und_x_variant":[
        "Saint-Martin",
        "Saint-Martin-d\u2019Armagnac"
    ],
    "name:urd_x_preferred":[
        "\u0633\u06cc\u0646\u0679-\u0645\u0627\u0631\u0679\u0646-\u062f\u0631\u0645\u06af\u0646\u0627\u06a9"
    ],
    "name:vie_x_preferred":[
        "Saint-Martin-d'Armagnac"
    ],
    "name:vol_x_preferred":[
        "Saint-Martin-d'Armagnac"
    ],
    "name:war_x_preferred":[
        "Saint-Martin-d'Armagnac"
    ],
    "name:zho_x_preferred":[
        "\u5723\u9a6c\u4e01\u8fbe\u5c14\u9a6c\u5c3c\u4e9a\u514b"
    ],
    "wof:name":"Saint-Martin-d'Armagnac",
    "wof:placetype":"locality"
},
  "geometry": {"coordinates":[-0.06634,43.71509],"type":"Point"}
}