{
  "type": "Feature",
  "properties": {
    "gn:admin1_code":"76",
    "gn:admin2_code":"32",
    "gn:admin3_code":"322",
    "gn:admin4_code":"32390",
    "gn:asciiname":"Saint-Martin-d'Armagnac",
    "gn:country_code":"FR",
    "gn:dem":143,
    "gn:feature_class":"P",
    "gn:feature_code":"PPL",
    "gn:name":"Saint-Martin-d\u2019Armagnac",
    "gn:population":0,
    "gn:timezone":"Europe/Paris",
    "iso:country":"FR",
    "name:und_x_variant":[
        "Saint-Martin",
        "Saint-Martin-d\u2019Armagnac"
    ],
    "wof:name":"Saint-Martin-d'Armagnac",
    "wof:placetype":"locality"
},
  "geometry": {"coordinates":[-0.06634,43.71509],"type":"Point"}
}