{
  "type": "Feature",
  "properties": {
    "gn:admin1_code":"24",
    "gn:admin2_code":"41",
    "gn:admin3_code":"413",
    "gn:admin4_code":"41218",
    "gn:asciiname":"Les Barbillons",
    "gn:country_code":"FR",
    "gn:dem":123,
    "gn:feature_class":"P",
    "gn:feature_code":"PPL",
    "gn:name":"Les Barbillons",
    "gn:population":0,
    "gn:timezone":"Europe/Paris",
    "iso:country":"FR",
    "wof:name":"Les Barbillons",
    "wof:placetype":"locality"
},
  "geometry": {"coordinates":[1.79552,47.26848],"type":"Point"}
}