{
  "type": "Feature",
  "properties": {
    "frgov:code_epci":"200070282",
    "frgov:insee_arr":"1",
    "frgov:insee_com":"16394",
    "frgov:insee_dep":"16",
    "frgov:insee_reg":"75",
    "frgov:nom_com":"Vaux-Lavalette",
    "frgov:nom_com_m":"VAUX-LAVALETTE",
    "frgov:nom_dep":"CHARENTE",
    "frgov:nom_reg":"NOUVELLE-AQUITAINE",
    "frgov:statut":"Commune simple",
    "gn:admin1_code":"75",
    "gn:admin2_code":"16",
    "gn:admin3_code":"161",
    "gn:admin4_code":"16394",
    "gn:asciiname":"Vaux-Lavalette",
    "gn:country_code":"FR",
    "gn:dem":106,
    "gn:feature_class":"P",
    "gn:feature_code":"PPL",
    "gn:name":"Vaux-Lavalette",
    "gn:population":0,
    "gn:timezone":"Europe/Paris",
    "iso:country":"FR",
    "name:cat_x_preferred":[
        "Vaus"
    ],
    "name:ceb_x_preferred":[
        "Vaux-Lavalette"
    ],
    "name:deu_x_preferred":[
        "Vaux-Lavalette"
    ],
    "name:eus_x_preferred":[
        "Vaux-Lavalette"
    ],
    "name:fas_x_preferred":[
        "\u0648\u0648-\u0644\u0627\u0648\u0627\u0644\u062a"
    ],
    "name:fra_x_preferred":[
        "Vaux-Lavalette"
    ],
    "name:hun_x_preferred":[
        "Vaux-Lavalette"
    ],
    "name:hye_x_preferred":[
        "\u054e\u0578 \u053c\u0561\u057e\u0561\u056c\u0565\u0569"
    ],
    "name:ita_x_preferred":[
        "Vaux-Lavalette"
    ],
    "name:lat_x_preferred":[
        "Vaux-Lavalette"
    ],
    "name:msa_x_preferred":[
        "Vaux-Lavalette"
    ],
    "name:nld_x_preferred":[
        "Vaux-Lavalette"
    ],
    "name:oci_x_preferred":[
        "Vaux-Lavalette"
    ],
    "name:pol_x_preferred":[
        "Vaux-Lavalette"
    ],
    "name:por_x_preferred":[
        "Vaux-Lavalette"
    ],
    "name:ron_x_preferred":[
        "Vaux-Lavalette"
    ],
    "name:rus_x_preferred":[
        "\u0412\u043e-\u041b\u0430\u0432\u0430\u043b\u0435\u0442"
    ],
    "name:slk_x_preferred":[
        "Vaux-Lavalette"
    ],
    "name:spa_x_preferred":[
        "Vaux-Lavalette"
    ],
    "name:swe_x_preferred":[
        "Vaux-Lavalette"
    ],
    "name:ukr_x_preferred":[
        "\u0412\u043e-\u041b\u0430\u0432\u0430\u043b\u0435\u0442\u0442"
    ],
    "name:vie_x_preferred":[
        "Vaux-Lavalette"
    ],
    "name:vol_x_preferred":[
        "Vaux-Lavalette"
    ],
    "name:war_x_preferred":[
        "Vaux-Lavalette"
    ],
    "name:zho_x_preferred":[
        "\u6c83\u62c9\u74e6\u83b1\u7279"
    ],
    "qs:a0":"France",
    "qs:a1":"CHARENTE",
    "qs:a1_lc":"16",
    "qs:a1r":"POITOU-CHARENTES",
    "qs:a1r_lc":"54",
    "qs:a2_lc":"28",
    "qs:a2r_lc":"1",
    "qs:adm0":"France",
    "qs:adm0_a3":"FRA",
    "qs:la":"VAUX-LAVALETTE",
    "qs:la_lc":"16394",
    "qs:level":"localadmin",
    "qs:type":"Commune simple",
    "wof:coterminous":[
        404413201
    ],
    "wof:name":"Vaux-Lavalette",
    "wof:placetype":"locality",
    "wof:placetype_local":"Commune simple"
},
  "geometry": {"coordinates":[0.23333,45.41667],"type":"Point"}
}