{
  "type": "Feature",
  "properties": {
    "gn:admin1_code":"75",
    "gn:admin2_code":"16",
    "gn:admin3_code":"161",
    "gn:admin4_code":"16394",
    "gn:asciiname":"Vaux-Lavalette",
    "gn:country_code":"FR",
    "gn:dem":106,
    "gn:feature_class":"P",
    "gn:feature_code":"PPL",
    "gn:name":"Vaux-Lavalette",
    "gn:population":0,
    "gn:timezone":"Europe/Paris",
    "iso:country":"FR",
    "name:cat_x_preferred":[
        "Vaus"
    ],
    "name:ceb_x_preferred":[
        "Vaux-Lavalette"
    ],
    "name:deu_x_preferred":[
        "Vaux-Lavalette"
    ],
    "name:eus_x_preferred":[
        "Vaux-Lavalette"
    ],
    "name:fas_x_preferred":[
        "\u0648\u0648-\u0644\u0627\u0648\u0627\u0644\u062a"
    ],
    "name:fra_x_preferred":[
        "Vaux-Lavalette"
    ],
    "name:hun_x_preferred":[
        "Vaux-Lavalette"
    ],
    "name:hye_x_preferred":[
        "\u054e\u0578 \u053c\u0561\u057e\u0561\u056c\u0565\u0569"
    ],
    "name:ita_x_preferred":[
        "Vaux-Lavalette"
    ],
    "name:lat_x_preferred":[
        "Vaux-Lavalette"
    ],
    "name:msa_x_preferred":[
        "Vaux-Lavalette"
    ],
    "name:nld_x_preferred":[
        "Vaux-Lavalette"
    ],
    "name:oci_x_preferred":[
        "Vaux-Lavalette"
    ],
    "name:pol_x_preferred":[
        "Vaux-Lavalette"
    ],
    "name:por_x_preferred":[
        "Vaux-Lavalette"
    ],
    "name:ron_x_preferred":[
        "Vaux-Lavalette"
    ],
    "name:rus_x_preferred":[
        "\u0412\u043e-\u041b\u0430\u0432\u0430\u043b\u0435\u0442"
    ],
    "name:slk_x_preferred":[
        "Vaux-Lavalette"
    ],
    "name:spa_x_preferred":[
        "Vaux-Lavalette"
    ],
    "name:swe_x_preferred":[
        "Vaux-Lavalette"
    ],
    "name:ukr_x_preferred":[
        "\u0412\u043e-\u041b\u0430\u0432\u0430\u043b\u0435\u0442\u0442"
    ],
    "name:vie_x_preferred":[
        "Vaux-Lavalette"
    ],
    "name:vol_x_preferred":[
        "Vaux-Lavalette"
    ],
    "name:war_x_preferred":[
        "Vaux-Lavalette"
    ],
    "name:zho_x_preferred":[
        "\u6c83\u62c9\u74e6\u83b1\u7279"
    ],
    "wof:name":"Vaux-Lavalette",
    "wof:placetype":"locality"
},
  "geometry": {"coordinates":[0.23333,45.41667],"type":"Point"}
}