{
  "type": "Feature",
  "properties": {
    "gn:admin1_code":"75",
    "gn:admin2_code":"79",
    "gn:admin3_code":"792",
    "gn:admin4_code":"79133",
    "gn:asciiname":"Rouvre",
    "gn:country_code":"FR",
    "gn:dem":82,
    "gn:feature_class":"P",
    "gn:feature_code":"PPL",
    "gn:name":"Rouvre",
    "gn:population":0,
    "gn:timezone":"Europe/Paris",
    "iso:country":"FR",
    "name:ceb_x_preferred":[
        "Rouvre"
    ],
    "name:deu_x_preferred":[
        "Rouvre"
    ],
    "name:fra_x_preferred":[
        "Rouvre"
    ],
    "name:pol_x_preferred":[
        "Rouvre"
    ],
    "wof:name":"Rouvre",
    "wof:placetype":"locality"
},
  "geometry": {"coordinates":[-0.40286,46.42938],"type":"Point"}
}