{
  "type": "Feature",
  "properties": {
    "gn:admin1_code":"27",
    "gn:admin2_code":"21",
    "gn:admin3_code":"213",
    "gn:admin4_code":"21429.0",
    "gn:asciiname":"Villiers",
    "gn:country_code":"FR",
    "gn:dem":249,
    "gn:feature_class":"P",
    "gn:feature_code":"PPL",
    "gn:name":"Villiers",
    "gn:population":0,
    "gn:timezone":"Europe/Paris",
    "iso:country":"FR",
    "wof:name":"Villiers",
    "wof:placetype":"locality"
},
  "geometry": {"coordinates":[4.33488,47.59929],"type":"Point"}
}