{
  "type": "Feature",
  "properties": {
    "gn:population":1049,
    "iso:country":"FO",
    "name:bar_x_preferred":[
        "Kollafj\u00f8r\u00f0ur"
    ],
    "name:cat_x_preferred":[
        "Kollafj\u00f8r\u00f0ur"
    ],
    "name:dan_x_preferred":[
        "Kollafj\u00f8r\u00f0ur"
    ],
    "name:deu_x_preferred":[
        "Kollafj\u00f8r\u00f0ur"
    ],
    "name:ell_x_preferred":[
        "\u039a\u03cc\u03bb\u03b1\u03c6\u03b9\u03bf\u03c1\u03bd\u03c4\u03bf\u03c5\u03c1"
    ],
    "name:eng_x_preferred":[
        "Kollafj\u00f8r\u00f0ur"
    ],
    "name:fao_x_preferred":[
        "Kollafj\u00f8r\u00f0ur"
    ],
    "name:fra_x_preferred":[
        "Kollafj\u00f8r\u00f0ur"
    ],
    "name:glv_x_preferred":[
        "Kollafj\u00f8r\u00f0ur"
    ],
    "name:hun_x_preferred":[
        "Kollafj\u00f8r\u00f0ur"
    ],
    "name:isl_x_preferred":[
        "Kollafj\u00f8r\u00f0ur"
    ],
    "name:lit_x_preferred":[
        "Kolafjorduras"
    ],
    "name:nld_x_preferred":[
        "Kollafj\u00f8r\u00f0ur"
    ],
    "name:nno_x_preferred":[
        "Kollafj\u00f8r\u00f0ur"
    ],
    "name:nob_x_preferred":[
        "Kollafj\u00f8r\u00f0ur"
    ],
    "name:nor_x_preferred":[
        "Kollafj\u00f8r\u00f0ur"
    ],
    "name:oss_x_preferred":[
        "\u041a\u043e\u0442\u043b\u0430\u0444\u044c\u0451\u0440\u0443\u0440"
    ],
    "name:pol_x_preferred":[
        "Kollafj\u00f8r\u00f0ur"
    ],
    "name:por_x_preferred":[
        "Kollafj\u00f8r\u00f0ur"
    ],
    "name:ron_x_preferred":[
        "Kollafj\u00f8r\u00f0ur"
    ],
    "name:rus_x_preferred":[
        "\u041a\u043e\u0434\u043b\u0430\u0444\u044c\u043e\u0440\u0434\u0443\u0440"
    ],
    "name:spa_x_preferred":[
        "Kollafj\u00f8r\u00f0ur"
    ],
    "name:swe_x_preferred":[
        "Kollafj\u00f8r\u00f0ur"
    ],
    "name:unk_x_variant":[
        "Kollefiord Church"
    ],
    "qs:a0":"Foroyar#F\u00e6r\u00f8erne",
    "qs:a1":"*",
    "qs:a1r":"0",
    "qs:adm0":"Foroyar#F\u00e6r\u00f8erne",
    "qs:la_lc":"*",
    "qs:level":"locality",
    "qs:loc":"Kollafj\u00f8rdur",
    "qs:loc_alt":"Kollafjordur",
    "qs:pop":0,
    "qs:type":"buffered point",
    "wd:wordcount":653,
    "wof:name":"Kollafj\u00f8rdur",
    "wof:placetype":"locality",
    "wof:population":1049
},
  "geometry": {"coordinates":[-6.873705,62.122071],"type":"Point"}
}