{
  "type": "Feature",
  "properties": {
    "gn:admin1_code":"76",
    "gn:admin2_code":"30",
    "gn:admin3_code":"303",
    "gn:admin4_code":"30229",
    "gn:asciiname":"La Coste",
    "gn:country_code":"FR",
    "gn:dem":361,
    "gn:feature_class":"P",
    "gn:feature_code":"PPL",
    "gn:name":"La Coste",
    "gn:population":0,
    "gn:timezone":"Europe/Paris",
    "iso:country":"FR",
    "wof:name":"La Coste",
    "wof:placetype":"locality"
},
  "geometry": {"coordinates":[3.67017,44.0432],"type":"Point"}
}