{
  "type": "Feature",
  "properties": {
    "gn:admin1_code":"11",
    "gn:admin2_code":"78",
    "gn:admin3_code":"782",
    "gn:admin4_code":"78236",
    "gn:asciiname":"Feranville",
    "gn:country_code":"FR",
    "gn:dem":124,
    "gn:feature_class":"P",
    "gn:feature_code":"PPL",
    "gn:name":"F\u00e9ranville",
    "gn:population":0,
    "gn:timezone":"Europe/Paris",
    "iso:country":"FR",
    "wof:name":"Feranville",
    "wof:placetype":"locality"
},
  "geometry": {"coordinates":[1.74689,48.86319],"type":"Point"}
}