{
  "type": "Feature",
  "properties": {
    "frgov:code_epci":"200073393",
    "frgov:insee_arr":"1",
    "frgov:insee_com":"43133",
    "frgov:insee_dep":"43",
    "frgov:insee_reg":"84",
    "frgov:nom_com":"Merc\u0153ur",
    "frgov:nom_com_m":"MERC\u0152UR",
    "frgov:nom_dep":"HAUTE-LOIRE",
    "frgov:nom_reg":"AUVERGNE-RHONE-ALPES",
    "frgov:statut":"Commune simple",
    "gn:admin1_code":"84",
    "gn:admin2_code":"43",
    "gn:admin3_code":"431",
    "gn:admin4_code":"43133",
    "gn:asciiname":"Mercoeur",
    "gn:country_code":"FR",
    "gn:dem":843,
    "gn:feature_class":"P",
    "gn:feature_code":"PPL",
    "gn:name":"Merc\u0153ur",
    "gn:population":0,
    "gn:timezone":"Europe/Paris",
    "iso:country":"FR",
    "name:fra_x_preferred":[
        "Merc\u0153ur"
    ],
    "qs:a0":"France",
    "qs:a1":"HAUTE-LOIRE",
    "qs:a1_lc":"43",
    "qs:a1r":"AUVERGNE",
    "qs:a1r_lc":"83",
    "qs:a2_lc":"11",
    "qs:a2r_lc":"1",
    "qs:adm0":"France",
    "qs:adm0_a3":"FRA",
    "qs:la":"MERCOEUR",
    "qs:la_lc":"43133",
    "qs:level":"localadmin",
    "qs:type":"Commune simple",
    "wof:coterminous":[
        404355043
    ],
    "wof:name":"Mercoeur",
    "wof:placetype":"locality",
    "wof:placetype_local":"Commune simple"
},
  "geometry": {"coordinates":[3.3,45.2],"type":"Point"}
}