{
  "type": "Feature",
  "properties": {
    "gn:gn_country":"FR",
    "gn:gn_fcode":"PPL",
    "gn:gn_pop":0,
    "iso:country":"FR",
    "name:ara_x_preferred":[
        "\u0644\u0648\u062d\u0629 \u0627\u0644\u0623\u0644\u0648\u0627\u0646"
    ],
    "name:deu_x_preferred":[
        "Palette"
    ],
    "name:fra_x_preferred":[
        "Palette"
    ],
    "name:ita_x_preferred":[
        "Palette"
    ],
    "name:jpn_x_preferred":[
        "\u30d1\u30ec\u30c3\u30c8"
    ],
    "name:kor_x_preferred":[
        "\ud314\ub808\ud2b8"
    ],
    "name:rus_x_preferred":[
        "\u041f\u0430\u043b\u0438\u0442\u0440\u0430"
    ],
    "name:swe_x_preferred":[
        "Palett"
    ],
    "qs_pg:aaroncc":"FR",
    "qs_pg:gn_country":"FR",
    "qs_pg:gn_fcode":"PPL",
    "qs_pg:gn_pop":0,
    "qs_pg:name":"Palette",
    "qs_pg:name_adm0":"France",
    "qs_pg:name_adm1":"Provence-Alpes-C\u00f4te d'Azur",
    "qs_pg:photos":121,
    "qs_pg:photos_1k":25,
    "qs_pg:photos_9k":1,
    "qs_pg:photos_9r":3,
    "qs_pg:photos_all":121,
    "qs_pg:photos_sr":3,
    "qs_pg:pop_sr":0,
    "qs_pg:qs_pg_placetype":"locality",
    "qs_pg:qs_pg_placetype_gp":"Town",
    "qs_pg:woe_adm0":23424819,
    "woe:adm0_id":23424819,
    "woe:name_adm0":"France",
    "woe:name_adm1":"Provence-Alpes-C\u00f4te d'Azur",
    "woe:placetype":"Town",
    "wof:name":"Palette",
    "wof:placetype":"neighbourhood"
},
  "geometry": {"coordinates":[5.49299,43.51009],"type":"Point"}
}