{
  "type": "Feature",
  "properties": {
    "frgov:code_epci":"200043396",
    "frgov:insee_arr":"1",
    "frgov:insee_com":"59076",
    "frgov:insee_dep":"59",
    "frgov:insee_reg":"32",
    "frgov:nom_com":"Bettignies",
    "frgov:nom_com_m":"BETTIGNIES",
    "frgov:nom_dep":"NORD",
    "frgov:nom_reg":"HAUTS-DE-FRANCE",
    "frgov:statut":"Commune simple",
    "gn:admin1_code":"32",
    "gn:admin2_code":"59",
    "gn:admin3_code":"591",
    "gn:admin4_code":"59076",
    "gn:asciiname":"Bettignies",
    "gn:country_code":"FR",
    "gn:dem":143,
    "gn:feature_class":"P",
    "gn:feature_code":"PPL",
    "gn:name":"Bettignies",
    "gn:population":0,
    "gn:timezone":"Europe/Paris",
    "iso:country":"FR",
    "name:bre_x_preferred":[
        "Bettignies"
    ],
    "name:cat_x_preferred":[
        "Bettignies"
    ],
    "name:ceb_x_preferred":[
        "Bettignies"
    ],
    "name:deu_x_preferred":[
        "Bettignies"
    ],
    "name:epo_x_preferred":[
        "Bettignies"
    ],
    "name:eus_x_preferred":[
        "Bettignies"
    ],
    "name:fra_x_preferred":[
        "Bettignies"
    ],
    "name:hun_x_preferred":[
        "Bettignies"
    ],
    "name:ind_x_preferred":[
        "Bettignies"
    ],
    "name:ita_x_preferred":[
        "Bettignies"
    ],
    "name:kaz_x_preferred":[
        "\u0411\u0435\u0442\u0442\u0438\u043d\u0438"
    ],
    "name:lat_x_preferred":[
        "Bettignies"
    ],
    "name:mlg_x_preferred":[
        "Bettignies"
    ],
    "name:msa_x_preferred":[
        "Bettignies"
    ],
    "name:nld_x_preferred":[
        "Bettignies"
    ],
    "name:oci_x_preferred":[
        "Bettignies"
    ],
    "name:pol_x_preferred":[
        "Bettignies"
    ],
    "name:ron_x_preferred":[
        "Bettignies"
    ],
    "name:slk_x_preferred":[
        "Bettignies"
    ],
    "name:spa_x_preferred":[
        "Bettignies"
    ],
    "name:srp_x_preferred":[
        "\u0411\u0435\u0442\u0438\u045a\u0438"
    ],
    "name:swe_x_preferred":[
        "Bettignies"
    ],
    "name:ukr_x_preferred":[
        "\u0411\u0435\u0442\u0442\u0456\u043d\u0456"
    ],
    "name:vie_x_preferred":[
        "Bettignies"
    ],
    "name:vol_x_preferred":[
        "Bettignies"
    ],
    "name:war_x_preferred":[
        "Bettignies"
    ],
    "name:zho_x_preferred":[
        "\u8d1d\u8482\u5c3c"
    ],
    "qs:a0":"France",
    "qs:a1":"NORD",
    "qs:a1_lc":"59",
    "qs:a1r":"NORD-PAS-DE-CALAIS",
    "qs:a1r_lc":"31",
    "qs:a2_lc":"44",
    "qs:a2r_lc":"1",
    "qs:adm0":"France",
    "qs:adm0_a3":"FRA",
    "qs:la":"BETTIGNIES",
    "qs:la_lc":"59076",
    "qs:level":"localadmin",
    "qs:type":"Commune simple",
    "wof:coterminous":[
        404415995
    ],
    "wof:name":"Bettignies",
    "wof:placetype":"locality",
    "wof:placetype_local":"Commune simple"
},
  "geometry": {"coordinates":[3.9731,50.33401],"type":"Point"}
}