{
  "type": "Feature",
  "properties": {
    "gn:admin1_code":"11",
    "gn:admin2_code":"77",
    "gn:admin3_code":"773",
    "gn:admin4_code":"77311",
    "gn:asciiname":"La Fontaine-Geoffroy",
    "gn:country_code":"FR",
    "gn:dem":111,
    "gn:feature_class":"P",
    "gn:feature_code":"PPL",
    "gn:name":"La Fontaine-Geoffroy",
    "gn:population":0,
    "gn:timezone":"Europe/Paris",
    "iso:country":"FR",
    "wof:name":"La Fontaine-Geoffroy",
    "wof:placetype":"locality"
},
  "geometry": {"coordinates":[3.06139,48.45502000000001],"type":"Point"}
}