{
  "type": "Feature",
  "properties": {
    "gn:admin1_code":"84",
    "gn:admin2_code":"38",
    "gn:admin3_code":"382",
    "gn:admin4_code":"38026.0",
    "gn:asciiname":"La Brosse",
    "gn:country_code":"FR",
    "gn:dem":200,
    "gn:feature_class":"P",
    "gn:feature_code":"PPL",
    "gn:name":"La Brosse",
    "gn:population":0,
    "gn:timezone":"Europe/Paris",
    "iso:country":"FR",
    "name:deu_x_preferred":[
        "La Brosse"
    ],
    "name:fra_x_preferred":[
        "La Brosse"
    ],
    "wof:name":"La Brosse",
    "wof:placetype":"locality"
},
  "geometry": {"coordinates":[5.30002,45.82768],"type":"Point"}
}