{
  "type": "Feature",
  "properties": {
    "gn:admin1_code":"76",
    "gn:admin2_code":"46",
    "gn:admin3_code":"462",
    "gn:admin4_code":"46122",
    "gn:asciiname":"Puy del Claux",
    "gn:country_code":"FR",
    "gn:dem":316,
    "gn:feature_class":"P",
    "gn:feature_code":"PPL",
    "gn:name":"Puy del Claux",
    "gn:population":0,
    "gn:timezone":"Europe/Paris",
    "iso:country":"FR",
    "wof:name":"Puy del Claux",
    "wof:placetype":"locality"
},
  "geometry": {"coordinates":[1.73575,44.87016],"type":"Point"}
}