{
  "type": "Feature",
  "properties": {
    "gn:admin1_code":"24",
    "gn:admin2_code":"28",
    "gn:admin3_code":"283",
    "gn:admin4_code":"28098",
    "gn:asciiname":"Les Osmeaux",
    "gn:country_code":"FR",
    "gn:dem":92,
    "gn:feature_class":"P",
    "gn:feature_code":"PPL",
    "gn:name":"Les Osmeaux",
    "gn:population":0,
    "gn:timezone":"Europe/Paris",
    "iso:country":"FR",
    "wof:name":"Les Osmeaux",
    "wof:placetype":"locality"
},
  "geometry": {"coordinates":[1.41226,48.76414000000001],"type":"Point"}
}