{
  "type": "Feature",
  "properties": {
    "gn:admin1_code":"27",
    "gn:admin2_code":"58",
    "gn:admin3_code":"582",
    "gn:admin4_code":"58304",
    "gn:asciiname":"Charlay",
    "gn:country_code":"FR",
    "gn:dem":246,
    "gn:feature_class":"P",
    "gn:feature_code":"PPL",
    "gn:name":"Charlay",
    "gn:population":0,
    "gn:timezone":"Europe/Paris",
    "iso:country":"FR",
    "wof:name":"Charlay",
    "wof:placetype":"locality"
},
  "geometry": {"coordinates":[3.41476,47.35428],"type":"Point"}
}