{
  "type": "Feature",
  "properties": {
    "gn:admin1_code":"32",
    "gn:admin2_code":"62",
    "gn:admin3_code":"625",
    "gn:admin4_code":"62852",
    "gn:asciiname":"Pont d'Oye",
    "gn:country_code":"FR",
    "gn:dem":2,
    "gn:feature_class":"P",
    "gn:feature_code":"PPL",
    "gn:name":"Pont d\u2019Oye",
    "gn:population":0,
    "gn:timezone":"Europe/Paris",
    "iso:country":"FR",
    "wof:name":"Pont d'Oye",
    "wof:placetype":"locality"
},
  "geometry": {"coordinates":[2.04586,50.96284],"type":"Point"}
}