{
  "type": "Feature",
  "properties": {
    "frgov:code_epci":"248200065",
    "frgov:insee_arr":"1",
    "frgov:insee_com":"82129",
    "frgov:insee_dep":"82",
    "frgov:insee_reg":"76",
    "frgov:nom_com":"Montgaillard",
    "frgov:nom_com_m":"MONTGAILLARD",
    "frgov:nom_dep":"TARN-ET-GARONNE",
    "frgov:nom_reg":"OCCITANIE",
    "frgov:statut":"Commune simple",
    "gn:admin1_code":"76",
    "gn:admin2_code":"82",
    "gn:admin3_code":"821",
    "gn:admin4_code":"82129",
    "gn:asciiname":"Montgaillard",
    "gn:country_code":"FR",
    "gn:dem":252,
    "gn:feature_class":"P",
    "gn:feature_code":"PPL",
    "gn:name":"Montgaillard",
    "gn:population":0,
    "gn:timezone":"Europe/Paris",
    "iso:country":"FR",
    "name:arg_x_preferred":[
        "Montgaillard"
    ],
    "name:ceb_x_preferred":[
        "Montgaillard"
    ],
    "name:deu_x_preferred":[
        "Montgaillard"
    ],
    "name:fra_x_preferred":[
        "Montgaillard"
    ],
    "name:hun_x_preferred":[
        "Montgaillard"
    ],
    "name:ita_x_preferred":[
        "Montgaillard"
    ],
    "name:nds_x_preferred":[
        "Montgaillard"
    ],
    "name:nld_x_preferred":[
        "Montgaillard"
    ],
    "name:oci_x_preferred":[
        "Montgalhard"
    ],
    "name:pms_x_preferred":[
        "Montgaillard"
    ],
    "name:pol_x_preferred":[
        "Montgaillard"
    ],
    "name:por_x_preferred":[
        "Montgaillard"
    ],
    "name:rus_x_preferred":[
        "\u041c\u043e\u043d\u0433\u0430\u0439\u0430\u0440"
    ],
    "name:slk_x_preferred":[
        "Montgaillard"
    ],
    "name:slv_x_preferred":[
        "Montgaillard"
    ],
    "name:spa_x_preferred":[
        "Montgaillard"
    ],
    "name:swe_x_preferred":[
        "Montgaillard"
    ],
    "name:ukr_x_preferred":[
        "\u041c\u043e\u043d\u0433\u0430\u044f\u0440"
    ],
    "qs:a0":"France",
    "qs:a1":"TARN-ET-GARONNE",
    "qs:a1_lc":"82",
    "qs:a1r":"MIDI-PYRENEES",
    "qs:a1r_lc":"73",
    "qs:a2_lc":"10",
    "qs:a2r_lc":"1",
    "qs:adm0":"France",
    "qs:adm0_a3":"FRA",
    "qs:la":"MONTGAILLARD",
    "qs:la_lc":"82129",
    "qs:level":"localadmin",
    "qs:type":"Commune simple",
    "wof:coterminous":[
        404410043
    ],
    "wof:name":"Montgaillard",
    "wof:placetype":"locality",
    "wof:placetype_local":"Commune simple"
},
  "geometry": {"coordinates":[0.87633,43.93264],"type":"Point"}
}