{
  "type": "Feature",
  "properties": {
    "gn:country":"FR",
    "gn:fcode":"PPL",
    "gn:population":1259,
    "iso:country":"FR",
    "name:und_x_variant":[
        "Saint Aubin"
    ],
    "qs_pg:aaroncc":"FR",
    "qs_pg:gn_country":"FR",
    "qs_pg:gn_fcode":"PPL",
    "qs_pg:gn_pop":1259,
    "qs_pg:name":"Saint-aubin-sur-risle",
    "qs_pg:name_adm0":"France",
    "qs_pg:name_adm1":"Haute-Normandie",
    "qs_pg:photos_9r":0,
    "qs_pg:photos_sr":0,
    "qs_pg:pop_sr":3,
    "qs_pg:qs_pg_placetype":"locality",
    "qs_pg:qs_pg_placetype_gp":"Town",
    "qs_pg:woe_adm0":23424819,
    "woe:adm0_id":23424819,
    "woe:name_adm0":"France",
    "woe:name_adm1":"Haute-Normandie",
    "woe:placetype":"Town",
    "wof:name":"Saint-aubin-sur-risle",
    "wof:placetype":"neighbourhood",
    "wof:population":1259
},
  "geometry": {"coordinates":[1.06823,49.87162],"type":"Point"}
}