{
  "type": "Feature",
  "properties": {
    "gn:country":"FR",
    "gn:fcode":"PPL",
    "gn:population":0,
    "iso:country":"FR",
    "name:und_x_variant":[
        "Kermeur"
    ],
    "qs_pg:aaroncc":"FR",
    "qs_pg:gn_country":"FR",
    "qs_pg:gn_fcode":"PPL",
    "qs_pg:gn_pop":0,
    "qs_pg:name":"Le Guermeur",
    "qs_pg:name_adm0":"France",
    "qs_pg:name_adm1":"Bretagne",
    "qs_pg:photos":33,
    "qs_pg:photos_1k":7,
    "qs_pg:photos_9k":1,
    "qs_pg:photos_9r":2,
    "qs_pg:photos_all":33,
    "qs_pg:photos_sr":2,
    "qs_pg:pop_sr":0,
    "qs_pg:qs_pg_placetype":"locality",
    "qs_pg:qs_pg_placetype_gp":"Town",
    "qs_pg:woe_adm0":23424819,
    "woe:adm0_id":23424819,
    "woe:name_adm0":"France",
    "woe:name_adm1":"Bretagne",
    "woe:placetype":"Town",
    "wof:name":"Le Guermeur",
    "wof:placetype":"neighbourhood"
},
  "geometry": {"coordinates":[-3.73733,48.46717],"type":"Point"}
}