{
  "type": "Feature",
  "properties": {
    "gn:admin1_code":"24",
    "gn:admin2_code":"45",
    "gn:admin3_code":"451",
    "gn:admin4_code":"45115",
    "gn:asciiname":"La Jacqueminiere",
    "gn:country_code":"FR",
    "gn:dem":174,
    "gn:feature_class":"P",
    "gn:feature_code":"PPL",
    "gn:name":"La Jacquemini\u00e8re",
    "gn:population":0,
    "gn:timezone":"Europe/Paris",
    "iso:country":"FR",
    "wof:name":"La Jacqueminiere",
    "wof:placetype":"locality"
},
  "geometry": {"coordinates":[3.08377,47.99955],"type":"Point"}
}