{
  "type": "Feature",
  "properties": {
    "iso:country":"FR",
    "name:fra_x_variant":[
        "Faubourg-du-Roule"
    ],
    "wof:name":"Faubourg-du-Roule",
    "wof:placetype":"neighbourhood"
},
  "geometry": {"coordinates":[2.304254,48.874698],"type":"Point"}
}