{
  "type": "Feature",
  "properties": {
    "gn:admin1_code":"94",
    "gn:admin2_code":"2A",
    "gn:admin3_code":"2A4",
    "gn:admin4_code":"2A269",
    "gn:asciiname":"Cannella",
    "gn:country_code":"FR",
    "gn:dem":19,
    "gn:feature_class":"P",
    "gn:feature_code":"PPL",
    "gn:name":"Cannella",
    "gn:population":0,
    "gn:timezone":"Europe/Paris",
    "iso:country":"FR",
    "wof:name":"Cannella",
    "wof:placetype":"locality"
},
  "geometry": {"coordinates":[9.39733,41.80424],"type":"Point"}
}