{
  "type": "Feature",
  "properties": {
    "gn:admin1_code":"32",
    "gn:admin2_code":"62",
    "gn:admin3_code":"624",
    "gn:admin4_code":"62257",
    "gn:asciiname":"Prehedre",
    "gn:country_code":"FR",
    "gn:dem":161,
    "gn:feature_class":"P",
    "gn:feature_code":"PPL",
    "gn:name":"Pr\u00e9h\u00e9dr\u00e9",
    "gn:population":0,
    "gn:timezone":"Europe/Paris",
    "iso:country":"FR",
    "wof:name":"Prehedre",
    "wof:placetype":"locality"
},
  "geometry": {"coordinates":[2.06149,50.49938],"type":"Point"}
}