{
  "type": "Feature",
  "properties": {
    "gn:admin1_code":"28",
    "gn:admin2_code":"61",
    "gn:admin3_code":"613",
    "gn:admin4_code":"61491",
    "gn:asciiname":"La Haute Duquerie",
    "gn:country_code":"FR",
    "gn:dem":233,
    "gn:feature_class":"P",
    "gn:feature_code":"PPL",
    "gn:name":"La Haute Duquerie",
    "gn:population":0,
    "gn:timezone":"Europe/Paris",
    "iso:country":"FR",
    "wof:name":"La Haute Duquerie",
    "wof:placetype":"locality"
},
  "geometry": {"coordinates":[0.68249,48.55999],"type":"Point"}
}