{
  "type": "Feature",
  "properties": {
    "gn:admin1_code":"76",
    "gn:admin2_code":"11",
    "gn:admin3_code":"112",
    "gn:admin4_code":"11060",
    "gn:asciiname":"Cailla",
    "gn:country_code":"FR",
    "gn:dem":511,
    "gn:feature_class":"P",
    "gn:feature_code":"PPL",
    "gn:name":"Cailla",
    "gn:population":0,
    "gn:timezone":"Europe/Paris",
    "iso:country":"FR",
    "name:cat_x_preferred":[
        "Calhan"
    ],
    "name:ceb_x_preferred":[
        "Cailla"
    ],
    "name:deu_x_preferred":[
        "Cailla"
    ],
    "name:eus_x_preferred":[
        "Calhan"
    ],
    "name:fra_x_preferred":[
        "Cailla"
    ],
    "name:hun_x_preferred":[
        "Cailla"
    ],
    "name:hye_x_preferred":[
        "\u053f\u0561\u0575\u0561"
    ],
    "name:ita_x_preferred":[
        "Cailla"
    ],
    "name:kaz_x_preferred":[
        "\u041a\u0430\u044f"
    ],
    "name:lat_x_preferred":[
        "Cailla"
    ],
    "name:lmo_x_preferred":[
        "Cailla"
    ],
    "name:msa_x_preferred":[
        "Cailla"
    ],
    "name:nld_x_preferred":[
        "Cailla"
    ],
    "name:oci_x_preferred":[
        "Calhan"
    ],
    "name:pms_x_preferred":[
        "Cailla"
    ],
    "name:pol_x_preferred":[
        "Cailla"
    ],
    "name:por_x_preferred":[
        "Cailla"
    ],
    "name:ron_x_preferred":[
        "Cailla"
    ],
    "name:rus_x_preferred":[
        "\u041a\u0430\u0439\u044f"
    ],
    "name:slk_x_preferred":[
        "Cailla"
    ],
    "name:spa_x_preferred":[
        "Cailla"
    ],
    "name:srp_x_preferred":[
        "\u041a\u0430\u0458\u0430"
    ],
    "name:swe_x_preferred":[
        "Cailla"
    ],
    "name:ukr_x_preferred":[
        "\u041a\u0430\u044f"
    ],
    "name:vie_x_preferred":[
        "Cailla"
    ],
    "name:vol_x_preferred":[
        "Cailla"
    ],
    "name:war_x_preferred":[
        "Cailla"
    ],
    "wof:name":"Cailla",
    "wof:placetype":"locality"
},
  "geometry": {"coordinates":[2.19594,42.81416],"type":"Point"}
}