{
  "type": "Feature",
  "properties": {
    "frgov:code_epci":"200043776",
    "frgov:insee_arr":"2",
    "frgov:insee_com":"11060",
    "frgov:insee_dep":"11",
    "frgov:insee_reg":"76",
    "frgov:nom_com":"Cailla",
    "frgov:nom_com_m":"CAILLA",
    "frgov:nom_dep":"AUDE",
    "frgov:nom_reg":"OCCITANIE",
    "frgov:statut":"Commune simple",
    "gn:admin1_code":"76",
    "gn:admin2_code":"11",
    "gn:admin3_code":"112",
    "gn:admin4_code":"11060",
    "gn:asciiname":"Cailla",
    "gn:country_code":"FR",
    "gn:dem":511,
    "gn:feature_class":"P",
    "gn:feature_code":"PPL",
    "gn:name":"Cailla",
    "gn:population":0,
    "gn:timezone":"Europe/Paris",
    "iso:country":"FR",
    "name:cat_x_preferred":[
        "Calhan"
    ],
    "name:ceb_x_preferred":[
        "Cailla"
    ],
    "name:deu_x_preferred":[
        "Cailla"
    ],
    "name:eus_x_preferred":[
        "Calhan"
    ],
    "name:fra_x_preferred":[
        "Cailla"
    ],
    "name:hun_x_preferred":[
        "Cailla"
    ],
    "name:hye_x_preferred":[
        "\u053f\u0561\u0575\u0561"
    ],
    "name:ita_x_preferred":[
        "Cailla"
    ],
    "name:kaz_x_preferred":[
        "\u041a\u0430\u044f"
    ],
    "name:lat_x_preferred":[
        "Cailla"
    ],
    "name:lmo_x_preferred":[
        "Cailla"
    ],
    "name:msa_x_preferred":[
        "Cailla"
    ],
    "name:nld_x_preferred":[
        "Cailla"
    ],
    "name:oci_x_preferred":[
        "Calhan"
    ],
    "name:pms_x_preferred":[
        "Cailla"
    ],
    "name:pol_x_preferred":[
        "Cailla"
    ],
    "name:por_x_preferred":[
        "Cailla"
    ],
    "name:ron_x_preferred":[
        "Cailla"
    ],
    "name:rus_x_preferred":[
        "\u041a\u0430\u0439\u044f"
    ],
    "name:slk_x_preferred":[
        "Cailla"
    ],
    "name:spa_x_preferred":[
        "Cailla"
    ],
    "name:srp_x_preferred":[
        "\u041a\u0430\u0458\u0430"
    ],
    "name:swe_x_preferred":[
        "Cailla"
    ],
    "name:ukr_x_preferred":[
        "\u041a\u0430\u044f"
    ],
    "name:vie_x_preferred":[
        "Cailla"
    ],
    "name:vol_x_preferred":[
        "Cailla"
    ],
    "name:war_x_preferred":[
        "Cailla"
    ],
    "qs:a0":"France",
    "qs:a1":"AUDE",
    "qs:a1_lc":"11",
    "qs:a1r":"LANGUEDOC-ROUSSILLON",
    "qs:a1r_lc":"91",
    "qs:a2_lc":"03",
    "qs:a2r_lc":"2",
    "qs:adm0":"France",
    "qs:adm0_a3":"FRA",
    "qs:la":"CAILLA",
    "qs:la_lc":"11060",
    "qs:level":"localadmin",
    "qs:type":"Commune simple",
    "wof:coterminous":[
        404419227
    ],
    "wof:name":"Cailla",
    "wof:placetype":"locality",
    "wof:placetype_local":"Commune simple"
},
  "geometry": {"coordinates":[2.19594,42.81416],"type":"Point"}
}