{
  "type": "Feature",
  "properties": {
    "gn:admin1_code":"76",
    "gn:admin2_code":"11",
    "gn:admin3_code":"112",
    "gn:admin4_code":"11060",
    "gn:asciiname":"Cailla",
    "gn:country_code":"FR",
    "gn:dem":511,
    "gn:feature_class":"P",
    "gn:feature_code":"PPL",
    "gn:name":"Cailla",
    "gn:population":0,
    "gn:timezone":"Europe/Paris",
    "iso:country":"FR",
    "wof:name":"Cailla",
    "wof:placetype":"locality"
},
  "geometry": {"coordinates":[2.19594,42.81416],"type":"Point"}
}