{
  "type": "Feature",
  "properties": {
    "gn:admin1_code":"32",
    "gn:admin2_code":"62",
    "gn:admin3_code":"626",
    "gn:admin4_code":"62548",
    "gn:asciiname":"Les Hemmes de Marck",
    "gn:country_code":"FR",
    "gn:dem":4,
    "gn:feature_class":"P",
    "gn:feature_code":"PPL",
    "gn:name":"Les Hemmes de Marck",
    "gn:population":0,
    "gn:timezone":"Europe/Paris",
    "iso:country":"FR",
    "name:und_x_variant":[
        "Hemmes",
        "Les Hemmes",
        "Les Petites Hemmes",
        "Les Hemmes de Marck"
    ],
    "wof:name":"Les Hemmes de Marck",
    "wof:placetype":"locality"
},
  "geometry": {"coordinates":[1.96263,50.98023],"type":"Point"}
}