{
  "type": "Feature",
  "properties": {
    "gn:admin1_code":"52",
    "gn:admin2_code":"72",
    "gn:admin3_code":"723",
    "gn:admin4_code":"72329",
    "gn:asciiname":"Malessard",
    "gn:country_code":"FR",
    "gn:dem":70,
    "gn:feature_class":"P",
    "gn:feature_code":"PPL",
    "gn:name":"Malessard",
    "gn:population":0,
    "gn:timezone":"Europe/Paris",
    "iso:country":"FR",
    "wof:name":"Malessard",
    "wof:placetype":"locality"
},
  "geometry": {"coordinates":[0.27268,48.08515],"type":"Point"}
}