{
  "type": "Feature",
  "properties": {
    "gn:admin1_code":"27",
    "gn:admin2_code":"89",
    "gn:admin3_code":"892",
    "gn:admin4_code":"89318",
    "gn:asciiname":"Bousson",
    "gn:country_code":"FR",
    "gn:dem":366,
    "gn:feature_class":"P",
    "gn:feature_code":"PPL",
    "gn:name":"Bousson",
    "gn:population":0,
    "gn:timezone":"Europe/Paris",
    "iso:country":"FR",
    "wof:name":"Bousson",
    "wof:placetype":"locality"
},
  "geometry": {"coordinates":[3.97907,47.35427],"type":"Point"}
}