{
  "type": "Feature",
  "properties": {
    "iso:country":"FR",
    "name:eng_x_preferred":[
        "Epoque"
    ],
    "name:fra_x_preferred":[
        "\u00c9poque"
    ],
    "wof:name":"Epoque",
    "wof:placetype":"neighbourhood"
},
  "geometry": {"coordinates":[2.53181058882785,48.87829680006027],"type":"Point"}
}