{
  "type": "Feature",
  "properties": {
    "gn:admin1_code":"28",
    "gn:admin2_code":"76",
    "gn:admin3_code":"762",
    "gn:admin4_code":"76382",
    "gn:asciiname":"Le Moulin",
    "gn:country_code":"FR",
    "gn:dem":146,
    "gn:feature_class":"P",
    "gn:feature_code":"PPL",
    "gn:name":"Le Moulin",
    "gn:population":0,
    "gn:timezone":"Europe/Paris",
    "iso:country":"FR",
    "name:ces_x_preferred":[
        "Le Moulin"
    ],
    "name:fra_x_preferred":[
        "Le Moulin"
    ],
    "name:pol_x_preferred":[
        "Le Moulin"
    ],
    "wof:name":"Le Moulin",
    "wof:placetype":"locality"
},
  "geometry": {"coordinates":[0.54218,49.59147],"type":"Point"}
}