{
  "type": "Feature",
  "properties": {
    "gn:admin1_code":"93",
    "gn:admin2_code":"05",
    "gn:admin3_code":"052",
    "gn:admin4_code":"05047",
    "gn:asciiname":"Les Peyres",
    "gn:country_code":"FR",
    "gn:dem":1000,
    "gn:feature_class":"P",
    "gn:feature_code":"PPL",
    "gn:name":"Les Peyres",
    "gn:population":0,
    "gn:timezone":"Europe/Paris",
    "iso:country":"FR",
    "wof:name":"Les Peyres",
    "wof:placetype":"locality"
},
  "geometry": {"coordinates":[5.71841,44.21411],"type":"Point"}
}