{
  "type": "Feature",
  "properties": {
    "gn:admin1_code":"75",
    "gn:admin2_code":"23",
    "gn:admin3_code":"232",
    "gn:admin4_code":"23120",
    "gn:asciiname":"Grand Chaumeix",
    "gn:country_code":"FR",
    "gn:dem":340,
    "gn:feature_class":"P",
    "gn:feature_code":"PPL",
    "gn:name":"Grand Chaumeix",
    "gn:population":0,
    "gn:timezone":"Europe/Paris",
    "iso:country":"FR",
    "wof:name":"Grand Chaumeix",
    "wof:placetype":"locality"
},
  "geometry": {"coordinates":[2.15492,46.33892],"type":"Point"}
}