{
  "type": "Feature",
  "properties": {
    "gn:admin1_code":"75",
    "gn:admin2_code":"87",
    "gn:admin3_code":"872",
    "gn:admin4_code":"87169",
    "gn:asciiname":"Triquerie",
    "gn:country_code":"FR",
    "gn:dem":407,
    "gn:feature_class":"P",
    "gn:feature_code":"PPL",
    "gn:name":"Triquerie",
    "gn:population":0,
    "gn:timezone":"Europe/Paris",
    "iso:country":"FR",
    "wof:name":"Triquerie",
    "wof:placetype":"locality"
},
  "geometry": {"coordinates":[1.23226,45.6939],"type":"Point"}
}