{
  "type": "Feature",
  "properties": {
    "gn:admin1_code":"52",
    "gn:admin2_code":"44",
    "gn:admin3_code":"441",
    "gn:admin4_code":"44123",
    "gn:asciiname":"Boudrinal",
    "gn:country_code":"FR",
    "gn:dem":16,
    "gn:feature_class":"P",
    "gn:feature_code":"PPL",
    "gn:name":"Boudrinal",
    "gn:population":0,
    "gn:timezone":"Europe/Paris",
    "iso:country":"FR",
    "wof:name":"Boudrinal",
    "wof:placetype":"locality"
},
  "geometry": {"coordinates":[-1.78666,47.68866],"type":"Point"}
}