{
  "type": "Feature",
  "properties": {
    "gn:admin1_code":"53",
    "gn:admin2_code":"29",
    "gn:admin3_code":"293",
    "gn:admin4_code":"29067",
    "gn:asciiname":"Kerahet",
    "gn:country_code":"FR",
    "gn:dem":242,
    "gn:feature_class":"P",
    "gn:feature_code":"PPL",
    "gn:name":"Kerahet",
    "gn:population":0,
    "gn:timezone":"Europe/Paris",
    "iso:country":"FR",
    "wof:name":"Kerahet",
    "wof:placetype":"locality"
},
  "geometry": {"coordinates":[-3.58333,48.53333],"type":"Point"}
}