{
  "type": "Feature",
  "properties": {
    "iso:country":"FR",
    "name:eng_x_preferred":[
        "Lallier Bicetre"
    ],
    "name:fra_x_preferred":[
        "Lallier Bic\u00eatre"
    ],
    "name:fra_x_variant":[
        "Lallier"
    ],
    "wof:name":"Lallier Bicetre",
    "wof:placetype":"neighbourhood"
},
  "geometry": {"coordinates":[2.35866684744982,48.77798449388766],"type":"Point"}
}