{
  "type": "Feature",
  "properties": {
    "iso:country":"FR",
    "oa:elevation_ft":"299",
    "oa:type":"small_airport",
    "woe:hierarchy":{
        "country_id":23424819,
        "county_id":12597121,
        "localadmin_id":12654130,
        "planet_id":1,
        "state_id":7153314
    },
    "wof:name":"A\u00e9rodrome de Tours-sorigny",
    "wof:placetype":"campus"
},
  "geometry": {"coordinates":[0.69917,47.2664],"type":"Point"}
}