{
  "type": "Feature",
  "properties": {
    "gn:admin1_code":"75",
    "gn:admin2_code":"19",
    "gn:admin3_code":"193",
    "gn:admin4_code":"19113",
    "gn:asciiname":"Mareges",
    "gn:country_code":"FR",
    "gn:dem":567,
    "gn:feature_class":"P",
    "gn:feature_code":"PPL",
    "gn:name":"Mar\u00e8ges",
    "gn:population":0,
    "gn:timezone":"Europe/Paris",
    "iso:country":"FR",
    "name:und_x_variant":[
        "Mar\u00e8ge",
        "Mar\u00e8ges"
    ],
    "wof:name":"Mareges",
    "wof:placetype":"locality"
},
  "geometry": {"coordinates":[2.35356,45.39257],"type":"Point"}
}