{
  "type": "Feature",
  "properties": {
    "gn:admin1_code":"24",
    "gn:admin2_code":"41",
    "gn:admin3_code":"412",
    "gn:admin4_code":"41177",
    "gn:asciiname":"Borde Bruyere",
    "gn:country_code":"FR",
    "gn:dem":210,
    "gn:feature_class":"P",
    "gn:feature_code":"PPL",
    "gn:name":"Borde Bruy\u00e8re",
    "gn:population":0,
    "gn:timezone":"Europe/Paris",
    "iso:country":"FR",
    "wof:name":"Borde Bruyere",
    "wof:placetype":"locality"
},
  "geometry": {"coordinates":[0.86556,48.09613],"type":"Point"}
}