{
  "type": "Feature",
  "properties": {
    "iso:country":"FR",
    "qs_pg:aaroncc":"FR",
    "qs_pg:name":"Le Mourtis",
    "qs_pg:name_adm0":"France",
    "qs_pg:name_adm1":"Midi-Pyr\u00e9n\u00e9es",
    "qs_pg:photos":51,
    "qs_pg:photos_1k":10,
    "qs_pg:photos_9k":1,
    "qs_pg:photos_9r":2,
    "qs_pg:photos_all":51,
    "qs_pg:photos_sr":2,
    "qs_pg:pop_sr":0,
    "qs_pg:qs_pg_placetype":"locality",
    "qs_pg:qs_pg_placetype_gp":"Town",
    "qs_pg:woe_adm0":23424819,
    "woe:adm0_id":23424819,
    "woe:name_adm0":"France",
    "woe:name_adm1":"Midi-Pyr\u00e9n\u00e9es",
    "woe:placetype":"Town",
    "wof:name":"Le Mourtis",
    "wof:placetype":"neighbourhood"
},
  "geometry": {"coordinates":[0.765352,42.911491],"type":"Point"}
}