{
  "type": "Feature",
  "properties": {
    "gn:admin1_code":"76",
    "gn:admin2_code":"48",
    "gn:admin3_code":"482",
    "gn:admin4_code":"48080",
    "gn:asciiname":"Chabaliou",
    "gn:country_code":"FR",
    "gn:dem":988,
    "gn:elevation":"988.0",
    "gn:feature_class":"P",
    "gn:feature_code":"PPLL",
    "gn:name":"Chabaliou",
    "gn:population":0,
    "gn:timezone":"Europe/Paris",
    "iso:country":"FR",
    "name:fra_x_preferred":[
        "Les Chavailloux"
    ],
    "wof:name":"Chabaliou",
    "wof:placetype":"locality"
},
  "geometry": {"coordinates":[3.86433,44.69983],"type":"Point"}
}