{
  "type": "Feature",
  "properties": {
    "gn:admin1_code":"76",
    "gn:admin2_code":"31",
    "gn:admin3_code":"311",
    "gn:admin4_code":"31460",
    "gn:asciiname":"Roques",
    "gn:country_code":"FR",
    "gn:dem":157,
    "gn:feature_class":"P",
    "gn:feature_code":"PPL",
    "gn:name":"Roques",
    "gn:population":0,
    "gn:timezone":"Europe/Paris",
    "iso:country":"FR",
    "name:arg_x_preferred":[
        "R\u00f2cas"
    ],
    "name:bre_x_preferred":[
        "Roques"
    ],
    "name:ceb_x_preferred":[
        "Roques"
    ],
    "name:deu_x_preferred":[
        "Roques"
    ],
    "name:fra_x_preferred":[
        "Roques"
    ],
    "name:ita_x_preferred":[
        "Roques"
    ],
    "name:nds_x_preferred":[
        "Roques"
    ],
    "name:nld_x_preferred":[
        "Roques"
    ],
    "name:oci_x_preferred":[
        "R\u00f2cas"
    ],
    "name:pol_x_preferred":[
        "Roques"
    ],
    "name:por_x_preferred":[
        "Roques"
    ],
    "name:slk_x_preferred":[
        "Roques"
    ],
    "name:spa_x_preferred":[
        "Roques"
    ],
    "name:swe_x_preferred":[
        "Roques"
    ],
    "wof:name":"Roques",
    "wof:placetype":"locality"
},
  "geometry": {"coordinates":[1.3714,43.50100000000001],"type":"Point"}
}