{
  "type": "Feature",
  "properties": {
    "gn:admin1_code":"28",
    "gn:admin2_code":"50",
    "gn:admin3_code":"503",
    "gn:admin4_code":"50223",
    "gn:asciiname":"Guehebert",
    "gn:country_code":"FR",
    "gn:dem":68,
    "gn:feature_class":"P",
    "gn:feature_code":"PPL",
    "gn:name":"Gu\u00e9h\u00e9bert",
    "gn:population":0,
    "gn:timezone":"Europe/Paris",
    "iso:country":"FR",
    "wof:name":"Guehebert",
    "wof:placetype":"locality"
},
  "geometry": {"coordinates":[-1.37415,48.97019],"type":"Point"}
}