{
  "type": "Feature",
  "properties": {
    "frgov:code_epci":"200067023",
    "frgov:insee_arr":"3",
    "frgov:insee_com":"50223",
    "frgov:insee_dep":"50",
    "frgov:insee_reg":"28",
    "frgov:nom_com":"Gu\u00e9h\u00e9bert",
    "frgov:nom_com_m":"GUEHEBERT",
    "frgov:nom_dep":"MANCHE",
    "frgov:nom_reg":"NORMANDIE",
    "frgov:statut":"Commune simple",
    "gn:admin1_code":"28",
    "gn:admin2_code":"50",
    "gn:admin3_code":"503",
    "gn:admin4_code":"50223",
    "gn:asciiname":"Guehebert",
    "gn:country_code":"FR",
    "gn:dem":68,
    "gn:feature_class":"P",
    "gn:feature_code":"PPL",
    "gn:name":"Gu\u00e9h\u00e9bert",
    "gn:population":0,
    "gn:timezone":"Europe/Paris",
    "iso:country":"FR",
    "name:fra_x_preferred":[
        "Gu\u00e9h\u00e9bert"
    ],
    "qs:a0":"France",
    "qs:a1":"MANCHE",
    "qs:a1_lc":"50",
    "qs:a1r":"BASSE-NORMANDIE",
    "qs:a1r_lc":"25",
    "qs:a2_lc":"10",
    "qs:a2r_lc":"3",
    "qs:adm0":"France",
    "qs:adm0_a3":"FRA",
    "qs:la":"GUEHEBERT",
    "qs:la_lc":"50223",
    "qs:level":"localadmin",
    "qs:type":"Commune simple",
    "wof:coterminous":[
        404409971
    ],
    "wof:name":"Guehebert",
    "wof:placetype":"locality",
    "wof:placetype_local":"Commune simple"
},
  "geometry": {"coordinates":[-1.37415,48.97019],"type":"Point"}
}