{
  "type": "Feature",
  "properties": {
    "gn:admin1_code":"24",
    "gn:admin2_code":"37",
    "gn:admin3_code":"373",
    "gn:admin4_code":"37168",
    "gn:asciiname":"Mont Garni",
    "gn:country_code":"FR",
    "gn:dem":100,
    "gn:feature_class":"P",
    "gn:feature_code":"PPL",
    "gn:name":"Mont Garni",
    "gn:population":0,
    "gn:timezone":"Europe/Paris",
    "iso:country":"FR",
    "wof:name":"Mont Garni",
    "wof:placetype":"locality"
},
  "geometry": {"coordinates":[0.78572,46.948],"type":"Point"}
}