{
  "type": "Feature",
  "properties": {
    "gn:admin1_code":"52",
    "gn:admin2_code":"44",
    "gn:admin3_code":"443",
    "gn:admin4_code":"44030",
    "gn:asciiname":"Ranrais",
    "gn:country_code":"FR",
    "gn:dem":4,
    "gn:feature_class":"P",
    "gn:feature_code":"PPL",
    "gn:name":"Ranrais",
    "gn:population":0,
    "gn:timezone":"Europe/Paris",
    "iso:country":"FR",
    "wof:name":"Ranrais",
    "wof:placetype":"locality"
},
  "geometry": {"coordinates":[-2.25785,47.44524000000001],"type":"Point"}
}