{
  "type": "Feature",
  "properties": {
    "frgov:code_epci":"200066124",
    "frgov:insee_arr":"1",
    "frgov:insee_com":"81316",
    "frgov:insee_dep":"81",
    "frgov:insee_reg":"76",
    "frgov:nom_com":"Vieux",
    "frgov:nom_com_m":"VIEUX",
    "frgov:nom_dep":"TARN",
    "frgov:nom_reg":"OCCITANIE",
    "frgov:statut":"Commune simple",
    "gn:admin1_code":"76",
    "gn:admin2_code":"81",
    "gn:admin3_code":"811",
    "gn:admin4_code":"81316",
    "gn:asciiname":"Vieux",
    "gn:country_code":"FR",
    "gn:dem":205,
    "gn:feature_class":"P",
    "gn:feature_code":"PPL",
    "gn:name":"Vieux",
    "gn:population":162,
    "gn:timezone":"Europe/Paris",
    "iso:country":"FR",
    "name:bre_x_preferred":[
        "Vieux"
    ],
    "name:ceb_x_preferred":[
        "Vieux"
    ],
    "name:deu_x_preferred":[
        "Vieux"
    ],
    "name:fra_x_preferred":[
        "Vieux"
    ],
    "name:ita_x_preferred":[
        "Vieux"
    ],
    "name:nds_x_preferred":[
        "Vieux"
    ],
    "name:nld_x_preferred":[
        "Vieux"
    ],
    "name:oci_x_preferred":[
        "Vieux"
    ],
    "name:pol_x_preferred":[
        "Vieux"
    ],
    "name:scn_x_preferred":[
        "Vieux"
    ],
    "name:slk_x_preferred":[
        "Vieux"
    ],
    "name:spa_x_preferred":[
        "Vieux"
    ],
    "name:sqi_x_preferred":[
        "Vieux"
    ],
    "name:swe_x_preferred":[
        "Vieux"
    ],
    "name:ukr_x_preferred":[
        "\u0412'\u0454"
    ],
    "qs:a0":"France",
    "qs:a1":"TARN",
    "qs:a1_lc":"81",
    "qs:a1r":"MIDI-PYRENEES",
    "qs:a1r_lc":"73",
    "qs:a2_lc":"07",
    "qs:a2r_lc":"1",
    "qs:adm0":"France",
    "qs:adm0_a3":"FRA",
    "qs:la":"VIEUX",
    "qs:la_lc":"81316",
    "qs:level":"localadmin",
    "qs:type":"Commune simple",
    "wof:coterminous":[
        404399399
    ],
    "wof:name":"Vieux",
    "wof:placetype":"locality",
    "wof:placetype_local":"Commune simple",
    "wof:population":162
},
  "geometry": {"coordinates":[1.87225,43.99311],"type":"Point"}
}