{
  "type": "Feature",
  "properties": {
    "gn:admin1_code":"76",
    "gn:admin2_code":"81",
    "gn:admin3_code":"811",
    "gn:admin4_code":"81316",
    "gn:asciiname":"Vieux",
    "gn:country_code":"FR",
    "gn:dem":205,
    "gn:feature_class":"P",
    "gn:feature_code":"PPL",
    "gn:name":"Vieux",
    "gn:population":162,
    "gn:timezone":"Europe/Paris",
    "iso:country":"FR",
    "wof:name":"Vieux",
    "wof:placetype":"locality",
    "wof:population":162
},
  "geometry": {"coordinates":[1.87225,43.99311],"type":"Point"}
}