{
  "type": "Feature",
  "properties": {
    "gn:admin1_code":"75",
    "gn:admin2_code":"47",
    "gn:admin3_code":"473",
    "gn:admin4_code":"47185",
    "gn:asciiname":"Pons",
    "gn:country_code":"FR",
    "gn:dem":83,
    "gn:feature_class":"P",
    "gn:feature_code":"PPL",
    "gn:name":"Pons",
    "gn:population":0,
    "gn:timezone":"Europe/Paris",
    "iso:country":"FR",
    "name:ara_x_preferred":[
        "\u062c\u0633\u0631"
    ],
    "name:bos_x_preferred":[
        "Most"
    ],
    "name:cat_x_preferred":[
        "Protuber\u00e0ncia anular"
    ],
    "name:ces_x_preferred":[
        "Varol\u016fv most"
    ],
    "name:dan_x_preferred":[
        "Pons"
    ],
    "name:deu_x_preferred":[
        "Pons"
    ],
    "name:ell_x_preferred":[
        "\u0393\u03ad\u03c6\u03c5\u03c1\u03b1"
    ],
    "name:epo_x_preferred":[
        "Cerba ponto"
    ],
    "name:fas_x_preferred":[
        "\u067e\u0644 \u0645\u063a\u0632"
    ],
    "name:fin_x_preferred":[
        "Aivosilta"
    ],
    "name:fra_x_preferred":[
        "Pont"
    ],
    "name:glg_x_preferred":[
        "Protuberancia anular"
    ],
    "name:heb_x_preferred":[
        "\u05e4\u05d5\u05e0\u05e1"
    ],
    "name:hye_x_preferred":[
        "\u054e\u0561\u0580\u0578\u056c\u0575\u0561\u0576 \u056f\u0561\u0574\u0578\u0582\u0580\u057b"
    ],
    "name:jpn_x_preferred":[
        "\u6a4b"
    ],
    "name:kaz_x_preferred":[
        "\u041c\u0438 \u043a\u04e9\u043f\u0456\u0440\u0456"
    ],
    "name:kor_x_preferred":[
        "\ub2e4\ub9ac\ub1cc"
    ],
    "name:lav_x_preferred":[
        "Smadze\u0146u tilts"
    ],
    "name:lit_x_preferred":[
        "Tiltas"
    ],
    "name:nld_x_preferred":[
        "Pons"
    ],
    "name:pol_x_preferred":[
        "Most"
    ],
    "name:por_x_preferred":[
        "Ponte"
    ],
    "name:rus_x_preferred":[
        "\u0412\u0430\u0440\u043e\u043b\u0438\u0435\u0432 \u043c\u043e\u0441\u0442"
    ],
    "name:slk_x_preferred":[
        "Varolov most"
    ],
    "name:spa_x_preferred":[
        "Puente troncoencef\u00e1lico"
    ],
    "name:srp_x_preferred":[
        "\u0412\u0430\u0440\u043e\u043b\u0438\u0458\u0435\u0432 \u043c\u043e\u0441\u0442"
    ],
    "name:swe_x_preferred":[
        "Hj\u00e4rnbryggan"
    ],
    "name:tgl_x_preferred":[
        "Pons"
    ],
    "name:tha_x_preferred":[
        "\u0e1e\u0e2d\u0e19\u0e2a\u0e4c"
    ],
    "name:tur_x_preferred":[
        "Pons"
    ],
    "name:uig_x_preferred":[
        "\u0645\u06d0\u06ad\u06d5 \u0643\u06c6\u06cb\u0631\u06c8\u0643\u0649"
    ],
    "name:ukr_x_preferred":[
        "\u041c\u0456\u0441\u0442"
    ],
    "wof:name":"Pons",
    "wof:placetype":"locality"
},
  "geometry": {"coordinates":[0.96815,44.48672],"type":"Point"}
}