{
  "type": "Feature",
  "properties": {
    "gn:admin1_code":"75",
    "gn:admin2_code":"87",
    "gn:admin3_code":"871",
    "gn:admin4_code":"87109",
    "gn:asciiname":"La Dapeire",
    "gn:country_code":"FR",
    "gn:dem":201,
    "gn:feature_class":"P",
    "gn:feature_code":"PPL",
    "gn:name":"La Dapeire",
    "gn:population":0,
    "gn:timezone":"Europe/Paris",
    "iso:country":"FR",
    "wof:name":"La Dapeire",
    "wof:placetype":"locality"
},
  "geometry": {"coordinates":[1.05292,46.23326],"type":"Point"}
}