{
  "type": "Feature",
  "properties": {
    "gn:admin1_code":"27",
    "gn:admin2_code":"89",
    "gn:admin3_code":"891",
    "gn:admin4_code":"89344",
    "gn:asciiname":"Septfonds",
    "gn:country_code":"FR",
    "gn:dem":197,
    "gn:feature_class":"P",
    "gn:feature_code":"PPL",
    "gn:name":"Septfonds",
    "gn:population":0,
    "gn:timezone":"Europe/Paris",
    "iso:country":"FR",
    "name:cat_x_preferred":[
        "S\u00e8tfonts"
    ],
    "name:ceb_x_preferred":[
        "Septfonds"
    ],
    "name:deu_x_preferred":[
        "Septfonds"
    ],
    "name:eus_x_preferred":[
        "Septfonds"
    ],
    "name:fra_x_preferred":[
        "Septfonds"
    ],
    "name:hun_x_preferred":[
        "Septfonds"
    ],
    "name:ita_x_preferred":[
        "Septfonds"
    ],
    "name:lat_x_preferred":[
        "Septfonds"
    ],
    "name:msa_x_preferred":[
        "Septfonds"
    ],
    "name:nld_x_preferred":[
        "Septfonds"
    ],
    "name:oci_x_preferred":[
        "S\u00e8tfonts"
    ],
    "name:pol_x_preferred":[
        "Septfonds"
    ],
    "name:ron_x_preferred":[
        "Septfonds"
    ],
    "name:slk_x_preferred":[
        "Septfonds"
    ],
    "name:spa_x_preferred":[
        "Septfonds"
    ],
    "name:swe_x_preferred":[
        "Septfonds"
    ],
    "name:ukr_x_preferred":[
        "\u0421\u0435\u0442\u0444\u043e\u043d"
    ],
    "name:vie_x_preferred":[
        "Septfonds"
    ],
    "name:vol_x_preferred":[
        "Septfonds"
    ],
    "name:war_x_preferred":[
        "Septfonds"
    ],
    "wof:name":"Septfonds",
    "wof:placetype":"locality"
},
  "geometry": {"coordinates":[3.09683,47.70256],"type":"Point"}
}