{
  "type": "Feature",
  "properties": {
    "gn:admin1_code":"27",
    "gn:admin2_code":"89",
    "gn:admin3_code":"891",
    "gn:admin4_code":"89344",
    "gn:asciiname":"Septfonds",
    "gn:country_code":"FR",
    "gn:dem":197,
    "gn:feature_class":"P",
    "gn:feature_code":"PPL",
    "gn:name":"Septfonds",
    "gn:population":0,
    "gn:timezone":"Europe/Paris",
    "iso:country":"FR",
    "wof:name":"Septfonds",
    "wof:placetype":"locality"
},
  "geometry": {"coordinates":[3.09683,47.70256],"type":"Point"}
}