{
  "type": "Feature",
  "properties": {
    "gn:admin1_code":"11",
    "gn:admin2_code":"77",
    "gn:admin3_code":"774",
    "gn:admin4_code":"77048",
    "gn:asciiname":"Marlotte",
    "gn:country_code":"FR",
    "gn:dem":99,
    "gn:feature_class":"P",
    "gn:feature_code":"PPL",
    "gn:name":"Marlotte",
    "gn:population":0,
    "gn:timezone":"Europe/Paris",
    "iso:country":"FR",
    "wof:name":"Marlotte",
    "wof:placetype":"locality"
},
  "geometry": {"coordinates":[2.71808,48.34296],"type":"Point"}
}