{
  "type": "Feature",
  "properties": {
    "gn:admin1_code":"94",
    "gn:admin2_code":"2A",
    "gn:admin3_code":"2A1",
    "gn:admin4_code":"2A048",
    "gn:asciiname":"Orcino",
    "gn:country_code":"FR",
    "gn:dem":76,
    "gn:feature_class":"P",
    "gn:feature_code":"PPL",
    "gn:name":"Orcino",
    "gn:population":0,
    "gn:timezone":"Europe/Paris",
    "iso:country":"FR",
    "wof:name":"Orcino",
    "wof:placetype":"locality"
},
  "geometry": {"coordinates":[8.73889,42.03778],"type":"Point"}
}