{
  "type": "Feature",
  "properties": {
    "gn:country":"FR",
    "gn:fcode":"PPL",
    "gn:population":402,
    "iso:country":"FR",
    "name:cat_x_preferred":[
        "Perpesac"
    ],
    "name:ceb_x_preferred":[
        "Perpezat"
    ],
    "name:deu_x_preferred":[
        "Perpezat"
    ],
    "name:eus_x_preferred":[
        "Perpezat"
    ],
    "name:fra_x_preferred":[
        "Perpezat"
    ],
    "name:hun_x_preferred":[
        "Perpezat"
    ],
    "name:ita_x_preferred":[
        "Perpezat"
    ],
    "name:lat_x_preferred":[
        "Perpezat"
    ],
    "name:mlg_x_preferred":[
        "Perpezat"
    ],
    "name:msa_x_preferred":[
        "Perpezat"
    ],
    "name:nld_x_preferred":[
        "Perpezat"
    ],
    "name:oci_x_preferred":[
        "Perpesat"
    ],
    "name:pms_x_preferred":[
        "Perpezat"
    ],
    "name:pol_x_preferred":[
        "Perpezat"
    ],
    "name:por_x_preferred":[
        "Perpezat"
    ],
    "name:ron_x_preferred":[
        "Perpezat"
    ],
    "name:slk_x_preferred":[
        "Perpezat"
    ],
    "name:spa_x_preferred":[
        "Perpezat"
    ],
    "name:swe_x_preferred":[
        "Perpezat"
    ],
    "name:ukr_x_preferred":[
        "\u041f\u0435\u0440\u043f\u0435\u0437\u0430"
    ],
    "name:uzb_x_preferred":[
        "Perpezat"
    ],
    "name:vie_x_preferred":[
        "Perpezat"
    ],
    "name:vol_x_preferred":[
        "Perpezat"
    ],
    "name:war_x_preferred":[
        "Perpezat"
    ],
    "name:zho_x_preferred":[
        "\u4f69\u5c14\u4f69\u624e"
    ],
    "qs_pg:aaroncc":"FR",
    "qs_pg:gn_country":"FR",
    "qs_pg:gn_fcode":"PPL",
    "qs_pg:gn_pop":402,
    "qs_pg:name":"Perpezat",
    "qs_pg:photos_9r":0,
    "qs_pg:photos_sr":0,
    "qs_pg:pop_sr":2,
    "qs_pg:qs_pg_placetype":"locality",
    "wof:name":"Perpezat",
    "wof:placetype":"neighbourhood",
    "wof:population":402
},
  "geometry": {"coordinates":[3.15588,45.39446],"type":"Point"}
}