{
  "type": "Feature",
  "properties": {
    "gn:admin1_code":"27",
    "gn:admin2_code":"39",
    "gn:admin3_code":"392",
    "gn:admin4_code":"39038.0",
    "gn:asciiname":"Baresia-sur-l'Ain",
    "gn:country_code":"FR",
    "gn:dem":496,
    "gn:feature_class":"P",
    "gn:feature_code":"PPL",
    "gn:name":"Bar\u00e9sia-sur-l'Ain",
    "gn:population":0,
    "gn:timezone":"Europe/Paris",
    "iso:country":"FR",
    "name:und_x_variant":[
        "Bar\u00e9sia",
        "Bar\u00e9sia-sur-l'Ain"
    ],
    "wof:name":"Baresia-sur-l'Ain",
    "wof:placetype":"locality"
},
  "geometry": {"coordinates":[5.71126,46.54912],"type":"Point"}
}