{
  "type": "Feature",
  "properties": {
    "gn:admin1_code":"84",
    "gn:admin2_code":"42",
    "gn:admin3_code":"423",
    "gn:admin4_code":"42225",
    "gn:asciiname":"Tapigneux",
    "gn:country_code":"FR",
    "gn:dem":434,
    "gn:feature_class":"P",
    "gn:feature_code":"PPL",
    "gn:name":"Tapigneux",
    "gn:population":0,
    "gn:timezone":"Europe/Paris",
    "iso:country":"FR",
    "wof:name":"Tapigneux",
    "wof:placetype":"locality"
},
  "geometry": {"coordinates":[4.5656,45.53772],"type":"Point"}
}