{
  "type": "Feature",
  "properties": {
    "gn:admin1_code":"52",
    "gn:admin2_code":"49",
    "gn:admin3_code":"492",
    "gn:admin4_code":"49092",
    "gn:asciiname":"Cosse-d'Anjou",
    "gn:country_code":"FR",
    "gn:dem":151,
    "gn:feature_class":"P",
    "gn:feature_code":"PPL",
    "gn:name":"Coss\u00e9-d\u2019Anjou",
    "gn:population":0,
    "gn:timezone":"Europe/Paris",
    "iso:country":"FR",
    "name:und_x_variant":[
        "Coss\u00e9",
        "Coss\u00e9-d\u2019Anjou"
    ],
    "wof:name":"Cosse-d'Anjou",
    "wof:placetype":"locality"
},
  "geometry": {"coordinates":[-0.67822,47.16274],"type":"Point"}
}