{
  "type": "Feature",
  "properties": {
    "gn:admin1_code":"52",
    "gn:admin2_code":"49",
    "gn:admin3_code":"492",
    "gn:admin4_code":"49092",
    "gn:asciiname":"Cosse-d'Anjou",
    "gn:country_code":"FR",
    "gn:dem":151,
    "gn:feature_class":"P",
    "gn:feature_code":"PPL",
    "gn:name":"Coss\u00e9-d\u2019Anjou",
    "gn:population":0,
    "gn:timezone":"Europe/Paris",
    "iso:country":"FR",
    "name:cat_x_preferred":[
        "Coss\u00e9-d'Anjou"
    ],
    "name:ceb_x_preferred":[
        "Coss\u00e9-d'Anjou"
    ],
    "name:deu_x_preferred":[
        "Coss\u00e9-d\u2019Anjou"
    ],
    "name:eus_x_preferred":[
        "Coss\u00e9-d'Anjou"
    ],
    "name:fra_x_preferred":[
        "Coss\u00e9-d'Anjou"
    ],
    "name:hun_x_preferred":[
        "Coss\u00e9-d\u2019Anjou"
    ],
    "name:ita_x_preferred":[
        "Coss\u00e9-d'Anjou"
    ],
    "name:jpn_x_preferred":[
        "\u30b3\u30bb\uff1d\u30c0\u30f3\u30b8\u30e5\u30fc"
    ],
    "name:lat_x_preferred":[
        "Coss\u00e9-d'Anjou"
    ],
    "name:mlg_x_preferred":[
        "Coss\u00e9-d'Anjou"
    ],
    "name:msa_x_preferred":[
        "Coss\u00e9-d'Anjou"
    ],
    "name:nld_x_preferred":[
        "Coss\u00e9-d'Anjou"
    ],
    "name:oci_x_preferred":[
        "Coss\u00e9-d'Anjou"
    ],
    "name:pms_x_preferred":[
        "Coss\u00e9-d'Anjou"
    ],
    "name:pol_x_preferred":[
        "Coss\u00e9-d\u2019Anjou"
    ],
    "name:por_x_preferred":[
        "Coss\u00e9-d'Anjou"
    ],
    "name:ron_x_preferred":[
        "Coss\u00e9-d'Anjou"
    ],
    "name:slk_x_preferred":[
        "Coss\u00e9-d\u2019Anjou"
    ],
    "name:spa_x_preferred":[
        "Coss\u00e9-d'Anjou"
    ],
    "name:swe_x_preferred":[
        "Coss\u00e9-d'Anjou"
    ],
    "name:ukr_x_preferred":[
        "\u041a\u043e\u0441\u0441\u0435-\u0434'\u0410\u043d\u0436\u0443"
    ],
    "name:und_x_variant":[
        "Coss\u00e9"
    ],
    "name:vie_x_preferred":[
        "Coss\u00e9-d'Anjou"
    ],
    "name:vol_x_preferred":[
        "Coss\u00e9-d'Anjou"
    ],
    "name:war_x_preferred":[
        "Coss\u00e9-d'Anjou"
    ],
    "name:zho_x_preferred":[
        "\u79d1\u585e\u5f53\u8339"
    ],
    "wof:name":"Cosse-d'Anjou",
    "wof:placetype":"locality"
},
  "geometry": {"coordinates":[-0.67822,47.16274],"type":"Point"}
}