{
  "type": "Feature",
  "properties": {
    "gn:admin1_code":"52",
    "gn:admin2_code":"53",
    "gn:admin3_code":"531",
    "gn:admin4_code":"53210",
    "gn:asciiname":"La Guerouillere",
    "gn:country_code":"FR",
    "gn:dem":99,
    "gn:feature_class":"P",
    "gn:feature_code":"PPL",
    "gn:name":"La Gu\u00e9rouill\u00e8re",
    "gn:population":0,
    "gn:timezone":"Europe/Paris",
    "iso:country":"FR",
    "wof:name":"La Guerouillere",
    "wof:placetype":"locality"
},
  "geometry": {"coordinates":[-0.4806,47.8148],"type":"Point"}
}