{
  "type": "Feature",
  "properties": {
    "gn:admin1_code":"75",
    "gn:admin2_code":"33",
    "gn:admin3_code":"332",
    "gn:admin4_code":"33262",
    "gn:asciiname":"Bernes",
    "gn:country_code":"FR",
    "gn:dem":10,
    "gn:feature_class":"P",
    "gn:feature_code":"PPL",
    "gn:name":"Bernes",
    "gn:population":0,
    "gn:timezone":"Europe/Paris",
    "iso:country":"FR",
    "wof:name":"Bernes",
    "wof:placetype":"locality"
},
  "geometry": {"coordinates":[-0.62761,45.00738],"type":"Point"}
}