{
  "type": "Feature",
  "properties": {
    "gn:admin1_code":"75",
    "gn:admin2_code":"33",
    "gn:admin3_code":"332",
    "gn:admin4_code":"33262",
    "gn:asciiname":"Bernes",
    "gn:country_code":"FR",
    "gn:dem":10,
    "gn:feature_class":"P",
    "gn:feature_code":"PPL",
    "gn:name":"Bernes",
    "gn:population":0,
    "gn:timezone":"Europe/Paris",
    "iso:country":"FR",
    "name:bug_x_preferred":[
        "Bernes"
    ],
    "name:cat_x_preferred":[
        "Bernes"
    ],
    "name:ceb_x_preferred":[
        "Bernes"
    ],
    "name:deu_x_preferred":[
        "Bernes"
    ],
    "name:eus_x_preferred":[
        "Bernes"
    ],
    "name:fas_x_preferred":[
        "\u0628\u0631\u0646\u0633"
    ],
    "name:fra_x_preferred":[
        "Bernes"
    ],
    "name:hun_x_preferred":[
        "Bernes"
    ],
    "name:hye_x_preferred":[
        "\u0532\u0565\u057c\u0576"
    ],
    "name:ita_x_preferred":[
        "Bernes"
    ],
    "name:lat_x_preferred":[
        "Bernes"
    ],
    "name:mlg_x_preferred":[
        "Bernes"
    ],
    "name:msa_x_preferred":[
        "Bernes"
    ],
    "name:nld_x_preferred":[
        "Bernes"
    ],
    "name:oci_x_preferred":[
        "Bernes"
    ],
    "name:pcd_x_preferred":[
        "B\u00e8rne"
    ],
    "name:pms_x_preferred":[
        "Bernes"
    ],
    "name:pol_x_preferred":[
        "Bernes"
    ],
    "name:por_x_preferred":[
        "Bernes"
    ],
    "name:ron_x_preferred":[
        "Bernes"
    ],
    "name:slk_x_preferred":[
        "Bernes"
    ],
    "name:spa_x_preferred":[
        "Bernes"
    ],
    "name:srp_x_preferred":[
        "\u0411\u0435\u0440\u043d"
    ],
    "name:swe_x_preferred":[
        "Bernes"
    ],
    "name:ukr_x_preferred":[
        "\u0411\u0435\u0440\u043d"
    ],
    "name:uzb_x_preferred":[
        "Bernes"
    ],
    "name:vie_x_preferred":[
        "Bernes"
    ],
    "name:vol_x_preferred":[
        "Bernes"
    ],
    "name:war_x_preferred":[
        "Bernes"
    ],
    "name:zho_x_preferred":[
        "\u8d1d\u5c14\u8bb7"
    ],
    "wof:name":"Bernes",
    "wof:placetype":"locality"
},
  "geometry": {"coordinates":[-0.62761,45.00738],"type":"Point"}
}