{
  "type": "Feature",
  "properties": {
    "gn:admin1_code":"52",
    "gn:admin2_code":"72",
    "gn:admin3_code":"723",
    "gn:admin4_code":"72299",
    "gn:asciiname":"Les Grandes Prouilleres",
    "gn:country_code":"FR",
    "gn:dem":130,
    "gn:feature_class":"P",
    "gn:feature_code":"PPL",
    "gn:name":"Les Grandes Prouill\u00e8res",
    "gn:population":0,
    "gn:timezone":"Europe/Paris",
    "iso:country":"FR",
    "wof:name":"Les Grandes Prouilleres",
    "wof:placetype":"locality"
},
  "geometry": {"coordinates":[0.33296,47.8535],"type":"Point"}
}