{
  "type": "Feature",
  "properties": {
    "gn:admin1_code":"32",
    "gn:admin2_code":"59",
    "gn:admin3_code":"591",
    "gn:admin4_code":"59147",
    "gn:asciiname":"Choisies",
    "gn:country_code":"FR",
    "gn:dem":178,
    "gn:feature_class":"P",
    "gn:feature_code":"PPL",
    "gn:name":"Choisies",
    "gn:population":0,
    "gn:timezone":"Europe/Paris",
    "iso:country":"FR",
    "name:bre_x_preferred":[
        "Choisies"
    ],
    "name:cat_x_preferred":[
        "Choisies"
    ],
    "name:ceb_x_preferred":[
        "Choisies"
    ],
    "name:deu_x_preferred":[
        "Choisies"
    ],
    "name:epo_x_preferred":[
        "Choisies"
    ],
    "name:eus_x_preferred":[
        "Choisies"
    ],
    "name:fra_x_preferred":[
        "Choisies"
    ],
    "name:hun_x_preferred":[
        "Choisies"
    ],
    "name:ind_x_preferred":[
        "Choisies"
    ],
    "name:ita_x_preferred":[
        "Choisies"
    ],
    "name:kaz_x_preferred":[
        "\u0428\u0443\u0430\u0437\u0438"
    ],
    "name:lat_x_preferred":[
        "Choisies"
    ],
    "name:mlg_x_preferred":[
        "Choisies"
    ],
    "name:msa_x_preferred":[
        "Choisies"
    ],
    "name:nld_x_preferred":[
        "Choisies"
    ],
    "name:oci_x_preferred":[
        "Choisies"
    ],
    "name:pol_x_preferred":[
        "Choisies"
    ],
    "name:ron_x_preferred":[
        "Choisies"
    ],
    "name:slk_x_preferred":[
        "Choisies"
    ],
    "name:spa_x_preferred":[
        "Choisies"
    ],
    "name:srp_x_preferred":[
        "\u0428\u043e\u0430\u0437\u0438"
    ],
    "name:swe_x_preferred":[
        "Choisies"
    ],
    "name:ukr_x_preferred":[
        "\u0428\u0443\u0430\u0437\u0456"
    ],
    "name:vie_x_preferred":[
        "Choisies"
    ],
    "name:vol_x_preferred":[
        "Choisies"
    ],
    "name:war_x_preferred":[
        "Choisies"
    ],
    "name:zho_x_preferred":[
        "\u8212\u74e6\u897f"
    ],
    "wof:name":"Choisies",
    "wof:placetype":"locality"
},
  "geometry": {"coordinates":[4.04194,50.21403],"type":"Point"}
}