{
  "type": "Feature",
  "properties": {
    "gn:admin1_code":"84",
    "gn:admin2_code":"74",
    "gn:admin3_code":"741",
    "gn:admin4_code":"74010",
    "gn:asciiname":"Malaz",
    "gn:country_code":"FR",
    "gn:dem":535,
    "gn:feature_class":"P",
    "gn:feature_code":"PPL",
    "gn:name":"Malaz",
    "gn:population":0,
    "gn:timezone":"Europe/Paris",
    "iso:country":"FR",
    "name:und_x_variant":[
        "Mala",
        "Malaz"
    ],
    "wof:name":"Malaz",
    "wof:placetype":"locality"
},
  "geometry": {"coordinates":[6.10251,45.88033],"type":"Point"}
}