{
  "type": "Feature",
  "properties": {
    "gn:admin1_code":"53",
    "gn:admin2_code":"29",
    "gn:admin3_code":"293",
    "gn:admin4_code":"29202",
    "gn:asciiname":"Keryel",
    "gn:country_code":"FR",
    "gn:dem":214,
    "gn:feature_class":"P",
    "gn:feature_code":"PPL",
    "gn:name":"Keryel",
    "gn:population":0,
    "gn:timezone":"Europe/Paris",
    "iso:country":"FR",
    "wof:name":"Keryel",
    "wof:placetype":"locality"
},
  "geometry": {"coordinates":[-3.86189,48.46045],"type":"Point"}
}