{
  "type": "Feature",
  "properties": {
    "gn:admin1_code":"52",
    "gn:admin2_code":"49",
    "gn:admin3_code":"493",
    "gn:admin4_code":"49328",
    "gn:asciiname":"La Croix Verte",
    "gn:country_code":"FR",
    "gn:dem":29,
    "gn:feature_class":"P",
    "gn:feature_code":"PPL",
    "gn:name":"La Croix Verte",
    "gn:population":0,
    "gn:timezone":"Europe/Paris",
    "iso:country":"FR",
    "wof:name":"La Croix Verte",
    "wof:placetype":"locality"
},
  "geometry": {"coordinates":[-0.06694,47.26964],"type":"Point"}
}