{
  "type": "Feature",
  "properties": {
    "gn:admin1_code":"75",
    "gn:admin2_code":"79",
    "gn:admin3_code":"791",
    "gn:admin4_code":"79049",
    "gn:asciiname":"Saint-Porchaire",
    "gn:country_code":"FR",
    "gn:dem":175,
    "gn:feature_class":"P",
    "gn:feature_code":"PPL",
    "gn:name":"Saint-Porchaire",
    "gn:population":0,
    "gn:timezone":"Europe/Paris",
    "iso:country":"FR",
    "name:cat_x_preferred":[
        "Saint-Porchaire"
    ],
    "name:ceb_x_preferred":[
        "Saint-Porchaire"
    ],
    "name:deu_x_preferred":[
        "Saint-Porchaire"
    ],
    "name:epo_x_preferred":[
        "Saint-Porchaire"
    ],
    "name:eus_x_preferred":[
        "Saint-Porchaire"
    ],
    "name:fra_x_preferred":[
        "Saint-Porchaire"
    ],
    "name:hun_x_preferred":[
        "Saint-Porchaire"
    ],
    "name:hye_x_preferred":[
        "\u054d\u0565\u0576 \u054a\u0578\u0580\u0577\u0565\u0580"
    ],
    "name:ita_x_preferred":[
        "Saint-Porchaire"
    ],
    "name:lat_x_preferred":[
        "Saint-Porchaire"
    ],
    "name:msa_x_preferred":[
        "Saint-Porchaire"
    ],
    "name:nld_x_preferred":[
        "Saint-Porchaire"
    ],
    "name:oci_x_preferred":[
        "Saint-Porchaire"
    ],
    "name:pol_x_preferred":[
        "Saint-Porchaire"
    ],
    "name:por_x_preferred":[
        "Saint-Porchaire"
    ],
    "name:ron_x_preferred":[
        "Saint-Porchaire"
    ],
    "name:rus_x_preferred":[
        "\u0421\u0435\u043d-\u041f\u043e\u0440\u0448\u0435\u0440"
    ],
    "name:slk_x_preferred":[
        "Saint-Porchaire"
    ],
    "name:slv_x_preferred":[
        "Saint-Porchaire"
    ],
    "name:spa_x_preferred":[
        "Saint-Porchaire"
    ],
    "name:swe_x_preferred":[
        "Saint-Porchaire"
    ],
    "name:ukr_x_preferred":[
        "\u0421\u0435\u043d-\u041f\u043e\u0440\u0448\u0435\u0440"
    ],
    "name:urd_x_preferred":[
        "\u0633\u06cc\u0646-\u067e\u0648\u0631\u0686\u06cc\u0631\u06d2"
    ],
    "name:vie_x_preferred":[
        "Saint-Porchaire"
    ],
    "name:vol_x_preferred":[
        "Saint-Porchaire"
    ],
    "name:war_x_preferred":[
        "Saint-Porchaire"
    ],
    "name:zho_x_preferred":[
        "\u5723\u6ce2\u5c14\u8c22\u5c14"
    ],
    "wof:name":"Saint-Porchaire",
    "wof:placetype":"locality"
},
  "geometry": {"coordinates":[-0.45178,46.85476],"type":"Point"}
}