{
  "type": "Feature",
  "properties": {
    "gn:admin1_code":"84",
    "gn:admin2_code":"74",
    "gn:admin3_code":"741",
    "gn:admin4_code":"74010",
    "gn:asciiname":"Mathonex",
    "gn:country_code":"FR",
    "gn:dem":604,
    "gn:feature_class":"P",
    "gn:feature_code":"PPL",
    "gn:name":"Mathonex",
    "gn:population":0,
    "gn:timezone":"Europe/Paris",
    "iso:country":"FR",
    "wof:name":"Mathonex",
    "wof:placetype":"locality"
},
  "geometry": {"coordinates":[6.07232,45.85648],"type":"Point"}
}