{
  "type": "Feature",
  "properties": {
    "iso:country":"FR",
    "name:eng_x_preferred":[
        "Les Barnufles-Les Glacis"
    ],
    "name:fra_x_preferred":[
        "Les Barnufles-Les Glacis"
    ],
    "wof:name":"Les Barnufles-Les Glacis",
    "wof:placetype":"neighbourhood"
},
  "geometry": {"coordinates":[2.35002824058847,48.80753262693195],"type":"Point"}
}