{
  "type": "Feature",
  "properties": {
    "frgov:code_epci":"200066561",
    "frgov:insee_arr":"2",
    "frgov:insee_com":"81062",
    "frgov:insee_dep":"81",
    "frgov:insee_reg":"76",
    "frgov:nom_com":"Fontrieu",
    "frgov:nom_com_m":"FONTRIEU",
    "frgov:nom_dep":"TARN",
    "frgov:nom_reg":"OCCITANIE",
    "frgov:statut":"Commune simple",
    "gn:admin1_code":"76",
    "gn:admin2_code":"81",
    "gn:admin3_code":"812",
    "gn:admin4_code":"81062",
    "gn:asciiname":"Le Margnes",
    "gn:country_code":"FR",
    "gn:dem":807,
    "gn:feature_class":"P",
    "gn:feature_code":"PPL",
    "gn:name":"Le Margn\u00e8s",
    "gn:population":0,
    "gn:timezone":"Europe/Paris",
    "iso:country":"FR",
    "name:fra_x_preferred":[
        "Fontrieu"
    ],
    "qs:a0":"France",
    "qs:a1":"TARN",
    "qs:a1_lc":"81",
    "qs:a1r":"MIDI-PYRENEES",
    "qs:a1r_lc":"73",
    "qs:a2_lc":"04",
    "qs:a2r_lc":"2",
    "qs:adm0":"France",
    "qs:adm0_a3":"FRA",
    "qs:la":"LE MARGNES",
    "qs:la_lc":"81153",
    "qs:level":"localadmin",
    "qs:type":"Commune simple",
    "wof:coterminous":[
        404415385
    ],
    "wof:name":"Le Margnes",
    "wof:placetype":"locality",
    "wof:placetype_local":"Commune simple"
},
  "geometry": {"coordinates":[2.6005,43.64204],"type":"Point"}
}