{
  "type": "Feature",
  "properties": {
    "gn:admin1_code":"76",
    "gn:admin2_code":"81",
    "gn:admin3_code":"812",
    "gn:admin4_code":"81062",
    "gn:asciiname":"Le Margnes",
    "gn:country_code":"FR",
    "gn:dem":807,
    "gn:feature_class":"P",
    "gn:feature_code":"PPL",
    "gn:name":"Le Margn\u00e8s",
    "gn:population":0,
    "gn:timezone":"Europe/Paris",
    "iso:country":"FR",
    "wof:name":"Le Margnes",
    "wof:placetype":"locality"
},
  "geometry": {"coordinates":[2.6005,43.64204],"type":"Point"}
}