{
  "type": "Feature",
  "properties": {
    "gn:admin1_code":"32",
    "gn:admin2_code":"62",
    "gn:admin3_code":"621",
    "gn:admin4_code":"62182",
    "gn:asciiname":"Bachimont",
    "gn:country_code":"FR",
    "gn:dem":138,
    "gn:feature_class":"P",
    "gn:feature_code":"PPL",
    "gn:name":"Bachimont",
    "gn:population":0,
    "gn:timezone":"Europe/Paris",
    "iso:country":"FR",
    "wof:name":"Bachimont",
    "wof:placetype":"locality"
},
  "geometry": {"coordinates":[2.14234,50.27143],"type":"Point"}
}