{
  "type": "Feature",
  "properties": {
    "gn:admin1_code":"76",
    "gn:admin2_code":"48",
    "gn:admin3_code":"482",
    "gn:admin4_code":"48139",
    "gn:asciiname":"Le Bouchet",
    "gn:country_code":"FR",
    "gn:dem":1064,
    "gn:feature_class":"P",
    "gn:feature_code":"PPL",
    "gn:name":"Le Bouchet",
    "gn:population":0,
    "gn:timezone":"Europe/Paris",
    "iso:country":"FR",
    "wof:name":"Le Bouchet",
    "wof:placetype":"locality"
},
  "geometry": {"coordinates":[3.68333,44.81667],"type":"Point"}
}