{
  "type": "Feature",
  "properties": {
    "gn:admin1_code":"24",
    "gn:admin2_code":"18",
    "gn:admin3_code":"182",
    "gn:admin4_code":"18238",
    "gn:asciiname":"Penserole",
    "gn:country_code":"FR",
    "gn:dem":253,
    "gn:feature_class":"P",
    "gn:feature_code":"PPL",
    "gn:name":"Penserole",
    "gn:population":0,
    "gn:timezone":"Europe/Paris",
    "iso:country":"FR",
    "name:und_x_variant":[
        "Penserolles",
        "Penserole"
    ],
    "wof:name":"Penserole",
    "wof:placetype":"locality"
},
  "geometry": {"coordinates":[2.50828,46.52685],"type":"Point"}
}