{
  "type": "Feature",
  "properties": {
    "gn:admin1_code":"32",
    "gn:admin2_code":"59",
    "gn:admin3_code":"592",
    "gn:admin4_code":"59139",
    "gn:asciiname":"Audencourt",
    "gn:country_code":"FR",
    "gn:dem":135,
    "gn:feature_class":"P",
    "gn:feature_code":"PPL",
    "gn:name":"Audencourt",
    "gn:population":0,
    "gn:timezone":"Europe/Paris",
    "iso:country":"FR",
    "wof:name":"Audencourt",
    "wof:placetype":"locality"
},
  "geometry": {"coordinates":[3.43916,50.11831],"type":"Point"}
}