{
  "type": "Feature",
  "properties": {
    "gn:admin1_code":"75",
    "gn:admin2_code":"23",
    "gn:admin3_code":"232",
    "gn:admin4_code":"23235",
    "gn:asciiname":"Mazeirat",
    "gn:country_code":"FR",
    "gn:dem":411,
    "gn:feature_class":"P",
    "gn:feature_code":"PPL",
    "gn:name":"Mazeirat",
    "gn:population":0,
    "gn:timezone":"Europe/Paris",
    "iso:country":"FR",
    "wof:name":"Mazeirat",
    "wof:placetype":"locality"
},
  "geometry": {"coordinates":[1.53666,46.23029],"type":"Point"}
}