{
  "type": "Feature",
  "properties": {
    "gn:admin1_code":"75",
    "gn:admin2_code":"23",
    "gn:admin3_code":"232",
    "gn:admin4_code":"23235",
    "gn:asciiname":"Mazeirat",
    "gn:country_code":"FR",
    "gn:dem":411,
    "gn:feature_class":"P",
    "gn:feature_code":"PPL",
    "gn:name":"Mazeirat",
    "gn:population":0,
    "gn:timezone":"Europe/Paris",
    "iso:country":"FR",
    "name:cat_x_preferred":[
        "Maseirac"
    ],
    "name:ceb_x_preferred":[
        "Mazeirat"
    ],
    "name:deu_x_preferred":[
        "Mazeirat"
    ],
    "name:epo_x_preferred":[
        "Mazeirat"
    ],
    "name:eus_x_preferred":[
        "Mazeirat"
    ],
    "name:fra_x_preferred":[
        "Mazeirat"
    ],
    "name:hun_x_preferred":[
        "Mazeirat"
    ],
    "name:ind_x_preferred":[
        "Mazeirat"
    ],
    "name:ita_x_preferred":[
        "Mazeirat"
    ],
    "name:kaz_x_preferred":[
        "\u041c\u0430\u0437\u0435\u0440\u0430"
    ],
    "name:lat_x_preferred":[
        "Mazeirat"
    ],
    "name:mlg_x_preferred":[
        "Mazeirat"
    ],
    "name:msa_x_preferred":[
        "Mazeirat"
    ],
    "name:nld_x_preferred":[
        "Mazeirat"
    ],
    "name:oci_x_preferred":[
        "Mas\u00e8irac"
    ],
    "name:pms_x_preferred":[
        "Mazeirat"
    ],
    "name:pol_x_preferred":[
        "Mazeirat"
    ],
    "name:por_x_preferred":[
        "Mazeirat"
    ],
    "name:ron_x_preferred":[
        "Mazeirat"
    ],
    "name:rus_x_preferred":[
        "\u041c\u0430\u0437\u0435\u0440\u0430"
    ],
    "name:slk_x_preferred":[
        "Mazeirat"
    ],
    "name:spa_x_preferred":[
        "Mazeirat"
    ],
    "name:swe_x_preferred":[
        "Mazeirat"
    ],
    "name:ukr_x_preferred":[
        "\u041c\u0430\u0437\u0435\u0440\u0430"
    ],
    "name:uzb_x_preferred":[
        "Mazeirat"
    ],
    "name:vie_x_preferred":[
        "Mazeirat"
    ],
    "name:vol_x_preferred":[
        "Mazeirat"
    ],
    "name:war_x_preferred":[
        "Mazeirat"
    ],
    "name:zho_x_preferred":[
        "\u9a6c\u6cfd\u62c9"
    ],
    "wof:name":"Mazeirat",
    "wof:placetype":"locality"
},
  "geometry": {"coordinates":[1.53666,46.23029],"type":"Point"}
}