{
  "type": "Feature",
  "properties": {
    "gn:admin1_code":"84",
    "gn:admin2_code":"73",
    "gn:admin3_code":"733",
    "gn:admin4_code":"73290",
    "gn:asciiname":"L'Adroit",
    "gn:country_code":"FR",
    "gn:dem":1468,
    "gn:feature_class":"P",
    "gn:feature_code":"PPL",
    "gn:name":"L'Adroit",
    "gn:population":0,
    "gn:timezone":"Europe/Paris",
    "iso:country":"FR",
    "name:fra_x_preferred":[
        "L'Adroit"
    ],
    "wof:name":"L'Adroit",
    "wof:placetype":"locality"
},
  "geometry": {"coordinates":[6.91254,45.29109],"type":"Point"}
}