{
  "type": "Feature",
  "properties": {
    "gn:admin1_code":"24",
    "gn:admin2_code":"37",
    "gn:admin3_code":"372",
    "gn:admin4_code":"37008",
    "gn:asciiname":"Bono",
    "gn:country_code":"FR",
    "gn:dem":97,
    "gn:feature_class":"P",
    "gn:feature_code":"PPL",
    "gn:name":"Bono",
    "gn:population":0,
    "gn:timezone":"Europe/Paris",
    "iso:country":"FR",
    "wof:name":"Bono",
    "wof:placetype":"locality"
},
  "geometry": {"coordinates":[0.92626,47.31776],"type":"Point"}
}