{
  "type": "Feature",
  "properties": {
    "gn:admin1_code":"53",
    "gn:admin2_code":"29",
    "gn:admin3_code":"293",
    "gn:admin4_code":"29073",
    "gn:asciiname":"Keralegan",
    "gn:country_code":"FR",
    "gn:dem":39,
    "gn:feature_class":"P",
    "gn:feature_code":"PPL",
    "gn:name":"Keral\u00e9gan",
    "gn:population":0,
    "gn:timezone":"Europe/Paris",
    "iso:country":"FR",
    "wof:name":"Keralegan",
    "wof:placetype":"locality"
},
  "geometry": {"coordinates":[-3.68222,48.67055],"type":"Point"}
}