{
  "type": "Feature",
  "properties": {
    "gn:admin1_code":"93",
    "gn:admin2_code":"05",
    "gn:admin3_code":"052",
    "gn:admin4_code":"05018",
    "gn:asciiname":"Larra Grand",
    "gn:country_code":"FR",
    "gn:dem":885,
    "gn:feature_class":"P",
    "gn:feature_code":"PPL",
    "gn:name":"Larra Grand",
    "gn:population":0,
    "gn:timezone":"Europe/Paris",
    "iso:country":"FR",
    "name:und_x_variant":[
        "Grand-Larra",
        "Larra Grand"
    ],
    "wof:name":"Larra Grand",
    "wof:placetype":"locality"
},
  "geometry": {"coordinates":[6.14778,44.56901],"type":"Point"}
}