{
  "type": "Feature",
  "properties": {
    "gn:admin1_code":"27",
    "gn:admin2_code":"21",
    "gn:admin3_code":"213",
    "gn:admin4_code":"21497",
    "gn:asciiname":"Massene",
    "gn:country_code":"FR",
    "gn:dem":306,
    "gn:feature_class":"P",
    "gn:feature_code":"PPL",
    "gn:name":"Mass\u00e8ne",
    "gn:population":0,
    "gn:timezone":"Europe/Paris",
    "iso:country":"FR",
    "wof:name":"Massene",
    "wof:placetype":"locality"
},
  "geometry": {"coordinates":[4.36381,47.47881],"type":"Point"}
}