{
  "type": "Feature",
  "properties": {
    "gn:admin1_code":"44",
    "gn:admin2_code":"10",
    "gn:admin3_code":"103",
    "gn:admin4_code":"10395",
    "gn:asciiname":"Rue du Laps",
    "gn:country_code":"FR",
    "gn:dem":131,
    "gn:feature_class":"P",
    "gn:feature_code":"PPL",
    "gn:name":"Rue du Laps",
    "gn:population":0,
    "gn:timezone":"Europe/Paris",
    "iso:country":"FR",
    "name:und_x_variant":[
        "La Rue-du-Laps",
        "Rue du Laps"
    ],
    "wof:name":"Rue du Laps",
    "wof:placetype":"locality"
},
  "geometry": {"coordinates":[3.97419,48.03399],"type":"Point"}
}