{
  "type": "Feature",
  "properties": {
    "gn:admin1_code":"28",
    "gn:admin2_code":"27",
    "gn:admin3_code":"271",
    "gn:admin4_code":"27315",
    "gn:asciiname":"Travailles",
    "gn:country_code":"FR",
    "gn:dem":61,
    "gn:feature_class":"P",
    "gn:feature_code":"PPL",
    "gn:name":"Travailles",
    "gn:population":0,
    "gn:timezone":"Europe/Paris",
    "iso:country":"FR",
    "wof:name":"Travailles",
    "wof:placetype":"locality"
},
  "geometry": {"coordinates":[1.52278,49.24521],"type":"Point"}
}