{
  "type": "Feature",
  "properties": {
    "gn:admin1_code":"11",
    "gn:admin2_code":"91",
    "gn:admin3_code":"911",
    "gn:admin4_code":"91129",
    "gn:asciiname":"Longueville",
    "gn:country_code":"FR",
    "gn:dem":78,
    "gn:feature_class":"P",
    "gn:feature_code":"PPL",
    "gn:name":"Longueville",
    "gn:population":0,
    "gn:timezone":"Europe/Paris",
    "iso:country":"FR",
    "name:bre_x_preferred":[
        "Longueville"
    ],
    "name:ceb_x_preferred":[
        "Longueville"
    ],
    "name:deu_x_preferred":[
        "Longueville"
    ],
    "name:eus_x_preferred":[
        "Longueville"
    ],
    "name:fra_x_preferred":[
        "Longueville"
    ],
    "name:hun_x_preferred":[
        "Longueville"
    ],
    "name:ind_x_preferred":[
        "Longueville"
    ],
    "name:ita_x_preferred":[
        "Longueville"
    ],
    "name:nds_x_preferred":[
        "Longueville"
    ],
    "name:nld_x_preferred":[
        "Longueville"
    ],
    "name:pms_x_preferred":[
        "Longueville"
    ],
    "name:pol_x_preferred":[
        "Longueville"
    ],
    "name:por_x_preferred":[
        "Longueville"
    ],
    "name:rus_x_preferred":[
        "\u041b\u043e\u043d\u0433\u0432\u0438\u043b\u044c"
    ],
    "name:slk_x_preferred":[
        "Longueville"
    ],
    "name:spa_x_preferred":[
        "Longueville"
    ],
    "name:swe_x_preferred":[
        "Longueville"
    ],
    "name:ukr_x_preferred":[
        "\u041b\u043e\u043d\u0433\u0432\u0456\u043b\u044c"
    ],
    "wof:name":"Longueville",
    "wof:placetype":"locality"
},
  "geometry": {"coordinates":[2.31667,48.46667],"type":"Point"}
}