{
  "type": "Feature",
  "properties": {
    "gn:admin1_code":"11",
    "gn:admin2_code":"91",
    "gn:admin3_code":"911",
    "gn:admin4_code":"91129",
    "gn:asciiname":"Longueville",
    "gn:country_code":"FR",
    "gn:dem":78,
    "gn:feature_class":"P",
    "gn:feature_code":"PPL",
    "gn:name":"Longueville",
    "gn:population":0,
    "gn:timezone":"Europe/Paris",
    "iso:country":"FR",
    "wof:name":"Longueville",
    "wof:placetype":"locality"
},
  "geometry": {"coordinates":[2.31667,48.46667],"type":"Point"}
}