{
  "type": "Feature",
  "properties": {
    "frgov:code_epci":"200069003",
    "frgov:insee_arr":"3",
    "frgov:insee_com":"10294",
    "frgov:insee_dep":"10",
    "frgov:insee_reg":"44",
    "frgov:nom_com":"Poligny",
    "frgov:nom_com_m":"POLIGNY",
    "frgov:nom_dep":"AUBE",
    "frgov:nom_reg":"GRAND EST",
    "frgov:statut":"Commune simple",
    "gn:admin1_code":"44",
    "gn:admin2_code":"10",
    "gn:admin3_code":"103",
    "gn:admin4_code":"10294",
    "gn:asciiname":"Poligny",
    "gn:country_code":"FR",
    "gn:dem":145,
    "gn:feature_class":"P",
    "gn:feature_code":"PPL",
    "gn:name":"Poligny",
    "gn:population":30,
    "gn:timezone":"Europe/Paris",
    "iso:country":"FR",
    "name:cat_x_preferred":[
        "Poligny"
    ],
    "name:ceb_x_preferred":[
        "Poligny"
    ],
    "name:deu_x_preferred":[
        "Poligny"
    ],
    "name:fin_x_preferred":[
        "Poligny"
    ],
    "name:fra_x_preferred":[
        "Poligny"
    ],
    "name:ita_x_preferred":[
        "Poligny"
    ],
    "name:nds_x_preferred":[
        "Poligny"
    ],
    "name:nld_x_preferred":[
        "Poligny"
    ],
    "name:pms_x_preferred":[
        "Poligny"
    ],
    "name:pol_x_preferred":[
        "Poligny"
    ],
    "name:por_x_preferred":[
        "Poligny"
    ],
    "name:rus_x_preferred":[
        "\u041f\u043e\u043b\u0438\u043d\u044c\u0438"
    ],
    "name:slk_x_preferred":[
        "Poligny"
    ],
    "name:spa_x_preferred":[
        "Poligny"
    ],
    "name:swe_x_preferred":[
        "Poligny"
    ],
    "name:ukr_x_preferred":[
        "\u041f\u043e\u043b\u0456\u043d\u044c\u0457"
    ],
    "qs:a0":"France",
    "qs:a1":"AUBE",
    "qs:a1_lc":"10",
    "qs:a1r":"CHAMPAGNE-ARDENNE",
    "qs:a1r_lc":"21",
    "qs:a2_lc":"04",
    "qs:a2r_lc":"3",
    "qs:adm0":"France",
    "qs:adm0_a3":"FRA",
    "qs:la":"POLIGNY",
    "qs:la_lc":"10294",
    "qs:level":"localadmin",
    "qs:type":"Commune simple",
    "wof:coterminous":[
        404415401
    ],
    "wof:name":"Poligny",
    "wof:placetype":"locality",
    "wof:placetype_local":"Commune simple",
    "wof:population":30
},
  "geometry": {"coordinates":[4.34304,48.17487],"type":"Point"}
}