{
  "type": "Feature",
  "properties": {
    "gn:admin1_code":"44",
    "gn:admin2_code":"10",
    "gn:admin3_code":"103",
    "gn:admin4_code":"10294",
    "gn:asciiname":"Poligny",
    "gn:country_code":"FR",
    "gn:dem":145,
    "gn:feature_class":"P",
    "gn:feature_code":"PPL",
    "gn:name":"Poligny",
    "gn:population":30,
    "gn:timezone":"Europe/Paris",
    "iso:country":"FR",
    "wof:name":"Poligny",
    "wof:placetype":"locality",
    "wof:population":30
},
  "geometry": {"coordinates":[4.34304,48.17487],"type":"Point"}
}