{
  "type": "Feature",
  "properties": {
    "iso:country":"FR",
    "name:eng_x_preferred":[
        "Resistance-Republique"
    ],
    "name:fra_x_preferred":[
        "Resistance-Republique"
    ],
    "wof:name":"Resistance-Republique",
    "wof:placetype":"neighbourhood"
},
  "geometry": {"coordinates":[2.27500516172864,48.78222344270159],"type":"Point"}
}