{
  "type": "Feature",
  "properties": {
    "iso:country":"FR",
    "name:eng_x_preferred":[
        "Le Chenay"
    ],
    "name:fra_x_preferred":[
        "Le Ch\u00e9nay"
    ],
    "name:fra_x_variant":[
        "Ch\u00e9nay"
    ],
    "wof:name":"Le Chenay",
    "wof:placetype":"neighbourhood"
},
  "geometry": {"coordinates":[2.55858977710654,48.87235064395993],"type":"Point"}
}