{
  "type": "Feature",
  "properties": {
    "gn:admin1_code":"76",
    "gn:admin2_code":"12",
    "gn:admin3_code":"122",
    "gn:admin4_code":"12102",
    "gn:asciiname":"Vayssac",
    "gn:country_code":"FR",
    "gn:dem":653,
    "gn:feature_class":"P",
    "gn:feature_code":"PPL",
    "gn:name":"Vayssac",
    "gn:population":0,
    "gn:timezone":"Europe/Paris",
    "iso:country":"FR",
    "wof:name":"Vayssac",
    "wof:placetype":"locality"
},
  "geometry": {"coordinates":[2.65039,44.29315],"type":"Point"}
}