{
  "type": "Feature",
  "properties": {
    "gn:admin1_code":"11",
    "gn:admin2_code":"78",
    "gn:admin3_code":"781",
    "gn:admin4_code":"78668",
    "gn:asciiname":"Les Marcets",
    "gn:country_code":"FR",
    "gn:dem":136,
    "gn:feature_class":"P",
    "gn:feature_code":"PPL",
    "gn:name":"Les Marcets",
    "gn:population":0,
    "gn:timezone":"Europe/Paris",
    "iso:country":"FR",
    "wof:name":"Les Marcets",
    "wof:placetype":"locality"
},
  "geometry": {"coordinates":[1.53237,49.00744],"type":"Point"}
}