{
  "type": "Feature",
  "properties": {
    "gn:admin1_code":"76",
    "gn:admin2_code":"66",
    "gn:admin3_code":"663",
    "gn:admin4_code":"66025",
    "gn:asciiname":"Ix",
    "gn:cc2":"ES,FR",
    "gn:country_code":"FR",
    "gn:dem":1159,
    "gn:feature_class":"P",
    "gn:feature_code":"PPL",
    "gn:name":"Ix",
    "gn:population":0,
    "gn:timezone":"Europe/Paris",
    "iso:country":"FR",
    "name:hun_x_preferred":[
        "IX"
    ],
    "name:rus_x_preferred":[
        "IX"
    ],
    "wof:name":"Ix",
    "wof:placetype":"locality"
},
  "geometry": {"coordinates":[1.95445,42.43352],"type":"Point"}
}