{
  "type": "Feature",
  "properties": {
    "gn:admin1_code":"93",
    "gn:admin2_code":"05",
    "gn:admin3_code":"052",
    "gn:admin4_code":"05179",
    "gn:asciiname":"Le Petit Veaux",
    "gn:country_code":"FR",
    "gn:dem":964,
    "gn:feature_class":"P",
    "gn:feature_code":"PPL",
    "gn:name":"Le Petit Veaux",
    "gn:population":0,
    "gn:timezone":"Europe/Paris",
    "iso:country":"FR",
    "name:und_x_variant":[
        "Veaux",
        "Le Petit Vaux",
        "Le Petit Veaux"
    ],
    "wof:name":"Le Petit Veaux",
    "wof:placetype":"locality"
},
  "geometry": {"coordinates":[5.84832,44.58794],"type":"Point"}
}