{
  "type": "Feature",
  "properties": {
    "gn:admin1_code":"84",
    "gn:admin2_code":"42",
    "gn:admin3_code":"423",
    "gn:admin4_code":"42056",
    "gn:asciiname":"La Grande Gorge",
    "gn:country_code":"FR",
    "gn:dem":186,
    "gn:feature_class":"P",
    "gn:feature_code":"PPL",
    "gn:name":"La Grande Gorge",
    "gn:population":0,
    "gn:timezone":"Europe/Paris",
    "iso:country":"FR",
    "wof:name":"La Grande Gorge",
    "wof:placetype":"locality"
},
  "geometry": {"coordinates":[4.73536,45.40031],"type":"Point"}
}