{
  "type": "Feature",
  "properties": {
    "gn:admin1_code":"44",
    "gn:admin2_code":"68",
    "gn:admin3_code":"681",
    "gn:admin4_code":"68192",
    "gn:asciiname":"Valdieu-Lutran",
    "gn:country_code":"FR",
    "gn:dem":327,
    "gn:feature_class":"P",
    "gn:feature_code":"PPL",
    "gn:name":"Valdieu-Lutran",
    "gn:population":0,
    "gn:timezone":"Europe/Paris",
    "iso:country":"FR",
    "name:kaz_x_preferred":[
        "\u0412\u0430\u043b\u044c\u0434\u044c\u0435-\u041b\u044e\u0442\u0440\u0430\u043d"
    ],
    "name:rus_x_preferred":[
        "\u0412\u0430\u043b\u0434\u044c\u0451-\u041b\u044e\u0442\u0440\u0430\u043d"
    ],
    "name:ukr_x_preferred":[
        "\u0412\u0430\u043b\u044c\u0434\u044c\u0454-\u041b\u044e\u0442\u0440\u0430\u043d"
    ],
    "name:zho_x_preferred":[
        "\u74e6\u5c14\u8fea\u5384\u5415\u7279\u6717"
    ],
    "wof:name":"Valdieu-Lutran",
    "wof:placetype":"locality"
},
  "geometry": {"coordinates":[7.06667,47.63333],"type":"Point"}
}