{
  "type": "Feature",
  "properties": {
    "gn:admin1_code":"44",
    "gn:admin2_code":"55",
    "gn:admin3_code":"553",
    "gn:admin4_code":"55500",
    "gn:asciiname":"Ollieres",
    "gn:country_code":"FR",
    "gn:dem":271,
    "gn:feature_class":"P",
    "gn:feature_code":"PPL",
    "gn:name":"Olli\u00e8res",
    "gn:population":0,
    "gn:timezone":"Europe/Paris",
    "iso:country":"FR",
    "name:und_x_variant":[
        "Olli\u00e8res"
    ],
    "wof:name":"Ollieres",
    "wof:placetype":"locality"
},
  "geometry": {"coordinates":[5.71743,49.35303],"type":"Point"}
}