{
  "type": "Feature",
  "properties": {
    "gn:country":"FR",
    "iso:country":"FR",
    "qs_pg:aaroncc":"FR",
    "qs_pg:gn_country":"FR",
    "qs_pg:name":"La Boutinardi\u00e8re",
    "qs_pg:name_adm0":"France",
    "qs_pg:name_adm1":"Pays de la Loire",
    "qs_pg:photos":158,
    "qs_pg:photos_1k":32,
    "qs_pg:photos_9k":1,
    "qs_pg:photos_9r":4,
    "qs_pg:photos_all":158,
    "qs_pg:photos_sr":4,
    "qs_pg:pop_sr":0,
    "qs_pg:qs_pg_placetype":"locality",
    "qs_pg:qs_pg_placetype_gp":"Town",
    "qs_pg:woe_adm0":23424819,
    "woe:adm0_id":23424819,
    "woe:name_adm0":"France",
    "woe:name_adm1":"Pays de la Loire",
    "woe:placetype":"Town",
    "wof:name":"La Boutinardi\u00e8re",
    "wof:placetype":"neighbourhood"
},
  "geometry": {"coordinates":[-2.0522865,47.093982],"type":"Point"}
}