{
  "type": "Feature",
  "properties": {
    "gn:admin1_code":"84",
    "gn:admin2_code":"63",
    "gn:admin3_code":"633",
    "gn:admin4_code":"63190",
    "gn:asciiname":"Ousclaux",
    "gn:country_code":"FR",
    "gn:dem":829,
    "gn:feature_class":"P",
    "gn:feature_code":"PPL",
    "gn:name":"Ousclaux",
    "gn:population":0,
    "gn:timezone":"Europe/Paris",
    "iso:country":"FR",
    "wof:name":"Ousclaux",
    "wof:placetype":"locality"
},
  "geometry": {"coordinates":[2.58333,45.53333],"type":"Point"}
}