{
  "type": "Feature",
  "properties": {
    "gn:admin1_code":"24",
    "gn:admin2_code":"28",
    "gn:admin3_code":"281",
    "gn:admin4_code":"28040",
    "gn:asciiname":"Maindreville",
    "gn:country_code":"FR",
    "gn:dem":202,
    "gn:feature_class":"P",
    "gn:feature_code":"PPL",
    "gn:name":"Maindreville",
    "gn:population":0,
    "gn:timezone":"Europe/Paris",
    "iso:country":"FR",
    "wof:name":"Maindreville",
    "wof:placetype":"locality"
},
  "geometry": {"coordinates":[1.19583,48.48446],"type":"Point"}
}