{
  "type": "Feature",
  "properties": {
    "gn:admin1_code":"93",
    "gn:admin2_code":"05",
    "gn:admin3_code":"051",
    "gn:admin4_code":"05038",
    "gn:asciiname":"Chateau-Queyras",
    "gn:cc2":"FR",
    "gn:country_code":"FR",
    "gn:dem":1450,
    "gn:feature_class":"P",
    "gn:feature_code":"PPL",
    "gn:name":"Ch\u00e2teau-Queyras",
    "gn:population":0,
    "gn:timezone":"Europe/Paris",
    "iso:country":"FR",
    "name:und_x_variant":[
        "Le Ch\u00e2teau",
        "Ch\u00e2teau-Queyras"
    ],
    "wof:name":"Chateau-Queyras",
    "wof:placetype":"locality"
},
  "geometry": {"coordinates":[6.78333,44.75],"type":"Point"}
}