{
  "type": "Feature",
  "properties": {
    "gn:admin1_code":"27",
    "gn:admin2_code":"39",
    "gn:admin3_code":"392",
    "gn:admin4_code":"39484",
    "gn:asciiname":"Saint-Jean-d'Etreux",
    "gn:country_code":"FR",
    "gn:dem":438,
    "gn:feature_class":"P",
    "gn:feature_code":"PPL",
    "gn:name":"Saint-Jean-d'\u00c9treux",
    "gn:population":0,
    "gn:timezone":"Europe/Paris",
    "iso:country":"FR",
    "name:und_x_variant":[
        "Saint-Jean",
        "Saint-Jean-d'\u00c9treux"
    ],
    "wof:name":"Saint-Jean-d'Etreux",
    "wof:placetype":"locality"
},
  "geometry": {"coordinates":[5.35815,46.4046],"type":"Point"}
}