{
  "type": "Feature",
  "properties": {
    "gn:admin1_code":"84",
    "gn:admin2_code":"03",
    "gn:admin3_code":"031",
    "gn:admin4_code":"03161",
    "gn:asciiname":"Romagere-aux-Osiers",
    "gn:country_code":"FR",
    "gn:dem":464,
    "gn:feature_class":"P",
    "gn:feature_code":"PPL",
    "gn:name":"Romag\u00e8re-aux-Osiers",
    "gn:population":0,
    "gn:timezone":"Europe/Paris",
    "iso:country":"FR",
    "wof:name":"Romagere-aux-Osiers",
    "wof:placetype":"locality"
},
  "geometry": {"coordinates":[2.61667,46.16667],"type":"Point"}
}