{
  "type": "Feature",
  "properties": {
    "gn:admin1_code":"52",
    "gn:admin2_code":"44",
    "gn:admin3_code":"441",
    "gn:admin4_code":"44067",
    "gn:asciiname":"Beix",
    "gn:country_code":"FR",
    "gn:dem":23,
    "gn:feature_class":"P",
    "gn:feature_code":"PPL",
    "gn:name":"Beix",
    "gn:population":0,
    "gn:timezone":"Europe/Paris",
    "iso:country":"FR",
    "wof:name":"Beix",
    "wof:placetype":"locality"
},
  "geometry": {"coordinates":[-1.84505,47.68305],"type":"Point"}
}