{
  "type": "Feature",
  "properties": {
    "gn:admin1_code":"75",
    "gn:admin2_code":"19",
    "gn:admin3_code":"192",
    "gn:admin4_code":"19287",
    "gn:asciiname":"Terrioux",
    "gn:country_code":"FR",
    "gn:dem":604,
    "gn:feature_class":"P",
    "gn:feature_code":"PPL",
    "gn:name":"Terrioux",
    "gn:population":0,
    "gn:timezone":"Europe/Paris",
    "iso:country":"FR",
    "wof:name":"Terrioux",
    "wof:placetype":"locality"
},
  "geometry": {"coordinates":[1.96235,45.38811],"type":"Point"}
}