{
  "type": "Feature",
  "properties": {
    "gn:admin1_code":"75",
    "gn:admin2_code":"24",
    "gn:admin3_code":"242",
    "gn:admin4_code":"24100",
    "gn:asciiname":"La Parentie",
    "gn:country_code":"FR",
    "gn:dem":260,
    "gn:feature_class":"P",
    "gn:feature_code":"PPL",
    "gn:name":"La Parentie",
    "gn:population":0,
    "gn:timezone":"Europe/Paris",
    "iso:country":"FR",
    "wof:name":"La Parentie",
    "wof:placetype":"locality"
},
  "geometry": {"coordinates":[0.70643,45.65698],"type":"Point"}
}