{
  "type": "Feature",
  "properties": {
    "gn:gn_country":"FR",
    "gn:gn_fcode":"PPL",
    "gn:gn_pop":56,
    "gn:population":56,
    "iso:country":"FR",
    "name:baq_x_preferred":[
        "Chartren\u00e9"
    ],
    "name:cat_x_preferred":[
        "Chartren\u00e9"
    ],
    "name:chi_x_preferred":[
        "\u6c99\u5c14\u7279\u96f7\u5185"
    ],
    "name:dut_x_preferred":[
        "Chartren\u00e9"
    ],
    "name:eng_x_preferred":[
        "Chartren\u00e9"
    ],
    "name:fre_x_preferred":[
        "Chartren\u00e9"
    ],
    "name:ger_x_preferred":[
        "Chartren\u00e9"
    ],
    "name:hun_x_preferred":[
        "Chartren\u00e9"
    ],
    "name:ita_x_preferred":[
        "Chartren\u00e9"
    ],
    "name:lat_x_preferred":[
        "Chartren\u00e9"
    ],
    "name:may_x_preferred":[
        "Chartren\u00e9"
    ],
    "name:mlg_x_preferred":[
        "Chartren\u00e9"
    ],
    "name:nan_x_preferred":[
        "Chartren\u00e9"
    ],
    "name:oci_x_preferred":[
        "Chartren\u00e9"
    ],
    "name:pms_x_preferred":[
        "Chartren\u00e9"
    ],
    "name:pol_x_preferred":[
        "Chartren\u00e9"
    ],
    "name:por_x_preferred":[
        "Chartren\u00e9"
    ],
    "name:rum_x_preferred":[
        "Chartren\u00e9"
    ],
    "name:slo_x_preferred":[
        "Chartren\u00e9"
    ],
    "name:spa_x_preferred":[
        "Chartren\u00e9"
    ],
    "name:srp_x_preferred":[
        "\u0428\u0430\u0440\u0442\u0440\u0435\u043d\u0435"
    ],
    "name:swe_x_preferred":[
        "Chartren\u00e9"
    ],
    "name:ukr_x_preferred":[
        "\u0428\u0430\u0440\u0442\u0440\u0435\u043d\u0435"
    ],
    "name:vie_x_preferred":[
        "Chartren\u00e9"
    ],
    "name:vol_x_preferred":[
        "Chartren\u00e9"
    ],
    "name:war_x_preferred":[
        "Chartren\u00e9"
    ],
    "name:zho_x_preferred":[
        "\u6c99\u5c14\u7279\u96f7\u5185"
    ],
    "qs_pg:aaroncc":"FR",
    "qs_pg:gn_country":"FR",
    "qs_pg:gn_fcode":"PPL",
    "qs_pg:gn_pop":56,
    "qs_pg:name":"Chartren\u00e9",
    "qs_pg:name_adm0":"France",
    "qs_pg:name_adm1":"Pays de la Loire",
    "qs_pg:photos_9r":0,
    "qs_pg:photos_sr":0,
    "qs_pg:pop_sr":1,
    "qs_pg:qs_pg_placetype":"locality",
    "qs_pg:qs_pg_placetype_gp":"Town",
    "qs_pg:woe_adm0":23424819,
    "woe:adm0_id":23424819,
    "woe:name_adm0":"France",
    "woe:name_adm1":"Pays de la Loire",
    "woe:placetype":"Town",
    "wof:name":"Chartren\u00e9",
    "wof:placetype":"neighbourhood",
    "wof:population":56
},
  "geometry": {"coordinates":[-0.12591,47.4916],"type":"Point"}
}