{
  "type": "Feature",
  "properties": {
    "gn:admin1_code":"27",
    "gn:admin2_code":"58",
    "gn:admin3_code":"583",
    "gn:admin4_code":"58092",
    "gn:asciiname":"Les Ravees",
    "gn:country_code":"FR",
    "gn:dem":312,
    "gn:feature_class":"P",
    "gn:feature_code":"PPL",
    "gn:name":"Les Rav\u00e9es",
    "gn:population":0,
    "gn:timezone":"Europe/Paris",
    "iso:country":"FR",
    "wof:name":"Les Ravees",
    "wof:placetype":"locality"
},
  "geometry": {"coordinates":[3.50544,47.14937000000001],"type":"Point"}
}