{
  "type": "Feature",
  "properties": {
    "gn:admin1_code":"52",
    "gn:admin2_code":"53",
    "gn:admin3_code":"532",
    "gn:admin4_code":"53009",
    "gn:asciiname":"Monfourmay",
    "gn:country_code":"FR",
    "gn:dem":86,
    "gn:feature_class":"P",
    "gn:feature_code":"PPL",
    "gn:name":"Monfourmay",
    "gn:population":0,
    "gn:timezone":"Europe/Paris",
    "iso:country":"FR",
    "wof:name":"Monfourmay",
    "wof:placetype":"locality"
},
  "geometry": {"coordinates":[-0.59902,47.99054],"type":"Point"}
}