{
  "type": "Feature",
  "properties": {
    "gn:admin1_code":"52",
    "gn:admin2_code":"49",
    "gn:admin3_code":"492",
    "gn:admin4_code":"49301",
    "gn:asciiname":"La Moncoillere",
    "gn:country_code":"FR",
    "gn:dem":92,
    "gn:feature_class":"P",
    "gn:feature_code":"PPL",
    "gn:name":"La Moncoill\u00e8re",
    "gn:population":0,
    "gn:timezone":"Europe/Paris",
    "iso:country":"FR",
    "name:und_x_variant":[
        "La Maucoill\u00e8re",
        "La Moncoill\u00e8re"
    ],
    "wof:name":"La Moncoillere",
    "wof:placetype":"locality"
},
  "geometry": {"coordinates":[-1.0131,47.13309],"type":"Point"}
}