{
  "type": "Feature",
  "properties": {
    "gn:admin1_code":"28",
    "gn:admin2_code":"14",
    "gn:admin3_code":"142",
    "gn:admin4_code":"14306",
    "gn:asciiname":"Gonneville-sur-Merville",
    "gn:cc2":"FR",
    "gn:country_code":"FR",
    "gn:dem":2,
    "gn:feature_class":"P",
    "gn:feature_code":"PPL",
    "gn:name":"Gonneville-sur-Merville",
    "gn:population":0,
    "gn:timezone":"Europe/Paris",
    "iso:country":"FR",
    "name:und_x_variant":[
        "Gonneville",
        "Gonneville-sur-Merville"
    ],
    "wof:name":"Gonneville-sur-Merville",
    "wof:placetype":"locality"
},
  "geometry": {"coordinates":[-0.18333,49.26667],"type":"Point"}
}