{
  "type": "Feature",
  "properties": {
    "gn:admin1_code":"94",
    "gn:admin2_code":"2B",
    "gn:admin3_code":"2B2",
    "gn:admin4_code":"2B305",
    "gn:asciiname":"Palagaccio",
    "gn:country_code":"FR",
    "gn:dem":1,
    "gn:feature_class":"P",
    "gn:feature_code":"PPL",
    "gn:name":"Palagaccio",
    "gn:population":0,
    "gn:timezone":"Europe/Paris",
    "iso:country":"FR",
    "wof:name":"Palagaccio",
    "wof:placetype":"locality"
},
  "geometry": {"coordinates":[9.45667,42.72],"type":"Point"}
}