{
  "type": "Feature",
  "properties": {
    "gn:admin1_code":"27",
    "gn:admin2_code":"70",
    "gn:admin3_code":"702",
    "gn:admin4_code":"70528",
    "gn:asciiname":"Echevanne",
    "gn:country_code":"FR",
    "gn:dem":211,
    "gn:feature_class":"P",
    "gn:feature_code":"PPL",
    "gn:name":"\u00c9chevanne",
    "gn:population":0,
    "gn:timezone":"Europe/Paris",
    "iso:country":"FR",
    "name:und_x_variant":[
        "\u00c9chevanne"
    ],
    "wof:name":"Echevanne",
    "wof:placetype":"locality"
},
  "geometry": {"coordinates":[5.66798,47.41939],"type":"Point"}
}