{
  "type": "Feature",
  "properties": {
    "gn:admin1_code":"93",
    "gn:admin2_code":"13",
    "gn:admin3_code":"134",
    "gn:admin4_code":"13088",
    "gn:asciiname":"Niolon",
    "gn:country_code":"FR",
    "gn:dem":23,
    "gn:feature_class":"P",
    "gn:feature_code":"PPL",
    "gn:name":"Niolon",
    "gn:population":0,
    "gn:timezone":"Europe/Paris",
    "iso:country":"FR",
    "wof:name":"Niolon",
    "wof:placetype":"locality"
},
  "geometry": {"coordinates":[5.25702,43.33877],"type":"Point"}
}