{
  "type": "Feature",
  "properties": {
    "gn:admin1_code":"76",
    "gn:admin2_code":"11",
    "gn:admin3_code":"112",
    "gn:admin4_code":"11303",
    "gn:asciiname":"Campsilvestre",
    "gn:country_code":"FR",
    "gn:dem":577,
    "gn:feature_class":"P",
    "gn:feature_code":"PPL",
    "gn:name":"Campsilvestre",
    "gn:population":0,
    "gn:timezone":"Europe/Paris",
    "iso:country":"FR",
    "name:und_x_variant":[
        "Camp Sylvestre",
        "Camsilvestre",
        "Campsilvestre"
    ],
    "wof:name":"Campsilvestre",
    "wof:placetype":"locality"
},
  "geometry": {"coordinates":[2.09175,42.89744],"type":"Point"}
}