{
  "type": "Feature",
  "properties": {
    "gn:admin1_code":"44",
    "gn:admin2_code":"68",
    "gn:admin3_code":"683",
    "gn:admin4_code":"68178",
    "gn:asciiname":"Sengern",
    "gn:country_code":"FR",
    "gn:dem":496,
    "gn:feature_class":"P",
    "gn:feature_code":"PPL",
    "gn:name":"Sengern",
    "gn:population":0,
    "gn:timezone":"Europe/Paris",
    "iso:country":"FR",
    "wof:name":"Sengern",
    "wof:placetype":"locality"
},
  "geometry": {"coordinates":[7.12184,47.94099],"type":"Point"}
}