{
  "type": "Feature",
  "properties": {
    "gn:admin1_code":"53",
    "gn:admin2_code":"29",
    "gn:admin3_code":"294",
    "gn:admin4_code":"29048",
    "gn:asciiname":"Coat-Drega",
    "gn:country_code":"FR",
    "gn:dem":103,
    "gn:feature_class":"P",
    "gn:feature_code":"PPL",
    "gn:name":"Coat-Dr\u00e9ga",
    "gn:population":0,
    "gn:timezone":"Europe/Paris",
    "iso:country":"FR",
    "wof:name":"Coat-Drega",
    "wof:placetype":"locality"
},
  "geometry": {"coordinates":[-3.989,48.078],"type":"Point"}
}