{
  "type": "Feature",
  "properties": {
    "gn:admin1_code":"84",
    "gn:admin2_code":"38",
    "gn:admin3_code":"381",
    "gn:admin4_code":"38020",
    "gn:asciiname":"Le Mailloz",
    "gn:country_code":"FR",
    "gn:dem":914,
    "gn:feature_class":"P",
    "gn:feature_code":"PPL",
    "gn:name":"Le Mailloz",
    "gn:population":0,
    "gn:timezone":"Europe/Paris",
    "iso:country":"FR",
    "wof:name":"Le Mailloz",
    "wof:placetype":"locality"
},
  "geometry": {"coordinates":[6.10111,45.04209],"type":"Point"}
}