{
  "type": "Feature",
  "properties": {
    "gn:admin1_code":"44",
    "gn:admin2_code":"52",
    "gn:admin3_code":"521",
    "gn:admin4_code":"52074",
    "gn:asciiname":"Colombey-les-Choiseul",
    "gn:cc2":"FR",
    "gn:country_code":"FR",
    "gn:dem":350,
    "gn:feature_class":"P",
    "gn:feature_code":"PPL",
    "gn:name":"Colombey-l\u00e8s-Choiseul",
    "gn:population":0,
    "gn:timezone":"Europe/Paris",
    "iso:country":"FR",
    "name:und_x_variant":[
        "Colombey"
    ],
    "wof:name":"Colombey-les-Choiseul",
    "wof:placetype":"locality"
},
  "geometry": {"coordinates":[5.62654,48.06695],"type":"Point"}
}