{
  "type": "Feature",
  "properties": {
    "iso:country":"FR",
    "name:deu_x_preferred":[
        "Fourvi\u00e8re"
    ],
    "name:eng_x_preferred":[
        "Fourvi\u00e8re"
    ],
    "name:fra_x_preferred":[
        "Fourvi\u00e8re"
    ],
    "name:hye_x_preferred":[
        "\u0556\u0578\u0582\u0580\u057e\u056b\u0565\u0580"
    ],
    "name:ind_x_preferred":[
        "Fourvi\u00e8re"
    ],
    "name:ita_x_preferred":[
        "Fourvi\u00e8re"
    ],
    "name:lat_x_preferred":[
        "Forum Vetus"
    ],
    "name:nld_x_preferred":[
        "Fourvi\u00e8re"
    ],
    "name:nob_x_preferred":[
        "Fourvi\u00e8re"
    ],
    "name:por_x_preferred":[
        "Fourvi\u00e8re"
    ],
    "name:rus_x_preferred":[
        "\u0424\u0443\u0440\u0432\u044c\u0435\u0440"
    ],
    "name:spa_x_preferred":[
        "Fourvi\u00e8re"
    ],
    "name:zho_x_preferred":[
        "\u5bcc\u7ef4\u8036\u5c71"
    ],
    "wof:name":"Fourviere",
    "wof:placetype":"neighbourhood"
},
  "geometry": {"coordinates":[4.81852800560464,45.76197161178779],"type":"Point"}
}