{
  "type": "Feature",
  "properties": {
    "gn:admin1_code":"11",
    "gn:admin2_code":"78",
    "gn:admin3_code":"782",
    "gn:admin4_code":"78601",
    "gn:asciiname":"La Cheraille",
    "gn:country_code":"FR",
    "gn:dem":163,
    "gn:feature_class":"P",
    "gn:feature_code":"PPL",
    "gn:name":"La Cheraille",
    "gn:population":0,
    "gn:timezone":"Europe/Paris",
    "iso:country":"FR",
    "wof:name":"La Cheraille",
    "wof:placetype":"locality"
},
  "geometry": {"coordinates":[1.84399,48.59277],"type":"Point"}
}