{
  "type": "Feature",
  "properties": {
    "gn:admin1_code":"32",
    "gn:admin2_code":"60",
    "gn:admin3_code":"601",
    "gn:admin4_code":"60566",
    "gn:asciiname":"Marcoquet",
    "gn:country_code":"FR",
    "gn:dem":202,
    "gn:feature_class":"P",
    "gn:feature_code":"PPL",
    "gn:name":"Marcoquet",
    "gn:population":0,
    "gn:timezone":"Europe/Paris",
    "iso:country":"FR",
    "wof:name":"Marcoquet",
    "wof:placetype":"locality"
},
  "geometry": {"coordinates":[1.80611,49.64226],"type":"Point"}
}