{
  "type": "Feature",
  "properties": {
    "iso:country":"FR",
    "name:eng_x_preferred":[
        "Rose des Vents"
    ],
    "name:fer_x_variant":[
        "Cit\u00e9 des Milles-Milles"
    ],
    "name:fra_x_preferred":[
        "Rose des Vents"
    ],
    "name:fra_x_variant":[
        "Cit\u00e9 des 3000"
    ],
    "wof:name":"Rose des Vents",
    "wof:placetype":"neighbourhood"
},
  "geometry": {"coordinates":[2.49485569787174,48.95696583762794],"type":"Point"}
}