{
  "type": "Feature",
  "properties": {
    "gn:admin1_code":"24",
    "gn:admin2_code":"18",
    "gn:admin3_code":"181",
    "gn:admin4_code":"18056",
    "gn:asciiname":"Dejointe",
    "gn:country_code":"FR",
    "gn:dem":216,
    "gn:feature_class":"P",
    "gn:feature_code":"PPL",
    "gn:name":"Dejointe",
    "gn:population":0,
    "gn:timezone":"Europe/Paris",
    "iso:country":"FR",
    "name:und_x_variant":[
        "Dejointes",
        "Dejointe"
    ],
    "wof:name":"Dejointe",
    "wof:placetype":"locality"
},
  "geometry": {"coordinates":[2.85563,47.03038],"type":"Point"}
}