{
  "type": "Feature",
  "properties": {
    "gn:admin1_code":"75",
    "gn:admin2_code":"23",
    "gn:admin3_code":"231",
    "gn:admin4_code":"23220",
    "gn:asciiname":"Vaurousset",
    "gn:country_code":"FR",
    "gn:dem":513,
    "gn:feature_class":"P",
    "gn:feature_code":"PPL",
    "gn:name":"Vaurousset",
    "gn:population":0,
    "gn:timezone":"Europe/Paris",
    "iso:country":"FR",
    "wof:name":"Vaurousset",
    "wof:placetype":"locality"
},
  "geometry": {"coordinates":[2.16804,46.03958],"type":"Point"}
}