{
  "type": "Feature",
  "properties": {
    "gn:admin1_code":"27",
    "gn:admin2_code":"58",
    "gn:admin3_code":"583",
    "gn:admin4_code":"58055",
    "gn:asciiname":"Bussiere",
    "gn:country_code":"FR",
    "gn:dem":257,
    "gn:feature_class":"P",
    "gn:feature_code":"PPL",
    "gn:name":"Bussi\u00e8re",
    "gn:population":0,
    "gn:timezone":"Europe/Paris",
    "iso:country":"FR",
    "wof:name":"Bussiere",
    "wof:placetype":"locality"
},
  "geometry": {"coordinates":[3.50535,46.88842],"type":"Point"}
}