{
  "type": "Feature",
  "properties": {
    "gn:admin1_code":"84",
    "gn:admin2_code":"42",
    "gn:admin3_code":"421",
    "gn:admin4_code":"42211",
    "gn:asciiname":"Lurieux",
    "gn:country_code":"FR",
    "gn:dem":379,
    "gn:feature_class":"P",
    "gn:feature_code":"PPL",
    "gn:name":"Lurieux",
    "gn:population":0,
    "gn:timezone":"Europe/Paris",
    "iso:country":"FR",
    "wof:name":"Lurieux",
    "wof:placetype":"locality"
},
  "geometry": {"coordinates":[4.21667,45.53333],"type":"Point"}
}