{
  "type": "Feature",
  "properties": {
    "frgov:code_epci":"242101509",
    "frgov:insee_arr":"1",
    "frgov:insee_com":"21436",
    "frgov:insee_dep":"21",
    "frgov:insee_reg":"27",
    "frgov:nom_com":"Montmain",
    "frgov:nom_com_m":"MONTMAIN",
    "frgov:nom_dep":"COTE-D'OR",
    "frgov:nom_reg":"BOURGOGNE-FRANCHE-COMTE",
    "frgov:statut":"Commune simple",
    "gn:admin1_code":"27",
    "gn:admin2_code":"21",
    "gn:admin3_code":"211",
    "gn:admin4_code":"21436",
    "gn:asciiname":"Montmain",
    "gn:country_code":"FR",
    "gn:dem":204,
    "gn:feature_class":"P",
    "gn:feature_code":"PPL",
    "gn:name":"Montmain",
    "gn:population":0,
    "gn:timezone":"Europe/Paris",
    "iso:country":"FR",
    "name:ceb_x_preferred":[
        "Montmain"
    ],
    "name:deu_x_preferred":[
        "Montmain"
    ],
    "name:fra_x_preferred":[
        "Montmain"
    ],
    "name:ita_x_preferred":[
        "Montmain"
    ],
    "name:nds_x_preferred":[
        "Montmain"
    ],
    "name:nld_x_preferred":[
        "Montmain"
    ],
    "name:pms_x_preferred":[
        "Montmain"
    ],
    "name:pol_x_preferred":[
        "Montmain"
    ],
    "name:rus_x_preferred":[
        "\u041c\u043e\u043d\u043c\u0435\u043d"
    ],
    "name:slk_x_preferred":[
        "Montmain"
    ],
    "name:spa_x_preferred":[
        "Montmain"
    ],
    "name:swe_x_preferred":[
        "Montmain"
    ],
    "name:ukr_x_preferred":[
        "\u041c\u043e\u043d\u043c\u0435\u043d"
    ],
    "qs:a0":"France",
    "qs:a1":"COTE-D'OR",
    "qs:a1_lc":"21",
    "qs:a1r":"BOURGOGNE",
    "qs:a1r_lc":"26",
    "qs:a2_lc":"34",
    "qs:a2r_lc":"1",
    "qs:adm0":"France",
    "qs:adm0_a3":"FRA",
    "qs:la":"MONTMAIN",
    "qs:la_lc":"21436",
    "qs:level":"localadmin",
    "qs:type":"Commune simple",
    "wof:coterminous":[
        404416273
    ],
    "wof:name":"Montmain",
    "wof:placetype":"locality",
    "wof:placetype_local":"Commune simple"
},
  "geometry": {"coordinates":[5.06296,47.02997],"type":"Point"}
}