{
  "type": "Feature",
  "properties": {
    "gn:admin1_code":"75",
    "gn:admin2_code":"16",
    "gn:admin3_code":"163",
    "gn:admin4_code":"16085",
    "gn:asciiname":"Le Peage",
    "gn:country_code":"FR",
    "gn:dem":134,
    "gn:feature_class":"P",
    "gn:feature_code":"PPL",
    "gn:name":"Le P\u00e9age",
    "gn:population":0,
    "gn:timezone":"Europe/Paris",
    "iso:country":"FR",
    "wof:name":"Le Peage",
    "wof:placetype":"locality"
},
  "geometry": {"coordinates":[0.41661,45.79758],"type":"Point"}
}