{
  "type": "Feature",
  "properties": {
    "gn:admin1_code":"28",
    "gn:admin2_code":"14",
    "gn:admin3_code":"142",
    "gn:admin4_code":"14118.0",
    "gn:asciiname":"Faubourg de Vaucelles",
    "gn:country_code":"FR",
    "gn:dem":24,
    "gn:feature_class":"P",
    "gn:feature_code":"PPL",
    "gn:name":"Faubourg de Vaucelles",
    "gn:population":0,
    "gn:timezone":"Europe/Paris",
    "iso:country":"FR",
    "wof:name":"Faubourg de Vaucelles",
    "wof:placetype":"locality"
},
  "geometry": {"coordinates":[-0.35187,49.17247],"type":"Point"}
}