{
  "type": "Feature",
  "properties": {
    "frgov:code_epci":"200040095",
    "frgov:insee_arr":"3",
    "frgov:insee_com":"24213",
    "frgov:insee_dep":"24",
    "frgov:insee_reg":"75",
    "frgov:nom_com":"Jaure",
    "frgov:nom_com_m":"JAURE",
    "frgov:nom_dep":"DORDOGNE",
    "frgov:nom_reg":"NOUVELLE-AQUITAINE",
    "frgov:statut":"Commune simple",
    "gn:admin1_code":"75",
    "gn:admin2_code":"24",
    "gn:admin3_code":"243",
    "gn:admin4_code":"24213",
    "gn:asciiname":"Jaure",
    "gn:cc2":"FR",
    "gn:country_code":"FR",
    "gn:dem":168,
    "gn:feature_class":"P",
    "gn:feature_code":"PPL",
    "gn:name":"Jaure",
    "gn:population":0,
    "gn:timezone":"Europe/Paris",
    "iso:country":"FR",
    "name:bug_x_preferred":[
        "Jaure"
    ],
    "name:cat_x_preferred":[
        "Jaure"
    ],
    "name:ceb_x_preferred":[
        "Jaure"
    ],
    "name:deu_x_preferred":[
        "Jaure"
    ],
    "name:eus_x_preferred":[
        "Jaure"
    ],
    "name:fra_x_preferred":[
        "Jaure"
    ],
    "name:hun_x_preferred":[
        "Jaure"
    ],
    "name:ita_x_preferred":[
        "Jaure"
    ],
    "name:kaz_x_preferred":[
        "\u0416\u043e\u0440"
    ],
    "name:lat_x_preferred":[
        "Jaure"
    ],
    "name:mlg_x_preferred":[
        "Jaure"
    ],
    "name:msa_x_preferred":[
        "Jaure"
    ],
    "name:nld_x_preferred":[
        "Jaure"
    ],
    "name:oci_x_preferred":[
        "Jaure"
    ],
    "name:pms_x_preferred":[
        "Jaure"
    ],
    "name:pol_x_preferred":[
        "Jaure"
    ],
    "name:por_x_preferred":[
        "Jaure"
    ],
    "name:ron_x_preferred":[
        "Jaure"
    ],
    "name:rus_x_preferred":[
        "\u0416\u043e\u0440"
    ],
    "name:slk_x_preferred":[
        "Jaure"
    ],
    "name:spa_x_preferred":[
        "Jaure"
    ],
    "name:swe_x_preferred":[
        "Jaure"
    ],
    "name:ukr_x_preferred":[
        "\u0416\u043e\u0440"
    ],
    "name:und_x_variant":[
        "Jaures",
        "Jaure"
    ],
    "name:uzb_x_preferred":[
        "Jaure"
    ],
    "name:vie_x_preferred":[
        "Jaure"
    ],
    "name:vol_x_preferred":[
        "Jaure"
    ],
    "name:war_x_preferred":[
        "Jaure"
    ],
    "name:zho_x_preferred":[
        "\u82e5\u5c14"
    ],
    "qs:a0":"France",
    "qs:a1":"DORDOGNE",
    "qs:a1_lc":"24",
    "qs:a1r":"AQUITAINE",
    "qs:a1r_lc":"72",
    "qs:a2_lc":"30",
    "qs:a2r_lc":"3",
    "qs:adm0":"France",
    "qs:adm0_a3":"FRA",
    "qs:la":"JAURE",
    "qs:la_lc":"24213",
    "qs:level":"localadmin",
    "qs:type":"Commune simple",
    "wof:coterminous":[
        404369969
    ],
    "wof:name":"Jaure",
    "wof:placetype":"locality",
    "wof:placetype_local":"Commune simple"
},
  "geometry": {"coordinates":[0.55464,45.05782],"type":"Point"}
}