{
  "type": "Feature",
  "properties": {
    "gn:admin1_code":"75",
    "gn:admin2_code":"24",
    "gn:admin3_code":"243",
    "gn:admin4_code":"24213",
    "gn:asciiname":"Jaure",
    "gn:cc2":"FR",
    "gn:country_code":"FR",
    "gn:dem":168,
    "gn:feature_class":"P",
    "gn:feature_code":"PPL",
    "gn:name":"Jaure",
    "gn:population":0,
    "gn:timezone":"Europe/Paris",
    "iso:country":"FR",
    "name:kaz_x_preferred":[
        "\u0416\u043e\u0440"
    ],
    "name:rus_x_preferred":[
        "\u0416\u043e\u0440"
    ],
    "name:ukr_x_preferred":[
        "\u0416\u043e\u0440"
    ],
    "name:und_x_variant":[
        "Jaures",
        "Jaure"
    ],
    "name:zho_x_preferred":[
        "\u82e5\u5c14"
    ],
    "wof:name":"Jaure",
    "wof:placetype":"locality"
},
  "geometry": {"coordinates":[0.55464,45.05782],"type":"Point"}
}