{
  "type": "Feature",
  "properties": {
    "gn:admin1_code":"84",
    "gn:admin2_code":"38",
    "gn:admin3_code":"382",
    "gn:admin4_code":"38013",
    "gn:asciiname":"La Contamine",
    "gn:country_code":"FR",
    "gn:dem":490,
    "gn:feature_class":"P",
    "gn:feature_code":"PPL",
    "gn:name":"La Contamine",
    "gn:population":0,
    "gn:timezone":"Europe/Paris",
    "iso:country":"FR",
    "name:und_x_variant":[
        "Contamine",
        "La Contamine"
    ],
    "wof:name":"La Contamine",
    "wof:placetype":"locality"
},
  "geometry": {"coordinates":[5.47307,45.39929],"type":"Point"}
}