{
  "type": "Feature",
  "properties": {
    "gn:admin1_code":"32",
    "gn:admin2_code":"59",
    "gn:admin3_code":"591",
    "gn:admin4_code":"59392",
    "gn:asciiname":"Faubourg des Sarts",
    "gn:cc2":"FR",
    "gn:country_code":"FR",
    "gn:dem":146,
    "gn:feature_class":"P",
    "gn:feature_code":"PPL",
    "gn:name":"Faubourg des Sarts",
    "gn:population":0,
    "gn:timezone":"Europe/Paris",
    "iso:country":"FR",
    "name:und_x_variant":[
        "Les Sarts"
    ],
    "wof:name":"Faubourg des Sarts",
    "wof:placetype":"locality"
},
  "geometry": {"coordinates":[3.97379,50.29279],"type":"Point"}
}