{
  "type": "Feature",
  "properties": {
    "gn:admin1_code":"84",
    "gn:admin2_code":"74",
    "gn:admin3_code":"742",
    "gn:admin4_code":"74241",
    "gn:asciiname":"Pont du Giffre",
    "gn:cc2":"FR",
    "gn:country_code":"FR",
    "gn:dem":536,
    "gn:feature_class":"P",
    "gn:feature_code":"PPL",
    "gn:name":"Pont du Giffre",
    "gn:population":0,
    "gn:timezone":"Europe/Paris",
    "iso:country":"FR",
    "name:und_x_variant":[
        "Le Giffre"
    ],
    "wof:name":"Pont du Giffre",
    "wof:placetype":"locality"
},
  "geometry": {"coordinates":[6.47829,46.13607],"type":"Point"}
}