{
  "type": "Feature",
  "properties": {
    "gn:admin1_code":"84",
    "gn:admin2_code":"43",
    "gn:admin3_code":"432",
    "gn:admin4_code":"43043",
    "gn:asciiname":"Mameas",
    "gn:country_code":"FR",
    "gn:dem":868,
    "gn:feature_class":"P",
    "gn:feature_code":"PPL",
    "gn:name":"Mameas",
    "gn:population":0,
    "gn:timezone":"Europe/Paris",
    "iso:country":"FR",
    "wof:name":"Mameas",
    "wof:placetype":"locality"
},
  "geometry": {"coordinates":[3.72727,45.15937],"type":"Point"}
}