{
  "type": "Feature",
  "properties": {
    "gn:admin1_code":"93",
    "gn:admin2_code":"83",
    "gn:admin3_code":"833",
    "gn:admin4_code":"83140",
    "gn:asciiname":"Boulon",
    "gn:country_code":"FR",
    "gn:dem":304,
    "gn:feature_class":"P",
    "gn:feature_code":"PPL",
    "gn:name":"Boulon",
    "gn:population":0,
    "gn:timezone":"Europe/Paris",
    "iso:country":"FR",
    "name:bre_x_preferred":[
        "Boulon"
    ],
    "name:cat_x_preferred":[
        "Boulon"
    ],
    "name:ceb_x_preferred":[
        "Boulon"
    ],
    "name:deu_x_preferred":[
        "Boulon"
    ],
    "name:eus_x_preferred":[
        "Boulon"
    ],
    "name:fra_x_preferred":[
        "Boulon"
    ],
    "name:hun_x_preferred":[
        "Boulon"
    ],
    "name:hye_x_preferred":[
        "\u0532\u0578\u0582\u056c\u0578\u0576"
    ],
    "name:ind_x_preferred":[
        "Boulon"
    ],
    "name:ita_x_preferred":[
        "Boulon"
    ],
    "name:kaz_x_preferred":[
        "\u0411\u0443\u043b\u043e\u043d"
    ],
    "name:lat_x_preferred":[
        "Boulon"
    ],
    "name:msa_x_preferred":[
        "Boulon"
    ],
    "name:nld_x_preferred":[
        "Boulon"
    ],
    "name:oci_x_preferred":[
        "Boulon"
    ],
    "name:pam_x_preferred":[
        "Boulon"
    ],
    "name:pms_x_preferred":[
        "Boulon"
    ],
    "name:pol_x_preferred":[
        "Boulon"
    ],
    "name:por_x_preferred":[
        "Boulon"
    ],
    "name:ron_x_preferred":[
        "Boulon"
    ],
    "name:rus_x_preferred":[
        "\u0411\u0443\u043b\u043e\u043d"
    ],
    "name:slk_x_preferred":[
        "Boulon"
    ],
    "name:spa_x_preferred":[
        "Boulon"
    ],
    "name:srp_x_preferred":[
        "\u0411\u0443\u043b\u043e\u043d"
    ],
    "name:swe_x_preferred":[
        "Boulon"
    ],
    "name:ukr_x_preferred":[
        "\u0411\u0443\u043b\u043e\u043d"
    ],
    "name:uzb_x_preferred":[
        "Boulon"
    ],
    "name:vie_x_preferred":[
        "Boulon"
    ],
    "name:vol_x_preferred":[
        "Boulon"
    ],
    "name:war_x_preferred":[
        "Boulon"
    ],
    "wof:name":"Boulon",
    "wof:placetype":"locality"
},
  "geometry": {"coordinates":[5.89303,43.42048],"type":"Point"}
}