{
  "type": "Feature",
  "properties": {
    "gn:admin1_code":"84",
    "gn:admin2_code":"01",
    "gn:admin3_code":"012",
    "gn:admin4_code":"01125",
    "gn:asciiname":"Arnans",
    "gn:country_code":"FR",
    "gn:dem":566,
    "gn:feature_class":"P",
    "gn:feature_code":"PPL",
    "gn:name":"Arnans",
    "gn:population":0,
    "gn:timezone":"Europe/Paris",
    "iso:country":"FR",
    "wof:name":"Arnans",
    "wof:placetype":"locality"
},
  "geometry": {"coordinates":[5.45834,46.26155],"type":"Point"}
}