{
  "type": "Feature",
  "properties": {
    "gn:admin1_code":"75",
    "gn:admin2_code":"17",
    "gn:admin3_code":"173",
    "gn:admin4_code":"17297",
    "gn:asciiname":"Les Caillaux",
    "gn:country_code":"FR",
    "gn:dem":3,
    "gn:feature_class":"P",
    "gn:feature_code":"PPL",
    "gn:name":"Les Caillaux",
    "gn:population":0,
    "gn:timezone":"Europe/Paris",
    "iso:country":"FR",
    "wof:name":"Les Caillaux",
    "wof:placetype":"locality"
},
  "geometry": {"coordinates":[-1.275,46.15833],"type":"Point"}
}