{
  "type": "Feature",
  "properties": {
    "gn:admin1_code":"75",
    "gn:admin2_code":"24",
    "gn:admin3_code":"241",
    "gn:admin4_code":"24073",
    "gn:asciiname":"Larives",
    "gn:country_code":"FR",
    "gn:dem":65,
    "gn:feature_class":"P",
    "gn:feature_code":"PPL",
    "gn:name":"Larives",
    "gn:population":0,
    "gn:timezone":"Europe/Paris",
    "iso:country":"FR",
    "wof:name":"Larives",
    "wof:placetype":"locality"
},
  "geometry": {"coordinates":[0.80881,44.87851],"type":"Point"}
}