{
  "type": "Feature",
  "properties": {
    "gn:admin1_code":"24",
    "gn:admin2_code":"41",
    "gn:admin3_code":"413",
    "gn:admin4_code":"41194",
    "gn:asciiname":"Lanthenay",
    "gn:country_code":"FR",
    "gn:dem":95,
    "gn:feature_class":"P",
    "gn:feature_code":"PPL",
    "gn:name":"Lanthenay",
    "gn:population":0,
    "gn:timezone":"Europe/Paris",
    "iso:country":"FR",
    "wof:name":"Lanthenay",
    "wof:placetype":"locality"
},
  "geometry": {"coordinates":[1.734,47.38267000000001],"type":"Point"}
}