{
  "type": "Feature",
  "properties": {
    "iso:country":"FR",
    "name:ceb_x_preferred":[
        "Cergy-Pontoise"
    ],
    "name:ces_x_preferred":[
        "Cergy-Pontoise"
    ],
    "name:deu_x_preferred":[
        "Cergy-Pontoise"
    ],
    "name:eng_x_preferred":[
        "Cergy-Pontoise"
    ],
    "name:fra_x_preferred":[
        "Cergy-Pontoise"
    ],
    "name:heb_x_preferred":[
        "\u05e1\u05e8\u05d6'\u05d9-\u05e4\u05d5\u05e0\u05d8\u05d5\u05d0\u05d6"
    ],
    "name:ita_x_preferred":[
        "Cergy-Pontoise"
    ],
    "name:jpn_x_preferred":[
        "\u30bb\u30eb\u30b8\u30fc\u30fb\u30dd\u30f3\u30c8\u30ef\u30fc\u30ba"
    ],
    "name:por_x_preferred":[
        "Cergy-Pontoise"
    ],
    "name:zho_x_preferred":[
        "\u585e\u5c14\u5409-\u84ec\u56fe\u74e6\u5179"
    ],
    "qs_pg:aaroncc":"FR",
    "qs_pg:name":"Cergy-Pontoise",
    "qs_pg:name_adm0":"France",
    "qs_pg:name_adm1":"\u00cele-de-France",
    "qs_pg:photos":44,
    "qs_pg:photos_1k":9,
    "qs_pg:photos_9k":1,
    "qs_pg:photos_9r":2,
    "qs_pg:photos_all":44,
    "qs_pg:photos_sr":2,
    "qs_pg:pop_sr":0,
    "qs_pg:qs_pg_placetype":"locality",
    "qs_pg:qs_pg_placetype_gp":"Town",
    "qs_pg:woe_adm0":23424819,
    "woe:adm0_id":23424819,
    "woe:name_adm0":"France",
    "woe:name_adm1":"\u00cele-de-France",
    "woe:placetype":"Town",
    "wof:name":"Cergy-Pontoise",
    "wof:placetype":"neighbourhood"
},
  "geometry": {"coordinates":[2.076189,49.037189],"type":"Point"}
}