{
  "type": "Feature",
  "properties": {
    "gn:admin1_code":"28",
    "gn:admin2_code":"76",
    "gn:admin3_code":"763",
    "gn:admin4_code":"76113",
    "gn:asciiname":"Boissay",
    "gn:country_code":"FR",
    "gn:dem":161,
    "gn:feature_class":"P",
    "gn:feature_code":"PPL",
    "gn:name":"Boissay",
    "gn:population":0,
    "gn:timezone":"Europe/Paris",
    "iso:country":"FR",
    "wof:name":"Boissay",
    "wof:placetype":"locality"
},
  "geometry": {"coordinates":[1.35695,49.52002],"type":"Point"}
}