{
  "type": "Feature",
  "properties": {
    "gn:admin1_code":"28",
    "gn:admin2_code":"76",
    "gn:admin3_code":"763",
    "gn:admin4_code":"76113",
    "gn:asciiname":"Boissay",
    "gn:country_code":"FR",
    "gn:dem":161,
    "gn:feature_class":"P",
    "gn:feature_code":"PPL",
    "gn:name":"Boissay",
    "gn:population":0,
    "gn:timezone":"Europe/Paris",
    "iso:country":"FR",
    "name:cat_x_preferred":[
        "Boissay"
    ],
    "name:ceb_x_preferred":[
        "Boissay"
    ],
    "name:deu_x_preferred":[
        "Boissay"
    ],
    "name:eus_x_preferred":[
        "Boissay"
    ],
    "name:fra_x_preferred":[
        "Boissay"
    ],
    "name:hun_x_preferred":[
        "Boissay"
    ],
    "name:ita_x_preferred":[
        "Boissay"
    ],
    "name:kaz_x_preferred":[
        "\u0411\u0443\u0430\u0441\u0441\u0435"
    ],
    "name:lat_x_preferred":[
        "Boissay"
    ],
    "name:mlg_x_preferred":[
        "Boissay"
    ],
    "name:msa_x_preferred":[
        "Boissay"
    ],
    "name:nld_x_preferred":[
        "Boissay"
    ],
    "name:oci_x_preferred":[
        "Boissay"
    ],
    "name:pms_x_preferred":[
        "Boissay"
    ],
    "name:pol_x_preferred":[
        "Boissay"
    ],
    "name:por_x_preferred":[
        "Boissay"
    ],
    "name:ron_x_preferred":[
        "Boissay"
    ],
    "name:slk_x_preferred":[
        "Boissay"
    ],
    "name:spa_x_preferred":[
        "Boissay"
    ],
    "name:srp_x_preferred":[
        "\u0411\u043e\u0430\u0441\u0435"
    ],
    "name:swe_x_preferred":[
        "Boissay"
    ],
    "name:ukr_x_preferred":[
        "\u0411\u0443\u0430\u0441\u0441\u0435"
    ],
    "name:vie_x_preferred":[
        "Boissay"
    ],
    "name:vol_x_preferred":[
        "Boissay"
    ],
    "name:war_x_preferred":[
        "Boissay"
    ],
    "wof:name":"Boissay",
    "wof:placetype":"locality"
},
  "geometry": {"coordinates":[1.35695,49.52002],"type":"Point"}
}