{
  "type": "Feature",
  "properties": {
    "frgov:code_epci":"200070449",
    "frgov:insee_arr":"3",
    "frgov:insee_com":"76113",
    "frgov:insee_dep":"76",
    "frgov:insee_reg":"28",
    "frgov:nom_com":"Boissay",
    "frgov:nom_com_m":"BOISSAY",
    "frgov:nom_dep":"SEINE-MARITIME",
    "frgov:nom_reg":"NORMANDIE",
    "frgov:statut":"Commune simple",
    "gn:admin1_code":"28",
    "gn:admin2_code":"76",
    "gn:admin3_code":"763",
    "gn:admin4_code":"76113",
    "gn:asciiname":"Boissay",
    "gn:country_code":"FR",
    "gn:dem":161,
    "gn:feature_class":"P",
    "gn:feature_code":"PPL",
    "gn:name":"Boissay",
    "gn:population":0,
    "gn:timezone":"Europe/Paris",
    "iso:country":"FR",
    "name:cat_x_preferred":[
        "Boissay"
    ],
    "name:ceb_x_preferred":[
        "Boissay"
    ],
    "name:deu_x_preferred":[
        "Boissay"
    ],
    "name:eus_x_preferred":[
        "Boissay"
    ],
    "name:fra_x_preferred":[
        "Boissay"
    ],
    "name:hun_x_preferred":[
        "Boissay"
    ],
    "name:ita_x_preferred":[
        "Boissay"
    ],
    "name:kaz_x_preferred":[
        "\u0411\u0443\u0430\u0441\u0441\u0435"
    ],
    "name:lat_x_preferred":[
        "Boissay"
    ],
    "name:mlg_x_preferred":[
        "Boissay"
    ],
    "name:msa_x_preferred":[
        "Boissay"
    ],
    "name:nld_x_preferred":[
        "Boissay"
    ],
    "name:oci_x_preferred":[
        "Boissay"
    ],
    "name:pms_x_preferred":[
        "Boissay"
    ],
    "name:pol_x_preferred":[
        "Boissay"
    ],
    "name:por_x_preferred":[
        "Boissay"
    ],
    "name:ron_x_preferred":[
        "Boissay"
    ],
    "name:slk_x_preferred":[
        "Boissay"
    ],
    "name:spa_x_preferred":[
        "Boissay"
    ],
    "name:srp_x_preferred":[
        "\u0411\u043e\u0430\u0441\u0435"
    ],
    "name:swe_x_preferred":[
        "Boissay"
    ],
    "name:ukr_x_preferred":[
        "\u0411\u0443\u0430\u0441\u0441\u0435"
    ],
    "name:vie_x_preferred":[
        "Boissay"
    ],
    "name:vol_x_preferred":[
        "Boissay"
    ],
    "name:war_x_preferred":[
        "Boissay"
    ],
    "qs:a0":"France",
    "qs:a1":"SEINE-MARITIME",
    "qs:a1_lc":"76",
    "qs:a1r":"HAUTE-NORMANDIE",
    "qs:a1r_lc":"23",
    "qs:a2_lc":"08",
    "qs:a2r_lc":"3",
    "qs:adm0":"France",
    "qs:adm0_a3":"FRA",
    "qs:la":"BOISSAY",
    "qs:la_lc":"76113",
    "qs:level":"localadmin",
    "qs:type":"Commune simple",
    "wof:coterminous":[
        404400913
    ],
    "wof:name":"Boissay",
    "wof:placetype":"locality",
    "wof:placetype_local":"Commune simple"
},
  "geometry": {"coordinates":[1.35695,49.52002],"type":"Point"}
}