{
  "type": "Feature",
  "properties": {
    "gn:admin1_code":"44",
    "gn:admin2_code":"54",
    "gn:admin3_code":"542",
    "gn:admin4_code":"54013",
    "gn:asciiname":"Amenoncourt",
    "gn:country_code":"FR",
    "gn:dem":279,
    "gn:feature_class":"P",
    "gn:feature_code":"PPL",
    "gn:name":"Amenoncourt",
    "gn:population":0,
    "gn:timezone":"Europe/Paris",
    "iso:country":"FR",
    "name:cat_x_preferred":[
        "Amenoncourt"
    ],
    "name:ceb_x_preferred":[
        "Amenoncourt"
    ],
    "name:deu_x_preferred":[
        "Amenoncourt"
    ],
    "name:eus_x_preferred":[
        "Amenoncourt"
    ],
    "name:fas_x_preferred":[
        "\u0627\u0645\u0646\u0627\u0646\u06a9\u0648\u0631\u062a"
    ],
    "name:fra_x_preferred":[
        "Amenoncourt"
    ],
    "name:hun_x_preferred":[
        "Amenoncourt"
    ],
    "name:ita_x_preferred":[
        "Amenoncourt"
    ],
    "name:kaz_x_preferred":[
        "\u0410\u043c\u0435\u043d\u043e\u043d\u043a\u0443\u0440"
    ],
    "name:lat_x_preferred":[
        "Amenoncourt"
    ],
    "name:ltz_x_preferred":[
        "Amenoncourt"
    ],
    "name:mlg_x_preferred":[
        "Amenoncourt"
    ],
    "name:msa_x_preferred":[
        "Amenoncourt"
    ],
    "name:nld_x_preferred":[
        "Amenoncourt"
    ],
    "name:nor_x_preferred":[
        "Amenoncourt"
    ],
    "name:oci_x_preferred":[
        "Amenoncourt"
    ],
    "name:pol_x_preferred":[
        "Amenoncourt"
    ],
    "name:rus_x_preferred":[
        "\u0410\u043c\u043d\u043e\u043d\u043a\u0443\u0440"
    ],
    "name:slk_x_preferred":[
        "Amenoncourt"
    ],
    "name:spa_x_preferred":[
        "Amenoncourt"
    ],
    "name:srn_x_preferred":[
        "Amenoncourt"
    ],
    "name:srp_x_preferred":[
        "\u0410\u043c\u0430\u043d\u043e\u043d\u043a\u0443\u0440"
    ],
    "name:swe_x_preferred":[
        "Amenoncourt"
    ],
    "name:ukr_x_preferred":[
        "\u0410\u043c\u0435\u043d\u043e\u043d\u043a\u0443\u0440"
    ],
    "name:uzb_x_preferred":[
        "Amenoncourt"
    ],
    "name:vie_x_preferred":[
        "Amenoncourt"
    ],
    "name:vol_x_preferred":[
        "Amenoncourt"
    ],
    "name:war_x_preferred":[
        "Amenoncourt"
    ],
    "name:zho_x_preferred":[
        "\u963f\u8292\u7fc1\u5e93\u5c14"
    ],
    "wof:name":"Amenoncourt",
    "wof:placetype":"locality"
},
  "geometry": {"coordinates":[6.78946,48.6277],"type":"Point"}
}