{
  "type": "Feature",
  "properties": {
    "gn:admin1_code":"44",
    "gn:admin2_code":"54",
    "gn:admin3_code":"542",
    "gn:admin4_code":"54013",
    "gn:asciiname":"Amenoncourt",
    "gn:country_code":"FR",
    "gn:dem":279,
    "gn:feature_class":"P",
    "gn:feature_code":"PPL",
    "gn:name":"Amenoncourt",
    "gn:population":0,
    "gn:timezone":"Europe/Paris",
    "iso:country":"FR",
    "wof:name":"Amenoncourt",
    "wof:placetype":"locality"
},
  "geometry": {"coordinates":[6.78946,48.6277],"type":"Point"}
}