{
  "type": "Feature",
  "properties": {
    "gn:admin1_code":"75",
    "gn:admin2_code":"24",
    "gn:admin3_code":"244",
    "gn:admin4_code":"24035",
    "gn:asciiname":"Fongalop",
    "gn:country_code":"FR",
    "gn:dem":239,
    "gn:feature_class":"P",
    "gn:feature_code":"PPL",
    "gn:name":"Fongalop",
    "gn:population":0,
    "gn:timezone":"Europe/Paris",
    "iso:country":"FR",
    "wof:name":"Fongalop",
    "wof:placetype":"locality"
},
  "geometry": {"coordinates":[0.96286,44.72525],"type":"Point"}
}