{
  "type": "Feature",
  "properties": {
    "gn:admin1_code":"75",
    "gn:admin2_code":"17",
    "gn:admin3_code":"175",
    "gn:admin4_code":"17384",
    "gn:asciiname":"Saint-Pierre-de-l'Isle",
    "gn:country_code":"FR",
    "gn:dem":28,
    "gn:feature_class":"P",
    "gn:feature_code":"PPL",
    "gn:name":"Saint-Pierre-de-l'\u00cesle",
    "gn:population":0,
    "gn:timezone":"Europe/Paris",
    "iso:country":"FR",
    "name:und_x_variant":[
        "Saint-Pierre",
        "Saint-Pierre-de-l'\u00cele"
    ],
    "wof:name":"Saint-Pierre-de-l'Isle",
    "wof:placetype":"locality"
},
  "geometry": {"coordinates":[-0.4303,46.0325],"type":"Point"}
}