{
  "type": "Feature",
  "properties": {
    "gn:admin1_code":"75",
    "gn:admin2_code":"17",
    "gn:admin3_code":"175",
    "gn:admin4_code":"17384",
    "gn:asciiname":"Saint-Pierre-de-l'Isle",
    "gn:country_code":"FR",
    "gn:dem":28,
    "gn:feature_class":"P",
    "gn:feature_code":"PPL",
    "gn:name":"Saint-Pierre-de-l'\u00cesle",
    "gn:population":0,
    "gn:timezone":"Europe/Paris",
    "iso:country":"FR",
    "name:cat_x_preferred":[
        "Saint-Pierre-de-l'Isle"
    ],
    "name:ceb_x_preferred":[
        "Saint-Pierre-de-l'Isle"
    ],
    "name:deu_x_preferred":[
        "Saint-Pierre-de-l\u2019Isle"
    ],
    "name:epo_x_preferred":[
        "Saint-Pierre-de-l'Isle"
    ],
    "name:eus_x_preferred":[
        "Saint-Pierre-de-l'Isle"
    ],
    "name:fra_x_preferred":[
        "Saint-Pierre-de-l'Isle"
    ],
    "name:hun_x_preferred":[
        "Saint-Pierre-de-l\u2019Isle"
    ],
    "name:ita_x_preferred":[
        "Saint-Pierre-de-l'Isle"
    ],
    "name:lat_x_preferred":[
        "Saint-Pierre-de-l'Isle"
    ],
    "name:mlg_x_preferred":[
        "Saint-Pierre-de-l'Isle"
    ],
    "name:msa_x_preferred":[
        "Saint-Pierre-de-l'Isle"
    ],
    "name:nld_x_preferred":[
        "Saint-Pierre-de-l'Isle"
    ],
    "name:oci_x_preferred":[
        "Saint-Pierre-de-l'Isle"
    ],
    "name:pol_x_preferred":[
        "Saint-Pierre-de-l\u2019Isle"
    ],
    "name:por_x_preferred":[
        "Saint-Pierre-de-l'Isle"
    ],
    "name:ron_x_preferred":[
        "Saint-Pierre-de-l'Isle"
    ],
    "name:rus_x_preferred":[
        "\u0421\u0435\u043d-\u041f\u044c\u0435\u0440-\u0434\u0435-\u043b\u2019\u0418\u043b\u044c"
    ],
    "name:slk_x_preferred":[
        "Saint-Pierre-de-l\u2019Isle"
    ],
    "name:spa_x_preferred":[
        "Saint-Pierre-de-l'Isle"
    ],
    "name:swe_x_preferred":[
        "Saint-Pierre-de-l'Isle"
    ],
    "name:ukr_x_preferred":[
        "\u0421\u0435\u043d-\u041f'\u0454\u0440\u0440-\u0434\u0435-\u043b'\u0406\u043b\u044c"
    ],
    "name:und_x_variant":[
        "Saint-Pierre",
        "Saint-Pierre-de-l'\u00cele"
    ],
    "name:urd_x_preferred":[
        "\u0633\u06cc\u0646-\u067e\u06cc\u0631\u06cc-\u062f\u06d2-\u0644\u0627\u0633\u0644\u06d2"
    ],
    "name:vie_x_preferred":[
        "Saint-Pierre-de-l'Isle"
    ],
    "name:vol_x_preferred":[
        "Saint-Pierre-de-l'Isle"
    ],
    "name:war_x_preferred":[
        "Saint-Pierre-de-l'Isle"
    ],
    "name:zho_x_preferred":[
        "\u5723\u76ae\u8036\u5c14\u5fb7\u5229\u52d2"
    ],
    "wof:name":"Saint-Pierre-de-l'Isle",
    "wof:placetype":"locality"
},
  "geometry": {"coordinates":[-0.4303,46.0325],"type":"Point"}
}