{
  "type": "Feature",
  "properties": {
    "gn:admin1_code":"75",
    "gn:admin2_code":"23",
    "gn:admin3_code":"231",
    "gn:admin4_code":"23212",
    "gn:asciiname":"Chertrain",
    "gn:country_code":"FR",
    "gn:dem":678,
    "gn:feature_class":"P",
    "gn:feature_code":"PPL",
    "gn:name":"Chertrain",
    "gn:population":0,
    "gn:timezone":"Europe/Paris",
    "iso:country":"FR",
    "wof:name":"Chertrain",
    "wof:placetype":"locality"
},
  "geometry": {"coordinates":[2.01831,45.84891],"type":"Point"}
}