{
  "type": "Feature",
  "properties": {
    "iso:country":"FR",
    "name:eng_x_preferred":[
        "Quartier de Charonne"
    ],
    "name:fra_x_preferred":[
        "Quartier de Charonne"
    ],
    "wof:name":"Quartier de Charonne",
    "wof:placetype":"neighbourhood"
},
  "geometry": {"coordinates":[2.40595958059587,48.85375614935883],"type":"Point"}
}