{
  "type": "Feature",
  "properties": {
    "gn:admin1_code":"84",
    "gn:admin2_code":"43",
    "gn:admin3_code":"431",
    "gn:admin4_code":"43214",
    "gn:asciiname":"Clersange",
    "gn:country_code":"FR",
    "gn:dem":871,
    "gn:feature_class":"P",
    "gn:feature_code":"PPL",
    "gn:name":"Clersange",
    "gn:population":0,
    "gn:timezone":"Europe/Paris",
    "iso:country":"FR",
    "wof:name":"Clersange",
    "wof:placetype":"locality"
},
  "geometry": {"coordinates":[3.64503,45.26671],"type":"Point"}
}