{
  "type": "Feature",
  "properties": {
    "gn:admin1_code":"32",
    "gn:admin2_code":"59",
    "gn:admin3_code":"591",
    "gn:admin4_code":"59490",
    "gn:asciiname":"Rainsars",
    "gn:country_code":"FR",
    "gn:dem":182,
    "gn:feature_class":"P",
    "gn:feature_code":"PPL",
    "gn:name":"Rainsars",
    "gn:population":0,
    "gn:timezone":"Europe/Paris",
    "iso:country":"FR",
    "name:bre_x_preferred":[
        "Rainsars"
    ],
    "name:cat_x_preferred":[
        "Rainsars"
    ],
    "name:ceb_x_preferred":[
        "Rainsars"
    ],
    "name:deu_x_preferred":[
        "Rainsars"
    ],
    "name:epo_x_preferred":[
        "Rainsars"
    ],
    "name:eus_x_preferred":[
        "Rainsars"
    ],
    "name:fra_x_preferred":[
        "Rainsars"
    ],
    "name:hun_x_preferred":[
        "Rainsars"
    ],
    "name:ind_x_preferred":[
        "Rainsars"
    ],
    "name:ita_x_preferred":[
        "Rainsars"
    ],
    "name:kaz_x_preferred":[
        "\u0420\u0435\u043d\u0441\u0430\u0440"
    ],
    "name:lat_x_preferred":[
        "Rainsars"
    ],
    "name:mlg_x_preferred":[
        "Rainsars"
    ],
    "name:msa_x_preferred":[
        "Rainsars"
    ],
    "name:nld_x_preferred":[
        "Rainsars"
    ],
    "name:oci_x_preferred":[
        "Rainsars"
    ],
    "name:pol_x_preferred":[
        "Rainsars"
    ],
    "name:ron_x_preferred":[
        "Rainsars"
    ],
    "name:slk_x_preferred":[
        "Rainsars"
    ],
    "name:spa_x_preferred":[
        "Rainsars"
    ],
    "name:swe_x_preferred":[
        "Rainsars"
    ],
    "name:ukr_x_preferred":[
        "\u0420\u0435\u043d\u0441\u0430\u0440"
    ],
    "name:und_x_variant":[
        "Rainsart",
        "Rainsars"
    ],
    "name:vie_x_preferred":[
        "Rainsars"
    ],
    "name:vol_x_preferred":[
        "Rainsars"
    ],
    "name:war_x_preferred":[
        "Rainsars"
    ],
    "name:zho_x_preferred":[
        "\u5170\u8428\u5c14"
    ],
    "wof:name":"Rainsars",
    "wof:placetype":"locality"
},
  "geometry": {"coordinates":[3.99074,50.07075],"type":"Point"}
}