{
  "type": "Feature",
  "properties": {
    "gn:admin1_code":"24",
    "gn:admin2_code":"28",
    "gn:admin3_code":"283",
    "gn:admin4_code":"28394",
    "gn:asciiname":"Fortisle",
    "gn:country_code":"FR",
    "gn:dem":107,
    "gn:feature_class":"P",
    "gn:feature_code":"PPL",
    "gn:name":"Fortisle",
    "gn:population":0,
    "gn:timezone":"Europe/Paris",
    "iso:country":"FR",
    "name:und_x_variant":[
        "Fort-Ile",
        "Fortisle"
    ],
    "wof:name":"Fortisle",
    "wof:placetype":"locality"
},
  "geometry": {"coordinates":[1.32856,48.68663],"type":"Point"}
}