{
  "type": "Feature",
  "properties": {
    "gn:admin1_code":"28",
    "gn:admin2_code":"50",
    "gn:admin3_code":"502",
    "gn:admin4_code":"50421.0",
    "gn:asciiname":"Le Havre",
    "gn:country_code":"FR",
    "gn:dem":4,
    "gn:feature_class":"P",
    "gn:feature_code":"PPL",
    "gn:name":"Le Havre",
    "gn:population":0,
    "gn:timezone":"Europe/Paris",
    "iso:country":"FR",
    "wof:name":"Le Havre",
    "wof:placetype":"locality"
},
  "geometry": {"coordinates":[-1.28761,49.51503],"type":"Point"}
}