{
  "type": "Feature",
  "properties": {
    "gn:admin1_code":"84",
    "gn:admin2_code":"03",
    "gn:admin3_code":"031",
    "gn:admin4_code":"03313",
    "gn:asciiname":"La Villatte",
    "gn:country_code":"FR",
    "gn:dem":338,
    "gn:feature_class":"P",
    "gn:feature_code":"PPL",
    "gn:name":"La Villatte",
    "gn:population":0,
    "gn:timezone":"Europe/Paris",
    "iso:country":"FR",
    "wof:name":"La Villatte",
    "wof:placetype":"locality"
},
  "geometry": {"coordinates":[2.80419,46.54676],"type":"Point"}
}