{
  "type": "Feature",
  "properties": {
    "gn:admin1_code":"75",
    "gn:admin2_code":"24",
    "gn:admin3_code":"244",
    "gn:admin4_code":"24330",
    "gn:asciiname":"La Gagerie",
    "gn:country_code":"FR",
    "gn:dem":234,
    "gn:feature_class":"P",
    "gn:feature_code":"PPL",
    "gn:name":"La Gagerie",
    "gn:population":0,
    "gn:timezone":"Europe/Paris",
    "iso:country":"FR",
    "wof:name":"La Gagerie",
    "wof:placetype":"locality"
},
  "geometry": {"coordinates":[1.06667,45.03333],"type":"Point"}
}