{
  "type": "Feature",
  "properties": {
    "gn:admin1_code":"52",
    "gn:admin2_code":"49",
    "gn:admin3_code":"493",
    "gn:admin4_code":"49003",
    "gn:asciiname":"Hilay",
    "gn:country_code":"FR",
    "gn:dem":70,
    "gn:feature_class":"P",
    "gn:feature_code":"PPL",
    "gn:name":"Hilay",
    "gn:population":0,
    "gn:timezone":"Europe/Paris",
    "iso:country":"FR",
    "wof:name":"Hilay",
    "wof:placetype":"locality"
},
  "geometry": {"coordinates":[-0.37113,47.24012000000001],"type":"Point"}
}