{
  "type": "Feature",
  "properties": {
    "gn:admin1_code":"75",
    "gn:admin2_code":"19",
    "gn:admin3_code":"192",
    "gn:admin4_code":"19010",
    "gn:asciiname":"Le Bastier, Argentat",
    "gn:country_code":"FR",
    "gn:dem":194,
    "gn:feature_class":"P",
    "gn:feature_code":"PPL",
    "gn:name":"Le Bastier, Argentat",
    "gn:population":0,
    "gn:timezone":"Europe/Paris",
    "iso:country":"FR",
    "wof:name":"Le Bastier, Argentat",
    "wof:placetype":"locality"
},
  "geometry": {"coordinates":[1.94239,45.08888],"type":"Point"}
}