{
  "type": "Feature",
  "properties": {
    "gn:admin1_code":"27",
    "gn:admin2_code":"21",
    "gn:admin3_code":"213",
    "gn:admin4_code":"21272",
    "gn:asciiname":"Allerey",
    "gn:country_code":"FR",
    "gn:dem":347,
    "gn:feature_class":"P",
    "gn:feature_code":"PPL",
    "gn:name":"Allerey",
    "gn:population":0,
    "gn:timezone":"Europe/Paris",
    "iso:country":"FR",
    "name:bug_x_preferred":[
        "Allerey"
    ],
    "name:cat_x_preferred":[
        "Allerey"
    ],
    "name:ceb_x_preferred":[
        "Allerey"
    ],
    "name:deu_x_preferred":[
        "Allerey"
    ],
    "name:epo_x_preferred":[
        "Allerey"
    ],
    "name:eus_x_preferred":[
        "Allerey"
    ],
    "name:fas_x_preferred":[
        "\u0627\u0644\u06cc\u0631\u06cc"
    ],
    "name:fra_x_preferred":[
        "Allerey"
    ],
    "name:hun_x_preferred":[
        "Allerey"
    ],
    "name:ind_x_preferred":[
        "Allerey"
    ],
    "name:ita_x_preferred":[
        "Allerey"
    ],
    "name:kaz_x_preferred":[
        "\u0410\u043b\u043b\u0435\u0440\u0435"
    ],
    "name:lat_x_preferred":[
        "Yliriacum"
    ],
    "name:mlg_x_preferred":[
        "Allerey"
    ],
    "name:msa_x_preferred":[
        "Allerey"
    ],
    "name:nld_x_preferred":[
        "Allerey"
    ],
    "name:oci_x_preferred":[
        "Allerey"
    ],
    "name:pms_x_preferred":[
        "Allerey"
    ],
    "name:pol_x_preferred":[
        "Allerey"
    ],
    "name:por_x_preferred":[
        "Allerey"
    ],
    "name:ron_x_preferred":[
        "Allerey"
    ],
    "name:rus_x_preferred":[
        "\u0410\u043b\u043b\u0435\u0440\u0435"
    ],
    "name:slk_x_preferred":[
        "Allerey"
    ],
    "name:spa_x_preferred":[
        "Allerey"
    ],
    "name:srp_x_preferred":[
        "\u0410\u043b\u0435\u0440\u0435"
    ],
    "name:swe_x_preferred":[
        "Allerey"
    ],
    "name:ukr_x_preferred":[
        "\u0410\u043b\u043b\u0435\u0440\u0435"
    ],
    "name:urd_x_preferred":[
        "\u0622\u0644\u0631\u06d2"
    ],
    "name:uzb_x_preferred":[
        "Allerey"
    ],
    "name:vie_x_preferred":[
        "Allerey"
    ],
    "name:vol_x_preferred":[
        "Allerey"
    ],
    "name:war_x_preferred":[
        "Allerey"
    ],
    "name:zho_x_preferred":[
        "\u963f\u52d2\u96f7"
    ],
    "wof:name":"Allerey",
    "wof:placetype":"locality"
},
  "geometry": {"coordinates":[4.34453,47.45048],"type":"Point"}
}