{
  "type": "Feature",
  "properties": {
    "gn:admin1_code":"84",
    "gn:admin2_code":"63",
    "gn:admin3_code":"633",
    "gn:admin4_code":"63117",
    "gn:asciiname":"Brion",
    "gn:country_code":"FR",
    "gn:dem":1221,
    "gn:feature_class":"P",
    "gn:feature_code":"PPL",
    "gn:name":"Brion",
    "gn:population":0,
    "gn:timezone":"Europe/Paris",
    "iso:country":"FR",
    "name:ceb_x_preferred":[
        "Brion"
    ],
    "name:deu_x_preferred":[
        "Brion"
    ],
    "name:fra_x_preferred":[
        "Brion"
    ],
    "name:hun_x_preferred":[
        "Brion"
    ],
    "name:hye_x_preferred":[
        "\u0532\u0580\u056b\u0578\u0576"
    ],
    "name:ita_x_preferred":[
        "Brion"
    ],
    "name:jpn_x_preferred":[
        "\u30d6\u30ea\u30aa\u30f3"
    ],
    "name:kor_x_preferred":[
        "\ube0c\ub9ac\uc639"
    ],
    "name:nds_x_preferred":[
        "Brion"
    ],
    "name:nld_x_preferred":[
        "Brion"
    ],
    "name:oci_x_preferred":[
        "Brion"
    ],
    "name:pms_x_preferred":[
        "Brion"
    ],
    "name:pol_x_preferred":[
        "Brion"
    ],
    "name:por_x_preferred":[
        "Brion"
    ],
    "name:ron_x_preferred":[
        "Brion"
    ],
    "name:rus_x_preferred":[
        "\u0411\u0440\u0438\u043e\u043d"
    ],
    "name:slk_x_preferred":[
        "Brion"
    ],
    "name:srp_x_preferred":[
        "\u0411\u0440\u0438\u043e\u043d"
    ],
    "name:swe_x_preferred":[
        "Brion"
    ],
    "name:ukr_x_preferred":[
        "\u0411\u0440\u0456\u043e\u043d"
    ],
    "name:zho_x_preferred":[
        "\u5e03\u91cc\u7fc1"
    ],
    "wof:name":"Brion",
    "wof:placetype":"locality"
},
  "geometry": {"coordinates":[2.95794,45.41494],"type":"Point"}
}