{
  "type": "Feature",
  "properties": {
    "iso:country":"FR",
    "name:eng_x_preferred":[
        "Bois l'Abbe"
    ],
    "name:fra_x_preferred":[
        "Bois l'Abb\u00e9"
    ],
    "name:fra_x_variant":[
        "Bois-L'abb\u00e9-Salvador-Allende"
    ],
    "wof:name":"Bois l'Abbe",
    "wof:placetype":"neighbourhood"
},
  "geometry": {"coordinates":[2.55078463515444,48.80604013829748],"type":"Point"}
}