{
  "type": "Feature",
  "properties": {
    "gn:admin1_code":"75",
    "gn:admin2_code":"79",
    "gn:admin3_code":"791",
    "gn:admin4_code":"79171",
    "gn:asciiname":"Rigne",
    "gn:country_code":"FR",
    "gn:dem":105,
    "gn:feature_class":"P",
    "gn:feature_code":"PPL",
    "gn:name":"Rign\u00e9",
    "gn:population":0,
    "gn:timezone":"Europe/Paris",
    "iso:country":"FR",
    "name:und_x_variant":[
        "Rign\u00e9"
    ],
    "wof:name":"Rigne",
    "wof:placetype":"locality"
},
  "geometry": {"coordinates":[-0.24734,46.94341],"type":"Point"}
}