{
  "type": "Feature",
  "properties": {
    "gn:admin1_code":"84",
    "gn:admin2_code":"43",
    "gn:admin3_code":"433",
    "gn:admin4_code":"43244",
    "gn:asciiname":"Chaumargeais",
    "gn:country_code":"FR",
    "gn:dem":1004,
    "gn:feature_class":"P",
    "gn:feature_code":"PPL",
    "gn:name":"Chaumargeais",
    "gn:population":0,
    "gn:timezone":"Europe/Paris",
    "iso:country":"FR",
    "wof:name":"Chaumargeais",
    "wof:placetype":"locality"
},
  "geometry": {"coordinates":[4.344,45.09006],"type":"Point"}
}