{
  "type": "Feature",
  "properties": {
    "gn:admin1_code":"28",
    "gn:admin2_code":"61",
    "gn:admin3_code":"613",
    "gn:admin4_code":"61411.0",
    "gn:asciiname":"La Gravelle",
    "gn:country_code":"FR",
    "gn:dem":169,
    "gn:feature_class":"P",
    "gn:feature_code":"PPL",
    "gn:name":"La Gravelle",
    "gn:population":0,
    "gn:timezone":"Europe/Paris",
    "iso:country":"FR",
    "name:und_x_variant":[
        "La Basse Gravelle",
        "La Gravelle"
    ],
    "wof:name":"La Gravelle",
    "wof:placetype":"locality"
},
  "geometry": {"coordinates":[0.45842,48.4408],"type":"Point"}
}