{
  "type": "Feature",
  "properties": {
    "gn:admin1_code":"28",
    "gn:admin2_code":"61",
    "gn:admin3_code":"613",
    "gn:admin4_code":"61411.0",
    "gn:asciiname":"La Gravelle",
    "gn:country_code":"FR",
    "gn:dem":169,
    "gn:feature_class":"P",
    "gn:feature_code":"PPL",
    "gn:name":"La Gravelle",
    "gn:population":0,
    "gn:timezone":"Europe/Paris",
    "iso:country":"FR",
    "name:cat_x_preferred":[
        "La Gravelle"
    ],
    "name:ceb_x_preferred":[
        "La Gravelle"
    ],
    "name:deu_x_preferred":[
        "La Gravelle"
    ],
    "name:eus_x_preferred":[
        "La Gravelle"
    ],
    "name:fra_x_preferred":[
        "La Gravelle"
    ],
    "name:hun_x_preferred":[
        "La Gravelle"
    ],
    "name:ita_x_preferred":[
        "La Gravelle"
    ],
    "name:lat_x_preferred":[
        "La Gravelle"
    ],
    "name:msa_x_preferred":[
        "La Gravelle"
    ],
    "name:nld_x_preferred":[
        "La Gravelle"
    ],
    "name:oci_x_preferred":[
        "La Gravelle"
    ],
    "name:pms_x_preferred":[
        "La Gravelle"
    ],
    "name:pol_x_preferred":[
        "La Gravelle"
    ],
    "name:por_x_preferred":[
        "La Gravelle"
    ],
    "name:ron_x_preferred":[
        "La Gravelle"
    ],
    "name:slk_x_preferred":[
        "La Gravelle"
    ],
    "name:spa_x_preferred":[
        "La Gravelle"
    ],
    "name:swe_x_preferred":[
        "La Gravelle"
    ],
    "name:ukr_x_preferred":[
        "\u041b\u0430-\u0413\u0440\u0430\u0432\u0435\u043b\u044c"
    ],
    "name:und_x_variant":[
        "La Basse Gravelle",
        "La Gravelle"
    ],
    "name:urd_x_preferred":[
        "\u0644\u0627 \u06af\u0631\u0627\u0648\u06cc\u0644\u06cc"
    ],
    "name:vie_x_preferred":[
        "La Gravelle"
    ],
    "name:vol_x_preferred":[
        "La Gravelle"
    ],
    "name:war_x_preferred":[
        "La Gravelle"
    ],
    "name:zho_x_preferred":[
        "\u62c9\u683c\u62c9\u97e6\u5c14"
    ],
    "wof:name":"La Gravelle",
    "wof:placetype":"locality"
},
  "geometry": {"coordinates":[0.45842,48.4408],"type":"Point"}
}