{
  "type": "Feature",
  "properties": {
    "gn:admin1_code":"75",
    "gn:admin2_code":"24",
    "gn:admin3_code":"244",
    "gn:admin4_code":"24081",
    "gn:asciiname":"Le Mas",
    "gn:country_code":"FR",
    "gn:dem":236,
    "gn:feature_class":"P",
    "gn:feature_code":"PPL",
    "gn:name":"Le Mas",
    "gn:population":0,
    "gn:timezone":"Europe/Paris",
    "iso:country":"FR",
    "wof:name":"Le Mas",
    "wof:placetype":"locality"
},
  "geometry": {"coordinates":[1.33333,44.88333],"type":"Point"}
}