{
  "type": "Feature",
  "properties": {
    "gn:admin1_code":"84",
    "gn:admin2_code":"63",
    "gn:admin3_code":"635",
    "gn:admin4_code":"63195",
    "gn:asciiname":"Les Bontemps",
    "gn:country_code":"FR",
    "gn:dem":333,
    "gn:feature_class":"P",
    "gn:feature_code":"PPL",
    "gn:name":"Les Bontemps",
    "gn:population":0,
    "gn:timezone":"Europe/Paris",
    "iso:country":"FR",
    "wof:name":"Les Bontemps",
    "wof:placetype":"locality"
},
  "geometry": {"coordinates":[3.3719,45.80617],"type":"Point"}
}