{
  "type": "Feature",
  "properties": {
    "gn:admin1_code":"93",
    "gn:admin2_code":"05",
    "gn:admin3_code":"052",
    "gn:admin4_code":"05159",
    "gn:asciiname":"La Tuiliere",
    "gn:country_code":"FR",
    "gn:dem":605,
    "gn:feature_class":"P",
    "gn:feature_code":"PPL",
    "gn:name":"La Tuili\u00e8re",
    "gn:population":0,
    "gn:timezone":"Europe/Paris",
    "iso:country":"FR",
    "wof:name":"La Tuiliere",
    "wof:placetype":"locality"
},
  "geometry": {"coordinates":[5.7844,44.31687],"type":"Point"}
}