{
  "type": "Feature",
  "properties": {
    "gn:admin1_code":"84",
    "gn:admin2_code":"43",
    "gn:admin3_code":"431",
    "gn:admin4_code":"43123",
    "gn:asciiname":"Angelane",
    "gn:country_code":"FR",
    "gn:dem":565,
    "gn:feature_class":"P",
    "gn:feature_code":"PPL",
    "gn:name":"Angelane",
    "gn:population":0,
    "gn:timezone":"Europe/Paris",
    "iso:country":"FR",
    "wof:name":"Angelane",
    "wof:placetype":"locality"
},
  "geometry": {"coordinates":[3.24591,45.32863],"type":"Point"}
}