{
  "type": "Feature",
  "properties": {
    "iso:country":"FR",
    "name:eng_x_preferred":[
        "Haut de Puteaux"
    ],
    "name:fra_x_preferred":[
        "Haut de Puteaux"
    ],
    "wof:name":"Haut de Puteaux",
    "wof:placetype":"neighbourhood"
},
  "geometry": {"coordinates":[2.22923592406963,48.88518357055787],"type":"Point"}
}