{
  "type": "Feature",
  "properties": {
    "gn:admin1_code":"24",
    "gn:admin2_code":"37",
    "gn:admin3_code":"371",
    "gn:admin4_code":"37228",
    "gn:asciiname":"L'Epaisse",
    "gn:country_code":"FR",
    "gn:dem":64,
    "gn:feature_class":"P",
    "gn:feature_code":"PPL",
    "gn:name":"L\u2019\u00c9paisse",
    "gn:population":0,
    "gn:timezone":"Europe/Paris",
    "iso:country":"FR",
    "wof:name":"L'Epaisse",
    "wof:placetype":"locality"
},
  "geometry": {"coordinates":[0.13442,47.29852],"type":"Point"}
}