{
  "type": "Feature",
  "properties": {
    "gn:admin1_code":"44",
    "gn:admin2_code":"10",
    "gn:admin3_code":"103",
    "gn:admin4_code":"10241",
    "gn:asciiname":"Le Vau",
    "gn:country_code":"FR",
    "gn:dem":133,
    "gn:feature_class":"P",
    "gn:feature_code":"PPL",
    "gn:name":"Le Vau",
    "gn:population":0,
    "gn:timezone":"Europe/Paris",
    "iso:country":"FR",
    "name:und_x_variant":[
        "Le Veau",
        "Le Vau"
    ],
    "wof:name":"Le Vau",
    "wof:placetype":"locality"
},
  "geometry": {"coordinates":[4.08463,48.06927],"type":"Point"}
}