{
  "type": "Feature",
  "properties": {
    "gn:admin1_code":"84",
    "gn:admin2_code":"63",
    "gn:admin3_code":"634",
    "gn:admin4_code":"63338",
    "gn:asciiname":"Les Forges",
    "gn:country_code":"FR",
    "gn:dem":593,
    "gn:feature_class":"P",
    "gn:feature_code":"PPL",
    "gn:name":"Les Forges",
    "gn:population":0,
    "gn:timezone":"Europe/Paris",
    "iso:country":"FR",
    "wof:name":"Les Forges",
    "wof:placetype":"locality"
},
  "geometry": {"coordinates":[2.82825,46.17591],"type":"Point"}
}