{
  "type": "Feature",
  "properties": {
    "gn:admin1_code":"84",
    "gn:admin2_code":"43",
    "gn:admin3_code":"431",
    "gn:admin4_code":"43222",
    "gn:asciiname":"Cerzat",
    "gn:country_code":"FR",
    "gn:dem":668,
    "gn:feature_class":"P",
    "gn:feature_code":"PPL",
    "gn:name":"Cerzat",
    "gn:population":0,
    "gn:timezone":"Europe/Paris",
    "iso:country":"FR",
    "name:bug_x_preferred":[
        "Cerzat"
    ],
    "name:cat_x_preferred":[
        "Cerzac"
    ],
    "name:ceb_x_preferred":[
        "Cerzat"
    ],
    "name:deu_x_preferred":[
        "Cerzat"
    ],
    "name:eus_x_preferred":[
        "Cerzat"
    ],
    "name:fra_x_preferred":[
        "Cerzat"
    ],
    "name:hun_x_preferred":[
        "Cerzat"
    ],
    "name:ita_x_preferred":[
        "Cerzat"
    ],
    "name:kaz_x_preferred":[
        "\u0421\u0435\u0440\u0437\u0430"
    ],
    "name:lat_x_preferred":[
        "Cerzat"
    ],
    "name:ltz_x_preferred":[
        "Cerzat"
    ],
    "name:mlg_x_preferred":[
        "Cerzat"
    ],
    "name:msa_x_preferred":[
        "Cerzat"
    ],
    "name:nld_x_preferred":[
        "Cerzat"
    ],
    "name:oci_x_preferred":[
        "Cerzat"
    ],
    "name:pms_x_preferred":[
        "Cerzat"
    ],
    "name:pol_x_preferred":[
        "Cerzat"
    ],
    "name:por_x_preferred":[
        "Cerzat"
    ],
    "name:ron_x_preferred":[
        "Cerzat"
    ],
    "name:slk_x_preferred":[
        "Cerzat"
    ],
    "name:spa_x_preferred":[
        "Cerzat"
    ],
    "name:srp_x_preferred":[
        "\u0421\u0435\u0440\u0437\u0430"
    ],
    "name:swe_x_preferred":[
        "Cerzat"
    ],
    "name:ukr_x_preferred":[
        "\u0421\u0435\u0440\u0437\u0430"
    ],
    "name:und_x_variant":[
        "Cerzat du Dragon",
        "Cerzat"
    ],
    "name:uzb_x_preferred":[
        "Cerzat"
    ],
    "name:vie_x_preferred":[
        "Cerzat"
    ],
    "name:vol_x_preferred":[
        "Cerzat"
    ],
    "name:war_x_preferred":[
        "Cerzat"
    ],
    "name:zho_x_preferred":[
        "\u585e\u5c14\u624e"
    ],
    "wof:name":"Cerzat",
    "wof:placetype":"locality"
},
  "geometry": {"coordinates":[3.42098,45.20133],"type":"Point"}
}