{
  "type": "Feature",
  "properties": {
    "gn:admin1_code":"84",
    "gn:admin2_code":"43",
    "gn:admin3_code":"431",
    "gn:admin4_code":"43222",
    "gn:asciiname":"Cerzat",
    "gn:country_code":"FR",
    "gn:dem":668,
    "gn:feature_class":"P",
    "gn:feature_code":"PPL",
    "gn:name":"Cerzat",
    "gn:population":0,
    "gn:timezone":"Europe/Paris",
    "iso:country":"FR",
    "name:und_x_variant":[
        "Cerzat du Dragon",
        "Cerzat"
    ],
    "wof:name":"Cerzat",
    "wof:placetype":"locality"
},
  "geometry": {"coordinates":[3.42098,45.20133],"type":"Point"}
}