{
  "type": "Feature",
  "properties": {
    "gn:admin1_code":"28",
    "gn:admin2_code":"76",
    "gn:admin3_code":"761",
    "gn:admin4_code":"76526.0",
    "gn:asciiname":"Val-de-Ricarville",
    "gn:country_code":"FR",
    "gn:dem":77,
    "gn:feature_class":"P",
    "gn:feature_code":"PPL",
    "gn:name":"Val-de-Ricarville",
    "gn:population":0,
    "gn:timezone":"Europe/Paris",
    "iso:country":"FR",
    "wof:name":"Val-de-Ricarville",
    "wof:placetype":"locality"
},
  "geometry": {"coordinates":[1.26483,49.79991],"type":"Point"}
}