{
  "type": "Feature",
  "properties": {
    "gn:admin1_code":"44",
    "gn:admin2_code":"08",
    "gn:admin3_code":"081",
    "gn:admin4_code":"08105",
    "gn:asciiname":"Mohon",
    "gn:country_code":"FR",
    "gn:dem":152,
    "gn:feature_class":"P",
    "gn:feature_code":"PPL",
    "gn:name":"Mohon",
    "gn:population":0,
    "gn:timezone":"Europe/Paris",
    "iso:country":"FR",
    "wof:name":"Mohon",
    "wof:placetype":"locality"
},
  "geometry": {"coordinates":[4.72838,49.74978],"type":"Point"}
}