{
  "type": "Feature",
  "properties": {
    "gn:admin1_code":"84",
    "gn:admin2_code":"26",
    "gn:admin3_code":"261",
    "gn:admin4_code":"26368",
    "gn:asciiname":"Peyrache",
    "gn:country_code":"FR",
    "gn:dem":392,
    "gn:feature_class":"P",
    "gn:feature_code":"PPL",
    "gn:name":"Peyrache",
    "gn:population":0,
    "gn:timezone":"Europe/Paris",
    "iso:country":"FR",
    "wof:name":"Peyrache",
    "wof:placetype":"locality"
},
  "geometry": {"coordinates":[5.25639,44.71016],"type":"Point"}
}