{
  "type": "Feature",
  "properties": {
    "gn:admin1_code":"24",
    "gn:admin2_code":"45",
    "gn:admin3_code":"451",
    "gn:admin4_code":"45227.0",
    "gn:asciiname":"Montoire",
    "gn:country_code":"FR",
    "gn:dem":137,
    "gn:feature_class":"P",
    "gn:feature_code":"PPL",
    "gn:name":"Montoire",
    "gn:population":0,
    "gn:timezone":"Europe/Paris",
    "iso:country":"FR",
    "name:und_x_variant":[
        "Montoir",
        "Montoire"
    ],
    "wof:name":"Montoire",
    "wof:placetype":"locality"
},
  "geometry": {"coordinates":[2.55991,47.71924],"type":"Point"}
}