{
  "type": "Feature",
  "properties": {
    "gn:admin1_code":"84",
    "gn:admin2_code":"38",
    "gn:admin3_code":"381",
    "gn:admin4_code":"38245",
    "gn:asciiname":"Montagne",
    "gn:country_code":"FR",
    "gn:dem":447,
    "gn:feature_class":"P",
    "gn:feature_code":"PPL",
    "gn:name":"Montagne",
    "gn:population":0,
    "gn:timezone":"Europe/Paris",
    "iso:country":"FR",
    "name:bel_x_preferred":[
        "\u041c\u0430\u043d\u0442\u0430\u043d\u044c\u0435"
    ],
    "name:ceb_x_preferred":[
        "Montagne"
    ],
    "name:deu_x_preferred":[
        "Montagne"
    ],
    "name:epo_x_preferred":[
        "Montagne"
    ],
    "name:eus_x_preferred":[
        "Montagne"
    ],
    "name:fra_x_preferred":[
        "Montagne"
    ],
    "name:ita_x_preferred":[
        "Montagne"
    ],
    "name:jpn_x_preferred":[
        "\u30e2\u30f3\u30bf\u30fc\u30cb\u30e5"
    ],
    "name:nds_x_preferred":[
        "Montagne"
    ],
    "name:nld_x_preferred":[
        "Montagne"
    ],
    "name:pms_x_preferred":[
        "Montagne"
    ],
    "name:pol_x_preferred":[
        "Montagne"
    ],
    "name:por_x_preferred":[
        "Montagne"
    ],
    "name:ron_x_preferred":[
        "Montagne"
    ],
    "name:slk_x_preferred":[
        "Montagne"
    ],
    "name:spa_x_preferred":[
        "Montagne"
    ],
    "name:srp_x_preferred":[
        "Montanje"
    ],
    "name:swe_x_preferred":[
        "Montagne"
    ],
    "name:ukr_x_preferred":[
        "\u041c\u043e\u043d\u0442\u0430\u043d\u044c"
    ],
    "wof:name":"Montagne",
    "wof:placetype":"locality"
},
  "geometry": {"coordinates":[5.19272,45.14196],"type":"Point"}
}