{
  "type": "Feature",
  "properties": {
    "frgov:code_epci":"200070431",
    "frgov:insee_arr":"1",
    "frgov:insee_com":"38245",
    "frgov:insee_dep":"38",
    "frgov:insee_reg":"84",
    "frgov:nom_com":"Montagne",
    "frgov:nom_com_m":"MONTAGNE",
    "frgov:nom_dep":"ISERE",
    "frgov:nom_reg":"AUVERGNE-RHONE-ALPES",
    "frgov:statut":"Commune simple",
    "gn:admin1_code":"84",
    "gn:admin2_code":"38",
    "gn:admin3_code":"381",
    "gn:admin4_code":"38245",
    "gn:asciiname":"Montagne",
    "gn:country_code":"FR",
    "gn:dem":447,
    "gn:feature_class":"P",
    "gn:feature_code":"PPL",
    "gn:name":"Montagne",
    "gn:population":0,
    "gn:timezone":"Europe/Paris",
    "iso:country":"FR",
    "name:bel_x_preferred":[
        "\u041c\u0430\u043d\u0442\u0430\u043d\u044c\u0435"
    ],
    "name:ceb_x_preferred":[
        "Montagne"
    ],
    "name:deu_x_preferred":[
        "Montagne"
    ],
    "name:epo_x_preferred":[
        "Montagne"
    ],
    "name:eus_x_preferred":[
        "Montagne"
    ],
    "name:fra_x_preferred":[
        "Montagne"
    ],
    "name:ita_x_preferred":[
        "Montagne"
    ],
    "name:jpn_x_preferred":[
        "\u30e2\u30f3\u30bf\u30fc\u30cb\u30e5"
    ],
    "name:nds_x_preferred":[
        "Montagne"
    ],
    "name:nld_x_preferred":[
        "Montagne"
    ],
    "name:pms_x_preferred":[
        "Montagne"
    ],
    "name:pol_x_preferred":[
        "Montagne"
    ],
    "name:por_x_preferred":[
        "Montagne"
    ],
    "name:ron_x_preferred":[
        "Montagne"
    ],
    "name:slk_x_preferred":[
        "Montagne"
    ],
    "name:spa_x_preferred":[
        "Montagne"
    ],
    "name:srp_x_preferred":[
        "Montanje"
    ],
    "name:swe_x_preferred":[
        "Montagne"
    ],
    "name:ukr_x_preferred":[
        "\u041c\u043e\u043d\u0442\u0430\u043d\u044c"
    ],
    "qs:a0":"France",
    "qs:a1":"ISERE",
    "qs:a1_lc":"38",
    "qs:a1r":"RHONE-ALPES",
    "qs:a1r_lc":"82",
    "qs:a2_lc":"30",
    "qs:a2r_lc":"1",
    "qs:adm0":"France",
    "qs:adm0_a3":"FRA",
    "qs:la":"MONTAGNE",
    "qs:la_lc":"38245",
    "qs:level":"localadmin",
    "qs:type":"Commune simple",
    "wof:coterminous":[
        404378061
    ],
    "wof:name":"Montagne",
    "wof:placetype":"locality",
    "wof:placetype_local":"Commune simple"
},
  "geometry": {"coordinates":[5.19272,45.14196],"type":"Point"}
}