{
  "type": "Feature",
  "properties": {
    "gn:admin1_code":"53",
    "gn:asciiname":"Le Lue",
    "gn:country_code":"FR",
    "gn:dem":-9999,
    "gn:feature_class":"P",
    "gn:feature_code":"PPL",
    "gn:name":"Le Lu\u00e9",
    "gn:population":0,
    "gn:timezone":"Europe/Paris",
    "iso:country":"FR",
    "wof:name":"Le Lue",
    "wof:placetype":"locality"
},
  "geometry": {"coordinates":[-3.94583,47.68611],"type":"Point"}
}