{
  "type": "Feature",
  "properties": {
    "gn:admin1_code":"44",
    "gn:admin2_code":"54",
    "gn:admin3_code":"541",
    "gn:admin4_code":"54138",
    "gn:asciiname":"Vaux",
    "gn:country_code":"FR",
    "gn:dem":281,
    "gn:feature_class":"P",
    "gn:feature_code":"PPL",
    "gn:name":"Vaux",
    "gn:population":0,
    "gn:timezone":"Europe/Paris",
    "iso:country":"FR",
    "wof:name":"Vaux",
    "wof:placetype":"locality"
},
  "geometry": {"coordinates":[5.71091,49.53384000000001],"type":"Point"}
}