{
  "type": "Feature",
  "properties": {
    "gn:admin1_code":"75",
    "gn:admin2_code":"86",
    "gn:admin3_code":"862",
    "gn:admin4_code":"86189",
    "gn:asciiname":"La Touche",
    "gn:country_code":"FR",
    "gn:dem":155,
    "gn:feature_class":"P",
    "gn:feature_code":"PPL",
    "gn:name":"La Touche",
    "gn:population":0,
    "gn:timezone":"Europe/Paris",
    "iso:country":"FR",
    "wof:name":"La Touche",
    "wof:placetype":"locality"
},
  "geometry": {"coordinates":[0.48824,46.225],"type":"Point"}
}