{
  "type": "Feature",
  "properties": {
    "gn:admin1_code":"84",
    "gn:admin2_code":"03",
    "gn:admin3_code":"031",
    "gn:admin4_code":"03191",
    "gn:asciiname":"Risseau",
    "gn:country_code":"FR",
    "gn:dem":304,
    "gn:feature_class":"P",
    "gn:feature_code":"PPL",
    "gn:name":"Risseau",
    "gn:population":0,
    "gn:timezone":"Europe/Paris",
    "iso:country":"FR",
    "wof:name":"Risseau",
    "wof:placetype":"locality"
},
  "geometry": {"coordinates":[2.88839,46.39715],"type":"Point"}
}