{
  "type": "Feature",
  "properties": {
    "gn:admin1_code":"52",
    "gn:admin2_code":"72",
    "gn:admin3_code":"721",
    "gn:admin4_code":"72154",
    "gn:asciiname":"Verron",
    "gn:country_code":"FR",
    "gn:dem":44,
    "gn:feature_class":"P",
    "gn:feature_code":"PPL",
    "gn:name":"Verron",
    "gn:population":0,
    "gn:timezone":"Europe/Paris",
    "iso:country":"FR",
    "name:deu_x_preferred":[
        "Verron"
    ],
    "wof:name":"Verron",
    "wof:placetype":"locality"
},
  "geometry": {"coordinates":[-0.10455,47.72088],"type":"Point"}
}