{
  "type": "Feature",
  "properties": {
    "gn:admin1_code":"84",
    "gn:admin2_code":"03",
    "gn:admin3_code":"032",
    "gn:admin4_code":"03277",
    "gn:asciiname":"Verzun le Bas",
    "gn:country_code":"FR",
    "gn:dem":404,
    "gn:feature_class":"P",
    "gn:feature_code":"PPL",
    "gn:name":"Verzun le Bas",
    "gn:population":0,
    "gn:timezone":"Europe/Paris",
    "iso:country":"FR",
    "wof:name":"Verzun le Bas",
    "wof:placetype":"locality"
},
  "geometry": {"coordinates":[3.06667,46.26667],"type":"Point"}
}