{
  "type": "Feature",
  "properties": {
    "gn:admin1_code":"44",
    "gn:admin2_code":"67",
    "gn:admin3_code":"676",
    "gn:admin4_code":"67137",
    "gn:asciiname":"Ohnheim",
    "gn:country_code":"FR",
    "gn:dem":146,
    "gn:feature_class":"P",
    "gn:feature_code":"PPL",
    "gn:name":"Ohnheim",
    "gn:population":0,
    "gn:timezone":"Europe/Paris",
    "iso:country":"FR",
    "wof:name":"Ohnheim",
    "wof:placetype":"locality"
},
  "geometry": {"coordinates":[7.70107,48.48828],"type":"Point"}
}