{
  "type": "Feature",
  "properties": {
    "gn:admin1_code":"75",
    "gn:admin2_code":"19",
    "gn:admin3_code":"191",
    "gn:admin4_code":"19047",
    "gn:asciiname":"Battut",
    "gn:country_code":"FR",
    "gn:dem":265,
    "gn:feature_class":"P",
    "gn:feature_code":"PPL",
    "gn:name":"Battut",
    "gn:population":0,
    "gn:timezone":"Europe/Paris",
    "iso:country":"FR",
    "wof:name":"Battut",
    "wof:placetype":"locality"
},
  "geometry": {"coordinates":[1.41962,45.05862],"type":"Point"}
}