{
  "type": "Feature",
  "properties": {
    "gn:admin1_code":"84",
    "gn:admin2_code":"42",
    "gn:admin3_code":"421",
    "gn:admin4_code":"42296",
    "gn:asciiname":"Donzy",
    "gn:country_code":"FR",
    "gn:dem":358,
    "gn:feature_class":"P",
    "gn:feature_code":"PPL",
    "gn:name":"Donzy",
    "gn:population":0,
    "gn:timezone":"Europe/Paris",
    "iso:country":"FR",
    "name:und_x_variant":[
        "Donzi",
        "Donzy"
    ],
    "wof:name":"Donzy",
    "wof:placetype":"locality"
},
  "geometry": {"coordinates":[4.28133,45.74779],"type":"Point"}
}