{
  "type": "Feature",
  "properties": {
    "gn:admin1_code":"84",
    "gn:admin2_code":"42",
    "gn:admin3_code":"421",
    "gn:admin4_code":"42296",
    "gn:asciiname":"Donzy",
    "gn:country_code":"FR",
    "gn:dem":358,
    "gn:feature_class":"P",
    "gn:feature_code":"PPL",
    "gn:name":"Donzy",
    "gn:population":0,
    "gn:timezone":"Europe/Paris",
    "iso:country":"FR",
    "name:cat_x_preferred":[
        "Donzy"
    ],
    "name:ceb_x_preferred":[
        "Donzy"
    ],
    "name:deu_x_preferred":[
        "Donzy"
    ],
    "name:eus_x_preferred":[
        "Donzy"
    ],
    "name:fra_x_preferred":[
        "Donzy"
    ],
    "name:hun_x_preferred":[
        "Donzy"
    ],
    "name:ita_x_preferred":[
        "Donzy"
    ],
    "name:kaz_x_preferred":[
        "\u0414\u043e\u043d\u0437\u0438"
    ],
    "name:kor_x_preferred":[
        "\ub3d9\uc9c0"
    ],
    "name:lat_x_preferred":[
        "Donziacum"
    ],
    "name:msa_x_preferred":[
        "Donzy"
    ],
    "name:nld_x_preferred":[
        "Donzy"
    ],
    "name:oci_x_preferred":[
        "Donzy"
    ],
    "name:pms_x_preferred":[
        "Donzy"
    ],
    "name:pol_x_preferred":[
        "Donzy"
    ],
    "name:por_x_preferred":[
        "Donzy"
    ],
    "name:ron_x_preferred":[
        "Donzy"
    ],
    "name:slk_x_preferred":[
        "Donzy"
    ],
    "name:spa_x_preferred":[
        "Donzy"
    ],
    "name:srp_x_preferred":[
        "\u0414\u043e\u043d\u0437\u0438"
    ],
    "name:swe_x_preferred":[
        "Donzy"
    ],
    "name:ukr_x_preferred":[
        "\u0414\u043e\u043d\u0437\u0456"
    ],
    "name:und_x_variant":[
        "Donzi"
    ],
    "name:uzb_x_preferred":[
        "Donzy"
    ],
    "name:vie_x_preferred":[
        "Donzy"
    ],
    "name:vol_x_preferred":[
        "Donzy"
    ],
    "name:war_x_preferred":[
        "Donzy"
    ],
    "wof:name":"Donzy",
    "wof:placetype":"locality"
},
  "geometry": {"coordinates":[4.28133,45.74779],"type":"Point"}
}