{
  "type": "Feature",
  "properties": {
    "gn:admin1_code":"27",
    "gn:admin2_code":"58",
    "gn:admin3_code":"584",
    "gn:admin4_code":"58227",
    "gn:asciiname":"Argenoux",
    "gn:country_code":"FR",
    "gn:dem":174,
    "gn:feature_class":"P",
    "gn:feature_code":"PPL",
    "gn:name":"Argenoux",
    "gn:population":0,
    "gn:timezone":"Europe/Paris",
    "iso:country":"FR",
    "wof:name":"Argenoux",
    "wof:placetype":"locality"
},
  "geometry": {"coordinates":[3.03847,47.52867],"type":"Point"}
}