{
  "type": "Feature",
  "properties": {
    "gn:admin1_code":"75",
    "gn:admin2_code":"87",
    "gn:admin3_code":"871",
    "gn:admin4_code":"87139",
    "gn:asciiname":"Mas-du-Bost",
    "gn:country_code":"FR",
    "gn:dem":250,
    "gn:feature_class":"P",
    "gn:feature_code":"PPL",
    "gn:name":"Mas-du-Bost",
    "gn:population":0,
    "gn:timezone":"Europe/Paris",
    "iso:country":"FR",
    "wof:name":"Mas-du-Bost",
    "wof:placetype":"locality"
},
  "geometry": {"coordinates":[0.90739,46.17907],"type":"Point"}
}