{
  "type": "Feature",
  "properties": {
    "iso:country":"FR",
    "name:eng_x_preferred":[
        "Petite Garenne"
    ],
    "name:fra_x_preferred":[
        "Petite Garenne"
    ],
    "wof:name":"Petite Garenne",
    "wof:placetype":"neighbourhood"
},
  "geometry": {"coordinates":[2.24738197125527,48.91554362370969],"type":"Point"}
}