{
  "type": "Feature",
  "properties": {
    "gn:admin1_code":"84",
    "gn:admin2_code":"63",
    "gn:admin3_code":"635",
    "gn:admin4_code":"63151.0",
    "gn:asciiname":"Vorton",
    "gn:country_code":"FR",
    "gn:dem":307,
    "gn:feature_class":"P",
    "gn:feature_code":"PPL",
    "gn:name":"Vorton",
    "gn:population":0,
    "gn:timezone":"Europe/Paris",
    "iso:country":"FR",
    "wof:name":"Vorton",
    "wof:placetype":"locality"
},
  "geometry": {"coordinates":[3.52844,45.81356],"type":"Point"}
}