{
  "type": "Feature",
  "properties": {
    "gn:admin1_code":"44",
    "gn:admin2_code":"52",
    "gn:admin3_code":"522",
    "gn:admin4_code":"52504",
    "gn:asciiname":"Varennes-sur-Amance",
    "gn:country_code":"FR",
    "gn:dem":337,
    "gn:feature_class":"P",
    "gn:feature_code":"PPL",
    "gn:name":"Varennes-sur-Amance",
    "gn:population":0,
    "gn:timezone":"Europe/Paris",
    "iso:country":"FR",
    "name:und_x_variant":[
        "Varennes",
        "Varennes-sur-Amance"
    ],
    "wof:name":"Varennes-sur-Amance",
    "wof:placetype":"locality"
},
  "geometry": {"coordinates":[5.62767,47.89603],"type":"Point"}
}