{
  "type": "Feature",
  "properties": {
    "gn:admin1_code":"44",
    "gn:admin2_code":"52",
    "gn:admin3_code":"522",
    "gn:admin4_code":"52504",
    "gn:asciiname":"Varennes-sur-Amance",
    "gn:country_code":"FR",
    "gn:dem":337,
    "gn:feature_class":"P",
    "gn:feature_code":"PPL",
    "gn:name":"Varennes-sur-Amance",
    "gn:population":0,
    "gn:timezone":"Europe/Paris",
    "iso:country":"FR",
    "name:cat_x_preferred":[
        "Varennes-sur-Amance"
    ],
    "name:deu_x_preferred":[
        "Varennes-sur-Amance"
    ],
    "name:fra_x_preferred":[
        "Varennes-sur-Amance"
    ],
    "name:ita_x_preferred":[
        "Varennes-sur-Amance"
    ],
    "name:lat_x_preferred":[
        "Varennes-sur-Amance"
    ],
    "name:oci_x_preferred":[
        "Varennes-sur-Amance"
    ],
    "name:spa_x_preferred":[
        "Varennes-sur-Amance"
    ],
    "name:swe_x_preferred":[
        "Varennes-sur-Amance"
    ],
    "name:ukr_x_preferred":[
        "\u0412\u0430\u0440\u0435\u043d\u043d-\u0441\u044e\u0440-\u0410\u043c\u0430\u043d\u0441"
    ],
    "name:und_x_variant":[
        "Varennes"
    ],
    "wof:name":"Varennes-sur-Amance",
    "wof:placetype":"locality"
},
  "geometry": {"coordinates":[5.62767,47.89603],"type":"Point"}
}