{
  "type": "Feature",
  "properties": {
    "iso:country":"FR",
    "oa:elevation_ft":"177",
    "oa:type":"medium_airport",
    "woe:hierarchy":{
        "country_id":23424819,
        "county_id":12597175,
        "localadmin_id":12668593,
        "planet_id":1,
        "state_id":7153324
    },
    "wof:name":"A\u00e9rodrome de Valenciennes-Denain",
    "wof:placetype":"campus"
},
  "geometry": {"coordinates":[3.46556,50.3247],"type":"Point"}
}