{
  "type": "Feature",
  "properties": {
    "iso:country":"FR",
    "name:ceb_x_preferred":[
        "Valenciennes-Denain Airport"
    ],
    "name:eng_x_preferred":[
        "Valenciennes-Denain Airport"
    ],
    "name:fas_x_preferred":[
        "\u0641\u0631\u0648\u062f\u06af\u0627\u0647 \u0648\u0644\u0646\u0633\u06cc\u0646\u0633-\u062f\u0646\u0627\u06cc\u0646"
    ],
    "name:msa_x_preferred":[
        "Lapangan Terbang Denain"
    ],
    "name:ron_x_preferred":[
        "Aeroportul Valenciennes-Denain"
    ],
    "name:tgk_x_preferred":[
        "\u0424\u0443\u0440\u0443\u0434\u0433\u043e\u04b3\u0438 \u0432\u043b\u043d\u0441\u0438\u043d\u0441-\u0434\u043d\u043e\u0438\u043d"
    ],
    "oa:elevation_ft":"177",
    "oa:type":"medium_airport",
    "woe:hierarchy":{
        "country_id":23424819,
        "county_id":12597175,
        "localadmin_id":12668593,
        "planet_id":1,
        "state_id":7153324
    },
    "wof:name":"A\u00e9rodrome de Valenciennes-Denain",
    "wof:placetype":"campus"
},
  "geometry": {"coordinates":[3.46556,50.3247],"type":"Point"}
}