{
  "type": "Feature",
  "properties": {
    "gn:admin1_code":"27",
    "gn:admin2_code":"25",
    "gn:admin3_code":"251",
    "gn:admin4_code":"25092.0",
    "gn:asciiname":"La Breteniere",
    "gn:country_code":"FR",
    "gn:dem":339,
    "gn:feature_class":"P",
    "gn:feature_code":"PPL",
    "gn:name":"La Breteni\u00e8re",
    "gn:population":0,
    "gn:timezone":"Europe/Paris",
    "iso:country":"FR",
    "name:und_x_variant":[
        "La Breteni\u00e8re"
    ],
    "wof:name":"La Breteniere",
    "wof:placetype":"locality"
},
  "geometry": {"coordinates":[6.27317,47.3798],"type":"Point"}
}