{
  "type": "Feature",
  "properties": {
    "frgov:code_epci":"242504447",
    "frgov:insee_arr":"1",
    "frgov:insee_com":"25092",
    "frgov:insee_dep":"25",
    "frgov:insee_reg":"27",
    "frgov:nom_com":"La Breteni\u00e8re",
    "frgov:nom_com_m":"LA BRETENIERE",
    "frgov:nom_dep":"DOUBS",
    "frgov:nom_reg":"BOURGOGNE-FRANCHE-COMTE",
    "frgov:statut":"Commune simple",
    "gn:admin1_code":"27",
    "gn:admin2_code":"25",
    "gn:admin3_code":"251",
    "gn:admin4_code":"25092.0",
    "gn:asciiname":"La Breteniere",
    "gn:country_code":"FR",
    "gn:dem":339,
    "gn:feature_class":"P",
    "gn:feature_code":"PPL",
    "gn:name":"La Breteni\u00e8re",
    "gn:population":0,
    "gn:timezone":"Europe/Paris",
    "iso:country":"FR",
    "name:fra_x_preferred":[
        "La Breteni\u00e8re"
    ],
    "name:und_x_variant":[
        "La Breteni\u00e8re"
    ],
    "qs:a0":"France",
    "qs:a1":"DOUBS",
    "qs:a1_lc":"25",
    "qs:a1r":"FRANCHE-COMTE",
    "qs:a1r_lc":"43",
    "qs:a2_lc":"13",
    "qs:a2r_lc":"1",
    "qs:adm0":"France",
    "qs:adm0_a3":"FRA",
    "qs:la":"LA BRETENIERE",
    "qs:la_lc":"25092",
    "qs:level":"localadmin",
    "qs:type":"Commune simple",
    "wof:coterminous":[
        404374297
    ],
    "wof:name":"La Breteniere",
    "wof:placetype":"locality",
    "wof:placetype_local":"Commune simple"
},
  "geometry": {"coordinates":[6.27317,47.3798],"type":"Point"}
}