{
  "type": "Feature",
  "properties": {
    "gn:admin1_code":"75",
    "gn:admin2_code":"23",
    "gn:admin3_code":"231",
    "gn:admin4_code":"23226",
    "gn:asciiname":"Saint-Pardoux-d'Arnet",
    "gn:country_code":"FR",
    "gn:dem":674,
    "gn:feature_class":"P",
    "gn:feature_code":"PPL",
    "gn:name":"Saint-Pardoux-d\u2019Arnet",
    "gn:population":0,
    "gn:timezone":"Europe/Paris",
    "iso:country":"FR",
    "name:und_x_variant":[
        "Saint-Pardoux",
        "Saint-Pardoux-d\u2019Arnet"
    ],
    "wof:name":"Saint-Pardoux-d'Arnet",
    "wof:placetype":"locality"
},
  "geometry": {"coordinates":[2.33279,45.87848],"type":"Point"}
}