{
  "type": "Feature",
  "properties": {
    "gn:admin1_code":"75",
    "gn:admin2_code":"23",
    "gn:admin3_code":"231",
    "gn:admin4_code":"23226",
    "gn:asciiname":"Saint-Pardoux-d'Arnet",
    "gn:country_code":"FR",
    "gn:dem":674,
    "gn:feature_class":"P",
    "gn:feature_code":"PPL",
    "gn:name":"Saint-Pardoux-d\u2019Arnet",
    "gn:population":0,
    "gn:timezone":"Europe/Paris",
    "iso:country":"FR",
    "name:ceb_x_preferred":[
        "Saint-Pardoux-d'Arnet"
    ],
    "name:deu_x_preferred":[
        "Saint-Pardoux-d\u2019Arnet"
    ],
    "name:epo_x_preferred":[
        "Saint-Pardoux-d'Arnet"
    ],
    "name:eus_x_preferred":[
        "Saint-Pardoux-d'Arnet"
    ],
    "name:fra_x_preferred":[
        "Saint-Pardoux-d'Arnet"
    ],
    "name:hun_x_preferred":[
        "Saint-Pardoux-d\u2019Arnet"
    ],
    "name:ind_x_preferred":[
        "Saint-Pardoux-d'Arnet"
    ],
    "name:ita_x_preferred":[
        "Saint-Pardoux-d'Arnet"
    ],
    "name:kaz_x_preferred":[
        "\u0421\u0435\u043d-\u041f\u0430\u0440\u0434\u0443-\u0434'\u0410\u0440\u043d\u0435"
    ],
    "name:lat_x_preferred":[
        "Saint-Pardoux-d'Arnet"
    ],
    "name:mlg_x_preferred":[
        "Saint-Pardoux-d'Arnet"
    ],
    "name:msa_x_preferred":[
        "Saint-Pardoux-d'Arnet"
    ],
    "name:nld_x_preferred":[
        "Saint-Pardoux-d'Arnet"
    ],
    "name:pms_x_preferred":[
        "Saint-Pardoux-d'Arnet"
    ],
    "name:pol_x_preferred":[
        "Saint-Pardoux-d\u2019Arnet"
    ],
    "name:por_x_preferred":[
        "Saint-Pardoux-d'Arnet"
    ],
    "name:ron_x_preferred":[
        "Saint-Pardoux-d'Arnet"
    ],
    "name:rus_x_preferred":[
        "\u0421\u0435\u043d-\u041f\u0430\u0440\u0434\u0443-\u0434\u2019\u0410\u0440\u043d\u0435"
    ],
    "name:slk_x_preferred":[
        "Saint-Pardoux-d\u2019Arnet"
    ],
    "name:spa_x_preferred":[
        "Saint-Pardoux-d'Arnet"
    ],
    "name:swe_x_preferred":[
        "Saint-Pardoux-d'Arnet"
    ],
    "name:ukr_x_preferred":[
        "\u0421\u0435\u043d-\u041f\u0430\u0440\u0434\u0443-\u0434'\u0410\u0440\u043d\u0435"
    ],
    "name:und_x_variant":[
        "Saint-Pardoux"
    ],
    "name:urd_x_preferred":[
        "\u0633\u06cc\u0646\u0679-\u067e\u0627\u0631\u062f\u0648-\u062f\u0631\u0646\u0679"
    ],
    "name:uzb_x_preferred":[
        "Saint-Pardoux-d'Arnet"
    ],
    "name:vie_x_preferred":[
        "Saint-Pardoux-d'Arnet"
    ],
    "name:vol_x_preferred":[
        "Saint-Pardoux-d'Arnet"
    ],
    "name:war_x_preferred":[
        "Saint-Pardoux-d'Arnet"
    ],
    "name:zho_x_preferred":[
        "\u5723\u5e15\u5c14\u675c\u8fbe\u5c14\u5185"
    ],
    "wof:name":"Saint-Pardoux-d'Arnet",
    "wof:placetype":"locality"
},
  "geometry": {"coordinates":[2.33279,45.87848],"type":"Point"}
}