{
  "type": "Feature",
  "properties": {
    "frgov:code_epci":"200035756",
    "frgov:insee_arr":"3",
    "frgov:insee_com":"32278",
    "frgov:insee_dep":"32",
    "frgov:insee_reg":"76",
    "frgov:nom_com":"Montaut",
    "frgov:nom_com_m":"MONTAUT",
    "frgov:nom_dep":"GERS",
    "frgov:nom_reg":"OCCITANIE",
    "frgov:statut":"Commune simple",
    "gn:admin1_code":"76",
    "gn:admin2_code":"32",
    "gn:admin3_code":"323",
    "gn:admin4_code":"32278",
    "gn:asciiname":"Montaut",
    "gn:country_code":"FR",
    "gn:dem":253,
    "gn:feature_class":"P",
    "gn:feature_code":"PPL",
    "gn:name":"Montaut",
    "gn:population":126,
    "gn:timezone":"Europe/Paris",
    "iso:country":"FR",
    "name:arg_x_preferred":[
        "Montaut"
    ],
    "name:cat_x_preferred":[
        "Montaut de Barcunhan"
    ],
    "name:ceb_x_preferred":[
        "Montaut"
    ],
    "name:deu_x_preferred":[
        "Montaut"
    ],
    "name:fra_x_preferred":[
        "Montaut"
    ],
    "name:hun_x_preferred":[
        "Montaut"
    ],
    "name:ita_x_preferred":[
        "Montaut"
    ],
    "name:nds_x_preferred":[
        "Montaut"
    ],
    "name:nld_x_preferred":[
        "Montaut"
    ],
    "name:oci_x_preferred":[
        "Montaut"
    ],
    "name:pms_x_preferred":[
        "Montaut"
    ],
    "name:pol_x_preferred":[
        "Montaut"
    ],
    "name:por_x_preferred":[
        "Montaut"
    ],
    "name:rus_x_preferred":[
        "\u041c\u043e\u043d\u0442\u043e"
    ],
    "name:rus_x_variant":[
        "\u041c\u043e\u043d\u0442\u043e"
    ],
    "name:slk_x_preferred":[
        "Montaut"
    ],
    "name:spa_x_preferred":[
        "Montaut"
    ],
    "name:swe_x_preferred":[
        "Montaut"
    ],
    "name:ukr_x_preferred":[
        "\u041c\u043e\u043d\u0442\u043e"
    ],
    "name:zho_x_preferred":[
        "\u8499\u6258"
    ],
    "qs:a0":"France",
    "qs:a1":"GERS",
    "qs:a1_lc":"32",
    "qs:a1r":"MIDI-PYRENEES",
    "qs:a1r_lc":"73",
    "qs:a2_lc":"17",
    "qs:a2r_lc":"3",
    "qs:adm0":"France",
    "qs:adm0_a3":"FRA",
    "qs:la":"MONTAUT",
    "qs:la_lc":"32278",
    "qs:level":"localadmin",
    "qs:type":"Commune simple",
    "wof:coterminous":[
        404393361
    ],
    "wof:name":"Montaut",
    "wof:placetype":"locality",
    "wof:placetype_local":"Commune simple",
    "wof:population":126
},
  "geometry": {"coordinates":[0.41981,43.39407],"type":"Point"}
}