{
  "type": "Feature",
  "properties": {
    "gn:admin1_code":"76",
    "gn:admin2_code":"32",
    "gn:admin3_code":"323",
    "gn:admin4_code":"32278",
    "gn:asciiname":"Montaut",
    "gn:country_code":"FR",
    "gn:dem":253,
    "gn:feature_class":"P",
    "gn:feature_code":"PPL",
    "gn:name":"Montaut",
    "gn:population":126,
    "gn:timezone":"Europe/Paris",
    "iso:country":"FR",
    "name:arg_x_preferred":[
        "Montaut"
    ],
    "name:ceb_x_preferred":[
        "Montaut"
    ],
    "name:deu_x_preferred":[
        "Montaut"
    ],
    "name:fra_x_preferred":[
        "Montaut"
    ],
    "name:hun_x_preferred":[
        "Montaut"
    ],
    "name:ita_x_preferred":[
        "Montaut"
    ],
    "name:nds_x_preferred":[
        "Montaut"
    ],
    "name:nld_x_preferred":[
        "Montaut"
    ],
    "name:oci_x_preferred":[
        "Montaut"
    ],
    "name:pms_x_preferred":[
        "Montaut"
    ],
    "name:pol_x_preferred":[
        "Montaut"
    ],
    "name:por_x_preferred":[
        "Montaut"
    ],
    "name:rus_x_preferred":[
        "\u041c\u043e\u043d\u0442\u043e"
    ],
    "name:slk_x_preferred":[
        "Montaut"
    ],
    "name:spa_x_preferred":[
        "Montaut"
    ],
    "name:swe_x_preferred":[
        "Montaut"
    ],
    "name:ukr_x_preferred":[
        "\u041c\u043e\u043d\u0442\u043e"
    ],
    "wof:name":"Montaut",
    "wof:placetype":"locality",
    "wof:population":126
},
  "geometry": {"coordinates":[0.41981,43.39407],"type":"Point"}
}