{
  "type": "Feature",
  "properties": {
    "gn:admin1_code":"84",
    "gn:admin2_code":"63",
    "gn:admin3_code":"633",
    "gn:admin4_code":"63088.0",
    "gn:asciiname":"Martres",
    "gn:country_code":"FR",
    "gn:dem":689,
    "gn:feature_class":"P",
    "gn:feature_code":"PPL",
    "gn:name":"Martres",
    "gn:population":0,
    "gn:timezone":"Europe/Paris",
    "iso:country":"FR",
    "wof:name":"Martres",
    "wof:placetype":"locality"
},
  "geometry": {"coordinates":[3.39031,45.46267],"type":"Point"}
}