{
  "type": "Feature",
  "properties": {
    "gn:admin1_code":"84",
    "gn:admin2_code":"63",
    "gn:admin3_code":"633",
    "gn:admin4_code":"63088.0",
    "gn:asciiname":"Martres",
    "gn:country_code":"FR",
    "gn:dem":689,
    "gn:feature_class":"P",
    "gn:feature_code":"PPL",
    "gn:name":"Martres",
    "gn:population":0,
    "gn:timezone":"Europe/Paris",
    "iso:country":"FR",
    "name:bug_x_preferred":[
        "Martres"
    ],
    "name:cat_x_preferred":[
        "Martras"
    ],
    "name:ceb_x_preferred":[
        "Martres"
    ],
    "name:deu_x_preferred":[
        "Martres"
    ],
    "name:eus_x_preferred":[
        "Martres"
    ],
    "name:fra_x_preferred":[
        "Martres"
    ],
    "name:hun_x_preferred":[
        "Martres"
    ],
    "name:ind_x_preferred":[
        "Martres"
    ],
    "name:ita_x_preferred":[
        "Martres"
    ],
    "name:kaz_x_preferred":[
        "\u041c\u0430\u0440\u0442\u0440"
    ],
    "name:lat_x_preferred":[
        "Martres"
    ],
    "name:mlg_x_preferred":[
        "Martres"
    ],
    "name:msa_x_preferred":[
        "Martres"
    ],
    "name:nld_x_preferred":[
        "Martres"
    ],
    "name:oci_x_preferred":[
        "Martres"
    ],
    "name:pms_x_preferred":[
        "Martres"
    ],
    "name:pol_x_preferred":[
        "Martres"
    ],
    "name:por_x_preferred":[
        "Martres"
    ],
    "name:ron_x_preferred":[
        "Martres"
    ],
    "name:slk_x_preferred":[
        "Martres"
    ],
    "name:spa_x_preferred":[
        "Martres"
    ],
    "name:swe_x_preferred":[
        "Martres"
    ],
    "name:ukr_x_preferred":[
        "\u041c\u0430\u0440\u0442\u0440"
    ],
    "name:uzb_x_preferred":[
        "Martres"
    ],
    "name:vie_x_preferred":[
        "Martres"
    ],
    "name:vol_x_preferred":[
        "Martres"
    ],
    "name:war_x_preferred":[
        "Martres"
    ],
    "name:zho_x_preferred":[
        "\u9a6c\u5c14\u7279\u96f7"
    ],
    "wof:name":"Martres",
    "wof:placetype":"locality"
},
  "geometry": {"coordinates":[3.39031,45.46267],"type":"Point"}
}