{
  "type": "Feature",
  "properties": {
    "gn:admin1_code":"84",
    "gn:admin2_code":"43",
    "gn:admin3_code":"433",
    "gn:admin4_code":"43163",
    "gn:asciiname":"Pourrat",
    "gn:country_code":"FR",
    "gn:dem":1023,
    "gn:feature_class":"P",
    "gn:feature_code":"PPL",
    "gn:name":"Pourrat",
    "gn:population":0,
    "gn:timezone":"Europe/Paris",
    "iso:country":"FR",
    "wof:name":"Pourrat",
    "wof:placetype":"locality"
},
  "geometry": {"coordinates":[4.41662,45.2124],"type":"Point"}
}