{
  "type": "Feature",
  "properties": {
    "frgov:code_epci":"200070514",
    "frgov:insee_arr":"2",
    "frgov:insee_com":"16204",
    "frgov:insee_dep":"16",
    "frgov:insee_reg":"75",
    "frgov:nom_com":"Bellevigne",
    "frgov:nom_com_m":"BELLEVIGNE",
    "frgov:nom_dep":"CHARENTE",
    "frgov:nom_reg":"NOUVELLE-AQUITAINE",
    "frgov:statut":"Commune simple",
    "gn:admin1_code":"75",
    "gn:admin2_code":"16",
    "gn:admin3_code":"162",
    "gn:admin4_code":"16204",
    "gn:asciiname":"Malaville",
    "gn:country_code":"FR",
    "gn:dem":73,
    "gn:feature_class":"P",
    "gn:feature_code":"PPL",
    "gn:name":"Malaville",
    "gn:population":0,
    "gn:timezone":"Europe/Paris",
    "iso:country":"FR",
    "name:cat_x_preferred":[
        "Malaville"
    ],
    "name:ceb_x_preferred":[
        "Malaville"
    ],
    "name:deu_x_preferred":[
        "Malaville"
    ],
    "name:eus_x_preferred":[
        "Malaville"
    ],
    "name:fra_x_preferred":[
        "Malaville"
    ],
    "name:fra_x_variant":[
        "Malaville"
    ],
    "name:hun_x_preferred":[
        "Malaville"
    ],
    "name:hye_x_preferred":[
        "\u0544\u0561\u056c\u0561\u057e\u056b\u056c"
    ],
    "name:ita_x_preferred":[
        "Malaville"
    ],
    "name:lat_x_preferred":[
        "Malaville"
    ],
    "name:msa_x_preferred":[
        "Malaville"
    ],
    "name:nld_x_preferred":[
        "Malaville"
    ],
    "name:oci_x_preferred":[
        "Malaville"
    ],
    "name:pol_x_preferred":[
        "Malaville"
    ],
    "name:por_x_preferred":[
        "Malaville"
    ],
    "name:ron_x_preferred":[
        "Malaville"
    ],
    "name:rus_x_preferred":[
        "\u041c\u0430\u043b\u0430\u0432\u0438\u043b\u044c"
    ],
    "name:slk_x_preferred":[
        "Malaville"
    ],
    "name:spa_x_preferred":[
        "Malaville"
    ],
    "name:swe_x_preferred":[
        "Malaville"
    ],
    "name:ukr_x_preferred":[
        "\u041c\u0430\u043b\u0430\u0432\u0456\u043b\u044c"
    ],
    "name:vie_x_preferred":[
        "Malaville"
    ],
    "name:vol_x_preferred":[
        "Malaville"
    ],
    "name:war_x_preferred":[
        "Malaville"
    ],
    "name:zho_x_preferred":[
        "\u9a6c\u62c9\u7ef4\u5c14"
    ],
    "qs:a0":"France",
    "qs:a1":"CHARENTE",
    "qs:a1_lc":"16",
    "qs:a1r":"POITOU-CHARENTES",
    "qs:a1r_lc":"54",
    "qs:a2_lc":"12",
    "qs:a2r_lc":"2",
    "qs:adm0":"France",
    "qs:adm0_a3":"FRA",
    "qs:la":"MALAVILLE",
    "qs:la_lc":"16204",
    "qs:level":"localadmin",
    "qs:type":"Commune simple",
    "wof:coterminous":[
        404388915
    ],
    "wof:name":"Malaville",
    "wof:placetype":"locality",
    "wof:placetype_local":"Commune simple"
},
  "geometry": {"coordinates":[-0.1,45.55],"type":"Point"}
}