{
  "type": "Feature",
  "properties": {
    "gn:admin1_code":"76",
    "gn:admin2_code":"48",
    "gn:admin3_code":"482",
    "gn:admin4_code":"48123",
    "gn:asciiname":"Recoules-d'Aubrac",
    "gn:country_code":"FR",
    "gn:dem":1092,
    "gn:feature_class":"P",
    "gn:feature_code":"PPL",
    "gn:name":"Recoules-d\u2019Aubrac",
    "gn:population":0,
    "gn:timezone":"Europe/Paris",
    "iso:country":"FR",
    "name:cat_x_preferred":[
        "Recola d'Aubrac"
    ],
    "name:ceb_x_preferred":[
        "Recoules-d'Aubrac"
    ],
    "name:deu_x_preferred":[
        "Recoules-d\u2019Aubrac"
    ],
    "name:eus_x_preferred":[
        "Recoules-d'Aubrac"
    ],
    "name:fra_x_preferred":[
        "Recoules-d'Aubrac"
    ],
    "name:hun_x_preferred":[
        "Recoules-d\u2019Aubrac"
    ],
    "name:ita_x_preferred":[
        "Recoules-d'Aubrac"
    ],
    "name:kaz_x_preferred":[
        "\u0420\u0435\u043a\u0443\u043b\u044c-\u0434'\u041e\u0431\u0440\u0430\u043a"
    ],
    "name:lat_x_preferred":[
        "Recoules-d'Aubrac"
    ],
    "name:lmo_x_preferred":[
        "Recoules-d'Aubrac"
    ],
    "name:mlg_x_preferred":[
        "Recoules-d'Aubrac"
    ],
    "name:msa_x_preferred":[
        "Recoules-d'Aubrac"
    ],
    "name:nld_x_preferred":[
        "Recoules-d'Aubrac"
    ],
    "name:oci_x_preferred":[
        "Recola d'Aubrac"
    ],
    "name:pol_x_preferred":[
        "Recoules-d\u2019Aubrac"
    ],
    "name:por_x_preferred":[
        "Recoules-d'Aubrac"
    ],
    "name:ron_x_preferred":[
        "Recoules-d'Aubrac"
    ],
    "name:slk_x_preferred":[
        "Recoules-d\u2019Aubrac"
    ],
    "name:spa_x_preferred":[
        "Recoules-d'Aubrac"
    ],
    "name:swe_x_preferred":[
        "Recoules-d'Aubrac"
    ],
    "name:ukr_x_preferred":[
        "\u0420\u0435\u043a\u0443\u043b\u044c-\u0434'\u041e\u0431\u0440\u0430\u043a"
    ],
    "name:und_x_variant":[
        "Recoules"
    ],
    "name:vie_x_preferred":[
        "Recoules-d'Aubrac"
    ],
    "name:vol_x_preferred":[
        "Recoules-d'Aubrac"
    ],
    "name:war_x_preferred":[
        "Recoules-d'Aubrac"
    ],
    "name:zho_x_preferred":[
        "\u96f7\u5e93\u83b1\u591a\u5e03\u62c9\u514b"
    ],
    "wof:name":"Recoules-d'Aubrac",
    "wof:placetype":"locality"
},
  "geometry": {"coordinates":[3.02469,44.69193],"type":"Point"}
}