{
  "type": "Feature",
  "properties": {
    "gn:admin1_code":"76",
    "gn:admin2_code":"48",
    "gn:admin3_code":"482",
    "gn:admin4_code":"48123",
    "gn:asciiname":"Recoules-d'Aubrac",
    "gn:country_code":"FR",
    "gn:dem":1092,
    "gn:feature_class":"P",
    "gn:feature_code":"PPL",
    "gn:name":"Recoules-d\u2019Aubrac",
    "gn:population":0,
    "gn:timezone":"Europe/Paris",
    "iso:country":"FR",
    "name:und_x_variant":[
        "Recoules",
        "Recoules-d\u2019Aubrac"
    ],
    "wof:name":"Recoules-d'Aubrac",
    "wof:placetype":"locality"
},
  "geometry": {"coordinates":[3.02469,44.69193],"type":"Point"}
}