{
  "type": "Feature",
  "properties": {
    "gn:admin1_code":"84",
    "gn:admin2_code":"73",
    "gn:admin3_code":"732",
    "gn:admin4_code":"73228",
    "gn:asciiname":"La Combaz",
    "gn:country_code":"FR",
    "gn:dem":635,
    "gn:feature_class":"P",
    "gn:feature_code":"PPL",
    "gn:name":"La Combaz",
    "gn:population":0,
    "gn:timezone":"Europe/Paris",
    "iso:country":"FR",
    "name:und_x_variant":[
        "La Combe",
        "La Combaz"
    ],
    "wof:name":"La Combaz",
    "wof:placetype":"locality"
},
  "geometry": {"coordinates":[5.87833,45.5325],"type":"Point"}
}