{
  "type": "Feature",
  "properties": {
    "gn:admin1_code":"27",
    "gn:admin2_code":"25",
    "gn:admin3_code":"251",
    "gn:admin4_code":"25374",
    "gn:asciiname":"Cottier",
    "gn:country_code":"FR",
    "gn:dem":257,
    "gn:feature_class":"P",
    "gn:feature_code":"PPL",
    "gn:name":"Cottier",
    "gn:population":0,
    "gn:timezone":"Europe/Paris",
    "iso:country":"FR",
    "name:deu_x_preferred":[
        "Cottier"
    ],
    "name:fra_x_preferred":[
        "Cottier"
    ],
    "name:nds_x_preferred":[
        "Cottier"
    ],
    "wof:name":"Cottier",
    "wof:placetype":"locality"
},
  "geometry": {"coordinates":[5.76756,47.21084000000001],"type":"Point"}
}