{
  "type": "Feature",
  "properties": {
    "gn:admin1_code":"84",
    "gn:admin2_code":"69",
    "gn:admin3_code":"691",
    "gn:admin4_code":"69021",
    "gn:asciiname":"Lurcieux",
    "gn:country_code":"FR",
    "gn:dem":438,
    "gn:feature_class":"P",
    "gn:feature_code":"PPL",
    "gn:name":"Lurcieux",
    "gn:population":0,
    "gn:timezone":"Europe/Paris",
    "iso:country":"FR",
    "wof:name":"Lurcieux",
    "wof:placetype":"locality"
},
  "geometry": {"coordinates":[4.54059,45.77073],"type":"Point"}
}