{
  "type": "Feature",
  "properties": {
    "gn:admin1_code":"84",
    "gn:admin2_code":"63",
    "gn:admin3_code":"634",
    "gn:admin4_code":"63118",
    "gn:asciiname":"Vatanges",
    "gn:country_code":"FR",
    "gn:dem":744,
    "gn:feature_class":"P",
    "gn:feature_code":"PPL",
    "gn:name":"Vatanges",
    "gn:population":0,
    "gn:timezone":"Europe/Paris",
    "iso:country":"FR",
    "wof:name":"Vatanges",
    "wof:placetype":"locality"
},
  "geometry": {"coordinates":[2.51667,45.83333],"type":"Point"}
}