{
  "type": "Feature",
  "properties": {
    "gn:admin1_code":"32",
    "gn:admin2_code":"62",
    "gn:admin3_code":"626",
    "gn:admin4_code":"62193",
    "gn:asciiname":"Le Moulin Bas",
    "gn:country_code":"FR",
    "gn:dem":6,
    "gn:feature_class":"P",
    "gn:feature_code":"PPL",
    "gn:name":"Le Moulin Bas",
    "gn:population":0,
    "gn:timezone":"Europe/Paris",
    "iso:country":"FR",
    "wof:name":"Le Moulin Bas",
    "wof:placetype":"locality"
},
  "geometry": {"coordinates":[1.80766,50.94399],"type":"Point"}
}