{
  "type": "Feature",
  "properties": {
    "iso:country":"FR",
    "wof:name":"La Benauge",
    "wof:placetype":"neighbourhood"
},
  "geometry": {"coordinates":[-0.54316063341131,44.84526925443915],"type":"Point"}
}