{
  "type": "Feature",
  "properties": {
    "gn:admin1_code":"84",
    "gn:admin2_code":"63",
    "gn:admin3_code":"632",
    "gn:admin4_code":"63365",
    "gn:asciiname":"Le Theil",
    "gn:country_code":"FR",
    "gn:dem":655,
    "gn:feature_class":"P",
    "gn:feature_code":"PPL",
    "gn:name":"Le Theil",
    "gn:population":0,
    "gn:timezone":"Europe/Paris",
    "iso:country":"FR",
    "name:bre_x_preferred":[
        "Le Theil"
    ],
    "name:ceb_x_preferred":[
        "Le Theil"
    ],
    "name:deu_x_preferred":[
        "Le Theil"
    ],
    "name:fra_x_preferred":[
        "Le Theil"
    ],
    "name:ita_x_preferred":[
        "Le Theil"
    ],
    "name:nds_x_preferred":[
        "Le Theil"
    ],
    "name:nld_x_preferred":[
        "Le Theil"
    ],
    "name:pms_x_preferred":[
        "Le Theil"
    ],
    "name:pol_x_preferred":[
        "Le Theil"
    ],
    "name:por_x_preferred":[
        "Le Theil"
    ],
    "name:rus_x_preferred":[
        "\u041b\u0435-\u0422\u0435\u0439"
    ],
    "name:slk_x_preferred":[
        "Le Theil"
    ],
    "name:spa_x_preferred":[
        "Le Theil"
    ],
    "name:sqi_x_preferred":[
        "Le Theil"
    ],
    "name:swe_x_preferred":[
        "Le Theil"
    ],
    "name:ukr_x_preferred":[
        "\u041b\u0435-\u0422\u0435\u0439"
    ],
    "wof:name":"Le Theil",
    "wof:placetype":"locality"
},
  "geometry": {"coordinates":[3.44476,45.63915],"type":"Point"}
}