{
  "type": "Feature",
  "properties": {
    "gn:admin1_code":"84",
    "gn:admin2_code":"63",
    "gn:admin3_code":"632",
    "gn:admin4_code":"63365",
    "gn:asciiname":"Le Theil",
    "gn:country_code":"FR",
    "gn:dem":655,
    "gn:feature_class":"P",
    "gn:feature_code":"PPL",
    "gn:name":"Le Theil",
    "gn:population":0,
    "gn:timezone":"Europe/Paris",
    "iso:country":"FR",
    "wof:name":"Le Theil",
    "wof:placetype":"locality"
},
  "geometry": {"coordinates":[3.44476,45.63915],"type":"Point"}
}