{
  "type": "Feature",
  "properties": {
    "gn:admin1_code":"76",
    "gn:admin2_code":"11",
    "gn:admin3_code":"111",
    "gn:admin4_code":"11371",
    "gn:asciiname":"Saint-Hubert",
    "gn:country_code":"FR",
    "gn:dem":227,
    "gn:feature_class":"P",
    "gn:feature_code":"PPL",
    "gn:name":"Saint-Hubert",
    "gn:population":0,
    "gn:timezone":"Europe/Paris",
    "iso:country":"FR",
    "wof:name":"Saint-Hubert",
    "wof:placetype":"locality"
},
  "geometry": {"coordinates":[1.79385,43.28045],"type":"Point"}
}