{
  "type": "Feature",
  "properties": {
    "gn:admin1_code":"76",
    "gn:admin2_code":"11",
    "gn:admin3_code":"111",
    "gn:admin4_code":"11371",
    "gn:asciiname":"Saint-Hubert",
    "gn:country_code":"FR",
    "gn:dem":227,
    "gn:feature_class":"P",
    "gn:feature_code":"PPL",
    "gn:name":"Saint-Hubert",
    "gn:population":0,
    "gn:timezone":"Europe/Paris",
    "iso:country":"FR",
    "name:cat_x_preferred":[
        "Saint-Hubert"
    ],
    "name:ceb_x_preferred":[
        "Saint-Hubert"
    ],
    "name:deu_x_preferred":[
        "Saint-Hubert"
    ],
    "name:fra_x_preferred":[
        "Saint-Hubert"
    ],
    "name:ita_x_preferred":[
        "Saint-Hubert"
    ],
    "name:ltz_x_preferred":[
        "Saint-Hubert"
    ],
    "name:nld_x_preferred":[
        "Saint-Hubert"
    ],
    "name:oci_x_preferred":[
        "Saint-Hubert"
    ],
    "name:pol_x_preferred":[
        "Saint-Hubert"
    ],
    "name:spa_x_preferred":[
        "Saint-Hubert"
    ],
    "name:swe_x_preferred":[
        "Saint-Hubert"
    ],
    "name:vol_x_preferred":[
        "Saint-Hubert"
    ],
    "name:wln_x_preferred":[
        "Sint-Houbert"
    ],
    "wof:name":"Saint-Hubert",
    "wof:placetype":"locality"
},
  "geometry": {"coordinates":[1.79385,43.28045],"type":"Point"}
}