{
  "type": "Feature",
  "properties": {
    "gn:admin1_code":"84",
    "gn:admin2_code":"07",
    "gn:admin3_code":"073",
    "gn:admin4_code":"07095",
    "gn:asciiname":"Le Temple",
    "gn:country_code":"FR",
    "gn:dem":777,
    "gn:feature_class":"P",
    "gn:feature_code":"PPL",
    "gn:name":"Le Temple",
    "gn:population":0,
    "gn:timezone":"Europe/Paris",
    "iso:country":"FR",
    "name:ceb_x_preferred":[
        "Le Temple"
    ],
    "name:deu_x_preferred":[
        "Le Temple"
    ],
    "name:fra_x_preferred":[
        "Le Temple"
    ],
    "name:ita_x_preferred":[
        "Le Temple"
    ],
    "name:nds_x_preferred":[
        "Le Temple"
    ],
    "name:nld_x_preferred":[
        "Le Temple"
    ],
    "name:pms_x_preferred":[
        "Le Temple"
    ],
    "name:pol_x_preferred":[
        "Le Temple"
    ],
    "name:por_x_preferred":[
        "Le Temple"
    ],
    "name:rus_x_preferred":[
        "\u0422\u0435\u043c\u043f\u043b\u044c"
    ],
    "name:slk_x_preferred":[
        "Le Temple"
    ],
    "name:spa_x_preferred":[
        "Le Temple"
    ],
    "name:swe_x_preferred":[
        "Le Temple"
    ],
    "name:ukr_x_preferred":[
        "\u041b\u0435-\u0422\u0430\u043c\u043f\u043b\u044c"
    ],
    "wof:name":"Le Temple",
    "wof:placetype":"locality"
},
  "geometry": {"coordinates":[4.66667,44.96667],"type":"Point"}
}