{
  "type": "Feature",
  "properties": {
    "iso:country":"FR",
    "name:eng_x_preferred":[
        "Paris"
    ],
    "name:fra_x_preferred":[
        "Paris"
    ],
    "wof:name":"Paris",
    "wof:placetype":"neighbourhood"
},
  "geometry": {"coordinates":[2.46649885666184,48.81856916556748],"type":"Point"}
}