{
  "type": "Feature",
  "properties": {
    "gn:admin1_code":"32",
    "gn:admin2_code":"59",
    "gn:admin3_code":"594",
    "gn:admin4_code":"59159",
    "gn:asciiname":"Les Planches",
    "gn:country_code":"FR",
    "gn:dem":2,
    "gn:feature_class":"P",
    "gn:feature_code":"PPL",
    "gn:name":"Les Planches",
    "gn:population":0,
    "gn:timezone":"Europe/Paris",
    "iso:country":"FR",
    "wof:name":"Les Planches",
    "wof:placetype":"locality"
},
  "geometry": {"coordinates":[2.21346,50.97319],"type":"Point"}
}