{
  "type": "Feature",
  "properties": {
    "gn:admin1_code":"75",
    "gn:admin2_code":"24",
    "gn:admin3_code":"243",
    "gn:admin4_code":"24308",
    "gn:asciiname":"Le Maine",
    "gn:country_code":"FR",
    "gn:dem":194,
    "gn:feature_class":"P",
    "gn:feature_code":"PPL",
    "gn:name":"Le Maine",
    "gn:population":0,
    "gn:timezone":"Europe/Paris",
    "iso:country":"FR",
    "wof:name":"Le Maine",
    "wof:placetype":"locality"
},
  "geometry": {"coordinates":[0.90334,45.34136],"type":"Point"}
}