{
  "type": "Feature",
  "properties": {
    "gn:admin1_code":"75",
    "gn:admin2_code":"23",
    "gn:admin3_code":"232",
    "gn:admin4_code":"23012",
    "gn:asciiname":"Le Mazeau",
    "gn:country_code":"FR",
    "gn:dem":441,
    "gn:feature_class":"P",
    "gn:feature_code":"PPL",
    "gn:name":"Le Mazeau",
    "gn:population":0,
    "gn:timezone":"Europe/Paris",
    "iso:country":"FR",
    "name:cat_x_preferred":[
        "Le Mazeau"
    ],
    "name:ceb_x_preferred":[
        "Le Mazeau"
    ],
    "name:deu_x_preferred":[
        "Le Mazeau"
    ],
    "name:eus_x_preferred":[
        "Le Mazeau"
    ],
    "name:fra_x_preferred":[
        "Le Mazeau"
    ],
    "name:hun_x_preferred":[
        "Le Mazeau"
    ],
    "name:ita_x_preferred":[
        "Le Mazeau"
    ],
    "name:msa_x_preferred":[
        "Le Mazeau"
    ],
    "name:nld_x_preferred":[
        "Le Mazeau"
    ],
    "name:oci_x_preferred":[
        "Le Mazeau"
    ],
    "name:pms_x_preferred":[
        "Le Mazeau"
    ],
    "name:pol_x_preferred":[
        "Le Mazeau"
    ],
    "name:por_x_preferred":[
        "Le Mazeau"
    ],
    "name:ron_x_preferred":[
        "Le Mazeau"
    ],
    "name:slk_x_preferred":[
        "Le Mazeau"
    ],
    "name:spa_x_preferred":[
        "Le Mazeau"
    ],
    "name:swe_x_preferred":[
        "Le Mazeau"
    ],
    "name:ukr_x_preferred":[
        "\u041b\u0435-\u041c\u0430\u0437\u043e"
    ],
    "name:vie_x_preferred":[
        "Le Mazeau"
    ],
    "name:vol_x_preferred":[
        "Le Mazeau"
    ],
    "name:war_x_preferred":[
        "Le Mazeau"
    ],
    "name:zho_x_preferred":[
        "\u83b1\u9a6c\u4f50"
    ],
    "wof:name":"Le Mazeau",
    "wof:placetype":"locality"
},
  "geometry": {"coordinates":[1.65698,45.87985],"type":"Point"}
}