{
  "type": "Feature",
  "properties": {
    "gn:admin1_code":"75",
    "gn:admin2_code":"23",
    "gn:admin3_code":"232",
    "gn:admin4_code":"23012",
    "gn:asciiname":"Le Mazeau",
    "gn:country_code":"FR",
    "gn:dem":441,
    "gn:feature_class":"P",
    "gn:feature_code":"PPL",
    "gn:name":"Le Mazeau",
    "gn:population":0,
    "gn:timezone":"Europe/Paris",
    "iso:country":"FR",
    "wof:name":"Le Mazeau",
    "wof:placetype":"locality"
},
  "geometry": {"coordinates":[1.65698,45.87985],"type":"Point"}
}