{
  "type": "Feature",
  "properties": {
    "gn:admin1_code":"84",
    "gn:admin2_code":"07",
    "gn:admin3_code":"073",
    "gn:admin4_code":"07102",
    "gn:asciiname":"Guilherand-Granges",
    "gn:country_code":"FR",
    "gn:dem":112,
    "gn:feature_class":"P",
    "gn:feature_code":"PPL",
    "gn:name":"Guilherand-Granges",
    "gn:population":11365,
    "gn:timezone":"Europe/Paris",
    "iso:country":"FR",
    "name:und_x_variant":[
        "Granges-l\u00e8s-Valence"
    ],
    "wof:name":"Guilherand-Granges",
    "wof:placetype":"locality",
    "wof:population":11365
},
  "geometry": {"coordinates":[4.87372,44.93278],"type":"Point"}
}