{
  "type": "Feature",
  "properties": {
    "gn:admin1_code":"84",
    "gn:admin2_code":"07",
    "gn:admin3_code":"073",
    "gn:admin4_code":"7041.0",
    "gn:asciiname":"Seux",
    "gn:country_code":"FR",
    "gn:dem":511,
    "gn:feature_class":"P",
    "gn:feature_code":"PPL",
    "gn:name":"Seux",
    "gn:population":0,
    "gn:timezone":"Europe/Paris",
    "iso:country":"FR",
    "wof:name":"Seux",
    "wof:placetype":"locality"
},
  "geometry": {"coordinates":[4.63617,45.26344],"type":"Point"}
}