{
  "type": "Feature",
  "properties": {
    "gn:admin1_code":"53",
    "gn:admin2_code":"22",
    "gn:admin3_code":"222",
    "gn:admin4_code":"22072",
    "gn:asciiname":"Kergaer",
    "gn:country_code":"FR",
    "gn:dem":177,
    "gn:feature_class":"P",
    "gn:feature_code":"PPL",
    "gn:name":"Kerga\u00ebr",
    "gn:population":0,
    "gn:timezone":"Europe/Paris",
    "iso:country":"FR",
    "wof:name":"Kergaer",
    "wof:placetype":"locality"
},
  "geometry": {"coordinates":[-3.32363,48.50772],"type":"Point"}
}