{
  "type": "Feature",
  "properties": {
    "gn:admin1_code":"76",
    "gn:admin2_code":"46",
    "gn:admin3_code":"462",
    "gn:admin4_code":"46102",
    "gn:asciiname":"Puy de Corn",
    "gn:country_code":"FR",
    "gn:dem":284,
    "gn:feature_class":"P",
    "gn:feature_code":"PPL",
    "gn:name":"Puy de Corn",
    "gn:population":0,
    "gn:timezone":"Europe/Paris",
    "iso:country":"FR",
    "wof:name":"Puy de Corn",
    "wof:placetype":"locality"
},
  "geometry": {"coordinates":[1.98171,44.60169000000001],"type":"Point"}
}