{
  "type": "Feature",
  "properties": {
    "gn:admin1_code":"75",
    "gn:admin2_code":"64",
    "gn:admin3_code":"641",
    "gn:admin4_code":"64547",
    "gn:asciiname":"Hiribehere",
    "gn:country_code":"FR",
    "gn:dem":14,
    "gn:feature_class":"P",
    "gn:feature_code":"PPL",
    "gn:name":"Hirib\u00e9here",
    "gn:population":0,
    "gn:timezone":"Europe/Paris",
    "iso:country":"FR",
    "wof:name":"Hiribehere",
    "wof:placetype":"locality"
},
  "geometry": {"coordinates":[-1.46004,43.40217],"type":"Point"}
}