{
  "type": "Feature",
  "properties": {
    "gn:admin1_code":"84",
    "gn:admin2_code":"73",
    "gn:admin3_code":"732",
    "gn:admin4_code":"73107",
    "gn:asciiname":"Les Rigauds",
    "gn:country_code":"FR",
    "gn:dem":1044,
    "gn:feature_class":"P",
    "gn:feature_code":"PPL",
    "gn:name":"Les Rigauds",
    "gn:population":0,
    "gn:timezone":"Europe/Paris",
    "iso:country":"FR",
    "wof:name":"Les Rigauds",
    "wof:placetype":"locality"
},
  "geometry": {"coordinates":[5.88631,45.43379],"type":"Point"}
}