{
  "type": "Feature",
  "properties": {
    "gn:admin1_code":"84",
    "gn:admin2_code":"15",
    "gn:admin3_code":"153",
    "gn:admin4_code":"15148",
    "gn:asciiname":"La Salesse",
    "gn:country_code":"FR",
    "gn:dem":1034,
    "gn:feature_class":"P",
    "gn:feature_code":"PPL",
    "gn:name":"La Salesse",
    "gn:population":0,
    "gn:timezone":"Europe/Paris",
    "iso:country":"FR",
    "wof:name":"La Salesse",
    "wof:placetype":"locality"
},
  "geometry": {"coordinates":[2.92954,45.00164],"type":"Point"}
}