{
  "type": "Feature",
  "properties": {
    "gn:admin1_code":"24",
    "gn:admin2_code":"36",
    "gn:admin3_code":"361",
    "gn:admin4_code":"36168",
    "gn:asciiname":"Le Chatellier",
    "gn:country_code":"FR",
    "gn:dem":171,
    "gn:feature_class":"P",
    "gn:feature_code":"PPL",
    "gn:name":"Le Ch\u00e2tellier",
    "gn:population":0,
    "gn:timezone":"Europe/Paris",
    "iso:country":"FR",
    "wof:name":"Le Chatellier",
    "wof:placetype":"locality"
},
  "geometry": {"coordinates":[1.33815,46.505],"type":"Point"}
}