{
  "type": "Feature",
  "properties": {
    "gn:admin1_code":"84",
    "gn:admin2_code":"26",
    "gn:admin3_code":"263",
    "gn:admin4_code":"26009",
    "gn:asciiname":"Bancel",
    "gn:country_code":"FR",
    "gn:dem":142,
    "gn:feature_class":"P",
    "gn:feature_code":"PPL",
    "gn:name":"Bancel",
    "gn:population":0,
    "gn:timezone":"Europe/Paris",
    "iso:country":"FR",
    "wof:name":"Bancel",
    "wof:placetype":"locality"
},
  "geometry": {"coordinates":[4.81755,45.23143],"type":"Point"}
}