{
  "type": "Feature",
  "properties": {
    "gn:admin1_code":"52",
    "gn:admin2_code":"44",
    "gn:admin3_code":"443",
    "gn:admin4_code":"44080",
    "gn:asciiname":"La Fontaine",
    "gn:country_code":"FR",
    "gn:dem":5,
    "gn:feature_class":"P",
    "gn:feature_code":"PPL",
    "gn:name":"La Fontaine",
    "gn:population":0,
    "gn:timezone":"Europe/Paris",
    "iso:country":"FR",
    "wof:name":"La Fontaine",
    "wof:placetype":"locality"
},
  "geometry": {"coordinates":[-1.98186,47.31175],"type":"Point"}
}