{
  "type": "Feature",
  "properties": {
    "gn:admin1_code":"93",
    "gn:admin2_code":"04",
    "gn:admin3_code":"044",
    "gn:admin4_code":"04095",
    "gn:asciiname":"Les Girons",
    "gn:country_code":"FR",
    "gn:dem":1020,
    "gn:feature_class":"P",
    "gn:feature_code":"PPL",
    "gn:name":"Les Girons",
    "gn:population":0,
    "gn:timezone":"Europe/Paris",
    "iso:country":"FR",
    "wof:name":"Les Girons",
    "wof:placetype":"locality"
},
  "geometry": {"coordinates":[5.69713,44.10979],"type":"Point"}
}