{
  "type": "Feature",
  "properties": {
    "gn:admin1_code":"93",
    "gn:admin2_code":"05",
    "gn:admin3_code":"051",
    "gn:admin4_code":"05107",
    "gn:asciiname":"Puy Chalvin",
    "gn:cc2":"FR",
    "gn:country_code":"FR",
    "gn:dem":1634,
    "gn:feature_class":"P",
    "gn:feature_code":"PPL",
    "gn:name":"Puy Chalvin",
    "gn:population":0,
    "gn:timezone":"Europe/Paris",
    "iso:country":"FR",
    "name:und_x_variant":[
        "Chalvin",
        "Puy Chalvin"
    ],
    "wof:name":"Puy Chalvin",
    "wof:placetype":"locality"
},
  "geometry": {"coordinates":[6.58969,44.87926],"type":"Point"}
}