{
  "type": "Feature",
  "properties": {
    "gn:admin1_code":"84",
    "gn:admin2_code":"63",
    "gn:admin3_code":"632",
    "gn:admin4_code":"63252",
    "gn:asciiname":"Neuville",
    "gn:country_code":"FR",
    "gn:dem":417,
    "gn:feature_class":"P",
    "gn:feature_code":"PPL",
    "gn:name":"Neuville",
    "gn:population":335,
    "gn:timezone":"Europe/Paris",
    "iso:country":"FR",
    "wof:name":"Neuville",
    "wof:placetype":"locality",
    "wof:population":335
},
  "geometry": {"coordinates":[3.43676,45.74604],"type":"Point"}
}