{
  "type": "Feature",
  "properties": {
    "frgov:code_epci":"200067627",
    "frgov:insee_arr":"2",
    "frgov:insee_com":"63252",
    "frgov:insee_dep":"63",
    "frgov:insee_reg":"84",
    "frgov:nom_com":"Neuville",
    "frgov:nom_com_m":"NEUVILLE",
    "frgov:nom_dep":"PUY-DE-DOME",
    "frgov:nom_reg":"AUVERGNE-RHONE-ALPES",
    "frgov:statut":"Commune simple",
    "gn:admin1_code":"84",
    "gn:admin2_code":"63",
    "gn:admin3_code":"632",
    "gn:admin4_code":"63252",
    "gn:asciiname":"Neuville",
    "gn:country_code":"FR",
    "gn:dem":417,
    "gn:feature_class":"P",
    "gn:feature_code":"PPL",
    "gn:name":"Neuville",
    "gn:population":335,
    "gn:timezone":"Europe/Paris",
    "iso:country":"FR",
    "name:bre_x_preferred":[
        "Neuville"
    ],
    "name:cat_x_preferred":[
        "Neuville"
    ],
    "name:cat_x_variant":[
        "Neuville"
    ],
    "name:ceb_x_preferred":[
        "Neuville"
    ],
    "name:deu_x_preferred":[
        "Neuville"
    ],
    "name:fas_x_preferred":[
        "\u0646\u0648\u0648\u06cc\u0644"
    ],
    "name:fra_x_preferred":[
        "Neuville"
    ],
    "name:ita_x_preferred":[
        "Neuville"
    ],
    "name:kaz_x_preferred":[
        "\u041d\u0435\u0432\u0438\u043b\u044c"
    ],
    "name:nds_x_preferred":[
        "Neuville"
    ],
    "name:nld_x_preferred":[
        "Neuville"
    ],
    "name:oci_x_preferred":[
        "Neuviala"
    ],
    "name:pms_x_preferred":[
        "Neuville"
    ],
    "name:pol_x_preferred":[
        "Neuville"
    ],
    "name:por_x_preferred":[
        "Neuville"
    ],
    "name:rus_x_preferred":[
        "\u041d\u0451\u0432\u0438\u043b\u044c"
    ],
    "name:slk_x_preferred":[
        "Neuville"
    ],
    "name:spa_x_preferred":[
        "Neuville"
    ],
    "name:sqi_x_preferred":[
        "Neuville"
    ],
    "name:swe_x_preferred":[
        "Neuville"
    ],
    "name:ukr_x_preferred":[
        "\u041d\u0435\u0432\u0456\u043b\u044c"
    ],
    "name:zho_x_preferred":[
        "\u8bb7\u7ef4\u5c14"
    ],
    "qs:a0":"France",
    "qs:a1":"PUY-DE-DOME",
    "qs:a1_lc":"63",
    "qs:a1r":"AUVERGNE",
    "qs:a1r_lc":"83",
    "qs:a2_lc":"06",
    "qs:a2r_lc":"2",
    "qs:adm0":"France",
    "qs:adm0_a3":"FRA",
    "qs:la":"NEUVILLE",
    "qs:la_lc":"63252",
    "qs:level":"localadmin",
    "qs:type":"Commune simple",
    "wof:coterminous":[
        404394401
    ],
    "wof:name":"Neuville",
    "wof:placetype":"locality",
    "wof:placetype_local":"Commune simple",
    "wof:population":335
},
  "geometry": {"coordinates":[3.43676,45.74604],"type":"Point"}
}