{
  "type": "Feature",
  "properties": {
    "gn:admin1_code":"84",
    "gn:admin2_code":"43",
    "gn:admin3_code":"433",
    "gn:admin4_code":"43249",
    "gn:asciiname":"La Valtaillet",
    "gn:country_code":"FR",
    "gn:dem":814,
    "gn:feature_class":"P",
    "gn:feature_code":"PPL",
    "gn:name":"La Valtaillet",
    "gn:population":0,
    "gn:timezone":"Europe/Paris",
    "iso:country":"FR",
    "wof:name":"La Valtaillet",
    "wof:placetype":"locality"
},
  "geometry": {"coordinates":[4.05046,45.3387],"type":"Point"}
}