{
  "type": "Feature",
  "properties": {
    "gn:admin1_code":"24",
    "gn:admin2_code":"28",
    "gn:admin3_code":"281",
    "gn:admin4_code":"28191",
    "gn:asciiname":"Ouance",
    "gn:country_code":"FR",
    "gn:dem":112,
    "gn:feature_class":"P",
    "gn:feature_code":"PPL",
    "gn:name":"Ouanc\u00e9",
    "gn:population":0,
    "gn:timezone":"Europe/Paris",
    "iso:country":"FR",
    "wof:name":"Ouance",
    "wof:placetype":"locality"
},
  "geometry": {"coordinates":[1.64035,48.60607],"type":"Point"}
}