{
  "type": "Feature",
  "properties": {
    "gn:admin1_code":"76",
    "gn:admin2_code":"48",
    "gn:admin3_code":"481",
    "gn:admin4_code":"48152",
    "gn:asciiname":"Penens",
    "gn:country_code":"FR",
    "gn:dem":541,
    "gn:feature_class":"P",
    "gn:feature_code":"PPL",
    "gn:name":"P\u00e9nens",
    "gn:population":0,
    "gn:timezone":"Europe/Paris",
    "iso:country":"FR",
    "wof:name":"Penens",
    "wof:placetype":"locality"
},
  "geometry": {"coordinates":[3.89852,44.28467],"type":"Point"}
}