{
  "type": "Feature",
  "properties": {
    "iso:country":"FR",
    "qs_pg:aaroncc":"FR",
    "qs_pg:name":"Vall\u00e9e Etroite",
    "qs_pg:name_adm0":"France",
    "qs_pg:name_adm1":"Provence-Alpes-C\u00f4te d'Azur",
    "qs_pg:photos":347,
    "qs_pg:photos_1k":70,
    "qs_pg:photos_9k":2,
    "qs_pg:photos_9r":5,
    "qs_pg:photos_all":347,
    "qs_pg:photos_sr":5,
    "qs_pg:pop_sr":0,
    "qs_pg:qs_pg_placetype":"locality",
    "qs_pg:qs_pg_placetype_gp":"Town",
    "qs_pg:woe_adm0":23424819,
    "woe:adm0_id":23424819,
    "woe:name_adm0":"France",
    "woe:name_adm1":"Provence-Alpes-C\u00f4te d'Azur",
    "woe:placetype":"Town",
    "wof:name":"Vall\u00e9e Etroite",
    "wof:placetype":"neighbourhood"
},
  "geometry": {"coordinates":[6.619983,45.071352],"type":"Point"}
}