{
  "type": "Feature",
  "properties": {
    "gn:admin1_code":"52",
    "gn:admin2_code":"72",
    "gn:admin3_code":"722",
    "gn:admin4_code":"72144",
    "gn:asciiname":"Vaufargis",
    "gn:country_code":"FR",
    "gn:dem":164,
    "gn:feature_class":"P",
    "gn:feature_code":"PPL",
    "gn:name":"Vaufargis",
    "gn:population":0,
    "gn:timezone":"Europe/Paris",
    "iso:country":"FR",
    "wof:name":"Vaufargis",
    "wof:placetype":"locality"
},
  "geometry": {"coordinates":[0.79854,48.11549],"type":"Point"}
}