{
  "type": "Feature",
  "properties": {
    "gn:admin1_code":"84",
    "gn:admin2_code":"03",
    "gn:admin3_code":"031",
    "gn:admin4_code":"03048",
    "gn:asciiname":"Marsin",
    "gn:country_code":"FR",
    "gn:dem":307,
    "gn:feature_class":"P",
    "gn:feature_code":"PPL",
    "gn:name":"Marsin",
    "gn:population":0,
    "gn:timezone":"Europe/Paris",
    "iso:country":"FR",
    "wof:name":"Marsin",
    "wof:placetype":"locality"
},
  "geometry": {"coordinates":[2.8022,46.63638],"type":"Point"}
}