{
  "type": "Feature",
  "properties": {
    "iso:country":"FR",
    "name:eng_x_preferred":[
        "Noyer Dore"
    ],
    "name:fra_x_preferred":[
        "Noyer Dor\u00e9"
    ],
    "wof:name":"Noyer Dore",
    "wof:placetype":"neighbourhood"
},
  "geometry": {"coordinates":[2.28463966135775,48.73682158221535],"type":"Point"}
}