{
  "type": "Feature",
  "properties": {
    "gn:admin1_code":"24",
    "gn:admin2_code":"36",
    "gn:admin3_code":"362",
    "gn:admin4_code":"36024.0",
    "gn:asciiname":"Bretagne",
    "gn:country_code":"FR",
    "gn:dem":142,
    "gn:feature_class":"P",
    "gn:feature_code":"PPL",
    "gn:name":"Bretagne",
    "gn:population":0,
    "gn:timezone":"Europe/Paris",
    "iso:country":"FR",
    "name:rus_x_preferred":[
        "\u0411\u0440\u0435\u0442\u0430\u043d\u044c"
    ],
    "wof:name":"Bretagne",
    "wof:placetype":"locality"
},
  "geometry": {"coordinates":[1.68135,47.00343],"type":"Point"}
}