{
  "type": "Feature",
  "properties": {
    "frgov:code_epci":"243600293",
    "frgov:insee_arr":"2",
    "frgov:insee_com":"36024",
    "frgov:insee_dep":"36",
    "frgov:insee_reg":"24",
    "frgov:nom_com":"Bretagne",
    "frgov:nom_com_m":"BRETAGNE",
    "frgov:nom_dep":"INDRE",
    "frgov:nom_reg":"CENTRE-VAL DE LOIRE",
    "frgov:statut":"Commune simple",
    "gn:admin1_code":"24",
    "gn:admin2_code":"36",
    "gn:admin3_code":"362",
    "gn:admin4_code":"36024.0",
    "gn:asciiname":"Bretagne",
    "gn:country_code":"FR",
    "gn:dem":142,
    "gn:feature_class":"P",
    "gn:feature_code":"PPL",
    "gn:name":"Bretagne",
    "gn:population":0,
    "gn:timezone":"Europe/Paris",
    "iso:country":"FR",
    "name:bel_x_preferred":[
        "\u0411\u0440\u044d\u0442\u0430\u043d\u044c"
    ],
    "name:bre_x_preferred":[
        "Bretagne"
    ],
    "name:ceb_x_preferred":[
        "Bretagne"
    ],
    "name:deu_x_preferred":[
        "Bretagne"
    ],
    "name:eus_x_preferred":[
        "Bretainia"
    ],
    "name:fra_x_preferred":[
        "Bretagne"
    ],
    "name:fry_x_preferred":[
        "Bretanje"
    ],
    "name:glv_x_preferred":[
        "Yn Vritaan"
    ],
    "name:heb_x_preferred":[
        "\u05d1\u05e8\u05d9\u05d8\u05e0\u05d9"
    ],
    "name:hin_x_preferred":[
        "\u092c\u094d\u0930\u0947\u091f\u0947\u0917\u0928\u0947"
    ],
    "name:ita_x_preferred":[
        "Bretagne"
    ],
    "name:jpn_x_preferred":[
        "\u30d6\u30eb\u30bf\u30fc\u30cb\u30e5"
    ],
    "name:kor_x_preferred":[
        "\ube0c\ub974\ud0c0\ub274"
    ],
    "name:nds_x_preferred":[
        "Bretagne"
    ],
    "name:nld_x_preferred":[
        "Bretagne"
    ],
    "name:pms_x_preferred":[
        "Bretagne"
    ],
    "name:pol_x_preferred":[
        "Bretagne"
    ],
    "name:por_x_preferred":[
        "Bretagne"
    ],
    "name:ron_x_preferred":[
        "Bretagne"
    ],
    "name:rus_x_preferred":[
        "\u0411\u0440\u0435\u0442\u0430\u043d\u044c"
    ],
    "name:slk_x_preferred":[
        "Bretagne"
    ],
    "name:spa_x_preferred":[
        "Bretagne"
    ],
    "name:srp_x_preferred":[
        "\u0411\u0440\u0435\u0442\u0430\u045a"
    ],
    "name:swe_x_preferred":[
        "Bretagne"
    ],
    "name:ukr_x_preferred":[
        "\u0411\u0440\u0435\u0442\u0430\u043d\u044c"
    ],
    "name:vie_x_preferred":[
        "Bretagne"
    ],
    "name:zho_x_preferred":[
        "\u5e03\u5217\u5854\u5c3c"
    ],
    "qs:a0":"France",
    "qs:a1":"INDRE",
    "qs:a1_lc":"36",
    "qs:a1r":"CENTRE",
    "qs:a1r_lc":"24",
    "qs:a2_lc":"14",
    "qs:a2r_lc":"2",
    "qs:adm0":"France",
    "qs:adm0_a3":"FRA",
    "qs:la":"BRETAGNE",
    "qs:la_lc":"36024",
    "qs:level":"localadmin",
    "qs:type":"Commune simple",
    "wof:coterminous":[
        404426629
    ],
    "wof:name":"Bretagne",
    "wof:placetype":"locality",
    "wof:placetype_local":"Commune simple"
},
  "geometry": {"coordinates":[1.68135,47.00343],"type":"Point"}
}