{
  "type": "Feature",
  "properties": {
    "gn:admin1_code":"84",
    "gn:admin2_code":"38",
    "gn:admin3_code":"383",
    "gn:admin4_code":"38555",
    "gn:asciiname":"La Fetas",
    "gn:country_code":"FR",
    "gn:dem":480,
    "gn:feature_class":"P",
    "gn:feature_code":"PPL",
    "gn:name":"La F\u00e9tas",
    "gn:population":0,
    "gn:timezone":"Europe/Paris",
    "iso:country":"FR",
    "name:und_x_variant":[
        "La Feytas",
        "La F\u00e9tas"
    ],
    "wof:name":"La Fetas",
    "wof:placetype":"locality"
},
  "geometry": {"coordinates":[5.09009,45.44719],"type":"Point"}
}