{
  "type": "Feature",
  "properties": {
    "iso:country":"FR",
    "name:eng_x_preferred":[
        "Le Clos Montceleux"
    ],
    "name:fra_x_preferred":[
        "Le Clos Montceleux"
    ],
    "wof:name":"Le Clos Montceleux",
    "wof:placetype":"neighbourhood"
},
  "geometry": {"coordinates":[2.53586848248445,48.95438266071284],"type":"Point"}
}