{
  "type": "Feature",
  "properties": {
    "gn:admin1_code":"53",
    "gn:admin2_code":"29",
    "gn:admin3_code":"292",
    "gn:admin4_code":"29176",
    "gn:asciiname":"Plonevez-Porzay",
    "gn:country_code":"FR",
    "gn:dem":92,
    "gn:feature_class":"P",
    "gn:feature_code":"PPL",
    "gn:name":"Plon\u00e9vez-Porzay",
    "gn:population":0,
    "gn:timezone":"Europe/Paris",
    "iso:country":"FR",
    "name:bre_x_preferred":[
        "Plonevez-Porzhe"
    ],
    "name:jpn_x_preferred":[
        "\u30d7\u30ed\u30cd\u30f4\u30a7\uff1d\u30dd\u30eb\u30bc"
    ],
    "name:kaz_x_preferred":[
        "\u041f\u043b\u043e\u043d\u0435\u0432\u0435-\u041f\u043e\u0440\u0437\u0435"
    ],
    "name:oci_x_preferred":[
        "Plonevez-Porzhe"
    ],
    "name:ukr_x_preferred":[
        "\u041f\u043b\u043e\u043d\u0435\u0432\u0435-\u041f\u043e\u0440\u0437\u0435"
    ],
    "name:zho_x_preferred":[
        "\u666e\u6d1b\u5185\u97e6\u6ce2\u5c14\u6cfd"
    ],
    "wof:name":"Plonevez-Porzay",
    "wof:placetype":"locality"
},
  "geometry": {"coordinates":[-4.21873,48.12425],"type":"Point"}
}