{
  "type": "Feature",
  "properties": {
    "gn:admin1_code":"75",
    "gn:admin2_code":"24",
    "gn:admin3_code":"241",
    "gn:admin4_code":"24345",
    "gn:asciiname":"La Mouthe",
    "gn:country_code":"FR",
    "gn:dem":115,
    "gn:feature_class":"P",
    "gn:feature_code":"PPL",
    "gn:name":"La Mouthe",
    "gn:population":0,
    "gn:timezone":"Europe/Paris",
    "iso:country":"FR",
    "wof:name":"La Mouthe",
    "wof:placetype":"locality"
},
  "geometry": {"coordinates":[0.52788,44.91147],"type":"Point"}
}