{
  "type": "Feature",
  "properties": {
    "gn:admin1_code":"84",
    "gn:admin2_code":"43",
    "gn:admin3_code":"433",
    "gn:admin4_code":"43246",
    "gn:asciiname":"Arnaud",
    "gn:country_code":"FR",
    "gn:dem":883,
    "gn:feature_class":"P",
    "gn:feature_code":"PPL",
    "gn:name":"Arnaud",
    "gn:population":0,
    "gn:timezone":"Europe/Paris",
    "iso:country":"FR",
    "name:ceb_x_preferred":[
        "Arnaud"
    ],
    "name:deu_x_preferred":[
        "Arnaud"
    ],
    "name:fra_x_preferred":[
        "Arnaud"
    ],
    "name:ita_x_preferred":[
        "Arnaud"
    ],
    "name:jpn_x_preferred":[
        "\u30a2\u30eb\u30ce\u30fc\u5ddd"
    ],
    "name:jpn_x_variant":[
        "\u30a2\u30eb\u30ce\u30fc"
    ],
    "name:kor_x_preferred":[
        "\uc544\ub974\ub178"
    ],
    "name:nld_x_preferred":[
        "Arnaud"
    ],
    "name:por_x_preferred":[
        "Arnaud"
    ],
    "name:ron_x_preferred":[
        "Arnaud"
    ],
    "name:slv_x_preferred":[
        "Arnaud"
    ],
    "name:spa_x_preferred":[
        "Arnaud"
    ],
    "name:swe_x_preferred":[
        "Arnaud"
    ],
    "name:tur_x_preferred":[
        "Arnaud"
    ],
    "name:ukr_x_preferred":[
        "\u0410\u0440\u043d\u0430\u0443\u0434"
    ],
    "name:urd_x_preferred":[
        "\u0622\u0645\u0648\u062f"
    ],
    "name:vie_x_preferred":[
        "S\u00f4ng Arnaud"
    ],
    "name:war_x_preferred":[
        "Arnaud"
    ],
    "name:zho_cn_x_preferred":[
        "\u963f\u8bfa\u6cb3"
    ],
    "name:zho_tw_x_preferred":[
        "\u963f\u7459\u5fb7\u6cb3"
    ],
    "wof:name":"Arnaud",
    "wof:placetype":"locality"
},
  "geometry": {"coordinates":[4.01138,45.29404],"type":"Point"}
}