{
  "type": "Feature",
  "properties": {
    "gn:admin1_code":"53",
    "gn:admin2_code":"29",
    "gn:admin3_code":"292",
    "gn:admin4_code":"29261",
    "gn:asciiname":"Bodingar",
    "gn:country_code":"FR",
    "gn:dem":166,
    "gn:feature_class":"P",
    "gn:feature_code":"PPL",
    "gn:name":"Bodingar",
    "gn:population":0,
    "gn:timezone":"Europe/Paris",
    "iso:country":"FR",
    "wof:name":"Bodingar",
    "wof:placetype":"locality"
},
  "geometry": {"coordinates":[-4.01645,48.34756],"type":"Point"}
}