{
  "type": "Feature",
  "properties": {
    "gn:admin1_code":"84",
    "gn:admin2_code":"63",
    "gn:admin3_code":"634",
    "gn:admin4_code":"63251",
    "gn:asciiname":"Les Chers",
    "gn:country_code":"FR",
    "gn:dem":606,
    "gn:feature_class":"P",
    "gn:feature_code":"PPL",
    "gn:name":"Les Chers",
    "gn:population":0,
    "gn:timezone":"Europe/Paris",
    "iso:country":"FR",
    "wof:name":"Les Chers",
    "wof:placetype":"locality"
},
  "geometry": {"coordinates":[2.8567,46.08735],"type":"Point"}
}