{
  "type": "Feature",
  "properties": {
    "gn:admin1_code":"93",
    "gn:admin2_code":"83",
    "gn:admin3_code":"833",
    "gn:admin4_code":"83005",
    "gn:asciiname":"Fontaine",
    "gn:country_code":"FR",
    "gn:dem":531,
    "gn:feature_class":"P",
    "gn:feature_code":"PPL",
    "gn:name":"Fontaine",
    "gn:population":0,
    "gn:timezone":"Europe/Paris",
    "iso:country":"FR",
    "name:azb_x_preferred":[
        "\u0641\u0648\u0646\u062a\u0646"
    ],
    "name:bre_x_preferred":[
        "Fontaine"
    ],
    "name:cat_x_preferred":[
        "Fontaine"
    ],
    "name:ceb_x_preferred":[
        "Fontaine"
    ],
    "name:deu_x_preferred":[
        "Fontaine"
    ],
    "name:epo_x_preferred":[
        "Fontaine"
    ],
    "name:fas_x_preferred":[
        "\u0641\u0648\u0646\u062a\u0646"
    ],
    "name:fra_x_preferred":[
        "Fontaine"
    ],
    "name:heb_x_preferred":[
        "\u05e4\u05d5\u05e0\u05d8\u05d9\u05d9\u05df"
    ],
    "name:ita_x_preferred":[
        "Fontaine"
    ],
    "name:jpn_x_preferred":[
        "\u30d5\u30a9\u30f3\u30c6\u30fc\u30cc"
    ],
    "name:lav_x_preferred":[
        "Fontaine"
    ],
    "name:nds_x_preferred":[
        "Fontaine"
    ],
    "name:nld_x_preferred":[
        "Fontaine"
    ],
    "name:pms_x_preferred":[
        "Fontaine"
    ],
    "name:pol_x_preferred":[
        "Fontaine"
    ],
    "name:por_x_preferred":[
        "Fontaine"
    ],
    "name:rus_x_preferred":[
        "\u0424\u043e\u043d\u0442\u0435\u0439\u043d"
    ],
    "name:slk_x_preferred":[
        "Fontaine"
    ],
    "name:spa_x_preferred":[
        "Fontaine"
    ],
    "name:srp_x_preferred":[
        "\u0424\u043e\u043d\u0442\u0435\u043d"
    ],
    "name:swe_x_preferred":[
        "Fontaine"
    ],
    "name:ukr_x_preferred":[
        "\u0424\u043e\u043d\u0442\u0435\u043d"
    ],
    "wof:name":"Fontaine",
    "wof:placetype":"locality"
},
  "geometry": {"coordinates":[6.11206,43.6909],"type":"Point"}
}