{
  "type": "Feature",
  "properties": {
    "gn:admin1_code":"93",
    "gn:admin2_code":"83",
    "gn:admin3_code":"833",
    "gn:admin4_code":"83005",
    "gn:asciiname":"Fontaine",
    "gn:country_code":"FR",
    "gn:dem":531,
    "gn:feature_class":"P",
    "gn:feature_code":"PPL",
    "gn:name":"Fontaine",
    "gn:population":0,
    "gn:timezone":"Europe/Paris",
    "iso:country":"FR",
    "wof:name":"Fontaine",
    "wof:placetype":"locality"
},
  "geometry": {"coordinates":[6.11206,43.6909],"type":"Point"}
}