{
  "type": "Feature",
  "properties": {
    "gn:admin1_code":"84",
    "gn:admin2_code":"07",
    "gn:admin3_code":"071",
    "gn:admin4_code":"07024",
    "gn:asciiname":"La Lauze",
    "gn:country_code":"FR",
    "gn:dem":146,
    "gn:feature_class":"P",
    "gn:feature_code":"PPL",
    "gn:name":"La Lauze",
    "gn:population":0,
    "gn:timezone":"Europe/Paris",
    "iso:country":"FR",
    "name:und_x_variant":[
        "Lauze",
        "La Lauze"
    ],
    "wof:name":"La Lauze",
    "wof:placetype":"locality"
},
  "geometry": {"coordinates":[4.17594,44.37454],"type":"Point"}
}