{
  "type": "Feature",
  "properties": {
    "iso:country":"FR",
    "name:eng_x_preferred":[
        "La Pepiniere"
    ],
    "name:fra_x_preferred":[
        "La P\u00e9pini\u00e8re"
    ],
    "name:fra_x_variant":[
        "La Pep"
    ],
    "wof:name":"La Pepiniere",
    "wof:placetype":"neighbourhood"
},
  "geometry": {"coordinates":[2.27610665611831,48.78477781611999],"type":"Point"}
}