{
  "type": "Feature",
  "properties": {
    "gn:admin1_code":"27",
    "gn:admin2_code":"58",
    "gn:admin3_code":"584",
    "gn:admin4_code":"58036",
    "gn:asciiname":"Forges",
    "gn:country_code":"FR",
    "gn:dem":246,
    "gn:feature_class":"P",
    "gn:feature_code":"PPL",
    "gn:name":"Forges",
    "gn:population":0,
    "gn:timezone":"Europe/Paris",
    "iso:country":"FR",
    "name:ceb_x_preferred":[
        "Forges"
    ],
    "name:ces_x_preferred":[
        "Forges"
    ],
    "name:deu_x_preferred":[
        "Forges"
    ],
    "name:fra_x_preferred":[
        "Forges"
    ],
    "name:ita_x_preferred":[
        "Forges"
    ],
    "name:nds_x_preferred":[
        "Forges"
    ],
    "name:nld_x_preferred":[
        "Forges"
    ],
    "name:oci_x_preferred":[
        "Forges"
    ],
    "name:pms_x_preferred":[
        "Forges"
    ],
    "name:pol_x_preferred":[
        "Forges"
    ],
    "name:por_x_preferred":[
        "Forges"
    ],
    "name:rus_x_preferred":[
        "\u0424\u043e\u0440\u0436"
    ],
    "name:slk_x_preferred":[
        "Forges"
    ],
    "name:spa_x_preferred":[
        "Forges"
    ],
    "name:srp_x_preferred":[
        "\u0424\u043e\u0440\u0436"
    ],
    "name:swe_x_preferred":[
        "Forges"
    ],
    "name:ukr_x_preferred":[
        "\u0424\u043e\u0440\u0436"
    ],
    "wof:name":"Forges",
    "wof:placetype":"locality"
},
  "geometry": {"coordinates":[3.20333,47.48321],"type":"Point"}
}