{
  "type": "Feature",
  "properties": {
    "gn:admin1_code":"27",
    "gn:admin2_code":"58",
    "gn:admin3_code":"584",
    "gn:admin4_code":"58193",
    "gn:asciiname":"Gardefort",
    "gn:country_code":"FR",
    "gn:dem":172,
    "gn:feature_class":"P",
    "gn:feature_code":"PPL",
    "gn:name":"Gardefort",
    "gn:population":0,
    "gn:timezone":"Europe/Paris",
    "iso:country":"FR",
    "name:cat_x_preferred":[
        "Gardefort"
    ],
    "name:ceb_x_preferred":[
        "Gardefort"
    ],
    "name:deu_x_preferred":[
        "Gardefort"
    ],
    "name:eus_x_preferred":[
        "Gardefort"
    ],
    "name:fra_x_preferred":[
        "Gardefort"
    ],
    "name:hun_x_preferred":[
        "Gardefort"
    ],
    "name:ita_x_preferred":[
        "Gardefort"
    ],
    "name:lat_x_preferred":[
        "Gardefort"
    ],
    "name:msa_x_preferred":[
        "Gardefort"
    ],
    "name:nld_x_preferred":[
        "Gardefort"
    ],
    "name:oci_x_preferred":[
        "Gardefort"
    ],
    "name:pms_x_preferred":[
        "Gardefort"
    ],
    "name:pol_x_preferred":[
        "Gardefort"
    ],
    "name:por_x_preferred":[
        "Gardefort"
    ],
    "name:ron_x_preferred":[
        "Gardefort"
    ],
    "name:rus_x_preferred":[
        "\u0413\u0430\u0440\u0434\u0444\u043e\u0440"
    ],
    "name:slk_x_preferred":[
        "Gardefort"
    ],
    "name:spa_x_preferred":[
        "Gardefort"
    ],
    "name:swe_x_preferred":[
        "Gardefort"
    ],
    "name:ukr_x_preferred":[
        "\u0413\u0430\u0440\u0434\u0444\u043e\u0440"
    ],
    "name:uzb_x_preferred":[
        "Gardefort"
    ],
    "name:vie_x_preferred":[
        "Gardefort"
    ],
    "name:vol_x_preferred":[
        "Gardefort"
    ],
    "name:war_x_preferred":[
        "Gardefort"
    ],
    "name:zho_x_preferred":[
        "\u52a0\u5c14\u4ee3\u798f\u5c14"
    ],
    "wof:name":"Gardefort",
    "wof:placetype":"locality"
},
  "geometry": {"coordinates":[2.88638,47.53438],"type":"Point"}
}