{
  "type": "Feature",
  "properties": {
    "gn:admin1_code":"84",
    "gn:admin2_code":"43",
    "gn:admin3_code":"433",
    "gn:admin4_code":"43025",
    "gn:asciiname":"Les Vivas",
    "gn:country_code":"FR",
    "gn:dem":602,
    "gn:feature_class":"P",
    "gn:feature_code":"PPL",
    "gn:name":"Les Vivas",
    "gn:population":0,
    "gn:timezone":"Europe/Paris",
    "iso:country":"FR",
    "wof:name":"Les Vivas",
    "wof:placetype":"locality"
},
  "geometry": {"coordinates":[4.09077,45.25053],"type":"Point"}
}