{
  "type": "Feature",
  "properties": {
    "gn:admin1_code":"75",
    "gn:admin2_code":"24",
    "gn:admin3_code":"241",
    "gn:admin4_code":"24168",
    "gn:asciiname":"Maine-Chevalier",
    "gn:country_code":"FR",
    "gn:dem":118,
    "gn:feature_class":"P",
    "gn:feature_code":"PPL",
    "gn:name":"Maine-Chevalier",
    "gn:population":0,
    "gn:timezone":"Europe/Paris",
    "iso:country":"FR",
    "wof:name":"Maine-Chevalier",
    "wof:placetype":"locality"
},
  "geometry": {"coordinates":[0.53763,44.70092],"type":"Point"}
}