{
  "type": "Feature",
  "properties": {
    "gn:admin1_code":"53",
    "gn:admin2_code":"29",
    "gn:admin3_code":"291",
    "gn:admin4_code":"29124",
    "gn:asciiname":"Languengar",
    "gn:country_code":"FR",
    "gn:dem":52,
    "gn:feature_class":"P",
    "gn:feature_code":"PPL",
    "gn:name":"Languengar",
    "gn:population":0,
    "gn:timezone":"Europe/Paris",
    "iso:country":"FR",
    "wof:name":"Languengar",
    "wof:placetype":"locality"
},
  "geometry": {"coordinates":[-4.31667,48.58333],"type":"Point"}
}