{
  "type": "Feature",
  "properties": {
    "gn:admin1_code":"76",
    "gn:admin2_code":"81",
    "gn:admin3_code":"811",
    "gn:admin4_code":"81201",
    "gn:asciiname":"Teillet",
    "gn:country_code":"FR",
    "gn:dem":484,
    "gn:feature_class":"P",
    "gn:feature_code":"PPL",
    "gn:name":"Teillet",
    "gn:population":0,
    "gn:timezone":"Europe/Paris",
    "iso:country":"FR",
    "wof:name":"Teillet",
    "wof:placetype":"locality"
},
  "geometry": {"coordinates":[2.285,44.13666],"type":"Point"}
}