{
  "type": "Feature",
  "properties": {
    "gn:admin1_code":"24",
    "gn:admin2_code":"36",
    "gn:admin3_code":"363",
    "gn:admin4_code":"36164",
    "gn:asciiname":"Vaudouan",
    "gn:country_code":"FR",
    "gn:dem":290,
    "gn:feature_class":"P",
    "gn:feature_code":"PPL",
    "gn:name":"Vaudouan",
    "gn:population":0,
    "gn:timezone":"Europe/Paris",
    "iso:country":"FR",
    "wof:name":"Vaudouan",
    "wof:placetype":"locality"
},
  "geometry": {"coordinates":[1.98333,46.53333],"type":"Point"}
}