{
  "type": "Feature",
  "properties": {
    "gn:admin1_code":"76",
    "gn:admin2_code":"32",
    "gn:admin3_code":"323",
    "gn:admin4_code":"32403",
    "gn:asciiname":"Saint-Pierre-d'Aubezies",
    "gn:cc2":"FR",
    "gn:country_code":"FR",
    "gn:dem":200,
    "gn:feature_class":"P",
    "gn:feature_code":"PPL",
    "gn:name":"Saint-Pierre-d'Aub\u00e9zies",
    "gn:population":0,
    "gn:timezone":"Europe/Paris",
    "iso:country":"FR",
    "name:und_x_variant":[
        "Saint-Pierre"
    ],
    "wof:name":"Saint-Pierre-d'Aubezies",
    "wof:placetype":"locality"
},
  "geometry": {"coordinates":[0.16667,43.65],"type":"Point"}
}