{
  "type": "Feature",
  "properties": {
    "iso:country":"FR",
    "name:eng_x_preferred":[
        "Centre Ancien"
    ],
    "name:fra_x_preferred":[
        "Centre Ancien"
    ],
    "wof:name":"Centre Ancien",
    "wof:placetype":"neighbourhood"
},
  "geometry": {"coordinates":[2.46315145812701,48.79134044707089],"type":"Point"}
}