{
  "type": "Feature",
  "properties": {
    "gn:admin1_code":"24",
    "gn:admin2_code":"41",
    "gn:admin3_code":"413",
    "gn:admin4_code":"41176",
    "gn:asciiname":"Le Surgis",
    "gn:country_code":"FR",
    "gn:dem":122,
    "gn:feature_class":"P",
    "gn:feature_code":"PPL",
    "gn:name":"Le Surgis",
    "gn:population":0,
    "gn:timezone":"Europe/Paris",
    "iso:country":"FR",
    "wof:name":"Le Surgis",
    "wof:placetype":"locality"
},
  "geometry": {"coordinates":[2.15,47.51667],"type":"Point"}
}