{
  "type": "Feature",
  "properties": {
    "iso:country":"FR",
    "name:eng_x_preferred":[
        "Villejean-Beauregard"
    ],
    "name:fra_x_preferred":[
        "Villejean-Beauregard"
    ],
    "wof:name":"Villejean-Beauregard",
    "wof:placetype":"neighbourhood"
},
  "geometry": {"coordinates":[-1.71180298129124,48.12695648068222],"type":"Point"}
}