{
  "type": "Feature",
  "properties": {
    "gn:admin1_code":"28",
    "gn:admin2_code":"76",
    "gn:admin3_code":"761",
    "gn:admin4_code":"76459",
    "gn:asciiname":"Mare aux Daims",
    "gn:country_code":"FR",
    "gn:dem":241,
    "gn:feature_class":"P",
    "gn:feature_code":"PPL",
    "gn:name":"Mare aux Daims",
    "gn:population":0,
    "gn:timezone":"Europe/Paris",
    "iso:country":"FR",
    "name:und_x_variant":[
        "La Mare aux Daims",
        "Mare aux Daims"
    ],
    "wof:name":"Mare aux Daims",
    "wof:placetype":"locality"
},
  "geometry": {"coordinates":[1.53851,49.71203],"type":"Point"}
}