{
  "type": "Feature",
  "properties": {
    "gn:admin1_code":"84",
    "gn:admin2_code":"42",
    "gn:admin3_code":"421",
    "gn:admin4_code":"42291",
    "gn:asciiname":"Mayen",
    "gn:country_code":"FR",
    "gn:dem":703,
    "gn:feature_class":"P",
    "gn:feature_code":"PPL",
    "gn:name":"Mayen",
    "gn:population":0,
    "gn:timezone":"Europe/Paris",
    "iso:country":"FR",
    "name:ara_x_preferred":[
        "\u0645\u0627\u064a\u0646"
    ],
    "name:azb_x_preferred":[
        "\u0645\u0627\u06cc\u0646\u060c"
    ],
    "name:ceb_x_preferred":[
        "Mayen"
    ],
    "name:ces_x_preferred":[
        "Mayen"
    ],
    "name:deu_x_preferred":[
        "Mayen"
    ],
    "name:epo_x_preferred":[
        "Mayen"
    ],
    "name:fas_x_preferred":[
        "\u0645\u0627\u06cc\u0646"
    ],
    "name:fra_x_preferred":[
        "Mayen"
    ],
    "name:hun_x_preferred":[
        "Mayen"
    ],
    "name:ita_x_preferred":[
        "Mayen"
    ],
    "name:jpn_x_preferred":[
        "\u30de\u30a4\u30a8\u30f3"
    ],
    "name:msa_x_preferred":[
        "Mayen"
    ],
    "name:nld_x_preferred":[
        "Mayen"
    ],
    "name:pol_x_preferred":[
        "Mayen"
    ],
    "name:por_x_preferred":[
        "Mayen"
    ],
    "name:ron_x_preferred":[
        "Mayen"
    ],
    "name:rus_x_preferred":[
        "\u041c\u0430\u0439\u0435\u043d"
    ],
    "name:spa_x_preferred":[
        "Mayen"
    ],
    "name:srp_x_preferred":[
        "\u041c\u0430\u0458\u0435\u043d"
    ],
    "name:swa_x_preferred":[
        "Mayen"
    ],
    "name:swe_x_preferred":[
        "Mayen"
    ],
    "name:tur_x_preferred":[
        "Mayen"
    ],
    "name:ukr_x_preferred":[
        "\u041c\u0430\u0454\u043d"
    ],
    "name:uzb_x_preferred":[
        "Mayen"
    ],
    "name:vie_x_preferred":[
        "Mayen"
    ],
    "name:vol_x_preferred":[
        "Mayen"
    ],
    "name:war_x_preferred":[
        "Mayen"
    ],
    "wof:name":"Mayen",
    "wof:placetype":"locality"
},
  "geometry": {"coordinates":[3.87947,45.83049000000001],"type":"Point"}
}