{
  "type": "Feature",
  "properties": {
    "gn:admin1_code":"84",
    "gn:admin2_code":"42",
    "gn:admin3_code":"421",
    "gn:admin4_code":"42291",
    "gn:asciiname":"Mayen",
    "gn:country_code":"FR",
    "gn:dem":703,
    "gn:feature_class":"P",
    "gn:feature_code":"PPL",
    "gn:name":"Mayen",
    "gn:population":0,
    "gn:timezone":"Europe/Paris",
    "iso:country":"FR",
    "wof:name":"Mayen",
    "wof:placetype":"locality"
},
  "geometry": {"coordinates":[3.87947,45.83049000000001],"type":"Point"}
}