{
  "type": "Feature",
  "properties": {
    "gn:admin1_code":"24",
    "gn:admin2_code":"18",
    "gn:admin3_code":"181",
    "gn:admin4_code":"18033",
    "gn:asciiname":"Pisse Vieille",
    "gn:country_code":"FR",
    "gn:dem":159,
    "gn:feature_class":"P",
    "gn:feature_code":"PPL",
    "gn:name":"Pisse Vieille",
    "gn:population":0,
    "gn:timezone":"Europe/Paris",
    "iso:country":"FR",
    "wof:name":"Pisse Vieille",
    "wof:placetype":"locality"
},
  "geometry": {"coordinates":[2.33885,47.03762],"type":"Point"}
}