{
  "type": "Feature",
  "properties": {
    "gn:admin1_code":"75",
    "gn:admin2_code":"19",
    "gn:admin3_code":"192",
    "gn:admin4_code":"19091",
    "gn:asciiname":"Les Taules, Hautefage",
    "gn:country_code":"FR",
    "gn:dem":207,
    "gn:feature_class":"P",
    "gn:feature_code":"PPL",
    "gn:name":"Les Taules, Hautefage",
    "gn:population":0,
    "gn:timezone":"Europe/Paris",
    "iso:country":"FR",
    "wof:name":"Les Taules, Hautefage",
    "wof:placetype":"locality"
},
  "geometry": {"coordinates":[1.97713,45.06937],"type":"Point"}
}