{
  "type": "Feature",
  "properties": {
    "gn:admin1_code":"27",
    "gn:admin2_code":"89",
    "gn:admin3_code":"892",
    "gn:admin4_code":"89210",
    "gn:asciiname":"La Loge",
    "gn:country_code":"FR",
    "gn:dem":239,
    "gn:feature_class":"P",
    "gn:feature_code":"PPL",
    "gn:name":"La Loge",
    "gn:population":0,
    "gn:timezone":"Europe/Paris",
    "iso:country":"FR",
    "name:cat_x_preferred":[
        "La llotja"
    ],
    "name:fra_x_preferred":[
        "La Loge"
    ],
    "name:hye_x_preferred":[
        "\u0555\u0569\u0575\u0561\u056f"
    ],
    "name:ita_x_preferred":[
        "Il palco"
    ],
    "name:mal_x_preferred":[
        "\u0d32\u0d3e \u0d32\u0d4b\u0d17\u0d46"
    ],
    "name:msa_x_preferred":[
        "Kotak teater"
    ],
    "name:nld_x_preferred":[
        "De loge"
    ],
    "name:pol_x_preferred":[
        "Lo\u017ca"
    ],
    "name:por_x_preferred":[
        "L'avant-sc\u00e8ne"
    ],
    "name:rus_x_preferred":[
        "\u041b\u043e\u0436\u0430"
    ],
    "name:spa_x_preferred":[
        "El palco"
    ],
    "wof:name":"La Loge",
    "wof:placetype":"locality"
},
  "geometry": {"coordinates":[4.28978,47.78893],"type":"Point"}
}