{
  "type": "Feature",
  "properties": {
    "gn:admin1_code":"27",
    "gn:admin2_code":"89",
    "gn:admin3_code":"892",
    "gn:admin4_code":"89210",
    "gn:asciiname":"La Loge",
    "gn:country_code":"FR",
    "gn:dem":239,
    "gn:feature_class":"P",
    "gn:feature_code":"PPL",
    "gn:name":"La Loge",
    "gn:population":0,
    "gn:timezone":"Europe/Paris",
    "iso:country":"FR",
    "wof:name":"La Loge",
    "wof:placetype":"locality"
},
  "geometry": {"coordinates":[4.28978,47.78893],"type":"Point"}
}