{
  "type": "Feature",
  "properties": {
    "gn:admin1_code":"93",
    "gn:admin2_code":"83",
    "gn:admin3_code":"832",
    "gn:admin4_code":"83100",
    "gn:asciiname":"La Foux",
    "gn:country_code":"FR",
    "gn:dem":214,
    "gn:feature_class":"P",
    "gn:feature_code":"PPL",
    "gn:name":"La Foux",
    "gn:population":0,
    "gn:timezone":"Europe/Paris",
    "iso:country":"FR",
    "wof:name":"La Foux",
    "wof:placetype":"locality"
},
  "geometry": {"coordinates":[6.14315,43.29539000000001],"type":"Point"}
}