{
  "type": "Feature",
  "properties": {
    "iso:country":"FR",
    "name:eng_x_preferred":[
        "Le Parc de la Noue"
    ],
    "name:fra_x_preferred":[
        "Le Parc de la Noue"
    ],
    "wof:name":"Le Parc de la Noue",
    "wof:placetype":"neighbourhood"
},
  "geometry": {"coordinates":[2.53984530638481,48.95803663615182],"type":"Point"}
}