{
  "type": "Feature",
  "properties": {
    "gn:admin1_code":"76",
    "gn:admin2_code":"32",
    "gn:admin3_code":"322",
    "gn:admin4_code":"32369",
    "gn:asciiname":"Sainte-Christie-d'Armagnac",
    "gn:country_code":"FR",
    "gn:dem":117,
    "gn:feature_class":"P",
    "gn:feature_code":"PPL",
    "gn:name":"Sainte-Christie-d\u2019Armagnac",
    "gn:population":0,
    "gn:timezone":"Europe/Paris",
    "iso:country":"FR",
    "name:und_x_variant":[
        "Sainte-Christie",
        "Sainte-Christie-d\u2019Armagnac"
    ],
    "wof:name":"Sainte-Christie-d'Armagnac",
    "wof:placetype":"locality"
},
  "geometry": {"coordinates":[-0.00927,43.78461],"type":"Point"}
}