{
  "type": "Feature",
  "properties": {
    "gn:admin1_code":"76",
    "gn:admin2_code":"32",
    "gn:admin3_code":"322",
    "gn:admin4_code":"32369",
    "gn:asciiname":"Sainte-Christie-d'Armagnac",
    "gn:country_code":"FR",
    "gn:dem":117,
    "gn:feature_class":"P",
    "gn:feature_code":"PPL",
    "gn:name":"Sainte-Christie-d\u2019Armagnac",
    "gn:population":0,
    "gn:timezone":"Europe/Paris",
    "iso:country":"FR",
    "name:bug_x_preferred":[
        "Sainte-Christie-d'Armagnac"
    ],
    "name:ceb_x_preferred":[
        "Sainte-Christie-d'Armagnac"
    ],
    "name:eus_x_preferred":[
        "Sainte-Christie-d'Armagnac"
    ],
    "name:fra_x_preferred":[
        "Sainte-Christie-d'Armagnac"
    ],
    "name:hun_x_preferred":[
        "Sainte-Christie-d\u2019Armagnac"
    ],
    "name:ita_x_preferred":[
        "Sainte-Christie-d'Armagnac"
    ],
    "name:lat_x_preferred":[
        "Sainte-Christie-d'Armagnac"
    ],
    "name:mlg_x_preferred":[
        "Sainte-Christie-d'Armagnac"
    ],
    "name:msa_x_preferred":[
        "Sainte-Christie-d'Armagnac"
    ],
    "name:nld_x_preferred":[
        "Sainte-Christie-d'Armagnac"
    ],
    "name:pms_x_preferred":[
        "Sainte-Christie-d'Armagnac"
    ],
    "name:pol_x_preferred":[
        "Sainte-Christie-d\u2019Armagnac"
    ],
    "name:por_x_preferred":[
        "Sainte-Christie-d'Armagnac"
    ],
    "name:ron_x_preferred":[
        "Sainte-Christie-d'Armagnac"
    ],
    "name:rus_x_preferred":[
        "\u0421\u0435\u043d\u0442-\u041a\u0440\u0438\u0441\u0442\u0438-\u0434\u2019\u0410\u0440\u043c\u0430\u043d\u044c\u044f\u043a"
    ],
    "name:slk_x_preferred":[
        "Sainte-Christie-d\u2019Armagnac"
    ],
    "name:spa_x_preferred":[
        "Sainte-Christie-d'Armagnac"
    ],
    "name:swe_x_preferred":[
        "Sainte-Christie-d'Armagnac"
    ],
    "name:ukr_x_preferred":[
        "\u0421\u0435\u043d\u0442-\u041a\u0440\u0438\u0441\u0442\u0456-\u0434'\u0410\u0440\u043c\u0430\u043d\u044c\u044f\u043a"
    ],
    "name:und_x_variant":[
        "Sainte-Christie",
        "Sainte-Christie-d\u2019Armagnac"
    ],
    "name:urd_x_preferred":[
        "\u0633\u06cc\u0646-\u06a9\u0631\u0633\u0679\u06cc-\u062f\u0631\u0645\u06af\u0646\u0627\u06a9"
    ],
    "name:vie_x_preferred":[
        "Sainte-Christie-d'Armagnac"
    ],
    "name:vol_x_preferred":[
        "Sainte-Christie-d'Armagnac"
    ],
    "name:war_x_preferred":[
        "Sainte-Christie-d'Armagnac"
    ],
    "name:zho_x_preferred":[
        "\u5723\u514b\u91cc\u65af\u63d0\u8fbe\u5c14\u9a6c\u5c3c\u4e9a\u514b"
    ],
    "wof:name":"Sainte-Christie-d'Armagnac",
    "wof:placetype":"locality"
},
  "geometry": {"coordinates":[-0.00927,43.78461],"type":"Point"}
}