{
  "type": "Feature",
  "properties": {
    "gn:admin1_code":"52",
    "gn:admin2_code":"85",
    "gn:admin3_code":"853",
    "gn:admin4_code":"85113",
    "gn:asciiname":"Ker borny",
    "gn:country_code":"FR",
    "gn:dem":19,
    "gn:feature_class":"P",
    "gn:feature_code":"PPL",
    "gn:name":"Ker borny",
    "gn:population":0,
    "gn:timezone":"Europe/Paris",
    "iso:country":"FR",
    "wof:name":"Ker borny",
    "wof:placetype":"locality"
},
  "geometry": {"coordinates":[-2.36667,46.71667],"type":"Point"}
}