{
  "type": "Feature",
  "properties": {
    "gn:admin1_code":"52",
    "gn:admin2_code":"72",
    "gn:admin3_code":"722",
    "gn:admin4_code":"72144",
    "gn:asciiname":"Saint-Louis",
    "gn:country_code":"FR",
    "gn:dem":250,
    "gn:feature_class":"P",
    "gn:feature_code":"PPL",
    "gn:name":"Saint-Louis",
    "gn:population":0,
    "gn:timezone":"Europe/Paris",
    "iso:country":"FR",
    "name:ben_x_preferred":[
        "\u09b8\u09c7\u09a8\u09cd\u099f-\u09b2\u09c1\u0987\u09b8"
    ],
    "name:hun_x_preferred":[
        "Saint-Louis"
    ],
    "wof:name":"Saint-Louis",
    "wof:placetype":"locality"
},
  "geometry": {"coordinates":[0.85356,48.13799],"type":"Point"}
}