{
  "type": "Feature",
  "properties": {
    "gn:admin1_code":"75",
    "gn:admin2_code":"19",
    "gn:admin3_code":"191",
    "gn:admin4_code":"19049",
    "gn:asciiname":"Beaugou",
    "gn:country_code":"FR",
    "gn:dem":268,
    "gn:feature_class":"P",
    "gn:feature_code":"PPL",
    "gn:name":"Beaugou",
    "gn:population":0,
    "gn:timezone":"Europe/Paris",
    "iso:country":"FR",
    "wof:name":"Beaugou",
    "wof:placetype":"locality"
},
  "geometry": {"coordinates":[1.4336,45.0789],"type":"Point"}
}