{
  "type": "Feature",
  "properties": {
    "gn:admin1_code":"52",
    "gn:admin2_code":"49",
    "gn:admin3_code":"494",
    "gn:admin4_code":"49331",
    "gn:asciiname":"Les Hauts-Saint-Jean",
    "gn:country_code":"FR",
    "gn:dem":39,
    "gn:feature_class":"P",
    "gn:feature_code":"PPL",
    "gn:name":"Les Hauts-Saint-Jean",
    "gn:population":0,
    "gn:timezone":"Europe/Paris",
    "iso:country":"FR",
    "wof:name":"Les Hauts-Saint-Jean",
    "wof:placetype":"locality"
},
  "geometry": {"coordinates":[-0.86667,47.68333],"type":"Point"}
}