{
  "type": "Feature",
  "properties": {
    "gn:admin1_code":"76",
    "gn:admin2_code":"46",
    "gn:admin3_code":"462",
    "gn:admin4_code":"46311",
    "gn:asciiname":"Les Teuilleres",
    "gn:country_code":"FR",
    "gn:dem":569,
    "gn:feature_class":"P",
    "gn:feature_code":"PPL",
    "gn:name":"Les Teuill\u00e8res",
    "gn:population":0,
    "gn:timezone":"Europe/Paris",
    "iso:country":"FR",
    "wof:name":"Les Teuilleres",
    "wof:placetype":"locality"
},
  "geometry": {"coordinates":[2.04072,44.8343],"type":"Point"}
}