{
  "type": "Feature",
  "properties": {
    "gn:admin1_code":"93",
    "gn:admin2_code":"04",
    "gn:admin3_code":"043",
    "gn:admin4_code":"04167",
    "gn:asciiname":"Ainac",
    "gn:cc2":"FR",
    "gn:country_code":"FR",
    "gn:dem":1090,
    "gn:feature_class":"P",
    "gn:feature_code":"PPL",
    "gn:name":"Ainac",
    "gn:population":0,
    "gn:timezone":"Europe/Paris",
    "iso:country":"FR",
    "name:und_x_variant":[
        "Ainar",
        "Ainac"
    ],
    "wof:name":"Ainac",
    "wof:placetype":"locality"
},
  "geometry": {"coordinates":[6.21361,44.21226],"type":"Point"}
}