{
  "type": "Feature",
  "properties": {
    "gn:admin1_code":"75",
    "gn:admin2_code":"24",
    "gn:admin3_code":"244",
    "gn:admin4_code":"24087",
    "gn:asciiname":"La Boissiere",
    "gn:country_code":"FR",
    "gn:dem":149,
    "gn:feature_class":"P",
    "gn:feature_code":"PPL",
    "gn:name":"La Boissi\u00e8re",
    "gn:population":0,
    "gn:timezone":"Europe/Paris",
    "iso:country":"FR",
    "wof:name":"La Boissiere",
    "wof:placetype":"locality"
},
  "geometry": {"coordinates":[1.06566,44.8629],"type":"Point"}
}