{
  "type": "Feature",
  "properties": {
    "gn:admin1_code":"84",
    "gn:admin2_code":"73",
    "gn:admin3_code":"733",
    "gn:admin4_code":"73231",
    "gn:asciiname":"Le Monthion",
    "gn:cc2":"FR",
    "gn:country_code":"FR",
    "gn:dem":993,
    "gn:feature_class":"P",
    "gn:feature_code":"PPL",
    "gn:name":"Le Monthion",
    "gn:population":0,
    "gn:timezone":"Europe/Paris",
    "iso:country":"FR",
    "name:und_x_variant":[
        "Monthion",
        "Le Monthion"
    ],
    "wof:name":"Le Monthion",
    "wof:placetype":"locality"
},
  "geometry": {"coordinates":[6.26667,45.33333],"type":"Point"}
}