{
  "type": "Feature",
  "properties": {
    "gn:admin1_code":"84",
    "gn:admin2_code":"43",
    "gn:admin3_code":"432",
    "gn:admin4_code":"43039",
    "gn:asciiname":"Bessarioux",
    "gn:country_code":"FR",
    "gn:dem":990,
    "gn:feature_class":"P",
    "gn:feature_code":"PPL",
    "gn:name":"Bessarioux",
    "gn:population":0,
    "gn:timezone":"Europe/Paris",
    "iso:country":"FR",
    "wof:name":"Bessarioux",
    "wof:placetype":"locality"
},
  "geometry": {"coordinates":[3.8674,44.90338],"type":"Point"}
}