{
  "type": "Feature",
  "properties": {
    "gn:admin1_code":"75",
    "gn:admin2_code":"19",
    "gn:admin3_code":"192",
    "gn:admin4_code":"19100",
    "gn:asciiname":"Chapou",
    "gn:country_code":"FR",
    "gn:dem":460,
    "gn:feature_class":"P",
    "gn:feature_code":"PPL",
    "gn:name":"Chapou",
    "gn:population":0,
    "gn:timezone":"Europe/Paris",
    "iso:country":"FR",
    "wof:name":"Chapou",
    "wof:placetype":"locality"
},
  "geometry": {"coordinates":[1.63629,45.36512000000001],"type":"Point"}
}