{
  "type": "Feature",
  "properties": {
    "iso:country":"FR",
    "name:eng_x_preferred":[
        "La Touche"
    ],
    "name:fra_x_preferred":[
        "La Touche"
    ],
    "wof:name":"La Touche",
    "wof:placetype":"neighbourhood"
},
  "geometry": {"coordinates":[-1.69091750325338,48.11641394796571],"type":"Point"}
}