{
  "type": "Feature",
  "properties": {
    "gn:admin1_code":"76",
    "gn:admin2_code":"66",
    "gn:admin3_code":"662",
    "gn:admin4_code":"66127",
    "gn:asciiname":"Perillos",
    "gn:country_code":"FR",
    "gn:dem":388,
    "gn:feature_class":"P",
    "gn:feature_code":"PPL",
    "gn:name":"P\u00e9rillos",
    "gn:population":0,
    "gn:timezone":"Europe/Paris",
    "iso:country":"FR",
    "name:cat_x_preferred":[
        "Perell\u00f3s"
    ],
    "name:fra_x_preferred":[
        "P\u00e9rillos"
    ],
    "name:und_x_variant":[
        "P\u00e9rillos"
    ],
    "wof:name":"Perillos",
    "wof:placetype":"locality"
},
  "geometry": {"coordinates":[2.84662,42.89706],"type":"Point"}
}