{
  "type": "Feature",
  "properties": {
    "gn:admin1_code":"94",
    "gn:admin2_code":"2B",
    "gn:admin3_code":"2B3",
    "gn:admin4_code":"2B277",
    "gn:asciiname":"Serracinella",
    "gn:country_code":"FR",
    "gn:dem":12,
    "gn:feature_class":"P",
    "gn:feature_code":"PPL",
    "gn:name":"Serracinella",
    "gn:population":0,
    "gn:timezone":"Europe/Paris",
    "iso:country":"FR",
    "wof:name":"Serracinella",
    "wof:placetype":"locality"
},
  "geometry": {"coordinates":[9.38333,41.98333],"type":"Point"}
}