{
  "type": "Feature",
  "properties": {
    "gn:admin1_code":"84",
    "gn:admin2_code":"63",
    "gn:admin3_code":"632",
    "gn:admin4_code":"63450",
    "gn:asciiname":"Chatonnier",
    "gn:country_code":"FR",
    "gn:dem":746,
    "gn:feature_class":"P",
    "gn:feature_code":"PPL",
    "gn:name":"Chatonnier",
    "gn:population":0,
    "gn:timezone":"Europe/Paris",
    "iso:country":"FR",
    "wof:name":"Chatonnier",
    "wof:placetype":"locality"
},
  "geometry": {"coordinates":[2.51411,45.72629000000001],"type":"Point"}
}