{
  "type": "Feature",
  "properties": {
    "gn:admin1_code":"11",
    "gn:admin2_code":"94",
    "gn:admin3_code":"941",
    "gn:admin4_code":"94054",
    "gn:asciiname":"Grignon",
    "gn:country_code":"FR",
    "gn:dem":81,
    "gn:feature_class":"P",
    "gn:feature_code":"PPL",
    "gn:name":"Grignon",
    "gn:population":0,
    "gn:timezone":"Europe/Paris",
    "iso:country":"FR",
    "name:ceb_x_preferred":[
        "Grignon"
    ],
    "name:deu_x_preferred":[
        "Grignon"
    ],
    "name:fra_x_preferred":[
        "Grignon"
    ],
    "name:ita_x_preferred":[
        "Grignon"
    ],
    "name:nds_x_preferred":[
        "Grignon"
    ],
    "name:nld_x_preferred":[
        "Grignon"
    ],
    "name:oci_x_preferred":[
        "Grignon"
    ],
    "name:pol_x_preferred":[
        "Grignon"
    ],
    "name:rus_x_preferred":[
        "\u0413\u0440\u0438\u043d\u044c\u043e\u043d"
    ],
    "name:slk_x_preferred":[
        "Grignon"
    ],
    "name:spa_x_preferred":[
        "Grignon"
    ],
    "name:swe_x_preferred":[
        "Grignon"
    ],
    "name:ukr_x_preferred":[
        "\u0413\u0440\u0438\u043d\u044c\u043e\u043d"
    ],
    "wof:name":"Grignon",
    "wof:placetype":"locality"
},
  "geometry": {"coordinates":[2.39276,48.7507],"type":"Point"}
}