{
  "type": "Feature",
  "properties": {
    "gn:admin1_code":"76",
    "gn:admin2_code":"12",
    "gn:admin3_code":"123",
    "gn:admin4_code":"12089",
    "gn:asciiname":"Saint-Michel",
    "gn:country_code":"FR",
    "gn:dem":274,
    "gn:feature_class":"P",
    "gn:feature_code":"PPL",
    "gn:name":"Saint-Michel",
    "gn:population":0,
    "gn:timezone":"Europe/Paris",
    "iso:country":"FR",
    "wof:name":"Saint-Michel",
    "wof:placetype":"locality"
},
  "geometry": {"coordinates":[2.27606,44.56192],"type":"Point"}
}