{
  "type": "Feature",
  "properties": {
    "gn:admin1_code":"32",
    "gn:admin2_code":"60",
    "gn:admin3_code":"601",
    "gn:admin4_code":"60405",
    "gn:asciiname":"La Neuville",
    "gn:country_code":"FR",
    "gn:dem":215,
    "gn:feature_class":"P",
    "gn:feature_code":"PPL",
    "gn:name":"La Neuville",
    "gn:population":0,
    "gn:timezone":"Europe/Paris",
    "iso:country":"FR",
    "name:deu_x_preferred":[
        "La Neuville"
    ],
    "name:nld_x_preferred":[
        "La Neuville"
    ],
    "name:und_x_variant":[
        "La Neuville Moliens",
        "La Neuville"
    ],
    "wof:name":"La Neuville",
    "wof:placetype":"locality"
},
  "geometry": {"coordinates":[1.81391,49.67842],"type":"Point"}
}