{
  "type": "Feature",
  "properties": {
    "gn:admin1_code":"75",
    "gn:admin2_code":"23",
    "gn:admin3_code":"231",
    "gn:admin4_code":"23134",
    "gn:asciiname":"Chatain",
    "gn:country_code":"FR",
    "gn:dem":605,
    "gn:feature_class":"P",
    "gn:feature_code":"PPL",
    "gn:name":"Chatain",
    "gn:population":0,
    "gn:timezone":"Europe/Paris",
    "iso:country":"FR",
    "wof:name":"Chatain",
    "wof:placetype":"locality"
},
  "geometry": {"coordinates":[1.94482,45.88822],"type":"Point"}
}