{
  "type": "Feature",
  "properties": {
    "gn:admin1_code":"75",
    "gn:admin2_code":"23",
    "gn:admin3_code":"231",
    "gn:admin4_code":"23134",
    "gn:asciiname":"Chatain",
    "gn:country_code":"FR",
    "gn:dem":605,
    "gn:feature_class":"P",
    "gn:feature_code":"PPL",
    "gn:name":"Chatain",
    "gn:population":0,
    "gn:timezone":"Europe/Paris",
    "iso:country":"FR",
    "name:cat_x_preferred":[
        "Chatain"
    ],
    "name:ceb_x_preferred":[
        "Chatain"
    ],
    "name:deu_x_preferred":[
        "Chatain"
    ],
    "name:eus_x_preferred":[
        "Chatain"
    ],
    "name:fra_x_preferred":[
        "Chatain"
    ],
    "name:hun_x_preferred":[
        "Chatain"
    ],
    "name:ita_x_preferred":[
        "Chatain"
    ],
    "name:lat_x_preferred":[
        "Castanea"
    ],
    "name:mlg_x_preferred":[
        "Chatain"
    ],
    "name:msa_x_preferred":[
        "Chatain"
    ],
    "name:nld_x_preferred":[
        "Chatain"
    ],
    "name:oci_x_preferred":[
        "Chastanh"
    ],
    "name:pms_x_preferred":[
        "Chatain"
    ],
    "name:pol_x_preferred":[
        "Chatain"
    ],
    "name:por_x_preferred":[
        "Chatain"
    ],
    "name:ron_x_preferred":[
        "Chatain"
    ],
    "name:slk_x_preferred":[
        "Chatain"
    ],
    "name:spa_x_preferred":[
        "Chatain"
    ],
    "name:srp_x_preferred":[
        "\u0428\u0430\u0442\u0435\u043d"
    ],
    "name:swe_x_preferred":[
        "Chatain"
    ],
    "name:ukr_x_preferred":[
        "\u0428\u0430\u0442\u0435\u043d"
    ],
    "name:vie_x_preferred":[
        "Chatain"
    ],
    "name:vol_x_preferred":[
        "Chatain"
    ],
    "name:war_x_preferred":[
        "Chatain"
    ],
    "wof:name":"Chatain",
    "wof:placetype":"locality"
},
  "geometry": {"coordinates":[1.94482,45.88822],"type":"Point"}
}