{
  "type": "Feature",
  "properties": {
    "gn:admin1_code":"84",
    "gn:admin2_code":"38",
    "gn:admin3_code":"382",
    "gn:admin4_code":"38172",
    "gn:asciiname":"Alliat",
    "gn:country_code":"FR",
    "gn:dem":425,
    "gn:feature_class":"P",
    "gn:feature_code":"PPL",
    "gn:name":"Alliat",
    "gn:population":0,
    "gn:timezone":"Europe/Paris",
    "iso:country":"FR",
    "name:bug_x_preferred":[
        "Alliat"
    ],
    "name:cat_x_preferred":[
        "Aliat"
    ],
    "name:ceb_x_preferred":[
        "Alliat"
    ],
    "name:eus_x_preferred":[
        "Aliat"
    ],
    "name:fas_x_preferred":[
        "\u0622\u0644\u06cc\u0627"
    ],
    "name:fra_x_preferred":[
        "Alliat"
    ],
    "name:hun_x_preferred":[
        "Alliat"
    ],
    "name:hye_x_preferred":[
        "\u0531\u056c\u056b\u0561"
    ],
    "name:ita_x_preferred":[
        "Alliat"
    ],
    "name:lat_x_preferred":[
        "Alliat"
    ],
    "name:mlg_x_preferred":[
        "Alliat"
    ],
    "name:msa_x_preferred":[
        "Alliat"
    ],
    "name:nld_x_preferred":[
        "Alliat"
    ],
    "name:oci_x_preferred":[
        "Aliat"
    ],
    "name:pol_x_preferred":[
        "Alliat"
    ],
    "name:por_x_preferred":[
        "Alliat"
    ],
    "name:ron_x_preferred":[
        "Alliat"
    ],
    "name:rus_x_preferred":[
        "\u0410\u043b\u044c\u044f"
    ],
    "name:slk_x_preferred":[
        "Alliat"
    ],
    "name:spa_x_preferred":[
        "Alliat"
    ],
    "name:srp_x_preferred":[
        "\u0410\u043b\u0438\u0458\u0430"
    ],
    "name:swe_x_preferred":[
        "Alliat"
    ],
    "name:ukr_x_preferred":[
        "\u0410\u043b\u044c\u044f\u0442"
    ],
    "name:urd_x_preferred":[
        "\u0622\u0644\u06cc\u0627"
    ],
    "name:vie_x_preferred":[
        "Alliat"
    ],
    "name:vol_x_preferred":[
        "Alliat"
    ],
    "name:war_x_preferred":[
        "Alliat"
    ],
    "name:zho_x_preferred":[
        "\u963f\u5229\u963f"
    ],
    "wof:name":"Alliat",
    "wof:placetype":"locality"
},
  "geometry": {"coordinates":[5.1863,45.56762],"type":"Point"}
}