{
  "type": "Feature",
  "properties": {
    "iso:country":"FR",
    "name:eng_x_preferred":[
        "Abbay-Jouhaux"
    ],
    "name:fra_x_preferred":[
        "Abbay-Jouhaux"
    ],
    "wof:name":"Abbay-Jouhaux",
    "wof:placetype":"neighbourhood"
},
  "geometry": {"coordinates":[5.74515839433011,45.18115848401806],"type":"Point"}
}