{
  "type": "Feature",
  "properties": {
    "gn:admin1_code":"75",
    "gn:admin2_code":"23",
    "gn:admin3_code":"232",
    "gn:admin4_code":"23022",
    "gn:asciiname":"Tournessac",
    "gn:country_code":"FR",
    "gn:dem":285,
    "gn:feature_class":"P",
    "gn:feature_code":"PPL",
    "gn:name":"Tournessac",
    "gn:population":0,
    "gn:timezone":"Europe/Paris",
    "iso:country":"FR",
    "wof:name":"Tournessac",
    "wof:placetype":"locality"
},
  "geometry": {"coordinates":[2.05466,46.34331],"type":"Point"}
}