{
  "type": "Feature",
  "properties": {
    "gn:admin1_code":"24",
    "gn:admin2_code":"37",
    "gn:admin3_code":"373",
    "gn:admin4_code":"37064",
    "gn:asciiname":"Le Carroi",
    "gn:country_code":"FR",
    "gn:dem":80,
    "gn:feature_class":"P",
    "gn:feature_code":"PPL",
    "gn:name":"Le Carroi",
    "gn:population":0,
    "gn:timezone":"Europe/Paris",
    "iso:country":"FR",
    "name:und_x_variant":[
        "Le Carro",
        "Le Carroi"
    ],
    "wof:name":"Le Carroi",
    "wof:placetype":"locality"
},
  "geometry": {"coordinates":[0.84428,46.86898],"type":"Point"}
}