{
  "type": "Feature",
  "properties": {
    "gn:admin1_code":"75",
    "gn:admin2_code":"87",
    "gn:admin3_code":"872",
    "gn:admin4_code":"87077",
    "gn:asciiname":"Chamessouze",
    "gn:country_code":"FR",
    "gn:dem":394,
    "gn:feature_class":"P",
    "gn:feature_code":"PPL",
    "gn:name":"Chamessouze",
    "gn:population":0,
    "gn:timezone":"Europe/Paris",
    "iso:country":"FR",
    "name:und_x_variant":[
        "Chamessouse",
        "Chamessouze"
    ],
    "wof:name":"Chamessouze",
    "wof:placetype":"locality"
},
  "geometry": {"coordinates":[1.20814,45.6528],"type":"Point"}
}