{
  "type": "Feature",
  "properties": {
    "frgov:code_epci":"200067841",
    "frgov:insee_arr":"4",
    "frgov:insee_com":"67396",
    "frgov:insee_dep":"67",
    "frgov:insee_reg":"44",
    "frgov:nom_com":"Rexingen",
    "frgov:nom_com_m":"REXINGEN",
    "frgov:nom_dep":"BAS-RHIN",
    "frgov:nom_reg":"GRAND EST",
    "frgov:statut":"Commune simple",
    "gn:admin1_code":"44",
    "gn:admin2_code":"67",
    "gn:admin3_code":"674",
    "gn:admin4_code":"67396",
    "gn:asciiname":"Rexingen",
    "gn:country_code":"FR",
    "gn:dem":252,
    "gn:feature_class":"P",
    "gn:feature_code":"PPL",
    "gn:name":"Rexingen",
    "gn:population":0,
    "gn:timezone":"Europe/Paris",
    "iso:country":"FR",
    "name:ara_x_preferred":[
        "\u0631\u064a\u0643\u0633\u064a\u0646\u063a\u064a\u0646"
    ],
    "name:deu_x_preferred":[
        "Rexingen"
    ],
    "name:fra_x_preferred":[
        "Rexingen"
    ],
    "name:kaz_x_preferred":[
        "\u0420\u0435\u043a\u0441\u0438\u043d\u0433\u0435\u043d"
    ],
    "name:pfl_x_preferred":[
        "Rexinge"
    ],
    "name:rus_x_preferred":[
        "\u0420\u0435\u043a\u0441\u0438\u043d\u0433\u0435\u043d"
    ],
    "name:ukr_x_preferred":[
        "\u0420\u0435\u043a\u0441\u0456\u043d\u0433\u0435\u043d"
    ],
    "name:zho_x_preferred":[
        "\u52d2\u514b\u6851\u8ba9"
    ],
    "qs:a0":"France",
    "qs:a1":"BAS-RHIN",
    "qs:a1_lc":"67",
    "qs:a1r":"ALSACE",
    "qs:a1r_lc":"42",
    "qs:a2_lc":"06",
    "qs:a2r_lc":"4",
    "qs:adm0":"France",
    "qs:adm0_a3":"FRA",
    "qs:la":"REXINGEN",
    "qs:la_lc":"67396",
    "qs:level":"localadmin",
    "qs:type":"Commune simple",
    "wof:coterminous":[
        404388205
    ],
    "wof:name":"Rexingen",
    "wof:placetype":"locality",
    "wof:placetype_local":"Commune simple"
},
  "geometry": {"coordinates":[7.18,48.9],"type":"Point"}
}