{
  "type": "Feature",
  "properties": {
    "gn:admin1_code":"53",
    "gn:admin2_code":"29",
    "gn:admin3_code":"293",
    "gn:admin4_code":"29251",
    "gn:asciiname":"Croazic",
    "gn:country_code":"FR",
    "gn:dem":80,
    "gn:feature_class":"P",
    "gn:feature_code":"PPL",
    "gn:name":"Croazic",
    "gn:population":0,
    "gn:timezone":"Europe/Paris",
    "iso:country":"FR",
    "wof:name":"Croazic",
    "wof:placetype":"locality"
},
  "geometry": {"coordinates":[-3.75,48.68333],"type":"Point"}
}