{
  "type": "Feature",
  "properties": {
    "gn:admin1_code":"84",
    "gn:admin2_code":"03",
    "gn:admin3_code":"031",
    "gn:admin4_code":"03305",
    "gn:asciiname":"Mirebeau",
    "gn:country_code":"FR",
    "gn:dem":374,
    "gn:feature_class":"P",
    "gn:feature_code":"PPL",
    "gn:name":"Mirebeau",
    "gn:population":0,
    "gn:timezone":"Europe/Paris",
    "iso:country":"FR",
    "name:und_x_variant":[
        "Mirbaud",
        "Mirebeau"
    ],
    "wof:name":"Mirebeau",
    "wof:placetype":"locality"
},
  "geometry": {"coordinates":[2.67696,46.414],"type":"Point"}
}