{
  "type": "Feature",
  "properties": {
    "gn:admin1_code":"84",
    "gn:admin2_code":"03",
    "gn:admin3_code":"031",
    "gn:admin4_code":"03305",
    "gn:asciiname":"Mirebeau",
    "gn:country_code":"FR",
    "gn:dem":374,
    "gn:feature_class":"P",
    "gn:feature_code":"PPL",
    "gn:name":"Mirebeau",
    "gn:population":0,
    "gn:timezone":"Europe/Paris",
    "iso:country":"FR",
    "name:cat_x_preferred":[
        "Mirebeau"
    ],
    "name:ceb_x_preferred":[
        "Mirebeau"
    ],
    "name:deu_x_preferred":[
        "Mirebeau"
    ],
    "name:eus_x_preferred":[
        "Mirebeau"
    ],
    "name:fra_x_preferred":[
        "Mirebeau"
    ],
    "name:hun_x_preferred":[
        "Mirebeau"
    ],
    "name:ita_x_preferred":[
        "Mirebeau"
    ],
    "name:lat_x_preferred":[
        "Mirabellum"
    ],
    "name:mlg_x_preferred":[
        "Mirebeau"
    ],
    "name:msa_x_preferred":[
        "Mirebeau"
    ],
    "name:nld_x_preferred":[
        "Mirebeau"
    ],
    "name:oci_x_preferred":[
        "Mirebeau"
    ],
    "name:pms_x_preferred":[
        "Mirebeau"
    ],
    "name:pol_x_preferred":[
        "Mirebeau"
    ],
    "name:por_x_preferred":[
        "Mirebeau"
    ],
    "name:ron_x_preferred":[
        "Mirebeau"
    ],
    "name:slk_x_preferred":[
        "Mirebeau"
    ],
    "name:spa_x_preferred":[
        "Mirebeau"
    ],
    "name:swe_x_preferred":[
        "Mirebeau"
    ],
    "name:ukr_x_preferred":[
        "\u041c\u0456\u0440\u0431\u043e"
    ],
    "name:und_x_variant":[
        "Mirbaud",
        "Mirebeau"
    ],
    "name:vie_x_preferred":[
        "Mirebeau"
    ],
    "name:vol_x_preferred":[
        "Mirebeau"
    ],
    "name:war_x_preferred":[
        "Mirebeau"
    ],
    "name:zho_x_preferred":[
        "\u7c73\u5c14\u535a"
    ],
    "wof:name":"Mirebeau",
    "wof:placetype":"locality"
},
  "geometry": {"coordinates":[2.67696,46.414],"type":"Point"}
}