{
  "type": "Feature",
  "properties": {
    "gn:country":"FR",
    "gn:fcode":"PPL",
    "gn:population":0,
    "iso:country":"FR",
    "qs_pg:aaroncc":"FR",
    "qs_pg:gn_country":"FR",
    "qs_pg:gn_fcode":"PPL",
    "qs_pg:gn_pop":0,
    "qs_pg:name":"Les Huguets",
    "qs_pg:name_adm0":"France",
    "qs_pg:name_adm1":"Provence-Alpes-C\u00f4te d'Azur",
    "qs_pg:photos":128,
    "qs_pg:photos_1k":26,
    "qs_pg:photos_9k":1,
    "qs_pg:photos_9r":3,
    "qs_pg:photos_all":128,
    "qs_pg:photos_sr":3,
    "qs_pg:pop_sr":0,
    "qs_pg:qs_pg_placetype":"locality",
    "qs_pg:qs_pg_placetype_gp":"Town",
    "qs_pg:woe_adm0":23424819,
    "woe:adm0_id":23424819,
    "woe:name_adm0":"France",
    "woe:name_adm1":"Provence-Alpes-C\u00f4te d'Azur",
    "woe:placetype":"Town",
    "wof:name":"Les Huguets",
    "wof:placetype":"neighbourhood"
},
  "geometry": {"coordinates":[5.35,43.88333],"type":"Point"}
}