{
  "type": "Feature",
  "properties": {
    "gn:admin1_code":"75",
    "gn:admin2_code":"47",
    "gn:admin3_code":"474",
    "gn:admin4_code":"47097",
    "gn:asciiname":"Limon",
    "gn:country_code":"FR",
    "gn:dem":135,
    "gn:feature_class":"P",
    "gn:feature_code":"PPL",
    "gn:name":"Limon",
    "gn:population":0,
    "gn:timezone":"Europe/Paris",
    "iso:country":"FR",
    "wof:name":"Limon",
    "wof:placetype":"locality"
},
  "geometry": {"coordinates":[0.35119,44.19465],"type":"Point"}
}