{
  "type": "Feature",
  "properties": {
    "gn:admin1_code":"75",
    "gn:admin2_code":"47",
    "gn:admin3_code":"474",
    "gn:admin4_code":"47097",
    "gn:asciiname":"Limon",
    "gn:country_code":"FR",
    "gn:dem":135,
    "gn:feature_class":"P",
    "gn:feature_code":"PPL",
    "gn:name":"Limon",
    "gn:population":0,
    "gn:timezone":"Europe/Paris",
    "iso:country":"FR",
    "name:bre_x_preferred":[
        "Limon"
    ],
    "name:bul_x_preferred":[
        "\u041b\u0438\u043c\u043e\u043d"
    ],
    "name:ceb_x_preferred":[
        "Limon"
    ],
    "name:fra_x_preferred":[
        "Limon"
    ],
    "name:heb_x_preferred":[
        "\u05dc\u05d9\u05de\u05d5\u05df"
    ],
    "name:ita_x_preferred":[
        "Limon"
    ],
    "name:lmo_x_preferred":[
        "Limon"
    ],
    "name:nld_x_preferred":[
        "Limon"
    ],
    "name:oci_x_preferred":[
        "Limon"
    ],
    "name:pms_x_preferred":[
        "Limon"
    ],
    "name:pol_x_preferred":[
        "Limon"
    ],
    "name:srp_x_preferred":[
        "\u041b\u0438\u043c\u043e\u043d"
    ],
    "name:swe_x_preferred":[
        "Limon"
    ],
    "name:tur_x_preferred":[
        "Limon"
    ],
    "wof:name":"Limon",
    "wof:placetype":"locality"
},
  "geometry": {"coordinates":[0.35119,44.19465],"type":"Point"}
}