{
  "type": "Feature",
  "properties": {
    "gn:admin1_code":"27",
    "gn:admin2_code":"89",
    "gn:admin3_code":"891",
    "gn:admin4_code":"89405",
    "gn:asciiname":"Le Suchois",
    "gn:country_code":"FR",
    "gn:dem":339,
    "gn:feature_class":"P",
    "gn:feature_code":"PPL",
    "gn:name":"Le Suchois",
    "gn:population":0,
    "gn:timezone":"Europe/Paris",
    "iso:country":"FR",
    "name:und_x_variant":[
        "Suchois",
        "Le Suchois"
    ],
    "wof:name":"Le Suchois",
    "wof:placetype":"locality"
},
  "geometry": {"coordinates":[3.46144,47.62306],"type":"Point"}
}