{
  "type": "Feature",
  "properties": {
    "iso:country":"FR",
    "name:fra_x_preferred":[
        "Bordeaux Nord"
    ],
    "qs:gn_adm0_cc":"FR",
    "qs:gn_local":3031582,
    "qs:local_max":18345,
    "qs:local_sum":32225,
    "qs:localhoods":10,
    "qs:name":"Bordeaux Nord",
    "qs:name_adm0":"France",
    "qs:name_adm1":"Aquitaine",
    "qs:name_adm2":"Gironde",
    "qs:name_lau":"Bordeaux",
    "qs:name_local":"Bordeaux",
    "qs:photo_max":170,
    "qs:photo_sum":306,
    "qs:placetype":"Suburb",
    "qs:quad_count":13,
    "qs:woe_adm0":23424819,
    "qs:woe_adm1":7153309,
    "qs:woe_adm2":12597132,
    "qs:woe_lau":20074993,
    "qs:woe_local":580778,
    "qs:woe_ver":"7.10.0",
    "wof:lang":[
        "fre"
    ],
    "wof:name":"Bordeaux Maritime",
    "wof:placetype":"neighbourhood"
},
  "geometry": {"coordinates":[-0.556768,44.885758],"type":"Point"}
}