{
  "type": "Feature",
  "properties": {
    "gn:admin1_code":"84",
    "gn:admin2_code":"42",
    "gn:admin3_code":"421",
    "gn:admin4_code":"42159",
    "gn:asciiname":"Verine",
    "gn:country_code":"FR",
    "gn:dem":874,
    "gn:feature_class":"P",
    "gn:feature_code":"PPL",
    "gn:name":"V\u00e9rine",
    "gn:population":0,
    "gn:timezone":"Europe/Paris",
    "iso:country":"FR",
    "wof:name":"Verine",
    "wof:placetype":"locality"
},
  "geometry": {"coordinates":[3.73834,45.80227],"type":"Point"}
}