{
  "type": "Feature",
  "properties": {
    "iso:country":"FR",
    "name:eng_x_preferred":[
        "Le Plateau"
    ],
    "name:fra_x_preferred":[
        "Le Plateau"
    ],
    "wof:name":"Le Plateau",
    "wof:placetype":"neighbourhood"
},
  "geometry": {"coordinates":[2.53591615882571,48.89706206145264],"type":"Point"}
}