{
  "type": "Feature",
  "properties": {
    "gn:admin1_code":"93",
    "gn:admin2_code":"04",
    "gn:admin3_code":"041",
    "gn:admin4_code":"04226",
    "gn:asciiname":"Uvernet-Fours",
    "gn:country_code":"FR",
    "gn:dem":1180,
    "gn:feature_class":"P",
    "gn:feature_code":"PPL",
    "gn:name":"Uvernet-Fours",
    "gn:population":0,
    "gn:timezone":"Europe/Paris",
    "iso:country":"FR",
    "name:cat_x_preferred":[
        "Uvernet e Forns"
    ],
    "name:oci_x_preferred":[
        "Uvernet e Forns"
    ],
    "name:rus_x_preferred":[
        "\u042e\u0432\u0435\u0440\u043d\u0435-\u0424\u0443\u0440"
    ],
    "name:ukr_x_preferred":[
        "\u042e\u0432\u0435\u0440\u043d\u0435-\u0424\u0443\u0440"
    ],
    "name:zho_x_preferred":[
        "\u4e8e\u97e6\u5c14\u5185\u5bcc\u5c14"
    ],
    "wof:name":"Uvernet-Fours",
    "wof:placetype":"locality"
},
  "geometry": {"coordinates":[6.62694,44.36194],"type":"Point"}
}