{
  "type": "Feature",
  "properties": {
    "gn:admin1_code":"53",
    "gn:admin2_code":"29",
    "gn:admin3_code":"293",
    "gn:admin4_code":"29079",
    "gn:asciiname":"Kergestin",
    "gn:country_code":"FR",
    "gn:dem":51,
    "gn:feature_class":"P",
    "gn:feature_code":"PPL",
    "gn:name":"Kergestin",
    "gn:population":0,
    "gn:timezone":"Europe/Paris",
    "iso:country":"FR",
    "wof:name":"Kergestin",
    "wof:placetype":"locality"
},
  "geometry": {"coordinates":[-3.94266,48.62055],"type":"Point"}
}