{
  "type": "Feature",
  "properties": {
    "gn:gn_country":"FR",
    "gn:gn_fcode":"PPL",
    "gn:gn_pop":0,
    "iso:country":"FR",
    "name:unk_x_variant":[
        "Les Arcs 1800"
    ],
    "qs_pg:aaroncc":"FR",
    "qs_pg:gn_country":"FR",
    "qs_pg:gn_fcode":"PPL",
    "qs_pg:gn_pop":0,
    "qs_pg:name":"Arc 1800",
    "qs_pg:name_adm0":"France",
    "qs_pg:name_adm1":"Rh\u00f4ne-Alpes",
    "qs_pg:photos":731,
    "qs_pg:photos_1k":148,
    "qs_pg:photos_9k":3,
    "qs_pg:photos_9r":5,
    "qs_pg:photos_all":731,
    "qs_pg:photos_sr":8,
    "qs_pg:pop_sr":0,
    "qs_pg:qs_pg_placetype":"locality",
    "qs_pg:qs_pg_placetype_gp":"Town",
    "qs_pg:woe_adm0":23424819,
    "woe:adm0_id":23424819,
    "woe:name_adm0":"France",
    "woe:name_adm1":"Rh\u00f4ne-Alpes",
    "woe:placetype":"Town",
    "wof:name":"Arc 1800",
    "wof:placetype":"neighbourhood"
},
  "geometry": {"coordinates":[6.78165,45.57755],"type":"Point"}
}