{
  "type": "Feature",
  "properties": {
    "gn:admin1_code":"28",
    "gn:admin2_code":"76",
    "gn:admin3_code":"761",
    "gn:admin4_code":"76749",
    "gn:asciiname":"Le Hamel",
    "gn:country_code":"FR",
    "gn:dem":60,
    "gn:feature_class":"P",
    "gn:feature_code":"PPL",
    "gn:name":"Le Hamel",
    "gn:population":0,
    "gn:timezone":"Europe/Paris",
    "iso:country":"FR",
    "name:ceb_x_preferred":[
        "Le Hamel"
    ],
    "name:deu_x_preferred":[
        "Le Hamel"
    ],
    "name:fra_x_preferred":[
        "Le Hamel"
    ],
    "name:ita_x_preferred":[
        "Le Hamel"
    ],
    "name:nds_x_preferred":[
        "Le Hamel"
    ],
    "name:nld_x_preferred":[
        "Le Hamel"
    ],
    "name:oci_x_preferred":[
        "Le Hamel"
    ],
    "name:pol_x_preferred":[
        "Le Hamel"
    ],
    "name:slk_x_preferred":[
        "Le Hamel"
    ],
    "name:spa_x_preferred":[
        "Le Hamel"
    ],
    "name:swe_x_preferred":[
        "Le Hamel"
    ],
    "name:ukr_x_preferred":[
        "\u041b\u0435-\u0410\u043c\u0435\u043b\u044c"
    ],
    "wof:name":"Le Hamel",
    "wof:placetype":"locality"
},
  "geometry": {"coordinates":[1.35159,49.84914000000001],"type":"Point"}
}