{
  "type": "Feature",
  "properties": {
    "gn:admin1_code":"93",
    "gn:admin2_code":"04",
    "gn:admin3_code":"041",
    "gn:admin4_code":"04102",
    "gn:asciiname":"Le Plan",
    "gn:country_code":"FR",
    "gn:dem":778,
    "gn:feature_class":"P",
    "gn:feature_code":"PPL",
    "gn:name":"Le Plan",
    "gn:population":0,
    "gn:timezone":"Europe/Paris",
    "iso:country":"FR",
    "wof:name":"Le Plan",
    "wof:placetype":"locality"
},
  "geometry": {"coordinates":[6.35,44.46667],"type":"Point"}
}