{
  "type": "Feature",
  "properties": {
    "gn:admin1_code":"28",
    "gn:admin2_code":"76",
    "gn:admin3_code":"761",
    "gn:admin4_code":"76423",
    "gn:asciiname":"Viviere",
    "gn:country_code":"FR",
    "gn:dem":138,
    "gn:feature_class":"P",
    "gn:feature_code":"PPL",
    "gn:name":"Vivi\u00e8re",
    "gn:population":0,
    "gn:timezone":"Europe/Paris",
    "iso:country":"FR",
    "wof:name":"Viviere",
    "wof:placetype":"locality"
},
  "geometry": {"coordinates":[1.63848,49.56846],"type":"Point"}
}