{
  "type": "Feature",
  "properties": {
    "gn:admin1_code":"44",
    "gn:admin2_code":"10",
    "gn:admin3_code":"102",
    "gn:admin4_code":"10031",
    "gn:asciiname":"Courtavant",
    "gn:country_code":"FR",
    "gn:dem":63,
    "gn:feature_class":"P",
    "gn:feature_code":"PPL",
    "gn:name":"Courtavant",
    "gn:population":0,
    "gn:timezone":"Europe/Paris",
    "iso:country":"FR",
    "wof:name":"Courtavant",
    "wof:placetype":"locality"
},
  "geometry": {"coordinates":[3.57941,48.5463],"type":"Point"}
}