{
  "type": "Feature",
  "properties": {
    "gn:admin1_code":"53",
    "gn:admin2_code":"56",
    "gn:admin3_code":"561",
    "gn:admin4_code":"56162",
    "gn:asciiname":"Pen-Palud",
    "gn:country_code":"FR",
    "gn:dem":11,
    "gn:feature_class":"P",
    "gn:feature_code":"PPL",
    "gn:name":"Pen-Palud",
    "gn:population":0,
    "gn:timezone":"Europe/Paris",
    "iso:country":"FR",
    "wof:name":"Pen-Palud",
    "wof:placetype":"locality"
},
  "geometry": {"coordinates":[-3.42206,47.70731],"type":"Point"}
}