{
  "type": "Feature",
  "properties": {
    "gn:admin1_code":"32",
    "gn:admin2_code":"60",
    "gn:admin3_code":"601",
    "gn:admin4_code":"60331",
    "gn:asciiname":"Montcornet",
    "gn:country_code":"FR",
    "gn:dem":179,
    "gn:feature_class":"P",
    "gn:feature_code":"PPL",
    "gn:name":"Montcornet",
    "gn:population":0,
    "gn:timezone":"Europe/Paris",
    "iso:country":"FR",
    "name:ceb_x_preferred":[
        "Montcornet"
    ],
    "name:ces_x_preferred":[
        "Montcornet"
    ],
    "name:deu_x_preferred":[
        "Montcornet"
    ],
    "name:epo_x_preferred":[
        "Montcornet"
    ],
    "name:fra_x_preferred":[
        "Montcornet"
    ],
    "name:hun_x_preferred":[
        "Montcornet"
    ],
    "name:ita_x_preferred":[
        "Montcornet"
    ],
    "name:ltz_x_preferred":[
        "Montcornet"
    ],
    "name:nds_x_preferred":[
        "Montcornet"
    ],
    "name:nld_x_preferred":[
        "Montcornet"
    ],
    "name:oci_x_preferred":[
        "Montcornet"
    ],
    "name:pms_x_preferred":[
        "Montcornet"
    ],
    "name:pol_x_preferred":[
        "Montcornet"
    ],
    "name:por_x_preferred":[
        "Montcornet"
    ],
    "name:rus_x_preferred":[
        "\u041c\u043e\u043d\u043a\u043e\u0440\u043d\u0435"
    ],
    "name:slk_x_preferred":[
        "Montcornet"
    ],
    "name:spa_x_preferred":[
        "Montcornet"
    ],
    "name:swe_x_preferred":[
        "Montcornet"
    ],
    "name:ukr_x_preferred":[
        "\u041c\u043e\u043d\u043a\u043e\u0440\u043d\u0435"
    ],
    "wof:name":"Montcornet",
    "wof:placetype":"locality"
},
  "geometry": {"coordinates":[1.89353,49.35804],"type":"Point"}
}