{
  "type": "Feature",
  "properties": {
    "gn:admin1_code":"28",
    "gn:admin2_code":"76",
    "gn:admin3_code":"762",
    "gn:admin4_code":"76688",
    "gn:asciiname":"Le Fils",
    "gn:country_code":"FR",
    "gn:dem":127,
    "gn:feature_class":"P",
    "gn:feature_code":"PPL",
    "gn:name":"Le Fils",
    "gn:population":0,
    "gn:timezone":"Europe/Paris",
    "iso:country":"FR",
    "wof:name":"Le Fils",
    "wof:placetype":"locality"
},
  "geometry": {"coordinates":[0.50058,49.73381],"type":"Point"}
}