{
  "type": "Feature",
  "properties": {
    "gn:admin1_code":"84",
    "gn:admin2_code":"03",
    "gn:admin3_code":"032",
    "gn:admin4_code":"03116",
    "gn:asciiname":"Blanzat",
    "gn:country_code":"FR",
    "gn:dem":267,
    "gn:feature_class":"P",
    "gn:feature_code":"PPL",
    "gn:name":"Blanzat",
    "gn:population":0,
    "gn:timezone":"Europe/Paris",
    "iso:country":"FR",
    "name:cat_x_preferred":[
        "Blanzac"
    ],
    "name:ceb_x_preferred":[
        "Blanzat"
    ],
    "name:deu_x_preferred":[
        "Blanzat"
    ],
    "name:eus_x_preferred":[
        "Blanzat"
    ],
    "name:fra_x_preferred":[
        "Blanzat"
    ],
    "name:hun_x_preferred":[
        "Blanzat"
    ],
    "name:ita_x_preferred":[
        "Blanzat"
    ],
    "name:lat_x_preferred":[
        "Blanzat"
    ],
    "name:msa_x_preferred":[
        "Blanzat"
    ],
    "name:nld_x_preferred":[
        "Blanzat"
    ],
    "name:oci_x_preferred":[
        "Blanzat"
    ],
    "name:pms_x_preferred":[
        "Blanzat"
    ],
    "name:pol_x_preferred":[
        "Blanzat"
    ],
    "name:por_x_preferred":[
        "Blanzat"
    ],
    "name:ron_x_preferred":[
        "Blanzat"
    ],
    "name:slk_x_preferred":[
        "Blanzat"
    ],
    "name:spa_x_preferred":[
        "Blanzat"
    ],
    "name:srp_x_preferred":[
        "\u0411\u043b\u0430\u043d\u0437\u0430"
    ],
    "name:swe_x_preferred":[
        "Blanzat"
    ],
    "name:ukr_x_preferred":[
        "\u0411\u043b\u0430\u043d\u0437\u0430"
    ],
    "name:uzb_x_preferred":[
        "Blanzat"
    ],
    "name:vie_x_preferred":[
        "Blanzat"
    ],
    "name:vol_x_preferred":[
        "Blanzat"
    ],
    "name:war_x_preferred":[
        "Blanzat"
    ],
    "name:zho_x_preferred":[
        "\u5e03\u6717\u624e"
    ],
    "wof:name":"Blanzat",
    "wof:placetype":"locality"
},
  "geometry": {"coordinates":[3.20333,46.2595],"type":"Point"}
}