{
  "type": "Feature",
  "properties": {
    "gn:admin1_code":"53",
    "gn:admin2_code":"29",
    "gn:admin3_code":"294",
    "gn:admin4_code":"29168",
    "gn:asciiname":"Le Loch",
    "gn:cc2":"FR",
    "gn:country_code":"FR",
    "gn:dem":57,
    "gn:feature_class":"P",
    "gn:feature_code":"PPL",
    "gn:name":"Le Loch",
    "gn:population":0,
    "gn:timezone":"Europe/Paris",
    "iso:country":"FR",
    "name:und_x_variant":[
        "Loch"
    ],
    "wof:name":"Le Loch",
    "wof:placetype":"locality"
},
  "geometry": {"coordinates":[-4.6594,48.02994],"type":"Point"}
}