{
  "type": "Feature",
  "properties": {
    "gn:admin1_code":"11",
    "gn:admin2_code":"78",
    "gn:admin3_code":"782",
    "gn:admin4_code":"78009",
    "gn:asciiname":"Obville",
    "gn:country_code":"FR",
    "gn:dem":159,
    "gn:feature_class":"P",
    "gn:feature_code":"PPL",
    "gn:name":"Obville",
    "gn:population":0,
    "gn:timezone":"Europe/Paris",
    "iso:country":"FR",
    "name:und_x_variant":[
        "Obeville",
        "Obville"
    ],
    "wof:name":"Obville",
    "wof:placetype":"locality"
},
  "geometry": {"coordinates":[1.90307,48.48515],"type":"Point"}
}