{
  "type": "Feature",
  "properties": {
    "gn:admin1_code":"28",
    "gn:admin2_code":"61",
    "gn:admin3_code":"613",
    "gn:admin4_code":"61259",
    "gn:asciiname":"Secheville",
    "gn:country_code":"FR",
    "gn:dem":278,
    "gn:feature_class":"P",
    "gn:feature_code":"PPL",
    "gn:name":"S\u00e9cheville",
    "gn:population":0,
    "gn:timezone":"Europe/Paris",
    "iso:country":"FR",
    "wof:name":"Secheville",
    "wof:placetype":"locality"
},
  "geometry": {"coordinates":[0.49694,48.6973],"type":"Point"}
}