{
  "type": "Feature",
  "properties": {
    "gn:admin1_code":"28",
    "gn:admin2_code":"27",
    "gn:admin3_code":"271",
    "gn:admin4_code":"27372",
    "gn:asciiname":"Bifauvel",
    "gn:country_code":"FR",
    "gn:dem":124,
    "gn:feature_class":"P",
    "gn:feature_code":"PPL",
    "gn:name":"Bifauvel",
    "gn:population":0,
    "gn:timezone":"Europe/Paris",
    "iso:country":"FR",
    "wof:name":"Bifauvel",
    "wof:placetype":"locality"
},
  "geometry": {"coordinates":[1.62731,49.34667],"type":"Point"}
}