{
  "type": "Feature",
  "properties": {
    "gn:admin1_code":"84",
    "gn:admin2_code":"07",
    "gn:admin3_code":"072",
    "gn:admin4_code":"7096.0",
    "gn:asciiname":"Le Pral",
    "gn:country_code":"FR",
    "gn:dem":692,
    "gn:feature_class":"P",
    "gn:feature_code":"PPL",
    "gn:name":"Le Pral",
    "gn:population":0,
    "gn:timezone":"Europe/Paris",
    "iso:country":"FR",
    "wof:name":"Le Pral",
    "wof:placetype":"locality"
},
  "geometry": {"coordinates":[4.50148,44.84125],"type":"Point"}
}