{
  "type": "Feature",
  "properties": {
    "gn:admin1_code":"75",
    "gn:admin2_code":"19",
    "gn:admin3_code":"191",
    "gn:admin4_code":"19025",
    "gn:asciiname":"Le Mechenin",
    "gn:country_code":"FR",
    "gn:dem":369,
    "gn:feature_class":"P",
    "gn:feature_code":"PPL",
    "gn:name":"Le M\u00e9chenin",
    "gn:population":0,
    "gn:timezone":"Europe/Paris",
    "iso:country":"FR",
    "wof:name":"Le Mechenin",
    "wof:placetype":"locality"
},
  "geometry": {"coordinates":[1.29848,45.41009],"type":"Point"}
}