{
  "type": "Feature",
  "properties": {
    "iso:country":"FR",
    "name:eng_x_preferred":[
        "Le Port"
    ],
    "name:fra_x_preferred":[
        "Le Port"
    ],
    "wof:name":"Le Port",
    "wof:placetype":"neighbourhood"
},
  "geometry": {"coordinates":[7.28498302571227,43.70010261785896],"type":"Point"}
}