{
  "type": "Feature",
  "properties": {
    "gn:admin1_code":"75",
    "gn:admin2_code":"79",
    "gn:admin3_code":"791",
    "gn:admin4_code":"79299",
    "gn:asciiname":"Riblaire",
    "gn:country_code":"FR",
    "gn:dem":96,
    "gn:feature_class":"P",
    "gn:feature_code":"PPL",
    "gn:name":"Riblaire",
    "gn:population":0,
    "gn:timezone":"Europe/Paris",
    "iso:country":"FR",
    "wof:name":"Riblaire",
    "wof:placetype":"locality"
},
  "geometry": {"coordinates":[-0.20126,46.88874000000001],"type":"Point"}
}