{
  "type": "Feature",
  "properties": {
    "gn:admin1_code":"24",
    "gn:admin2_code":"28",
    "gn:admin3_code":"281",
    "gn:admin4_code":"28309",
    "gn:asciiname":"Boinville-au-Chemin",
    "gn:country_code":"FR",
    "gn:dem":149,
    "gn:feature_class":"P",
    "gn:feature_code":"PPL",
    "gn:name":"Boinville-au-Chemin",
    "gn:population":0,
    "gn:timezone":"Europe/Paris",
    "iso:country":"FR",
    "name:und_x_variant":[
        "Boinville",
        "Boinville-au-Chemin"
    ],
    "wof:name":"Boinville-au-Chemin",
    "wof:placetype":"locality"
},
  "geometry": {"coordinates":[1.66027,48.37919],"type":"Point"}
}