{
  "type": "Feature",
  "properties": {
    "gn:admin1_code":"93",
    "gn:admin2_code":"06",
    "gn:admin3_code":"062",
    "gn:admin4_code":"06160",
    "gn:asciiname":"Enaux",
    "gn:country_code":"FR",
    "gn:dem":1394,
    "gn:feature_class":"P",
    "gn:feature_code":"PPL",
    "gn:name":"\u00c9naux",
    "gn:population":0,
    "gn:timezone":"Europe/Paris",
    "iso:country":"FR",
    "name:und_x_variant":[
        "\u00c9neaux",
        "\u00c9naux"
    ],
    "wof:name":"Enaux",
    "wof:placetype":"locality"
},
  "geometry": {"coordinates":[6.77264,44.10669],"type":"Point"}
}