{
  "type": "Feature",
  "properties": {
    "gn:admin1_code":"53",
    "gn:admin2_code":"22",
    "gn:admin3_code":"221",
    "gn:admin4_code":"22388",
    "gn:asciiname":"Bocule",
    "gn:country_code":"FR",
    "gn:dem":103,
    "gn:feature_class":"P",
    "gn:feature_code":"PPL",
    "gn:name":"Bocul\u00e9",
    "gn:population":0,
    "gn:timezone":"Europe/Paris",
    "iso:country":"FR",
    "wof:name":"Bocule",
    "wof:placetype":"locality"
},
  "geometry": {"coordinates":[-2.14158,48.42261],"type":"Point"}
}