{
  "type": "Feature",
  "properties": {
    "frgov:code_epci":"200071157",
    "frgov:insee_arr":"1",
    "frgov:insee_com":"88177",
    "frgov:insee_dep":"88",
    "frgov:insee_reg":"44",
    "frgov:nom_com":"La Forge",
    "frgov:nom_com_m":"LA FORGE",
    "frgov:nom_dep":"VOSGES",
    "frgov:nom_reg":"GRAND EST",
    "frgov:statut":"Commune simple",
    "gn:admin1_code":"44",
    "gn:admin2_code":"88",
    "gn:admin3_code":"881",
    "gn:admin4_code":"88177",
    "gn:asciiname":"La Forge",
    "gn:country_code":"FR",
    "gn:dem":485,
    "gn:feature_class":"P",
    "gn:feature_code":"PPL",
    "gn:name":"La Forge",
    "gn:population":560,
    "gn:timezone":"Europe/Paris",
    "iso:country":"FR",
    "name:deu_x_preferred":[
        "La Forge"
    ],
    "name:fra_x_preferred":[
        "La Forge"
    ],
    "name:hbs_x_preferred":[
        "Forge"
    ],
    "name:kaz_x_preferred":[
        "\u041b\u0430-\u0424\u043e\u0440\u0436"
    ],
    "name:srp_x_preferred":[
        "\u0424\u043e\u0440\u0436\u0435"
    ],
    "name:ukr_x_preferred":[
        "\u041b\u0430-\u0424\u043e\u0440\u0436"
    ],
    "name:urd_x_preferred":[
        "\u0644\u0627 \u0641\u0648\u0631\u06af\u06cc\u060c \u0648\u0648\u0633\u06af\u06cc\u0633"
    ],
    "name:zho_x_preferred":[
        "\u62c9\u798f\u5c14\u683c"
    ],
    "qs:a0":"France",
    "qs:a1":"VOSGES",
    "qs:a1_lc":"88",
    "qs:a1r":"LORRAINE",
    "qs:a1r_lc":"41",
    "qs:a2_lc":"23",
    "qs:a2r_lc":"1",
    "qs:adm0":"France",
    "qs:adm0_a3":"FRA",
    "qs:la":"LA FORGE",
    "qs:la_lc":"88177",
    "qs:level":"localadmin",
    "qs:type":"Commune simple",
    "wof:coterminous":[
        404408649
    ],
    "wof:name":"La Forge",
    "wof:placetype":"locality",
    "wof:placetype_local":"Commune simple",
    "wof:population":560
},
  "geometry": {"coordinates":[6.72385,48.06506],"type":"Point"}
}