{
  "type": "Feature",
  "properties": {
    "gn:admin1_code":"44",
    "gn:admin2_code":"88",
    "gn:admin3_code":"881",
    "gn:admin4_code":"88177",
    "gn:asciiname":"La Forge",
    "gn:country_code":"FR",
    "gn:dem":485,
    "gn:feature_class":"P",
    "gn:feature_code":"PPL",
    "gn:name":"La Forge",
    "gn:population":560,
    "gn:timezone":"Europe/Paris",
    "iso:country":"FR",
    "wof:name":"La Forge",
    "wof:placetype":"locality",
    "wof:population":560
},
  "geometry": {"coordinates":[6.72385,48.06506],"type":"Point"}
}