{
  "type": "Feature",
  "properties": {
    "gn:admin1_code":"84",
    "gn:admin2_code":"03",
    "gn:admin3_code":"031",
    "gn:admin4_code":"03219",
    "gn:asciiname":"Les Villards",
    "gn:country_code":"FR",
    "gn:dem":463,
    "gn:feature_class":"P",
    "gn:feature_code":"PPL",
    "gn:name":"Les Villards",
    "gn:population":0,
    "gn:timezone":"Europe/Paris",
    "iso:country":"FR",
    "wof:name":"Les Villards",
    "wof:placetype":"locality"
},
  "geometry": {"coordinates":[2.92374,46.29969000000001],"type":"Point"}
}