{
  "type": "Feature",
  "properties": {
    "gn:admin1_code":"44",
    "gn:admin2_code":"51",
    "gn:admin3_code":"512",
    "gn:admin4_code":"51369",
    "gn:asciiname":"Verdey",
    "gn:country_code":"FR",
    "gn:dem":176,
    "gn:feature_class":"P",
    "gn:feature_code":"PPL",
    "gn:name":"Verdey",
    "gn:population":0,
    "gn:timezone":"Europe/Paris",
    "iso:country":"FR",
    "wof:name":"Verdey",
    "wof:placetype":"locality"
},
  "geometry": {"coordinates":[3.69683,48.74531],"type":"Point"}
}