{
  "type": "Feature",
  "properties": {
    "gn:admin1_code":"24",
    "gn:admin2_code":"45",
    "gn:admin3_code":"451",
    "gn:admin4_code":"45219",
    "gn:asciiname":"La Chaume",
    "gn:country_code":"FR",
    "gn:dem":98,
    "gn:feature_class":"P",
    "gn:feature_code":"PPL",
    "gn:name":"La Chaume",
    "gn:population":0,
    "gn:timezone":"Europe/Paris",
    "iso:country":"FR",
    "wof:name":"La Chaume",
    "wof:placetype":"locality"
},
  "geometry": {"coordinates":[2.60771,48.01474],"type":"Point"}
}