{
  "type": "Feature",
  "properties": {
    "gn:admin1_code":"28",
    "gn:admin2_code":"61",
    "gn:admin3_code":"613",
    "gn:admin4_code":"61140",
    "gn:asciiname":"Les Clos",
    "gn:country_code":"FR",
    "gn:dem":239,
    "gn:feature_class":"P",
    "gn:feature_code":"PPL",
    "gn:name":"Les Clos",
    "gn:population":0,
    "gn:timezone":"Europe/Paris",
    "iso:country":"FR",
    "wof:name":"Les Clos",
    "wof:placetype":"locality"
},
  "geometry": {"coordinates":[0.66818,48.68801],"type":"Point"}
}