{
  "type": "Feature",
  "properties": {
    "gn:admin1_code":"84",
    "gn:admin2_code":"43",
    "gn:admin3_code":"432",
    "gn:admin4_code":"43108.0",
    "gn:asciiname":"Le Mont",
    "gn:country_code":"FR",
    "gn:dem":966,
    "gn:feature_class":"P",
    "gn:feature_code":"PPL",
    "gn:name":"Le Mont",
    "gn:population":0,
    "gn:timezone":"Europe/Paris",
    "iso:country":"FR",
    "wof:name":"Le Mont",
    "wof:placetype":"locality"
},
  "geometry": {"coordinates":[3.78882,45.29065],"type":"Point"}
}