{
  "type": "Feature",
  "properties": {
    "iso:country":"FR",
    "wof:name":"Les Cinq Avenues",
    "wof:placetype":"neighbourhood"
},
  "geometry": {"coordinates":[5.39625866503958,43.30268611432366],"type":"Point"}
}