{
  "type": "Feature",
  "properties": {
    "gn:admin1_code":"84",
    "gn:admin2_code":"38",
    "gn:admin3_code":"382",
    "gn:admin4_code":"38339",
    "gn:asciiname":"La Croix",
    "gn:country_code":"FR",
    "gn:dem":375,
    "gn:feature_class":"P",
    "gn:feature_code":"PPL",
    "gn:name":"La Croix",
    "gn:population":0,
    "gn:timezone":"Europe/Paris",
    "iso:country":"FR",
    "wof:name":"La Croix",
    "wof:placetype":"locality"
},
  "geometry": {"coordinates":[5.16245,45.58583],"type":"Point"}
}