{
  "type": "Feature",
  "properties": {
    "gn:admin1_code":"84",
    "gn:admin2_code":"38",
    "gn:admin3_code":"382",
    "gn:admin4_code":"38339",
    "gn:asciiname":"La Croix",
    "gn:country_code":"FR",
    "gn:dem":375,
    "gn:feature_class":"P",
    "gn:feature_code":"PPL",
    "gn:name":"La Croix",
    "gn:population":0,
    "gn:timezone":"Europe/Paris",
    "iso:country":"FR",
    "name:deu_x_preferred":[
        "La Croix"
    ],
    "name:eus_x_preferred":[
        "La Croix"
    ],
    "name:fra_x_preferred":[
        "La Croix"
    ],
    "name:heb_x_preferred":[
        "\u05dc\u05d4 \u05e7\u05e8\u05d5\u05d0\u05d4"
    ],
    "name:ita_x_preferred":[
        "La Croix"
    ],
    "name:lat_x_preferred":[
        "La Croix"
    ],
    "name:nld_x_preferred":[
        "La Croix"
    ],
    "name:spa_x_preferred":[
        "La Croix"
    ],
    "name:tur_x_preferred":[
        "La Croix"
    ],
    "name:zho_x_preferred":[
        "\u5341\u5b57\u67b6\u62a5"
    ],
    "wof:name":"La Croix",
    "wof:placetype":"locality"
},
  "geometry": {"coordinates":[5.16245,45.58583],"type":"Point"}
}