{
  "type": "Feature",
  "properties": {
    "gn:admin1_code":"84",
    "gn:admin2_code":"38",
    "gn:admin3_code":"382",
    "gn:admin4_code":"38146",
    "gn:asciiname":"Peyrieu",
    "gn:country_code":"FR",
    "gn:dem":363,
    "gn:feature_class":"P",
    "gn:feature_code":"PPL",
    "gn:name":"Peyrieu",
    "gn:population":0,
    "gn:timezone":"Europe/Paris",
    "iso:country":"FR",
    "name:ara_x_preferred":[
        "\u0628\u064a\u0631\u064a\u0648"
    ],
    "name:bug_x_preferred":[
        "Peyrieu"
    ],
    "name:cat_x_preferred":[
        "Peyrieu"
    ],
    "name:ceb_x_preferred":[
        "Peyrieu"
    ],
    "name:deu_x_preferred":[
        "Peyrieu"
    ],
    "name:eus_x_preferred":[
        "Peyrieu"
    ],
    "name:fra_x_preferred":[
        "Peyrieu"
    ],
    "name:glg_x_preferred":[
        "Peyrieu"
    ],
    "name:hun_x_preferred":[
        "Peyrieu"
    ],
    "name:hye_x_preferred":[
        "\u054a\u0565\u0580\u056b\u0578"
    ],
    "name:ind_x_preferred":[
        "Peyrieu"
    ],
    "name:ita_x_preferred":[
        "Peyrieu"
    ],
    "name:lat_x_preferred":[
        "Peyrieu"
    ],
    "name:lmo_x_preferred":[
        "Peyrieu"
    ],
    "name:ltz_x_preferred":[
        "Peyrieu"
    ],
    "name:mlg_x_preferred":[
        "Peyrieu"
    ],
    "name:msa_x_preferred":[
        "Peyrieu"
    ],
    "name:nld_x_preferred":[
        "Peyrieu"
    ],
    "name:oci_x_preferred":[
        "Peyrieu"
    ],
    "name:pol_x_preferred":[
        "Peyrieu"
    ],
    "name:por_x_preferred":[
        "Peyrieu"
    ],
    "name:rus_x_preferred":[
        "\u041f\u0435\u0440\u044c\u0451"
    ],
    "name:slk_x_preferred":[
        "Peyrieu"
    ],
    "name:spa_x_preferred":[
        "Peyrieu"
    ],
    "name:swe_x_preferred":[
        "Peyrieu"
    ],
    "name:tgl_x_preferred":[
        "Peyrieu"
    ],
    "name:ukr_x_preferred":[
        "\u041f\u0435\u0439\u0440'\u0454"
    ],
    "name:uzb_x_preferred":[
        "Peyrieu"
    ],
    "name:vie_x_preferred":[
        "Peyrieu"
    ],
    "name:vol_x_preferred":[
        "Peyrieu"
    ],
    "name:war_x_preferred":[
        "Peyrieu"
    ],
    "name:zea_x_preferred":[
        "Peyrieu"
    ],
    "name:zho_x_preferred":[
        "\u4f69\u91cc\u5384"
    ],
    "wof:name":"Peyrieu",
    "wof:placetype":"locality"
},
  "geometry": {"coordinates":[5.28416,45.71568],"type":"Point"}
}