{
  "type": "Feature",
  "properties": {
    "gn:admin1_code":"84",
    "gn:admin2_code":"38",
    "gn:admin3_code":"382",
    "gn:admin4_code":"38146",
    "gn:asciiname":"Peyrieu",
    "gn:country_code":"FR",
    "gn:dem":363,
    "gn:feature_class":"P",
    "gn:feature_code":"PPL",
    "gn:name":"Peyrieu",
    "gn:population":0,
    "gn:timezone":"Europe/Paris",
    "iso:country":"FR",
    "wof:name":"Peyrieu",
    "wof:placetype":"locality"
},
  "geometry": {"coordinates":[5.28416,45.71568],"type":"Point"}
}