{
  "type": "Feature",
  "properties": {
    "gn:admin1_code":"24",
    "gn:admin2_code":"28",
    "gn:admin3_code":"283",
    "gn:admin4_code":"28151",
    "gn:asciiname":"Fessanvilliers-Mattanvilliers",
    "gn:country_code":"FR",
    "gn:dem":178,
    "gn:feature_class":"P",
    "gn:feature_code":"PPL",
    "gn:name":"Fessanvilliers-Mattanvilliers",
    "gn:population":0,
    "gn:timezone":"Europe/Paris",
    "iso:country":"FR",
    "name:bug_x_preferred":[
        "Fessanvilliers-Mattanvilliers"
    ],
    "name:cat_x_preferred":[
        "Fessanvilliers-Mattanvilliers"
    ],
    "name:ceb_x_preferred":[
        "Fessanvilliers-Mattanvilliers"
    ],
    "name:deu_x_preferred":[
        "Fessanvilliers-Mattanvilliers"
    ],
    "name:eus_x_preferred":[
        "Fessanvilliers-Mattanvilliers"
    ],
    "name:fra_x_preferred":[
        "Fessanvilliers-Mattanvilliers"
    ],
    "name:hun_x_preferred":[
        "Fessanvilliers-Mattanvilliers"
    ],
    "name:ind_x_preferred":[
        "Fessanvilliers-Mattanvilliers"
    ],
    "name:ita_x_preferred":[
        "Fessanvilliers-Mattanvilliers"
    ],
    "name:lat_x_preferred":[
        "Fessanvilliers-Mattanvilliers"
    ],
    "name:mlg_x_preferred":[
        "Fessanvilliers-Mattanvilliers"
    ],
    "name:msa_x_preferred":[
        "Fessanvilliers-Mattanvilliers"
    ],
    "name:nld_x_preferred":[
        "Fessanvilliers-Mattanvilliers"
    ],
    "name:oci_x_preferred":[
        "Fessanvilliers-Mattanvilliers"
    ],
    "name:pms_x_preferred":[
        "Fessanvilliers-Mattanvilliers"
    ],
    "name:pol_x_preferred":[
        "Fessanvilliers-Mattanvilliers"
    ],
    "name:por_x_preferred":[
        "Fessanvilliers-Mattanvilliers"
    ],
    "name:ron_x_preferred":[
        "Fessanvilliers-Mattanvilliers"
    ],
    "name:slk_x_preferred":[
        "Fessanvilliers-Mattanvilliers"
    ],
    "name:spa_x_preferred":[
        "Fessanvilliers-Mattanvilliers"
    ],
    "name:swe_x_preferred":[
        "Fessanvilliers-Mattanvilliers"
    ],
    "name:ukr_x_preferred":[
        "\u0424\u0435\u0441\u0441\u0430\u043d\u0432\u0456\u043b\u044c\u0454-\u041c\u0430\u0442\u0442\u0430\u043d\u0432\u0456\u043b\u044c\u0454"
    ],
    "name:uzb_x_preferred":[
        "Fessanvilliers-Mattanvilliers"
    ],
    "name:vie_x_preferred":[
        "Fessanvilliers-Mattanvilliers"
    ],
    "name:vol_x_preferred":[
        "Fessanvilliers-Mattanvilliers"
    ],
    "name:war_x_preferred":[
        "Fessanvilliers-Mattanvilliers"
    ],
    "name:zho_x_preferred":[
        "\u8d39\u6851\u7ef4\u5217\u9a6c\u5510\u7ef4\u5217"
    ],
    "wof:name":"Fessanvilliers-Mattanvilliers",
    "wof:placetype":"locality"
},
  "geometry": {"coordinates":[1.04662,48.71226],"type":"Point"}
}