{
  "type": "Feature",
  "properties": {
    "gn:admin1_code":"24",
    "gn:admin2_code":"28",
    "gn:admin3_code":"283",
    "gn:admin4_code":"28151",
    "gn:asciiname":"Fessanvilliers-Mattanvilliers",
    "gn:country_code":"FR",
    "gn:dem":178,
    "gn:feature_class":"P",
    "gn:feature_code":"PPL",
    "gn:name":"Fessanvilliers-Mattanvilliers",
    "gn:population":0,
    "gn:timezone":"Europe/Paris",
    "iso:country":"FR",
    "wof:name":"Fessanvilliers-Mattanvilliers",
    "wof:placetype":"locality"
},
  "geometry": {"coordinates":[1.04662,48.71226],"type":"Point"}
}