{
  "type": "Feature",
  "properties": {
    "gn:admin1_code":"84",
    "gn:admin2_code":"43",
    "gn:admin3_code":"431",
    "gn:admin4_code":"43232",
    "gn:asciiname":"Le Marcet",
    "gn:country_code":"FR",
    "gn:dem":528,
    "gn:feature_class":"P",
    "gn:feature_code":"PPL",
    "gn:name":"Le Marcet",
    "gn:population":0,
    "gn:timezone":"Europe/Paris",
    "iso:country":"FR",
    "wof:name":"Le Marcet",
    "wof:placetype":"locality"
},
  "geometry": {"coordinates":[3.49604,45.20911],"type":"Point"}
}