{
  "type": "Feature",
  "properties": {
    "gn:admin1_code":"84",
    "gn:admin2_code":"73",
    "gn:admin3_code":"732",
    "gn:admin4_code":"73120",
    "gn:asciiname":"Fiardiere",
    "gn:country_code":"FR",
    "gn:dem":316,
    "gn:feature_class":"P",
    "gn:feature_code":"PPL",
    "gn:name":"Fiardi\u00e8re",
    "gn:population":0,
    "gn:timezone":"Europe/Paris",
    "iso:country":"FR",
    "name:und_x_variant":[
        "Fliardi\u00e8re",
        "Fiardi\u00e8re"
    ],
    "wof:name":"Fiardiere",
    "wof:placetype":"locality"
},
  "geometry": {"coordinates":[6.21791,45.58631],"type":"Point"}
}