{
  "type": "Feature",
  "properties": {
    "gn:admin1_code":"53",
    "gn:admin2_code":"35",
    "gn:admin3_code":"354",
    "gn:admin4_code":"35299",
    "gn:asciiname":"Le Bouillon",
    "gn:country_code":"FR",
    "gn:dem":45,
    "gn:feature_class":"P",
    "gn:feature_code":"PPL",
    "gn:name":"Le Bouillon",
    "gn:population":0,
    "gn:timezone":"Europe/Paris",
    "iso:country":"FR",
    "wof:name":"Le Bouillon",
    "wof:placetype":"locality"
},
  "geometry": {"coordinates":[-1.91707,48.63715],"type":"Point"}
}