{
  "type": "Feature",
  "properties": {
    "gn:admin1_code":"53",
    "gn:admin2_code":"35",
    "gn:admin3_code":"354",
    "gn:admin4_code":"35299",
    "gn:asciiname":"Le Bouillon",
    "gn:country_code":"FR",
    "gn:dem":45,
    "gn:feature_class":"P",
    "gn:feature_code":"PPL",
    "gn:name":"Le Bouillon",
    "gn:population":0,
    "gn:timezone":"Europe/Paris",
    "iso:country":"FR",
    "name:cat_x_preferred":[
        "Le Bouillon"
    ],
    "name:ceb_x_preferred":[
        "Le Bouillon"
    ],
    "name:deu_x_preferred":[
        "Le Bouillon"
    ],
    "name:epo_x_preferred":[
        "Le Bouillon"
    ],
    "name:eus_x_preferred":[
        "Le Bouillon"
    ],
    "name:fra_x_preferred":[
        "Le Bouillon"
    ],
    "name:hun_x_preferred":[
        "Le Bouillon"
    ],
    "name:ind_x_preferred":[
        "Le Bouillon"
    ],
    "name:ita_x_preferred":[
        "Le Bouillon"
    ],
    "name:kaz_x_preferred":[
        "\u041b\u0435-\u0411\u0443\u0439\u043e\u043d"
    ],
    "name:lat_x_preferred":[
        "Le Bouillon"
    ],
    "name:mlg_x_preferred":[
        "Le Bouillon"
    ],
    "name:msa_x_preferred":[
        "Le Bouillon"
    ],
    "name:nld_x_preferred":[
        "Le Bouillon"
    ],
    "name:oci_x_preferred":[
        "Le Bouillon"
    ],
    "name:pms_x_preferred":[
        "Le Bouillon"
    ],
    "name:pol_x_preferred":[
        "Le Bouillon"
    ],
    "name:por_x_preferred":[
        "Le Bouillon"
    ],
    "name:ron_x_preferred":[
        "Le Bouillon"
    ],
    "name:slk_x_preferred":[
        "Le Bouillon"
    ],
    "name:spa_x_preferred":[
        "Le Bouillon"
    ],
    "name:srp_x_preferred":[
        "\u0411\u0443\u0458\u043e\u043d"
    ],
    "name:swe_x_preferred":[
        "Le Bouillon"
    ],
    "name:ukr_x_preferred":[
        "\u041b\u0435-\u0411\u0443\u0439\u043e\u043d"
    ],
    "name:uzb_x_preferred":[
        "Le Bouillon"
    ],
    "name:vie_x_preferred":[
        "Le Bouillon"
    ],
    "name:vol_x_preferred":[
        "Le Bouillon"
    ],
    "name:war_x_preferred":[
        "Le Bouillon"
    ],
    "name:zho_x_preferred":[
        "\u52d2\u5e03\u6c38"
    ],
    "wof:name":"Le Bouillon",
    "wof:placetype":"locality"
},
  "geometry": {"coordinates":[-1.91707,48.63715],"type":"Point"}
}