{
  "type": "Feature",
  "properties": {
    "gn:admin1_code":"76",
    "gn:admin2_code":"48",
    "gn:admin3_code":"482",
    "gn:admin4_code":"48184",
    "gn:asciiname":"Ancette",
    "gn:country_code":"FR",
    "gn:dem":1151,
    "gn:feature_class":"P",
    "gn:feature_code":"PPL",
    "gn:name":"Ancette",
    "gn:population":0,
    "gn:timezone":"Europe/Paris",
    "iso:country":"FR",
    "wof:name":"Ancette",
    "wof:placetype":"locality"
},
  "geometry": {"coordinates":[3.61858,44.82403],"type":"Point"}
}