{
  "type": "Feature",
  "properties": {
    "gn:admin1_code":"84",
    "gn:admin2_code":"38",
    "gn:admin3_code":"382",
    "gn:admin4_code":"38507",
    "gn:asciiname":"Jameyzieu",
    "gn:country_code":"FR",
    "gn:dem":207,
    "gn:feature_class":"P",
    "gn:feature_code":"PPL",
    "gn:name":"Jameyzieu",
    "gn:population":0,
    "gn:timezone":"Europe/Paris",
    "iso:country":"FR",
    "name:und_x_variant":[
        "Jameysieu",
        "Jameyzieu"
    ],
    "wof:name":"Jameyzieu",
    "wof:placetype":"locality"
},
  "geometry": {"coordinates":[5.16314,45.71666],"type":"Point"}
}