{
  "type": "Feature",
  "properties": {
    "gn:admin1_code":"27",
    "gn:admin2_code":"89",
    "gn:admin3_code":"891",
    "gn:admin4_code":"89024",
    "gn:asciiname":"Les Chesnez",
    "gn:country_code":"FR",
    "gn:dem":152,
    "gn:feature_class":"P",
    "gn:feature_code":"PPL",
    "gn:name":"Les Chesnez",
    "gn:population":0,
    "gn:timezone":"Europe/Paris",
    "iso:country":"FR",
    "name:und_x_variant":[
        "Les Ch\u00eanaies",
        "Les Chesn\u00e9es",
        "Les Chesnez"
    ],
    "wof:name":"Les Chesnez",
    "wof:placetype":"locality"
},
  "geometry": {"coordinates":[3.55875,47.82036],"type":"Point"}
}