{
  "type": "Feature",
  "properties": {
    "iso:country":"FR",
    "name:eng_x_preferred":[
        "Vieux-Pays"
    ],
    "name:fra_x_preferred":[
        "Vieux-Pays"
    ],
    "wof:name":"Vieux-Pays",
    "wof:placetype":"neighbourhood"
},
  "geometry": {"coordinates":[2.55745491149756,48.97915681548002],"type":"Point"}
}