{
  "type": "Feature",
  "properties": {
    "gn:admin1_code":"93",
    "gn:admin2_code":"04",
    "gn:admin3_code":"043",
    "gn:admin4_code":"04205",
    "gn:asciiname":"Seyne-les-Alpes",
    "gn:country_code":"FR",
    "gn:dem":1189,
    "gn:feature_class":"P",
    "gn:feature_code":"PPL",
    "gn:name":"Seyne-les-Alpes",
    "gn:population":1438,
    "gn:timezone":"Europe/Paris",
    "iso:country":"FR",
    "name:bug_x_preferred":[
        "Seyne"
    ],
    "name:cat_x_preferred":[
        "S\u00e8ina"
    ],
    "name:ceb_x_preferred":[
        "Seyne"
    ],
    "name:deu_x_preferred":[
        "Seyne"
    ],
    "name:eus_x_preferred":[
        "Seyne"
    ],
    "name:fin_x_preferred":[
        "Seyne"
    ],
    "name:fra_x_preferred":[
        "Seyne"
    ],
    "name:hun_x_preferred":[
        "Seyne"
    ],
    "name:hye_x_preferred":[
        "\u054d\u0565\u0576"
    ],
    "name:ile_x_preferred":[
        "Seyne"
    ],
    "name:ind_x_preferred":[
        "Seyne"
    ],
    "name:ita_x_preferred":[
        "Seyne"
    ],
    "name:jpn_x_preferred":[
        "\u30bb\u30fc\u30cc"
    ],
    "name:kor_x_preferred":[
        "\uc13c"
    ],
    "name:lat_x_preferred":[
        "Seyne"
    ],
    "name:lmo_x_preferred":[
        "Seyne"
    ],
    "name:ltz_x_preferred":[
        "Seyne"
    ],
    "name:msa_x_preferred":[
        "Seyne"
    ],
    "name:nld_x_preferred":[
        "Seyne"
    ],
    "name:oci_x_preferred":[
        "Sanha"
    ],
    "name:oci_x_variant":[
        "S\u00e8ina"
    ],
    "name:pms_x_preferred":[
        "Seyne"
    ],
    "name:pol_x_preferred":[
        "Seyne"
    ],
    "name:por_x_preferred":[
        "Seyne"
    ],
    "name:ron_x_preferred":[
        "Seyne"
    ],
    "name:rus_x_preferred":[
        "\u0421\u0435\u043d"
    ],
    "name:slk_x_preferred":[
        "Seyne"
    ],
    "name:slv_x_preferred":[
        "Seyne"
    ],
    "name:spa_x_preferred":[
        "Seyne"
    ],
    "name:sqi_x_preferred":[
        "Seyne"
    ],
    "name:swe_x_preferred":[
        "Seyne"
    ],
    "name:ukr_x_preferred":[
        "\u0421\u0435\u0439\u043d"
    ],
    "name:vie_x_preferred":[
        "Seyne"
    ],
    "name:vol_x_preferred":[
        "Seyne"
    ],
    "name:war_x_preferred":[
        "Seyne"
    ],
    "name:zho_x_preferred":[
        "\u585e\u6069"
    ],
    "wof:name":"Seyne-les-Alpes",
    "wof:placetype":"locality",
    "wof:population":1438
},
  "geometry": {"coordinates":[6.35634,44.35042],"type":"Point"}
}