{
  "type": "Feature",
  "properties": {
    "gn:admin1_code":"93",
    "gn:admin2_code":"04",
    "gn:admin3_code":"043",
    "gn:admin4_code":"04205",
    "gn:asciiname":"Seyne-les-Alpes",
    "gn:country_code":"FR",
    "gn:dem":1189,
    "gn:feature_class":"P",
    "gn:feature_code":"PPL",
    "gn:name":"Seyne-les-Alpes",
    "gn:population":1438,
    "gn:timezone":"Europe/Paris",
    "iso:country":"FR",
    "name:cat_x_preferred":[
        "S\u00e8ina"
    ],
    "name:fra_x_preferred":[
        "Seyne"
    ],
    "name:kor_x_preferred":[
        "\uc13c"
    ],
    "name:oci_x_preferred":[
        "Sanha"
    ],
    "name:rus_x_preferred":[
        "\u0421\u0435\u043d"
    ],
    "name:ukr_x_preferred":[
        "\u0421\u0435\u0439\u043d"
    ],
    "name:und_x_variant":[
        "Seyne"
    ],
    "name:zho_x_preferred":[
        "\u585e\u6069"
    ],
    "wof:name":"Seyne-les-Alpes",
    "wof:placetype":"locality",
    "wof:population":1438
},
  "geometry": {"coordinates":[6.35634,44.35042],"type":"Point"}
}