{
  "type": "Feature",
  "properties": {
    "gn:admin1_code":"32",
    "gn:admin2_code":"80",
    "gn:admin3_code":"802",
    "gn:admin4_code":"80443",
    "gn:asciiname":"Tronchoy",
    "gn:country_code":"FR",
    "gn:dem":174,
    "gn:feature_class":"P",
    "gn:feature_code":"PPL",
    "gn:name":"Tronchoy",
    "gn:population":0,
    "gn:timezone":"Europe/Paris",
    "iso:country":"FR",
    "wof:name":"Tronchoy",
    "wof:placetype":"locality"
},
  "geometry": {"coordinates":[1.86502,49.82673],"type":"Point"}
}