{
  "type": "Feature",
  "properties": {
    "gn:admin1_code":"32",
    "gn:admin2_code":"80",
    "gn:admin3_code":"802",
    "gn:admin4_code":"80443",
    "gn:asciiname":"Tronchoy",
    "gn:country_code":"FR",
    "gn:dem":174,
    "gn:feature_class":"P",
    "gn:feature_code":"PPL",
    "gn:name":"Tronchoy",
    "gn:population":0,
    "gn:timezone":"Europe/Paris",
    "iso:country":"FR",
    "name:bug_x_preferred":[
        "Tronchoy"
    ],
    "name:cat_x_preferred":[
        "Tronchoy"
    ],
    "name:ceb_x_preferred":[
        "Tronchoy"
    ],
    "name:deu_x_preferred":[
        "Tronchoy"
    ],
    "name:epo_x_preferred":[
        "Tronchoy"
    ],
    "name:eus_x_preferred":[
        "Tronchoy"
    ],
    "name:fra_x_preferred":[
        "Tronchoy"
    ],
    "name:hun_x_preferred":[
        "Tronchoy"
    ],
    "name:ita_x_preferred":[
        "Tronchoy"
    ],
    "name:kaz_x_preferred":[
        "\u0422\u0440\u043e\u043d\u0448\u0443\u0430"
    ],
    "name:lat_x_preferred":[
        "Tronchoy"
    ],
    "name:msa_x_preferred":[
        "Tronchoy"
    ],
    "name:nld_x_preferred":[
        "Tronchoy"
    ],
    "name:oci_x_preferred":[
        "Tronchoy"
    ],
    "name:pms_x_preferred":[
        "Tronchoy"
    ],
    "name:pol_x_preferred":[
        "Tronchoy"
    ],
    "name:por_x_preferred":[
        "Tronchoy"
    ],
    "name:ron_x_preferred":[
        "Tronchoy"
    ],
    "name:slk_x_preferred":[
        "Tronchoy"
    ],
    "name:spa_x_preferred":[
        "Tronchoy"
    ],
    "name:swe_x_preferred":[
        "Tronchoy"
    ],
    "name:ukr_x_preferred":[
        "\u0422\u0440\u043e\u043d\u0448\u0443\u0430"
    ],
    "name:uzb_x_preferred":[
        "Tronchoy"
    ],
    "name:vie_x_preferred":[
        "Tronchoy"
    ],
    "name:vol_x_preferred":[
        "Tronchoy"
    ],
    "name:war_x_preferred":[
        "Tronchoy"
    ],
    "name:zho_x_preferred":[
        "\u7279\u9f99\u8212\u74e6"
    ],
    "wof:name":"Tronchoy",
    "wof:placetype":"locality"
},
  "geometry": {"coordinates":[1.86502,49.82673],"type":"Point"}
}