{
  "type": "Feature",
  "properties": {
    "gn:gn_country":"FR",
    "gn:gn_fcode":"PPL",
    "gn:gn_pop":111,
    "gn:population":111,
    "iso:country":"FR",
    "name:unk_x_variant":[
        "Saint Boys"
    ],
    "qs_pg:aaroncc":"FR",
    "qs_pg:gn_country":"FR",
    "qs_pg:gn_fcode":"PPL",
    "qs_pg:gn_pop":111,
    "qs_pg:name":"St.-Bois",
    "qs_pg:name_adm0":"France",
    "qs_pg:name_adm1":"Rh\u00f4ne-Alpes",
    "qs_pg:photos_9r":0,
    "qs_pg:photos_sr":0,
    "qs_pg:pop_sr":1,
    "qs_pg:qs_pg_placetype":"locality",
    "qs_pg:qs_pg_placetype_gp":"Town",
    "qs_pg:woe_adm0":23424819,
    "woe:adm0_id":23424819,
    "woe:name_adm0":"France",
    "woe:name_adm1":"Rh\u00f4ne-Alpes",
    "woe:placetype":"Town",
    "wof:name":"St.-Bois",
    "wof:placetype":"neighbourhood",
    "wof:population":111
},
  "geometry": {"coordinates":[5.64119,45.70089],"type":"Point"}
}