{
  "type": "Feature",
  "properties": {
    "gn:admin1_code":"93",
    "gn:admin2_code":"83",
    "gn:admin3_code":"833",
    "gn:admin4_code":"83060",
    "gn:asciiname":"Amphoux",
    "gn:country_code":"FR",
    "gn:dem":421,
    "gn:feature_class":"P",
    "gn:feature_code":"PPL",
    "gn:name":"Amphoux",
    "gn:population":0,
    "gn:timezone":"Europe/Paris",
    "iso:country":"FR",
    "wof:name":"Amphoux",
    "wof:placetype":"locality"
},
  "geometry": {"coordinates":[6.10789,43.59582],"type":"Point"}
}