{
  "type": "Feature",
  "properties": {
    "gn:admin1_code":"27",
    "gn:admin2_code":"39",
    "gn:admin3_code":"392",
    "gn:admin4_code":"39209",
    "gn:asciiname":"Poisoux",
    "gn:country_code":"FR",
    "gn:dem":454,
    "gn:feature_class":"P",
    "gn:feature_code":"PPL",
    "gn:name":"Poisoux",
    "gn:population":0,
    "gn:timezone":"Europe/Paris",
    "iso:country":"FR",
    "wof:name":"Poisoux",
    "wof:placetype":"locality"
},
  "geometry": {"coordinates":[5.37856,46.37074000000001],"type":"Point"}
}