{
  "type": "Feature",
  "properties": {
    "gn:admin1_code":"53",
    "gn:admin2_code":"35",
    "gn:admin3_code":"353",
    "gn:admin4_code":"35334",
    "gn:asciiname":"Thorigne-Fouillard",
    "gn:cc2":"FR",
    "gn:country_code":"FR",
    "gn:dem":65,
    "gn:feature_class":"P",
    "gn:feature_code":"PPL",
    "gn:name":"Thorign\u00e9-Fouillard",
    "gn:population":0,
    "gn:timezone":"Europe/Paris",
    "iso:country":"FR",
    "name:und_x_variant":[
        "Thorign\u00e9",
        "Thorign\u00e9-sur-Vilaine"
    ],
    "wof:name":"Thorigne-Fouillard",
    "wof:placetype":"locality"
},
  "geometry": {"coordinates":[-1.58333,48.15],"type":"Point"}
}