{
  "type": "Feature",
  "properties": {
    "gn:admin1_code":"24",
    "gn:admin2_code":"28",
    "gn:admin3_code":"282",
    "gn:admin4_code":"28246",
    "gn:asciiname":"Andeville",
    "gn:country_code":"FR",
    "gn:dem":147,
    "gn:feature_class":"P",
    "gn:feature_code":"PPL",
    "gn:name":"Andeville",
    "gn:population":0,
    "gn:timezone":"Europe/Paris",
    "iso:country":"FR",
    "name:cat_x_preferred":[
        "Andeville"
    ],
    "name:ceb_x_preferred":[
        "Andeville"
    ],
    "name:deu_x_preferred":[
        "Andeville"
    ],
    "name:eus_x_preferred":[
        "Andeville"
    ],
    "name:fra_x_preferred":[
        "Andeville"
    ],
    "name:hun_x_preferred":[
        "Andeville"
    ],
    "name:ind_x_preferred":[
        "Andeville"
    ],
    "name:ita_x_preferred":[
        "Andeville"
    ],
    "name:lat_x_preferred":[
        "Andeville"
    ],
    "name:mlg_x_preferred":[
        "Andeville"
    ],
    "name:msa_x_preferred":[
        "Andeville"
    ],
    "name:nld_x_preferred":[
        "Andeville"
    ],
    "name:oci_x_preferred":[
        "Andeville"
    ],
    "name:pol_x_preferred":[
        "Andeville"
    ],
    "name:ron_x_preferred":[
        "Andeville"
    ],
    "name:rus_x_preferred":[
        "\u0410\u043d\u0434\u0435\u0432\u0438\u043b\u044c"
    ],
    "name:slk_x_preferred":[
        "Andeville"
    ],
    "name:spa_x_preferred":[
        "Andeville"
    ],
    "name:srp_x_preferred":[
        "\u041e\u043d\u0434\u0435\u0432\u0438\u0458"
    ],
    "name:swe_x_preferred":[
        "Andeville"
    ],
    "name:ukr_x_preferred":[
        "\u0410\u043d\u0434\u0435\u0432\u0456\u043b\u044c"
    ],
    "name:uzb_x_preferred":[
        "Andeville"
    ],
    "name:vie_x_preferred":[
        "Andeville"
    ],
    "name:vol_x_preferred":[
        "Andeville"
    ],
    "name:war_x_preferred":[
        "Andeville"
    ],
    "name:zho_x_preferred":[
        "\u6602\u5fb7\u7ef4\u5c14"
    ],
    "wof:name":"Andeville",
    "wof:placetype":"locality"
},
  "geometry": {"coordinates":[1.4903,48.28452],"type":"Point"}
}