{
  "type": "Feature",
  "properties": {
    "gn:admin1_code":"84",
    "gn:admin2_code":"03",
    "gn:admin3_code":"032",
    "gn:admin4_code":"03286",
    "gn:asciiname":"Les Segauds",
    "gn:country_code":"FR",
    "gn:dem":268,
    "gn:feature_class":"P",
    "gn:feature_code":"PPL",
    "gn:name":"Les S\u00e9gauds",
    "gn:population":0,
    "gn:timezone":"Europe/Paris",
    "iso:country":"FR",
    "wof:name":"Les Segauds",
    "wof:placetype":"locality"
},
  "geometry": {"coordinates":[3.39819,46.52466],"type":"Point"}
}