{
  "type": "Feature",
  "properties": {
    "gn:admin1_code":"84",
    "gn:admin2_code":"03",
    "gn:admin3_code":"032",
    "gn:admin4_code":"03155",
    "gn:asciiname":"La Cinardiere",
    "gn:country_code":"FR",
    "gn:dem":246,
    "gn:feature_class":"P",
    "gn:feature_code":"PPL",
    "gn:name":"La Cinardi\u00e8re",
    "gn:population":0,
    "gn:timezone":"Europe/Paris",
    "iso:country":"FR",
    "wof:name":"La Cinardiere",
    "wof:placetype":"locality"
},
  "geometry": {"coordinates":[2.88333,46.71667],"type":"Point"}
}