{
  "type": "Feature",
  "properties": {
    "gn:country":"FR",
    "gn:fcode":"PPL",
    "gn:population":12966,
    "iso:country":"FR",
    "name:und_x_variant":[
        "Valfin"
    ],
    "qs_pg:aaroncc":"FR",
    "qs_pg:gn_country":"FR",
    "qs_pg:gn_fcode":"PPL",
    "qs_pg:gn_pop":12966,
    "qs_pg:name":"Valfin-l\u00e8s-St.-Claude",
    "qs_pg:name_adm0":"France",
    "qs_pg:name_adm1":"Franche-Comt\u00e9",
    "qs_pg:photos_9k":1,
    "qs_pg:photos_9r":1,
    "qs_pg:photos_all":1,
    "qs_pg:photos_sr":0,
    "qs_pg:pop_sr":6,
    "qs_pg:qs_pg_placetype":"locality",
    "qs_pg:qs_pg_placetype_gp":"Town",
    "qs_pg:woe_adm0":23424819,
    "woe:adm0_id":23424819,
    "woe:name_adm0":"France",
    "woe:name_adm1":"Franche-Comt\u00e9",
    "woe:placetype":"Town",
    "wof:name":"Valfin-l\u00e8s-St.-Claude",
    "wof:placetype":"neighbourhood",
    "wof:population":12966
},
  "geometry": {"coordinates":[5.85513,46.43758],"type":"Point"}
}