{
  "type": "Feature",
  "properties": {
    "gn:admin1_code":"11",
    "gn:admin2_code":"92",
    "gn:admin3_code":"921",
    "gn:admin4_code":"92002.0",
    "gn:asciiname":"Le Pont-d'Antony",
    "gn:country_code":"FR",
    "gn:dem":52,
    "gn:feature_class":"P",
    "gn:feature_code":"PPL",
    "gn:name":"Le Pont-d\u2019Antony",
    "gn:population":0,
    "gn:timezone":"Europe/Paris",
    "iso:country":"FR",
    "wof:name":"Le Pont-d'Antony",
    "wof:placetype":"locality"
},
  "geometry": {"coordinates":[2.30506,48.75228],"type":"Point"}
}