{
  "type": "Feature",
  "properties": {
    "gn:admin1_code":"75",
    "gn:admin2_code":"33",
    "gn:admin3_code":"334",
    "gn:admin4_code":"33493",
    "gn:asciiname":"Queyzans",
    "gn:country_code":"FR",
    "gn:dem":5,
    "gn:feature_class":"P",
    "gn:feature_code":"PPL",
    "gn:name":"Queyzans",
    "gn:population":0,
    "gn:timezone":"Europe/Paris",
    "iso:country":"FR",
    "wof:name":"Queyzans",
    "wof:placetype":"locality"
},
  "geometry": {"coordinates":[-0.81607,45.33571],"type":"Point"}
}