{
  "type": "Feature",
  "properties": {
    "gn:admin1_code":"11",
    "gn:admin2_code":"77",
    "gn:admin3_code":"774",
    "gn:admin4_code":"77158",
    "gn:asciiname":"Les Joncheries",
    "gn:country_code":"FR",
    "gn:dem":137,
    "gn:feature_class":"P",
    "gn:feature_code":"PPL",
    "gn:name":"Les Joncheries",
    "gn:population":0,
    "gn:timezone":"Europe/Paris",
    "iso:country":"FR",
    "wof:name":"Les Joncheries",
    "wof:placetype":"locality"
},
  "geometry": {"coordinates":[3.00576,48.30034000000001],"type":"Point"}
}