{
  "type": "Feature",
  "properties": {
    "iso:country":"FR",
    "name:eng_x_preferred":[
        "Cristaller-Manufacture"
    ],
    "name:fra_x_preferred":[
        "Cristaller-Manufacture"
    ],
    "wof:name":"Cristaller-Manufacture",
    "wof:placetype":"neighbourhood"
},
  "geometry": {"coordinates":[2.22075298675699,48.82540879134663],"type":"Point"}
}