{
  "type": "Feature",
  "properties": {
    "gn:admin1_code":"76",
    "gn:admin2_code":"12",
    "gn:admin3_code":"121",
    "gn:admin4_code":"12270",
    "gn:asciiname":"Le Samonta",
    "gn:country_code":"FR",
    "gn:dem":601,
    "gn:feature_class":"P",
    "gn:feature_code":"PPL",
    "gn:name":"Le Samonta",
    "gn:population":0,
    "gn:timezone":"Europe/Paris",
    "iso:country":"FR",
    "wof:name":"Le Samonta",
    "wof:placetype":"locality"
},
  "geometry": {"coordinates":[3.13223,44.24329],"type":"Point"}
}