{
  "type": "Feature",
  "properties": {
    "gn:admin1_code":"28",
    "gn:admin2_code":"76",
    "gn:admin3_code":"761",
    "gn:admin4_code":"76619",
    "gn:asciiname":"Etocquigny",
    "gn:country_code":"FR",
    "gn:dem":101,
    "gn:feature_class":"P",
    "gn:feature_code":"PPL",
    "gn:name":"\u00c9tocquigny",
    "gn:population":0,
    "gn:timezone":"Europe/Paris",
    "iso:country":"FR",
    "wof:name":"Etocquigny",
    "wof:placetype":"locality"
},
  "geometry": {"coordinates":[1.37873,49.98801],"type":"Point"}
}