{
  "type": "Feature",
  "properties": {
    "iso:country":"FR",
    "name:eng_x_preferred":[
        "Le Plateau"
    ],
    "name:fra_x_preferred":[
        "Le Plateau"
    ],
    "name:fra_x_variant":[
        "Plateau"
    ],
    "wof:name":"Le Plateau",
    "wof:placetype":"neighbourhood"
},
  "geometry": {"coordinates":[2.52725440748877,48.89794137307564],"type":"Point"}
}