{
  "type": "Feature",
  "properties": {
    "gn:admin1_code":"24",
    "gn:admin2_code":"28",
    "gn:admin3_code":"281",
    "gn:admin4_code":"28406",
    "gn:asciiname":"Ohe",
    "gn:country_code":"FR",
    "gn:dem":137,
    "gn:feature_class":"P",
    "gn:feature_code":"PPL",
    "gn:name":"Oh\u00e9",
    "gn:population":0,
    "gn:timezone":"Europe/Paris",
    "iso:country":"FR",
    "name:ceb_x_preferred":[
        "Ohe"
    ],
    "name:deu_x_preferred":[
        "Ohe"
    ],
    "name:nld_x_preferred":[
        "Ohe"
    ],
    "name:swe_x_preferred":[
        "Ohe"
    ],
    "wof:name":"Ohe",
    "wof:placetype":"locality"
},
  "geometry": {"coordinates":[1.67786,48.19466],"type":"Point"}
}