{
  "type": "Feature",
  "properties": {
    "iso:country":"FR",
    "name:eng_x_preferred":[
        "Le Rondeau"
    ],
    "name:fra_x_preferred":[
        "Le Rondeau"
    ],
    "wof:name":"Le Rondeau",
    "wof:placetype":"neighbourhood"
},
  "geometry": {"coordinates":[5.70650605518333,45.16272342873993],"type":"Point"}
}