{
  "type": "Feature",
  "properties": {
    "gn:admin1_code":"75",
    "gn:admin2_code":"19",
    "gn:admin3_code":"191",
    "gn:admin4_code":"19230",
    "gn:asciiname":"Sageau",
    "gn:country_code":"FR",
    "gn:dem":406,
    "gn:feature_class":"P",
    "gn:feature_code":"PPL",
    "gn:name":"Sageau",
    "gn:population":0,
    "gn:timezone":"Europe/Paris",
    "iso:country":"FR",
    "wof:name":"Sageau",
    "wof:placetype":"locality"
},
  "geometry": {"coordinates":[1.47132,45.41775],"type":"Point"}
}