{
  "type": "Feature",
  "properties": {
    "gn:admin1_code":"24",
    "gn:admin2_code":"18",
    "gn:admin3_code":"181",
    "gn:admin4_code":"18184",
    "gn:asciiname":"Les Chaumes-de-Loudin",
    "gn:country_code":"FR",
    "gn:dem":182,
    "gn:feature_class":"P",
    "gn:feature_code":"PPL",
    "gn:name":"Les Chaumes-de-Loudin",
    "gn:population":0,
    "gn:timezone":"Europe/Paris",
    "iso:country":"FR",
    "wof:name":"Les Chaumes-de-Loudin",
    "wof:placetype":"locality"
},
  "geometry": {"coordinates":[2.93189,47.08564000000001],"type":"Point"}
}