{
  "type": "Feature",
  "properties": {
    "gn:admin1_code":"24",
    "gn:admin2_code":"28",
    "gn:admin3_code":"282",
    "gn:admin4_code":"28398",
    "gn:asciiname":"Les Lheoris",
    "gn:country_code":"FR",
    "gn:dem":215,
    "gn:feature_class":"P",
    "gn:feature_code":"PPL",
    "gn:name":"Les Lh\u00e9oris",
    "gn:population":0,
    "gn:timezone":"Europe/Paris",
    "iso:country":"FR",
    "wof:name":"Les Lheoris",
    "wof:placetype":"locality"
},
  "geometry": {"coordinates":[0.97639,48.20156],"type":"Point"}
}