{
  "type": "Feature",
  "properties": {
    "gn:admin1_code":"75",
    "gn:admin2_code":"19",
    "gn:admin3_code":"192",
    "gn:admin4_code":"19007",
    "gn:asciiname":"Fontmerle",
    "gn:cc2":"FR",
    "gn:country_code":"FR",
    "gn:dem":331,
    "gn:feature_class":"P",
    "gn:feature_code":"PPL",
    "gn:name":"Fontmerle",
    "gn:population":0,
    "gn:timezone":"Europe/Paris",
    "iso:country":"FR",
    "name:und_x_variant":[
        "Fonmerle",
        "Fontmerle"
    ],
    "wof:name":"Fontmerle",
    "wof:placetype":"locality"
},
  "geometry": {"coordinates":[1.87652,44.96207],"type":"Point"}
}