{
  "type": "Feature",
  "properties": {
    "gn:admin1_code":"84",
    "gn:admin2_code":"73",
    "gn:admin3_code":"731",
    "gn:admin4_code":"73187",
    "gn:asciiname":"Naves",
    "gn:country_code":"FR",
    "gn:dem":1331,
    "gn:feature_class":"P",
    "gn:feature_code":"PPL",
    "gn:name":"Naves",
    "gn:population":0,
    "gn:timezone":"Europe/Paris",
    "iso:country":"FR",
    "wof:name":"Naves",
    "wof:placetype":"locality"
},
  "geometry": {"coordinates":[6.52221,45.55971],"type":"Point"}
}