{
  "type": "Feature",
  "properties": {
    "gn:admin1_code":"75",
    "gn:admin2_code":"64",
    "gn:admin3_code":"641",
    "gn:admin4_code":"64065",
    "gn:asciiname":"Serres",
    "gn:country_code":"FR",
    "gn:dem":46,
    "gn:feature_class":"P",
    "gn:feature_code":"PPL",
    "gn:name":"Serres",
    "gn:population":0,
    "gn:timezone":"Europe/Paris",
    "iso:country":"FR",
    "wof:name":"Serres",
    "wof:placetype":"locality"
},
  "geometry": {"coordinates":[-1.62132,43.36063],"type":"Point"}
}