{
  "type": "Feature",
  "properties": {
    "gn:admin1_code":"75",
    "gn:admin2_code":"64",
    "gn:admin3_code":"641",
    "gn:admin4_code":"64065",
    "gn:asciiname":"Serres",
    "gn:country_code":"FR",
    "gn:dem":46,
    "gn:feature_class":"P",
    "gn:feature_code":"PPL",
    "gn:name":"Serres",
    "gn:population":0,
    "gn:timezone":"Europe/Paris",
    "iso:country":"FR",
    "name:ara_x_preferred":[
        "\u0633\u064a\u0631\u0633"
    ],
    "name:bel_x_preferred":[
        "\u0421\u0435\u0440\u044d"
    ],
    "name:bul_x_preferred":[
        "\u0421\u044f\u0440"
    ],
    "name:cat_x_preferred":[
        "Serres"
    ],
    "name:ceb_x_preferred":[
        "S\u00e9rres"
    ],
    "name:chu_x_preferred":[
        "\u0421\u0463\u0440\u044a"
    ],
    "name:deu_x_preferred":[
        "Serres"
    ],
    "name:ell_x_preferred":[
        "\u03a3\u03ad\u03c1\u03c1\u03b5\u03c2"
    ],
    "name:epo_x_preferred":[
        "Seres"
    ],
    "name:eus_x_preferred":[
        "Serres"
    ],
    "name:fas_x_preferred":[
        "\u0633\u0631\u0633"
    ],
    "name:fin_x_preferred":[
        "S\u00e9rres"
    ],
    "name:fra_x_preferred":[
        "Serr\u00e8s"
    ],
    "name:heb_x_preferred":[
        "\u05e1\u05e8\u05e1"
    ],
    "name:hrv_x_preferred":[
        "Ser"
    ],
    "name:hye_x_preferred":[
        "\u054d\u0565\u0580\u0565\u057d"
    ],
    "name:ind_x_preferred":[
        "Serres"
    ],
    "name:isl_x_preferred":[
        "Serres"
    ],
    "name:ita_x_preferred":[
        "Serres"
    ],
    "name:jpn_x_preferred":[
        "\u30bb\u30ec\u30b9"
    ],
    "name:kor_x_preferred":[
        "\uc138\ub808\uc2a4"
    ],
    "name:lat_x_preferred":[
        "Serrhae"
    ],
    "name:lit_x_preferred":[
        "Ser\u0117s"
    ],
    "name:mkd_x_preferred":[
        "\u0421\u0435\u0440"
    ],
    "name:nld_x_preferred":[
        "Serres"
    ],
    "name:nno_x_preferred":[
        "S\u00e9rres"
    ],
    "name:nor_x_preferred":[
        "S\u00e9rres"
    ],
    "name:pnt_x_preferred":[
        "\u03a3\u03ad\u03c1\u03c1\u03b5\u03c2"
    ],
    "name:pol_x_preferred":[
        "Seres"
    ],
    "name:por_x_preferred":[
        "Serres"
    ],
    "name:ron_x_preferred":[
        "Serres"
    ],
    "name:rus_x_preferred":[
        "\u0421\u0435\u0440\u0435"
    ],
    "name:sco_x_preferred":[
        "Serres"
    ],
    "name:spa_x_preferred":[
        "Serres"
    ],
    "name:srp_x_preferred":[
        "\u0421\u0435\u0440"
    ],
    "name:swe_x_preferred":[
        "Serrai"
    ],
    "name:tur_x_preferred":[
        "Serez"
    ],
    "name:ukr_x_preferred":[
        "\u0421\u0435\u0440\u0435"
    ],
    "name:urd_x_preferred":[
        "\u0633\u06cc\u0631\u0633"
    ],
    "name:vie_x_preferred":[
        "Serres"
    ],
    "name:war_x_preferred":[
        "Serres"
    ],
    "name:zho_x_preferred":[
        "\u585e\u96f7"
    ],
    "wof:name":"Serres",
    "wof:placetype":"locality"
},
  "geometry": {"coordinates":[-1.62132,43.36063],"type":"Point"}
}