{
  "type": "Feature",
  "properties": {
    "gn:admin1_code":"84",
    "gn:admin2_code":"63",
    "gn:admin3_code":"632",
    "gn:admin4_code":"63045",
    "gn:asciiname":"Morel",
    "gn:country_code":"FR",
    "gn:dem":402,
    "gn:feature_class":"P",
    "gn:feature_code":"PPL",
    "gn:name":"Morel",
    "gn:population":0,
    "gn:timezone":"Europe/Paris",
    "iso:country":"FR",
    "wof:name":"Morel",
    "wof:placetype":"locality"
},
  "geometry": {"coordinates":[3.41351,45.77813],"type":"Point"}
}