{
  "type": "Feature",
  "properties": {
    "gn:admin1_code":"75",
    "gn:admin2_code":"40",
    "gn:admin3_code":"402",
    "gn:admin4_code":"40182",
    "gn:asciiname":"Lisacq",
    "gn:country_code":"FR",
    "gn:dem":56,
    "gn:feature_class":"P",
    "gn:feature_code":"PPL",
    "gn:name":"Lisacq",
    "gn:population":0,
    "gn:timezone":"Europe/Paris",
    "iso:country":"FR",
    "wof:name":"Lisacq",
    "wof:placetype":"locality"
},
  "geometry": {"coordinates":[-1.15086,44.12769],"type":"Point"}
}