{
  "type": "Feature",
  "properties": {
    "gn:admin1_code":"75",
    "gn:admin2_code":"47",
    "gn:admin3_code":"473",
    "gn:admin4_code":"47182",
    "gn:asciiname":"Jolibet",
    "gn:country_code":"FR",
    "gn:dem":115,
    "gn:feature_class":"P",
    "gn:feature_code":"PPL",
    "gn:name":"Jolibet",
    "gn:population":0,
    "gn:timezone":"Europe/Paris",
    "iso:country":"FR",
    "wof:name":"Jolibet",
    "wof:placetype":"locality"
},
  "geometry": {"coordinates":[0.51391,44.50545],"type":"Point"}
}