{
  "type": "Feature",
  "properties": {
    "gn:admin1_code":"75",
    "gn:admin2_code":"17",
    "gn:admin3_code":"172",
    "gn:admin4_code":"17353",
    "gn:asciiname":"Charras",
    "gn:country_code":"FR",
    "gn:dem":16,
    "gn:feature_class":"P",
    "gn:feature_code":"PPL",
    "gn:name":"Charras",
    "gn:population":0,
    "gn:timezone":"Europe/Paris",
    "iso:country":"FR",
    "name:cat_x_preferred":[
        "Charr\u00e0s"
    ],
    "name:ceb_x_preferred":[
        "Charras"
    ],
    "name:deu_x_preferred":[
        "Charras"
    ],
    "name:eus_x_preferred":[
        "Charras"
    ],
    "name:fra_x_preferred":[
        "Charras"
    ],
    "name:hun_x_preferred":[
        "Charras"
    ],
    "name:hye_x_preferred":[
        "\u0547\u0561\u0580\u0580\u0561"
    ],
    "name:ita_x_preferred":[
        "Charras"
    ],
    "name:lat_x_preferred":[
        "Charras"
    ],
    "name:msa_x_preferred":[
        "Charras"
    ],
    "name:nld_x_preferred":[
        "Charras"
    ],
    "name:oci_x_preferred":[
        "Charre\u00e7"
    ],
    "name:pol_x_preferred":[
        "Charras"
    ],
    "name:por_x_preferred":[
        "Charras"
    ],
    "name:ron_x_preferred":[
        "Charras"
    ],
    "name:rus_x_preferred":[
        "\u0428\u0430\u0440\u0440\u0430"
    ],
    "name:slk_x_preferred":[
        "Charras"
    ],
    "name:spa_x_preferred":[
        "Charras"
    ],
    "name:srp_x_preferred":[
        "\u0428\u0430\u0440\u0430"
    ],
    "name:swe_x_preferred":[
        "Charras"
    ],
    "name:ukr_x_preferred":[
        "\u0428\u0430\u0440\u0440\u0430"
    ],
    "name:vie_x_preferred":[
        "Charras"
    ],
    "name:vol_x_preferred":[
        "Charras"
    ],
    "name:war_x_preferred":[
        "Charras"
    ],
    "name:zho_x_preferred":[
        "\u6c99\u5c14\u62c9"
    ],
    "wof:name":"Charras",
    "wof:placetype":"locality"
},
  "geometry": {"coordinates":[-1.00867,45.9837],"type":"Point"}
}