{
  "type": "Feature",
  "properties": {
    "gn:admin1_code":"75",
    "gn:admin2_code":"17",
    "gn:admin3_code":"172",
    "gn:admin4_code":"17353",
    "gn:asciiname":"Charras",
    "gn:country_code":"FR",
    "gn:dem":16,
    "gn:feature_class":"P",
    "gn:feature_code":"PPL",
    "gn:name":"Charras",
    "gn:population":0,
    "gn:timezone":"Europe/Paris",
    "iso:country":"FR",
    "wof:name":"Charras",
    "wof:placetype":"locality"
},
  "geometry": {"coordinates":[-1.00867,45.9837],"type":"Point"}
}