{
  "type": "Feature",
  "properties": {
    "gn:admin1_code":"53",
    "gn:admin2_code":"22",
    "gn:admin3_code":"224",
    "gn:admin4_code":"22241",
    "gn:asciiname":"Saint-Leau",
    "gn:country_code":"FR",
    "gn:dem":128,
    "gn:feature_class":"P",
    "gn:feature_code":"PPL",
    "gn:name":"Saint-Leau",
    "gn:population":0,
    "gn:timezone":"Europe/Paris",
    "iso:country":"FR",
    "wof:name":"Saint-Leau",
    "wof:placetype":"locality"
},
  "geometry": {"coordinates":[-2.59767,48.09396],"type":"Point"}
}