{
  "type": "Feature",
  "properties": {
    "gn:admin1_code":"24",
    "gn:admin2_code":"18",
    "gn:admin3_code":"182",
    "gn:admin4_code":"18212",
    "gn:asciiname":"La Pierre",
    "gn:country_code":"FR",
    "gn:dem":166,
    "gn:feature_class":"P",
    "gn:feature_code":"PPL",
    "gn:name":"La Pierre",
    "gn:population":0,
    "gn:timezone":"Europe/Paris",
    "iso:country":"FR",
    "wof:name":"La Pierre",
    "wof:placetype":"locality"
},
  "geometry": {"coordinates":[2.44843,46.87481],"type":"Point"}
}