{
  "type": "Feature",
  "properties": {
    "iso:country":"FR",
    "name:eng_x_preferred":[
        "Adamville"
    ],
    "name:fra_x_preferred":[
        "Adamville"
    ],
    "wof:name":"Adamville",
    "wof:placetype":"neighbourhood"
},
  "geometry": {"coordinates":[2.48601104299313,48.79825737684686],"type":"Point"}
}