{
  "type": "Feature",
  "properties": {
    "gn:admin1_code":"76",
    "gn:admin2_code":"12",
    "gn:admin3_code":"122",
    "gn:admin4_code":"12093",
    "gn:asciiname":"Enguiales",
    "gn:country_code":"FR",
    "gn:dem":476,
    "gn:feature_class":"P",
    "gn:feature_code":"PPL",
    "gn:name":"Enguial\u00e8s",
    "gn:population":0,
    "gn:timezone":"Europe/Paris",
    "iso:country":"FR",
    "name:und_x_variant":[
        "Enguial\u00e8s"
    ],
    "wof:name":"Enguiales",
    "wof:placetype":"locality"
},
  "geometry": {"coordinates":[2.52971,44.65891],"type":"Point"}
}