{
  "type": "Feature",
  "properties": {
    "gn:admin1_code":"53",
    "gn:admin2_code":"22",
    "gn:admin3_code":"221",
    "gn:admin4_code":"22371",
    "gn:asciiname":"La Billiaye",
    "gn:country_code":"FR",
    "gn:dem":116,
    "gn:feature_class":"P",
    "gn:feature_code":"PPL",
    "gn:name":"La Billiaye",
    "gn:population":0,
    "gn:timezone":"Europe/Paris",
    "iso:country":"FR",
    "wof:name":"La Billiaye",
    "wof:placetype":"locality"
},
  "geometry": {"coordinates":[-2.32302,48.18126],"type":"Point"}
}