{
  "type": "Feature",
  "properties": {
    "iso:country":"FR",
    "name:eng_x_preferred":[
        "Arlequin"
    ],
    "name:fra_x_preferred":[
        "Arlequin"
    ],
    "wof:name":"Arlequin",
    "wof:placetype":"neighbourhood"
},
  "geometry": {"coordinates":[5.73188327562981,45.16506344783959],"type":"Point"}
}