{
  "type": "Feature",
  "properties": {
    "gn:admin1_code":"84",
    "gn:admin2_code":"38",
    "gn:admin3_code":"381",
    "gn:admin4_code":"38334",
    "gn:asciiname":"Les Molettes",
    "gn:country_code":"FR",
    "gn:dem":938,
    "gn:feature_class":"P",
    "gn:feature_code":"PPL",
    "gn:name":"Les Molettes",
    "gn:population":0,
    "gn:timezone":"Europe/Paris",
    "iso:country":"FR",
    "name:und_x_variant":[
        "les Mollettes",
        "Les Molettes"
    ],
    "wof:name":"Les Molettes",
    "wof:placetype":"locality"
},
  "geometry": {"coordinates":[5.89208,45.18358],"type":"Point"}
}