{
  "type": "Feature",
  "properties": {
    "iso:country":"FR",
    "name:eng_x_preferred":[
        "Le Parc Saint-Maur"
    ],
    "name:fra_x_preferred":[
        "Le Parc Saint-Maur"
    ],
    "wof:name":"Le Parc Saint-Maur",
    "wof:placetype":"neighbourhood"
},
  "geometry": {"coordinates":[2.49608184884152,48.80564443380693],"type":"Point"}
}