{
  "type": "Feature",
  "properties": {
    "iso:country":"FO",
    "name:ara_x_preferred":[
        "\u062a\u0648\u0641\u062a\u064a\u0631"
    ],
    "name:arz_x_preferred":[
        "\u062a\u0648\u0641\u062a\u064a\u0631"
    ],
    "name:cat_x_preferred":[
        "Toftir"
    ],
    "name:ces_x_preferred":[
        "Toftir"
    ],
    "name:dan_x_preferred":[
        "Toftir"
    ],
    "name:deu_x_preferred":[
        "Toftir"
    ],
    "name:eng_x_preferred":[
        "Toftir"
    ],
    "name:fao_x_preferred":[
        "Toftir"
    ],
    "name:fin_x_preferred":[
        "Toftir"
    ],
    "name:fra_x_preferred":[
        "Toftir"
    ],
    "name:glv_x_preferred":[
        "Toftir"
    ],
    "name:hun_x_preferred":[
        "Toftir"
    ],
    "name:isl_x_preferred":[
        "Toftir"
    ],
    "name:ita_x_preferred":[
        "Toftir"
    ],
    "name:kor_x_preferred":[
        "\ud1a0\ud504\ud2f0\ub974"
    ],
    "name:lit_x_preferred":[
        "Toftiras"
    ],
    "name:nld_x_preferred":[
        "Toftir"
    ],
    "name:nob_x_preferred":[
        "Toftir"
    ],
    "name:nor_x_preferred":[
        "Toftir"
    ],
    "name:pol_x_preferred":[
        "Toftir"
    ],
    "name:ron_x_preferred":[
        "Toftir"
    ],
    "name:rus_x_preferred":[
        "\u0422\u043e\u0444\u0442\u0438\u0440"
    ],
    "name:slk_x_preferred":[
        "Toftir"
    ],
    "name:spa_x_preferred":[
        "Toftir"
    ],
    "name:swe_x_preferred":[
        "Toftir"
    ],
    "name:unk_x_variant":[
        "Tofte"
    ],
    "name:zho_x_preferred":[
        "\u6258\u592b\u8fea\u4e9e"
    ],
    "qs:a0":"Foroyar#F\u00e6r\u00f8erne",
    "qs:a1":"*",
    "qs:a1r":"0",
    "qs:adm0":"Foroyar#F\u00e6r\u00f8erne",
    "qs:la_lc":"*",
    "qs:level":"locality",
    "qs:loc":"Toftir",
    "qs:loc_alt":"Toftir",
    "qs:pop":0,
    "qs:type":"buffered point",
    "wd:wordcount":603,
    "wof:name":"Toftir",
    "wof:placetype":"locality"
},
  "geometry": {"coordinates":[-6.736576,62.08878],"type":"Point"}
}