{
  "type": "Feature",
  "properties": {
    "iso:country":"FR",
    "name:eng_x_preferred":[
        "Lisiere Nord"
    ],
    "name:fra_x_preferred":[
        "Lisi\u00e8re Nord"
    ],
    "wof:name":"Lisiere Nord",
    "wof:placetype":"neighbourhood"
},
  "geometry": {"coordinates":[2.52496558797777,48.87461346546278],"type":"Point"}
}