{
  "type": "Feature",
  "properties": {
    "gn:admin1_code":"75",
    "gn:admin2_code":"86",
    "gn:admin3_code":"861",
    "gn:admin4_code":"86096",
    "gn:asciiname":"La Clozure",
    "gn:country_code":"FR",
    "gn:dem":81,
    "gn:feature_class":"P",
    "gn:feature_code":"PPL",
    "gn:name":"La Clozure",
    "gn:population":0,
    "gn:timezone":"Europe/Paris",
    "iso:country":"FR",
    "wof:name":"La Clozure",
    "wof:placetype":"locality"
},
  "geometry": {"coordinates":[0.29873,46.82195],"type":"Point"}
}