{
  "type": "Feature",
  "properties": {
    "gn:admin1_code":"84",
    "gn:admin2_code":"63",
    "gn:admin3_code":"631",
    "gn:admin4_code":"63221",
    "gn:asciiname":"La Fayolle",
    "gn:country_code":"FR",
    "gn:dem":1038,
    "gn:feature_class":"P",
    "gn:feature_code":"PPL",
    "gn:name":"La Fayolle",
    "gn:population":0,
    "gn:timezone":"Europe/Paris",
    "iso:country":"FR",
    "wof:name":"La Fayolle",
    "wof:placetype":"locality"
},
  "geometry": {"coordinates":[3.81632,45.42468],"type":"Point"}
}