{
  "type": "Feature",
  "properties": {
    "gn:admin1_code":"44",
    "gn:admin2_code":"10",
    "gn:admin3_code":"102",
    "gn:admin4_code":"10341",
    "gn:asciiname":"Pommereau",
    "gn:country_code":"FR",
    "gn:dem":128,
    "gn:feature_class":"P",
    "gn:feature_code":"PPL",
    "gn:name":"Pommereau",
    "gn:population":0,
    "gn:timezone":"Europe/Paris",
    "iso:country":"FR",
    "wof:name":"Pommereau",
    "wof:placetype":"locality"
},
  "geometry": {"coordinates":[3.63333,48.48333],"type":"Point"}
}