{
  "type": "Feature",
  "properties": {
    "gn:admin1_code":"75",
    "gn:admin2_code":"79",
    "gn:admin3_code":"791",
    "gn:admin4_code":"79103",
    "gn:asciiname":"La Laimiere",
    "gn:country_code":"FR",
    "gn:dem":216,
    "gn:feature_class":"P",
    "gn:feature_code":"PPL",
    "gn:name":"La Laimi\u00e8re",
    "gn:population":0,
    "gn:timezone":"Europe/Paris",
    "iso:country":"FR",
    "wof:name":"La Laimiere",
    "wof:placetype":"locality"
},
  "geometry": {"coordinates":[-0.58202,46.80452],"type":"Point"}
}