{
  "type": "Feature",
  "properties": {
    "gn:admin1_code":"24",
    "gn:admin2_code":"45",
    "gn:admin3_code":"453",
    "gn:admin4_code":"45191",
    "gn:asciiname":"Pinson",
    "gn:country_code":"FR",
    "gn:dem":87,
    "gn:feature_class":"P",
    "gn:feature_code":"PPL",
    "gn:name":"Pinson",
    "gn:population":0,
    "gn:timezone":"Europe/Paris",
    "iso:country":"FR",
    "name:deu_x_preferred":[
        "Pinson"
    ],
    "name:fra_x_preferred":[
        "Pinson"
    ],
    "name:ita_x_preferred":[
        "Pinson"
    ],
    "name:pol_x_preferred":[
        "Pinson"
    ],
    "name:por_x_preferred":[
        "Pinson"
    ],
    "name:rus_x_preferred":[
        "\u041f\u0438\u043d\u0441\u043e\u043d"
    ],
    "name:und_x_variant":[
        "Pin\u00e7on",
        "Pinson"
    ],
    "wof:name":"Pinson",
    "wof:placetype":"locality"
},
  "geometry": {"coordinates":[2.41624,48.28436],"type":"Point"}
}