{
  "type": "Feature",
  "properties": {
    "gn:admin1_code":"28",
    "gn:admin2_code":"76",
    "gn:admin3_code":"763",
    "gn:admin4_code":"76610",
    "gn:asciiname":"Le Meniltat",
    "gn:country_code":"FR",
    "gn:dem":151,
    "gn:feature_class":"P",
    "gn:feature_code":"PPL",
    "gn:name":"Le M\u00e9niltat",
    "gn:population":0,
    "gn:timezone":"Europe/Paris",
    "iso:country":"FR",
    "wof:name":"Le Meniltat",
    "wof:placetype":"locality"
},
  "geometry": {"coordinates":[0.7765,49.63037],"type":"Point"}
}