{
  "type": "Feature",
  "properties": {
    "gn:admin1_code":"11",
    "gn:admin2_code":"94",
    "gn:admin3_code":"941",
    "gn:admin4_code":"94068",
    "gn:asciiname":"Champignol",
    "gn:country_code":"FR",
    "gn:dem":48,
    "gn:feature_class":"P",
    "gn:feature_code":"PPL",
    "gn:name":"Champignol",
    "gn:population":0,
    "gn:timezone":"Europe/Paris",
    "iso:country":"FR",
    "wof:name":"Champignol",
    "wof:placetype":"locality"
},
  "geometry": {"coordinates":[2.5056,48.80865],"type":"Point"}
}