{
  "type": "Feature",
  "properties": {
    "gn:admin1_code":"84",
    "gn:admin2_code":"63",
    "gn:admin3_code":"633",
    "gn:admin4_code":"63458",
    "gn:asciiname":"Villeneuve",
    "gn:country_code":"FR",
    "gn:dem":530,
    "gn:feature_class":"P",
    "gn:feature_code":"PPL",
    "gn:name":"Villeneuve",
    "gn:population":139,
    "gn:timezone":"Europe/Paris",
    "iso:country":"FR",
    "name:als_x_preferred":[
        "Villeneuve"
    ],
    "name:bre_x_preferred":[
        "Villeneuve"
    ],
    "name:bul_x_preferred":[
        "\u0412\u0438\u043b\u043d\u044c\u043e\u0432"
    ],
    "name:cat_x_preferred":[
        "Villeneuve"
    ],
    "name:ceb_x_preferred":[
        "Villeneuve"
    ],
    "name:ces_x_preferred":[
        "Villeneuve"
    ],
    "name:deu_x_preferred":[
        "Villeneuve"
    ],
    "name:ell_x_preferred":[
        "\u0392\u03b9\u03bb\u03bd\u03ad\u03b2"
    ],
    "name:epo_x_preferred":[
        "Villeneuve"
    ],
    "name:eus_x_preferred":[
        "Villeneuve"
    ],
    "name:fas_x_preferred":[
        "\u0648\u06cc\u0646\u0648"
    ],
    "name:fin_x_preferred":[
        "Villeneuve"
    ],
    "name:fra_x_preferred":[
        "Villeneuve"
    ],
    "name:hun_x_preferred":[
        "Villeneuve"
    ],
    "name:hye_x_preferred":[
        "\u054e\u056b\u056c\u0576\u0575\u0578\u057e"
    ],
    "name:ita_x_preferred":[
        "Villeneuve"
    ],
    "name:jpn_x_preferred":[
        "\u30f4\u30a3\u30eb\u30cc\u30fc\u30f4"
    ],
    "name:kor_x_preferred":[
        "\ube4c\ub1cc\ube0c"
    ],
    "name:lav_x_preferred":[
        "Viln\u0113vs"
    ],
    "name:lmo_x_preferred":[
        "Villeneuve"
    ],
    "name:nds_x_preferred":[
        "Villeneuve"
    ],
    "name:nld_x_preferred":[
        "Villeneuve"
    ],
    "name:pms_x_preferred":[
        "Villeneuve"
    ],
    "name:pol_x_preferred":[
        "Villeneuve"
    ],
    "name:por_x_preferred":[
        "Villeneuve"
    ],
    "name:roh_x_preferred":[
        "Villeneuve"
    ],
    "name:ron_x_preferred":[
        "Villeneuve"
    ],
    "name:rus_x_preferred":[
        "\u0412\u0438\u043b\u044c\u043d\u0451\u0432"
    ],
    "name:sco_x_preferred":[
        "Villeneuve"
    ],
    "name:slk_x_preferred":[
        "Villeneuve"
    ],
    "name:slv_x_preferred":[
        "Villeneuve"
    ],
    "name:spa_x_preferred":[
        "Villeneuve"
    ],
    "name:swe_x_preferred":[
        "Villeneuve"
    ],
    "name:ukr_x_preferred":[
        "\u0412\u0456\u043b\u044c\u043d\u0435\u0432"
    ],
    "name:vie_x_preferred":[
        "Villeneuve"
    ],
    "name:vol_x_preferred":[
        "Villeneuve"
    ],
    "wof:name":"Villeneuve",
    "wof:placetype":"locality",
    "wof:population":139
},
  "geometry": {"coordinates":[3.18552,45.47758],"type":"Point"}
}