{
  "type": "Feature",
  "properties": {
    "gn:admin1_code":"84",
    "gn:admin2_code":"63",
    "gn:admin3_code":"633",
    "gn:admin4_code":"63458",
    "gn:asciiname":"Villeneuve",
    "gn:country_code":"FR",
    "gn:dem":530,
    "gn:feature_class":"P",
    "gn:feature_code":"PPL",
    "gn:name":"Villeneuve",
    "gn:population":139,
    "gn:timezone":"Europe/Paris",
    "iso:country":"FR",
    "wof:name":"Villeneuve",
    "wof:placetype":"locality",
    "wof:population":139
},
  "geometry": {"coordinates":[3.18552,45.47758],"type":"Point"}
}