{
  "type": "Feature",
  "properties": {
    "gn:admin1_code":"24",
    "gn:admin2_code":"18",
    "gn:admin3_code":"182",
    "gn:admin4_code":"18169",
    "gn:asciiname":"Nozieres",
    "gn:country_code":"FR",
    "gn:dem":208,
    "gn:feature_class":"P",
    "gn:feature_code":"PPL",
    "gn:name":"Nozi\u00e8res",
    "gn:population":230,
    "gn:timezone":"Europe/Paris",
    "iso:country":"FR",
    "name:und_x_variant":[
        "Nozi\u00e8res"
    ],
    "wof:name":"Nozieres",
    "wof:placetype":"locality",
    "wof:population":230
},
  "geometry": {"coordinates":[2.43457,46.7339],"type":"Point"}
}