{
  "type": "Feature",
  "properties": {
    "gn:admin1_code":"53",
    "gn:admin2_code":"35",
    "gn:admin3_code":"354",
    "gn:admin4_code":"35288",
    "gn:asciiname":"Moka",
    "gn:country_code":"FR",
    "gn:dem":8,
    "gn:elevation":"8.0",
    "gn:feature_class":"P",
    "gn:feature_code":"PPL",
    "gn:name":"Moka",
    "gn:population":0,
    "gn:timezone":"Europe/Paris",
    "iso:country":"FR",
    "wof:name":"Moka",
    "wof:placetype":"locality"
},
  "geometry": {"coordinates":[-2.00297,48.64958],"type":"Point"}
}