{
  "type": "Feature",
  "properties": {
    "gn:admin1_code":"53",
    "gn:admin2_code":"35",
    "gn:admin3_code":"354",
    "gn:admin4_code":"35288",
    "gn:asciiname":"Moka",
    "gn:country_code":"FR",
    "gn:dem":8,
    "gn:elevation":"8.0",
    "gn:feature_class":"P",
    "gn:feature_code":"PPL",
    "gn:name":"Moka",
    "gn:population":0,
    "gn:timezone":"Europe/Paris",
    "iso:country":"FR",
    "name:bul_x_preferred":[
        "\u041c\u043e\u043a\u0430"
    ],
    "name:ceb_x_preferred":[
        "Moka"
    ],
    "name:fas_x_preferred":[
        "\u0645\u0648\u06a9\u0627"
    ],
    "name:fra_x_preferred":[
        "Moka"
    ],
    "name:hin_x_preferred":[
        "\u092e\u094b\u0915\u093e"
    ],
    "name:ita_x_preferred":[
        "Moka"
    ],
    "name:mal_x_preferred":[
        "\u0d2e\u0d4a\u0d15"
    ],
    "name:pol_x_preferred":[
        "Moka"
    ],
    "name:por_x_preferred":[
        "Moka"
    ],
    "name:swe_x_preferred":[
        "Moka"
    ],
    "name:tam_x_preferred":[
        "\u0bae\u0bcb\u0b95\u0bcd\u0b95\u0bbe"
    ],
    "name:tur_x_preferred":[
        "Moka"
    ],
    "wof:name":"Moka",
    "wof:placetype":"locality"
},
  "geometry": {"coordinates":[-2.00297,48.64958],"type":"Point"}
}