{
  "type": "Feature",
  "properties": {
    "gn:admin1_code":"75",
    "gn:admin2_code":"16",
    "gn:admin3_code":"163",
    "gn:admin4_code":"16054",
    "gn:asciiname":"La Grange",
    "gn:country_code":"FR",
    "gn:dem":170,
    "gn:feature_class":"P",
    "gn:feature_code":"PPL",
    "gn:name":"La Grange",
    "gn:population":0,
    "gn:timezone":"Europe/Paris",
    "iso:country":"FR",
    "name:deu_x_preferred":[
        "La Grange"
    ],
    "name:nld_x_preferred":[
        "La Grange"
    ],
    "wof:name":"La Grange",
    "wof:placetype":"locality"
},
  "geometry": {"coordinates":[0.37854,46.04835],"type":"Point"}
}