{
  "type": "Feature",
  "properties": {
    "gn:admin1_code":"24",
    "gn:admin2_code":"28",
    "gn:admin3_code":"283",
    "gn:admin4_code":"28347.0",
    "gn:asciiname":"Le Coudray",
    "gn:country_code":"FR",
    "gn:dem":119,
    "gn:feature_class":"P",
    "gn:feature_code":"PPL",
    "gn:name":"Le Coudray",
    "gn:population":0,
    "gn:timezone":"Europe/Paris",
    "iso:country":"FR",
    "name:bug_x_preferred":[
        "Le Coudray"
    ],
    "name:cat_x_preferred":[
        "Le Coudray"
    ],
    "name:ceb_x_preferred":[
        "Le Coudray"
    ],
    "name:deu_x_preferred":[
        "Le Coudray"
    ],
    "name:eus_x_preferred":[
        "Le Coudray"
    ],
    "name:fra_x_preferred":[
        "Le Coudray"
    ],
    "name:hun_x_preferred":[
        "Le Coudray"
    ],
    "name:ind_x_preferred":[
        "Le Coudray"
    ],
    "name:ita_x_preferred":[
        "Le Coudray"
    ],
    "name:lat_x_preferred":[
        "Le Coudray"
    ],
    "name:mlg_x_preferred":[
        "Le Coudray"
    ],
    "name:msa_x_preferred":[
        "Le Coudray"
    ],
    "name:nld_x_preferred":[
        "Le Coudray"
    ],
    "name:oci_x_preferred":[
        "Le Coudray"
    ],
    "name:pms_x_preferred":[
        "Le Coudray"
    ],
    "name:pol_x_preferred":[
        "Le Coudray"
    ],
    "name:por_x_preferred":[
        "Le Coudray"
    ],
    "name:ron_x_preferred":[
        "Le Coudray"
    ],
    "name:slk_x_preferred":[
        "Le Coudray"
    ],
    "name:spa_x_preferred":[
        "Le Coudray"
    ],
    "name:swe_x_preferred":[
        "Le Coudray"
    ],
    "name:ukr_x_preferred":[
        "\u041b\u0435-\u041a\u0443\u0434\u0440\u0435"
    ],
    "name:uzb_x_preferred":[
        "Le Coudray"
    ],
    "name:vie_x_preferred":[
        "Le Coudray"
    ],
    "name:vol_x_preferred":[
        "Le Coudray"
    ],
    "name:war_x_preferred":[
        "Le Coudray"
    ],
    "name:zho_x_preferred":[
        "\u52d2\u5e93\u5fb7\u8d56"
    ],
    "wof:name":"Le Coudray",
    "wof:placetype":"locality"
},
  "geometry": {"coordinates":[1.56176,48.81182],"type":"Point"}
}