{
  "type": "Feature",
  "properties": {
    "gn:admin1_code":"75",
    "gn:admin2_code":"86",
    "gn:admin3_code":"862",
    "gn:admin4_code":"86237",
    "gn:asciiname":"Saint-Pierre-d'Exideuil",
    "gn:cc2":"FR",
    "gn:country_code":"FR",
    "gn:dem":119,
    "gn:feature_class":"P",
    "gn:feature_code":"PPL",
    "gn:name":"Saint-Pierre-d'Exideuil",
    "gn:population":0,
    "gn:timezone":"Europe/Paris",
    "iso:country":"FR",
    "name:eng_x_preferred":[
        "Saint-Pierre-dExideuil"
    ],
    "name:und_x_variant":[
        "Saint-Pierre"
    ],
    "wof:name":"Saint-Pierre-d'Exideuil",
    "wof:placetype":"locality"
},
  "geometry": {"coordinates":[0.26667,46.15],"type":"Point"}
}