{
  "type": "Feature",
  "properties": {
    "gn:admin1_code":"75",
    "gn:admin2_code":"86",
    "gn:admin3_code":"862",
    "gn:admin4_code":"86237",
    "gn:asciiname":"Saint-Pierre-d'Exideuil",
    "gn:cc2":"FR",
    "gn:country_code":"FR",
    "gn:dem":119,
    "gn:feature_class":"P",
    "gn:feature_code":"PPL",
    "gn:name":"Saint-Pierre-d'Exideuil",
    "gn:population":0,
    "gn:timezone":"Europe/Paris",
    "iso:country":"FR",
    "name:cat_x_preferred":[
        "Saint-Pierre-d'Exideuil"
    ],
    "name:ceb_x_preferred":[
        "Saint-Pierre-d'Exideuil"
    ],
    "name:deu_x_preferred":[
        "Saint-Pierre-d\u2019Exideuil"
    ],
    "name:eng_x_preferred":[
        "Saint-Pierre-dExideuil"
    ],
    "name:eus_x_preferred":[
        "Saint-Pierre-d'Exideuil"
    ],
    "name:fra_x_preferred":[
        "Saint-Pierre-d'Exideuil"
    ],
    "name:hun_x_preferred":[
        "Saint-Pierre-d\u2019Exideuil"
    ],
    "name:ita_x_preferred":[
        "Saint-Pierre-d'Exideuil"
    ],
    "name:lat_x_preferred":[
        "Saint-Pierre-d'Exideuil"
    ],
    "name:msa_x_preferred":[
        "Saint-Pierre-d'Exideuil"
    ],
    "name:nld_x_preferred":[
        "Saint-Pierre-d'Exideuil"
    ],
    "name:oci_x_preferred":[
        "Saint-Pierre-d'Exideuil"
    ],
    "name:pms_x_preferred":[
        "Saint-Pierre-d'Exideuil"
    ],
    "name:pol_x_preferred":[
        "Saint-Pierre-d\u2019Exideuil"
    ],
    "name:por_x_preferred":[
        "Saint-Pierre-d'Exideuil"
    ],
    "name:ron_x_preferred":[
        "Saint-Pierre-d'Exideuil"
    ],
    "name:slk_x_preferred":[
        "Saint-Pierre-d\u2019Exideuil"
    ],
    "name:spa_x_preferred":[
        "Saint-Pierre-d'Exideuil"
    ],
    "name:swe_x_preferred":[
        "Saint-Pierre-d'Exideuil"
    ],
    "name:ukr_x_preferred":[
        "\u0421\u0435\u043d-\u041f'\u0454\u0440\u0440-\u0434'\u0415\u043a\u0441\u0456\u0434\u0435\u0439"
    ],
    "name:und_x_variant":[
        "Saint-Pierre"
    ],
    "name:urd_x_preferred":[
        "\u0633\u06cc\u0646-\u067e\u06cc\u0631\u06cc-\u062f\u06a9\u0633\u06cc\u062f\u06cc\u0648"
    ],
    "name:vie_x_preferred":[
        "Saint-Pierre-d'Exideuil"
    ],
    "name:vol_x_preferred":[
        "Saint-Pierre-d'Exideuil"
    ],
    "name:war_x_preferred":[
        "Saint-Pierre-d'Exideuil"
    ],
    "name:zho_x_preferred":[
        "\u5723\u76ae\u8036\u5c14\u52d2\u5fb7\u514b\u897f\u5fb7\u4f0a"
    ],
    "wof:name":"Saint-Pierre-d'Exideuil",
    "wof:placetype":"locality"
},
  "geometry": {"coordinates":[0.26667,46.15],"type":"Point"}
}