{
  "type": "Feature",
  "properties": {
    "gn:admin1_code":"84",
    "gn:admin2_code":"73",
    "gn:admin3_code":"732",
    "gn:admin4_code":"73270",
    "gn:asciiname":"Pau",
    "gn:country_code":"FR",
    "gn:dem":303,
    "gn:feature_class":"P",
    "gn:feature_code":"PPL",
    "gn:name":"Pau",
    "gn:population":0,
    "gn:timezone":"Europe/Paris",
    "iso:country":"FR",
    "name:arg_x_preferred":[
        "Pau"
    ],
    "name:cat_x_preferred":[
        "Pau"
    ],
    "name:ceb_x_preferred":[
        "Pau"
    ],
    "name:ces_x_preferred":[
        "Pau"
    ],
    "name:deu_x_preferred":[
        "Pau"
    ],
    "name:epo_x_preferred":[
        "Pau"
    ],
    "name:eus_x_preferred":[
        "Pau"
    ],
    "name:fin_x_preferred":[
        "Pau"
    ],
    "name:fra_x_preferred":[
        "Pau"
    ],
    "name:glg_x_preferred":[
        "Pau"
    ],
    "name:ind_x_preferred":[
        "Pau"
    ],
    "name:msa_x_preferred":[
        "Pau"
    ],
    "name:nld_x_preferred":[
        "Pau"
    ],
    "name:pol_x_preferred":[
        "Pau"
    ],
    "name:por_x_preferred":[
        "Pau"
    ],
    "name:scn_x_preferred":[
        "Pau"
    ],
    "name:slk_x_preferred":[
        "Pau"
    ],
    "name:slv_x_preferred":[
        "Pau"
    ],
    "name:spa_x_preferred":[
        "Pau"
    ],
    "name:sqi_x_preferred":[
        "Pau"
    ],
    "name:swe_x_preferred":[
        "Pau"
    ],
    "name:szl_x_preferred":[
        "Pau"
    ],
    "name:vie_x_preferred":[
        "Pau"
    ],
    "name:vol_x_preferred":[
        "Pau"
    ],
    "name:war_x_preferred":[
        "Pau"
    ],
    "wof:name":"Pau",
    "wof:placetype":"locality"
},
  "geometry": {"coordinates":[6.17255,45.56158],"type":"Point"}
}