{
  "type": "Feature",
  "properties": {
    "gn:admin1_code":"84",
    "gn:admin2_code":"73",
    "gn:admin3_code":"732",
    "gn:admin4_code":"73270",
    "gn:asciiname":"Pau",
    "gn:country_code":"FR",
    "gn:dem":303,
    "gn:feature_class":"P",
    "gn:feature_code":"PPL",
    "gn:name":"Pau",
    "gn:population":0,
    "gn:timezone":"Europe/Paris",
    "iso:country":"FR",
    "wof:name":"Pau",
    "wof:placetype":"locality"
},
  "geometry": {"coordinates":[6.17255,45.56158],"type":"Point"}
}