{
  "type": "Feature",
  "properties": {
    "iso:country":"FR",
    "name:eng_x_preferred":[
        "Coteau"
    ],
    "name:fra_x_preferred":[
        "Coteau"
    ],
    "wof:name":"Coteau",
    "wof:placetype":"neighbourhood"
},
  "geometry": {"coordinates":[2.34138626014177,48.79080325891423],"type":"Point"}
}