{
  "type": "Feature",
  "properties": {
    "gn:admin1_code":"75",
    "gn:admin2_code":"17",
    "gn:admin3_code":"171",
    "gn:admin4_code":"17405",
    "gn:asciiname":"Les Blanchards",
    "gn:country_code":"FR",
    "gn:dem":52,
    "gn:feature_class":"P",
    "gn:feature_code":"PPL",
    "gn:name":"Les Blanchards",
    "gn:population":0,
    "gn:timezone":"Europe/Paris",
    "iso:country":"FR",
    "wof:name":"Les Blanchards",
    "wof:placetype":"locality"
},
  "geometry": {"coordinates":[-0.67897,45.37593],"type":"Point"}
}