{
  "type": "Feature",
  "properties": {
    "gn:admin1_code":"53",
    "gn:admin2_code":"29",
    "gn:admin3_code":"292",
    "gn:admin4_code":"29139",
    "gn:asciiname":"Kervez",
    "gn:country_code":"FR",
    "gn:dem":122,
    "gn:feature_class":"P",
    "gn:feature_code":"PPL",
    "gn:name":"Kervez",
    "gn:population":0,
    "gn:timezone":"Europe/Paris",
    "iso:country":"FR",
    "wof:name":"Kervez",
    "wof:placetype":"locality"
},
  "geometry": {"coordinates":[-4.02856,48.30222],"type":"Point"}
}