{
  "type": "Feature",
  "properties": {
    "gn:admin1_code":"76",
    "gn:admin2_code":"82",
    "gn:admin3_code":"822",
    "gn:admin4_code":"82076",
    "gn:asciiname":"L'Honor-de-Cos",
    "gn:country_code":"FR",
    "gn:dem":189,
    "gn:feature_class":"P",
    "gn:feature_code":"PPL",
    "gn:name":"L'Honor-de-Cos",
    "gn:population":0,
    "gn:timezone":"Europe/Paris",
    "iso:country":"FR",
    "wof:name":"L'Honor-de-Cos",
    "wof:placetype":"locality"
},
  "geometry": {"coordinates":[1.3499,44.1225],"type":"Point"}
}