{
  "type": "Feature",
  "properties": {
    "gn:admin1_code":"76",
    "gn:admin2_code":"82",
    "gn:admin3_code":"822",
    "gn:admin4_code":"82076",
    "gn:asciiname":"L'Honor-de-Cos",
    "gn:country_code":"FR",
    "gn:dem":189,
    "gn:feature_class":"P",
    "gn:feature_code":"PPL",
    "gn:name":"L'Honor-de-Cos",
    "gn:population":0,
    "gn:timezone":"Europe/Paris",
    "iso:country":"FR",
    "name:ceb_x_preferred":[
        "L'Honor-de-Cos"
    ],
    "name:deu_x_preferred":[
        "L\u2019Honor-de-Cos"
    ],
    "name:eus_x_preferred":[
        "L'Honor-de-Cos"
    ],
    "name:fra_x_preferred":[
        "L'Honor-de-Cos"
    ],
    "name:hun_x_preferred":[
        "L\u2019Honor-de-Cos"
    ],
    "name:ita_x_preferred":[
        "L'Honor-de-Cos"
    ],
    "name:lat_x_preferred":[
        "L'Honor-de-Cos"
    ],
    "name:mlg_x_preferred":[
        "L'Honor-de-Cos"
    ],
    "name:msa_x_preferred":[
        "L'Honor-de-Cos"
    ],
    "name:nld_x_preferred":[
        "L'Honor-de-Cos"
    ],
    "name:pms_x_preferred":[
        "L'Honor-de-Cos"
    ],
    "name:pol_x_preferred":[
        "L\u2019Honor-de-Cos"
    ],
    "name:por_x_preferred":[
        "L'Honor-de-Cos"
    ],
    "name:ron_x_preferred":[
        "L'Honor-de-Cos"
    ],
    "name:slk_x_preferred":[
        "L\u2019Honor-de-Cos"
    ],
    "name:spa_x_preferred":[
        "L'Honor-de-Cos"
    ],
    "name:swe_x_preferred":[
        "L'Honor-de-Cos"
    ],
    "name:ukr_x_preferred":[
        "\u041b'\u041e\u043d\u043e\u0440-\u0434\u0435-\u041a\u043e\u0441"
    ],
    "name:vie_x_preferred":[
        "L'Honor-de-Cos"
    ],
    "name:vol_x_preferred":[
        "L'Honor-de-Cos"
    ],
    "name:war_x_preferred":[
        "L'Honor-de-Cos"
    ],
    "name:zho_x_preferred":[
        "\u9686\u8bfa\u5fb7\u79d1"
    ],
    "wof:name":"L'Honor-de-Cos",
    "wof:placetype":"locality"
},
  "geometry": {"coordinates":[1.3499,44.1225],"type":"Point"}
}