{
  "type": "Feature",
  "properties": {
    "gn:admin1_code":"76",
    "gn:admin2_code":"46",
    "gn:admin3_code":"462",
    "gn:admin4_code":"46055",
    "gn:asciiname":"Capendac-Village",
    "gn:country_code":"FR",
    "gn:dem":291,
    "gn:feature_class":"P",
    "gn:feature_code":"PPL",
    "gn:name":"Capendac-Village",
    "gn:population":0,
    "gn:timezone":"Europe/Paris",
    "iso:country":"FR",
    "name:und_x_variant":[
        "Capendac",
        "Capendac-Village"
    ],
    "wof:name":"Capendac-Village",
    "wof:placetype":"locality"
},
  "geometry": {"coordinates":[2.06956,44.58021],"type":"Point"}
}