{
  "type": "Feature",
  "properties": {
    "gn:admin1_code":"53",
    "gn:admin2_code":"29",
    "gn:admin3_code":"294",
    "gn:admin4_code":"29046",
    "gn:asciiname":"Brunguen",
    "gn:country_code":"FR",
    "gn:dem":41,
    "gn:feature_class":"P",
    "gn:feature_code":"PPL",
    "gn:name":"Brunguen",
    "gn:population":0,
    "gn:timezone":"Europe/Paris",
    "iso:country":"FR",
    "wof:name":"Brunguen",
    "wof:placetype":"locality"
},
  "geometry": {"coordinates":[-4.34775,48.06875],"type":"Point"}
}