{
  "type": "Feature",
  "properties": {
    "gn:admin1_code":"84",
    "gn:admin2_code":"43",
    "gn:admin3_code":"432",
    "gn:admin4_code":"43168",
    "gn:asciiname":"La Brugere",
    "gn:country_code":"FR",
    "gn:dem":1098,
    "gn:feature_class":"P",
    "gn:feature_code":"PPL",
    "gn:name":"La Brug\u00e8re",
    "gn:population":0,
    "gn:timezone":"Europe/Paris",
    "iso:country":"FR",
    "wof:name":"La Brugere",
    "wof:placetype":"locality"
},
  "geometry": {"coordinates":[3.93059,44.82142],"type":"Point"}
}