{
  "type": "Feature",
  "properties": {
    "gn:admin1_code":"93",
    "gn:admin2_code":"84",
    "gn:admin3_code":"842",
    "gn:admin4_code":"84132",
    "gn:asciiname":"Les Taillades",
    "gn:country_code":"FR",
    "gn:dem":47,
    "gn:feature_class":"P",
    "gn:feature_code":"PPL",
    "gn:name":"Les Taillades",
    "gn:population":0,
    "gn:timezone":"Europe/Paris",
    "iso:country":"FR",
    "wof:name":"Les Taillades",
    "wof:placetype":"locality"
},
  "geometry": {"coordinates":[4.96048,43.93813],"type":"Point"}
}