{
  "type": "Feature",
  "properties": {
    "gn:admin1_code":"75",
    "gn:admin2_code":"24",
    "gn:admin3_code":"241",
    "gn:admin4_code":"24441",
    "gn:asciiname":"Saint-Leon-d'Issigeac",
    "gn:country_code":"FR",
    "gn:dem":152,
    "gn:feature_class":"P",
    "gn:feature_code":"PPL",
    "gn:name":"Saint-L\u00e9on-d\u2019Issigeac",
    "gn:population":0,
    "gn:timezone":"Europe/Paris",
    "iso:country":"FR",
    "name:und_x_variant":[
        "Saint-L\u00e9on",
        "Saint-L\u00e9on-d\u2019Issigeac"
    ],
    "wof:name":"Saint-Leon-d'Issigeac",
    "wof:placetype":"locality"
},
  "geometry": {"coordinates":[0.69163,44.72011],"type":"Point"}
}