{
  "type": "Feature",
  "properties": {
    "gn:admin1_code":"75",
    "gn:admin2_code":"24",
    "gn:admin3_code":"241",
    "gn:admin4_code":"24441",
    "gn:asciiname":"Saint-Leon-d'Issigeac",
    "gn:country_code":"FR",
    "gn:dem":152,
    "gn:feature_class":"P",
    "gn:feature_code":"PPL",
    "gn:name":"Saint-L\u00e9on-d\u2019Issigeac",
    "gn:population":0,
    "gn:timezone":"Europe/Paris",
    "iso:country":"FR",
    "name:bug_x_preferred":[
        "Saint-L\u00e9on-d'Issigeac"
    ],
    "name:ceb_x_preferred":[
        "Saint-L\u00e9on-d'Issigeac"
    ],
    "name:deu_x_preferred":[
        "Saint-L\u00e9on-d\u2019Issigeac"
    ],
    "name:eus_x_preferred":[
        "Saint-L\u00e9on-d'Issigeac"
    ],
    "name:fra_x_preferred":[
        "Saint-L\u00e9on-d'Issigeac"
    ],
    "name:hun_x_preferred":[
        "Saint-L\u00e9on-d\u2019Issigeac"
    ],
    "name:ita_x_preferred":[
        "Saint-L\u00e9on-d'Issigeac"
    ],
    "name:kaz_x_preferred":[
        "\u0421\u0435\u043d-\u041b\u0435\u043e\u043d-\u0434'\u0418\u0441\u0441\u0438\u0436\u0430\u043a"
    ],
    "name:lat_x_preferred":[
        "Saint-L\u00e9on-d'Issigeac"
    ],
    "name:mlg_x_preferred":[
        "Saint-L\u00e9on-d'Issigeac"
    ],
    "name:msa_x_preferred":[
        "Saint-L\u00e9on-d'Issigeac"
    ],
    "name:nld_x_preferred":[
        "Saint-L\u00e9on-d'Issigeac"
    ],
    "name:pms_x_preferred":[
        "Saint-L\u00e9on-d'Issigeac"
    ],
    "name:pol_x_preferred":[
        "Saint-L\u00e9on-d\u2019Issigeac"
    ],
    "name:por_x_preferred":[
        "Saint-L\u00e9on-d'Issigeac"
    ],
    "name:ron_x_preferred":[
        "Saint-L\u00e9on-d'Issigeac"
    ],
    "name:slk_x_preferred":[
        "Saint-L\u00e9on-d\u2019Issigeac"
    ],
    "name:spa_x_preferred":[
        "Saint-L\u00e9on-d'Issigeac"
    ],
    "name:swe_x_preferred":[
        "Saint-L\u00e9on-d'Issigeac"
    ],
    "name:ukr_x_preferred":[
        "\u0421\u0435\u043d-\u041b\u0435\u043e\u043d-\u0434'\u0406\u0441\u0441\u0456\u0436\u0430\u043a"
    ],
    "name:und_x_variant":[
        "Saint-L\u00e9on",
        "Saint-L\u00e9on-d\u2019Issigeac"
    ],
    "name:urd_x_preferred":[
        "\u0633\u06cc\u0646\u0679-\u0644\u0648\u06ba -\u062f\u0633\u0633\u06af\u0627\u06a9"
    ],
    "name:uzb_x_preferred":[
        "Saint-L\u00e9on-d'Issigeac"
    ],
    "name:vie_x_preferred":[
        "Saint-L\u00e9on-d'Issigeac"
    ],
    "name:vol_x_preferred":[
        "Saint-L\u00e9on-d'Issigeac"
    ],
    "name:war_x_preferred":[
        "Saint-L\u00e9on-d'Issigeac"
    ],
    "name:zho_x_preferred":[
        "\u4f0a\u897f\u96c5\u514b\u7684\u5723\u83b1\u6602"
    ],
    "wof:name":"Saint-Leon-d'Issigeac",
    "wof:placetype":"locality"
},
  "geometry": {"coordinates":[0.69163,44.72011],"type":"Point"}
}