{
  "type": "Feature",
  "properties": {
    "gn:admin1_code":"84",
    "gn:admin2_code":"73",
    "gn:admin3_code":"732",
    "gn:admin4_code":"73247",
    "gn:asciiname":"Bourg Evescal",
    "gn:country_code":"FR",
    "gn:dem":321,
    "gn:feature_class":"P",
    "gn:feature_code":"PPL",
    "gn:name":"Bourg Evescal",
    "gn:population":0,
    "gn:timezone":"Europe/Paris",
    "iso:country":"FR",
    "wof:name":"Bourg Evescal",
    "wof:placetype":"locality"
},
  "geometry": {"coordinates":[6.13835,45.56259],"type":"Point"}
}