{
  "type": "Feature",
  "properties": {
    "gn:admin1_code":"84",
    "gn:admin2_code":"63",
    "gn:admin3_code":"634",
    "gn:admin4_code":"63369",
    "gn:asciiname":"Saint-Julien-la-Geneste",
    "gn:country_code":"FR",
    "gn:dem":688,
    "gn:feature_class":"P",
    "gn:feature_code":"PPL",
    "gn:name":"Saint-Julien-la-Geneste",
    "gn:population":0,
    "gn:timezone":"Europe/Paris",
    "iso:country":"FR",
    "name:ceb_x_preferred":[
        "Saint-Julien-la-Geneste"
    ],
    "name:deu_x_preferred":[
        "Saint-Julien-la-Geneste"
    ],
    "name:eus_x_preferred":[
        "Saint-Julien-la-Geneste"
    ],
    "name:fra_x_preferred":[
        "Saint-Julien-la-Geneste"
    ],
    "name:hun_x_preferred":[
        "Saint-Julien-la-Geneste"
    ],
    "name:ita_x_preferred":[
        "Saint-Julien-la-Geneste"
    ],
    "name:lat_x_preferred":[
        "Saint-Julien-la-Geneste"
    ],
    "name:msa_x_preferred":[
        "Saint-Julien-la-Geneste"
    ],
    "name:nld_x_preferred":[
        "Saint-Julien-la-Geneste"
    ],
    "name:oci_x_preferred":[
        "Saint-Julien-la-Geneste"
    ],
    "name:pms_x_preferred":[
        "Saint-Julien-la-Geneste"
    ],
    "name:pol_x_preferred":[
        "Saint-Julien-la-Geneste"
    ],
    "name:por_x_preferred":[
        "Saint-Julien-la-Geneste"
    ],
    "name:ron_x_preferred":[
        "Saint-Julien-la-Geneste"
    ],
    "name:slk_x_preferred":[
        "Saint-Julien-la-Geneste"
    ],
    "name:spa_x_preferred":[
        "Saint-Julien-la-Geneste"
    ],
    "name:swe_x_preferred":[
        "Saint-Julien-la-Geneste"
    ],
    "name:ukr_x_preferred":[
        "\u0421\u0435\u043d-\u0416\u0443\u043b\u044c\u0454\u043d-\u043b\u0430-\u0416\u0435\u043d\u0435\u0441\u0442"
    ],
    "name:und_x_variant":[
        "Saint-Julien"
    ],
    "name:urd_x_preferred":[
        "\u0633\u06cc\u0646\u0679-\u062c\u0644\u06cc\u06ba -\u0644\u0627-\u06af\u0646\u0633\u062a\u06d2"
    ],
    "name:uzb_x_preferred":[
        "Saint-Julien-la-Geneste"
    ],
    "name:vie_x_preferred":[
        "Saint-Julien-la-Geneste"
    ],
    "name:vol_x_preferred":[
        "Saint-Julien-la-Geneste"
    ],
    "name:war_x_preferred":[
        "Saint-Julien-la-Geneste"
    ],
    "name:zho_x_preferred":[
        "\u5723\u745e\u5229\u5b89\u62c9\u70ed\u5185\u65af\u7279"
    ],
    "wof:name":"Saint-Julien-la-Geneste",
    "wof:placetype":"locality"
},
  "geometry": {"coordinates":[2.73427,46.05137],"type":"Point"}
}