{
  "type": "Feature",
  "properties": {
    "gn:admin1_code":"84",
    "gn:admin2_code":"63",
    "gn:admin3_code":"634",
    "gn:admin4_code":"63369",
    "gn:asciiname":"Saint-Julien-la-Geneste",
    "gn:country_code":"FR",
    "gn:dem":688,
    "gn:feature_class":"P",
    "gn:feature_code":"PPL",
    "gn:name":"Saint-Julien-la-Geneste",
    "gn:population":0,
    "gn:timezone":"Europe/Paris",
    "iso:country":"FR",
    "name:und_x_variant":[
        "Saint-Julien",
        "Saint-Julien-la-Geneste"
    ],
    "wof:name":"Saint-Julien-la-Geneste",
    "wof:placetype":"locality"
},
  "geometry": {"coordinates":[2.73427,46.05137],"type":"Point"}
}