{
  "type": "Feature",
  "properties": {
    "gn:admin1_code":"84",
    "gn:admin2_code":"43",
    "gn:admin3_code":"431",
    "gn:admin4_code":"43239.0",
    "gn:asciiname":"Laniac",
    "gn:country_code":"FR",
    "gn:dem":864,
    "gn:feature_class":"P",
    "gn:feature_code":"PPL",
    "gn:name":"Laniac",
    "gn:population":0,
    "gn:timezone":"Europe/Paris",
    "iso:country":"FR",
    "wof:name":"Laniac",
    "wof:placetype":"locality"
},
  "geometry": {"coordinates":[3.62042,45.09534],"type":"Point"}
}