{
  "type": "Feature",
  "properties": {
    "gn:admin1_code":"93",
    "gn:admin2_code":"05",
    "gn:admin3_code":"051",
    "gn:admin4_code":"05052",
    "gn:asciiname":"Gros",
    "gn:country_code":"FR",
    "gn:dem":1310,
    "gn:feature_class":"P",
    "gn:feature_code":"PPL",
    "gn:name":"Gros",
    "gn:population":0,
    "gn:timezone":"Europe/Paris",
    "iso:country":"FR",
    "name:bel_x_preferred":[
        "\u0413\u0440\u043e\u0441"
    ],
    "name:cat_x_preferred":[
        "Gros"
    ],
    "name:ces_x_preferred":[
        "Gros"
    ],
    "name:deu_x_preferred":[
        "Gros"
    ],
    "name:eus_x_preferred":[
        "Gros"
    ],
    "name:fra_x_preferred":[
        "Gros"
    ],
    "name:ita_x_preferred":[
        "Gros"
    ],
    "name:nld_x_preferred":[
        "Gros"
    ],
    "name:por_x_preferred":[
        "Gros"
    ],
    "name:rus_x_preferred":[
        "\u0413\u0440\u043e\u0441"
    ],
    "name:slv_x_preferred":[
        "Gros"
    ],
    "name:spa_x_preferred":[
        "Gros"
    ],
    "name:swe_x_preferred":[
        "Gros"
    ],
    "name:ukr_x_preferred":[
        "\u0413\u0440\u043e\u0441"
    ],
    "wof:name":"Gros",
    "wof:placetype":"locality"
},
  "geometry": {"coordinates":[6.6705,44.67421],"type":"Point"}
}