{
  "type": "Feature",
  "properties": {
    "gn:admin1_code":"93",
    "gn:admin2_code":"05",
    "gn:admin3_code":"051",
    "gn:admin4_code":"05052",
    "gn:asciiname":"Gros",
    "gn:country_code":"FR",
    "gn:dem":1310,
    "gn:feature_class":"P",
    "gn:feature_code":"PPL",
    "gn:name":"Gros",
    "gn:population":0,
    "gn:timezone":"Europe/Paris",
    "iso:country":"FR",
    "wof:name":"Gros",
    "wof:placetype":"locality"
},
  "geometry": {"coordinates":[6.6705,44.67421],"type":"Point"}
}