{
  "type": "Feature",
  "properties": {
    "gn:admin1_code":"84",
    "gn:admin2_code":"63",
    "gn:admin3_code":"632",
    "gn:admin4_code":"63177",
    "gn:asciiname":"Segnoux",
    "gn:country_code":"FR",
    "gn:dem":599,
    "gn:feature_class":"P",
    "gn:feature_code":"PPL",
    "gn:name":"S\u00e9gnoux",
    "gn:population":0,
    "gn:timezone":"Europe/Paris",
    "iso:country":"FR",
    "wof:name":"Segnoux",
    "wof:placetype":"locality"
},
  "geometry": {"coordinates":[3.35825,45.6679],"type":"Point"}
}