{
  "type": "Feature",
  "properties": {
    "gn:admin1_code":"93",
    "gn:admin2_code":"05",
    "gn:admin3_code":"052",
    "gn:admin4_code":"05153",
    "gn:asciiname":"Chaillolet",
    "gn:country_code":"FR",
    "gn:dem":1526,
    "gn:feature_class":"P",
    "gn:feature_code":"PPL",
    "gn:name":"Chaillolet",
    "gn:population":0,
    "gn:timezone":"Europe/Paris",
    "iso:country":"FR",
    "wof:name":"Chaillolet",
    "wof:placetype":"locality"
},
  "geometry": {"coordinates":[6.15758,44.68667],"type":"Point"}
}