{
  "type": "Feature",
  "properties": {
    "gn:admin1_code":"24",
    "gn:admin2_code":"28",
    "gn:admin3_code":"282",
    "gn:admin4_code":"28283",
    "gn:asciiname":"Le Bois",
    "gn:country_code":"FR",
    "gn:dem":142,
    "gn:feature_class":"P",
    "gn:feature_code":"PPL",
    "gn:name":"Le Bois",
    "gn:population":0,
    "gn:timezone":"Europe/Paris",
    "iso:country":"FR",
    "wof:name":"Le Bois",
    "wof:placetype":"locality"
},
  "geometry": {"coordinates":[1.50344,48.12524000000001],"type":"Point"}
}