{
  "type": "Feature",
  "properties": {
    "gn:admin1_code":"76",
    "gn:admin2_code":"48",
    "gn:admin3_code":"482",
    "gn:admin4_code":"48138",
    "gn:asciiname":"La Rouviere",
    "gn:country_code":"FR",
    "gn:dem":705,
    "gn:feature_class":"P",
    "gn:feature_code":"PPL",
    "gn:name":"La Rouvi\u00e8re",
    "gn:population":0,
    "gn:timezone":"Europe/Paris",
    "iso:country":"FR",
    "wof:name":"La Rouviere",
    "wof:placetype":"locality"
},
  "geometry": {"coordinates":[3.25156,44.49244],"type":"Point"}
}