{
  "type": "Feature",
  "properties": {
    "gn:admin1_code":"84",
    "gn:admin2_code":"63",
    "gn:admin3_code":"632",
    "gn:admin4_code":"63289.0",
    "gn:asciiname":"L'Estival",
    "gn:country_code":"FR",
    "gn:dem":841,
    "gn:feature_class":"P",
    "gn:feature_code":"PPL",
    "gn:name":"L\u2019Estival",
    "gn:population":0,
    "gn:timezone":"Europe/Paris",
    "iso:country":"FR",
    "wof:name":"L'Estival",
    "wof:placetype":"locality"
},
  "geometry": {"coordinates":[2.6591,45.77006],"type":"Point"}
}