{
  "type": "Feature",
  "properties": {
    "iso:country":"FR",
    "name:eng_x_preferred":[
        "Val d\u2019Or"
    ],
    "name:fra_x_preferred":[
        "Val d\u2019Or"
    ],
    "wof:name":"Val d\u2019Or",
    "wof:placetype":"neighbourhood"
},
  "geometry": {"coordinates":[2.21171214968855,48.85388265805714],"type":"Point"}
}