{
  "type": "Feature",
  "properties": {
    "iso:country":"FR",
    "name:eng_x_preferred":[
        "Villette"
    ],
    "name:fra_x_preferred":[
        "Villette"
    ],
    "wof:name":"Villette",
    "wof:placetype":"neighbourhood"
},
  "geometry": {"coordinates":[2.3867948067087,48.90403577896687],"type":"Point"}
}