{
  "type": "Feature",
  "properties": {
    "gn:admin1_code":"75",
    "gn:admin2_code":"79",
    "gn:admin3_code":"791",
    "gn:admin4_code":"79088",
    "gn:asciiname":"Chiche",
    "gn:country_code":"FR",
    "gn:dem":152,
    "gn:feature_class":"P",
    "gn:feature_code":"PPL",
    "gn:name":"Chich\u00e9",
    "gn:population":1459,
    "gn:timezone":"Europe/Paris",
    "iso:country":"FR",
    "name:und_x_variant":[
        "Chich\u00e9"
    ],
    "wof:name":"Chiche",
    "wof:placetype":"locality",
    "wof:population":1459
},
  "geometry": {"coordinates":[-0.3556,46.79643],"type":"Point"}
}