{
  "type": "Feature",
  "properties": {
    "gn:admin1_code":"76",
    "gn:admin2_code":"46",
    "gn:admin3_code":"463",
    "gn:admin4_code":"46151",
    "gn:asciiname":"Murat",
    "gn:country_code":"FR",
    "gn:dem":403,
    "gn:feature_class":"P",
    "gn:feature_code":"PPL",
    "gn:name":"Murat",
    "gn:population":0,
    "gn:timezone":"Europe/Paris",
    "iso:country":"FR",
    "name:bre_x_preferred":[
        "Murat"
    ],
    "name:cat_x_preferred":[
        "Murat"
    ],
    "name:ceb_x_preferred":[
        "Murat"
    ],
    "name:ces_x_preferred":[
        "Murat"
    ],
    "name:deu_x_preferred":[
        "Murat"
    ],
    "name:fin_x_preferred":[
        "Murat"
    ],
    "name:fra_x_preferred":[
        "Murat"
    ],
    "name:hrv_x_preferred":[
        "Murat"
    ],
    "name:hun_x_preferred":[
        "Murat"
    ],
    "name:ita_x_preferred":[
        "Murat"
    ],
    "name:kor_x_preferred":[
        "\ubb88\ub77c"
    ],
    "name:kur_x_preferred":[
        "Murat"
    ],
    "name:nds_x_preferred":[
        "Murat"
    ],
    "name:nld_x_preferred":[
        "Murat"
    ],
    "name:pol_x_preferred":[
        "Murat"
    ],
    "name:por_x_preferred":[
        "Murat"
    ],
    "name:ron_x_preferred":[
        "Murat"
    ],
    "name:rus_x_preferred":[
        "\u041c\u044e\u0440\u0430"
    ],
    "name:slk_x_preferred":[
        "Murat"
    ],
    "name:spa_x_preferred":[
        "Murat"
    ],
    "name:sqi_x_preferred":[
        "Murat"
    ],
    "name:swe_x_preferred":[
        "Murat"
    ],
    "name:tur_x_preferred":[
        "Murat"
    ],
    "name:ukr_x_preferred":[
        "\u041c\u044e\u0440\u0430"
    ],
    "name:zho_x_preferred":[
        "\u6728\u62c9\u63d0"
    ],
    "wof:name":"Murat",
    "wof:placetype":"locality"
},
  "geometry": {"coordinates":[1.51076,44.62247],"type":"Point"}
}