{
  "type": "Feature",
  "properties": {
    "gn:admin1_code":"76",
    "gn:admin2_code":"46",
    "gn:admin3_code":"463",
    "gn:admin4_code":"46151",
    "gn:asciiname":"Murat",
    "gn:country_code":"FR",
    "gn:dem":403,
    "gn:feature_class":"P",
    "gn:feature_code":"PPL",
    "gn:name":"Murat",
    "gn:population":0,
    "gn:timezone":"Europe/Paris",
    "iso:country":"FR",
    "wof:name":"Murat",
    "wof:placetype":"locality"
},
  "geometry": {"coordinates":[1.51076,44.62247],"type":"Point"}
}