{
  "type": "Feature",
  "properties": {
    "gn:admin1_code":"24",
    "gn:admin2_code":"28",
    "gn:admin3_code":"281",
    "gn:admin4_code":"28032.0",
    "gn:asciiname":"Beauvilliers",
    "gn:country_code":"FR",
    "gn:dem":147,
    "gn:feature_class":"P",
    "gn:feature_code":"PPL",
    "gn:name":"Beauvilliers",
    "gn:population":0,
    "gn:timezone":"Europe/Paris",
    "iso:country":"FR",
    "wof:name":"Beauvilliers",
    "wof:placetype":"locality"
},
  "geometry": {"coordinates":[1.6561,48.29701],"type":"Point"}
}