{
  "type": "Feature",
  "properties": {
    "frgov:code_epci":"200070159",
    "frgov:insee_arr":"1",
    "frgov:insee_com":"28032",
    "frgov:insee_dep":"28",
    "frgov:insee_reg":"24",
    "frgov:nom_com":"Beauvilliers",
    "frgov:nom_com_m":"BEAUVILLIERS",
    "frgov:nom_dep":"EURE-ET-LOIR",
    "frgov:nom_reg":"CENTRE-VAL DE LOIRE",
    "frgov:statut":"Commune simple",
    "gn:admin1_code":"24",
    "gn:admin2_code":"28",
    "gn:admin3_code":"281",
    "gn:admin4_code":"28032.0",
    "gn:asciiname":"Beauvilliers",
    "gn:country_code":"FR",
    "gn:dem":147,
    "gn:feature_class":"P",
    "gn:feature_code":"PPL",
    "gn:name":"Beauvilliers",
    "gn:population":0,
    "gn:timezone":"Europe/Paris",
    "iso:country":"FR",
    "name:ceb_x_preferred":[
        "Beauvilliers"
    ],
    "name:deu_x_preferred":[
        "Beauvilliers"
    ],
    "name:epo_x_preferred":[
        "Beauvilliers"
    ],
    "name:fra_x_preferred":[
        "Beauvilliers"
    ],
    "name:ita_x_preferred":[
        "Beauvilliers"
    ],
    "name:nds_x_preferred":[
        "Beauvilliers"
    ],
    "name:nld_x_preferred":[
        "Beauvilliers"
    ],
    "name:oci_x_preferred":[
        "Beauvilliers"
    ],
    "name:pms_x_preferred":[
        "Beauvilliers"
    ],
    "name:pol_x_preferred":[
        "Beauvilliers"
    ],
    "name:por_x_preferred":[
        "Beauvilliers"
    ],
    "name:ron_x_preferred":[
        "Beauvilliers"
    ],
    "name:slk_x_preferred":[
        "Beauvilliers"
    ],
    "name:spa_x_preferred":[
        "Beauvilliers"
    ],
    "name:srp_x_preferred":[
        "\u0411\u043e\u0432\u0438\u043b\u0438\u0458\u0435"
    ],
    "name:swe_x_preferred":[
        "Beauvilliers"
    ],
    "name:ukr_x_preferred":[
        "\u0411\u043e\u0432\u0456\u043b\u044c\u0454"
    ],
    "qs:a0":"France",
    "qs:a1":"EURE-ET-LOIR",
    "qs:a1_lc":"28",
    "qs:a1r":"CENTRE",
    "qs:a1r_lc":"24",
    "qs:a2_lc":"24",
    "qs:a2r_lc":"1",
    "qs:adm0":"France",
    "qs:adm0_a3":"FRA",
    "qs:la":"BEAUVILLIERS",
    "qs:la_lc":"28032",
    "qs:level":"localadmin",
    "qs:type":"Commune simple",
    "wof:coterminous":[
        404401571
    ],
    "wof:name":"Beauvilliers",
    "wof:placetype":"locality",
    "wof:placetype_local":"Commune simple"
},
  "geometry": {"coordinates":[1.6561,48.29701],"type":"Point"}
}