{
  "type": "Feature",
  "properties": {
    "gn:admin1_code":"53",
    "gn:admin2_code":"29",
    "gn:admin3_code":"294",
    "gn:admin4_code":"29226",
    "gn:asciiname":"Haut Kerinec",
    "gn:country_code":"FR",
    "gn:dem":51,
    "gn:feature_class":"P",
    "gn:feature_code":"PPL",
    "gn:name":"Haut Kerinec",
    "gn:population":0,
    "gn:timezone":"Europe/Paris",
    "iso:country":"FR",
    "name:und_x_variant":[
        "Kerinec",
        "Haut Kerinec"
    ],
    "wof:name":"Haut Kerinec",
    "wof:placetype":"locality"
},
  "geometry": {"coordinates":[-4.40811,48.06235],"type":"Point"}
}