{
  "type": "Feature",
  "properties": {
    "iso:country":"FR",
    "qs_pg:aaroncc":"FR",
    "qs_pg:name":"Orbey Pairis",
    "qs_pg:name_adm0":"France",
    "qs_pg:name_adm1":"Alsace",
    "qs_pg:photos":14,
    "qs_pg:photos_1k":3,
    "qs_pg:photos_9k":1,
    "qs_pg:photos_9r":1,
    "qs_pg:photos_all":14,
    "qs_pg:photos_sr":1,
    "qs_pg:pop_sr":0,
    "qs_pg:qs_pg_placetype":"locality",
    "qs_pg:qs_pg_placetype_gp":"Town",
    "qs_pg:woe_adm0":23424819,
    "woe:adm0_id":23424819,
    "woe:name_adm0":"France",
    "woe:name_adm1":"Alsace",
    "woe:placetype":"Town",
    "wof:name":"Orbey Pairis",
    "wof:placetype":"neighbourhood"
},
  "geometry": {"coordinates":[7.0960515,48.12084],"type":"Point"}
}