{
  "type": "Feature",
  "properties": {
    "frgov:code_epci":"200069417",
    "frgov:insee_arr":"1",
    "frgov:insee_com":"40101",
    "frgov:insee_dep":"40",
    "frgov:insee_reg":"75",
    "frgov:nom_com":"Gaas",
    "frgov:nom_com_m":"GAAS",
    "frgov:nom_dep":"LANDES",
    "frgov:nom_reg":"NOUVELLE-AQUITAINE",
    "frgov:statut":"Commune simple",
    "gn:admin1_code":"75",
    "gn:admin2_code":"40",
    "gn:admin3_code":"401",
    "gn:admin4_code":"40101",
    "gn:asciiname":"Gaas",
    "gn:country_code":"FR",
    "gn:dem":78,
    "gn:feature_class":"P",
    "gn:feature_code":"PPL",
    "gn:name":"Gaas",
    "gn:population":396,
    "gn:timezone":"Europe/Paris",
    "iso:country":"FR",
    "name:cat_x_preferred":[
        "Gars"
    ],
    "name:ceb_x_preferred":[
        "Gaas"
    ],
    "name:deu_x_preferred":[
        "Gaas"
    ],
    "name:eus_x_preferred":[
        "Gars"
    ],
    "name:fra_x_preferred":[
        "Gaas"
    ],
    "name:hun_x_preferred":[
        "Gaas"
    ],
    "name:ita_x_preferred":[
        "Gaas"
    ],
    "name:kaz_x_preferred":[
        "\u0413\u0430\u0430\u0441"
    ],
    "name:lat_x_preferred":[
        "Gaas"
    ],
    "name:msa_x_preferred":[
        "Gaas"
    ],
    "name:nld_x_preferred":[
        "Gaas"
    ],
    "name:oci_x_preferred":[
        "Gars"
    ],
    "name:pms_x_preferred":[
        "Gaas"
    ],
    "name:pol_x_preferred":[
        "Gaas"
    ],
    "name:por_x_preferred":[
        "Gaas"
    ],
    "name:ron_x_preferred":[
        "Gaas"
    ],
    "name:slk_x_preferred":[
        "Gaas"
    ],
    "name:slv_x_preferred":[
        "Gaas"
    ],
    "name:spa_x_preferred":[
        "Gaas"
    ],
    "name:swe_x_preferred":[
        "Gaas"
    ],
    "name:ukr_x_preferred":[
        "\u0413\u0430\u0430\u0441"
    ],
    "name:uzb_x_preferred":[
        "Gaas"
    ],
    "name:vie_x_preferred":[
        "Gaas"
    ],
    "name:vol_x_preferred":[
        "Gaas"
    ],
    "name:war_x_preferred":[
        "Gaas"
    ],
    "qs:a0":"France",
    "qs:a1":"LANDES",
    "qs:a1_lc":"40",
    "qs:a1r":"AQUITAINE",
    "qs:a1r_lc":"72",
    "qs:a2_lc":"18",
    "qs:a2r_lc":"1",
    "qs:adm0":"France",
    "qs:adm0_a3":"FRA",
    "qs:la":"GAAS",
    "qs:la_lc":"40101",
    "qs:level":"localadmin",
    "qs:type":"Commune simple",
    "wof:coterminous":[
        404388483
    ],
    "wof:name":"Gaas",
    "wof:placetype":"locality",
    "wof:placetype_local":"Commune simple",
    "wof:population":396
},
  "geometry": {"coordinates":[-1.03576,43.61324],"type":"Point"}
}