{
  "type": "Feature",
  "properties": {
    "gn:admin1_code":"75",
    "gn:admin2_code":"40",
    "gn:admin3_code":"401",
    "gn:admin4_code":"40101",
    "gn:asciiname":"Gaas",
    "gn:country_code":"FR",
    "gn:dem":78,
    "gn:feature_class":"P",
    "gn:feature_code":"PPL",
    "gn:name":"Gaas",
    "gn:population":396,
    "gn:timezone":"Europe/Paris",
    "iso:country":"FR",
    "wof:name":"Gaas",
    "wof:placetype":"locality",
    "wof:population":396
},
  "geometry": {"coordinates":[-1.03576,43.61324000000001],"type":"Point"}
}