{
  "type": "Feature",
  "properties": {
    "iso:country":"FR",
    "name:eng_x_preferred":[
        "Centre ville-Poudrerie"
    ],
    "name:fra_x_preferred":[
        "Centre ville-Poudrerie"
    ],
    "wof:name":"Centre ville-Poudrerie",
    "wof:placetype":"neighbourhood"
},
  "geometry": {"coordinates":[2.56891807514992,48.93550180697261],"type":"Point"}
}