{
  "type": "Feature",
  "properties": {
    "gn:admin1_code":"24",
    "gn:admin2_code":"18",
    "gn:admin3_code":"181",
    "gn:admin4_code":"18019",
    "gn:asciiname":"Regny",
    "gn:country_code":"FR",
    "gn:dem":208,
    "gn:feature_class":"P",
    "gn:feature_code":"PPL",
    "gn:name":"Regny",
    "gn:population":0,
    "gn:timezone":"Europe/Paris",
    "iso:country":"FR",
    "name:bug_x_preferred":[
        "Regny"
    ],
    "name:cat_x_preferred":[
        "Regny"
    ],
    "name:ceb_x_preferred":[
        "Regny"
    ],
    "name:deu_x_preferred":[
        "Regny"
    ],
    "name:eus_x_preferred":[
        "Regny"
    ],
    "name:fra_x_preferred":[
        "Regny"
    ],
    "name:hun_x_preferred":[
        "Regny"
    ],
    "name:hye_x_preferred":[
        "\u054c\u0565\u0576\u056b"
    ],
    "name:ind_x_preferred":[
        "Regny"
    ],
    "name:ita_x_preferred":[
        "Regny"
    ],
    "name:lat_x_preferred":[
        "Regny"
    ],
    "name:ltz_x_preferred":[
        "Regny"
    ],
    "name:mlg_x_preferred":[
        "Regny"
    ],
    "name:msa_x_preferred":[
        "Regny"
    ],
    "name:nld_x_preferred":[
        "Regny"
    ],
    "name:oci_x_preferred":[
        "Regny"
    ],
    "name:pms_x_preferred":[
        "Regny"
    ],
    "name:pol_x_preferred":[
        "Regny"
    ],
    "name:por_x_preferred":[
        "Regny"
    ],
    "name:ron_x_preferred":[
        "Regny"
    ],
    "name:rus_x_preferred":[
        "\u0420\u0435\u043d\u044c\u0438"
    ],
    "name:slk_x_preferred":[
        "Regny"
    ],
    "name:spa_x_preferred":[
        "Regny"
    ],
    "name:sqi_x_preferred":[
        "Regny"
    ],
    "name:swe_x_preferred":[
        "Regny"
    ],
    "name:ukr_x_preferred":[
        "\u0420\u0435\u043d\u044c\u0457"
    ],
    "name:uzb_x_preferred":[
        "Regny"
    ],
    "name:vie_x_preferred":[
        "Regny"
    ],
    "name:vol_x_preferred":[
        "Regny"
    ],
    "name:war_x_preferred":[
        "Regny"
    ],
    "name:zea_x_preferred":[
        "Regny"
    ],
    "wof:name":"Regny",
    "wof:placetype":"locality"
},
  "geometry": {"coordinates":[2.7149,47.1977],"type":"Point"}
}