{
  "type": "Feature",
  "properties": {
    "gn:admin1_code":"24",
    "gn:admin2_code":"18",
    "gn:admin3_code":"181",
    "gn:admin4_code":"18019",
    "gn:asciiname":"Regny",
    "gn:country_code":"FR",
    "gn:dem":208,
    "gn:feature_class":"P",
    "gn:feature_code":"PPL",
    "gn:name":"Regny",
    "gn:population":0,
    "gn:timezone":"Europe/Paris",
    "iso:country":"FR",
    "wof:name":"Regny",
    "wof:placetype":"locality"
},
  "geometry": {"coordinates":[2.7149,47.1977],"type":"Point"}
}