{
  "type": "Feature",
  "properties": {
    "gn:admin1_code":"11",
    "gn:admin2_code":"77",
    "gn:admin3_code":"773",
    "gn:admin4_code":"77020",
    "gn:asciiname":"Les Essarts",
    "gn:country_code":"FR",
    "gn:dem":147,
    "gn:feature_class":"P",
    "gn:feature_code":"PPL",
    "gn:name":"Les Essarts",
    "gn:population":0,
    "gn:timezone":"Europe/Paris",
    "iso:country":"FR",
    "name:bre_x_preferred":[
        "Les Essarts"
    ],
    "name:ceb_x_preferred":[
        "Les Essarts"
    ],
    "name:deu_x_preferred":[
        "Les Essarts"
    ],
    "name:fra_x_preferred":[
        "Les Essarts"
    ],
    "name:ita_x_preferred":[
        "Les Essarts"
    ],
    "name:nds_x_preferred":[
        "Les Essarts"
    ],
    "name:nld_x_preferred":[
        "Les Essarts"
    ],
    "name:pms_x_preferred":[
        "Les Essarts"
    ],
    "name:pol_x_preferred":[
        "Les Essarts"
    ],
    "name:por_x_preferred":[
        "Les Essarts"
    ],
    "name:slk_x_preferred":[
        "Les Essarts"
    ],
    "name:spa_x_preferred":[
        "Les Essarts"
    ],
    "name:swe_x_preferred":[
        "Les Essarts"
    ],
    "wof:name":"Les Essarts",
    "wof:placetype":"locality"
},
  "geometry": {"coordinates":[3.17213,48.69357],"type":"Point"}
}