{
  "type": "Feature",
  "properties": {
    "gn:admin1_code":"75",
    "gn:admin2_code":"19",
    "gn:admin3_code":"191",
    "gn:admin4_code":"19011",
    "gn:asciiname":"Arnac-Pompadour",
    "gn:country_code":"FR",
    "gn:dem":360,
    "gn:feature_class":"P",
    "gn:feature_code":"PPL",
    "gn:name":"Arnac-Pompadour",
    "gn:population":1273,
    "gn:timezone":"Europe/Paris",
    "iso:country":"FR",
    "name:cat_x_preferred":[
        "Arnac e Pompador"
    ],
    "name:jpn_x_preferred":[
        "\u30a2\u30eb\u30ca\u30c3\u30af\uff1d\u30dd\u30f3\u30d1\u30c9\u30a5\u30fc\u30eb"
    ],
    "name:kaz_x_preferred":[
        "\u0410\u0440\u043d\u0430\u043a-\u041f\u043e\u043c\u043f\u0430\u0434\u0443\u0440"
    ],
    "name:oci_x_preferred":[
        "Arnac e Pompador"
    ],
    "name:rus_x_preferred":[
        "\u0410\u0440\u043d\u0430\u043a-\u041f\u043e\u043c\u043f\u0430\u0434\u0443\u0440"
    ],
    "name:srp_x_preferred":[
        "\u0410\u0440\u043d\u0430\u043a \u041f\u043e\u043c\u043f\u0430\u0434\u0443\u0440"
    ],
    "name:ukr_x_preferred":[
        "\u0410\u0440\u043d\u0430\u043a-\u041f\u043e\u043c\u043f\u0430\u0434\u0443\u0440"
    ],
    "name:und_x_variant":[
        "Arnac",
        "Arnac-Pompadour"
    ],
    "name:zho_x_preferred":[
        "\u963f\u5c14\u7eb3\u514b\u84ec\u5e15\u675c"
    ],
    "wof:name":"Arnac-Pompadour",
    "wof:placetype":"locality",
    "wof:population":1273
},
  "geometry": {"coordinates":[1.36993,45.40975],"type":"Point"}
}