{
  "type": "Feature",
  "properties": {
    "gn:admin1_code":"53",
    "gn:admin2_code":"22",
    "gn:admin3_code":"221",
    "gn:admin4_code":"22337",
    "gn:asciiname":"Les Aunais",
    "gn:country_code":"FR",
    "gn:dem":49,
    "gn:feature_class":"P",
    "gn:feature_code":"PPL",
    "gn:name":"Les Aunais",
    "gn:population":0,
    "gn:timezone":"Europe/Paris",
    "iso:country":"FR",
    "wof:name":"Les Aunais",
    "wof:placetype":"locality"
},
  "geometry": {"coordinates":[-2.32972,48.34665],"type":"Point"}
}