{
  "type": "Feature",
  "properties": {
    "gn:gn_country":"FR",
    "gn:gn_fcode":"PPL",
    "gn:gn_pop":0,
    "iso:country":"FR",
    "name:unk_x_variant":[
        "Kerfany"
    ],
    "qs_pg:aaroncc":"FR",
    "qs_pg:gn_country":"FR",
    "qs_pg:gn_fcode":"PPL",
    "qs_pg:gn_pop":0,
    "qs_pg:name":"Kerfany-les-Pins",
    "qs_pg:name_adm0":"France",
    "qs_pg:name_adm1":"Bretagne",
    "qs_pg:photos":249,
    "qs_pg:photos_1k":50,
    "qs_pg:photos_9k":1,
    "qs_pg:photos_9r":4,
    "qs_pg:photos_all":249,
    "qs_pg:photos_sr":4,
    "qs_pg:pop_sr":0,
    "qs_pg:qs_pg_placetype":"locality",
    "qs_pg:qs_pg_placetype_gp":"Town",
    "qs_pg:woe_adm0":23424819,
    "woe:adm0_id":23424819,
    "woe:name_adm0":"France",
    "woe:name_adm1":"Bretagne",
    "woe:placetype":"Town",
    "wof:name":"Kerfany-les-Pins",
    "wof:placetype":"neighbourhood"
},
  "geometry": {"coordinates":[-3.71667,47.80556],"type":"Point"}
}