{
  "type": "Feature",
  "properties": {
    "gn:admin1_code":"28",
    "gn:admin2_code":"76",
    "gn:admin3_code":"761",
    "gn:admin4_code":"76062",
    "gn:asciiname":"Beuzeville-la-Giffarde",
    "gn:country_code":"FR",
    "gn:dem":160,
    "gn:feature_class":"P",
    "gn:feature_code":"PPL",
    "gn:name":"Beuzeville-la-Giffarde",
    "gn:population":0,
    "gn:timezone":"Europe/Paris",
    "iso:country":"FR",
    "name:und_x_variant":[
        "Beuzeville",
        "Beuzeville-la-Giffarde"
    ],
    "wof:name":"Beuzeville-la-Giffarde",
    "wof:placetype":"locality"
},
  "geometry": {"coordinates":[1.21223,49.65804],"type":"Point"}
}