{
  "type": "Feature",
  "properties": {
    "gn:admin1_code":"84",
    "gn:admin2_code":"26",
    "gn:admin3_code":"262",
    "gn:admin4_code":"26091",
    "gn:asciiname":"Laux-Montaux",
    "gn:country_code":"FR",
    "gn:dem":812,
    "gn:feature_class":"P",
    "gn:feature_code":"PPL",
    "gn:name":"Laux-Montaux",
    "gn:population":0,
    "gn:timezone":"Europe/Paris",
    "iso:country":"FR",
    "name:und_x_variant":[
        "Le Laux",
        "Laux-Montau",
        "Laux-Montaux"
    ],
    "wof:name":"Laux-Montaux",
    "wof:placetype":"locality"
},
  "geometry": {"coordinates":[5.55016,44.31807],"type":"Point"}
}