{
  "type": "Feature",
  "properties": {
    "gn:admin1_code":"84",
    "gn:admin2_code":"43",
    "gn:admin3_code":"431",
    "gn:admin4_code":"43035",
    "gn:asciiname":"Labrie",
    "gn:country_code":"FR",
    "gn:dem":937,
    "gn:feature_class":"P",
    "gn:feature_code":"PPL",
    "gn:name":"Labrie",
    "gn:population":0,
    "gn:timezone":"Europe/Paris",
    "iso:country":"FR",
    "wof:name":"Labrie",
    "wof:placetype":"locality"
},
  "geometry": {"coordinates":[3.72586,45.30377],"type":"Point"}
}