{
  "type": "Feature",
  "properties": {
    "gn:admin1_code":"75",
    "gn:admin2_code":"19",
    "gn:admin3_code":"193",
    "gn:admin4_code":"19134",
    "gn:asciiname":"Faux",
    "gn:country_code":"FR",
    "gn:dem":757,
    "gn:feature_class":"P",
    "gn:feature_code":"PPL",
    "gn:name":"Faux",
    "gn:population":0,
    "gn:timezone":"Europe/Paris",
    "iso:country":"FR",
    "name:ceb_x_preferred":[
        "Faux"
    ],
    "name:deu_x_preferred":[
        "Faux"
    ],
    "name:fra_x_preferred":[
        "Faux"
    ],
    "name:ita_x_preferred":[
        "Faux"
    ],
    "name:nds_x_preferred":[
        "Faux"
    ],
    "name:nld_x_preferred":[
        "Faux"
    ],
    "name:pms_x_preferred":[
        "Faux"
    ],
    "name:pol_x_preferred":[
        "Faux"
    ],
    "name:por_x_preferred":[
        "Faux"
    ],
    "name:slk_x_preferred":[
        "Faux"
    ],
    "name:spa_x_preferred":[
        "Faux"
    ],
    "name:sqi_x_preferred":[
        "Faux"
    ],
    "name:swe_x_preferred":[
        "Faux"
    ],
    "wof:name":"Faux",
    "wof:placetype":"locality"
},
  "geometry": {"coordinates":[2.44889,45.62448],"type":"Point"}
}