{
  "type": "Feature",
  "properties": {
    "gn:admin1_code":"28",
    "gn:admin2_code":"76",
    "gn:admin3_code":"761",
    "gn:admin4_code":"76732.0",
    "gn:asciiname":"Venesville",
    "gn:country_code":"FR",
    "gn:dem":82,
    "gn:feature_class":"P",
    "gn:feature_code":"PPL",
    "gn:name":"V\u00e9nesville",
    "gn:population":0,
    "gn:timezone":"Europe/Paris",
    "iso:country":"FR",
    "wof:name":"Venesville",
    "wof:placetype":"locality"
},
  "geometry": {"coordinates":[0.58717,49.81401],"type":"Point"}
}