{
  "type": "Feature",
  "properties": {
    "gn:admin1_code":"27",
    "gn:admin2_code":"58",
    "gn:admin3_code":"582",
    "gn:admin4_code":"58200",
    "gn:asciiname":"Le Plessis",
    "gn:country_code":"FR",
    "gn:dem":170,
    "gn:feature_class":"P",
    "gn:feature_code":"PPL",
    "gn:name":"Le Plessis",
    "gn:population":0,
    "gn:timezone":"Europe/Paris",
    "iso:country":"FR",
    "name:ceb_x_preferred":[
        "Le Plessis"
    ],
    "name:ces_x_preferred":[
        "Le Plessis"
    ],
    "name:deu_x_preferred":[
        "Le Plessis"
    ],
    "name:fra_x_preferred":[
        "Le Plessis"
    ],
    "name:nld_x_preferred":[
        "Le Plessis"
    ],
    "name:swe_x_preferred":[
        "Le Plessis"
    ],
    "wof:name":"Le Plessis",
    "wof:placetype":"locality"
},
  "geometry": {"coordinates":[3.49607,47.41798],"type":"Point"}
}