{
  "type": "Feature",
  "properties": {
    "iso:country":"FR",
    "name:eng_x_preferred":[
        "Centre"
    ],
    "name:fra_x_preferred":[
        "Centre"
    ],
    "wof:name":"Centre",
    "wof:placetype":"neighbourhood"
},
  "geometry": {"coordinates":[2.29149896732977,48.91084294842626],"type":"Point"}
}