{
  "type": "Feature",
  "properties": {
    "iso:country":"FR",
    "name:eng_x_preferred":[
        "Tours-Ouest"
    ],
    "name:fra_x_preferred":[
        "Tours-Ouest"
    ],
    "wof:name":"Tours-Ouest",
    "wof:placetype":"neighbourhood"
},
  "geometry": {"coordinates":[0.67837411703294,47.38538782427158],"type":"Point"}
}