{
  "type": "Feature",
  "properties": {
    "gn:admin1_code":"52",
    "gn:admin2_code":"44",
    "gn:admin3_code":"441",
    "gn:admin4_code":"44128",
    "gn:asciiname":"Tregouet",
    "gn:country_code":"FR",
    "gn:dem":46,
    "gn:feature_class":"P",
    "gn:feature_code":"PPL",
    "gn:name":"Tr\u00e9gouet",
    "gn:population":0,
    "gn:timezone":"Europe/Paris",
    "iso:country":"FR",
    "wof:name":"Tregouet",
    "wof:placetype":"locality"
},
  "geometry": {"coordinates":[-1.89705,47.57943],"type":"Point"}
}