{
  "type": "Feature",
  "properties": {
    "gn:admin1_code":"84",
    "gn:admin2_code":"26",
    "gn:admin3_code":"261",
    "gn:admin4_code":"26074",
    "gn:asciiname":"Mercier",
    "gn:country_code":"FR",
    "gn:dem":783,
    "gn:feature_class":"P",
    "gn:feature_code":"PPL",
    "gn:name":"Mercier",
    "gn:population":0,
    "gn:timezone":"Europe/Paris",
    "iso:country":"FR",
    "name:bre_x_preferred":[
        "Mercier"
    ],
    "name:ceb_x_preferred":[
        "Mercier"
    ],
    "name:ces_x_preferred":[
        "Mercier"
    ],
    "name:deu_x_preferred":[
        "Mercier"
    ],
    "name:fra_x_preferred":[
        "Mercier"
    ],
    "name:ita_x_preferred":[
        "Mercier"
    ],
    "name:nld_x_preferred":[
        "Mercier"
    ],
    "name:rus_x_preferred":[
        "\u041c\u0435\u0440\u0441\u044c\u0435"
    ],
    "name:scn_x_preferred":[
        "Mirceri"
    ],
    "name:spa_x_preferred":[
        "Mercier"
    ],
    "name:swe_x_preferred":[
        "Mercier"
    ],
    "name:und_x_variant":[
        "Les Merciers"
    ],
    "wof:name":"Mercier",
    "wof:placetype":"locality"
},
  "geometry": {"coordinates":[5.44388,44.98298],"type":"Point"}
}