{
  "type": "Feature",
  "properties": {
    "gn:admin1_code":"84",
    "gn:admin2_code":"73",
    "gn:admin3_code":"732",
    "gn:admin4_code":"73070",
    "gn:asciiname":"Leschaux",
    "gn:country_code":"FR",
    "gn:dem":217,
    "gn:feature_class":"P",
    "gn:feature_code":"PPL",
    "gn:name":"Leschaux",
    "gn:population":0,
    "gn:timezone":"Europe/Paris",
    "iso:country":"FR",
    "name:cat_x_preferred":[
        "Leschaux"
    ],
    "name:ceb_x_preferred":[
        "Leschaux"
    ],
    "name:deu_x_preferred":[
        "Leschaux"
    ],
    "name:eus_x_preferred":[
        "Leschaux"
    ],
    "name:fra_x_preferred":[
        "Leschaux"
    ],
    "name:hun_x_preferred":[
        "Leschaux"
    ],
    "name:ind_x_preferred":[
        "Leschaux"
    ],
    "name:ita_x_preferred":[
        "Leschaux"
    ],
    "name:lat_x_preferred":[
        "Calcariae"
    ],
    "name:lmo_x_preferred":[
        "Leschaux"
    ],
    "name:mlg_x_preferred":[
        "Leschaux"
    ],
    "name:msa_x_preferred":[
        "Leschaux"
    ],
    "name:nld_x_preferred":[
        "Leschaux"
    ],
    "name:oci_x_preferred":[
        "Leschaux"
    ],
    "name:pol_x_preferred":[
        "Leschaux"
    ],
    "name:ron_x_preferred":[
        "Leschaux"
    ],
    "name:slk_x_preferred":[
        "Leschaux"
    ],
    "name:spa_x_preferred":[
        "Leschaux"
    ],
    "name:swe_x_preferred":[
        "Leschaux"
    ],
    "name:ukr_x_preferred":[
        "\u041b\u0435\u0448\u043e"
    ],
    "name:uzb_x_preferred":[
        "Leschaux"
    ],
    "name:vie_x_preferred":[
        "Leschaux"
    ],
    "name:vol_x_preferred":[
        "Leschaux"
    ],
    "name:war_x_preferred":[
        "Leschaux"
    ],
    "wof:name":"Leschaux",
    "wof:placetype":"locality"
},
  "geometry": {"coordinates":[5.67923,45.63617],"type":"Point"}
}