{
  "type": "Feature",
  "properties": {
    "gn:admin1_code":"75",
    "gn:admin2_code":"19",
    "gn:admin3_code":"192",
    "gn:admin4_code":"19205",
    "gn:asciiname":"Le Vert",
    "gn:country_code":"FR",
    "gn:dem":488,
    "gn:feature_class":"P",
    "gn:feature_code":"PPL",
    "gn:name":"Le Vert",
    "gn:population":0,
    "gn:timezone":"Europe/Paris",
    "iso:country":"FR",
    "name:fra_x_preferred":[
        "Le Vert"
    ],
    "wof:name":"Le Vert",
    "wof:placetype":"locality"
},
  "geometry": {"coordinates":[2.04202,45.09077],"type":"Point"}
}