{
  "type": "Feature",
  "properties": {
    "gn:admin1_code":"75",
    "gn:admin2_code":"87",
    "gn:admin3_code":"872",
    "gn:admin4_code":"87169",
    "gn:asciiname":"Le Grand Village",
    "gn:country_code":"FR",
    "gn:dem":386,
    "gn:feature_class":"P",
    "gn:feature_code":"PPL",
    "gn:name":"Le Grand Village",
    "gn:population":0,
    "gn:timezone":"Europe/Paris",
    "iso:country":"FR",
    "wof:name":"Le Grand Village",
    "wof:placetype":"locality"
},
  "geometry": {"coordinates":[1.22566,45.70541],"type":"Point"}
}