{
  "type": "Feature",
  "properties": {
    "gn:admin1_code":"84",
    "gn:admin2_code":"73",
    "gn:admin3_code":"732",
    "gn:admin4_code":"73149",
    "gn:asciiname":"Veitrier",
    "gn:country_code":"FR",
    "gn:dem":405,
    "gn:feature_class":"P",
    "gn:feature_code":"PPL",
    "gn:name":"Veitrier",
    "gn:population":0,
    "gn:timezone":"Europe/Paris",
    "iso:country":"FR",
    "name:und_x_variant":[
        "V\u00e9tier",
        "Veitrier"
    ],
    "wof:name":"Veitrier",
    "wof:placetype":"locality"
},
  "geometry": {"coordinates":[5.78956,45.76942],"type":"Point"}
}