{
  "type": "Feature",
  "properties": {
    "gn:admin1_code":"93",
    "gn:admin2_code":"04",
    "gn:admin3_code":"042",
    "gn:admin4_code":"04219",
    "gn:asciiname":"Ondres",
    "gn:country_code":"FR",
    "gn:dem":1416,
    "gn:feature_class":"P",
    "gn:feature_code":"PPL",
    "gn:name":"Ondres",
    "gn:population":0,
    "gn:timezone":"Europe/Paris",
    "iso:country":"FR",
    "name:cat_x_preferred":[
        "Ondres"
    ],
    "name:ceb_x_preferred":[
        "Ondres"
    ],
    "name:deu_x_preferred":[
        "Ondres"
    ],
    "name:eus_x_preferred":[
        "Ondres"
    ],
    "name:fas_x_preferred":[
        "\u0627\u0648\u0646\u062f"
    ],
    "name:fra_x_preferred":[
        "Ondres"
    ],
    "name:hun_x_preferred":[
        "Ondres"
    ],
    "name:ita_x_preferred":[
        "Ondres"
    ],
    "name:kaz_x_preferred":[
        "\u041e\u043d\u0434\u0440"
    ],
    "name:lat_x_preferred":[
        "Ondres"
    ],
    "name:msa_x_preferred":[
        "Ondres"
    ],
    "name:nld_x_preferred":[
        "Ondres"
    ],
    "name:oci_x_preferred":[
        "Ondres"
    ],
    "name:pms_x_preferred":[
        "Ondres"
    ],
    "name:pol_x_preferred":[
        "Ondres"
    ],
    "name:por_x_preferred":[
        "Ondres"
    ],
    "name:ron_x_preferred":[
        "Ondres"
    ],
    "name:rus_x_preferred":[
        "\u041e\u043d\u0434\u0440"
    ],
    "name:slk_x_preferred":[
        "Ondres"
    ],
    "name:slv_x_preferred":[
        "Ondres"
    ],
    "name:spa_x_preferred":[
        "Ondres"
    ],
    "name:swe_x_preferred":[
        "Ondres"
    ],
    "name:ukr_x_preferred":[
        "\u041e\u043d\u0434\u0440"
    ],
    "name:uzb_x_preferred":[
        "Ondres"
    ],
    "name:vie_x_preferred":[
        "Ondres"
    ],
    "name:vol_x_preferred":[
        "Ondres"
    ],
    "name:war_x_preferred":[
        "Ondres"
    ],
    "name:zho_x_preferred":[
        "\u7fc1\u5fb7\u5c14"
    ],
    "wof:name":"Ondres",
    "wof:placetype":"locality"
},
  "geometry": {"coordinates":[6.5942,44.11798],"type":"Point"}
}