{
  "type": "Feature",
  "properties": {
    "gn:admin1_code":"11",
    "gn:admin2_code":"91",
    "gn:admin3_code":"913",
    "gn:admin4_code":"91589.0",
    "gn:asciiname":"Cherchefeuilles",
    "gn:country_code":"FR",
    "gn:dem":83,
    "gn:feature_class":"P",
    "gn:feature_code":"PPL",
    "gn:name":"Cherchefeuilles",
    "gn:population":0,
    "gn:timezone":"Europe/Paris",
    "iso:country":"FR",
    "wof:name":"Cherchefeuilles",
    "wof:placetype":"locality"
},
  "geometry": {"coordinates":[2.35231,48.68366],"type":"Point"}
}