{
  "type": "Feature",
  "properties": {
    "gn:admin1_code":"28",
    "gn:admin2_code":"50",
    "gn:admin3_code":"504",
    "gn:admin4_code":"50444",
    "gn:asciiname":"Saint-Symphorien-les-Buttes",
    "gn:cc2":"FR",
    "gn:country_code":"FR",
    "gn:dem":139,
    "gn:feature_class":"P",
    "gn:feature_code":"PPL",
    "gn:name":"Saint-Symphorien-les-Buttes",
    "gn:population":0,
    "gn:timezone":"Europe/Paris",
    "iso:country":"FR",
    "name:und_x_variant":[
        "Saint-Symphorien",
        "Saint-Symphorien-les-Buttes"
    ],
    "wof:name":"Saint-Symphorien-les-Buttes",
    "wof:placetype":"locality"
},
  "geometry": {"coordinates":[-0.9244,49.02008],"type":"Point"}
}