{
  "type": "Feature",
  "properties": {
    "gn:admin1_code":"93",
    "gn:admin2_code":"84",
    "gn:admin3_code":"843",
    "gn:admin4_code":"84015",
    "gn:asciiname":"Sainte-Marguerite",
    "gn:country_code":"FR",
    "gn:dem":502,
    "gn:feature_class":"P",
    "gn:feature_code":"PPL",
    "gn:name":"Sainte-Marguerite",
    "gn:population":0,
    "gn:timezone":"Europe/Paris",
    "iso:country":"FR",
    "name:und_x_variant":[
        "Sainte-Margerite",
        "Sainte-Marguerite"
    ],
    "wof:name":"Sainte-Marguerite",
    "wof:placetype":"locality"
},
  "geometry": {"coordinates":[5.18928,44.18017],"type":"Point"}
}