{
  "type": "Feature",
  "properties": {
    "gn:admin1_code":"84",
    "gn:admin2_code":"03",
    "gn:admin3_code":"032",
    "gn:admin4_code":"03016",
    "gn:asciiname":"Barberier",
    "gn:country_code":"FR",
    "gn:dem":262,
    "gn:feature_class":"P",
    "gn:feature_code":"PPL",
    "gn:name":"Barberier",
    "gn:population":120,
    "gn:timezone":"Europe/Paris",
    "iso:country":"FR",
    "name:bug_x_preferred":[
        "Barberier"
    ],
    "name:cat_x_preferred":[
        "Barber\u00e8ir"
    ],
    "name:ceb_x_preferred":[
        "Barberier"
    ],
    "name:deu_x_preferred":[
        "Barberier"
    ],
    "name:eus_x_preferred":[
        "Barberier"
    ],
    "name:fra_x_preferred":[
        "Barberier"
    ],
    "name:hun_x_preferred":[
        "Barberier"
    ],
    "name:hye_x_preferred":[
        "\u0532\u0561\u0580\u0562\u0565\u0580\u056b\u0565"
    ],
    "name:ind_x_preferred":[
        "Barberier"
    ],
    "name:ita_x_preferred":[
        "Barberier"
    ],
    "name:kaz_x_preferred":[
        "\u0411\u0430\u0440\u0431\u0435\u0440\u044c\u0435"
    ],
    "name:lat_x_preferred":[
        "Barberier"
    ],
    "name:msa_x_preferred":[
        "Barberier"
    ],
    "name:nld_x_preferred":[
        "Barberier"
    ],
    "name:oci_x_preferred":[
        "Barberier"
    ],
    "name:pms_x_preferred":[
        "Barberier"
    ],
    "name:pol_x_preferred":[
        "Barberier"
    ],
    "name:por_x_preferred":[
        "Barberier"
    ],
    "name:ron_x_preferred":[
        "Barberier"
    ],
    "name:rus_x_preferred":[
        "\u0411\u0430\u0440\u0431\u0435\u0440\u044c\u0435"
    ],
    "name:slk_x_preferred":[
        "Barberier"
    ],
    "name:spa_x_preferred":[
        "Barberier"
    ],
    "name:sqi_x_preferred":[
        "Barberier"
    ],
    "name:srp_x_preferred":[
        "\u0411\u0430\u0440\u0431\u0435\u0440\u0438\u0440"
    ],
    "name:srp_x_variant":[
        "\u0411\u0430\u0440\u0431\u0435\u0440\u0458\u0435"
    ],
    "name:swe_x_preferred":[
        "Barberier"
    ],
    "name:ukr_x_preferred":[
        "\u0411\u0430\u0440\u0431\u0435\u0440'\u0454"
    ],
    "name:uzb_x_preferred":[
        "Barberier"
    ],
    "name:vie_x_preferred":[
        "Barberier"
    ],
    "name:vol_x_preferred":[
        "Barberier"
    ],
    "name:war_x_preferred":[
        "Barberier"
    ],
    "name:zea_x_preferred":[
        "Barberier"
    ],
    "name:zho_x_preferred":[
        "\u5df4\u5c14\u4f2f\u91cc\u8036"
    ],
    "wof:name":"Barberier",
    "wof:placetype":"locality",
    "wof:population":120
},
  "geometry": {"coordinates":[3.25242,46.21435],"type":"Point"}
}