{
  "type": "Feature",
  "properties": {
    "gn:admin1_code":"84",
    "gn:admin2_code":"03",
    "gn:admin3_code":"032",
    "gn:admin4_code":"03016",
    "gn:asciiname":"Barberier",
    "gn:country_code":"FR",
    "gn:dem":262,
    "gn:feature_class":"P",
    "gn:feature_code":"PPL",
    "gn:name":"Barberier",
    "gn:population":120,
    "gn:timezone":"Europe/Paris",
    "iso:country":"FR",
    "name:ceb_x_preferred":[
        "Barberier"
    ],
    "name:fra_x_preferred":[
        "Barberier"
    ],
    "name:ita_x_preferred":[
        "Barberier"
    ],
    "name:nld_x_preferred":[
        "Barberier"
    ],
    "name:pol_x_preferred":[
        "Barberier"
    ],
    "name:por_x_preferred":[
        "Barberier"
    ],
    "name:srp_x_preferred":[
        "\u0411\u0430\u0440\u0431\u0435\u0440\u0438\u0440"
    ],
    "name:srp_x_variant":[
        "\u0411\u0430\u0440\u0431\u0435\u0440\u0458\u0435"
    ],
    "wof:name":"Barberier",
    "wof:placetype":"locality",
    "wof:population":120
},
  "geometry": {"coordinates":[3.25242,46.21435],"type":"Point"}
}