{
  "type": "Feature",
  "properties": {
    "gn:admin1_code":"76",
    "gn:admin2_code":"46",
    "gn:admin3_code":"461",
    "gn:admin4_code":"46103",
    "gn:asciiname":"Saint-Paul-de-Loubressac",
    "gn:country_code":"FR",
    "gn:dem":228,
    "gn:feature_class":"P",
    "gn:feature_code":"PPL",
    "gn:name":"Saint-Paul-de-Loubressac",
    "gn:population":0,
    "gn:timezone":"Europe/Paris",
    "iso:country":"FR",
    "name:ceb_x_preferred":[
        "Saint-Paul-de-Loubressac"
    ],
    "name:deu_x_preferred":[
        "Saint-Paul-de-Loubressac"
    ],
    "name:eus_x_preferred":[
        "Saint-Paul-de-Loubressac"
    ],
    "name:fra_x_preferred":[
        "Saint-Paul-de-Loubressac"
    ],
    "name:hun_x_preferred":[
        "Saint-Paul-de-Loubressac"
    ],
    "name:ita_x_preferred":[
        "Saint-Paul-de-Loubressac"
    ],
    "name:lat_x_preferred":[
        "Saint-Paul-de-Loubressac"
    ],
    "name:mlg_x_preferred":[
        "Saint-Paul-de-Loubressac"
    ],
    "name:msa_x_preferred":[
        "Saint-Paul-de-Loubressac"
    ],
    "name:nld_x_preferred":[
        "Saint-Paul-de-Loubressac"
    ],
    "name:pms_x_preferred":[
        "Saint-Paul-de-Loubressac"
    ],
    "name:pol_x_preferred":[
        "Saint-Paul-de-Loubressac"
    ],
    "name:por_x_preferred":[
        "Saint-Paul-de-Loubressac"
    ],
    "name:ron_x_preferred":[
        "Saint-Paul-de-Loubressac"
    ],
    "name:slk_x_preferred":[
        "Saint-Paul-de-Loubressac"
    ],
    "name:spa_x_preferred":[
        "Saint-Paul-de-Loubressac"
    ],
    "name:swe_x_preferred":[
        "Saint-Paul-de-Loubressac"
    ],
    "name:ukr_x_preferred":[
        "\u0421\u0435\u043d-\u041f\u043e\u043b\u044c-\u0434\u0435-\u041b\u0443\u0431\u0440\u0435\u0441\u0441\u0430\u043a"
    ],
    "name:urd_x_preferred":[
        "\u0633\u06cc\u0646-\u067e\u0627\u0644-\u062f\u06d2-\u0644\u0648\u0628\u0631\u0633\u0627\u06a9"
    ],
    "name:vie_x_preferred":[
        "Saint-Paul-de-Loubressac"
    ],
    "name:vol_x_preferred":[
        "Saint-Paul-de-Loubressac"
    ],
    "name:war_x_preferred":[
        "Saint-Paul-de-Loubressac"
    ],
    "name:zho_x_preferred":[
        "\u5723\u4fdd\u7f57\u5fb7\u5362\u5e03\u5c14\u8428\u514b"
    ],
    "wof:name":"Saint-Paul-de-Loubressac",
    "wof:placetype":"locality"
},
  "geometry": {"coordinates":[1.4489,44.2971],"type":"Point"}
}