{
  "type": "Feature",
  "properties": {
    "gn:admin1_code":"76",
    "gn:admin2_code":"46",
    "gn:admin3_code":"461",
    "gn:admin4_code":"46103",
    "gn:asciiname":"Saint-Paul-de-Loubressac",
    "gn:country_code":"FR",
    "gn:dem":228,
    "gn:feature_class":"P",
    "gn:feature_code":"PPL",
    "gn:name":"Saint-Paul-de-Loubressac",
    "gn:population":0,
    "gn:timezone":"Europe/Paris",
    "iso:country":"FR",
    "wof:name":"Saint-Paul-de-Loubressac",
    "wof:placetype":"locality"
},
  "geometry": {"coordinates":[1.4489,44.2971],"type":"Point"}
}