{
  "type": "Feature",
  "properties": {
    "gn:admin1_code":"28",
    "gn:admin2_code":"76",
    "gn:admin3_code":"762",
    "gn:admin4_code":"76587",
    "gn:asciiname":"Alvantot",
    "gn:country_code":"FR",
    "gn:dem":109,
    "gn:feature_class":"P",
    "gn:feature_code":"PPL",
    "gn:name":"Alvantot",
    "gn:population":0,
    "gn:timezone":"Europe/Paris",
    "iso:country":"FR",
    "name:und_x_variant":[
        "Alventot",
        "Alvantot"
    ],
    "wof:name":"Alvantot",
    "wof:placetype":"locality"
},
  "geometry": {"coordinates":[0.46139,49.76139000000001],"type":"Point"}
}