{
  "type": "Feature",
  "properties": {
    "gn:admin1_code":"27",
    "gn:admin2_code":"71",
    "gn:admin3_code":"715",
    "gn:admin4_code":"71217",
    "gn:asciiname":"Germolles-sur-Grosne",
    "gn:country_code":"FR",
    "gn:dem":371,
    "gn:feature_class":"P",
    "gn:feature_code":"PPL",
    "gn:name":"Germolles-sur-Grosne",
    "gn:population":0,
    "gn:timezone":"Europe/Paris",
    "iso:country":"FR",
    "name:und_x_variant":[
        "Germolles",
        "Germolles-sur-Grosne"
    ],
    "wof:name":"Germolles-sur-Grosne",
    "wof:placetype":"locality"
},
  "geometry": {"coordinates":[4.59052,46.27986],"type":"Point"}
}