{
  "type": "Feature",
  "properties": {
    "gn:admin1_code":"27",
    "gn:admin2_code":"71",
    "gn:admin3_code":"715",
    "gn:admin4_code":"71217",
    "gn:asciiname":"Germolles-sur-Grosne",
    "gn:country_code":"FR",
    "gn:dem":371,
    "gn:feature_class":"P",
    "gn:feature_code":"PPL",
    "gn:name":"Germolles-sur-Grosne",
    "gn:population":0,
    "gn:timezone":"Europe/Paris",
    "iso:country":"FR",
    "name:cat_x_preferred":[
        "Germolles-sur-Grosne"
    ],
    "name:ceb_x_preferred":[
        "Germolles-sur-Grosne"
    ],
    "name:deu_x_preferred":[
        "Germolles-sur-Grosne"
    ],
    "name:eus_x_preferred":[
        "Germolles-sur-Grosne"
    ],
    "name:fra_x_preferred":[
        "Germolles-sur-Grosne"
    ],
    "name:hun_x_preferred":[
        "Germolles-sur-Grosne"
    ],
    "name:ita_x_preferred":[
        "Germolles-sur-Grosne"
    ],
    "name:kaz_x_preferred":[
        "\u0416\u0435\u0440\u043c\u043e\u043b\u044c-\u0441\u044e\u0440-\u0413\u0440\u043e\u043d"
    ],
    "name:lat_x_preferred":[
        "Germolles-sur-Grosne"
    ],
    "name:msa_x_preferred":[
        "Germolles-sur-Grosne"
    ],
    "name:nld_x_preferred":[
        "Germolles-sur-Grosne"
    ],
    "name:oci_x_preferred":[
        "Germolles-sur-Grosne"
    ],
    "name:pms_x_preferred":[
        "Germolles-sur-Grosne"
    ],
    "name:pol_x_preferred":[
        "Germolles-sur-Grosne"
    ],
    "name:por_x_preferred":[
        "Germolles-sur-Grosne"
    ],
    "name:ron_x_preferred":[
        "Germolles-sur-Grosne"
    ],
    "name:slk_x_preferred":[
        "Germolles-sur-Grosne"
    ],
    "name:spa_x_preferred":[
        "Germolles-sur-Grosne"
    ],
    "name:swe_x_preferred":[
        "Germolles-sur-Grosne"
    ],
    "name:ukr_x_preferred":[
        "\u0416\u0435\u0440\u043c\u043e\u043b\u044c-\u0441\u044e\u0440-\u0413\u0440\u043e\u043d"
    ],
    "name:und_x_variant":[
        "Germolles",
        "Germolles-sur-Grosne"
    ],
    "name:uzb_x_preferred":[
        "Germolles-sur-Grosne"
    ],
    "name:vie_x_preferred":[
        "Germolles-sur-Grosne"
    ],
    "name:vol_x_preferred":[
        "Germolles-sur-Grosne"
    ],
    "name:war_x_preferred":[
        "Germolles-sur-Grosne"
    ],
    "wof:name":"Germolles-sur-Grosne",
    "wof:placetype":"locality"
},
  "geometry": {"coordinates":[4.59052,46.27986],"type":"Point"}
}