{
  "type": "Feature",
  "properties": {
    "gn:admin1_code":"84",
    "gn:admin2_code":"74",
    "gn:admin3_code":"743",
    "gn:admin4_code":"74185.0",
    "gn:asciiname":"Esserts-Saleve",
    "gn:country_code":"FR",
    "gn:dem":593,
    "gn:feature_class":"P",
    "gn:feature_code":"PPL",
    "gn:name":"Esserts-Sal\u00e8ve",
    "gn:population":0,
    "gn:timezone":"Europe/Paris",
    "iso:country":"FR",
    "name:und_x_variant":[
        "Esserts",
        "Esserts-Sal\u00e8ve"
    ],
    "wof:name":"Esserts-Saleve",
    "wof:placetype":"locality"
},
  "geometry": {"coordinates":[6.21796,46.14779],"type":"Point"}
}