{
  "type": "Feature",
  "properties": {
    "gn:admin1_code":"84",
    "gn:admin2_code":"26",
    "gn:admin3_code":"262",
    "gn:admin4_code":"26288",
    "gn:asciiname":"Romezellier",
    "gn:country_code":"FR",
    "gn:dem":434,
    "gn:feature_class":"P",
    "gn:feature_code":"PPL",
    "gn:name":"Romezellier",
    "gn:population":0,
    "gn:timezone":"Europe/Paris",
    "iso:country":"FR",
    "wof:name":"Romezellier",
    "wof:placetype":"locality"
},
  "geometry": {"coordinates":[5.26667,44.41667],"type":"Point"}
}