{
  "type": "Feature",
  "properties": {
    "iso:country":"FR",
    "name:eng_x_preferred":[
        "Zone d'Activite Ouest"
    ],
    "name:fra_x_preferred":[
        "Zone d'Activit\u00e9 Ouest"
    ],
    "name:fra_x_variant":[
        "ZA Ouest"
    ],
    "wof:name":"Zone d'Activite Ouest",
    "wof:placetype":"neighbourhood"
},
  "geometry": {"coordinates":[-1.72702363103939,48.10651880626705],"type":"Point"}
}