{
  "type": "Feature",
  "properties": {
    "gn:admin1_code":"52",
    "gn:admin2_code":"49",
    "gn:admin3_code":"491",
    "gn:admin4_code":"49214",
    "gn:asciiname":"Vauleard",
    "gn:country_code":"FR",
    "gn:dem":26,
    "gn:feature_class":"P",
    "gn:feature_code":"PPL",
    "gn:name":"Vaul\u00e9ard",
    "gn:population":0,
    "gn:timezone":"Europe/Paris",
    "iso:country":"FR",
    "wof:name":"Vauleard",
    "wof:placetype":"locality"
},
  "geometry": {"coordinates":[-0.62771,47.56631],"type":"Point"}
}