{
  "type": "Feature",
  "properties": {
    "gn:admin1_code":"84",
    "gn:admin2_code":"42",
    "gn:admin3_code":"421",
    "gn:admin4_code":"42227",
    "gn:asciiname":"Vial",
    "gn:country_code":"FR",
    "gn:dem":717,
    "gn:feature_class":"P",
    "gn:feature_code":"PPL",
    "gn:name":"Vial",
    "gn:population":0,
    "gn:timezone":"Europe/Paris",
    "iso:country":"FR",
    "wof:name":"Vial",
    "wof:placetype":"locality"
},
  "geometry": {"coordinates":[3.94174,45.70999000000001],"type":"Point"}
}