{
  "type": "Feature",
  "properties": {
    "gn:admin1_code":"84",
    "gn:admin2_code":"42",
    "gn:admin3_code":"421",
    "gn:admin4_code":"42227",
    "gn:asciiname":"Vial",
    "gn:country_code":"FR",
    "gn:dem":717,
    "gn:feature_class":"P",
    "gn:feature_code":"PPL",
    "gn:name":"Vial",
    "gn:population":0,
    "gn:timezone":"Europe/Paris",
    "iso:country":"FR",
    "name:cat_x_preferred":[
        "Vial"
    ],
    "name:deu_x_preferred":[
        "Phiole"
    ],
    "name:fas_x_preferred":[
        "\u0648\u06cc\u0627\u0644"
    ],
    "name:fra_x_preferred":[
        "Fiole"
    ],
    "name:ido_x_preferred":[
        "Fialo"
    ],
    "name:ind_x_preferred":[
        "Vial"
    ],
    "name:ita_x_preferred":[
        "Fiala"
    ],
    "name:nor_x_preferred":[
        "Hetteglass"
    ],
    "name:pol_x_preferred":[
        "Fiolka"
    ],
    "name:ron_x_preferred":[
        "Fiol\u0103"
    ],
    "name:rus_x_preferred":[
        "\u0424\u0438\u0430\u043b"
    ],
    "name:slv_x_preferred":[
        "Fiola"
    ],
    "name:spa_x_preferred":[
        "Vial"
    ],
    "name:swe_x_preferred":[
        "Vial"
    ],
    "name:ukr_x_preferred":[
        "\u0424\u0456\u0430\u043b"
    ],
    "wof:name":"Vial",
    "wof:placetype":"locality"
},
  "geometry": {"coordinates":[3.94174,45.70999000000001],"type":"Point"}
}