{
  "type": "Feature",
  "properties": {
    "gn:admin1_code":"24",
    "gn:admin2_code":"36",
    "gn:admin3_code":"362",
    "gn:admin4_code":"36155",
    "gn:asciiname":"La Verrerie",
    "gn:country_code":"FR",
    "gn:dem":138,
    "gn:feature_class":"P",
    "gn:feature_code":"PPL",
    "gn:name":"La Verrerie",
    "gn:population":0,
    "gn:timezone":"Europe/Paris",
    "iso:country":"FR",
    "name:als_x_preferred":[
        "La Verrerie"
    ],
    "name:cat_x_preferred":[
        "La Verrerie"
    ],
    "name:ceb_x_preferred":[
        "La Verrerie"
    ],
    "name:deu_x_preferred":[
        "La Verrerie"
    ],
    "name:epo_x_preferred":[
        "La Verrerie"
    ],
    "name:eus_x_preferred":[
        "La Verrerie"
    ],
    "name:fra_x_preferred":[
        "La Verrerie"
    ],
    "name:ita_x_preferred":[
        "La Verrerie"
    ],
    "name:lmo_x_preferred":[
        "La Verrerie"
    ],
    "name:msa_x_preferred":[
        "La Verrerie"
    ],
    "name:nld_x_preferred":[
        "La Verrerie"
    ],
    "name:nno_x_preferred":[
        "La Verrerie"
    ],
    "name:pms_x_preferred":[
        "La Verrerie"
    ],
    "name:por_x_preferred":[
        "La Verrerie"
    ],
    "name:roh_x_preferred":[
        "La Verrerie"
    ],
    "name:spa_x_preferred":[
        "La Verrerie"
    ],
    "name:sqi_x_preferred":[
        "La Verrerie"
    ],
    "name:swe_x_preferred":[
        "La Verrerie"
    ],
    "name:vol_x_preferred":[
        "La Verrerie"
    ],
    "name:war_x_preferred":[
        "La Verrerie"
    ],
    "name:zho_x_preferred":[
        "\u62c9\u97cb\u96f7\u91cc"
    ],
    "wof:name":"La Verrerie",
    "wof:placetype":"locality"
},
  "geometry": {"coordinates":[1.43333,46.98333],"type":"Point"}
}