{
  "type": "Feature",
  "properties": {
    "gn:admin1_code":"75",
    "gn:admin2_code":"24",
    "gn:admin3_code":"244",
    "gn:admin4_code":"24106",
    "gn:asciiname":"L'Air",
    "gn:country_code":"FR",
    "gn:dem":228,
    "gn:feature_class":"P",
    "gn:feature_code":"PPL",
    "gn:name":"L\u2019Air",
    "gn:population":0,
    "gn:timezone":"Europe/Paris",
    "iso:country":"FR",
    "wof:name":"L'Air",
    "wof:placetype":"locality"
},
  "geometry": {"coordinates":[1.18333,45.01667],"type":"Point"}
}