{
  "type": "Feature",
  "properties": {
    "gn:admin1_code":"53",
    "gn:admin2_code":"35",
    "gn:admin3_code":"352",
    "gn:admin4_code":"35033",
    "gn:asciiname":"L'Aubriais",
    "gn:country_code":"FR",
    "gn:dem":49,
    "gn:feature_class":"P",
    "gn:feature_code":"PPL",
    "gn:name":"L\u2019Aubriais",
    "gn:population":0,
    "gn:timezone":"Europe/Paris",
    "iso:country":"FR",
    "wof:name":"L'Aubriais",
    "wof:placetype":"locality"
},
  "geometry": {"coordinates":[-1.70733,47.91381],"type":"Point"}
}