{
  "type": "Feature",
  "properties": {
    "gn:admin1_code":"27",
    "gn:admin2_code":"25",
    "gn:admin3_code":"252",
    "gn:admin4_code":"25138",
    "gn:asciiname":"Neuvier",
    "gn:country_code":"FR",
    "gn:dem":700,
    "gn:feature_class":"P",
    "gn:feature_code":"PPL",
    "gn:name":"Neuvier",
    "gn:population":0,
    "gn:timezone":"Europe/Paris",
    "iso:country":"FR",
    "wof:name":"Neuvier",
    "wof:placetype":"locality"
},
  "geometry": {"coordinates":[6.73719,47.32445],"type":"Point"}
}