{
  "type": "Feature",
  "properties": {
    "gn:admin1_code":"52",
    "gn:admin2_code":"44",
    "gn:admin3_code":"443",
    "gn:admin4_code":"44050",
    "gn:asciiname":"La Guesne",
    "gn:country_code":"FR",
    "gn:dem":7,
    "gn:feature_class":"P",
    "gn:feature_code":"PPL",
    "gn:name":"La Guesne",
    "gn:population":0,
    "gn:timezone":"Europe/Paris",
    "iso:country":"FR",
    "wof:name":"La Guesne",
    "wof:placetype":"locality"
},
  "geometry": {"coordinates":[-2.13485,47.38422],"type":"Point"}
}