{
  "type": "Feature",
  "properties": {
    "gn:admin1_code":"44",
    "gn:admin2_code":"55",
    "gn:admin3_code":"553",
    "gn:admin4_code":"55060",
    "gn:asciiname":"Mesnil-sous-les-Cotes",
    "gn:country_code":"FR",
    "gn:dem":253,
    "gn:feature_class":"P",
    "gn:feature_code":"PPL",
    "gn:name":"Mesnil-sous-les-C\u00f4tes",
    "gn:population":0,
    "gn:timezone":"Europe/Paris",
    "iso:country":"FR",
    "name:und_x_variant":[
        "Mesnil",
        "Mesnil-sous-les-C\u00f4tes"
    ],
    "wof:name":"Mesnil-sous-les-Cotes",
    "wof:placetype":"locality"
},
  "geometry": {"coordinates":[5.57897,49.08835],"type":"Point"}
}