{
  "type": "Feature",
  "properties": {
    "gn:admin1_code":"84",
    "gn:admin2_code":"38",
    "gn:admin3_code":"381",
    "gn:admin4_code":"38236",
    "gn:asciiname":"Le Chaboud",
    "gn:country_code":"FR",
    "gn:dem":510,
    "gn:feature_class":"P",
    "gn:feature_code":"PPL",
    "gn:name":"Le Chaboud",
    "gn:population":0,
    "gn:timezone":"Europe/Paris",
    "iso:country":"FR",
    "wof:name":"Le Chaboud",
    "wof:placetype":"locality"
},
  "geometry": {"coordinates":[5.72182,45.43653],"type":"Point"}
}