{
  "type": "Feature",
  "properties": {
    "gn:gn_country":"FR",
    "gn:gn_fcode":"PPL",
    "gn:gn_pop":0,
    "iso:country":"FR",
    "qs_pg:aaroncc":"FR",
    "qs_pg:gn_country":"FR",
    "qs_pg:gn_fcode":"PPL",
    "qs_pg:gn_pop":0,
    "qs_pg:name":"Arcelot",
    "qs_pg:name_adm0":"France",
    "qs_pg:name_adm1":"Bourgogne",
    "qs_pg:photos":261,
    "qs_pg:photos_1k":53,
    "qs_pg:photos_9k":1,
    "qs_pg:photos_9r":4,
    "qs_pg:photos_all":261,
    "qs_pg:photos_sr":5,
    "qs_pg:pop_sr":0,
    "qs_pg:qs_pg_placetype":"locality",
    "qs_pg:qs_pg_placetype_gp":"Town",
    "qs_pg:woe_adm0":23424819,
    "woe:adm0_id":23424819,
    "woe:name_adm0":"France",
    "woe:name_adm1":"Bourgogne",
    "woe:placetype":"Town",
    "wof:name":"Arcelot",
    "wof:placetype":"neighbourhood"
},
  "geometry": {"coordinates":[5.19192,47.3695],"type":"Point"}
}