{
  "type": "Feature",
  "properties": {
    "gn:admin1_code":"24",
    "gn:admin2_code":"18",
    "gn:admin3_code":"183",
    "gn:admin4_code":"18124",
    "gn:asciiname":"Les Cocuas",
    "gn:country_code":"FR",
    "gn:dem":149,
    "gn:feature_class":"P",
    "gn:feature_code":"PPL",
    "gn:name":"Les Cocuas",
    "gn:population":0,
    "gn:timezone":"Europe/Paris",
    "iso:country":"FR",
    "wof:name":"Les Cocuas",
    "wof:placetype":"locality"
},
  "geometry": {"coordinates":[2.12143,47.04228],"type":"Point"}
}