{
  "type": "Feature",
  "properties": {
    "gn:admin1_code":"75",
    "gn:admin2_code":"23",
    "gn:admin3_code":"231",
    "gn:admin4_code":"23224",
    "gn:asciiname":"Meouze",
    "gn:country_code":"FR",
    "gn:dem":766,
    "gn:feature_class":"P",
    "gn:feature_code":"PPL",
    "gn:name":"M\u00e9ouze",
    "gn:population":0,
    "gn:timezone":"Europe/Paris",
    "iso:country":"FR",
    "wof:name":"Meouze",
    "wof:placetype":"locality"
},
  "geometry": {"coordinates":[2.35193,45.74212],"type":"Point"}
}