{
  "type": "Feature",
  "properties": {
    "iso:country":"FR",
    "name:eng_x_preferred":[
        "Zone d'Activite Sud-Est"
    ],
    "name:fra_x_preferred":[
        "Zone d'Activit\u00e9 Sud-Est"
    ],
    "wof:name":"Zone d'Activite Sud-Est",
    "wof:placetype":"neighbourhood"
},
  "geometry": {"coordinates":[-1.63088158866586,48.09948670123833],"type":"Point"}
}