{
  "type": "Feature",
  "properties": {
    "gn:admin1_code":"52",
    "gn:admin2_code":"44",
    "gn:admin3_code":"443",
    "gn:admin4_code":"44184",
    "gn:asciiname":"Brais",
    "gn:country_code":"FR",
    "gn:dem":9,
    "gn:feature_class":"P",
    "gn:feature_code":"PPL",
    "gn:name":"Brais",
    "gn:population":0,
    "gn:timezone":"Europe/Paris",
    "iso:country":"FR",
    "wof:name":"Brais",
    "wof:placetype":"locality"
},
  "geometry": {"coordinates":[-2.29038,47.29866],"type":"Point"}
}