{
  "type": "Feature",
  "properties": {
    "gn:admin1_code":"44",
    "gn:admin2_code":"51",
    "gn:admin3_code":"512",
    "gn:admin4_code":"51032",
    "gn:asciiname":"Becheret",
    "gn:country_code":"FR",
    "gn:dem":73,
    "gn:feature_class":"P",
    "gn:feature_code":"PPL",
    "gn:name":"B\u00e9cheret",
    "gn:population":0,
    "gn:timezone":"Europe/Paris",
    "iso:country":"FR",
    "wof:name":"Becheret",
    "wof:placetype":"locality"
},
  "geometry": {"coordinates":[3.84509,48.5627],"type":"Point"}
}