{
  "type": "Feature",
  "properties": {
    "iso:country":"FR",
    "oa:elevation_ft":"428",
    "oa:type":"small_airport",
    "woe:hierarchy":{
        "country_id":23424819,
        "county_id":12597137,
        "localadmin_id":12673075,
        "planet_id":1,
        "state_id":7153319
    },
    "wof:name":"Aerodrome de Nangis-les-Loges",
    "wof:placetype":"campus"
},
  "geometry": {"coordinates":[3.01051,48.5959],"type":"Point"}
}