{
  "type": "Feature",
  "properties": {
    "gn:admin1_code":"84",
    "gn:admin2_code":"42",
    "gn:admin3_code":"422",
    "gn:admin4_code":"42213",
    "gn:asciiname":"Saint-Cyr-de-Valorges",
    "gn:cc2":"FR",
    "gn:country_code":"FR",
    "gn:dem":642,
    "gn:feature_class":"P",
    "gn:feature_code":"PPL",
    "gn:name":"Saint-Cyr-de-Valorges",
    "gn:population":0,
    "gn:timezone":"Europe/Paris",
    "iso:country":"FR",
    "name:cat_x_preferred":[
        "Saint-Cyr-de-Valorges"
    ],
    "name:ceb_x_preferred":[
        "Saint-Cyr-de-Valorges"
    ],
    "name:deu_x_preferred":[
        "Saint-Cyr-de-Valorges"
    ],
    "name:eus_x_preferred":[
        "Saint-Cyr-de-Valorges"
    ],
    "name:fra_x_preferred":[
        "Saint-Cyr-de-Valorges"
    ],
    "name:hun_x_preferred":[
        "Saint-Cyr-de-Valorges"
    ],
    "name:ita_x_preferred":[
        "Saint-Cyr-de-Valorges"
    ],
    "name:jpn_x_preferred":[
        "\u30b5\u30f3\uff1d\u30b7\u30fc\u30eb\uff1d\u30c9\uff1d\u30f4\u30a1\u30ed\u30eb\u30b8\u30e5"
    ],
    "name:lat_x_preferred":[
        "Saint-Cyr-de-Valorges"
    ],
    "name:lmo_x_preferred":[
        "Saint-Cyr-de-Valorges"
    ],
    "name:mlg_x_preferred":[
        "Saint-Cyr-de-Valorges"
    ],
    "name:msa_x_preferred":[
        "Saint-Cyr-de-Valorges"
    ],
    "name:nld_x_preferred":[
        "Saint-Cyr-de-Valorges"
    ],
    "name:oci_x_preferred":[
        "Saint-Cyr-de-Valorges"
    ],
    "name:pms_x_preferred":[
        "Saint-Cyr-de-Valorges"
    ],
    "name:pol_x_preferred":[
        "Saint-Cyr-de-Valorges"
    ],
    "name:por_x_preferred":[
        "Saint-Cyr-de-Valorges"
    ],
    "name:ron_x_preferred":[
        "Saint-Cyr-de-Valorges"
    ],
    "name:slk_x_preferred":[
        "Saint-Cyr-de-Valorges"
    ],
    "name:spa_x_preferred":[
        "Saint-Cyr-de-Valorges"
    ],
    "name:swe_x_preferred":[
        "Saint-Cyr-de-Valorges"
    ],
    "name:ukr_x_preferred":[
        "\u0421\u0435\u043d-\u0421\u0456\u0440-\u0434\u0435-\u0412\u0430\u043b\u043e\u0440\u0436"
    ],
    "name:und_x_variant":[
        "Saint-Cyr"
    ],
    "name:urd_x_preferred":[
        "\u0633\u06cc\u0646\u0679-\u06a9\u06cc\u0631-\u062f\u06d2-\u0648\u0644\u0648\u0631\u06af\u0633"
    ],
    "name:uzb_x_preferred":[
        "Saint-Cyr-de-Valorges"
    ],
    "name:vie_x_preferred":[
        "Saint-Cyr-de-Valorges"
    ],
    "name:vol_x_preferred":[
        "Saint-Cyr-de-Valorges"
    ],
    "name:war_x_preferred":[
        "Saint-Cyr-de-Valorges"
    ],
    "name:zho_x_preferred":[
        "\u5723\u897f\u5fb7\u74e6\u6d1b\u5c14\u65e5"
    ],
    "wof:name":"Saint-Cyr-de-Valorges",
    "wof:placetype":"locality"
},
  "geometry": {"coordinates":[4.3064,45.8919],"type":"Point"}
}