{
  "type": "Feature",
  "properties": {
    "gn:admin1_code":"84",
    "gn:admin2_code":"42",
    "gn:admin3_code":"422",
    "gn:admin4_code":"42213",
    "gn:asciiname":"Saint-Cyr-de-Valorges",
    "gn:cc2":"FR",
    "gn:country_code":"FR",
    "gn:dem":642,
    "gn:feature_class":"P",
    "gn:feature_code":"PPL",
    "gn:name":"Saint-Cyr-de-Valorges",
    "gn:population":0,
    "gn:timezone":"Europe/Paris",
    "iso:country":"FR",
    "name:und_x_variant":[
        "Saint-Cyr"
    ],
    "wof:name":"Saint-Cyr-de-Valorges",
    "wof:placetype":"locality"
},
  "geometry": {"coordinates":[4.3064,45.8919],"type":"Point"}
}