{
  "type": "Feature",
  "properties": {
    "gn:admin1_code":"84",
    "gn:admin2_code":"26",
    "gn:admin3_code":"262",
    "gn:admin4_code":"26189",
    "gn:asciiname":"Ruissas",
    "gn:country_code":"FR",
    "gn:dem":865,
    "gn:feature_class":"P",
    "gn:feature_code":"PPL",
    "gn:name":"Ruissas",
    "gn:population":0,
    "gn:timezone":"Europe/Paris",
    "iso:country":"FR",
    "wof:name":"Ruissas",
    "wof:placetype":"locality"
},
  "geometry": {"coordinates":[5.52424,44.28684000000001],"type":"Point"}
}