{
  "type": "Feature",
  "properties": {
    "iso:country":"FR",
    "oa:elevation_ft":"1647",
    "oa:type":"small_airport",
    "woe:hierarchy":{
        "country_id":23424819,
        "county_id":12597193,
        "localadmin_id":12662292,
        "planet_id":1,
        "state_id":7153320
    },
    "wof:name":"A\u00e9rodrome de la Grand-combe",
    "wof:placetype":"campus"
},
  "geometry": {"coordinates":[4.01111,44.2431],"type":"Point"}
}