{
  "type": "Feature",
  "properties": {
    "iso:country":"FR",
    "name:eng_x_preferred":[
        "Saint-Rambert-d'Albon Airport"
    ],
    "name:msa_x_preferred":[
        "Lapangan Terbang St Rambert d'Albon"
    ],
    "oa:elevation_ft":"509",
    "oa:type":"small_airport",
    "woe:hierarchy":{
        "country_id":23424819,
        "county_id":12597190,
        "localadmin_id":12671151,
        "planet_id":1,
        "state_id":7153329
    },
    "wof:name":"A\u00e9rodrome de Saint-rambert-d'albon",
    "wof:placetype":"campus"
},
  "geometry": {"coordinates":[4.8262,45.2522],"type":"Point"}
}