{
  "type": "Feature",
  "properties": {
    "gn:admin1_code":"24",
    "gn:admin2_code":"45",
    "gn:admin3_code":"452",
    "gn:admin4_code":"45089",
    "gn:asciiname":"Laveau",
    "gn:country_code":"FR",
    "gn:dem":109,
    "gn:feature_class":"P",
    "gn:feature_code":"PPL",
    "gn:name":"Laveau",
    "gn:population":0,
    "gn:timezone":"Europe/Paris",
    "iso:country":"FR",
    "wof:name":"Laveau",
    "wof:placetype":"locality"
},
  "geometry": {"coordinates":[2.01021,47.90158],"type":"Point"}
}