{
  "type": "Feature",
  "properties": {
    "iso:country":"FR",
    "name:eng_x_preferred":[
        "Maladrerie-Emile Dubois"
    ],
    "name:fra_x_preferred":[
        "La Maladrerie/\u00c9mile Dubois"
    ],
    "name:fra_x_variant":[
        "La Maladrerie/\u00c9mile Dubois/Fort d'Aubervilliers"
    ],
    "wof:name":"Maladrerie-Emile Dubois",
    "wof:placetype":"neighbourhood"
},
  "geometry": {"coordinates":[2.39929748328754,48.91505496629924],"type":"Point"}
}