{
  "type": "Feature",
  "properties": {
    "iso:country":"FR",
    "name:eng_x_preferred":[
        "La Plaine"
    ],
    "name:fra_x_preferred":[
        "La Plaine"
    ],
    "wof:name":"La Plaine",
    "wof:placetype":"neighbourhood"
},
  "geometry": {"coordinates":[2.32981341648927,48.78702395046928],"type":"Point"}
}