{
  "type": "Feature",
  "properties": {
    "gn:admin1_code":"44",
    "gn:admin2_code":"10",
    "gn:admin3_code":"103",
    "gn:admin4_code":"10350",
    "gn:asciiname":"Lisiere-des-Bois",
    "gn:country_code":"FR",
    "gn:dem":234,
    "gn:feature_class":"P",
    "gn:feature_code":"PPL",
    "gn:name":"Lisi\u00e8re-des-Bois",
    "gn:population":0,
    "gn:timezone":"Europe/Paris",
    "iso:country":"FR",
    "name:und_x_variant":[
        "La Lisi\u00e8re-des-Bois",
        "Lisi\u00e8re-des-Bois"
    ],
    "wof:name":"Lisiere-des-Bois",
    "wof:placetype":"locality"
},
  "geometry": {"coordinates":[3.7921,48.15038],"type":"Point"}
}