{
  "type": "Feature",
  "properties": {
    "gn:admin1_code":"84",
    "gn:admin2_code":"43",
    "gn:admin3_code":"432",
    "gn:admin4_code":"43111",
    "gn:asciiname":"La Sauvetat",
    "gn:country_code":"FR",
    "gn:dem":1153,
    "gn:feature_class":"P",
    "gn:feature_code":"PPL",
    "gn:name":"La Sauvetat",
    "gn:population":0,
    "gn:timezone":"Europe/Paris",
    "iso:country":"FR",
    "name:cat_x_preferred":[
        "La Sauvetat"
    ],
    "name:ceb_x_preferred":[
        "La Sauvetat"
    ],
    "name:deu_x_preferred":[
        "La Sauvetat"
    ],
    "name:fra_x_preferred":[
        "La Sauvetat"
    ],
    "name:ita_x_preferred":[
        "La Sauvetat"
    ],
    "name:nds_x_preferred":[
        "La Sauvetat"
    ],
    "name:nld_x_preferred":[
        "La Sauvetat"
    ],
    "name:oci_x_preferred":[
        "La Sauvedat"
    ],
    "name:pol_x_preferred":[
        "La Sauvetat"
    ],
    "name:por_x_preferred":[
        "La Sauvetat"
    ],
    "name:scn_x_preferred":[
        "La Sauvetat"
    ],
    "name:slk_x_preferred":[
        "La Sauvetat"
    ],
    "name:spa_x_preferred":[
        "La Sauvetat"
    ],
    "name:swe_x_preferred":[
        "La Sauvetat"
    ],
    "name:ukr_x_preferred":[
        "\u041b\u0430-\u0421\u043e\u0432\u0442\u0430"
    ],
    "wof:name":"La Sauvetat",
    "wof:placetype":"locality"
},
  "geometry": {"coordinates":[3.8504,44.84904],"type":"Point"}
}