{
  "type": "Feature",
  "properties": {
    "gn:admin1_code":"75",
    "gn:admin2_code":"24",
    "gn:admin3_code":"243",
    "gn:admin4_code":"24026",
    "gn:asciiname":"La Raffinie",
    "gn:country_code":"FR",
    "gn:dem":199,
    "gn:feature_class":"P",
    "gn:feature_code":"PPL",
    "gn:name":"La Raffinie",
    "gn:population":0,
    "gn:timezone":"Europe/Paris",
    "iso:country":"FR",
    "wof:name":"La Raffinie",
    "wof:placetype":"locality"
},
  "geometry": {"coordinates":[0.83861,45.14725],"type":"Point"}
}