{
  "type": "Feature",
  "properties": {
    "gn:admin1_code":"27",
    "gn:admin2_code":"21",
    "gn:admin3_code":"213",
    "gn:admin4_code":"21101",
    "gn:asciiname":"La Croisee",
    "gn:country_code":"FR",
    "gn:dem":460,
    "gn:feature_class":"P",
    "gn:feature_code":"PPL",
    "gn:name":"La Crois\u00e9e",
    "gn:population":0,
    "gn:timezone":"Europe/Paris",
    "iso:country":"FR",
    "wof:name":"La Croisee",
    "wof:placetype":"locality"
},
  "geometry": {"coordinates":[4.42489,47.42083],"type":"Point"}
}