{
  "type": "Feature",
  "properties": {
    "gn:admin1_code":"24",
    "gn:admin2_code":"37",
    "gn:admin3_code":"373",
    "gn:admin4_code":"37132",
    "gn:asciiname":"Le Bordage",
    "gn:country_code":"FR",
    "gn:dem":132,
    "gn:feature_class":"P",
    "gn:feature_code":"PPL",
    "gn:name":"Le Bordage",
    "gn:population":0,
    "gn:timezone":"Europe/Paris",
    "iso:country":"FR",
    "name:und_x_variant":[
        "La Bordage",
        "Le Bordage"
    ],
    "wof:name":"Le Bordage",
    "wof:placetype":"locality"
},
  "geometry": {"coordinates":[0.97236,47.0981],"type":"Point"}
}