{
  "type": "Feature",
  "properties": {
    "gn:admin1_code":"75",
    "gn:admin2_code":"16",
    "gn:admin3_code":"163",
    "gn:admin4_code":"16245",
    "gn:asciiname":"Les Mias",
    "gn:country_code":"FR",
    "gn:dem":177,
    "gn:feature_class":"P",
    "gn:feature_code":"PPL",
    "gn:name":"Les Mias",
    "gn:population":0,
    "gn:timezone":"Europe/Paris",
    "iso:country":"FR",
    "wof:name":"Les Mias",
    "wof:placetype":"locality"
},
  "geometry": {"coordinates":[0.54485,45.87985],"type":"Point"}
}