{
  "type": "Feature",
  "properties": {
    "iso:country":"FR",
    "name:eng_x_preferred":[
        "Les Barmonts"
    ],
    "name:fra_x_preferred":[
        "Les Barmonts"
    ],
    "wof:name":"Les Barmonts",
    "wof:placetype":"neighbourhood"
},
  "geometry": {"coordinates":[2.36121428462326,48.80474119433468],"type":"Point"}
}