{
  "type": "Feature",
  "properties": {
    "gn:admin1_code":"84",
    "gn:admin2_code":"43",
    "gn:admin3_code":"431",
    "gn:admin4_code":"43132",
    "gn:asciiname":"Rougeac",
    "gn:country_code":"FR",
    "gn:dem":682,
    "gn:feature_class":"P",
    "gn:feature_code":"PPL",
    "gn:name":"Rougeac",
    "gn:population":0,
    "gn:timezone":"Europe/Paris",
    "iso:country":"FR",
    "wof:name":"Rougeac",
    "wof:placetype":"locality"
},
  "geometry": {"coordinates":[3.565,45.1364],"type":"Point"}
}