{
  "type": "Feature",
  "properties": {
    "gn:admin1_code":"27",
    "gn:admin2_code":"58",
    "gn:admin3_code":"584",
    "gn:admin4_code":"58174",
    "gn:asciiname":"Marciges",
    "gn:country_code":"FR",
    "gn:dem":265,
    "gn:feature_class":"P",
    "gn:feature_code":"PPL",
    "gn:name":"Marciges",
    "gn:population":0,
    "gn:timezone":"Europe/Paris",
    "iso:country":"FR",
    "wof:name":"Marciges",
    "wof:placetype":"locality"
},
  "geometry": {"coordinates":[3.44453,47.22274],"type":"Point"}
}