{
  "type": "Feature",
  "properties": {
    "gn:admin1_code":"27",
    "gn:admin2_code":"58",
    "gn:admin3_code":"582",
    "gn:admin4_code":"58229.0",
    "gn:asciiname":"Ouches",
    "gn:country_code":"FR",
    "gn:dem":315,
    "gn:feature_class":"P",
    "gn:feature_code":"PPL",
    "gn:name":"Ouches",
    "gn:population":0,
    "gn:timezone":"Europe/Paris",
    "iso:country":"FR",
    "name:und_x_variant":[
        "Ouche",
        "Ouches"
    ],
    "wof:name":"Ouches",
    "wof:placetype":"locality"
},
  "geometry": {"coordinates":[3.87857,47.40559],"type":"Point"}
}