{
  "type": "Feature",
  "properties": {
    "gn:admin1_code":"24",
    "gn:admin2_code":"28",
    "gn:admin3_code":"281",
    "gn:admin4_code":"28183",
    "gn:asciiname":"Gaudreville",
    "gn:country_code":"FR",
    "gn:dem":144,
    "gn:feature_class":"P",
    "gn:feature_code":"PPL",
    "gn:name":"Gaudreville",
    "gn:population":0,
    "gn:timezone":"Europe/Paris",
    "iso:country":"FR",
    "wof:name":"Gaudreville",
    "wof:placetype":"locality"
},
  "geometry": {"coordinates":[1.97591,48.37437],"type":"Point"}
}