{
  "type": "Feature",
  "properties": {
    "gn:admin1_code":"53",
    "gn:admin2_code":"29",
    "gn:admin3_code":"292",
    "gn:admin4_code":"29238",
    "gn:asciiname":"Trevarguen",
    "gn:country_code":"FR",
    "gn:dem":43,
    "gn:feature_class":"P",
    "gn:feature_code":"PPL",
    "gn:name":"Tr\u00e9varguen",
    "gn:population":0,
    "gn:timezone":"Europe/Paris",
    "iso:country":"FR",
    "wof:name":"Trevarguen",
    "wof:placetype":"locality"
},
  "geometry": {"coordinates":[-4.54885,48.32213],"type":"Point"}
}