{
  "type": "Feature",
  "properties": {
    "gn:admin1_code":"28",
    "gn:admin2_code":"50",
    "gn:admin3_code":"502",
    "gn:admin4_code":"50178.0",
    "gn:asciiname":"Inglemare",
    "gn:country_code":"FR",
    "gn:dem":14,
    "gn:feature_class":"P",
    "gn:feature_code":"PPLL",
    "gn:name":"Inglemare",
    "gn:population":0,
    "gn:timezone":"Europe/Paris",
    "iso:country":"FR",
    "wof:name":"Inglemare",
    "wof:placetype":"locality"
},
  "geometry": {"coordinates":[-1.46222,49.69167],"type":"Point"}
}