{
  "type": "Feature",
  "properties": {
    "gn:admin1_code":"84",
    "gn:admin2_code":"43",
    "gn:admin3_code":"432",
    "gn:admin4_code":"43122",
    "gn:asciiname":"Lissac",
    "gn:country_code":"FR",
    "gn:dem":841,
    "gn:feature_class":"P",
    "gn:feature_code":"PPL",
    "gn:name":"Lissac",
    "gn:population":255,
    "gn:timezone":"Europe/Paris",
    "iso:country":"FR",
    "wof:name":"Lissac",
    "wof:placetype":"locality",
    "wof:population":255
},
  "geometry": {"coordinates":[3.76779,45.13265],"type":"Point"}
}