{
  "type": "Feature",
  "properties": {
    "gn:admin1_code":"84",
    "gn:admin2_code":"43",
    "gn:admin3_code":"432",
    "gn:admin4_code":"43122",
    "gn:asciiname":"Lissac",
    "gn:country_code":"FR",
    "gn:dem":841,
    "gn:feature_class":"P",
    "gn:feature_code":"PPL",
    "gn:name":"Lissac",
    "gn:population":255,
    "gn:timezone":"Europe/Paris",
    "iso:country":"FR",
    "name:ceb_x_preferred":[
        "Lissac"
    ],
    "name:deu_x_preferred":[
        "Lissac"
    ],
    "name:fra_x_preferred":[
        "Lissac"
    ],
    "name:ita_x_preferred":[
        "Lissac"
    ],
    "name:nds_x_preferred":[
        "Lissac"
    ],
    "name:nld_x_preferred":[
        "Lissac"
    ],
    "name:oci_x_preferred":[
        "Lissac"
    ],
    "name:pol_x_preferred":[
        "Lissac"
    ],
    "name:por_x_preferred":[
        "Lissac"
    ],
    "name:rus_x_preferred":[
        "\u041b\u0438\u0441\u0441\u0430\u043a"
    ],
    "name:scn_x_preferred":[
        "Lissac"
    ],
    "name:slk_x_preferred":[
        "Lissac"
    ],
    "name:spa_x_preferred":[
        "Lissac"
    ],
    "name:swe_x_preferred":[
        "Lissac"
    ],
    "name:ukr_x_preferred":[
        "\u041b\u0456\u0441\u0441\u0430\u043a"
    ],
    "wof:name":"Lissac",
    "wof:placetype":"locality",
    "wof:population":255
},
  "geometry": {"coordinates":[3.76779,45.13265],"type":"Point"}
}