{
  "type": "Feature",
  "properties": {
    "frgov:code_epci":"200073419",
    "frgov:insee_arr":"2",
    "frgov:insee_com":"43122",
    "frgov:insee_dep":"43",
    "frgov:insee_reg":"84",
    "frgov:nom_com":"Lissac",
    "frgov:nom_com_m":"LISSAC",
    "frgov:nom_dep":"HAUTE-LOIRE",
    "frgov:nom_reg":"AUVERGNE-RHONE-ALPES",
    "frgov:statut":"Commune simple",
    "gn:admin1_code":"84",
    "gn:admin2_code":"43",
    "gn:admin3_code":"432",
    "gn:admin4_code":"43122",
    "gn:asciiname":"Lissac",
    "gn:country_code":"FR",
    "gn:dem":841,
    "gn:feature_class":"P",
    "gn:feature_code":"PPL",
    "gn:name":"Lissac",
    "gn:population":255,
    "gn:timezone":"Europe/Paris",
    "iso:country":"FR",
    "name:ceb_x_preferred":[
        "Lissac"
    ],
    "name:deu_x_preferred":[
        "Lissac"
    ],
    "name:fra_x_preferred":[
        "Lissac"
    ],
    "name:ita_x_preferred":[
        "Lissac"
    ],
    "name:nds_x_preferred":[
        "Lissac"
    ],
    "name:nld_x_preferred":[
        "Lissac"
    ],
    "name:oci_x_preferred":[
        "Lissac"
    ],
    "name:pol_x_preferred":[
        "Lissac"
    ],
    "name:por_x_preferred":[
        "Lissac"
    ],
    "name:rus_x_preferred":[
        "\u041b\u0438\u0441\u0441\u0430\u043a"
    ],
    "name:scn_x_preferred":[
        "Lissac"
    ],
    "name:slk_x_preferred":[
        "Lissac"
    ],
    "name:spa_x_preferred":[
        "Lissac"
    ],
    "name:swe_x_preferred":[
        "Lissac"
    ],
    "name:ukr_x_preferred":[
        "\u041b\u0456\u0441\u0441\u0430\u043a"
    ],
    "qs:a0":"France",
    "qs:a1":"HAUTE-LOIRE",
    "qs:a1_lc":"43",
    "qs:a1r":"AUVERGNE",
    "qs:a1r_lc":"83",
    "qs:a2_lc":"24",
    "qs:a2r_lc":"2",
    "qs:adm0":"France",
    "qs:adm0_a3":"FRA",
    "qs:la":"LISSAC",
    "qs:la_lc":"43122",
    "qs:level":"localadmin",
    "qs:type":"Commune simple",
    "wof:coterminous":[
        404363035
    ],
    "wof:name":"Lissac",
    "wof:placetype":"locality",
    "wof:placetype_local":"Commune simple",
    "wof:population":255
},
  "geometry": {"coordinates":[3.76779,45.13265],"type":"Point"}
}