{
  "type": "Feature",
  "properties": {
    "gn:admin1_code":"75",
    "gn:admin2_code":"23",
    "gn:admin3_code":"231",
    "gn:admin4_code":"23220",
    "gn:asciiname":"Empeaux",
    "gn:country_code":"FR",
    "gn:dem":555,
    "gn:feature_class":"P",
    "gn:feature_code":"PPL",
    "gn:name":"Empeaux",
    "gn:population":0,
    "gn:timezone":"Europe/Paris",
    "iso:country":"FR",
    "name:arg_x_preferred":[
        "Emp\u00e8uts"
    ],
    "name:bug_x_preferred":[
        "Empeaux"
    ],
    "name:cat_x_preferred":[
        "Emp\u00e8uts"
    ],
    "name:ceb_x_preferred":[
        "Empeaux"
    ],
    "name:deu_x_preferred":[
        "Empeaux"
    ],
    "name:eus_x_preferred":[
        "Empeaux"
    ],
    "name:fra_x_preferred":[
        "Empeaux"
    ],
    "name:hun_x_preferred":[
        "Empeaux"
    ],
    "name:ita_x_preferred":[
        "Empeaux"
    ],
    "name:lat_x_preferred":[
        "Empeaux"
    ],
    "name:msa_x_preferred":[
        "Empeaux"
    ],
    "name:nld_x_preferred":[
        "Empeaux"
    ],
    "name:oci_x_preferred":[
        "Emp\u00e8uts"
    ],
    "name:pol_x_preferred":[
        "Empeaux"
    ],
    "name:ron_x_preferred":[
        "Empeaux"
    ],
    "name:rus_x_preferred":[
        "\u0410\u043c\u043f\u043e"
    ],
    "name:slk_x_preferred":[
        "Empeaux"
    ],
    "name:spa_x_preferred":[
        "Empeaux"
    ],
    "name:swe_x_preferred":[
        "Empeaux"
    ],
    "name:ukr_x_preferred":[
        "\u0410\u043c\u043f\u043e"
    ],
    "name:vie_x_preferred":[
        "Empeaux"
    ],
    "name:vol_x_preferred":[
        "Empeaux"
    ],
    "name:war_x_preferred":[
        "Empeaux"
    ],
    "wof:name":"Empeaux",
    "wof:placetype":"locality"
},
  "geometry": {"coordinates":[2.17577,46.01071],"type":"Point"}
}