{
  "type": "Feature",
  "properties": {
    "gn:admin1_code":"53",
    "gn:admin2_code":"22",
    "gn:admin3_code":"221",
    "gn:admin4_code":"22305",
    "gn:asciiname":"Saint-Jouan-de-l'Isle",
    "gn:country_code":"FR",
    "gn:dem":93,
    "gn:feature_class":"P",
    "gn:feature_code":"PPL",
    "gn:name":"Saint-Jouan-de-l\u2019Isle",
    "gn:population":0,
    "gn:timezone":"Europe/Paris",
    "iso:country":"FR",
    "name:bre_x_preferred":[
        "Sant-Yowan-an-Enez"
    ],
    "name:bug_x_preferred":[
        "Saint-Jouan-de-l'Isle"
    ],
    "name:cat_x_preferred":[
        "Saint-Jouan-de-l'Isle"
    ],
    "name:ceb_x_preferred":[
        "Saint-Jouan-de-l'Isle"
    ],
    "name:cym_x_preferred":[
        "Sant-Yowan-an-Enez"
    ],
    "name:deu_x_preferred":[
        "Saint-Jouan-de-l\u2019Isle"
    ],
    "name:epo_x_preferred":[
        "Saint-Jouan-de-l'Isle"
    ],
    "name:eus_x_preferred":[
        "Saint-Jouan-de-l'Isle"
    ],
    "name:fra_x_preferred":[
        "Saint-Jouan-de-l'Isle"
    ],
    "name:hun_x_preferred":[
        "Saint-Jouan-de-l\u2019Isle"
    ],
    "name:ita_x_preferred":[
        "Saint-Jouan-de-l'Isle"
    ],
    "name:kaz_x_preferred":[
        "\u0421\u0435\u043d-\u0416\u0443\u0430\u043d-\u0434\u0435-\u043b'\u0418\u043b\u044c"
    ],
    "name:msa_x_preferred":[
        "Saint-Jouan-de-l'Isle"
    ],
    "name:nld_x_preferred":[
        "Saint-Jouan-de-l'Isle"
    ],
    "name:oci_x_preferred":[
        "Saint-Jouan-de-l'Isle"
    ],
    "name:pms_x_preferred":[
        "Saint-Jouan-de-l'Isle"
    ],
    "name:pol_x_preferred":[
        "Saint-Jouan-de-l\u2019Isle"
    ],
    "name:por_x_preferred":[
        "Saint-Jouan-de-l'Isle"
    ],
    "name:ron_x_preferred":[
        "Saint-Jouan-de-l'Isle"
    ],
    "name:rus_x_preferred":[
        "\u0421\u0435\u043d-\u0416\u0443\u0430\u043d-\u0434\u0435-\u043b\u2019\u0418\u043b\u044c"
    ],
    "name:slk_x_preferred":[
        "Saint-Jouan-de-l\u2019Isle"
    ],
    "name:spa_x_preferred":[
        "Saint-Jouan-de-l'Isle"
    ],
    "name:swe_x_preferred":[
        "Saint-Jouan-de-l'Isle"
    ],
    "name:ukr_x_preferred":[
        "\u0421\u0435\u043d-\u0416\u0443\u0430\u043d-\u0434\u0435-\u043b'\u0406\u043b\u044c"
    ],
    "name:und_x_variant":[
        "Saint-Jouan-de-l\u2019Isle"
    ],
    "name:urd_x_preferred":[
        "\u0633\u06cc\u0646\u0679-\u062c\u0648\u0627\u0646-\u062f\u06d2-\u0644\u0633\u0644\u06d2"
    ],
    "name:uzb_x_preferred":[
        "Saint-Jouan-de-l'Isle"
    ],
    "name:vie_x_preferred":[
        "Saint-Jouan-de-l'Isle"
    ],
    "name:vol_x_preferred":[
        "Saint-Jouan-de-l'Isle"
    ],
    "name:war_x_preferred":[
        "Saint-Jouan-de-l'Isle"
    ],
    "name:zho_x_preferred":[
        "\u5723\u8339\u6602\u5fb7\u5229\u52d2"
    ],
    "wof:name":"Saint-Jouan-de-l'Isle",
    "wof:placetype":"locality"
},
  "geometry": {"coordinates":[-2.15925,48.26703],"type":"Point"}
}