{
  "type": "Feature",
  "properties": {
    "gn:admin1_code":"53",
    "gn:admin2_code":"22",
    "gn:admin3_code":"221",
    "gn:admin4_code":"22305",
    "gn:asciiname":"Saint-Jouan-de-l'Isle",
    "gn:country_code":"FR",
    "gn:dem":93,
    "gn:feature_class":"P",
    "gn:feature_code":"PPL",
    "gn:name":"Saint-Jouan-de-l\u2019Isle",
    "gn:population":0,
    "gn:timezone":"Europe/Paris",
    "iso:country":"FR",
    "name:bre_x_preferred":[
        "Sant-Yowan-an-Enez"
    ],
    "name:fra_x_preferred":[
        "Saint-Jouan-de-l'Isle"
    ],
    "name:und_x_variant":[
        "Saint-Jouan-de-l\u2019Isle"
    ],
    "wof:name":"Saint-Jouan-de-l'Isle",
    "wof:placetype":"locality"
},
  "geometry": {"coordinates":[-2.15925,48.26703],"type":"Point"}
}