{
  "type": "Feature",
  "properties": {
    "gn:admin1_code":"11",
    "gn:admin2_code":"77",
    "gn:admin3_code":"773",
    "gn:admin4_code":"77262.0",
    "gn:asciiname":"Ecurie",
    "gn:cc2":"FR",
    "gn:country_code":"FR",
    "gn:dem":162,
    "gn:feature_class":"P",
    "gn:feature_code":"PPL",
    "gn:name":"\u00c9curie",
    "gn:population":0,
    "gn:timezone":"Europe/Paris",
    "iso:country":"FR",
    "name:fra_x_preferred":[
        "\u00c9curie"
    ],
    "name:rus_x_preferred":[
        "\u042d\u043a\u044e\u0440\u0438"
    ],
    "name:und_x_variant":[
        "Ecury"
    ],
    "wof:name":"Ecurie",
    "wof:placetype":"locality"
},
  "geometry": {"coordinates":[3.47091,48.61197],"type":"Point"}
}