{
  "type": "Feature",
  "properties": {
    "gn:gn_country":"FR",
    "gn:gn_fcode":"PPL",
    "gn:gn_pop":528,
    "gn:population":528,
    "iso:country":"FR",
    "name:bug_x_preferred":[
        "Vengeons"
    ],
    "name:cat_x_preferred":[
        "Vengeons"
    ],
    "name:ceb_x_preferred":[
        "Vengeons"
    ],
    "name:ces_x_preferred":[
        "Vengeons"
    ],
    "name:deu_x_preferred":[
        "Vengeons"
    ],
    "name:ell_x_preferred":[
        "\u0392\u03b1\u03bd\u03b6\u03cc\u03bd"
    ],
    "name:eng_x_preferred":[
        "Vengeons"
    ],
    "name:eus_x_preferred":[
        "Vengeons"
    ],
    "name:fas_x_preferred":[
        "\u0648\u0646\u06af\u0626\u0648\u0646\u0633"
    ],
    "name:fra_x_preferred":[
        "Vengeons"
    ],
    "name:hun_x_preferred":[
        "Vengeons"
    ],
    "name:ita_x_preferred":[
        "Vengeons"
    ],
    "name:kaz_x_preferred":[
        "\u0412\u0430\u043d\u0436\u043e\u043d"
    ],
    "name:lat_x_preferred":[
        "Vengeons"
    ],
    "name:msa_x_preferred":[
        "Vengeons"
    ],
    "name:nan_x_preferred":[
        "Vengeons"
    ],
    "name:nld_x_preferred":[
        "Vengeons"
    ],
    "name:oci_x_preferred":[
        "Vengeons"
    ],
    "name:pms_x_preferred":[
        "Vengeons"
    ],
    "name:pol_x_preferred":[
        "Vengeons"
    ],
    "name:por_x_preferred":[
        "Vengeons"
    ],
    "name:ron_x_preferred":[
        "Vengeons"
    ],
    "name:slk_x_preferred":[
        "Vengeons"
    ],
    "name:spa_x_preferred":[
        "Vengeons"
    ],
    "name:swe_x_preferred":[
        "Vengeons"
    ],
    "name:ukr_x_preferred":[
        "\u0412\u0430\u043d\u0436\u043e\u043d"
    ],
    "name:uzb_x_preferred":[
        "Vengeons"
    ],
    "name:vie_x_preferred":[
        "Vengeons"
    ],
    "name:vol_x_preferred":[
        "Vengeons"
    ],
    "name:war_x_preferred":[
        "Vengeons"
    ],
    "name:zho_x_preferred":[
        "\u65fa\u5bb9"
    ],
    "qs_pg:aaroncc":"FR",
    "qs_pg:gn_country":"FR",
    "qs_pg:gn_fcode":"PPL",
    "qs_pg:gn_pop":528,
    "qs_pg:name":"Vengeons",
    "qs_pg:name_adm0":"France",
    "qs_pg:name_adm1":"Basse-Normandie",
    "qs_pg:photos_9k":1,
    "qs_pg:photos_9r":1,
    "qs_pg:photos_all":1,
    "qs_pg:photos_sr":0,
    "qs_pg:pop_sr":2,
    "qs_pg:qs_pg_placetype":"locality",
    "qs_pg:qs_pg_placetype_gp":"Town",
    "qs_pg:woe_adm0":23424819,
    "woe:adm0_id":23424819,
    "woe:name_adm0":"France",
    "woe:name_adm1":"Basse-Normandie",
    "woe:placetype":"Town",
    "wof:name":"Vengeons",
    "wof:placetype":"neighbourhood",
    "wof:population":528
},
  "geometry": {"coordinates":[-0.9166,48.75409],"type":"Point"}
}