{
  "type": "Feature",
  "properties": {
    "gn:admin1_code":"53",
    "gn:admin2_code":"29",
    "gn:admin3_code":"292",
    "gn:admin4_code":"29018",
    "gn:asciiname":"Kerhornou",
    "gn:country_code":"FR",
    "gn:dem":235,
    "gn:feature_class":"P",
    "gn:feature_code":"PPL",
    "gn:name":"Kerhornou",
    "gn:population":0,
    "gn:timezone":"Europe/Paris",
    "iso:country":"FR",
    "wof:name":"Kerhornou",
    "wof:placetype":"locality"
},
  "geometry": {"coordinates":[-3.85856,48.36422],"type":"Point"}
}