{
  "type": "Feature",
  "properties": {
    "gn:admin1_code":"24",
    "gn:admin2_code":"28",
    "gn:admin3_code":"282",
    "gn:admin4_code":"28382.0",
    "gn:asciiname":"Frecu",
    "gn:country_code":"FR",
    "gn:dem":125,
    "gn:feature_class":"P",
    "gn:feature_code":"PPL",
    "gn:name":"Fr\u00e9cu",
    "gn:population":0,
    "gn:timezone":"Europe/Paris",
    "iso:country":"FR",
    "wof:name":"Frecu",
    "wof:placetype":"locality"
},
  "geometry": {"coordinates":[1.74358,48.07083],"type":"Point"}
}