{
  "type": "Feature",
  "properties": {
    "gn:admin1_code":"76",
    "gn:admin2_code":"12",
    "gn:admin3_code":"121",
    "gn:admin4_code":"12168",
    "gn:asciiname":"Combe-Redonde",
    "gn:cc2":"FR",
    "gn:country_code":"FR",
    "gn:dem":807,
    "gn:feature_class":"P",
    "gn:feature_code":"PPL",
    "gn:name":"Combe-Redonde",
    "gn:population":0,
    "gn:timezone":"Europe/Paris",
    "iso:country":"FR",
    "name:und_x_variant":[
        "Cumbe-Redonde",
        "Combe-Redonne",
        "Combe-Redonde"
    ],
    "wof:name":"Combe-Redonde",
    "wof:placetype":"locality"
},
  "geometry": {"coordinates":[3.32439,43.9628],"type":"Point"}
}