{
  "type": "Feature",
  "properties": {
    "gn:admin1_code":"52",
    "gn:admin2_code":"72",
    "gn:admin3_code":"722",
    "gn:admin4_code":"72196",
    "gn:asciiname":"Ponthouin",
    "gn:country_code":"FR",
    "gn:dem":61,
    "gn:feature_class":"P",
    "gn:feature_code":"PPL",
    "gn:name":"Ponthouin",
    "gn:population":0,
    "gn:timezone":"Europe/Paris",
    "iso:country":"FR",
    "wof:name":"Ponthouin",
    "wof:placetype":"locality"
},
  "geometry": {"coordinates":[0.29294,48.21212],"type":"Point"}
}