{
  "type": "Feature",
  "properties": {
    "gn:admin1_code":"84",
    "gn:admin2_code":"43",
    "gn:admin3_code":"433",
    "gn:admin4_code":"43203",
    "gn:asciiname":"Mortesagne",
    "gn:country_code":"FR",
    "gn:dem":936,
    "gn:feature_class":"P",
    "gn:feature_code":"PPL",
    "gn:name":"Mortesagne",
    "gn:population":0,
    "gn:timezone":"Europe/Paris",
    "iso:country":"FR",
    "wof:name":"Mortesagne",
    "wof:placetype":"locality"
},
  "geometry": {"coordinates":[4.05268,45.14654],"type":"Point"}
}