{
  "type": "Feature",
  "properties": {
    "gn:admin1_code":"84",
    "gn:admin2_code":"63",
    "gn:admin3_code":"633",
    "gn:admin4_code":"63383.0",
    "gn:asciiname":"Oursiere",
    "gn:country_code":"FR",
    "gn:dem":806,
    "gn:feature_class":"P",
    "gn:feature_code":"PPL",
    "gn:name":"Oursi\u00e8re",
    "gn:population":0,
    "gn:timezone":"Europe/Paris",
    "iso:country":"FR",
    "wof:name":"Oursiere",
    "wof:placetype":"locality"
},
  "geometry": {"coordinates":[2.96614,45.52148],"type":"Point"}
}