{
  "type": "Feature",
  "properties": {
    "gn:admin1_code":"53",
    "gn:admin2_code":"29",
    "gn:admin3_code":"294",
    "gn:admin4_code":"29197",
    "gn:asciiname":"Kerdreal",
    "gn:country_code":"FR",
    "gn:dem":55,
    "gn:feature_class":"P",
    "gn:feature_code":"PPL",
    "gn:name":"Kerdr\u00e9al",
    "gn:population":0,
    "gn:timezone":"Europe/Paris",
    "iso:country":"FR",
    "wof:name":"Kerdreal",
    "wof:placetype":"locality"
},
  "geometry": {"coordinates":[-4.48475,47.99784],"type":"Point"}
}