{
  "type": "Feature",
  "properties": {
    "gn:admin1_code":"27",
    "gn:admin2_code":"58",
    "gn:admin3_code":"581",
    "gn:admin4_code":"58001",
    "gn:asciiname":"Roche",
    "gn:country_code":"FR",
    "gn:dem":273,
    "gn:feature_class":"P",
    "gn:feature_code":"PPL",
    "gn:name":"Roche",
    "gn:population":0,
    "gn:timezone":"Europe/Paris",
    "iso:country":"FR",
    "name:als_x_preferred":[
        "Roche"
    ],
    "name:bre_x_preferred":[
        "Roche"
    ],
    "name:cat_x_preferred":[
        "Roche"
    ],
    "name:ceb_x_preferred":[
        "Roche"
    ],
    "name:ces_x_preferred":[
        "Roche"
    ],
    "name:deu_x_preferred":[
        "Roche"
    ],
    "name:epo_x_preferred":[
        "Roche"
    ],
    "name:fin_x_preferred":[
        "Roche"
    ],
    "name:fra_x_preferred":[
        "Roche"
    ],
    "name:ita_x_preferred":[
        "Roche"
    ],
    "name:jpn_x_preferred":[
        "\u30ed\u30c3\u30b7\u30e5"
    ],
    "name:lmo_x_preferred":[
        "Roche"
    ],
    "name:nds_x_preferred":[
        "Roche"
    ],
    "name:nld_x_preferred":[
        "Roche"
    ],
    "name:pms_x_preferred":[
        "Roche"
    ],
    "name:pol_x_preferred":[
        "Roche"
    ],
    "name:por_x_preferred":[
        "Roche"
    ],
    "name:ron_x_preferred":[
        "Roche"
    ],
    "name:rus_x_preferred":[
        "\u0420\u043e\u0448"
    ],
    "name:scn_x_preferred":[
        "Roche"
    ],
    "name:sco_x_preferred":[
        "Roche"
    ],
    "name:slk_x_preferred":[
        "Roche"
    ],
    "name:spa_x_preferred":[
        "Roche"
    ],
    "name:swe_x_preferred":[
        "Roche"
    ],
    "name:tur_x_preferred":[
        "Roche"
    ],
    "name:ukr_x_preferred":[
        "\u0420\u043e\u0448"
    ],
    "wof:name":"Roche",
    "wof:placetype":"locality"
},
  "geometry": {"coordinates":[3.65476,47.11107],"type":"Point"}
}