{
  "type": "Feature",
  "properties": {
    "gn:admin1_code":"27",
    "gn:admin2_code":"58",
    "gn:admin3_code":"581",
    "gn:admin4_code":"58001",
    "gn:asciiname":"Roche",
    "gn:country_code":"FR",
    "gn:dem":273,
    "gn:feature_class":"P",
    "gn:feature_code":"PPL",
    "gn:name":"Roche",
    "gn:population":0,
    "gn:timezone":"Europe/Paris",
    "iso:country":"FR",
    "wof:name":"Roche",
    "wof:placetype":"locality"
},
  "geometry": {"coordinates":[3.65476,47.11107],"type":"Point"}
}