{
  "type": "Feature",
  "properties": {
    "iso:country":"FR",
    "name:eng_x_preferred":[
        "Edouard Vaillant-Abreuvoir"
    ],
    "name:fra_x_preferred":[
        "Edouard Vaillant-Abreuvoir"
    ],
    "wof:name":"Edouard Vaillant-Abreuvoir",
    "wof:placetype":"neighbourhood"
},
  "geometry": {"coordinates":[2.46790960910515,48.91084699910913],"type":"Point"}
}