{
  "type": "Feature",
  "properties": {
    "gn:admin1_code":"84",
    "gn:admin2_code":"15",
    "gn:admin3_code":"153",
    "gn:admin4_code":"15201",
    "gn:asciiname":"Vigouroux",
    "gn:country_code":"FR",
    "gn:dem":1066,
    "gn:feature_class":"P",
    "gn:feature_code":"PPL",
    "gn:name":"Vigouroux",
    "gn:population":0,
    "gn:timezone":"Europe/Paris",
    "iso:country":"FR",
    "name:fra_x_preferred":[
        "Vigouroux"
    ],
    "wof:name":"Vigouroux",
    "wof:placetype":"locality"
},
  "geometry": {"coordinates":[2.79801,44.95132],"type":"Point"}
}