{
  "type": "Feature",
  "properties": {
    "iso:country":"FR",
    "name:deu_x_preferred":[
        "La Croix-Rousse"
    ],
    "name:epo_x_preferred":[
        "La Croix-Rousse"
    ],
    "name:fra_x_preferred":[
        "La Croix-Rousse"
    ],
    "name:hye_x_preferred":[
        "\u053f\u0580\u0578\u0582\u0561 \u054c\u0578\u0582\u057d"
    ],
    "name:ind_x_preferred":[
        "La Croix-Rousse"
    ],
    "name:ita_x_preferred":[
        "La Croix-Rousse"
    ],
    "name:nld_x_preferred":[
        "La Croix-Rousse"
    ],
    "name:nor_x_preferred":[
        "Croix-Rousse"
    ],
    "name:por_x_preferred":[
        "Croix-Rousse"
    ],
    "name:rus_x_preferred":[
        "\u041a\u0440\u0443\u0430-\u0420\u0443\u0441\u0441"
    ],
    "name:spa_x_preferred":[
        "La Croix Rousse"
    ],
    "name:zho_x_preferred":[
        "\u7ea2\u5341\u5b57\u5c71"
    ],
    "wof:name":"La Croix-Rousse",
    "wof:placetype":"neighbourhood"
},
  "geometry": {"coordinates":[4.82653495099482,45.77747059576843],"type":"Point"}
}