{
  "type": "Feature",
  "properties": {
    "iso:country":"FR",
    "wof:name":"La Croix-Rousse",
    "wof:placetype":"neighbourhood"
},
  "geometry": {"coordinates":[4.82653495099482,45.77747059576843],"type":"Point"}
}