{
  "type": "Feature",
  "properties": {
    "gn:admin1_code":"53",
    "gn:admin2_code":"29",
    "gn:admin3_code":"293",
    "gn:admin4_code":"29113",
    "gn:asciiname":"Kermerchou",
    "gn:country_code":"FR",
    "gn:dem":116,
    "gn:feature_class":"P",
    "gn:feature_code":"PPL",
    "gn:name":"Kermerchou",
    "gn:population":0,
    "gn:timezone":"Europe/Paris",
    "iso:country":"FR",
    "wof:name":"Kermerchou",
    "wof:placetype":"locality"
},
  "geometry": {"coordinates":[-3.74589,48.65555],"type":"Point"}
}