{
  "type": "Feature",
  "properties": {
    "gn:admin1_code":"94",
    "gn:admin2_code":"2B",
    "gn:admin3_code":"2B5",
    "gn:admin4_code":"2B235",
    "gn:asciiname":"Forcili",
    "gn:country_code":"FR",
    "gn:dem":783,
    "gn:feature_class":"P",
    "gn:feature_code":"PPL",
    "gn:name":"Forcili",
    "gn:population":0,
    "gn:timezone":"Europe/Paris",
    "iso:country":"FR",
    "name:und_x_variant":[
        "Porcili",
        "Forcili"
    ],
    "wof:name":"Forcili",
    "wof:placetype":"locality"
},
  "geometry": {"coordinates":[9.0001,42.52823],"type":"Point"}
}