{
  "type": "Feature",
  "properties": {
    "frgov:code_epci":"200073419",
    "frgov:insee_arr":"2",
    "frgov:insee_com":"43140",
    "frgov:insee_dep":"43",
    "frgov:insee_reg":"84",
    "frgov:nom_com":"Le Monteil",
    "frgov:nom_com_m":"LE MONTEIL",
    "frgov:nom_dep":"HAUTE-LOIRE",
    "frgov:nom_reg":"AUVERGNE-RHONE-ALPES",
    "frgov:statut":"Commune simple",
    "gn:admin1_code":"84",
    "gn:admin2_code":"43",
    "gn:admin3_code":"432",
    "gn:admin4_code":"43140",
    "gn:asciiname":"Le Monteil",
    "gn:country_code":"FR",
    "gn:dem":635,
    "gn:feature_class":"P",
    "gn:feature_code":"PPL",
    "gn:name":"Le Monteil",
    "gn:population":0,
    "gn:timezone":"Europe/Paris",
    "iso:country":"FR",
    "name:ceb_x_preferred":[
        "Le Monteil"
    ],
    "name:deu_x_preferred":[
        "Le Monteil"
    ],
    "name:fra_x_preferred":[
        "Le Monteil"
    ],
    "name:ita_x_preferred":[
        "Le Monteil"
    ],
    "name:nds_x_preferred":[
        "Le Monteil"
    ],
    "name:nld_x_preferred":[
        "Le Monteil"
    ],
    "name:pol_x_preferred":[
        "Le Monteil"
    ],
    "name:por_x_preferred":[
        "Le Monteil"
    ],
    "name:rus_x_preferred":[
        "\u041b\u0435-\u041c\u043e\u043d\u0442\u0435\u0439"
    ],
    "name:scn_x_preferred":[
        "Le Monteil"
    ],
    "name:slk_x_preferred":[
        "Le Monteil"
    ],
    "name:spa_x_preferred":[
        "Le Monteil"
    ],
    "name:swe_x_preferred":[
        "Le Monteil"
    ],
    "name:ukr_x_preferred":[
        "\u041b\u0435-\u041c\u043e\u043d\u0442\u0435\u0439"
    ],
    "qs:a0":"France",
    "qs:a1":"HAUTE-LOIRE",
    "qs:a1_lc":"43",
    "qs:a1r":"AUVERGNE",
    "qs:a1r_lc":"83",
    "qs:a2_lc":"19",
    "qs:a2r_lc":"2",
    "qs:adm0":"France",
    "qs:adm0_a3":"FRA",
    "qs:la":"LE MONTEIL",
    "qs:la_lc":"43140",
    "qs:level":"localadmin",
    "qs:type":"Commune simple",
    "wof:coterminous":[
        404380223
    ],
    "wof:name":"Le Monteil",
    "wof:placetype":"locality",
    "wof:placetype_local":"Commune simple"
},
  "geometry": {"coordinates":[3.91348,45.06544],"type":"Point"}
}