{
  "type": "Feature",
  "properties": {
    "gn:admin1_code":"84",
    "gn:admin2_code":"43",
    "gn:admin3_code":"432",
    "gn:admin4_code":"43140",
    "gn:asciiname":"Le Monteil",
    "gn:country_code":"FR",
    "gn:dem":635,
    "gn:feature_class":"P",
    "gn:feature_code":"PPL",
    "gn:name":"Le Monteil",
    "gn:population":0,
    "gn:timezone":"Europe/Paris",
    "iso:country":"FR",
    "wof:name":"Le Monteil",
    "wof:placetype":"locality"
},
  "geometry": {"coordinates":[3.91348,45.06544],"type":"Point"}
}