{
  "type": "Feature",
  "properties": {
    "gn:admin1_code":"11",
    "gn:admin2_code":"91",
    "gn:admin3_code":"911",
    "gn:admin4_code":"91079",
    "gn:asciiname":"Boissy-la-Riviere",
    "gn:country_code":"FR",
    "gn:dem":108,
    "gn:feature_class":"P",
    "gn:feature_code":"PPL",
    "gn:name":"Boissy-la-Rivi\u00e8re",
    "gn:population":0,
    "gn:timezone":"Europe/Paris",
    "iso:country":"FR",
    "name:kaz_x_preferred":[
        "\u0411\u0443\u0430\u0441\u0441\u0438-\u043b\u0430-\u0420\u0438\u0432\u044c\u0435\u0440"
    ],
    "name:srp_x_preferred":[
        "\u0411\u043e\u0430\u0441\u0438 \u043b\u0430 \u0420\u0438\u0432\u0458\u0435\u0440"
    ],
    "name:ukr_x_preferred":[
        "\u0411\u0443\u0430\u0441\u0441\u0456-\u043b\u0430-\u0420\u0438\u0432\u0454\u0440"
    ],
    "name:und_x_variant":[
        "Boissy",
        "Boissy-la-Rivi\u00e8re"
    ],
    "name:zho_x_preferred":[
        "\u5e03\u74e6\u897f\u62c9\u91cc\u7ef4\u57c3"
    ],
    "wof:name":"Boissy-la-Riviere",
    "wof:placetype":"locality"
},
  "geometry": {"coordinates":[2.1451,48.37317],"type":"Point"}
}