{
  "type": "Feature",
  "properties": {
    "gn:admin1_code":"76",
    "gn:admin2_code":"12",
    "gn:admin3_code":"122",
    "gn:admin4_code":"12119",
    "gn:asciiname":"Auriac",
    "gn:country_code":"FR",
    "gn:dem":905,
    "gn:feature_class":"P",
    "gn:feature_code":"PPL",
    "gn:name":"Auriac",
    "gn:population":0,
    "gn:timezone":"Europe/Paris",
    "iso:country":"FR",
    "wof:name":"Auriac",
    "wof:placetype":"locality"
},
  "geometry": {"coordinates":[2.80284,44.70475],"type":"Point"}
}