{
  "type": "Feature",
  "properties": {
    "gn:admin1_code":"76",
    "gn:admin2_code":"12",
    "gn:admin3_code":"122",
    "gn:admin4_code":"12119",
    "gn:asciiname":"Auriac",
    "gn:country_code":"FR",
    "gn:dem":905,
    "gn:feature_class":"P",
    "gn:feature_code":"PPL",
    "gn:name":"Auriac",
    "gn:population":0,
    "gn:timezone":"Europe/Paris",
    "iso:country":"FR",
    "name:ceb_x_preferred":[
        "Auriac"
    ],
    "name:deu_x_preferred":[
        "Auriac"
    ],
    "name:eus_x_preferred":[
        "Auriac"
    ],
    "name:fra_x_preferred":[
        "Auriac"
    ],
    "name:ita_x_preferred":[
        "Auriac"
    ],
    "name:lmo_x_preferred":[
        "Auriac"
    ],
    "name:ltz_x_preferred":[
        "Auriac"
    ],
    "name:nds_x_preferred":[
        "Auriac"
    ],
    "name:nld_x_preferred":[
        "Auriac"
    ],
    "name:oci_x_preferred":[
        "Auriac"
    ],
    "name:pms_x_preferred":[
        "Auriac"
    ],
    "name:pol_x_preferred":[
        "Auriac"
    ],
    "name:por_x_preferred":[
        "Auriac"
    ],
    "name:rus_x_preferred":[
        "\u041e\u0440\u044c\u044f\u043a"
    ],
    "name:slk_x_preferred":[
        "Auriac"
    ],
    "name:spa_x_preferred":[
        "Auriac"
    ],
    "name:swe_x_preferred":[
        "Auriac"
    ],
    "name:ukr_x_preferred":[
        "\u041e\u0440\u0456\u0430\u043a"
    ],
    "wof:name":"Auriac",
    "wof:placetype":"locality"
},
  "geometry": {"coordinates":[2.80284,44.70475],"type":"Point"}
}