{
  "type": "Feature",
  "properties": {
    "gn:admin1_code":"53",
    "gn:admin2_code":"56",
    "gn:admin3_code":"561",
    "gn:admin4_code":"56089",
    "gn:asciiname":"Kerguendo",
    "gn:country_code":"FR",
    "gn:dem":156,
    "gn:feature_class":"P",
    "gn:feature_code":"PPL",
    "gn:name":"Kerguendo",
    "gn:population":0,
    "gn:timezone":"Europe/Paris",
    "iso:country":"FR",
    "wof:name":"Kerguendo",
    "wof:placetype":"locality"
},
  "geometry": {"coordinates":[-3.25406,47.97798],"type":"Point"}
}