{
  "type": "Feature",
  "properties": {
    "gn:admin1_code":"84",
    "gn:admin2_code":"07",
    "gn:admin3_code":"073",
    "gn:admin4_code":"07309",
    "gn:asciiname":"Sermailles",
    "gn:country_code":"FR",
    "gn:dem":606,
    "gn:feature_class":"P",
    "gn:feature_code":"PPL",
    "gn:name":"Sermailles",
    "gn:population":0,
    "gn:timezone":"Europe/Paris",
    "iso:country":"FR",
    "wof:name":"Sermailles",
    "wof:placetype":"locality"
},
  "geometry": {"coordinates":[4.59822,45.13513],"type":"Point"}
}