{
  "type": "Feature",
  "properties": {
    "gn:admin1_code":"84",
    "gn:admin2_code":"38",
    "gn:admin3_code":"381",
    "gn:admin4_code":"38396",
    "gn:asciiname":"Fugiere",
    "gn:country_code":"FR",
    "gn:dem":1030,
    "gn:feature_class":"P",
    "gn:feature_code":"PPL",
    "gn:name":"Fugi\u00e8re",
    "gn:population":0,
    "gn:timezone":"Europe/Paris",
    "iso:country":"FR",
    "name:und_x_variant":[
        "Fugi\u00e8res",
        "Fugi\u00e8re"
    ],
    "wof:name":"Fugiere",
    "wof:placetype":"locality"
},
  "geometry": {"coordinates":[5.80645,44.95441],"type":"Point"}
}