{
  "type": "Feature",
  "properties": {
    "gn:admin1_code":"76",
    "gn:admin2_code":"48",
    "gn:admin3_code":"482",
    "gn:admin4_code":"48044",
    "gn:asciiname":"Echalouppe",
    "gn:country_code":"FR",
    "gn:dem":1035,
    "gn:feature_class":"P",
    "gn:feature_code":"PPL",
    "gn:name":"\u00c9chalouppe",
    "gn:population":0,
    "gn:timezone":"Europe/Paris",
    "iso:country":"FR",
    "wof:name":"Echalouppe",
    "wof:placetype":"locality"
},
  "geometry": {"coordinates":[3.05229,44.78338],"type":"Point"}
}