{
  "type": "Feature",
  "properties": {
    "gn:admin1_code":"84",
    "gn:admin2_code":"26",
    "gn:admin3_code":"262",
    "gn:admin4_code":"26279",
    "gn:asciiname":"Les Granges",
    "gn:country_code":"FR",
    "gn:dem":757,
    "gn:feature_class":"P",
    "gn:feature_code":"PPL",
    "gn:name":"Les Granges",
    "gn:population":0,
    "gn:timezone":"Europe/Paris",
    "iso:country":"FR",
    "wof:name":"Les Granges",
    "wof:placetype":"locality"
},
  "geometry": {"coordinates":[5.43113,44.25946],"type":"Point"}
}