{
  "type": "Feature",
  "properties": {
    "gn:admin1_code":"27",
    "gn:admin2_code":"89",
    "gn:admin3_code":"892",
    "gn:admin4_code":"89190",
    "gn:asciiname":"Givry",
    "gn:country_code":"FR",
    "gn:dem":147,
    "gn:feature_class":"P",
    "gn:feature_code":"PPL",
    "gn:name":"Givry",
    "gn:population":191,
    "gn:timezone":"Europe/Paris",
    "iso:country":"FR",
    "wof:name":"Givry",
    "wof:placetype":"locality",
    "wof:population":191
},
  "geometry": {"coordinates":[3.79761,47.51964],"type":"Point"}
}