{
  "type": "Feature",
  "properties": {
    "frgov:code_epci":"200039758",
    "frgov:insee_arr":"2",
    "frgov:insee_com":"89190",
    "frgov:insee_dep":"89",
    "frgov:insee_reg":"27",
    "frgov:nom_com":"Givry",
    "frgov:nom_com_m":"GIVRY",
    "frgov:nom_dep":"YONNE",
    "frgov:nom_reg":"BOURGOGNE-FRANCHE-COMTE",
    "frgov:statut":"Commune simple",
    "gn:admin1_code":"27",
    "gn:admin2_code":"89",
    "gn:admin3_code":"892",
    "gn:admin4_code":"89190",
    "gn:asciiname":"Givry",
    "gn:country_code":"FR",
    "gn:dem":147,
    "gn:feature_class":"P",
    "gn:feature_code":"PPL",
    "gn:name":"Givry",
    "gn:population":191,
    "gn:timezone":"Europe/Paris",
    "iso:country":"FR",
    "name:ceb_x_preferred":[
        "Givry"
    ],
    "name:ces_x_preferred":[
        "Givry"
    ],
    "name:deu_x_preferred":[
        "Givry"
    ],
    "name:epo_x_preferred":[
        "Givry"
    ],
    "name:fra_x_preferred":[
        "Givry"
    ],
    "name:ita_x_preferred":[
        "Givry"
    ],
    "name:kaz_x_preferred":[
        "\u0416\u0438\u0432\u0440\u0438"
    ],
    "name:ltz_x_preferred":[
        "Givry"
    ],
    "name:nds_x_preferred":[
        "Givry"
    ],
    "name:nld_x_preferred":[
        "Givry"
    ],
    "name:oci_x_preferred":[
        "Givry"
    ],
    "name:pms_x_preferred":[
        "Givry"
    ],
    "name:pol_x_preferred":[
        "Givry"
    ],
    "name:rus_x_preferred":[
        "\u0416\u0438\u0432\u0440\u0438"
    ],
    "name:slk_x_preferred":[
        "Givry"
    ],
    "name:spa_x_preferred":[
        "Givry"
    ],
    "name:srp_x_preferred":[
        "\u0416\u0438\u0432\u0440\u0438"
    ],
    "name:swe_x_preferred":[
        "Givry"
    ],
    "name:ukr_x_preferred":[
        "\u0416\u0438\u0432\u0440\u0456"
    ],
    "name:zho_x_preferred":[
        "\u5409\u592b\u91cc"
    ],
    "qs:a0":"France",
    "qs:a1":"YONNE",
    "qs:a1_lc":"89",
    "qs:a1r":"BOURGOGNE",
    "qs:a1r_lc":"26",
    "qs:a2_lc":"35",
    "qs:a2r_lc":"2",
    "qs:adm0":"France",
    "qs:adm0_a3":"FRA",
    "qs:la":"GIVRY",
    "qs:la_lc":"89190",
    "qs:level":"localadmin",
    "qs:type":"Commune simple",
    "wof:coterminous":[
        404399001
    ],
    "wof:name":"Givry",
    "wof:placetype":"locality",
    "wof:placetype_local":"Commune simple",
    "wof:population":191
},
  "geometry": {"coordinates":[3.79761,47.51964],"type":"Point"}
}