{
  "type": "Feature",
  "properties": {
    "gn:admin1_code":"27",
    "gn:admin2_code":"89",
    "gn:admin3_code":"892",
    "gn:admin4_code":"89190",
    "gn:asciiname":"Givry",
    "gn:country_code":"FR",
    "gn:dem":147,
    "gn:feature_class":"P",
    "gn:feature_code":"PPL",
    "gn:name":"Givry",
    "gn:population":191,
    "gn:timezone":"Europe/Paris",
    "iso:country":"FR",
    "name:ceb_x_preferred":[
        "Givry"
    ],
    "name:ces_x_preferred":[
        "Givry"
    ],
    "name:deu_x_preferred":[
        "Givry"
    ],
    "name:epo_x_preferred":[
        "Givry"
    ],
    "name:fra_x_preferred":[
        "Givry"
    ],
    "name:ita_x_preferred":[
        "Givry"
    ],
    "name:ltz_x_preferred":[
        "Givry"
    ],
    "name:nds_x_preferred":[
        "Givry"
    ],
    "name:nld_x_preferred":[
        "Givry"
    ],
    "name:oci_x_preferred":[
        "Givry"
    ],
    "name:pms_x_preferred":[
        "Givry"
    ],
    "name:pol_x_preferred":[
        "Givry"
    ],
    "name:rus_x_preferred":[
        "\u0416\u0438\u0432\u0440\u0438"
    ],
    "name:slk_x_preferred":[
        "Givry"
    ],
    "name:spa_x_preferred":[
        "Givry"
    ],
    "name:srp_x_preferred":[
        "\u0416\u0438\u0432\u0440\u0438"
    ],
    "name:swe_x_preferred":[
        "Givry"
    ],
    "name:ukr_x_preferred":[
        "\u0416\u0438\u0432\u0440\u0456"
    ],
    "wof:name":"Givry",
    "wof:placetype":"locality",
    "wof:population":191
},
  "geometry": {"coordinates":[3.79761,47.51964],"type":"Point"}
}