{
  "type": "Feature",
  "properties": {
    "gn:admin1_code":"84",
    "gn:admin2_code":"26",
    "gn:admin3_code":"263",
    "gn:admin4_code":"26281.0",
    "gn:asciiname":"La Goubette",
    "gn:country_code":"FR",
    "gn:dem":156,
    "gn:feature_class":"P",
    "gn:feature_code":"PPL",
    "gn:name":"La Goubette",
    "gn:population":0,
    "gn:timezone":"Europe/Paris",
    "iso:country":"FR",
    "wof:name":"La Goubette",
    "wof:placetype":"locality"
},
  "geometry": {"coordinates":[5.00288,45.04545],"type":"Point"}
}