{
  "type": "Feature",
  "properties": {
    "gn:admin1_code":"84",
    "gn:admin2_code":"38",
    "gn:admin3_code":"382",
    "gn:admin4_code":"38139",
    "gn:asciiname":"Pusignieu",
    "gn:country_code":"FR",
    "gn:dem":288,
    "gn:feature_class":"P",
    "gn:feature_code":"PPL",
    "gn:name":"Pusignieu",
    "gn:population":0,
    "gn:timezone":"Europe/Paris",
    "iso:country":"FR",
    "name:und_x_variant":[
        "Pusigneu",
        "Pusignieu"
    ],
    "wof:name":"Pusignieu",
    "wof:placetype":"locality"
},
  "geometry": {"coordinates":[5.47572,45.73854],"type":"Point"}
}