{
  "type": "Feature",
  "properties": {
    "gn:admin1_code":"84",
    "gn:admin2_code":"73",
    "gn:admin3_code":"731",
    "gn:admin4_code":"73150",
    "gn:asciiname":"Bergerie",
    "gn:country_code":"FR",
    "gn:dem":1169,
    "gn:feature_class":"P",
    "gn:feature_code":"PPL",
    "gn:name":"Bergerie",
    "gn:population":0,
    "gn:timezone":"Europe/Paris",
    "iso:country":"FR",
    "wof:name":"Bergerie",
    "wof:placetype":"locality"
},
  "geometry": {"coordinates":[6.67499,45.57398],"type":"Point"}
}