{
  "type": "Feature",
  "properties": {
    "gn:admin1_code":"24",
    "gn:admin2_code":"41",
    "gn:admin3_code":"411",
    "gn:admin4_code":"41055",
    "gn:asciiname":"Coulanges",
    "gn:country_code":"FR",
    "gn:dem":87,
    "gn:feature_class":"P",
    "gn:feature_code":"PPL",
    "gn:name":"Coulanges",
    "gn:population":327,
    "gn:timezone":"Europe/Paris",
    "iso:country":"FR",
    "wof:name":"Coulanges",
    "wof:placetype":"locality",
    "wof:population":327
},
  "geometry": {"coordinates":[1.22368,47.54284000000001],"type":"Point"}
}