{
  "type": "Feature",
  "properties": {
    "gn:admin1_code":"84",
    "gn:admin2_code":"63",
    "gn:admin3_code":"631",
    "gn:admin4_code":"63371",
    "gn:asciiname":"Le Cros",
    "gn:country_code":"FR",
    "gn:dem":941,
    "gn:feature_class":"P",
    "gn:feature_code":"PPL",
    "gn:name":"Le Cros",
    "gn:population":0,
    "gn:timezone":"Europe/Paris",
    "iso:country":"FR",
    "name:cat_x_preferred":[
        "Lo Cr\u00f2s"
    ],
    "name:ceb_x_preferred":[
        "Le Cros"
    ],
    "name:deu_x_preferred":[
        "Le Cros"
    ],
    "name:eus_x_preferred":[
        "Le Cros"
    ],
    "name:fas_x_preferred":[
        "\u0644 \u06a9\u0631\u0648"
    ],
    "name:fra_x_preferred":[
        "Le Cros"
    ],
    "name:hun_x_preferred":[
        "Le Cros"
    ],
    "name:ita_x_preferred":[
        "Le Cros"
    ],
    "name:kaz_x_preferred":[
        "\u041b\u0435-\u041a\u0440\u043e"
    ],
    "name:lat_x_preferred":[
        "Le Cros"
    ],
    "name:lmo_x_preferred":[
        "Le Cros"
    ],
    "name:mlg_x_preferred":[
        "Le Cros"
    ],
    "name:msa_x_preferred":[
        "Le Cros"
    ],
    "name:nld_x_preferred":[
        "Le Cros"
    ],
    "name:oci_x_preferred":[
        "Lo Cr\u00f2s"
    ],
    "name:pms_x_preferred":[
        "Le Cros"
    ],
    "name:pol_x_preferred":[
        "Le Cros"
    ],
    "name:por_x_preferred":[
        "Le Cros"
    ],
    "name:ron_x_preferred":[
        "Le Cros"
    ],
    "name:slk_x_preferred":[
        "Le Cros"
    ],
    "name:spa_x_preferred":[
        "Le Cros"
    ],
    "name:srp_x_preferred":[
        "\u041a\u0440\u043e"
    ],
    "name:swe_x_preferred":[
        "Le Cros"
    ],
    "name:ukr_x_preferred":[
        "\u041b\u0435-\u041a\u0440\u043e"
    ],
    "name:vie_x_preferred":[
        "Le Cros"
    ],
    "name:vol_x_preferred":[
        "Le Cros"
    ],
    "name:war_x_preferred":[
        "Le Cros"
    ],
    "name:zho_x_preferred":[
        "\u52d2\u514b\u7f57"
    ],
    "wof:name":"Le Cros",
    "wof:placetype":"locality"
},
  "geometry": {"coordinates":[3.82015,45.44365],"type":"Point"}
}