{
  "type": "Feature",
  "properties": {
    "gn:admin1_code":"75",
    "gn:admin2_code":"24",
    "gn:admin3_code":"241",
    "gn:admin4_code":"24454",
    "gn:asciiname":"Saint-Martin-de-Gurcon",
    "gn:cc2":"FR",
    "gn:country_code":"FR",
    "gn:dem":64,
    "gn:feature_class":"P",
    "gn:feature_code":"PPL",
    "gn:name":"Saint-Martin-de-Gur\u00e7on",
    "gn:population":0,
    "gn:timezone":"Europe/Paris",
    "iso:country":"FR",
    "name:und_x_variant":[
        "Saint-Martin",
        "Saint-Martin-de-Gur\u00e7on"
    ],
    "wof:name":"Saint-Martin-de-Gurcon",
    "wof:placetype":"locality"
},
  "geometry": {"coordinates":[0.11667,44.95],"type":"Point"}
}