{
  "type": "Feature",
  "properties": {
    "gn:admin1_code":"75",
    "gn:admin2_code":"23",
    "gn:admin3_code":"232",
    "gn:admin4_code":"23149",
    "gn:asciiname":"Marsat",
    "gn:country_code":"FR",
    "gn:dem":464,
    "gn:feature_class":"P",
    "gn:feature_code":"PPL",
    "gn:name":"Marsat",
    "gn:population":0,
    "gn:timezone":"Europe/Paris",
    "iso:country":"FR",
    "name:ceb_x_preferred":[
        "Marsat"
    ],
    "name:deu_x_preferred":[
        "Marsat"
    ],
    "name:eus_x_preferred":[
        "Marsat"
    ],
    "name:fra_x_preferred":[
        "Marsat"
    ],
    "name:hun_x_preferred":[
        "Marsat"
    ],
    "name:ita_x_preferred":[
        "Marsat"
    ],
    "name:lat_x_preferred":[
        "Marsat"
    ],
    "name:msa_x_preferred":[
        "Marsat"
    ],
    "name:nld_x_preferred":[
        "Marsat"
    ],
    "name:oci_x_preferred":[
        "Marsat"
    ],
    "name:pms_x_preferred":[
        "Marsat"
    ],
    "name:pol_x_preferred":[
        "Marsat"
    ],
    "name:por_x_preferred":[
        "Marsat"
    ],
    "name:ron_x_preferred":[
        "Marsat"
    ],
    "name:slk_x_preferred":[
        "Marsat"
    ],
    "name:spa_x_preferred":[
        "Marsat"
    ],
    "name:swe_x_preferred":[
        "Marsat"
    ],
    "name:ukr_x_preferred":[
        "\u041c\u0430\u0440\u0441\u0430"
    ],
    "name:uzb_x_preferred":[
        "Marsat"
    ],
    "name:vie_x_preferred":[
        "Marsat"
    ],
    "name:vol_x_preferred":[
        "Marsat"
    ],
    "name:war_x_preferred":[
        "Marsat"
    ],
    "name:zho_x_preferred":[
        "\u9a6c\u5c14\u8428"
    ],
    "wof:name":"Marsat",
    "wof:placetype":"locality"
},
  "geometry": {"coordinates":[2.11581,46.18622],"type":"Point"}
}