{
  "type": "Feature",
  "properties": {
    "gn:admin1_code":"84",
    "gn:admin2_code":"42",
    "gn:admin3_code":"423",
    "gn:admin4_code":"42168",
    "gn:asciiname":"Le Priel",
    "gn:country_code":"FR",
    "gn:dem":722,
    "gn:feature_class":"P",
    "gn:feature_code":"PPL",
    "gn:name":"Le Priel",
    "gn:population":0,
    "gn:timezone":"Europe/Paris",
    "iso:country":"FR",
    "wof:name":"Le Priel",
    "wof:placetype":"locality"
},
  "geometry": {"coordinates":[4.63279,45.42368],"type":"Point"}
}