{
  "type": "Feature",
  "properties": {
    "gn:admin1_code":"75",
    "gn:admin2_code":"24",
    "gn:admin3_code":"243",
    "gn:admin4_code":"24401",
    "gn:asciiname":"Exorbepey",
    "gn:country_code":"FR",
    "gn:dem":160,
    "gn:feature_class":"P",
    "gn:feature_code":"PPL",
    "gn:name":"Exorbepey",
    "gn:population":0,
    "gn:timezone":"Europe/Paris",
    "iso:country":"FR",
    "wof:name":"Exorbepey",
    "wof:placetype":"locality"
},
  "geometry": {"coordinates":[1.02808,45.26894],"type":"Point"}
}