{
  "type": "Feature",
  "properties": {
    "gn:admin1_code":"24",
    "gn:admin2_code":"18",
    "gn:admin3_code":"182",
    "gn:admin4_code":"18038",
    "gn:asciiname":"Allichamps",
    "gn:country_code":"FR",
    "gn:dem":158,
    "gn:feature_class":"P",
    "gn:feature_code":"PPL",
    "gn:name":"Allichamps",
    "gn:population":0,
    "gn:timezone":"Europe/Paris",
    "iso:country":"FR",
    "name:bug_x_preferred":[
        "Allichamps"
    ],
    "name:cat_x_preferred":[
        "Allichamps"
    ],
    "name:ceb_x_preferred":[
        "Allichamps"
    ],
    "name:eus_x_preferred":[
        "Allichamps"
    ],
    "name:fas_x_preferred":[
        "\u0627\u0644\u06cc\u0686\u0627\u0645\u067e\u0633"
    ],
    "name:fra_x_preferred":[
        "Allichamps"
    ],
    "name:hun_x_preferred":[
        "Allichamps"
    ],
    "name:ita_x_preferred":[
        "Allichamps"
    ],
    "name:lat_x_preferred":[
        "Allichamps"
    ],
    "name:mlg_x_preferred":[
        "Allichamps"
    ],
    "name:msa_x_preferred":[
        "Allichamps"
    ],
    "name:nld_x_preferred":[
        "Allichamps"
    ],
    "name:oci_x_preferred":[
        "Allichamps"
    ],
    "name:pms_x_preferred":[
        "Allichamps"
    ],
    "name:pol_x_preferred":[
        "Allichamps"
    ],
    "name:por_x_preferred":[
        "Allichamps"
    ],
    "name:ron_x_preferred":[
        "Allichamps"
    ],
    "name:slk_x_preferred":[
        "Allichamps"
    ],
    "name:spa_x_preferred":[
        "Allichamps"
    ],
    "name:srp_x_preferred":[
        "\u0410\u043b\u0438\u0448\u0430\u043d"
    ],
    "name:swe_x_preferred":[
        "Allichamps"
    ],
    "name:ukr_x_preferred":[
        "\u0410\u043b\u043b\u0456\u0448\u0430\u043c"
    ],
    "name:vie_x_preferred":[
        "Allichamps"
    ],
    "name:vol_x_preferred":[
        "Allichamps"
    ],
    "name:war_x_preferred":[
        "Allichamps"
    ],
    "name:zho_x_preferred":[
        "\u963f\u5229\u5c1a\u666e"
    ],
    "wof:name":"Allichamps",
    "wof:placetype":"locality"
},
  "geometry": {"coordinates":[2.43333,46.78333],"type":"Point"}
}