{
  "type": "Feature",
  "properties": {
    "gn:admin1_code":"27",
    "gn:admin2_code":"89",
    "gn:admin3_code":"891",
    "gn:admin4_code":"89295",
    "gn:asciiname":"Breandes",
    "gn:country_code":"FR",
    "gn:dem":134,
    "gn:feature_class":"P",
    "gn:feature_code":"PPL",
    "gn:name":"Br\u00e9andes",
    "gn:population":0,
    "gn:timezone":"Europe/Paris",
    "iso:country":"FR",
    "name:und_x_variant":[
        "Les Br\u00e9andes",
        "Br\u00e9andes"
    ],
    "wof:name":"Breandes",
    "wof:placetype":"locality"
},
  "geometry": {"coordinates":[3.54511,47.82679],"type":"Point"}
}