{
  "type": "Feature",
  "properties": {
    "frgov:code_epci":"200066371",
    "frgov:insee_arr":"3",
    "frgov:insee_com":"46074",
    "frgov:insee_dep":"46",
    "frgov:insee_reg":"76",
    "frgov:nom_com":"Condat",
    "frgov:nom_com_m":"CONDAT",
    "frgov:nom_dep":"LOT",
    "frgov:nom_reg":"OCCITANIE",
    "frgov:statut":"Commune simple",
    "gn:admin1_code":"76",
    "gn:admin2_code":"46",
    "gn:admin3_code":"463",
    "gn:admin4_code":"46074",
    "gn:asciiname":"Condat",
    "gn:country_code":"FR",
    "gn:dem":129,
    "gn:feature_class":"P",
    "gn:feature_code":"PPL",
    "gn:name":"Condat",
    "gn:population":0,
    "gn:timezone":"Europe/Paris",
    "iso:country":"FR",
    "name:bel_x_preferred":[
        "\u041a\u043e\u043d\u0434\u0430"
    ],
    "name:ceb_x_preferred":[
        "Condat"
    ],
    "name:deu_x_preferred":[
        "Condat"
    ],
    "name:fra_x_preferred":[
        "Condat"
    ],
    "name:ita_x_preferred":[
        "Condat"
    ],
    "name:nds_x_preferred":[
        "Condat"
    ],
    "name:nld_x_preferred":[
        "Condat"
    ],
    "name:oci_x_preferred":[
        "Condat"
    ],
    "name:pms_x_preferred":[
        "Condat"
    ],
    "name:pol_x_preferred":[
        "Condat"
    ],
    "name:por_x_preferred":[
        "Condat"
    ],
    "name:rus_x_preferred":[
        "\u041a\u043e\u043d\u0434\u0430"
    ],
    "name:scn_x_preferred":[
        "Condat"
    ],
    "name:slk_x_preferred":[
        "Condat"
    ],
    "name:spa_x_preferred":[
        "Condat"
    ],
    "name:srp_x_preferred":[
        "\u041a\u043e\u043d\u0434\u0430"
    ],
    "name:swe_x_preferred":[
        "Condat"
    ],
    "name:ukr_x_preferred":[
        "\u041a\u043e\u043d\u0434\u0430"
    ],
    "qs:a0":"France",
    "qs:a1":"LOT",
    "qs:a1_lc":"46",
    "qs:a1r":"MIDI-PYRENEES",
    "qs:a1r_lc":"73",
    "qs:a2_lc":"29",
    "qs:a2r_lc":"3",
    "qs:adm0":"France",
    "qs:adm0_a3":"FRA",
    "qs:la":"CONDAT",
    "qs:la_lc":"46074",
    "qs:level":"localadmin",
    "qs:type":"Commune simple",
    "wof:coterminous":[
        404356701
    ],
    "wof:name":"Condat",
    "wof:placetype":"locality",
    "wof:placetype_local":"Commune simple"
},
  "geometry": {"coordinates":[1.66373,44.99032],"type":"Point"}
}