{
  "type": "Feature",
  "properties": {
    "gn:admin1_code":"76",
    "gn:admin2_code":"46",
    "gn:admin3_code":"463",
    "gn:admin4_code":"46074",
    "gn:asciiname":"Condat",
    "gn:country_code":"FR",
    "gn:dem":129,
    "gn:feature_class":"P",
    "gn:feature_code":"PPL",
    "gn:name":"Condat",
    "gn:population":0,
    "gn:timezone":"Europe/Paris",
    "iso:country":"FR",
    "name:bel_x_preferred":[
        "\u041a\u043e\u043d\u0434\u0430"
    ],
    "name:ceb_x_preferred":[
        "Condat"
    ],
    "name:deu_x_preferred":[
        "Condat"
    ],
    "name:fra_x_preferred":[
        "Condat"
    ],
    "name:ita_x_preferred":[
        "Condat"
    ],
    "name:nds_x_preferred":[
        "Condat"
    ],
    "name:nld_x_preferred":[
        "Condat"
    ],
    "name:oci_x_preferred":[
        "Condat"
    ],
    "name:pms_x_preferred":[
        "Condat"
    ],
    "name:pol_x_preferred":[
        "Condat"
    ],
    "name:por_x_preferred":[
        "Condat"
    ],
    "name:rus_x_preferred":[
        "\u041a\u043e\u043d\u0434\u0430"
    ],
    "name:scn_x_preferred":[
        "Condat"
    ],
    "name:slk_x_preferred":[
        "Condat"
    ],
    "name:spa_x_preferred":[
        "Condat"
    ],
    "name:srp_x_preferred":[
        "\u041a\u043e\u043d\u0434\u0430"
    ],
    "name:swe_x_preferred":[
        "Condat"
    ],
    "name:ukr_x_preferred":[
        "\u041a\u043e\u043d\u0434\u0430"
    ],
    "wof:name":"Condat",
    "wof:placetype":"locality"
},
  "geometry": {"coordinates":[1.66373,44.99032],"type":"Point"}
}