{
  "type": "Feature",
  "properties": {
    "gn:admin1_code":"76",
    "gn:admin2_code":"46",
    "gn:admin3_code":"463",
    "gn:admin4_code":"46074",
    "gn:asciiname":"Condat",
    "gn:country_code":"FR",
    "gn:dem":129,
    "gn:feature_class":"P",
    "gn:feature_code":"PPL",
    "gn:name":"Condat",
    "gn:population":0,
    "gn:timezone":"Europe/Paris",
    "iso:country":"FR",
    "wof:name":"Condat",
    "wof:placetype":"locality"
},
  "geometry": {"coordinates":[1.66373,44.99032],"type":"Point"}
}