{
  "type": "Feature",
  "properties": {
    "gn:admin1_code":"84",
    "gn:admin2_code":"38",
    "gn:admin3_code":"381",
    "gn:admin4_code":"38446",
    "gn:asciiname":"Preversin",
    "gn:country_code":"FR",
    "gn:dem":712,
    "gn:feature_class":"P",
    "gn:feature_code":"PPL",
    "gn:name":"Pr\u00e9versin",
    "gn:population":0,
    "gn:timezone":"Europe/Paris",
    "iso:country":"FR",
    "wof:name":"Preversin",
    "wof:placetype":"locality"
},
  "geometry": {"coordinates":[5.85048,45.40839],"type":"Point"}
}