{
  "type": "Feature",
  "properties": {
    "gn:admin1_code":"76",
    "gn:admin2_code":"65",
    "gn:admin3_code":"653",
    "gn:admin4_code":"65462",
    "gn:asciiname":"Lissarre",
    "gn:country_code":"FR",
    "gn:dem":192,
    "gn:feature_class":"P",
    "gn:feature_code":"PPL",
    "gn:name":"Lissarre",
    "gn:population":0,
    "gn:timezone":"Europe/Paris",
    "iso:country":"FR",
    "wof:name":"Lissarre",
    "wof:placetype":"locality"
},
  "geometry": {"coordinates":[-0.03333,43.45],"type":"Point"}
}