{
  "type": "Feature",
  "properties": {
    "gn:admin1_code":"76",
    "gn:admin2_code":"12",
    "gn:admin3_code":"121",
    "gn:admin4_code":"12225",
    "gn:asciiname":"Craissac",
    "gn:country_code":"FR",
    "gn:dem":493,
    "gn:feature_class":"P",
    "gn:feature_code":"PPL",
    "gn:name":"Craissac",
    "gn:population":0,
    "gn:timezone":"Europe/Paris",
    "iso:country":"FR",
    "wof:name":"Craissac",
    "wof:placetype":"locality"
},
  "geometry": {"coordinates":[2.96106,44.07024000000001],"type":"Point"}
}