{
  "type": "Feature",
  "properties": {
    "gn:admin1_code":"93",
    "gn:admin2_code":"04",
    "gn:admin3_code":"043",
    "gn:admin4_code":"04036",
    "gn:asciiname":"Le Mousteiret",
    "gn:country_code":"FR",
    "gn:dem":736,
    "gn:feature_class":"P",
    "gn:feature_code":"PPL",
    "gn:name":"Le Mousteiret",
    "gn:population":0,
    "gn:timezone":"Europe/Paris",
    "iso:country":"FR",
    "name:und_x_variant":[
        "Mousteiret",
        "Le Mousteiret"
    ],
    "wof:name":"Le Mousteiret",
    "wof:placetype":"locality"
},
  "geometry": {"coordinates":[6.29305,44.15726],"type":"Point"}
}