{
  "type": "Feature",
  "properties": {
    "gn:gn_country":"FR",
    "gn:gn_fcode":"PPL",
    "gn:gn_pop":416,
    "gn:population":416,
    "iso:country":"FR",
    "name:unk_x_variant":[
        "Auvergne"
    ],
    "qs_pg:aaroncc":"FR",
    "qs_pg:gn_country":"FR",
    "qs_pg:gn_fcode":"PPL",
    "qs_pg:gn_pop":416,
    "qs_pg:name":"Auvergny",
    "qs_pg:name_adm0":"France",
    "qs_pg:name_adm1":"Haute-Normandie",
    "qs_pg:photos_9r":0,
    "qs_pg:photos_sr":0,
    "qs_pg:pop_sr":2,
    "qs_pg:qs_pg_placetype":"locality",
    "qs_pg:qs_pg_placetype_gp":"Town",
    "qs_pg:woe_adm0":23424819,
    "woe:adm0_id":23424819,
    "woe:name_adm0":"France",
    "woe:name_adm1":"Haute-Normandie",
    "woe:placetype":"Town",
    "wof:name":"Auvergny",
    "wof:placetype":"neighbourhood",
    "wof:population":416
},
  "geometry": {"coordinates":[0.72903,48.88228],"type":"Point"}
}