{
  "type": "Feature",
  "properties": {
    "gn:admin1_code":"28",
    "gn:admin2_code":"61",
    "gn:admin3_code":"613",
    "gn:admin4_code":"61309",
    "gn:asciiname":"Biaville",
    "gn:country_code":"FR",
    "gn:dem":166,
    "gn:feature_class":"P",
    "gn:feature_code":"PPL",
    "gn:name":"Biaville",
    "gn:population":0,
    "gn:timezone":"Europe/Paris",
    "iso:country":"FR",
    "wof:name":"Biaville",
    "wof:placetype":"locality"
},
  "geometry": {"coordinates":[0.74816,48.37472],"type":"Point"}
}