{
  "type": "Feature",
  "properties": {
    "gn:admin1_code":"84",
    "gn:admin2_code":"15",
    "gn:admin3_code":"153",
    "gn:admin4_code":"15141",
    "gn:asciiname":"Chavagnac",
    "gn:country_code":"FR",
    "gn:dem":1100,
    "gn:feature_class":"P",
    "gn:feature_code":"PPL",
    "gn:name":"Chavagnac",
    "gn:population":0,
    "gn:timezone":"Europe/Paris",
    "iso:country":"FR",
    "wof:name":"Chavagnac",
    "wof:placetype":"locality"
},
  "geometry": {"coordinates":[2.88191,45.15322000000001],"type":"Point"}
}