{
  "type": "Feature",
  "properties": {
    "gn:admin1_code":"84",
    "gn:admin2_code":"15",
    "gn:admin3_code":"153",
    "gn:admin4_code":"15141",
    "gn:asciiname":"Chavagnac",
    "gn:country_code":"FR",
    "gn:dem":1100,
    "gn:feature_class":"P",
    "gn:feature_code":"PPL",
    "gn:name":"Chavagnac",
    "gn:population":0,
    "gn:timezone":"Europe/Paris",
    "iso:country":"FR",
    "name:ceb_x_preferred":[
        "Chavagnac"
    ],
    "name:deu_x_preferred":[
        "Chavagnac"
    ],
    "name:fra_x_preferred":[
        "Chavagnac"
    ],
    "name:ita_x_preferred":[
        "Chavagnac"
    ],
    "name:nds_x_preferred":[
        "Chavagnac"
    ],
    "name:nld_x_preferred":[
        "Chavagnac"
    ],
    "name:pms_x_preferred":[
        "Chavagnac"
    ],
    "name:pol_x_preferred":[
        "Chavagnac"
    ],
    "name:por_x_preferred":[
        "Chavagnac"
    ],
    "name:rus_x_preferred":[
        "\u0428\u0430\u0432\u0430\u043d\u044c\u044f\u043a"
    ],
    "name:slk_x_preferred":[
        "Chavagnac"
    ],
    "name:spa_x_preferred":[
        "Chavagnac"
    ],
    "name:srp_x_preferred":[
        "\u0428\u0430\u0432\u0430\u045a\u0430\u043a"
    ],
    "name:swe_x_preferred":[
        "Chavagnac"
    ],
    "name:ukr_x_preferred":[
        "\u0428\u0430\u0432\u0430\u043d\u044c\u044f\u043a"
    ],
    "wof:name":"Chavagnac",
    "wof:placetype":"locality"
},
  "geometry": {"coordinates":[2.88191,45.15322000000001],"type":"Point"}
}