{
  "type": "Feature",
  "properties": {
    "gn:admin1_code":"84",
    "gn:admin2_code":"26",
    "gn:admin3_code":"262",
    "gn:admin4_code":"26161",
    "gn:asciiname":"Lemps",
    "gn:country_code":"FR",
    "gn:dem":805,
    "gn:feature_class":"P",
    "gn:feature_code":"PPL",
    "gn:name":"Lemps",
    "gn:population":0,
    "gn:timezone":"Europe/Paris",
    "iso:country":"FR",
    "name:ceb_x_preferred":[
        "Lemps"
    ],
    "name:deu_x_preferred":[
        "Lemps"
    ],
    "name:fra_x_preferred":[
        "Lemps"
    ],
    "name:ita_x_preferred":[
        "Lemps"
    ],
    "name:nds_x_preferred":[
        "Lemps"
    ],
    "name:nld_x_preferred":[
        "Lemps"
    ],
    "name:pol_x_preferred":[
        "Lemps"
    ],
    "name:por_x_preferred":[
        "Lemps"
    ],
    "name:scn_x_preferred":[
        "Lemps"
    ],
    "name:slk_x_preferred":[
        "Lemps"
    ],
    "name:spa_x_preferred":[
        "Lemps"
    ],
    "name:sqi_x_preferred":[
        "Lemps"
    ],
    "name:swe_x_preferred":[
        "Lemps"
    ],
    "name:ukr_x_preferred":[
        "\u041b\u0430\u043c"
    ],
    "wof:name":"Lemps",
    "wof:placetype":"locality"
},
  "geometry": {"coordinates":[5.41861,44.3515],"type":"Point"}
}