{
  "type": "Feature",
  "properties": {
    "frgov:code_epci":"200068229",
    "frgov:insee_arr":"2",
    "frgov:insee_com":"26161",
    "frgov:insee_dep":"26",
    "frgov:insee_reg":"84",
    "frgov:nom_com":"Lemps",
    "frgov:nom_com_m":"LEMPS",
    "frgov:nom_dep":"DROME",
    "frgov:nom_reg":"AUVERGNE-RHONE-ALPES",
    "frgov:statut":"Commune simple",
    "gn:admin1_code":"84",
    "gn:admin2_code":"26",
    "gn:admin3_code":"262",
    "gn:admin4_code":"26161",
    "gn:asciiname":"Lemps",
    "gn:country_code":"FR",
    "gn:dem":805,
    "gn:feature_class":"P",
    "gn:feature_code":"PPL",
    "gn:name":"Lemps",
    "gn:population":0,
    "gn:timezone":"Europe/Paris",
    "iso:country":"FR",
    "name:ceb_x_preferred":[
        "Lemps"
    ],
    "name:deu_x_preferred":[
        "Lemps"
    ],
    "name:fra_x_preferred":[
        "Lemps"
    ],
    "name:ita_x_preferred":[
        "Lemps"
    ],
    "name:nds_x_preferred":[
        "Lemps"
    ],
    "name:nld_x_preferred":[
        "Lemps"
    ],
    "name:pol_x_preferred":[
        "Lemps"
    ],
    "name:por_x_preferred":[
        "Lemps"
    ],
    "name:scn_x_preferred":[
        "Lemps"
    ],
    "name:slk_x_preferred":[
        "Lemps"
    ],
    "name:spa_x_preferred":[
        "Lemps"
    ],
    "name:sqi_x_preferred":[
        "Lemps"
    ],
    "name:swe_x_preferred":[
        "Lemps"
    ],
    "name:ukr_x_preferred":[
        "\u041b\u0430\u043c"
    ],
    "qs:a0":"France",
    "qs:a1":"DROME",
    "qs:a1_lc":"26",
    "qs:a1r":"RHONE-ALPES",
    "qs:a1r_lc":"82",
    "qs:a2_lc":"20",
    "qs:a2r_lc":"2",
    "qs:adm0":"France",
    "qs:adm0_a3":"FRA",
    "qs:la":"LEMPS",
    "qs:la_lc":"26161",
    "qs:level":"localadmin",
    "qs:type":"Commune simple",
    "wof:coterminous":[
        404407831
    ],
    "wof:name":"Lemps",
    "wof:placetype":"locality",
    "wof:placetype_local":"Commune simple"
},
  "geometry": {"coordinates":[5.41861,44.3515],"type":"Point"}
}