{
  "type": "Feature",
  "properties": {
    "gn:admin1_code":"84",
    "gn:admin2_code":"38",
    "gn:admin3_code":"381",
    "gn:admin4_code":"38111",
    "gn:asciiname":"Malhivert",
    "gn:country_code":"FR",
    "gn:dem":452,
    "gn:feature_class":"P",
    "gn:feature_code":"PPL",
    "gn:name":"Malhivert",
    "gn:population":0,
    "gn:timezone":"Europe/Paris",
    "iso:country":"FR",
    "name:und_x_variant":[
        "Malivert",
        "Malhivert"
    ],
    "wof:name":"Malhivert",
    "wof:placetype":"locality"
},
  "geometry": {"coordinates":[5.66604,45.13207],"type":"Point"}
}