{
  "type": "Feature",
  "properties": {
    "iso:country":"FR",
    "name:deu_x_preferred":[
        "Flugplatz Coulommiers-Voisins"
    ],
    "name:fas_x_preferred":[
        "\u0641\u0631\u0648\u062f\u06af\u0627\u0647 \u06a9\u0648\u0644\u0648\u0645\u06cc\u0647-\u0648\u0648\u0622\u0632\u0646"
    ],
    "name:fra_x_preferred":[
        "A\u00e9rodrome de Coulommiers - Voisins"
    ],
    "name:tgk_x_preferred":[
        "\u0424\u0443\u0440\u0443\u0434\u0433\u043e\u04b3\u0438 \u043a\u0443\u043b\u0443\u043c\u0438\u0440-\u0432\u0443\u043e\u0437\u043d"
    ],
    "oa:elevation_ft":"470",
    "oa:type":"small_airport",
    "woe:hierarchy":{
        "country_id":23424819,
        "county_id":12597137,
        "localadmin_id":12649740,
        "planet_id":1,
        "state_id":7153319
    },
    "wof:name":"Voisins Airport",
    "wof:placetype":"campus"
},
  "geometry": {"coordinates":[3.01444444,48.8375],"type":"Point"}
}