{
  "type": "Feature",
  "properties": {
    "iso:country":"FR",
    "name:ceb_x_preferred":[
        "Coulommiers-Voisins Airport"
    ],
    "name:deu_x_preferred":[
        "Flugplatz Coulommiers-Voisins"
    ],
    "name:eng_x_preferred":[
        "Coulommiers \u2013 Voisins Aerodrome"
    ],
    "name:eng_x_variant":[
        "LFPK"
    ],
    "name:fas_x_preferred":[
        "\u0641\u0631\u0648\u062f\u06af\u0627\u0647 \u06a9\u0648\u0644\u0648\u0645\u06cc\u0647-\u0648\u0648\u0622\u0632\u0646"
    ],
    "name:fas_x_variant":[
        "\u0641\u0631\u0648\u062f\u06af\u0627\u0647 \u06a9\u0648\u0644\u0648\u0645\u06cc\u0631-\u0648\u0648\u0627\u0632\u0646"
    ],
    "name:fra_x_preferred":[
        "A\u00e9rodrome de Coulommiers - Voisins"
    ],
    "name:msa_x_preferred":[
        "Lapangan Terbang Voisins"
    ],
    "name:tgk_x_preferred":[
        "\u0424\u0443\u0440\u0443\u0434\u0433\u043e\u04b3\u0438 \u043a\u0443\u043b\u0443\u043c\u0438\u0440-\u0432\u0443\u043e\u0437\u043d"
    ],
    "name:urd_x_preferred":[
        "\u06a9\u0648\u0644\u0648\u0645\u06cc\u0631\u0633-\u0648\u0648\u0626\u0632\u0627\u06ba \u0627\u06cc\u0631\u0648\u0688\u0631\u0648\u0645"
    ],
    "oa:elevation_ft":"470",
    "oa:type":"small_airport",
    "woe:hierarchy":{
        "country_id":23424819,
        "county_id":12597137,
        "localadmin_id":12649740,
        "planet_id":1,
        "state_id":7153319
    },
    "wof:name":"Voisins Airport",
    "wof:placetype":"campus"
},
  "geometry": {"coordinates":[3.014444,48.8375],"type":"Point"}
}