{
  "type": "Feature",
  "properties": {
    "gn:admin1_code":"27",
    "gn:admin2_code":"89",
    "gn:admin3_code":"891",
    "gn:admin4_code":"89419",
    "gn:asciiname":"Les Fours",
    "gn:country_code":"FR",
    "gn:dem":240,
    "gn:feature_class":"P",
    "gn:feature_code":"PPL",
    "gn:name":"Les Fours",
    "gn:population":0,
    "gn:timezone":"Europe/Paris",
    "iso:country":"FR",
    "name:und_x_variant":[
        "Fours",
        "Les Fours"
    ],
    "wof:name":"Les Fours",
    "wof:placetype":"locality"
},
  "geometry": {"coordinates":[3.25804,47.73438],"type":"Point"}
}