{
  "type": "Feature",
  "properties": {
    "gn:admin1_code":"75",
    "gn:admin2_code":"24",
    "gn:admin3_code":"244",
    "gn:admin4_code":"24341",
    "gn:asciiname":"Saint-Quentin",
    "gn:country_code":"FR",
    "gn:dem":238,
    "gn:feature_class":"P",
    "gn:feature_code":"PPL",
    "gn:name":"Saint-Quentin",
    "gn:population":0,
    "gn:timezone":"Europe/Paris",
    "iso:country":"FR",
    "name:bre_x_preferred":[
        "Saint-Quentin"
    ],
    "name:cat_x_preferred":[
        "Saint-Quentin"
    ],
    "name:ceb_x_preferred":[
        "Saint-Quentin"
    ],
    "name:deu_x_preferred":[
        "Saint-Quentin"
    ],
    "name:epo_x_preferred":[
        "Saint-Quentin"
    ],
    "name:fra_x_preferred":[
        "Saint-Quentin"
    ],
    "name:jpn_x_preferred":[
        "\u30b5\u30f3\uff1d\u30ab\u30f3\u30bf\u30f3"
    ],
    "name:kor_x_preferred":[
        "\uc0dd\uce89\ud0f1"
    ],
    "name:nld_x_preferred":[
        "Saint-Quentin"
    ],
    "name:sco_x_preferred":[
        "Saint-Quentin"
    ],
    "name:swe_x_preferred":[
        "Saint-Quentin"
    ],
    "name:zho_x_preferred":[
        "\u5723\u5eb7\u5766"
    ],
    "wof:name":"Saint-Quentin",
    "wof:placetype":"locality"
},
  "geometry": {"coordinates":[1.23333,44.95],"type":"Point"}
}