{
  "type": "Feature",
  "properties": {
    "gn:admin1_code":"84",
    "gn:admin2_code":"03",
    "gn:admin3_code":"031",
    "gn:admin4_code":"03189",
    "gn:asciiname":"La Ville",
    "gn:country_code":"FR",
    "gn:dem":365,
    "gn:feature_class":"P",
    "gn:feature_code":"PPL",
    "gn:name":"La Ville",
    "gn:population":0,
    "gn:timezone":"Europe/Paris",
    "iso:country":"FR",
    "wof:name":"La Ville",
    "wof:placetype":"locality"
},
  "geometry": {"coordinates":[2.84531,46.30955],"type":"Point"}
}