{
  "type": "Feature",
  "properties": {
    "gn:admin1_code":"75",
    "gn:admin2_code":"16",
    "gn:admin3_code":"161",
    "gn:admin4_code":"16290",
    "gn:asciiname":"La Seguinie",
    "gn:country_code":"FR",
    "gn:dem":268,
    "gn:feature_class":"P",
    "gn:feature_code":"PPL",
    "gn:name":"La S\u00e9guinie",
    "gn:population":0,
    "gn:timezone":"Europe/Paris",
    "iso:country":"FR",
    "wof:name":"La Seguinie",
    "wof:placetype":"locality"
},
  "geometry": {"coordinates":[0.56485,45.72297],"type":"Point"}
}