{
  "type": "Feature",
  "properties": {
    "gn:admin1_code":"11",
    "gn:admin2_code":"95",
    "gn:admin3_code":"953",
    "gn:admin4_code":"95676",
    "gn:asciiname":"La Goulee",
    "gn:country_code":"FR",
    "gn:dem":119,
    "gn:feature_class":"P",
    "gn:feature_code":"PPL",
    "gn:name":"La Goul\u00e9e",
    "gn:population":0,
    "gn:timezone":"Europe/Paris",
    "iso:country":"FR",
    "wof:name":"La Goulee",
    "wof:placetype":"locality"
},
  "geometry": {"coordinates":[1.70623,49.07962],"type":"Point"}
}