{
  "type": "Feature",
  "properties": {
    "gn:admin1_code":"84",
    "gn:admin2_code":"03",
    "gn:admin3_code":"032",
    "gn:admin4_code":"03190",
    "gn:asciiname":"Les Bataillots",
    "gn:country_code":"FR",
    "gn:dem":215,
    "gn:feature_class":"P",
    "gn:feature_code":"PPL",
    "gn:name":"Les Bataillots",
    "gn:population":0,
    "gn:timezone":"Europe/Paris",
    "iso:country":"FR",
    "wof:name":"Les Bataillots",
    "wof:placetype":"locality"
},
  "geometry": {"coordinates":[3.33333,46.55],"type":"Point"}
}