{
  "type": "Feature",
  "properties": {
    "gn:admin1_code":"44",
    "gn:admin2_code":"08",
    "gn:admin3_code":"081",
    "gn:admin4_code":"08367",
    "gn:asciiname":"Hiraumont",
    "gn:country_code":"FR",
    "gn:dem":377,
    "gn:feature_class":"P",
    "gn:feature_code":"PPL",
    "gn:name":"Hiraumont",
    "gn:population":0,
    "gn:timezone":"Europe/Paris",
    "iso:country":"FR",
    "wof:name":"Hiraumont",
    "wof:placetype":"locality"
},
  "geometry": {"coordinates":[4.54336,49.93028],"type":"Point"}
}