{
  "type": "Feature",
  "properties": {
    "gn:gn_country":"FR",
    "gn:gn_fcode":"PPL",
    "gn:gn_pop":0,
    "iso:country":"FR",
    "name:ces_x_preferred":[
        "Golfe-Juan"
    ],
    "name:eng_x_preferred":[
        "Golfe-Juan"
    ],
    "name:fin_x_preferred":[
        "Golfe-Juan"
    ],
    "name:fra_x_preferred":[
        "Golfe-Juan"
    ],
    "name:jpn_x_preferred":[
        "\u30b4\u30eb\u30d5\uff1d\u30b8\u30e5\u30a2\u30f3"
    ],
    "name:nld_x_preferred":[
        "Golfe-Juan"
    ],
    "name:rus_x_preferred":[
        "\u0413\u043e\u043b\u044c\u0444-\u0416\u0443\u0430\u043d"
    ],
    "name:spa_x_preferred":[
        "Golfe-Juan"
    ],
    "name:swe_x_preferred":[
        "Golfe-Juan"
    ],
    "name:unk_x_variant":[
        "Golf-Juan"
    ],
    "qs_pg:aaroncc":"FR",
    "qs_pg:gn_country":"FR",
    "qs_pg:gn_fcode":"PPL",
    "qs_pg:gn_pop":0,
    "qs_pg:name":"Golfe Juan",
    "qs_pg:name_adm0":"France",
    "qs_pg:name_adm1":"Provence-Alpes-C\u00f4te d'Azur",
    "qs_pg:photos":288,
    "qs_pg:photos_1k":58,
    "qs_pg:photos_9k":1,
    "qs_pg:photos_9r":4,
    "qs_pg:photos_all":288,
    "qs_pg:photos_sr":5,
    "qs_pg:pop_sr":0,
    "qs_pg:qs_pg_placetype":"locality",
    "qs_pg:qs_pg_placetype_gp":"Town",
    "qs_pg:woe_adm0":23424819,
    "woe:adm0_id":23424819,
    "woe:name_adm0":"France",
    "woe:name_adm1":"Provence-Alpes-C\u00f4te d'Azur",
    "woe:placetype":"Town",
    "wof:name":"Golfe Juan",
    "wof:placetype":"neighbourhood"
},
  "geometry": {"coordinates":[7.07744,43.56812],"type":"Point"}
}