{
  "type": "Feature",
  "properties": {
    "gn:admin1_code":"28",
    "gn:admin2_code":"76",
    "gn:admin3_code":"761",
    "gn:admin4_code":"76070",
    "gn:asciiname":"Saint-Martin",
    "gn:country_code":"FR",
    "gn:dem":76,
    "gn:feature_class":"P",
    "gn:feature_code":"PPL",
    "gn:name":"Saint-Martin",
    "gn:population":0,
    "gn:timezone":"Europe/Paris",
    "iso:country":"FR",
    "name:ben_x_preferred":[
        "\u09b8\u09c7\u09a8\u09cd\u099f-\u09ae\u09be\u09b0\u09cd\u099f\u09bf\u09a8"
    ],
    "wof:name":"Saint-Martin",
    "wof:placetype":"locality"
},
  "geometry": {"coordinates":[1.21524,49.71488],"type":"Point"}
}