{
  "type": "Feature",
  "properties": {
    "gn:admin1_code":"28",
    "gn:admin2_code":"76",
    "gn:admin3_code":"763",
    "gn:admin4_code":"76378",
    "gn:asciiname":"Le Passage",
    "gn:country_code":"FR",
    "gn:dem":3,
    "gn:feature_class":"P",
    "gn:feature_code":"PPLL",
    "gn:name":"Le Passage",
    "gn:population":0,
    "gn:timezone":"Europe/Paris",
    "iso:country":"FR",
    "name:ceb_x_preferred":[
        "Le Passage"
    ],
    "name:fra_x_preferred":[
        "Le Passage"
    ],
    "name:ita_x_preferred":[
        "Le Passage"
    ],
    "name:nds_x_preferred":[
        "Le Passage"
    ],
    "name:nld_x_preferred":[
        "Le Passage"
    ],
    "name:pms_x_preferred":[
        "Le Passage"
    ],
    "name:pol_x_preferred":[
        "Le Passage"
    ],
    "name:por_x_preferred":[
        "Le Passage"
    ],
    "name:slk_x_preferred":[
        "Le Passage"
    ],
    "name:spa_x_preferred":[
        "Le Passage"
    ],
    "name:swe_x_preferred":[
        "Le Passage"
    ],
    "wof:name":"Le Passage",
    "wof:placetype":"locality"
},
  "geometry": {"coordinates":[0.80633,49.42722],"type":"Point"}
}