{
  "type": "Feature",
  "properties": {
    "gn:admin1_code":"32",
    "gn:admin2_code":"80",
    "gn:admin3_code":"802",
    "gn:admin4_code":"80776.0",
    "gn:asciiname":"Varennes",
    "gn:country_code":"FR",
    "gn:dem":147,
    "gn:feature_class":"P",
    "gn:feature_code":"PPL",
    "gn:name":"Varennes",
    "gn:population":187,
    "gn:timezone":"Europe/Paris",
    "iso:country":"FR",
    "wof:name":"Varennes",
    "wof:placetype":"locality",
    "wof:population":187
},
  "geometry": {"coordinates":[2.53393,50.04997],"type":"Point"}
}