{
  "type": "Feature",
  "properties": {
    "frgov:code_epci":"248000747",
    "frgov:insee_arr":"4",
    "frgov:insee_com":"80776",
    "frgov:insee_dep":"80",
    "frgov:insee_reg":"32",
    "frgov:nom_com":"Varennes",
    "frgov:nom_com_m":"VARENNES",
    "frgov:nom_dep":"SOMME",
    "frgov:nom_reg":"HAUTS-DE-FRANCE",
    "frgov:statut":"Commune simple",
    "gn:admin1_code":"32",
    "gn:admin2_code":"80",
    "gn:admin3_code":"802",
    "gn:admin4_code":"80776.0",
    "gn:asciiname":"Varennes",
    "gn:country_code":"FR",
    "gn:dem":147,
    "gn:feature_class":"P",
    "gn:feature_code":"PPL",
    "gn:name":"Varennes",
    "gn:population":187,
    "gn:timezone":"Europe/Paris",
    "iso:country":"FR",
    "name:fas_x_preferred":[
        "\u0648\u0631\u0646\u0633\u060c \u0633\u0648\u0645\u0647"
    ],
    "name:fra_x_preferred":[
        "Varennes"
    ],
    "name:pcd_x_preferred":[
        "Vareinne"
    ],
    "name:pms_x_preferred":[
        "Varennes-en-Croix"
    ],
    "name:por_x_preferred":[
        "Varennes-en-Croix"
    ],
    "name:ukr_x_preferred":[
        "\u0412\u0430\u0440\u0435\u043d\u043d"
    ],
    "name:vol_x_preferred":[
        "Varennes-en-Croix"
    ],
    "name:zho_x_preferred":[
        "\u74e6\u96f7\u8bb7"
    ],
    "qs:a0":"France",
    "qs:a1":"SOMME",
    "qs:a1_lc":"80",
    "qs:a1r":"PICARDIE",
    "qs:a1r_lc":"22",
    "qs:a2_lc":"03",
    "qs:a2r_lc":"2",
    "qs:adm0":"France",
    "qs:adm0_a3":"FRA",
    "qs:la":"VARENNES",
    "qs:la_lc":"80776",
    "qs:level":"localadmin",
    "qs:type":"Commune simple",
    "wof:coterminous":[
        404418521
    ],
    "wof:name":"Varennes",
    "wof:placetype":"locality",
    "wof:placetype_local":"Commune simple",
    "wof:population":187
},
  "geometry": {"coordinates":[2.53393,50.04997],"type":"Point"}
}