{
  "type": "Feature",
  "properties": {
    "gn:admin1_code":"44",
    "gn:admin2_code":"67",
    "gn:admin3_code":"677",
    "gn:admin4_code":"67339",
    "gn:asciiname":"Kuhlendorf",
    "gn:country_code":"FR",
    "gn:dem":167,
    "gn:feature_class":"P",
    "gn:feature_code":"PPL",
    "gn:name":"Kuhlendorf",
    "gn:population":0,
    "gn:timezone":"Europe/Paris",
    "iso:country":"FR",
    "name:und_x_variant":[
        "Kuhliendorf",
        "Kuhlendorf"
    ],
    "wof:name":"Kuhlendorf",
    "wof:placetype":"locality"
},
  "geometry": {"coordinates":[7.92173,48.91454],"type":"Point"}
}