{
  "type": "Feature",
  "properties": {
    "gn:admin1_code":"27",
    "gn:admin2_code":"89",
    "gn:admin3_code":"891",
    "gn:admin4_code":"89400",
    "gn:asciiname":"Pesseliere",
    "gn:country_code":"FR",
    "gn:dem":248,
    "gn:feature_class":"P",
    "gn:feature_code":"PPL",
    "gn:name":"Pesseli\u00e8re",
    "gn:population":0,
    "gn:timezone":"Europe/Paris",
    "iso:country":"FR",
    "wof:name":"Pesseliere",
    "wof:placetype":"locality"
},
  "geometry": {"coordinates":[3.34298,47.56453],"type":"Point"}
}