{
  "type": "Feature",
  "properties": {
    "gn:admin1_code":"84",
    "gn:admin2_code":"38",
    "gn:admin3_code":"381",
    "gn:admin4_code":"38084",
    "gn:asciiname":"Lesardieres",
    "gn:country_code":"FR",
    "gn:dem":389,
    "gn:feature_class":"P",
    "gn:feature_code":"PPL",
    "gn:name":"Lesardi\u00e8res",
    "gn:population":0,
    "gn:timezone":"Europe/Paris",
    "iso:country":"FR",
    "name:und_x_variant":[
        "Les Hardi\u00e8res",
        "Lesardi\u00e8res"
    ],
    "wof:name":"Lesardieres",
    "wof:placetype":"locality"
},
  "geometry": {"coordinates":[5.53585,45.35089],"type":"Point"}
}