{
  "type": "Feature",
  "properties": {
    "gn:admin1_code":"44",
    "gn:admin2_code":"54",
    "gn:admin3_code":"541",
    "gn:admin4_code":"54485",
    "gn:asciiname":"Bure-la-Ville",
    "gn:country_code":"FR",
    "gn:dem":242,
    "gn:feature_class":"P",
    "gn:feature_code":"PPL",
    "gn:name":"Bur\u00e9-la-Ville",
    "gn:population":0,
    "gn:timezone":"Europe/Paris",
    "iso:country":"FR",
    "wof:name":"Bure-la-Ville",
    "wof:placetype":"locality"
},
  "geometry": {"coordinates":[5.63232,49.53205],"type":"Point"}
}