{
  "type": "Feature",
  "properties": {
    "gn:admin1_code":"44",
    "gn:admin2_code":"67",
    "gn:admin3_code":"673",
    "gn:admin4_code":"67420",
    "gn:asciiname":"Hersbach",
    "gn:country_code":"FR",
    "gn:dem":320,
    "gn:feature_class":"P",
    "gn:feature_code":"PPL",
    "gn:name":"Hersbach",
    "gn:population":0,
    "gn:timezone":"Europe/Paris",
    "iso:country":"FR",
    "wof:name":"Hersbach",
    "wof:placetype":"locality"
},
  "geometry": {"coordinates":[7.25157,48.49943],"type":"Point"}
}