{
  "type": "Feature",
  "properties": {
    "gn:admin1_code":"75",
    "gn:admin2_code":"23",
    "gn:admin3_code":"231",
    "gn:admin4_code":"23216",
    "gn:asciiname":"Boussac",
    "gn:country_code":"FR",
    "gn:dem":515,
    "gn:feature_class":"P",
    "gn:feature_code":"PPL",
    "gn:name":"Boussac",
    "gn:population":0,
    "gn:timezone":"Europe/Paris",
    "iso:country":"FR",
    "wof:name":"Boussac",
    "wof:placetype":"locality"
},
  "geometry": {"coordinates":[1.83461,45.86778],"type":"Point"}
}