{
  "type": "Feature",
  "properties": {
    "gn:admin1_code":"75",
    "gn:admin2_code":"23",
    "gn:admin3_code":"231",
    "gn:admin4_code":"23216",
    "gn:asciiname":"Boussac",
    "gn:country_code":"FR",
    "gn:dem":515,
    "gn:feature_class":"P",
    "gn:feature_code":"PPL",
    "gn:name":"Boussac",
    "gn:population":0,
    "gn:timezone":"Europe/Paris",
    "iso:country":"FR",
    "name:bre_x_preferred":[
        "Boussac"
    ],
    "name:cat_x_preferred":[
        "Boussac"
    ],
    "name:ceb_x_preferred":[
        "Boussac"
    ],
    "name:deu_x_preferred":[
        "Boussac"
    ],
    "name:epo_x_preferred":[
        "Boussac"
    ],
    "name:fra_x_preferred":[
        "Boussac"
    ],
    "name:ita_x_preferred":[
        "Boussac"
    ],
    "name:nds_x_preferred":[
        "Boussac"
    ],
    "name:nld_x_preferred":[
        "Boussac"
    ],
    "name:oci_x_preferred":[
        "Bossac"
    ],
    "name:pam_x_preferred":[
        "Boussac"
    ],
    "name:pms_x_preferred":[
        "Boussac"
    ],
    "name:pol_x_preferred":[
        "Boussac"
    ],
    "name:por_x_preferred":[
        "Boussac"
    ],
    "name:rus_x_preferred":[
        "\u0411\u0443\u0441\u0441\u0430\u043a"
    ],
    "name:slk_x_preferred":[
        "Boussac"
    ],
    "name:spa_x_preferred":[
        "Boussac"
    ],
    "name:srp_x_preferred":[
        "\u0411\u0443\u0441\u0430\u043a"
    ],
    "name:swe_x_preferred":[
        "Boussac"
    ],
    "name:ukr_x_preferred":[
        "\u0411\u0443\u0441\u0441\u0430\u043a"
    ],
    "wof:name":"Boussac",
    "wof:placetype":"locality"
},
  "geometry": {"coordinates":[1.83461,45.86778],"type":"Point"}
}