{
  "type": "Feature",
  "properties": {
    "gn:admin1_code":"24",
    "gn:admin2_code":"18",
    "gn:admin3_code":"183",
    "gn:admin4_code":"18281.0",
    "gn:asciiname":"La Giraudiere",
    "gn:country_code":"FR",
    "gn:dem":131,
    "gn:feature_class":"P",
    "gn:feature_code":"PPL",
    "gn:name":"La Giraudi\u00e8re",
    "gn:population":0,
    "gn:timezone":"Europe/Paris",
    "iso:country":"FR",
    "name:und_x_variant":[
        "La Giraudi\u00e8re"
    ],
    "wof:name":"La Giraudiere",
    "wof:placetype":"locality"
},
  "geometry": {"coordinates":[2.16457,47.21124],"type":"Point"}
}