{
  "type": "Feature",
  "properties": {
    "gn:admin1_code":"24",
    "gn:admin2_code":"41",
    "gn:admin3_code":"413",
    "gn:admin4_code":"41164",
    "gn:asciiname":"La Croix Verte",
    "gn:country_code":"FR",
    "gn:dem":69,
    "gn:feature_class":"P",
    "gn:feature_code":"PPL",
    "gn:name":"La Croix Verte",
    "gn:population":0,
    "gn:timezone":"Europe/Paris",
    "iso:country":"FR",
    "wof:name":"La Croix Verte",
    "wof:placetype":"locality"
},
  "geometry": {"coordinates":[1.37897,47.278],"type":"Point"}
}