{
  "type": "Feature",
  "properties": {
    "iso:country":"FR",
    "qs_pg:aaroncc":"FR",
    "qs_pg:name":"St.-Pierre Divion",
    "qs_pg:name_adm0":"France",
    "qs_pg:name_adm1":"Picardie",
    "qs_pg:photos":12,
    "qs_pg:photos_1k":2,
    "qs_pg:photos_9k":1,
    "qs_pg:photos_9r":1,
    "qs_pg:photos_all":12,
    "qs_pg:photos_sr":1,
    "qs_pg:pop_sr":0,
    "qs_pg:qs_pg_placetype":"locality",
    "qs_pg:qs_pg_placetype_gp":"Town",
    "qs_pg:woe_adm0":23424819,
    "woe:adm0_id":23424819,
    "woe:name_adm0":"France",
    "woe:name_adm1":"Picardie",
    "woe:placetype":"Town",
    "wof:name":"St.-Pierre Divion",
    "wof:placetype":"neighbourhood"
},
  "geometry": {"coordinates":[2.67667,50.067161],"type":"Point"}
}