{
  "type": "Feature",
  "properties": {
    "gn:admin1_code":"27",
    "gn:admin2_code":"58",
    "gn:admin3_code":"582",
    "gn:admin4_code":"58156",
    "gn:asciiname":"Marcy",
    "gn:country_code":"FR",
    "gn:dem":264,
    "gn:feature_class":"P",
    "gn:feature_code":"PPL",
    "gn:name":"Marcy",
    "gn:population":0,
    "gn:timezone":"Europe/Paris",
    "iso:country":"FR",
    "name:bul_x_preferred":[
        "\u041c\u0430\u0440\u0441\u0438"
    ],
    "name:ceb_x_preferred":[
        "Marcy"
    ],
    "name:deu_x_preferred":[
        "Marcy"
    ],
    "name:fra_x_preferred":[
        "Marcy"
    ],
    "name:ita_x_preferred":[
        "Marcy"
    ],
    "name:lmo_x_preferred":[
        "Marcy"
    ],
    "name:nds_x_preferred":[
        "Marcy"
    ],
    "name:nld_x_preferred":[
        "Marcy"
    ],
    "name:oci_x_preferred":[
        "Marcy"
    ],
    "name:pms_x_preferred":[
        "Marcy"
    ],
    "name:pol_x_preferred":[
        "Marcy"
    ],
    "name:por_x_preferred":[
        "Marcy"
    ],
    "name:rus_x_preferred":[
        "\u041c\u0430\u0440\u0441\u0438"
    ],
    "name:scn_x_preferred":[
        "Marcy"
    ],
    "name:slk_x_preferred":[
        "Marcy"
    ],
    "name:spa_x_preferred":[
        "Marcy"
    ],
    "name:swe_x_preferred":[
        "Marcy"
    ],
    "name:ukr_x_preferred":[
        "\u041c\u0430\u0440\u0441\u0456"
    ],
    "wof:name":"Marcy",
    "wof:placetype":"locality"
},
  "geometry": {"coordinates":[3.40829,47.32],"type":"Point"}
}