{
  "type": "Feature",
  "properties": {
    "gn:admin1_code":"27",
    "gn:admin2_code":"58",
    "gn:admin3_code":"582",
    "gn:admin4_code":"58156",
    "gn:asciiname":"Marcy",
    "gn:country_code":"FR",
    "gn:dem":264,
    "gn:feature_class":"P",
    "gn:feature_code":"PPL",
    "gn:name":"Marcy",
    "gn:population":0,
    "gn:timezone":"Europe/Paris",
    "iso:country":"FR",
    "wof:name":"Marcy",
    "wof:placetype":"locality"
},
  "geometry": {"coordinates":[3.40829,47.32],"type":"Point"}
}