{
  "type": "Feature",
  "properties": {
    "gn:admin1_code":"75",
    "gn:admin2_code":"24",
    "gn:admin3_code":"243",
    "gn:admin4_code":"24064",
    "gn:asciiname":"Les Roches",
    "gn:country_code":"FR",
    "gn:dem":134,
    "gn:feature_class":"P",
    "gn:feature_code":"PPL",
    "gn:name":"Les Roches",
    "gn:population":0,
    "gn:timezone":"Europe/Paris",
    "iso:country":"FR",
    "wof:name":"Les Roches",
    "wof:placetype":"locality"
},
  "geometry": {"coordinates":[0.68017,45.36373],"type":"Point"}
}