{
  "type": "Feature",
  "properties": {
    "gn:admin1_code":"75",
    "gn:admin2_code":"87",
    "gn:admin3_code":"872",
    "gn:admin4_code":"87051",
    "gn:asciiname":"Reneix",
    "gn:country_code":"FR",
    "gn:dem":484,
    "gn:feature_class":"P",
    "gn:feature_code":"PPL",
    "gn:name":"Reneix",
    "gn:population":0,
    "gn:timezone":"Europe/Paris",
    "iso:country":"FR",
    "wof:name":"Reneix",
    "wof:placetype":"locality"
},
  "geometry": {"coordinates":[1.59564,45.58451],"type":"Point"}
}