{
  "type": "Feature",
  "properties": {
    "gn:admin1_code":"52",
    "gn:admin2_code":"72",
    "gn:admin3_code":"722",
    "gn:admin4_code":"72352",
    "gn:asciiname":"L'Angelerie",
    "gn:country_code":"FR",
    "gn:dem":88,
    "gn:feature_class":"P",
    "gn:feature_code":"PPL",
    "gn:name":"L\u2019Angelerie",
    "gn:population":0,
    "gn:timezone":"Europe/Paris",
    "iso:country":"FR",
    "wof:name":"L'Angelerie",
    "wof:placetype":"locality"
},
  "geometry": {"coordinates":[0.39521,48.20141],"type":"Point"}
}