{
  "type": "Feature",
  "properties": {
    "gn:admin1_code":"84",
    "gn:admin2_code":"15",
    "gn:admin3_code":"151",
    "gn:admin4_code":"15228",
    "gn:asciiname":"Roudettes",
    "gn:country_code":"FR",
    "gn:dem":613,
    "gn:feature_class":"P",
    "gn:feature_code":"PPL",
    "gn:name":"Roudettes",
    "gn:population":0,
    "gn:timezone":"Europe/Paris",
    "iso:country":"FR",
    "wof:name":"Roudettes",
    "wof:placetype":"locality"
},
  "geometry": {"coordinates":[2.09852,44.93369000000001],"type":"Point"}
}