{
  "type": "Feature",
  "properties": {
    "gn:admin1_code":"76",
    "gn:admin2_code":"34",
    "gn:admin3_code":"343",
    "gn:admin4_code":"34333",
    "gn:asciiname":"Domaine du Marin Palm",
    "gn:country_code":"FR",
    "gn:dem":6,
    "gn:feature_class":"P",
    "gn:feature_code":"PPL",
    "gn:name":"Domaine du Marin Palm",
    "gn:population":0,
    "gn:timezone":"Europe/Paris",
    "iso:country":"FR",
    "wof:name":"Domaine du Marin Palm",
    "wof:placetype":"locality"
},
  "geometry": {"coordinates":[3.79851,43.48405],"type":"Point"}
}