{
  "type": "Feature",
  "properties": {
    "gn:admin1_code":"44",
    "gn:admin2_code":"55",
    "gn:admin3_code":"552",
    "gn:admin4_code":"55551",
    "gn:asciiname":"Hattonchatel",
    "gn:country_code":"FR",
    "gn:dem":356,
    "gn:feature_class":"P",
    "gn:feature_code":"PPL",
    "gn:name":"Hattonch\u00e2tel",
    "gn:population":0,
    "gn:timezone":"Europe/Paris",
    "iso:country":"FR",
    "name:nor_x_preferred":[
        "Hattonchatel Chateau"
    ],
    "name:und_x_variant":[
        "Hattonch\u00e2tel"
    ],
    "wof:name":"Hattonchatel",
    "wof:placetype":"locality"
},
  "geometry": {"coordinates":[5.70272,48.99229],"type":"Point"}
}