{
  "type": "Feature",
  "properties": {
    "gn:admin1_code":"94",
    "gn:admin2_code":"2B",
    "gn:admin3_code":"2B2",
    "gn:admin4_code":"2B107",
    "gn:asciiname":"Piazza",
    "gn:country_code":"FR",
    "gn:dem":265,
    "gn:feature_class":"P",
    "gn:feature_code":"PPL",
    "gn:name":"Piazza",
    "gn:population":0,
    "gn:timezone":"Europe/Paris",
    "iso:country":"FR",
    "wof:name":"Piazza",
    "wof:placetype":"locality"
},
  "geometry": {"coordinates":[9.37594,42.97584000000001],"type":"Point"}
}