{
  "type": "Feature",
  "properties": {
    "gn:admin1_code":"52",
    "gn:admin2_code":"44",
    "gn:admin3_code":"443",
    "gn:admin4_code":"44132",
    "gn:asciiname":"La Ville-es-Babin",
    "gn:country_code":"FR",
    "gn:dem":12,
    "gn:feature_class":"P",
    "gn:feature_code":"PPLL",
    "gn:name":"La Ville-\u00e8s-Babin",
    "gn:population":0,
    "gn:timezone":"Europe/Paris",
    "iso:country":"FR",
    "wof:name":"La Ville-es-Babin",
    "wof:placetype":"locality"
},
  "geometry": {"coordinates":[-2.31145,47.25871],"type":"Point"}
}