{
  "type": "Feature",
  "properties": {
    "gn:admin1_code":"53",
    "gn:admin2_code":"22",
    "gn:admin3_code":"223",
    "gn:admin4_code":"22113",
    "gn:asciiname":"Buhulien",
    "gn:country_code":"FR",
    "gn:dem":68,
    "gn:feature_class":"P",
    "gn:feature_code":"PPL",
    "gn:name":"Buhulien",
    "gn:population":0,
    "gn:timezone":"Europe/Paris",
    "iso:country":"FR",
    "wof:name":"Buhulien",
    "wof:placetype":"locality"
},
  "geometry": {"coordinates":[-3.41181,48.71667],"type":"Point"}
}