{
  "type": "Feature",
  "properties": {
    "gn:admin1_code":"24",
    "gn:admin2_code":"28",
    "gn:admin3_code":"281",
    "gn:admin4_code":"28339",
    "gn:asciiname":"Le Charmois",
    "gn:country_code":"FR",
    "gn:dem":178,
    "gn:feature_class":"P",
    "gn:feature_code":"PPL",
    "gn:name":"Le Charmois",
    "gn:population":0,
    "gn:timezone":"Europe/Paris",
    "iso:country":"FR",
    "wof:name":"Le Charmois",
    "wof:placetype":"locality"
},
  "geometry": {"coordinates":[1.24411,48.42138],"type":"Point"}
}