{
  "type": "Feature",
  "properties": {
    "gn:admin1_code":"93",
    "gn:admin2_code":"13",
    "gn:admin3_code":"134",
    "gn:admin4_code":"13026",
    "gn:asciiname":"Leou",
    "gn:country_code":"FR",
    "gn:dem":20,
    "gn:feature_class":"P",
    "gn:feature_code":"PPL",
    "gn:name":"L\u00e9ou",
    "gn:population":0,
    "gn:timezone":"Europe/Paris",
    "iso:country":"FR",
    "wof:name":"Leou",
    "wof:placetype":"locality"
},
  "geometry": {"coordinates":[5.14955,43.39288],"type":"Point"}
}