{
  "type": "Feature",
  "properties": {
    "gn:admin1_code":"52",
    "gn:admin2_code":"49",
    "gn:admin3_code":"493",
    "gn:admin4_code":"49336",
    "gn:asciiname":"Le Plessis Neuf",
    "gn:country_code":"FR",
    "gn:dem":146,
    "gn:feature_class":"P",
    "gn:feature_code":"PPL",
    "gn:name":"Le Plessis Neuf",
    "gn:population":0,
    "gn:timezone":"Europe/Paris",
    "iso:country":"FR",
    "wof:name":"Le Plessis Neuf",
    "wof:placetype":"locality"
},
  "geometry": {"coordinates":[-0.59297,47.04512],"type":"Point"}
}