{
  "type": "Feature",
  "properties": {
    "gn:admin1_code":"27",
    "gn:admin2_code":"58",
    "gn:admin3_code":"583",
    "gn:admin4_code":"58105",
    "gn:asciiname":"Le Pavillon",
    "gn:country_code":"FR",
    "gn:dem":278,
    "gn:feature_class":"P",
    "gn:feature_code":"PPL",
    "gn:name":"Le Pavillon",
    "gn:population":0,
    "gn:timezone":"Europe/Paris",
    "iso:country":"FR",
    "name:und_x_variant":[
        "Pavillon",
        "Le Pavillon"
    ],
    "wof:name":"Le Pavillon",
    "wof:placetype":"locality"
},
  "geometry": {"coordinates":[3.3882,46.89591],"type":"Point"}
}