{
  "type": "Feature",
  "properties": {
    "gn:admin1_code":"53",
    "gn:admin2_code":"22",
    "gn:admin3_code":"221",
    "gn:admin4_code":"22175",
    "gn:asciiname":"Le Saint-Esprit",
    "gn:country_code":"FR",
    "gn:dem":97,
    "gn:feature_class":"P",
    "gn:feature_code":"PPL",
    "gn:name":"Le Saint-Esprit",
    "gn:population":0,
    "gn:timezone":"Europe/Paris",
    "iso:country":"FR",
    "wof:name":"Le Saint-Esprit",
    "wof:placetype":"locality"
},
  "geometry": {"coordinates":[-2.35539,48.45717],"type":"Point"}
}