{
  "type": "Feature",
  "properties": {
    "gn:admin1_code":"93",
    "gn:admin2_code":"05",
    "gn:admin3_code":"051",
    "gn:admin4_code":"05151",
    "gn:asciiname":"La Balmette",
    "gn:country_code":"FR",
    "gn:dem":1256,
    "gn:feature_class":"P",
    "gn:feature_code":"PPL",
    "gn:name":"La Balmette",
    "gn:population":0,
    "gn:timezone":"Europe/Paris",
    "iso:country":"FR",
    "wof:name":"La Balmette",
    "wof:placetype":"locality"
},
  "geometry": {"coordinates":[6.56667,44.81667],"type":"Point"}
}