{
  "type": "Feature",
  "properties": {
    "gn:admin1_code":"11",
    "gn:admin2_code":"91",
    "gn:admin3_code":"912",
    "gn:admin4_code":"91649",
    "gn:asciiname":"Le Bouchet",
    "gn:country_code":"FR",
    "gn:dem":67,
    "gn:feature_class":"P",
    "gn:feature_code":"PPL",
    "gn:name":"Le Bouchet",
    "gn:population":0,
    "gn:timezone":"Europe/Paris",
    "iso:country":"FR",
    "name:und_x_variant":[
        "Le Bouche",
        "Le Bouchet"
    ],
    "wof:name":"Le Bouchet",
    "wof:placetype":"locality"
},
  "geometry": {"coordinates":[2.36089,48.5382],"type":"Point"}
}