{
  "type": "Feature",
  "properties": {
    "gn:admin1_code":"24",
    "gn:admin2_code":"37",
    "gn:admin3_code":"372",
    "gn:admin4_code":"37006.0",
    "gn:asciiname":"Les Ansaults",
    "gn:country_code":"FR",
    "gn:dem":77,
    "gn:feature_class":"P",
    "gn:feature_code":"PPL",
    "gn:name":"Les Ansaults",
    "gn:population":0,
    "gn:timezone":"Europe/Paris",
    "iso:country":"FR",
    "wof:name":"Les Ansaults",
    "wof:placetype":"locality"
},
  "geometry": {"coordinates":[0.60806,47.26957],"type":"Point"}
}