{
  "type": "Feature",
  "properties": {
    "gn:admin1_code":"27",
    "gn:admin2_code":"58",
    "gn:admin3_code":"582",
    "gn:admin4_code":"58116.0",
    "gn:asciiname":"Flez-Cuzy",
    "gn:country_code":"FR",
    "gn:dem":253,
    "gn:feature_class":"P",
    "gn:feature_code":"PPL",
    "gn:name":"Flez-Cuzy",
    "gn:population":0,
    "gn:timezone":"Europe/Paris",
    "iso:country":"FR",
    "name:cat_x_preferred":[
        "Flez-Cuzy"
    ],
    "name:ceb_x_preferred":[
        "Flez-Cuzy"
    ],
    "name:deu_x_preferred":[
        "Flez-Cuzy"
    ],
    "name:eus_x_preferred":[
        "Flez-Cuzy"
    ],
    "name:fra_x_preferred":[
        "Flez-Cuzy"
    ],
    "name:hun_x_preferred":[
        "Flez-Cuzy"
    ],
    "name:ita_x_preferred":[
        "Flez-Cuzy"
    ],
    "name:kaz_x_preferred":[
        "\u0424\u043b\u0435\u0437-\u041a\u044e\u0437\u0438"
    ],
    "name:lat_x_preferred":[
        "Flaiacum"
    ],
    "name:ltz_x_preferred":[
        "Flez-Cuzy"
    ],
    "name:msa_x_preferred":[
        "Flez-Cuzy"
    ],
    "name:nld_x_preferred":[
        "Flez-Cuzy"
    ],
    "name:oci_x_preferred":[
        "Flez-Cuzy"
    ],
    "name:pms_x_preferred":[
        "Flez-Cuzy"
    ],
    "name:pol_x_preferred":[
        "Flez-Cuzy"
    ],
    "name:por_x_preferred":[
        "Flez-Cuzy"
    ],
    "name:ron_x_preferred":[
        "Flez-Cuzy"
    ],
    "name:slk_x_preferred":[
        "Flez-Cuzy"
    ],
    "name:spa_x_preferred":[
        "Flez-Cuzy"
    ],
    "name:swe_x_preferred":[
        "Flez-Cuzy"
    ],
    "name:ukr_x_preferred":[
        "\u0424\u043b\u0435\u0437-\u041a\u044e\u0437\u0456"
    ],
    "name:uzb_x_preferred":[
        "Flez-Cuzy"
    ],
    "name:vie_x_preferred":[
        "Flez-Cuzy"
    ],
    "name:vol_x_preferred":[
        "Flez-Cuzy"
    ],
    "name:war_x_preferred":[
        "Flez-Cuzy"
    ],
    "name:zho_x_preferred":[
        "\u5f17\u83b1\u5c48\u9f50"
    ],
    "wof:name":"Flez-Cuzy",
    "wof:placetype":"locality"
},
  "geometry": {"coordinates":[3.42387,47.4073],"type":"Point"}
}