{
  "type": "Feature",
  "properties": {
    "gn:admin1_code":"84",
    "gn:admin2_code":"42",
    "gn:admin3_code":"421",
    "gn:admin4_code":"42019",
    "gn:asciiname":"Groseillier",
    "gn:country_code":"FR",
    "gn:dem":443,
    "gn:feature_class":"P",
    "gn:feature_code":"PPL",
    "gn:name":"Groseillier",
    "gn:population":0,
    "gn:timezone":"Europe/Paris",
    "iso:country":"FR",
    "wof:name":"Groseillier",
    "wof:placetype":"locality"
},
  "geometry": {"coordinates":[4.00726,45.75444],"type":"Point"}
}