{
  "type": "Feature",
  "properties": {
    "gn:admin1_code":"53",
    "gn:admin2_code":"35",
    "gn:admin3_code":"354",
    "gn:admin4_code":"35308",
    "gn:asciiname":"Les Renardieres",
    "gn:country_code":"FR",
    "gn:dem":57,
    "gn:feature_class":"P",
    "gn:feature_code":"PPL",
    "gn:name":"Les Renardi\u00e8res",
    "gn:population":0,
    "gn:timezone":"Europe/Paris",
    "iso:country":"FR",
    "wof:name":"Les Renardieres",
    "wof:placetype":"locality"
},
  "geometry": {"coordinates":[-1.8745,48.45819],"type":"Point"}
}