{
  "type": "Feature",
  "properties": {
    "gn:admin1_code":"84",
    "gn:admin2_code":"63",
    "gn:admin3_code":"634",
    "gn:admin4_code":"63108",
    "gn:asciiname":"Le Cheix",
    "gn:cc2":"FR",
    "gn:country_code":"FR",
    "gn:dem":322,
    "gn:feature_class":"P",
    "gn:feature_code":"PPL",
    "gn:name":"Le Cheix",
    "gn:population":0,
    "gn:timezone":"Europe/Paris",
    "iso:country":"FR",
    "name:und_x_variant":[
        "Le Cheix-sur-Morge"
    ],
    "wof:name":"Le Cheix",
    "wof:placetype":"locality"
},
  "geometry": {"coordinates":[3.16667,45.95],"type":"Point"}
}