{
  "type": "Feature",
  "properties": {
    "gn:admin1_code":"75",
    "gn:admin2_code":"24",
    "gn:admin3_code":"244",
    "gn:admin4_code":"24086",
    "gn:asciiname":"La Chapelle-Pechaud",
    "gn:country_code":"FR",
    "gn:dem":265,
    "gn:feature_class":"P",
    "gn:feature_code":"PPL",
    "gn:name":"La Chapelle-P\u00e9chaud",
    "gn:population":0,
    "gn:timezone":"Europe/Paris",
    "iso:country":"FR",
    "name:und_x_variant":[
        "La Chapelle",
        "La Chapelle-P\u00e9chaud"
    ],
    "wof:name":"La Chapelle-Pechaud",
    "wof:placetype":"locality"
},
  "geometry": {"coordinates":[1.11553,44.77869000000001],"type":"Point"}
}