{
  "type": "Feature",
  "properties": {
    "gn:admin1_code":"84",
    "gn:admin2_code":"38",
    "gn:admin3_code":"382",
    "gn:admin4_code":"38139",
    "gn:asciiname":"Faverges-de-Mepieu",
    "gn:country_code":"FR",
    "gn:dem":231,
    "gn:feature_class":"P",
    "gn:feature_code":"PPL",
    "gn:name":"Faverges-de-M\u00e9pieu",
    "gn:population":0,
    "gn:timezone":"Europe/Paris",
    "iso:country":"FR",
    "name:und_x_variant":[
        "Faverge",
        "Faverges",
        "Faverges-de-M\u00e9pieu"
    ],
    "wof:name":"Faverges-de-Mepieu",
    "wof:placetype":"locality"
},
  "geometry": {"coordinates":[5.4461,45.76514],"type":"Point"}
}