{
  "type": "Feature",
  "properties": {
    "gn:admin1_code":"75",
    "gn:admin2_code":"87",
    "gn:admin3_code":"872",
    "gn:admin4_code":"87123",
    "gn:asciiname":"La Villeneuve",
    "gn:country_code":"FR",
    "gn:dem":534,
    "gn:feature_class":"P",
    "gn:feature_code":"PPL",
    "gn:name":"La Villeneuve",
    "gn:population":0,
    "gn:timezone":"Europe/Paris",
    "iso:country":"FR",
    "name:bar_x_preferred":[
        "La Villeneuve"
    ],
    "name:ceb_x_preferred":[
        "La Villeneuve"
    ],
    "name:deu_x_preferred":[
        "La Villeneuve"
    ],
    "name:epo_x_preferred":[
        "La Villeneuve"
    ],
    "name:fra_x_preferred":[
        "La Villeneuve"
    ],
    "name:ita_x_preferred":[
        "La Villeneuve"
    ],
    "name:nds_x_preferred":[
        "La Villeneuve"
    ],
    "name:nld_x_preferred":[
        "La Villeneuve"
    ],
    "name:pms_x_preferred":[
        "La Villeneuve"
    ],
    "name:pol_x_preferred":[
        "La Villeneuve"
    ],
    "name:por_x_preferred":[
        "La Villeneuve"
    ],
    "name:slk_x_preferred":[
        "La Villeneuve"
    ],
    "name:spa_x_preferred":[
        "La Villeneuve"
    ],
    "name:swe_x_preferred":[
        "La Villeneuve"
    ],
    "name:ukr_x_preferred":[
        "\u041b\u0430-\u0412\u0456\u043b\u044c\u043d\u0435\u0432"
    ],
    "wof:name":"La Villeneuve",
    "wof:placetype":"locality"
},
  "geometry": {"coordinates":[1.8469,45.68443],"type":"Point"}
}