{
  "type": "Feature",
  "properties": {
    "gn:admin1_code":"93",
    "gn:admin2_code":"05",
    "gn:admin3_code":"051",
    "gn:admin4_code":"05101",
    "gn:asciiname":"Chambran",
    "gn:country_code":"FR",
    "gn:dem":1721,
    "gn:feature_class":"P",
    "gn:feature_code":"PPL",
    "gn:name":"Chambran",
    "gn:population":0,
    "gn:timezone":"Europe/Paris",
    "iso:country":"FR",
    "wof:name":"Chambran",
    "wof:placetype":"locality"
},
  "geometry": {"coordinates":[6.49306,44.90293],"type":"Point"}
}