{
  "type": "Feature",
  "properties": {
    "gn:admin1_code":"76",
    "gn:admin2_code":"30",
    "gn:admin3_code":"302",
    "gn:admin4_code":"30001",
    "gn:asciiname":"Chabian",
    "gn:country_code":"FR",
    "gn:dem":257,
    "gn:feature_class":"P",
    "gn:feature_code":"PPL",
    "gn:name":"Chabian",
    "gn:population":0,
    "gn:timezone":"Europe/Paris",
    "iso:country":"FR",
    "name:und_x_variant":[
        "Le Chabian",
        "Chabian"
    ],
    "wof:name":"Chabian",
    "wof:placetype":"locality"
},
  "geometry": {"coordinates":[4.28839,44.08934],"type":"Point"}
}