{
  "type": "Feature",
  "properties": {
    "gn:admin1_code":"24",
    "gn:admin2_code":"18",
    "gn:admin3_code":"182",
    "gn:admin4_code":"18231",
    "gn:asciiname":"La Ville du Bout",
    "gn:country_code":"FR",
    "gn:dem":259,
    "gn:feature_class":"P",
    "gn:feature_code":"PPL",
    "gn:name":"La Ville du Bout",
    "gn:population":0,
    "gn:timezone":"Europe/Paris",
    "iso:country":"FR",
    "wof:name":"La Ville du Bout",
    "wof:placetype":"locality"
},
  "geometry": {"coordinates":[2.58317,46.74839],"type":"Point"}
}