{
  "type": "Feature",
  "properties": {
    "gn:admin1_code":"53",
    "gn:admin2_code":"56",
    "gn:admin3_code":"563",
    "gn:admin4_code":"56080",
    "gn:asciiname":"Lierou",
    "gn:country_code":"FR",
    "gn:dem":79,
    "gn:feature_class":"P",
    "gn:feature_code":"PPL",
    "gn:name":"Li\u00e9rou",
    "gn:population":0,
    "gn:timezone":"Europe/Paris",
    "iso:country":"FR",
    "wof:name":"Lierou",
    "wof:placetype":"locality"
},
  "geometry": {"coordinates":[-2.42323,48.04648],"type":"Point"}
}