{
  "type": "Feature",
  "properties": {
    "gn:admin1_code":"84",
    "gn:admin2_code":"63",
    "gn:admin3_code":"632",
    "gn:admin4_code":"63034",
    "gn:asciiname":"Beauregard-l'Eveque",
    "gn:country_code":"FR",
    "gn:dem":367,
    "gn:feature_class":"P",
    "gn:feature_code":"PPL",
    "gn:name":"Beauregard-l\u2019\u00c9v\u00eaque",
    "gn:population":0,
    "gn:timezone":"Europe/Paris",
    "iso:country":"FR",
    "name:cat_x_preferred":[
        "Biauregard d'Al\u00e8ir"
    ],
    "name:ceb_x_preferred":[
        "Beauregard-l'\u00c9v\u00eaque"
    ],
    "name:deu_x_preferred":[
        "Beauregard-l\u2019\u00c9v\u00eaque"
    ],
    "name:eus_x_preferred":[
        "Beauregard-l'\u00c9v\u00eaque"
    ],
    "name:fra_x_preferred":[
        "Beauregard-l'\u00c9v\u00eaque"
    ],
    "name:hun_x_preferred":[
        "Beauregard-l\u2019\u00c9v\u00eaque"
    ],
    "name:ita_x_preferred":[
        "Beauregard-l'\u00c9v\u00eaque"
    ],
    "name:lat_x_preferred":[
        "Beauregard-l'\u00c9v\u00eaque"
    ],
    "name:mlg_x_preferred":[
        "Beauregard-l'\u00c9v\u00eaque"
    ],
    "name:msa_x_preferred":[
        "Beauregard-l'\u00c9v\u00eaque"
    ],
    "name:nld_x_preferred":[
        "Beauregard-l'\u00c9v\u00eaque"
    ],
    "name:oci_x_preferred":[
        "Biauregard"
    ],
    "name:pms_x_preferred":[
        "Beauregard-l'\u00c9v\u00eaque"
    ],
    "name:pol_x_preferred":[
        "Beauregard-l\u2019\u00c9v\u00eaque"
    ],
    "name:por_x_preferred":[
        "Beauregard-l'\u00c9v\u00eaque"
    ],
    "name:ron_x_preferred":[
        "Beauregard-l'\u00c9v\u00eaque"
    ],
    "name:slk_x_preferred":[
        "Beauregard-l\u2019\u00c9v\u00eaque"
    ],
    "name:spa_x_preferred":[
        "Beauregard-l'\u00c9v\u00eaque"
    ],
    "name:sqi_x_preferred":[
        "Beauregard-l'\u00c9v\u00eaque"
    ],
    "name:srp_x_preferred":[
        "\u0411\u043e\u0440\u0435\u0433\u0430\u0440 \u043b'\u0415\u0432\u0435\u043a"
    ],
    "name:swe_x_preferred":[
        "Beauregard-l'\u00c9v\u00eaque"
    ],
    "name:ukr_x_preferred":[
        "\u0411\u043e\u0440\u0435\u0433\u0430\u0440-\u043b'\u0415\u0432\u0435\u043a"
    ],
    "name:und_x_variant":[
        "Beauregard",
        "Beauregard-l\u2019\u00c9v\u00eaque"
    ],
    "name:uzb_x_preferred":[
        "Beauregard-l'\u00c9v\u00eaque"
    ],
    "name:vie_x_preferred":[
        "Beauregard-l'\u00c9v\u00eaque"
    ],
    "name:vol_x_preferred":[
        "Beauregard-l'\u00c9v\u00eaque"
    ],
    "name:war_x_preferred":[
        "Beauregard-l'\u00c9v\u00eaque"
    ],
    "name:zho_x_preferred":[
        "\u535a\u52d2\u52a0\u5c14\u83b1\u97e6\u514b"
    ],
    "wof:name":"Beauregard-l'Eveque",
    "wof:placetype":"locality"
},
  "geometry": {"coordinates":[3.29989,45.81261],"type":"Point"}
}