{
  "type": "Feature",
  "properties": {
    "gn:admin1_code":"84",
    "gn:admin2_code":"63",
    "gn:admin3_code":"632",
    "gn:admin4_code":"63034",
    "gn:asciiname":"Beauregard-l'Eveque",
    "gn:country_code":"FR",
    "gn:dem":367,
    "gn:feature_class":"P",
    "gn:feature_code":"PPL",
    "gn:name":"Beauregard-l\u2019\u00c9v\u00eaque",
    "gn:population":0,
    "gn:timezone":"Europe/Paris",
    "iso:country":"FR",
    "name:und_x_variant":[
        "Beauregard",
        "Beauregard-l\u2019\u00c9v\u00eaque"
    ],
    "wof:name":"Beauregard-l'Eveque",
    "wof:placetype":"locality"
},
  "geometry": {"coordinates":[3.29989,45.81261],"type":"Point"}
}