{
  "type": "Feature",
  "properties": {
    "gn:admin1_code":"76",
    "gn:admin2_code":"30",
    "gn:admin3_code":"301",
    "gn:admin4_code":"30203",
    "gn:asciiname":"Portes",
    "gn:country_code":"FR",
    "gn:dem":586,
    "gn:feature_class":"P",
    "gn:feature_code":"PPL",
    "gn:name":"Portes",
    "gn:population":343,
    "gn:timezone":"Europe/Paris",
    "iso:country":"FR",
    "name:ceb_x_preferred":[
        "Portes"
    ],
    "name:deu_x_preferred":[
        "Portes"
    ],
    "name:fra_x_preferred":[
        "Portes"
    ],
    "name:ita_x_preferred":[
        "Portes"
    ],
    "name:lmo_x_preferred":[
        "Portes"
    ],
    "name:nds_x_preferred":[
        "Portes"
    ],
    "name:nld_x_preferred":[
        "Portes"
    ],
    "name:oci_x_preferred":[
        "Portes"
    ],
    "name:pms_x_preferred":[
        "Portes"
    ],
    "name:pol_x_preferred":[
        "Portes"
    ],
    "name:slk_x_preferred":[
        "Portes"
    ],
    "name:spa_x_preferred":[
        "Portes"
    ],
    "name:swe_x_preferred":[
        "Portes"
    ],
    "wof:name":"Portes",
    "wof:placetype":"locality",
    "wof:population":343
},
  "geometry": {"coordinates":[4.02179,44.26903],"type":"Point"}
}