{
  "type": "Feature",
  "properties": {
    "frgov:code_epci":"200066918",
    "frgov:insee_arr":"1",
    "frgov:insee_com":"30203",
    "frgov:insee_dep":"30",
    "frgov:insee_reg":"76",
    "frgov:nom_com":"Portes",
    "frgov:nom_com_m":"PORTES",
    "frgov:nom_dep":"GARD",
    "frgov:nom_reg":"OCCITANIE",
    "frgov:statut":"Commune simple",
    "gn:admin1_code":"76",
    "gn:admin2_code":"30",
    "gn:admin3_code":"301",
    "gn:admin4_code":"30203",
    "gn:asciiname":"Portes",
    "gn:country_code":"FR",
    "gn:dem":586,
    "gn:feature_class":"P",
    "gn:feature_code":"PPL",
    "gn:name":"Portes",
    "gn:population":343,
    "gn:timezone":"Europe/Paris",
    "iso:country":"FR",
    "name:cat_x_preferred":[
        "P\u00f2rtas"
    ],
    "name:ceb_x_preferred":[
        "Portes"
    ],
    "name:deu_x_preferred":[
        "Portes"
    ],
    "name:fra_x_preferred":[
        "Portes"
    ],
    "name:ita_x_preferred":[
        "Portes"
    ],
    "name:kaz_x_preferred":[
        "\u041f\u043e\u0440\u0442"
    ],
    "name:lmo_x_preferred":[
        "Portes"
    ],
    "name:nds_x_preferred":[
        "Portes"
    ],
    "name:nld_x_preferred":[
        "Portes"
    ],
    "name:oci_x_preferred":[
        "Portes"
    ],
    "name:oci_x_variant":[
        "Portes"
    ],
    "name:pms_x_preferred":[
        "Portes"
    ],
    "name:pol_x_preferred":[
        "Portes"
    ],
    "name:slk_x_preferred":[
        "Portes"
    ],
    "name:spa_x_preferred":[
        "Portes"
    ],
    "name:swe_x_preferred":[
        "Portes"
    ],
    "name:ukr_x_preferred":[
        "\u041f\u043e\u0440\u0442"
    ],
    "name:zho_x_preferred":[
        "\u6ce2\u5c14\u6cf0"
    ],
    "qs:a0":"France",
    "qs:a1":"GARD",
    "qs:a1_lc":"30",
    "qs:a1r":"LANGUEDOC-ROUSSILLON",
    "qs:a1r_lc":"91",
    "qs:a2_lc":"11",
    "qs:a2r_lc":"1",
    "qs:adm0":"France",
    "qs:adm0_a3":"FRA",
    "qs:la":"PORTES",
    "qs:la_lc":"30203",
    "qs:level":"localadmin",
    "qs:type":"Commune simple",
    "wof:coterminous":[
        404349451
    ],
    "wof:name":"Portes",
    "wof:placetype":"locality",
    "wof:placetype_local":"Commune simple",
    "wof:population":343
},
  "geometry": {"coordinates":[4.02179,44.26903],"type":"Point"}
}