{
  "type": "Feature",
  "properties": {
    "iso:country":"FR",
    "name:eng_x_preferred":[
        "Les Mobiles-La Briche-Les Beatus-Blumenthal"
    ],
    "name:fra_x_preferred":[
        "Les Mobiles-La Briche-Les B\u00e9atus-Blumenthal"
    ],
    "wof:name":"Les Mobiles-La Briche-Les Beatus-Blumenthal",
    "wof:placetype":"neighbourhood"
},
  "geometry": {"coordinates":[2.33583054023342,48.94860976925756],"type":"Point"}
}