{
  "type": "Feature",
  "properties": {
    "gn:admin1_code":"28",
    "gn:admin2_code":"14",
    "gn:admin3_code":"143",
    "gn:admin4_code":"14654",
    "gn:asciiname":"Garnetot",
    "gn:country_code":"FR",
    "gn:dem":120,
    "gn:feature_class":"P",
    "gn:feature_code":"PPL",
    "gn:name":"Garnetot",
    "gn:population":0,
    "gn:timezone":"Europe/Paris",
    "iso:country":"FR",
    "wof:name":"Garnetot",
    "wof:placetype":"locality"
},
  "geometry": {"coordinates":[0.04663,48.92861],"type":"Point"}
}