{
  "type": "Feature",
  "properties": {
    "gn:admin1_code":"24",
    "gn:admin2_code":"45",
    "gn:admin3_code":"453",
    "gn:admin4_code":"45191",
    "gn:asciiname":"Maisoncelles",
    "gn:country_code":"FR",
    "gn:dem":109,
    "gn:feature_class":"P",
    "gn:feature_code":"PPL",
    "gn:name":"Maisoncelles",
    "gn:population":0,
    "gn:timezone":"Europe/Paris",
    "iso:country":"FR",
    "name:und_x_variant":[
        "Maisoncelle",
        "Maisoncelles"
    ],
    "wof:name":"Maisoncelles",
    "wof:placetype":"locality"
},
  "geometry": {"coordinates":[2.37744,48.25409000000001],"type":"Point"}
}