{
  "type": "Feature",
  "properties": {
    "gn:admin1_code":"24",
    "gn:admin2_code":"45",
    "gn:admin3_code":"453",
    "gn:admin4_code":"45191",
    "gn:asciiname":"Maisoncelles",
    "gn:country_code":"FR",
    "gn:dem":109,
    "gn:feature_class":"P",
    "gn:feature_code":"PPL",
    "gn:name":"Maisoncelles",
    "gn:population":0,
    "gn:timezone":"Europe/Paris",
    "iso:country":"FR",
    "name:ceb_x_preferred":[
        "Maisoncelles"
    ],
    "name:deu_x_preferred":[
        "Maisoncelles"
    ],
    "name:fra_x_preferred":[
        "Maisoncelles"
    ],
    "name:ita_x_preferred":[
        "Maisoncelles"
    ],
    "name:nds_x_preferred":[
        "Maisoncelles"
    ],
    "name:nld_x_preferred":[
        "Maisoncelles"
    ],
    "name:pol_x_preferred":[
        "Maisoncelles"
    ],
    "name:por_x_preferred":[
        "Maisoncelles"
    ],
    "name:rus_x_preferred":[
        "\u041c\u0435\u0437\u043e\u043d\u0441\u0435\u043b\u044c"
    ],
    "name:slk_x_preferred":[
        "Maisoncelles"
    ],
    "name:spa_x_preferred":[
        "Maisoncelles"
    ],
    "name:swe_x_preferred":[
        "Maisoncelles"
    ],
    "name:ukr_x_preferred":[
        "\u041c\u0435\u0437\u043e\u043d\u0441\u0435\u043b\u044c"
    ],
    "name:und_x_variant":[
        "Maisoncelle"
    ],
    "wof:name":"Maisoncelles",
    "wof:placetype":"locality"
},
  "geometry": {"coordinates":[2.37744,48.25409000000001],"type":"Point"}
}