{
  "type": "Feature",
  "properties": {
    "gn:admin1_code":"84",
    "gn:admin2_code":"03",
    "gn:admin3_code":"031",
    "gn:admin4_code":"03106",
    "gn:asciiname":"Durdat",
    "gn:country_code":"FR",
    "gn:dem":471,
    "gn:feature_class":"P",
    "gn:feature_code":"PPL",
    "gn:name":"Durdat",
    "gn:population":0,
    "gn:timezone":"Europe/Paris",
    "iso:country":"FR",
    "wof:name":"Durdat",
    "wof:placetype":"locality"
},
  "geometry": {"coordinates":[2.67953,46.26161],"type":"Point"}
}