{
  "type": "Feature",
  "properties": {
    "gn:admin1_code":"75",
    "gn:admin2_code":"24",
    "gn:admin3_code":"243",
    "gn:admin4_code":"24021",
    "gn:asciiname":"Le Monteil",
    "gn:country_code":"FR",
    "gn:dem":291,
    "gn:feature_class":"P",
    "gn:feature_code":"PPL",
    "gn:name":"Le Monteil",
    "gn:population":0,
    "gn:timezone":"Europe/Paris",
    "iso:country":"FR",
    "wof:name":"Le Monteil",
    "wof:placetype":"locality"
},
  "geometry": {"coordinates":[1.1842,45.23156],"type":"Point"}
}