{
  "type": "Feature",
  "properties": {
    "gn:admin1_code":"52",
    "gn:admin2_code":"44",
    "gn:admin3_code":"441",
    "gn:admin4_code":"44128",
    "gn:asciiname":"Trelan",
    "gn:country_code":"FR",
    "gn:dem":43,
    "gn:feature_class":"P",
    "gn:feature_code":"PPL",
    "gn:name":"Trelan",
    "gn:population":0,
    "gn:timezone":"Europe/Paris",
    "iso:country":"FR",
    "name:eus_x_preferred":[
        "Trelan"
    ],
    "wof:name":"Trelan",
    "wof:placetype":"locality"
},
  "geometry": {"coordinates":[-1.80714,47.5601],"type":"Point"}
}