{
  "type": "Feature",
  "properties": {
    "gn:admin1_code":"93",
    "gn:admin2_code":"05",
    "gn:admin3_code":"052",
    "gn:admin4_code":"05184",
    "gn:asciiname":"Plan-de-Vitrolles",
    "gn:country_code":"FR",
    "gn:dem":613,
    "gn:feature_class":"P",
    "gn:feature_code":"PPL",
    "gn:name":"Plan-de-Vitrolles",
    "gn:population":0,
    "gn:timezone":"Europe/Paris",
    "iso:country":"FR",
    "name:und_x_variant":[
        "Le Plan-de-Vitrolles",
        "Plan-de-Vitrolles"
    ],
    "wof:name":"Plan-de-Vitrolles",
    "wof:placetype":"locality"
},
  "geometry": {"coordinates":[5.95397,44.41179],"type":"Point"}
}