{
  "type": "Feature",
  "properties": {
    "gn:admin1_code":"28",
    "gn:admin2_code":"27",
    "gn:admin3_code":"271",
    "gn:admin4_code":"27045",
    "gn:asciiname":"Thierceville",
    "gn:country_code":"FR",
    "gn:dem":63,
    "gn:feature_class":"P",
    "gn:feature_code":"PPL",
    "gn:name":"Thierceville",
    "gn:population":0,
    "gn:timezone":"Europe/Paris",
    "iso:country":"FR",
    "wof:name":"Thierceville",
    "wof:placetype":"locality"
},
  "geometry": {"coordinates":[1.76577,49.33486],"type":"Point"}
}