{
  "type": "Feature",
  "properties": {
    "gn:admin1_code":"44",
    "gn:admin2_code":"57",
    "gn:admin3_code":"574",
    "gn:admin4_code":"57307",
    "gn:asciiname":"Hayes",
    "gn:country_code":"FR",
    "gn:dem":245,
    "gn:feature_class":"P",
    "gn:feature_code":"PPL",
    "gn:name":"Hayes",
    "gn:population":166,
    "gn:timezone":"Europe/Paris",
    "iso:country":"FR",
    "name:cat_x_preferred":[
        "Hayes"
    ],
    "name:ceb_x_preferred":[
        "Hayes"
    ],
    "name:ces_x_preferred":[
        "Hayes"
    ],
    "name:deu_x_preferred":[
        "Hayes"
    ],
    "name:fin_x_preferred":[
        "Hayes"
    ],
    "name:fra_x_preferred":[
        "Hayes"
    ],
    "name:heb_x_preferred":[
        "\u05d4\u05d9\u05d9\u05d6"
    ],
    "name:hin_x_preferred":[
        "\u0939\u0947\u091c\u093c"
    ],
    "name:ita_x_preferred":[
        "Hayes"
    ],
    "name:nld_x_preferred":[
        "Hayes"
    ],
    "name:oci_x_preferred":[
        "Hayes"
    ],
    "name:pol_x_preferred":[
        "Hayes"
    ],
    "name:por_x_preferred":[
        "Hayes"
    ],
    "name:rus_x_preferred":[
        "\u0425\u0435\u0439\u0437"
    ],
    "name:spa_x_preferred":[
        "Hayes"
    ],
    "name:swe_x_preferred":[
        "Hayes"
    ],
    "name:ukr_x_preferred":[
        "\u0413\u0435\u0439\u0437"
    ],
    "name:und_x_variant":[
        "Haye",
        "Hayes"
    ],
    "name:zho_x_preferred":[
        "\u6d77\u8036\u65af"
    ],
    "wof:name":"Hayes",
    "wof:placetype":"locality",
    "wof:population":166
},
  "geometry": {"coordinates":[6.36667,49.16667],"type":"Point"}
}