{
  "type": "Feature",
  "properties": {
    "frgov:code_epci":"200067957",
    "frgov:insee_arr":"9",
    "frgov:insee_com":"57307",
    "frgov:insee_dep":"57",
    "frgov:insee_reg":"44",
    "frgov:nom_com":"Hayes",
    "frgov:nom_com_m":"HAYES",
    "frgov:nom_dep":"MOSELLE",
    "frgov:nom_reg":"GRAND EST",
    "frgov:statut":"Commune simple",
    "gn:admin1_code":"44",
    "gn:admin2_code":"57",
    "gn:admin3_code":"574",
    "gn:admin4_code":"57307",
    "gn:asciiname":"Hayes",
    "gn:country_code":"FR",
    "gn:dem":245,
    "gn:feature_class":"P",
    "gn:feature_code":"PPL",
    "gn:name":"Hayes",
    "gn:population":166,
    "gn:timezone":"Europe/Paris",
    "iso:country":"FR",
    "name:cat_x_preferred":[
        "Hayes"
    ],
    "name:ceb_x_preferred":[
        "Hayes"
    ],
    "name:ces_x_preferred":[
        "Hayes"
    ],
    "name:deu_x_preferred":[
        "Hayes"
    ],
    "name:fin_x_preferred":[
        "Hayes"
    ],
    "name:fra_x_preferred":[
        "Hayes"
    ],
    "name:heb_x_preferred":[
        "\u05d4\u05d9\u05d9\u05d6"
    ],
    "name:hin_x_preferred":[
        "\u0939\u0947\u0938"
    ],
    "name:hin_x_variant":[
        "\u0939\u0947\u091c\u093c"
    ],
    "name:hun_x_preferred":[
        "Hayes"
    ],
    "name:ind_x_preferred":[
        "Hayes"
    ],
    "name:ita_x_preferred":[
        "Hayes"
    ],
    "name:kaz_x_preferred":[
        "\u0415"
    ],
    "name:kor_x_preferred":[
        "\ud5e4\uc774\uc988"
    ],
    "name:nld_x_preferred":[
        "Hayes"
    ],
    "name:oci_x_preferred":[
        "Hayes"
    ],
    "name:pol_x_preferred":[
        "Hayes"
    ],
    "name:por_x_preferred":[
        "Hayes"
    ],
    "name:rus_x_preferred":[
        "\u0425\u0435\u0439\u0437"
    ],
    "name:spa_x_preferred":[
        "Hayes"
    ],
    "name:srp_x_preferred":[
        "\u0415"
    ],
    "name:swe_x_preferred":[
        "Hayes"
    ],
    "name:tur_x_preferred":[
        "Hayes"
    ],
    "name:ukr_x_preferred":[
        "\u0413\u0435\u0439\u0437"
    ],
    "name:ukr_x_variant":[
        "\u0413\u0435\u0439\u0437"
    ],
    "name:und_x_variant":[
        "Haye",
        "Hayes"
    ],
    "name:urd_x_preferred":[
        "\u06c1\u0627\u0626\u06cc\u0633"
    ],
    "name:vie_x_preferred":[
        "S\u00f4ng Hayes"
    ],
    "name:zho_cn_x_preferred":[
        "\u6d77\u8036\u65af\u6cb3"
    ],
    "name:zho_tw_x_preferred":[
        "\u6d77\u4f0a\u65af\u6cb3"
    ],
    "name:zho_x_preferred":[
        "\u6d77\u8036\u65af"
    ],
    "name:zho_x_variant":[
        "\u6d77\u8036\u65af"
    ],
    "qs:a0":"France",
    "qs:a1":"MOSELLE",
    "qs:a1_lc":"57",
    "qs:a1r":"LORRAINE",
    "qs:a1r_lc":"41",
    "qs:a2_lc":"35",
    "qs:a2r_lc":"4",
    "qs:adm0":"France",
    "qs:adm0_a3":"FRA",
    "qs:la":"HAYES",
    "qs:la_lc":"57307",
    "qs:level":"localadmin",
    "qs:type":"Commune simple",
    "wof:coterminous":[
        404404679
    ],
    "wof:name":"Hayes",
    "wof:placetype":"locality",
    "wof:placetype_local":"Commune simple",
    "wof:population":166
},
  "geometry": {"coordinates":[6.36667,49.16667],"type":"Point"}
}