{
  "type": "Feature",
  "properties": {
    "gn:admin1_code":"28",
    "gn:asciiname":"Saint-Leger",
    "gn:country_code":"FR",
    "gn:dem":271,
    "gn:feature_class":"P",
    "gn:feature_code":"PPL",
    "gn:name":"Saint-L\u00e9ger",
    "gn:population":0,
    "gn:timezone":"Europe/Paris",
    "iso:country":"FR",
    "wof:name":"Saint-Leger",
    "wof:placetype":"locality"
},
  "geometry": {"coordinates":[0.83333,48.21667],"type":"Point"}
}