{
  "type": "Feature",
  "properties": {
    "gn:country":"GP",
    "gn:fcode":"ADM4",
    "gn:population":1770,
    "iso:country":"GP",
    "name:ukr_x_preferred":[
        "\u0412\u0454-\u0424\u043e\u0440"
    ],
    "qs:name":"Vieux-Fort",
    "qs:photos_9r":0,
    "qs:photos_sr":0,
    "qs:pop_sr":"3",
    "wof:name":"Vieux-Fort",
    "wof:placetype":"localadmin",
    "wof:population":1770
},
  "geometry": {"coordinates":[-61.68333,15.95],"type":"Point"}
}