{
  "type": "Feature",
  "properties": {
    "iso:country":"FR",
    "name:ceb_x_preferred":[
        "Castres\u2013Mazamet Airport"
    ],
    "name:deu_x_preferred":[
        "Flughafen Castres-Mazamet"
    ],
    "name:eng_x_preferred":[
        "Castres\u2013Mazamet Airport"
    ],
    "name:eng_x_variant":[
        "DCM",
        "LFCK"
    ],
    "name:fas_x_preferred":[
        "\u0641\u0631\u0648\u062f\u06af\u0627\u0647 \u06a9\u0633\u062a\u0631\u2013\u0645\u0627\u0632\u0627\u0645\u062a"
    ],
    "name:fra_x_preferred":[
        "A\u00e9roport de Castres-Mazamet"
    ],
    "name:fra_x_variant":[
        "a\u00e9roport de Castres-Mazamet"
    ],
    "name:hun_x_preferred":[
        "Castres-Mazamet rep\u00fcl\u0151t\u00e9r"
    ],
    "name:jpn_x_preferred":[
        "\u30ab\u30b9\u30c8\u30eb\u30fb\u30de\u30b6\u30e1\u7a7a\u6e2f"
    ],
    "name:msa_x_preferred":[
        "Lapangan Terbang Castres-Mazamet"
    ],
    "name:nld_x_preferred":[
        "A\u00e9roport de Castres-Mazamet"
    ],
    "name:nld_x_variant":[
        "Luchthaven Castres-Mazamet"
    ],
    "name:ron_x_preferred":[
        "Aeroportul Castres\u2013Mazamet"
    ],
    "name:tgk_x_preferred":[
        "\u0424\u0443\u0440\u0443\u0434\u0433\u043e\u04b3\u0438 \u043a\u0441\u0442\u0440\u2013\u043c\u043e\u0437\u043e\u043c\u0442"
    ],
    "name:vie_x_preferred":[
        "S\u00e2n bay Castres-Mazamet"
    ],
    "name:zho_x_preferred":[
        "\u5361\u65af\u7279\u723e-\u99ac\u624e\u9ed8\u6a5f\u5834"
    ],
    "oa:elevation_ft":"788",
    "oa:type":"medium_airport",
    "woe:hierarchy":{
        "country_id":23424819,
        "county_id":12597192,
        "localadmin_id":12664190,
        "planet_id":1,
        "state_id":7153323
    },
    "wof:name":"A\u00e9roport Castres-Mazamet",
    "wof:placetype":"campus"
},
  "geometry": {"coordinates":[2.28918,43.556301],"type":"Point"}
}