{
  "type": "Feature",
  "properties": {
    "gn:admin1_code":"53",
    "gn:admin2_code":"22",
    "gn:admin3_code":"221",
    "gn:admin4_code":"22197",
    "gn:asciiname":"Mordreuc",
    "gn:country_code":"FR",
    "gn:dem":17,
    "gn:feature_class":"P",
    "gn:feature_code":"PPL",
    "gn:name":"Mordreuc",
    "gn:population":0,
    "gn:timezone":"Europe/Paris",
    "iso:country":"FR",
    "wof:name":"Mordreuc",
    "wof:placetype":"locality"
},
  "geometry": {"coordinates":[-1.97582,48.51124],"type":"Point"}
}