{
  "type": "Feature",
  "properties": {
    "gn:admin1_code":"75",
    "gn:admin2_code":"24",
    "gn:admin3_code":"243",
    "gn:admin4_code":"24576",
    "gn:asciiname":"La Denteille",
    "gn:country_code":"FR",
    "gn:dem":209,
    "gn:feature_class":"P",
    "gn:feature_code":"PPL",
    "gn:name":"La Denteille",
    "gn:population":0,
    "gn:timezone":"Europe/Paris",
    "iso:country":"FR",
    "wof:name":"La Denteille",
    "wof:placetype":"locality"
},
  "geometry": {"coordinates":[0.75308,45.00597],"type":"Point"}
}