{
  "type": "Feature",
  "properties": {
    "gn:admin1_code":"75",
    "gn:admin2_code":"33",
    "gn:admin3_code":"332",
    "gn:admin4_code":"33554",
    "gn:asciiname":"Tabernottes",
    "gn:country_code":"FR",
    "gn:dem":70,
    "gn:feature_class":"P",
    "gn:feature_code":"PPL",
    "gn:name":"Tabernottes",
    "gn:population":0,
    "gn:timezone":"Europe/Paris",
    "iso:country":"FR",
    "wof:name":"Tabernottes",
    "wof:placetype":"locality"
},
  "geometry": {"coordinates":[-0.46496,44.87076],"type":"Point"}
}