{
  "type": "Feature",
  "properties": {
    "gn:admin1_code":"76",
    "gn:admin2_code":"48",
    "gn:admin3_code":"482",
    "gn:admin4_code":"48031",
    "gn:asciiname":"Brion",
    "gn:country_code":"FR",
    "gn:dem":1129,
    "gn:feature_class":"P",
    "gn:feature_code":"PPL",
    "gn:name":"Brion",
    "gn:population":117,
    "gn:timezone":"Europe/Paris",
    "iso:country":"FR",
    "wof:name":"Brion",
    "wof:placetype":"locality",
    "wof:population":117
},
  "geometry": {"coordinates":[3.07069,44.75499],"type":"Point"}
}