{
  "type": "Feature",
  "properties": {
    "frgov:code_epci":"200069144",
    "frgov:insee_arr":"2",
    "frgov:insee_com":"48031",
    "frgov:insee_dep":"48",
    "frgov:insee_reg":"76",
    "frgov:nom_com":"Brion",
    "frgov:nom_com_m":"BRION",
    "frgov:nom_dep":"LOZERE",
    "frgov:nom_reg":"OCCITANIE",
    "frgov:statut":"Commune simple",
    "gn:admin1_code":"76",
    "gn:admin2_code":"48",
    "gn:admin3_code":"482",
    "gn:admin4_code":"48031",
    "gn:asciiname":"Brion",
    "gn:country_code":"FR",
    "gn:dem":1129,
    "gn:feature_class":"P",
    "gn:feature_code":"PPL",
    "gn:name":"Brion",
    "gn:population":117,
    "gn:timezone":"Europe/Paris",
    "iso:country":"FR",
    "name:ceb_x_preferred":[
        "Brion"
    ],
    "name:deu_x_preferred":[
        "Brion"
    ],
    "name:fra_x_preferred":[
        "Brion"
    ],
    "name:hun_x_preferred":[
        "Brion"
    ],
    "name:hye_x_preferred":[
        "\u0532\u0580\u056b\u0578\u0576"
    ],
    "name:ita_x_preferred":[
        "Brion"
    ],
    "name:jpn_x_preferred":[
        "\u30d6\u30ea\u30aa\u30f3"
    ],
    "name:kor_x_preferred":[
        "\ube0c\ub9ac\uc639"
    ],
    "name:nds_x_preferred":[
        "Brion"
    ],
    "name:nld_x_preferred":[
        "Brion"
    ],
    "name:oci_x_preferred":[
        "Brion"
    ],
    "name:pms_x_preferred":[
        "Brion"
    ],
    "name:pol_x_preferred":[
        "Brion"
    ],
    "name:por_x_preferred":[
        "Brion"
    ],
    "name:ron_x_preferred":[
        "Brion"
    ],
    "name:rus_x_preferred":[
        "\u0411\u0440\u0438\u043e\u043d"
    ],
    "name:slk_x_preferred":[
        "Brion"
    ],
    "name:srp_x_preferred":[
        "\u0411\u0440\u0438\u043e\u043d"
    ],
    "name:swe_x_preferred":[
        "Brion"
    ],
    "name:ukr_x_preferred":[
        "\u0411\u0440\u0456\u043e\u043d"
    ],
    "name:zho_x_preferred":[
        "\u5e03\u91cc\u7fc1"
    ],
    "qs:a0":"France",
    "qs:a1":"LOZERE",
    "qs:a1_lc":"48",
    "qs:a1r":"LANGUEDOC-ROUSSILLON",
    "qs:a1r_lc":"91",
    "qs:a2_lc":"08",
    "qs:a2r_lc":"2",
    "qs:adm0":"France",
    "qs:adm0_a3":"FRA",
    "qs:la":"BRION",
    "qs:la_lc":"48031",
    "qs:level":"localadmin",
    "qs:type":"Commune simple",
    "wof:coterminous":[
        404411395
    ],
    "wof:name":"Brion",
    "wof:placetype":"locality",
    "wof:placetype_local":"Commune simple",
    "wof:population":117
},
  "geometry": {"coordinates":[3.07069,44.75499],"type":"Point"}
}