{
  "type": "Feature",
  "properties": {
    "gn:admin1_code":"84",
    "gn:admin2_code":"73",
    "gn:admin3_code":"733",
    "gn:admin4_code":"73255",
    "gn:asciiname":"Le Pinay",
    "gn:cc2":"FR",
    "gn:country_code":"FR",
    "gn:dem":1238,
    "gn:feature_class":"P",
    "gn:feature_code":"PPL",
    "gn:name":"Le Pinay",
    "gn:population":0,
    "gn:timezone":"Europe/Paris",
    "iso:country":"FR",
    "name:und_x_variant":[
        "Piney",
        "Le Pinay"
    ],
    "wof:name":"Le Pinay",
    "wof:placetype":"locality"
},
  "geometry": {"coordinates":[6.28333,45.31667],"type":"Point"}
}