{
  "type": "Feature",
  "properties": {
    "gn:admin1_code":"76",
    "gn:admin2_code":"66",
    "gn:admin3_code":"661",
    "gn:admin4_code":"66009",
    "gn:asciiname":"Alzina Rodona",
    "gn:country_code":"FR",
    "gn:dem":250,
    "gn:feature_class":"P",
    "gn:feature_code":"PPL",
    "gn:name":"Alzina Rodona",
    "gn:population":0,
    "gn:timezone":"Europe/Paris",
    "iso:country":"FR",
    "wof:name":"Alzina Rodona",
    "wof:placetype":"locality"
},
  "geometry": {"coordinates":[2.65419,42.46675],"type":"Point"}
}