{
  "type": "Feature",
  "properties": {
    "gn:admin1_code":"11",
    "gn:admin2_code":"95",
    "gn:admin3_code":"952",
    "gn:admin4_code":"95014",
    "gn:asciiname":"Andilly",
    "gn:country_code":"FR",
    "gn:dem":170,
    "gn:feature_class":"P",
    "gn:feature_code":"PPL",
    "gn:name":"Andilly",
    "gn:population":2138,
    "gn:timezone":"Europe/Paris",
    "iso:country":"FR",
    "wof:name":"Andilly",
    "wof:placetype":"locality",
    "wof:population":2138
},
  "geometry": {"coordinates":[2.3024,49.00935],"type":"Point"}
}