{
  "type": "Feature",
  "properties": {
    "gn:admin1_code":"28",
    "gn:admin2_code":"76",
    "gn:admin3_code":"763",
    "gn:admin4_code":"76039",
    "gn:asciiname":"Le Port-Saint-Ouen",
    "gn:country_code":"FR",
    "gn:dem":37,
    "gn:feature_class":"P",
    "gn:feature_code":"PPL",
    "gn:name":"Le Port-Saint-Ouen",
    "gn:population":0,
    "gn:timezone":"Europe/Paris",
    "iso:country":"FR",
    "wof:name":"Le Port-Saint-Ouen",
    "wof:placetype":"locality"
},
  "geometry": {"coordinates":[1.13071,49.35067],"type":"Point"}
}