{
  "type": "Feature",
  "properties": {
    "gn:admin1_code":"28",
    "gn:admin2_code":"50",
    "gn:admin3_code":"504",
    "gn:admin4_code":"50546",
    "gn:asciiname":"Saint-Samson-de-Bonfosse",
    "gn:country_code":"FR",
    "gn:dem":108,
    "gn:feature_class":"P",
    "gn:feature_code":"PPL",
    "gn:name":"Saint-Samson-de-Bonfoss\u00e9",
    "gn:population":741,
    "gn:timezone":"Europe/Paris",
    "iso:country":"FR",
    "name:und_x_variant":[
        "Saint-Samson",
        "Saint-Samson-de-Bonfoss\u00e9"
    ],
    "wof:name":"Saint-Samson-de-Bonfosse",
    "wof:placetype":"locality",
    "wof:population":741
},
  "geometry": {"coordinates":[-1.1285,49.04946],"type":"Point"}
}