{
  "type": "Feature",
  "properties": {
    "gn:gn_country":"FR",
    "gn:gn_fcode":"PPL",
    "gn:gn_pop":0,
    "iso:country":"FR",
    "name:unk_x_variant":[
        "Richard"
    ],
    "qs_pg:aaroncc":"FR",
    "qs_pg:gn_country":"FR",
    "qs_pg:gn_fcode":"PPL",
    "qs_pg:gn_pop":0,
    "qs_pg:name":"Port de Richard",
    "qs_pg:name_adm0":"France",
    "qs_pg:name_adm1":"Aquitaine",
    "qs_pg:photos":56,
    "qs_pg:photos_1k":11,
    "qs_pg:photos_9k":1,
    "qs_pg:photos_9r":2,
    "qs_pg:photos_all":56,
    "qs_pg:photos_sr":2,
    "qs_pg:pop_sr":0,
    "qs_pg:qs_pg_placetype":"locality",
    "qs_pg:qs_pg_placetype_gp":"Town",
    "qs_pg:woe_adm0":23424819,
    "woe:adm0_id":23424819,
    "woe:name_adm0":"France",
    "woe:name_adm1":"Aquitaine",
    "woe:placetype":"Town",
    "wof:name":"Port de Richard",
    "wof:placetype":"neighbourhood"
},
  "geometry": {"coordinates":[-0.92658,45.41712],"type":"Point"}
}