{
  "type": "Feature",
  "properties": {
    "gn:admin1_code":"84",
    "gn:admin2_code":"42",
    "gn:admin3_code":"422",
    "gn:admin4_code":"42254.0",
    "gn:asciiname":"Felines",
    "gn:country_code":"FR",
    "gn:dem":487,
    "gn:feature_class":"P",
    "gn:feature_code":"PPL",
    "gn:name":"F\u00e9lines",
    "gn:population":0,
    "gn:timezone":"Europe/Paris",
    "iso:country":"FR",
    "name:und_x_variant":[
        "F\u00e9line",
        "F\u00e9lines"
    ],
    "wof:name":"Felines",
    "wof:placetype":"locality"
},
  "geometry": {"coordinates":[4.20846,45.84897],"type":"Point"}
}