{
  "type": "Feature",
  "properties": {
    "gn:admin1_code":"75",
    "gn:admin2_code":"19",
    "gn:admin3_code":"192",
    "gn:admin4_code":"19106",
    "gn:asciiname":"Valeix",
    "gn:country_code":"FR",
    "gn:dem":537,
    "gn:feature_class":"P",
    "gn:feature_code":"PPL",
    "gn:name":"Valeix",
    "gn:population":0,
    "gn:timezone":"Europe/Paris",
    "iso:country":"FR",
    "wof:name":"Valeix",
    "wof:placetype":"locality"
},
  "geometry": {"coordinates":[2.15,45.31667],"type":"Point"}
}