{
  "type": "Feature",
  "properties": {
    "gn:admin1_code":"75",
    "gn:admin2_code":"24",
    "gn:admin3_code":"243",
    "gn:admin4_code":"24241",
    "gn:asciiname":"Cournazac",
    "gn:country_code":"FR",
    "gn:dem":247,
    "gn:feature_class":"P",
    "gn:feature_code":"PPL",
    "gn:name":"Cournazac",
    "gn:population":0,
    "gn:timezone":"Europe/Paris",
    "iso:country":"FR",
    "wof:name":"Cournazac",
    "wof:placetype":"locality"
},
  "geometry": {"coordinates":[0.97296,45.14201],"type":"Point"}
}