{
  "type": "Feature",
  "properties": {
    "gn:admin1_code":"24",
    "gn:admin2_code":"18",
    "gn:admin3_code":"182",
    "gn:admin4_code":"18052",
    "gn:asciiname":"La Mignardise",
    "gn:country_code":"FR",
    "gn:dem":183,
    "gn:feature_class":"P",
    "gn:feature_code":"PPL",
    "gn:name":"La Mignardise",
    "gn:population":0,
    "gn:timezone":"Europe/Paris",
    "iso:country":"FR",
    "wof:name":"La Mignardise",
    "wof:placetype":"locality"
},
  "geometry": {"coordinates":[2.67218,46.73906],"type":"Point"}
}