{
  "type": "Feature",
  "properties": {
    "gn:admin1_code":"27",
    "gn:admin2_code":"21",
    "gn:admin3_code":"213",
    "gn:admin4_code":"21205",
    "gn:asciiname":"Ruffey",
    "gn:country_code":"FR",
    "gn:dem":374,
    "gn:feature_class":"P",
    "gn:feature_code":"PPL",
    "gn:name":"Ruffey",
    "gn:population":0,
    "gn:timezone":"Europe/Paris",
    "iso:country":"FR",
    "wof:name":"Ruffey",
    "wof:placetype":"locality"
},
  "geometry": {"coordinates":[4.2806,47.44261],"type":"Point"}
}