{
  "type": "Feature",
  "properties": {
    "gn:admin1_code":"84",
    "gn:admin2_code":"63",
    "gn:admin3_code":"633",
    "gn:admin4_code":"63006",
    "gn:asciiname":"Apcher",
    "gn:country_code":"FR",
    "gn:dem":1177,
    "gn:feature_class":"P",
    "gn:feature_code":"PPL",
    "gn:name":"Apcher",
    "gn:population":0,
    "gn:timezone":"Europe/Paris",
    "iso:country":"FR",
    "wof:name":"Apcher",
    "wof:placetype":"locality"
},
  "geometry": {"coordinates":[3.02841,45.31605],"type":"Point"}
}