{
  "type": "Feature",
  "properties": {
    "gn:admin1_code":"44",
    "gn:admin2_code":"51",
    "gn:admin3_code":"514",
    "gn:admin4_code":"51277",
    "gn:asciiname":"Blaise-sous-Hauteville",
    "gn:country_code":"FR",
    "gn:dem":120,
    "gn:feature_class":"P",
    "gn:feature_code":"PPL",
    "gn:name":"Blaise-sous-Hauteville",
    "gn:population":0,
    "gn:timezone":"Europe/Paris",
    "iso:country":"FR",
    "name:und_x_variant":[
        "Blaise",
        "Blaise-sous-Hauteville"
    ],
    "wof:name":"Blaise-sous-Hauteville",
    "wof:placetype":"locality"
},
  "geometry": {"coordinates":[4.77835,48.61985],"type":"Point"}
}