{
  "type": "Feature",
  "properties": {
    "gn:admin1_code":"28",
    "gn:admin2_code":"27",
    "gn:admin3_code":"271",
    "gn:admin4_code":"27016.0",
    "gn:asciiname":"La Baguelande",
    "gn:country_code":"FR",
    "gn:dem":151,
    "gn:feature_class":"P",
    "gn:feature_code":"PPL",
    "gn:name":"La Baguelande",
    "gn:population":0,
    "gn:timezone":"Europe/Paris",
    "iso:country":"FR",
    "name:und_x_variant":[
        "la Banguelande",
        "La Baguelande"
    ],
    "wof:name":"La Baguelande",
    "wof:placetype":"locality"
},
  "geometry": {"coordinates":[1.43237,49.2187],"type":"Point"}
}