{
  "type": "Feature",
  "properties": {
    "gn:admin1_code":"28",
    "gn:admin2_code":"14",
    "gn:admin3_code":"141",
    "gn:admin4_code":"14377",
    "gn:asciiname":"Fontenailles",
    "gn:country_code":"FR",
    "gn:dem":60,
    "gn:feature_class":"P",
    "gn:feature_code":"PPL",
    "gn:name":"Fontenailles",
    "gn:population":0,
    "gn:timezone":"Europe/Paris",
    "iso:country":"FR",
    "name:ceb_x_preferred":[
        "Fontenailles"
    ],
    "name:deu_x_preferred":[
        "Fontenailles"
    ],
    "name:fra_x_preferred":[
        "Fontenailles"
    ],
    "name:ita_x_preferred":[
        "Fontenailles"
    ],
    "name:nds_x_preferred":[
        "Fontenailles"
    ],
    "name:nld_x_preferred":[
        "Fontenailles"
    ],
    "name:oci_x_preferred":[
        "Fontenailles"
    ],
    "name:pms_x_preferred":[
        "Fontenailles"
    ],
    "name:pol_x_preferred":[
        "Fontenailles"
    ],
    "name:por_x_preferred":[
        "Fontenailles"
    ],
    "name:slk_x_preferred":[
        "Fontenailles"
    ],
    "name:spa_x_preferred":[
        "Fontenailles"
    ],
    "name:srp_x_preferred":[
        "\u0424\u043e\u043d\u0442\u0435\u043d\u0430\u0458"
    ],
    "name:swe_x_preferred":[
        "Fontenailles"
    ],
    "name:ukr_x_preferred":[
        "\u0424\u043e\u043d\u0442\u0435\u043d\u0430\u0439"
    ],
    "name:zho_x_preferred":[
        "\u4e30\u7279\u7eb3\u8036"
    ],
    "wof:name":"Fontenailles",
    "wof:placetype":"locality"
},
  "geometry": {"coordinates":[-0.68,49.32958],"type":"Point"}
}