{
  "type": "Feature",
  "properties": {
    "gn:admin1_code":"24",
    "gn:admin2_code":"45",
    "gn:admin3_code":"452",
    "gn:admin4_code":"45171",
    "gn:asciiname":"La Picaudiere",
    "gn:country_code":"FR",
    "gn:dem":146,
    "gn:feature_class":"P",
    "gn:feature_code":"PPL",
    "gn:name":"La Picaudi\u00e8re",
    "gn:population":0,
    "gn:timezone":"Europe/Paris",
    "iso:country":"FR",
    "wof:name":"La Picaudiere",
    "wof:placetype":"locality"
},
  "geometry": {"coordinates":[2.26714,47.64705],"type":"Point"}
}