{
  "type": "Feature",
  "properties": {
    "gn:admin1_code":"27",
    "gn:admin2_code":"58",
    "gn:admin3_code":"583",
    "gn:admin4_code":"58303",
    "gn:asciiname":"Varennes-les-Nevers",
    "gn:country_code":"FR",
    "gn:dem":201,
    "gn:feature_class":"P",
    "gn:feature_code":"PPL",
    "gn:name":"Varennes-l\u00e8s-Nevers",
    "gn:population":0,
    "gn:timezone":"Europe/Paris",
    "iso:country":"FR",
    "name:und_x_variant":[
        "Varennes",
        "Varennes-l\u00e8s-Nevers"
    ],
    "wof:name":"Varennes-les-Nevers",
    "wof:placetype":"locality"
},
  "geometry": {"coordinates":[3.13837,47.05075],"type":"Point"}
}