{
  "type": "Feature",
  "properties": {
    "gn:admin1_code":"75",
    "gn:admin2_code":"24",
    "gn:admin3_code":"244",
    "gn:admin4_code":"24587",
    "gn:asciiname":"Vitrac",
    "gn:country_code":"FR",
    "gn:dem":104,
    "gn:feature_class":"P",
    "gn:feature_code":"PPL",
    "gn:name":"Vitrac",
    "gn:population":807,
    "gn:timezone":"Europe/Paris",
    "iso:country":"FR",
    "wof:name":"Vitrac",
    "wof:placetype":"locality",
    "wof:population":807
},
  "geometry": {"coordinates":[1.25,44.83333],"type":"Point"}
}