{
  "type": "Feature",
  "properties": {
    "gn:admin1_code":"27",
    "gn:admin2_code":"58",
    "gn:admin3_code":"583",
    "gn:admin4_code":"58204",
    "gn:asciiname":"Cognan",
    "gn:country_code":"FR",
    "gn:dem":252,
    "gn:feature_class":"P",
    "gn:feature_code":"PPL",
    "gn:name":"Cognan",
    "gn:population":0,
    "gn:timezone":"Europe/Paris",
    "iso:country":"FR",
    "wof:name":"Cognan",
    "wof:placetype":"locality"
},
  "geometry": {"coordinates":[3.32428,47.05076],"type":"Point"}
}