{
  "type": "Feature",
  "properties": {
    "gn:admin1_code":"44",
    "gn:admin2_code":"55",
    "gn:admin3_code":"553",
    "gn:admin4_code":"55117",
    "gn:asciiname":"Jubecourt",
    "gn:country_code":"FR",
    "gn:dem":228,
    "gn:feature_class":"P",
    "gn:feature_code":"PPL",
    "gn:name":"Jub\u00e9court",
    "gn:population":0,
    "gn:timezone":"Europe/Paris",
    "iso:country":"FR",
    "name:und_x_variant":[
        "Jub\u00e9s",
        "Jub\u00e9court"
    ],
    "wof:name":"Jubecourt",
    "wof:placetype":"locality"
},
  "geometry": {"coordinates":[5.16431,49.0922],"type":"Point"}
}