{
  "type": "Feature",
  "properties": {
    "gn:admin1_code":"94",
    "gn:admin2_code":"2B",
    "gn:admin3_code":"2B3",
    "gn:admin4_code":"2B063",
    "gn:asciiname":"Carcheto-Brustico",
    "gn:country_code":"FR",
    "gn:dem":629,
    "gn:feature_class":"P",
    "gn:feature_code":"PPL",
    "gn:name":"Carcheto-Brustico",
    "gn:population":0,
    "gn:timezone":"Europe/Paris",
    "iso:country":"FR",
    "wof:name":"Carcheto-Brustico",
    "wof:placetype":"locality"
},
  "geometry": {"coordinates":[9.36667,42.36667],"type":"Point"}
}