{
  "type": "Feature",
  "properties": {
    "gn:admin1_code":"94",
    "gn:admin2_code":"2B",
    "gn:admin3_code":"2B3",
    "gn:admin4_code":"2B063",
    "gn:asciiname":"Carcheto-Brustico",
    "gn:country_code":"FR",
    "gn:dem":629,
    "gn:feature_class":"P",
    "gn:feature_code":"PPL",
    "gn:name":"Carcheto-Brustico",
    "gn:population":0,
    "gn:timezone":"Europe/Paris",
    "iso:country":"FR",
    "name:cat_x_preferred":[
        "Carcheto-Brustico"
    ],
    "name:ceb_x_preferred":[
        "Carcheto-Brustico"
    ],
    "name:deu_x_preferred":[
        "Carcheto-Brustico"
    ],
    "name:eus_x_preferred":[
        "Carcheto-Brustico"
    ],
    "name:fra_x_preferred":[
        "Carcheto-Brustico"
    ],
    "name:hun_x_preferred":[
        "Carcheto-Brustico"
    ],
    "name:ita_x_preferred":[
        "Carcheto Brustico"
    ],
    "name:kaz_x_preferred":[
        "\u041a\u0430\u0440\u043a\u0435\u0442\u043e-\u0411\u0440\u0443\u0441\u0442\u0438\u043a\u043e"
    ],
    "name:lat_x_preferred":[
        "Carcheto-Brustico"
    ],
    "name:lmo_x_preferred":[
        "Carcheto-Brustico"
    ],
    "name:msa_x_preferred":[
        "Carcheto-Brustico"
    ],
    "name:nld_x_preferred":[
        "Carcheto-Brustico"
    ],
    "name:oci_x_preferred":[
        "Carcheto-Brustico"
    ],
    "name:pol_x_preferred":[
        "Carcheto-Brustico"
    ],
    "name:por_x_preferred":[
        "Carcheto-Brustico"
    ],
    "name:rus_x_preferred":[
        "\u041a\u0430\u0440\u043a\u0435\u0442\u043e-\u0411\u0440\u0443\u0441\u0442\u0438\u043a\u043e"
    ],
    "name:slk_x_preferred":[
        "Carcheto-Brustico"
    ],
    "name:slv_x_preferred":[
        "Carcheto-Brustico"
    ],
    "name:spa_x_preferred":[
        "Carcheto-Brustico"
    ],
    "name:srp_x_preferred":[
        "\u041a\u0430\u0440\u043a\u0435\u0442\u043e-\u0411\u0440\u0443\u0441\u0442\u0438\u043a\u043e"
    ],
    "name:swe_x_preferred":[
        "Carcheto-Brustico"
    ],
    "name:ukr_x_preferred":[
        "\u041a\u0430\u0440\u043a\u0435\u0442\u043e-\u0411\u0440\u0443\u0441\u0442\u0456\u043a\u043e"
    ],
    "name:vie_x_preferred":[
        "Carcheto-Brustico"
    ],
    "name:vol_x_preferred":[
        "Carcheto-Brustico"
    ],
    "name:war_x_preferred":[
        "Carcheto-Brustico"
    ],
    "wof:name":"Carcheto-Brustico",
    "wof:placetype":"locality"
},
  "geometry": {"coordinates":[9.36667,42.36667],"type":"Point"}
}