{
  "type": "Feature",
  "properties": {
    "gn:admin1_code":"76",
    "gn:admin2_code":"46",
    "gn:admin3_code":"461",
    "gn:admin4_code":"46001",
    "gn:asciiname":"La Riviere Basse",
    "gn:country_code":"FR",
    "gn:dem":122,
    "gn:feature_class":"P",
    "gn:feature_code":"PPL",
    "gn:name":"La Rivi\u00e8re Basse",
    "gn:population":0,
    "gn:timezone":"Europe/Paris",
    "iso:country":"FR",
    "wof:name":"La Riviere Basse",
    "wof:placetype":"locality"
},
  "geometry": {"coordinates":[1.22653,44.48253],"type":"Point"}
}