{
  "type": "Feature",
  "properties": {
    "gn:admin1_code":"27",
    "gn:admin2_code":"89",
    "gn:admin3_code":"892",
    "gn:admin4_code":"89333.0",
    "gn:asciiname":"Chevannes",
    "gn:country_code":"FR",
    "gn:dem":276,
    "gn:feature_class":"P",
    "gn:feature_code":"PPL",
    "gn:name":"Chevannes",
    "gn:population":0,
    "gn:timezone":"Europe/Paris",
    "iso:country":"FR",
    "name:ceb_x_preferred":[
        "Chevannes"
    ],
    "name:ces_x_preferred":[
        "Chevannes"
    ],
    "name:deu_x_preferred":[
        "Chevannes"
    ],
    "name:fra_x_preferred":[
        "Chevannes"
    ],
    "name:ita_x_preferred":[
        "Chevannes"
    ],
    "name:nds_x_preferred":[
        "Chevannes"
    ],
    "name:nld_x_preferred":[
        "Chevannes"
    ],
    "name:pms_x_preferred":[
        "Chevannes"
    ],
    "name:pol_x_preferred":[
        "Chevannes"
    ],
    "name:por_x_preferred":[
        "Chevannes"
    ],
    "name:slk_x_preferred":[
        "Chevannes"
    ],
    "name:spa_x_preferred":[
        "Chevannes"
    ],
    "name:srp_x_preferred":[
        "\u0428\u0435\u0432\u0430\u043d"
    ],
    "name:swe_x_preferred":[
        "Chevannes"
    ],
    "name:ukr_x_preferred":[
        "\u0428\u0435\u0432\u0430\u043d\u043d"
    ],
    "wof:name":"Chevannes",
    "wof:placetype":"locality"
},
  "geometry": {"coordinates":[4.08214,47.4775],"type":"Point"}
}