{
  "type": "Feature",
  "properties": {
    "gn:admin1_code":"27",
    "gn:admin2_code":"89",
    "gn:admin3_code":"892",
    "gn:admin4_code":"89333.0",
    "gn:asciiname":"Chevannes",
    "gn:country_code":"FR",
    "gn:dem":276,
    "gn:feature_class":"P",
    "gn:feature_code":"PPL",
    "gn:name":"Chevannes",
    "gn:population":0,
    "gn:timezone":"Europe/Paris",
    "iso:country":"FR",
    "wof:name":"Chevannes",
    "wof:placetype":"locality"
},
  "geometry": {"coordinates":[4.08214,47.4775],"type":"Point"}
}