{
  "type": "Feature",
  "properties": {
    "gn:admin1_code":"84",
    "gn:admin2_code":"73",
    "gn:admin3_code":"733",
    "gn:admin4_code":"73290",
    "gn:asciiname":"Le Rivet",
    "gn:country_code":"FR",
    "gn:dem":2033,
    "gn:feature_class":"P",
    "gn:feature_code":"PPL",
    "gn:name":"Le Rivet",
    "gn:population":0,
    "gn:timezone":"Europe/Paris",
    "iso:country":"FR",
    "wof:name":"Le Rivet",
    "wof:placetype":"locality"
},
  "geometry": {"coordinates":[6.89593,45.22785],"type":"Point"}
}