{
  "type": "Feature",
  "properties": {
    "gn:admin1_code":"27",
    "gn:admin2_code":"39",
    "gn:admin3_code":"391",
    "gn:admin4_code":"39233",
    "gn:asciiname":"Foucherans",
    "gn:country_code":"FR",
    "gn:dem":209,
    "gn:feature_class":"P",
    "gn:feature_code":"PPL",
    "gn:name":"Foucherans",
    "gn:population":1827,
    "gn:timezone":"Europe/Paris",
    "iso:country":"FR",
    "wof:name":"Foucherans",
    "wof:placetype":"locality",
    "wof:population":1827
},
  "geometry": {"coordinates":[5.45503,47.08094000000001],"type":"Point"}
}