{
  "type": "Feature",
  "properties": {
    "iso:country":"FR",
    "name:deu_x_preferred":[
        "Roquette"
    ],
    "name:fra_x_preferred":[
        "Roquette"
    ],
    "name:nds_x_preferred":[
        "Roquette"
    ],
    "wof:name":"Roquette",
    "wof:placetype":"neighbourhood"
},
  "geometry": {"coordinates":[2.380359,48.857209],"type":"Point"}
}