{
  "type": "Feature",
  "properties": {
    "gn:admin1_code":"52",
    "gn:admin2_code":"44",
    "gn:admin3_code":"442",
    "gn:admin4_code":"44035",
    "gn:asciiname":"La Haie",
    "gn:country_code":"FR",
    "gn:dem":16,
    "gn:feature_class":"P",
    "gn:feature_code":"PPL",
    "gn:name":"La Haie",
    "gn:population":0,
    "gn:timezone":"Europe/Paris",
    "iso:country":"FR",
    "name:ceb_x_preferred":[
        "La Haie"
    ],
    "name:swe_x_preferred":[
        "La Haie"
    ],
    "wof:name":"La Haie",
    "wof:placetype":"locality"
},
  "geometry": {"coordinates":[-1.54524,47.28976],"type":"Point"}
}