{
  "type": "Feature",
  "properties": {
    "gn:admin1_code":"75",
    "gn:admin2_code":"23",
    "gn:admin3_code":"231",
    "gn:admin4_code":"23017",
    "gn:asciiname":"Dimpoux",
    "gn:country_code":"FR",
    "gn:dem":773,
    "gn:feature_class":"P",
    "gn:feature_code":"PPL",
    "gn:name":"Dimpoux",
    "gn:population":0,
    "gn:timezone":"Europe/Paris",
    "iso:country":"FR",
    "wof:name":"Dimpoux",
    "wof:placetype":"locality"
},
  "geometry": {"coordinates":[2.39678,45.84582],"type":"Point"}
}