{
  "type": "Feature",
  "properties": {
    "gn:admin1_code":"75",
    "gn:admin2_code":"47",
    "gn:admin3_code":"473",
    "gn:admin4_code":"47096",
    "gn:asciiname":"Saint-Martin",
    "gn:country_code":"FR",
    "gn:dem":85,
    "gn:feature_class":"P",
    "gn:feature_code":"PPL",
    "gn:name":"Saint-Martin",
    "gn:population":0,
    "gn:timezone":"Europe/Paris",
    "iso:country":"FR",
    "wof:name":"Saint-Martin",
    "wof:placetype":"locality"
},
  "geometry": {"coordinates":[0.65,44.63333],"type":"Point"}
}