{
  "type": "Feature",
  "properties": {
    "gn:admin1_code":"32",
    "gn:admin2_code":"62",
    "gn:admin3_code":"623",
    "gn:admin4_code":"62653",
    "gn:asciiname":"Souverain-Moulin",
    "gn:country_code":"FR",
    "gn:dem":60,
    "gn:feature_class":"P",
    "gn:feature_code":"PPL",
    "gn:name":"Souverain-Moulin",
    "gn:population":0,
    "gn:timezone":"Europe/Paris",
    "iso:country":"FR",
    "wof:name":"Souverain-Moulin",
    "wof:placetype":"locality"
},
  "geometry": {"coordinates":[1.68333,50.75],"type":"Point"}
}