{
  "type": "Feature",
  "properties": {
    "gn:admin1_code":"11",
    "gn:admin2_code":"77",
    "gn:admin3_code":"773",
    "gn:admin4_code":"77109",
    "gn:asciiname":"La Croix de Chenoise",
    "gn:country_code":"FR",
    "gn:dem":145,
    "gn:feature_class":"P",
    "gn:feature_code":"PPL",
    "gn:name":"La Croix de Chenoise",
    "gn:population":0,
    "gn:timezone":"Europe/Paris",
    "iso:country":"FR",
    "name:und_x_variant":[
        "La Croix",
        "La Croix de Chenoise"
    ],
    "wof:name":"La Croix de Chenoise",
    "wof:placetype":"locality"
},
  "geometry": {"coordinates":[3.17974,48.61339],"type":"Point"}
}