{
  "type": "Feature",
  "properties": {
    "gn:admin1_code":"84",
    "gn:admin2_code":"63",
    "gn:admin3_code":"634",
    "gn:admin4_code":"63171",
    "gn:asciiname":"Le Reverdel",
    "gn:country_code":"FR",
    "gn:dem":740,
    "gn:feature_class":"P",
    "gn:feature_code":"PPL",
    "gn:name":"Le Reverdel",
    "gn:population":0,
    "gn:timezone":"Europe/Paris",
    "iso:country":"FR",
    "wof:name":"Le Reverdel",
    "wof:placetype":"locality"
},
  "geometry": {"coordinates":[2.77433,46.08922000000001],"type":"Point"}
}