{
  "type": "Feature",
  "properties": {
    "gn:admin1_code":"53",
    "gn:admin2_code":"22",
    "gn:admin3_code":"224",
    "gn:admin4_code":"22214",
    "gn:asciiname":"Port Lazo",
    "gn:country_code":"FR",
    "gn:dem":33,
    "gn:feature_class":"P",
    "gn:feature_code":"PPL",
    "gn:name":"Port Lazo",
    "gn:population":0,
    "gn:timezone":"Europe/Paris",
    "iso:country":"FR",
    "wof:name":"Port Lazo",
    "wof:placetype":"locality"
},
  "geometry": {"coordinates":[-2.96034,48.76267],"type":"Point"}
}