{
  "type": "Feature",
  "properties": {
    "iso:country":"FR",
    "name:eng_x_preferred":[
        "Gares"
    ],
    "name:fra_x_preferred":[
        "Gares"
    ],
    "wof:name":"Gares",
    "wof:placetype":"neighbourhood"
},
  "geometry": {"coordinates":[3.88256890049698,43.60443353406735],"type":"Point"}
}