{
  "type": "Feature",
  "properties": {
    "iso:country":"FR",
    "name:eng_x_preferred":[
        "Rion-des-Landes Airport"
    ],
    "name:eng_x_variant":[
        "LFIL"
    ],
    "oa:elevation_ft":"256",
    "oa:type":"small_airport",
    "woe:hierarchy":{
        "country_id":23424819,
        "county_id":12597149,
        "localadmin_id":12651310,
        "planet_id":1,
        "state_id":7153309
    },
    "wof:name":"A\u00e9rodrome de Rion-des-landes",
    "wof:placetype":"campus"
},
  "geometry": {"coordinates":[-0.94917,43.9158],"type":"Point"}
}