{
  "type": "Feature",
  "properties": {
    "gn:admin1_code":"24",
    "gn:admin2_code":"18",
    "gn:admin3_code":"182",
    "gn:admin4_code":"18057",
    "gn:asciiname":"Beau Merle",
    "gn:country_code":"FR",
    "gn:dem":306,
    "gn:feature_class":"P",
    "gn:feature_code":"PPL",
    "gn:name":"Beau Merle",
    "gn:population":0,
    "gn:timezone":"Europe/Paris",
    "iso:country":"FR",
    "wof:name":"Beau Merle",
    "wof:placetype":"locality"
},
  "geometry": {"coordinates":[2.19409,46.53438],"type":"Point"}
}