{
  "type": "Feature",
  "properties": {
    "gn:admin1_code":"76",
    "gn:admin2_code":"65",
    "gn:admin3_code":"652",
    "gn:admin4_code":"65092",
    "gn:asciiname":"Jumet",
    "gn:country_code":"FR",
    "gn:dem":850,
    "gn:feature_class":"P",
    "gn:feature_code":"PPL",
    "gn:name":"Jumet",
    "gn:population":0,
    "gn:timezone":"Europe/Paris",
    "iso:country":"FR",
    "wof:name":"Jumet",
    "wof:placetype":"locality"
},
  "geometry": {"coordinates":[0.36803,42.94547],"type":"Point"}
}