{
  "type": "Feature",
  "properties": {
    "gn:admin1_code":"76",
    "gn:admin2_code":"65",
    "gn:admin3_code":"652",
    "gn:admin4_code":"65092",
    "gn:asciiname":"Jumet",
    "gn:country_code":"FR",
    "gn:dem":850,
    "gn:feature_class":"P",
    "gn:feature_code":"PPL",
    "gn:name":"Jumet",
    "gn:population":0,
    "gn:timezone":"Europe/Paris",
    "iso:country":"FR",
    "name:ceb_x_preferred":[
        "Jumet"
    ],
    "name:fas_x_preferred":[
        "\u0698\u0648\u0645\u062a"
    ],
    "name:fra_x_preferred":[
        "Jumet"
    ],
    "name:hun_x_preferred":[
        "Jumet"
    ],
    "name:nld_x_preferred":[
        "Jumet"
    ],
    "name:swe_x_preferred":[
        "Jumet"
    ],
    "name:wln_x_preferred":[
        "Djumet"
    ],
    "wof:name":"Jumet",
    "wof:placetype":"locality"
},
  "geometry": {"coordinates":[0.36803,42.94547],"type":"Point"}
}