{
  "type": "Feature",
  "properties": {
    "gn:admin1_code":"84",
    "gn:admin2_code":"43",
    "gn:admin3_code":"432",
    "gn:admin4_code":"43039",
    "gn:asciiname":"Les Ceyssoux",
    "gn:country_code":"FR",
    "gn:dem":959,
    "gn:feature_class":"P",
    "gn:feature_code":"PPL",
    "gn:name":"Les Ceyssoux",
    "gn:population":0,
    "gn:timezone":"Europe/Paris",
    "iso:country":"FR",
    "wof:name":"Les Ceyssoux",
    "wof:placetype":"locality"
},
  "geometry": {"coordinates":[3.88469,44.91205],"type":"Point"}
}