{
  "type": "Feature",
  "properties": {
    "gn:admin1_code":"84",
    "gn:admin2_code":"74",
    "gn:admin3_code":"741",
    "gn:admin4_code":"74123",
    "gn:asciiname":"Vercheres",
    "gn:country_code":"FR",
    "gn:dem":622,
    "gn:feature_class":"P",
    "gn:feature_code":"PPL",
    "gn:name":"Verch\u00e8res",
    "gn:population":0,
    "gn:timezone":"Europe/Paris",
    "iso:country":"FR",
    "name:und_x_variant":[
        "Verch\u00e8re",
        "Verch\u00e8res"
    ],
    "wof:name":"Vercheres",
    "wof:placetype":"locality"
},
  "geometry": {"coordinates":[6.30764,45.73831],"type":"Point"}
}