{
  "type": "Feature",
  "properties": {
    "gn:admin1_code":"24",
    "gn:admin2_code":"28",
    "gn:admin3_code":"284",
    "gn:admin4_code":"28331.0",
    "gn:asciiname":"Le Souches",
    "gn:country_code":"FR",
    "gn:dem":259,
    "gn:feature_class":"P",
    "gn:feature_code":"PPL",
    "gn:name":"Le Souches",
    "gn:population":0,
    "gn:timezone":"Europe/Paris",
    "iso:country":"FR",
    "wof:name":"Le Souches",
    "wof:placetype":"locality"
},
  "geometry": {"coordinates":[1.01421,48.3323],"type":"Point"}
}