{
  "type": "Feature",
  "properties": {
    "gn:admin1_code":"84",
    "gn:admin2_code":"63",
    "gn:admin3_code":"633",
    "gn:admin4_code":"63022",
    "gn:asciiname":"La Combelle",
    "gn:country_code":"FR",
    "gn:dem":464,
    "gn:feature_class":"P",
    "gn:feature_code":"PPL",
    "gn:name":"La Combelle",
    "gn:population":0,
    "gn:timezone":"Europe/Paris",
    "iso:country":"FR",
    "wof:name":"La Combelle",
    "wof:placetype":"locality"
},
  "geometry": {"coordinates":[3.30685,45.43965],"type":"Point"}
}