{
  "type": "Feature",
  "properties": {
    "gn:admin1_code":"75",
    "gn:admin2_code":"24",
    "gn:admin3_code":"243",
    "gn:admin4_code":"24550",
    "gn:asciiname":"Chabroulie",
    "gn:country_code":"FR",
    "gn:dem":252,
    "gn:feature_class":"P",
    "gn:feature_code":"PPL",
    "gn:name":"Chabroulie",
    "gn:population":0,
    "gn:timezone":"Europe/Paris",
    "iso:country":"FR",
    "wof:name":"Chabroulie",
    "wof:placetype":"locality"
},
  "geometry": {"coordinates":[1.03817,45.12751],"type":"Point"}
}