{
  "type": "Feature",
  "properties": {
    "gn:admin1_code":"44",
    "gn:admin2_code":"10",
    "gn:admin3_code":"103",
    "gn:admin4_code":"10247",
    "gn:asciiname":"Les Ventes",
    "gn:country_code":"FR",
    "gn:dem":145,
    "gn:feature_class":"P",
    "gn:feature_code":"PPL",
    "gn:name":"Les Ventes",
    "gn:population":0,
    "gn:timezone":"Europe/Paris",
    "iso:country":"FR",
    "name:bug_x_preferred":[
        "Les Ventes"
    ],
    "name:cat_x_preferred":[
        "Les Ventes"
    ],
    "name:ceb_x_preferred":[
        "Les Ventes"
    ],
    "name:deu_x_preferred":[
        "Les Ventes"
    ],
    "name:eus_x_preferred":[
        "Les Ventes"
    ],
    "name:fra_x_preferred":[
        "Les Ventes"
    ],
    "name:hun_x_preferred":[
        "Les Ventes"
    ],
    "name:ind_x_preferred":[
        "Les Ventes"
    ],
    "name:ita_x_preferred":[
        "Les Ventes"
    ],
    "name:kaz_x_preferred":[
        "\u041b\u0435-\u0412\u0430\u043d\u0442"
    ],
    "name:lat_x_preferred":[
        "Les Ventes"
    ],
    "name:mlg_x_preferred":[
        "Les Ventes"
    ],
    "name:msa_x_preferred":[
        "Les Ventes"
    ],
    "name:nld_x_preferred":[
        "Les Ventes"
    ],
    "name:oci_x_preferred":[
        "Les Ventes"
    ],
    "name:pms_x_preferred":[
        "Les Ventes"
    ],
    "name:pol_x_preferred":[
        "Les Ventes"
    ],
    "name:por_x_preferred":[
        "Les Ventes"
    ],
    "name:slk_x_preferred":[
        "Les Ventes"
    ],
    "name:spa_x_preferred":[
        "Les Ventes"
    ],
    "name:swe_x_preferred":[
        "Les Ventes"
    ],
    "name:ukr_x_preferred":[
        "\u041b\u0435-\u0412\u0430\u043d\u0442"
    ],
    "name:vie_x_preferred":[
        "Les Ventes"
    ],
    "name:vol_x_preferred":[
        "Les Ventes"
    ],
    "name:war_x_preferred":[
        "Les Ventes"
    ],
    "name:zho_x_preferred":[
        "\u83b1\u65fa\u7279"
    ],
    "wof:name":"Les Ventes",
    "wof:placetype":"locality"
},
  "geometry": {"coordinates":[3.89776,48.0535],"type":"Point"}
}