{
  "type": "Feature",
  "properties": {
    "gn:admin1_code":"44",
    "gn:admin2_code":"10",
    "gn:admin3_code":"103",
    "gn:admin4_code":"10247",
    "gn:asciiname":"Les Ventes",
    "gn:country_code":"FR",
    "gn:dem":145,
    "gn:feature_class":"P",
    "gn:feature_code":"PPL",
    "gn:name":"Les Ventes",
    "gn:population":0,
    "gn:timezone":"Europe/Paris",
    "iso:country":"FR",
    "wof:name":"Les Ventes",
    "wof:placetype":"locality"
},
  "geometry": {"coordinates":[3.89776,48.0535],"type":"Point"}
}