{
  "type": "Feature",
  "properties": {
    "gn:admin1_code":"75",
    "gn:admin2_code":"24",
    "gn:admin3_code":"241",
    "gn:admin4_code":"24402",
    "gn:asciiname":"Graulet",
    "gn:country_code":"FR",
    "gn:dem":90,
    "gn:feature_class":"P",
    "gn:feature_code":"PPL",
    "gn:name":"Graulet",
    "gn:population":0,
    "gn:timezone":"Europe/Paris",
    "iso:country":"FR",
    "wof:name":"Graulet",
    "wof:placetype":"locality"
},
  "geometry": {"coordinates":[0.3747,44.70786],"type":"Point"}
}