{
  "type": "Feature",
  "properties": {
    "gn:admin1_code":"24",
    "gn:admin2_code":"45",
    "gn:admin3_code":"452",
    "gn:admin4_code":"45270",
    "gn:asciiname":"Les Braudins",
    "gn:country_code":"FR",
    "gn:dem":110,
    "gn:feature_class":"P",
    "gn:feature_code":"PPL",
    "gn:name":"Les Braudins",
    "gn:population":0,
    "gn:timezone":"Europe/Paris",
    "iso:country":"FR",
    "wof:name":"Les Braudins",
    "wof:placetype":"locality"
},
  "geometry": {"coordinates":[2.29638,47.80073],"type":"Point"}
}