{
  "type": "Feature",
  "properties": {
    "gn:admin1_code":"93",
    "gn:admin2_code":"05",
    "gn:admin3_code":"052",
    "gn:admin4_code":"05061",
    "gn:asciiname":"Romette",
    "gn:country_code":"FR",
    "gn:dem":832,
    "gn:feature_class":"P",
    "gn:feature_code":"PPL",
    "gn:name":"Romette",
    "gn:population":0,
    "gn:timezone":"Europe/Paris",
    "iso:country":"FR",
    "wof:name":"Romette",
    "wof:placetype":"locality"
},
  "geometry": {"coordinates":[6.10859,44.57979],"type":"Point"}
}