{
  "type": "Feature",
  "properties": {
    "gn:admin1_code":"93",
    "gn:admin2_code":"13",
    "gn:admin3_code":"133",
    "gn:admin4_code":"13028",
    "gn:asciiname":"Virebelle",
    "gn:country_code":"FR",
    "gn:dem":27,
    "gn:feature_class":"P",
    "gn:feature_code":"PPL",
    "gn:name":"Virebelle",
    "gn:population":0,
    "gn:timezone":"Europe/Paris",
    "iso:country":"FR",
    "wof:name":"Virebelle",
    "wof:placetype":"locality"
},
  "geometry": {"coordinates":[5.60384,43.18488],"type":"Point"}
}