{
  "type": "Feature",
  "properties": {
    "gn:admin1_code":"84",
    "gn:admin2_code":"15",
    "gn:admin3_code":"152",
    "gn:admin4_code":"15243",
    "gn:asciiname":"Chavaroche",
    "gn:country_code":"FR",
    "gn:dem":1006,
    "gn:feature_class":"P",
    "gn:feature_code":"PPL",
    "gn:name":"Chavaroche",
    "gn:population":0,
    "gn:timezone":"Europe/Paris",
    "iso:country":"FR",
    "wof:name":"Chavaroche",
    "wof:placetype":"locality"
},
  "geometry": {"coordinates":[2.55,45.26667],"type":"Point"}
}