{
  "type": "Feature",
  "properties": {
    "gn:admin1_code":"75",
    "gn:admin2_code":"19",
    "gn:admin3_code":"193",
    "gn:admin4_code":"19265",
    "gn:asciiname":"Couffy",
    "gn:country_code":"FR",
    "gn:dem":817,
    "gn:feature_class":"P",
    "gn:feature_code":"PPL",
    "gn:name":"Couffy",
    "gn:population":0,
    "gn:timezone":"Europe/Paris",
    "iso:country":"FR",
    "name:cat_x_preferred":[
        "Couffy"
    ],
    "name:ceb_x_preferred":[
        "Couffy"
    ],
    "name:deu_x_preferred":[
        "Couffy"
    ],
    "name:eus_x_preferred":[
        "Couffy"
    ],
    "name:fra_x_preferred":[
        "Couffy"
    ],
    "name:hun_x_preferred":[
        "Couffy"
    ],
    "name:ita_x_preferred":[
        "Couffy"
    ],
    "name:lat_x_preferred":[
        "Couffy"
    ],
    "name:msa_x_preferred":[
        "Couffy"
    ],
    "name:nld_x_preferred":[
        "Couffy"
    ],
    "name:oci_x_preferred":[
        "Couffy"
    ],
    "name:pms_x_preferred":[
        "Couffy"
    ],
    "name:pol_x_preferred":[
        "Couffy"
    ],
    "name:por_x_preferred":[
        "Couffy"
    ],
    "name:ron_x_preferred":[
        "Couffy"
    ],
    "name:slk_x_preferred":[
        "Couffy"
    ],
    "name:spa_x_preferred":[
        "Couffy"
    ],
    "name:swe_x_preferred":[
        "Couffy"
    ],
    "name:ukr_x_preferred":[
        "\u041a\u0443\u0444\u0444\u0456"
    ],
    "name:uzb_x_preferred":[
        "Couffy"
    ],
    "name:vie_x_preferred":[
        "Couffy"
    ],
    "name:vol_x_preferred":[
        "Couffy"
    ],
    "name:war_x_preferred":[
        "Couffy"
    ],
    "wof:name":"Couffy",
    "wof:placetype":"locality"
},
  "geometry": {"coordinates":[1.99142,45.67202],"type":"Point"}
}