{
  "type": "Feature",
  "properties": {
    "gn:admin1_code":"93",
    "gn:admin2_code":"04",
    "gn:admin3_code":"044",
    "gn:admin4_code":"04234",
    "gn:asciiname":"Urtis",
    "gn:country_code":"FR",
    "gn:dem":1089,
    "gn:feature_class":"P",
    "gn:feature_code":"PPL",
    "gn:name":"Urtis",
    "gn:population":0,
    "gn:timezone":"Europe/Paris",
    "iso:country":"FR",
    "wof:name":"Urtis",
    "wof:placetype":"locality"
},
  "geometry": {"coordinates":[6.07191,44.42952],"type":"Point"}
}