{
  "type": "Feature",
  "properties": {
    "iso:country":"FR",
    "name:deu_x_preferred":[
        "Fives"
    ],
    "name:fra_x_preferred":[
        "Fives"
    ],
    "name:pcd_x_preferred":[
        "Fives"
    ],
    "name:unk_x_variant":[
        "Fives"
    ],
    "name:zho_x_preferred":[
        "\u7246\u624b\u7403"
    ],
    "qs:gn_adm0_cc":"FR",
    "qs:gn_local":2998324,
    "qs:gn_nam_loc":"Lille, Nord, Nord-Pas-de-Calais, FR",
    "qs:gn_namadm1":"B4",
    "qs:local_max":4350,
    "qs:local_sum":8989,
    "qs:localhoods":4,
    "qs:name":"Fives",
    "qs:name_adm0":"France",
    "qs:name_adm1":"Nord-Pas-de-Calais",
    "qs:name_adm2":"Nord",
    "qs:name_lau":"Lezennes",
    "qs:name_local":"Lille",
    "qs:photo_max":446,
    "qs:photo_sum":4350,
    "qs:placetype":"Suburb",
    "qs:quad_count":116,
    "qs:woe_adm0":23424819,
    "qs:woe_adm1":7153324,
    "qs:woe_adm2":12597175,
    "qs:woe_lau":12661240,
    "qs:woe_local":608105,
    "qs:woe_ver":"7.10.0",
    "wd:wordcount":1606,
    "wof:lang":[
        "fre"
    ],
    "wof:name":"Fives",
    "wof:placetype":"neighbourhood"
},
  "geometry": {"coordinates":[3.074897,50.63184],"type":"Point"}
}