{
  "type": "Feature",
  "properties": {
    "gn:admin1_code":"76",
    "gn:admin2_code":"48",
    "gn:admin3_code":"481",
    "gn:admin4_code":"48146",
    "gn:asciiname":"Prades",
    "gn:country_code":"FR",
    "gn:dem":532,
    "gn:feature_class":"P",
    "gn:feature_code":"PPL",
    "gn:name":"Prades",
    "gn:population":0,
    "gn:timezone":"Europe/Paris",
    "iso:country":"FR",
    "name:cat_x_preferred":[
        "Prades"
    ],
    "name:ceb_x_preferred":[
        "Prades"
    ],
    "name:ces_x_preferred":[
        "Prades"
    ],
    "name:deu_x_preferred":[
        "Prades"
    ],
    "name:eus_x_preferred":[
        "Prades"
    ],
    "name:fra_x_preferred":[
        "Prades"
    ],
    "name:glg_x_preferred":[
        "Prades"
    ],
    "name:hun_x_preferred":[
        "Prades"
    ],
    "name:ita_x_preferred":[
        "Prades"
    ],
    "name:lat_x_preferred":[
        "Prades"
    ],
    "name:msa_x_preferred":[
        "Prades"
    ],
    "name:nds_x_preferred":[
        "Prades"
    ],
    "name:nld_x_preferred":[
        "Prades"
    ],
    "name:oci_x_preferred":[
        "Prades"
    ],
    "name:pms_x_preferred":[
        "Prades"
    ],
    "name:pol_x_preferred":[
        "Prades"
    ],
    "name:por_x_preferred":[
        "Prades"
    ],
    "name:ron_x_preferred":[
        "Prades"
    ],
    "name:rus_x_preferred":[
        "\u041f\u0440\u0430\u0434"
    ],
    "name:slk_x_preferred":[
        "Prades"
    ],
    "name:spa_x_preferred":[
        "Prades"
    ],
    "name:swe_x_preferred":[
        "Prades"
    ],
    "name:ukr_x_preferred":[
        "\u041f\u0440\u0430\u0434"
    ],
    "name:vie_x_preferred":[
        "Prades"
    ],
    "name:war_x_preferred":[
        "Prades"
    ],
    "wof:name":"Prades",
    "wof:placetype":"locality"
},
  "geometry": {"coordinates":[3.45811,44.35271],"type":"Point"}
}