{
  "type": "Feature",
  "properties": {
    "gn:admin1_code":"24",
    "gn:admin2_code":"45",
    "gn:admin3_code":"452",
    "gn:admin4_code":"45270",
    "gn:asciiname":"Les Places",
    "gn:country_code":"FR",
    "gn:dem":113,
    "gn:feature_class":"P",
    "gn:feature_code":"PPL",
    "gn:name":"Les Places",
    "gn:population":0,
    "gn:timezone":"Europe/Paris",
    "iso:country":"FR",
    "name:bug_x_preferred":[
        "Les Places"
    ],
    "name:cat_x_preferred":[
        "Les Places"
    ],
    "name:ceb_x_preferred":[
        "Les Places"
    ],
    "name:deu_x_preferred":[
        "Les Places"
    ],
    "name:epo_x_preferred":[
        "Les Places"
    ],
    "name:eus_x_preferred":[
        "Les Places"
    ],
    "name:fas_x_preferred":[
        "\u0644\u0632 \u067e\u0644\u0627\u0633\u0627\u0633"
    ],
    "name:fra_x_preferred":[
        "Les Places"
    ],
    "name:hun_x_preferred":[
        "Les Places"
    ],
    "name:ita_x_preferred":[
        "Les Places"
    ],
    "name:kaz_x_preferred":[
        "\u041b\u0435-\u041f\u043b\u0430\u0441"
    ],
    "name:lat_x_preferred":[
        "Les Places"
    ],
    "name:mlg_x_preferred":[
        "Les Places"
    ],
    "name:msa_x_preferred":[
        "Les Places"
    ],
    "name:nld_x_preferred":[
        "Les Places"
    ],
    "name:oci_x_preferred":[
        "Les Places"
    ],
    "name:pms_x_preferred":[
        "Les Places"
    ],
    "name:pol_x_preferred":[
        "Les Places"
    ],
    "name:por_x_preferred":[
        "Les Places"
    ],
    "name:slk_x_preferred":[
        "Les Places"
    ],
    "name:spa_x_preferred":[
        "Les Places"
    ],
    "name:swe_x_preferred":[
        "Les Places"
    ],
    "name:ukr_x_preferred":[
        "\u041b\u0435-\u041f\u043b\u0430\u0441"
    ],
    "name:vie_x_preferred":[
        "Les Places"
    ],
    "name:vol_x_preferred":[
        "Les Places"
    ],
    "name:war_x_preferred":[
        "Les Places"
    ],
    "name:zho_x_preferred":[
        "\u83b1\u666e\u62c9\u65af"
    ],
    "wof:name":"Les Places",
    "wof:placetype":"locality"
},
  "geometry": {"coordinates":[2.32734,47.79266],"type":"Point"}
}