{
  "type": "Feature",
  "properties": {
    "gn:gn_country":"FR",
    "gn:gn_fcode":"PPL",
    "gn:gn_pop":227,
    "gn:population":227,
    "iso:country":"FR",
    "name:unk_x_variant":[
        "Sainte-Colombe"
    ],
    "qs_pg:aaroncc":"FR",
    "qs_pg:gn_country":"FR",
    "qs_pg:gn_fcode":"PPL",
    "qs_pg:gn_pop":227,
    "qs_pg:name":"Ste.-Colombe-de-Peyre",
    "qs_pg:name_adm0":"France",
    "qs_pg:name_adm1":"Languedoc-Roussillon",
    "qs_pg:photos_9k":1,
    "qs_pg:photos_9r":1,
    "qs_pg:photos_all":1,
    "qs_pg:photos_sr":0,
    "qs_pg:pop_sr":2,
    "qs_pg:qs_pg_placetype":"locality",
    "qs_pg:qs_pg_placetype_gp":"Town",
    "qs_pg:woe_adm0":23424819,
    "woe:adm0_id":23424819,
    "woe:name_adm0":"France",
    "woe:name_adm1":"Languedoc-Roussillon",
    "woe:placetype":"Town",
    "wof:name":"Ste.-Colombe-de-Peyre",
    "wof:placetype":"neighbourhood",
    "wof:population":227
},
  "geometry": {"coordinates":[3.24019,44.69076],"type":"Point"}
}