{
  "type": "Feature",
  "properties": {
    "gn:admin1_code":"24",
    "gn:admin2_code":"18",
    "gn:admin3_code":"181",
    "gn:admin4_code":"18105",
    "gn:asciiname":"Les Chapelles",
    "gn:country_code":"FR",
    "gn:dem":206,
    "gn:feature_class":"P",
    "gn:feature_code":"PPL",
    "gn:name":"Les Chapelles",
    "gn:population":0,
    "gn:timezone":"Europe/Paris",
    "iso:country":"FR",
    "wof:name":"Les Chapelles",
    "wof:placetype":"locality"
},
  "geometry": {"coordinates":[2.76629,47.11581],"type":"Point"}
}