{
  "type": "Feature",
  "properties": {
    "gn:admin1_code":"24",
    "gn:admin2_code":"18",
    "gn:admin3_code":"181",
    "gn:admin4_code":"18105",
    "gn:asciiname":"Les Chapelles",
    "gn:country_code":"FR",
    "gn:dem":206,
    "gn:feature_class":"P",
    "gn:feature_code":"PPL",
    "gn:name":"Les Chapelles",
    "gn:population":0,
    "gn:timezone":"Europe/Paris",
    "iso:country":"FR",
    "name:cat_x_preferred":[
        "Les Chapelles"
    ],
    "name:ceb_x_preferred":[
        "Les Chapelles"
    ],
    "name:deu_x_preferred":[
        "Les Chapelles"
    ],
    "name:eus_x_preferred":[
        "Les Chapelles"
    ],
    "name:fra_x_preferred":[
        "Les Chapelles"
    ],
    "name:hun_x_preferred":[
        "Les Chapelles"
    ],
    "name:ita_x_preferred":[
        "Les Chapelles"
    ],
    "name:lat_x_preferred":[
        "Capellae Centronum"
    ],
    "name:lmo_x_preferred":[
        "Les Chapelles"
    ],
    "name:msa_x_preferred":[
        "Les Chapelles"
    ],
    "name:nld_x_preferred":[
        "Les Chapelles"
    ],
    "name:oci_x_preferred":[
        "Les Chapelles"
    ],
    "name:pol_x_preferred":[
        "Les Chapelles"
    ],
    "name:ron_x_preferred":[
        "Les Chapelles"
    ],
    "name:slk_x_preferred":[
        "Les Chapelles"
    ],
    "name:spa_x_preferred":[
        "Les Chapelles"
    ],
    "name:srp_x_preferred":[
        "\u0428\u0430\u043f\u0435\u043b"
    ],
    "name:swe_x_preferred":[
        "Les Chapelles"
    ],
    "name:ukr_x_preferred":[
        "\u041b\u0435-\u0428\u0430\u043f\u0435\u043b\u044c"
    ],
    "name:uzb_x_preferred":[
        "Les Chapelles"
    ],
    "name:vie_x_preferred":[
        "Les Chapelles"
    ],
    "name:vol_x_preferred":[
        "Les Chapelles"
    ],
    "name:war_x_preferred":[
        "Les Chapelles"
    ],
    "wof:name":"Les Chapelles",
    "wof:placetype":"locality"
},
  "geometry": {"coordinates":[2.76629,47.11581],"type":"Point"}
}