{
  "type": "Feature",
  "properties": {
    "gn:admin1_code":"24",
    "gn:admin2_code":"18",
    "gn:admin3_code":"181",
    "gn:admin4_code":"18239",
    "gn:asciiname":"Les Essards",
    "gn:country_code":"FR",
    "gn:dem":199,
    "gn:feature_class":"P",
    "gn:feature_code":"PPL",
    "gn:name":"Les Essards",
    "gn:population":0,
    "gn:timezone":"Europe/Paris",
    "iso:country":"FR",
    "name:und_x_variant":[
        "Les Essarts",
        "Les Essards"
    ],
    "wof:name":"Les Essards",
    "wof:placetype":"locality"
},
  "geometry": {"coordinates":[2.78257,47.04924000000001],"type":"Point"}
}