{
  "type": "Feature",
  "properties": {
    "gn:admin1_code":"24",
    "gn:admin2_code":"18",
    "gn:admin3_code":"181",
    "gn:admin4_code":"18239",
    "gn:asciiname":"Les Essards",
    "gn:country_code":"FR",
    "gn:dem":199,
    "gn:feature_class":"P",
    "gn:feature_code":"PPL",
    "gn:name":"Les Essards",
    "gn:population":0,
    "gn:timezone":"Europe/Paris",
    "iso:country":"FR",
    "name:cat_x_preferred":[
        "Les Essards"
    ],
    "name:ceb_x_preferred":[
        "Les Essards"
    ],
    "name:deu_x_preferred":[
        "Les Essards"
    ],
    "name:fra_x_preferred":[
        "Les Essards"
    ],
    "name:ita_x_preferred":[
        "Les Essards"
    ],
    "name:nds_x_preferred":[
        "Les Essards"
    ],
    "name:nld_x_preferred":[
        "Les Essards"
    ],
    "name:pol_x_preferred":[
        "Les Essards"
    ],
    "name:por_x_preferred":[
        "Les Essards"
    ],
    "name:rus_x_preferred":[
        "\u041b\u0435\u0437-\u042d\u0441\u0441\u0430\u0440"
    ],
    "name:slk_x_preferred":[
        "Les Essards"
    ],
    "name:spa_x_preferred":[
        "Les Essards"
    ],
    "name:srp_x_preferred":[
        "\u0415\u0441\u0430\u0440"
    ],
    "name:swe_x_preferred":[
        "Les Essards"
    ],
    "name:ukr_x_preferred":[
        "\u041b\u0435\u0437-\u0415\u0441\u0441\u0430\u0440"
    ],
    "name:und_x_variant":[
        "Les Essarts",
        "Les Essards"
    ],
    "wof:name":"Les Essards",
    "wof:placetype":"locality"
},
  "geometry": {"coordinates":[2.78257,47.04924000000001],"type":"Point"}
}