{
  "type": "Feature",
  "properties": {
    "gn:admin1_code":"52",
    "gn:admin2_code":"44",
    "gn:admin3_code":"441",
    "gn:admin4_code":"44214",
    "gn:asciiname":"Le Menil",
    "gn:country_code":"FR",
    "gn:dem":86,
    "gn:feature_class":"P",
    "gn:feature_code":"PPL",
    "gn:name":"Le M\u00e9nil",
    "gn:population":0,
    "gn:timezone":"Europe/Paris",
    "iso:country":"FR",
    "name:und_x_variant":[
        "Menil",
        "Le M\u00e9nil"
    ],
    "wof:name":"Le Menil",
    "wof:placetype":"locality"
},
  "geometry": {"coordinates":[-1.66588,47.56088],"type":"Point"}
}