{
  "type": "Feature",
  "properties": {
    "gn:admin1_code":"24",
    "gn:admin2_code":"36",
    "gn:admin3_code":"363",
    "gn:admin4_code":"36221",
    "gn:asciiname":"Beaudouin",
    "gn:country_code":"FR",
    "gn:dem":247,
    "gn:feature_class":"P",
    "gn:feature_code":"PPL",
    "gn:name":"Beaudouin",
    "gn:population":0,
    "gn:timezone":"Europe/Paris",
    "iso:country":"FR",
    "wof:name":"Beaudouin",
    "wof:placetype":"locality"
},
  "geometry": {"coordinates":[2.08609,46.65],"type":"Point"}
}