{
  "type": "Feature",
  "properties": {
    "gn:admin1_code":"93",
    "gn:admin2_code":"05",
    "gn:admin3_code":"052",
    "gn:admin4_code":"05139",
    "gn:asciiname":"Le Courtil",
    "gn:country_code":"FR",
    "gn:dem":1242,
    "gn:feature_class":"P",
    "gn:feature_code":"PPL",
    "gn:name":"Le Courtil",
    "gn:population":0,
    "gn:timezone":"Europe/Paris",
    "iso:country":"FR",
    "name:und_x_variant":[
        "Le Cortil",
        "Le Courtil"
    ],
    "wof:name":"Le Courtil",
    "wof:placetype":"locality"
},
  "geometry": {"coordinates":[5.92237,44.70646],"type":"Point"}
}