{
  "type": "Feature",
  "properties": {
    "gn:admin1_code":"11",
    "gn:admin2_code":"77",
    "gn:admin3_code":"772",
    "gn:admin4_code":"77381",
    "gn:asciiname":"Les Loges",
    "gn:country_code":"FR",
    "gn:dem":117,
    "gn:feature_class":"P",
    "gn:feature_code":"PPL",
    "gn:name":"Les Loges",
    "gn:population":0,
    "gn:timezone":"Europe/Paris",
    "iso:country":"FR",
    "name:ceb_x_preferred":[
        "Les Loges"
    ],
    "name:deu_x_preferred":[
        "Les Loges"
    ],
    "name:fra_x_preferred":[
        "Les Loges"
    ],
    "name:ind_x_preferred":[
        "Les Loges"
    ],
    "name:ita_x_preferred":[
        "Les Loges"
    ],
    "name:nds_x_preferred":[
        "Les Loges"
    ],
    "name:nld_x_preferred":[
        "Les Loges"
    ],
    "name:pms_x_preferred":[
        "Les Loges"
    ],
    "name:pol_x_preferred":[
        "Les Loges"
    ],
    "name:por_x_preferred":[
        "Les Loges"
    ],
    "name:rus_x_preferred":[
        "\u041b\u0435-\u041b\u043e\u0436"
    ],
    "name:slk_x_preferred":[
        "Les Loges"
    ],
    "name:spa_x_preferred":[
        "Les Loges"
    ],
    "name:swe_x_preferred":[
        "Les Loges"
    ],
    "name:ukr_x_preferred":[
        "\u041b\u0435-\u041b\u043e\u0436"
    ],
    "wof:name":"Les Loges",
    "wof:placetype":"locality"
},
  "geometry": {"coordinates":[2.96948,48.62024],"type":"Point"}
}