{
  "type": "Feature",
  "properties": {
    "gn:admin1_code":"44",
    "gn:admin2_code":"57",
    "gn:admin3_code":"577",
    "gn:admin4_code":"57365",
    "gn:asciiname":"Evendorff",
    "gn:country_code":"FR",
    "gn:dem":312,
    "gn:feature_class":"P",
    "gn:feature_code":"PPL",
    "gn:name":"Evendorff",
    "gn:population":0,
    "gn:timezone":"Europe/Paris",
    "iso:country":"FR",
    "wof:name":"Evendorff",
    "wof:placetype":"locality"
},
  "geometry": {"coordinates":[6.41677,49.41312],"type":"Point"}
}