{
  "type": "Feature",
  "properties": {
    "gn:admin1_code":"75",
    "gn:admin2_code":"24",
    "gn:admin3_code":"243",
    "gn:admin4_code":"24312",
    "gn:asciiname":"Cregandie",
    "gn:country_code":"FR",
    "gn:dem":150,
    "gn:feature_class":"P",
    "gn:feature_code":"PPL",
    "gn:name":"Cr\u00e9gandie",
    "gn:population":0,
    "gn:timezone":"Europe/Paris",
    "iso:country":"FR",
    "wof:name":"Cregandie",
    "wof:placetype":"locality"
},
  "geometry": {"coordinates":[0.71667,45.16667],"type":"Point"}
}