{
  "type": "Feature",
  "properties": {
    "gn:admin1_code":"75",
    "gn:admin2_code":"16",
    "gn:admin3_code":"161",
    "gn:admin4_code":"16323",
    "gn:asciiname":"Le Mas de Baud",
    "gn:country_code":"FR",
    "gn:dem":128,
    "gn:feature_class":"P",
    "gn:feature_code":"PPL",
    "gn:name":"Le Mas de Baud",
    "gn:population":0,
    "gn:timezone":"Europe/Paris",
    "iso:country":"FR",
    "wof:name":"Le Mas de Baud",
    "wof:placetype":"locality"
},
  "geometry": {"coordinates":[0.40663,45.64621],"type":"Point"}
}