{
  "type": "Feature",
  "properties": {
    "gn:admin1_code":"44",
    "gn:admin2_code":"10",
    "gn:admin3_code":"103",
    "gn:admin4_code":"10352",
    "gn:asciiname":"Culoison",
    "gn:country_code":"FR",
    "gn:dem":100,
    "gn:feature_class":"P",
    "gn:feature_code":"PPL",
    "gn:name":"Culoison",
    "gn:population":0,
    "gn:timezone":"Europe/Paris",
    "iso:country":"FR",
    "wof:name":"Culoison",
    "wof:placetype":"locality"
},
  "geometry": {"coordinates":[4.07198,48.33631],"type":"Point"}
}