{
  "type": "Feature",
  "properties": {
    "gn:admin1_code":"24",
    "gn:admin2_code":"45",
    "gn:admin3_code":"451",
    "gn:admin4_code":"45064.0",
    "gn:asciiname":"Bellevue",
    "gn:country_code":"FR",
    "gn:dem":264,
    "gn:feature_class":"P",
    "gn:feature_code":"PPL",
    "gn:name":"Bellevue",
    "gn:population":0,
    "gn:timezone":"Europe/Paris",
    "iso:country":"FR",
    "wof:name":"Bellevue",
    "wof:placetype":"locality"
},
  "geometry": {"coordinates":[2.68333,47.55],"type":"Point"}
}