{
  "type": "Feature",
  "properties": {
    "gn:admin1_code":"75",
    "gn:admin2_code":"16",
    "gn:admin3_code":"163",
    "gn:admin4_code":"16076",
    "gn:asciiname":"Chez Pouvaraud",
    "gn:country_code":"FR",
    "gn:dem":159,
    "gn:feature_class":"P",
    "gn:feature_code":"PPL",
    "gn:name":"Chez Pouvaraud",
    "gn:population":0,
    "gn:timezone":"Europe/Paris",
    "iso:country":"FR",
    "wof:name":"Chez Pouvaraud",
    "wof:placetype":"locality"
},
  "geometry": {"coordinates":[0.39513,45.97096],"type":"Point"}
}