{
  "type": "Feature",
  "properties": {
    "gn:admin1_code":"84",
    "gn:admin2_code":"03",
    "gn:admin3_code":"031",
    "gn:admin4_code":"03185",
    "gn:asciiname":"Saint-Jean",
    "gn:country_code":"FR",
    "gn:dem":255,
    "gn:feature_class":"P",
    "gn:feature_code":"PPL",
    "gn:name":"Saint-Jean",
    "gn:population":0,
    "gn:timezone":"Europe/Paris",
    "iso:country":"FR",
    "wof:name":"Saint-Jean",
    "wof:placetype":"locality"
},
  "geometry": {"coordinates":[2.61667,46.33333],"type":"Point"}
}