{
  "type": "Feature",
  "properties": {
    "gn:admin1_code":"84",
    "gn:admin2_code":"38",
    "gn:admin3_code":"381",
    "gn:admin4_code":"38163",
    "gn:asciiname":"Fond de France",
    "gn:country_code":"FR",
    "gn:dem":1089,
    "gn:feature_class":"P",
    "gn:feature_code":"PPL",
    "gn:name":"Fond de France",
    "gn:population":0,
    "gn:timezone":"Europe/Paris",
    "iso:country":"FR",
    "wof:name":"Fond de France",
    "wof:placetype":"locality"
},
  "geometry": {"coordinates":[6.07408,45.27972000000001],"type":"Point"}
}