{
  "type": "Feature",
  "properties": {
    "gn:admin1_code":"84",
    "gn:admin2_code":"07",
    "gn:admin3_code":"073",
    "gn:admin4_code":"07204",
    "gn:asciiname":"Le Grouzet",
    "gn:country_code":"FR",
    "gn:dem":852,
    "gn:feature_class":"P",
    "gn:feature_code":"PPL",
    "gn:name":"Le Grouzet",
    "gn:population":0,
    "gn:timezone":"Europe/Paris",
    "iso:country":"FR",
    "wof:name":"Le Grouzet",
    "wof:placetype":"locality"
},
  "geometry": {"coordinates":[4.45306,45.02235],"type":"Point"}
}