{
  "type": "Feature",
  "properties": {
    "gn:admin1_code":"24",
    "gn:admin2_code":"28",
    "gn:admin3_code":"281",
    "gn:admin4_code":"28383",
    "gn:asciiname":"Rosay-au-Val",
    "gn:country_code":"FR",
    "gn:dem":148,
    "gn:feature_class":"P",
    "gn:feature_code":"PPL",
    "gn:name":"Rosay-au-Val",
    "gn:population":0,
    "gn:timezone":"Europe/Paris",
    "iso:country":"FR",
    "name:und_x_variant":[
        "Rosay",
        "Rosay-au-Val"
    ],
    "wof:name":"Rosay-au-Val",
    "wof:placetype":"locality"
},
  "geometry": {"coordinates":[1.58528,48.35007],"type":"Point"}
}