{
  "type": "Feature",
  "properties": {
    "gn:admin1_code":"27",
    "gn:admin2_code":"89",
    "gn:admin3_code":"891",
    "gn:admin4_code":"89286",
    "gn:asciiname":"Parly",
    "gn:country_code":"FR",
    "gn:dem":208,
    "gn:feature_class":"P",
    "gn:feature_code":"PPL",
    "gn:name":"Parly",
    "gn:population":720,
    "gn:timezone":"Europe/Paris",
    "iso:country":"FR",
    "wof:name":"Parly",
    "wof:placetype":"locality",
    "wof:population":720
},
  "geometry": {"coordinates":[3.34782,47.76481],"type":"Point"}
}