{
  "type": "Feature",
  "properties": {
    "gn:admin1_code":"27",
    "gn:admin2_code":"89",
    "gn:admin3_code":"891",
    "gn:admin4_code":"89286",
    "gn:asciiname":"Parly",
    "gn:country_code":"FR",
    "gn:dem":208,
    "gn:feature_class":"P",
    "gn:feature_code":"PPL",
    "gn:name":"Parly",
    "gn:population":720,
    "gn:timezone":"Europe/Paris",
    "iso:country":"FR",
    "name:bug_x_preferred":[
        "Parly"
    ],
    "name:cat_x_preferred":[
        "Parly"
    ],
    "name:ceb_x_preferred":[
        "Parly"
    ],
    "name:deu_x_preferred":[
        "Parly"
    ],
    "name:eus_x_preferred":[
        "Parly"
    ],
    "name:fra_x_preferred":[
        "Parly"
    ],
    "name:hun_x_preferred":[
        "Parly"
    ],
    "name:ita_x_preferred":[
        "Parly"
    ],
    "name:kaz_x_preferred":[
        "\u041f\u0430\u0440\u043b\u0438"
    ],
    "name:lat_x_preferred":[
        "Parly"
    ],
    "name:msa_x_preferred":[
        "Parly"
    ],
    "name:nld_x_preferred":[
        "Parly"
    ],
    "name:oci_x_preferred":[
        "Parly"
    ],
    "name:pms_x_preferred":[
        "Parly"
    ],
    "name:pol_x_preferred":[
        "Parly"
    ],
    "name:por_x_preferred":[
        "Parly"
    ],
    "name:ron_x_preferred":[
        "Parly"
    ],
    "name:slk_x_preferred":[
        "Parly"
    ],
    "name:spa_x_preferred":[
        "Parly"
    ],
    "name:swe_x_preferred":[
        "Parly"
    ],
    "name:ukr_x_preferred":[
        "\u041f\u0430\u0440\u043b\u0456"
    ],
    "name:uzb_x_preferred":[
        "Parly"
    ],
    "name:vie_x_preferred":[
        "Parly"
    ],
    "name:vol_x_preferred":[
        "Parly"
    ],
    "name:war_x_preferred":[
        "Parly"
    ],
    "name:zho_x_preferred":[
        "\u5e15\u5c14\u5229"
    ],
    "wof:name":"Parly",
    "wof:placetype":"locality",
    "wof:population":720
},
  "geometry": {"coordinates":[3.34782,47.76481],"type":"Point"}
}