{
  "type": "Feature",
  "properties": {
    "frgov:code_epci":"200067130",
    "frgov:insee_arr":"1",
    "frgov:insee_com":"89286",
    "frgov:insee_dep":"89",
    "frgov:insee_reg":"27",
    "frgov:nom_com":"Parly",
    "frgov:nom_com_m":"PARLY",
    "frgov:nom_dep":"YONNE",
    "frgov:nom_reg":"BOURGOGNE-FRANCHE-COMTE",
    "frgov:statut":"Commune simple",
    "gn:admin1_code":"27",
    "gn:admin2_code":"89",
    "gn:admin3_code":"891",
    "gn:admin4_code":"89286",
    "gn:asciiname":"Parly",
    "gn:country_code":"FR",
    "gn:dem":208,
    "gn:feature_class":"P",
    "gn:feature_code":"PPL",
    "gn:name":"Parly",
    "gn:population":720,
    "gn:timezone":"Europe/Paris",
    "iso:country":"FR",
    "name:bug_x_preferred":[
        "Parly"
    ],
    "name:cat_x_preferred":[
        "Parly"
    ],
    "name:ceb_x_preferred":[
        "Parly"
    ],
    "name:deu_x_preferred":[
        "Parly"
    ],
    "name:eus_x_preferred":[
        "Parly"
    ],
    "name:fra_x_preferred":[
        "Parly"
    ],
    "name:hun_x_preferred":[
        "Parly"
    ],
    "name:ita_x_preferred":[
        "Parly"
    ],
    "name:kaz_x_preferred":[
        "\u041f\u0430\u0440\u043b\u0438"
    ],
    "name:lat_x_preferred":[
        "Parly"
    ],
    "name:msa_x_preferred":[
        "Parly"
    ],
    "name:nld_x_preferred":[
        "Parly"
    ],
    "name:oci_x_preferred":[
        "Parly"
    ],
    "name:pms_x_preferred":[
        "Parly"
    ],
    "name:pol_x_preferred":[
        "Parly"
    ],
    "name:por_x_preferred":[
        "Parly"
    ],
    "name:ron_x_preferred":[
        "Parly"
    ],
    "name:slk_x_preferred":[
        "Parly"
    ],
    "name:spa_x_preferred":[
        "Parly"
    ],
    "name:swe_x_preferred":[
        "Parly"
    ],
    "name:ukr_x_preferred":[
        "\u041f\u0430\u0440\u043b\u0456"
    ],
    "name:uzb_x_preferred":[
        "Parly"
    ],
    "name:vie_x_preferred":[
        "Parly"
    ],
    "name:vol_x_preferred":[
        "Parly"
    ],
    "name:war_x_preferred":[
        "Parly"
    ],
    "name:zho_x_preferred":[
        "\u5e15\u5c14\u5229"
    ],
    "qs:a0":"France",
    "qs:a1":"YONNE",
    "qs:a1_lc":"89",
    "qs:a1r":"BOURGOGNE",
    "qs:a1r_lc":"26",
    "qs:a2_lc":"33",
    "qs:a2r_lc":"1",
    "qs:adm0":"France",
    "qs:adm0_a3":"FRA",
    "qs:la":"PARLY",
    "qs:la_lc":"89286",
    "qs:level":"localadmin",
    "qs:type":"Commune simple",
    "wof:coterminous":[
        404428121
    ],
    "wof:name":"Parly",
    "wof:placetype":"locality",
    "wof:placetype_local":"Commune simple",
    "wof:population":720
},
  "geometry": {"coordinates":[3.34782,47.76481],"type":"Point"}
}