{
  "type": "Feature",
  "properties": {
    "gn:admin1_code":"53",
    "gn:admin2_code":"22",
    "gn:admin3_code":"221",
    "gn:admin4_code":"22308",
    "gn:asciiname":"La Gaudiere",
    "gn:country_code":"FR",
    "gn:dem":47,
    "gn:feature_class":"P",
    "gn:feature_code":"PPL",
    "gn:name":"La Gaudi\u00e8re",
    "gn:population":0,
    "gn:timezone":"Europe/Paris",
    "iso:country":"FR",
    "wof:name":"La Gaudiere",
    "wof:placetype":"locality"
},
  "geometry": {"coordinates":[-2.07719,48.36179],"type":"Point"}
}