{
  "type": "Feature",
  "properties": {
    "gn:admin1_code":"53",
    "gn:admin2_code":"22",
    "gn:admin3_code":"224",
    "gn:admin4_code":"22093",
    "gn:asciiname":"Saint-Aaron",
    "gn:country_code":"FR",
    "gn:dem":96,
    "gn:feature_class":"P",
    "gn:feature_code":"PPL",
    "gn:name":"Saint-Aaron",
    "gn:population":0,
    "gn:timezone":"Europe/Paris",
    "iso:country":"FR",
    "wof:name":"Saint-Aaron",
    "wof:placetype":"locality"
},
  "geometry": {"coordinates":[-2.48944,48.51016],"type":"Point"}
}