{
  "type": "Feature",
  "properties": {
    "gn:admin1_code":"27",
    "gn:admin2_code":"89",
    "gn:admin3_code":"891",
    "gn:admin4_code":"89311",
    "gn:asciiname":"Nantou",
    "gn:country_code":"FR",
    "gn:dem":211,
    "gn:feature_class":"P",
    "gn:feature_code":"PPL",
    "gn:name":"Nantou",
    "gn:population":0,
    "gn:timezone":"Europe/Paris",
    "iso:country":"FR",
    "name:und_x_variant":[
        "Nanton",
        "Nantou"
    ],
    "wof:name":"Nantou",
    "wof:placetype":"locality"
},
  "geometry": {"coordinates":[3.40592,47.78172],"type":"Point"}
}