{
  "type": "Feature",
  "properties": {
    "iso:country":"FR",
    "name:eng_x_preferred":[
        "Chemin Vert-Salvador Allende"
    ],
    "name:fra_x_preferred":[
        "Chemin Vert-Salvador Allende"
    ],
    "wof:name":"Chemin Vert-Salvador Allende",
    "wof:placetype":"neighbourhood"
},
  "geometry": {"coordinates":[2.44762494618892,48.90501754916014],"type":"Point"}
}