{
  "type": "Feature",
  "properties": {
    "gn:admin1_code":"75",
    "gn:admin2_code":"24",
    "gn:admin3_code":"242",
    "gn:admin4_code":"24253",
    "gn:asciiname":"La Chapelle-Pommier",
    "gn:country_code":"FR",
    "gn:dem":227,
    "gn:feature_class":"P",
    "gn:feature_code":"PPL",
    "gn:name":"La Chapelle-Pommier",
    "gn:population":0,
    "gn:timezone":"Europe/Paris",
    "iso:country":"FR",
    "wof:name":"La Chapelle-Pommier",
    "wof:placetype":"locality"
},
  "geometry": {"coordinates":[0.55631,45.453],"type":"Point"}
}