{
  "type": "Feature",
  "properties": {
    "gn:admin1_code":"53",
    "gn:admin2_code":"29",
    "gn:admin3_code":"291",
    "gn:admin4_code":"29237",
    "gn:asciiname":"Quinquis Meur",
    "gn:country_code":"FR",
    "gn:dem":73,
    "gn:feature_class":"P",
    "gn:feature_code":"PPL",
    "gn:name":"Quinquis Meur",
    "gn:population":0,
    "gn:timezone":"Europe/Paris",
    "iso:country":"FR",
    "wof:name":"Quinquis Meur",
    "wof:placetype":"locality"
},
  "geometry": {"coordinates":[-4.21667,48.48333],"type":"Point"}
}