{
  "type": "Feature",
  "properties": {
    "iso:country":"FR",
    "name:fra_x_variant":[
        "Ternes"
    ],
    "wof:name":"Ternes",
    "wof:placetype":"neighbourhood"
},
  "geometry": {"coordinates":[2.289969,48.881074],"type":"Point"}
}