{
  "type": "Feature",
  "properties": {
    "gn:admin1_code":"84",
    "gn:admin2_code":"73",
    "gn:admin3_code":"733",
    "gn:admin4_code":"73290",
    "gn:asciiname":"Le Chatelard",
    "gn:country_code":"FR",
    "gn:dem":1744,
    "gn:feature_class":"P",
    "gn:feature_code":"PPL",
    "gn:name":"Le Ch\u00e2telard",
    "gn:population":0,
    "gn:timezone":"Europe/Paris",
    "iso:country":"FR",
    "wof:name":"Le Chatelard",
    "wof:placetype":"locality"
},
  "geometry": {"coordinates":[6.87179,45.29343],"type":"Point"}
}