{
  "type": "Feature",
  "properties": {
    "gn:admin1_code":"28",
    "gn:asciiname":"Les Sablons",
    "gn:country_code":"FR",
    "gn:dem":212,
    "gn:feature_class":"P",
    "gn:feature_code":"PPL",
    "gn:name":"Les Sablons",
    "gn:population":0,
    "gn:timezone":"Europe/Paris",
    "iso:country":"FR",
    "wof:name":"Les Sablons",
    "wof:placetype":"locality"
},
  "geometry": {"coordinates":[0.93776,48.39271],"type":"Point"}
}