{
  "type": "Feature",
  "properties": {
    "gn:admin1_code":"84",
    "gn:admin2_code":"43",
    "gn:admin3_code":"432",
    "gn:admin4_code":"43201",
    "gn:asciiname":"Voirac",
    "gn:country_code":"FR",
    "gn:dem":781,
    "gn:feature_class":"P",
    "gn:feature_code":"PPL",
    "gn:name":"Voirac",
    "gn:population":0,
    "gn:timezone":"Europe/Paris",
    "iso:country":"FR",
    "wof:name":"Voirac",
    "wof:placetype":"locality"
},
  "geometry": {"coordinates":[3.93144,45.32129000000001],"type":"Point"}
}