{
  "type": "Feature",
  "properties": {
    "gn:admin1_code":"27",
    "gn:admin2_code":"89",
    "gn:admin3_code":"891",
    "gn:admin4_code":"89200.0",
    "gn:asciiname":"Chichy",
    "gn:country_code":"FR",
    "gn:dem":123,
    "gn:feature_class":"P",
    "gn:feature_code":"PPL",
    "gn:name":"Chichy",
    "gn:population":0,
    "gn:timezone":"Europe/Paris",
    "iso:country":"FR",
    "name:azb_x_preferred":[
        "\u062e\u06cc\u062e\u0647"
    ],
    "name:ceb_x_preferred":[
        "Chichy"
    ],
    "name:fas_x_preferred":[
        "\u062e\u06cc\u062e\u0647"
    ],
    "name:fra_x_preferred":[
        "Chichy"
    ],
    "name:nld_x_preferred":[
        "Chichy"
    ],
    "name:pol_x_preferred":[
        "Chichy"
    ],
    "name:ukr_x_preferred":[
        "\u0425\u0456\u0445\u0438"
    ],
    "wof:name":"Chichy",
    "wof:placetype":"locality"
},
  "geometry": {"coordinates":[3.59443,47.94446],"type":"Point"}
}