{
  "type": "Feature",
  "properties": {
    "gn:admin1_code":"24",
    "gn:admin2_code":"28",
    "gn:admin3_code":"281",
    "gn:admin4_code":"28048",
    "gn:asciiname":"Saint-Loup",
    "gn:country_code":"FR",
    "gn:dem":160,
    "gn:feature_class":"P",
    "gn:feature_code":"PPL",
    "gn:name":"Saint-Loup",
    "gn:population":0,
    "gn:timezone":"Europe/Paris",
    "iso:country":"FR",
    "name:bre_x_preferred":[
        "Saint-Loup"
    ],
    "name:cat_x_preferred":[
        "Saint-Loup"
    ],
    "name:ceb_x_preferred":[
        "Saint-Loup"
    ],
    "name:ces_x_preferred":[
        "Saint-Loup"
    ],
    "name:deu_x_preferred":[
        "Saint Loup"
    ],
    "name:epo_x_preferred":[
        "Saint-Loup"
    ],
    "name:fra_x_preferred":[
        "Saint-Loup"
    ],
    "name:hye_x_preferred":[
        "\u054d\u0565\u0576 \u053c\u0578\u0582"
    ],
    "name:ita_x_preferred":[
        "Saint-Loup"
    ],
    "name:nld_x_preferred":[
        "Saint-Loup"
    ],
    "name:oci_x_preferred":[
        "Saint-Loup"
    ],
    "name:pms_x_preferred":[
        "Saint-Loup"
    ],
    "name:pol_x_preferred":[
        "Saint-Loup"
    ],
    "name:por_x_preferred":[
        "Saint-Loup"
    ],
    "name:rus_x_preferred":[
        "\u0421\u0435\u043d-\u041b\u0443"
    ],
    "name:slk_x_preferred":[
        "Saint-Loup"
    ],
    "name:spa_x_preferred":[
        "Saint-Loup"
    ],
    "name:sqi_x_preferred":[
        "Saint-Loup"
    ],
    "name:swe_x_preferred":[
        "Saint-Loup"
    ],
    "name:ukr_x_preferred":[
        "\u0421\u0435\u043d-\u041b\u0443"
    ],
    "wof:name":"Saint-Loup",
    "wof:placetype":"locality"
},
  "geometry": {"coordinates":[1.40719,48.31927],"type":"Point"}
}