{
  "type": "Feature",
  "properties": {
    "gn:admin1_code":"84",
    "gn:admin2_code":"73",
    "gn:admin3_code":"732",
    "gn:admin4_code":"73274.0",
    "gn:asciiname":"Pierre Grosse",
    "gn:country_code":"FR",
    "gn:dem":783,
    "gn:feature_class":"P",
    "gn:feature_code":"PPL",
    "gn:name":"Pierre Grosse",
    "gn:population":0,
    "gn:timezone":"Europe/Paris",
    "iso:country":"FR",
    "wof:name":"Pierre Grosse",
    "wof:placetype":"locality"
},
  "geometry": {"coordinates":[5.86146,45.41457],"type":"Point"}
}