{
  "type": "Feature",
  "properties": {
    "gn:gn_country":"FO",
    "gn:gn_fcode":"PPLA",
    "gn:gn_pop":608,
    "gn:population":608,
    "iso:country":"FO",
    "name:baq_x_preferred":[
        "Sandur"
    ],
    "name:cze_x_preferred":[
        "Sandur"
    ],
    "name:dan_x_preferred":[
        "Sandur"
    ],
    "name:dut_x_preferred":[
        "Sandur"
    ],
    "name:eng_x_preferred":[
        "Sand"
    ],
    "name:fao_x_preferred":[
        "Sandur"
    ],
    "name:fin_x_preferred":[
        "Sandur"
    ],
    "name:ger_x_preferred":[
        "Sandur"
    ],
    "name:glv_x_preferred":[
        "Sandur"
    ],
    "name:heb_x_preferred":[
        "\u05e1\u05d0\u05e0\u05d3\u05d5\u05e8"
    ],
    "name:hun_x_preferred":[
        "Sandur"
    ],
    "name:kal_x_preferred":[
        "Sandur"
    ],
    "name:lit_x_preferred":[
        "Sanduras"
    ],
    "name:nob_x_preferred":[
        "Sandur"
    ],
    "name:oss_x_preferred":[
        "\u0421\u0430\u043d\u0434\u0443\u0440"
    ],
    "name:pol_x_preferred":[
        "Sandur"
    ],
    "name:rum_x_preferred":[
        "Sandur"
    ],
    "name:rus_x_preferred":[
        "\u0421\u0430\u043d\u0434\u0443\u0440"
    ],
    "name:slo_x_preferred":[
        "Sandur"
    ],
    "name:spa_x_preferred":[
        "Sandur"
    ],
    "name:swe_x_preferred":[
        "Sandur"
    ],
    "name:unk_x_variant":[
        "Sand"
    ],
    "qs:a0":"Foroyar#F\u00e6r\u00f8erne",
    "qs:a1":"*",
    "qs:a1r":"0",
    "qs:adm0":"Foroyar#F\u00e6r\u00f8erne",
    "qs:la_lc":"*",
    "qs:level":"locality",
    "qs:loc":"Sandur",
    "qs:loc_alt":"Sandur",
    "qs:pop":0,
    "qs:type":"buffered point",
    "qs_pg:aaroncc":"FO",
    "qs_pg:gn_country":"FO",
    "qs_pg:gn_fcode":"PPLA",
    "qs_pg:gn_pop":608,
    "qs_pg:name":"Sandur",
    "qs_pg:photos_9r":0,
    "qs_pg:photos_sr":0,
    "qs_pg:pop_sr":2,
    "qs_pg:qs_pg_placetype":"locality",
    "wof:lang":[
        "dan"
    ],
    "wof:name":"Sandur",
    "wof:placetype":"locality",
    "wof:population":608
},
  "geometry": {"coordinates":[-6.82055,61.838836],"type":"Point"}
}