{
  "type": "Feature",
  "properties": {
    "gn:admin1_code":"32",
    "gn:admin2_code":"80",
    "gn:admin3_code":"801",
    "gn:admin4_code":"80732",
    "gn:asciiname":"Rederie",
    "gn:country_code":"FR",
    "gn:dem":173,
    "gn:feature_class":"P",
    "gn:feature_code":"PPL",
    "gn:name":"R\u00e9derie",
    "gn:population":0,
    "gn:timezone":"Europe/Paris",
    "iso:country":"FR",
    "wof:name":"Rederie",
    "wof:placetype":"locality"
},
  "geometry": {"coordinates":[1.72082,49.90391],"type":"Point"}
}