{
  "type": "Feature",
  "properties": {
    "gn:admin1_code":"24",
    "gn:admin2_code":"41",
    "gn:admin3_code":"412",
    "gn:admin4_code":"41005.0",
    "gn:asciiname":"Le Coureil",
    "gn:country_code":"FR",
    "gn:dem":174,
    "gn:feature_class":"P",
    "gn:feature_code":"PPL",
    "gn:name":"Le Coureil",
    "gn:population":0,
    "gn:timezone":"Europe/Paris",
    "iso:country":"FR",
    "wof:name":"Le Coureil",
    "wof:placetype":"locality"
},
  "geometry": {"coordinates":[0.95501,48.06811],"type":"Point"}
}