{
  "type": "Feature",
  "properties": {
    "iso:country":"FR",
    "name:eng_x_preferred":[
        "La Guinet"
    ],
    "name:fra_x_preferred":[
        "La Guinet"
    ],
    "wof:name":"La Guinet",
    "wof:placetype":"neighbourhood"
},
  "geometry": {"coordinates":[2.36518998305617,48.7720264228911],"type":"Point"}
}