{
  "type": "Feature",
  "properties": {
    "gn:admin1_code":"84",
    "gn:admin2_code":"63",
    "gn:admin3_code":"633",
    "gn:admin4_code":"63038",
    "gn:asciiname":"Montredon",
    "gn:country_code":"FR",
    "gn:dem":1009,
    "gn:feature_class":"P",
    "gn:feature_code":"PPL",
    "gn:name":"Montredon",
    "gn:population":0,
    "gn:timezone":"Europe/Paris",
    "iso:country":"FR",
    "name:cat_x_preferred":[
        "Mont-redond"
    ],
    "name:ceb_x_preferred":[
        "Montredon"
    ],
    "name:eus_x_preferred":[
        "Montredon"
    ],
    "name:fra_x_preferred":[
        "Montredon"
    ],
    "name:hun_x_preferred":[
        "Montredon"
    ],
    "name:ita_x_preferred":[
        "Montredon"
    ],
    "name:lat_x_preferred":[
        "Montredon"
    ],
    "name:mlg_x_preferred":[
        "Montredon"
    ],
    "name:msa_x_preferred":[
        "Montredon"
    ],
    "name:nld_x_preferred":[
        "Montredon"
    ],
    "name:oci_x_preferred":[
        "Montredond"
    ],
    "name:pms_x_preferred":[
        "Montredon"
    ],
    "name:pol_x_preferred":[
        "Montredon"
    ],
    "name:por_x_preferred":[
        "Montredon"
    ],
    "name:ron_x_preferred":[
        "Montredon"
    ],
    "name:slk_x_preferred":[
        "Montredon"
    ],
    "name:spa_x_preferred":[
        "Montredon"
    ],
    "name:swe_x_preferred":[
        "Montredon"
    ],
    "name:ukr_x_preferred":[
        "\u041c\u043e\u043d\u0440\u0435\u0434\u043e\u043d"
    ],
    "name:vie_x_preferred":[
        "Montredon"
    ],
    "name:vol_x_preferred":[
        "Montredon"
    ],
    "name:war_x_preferred":[
        "Montredon"
    ],
    "name:zho_x_preferred":[
        "\u8499\u7279\u5c14\u4e1c"
    ],
    "wof:name":"Montredon",
    "wof:placetype":"locality"
},
  "geometry": {"coordinates":[2.95679,45.53232],"type":"Point"}
}