{
  "type": "Feature",
  "properties": {
    "gn:admin1_code":"27",
    "gn:admin2_code":"89",
    "gn:admin3_code":"893",
    "gn:admin4_code":"89229",
    "gn:asciiname":"Fontenelle",
    "gn:country_code":"FR",
    "gn:dem":143,
    "gn:feature_class":"P",
    "gn:feature_code":"PPL",
    "gn:name":"Fontenelle",
    "gn:population":0,
    "gn:timezone":"Europe/Paris",
    "iso:country":"FR",
    "wof:name":"Fontenelle",
    "wof:placetype":"locality"
},
  "geometry": {"coordinates":[3.11144,48.25286],"type":"Point"}
}