{
  "type": "Feature",
  "properties": {
    "gn:admin1_code":"27",
    "gn:admin2_code":"89",
    "gn:admin3_code":"893",
    "gn:admin4_code":"89229",
    "gn:asciiname":"Fontenelle",
    "gn:country_code":"FR",
    "gn:dem":143,
    "gn:feature_class":"P",
    "gn:feature_code":"PPL",
    "gn:name":"Fontenelle",
    "gn:population":0,
    "gn:timezone":"Europe/Paris",
    "iso:country":"FR",
    "name:cat_x_preferred":[
        "Fontenelle"
    ],
    "name:ceb_x_preferred":[
        "Fontenelle"
    ],
    "name:deu_x_preferred":[
        "Fontenelle"
    ],
    "name:epo_x_preferred":[
        "Fontenelle"
    ],
    "name:fra_x_preferred":[
        "Fontenelle"
    ],
    "name:ita_x_preferred":[
        "Fontenelle"
    ],
    "name:nds_x_preferred":[
        "Fontenelle"
    ],
    "name:nld_x_preferred":[
        "Fontenelle"
    ],
    "name:pms_x_preferred":[
        "Fontenelle"
    ],
    "name:pol_x_preferred":[
        "Fontenelle"
    ],
    "name:por_x_preferred":[
        "Fontenelle"
    ],
    "name:rus_x_preferred":[
        "\u0424\u043e\u043d\u0442\u0435\u043d\u0435\u043b\u043b"
    ],
    "name:sco_x_preferred":[
        "Fontenelle"
    ],
    "name:slk_x_preferred":[
        "Fontenelle"
    ],
    "name:spa_x_preferred":[
        "Fontenelle"
    ],
    "name:srp_x_preferred":[
        "\u0424\u043e\u043d\u0442\u043d\u0435\u043b"
    ],
    "name:swe_x_preferred":[
        "Fontenelle"
    ],
    "name:vol_x_preferred":[
        "Fontenelle"
    ],
    "wof:name":"Fontenelle",
    "wof:placetype":"locality"
},
  "geometry": {"coordinates":[3.11144,48.25286],"type":"Point"}
}