{
  "type": "Feature",
  "properties": {
    "gn:admin1_code":"52",
    "gn:admin2_code":"49",
    "gn:admin3_code":"492",
    "gn:admin4_code":"49244",
    "gn:asciiname":"L'Aleu",
    "gn:country_code":"FR",
    "gn:dem":12,
    "gn:feature_class":"P",
    "gn:feature_code":"PPL",
    "gn:name":"L\u2019Aleu",
    "gn:population":0,
    "gn:timezone":"Europe/Paris",
    "iso:country":"FR",
    "wof:name":"L'Aleu",
    "wof:placetype":"locality"
},
  "geometry": {"coordinates":[-0.95027,47.36881],"type":"Point"}
}