{
  "type": "Feature",
  "properties": {
    "gn:admin1_code":"75",
    "gn:admin2_code":"79",
    "gn:admin3_code":"791",
    "gn:admin4_code":"79079",
    "gn:asciiname":"Saint-Aubin-de-Baubigne",
    "gn:country_code":"FR",
    "gn:dem":175,
    "gn:feature_class":"P",
    "gn:feature_code":"PPL",
    "gn:name":"Saint-Aubin-de-Baubign\u00e9",
    "gn:population":0,
    "gn:timezone":"Europe/Paris",
    "iso:country":"FR",
    "name:und_x_variant":[
        "Saint-Aubin",
        "Saint-Aubin-de-Baubign\u00e9"
    ],
    "wof:name":"Saint-Aubin-de-Baubigne",
    "wof:placetype":"locality"
},
  "geometry": {"coordinates":[-0.69096,46.9406],"type":"Point"}
}