{
  "type": "Feature",
  "properties": {
    "gn:admin1_code":"27",
    "gn:admin2_code":"58",
    "gn:admin3_code":"583",
    "gn:admin4_code":"58254.0",
    "gn:asciiname":"Mont-Miens",
    "gn:country_code":"FR",
    "gn:dem":207,
    "gn:feature_class":"P",
    "gn:feature_code":"PPL",
    "gn:name":"Mont-Miens",
    "gn:population":0,
    "gn:timezone":"Europe/Paris",
    "iso:country":"FR",
    "wof:name":"Mont-Miens",
    "wof:placetype":"locality"
},
  "geometry": {"coordinates":[3.2194,47.03456],"type":"Point"}
}