{
  "type": "Feature",
  "properties": {
    "gn:admin1_code":"32",
    "gn:admin2_code":"62",
    "gn:admin3_code":"624",
    "gn:admin4_code":"62202",
    "gn:asciiname":"Happe",
    "gn:country_code":"FR",
    "gn:dem":127,
    "gn:feature_class":"P",
    "gn:feature_code":"PPL",
    "gn:name":"Happe",
    "gn:population":0,
    "gn:timezone":"Europe/Paris",
    "iso:country":"FR",
    "name:deu_x_preferred":[
        "Happe"
    ],
    "wof:name":"Happe",
    "wof:placetype":"locality"
},
  "geometry": {"coordinates":[2.01429,50.62163],"type":"Point"}
}