{
  "type": "Feature",
  "properties": {
    "gn:admin1_code":"84",
    "gn:admin2_code":"73",
    "gn:admin3_code":"732",
    "gn:admin4_code":"73065.0",
    "gn:asciiname":"Bissy",
    "gn:country_code":"FR",
    "gn:dem":263,
    "gn:feature_class":"P",
    "gn:feature_code":"PPL",
    "gn:name":"Bissy",
    "gn:population":0,
    "gn:timezone":"Europe/Paris",
    "iso:country":"FR",
    "name:ceb_x_preferred":[
        "Bissy"
    ],
    "name:deu_x_preferred":[
        "Bissy"
    ],
    "name:fra_x_preferred":[
        "Bissy"
    ],
    "name:swe_x_preferred":[
        "Bissy"
    ],
    "wof:name":"Bissy",
    "wof:placetype":"locality"
},
  "geometry": {"coordinates":[5.88949,45.57979],"type":"Point"}
}