{
  "type": "Feature",
  "properties": {
    "gn:admin1_code":"75",
    "gn:admin2_code":"87",
    "gn:admin3_code":"872",
    "gn:admin4_code":"87039",
    "gn:asciiname":"Puy-la-Brune",
    "gn:country_code":"FR",
    "gn:dem":416,
    "gn:feature_class":"P",
    "gn:feature_code":"PPL",
    "gn:name":"Puy-la-Brune",
    "gn:population":0,
    "gn:timezone":"Europe/Paris",
    "iso:country":"FR",
    "wof:name":"Puy-la-Brune",
    "wof:placetype":"locality"
},
  "geometry": {"coordinates":[1.34247,45.61807],"type":"Point"}
}