{
  "type": "Feature",
  "properties": {
    "gn:admin1_code":"27",
    "gn:admin2_code":"58",
    "gn:admin3_code":"583",
    "gn:admin4_code":"58267",
    "gn:asciiname":"Pouzy",
    "gn:country_code":"FR",
    "gn:dem":324,
    "gn:feature_class":"P",
    "gn:feature_code":"PPL",
    "gn:name":"Pouzy",
    "gn:population":0,
    "gn:timezone":"Europe/Paris",
    "iso:country":"FR",
    "wof:name":"Pouzy",
    "wof:placetype":"locality"
},
  "geometry": {"coordinates":[3.50482,47.12184],"type":"Point"}
}