{
  "type": "Feature",
  "properties": {
    "gn:admin1_code":"84",
    "gn:admin2_code":"15",
    "gn:admin3_code":"153",
    "gn:admin4_code":"15043",
    "gn:asciiname":"Le Brus",
    "gn:country_code":"FR",
    "gn:dem":1078,
    "gn:feature_class":"P",
    "gn:feature_code":"PPL",
    "gn:name":"Le Brus",
    "gn:population":0,
    "gn:timezone":"Europe/Paris",
    "iso:country":"FR",
    "name:und_x_variant":[
        "Le Bru",
        "Le Brus"
    ],
    "wof:name":"Le Brus",
    "wof:placetype":"locality"
},
  "geometry": {"coordinates":[3.05649,45.23681],"type":"Point"}
}