{
  "type": "Feature",
  "properties": {
    "gn:admin1_code":"94",
    "gn:admin2_code":"2A",
    "gn:admin3_code":"2A1",
    "gn:admin4_code":"2A090",
    "gn:asciiname":"Le Village de Penisola",
    "gn:country_code":"FR",
    "gn:dem":21,
    "gn:feature_class":"P",
    "gn:feature_code":"PPL",
    "gn:name":"Le Village de Penisola",
    "gn:population":0,
    "gn:timezone":"Europe/Paris",
    "iso:country":"FR",
    "wof:name":"Le Village de Penisola",
    "wof:placetype":"locality"
},
  "geometry": {"coordinates":[8.71124,42.09328],"type":"Point"}
}