{
  "type": "Feature",
  "properties": {
    "gn:admin1_code":"44",
    "gn:admin2_code":"52",
    "gn:admin3_code":"522",
    "gn:admin4_code":"52464",
    "gn:asciiname":"Seuchey",
    "gn:country_code":"FR",
    "gn:dem":311,
    "gn:feature_class":"P",
    "gn:feature_code":"PPL",
    "gn:name":"Seuchey",
    "gn:population":0,
    "gn:timezone":"Europe/Paris",
    "iso:country":"FR",
    "wof:name":"Seuchey",
    "wof:placetype":"locality"
},
  "geometry": {"coordinates":[5.52581,47.68804],"type":"Point"}
}