{
  "type": "Feature",
  "properties": {
    "gn:admin1_code":"24",
    "gn:admin2_code":"18",
    "gn:admin3_code":"181",
    "gn:admin4_code":"18137",
    "gn:asciiname":"Mesmains",
    "gn:country_code":"FR",
    "gn:dem":168,
    "gn:feature_class":"P",
    "gn:feature_code":"PPL",
    "gn:name":"Mesmains",
    "gn:population":0,
    "gn:timezone":"Europe/Paris",
    "iso:country":"FR",
    "name:und_x_variant":[
        "Mesmain",
        "Mesmains"
    ],
    "wof:name":"Mesmains",
    "wof:placetype":"locality"
},
  "geometry": {"coordinates":[2.17912,46.86988],"type":"Point"}
}