{
  "type": "Feature",
  "properties": {
    "gn:admin1_code":"53",
    "gn:admin2_code":"22",
    "gn:admin3_code":"222",
    "gn:admin4_code":"22272",
    "gn:asciiname":"Saint-Paterne",
    "gn:country_code":"FR",
    "gn:dem":119,
    "gn:feature_class":"P",
    "gn:feature_code":"PPL",
    "gn:name":"Saint-Paterne",
    "gn:population":0,
    "gn:timezone":"Europe/Paris",
    "iso:country":"FR",
    "name:und_x_variant":[
        "Saint-Patern",
        "Saint-Paterne"
    ],
    "wof:name":"Saint-Paterne",
    "wof:placetype":"locality"
},
  "geometry": {"coordinates":[-3.11492,48.57434],"type":"Point"}
}