{
  "type": "Feature",
  "properties": {
    "gn:admin1_code":"53",
    "gn:admin2_code":"22",
    "gn:admin3_code":"222",
    "gn:admin4_code":"22272",
    "gn:asciiname":"Saint-Paterne",
    "gn:country_code":"FR",
    "gn:dem":119,
    "gn:feature_class":"P",
    "gn:feature_code":"PPL",
    "gn:name":"Saint-Paterne",
    "gn:population":0,
    "gn:timezone":"Europe/Paris",
    "iso:country":"FR",
    "name:cat_x_preferred":[
        "Saint-Paterne"
    ],
    "name:ceb_x_preferred":[
        "Saint-Paterne"
    ],
    "name:deu_x_preferred":[
        "Saint-Paterne"
    ],
    "name:eus_x_preferred":[
        "Saint-Paterne"
    ],
    "name:fra_x_preferred":[
        "Saint-Paterne"
    ],
    "name:hun_x_preferred":[
        "Saint-Paterne"
    ],
    "name:ita_x_preferred":[
        "Saint-Paterne"
    ],
    "name:lat_x_preferred":[
        "Saint-Paterne"
    ],
    "name:mlg_x_preferred":[
        "Saint-Paterne"
    ],
    "name:msa_x_preferred":[
        "Saint-Paterne"
    ],
    "name:nld_x_preferred":[
        "Saint-Paterne"
    ],
    "name:oci_x_preferred":[
        "Saint-Paterne"
    ],
    "name:pol_x_preferred":[
        "Saint-Paterne"
    ],
    "name:ron_x_preferred":[
        "Saint-Paterne"
    ],
    "name:slk_x_preferred":[
        "Saint-Paterne"
    ],
    "name:spa_x_preferred":[
        "Saint-Paterne"
    ],
    "name:swe_x_preferred":[
        "Saint-Paterne"
    ],
    "name:ukr_x_preferred":[
        "\u0421\u0435\u043d-\u041f\u0430\u0442\u0435\u0440\u043d"
    ],
    "name:und_x_variant":[
        "Saint-Patern"
    ],
    "name:urd_x_preferred":[
        "\u0633\u06cc\u0646\u0679-\u067e\u062a\u0631\u0646\u06d2"
    ],
    "name:vie_x_preferred":[
        "Saint-Paterne"
    ],
    "name:vol_x_preferred":[
        "Saint-Paterne"
    ],
    "name:war_x_preferred":[
        "Saint-Paterne"
    ],
    "wof:name":"Saint-Paterne",
    "wof:placetype":"locality"
},
  "geometry": {"coordinates":[-3.11492,48.57434],"type":"Point"}
}