{
  "type": "Feature",
  "properties": {
    "gn:admin1_code":"75",
    "gn:admin2_code":"64",
    "gn:admin3_code":"641",
    "gn:admin4_code":"64102",
    "gn:asciiname":"Saint-Bernard",
    "gn:country_code":"FR",
    "gn:dem":5,
    "gn:feature_class":"P",
    "gn:feature_code":"PPL",
    "gn:name":"Saint-Bernard",
    "gn:population":0,
    "gn:timezone":"Europe/Paris",
    "iso:country":"FR",
    "wof:name":"Saint-Bernard",
    "wof:placetype":"locality"
},
  "geometry": {"coordinates":[-1.48491,43.50725],"type":"Point"}
}