{
  "type": "Feature",
  "properties": {
    "gn:admin1_code":"44",
    "gn:admin2_code":"10",
    "gn:admin3_code":"103",
    "gn:admin4_code":"10350",
    "gn:asciiname":"La Belle-Fayte",
    "gn:country_code":"FR",
    "gn:dem":246,
    "gn:feature_class":"P",
    "gn:feature_code":"PPL",
    "gn:name":"La Belle-Fayte",
    "gn:population":0,
    "gn:timezone":"Europe/Paris",
    "iso:country":"FR",
    "name:und_x_variant":[
        "Belle-Fayte",
        "La Belle-Fayte"
    ],
    "wof:name":"La Belle-Fayte",
    "wof:placetype":"locality"
},
  "geometry": {"coordinates":[3.82961,48.16688],"type":"Point"}
}