{
  "type": "Feature",
  "properties": {
    "gn:admin1_code":"84",
    "gn:admin2_code":"38",
    "gn:admin3_code":"381",
    "gn:admin4_code":"38100",
    "gn:asciiname":"Le Villard",
    "gn:country_code":"FR",
    "gn:dem":318,
    "gn:feature_class":"P",
    "gn:feature_code":"PPL",
    "gn:name":"Le Villard",
    "gn:population":0,
    "gn:timezone":"Europe/Paris",
    "iso:country":"FR",
    "wof:name":"Le Villard",
    "wof:placetype":"locality"
},
  "geometry": {"coordinates":[6.00486,45.38724000000001],"type":"Point"}
}