{
  "type": "Feature",
  "properties": {
    "gn:admin1_code":"75",
    "gn:admin2_code":"24",
    "gn:admin3_code":"241",
    "gn:admin4_code":"24043",
    "gn:asciiname":"Ballande",
    "gn:country_code":"FR",
    "gn:dem":187,
    "gn:feature_class":"P",
    "gn:feature_code":"PPL",
    "gn:name":"Ballande",
    "gn:population":0,
    "gn:timezone":"Europe/Paris",
    "iso:country":"FR",
    "wof:name":"Ballande",
    "wof:placetype":"locality"
},
  "geometry": {"coordinates":[0.8713,44.61269],"type":"Point"}
}