{
  "type": "Feature",
  "properties": {
    "gn:admin1_code":"11",
    "gn:admin2_code":"77",
    "gn:admin3_code":"771",
    "gn:admin4_code":"77142",
    "gn:asciiname":"Crecy-la-Chapelle",
    "gn:cc2":"FR",
    "gn:country_code":"FR",
    "gn:dem":52,
    "gn:feature_class":"P",
    "gn:feature_code":"PPL",
    "gn:name":"Cr\u00e9cy-la-Chapelle",
    "gn:population":0,
    "gn:timezone":"Europe/Paris",
    "iso:country":"FR",
    "name:bar_x_preferred":[
        "Cr\u00e9cy-la-Chapelle"
    ],
    "name:cat_x_preferred":[
        "Cr\u00e9cy-la-Chapelle"
    ],
    "name:ceb_x_preferred":[
        "Cr\u00e9cy-la-Chapelle"
    ],
    "name:deu_x_preferred":[
        "Cr\u00e9cy-la-Chapelle"
    ],
    "name:epo_x_preferred":[
        "Cr\u00e9cy-la-Chapelle"
    ],
    "name:eus_x_preferred":[
        "Cr\u00e9cy-la-Chapelle"
    ],
    "name:fra_x_preferred":[
        "Cr\u00e9cy-la-Chapelle"
    ],
    "name:hun_x_preferred":[
        "Cr\u00e9cy-la-Chapelle"
    ],
    "name:ind_x_preferred":[
        "Cr\u00e9cy-la-Chapelle"
    ],
    "name:ita_x_preferred":[
        "Cr\u00e9cy-la-Chapelle"
    ],
    "name:kaz_x_preferred":[
        "\u041a\u0440\u0435\u0441\u0438-\u043b\u0430-\u0428\u0430\u043f\u0435\u043b\u044c"
    ],
    "name:lat_x_preferred":[
        "Cr\u00e9cy-la-Chapelle"
    ],
    "name:msa_x_preferred":[
        "Cr\u00e9cy-la-Chapelle"
    ],
    "name:nld_x_preferred":[
        "Cr\u00e9cy-la-Chapelle"
    ],
    "name:oci_x_preferred":[
        "Cr\u00e9cy-la-Chapelle"
    ],
    "name:pms_x_preferred":[
        "Cr\u00e9cy-la-Chapelle"
    ],
    "name:pol_x_preferred":[
        "Cr\u00e9cy-la-Chapelle"
    ],
    "name:por_x_preferred":[
        "Cr\u00e9cy-la-Chapelle"
    ],
    "name:rus_x_preferred":[
        "\u041a\u0440\u0435\u0441\u0438-\u043b\u0430-\u0428\u0430\u043f\u0435\u043b\u044c"
    ],
    "name:slk_x_preferred":[
        "Cr\u00e9cy-la-Chapelle"
    ],
    "name:spa_x_preferred":[
        "Cr\u00e9cy-la-Chapelle"
    ],
    "name:srp_x_preferred":[
        "\u041a\u0440\u0435\u0441\u0438 \u043b\u0430 \u0428\u0430\u043f\u0435\u043b"
    ],
    "name:swe_x_preferred":[
        "Cr\u00e9cy-la-Chapelle"
    ],
    "name:ukr_x_preferred":[
        "\u041a\u0440\u0435\u0441\u0456-\u043b\u0430-\u0428\u0430\u043f\u0435\u043b\u044c"
    ],
    "name:und_x_variant":[
        "Cr\u00e9cy",
        "Cr\u00e9cy-en-Brie"
    ],
    "name:vie_x_preferred":[
        "Cr\u00e9cy-la-Chapelle"
    ],
    "name:vol_x_preferred":[
        "Cr\u00e9cy-la-Chapelle"
    ],
    "name:war_x_preferred":[
        "Cr\u00e9cy-la-Chapelle"
    ],
    "name:zho_x_preferred":[
        "\u514b\u96f7\u897f\u62c9\u6c99\u4f69\u52d2"
    ],
    "wof:name":"Crecy-la-Chapelle",
    "wof:placetype":"locality"
},
  "geometry": {"coordinates":[2.90743,48.85918],"type":"Point"}
}