{
  "type": "Feature",
  "properties": {
    "gn:admin1_code":"53",
    "gn:admin2_code":"22",
    "gn:admin3_code":"222",
    "gn:admin4_code":"22163",
    "gn:asciiname":"Saint-Eloi",
    "gn:country_code":"FR",
    "gn:dem":140,
    "gn:feature_class":"P",
    "gn:feature_code":"PPL",
    "gn:name":"Saint-\u00c9loi",
    "gn:population":0,
    "gn:timezone":"Europe/Paris",
    "iso:country":"FR",
    "wof:name":"Saint-Eloi",
    "wof:placetype":"locality"
},
  "geometry": {"coordinates":[-3.46667,48.25],"type":"Point"}
}