{
  "type": "Feature",
  "properties": {
    "gn:admin1_code":"24",
    "gn:admin2_code":"41",
    "gn:admin3_code":"413",
    "gn:admin4_code":"41231",
    "gn:asciiname":"Courmeme",
    "gn:country_code":"FR",
    "gn:dem":101,
    "gn:feature_class":"P",
    "gn:feature_code":"PPL",
    "gn:name":"Courmeme",
    "gn:population":0,
    "gn:timezone":"Europe/Paris",
    "iso:country":"FR",
    "wof:name":"Courmeme",
    "wof:placetype":"locality"
},
  "geometry": {"coordinates":[1.95257,47.54886],"type":"Point"}
}