{
  "type": "Feature",
  "properties": {
    "gn:admin1_code":"44",
    "gn:admin2_code":"10",
    "gn:admin3_code":"103",
    "gn:admin4_code":"10412",
    "gn:asciiname":"Belley",
    "gn:country_code":"FR",
    "gn:dem":107,
    "gn:feature_class":"P",
    "gn:feature_code":"PPL",
    "gn:name":"Belley",
    "gn:population":0,
    "gn:timezone":"Europe/Paris",
    "iso:country":"FR",
    "name:als_x_preferred":[
        "Belley"
    ],
    "name:ara_x_preferred":[
        "\u0628\u064a\u0644\u064a"
    ],
    "name:bre_x_preferred":[
        "Belley"
    ],
    "name:bug_x_preferred":[
        "Belley"
    ],
    "name:cat_x_preferred":[
        "Belley"
    ],
    "name:ceb_x_preferred":[
        "Belley"
    ],
    "name:ces_x_preferred":[
        "Belley"
    ],
    "name:deu_x_preferred":[
        "Belley"
    ],
    "name:epo_x_preferred":[
        "Belley"
    ],
    "name:est_x_preferred":[
        "Belley"
    ],
    "name:eus_x_preferred":[
        "Belley"
    ],
    "name:fas_x_preferred":[
        "\u0628\u0644\u06cc"
    ],
    "name:fin_x_preferred":[
        "Belley"
    ],
    "name:fra_x_preferred":[
        "Belley"
    ],
    "name:frp_x_preferred":[
        "B\u00e8l\u00ea"
    ],
    "name:glg_x_preferred":[
        "Belley"
    ],
    "name:hun_x_preferred":[
        "Belley"
    ],
    "name:hye_x_preferred":[
        "\u0532\u0565\u056c\u056c\u0565"
    ],
    "name:ind_x_preferred":[
        "Belley"
    ],
    "name:ita_x_preferred":[
        "Belley"
    ],
    "name:jpn_x_preferred":[
        "\u30d9\u30ec\u30fc"
    ],
    "name:lat_x_preferred":[
        "Bellicium"
    ],
    "name:lmo_x_preferred":[
        "Belley"
    ],
    "name:ltz_x_preferred":[
        "Belley"
    ],
    "name:mkd_x_preferred":[
        "\u0411\u0435\u043b\u0435"
    ],
    "name:mlg_x_preferred":[
        "Belley"
    ],
    "name:msa_x_preferred":[
        "Belley"
    ],
    "name:nld_x_preferred":[
        "Belley"
    ],
    "name:nno_x_preferred":[
        "Belley"
    ],
    "name:oci_x_preferred":[
        "Belley"
    ],
    "name:pam_x_preferred":[
        "Belley"
    ],
    "name:pol_x_preferred":[
        "Belley"
    ],
    "name:por_x_preferred":[
        "Belley"
    ],
    "name:ron_x_preferred":[
        "Belley"
    ],
    "name:rus_x_preferred":[
        "\u0411\u0435\u043b\u043b\u0435"
    ],
    "name:slk_x_preferred":[
        "Belley"
    ],
    "name:slv_x_preferred":[
        "Belley"
    ],
    "name:sme_x_preferred":[
        "Belley"
    ],
    "name:spa_x_preferred":[
        "Belley"
    ],
    "name:sqi_x_preferred":[
        "Belley"
    ],
    "name:srp_x_preferred":[
        "\u0411\u0435\u043b\u0435"
    ],
    "name:swe_x_preferred":[
        "Belley"
    ],
    "name:tgl_x_preferred":[
        "Belley"
    ],
    "name:tur_x_preferred":[
        "Belley"
    ],
    "name:ukr_x_preferred":[
        "\u0411\u0435\u043b\u043b\u0435"
    ],
    "name:urd_x_preferred":[
        "\u0628\u0644\u06d2"
    ],
    "name:uzb_x_preferred":[
        "Belley"
    ],
    "name:vie_x_preferred":[
        "Belley"
    ],
    "name:war_x_preferred":[
        "Belley"
    ],
    "name:zea_x_preferred":[
        "Belley"
    ],
    "wof:name":"Belley",
    "wof:placetype":"locality"
},
  "geometry": {"coordinates":[4.14501,48.30219],"type":"Point"}
}