{
  "type": "Feature",
  "properties": {
    "gn:admin1_code":"84",
    "gn:admin2_code":"43",
    "gn:admin3_code":"431",
    "gn:admin4_code":"43017",
    "gn:asciiname":"Lindes",
    "gn:country_code":"FR",
    "gn:dem":413,
    "gn:feature_class":"P",
    "gn:feature_code":"PPL",
    "gn:name":"Lindes",
    "gn:population":0,
    "gn:timezone":"Europe/Paris",
    "iso:country":"FR",
    "name:ast_x_preferred":[
        "\u1e36\u1e37indes"
    ],
    "name:deu_x_preferred":[
        "Lindes"
    ],
    "name:spa_x_preferred":[
        "Lindes"
    ],
    "wof:name":"Lindes",
    "wof:placetype":"locality"
},
  "geometry": {"coordinates":[3.38392,45.35195],"type":"Point"}
}