{
  "type": "Feature",
  "properties": {
    "gn:admin1_code":"53",
    "gn:admin2_code":"22",
    "gn:admin3_code":"222",
    "gn:admin4_code":"22139",
    "gn:asciiname":"Coat-Piquet",
    "gn:country_code":"FR",
    "gn:dem":272,
    "gn:feature_class":"P",
    "gn:feature_code":"PPL",
    "gn:name":"Coat-Piquet",
    "gn:population":0,
    "gn:timezone":"Europe/Paris",
    "iso:country":"FR",
    "wof:name":"Coat-Piquet",
    "wof:placetype":"locality"
},
  "geometry": {"coordinates":[-3.17393,48.39308],"type":"Point"}
}