{
  "type": "Feature",
  "properties": {
    "iso:country":"FR",
    "wof:name":"Victor Hugo",
    "wof:placetype":"neighbourhood"
},
  "geometry": {"coordinates":[-0.57604810876001,44.83598809317289],"type":"Point"}
}