{
  "type": "Feature",
  "properties": {
    "gn:admin1_code":"75",
    "gn:admin2_code":"86",
    "gn:admin3_code":"862",
    "gn:admin4_code":"86278",
    "gn:asciiname":"Vaux",
    "gn:country_code":"FR",
    "gn:dem":125,
    "gn:feature_class":"P",
    "gn:feature_code":"PPL",
    "gn:name":"Vaux",
    "gn:population":669,
    "gn:timezone":"Europe/Paris",
    "iso:country":"FR",
    "name:und_x_variant":[
        "Vaux-en Couh\u00e9",
        "Vaux"
    ],
    "wof:name":"Vaux",
    "wof:placetype":"locality",
    "wof:population":669
},
  "geometry": {"coordinates":[0.22134,46.29821],"type":"Point"}
}