{
  "type": "Feature",
  "properties": {
    "frgov:code_epci":"200070035",
    "frgov:insee_arr":"2",
    "frgov:insee_com":"86278",
    "frgov:insee_dep":"86",
    "frgov:insee_reg":"75",
    "frgov:nom_com":"Vaux",
    "frgov:nom_com_m":"VAUX",
    "frgov:nom_dep":"VIENNE",
    "frgov:nom_reg":"NOUVELLE-AQUITAINE",
    "frgov:statut":"Commune simple",
    "gn:admin1_code":"75",
    "gn:admin2_code":"86",
    "gn:admin3_code":"862",
    "gn:admin4_code":"86278",
    "gn:asciiname":"Vaux",
    "gn:country_code":"FR",
    "gn:dem":125,
    "gn:feature_class":"P",
    "gn:feature_code":"PPL",
    "gn:name":"Vaux",
    "gn:population":669,
    "gn:timezone":"Europe/Paris",
    "iso:country":"FR",
    "name:ceb_x_preferred":[
        "Vaux"
    ],
    "name:deu_x_preferred":[
        "Vaux"
    ],
    "name:epo_x_preferred":[
        "Vaux"
    ],
    "name:fra_x_preferred":[
        "Vaux"
    ],
    "name:hye_x_preferred":[
        "\u054e\u0578"
    ],
    "name:ita_x_preferred":[
        "Vaux"
    ],
    "name:jpn_x_preferred":[
        "\u30f4\u30a9\u30fc"
    ],
    "name:nds_x_preferred":[
        "Vaux"
    ],
    "name:nld_x_preferred":[
        "Vaux"
    ],
    "name:oci_x_preferred":[
        "Vaux"
    ],
    "name:pms_x_preferred":[
        "Vaux"
    ],
    "name:pol_x_preferred":[
        "Vaux"
    ],
    "name:por_x_preferred":[
        "Vaux"
    ],
    "name:slk_x_preferred":[
        "Vaux"
    ],
    "name:spa_x_preferred":[
        "Vaux"
    ],
    "name:swe_x_preferred":[
        "Vaux"
    ],
    "name:und_x_variant":[
        "Vaux-en Couh\u00e9",
        "Vaux"
    ],
    "qs:a0":"France",
    "qs:a1":"VIENNE",
    "qs:a1_lc":"86",
    "qs:a1r":"POITOU-CHARENTES",
    "qs:a1r_lc":"54",
    "qs:a2_lc":"06",
    "qs:a2r_lc":"2",
    "qs:adm0":"France",
    "qs:adm0_a3":"FRA",
    "qs:la":"VAUX",
    "qs:la_lc":"86278",
    "qs:level":"localadmin",
    "qs:type":"Commune simple",
    "wof:coterminous":[
        404409941
    ],
    "wof:name":"Vaux",
    "wof:placetype":"locality",
    "wof:placetype_local":"Commune simple",
    "wof:population":669
},
  "geometry": {"coordinates":[0.22134,46.29821],"type":"Point"}
}