{
  "type": "Feature",
  "properties": {
    "gn:gn_country":"FR",
    "gn:gn_fcode":"PPL",
    "gn:gn_pop":1505,
    "gn:population":1505,
    "iso:country":"FR",
    "name:ceb_x_preferred":[
        "Offenheim"
    ],
    "name:deu_x_preferred":[
        "Offenheim"
    ],
    "name:epo_x_preferred":[
        "Offenheim"
    ],
    "name:eus_x_preferred":[
        "Offenheim"
    ],
    "name:fra_x_preferred":[
        "Offenheim"
    ],
    "name:hun_x_preferred":[
        "Offenheim"
    ],
    "name:ita_x_preferred":[
        "Offenheim"
    ],
    "name:msa_x_preferred":[
        "Offenheim"
    ],
    "name:nld_x_preferred":[
        "Offenheim"
    ],
    "name:pol_x_preferred":[
        "Offenheim"
    ],
    "name:por_x_preferred":[
        "Offenheim"
    ],
    "name:ron_x_preferred":[
        "Offenheim"
    ],
    "name:rus_x_preferred":[
        "\u041e\u0444\u0444\u0435\u043d\u0445\u0430\u0439\u043c"
    ],
    "name:spa_x_preferred":[
        "Offenheim"
    ],
    "name:srp_x_preferred":[
        "\u041e\u0444\u0435\u043d\u0445\u0430\u0458\u043c"
    ],
    "name:ukr_x_preferred":[
        "\u041e\u0444\u0444\u0435\u043d\u0433\u0430\u0439\u043c"
    ],
    "name:uzb_x_preferred":[
        "Offenheim"
    ],
    "name:vie_x_preferred":[
        "Offenheim"
    ],
    "name:vol_x_preferred":[
        "Offenheim"
    ],
    "name:war_x_preferred":[
        "Offenheim"
    ],
    "name:zho_x_preferred":[
        "\u5965\u82ac\u6d77\u59c6"
    ],
    "qs_pg:aaroncc":"FR",
    "qs_pg:gn_country":"FR",
    "qs_pg:gn_fcode":"PPL",
    "qs_pg:gn_pop":1505,
    "qs_pg:name":"Offenheim",
    "qs_pg:name_adm0":"France",
    "qs_pg:name_adm1":"Alsace",
    "qs_pg:photos_9r":0,
    "qs_pg:photos_sr":0,
    "qs_pg:pop_sr":3,
    "qs_pg:qs_pg_placetype":"locality",
    "qs_pg:qs_pg_placetype_gp":"Town",
    "qs_pg:woe_adm0":23424819,
    "woe:adm0_id":23424819,
    "woe:name_adm0":"France",
    "woe:name_adm1":"Alsace",
    "woe:placetype":"Town",
    "wof:name":"Offenheim",
    "wof:placetype":"neighbourhood",
    "wof:population":1505
},
  "geometry": {"coordinates":[7.61752,48.63074],"type":"Point"}
}