{
  "type": "Feature",
  "properties": {
    "gn:admin1_code":"52",
    "gn:admin2_code":"85",
    "gn:admin3_code":"852",
    "gn:admin4_code":"85039",
    "gn:asciiname":"Saint-Symphorien",
    "gn:country_code":"FR",
    "gn:dem":84,
    "gn:feature_class":"P",
    "gn:feature_code":"PPL",
    "gn:name":"Saint-Symphorien",
    "gn:population":0,
    "gn:timezone":"Europe/Paris",
    "iso:country":"FR",
    "wof:name":"Saint-Symphorien",
    "wof:placetype":"locality"
},
  "geometry": {"coordinates":[-1.17333,46.98048],"type":"Point"}
}