{
  "type": "Feature",
  "properties": {
    "gn:admin1_code":"52",
    "gn:admin2_code":"85",
    "gn:admin3_code":"852",
    "gn:admin4_code":"85039",
    "gn:asciiname":"Saint-Symphorien",
    "gn:country_code":"FR",
    "gn:dem":84,
    "gn:feature_class":"P",
    "gn:feature_code":"PPL",
    "gn:name":"Saint-Symphorien",
    "gn:population":0,
    "gn:timezone":"Europe/Paris",
    "iso:country":"FR",
    "name:ceb_x_preferred":[
        "Saint-Symphorien"
    ],
    "name:deu_x_preferred":[
        "Saint-Symphorien"
    ],
    "name:fra_x_preferred":[
        "Saint-Symphorien"
    ],
    "name:hun_x_preferred":[
        "Saint-Symphorien"
    ],
    "name:ita_x_preferred":[
        "Saint-Symphorien"
    ],
    "name:nds_x_preferred":[
        "Saint-Symphorien"
    ],
    "name:nld_x_preferred":[
        "Saint-Symphorien"
    ],
    "name:pms_x_preferred":[
        "Saint-Symphorien"
    ],
    "name:pol_x_preferred":[
        "Saint-Symphorien"
    ],
    "name:por_x_preferred":[
        "Saint-Symphorien"
    ],
    "name:rus_x_preferred":[
        "\u0421\u0435\u043d-\u0421\u0435\u043d\u0444\u043e\u0440\u044c\u0435\u043d"
    ],
    "name:slk_x_preferred":[
        "Saint-Symphorien"
    ],
    "name:spa_x_preferred":[
        "Saint-Symphorien"
    ],
    "name:swe_x_preferred":[
        "Saint-Symphorien"
    ],
    "name:ukr_x_preferred":[
        "\u0421\u0435\u043d-\u0421\u0435\u043c\u0444\u043e\u0440'\u044f\u043d"
    ],
    "wof:name":"Saint-Symphorien",
    "wof:placetype":"locality"
},
  "geometry": {"coordinates":[-1.17333,46.98048],"type":"Point"}
}