{
  "type": "Feature",
  "properties": {
    "gn:admin1_code":"75",
    "gn:admin2_code":"24",
    "gn:admin3_code":"243",
    "gn:admin4_code":"24025",
    "gn:asciiname":"Marance",
    "gn:country_code":"FR",
    "gn:dem":241,
    "gn:feature_class":"P",
    "gn:feature_code":"PPL",
    "gn:name":"Marance",
    "gn:population":0,
    "gn:timezone":"Europe/Paris",
    "iso:country":"FR",
    "wof:name":"Marance",
    "wof:placetype":"locality"
},
  "geometry": {"coordinates":[1.03802,45.10417],"type":"Point"}
}