{
  "type": "Feature",
  "properties": {
    "iso:country":"FR",
    "qs_pg:aaroncc":"FR",
    "qs_pg:name":"Ilay",
    "qs_pg:name_adm0":"France",
    "qs_pg:name_adm1":"Franche-Comt\u00e9",
    "qs_pg:photos":473,
    "qs_pg:photos_1k":96,
    "qs_pg:photos_9k":2,
    "qs_pg:photos_9r":5,
    "qs_pg:photos_all":473,
    "qs_pg:photos_sr":7,
    "qs_pg:pop_sr":0,
    "qs_pg:qs_pg_placetype":"locality",
    "qs_pg:qs_pg_placetype_gp":"Town",
    "qs_pg:woe_adm0":23424819,
    "woe:adm0_id":23424819,
    "woe:name_adm0":"France",
    "woe:name_adm1":"Franche-Comt\u00e9",
    "woe:placetype":"Town",
    "wof:name":"Ilay",
    "wof:placetype":"neighbourhood"
},
  "geometry": {"coordinates":[5.877685,46.614621],"type":"Point"}
}