{
  "type": "Feature",
  "properties": {
    "gn:admin1_code":"53",
    "gn:admin2_code":"29",
    "gn:admin3_code":"293",
    "gn:admin4_code":"29259",
    "gn:asciiname":"Penlan",
    "gn:country_code":"FR",
    "gn:dem":53,
    "gn:feature_class":"P",
    "gn:feature_code":"PPL",
    "gn:name":"Penlan",
    "gn:population":0,
    "gn:timezone":"Europe/Paris",
    "iso:country":"FR",
    "wof:name":"Penlan",
    "wof:placetype":"locality"
},
  "geometry": {"coordinates":[-3.96667,48.65],"type":"Point"}
}