{
  "type": "Feature",
  "properties": {
    "gn:admin1_code":"76",
    "gn:admin2_code":"30",
    "gn:admin3_code":"302",
    "gn:admin4_code":"30131",
    "gn:asciiname":"La Bastide",
    "gn:country_code":"FR",
    "gn:dem":97,
    "gn:feature_class":"P",
    "gn:feature_code":"PPL",
    "gn:name":"La Bastide",
    "gn:population":0,
    "gn:timezone":"Europe/Paris",
    "iso:country":"FR",
    "wof:name":"La Bastide",
    "wof:placetype":"locality"
},
  "geometry": {"coordinates":[4.46566,44.20221],"type":"Point"}
}