{
  "type": "Feature",
  "properties": {
    "gn:admin1_code":"75",
    "gn:admin2_code":"24",
    "gn:admin3_code":"243",
    "gn:admin4_code":"24546",
    "gn:asciiname":"Temple-Laguyon",
    "gn:country_code":"FR",
    "gn:dem":226,
    "gn:feature_class":"P",
    "gn:feature_code":"PPL",
    "gn:name":"Temple-Laguyon",
    "gn:population":0,
    "gn:timezone":"Europe/Paris",
    "iso:country":"FR",
    "wof:name":"Temple-Laguyon",
    "wof:placetype":"locality"
},
  "geometry": {"coordinates":[1.1006,45.234],"type":"Point"}
}