{
  "type": "Feature",
  "properties": {
    "iso:country":"FR",
    "name:fra_x_preferred":[
        "M\u00e9nival"
    ],
    "wof:name":"Menival",
    "wof:placetype":"neighbourhood"
},
  "geometry": {"coordinates":[4.78543622893692,45.75762534368627],"type":"Point"}
}