{
  "type": "Feature",
  "properties": {
    "gn:admin1_code":"53",
    "gn:admin2_code":"29",
    "gn:admin3_code":"294",
    "gn:admin4_code":"29171",
    "gn:asciiname":"Kermatheano",
    "gn:country_code":"FR",
    "gn:dem":22,
    "gn:feature_class":"P",
    "gn:feature_code":"PPL",
    "gn:name":"Kermath\u00e9ano",
    "gn:population":0,
    "gn:timezone":"Europe/Paris",
    "iso:country":"FR",
    "wof:name":"Kermatheano",
    "wof:placetype":"locality"
},
  "geometry": {"coordinates":[-4.3004,47.81867],"type":"Point"}
}