{
  "type": "Feature",
  "properties": {
    "iso:country":"FR",
    "name:eng_x_preferred":[
        "Mont-Boron"
    ],
    "name:fra_x_preferred":[
        "Mont-Boron"
    ],
    "wof:name":"Mont-Boron",
    "wof:placetype":"neighbourhood"
},
  "geometry": {"coordinates":[7.29425274473181,43.69848922613657],"type":"Point"}
}