{
  "type": "Feature",
  "properties": {
    "gn:admin1_code":"84",
    "gn:admin2_code":"43",
    "gn:admin3_code":"432",
    "gn:admin4_code":"43156",
    "gn:asciiname":"Coste Chaude",
    "gn:country_code":"FR",
    "gn:dem":1112,
    "gn:feature_class":"P",
    "gn:feature_code":"PPL",
    "gn:name":"Coste Chaude",
    "gn:population":0,
    "gn:timezone":"Europe/Paris",
    "iso:country":"FR",
    "wof:name":"Coste Chaude",
    "wof:placetype":"locality"
},
  "geometry": {"coordinates":[4.03396,44.87564],"type":"Point"}
}