{
  "type": "Feature",
  "properties": {
    "gn:admin1_code":"53",
    "gn:admin2_code":"29",
    "gn:admin3_code":"293",
    "gn:admin4_code":"29030",
    "gn:asciiname":"Kervaliou",
    "gn:country_code":"FR",
    "gn:dem":3,
    "gn:feature_class":"P",
    "gn:feature_code":"PPL",
    "gn:name":"Kervaliou",
    "gn:population":0,
    "gn:timezone":"Europe/Paris",
    "iso:country":"FR",
    "wof:name":"Kervaliou",
    "wof:placetype":"locality"
},
  "geometry": {"coordinates":[-4.11822,48.69033],"type":"Point"}
}