{
  "type": "Feature",
  "properties": {
    "gn:admin1_code":"76",
    "gn:admin2_code":"12",
    "gn:admin3_code":"121",
    "gn:admin4_code":"12225",
    "gn:asciiname":"Luzancon",
    "gn:country_code":"FR",
    "gn:dem":553,
    "gn:feature_class":"P",
    "gn:feature_code":"PPL",
    "gn:name":"Luzan\u00e7on",
    "gn:population":0,
    "gn:timezone":"Europe/Paris",
    "iso:country":"FR",
    "name:und_x_variant":[
        "Luzen\u00e7on",
        "Luzan\u00e7on"
    ],
    "wof:name":"Luzancon",
    "wof:placetype":"locality"
},
  "geometry": {"coordinates":[2.96994,44.06514],"type":"Point"}
}