{
  "type": "Feature",
  "properties": {
    "gn:admin1_code":"11",
    "gn:admin2_code":"95",
    "gn:admin3_code":"953",
    "gn:admin4_code":"95150",
    "gn:asciiname":"Villarceaux",
    "gn:country_code":"FR",
    "gn:dem":128,
    "gn:feature_class":"P",
    "gn:feature_code":"PPL",
    "gn:name":"Villarceaux",
    "gn:population":0,
    "gn:timezone":"Europe/Paris",
    "iso:country":"FR",
    "wof:name":"Villarceaux",
    "wof:placetype":"locality"
},
  "geometry": {"coordinates":[1.71318,49.11894],"type":"Point"}
}