{
  "type": "Feature",
  "properties": {
    "gn:admin1_code":"27",
    "gn:admin2_code":"58",
    "gn:admin3_code":"583",
    "gn:admin4_code":"58160",
    "gn:asciiname":"Corcelles",
    "gn:country_code":"FR",
    "gn:dem":185,
    "gn:feature_class":"P",
    "gn:feature_code":"PPL",
    "gn:name":"Corcelles",
    "gn:population":0,
    "gn:timezone":"Europe/Paris",
    "iso:country":"FR",
    "name:cat_x_preferred":[
        "Corcelles"
    ],
    "name:deu_x_preferred":[
        "Corcelles"
    ],
    "name:epo_x_preferred":[
        "Corcelles"
    ],
    "name:eus_x_preferred":[
        "Corcelles"
    ],
    "name:fra_x_preferred":[
        "Corcelles"
    ],
    "name:glg_x_preferred":[
        "Corcelles"
    ],
    "name:hun_x_preferred":[
        "Corcelles"
    ],
    "name:ita_x_preferred":[
        "Corcelles"
    ],
    "name:msa_x_preferred":[
        "Corcelles"
    ],
    "name:nld_x_preferred":[
        "Corcelles"
    ],
    "name:por_x_preferred":[
        "Corcelles"
    ],
    "name:ron_x_preferred":[
        "Corcelles"
    ],
    "name:rus_x_preferred":[
        "\u041a\u043e\u0440\u0441\u0435\u043b\u044c"
    ],
    "name:slk_x_preferred":[
        "Corcelles"
    ],
    "name:spa_x_preferred":[
        "Corcelles"
    ],
    "name:swe_x_preferred":[
        "Corcelles"
    ],
    "name:vie_x_preferred":[
        "Corcelles"
    ],
    "name:vol_x_preferred":[
        "Corcelles"
    ],
    "name:war_x_preferred":[
        "Corcelles"
    ],
    "wof:name":"Corcelles",
    "wof:placetype":"locality"
},
  "geometry": {"coordinates":[3.07851,46.99652],"type":"Point"}
}