{
  "type": "Feature",
  "properties": {
    "gn:admin1_code":"84",
    "gn:admin2_code":"63",
    "gn:admin3_code":"633",
    "gn:admin4_code":"63279",
    "gn:asciiname":"Chareire",
    "gn:country_code":"FR",
    "gn:dem":1173,
    "gn:feature_class":"P",
    "gn:feature_code":"PPL",
    "gn:name":"Chareire",
    "gn:population":0,
    "gn:timezone":"Europe/Paris",
    "iso:country":"FR",
    "wof:name":"Chareire",
    "wof:placetype":"locality"
},
  "geometry": {"coordinates":[2.77768,45.48297],"type":"Point"}
}