{
  "type": "Feature",
  "properties": {
    "gn:admin1_code":"94",
    "gn:admin2_code":"2B",
    "gn:admin3_code":"2B3",
    "gn:admin4_code":"2B218",
    "gn:asciiname":"Pedale",
    "gn:country_code":"FR",
    "gn:dem":330,
    "gn:feature_class":"P",
    "gn:feature_code":"PPL",
    "gn:name":"Pedale",
    "gn:population":0,
    "gn:timezone":"Europe/Paris",
    "iso:country":"FR",
    "wof:name":"Pedale",
    "wof:placetype":"locality"
},
  "geometry": {"coordinates":[9.33333,42.18333],"type":"Point"}
}