{
  "type": "Feature",
  "properties": {
    "gn:admin1_code":"75",
    "gn:admin2_code":"24",
    "gn:admin3_code":"243",
    "gn:admin4_code":"24477",
    "gn:asciiname":"Saint-Pardoux-de-Drone",
    "gn:cc2":"FR",
    "gn:country_code":"FR",
    "gn:dem":122,
    "gn:feature_class":"P",
    "gn:feature_code":"PPL",
    "gn:name":"Saint-Pardoux-de-Dr\u00f4ne",
    "gn:population":0,
    "gn:timezone":"Europe/Paris",
    "iso:country":"FR",
    "name:bug_x_preferred":[
        "Saint-Pardoux-de-Dr\u00f4ne"
    ],
    "name:cat_x_preferred":[
        "Sent Pardol de Drona"
    ],
    "name:ceb_x_preferred":[
        "Saint-Pardoux-de-Dr\u00f4ne"
    ],
    "name:deu_x_preferred":[
        "Saint-Pardoux-de-Dr\u00f4ne"
    ],
    "name:eus_x_preferred":[
        "Saint-Pardoux-de-Dr\u00f4ne"
    ],
    "name:fra_x_preferred":[
        "Saint-Pardoux-de-Dr\u00f4ne"
    ],
    "name:hun_x_preferred":[
        "Saint-Pardoux-de-Dr\u00f4ne"
    ],
    "name:ita_x_preferred":[
        "Saint-Pardoux-de-Dr\u00f4ne"
    ],
    "name:kaz_x_preferred":[
        "\u0421\u0435\u043d-\u041f\u0430\u0440\u0434\u0443-\u0434\u0435-\u0414\u0440\u043e\u043d"
    ],
    "name:lat_x_preferred":[
        "Saint-Pardoux-de-Dr\u00f4ne"
    ],
    "name:mlg_x_preferred":[
        "Saint-Pardoux-de-Dr\u00f4ne"
    ],
    "name:msa_x_preferred":[
        "Saint-Pardoux-de-Dr\u00f4ne"
    ],
    "name:nld_x_preferred":[
        "Saint-Pardoux-de-Dr\u00f4ne"
    ],
    "name:oci_x_preferred":[
        "Sent Pardol de Drona"
    ],
    "name:pms_x_preferred":[
        "Saint-Pardoux-de-Dr\u00f4ne"
    ],
    "name:pol_x_preferred":[
        "Saint-Pardoux-de-Dr\u00f4ne"
    ],
    "name:por_x_preferred":[
        "Saint-Pardoux-de-Dr\u00f4ne"
    ],
    "name:ron_x_preferred":[
        "Saint-Pardoux-de-Dr\u00f4ne"
    ],
    "name:slk_x_preferred":[
        "Saint-Pardoux-de-Dr\u00f4ne"
    ],
    "name:spa_x_preferred":[
        "Saint-Pardoux-de-Dr\u00f4ne"
    ],
    "name:swe_x_preferred":[
        "Saint-Pardoux-de-Dr\u00f4ne"
    ],
    "name:ukr_x_preferred":[
        "\u0421\u0435\u043d-\u041f\u0430\u0440\u0434\u0443-\u0434\u0435-\u0414\u0440\u043e\u043d"
    ],
    "name:und_x_variant":[
        "Saint Pardoux"
    ],
    "name:urd_x_preferred":[
        "\u0633\u06cc\u0646\u0679-\u067e\u0627\u0631\u062f\u0648-\u062f\u06d2-\u0688\u0631\u0648\u0646"
    ],
    "name:uzb_x_preferred":[
        "Saint-Pardoux-de-Dr\u00f4ne"
    ],
    "name:vol_x_preferred":[
        "Saint-Pardoux-de-Dr\u00f4ne"
    ],
    "name:war_x_preferred":[
        "Saint-Pardoux-de-Dr\u00f4ne"
    ],
    "name:zho_x_preferred":[
        "\u5723\u5e15\u5c14\u675c\u5fb7\u5fb7\u9f99"
    ],
    "name:zho_x_variant":[
        "\u5723\u5e15\u5c14\u675c-\u5fb7\u5fb7\u7f57\u8bb7"
    ],
    "wof:name":"Saint-Pardoux-de-Drone",
    "wof:placetype":"locality"
},
  "geometry": {"coordinates":[0.41667,45.21667],"type":"Point"}
}