{
  "type": "Feature",
  "properties": {
    "gn:admin1_code":"52",
    "gn:admin2_code":"44",
    "gn:admin3_code":"442",
    "gn:admin4_code":"44120",
    "gn:asciiname":"Le Pe de Buzay",
    "gn:country_code":"FR",
    "gn:dem":13,
    "gn:feature_class":"P",
    "gn:feature_code":"PPL",
    "gn:name":"Le P\u00e9 de Buzay",
    "gn:population":0,
    "gn:timezone":"Europe/Paris",
    "iso:country":"FR",
    "wof:name":"Le Pe de Buzay",
    "wof:placetype":"locality"
},
  "geometry": {"coordinates":[-1.81682,47.20365],"type":"Point"}
}