{
  "type": "Feature",
  "properties": {
    "gn:admin1_code":"52",
    "gn:admin2_code":"44",
    "gn:admin3_code":"441",
    "gn:admin4_code":"44056",
    "gn:asciiname":"Le Grand Merimont",
    "gn:country_code":"FR",
    "gn:dem":77,
    "gn:feature_class":"P",
    "gn:feature_code":"PPL",
    "gn:name":"Le Grand Merimont",
    "gn:population":0,
    "gn:timezone":"Europe/Paris",
    "iso:country":"FR",
    "wof:name":"Le Grand Merimont",
    "wof:placetype":"locality"
},
  "geometry": {"coordinates":[-1.79154,47.36239000000001],"type":"Point"}
}