{
  "type": "Feature",
  "properties": {
    "gn:admin1_code":"11",
    "gn:admin2_code":"78",
    "gn:admin3_code":"782",
    "gn:admin4_code":"78601",
    "gn:asciiname":"Greffiers",
    "gn:country_code":"FR",
    "gn:dem":161,
    "gn:feature_class":"P",
    "gn:feature_code":"PPL",
    "gn:name":"Greffiers",
    "gn:population":0,
    "gn:timezone":"Europe/Paris",
    "iso:country":"FR",
    "name:und_x_variant":[
        "Greffier",
        "Greffiers"
    ],
    "wof:name":"Greffiers",
    "wof:placetype":"locality"
},
  "geometry": {"coordinates":[1.84006,48.61395],"type":"Point"}
}