{
  "type": "Feature",
  "properties": {
    "gn:admin1_code":"84",
    "gn:admin2_code":"15",
    "gn:admin3_code":"152",
    "gn:admin4_code":"15230",
    "gn:asciiname":"Tonnac",
    "gn:cc2":"FR",
    "gn:country_code":"FR",
    "gn:dem":686,
    "gn:feature_class":"P",
    "gn:feature_code":"PPL",
    "gn:name":"Tonnac",
    "gn:population":0,
    "gn:timezone":"Europe/Paris",
    "iso:country":"FR",
    "name:cat_x_preferred":[
        "Totnac"
    ],
    "name:ceb_x_preferred":[
        "Tonnac"
    ],
    "name:deu_x_preferred":[
        "Tonnac"
    ],
    "name:eus_x_preferred":[
        "Tonnac"
    ],
    "name:fra_x_preferred":[
        "Tonnac"
    ],
    "name:hun_x_preferred":[
        "Tonnac"
    ],
    "name:ita_x_preferred":[
        "Tonnac"
    ],
    "name:lat_x_preferred":[
        "Tonnac"
    ],
    "name:mlg_x_preferred":[
        "Tonnac"
    ],
    "name:msa_x_preferred":[
        "Tonnac"
    ],
    "name:nld_x_preferred":[
        "Tonnac"
    ],
    "name:oci_x_preferred":[
        "Totnac"
    ],
    "name:pms_x_preferred":[
        "Tonnac"
    ],
    "name:pol_x_preferred":[
        "Tonnac"
    ],
    "name:por_x_preferred":[
        "Tonnac"
    ],
    "name:ron_x_preferred":[
        "Tonnac"
    ],
    "name:rus_x_preferred":[
        "\u0422\u043e\u043d\u043d\u0430\u043a"
    ],
    "name:slk_x_preferred":[
        "Tonnac"
    ],
    "name:spa_x_preferred":[
        "Tonnac"
    ],
    "name:swe_x_preferred":[
        "Tonnac"
    ],
    "name:ukr_x_preferred":[
        "\u0422\u043e\u043d\u043d\u0430\u043a"
    ],
    "name:und_x_variant":[
        "Tonnat",
        "Tonnac"
    ],
    "name:vie_x_preferred":[
        "Tonnac"
    ],
    "name:vol_x_preferred":[
        "Tonnac"
    ],
    "name:war_x_preferred":[
        "Tonnac"
    ],
    "name:zho_x_preferred":[
        "\u6258\u7eb3\u514b"
    ],
    "wof:name":"Tonnac",
    "wof:placetype":"locality"
},
  "geometry": {"coordinates":[2.33331,45.25562],"type":"Point"}
}