{
  "type": "Feature",
  "properties": {
    "gn:admin1_code":"84",
    "gn:admin2_code":"15",
    "gn:admin3_code":"152",
    "gn:admin4_code":"15230",
    "gn:asciiname":"Tonnac",
    "gn:cc2":"FR",
    "gn:country_code":"FR",
    "gn:dem":686,
    "gn:feature_class":"P",
    "gn:feature_code":"PPL",
    "gn:name":"Tonnac",
    "gn:population":0,
    "gn:timezone":"Europe/Paris",
    "iso:country":"FR",
    "name:und_x_variant":[
        "Tonnat",
        "Tonnac"
    ],
    "wof:name":"Tonnac",
    "wof:placetype":"locality"
},
  "geometry": {"coordinates":[2.33331,45.25562],"type":"Point"}
}