{
  "type": "Feature",
  "properties": {
    "gn:admin1_code":"53",
    "gn:admin2_code":"56",
    "gn:admin3_code":"561",
    "gn:admin4_code":"56181",
    "gn:asciiname":"Mezat de Kerzo",
    "gn:country_code":"FR",
    "gn:dem":12,
    "gn:feature_class":"P",
    "gn:feature_code":"PPLL",
    "gn:name":"Mezat de Kerzo",
    "gn:population":0,
    "gn:timezone":"Europe/Paris",
    "iso:country":"FR",
    "wof:name":"Mezat de Kerzo",
    "wof:placetype":"locality"
},
  "geometry": {"coordinates":[-3.34722,47.71167],"type":"Point"}
}