{
  "type": "Feature",
  "properties": {
    "gn:admin1_code":"24",
    "gn:admin2_code":"28",
    "gn:admin3_code":"281",
    "gn:admin4_code":"28189",
    "gn:asciiname":"Boinville",
    "gn:country_code":"FR",
    "gn:dem":132,
    "gn:feature_class":"P",
    "gn:feature_code":"PPL",
    "gn:name":"Boinville",
    "gn:population":0,
    "gn:timezone":"Europe/Paris",
    "iso:country":"FR",
    "wof:name":"Boinville",
    "wof:placetype":"locality"
},
  "geometry": {"coordinates":[1.77624,48.20799],"type":"Point"}
}