{
  "type": "Feature",
  "properties": {
    "gn:admin1_code":"27",
    "gn:admin2_code":"89",
    "gn:admin3_code":"893",
    "gn:admin4_code":"89370",
    "gn:asciiname":"Fontaine",
    "gn:country_code":"FR",
    "gn:dem":170,
    "gn:feature_class":"P",
    "gn:feature_code":"PPL",
    "gn:name":"Fontaine",
    "gn:population":0,
    "gn:timezone":"Europe/Paris",
    "iso:country":"FR",
    "name:und_x_variant":[
        "Fontaines",
        "Fontaine"
    ],
    "wof:name":"Fontaine",
    "wof:placetype":"locality"
},
  "geometry": {"coordinates":[3.11826,48.19087],"type":"Point"}
}