{
  "type": "Feature",
  "properties": {
    "gn:admin1_code":"27",
    "gn:admin2_code":"89",
    "gn:admin3_code":"891",
    "gn:admin4_code":"89253",
    "gn:asciiname":"Magny",
    "gn:country_code":"FR",
    "gn:dem":133,
    "gn:feature_class":"P",
    "gn:feature_code":"PPL",
    "gn:name":"Magny",
    "gn:population":0,
    "gn:timezone":"Europe/Paris",
    "iso:country":"FR",
    "name:ceb_x_preferred":[
        "Magny"
    ],
    "name:ces_x_preferred":[
        "Magny"
    ],
    "name:deu_x_preferred":[
        "Magny"
    ],
    "name:epo_x_preferred":[
        "Magny"
    ],
    "name:fra_x_preferred":[
        "Magny"
    ],
    "name:ita_x_preferred":[
        "Magny"
    ],
    "name:nds_x_preferred":[
        "Magny"
    ],
    "name:nld_x_preferred":[
        "Magny"
    ],
    "name:oci_x_preferred":[
        "Magny"
    ],
    "name:pms_x_preferred":[
        "Magny"
    ],
    "name:pol_x_preferred":[
        "Magny"
    ],
    "name:por_x_preferred":[
        "Magny"
    ],
    "name:scn_x_preferred":[
        "Magny"
    ],
    "name:slk_x_preferred":[
        "Magny"
    ],
    "name:spa_x_preferred":[
        "Magny"
    ],
    "name:swe_x_preferred":[
        "Magny"
    ],
    "name:ukr_x_preferred":[
        "\u041c\u0430\u043d\u044c\u0457"
    ],
    "wof:name":"Magny",
    "wof:placetype":"locality"
},
  "geometry": {"coordinates":[3.62655,47.54798],"type":"Point"}
}