{
  "type": "Feature",
  "properties": {
    "gn:admin1_code":"76",
    "gn:admin2_code":"48",
    "gn:admin3_code":"482",
    "gn:admin4_code":"48165",
    "gn:asciiname":"Taupinet",
    "gn:country_code":"FR",
    "gn:dem":1297,
    "gn:feature_class":"P",
    "gn:feature_code":"PPL",
    "gn:name":"Taupinet",
    "gn:population":0,
    "gn:timezone":"Europe/Paris",
    "iso:country":"FR",
    "wof:name":"Taupinet",
    "wof:placetype":"locality"
},
  "geometry": {"coordinates":[3.16558,44.60042],"type":"Point"}
}