{
  "type": "Feature",
  "properties": {
    "gn:admin1_code":"24",
    "gn:admin2_code":"18",
    "gn:admin3_code":"182",
    "gn:admin4_code":"18195",
    "gn:asciiname":"Cernay",
    "gn:country_code":"FR",
    "gn:dem":218,
    "gn:feature_class":"P",
    "gn:feature_code":"PPL",
    "gn:name":"Cernay",
    "gn:population":0,
    "gn:timezone":"Europe/Paris",
    "iso:country":"FR",
    "name:als_x_preferred":[
        "Cernay"
    ],
    "name:bre_x_preferred":[
        "Cernay"
    ],
    "name:ceb_x_preferred":[
        "Cernay"
    ],
    "name:deu_x_preferred":[
        "Cernay"
    ],
    "name:fra_x_preferred":[
        "Cernay"
    ],
    "name:ind_x_preferred":[
        "Cernay"
    ],
    "name:ita_x_preferred":[
        "Cernay"
    ],
    "name:nds_x_preferred":[
        "Cernay"
    ],
    "name:nld_x_preferred":[
        "Cernay"
    ],
    "name:pms_x_preferred":[
        "Cernay"
    ],
    "name:pol_x_preferred":[
        "Cernay"
    ],
    "name:ron_x_preferred":[
        "Cernay"
    ],
    "name:rus_x_preferred":[
        "\u0421\u0435\u0440\u043d\u0435"
    ],
    "name:slk_x_preferred":[
        "Cernay"
    ],
    "name:spa_x_preferred":[
        "Cernay"
    ],
    "name:srp_x_preferred":[
        "\u0421\u0435\u0440\u043d\u0435"
    ],
    "name:swe_x_preferred":[
        "Cernay"
    ],
    "name:ukr_x_preferred":[
        "\u0421\u0435\u0440\u043d\u0435"
    ],
    "wof:name":"Cernay",
    "wof:placetype":"locality"
},
  "geometry": {"coordinates":[2.84614,46.85635],"type":"Point"}
}