{
  "type": "Feature",
  "properties": {
    "gn:admin1_code":"24",
    "gn:admin2_code":"18",
    "gn:admin3_code":"182",
    "gn:admin4_code":"18195",
    "gn:asciiname":"Cernay",
    "gn:country_code":"FR",
    "gn:dem":218,
    "gn:feature_class":"P",
    "gn:feature_code":"PPL",
    "gn:name":"Cernay",
    "gn:population":0,
    "gn:timezone":"Europe/Paris",
    "iso:country":"FR",
    "wof:name":"Cernay",
    "wof:placetype":"locality"
},
  "geometry": {"coordinates":[2.84614,46.85635],"type":"Point"}
}