{
  "type": "Feature",
  "properties": {
    "gn:admin1_code":"84",
    "gn:admin2_code":"42",
    "gn:admin3_code":"422",
    "gn:admin4_code":"42212",
    "gn:asciiname":"Bournat",
    "gn:country_code":"FR",
    "gn:dem":353,
    "gn:feature_class":"P",
    "gn:feature_code":"PPL",
    "gn:name":"Bournat",
    "gn:population":0,
    "gn:timezone":"Europe/Paris",
    "iso:country":"FR",
    "wof:name":"Bournat",
    "wof:placetype":"locality"
},
  "geometry": {"coordinates":[4.13333,45.96667],"type":"Point"}
}