{
  "type": "Feature",
  "properties": {
    "gn:admin1_code":"28",
    "gn:admin2_code":"50",
    "gn:admin3_code":"502",
    "gn:admin4_code":"50442",
    "gn:asciiname":"Le Rozel",
    "gn:country_code":"FR",
    "gn:dem":17,
    "gn:feature_class":"P",
    "gn:feature_code":"PPL",
    "gn:name":"Le Rozel",
    "gn:population":0,
    "gn:timezone":"Europe/Paris",
    "iso:country":"FR",
    "name:bug_x_preferred":[
        "Le Rozel"
    ],
    "name:cat_x_preferred":[
        "Le Rozel"
    ],
    "name:ceb_x_preferred":[
        "Le Rozel"
    ],
    "name:deu_x_preferred":[
        "Le Rozel"
    ],
    "name:eus_x_preferred":[
        "Le Rozel"
    ],
    "name:fas_x_preferred":[
        "\u0644 \u0631\u0648\u0632\u0644"
    ],
    "name:fra_x_preferred":[
        "Le Rozel"
    ],
    "name:hun_x_preferred":[
        "Le Rozel"
    ],
    "name:ita_x_preferred":[
        "Le Rozel"
    ],
    "name:kaz_x_preferred":[
        "\u041b\u0435-\u0420\u043e\u0437\u0435\u043b\u044c"
    ],
    "name:lat_x_preferred":[
        "Le Rozel"
    ],
    "name:msa_x_preferred":[
        "Le Rozel"
    ],
    "name:nld_x_preferred":[
        "Le Rozel"
    ],
    "name:oci_x_preferred":[
        "Le Rozel"
    ],
    "name:pms_x_preferred":[
        "Rozel"
    ],
    "name:pol_x_preferred":[
        "Le Rozel"
    ],
    "name:por_x_preferred":[
        "Rozel"
    ],
    "name:ron_x_preferred":[
        "Le Rozel"
    ],
    "name:slk_x_preferred":[
        "Le Rozel"
    ],
    "name:spa_x_preferred":[
        "Le Rozel"
    ],
    "name:swe_x_preferred":[
        "Le Rozel"
    ],
    "name:ukr_x_preferred":[
        "\u041b\u0435-\u0420\u043e\u0437\u0435\u043b\u044c"
    ],
    "name:uzb_x_preferred":[
        "Le Rozel"
    ],
    "name:vie_x_preferred":[
        "Le Rozel"
    ],
    "name:vol_x_preferred":[
        "Le Rozel"
    ],
    "name:war_x_preferred":[
        "Le Rozel"
    ],
    "name:zho_x_preferred":[
        "\u52d2\u7f57\u6cfd"
    ],
    "wof:name":"Le Rozel",
    "wof:placetype":"locality"
},
  "geometry": {"coordinates":[-1.828,49.4874],"type":"Point"}
}