{
  "type": "Feature",
  "properties": {
    "gn:admin1_code":"28",
    "gn:admin2_code":"50",
    "gn:admin3_code":"502",
    "gn:admin4_code":"50442",
    "gn:asciiname":"Le Rozel",
    "gn:country_code":"FR",
    "gn:dem":17,
    "gn:feature_class":"P",
    "gn:feature_code":"PPL",
    "gn:name":"Le Rozel",
    "gn:population":0,
    "gn:timezone":"Europe/Paris",
    "iso:country":"FR",
    "wof:name":"Le Rozel",
    "wof:placetype":"locality"
},
  "geometry": {"coordinates":[-1.828,49.4874],"type":"Point"}
}