{
  "type": "Feature",
  "properties": {
    "gn:admin1_code":"28",
    "gn:admin2_code":"76",
    "gn:admin3_code":"761",
    "gn:admin4_code":"76641",
    "gn:asciiname":"Bosc-le-Comte",
    "gn:country_code":"FR",
    "gn:dem":56,
    "gn:feature_class":"P",
    "gn:feature_code":"PPL",
    "gn:name":"Bosc-le-Comte",
    "gn:population":0,
    "gn:timezone":"Europe/Paris",
    "iso:country":"FR",
    "wof:name":"Bosc-le-Comte",
    "wof:placetype":"locality"
},
  "geometry": {"coordinates":[0.90931,49.83818],"type":"Point"}
}