{
  "type": "Feature",
  "properties": {
    "gn:admin1_code":"32",
    "gn:admin2_code":"60",
    "gn:admin3_code":"601",
    "gn:admin4_code":"60293",
    "gn:asciiname":"Damval",
    "gn:country_code":"FR",
    "gn:dem":137,
    "gn:feature_class":"P",
    "gn:feature_code":"PPL",
    "gn:name":"Damval",
    "gn:population":0,
    "gn:timezone":"Europe/Paris",
    "iso:country":"FR",
    "name:und_x_variant":[
        "Damral",
        "Damval"
    ],
    "wof:name":"Damval",
    "wof:placetype":"locality"
},
  "geometry": {"coordinates":[1.85036,49.19557],"type":"Point"}
}