{
  "type": "Feature",
  "properties": {
    "gn:admin1_code":"84",
    "gn:admin2_code":"15",
    "gn:admin3_code":"151",
    "gn:admin4_code":"15117",
    "gn:asciiname":"Vielcru",
    "gn:country_code":"FR",
    "gn:dem":579,
    "gn:feature_class":"P",
    "gn:feature_code":"PPL",
    "gn:name":"Vielcru",
    "gn:population":0,
    "gn:timezone":"Europe/Paris",
    "iso:country":"FR",
    "wof:name":"Vielcru",
    "wof:placetype":"locality"
},
  "geometry": {"coordinates":[2.30083,44.77511],"type":"Point"}
}