{
  "type": "Feature",
  "properties": {
    "gn:admin1_code":"24",
    "gn:admin2_code":"28",
    "gn:admin3_code":"281",
    "gn:admin4_code":"28081.0",
    "gn:asciiname":"Ecurolles",
    "gn:country_code":"FR",
    "gn:dem":154,
    "gn:feature_class":"P",
    "gn:feature_code":"PPL",
    "gn:name":"\u00c9curolles",
    "gn:population":0,
    "gn:timezone":"Europe/Paris",
    "iso:country":"FR",
    "wof:name":"Ecurolles",
    "wof:placetype":"locality"
},
  "geometry": {"coordinates":[1.31443,48.29243],"type":"Point"}
}