{
  "type": "Feature",
  "properties": {
    "gn:admin1_code":"84",
    "gn:admin2_code":"43",
    "gn:admin3_code":"432",
    "gn:admin4_code":"43004",
    "gn:asciiname":"Les Hebrards",
    "gn:country_code":"FR",
    "gn:dem":1058,
    "gn:feature_class":"P",
    "gn:feature_code":"PPL",
    "gn:name":"Les H\u00e9brards",
    "gn:population":0,
    "gn:timezone":"Europe/Paris",
    "iso:country":"FR",
    "wof:name":"Les Hebrards",
    "wof:placetype":"locality"
},
  "geometry": {"coordinates":[3.97879,44.88592],"type":"Point"}
}