{
  "type": "Feature",
  "properties": {
    "iso:country":"FR",
    "name:eng_x_preferred":[
        "La Justice"
    ],
    "name:fra_x_preferred":[
        "La Justice"
    ],
    "wof:name":"La Justice",
    "wof:placetype":"neighbourhood"
},
  "geometry": {"coordinates":[2.49360876067709,48.86294543059836],"type":"Point"}
}