{
  "type": "Feature",
  "properties": {
    "gn:admin1_code":"53",
    "gn:admin2_code":"35",
    "gn:admin3_code":"354",
    "gn:admin4_code":"35256",
    "gn:asciiname":"Le Vau Piard",
    "gn:country_code":"FR",
    "gn:dem":33,
    "gn:feature_class":"P",
    "gn:feature_code":"PPL",
    "gn:name":"Le Vau Piard",
    "gn:population":0,
    "gn:timezone":"Europe/Paris",
    "iso:country":"FR",
    "wof:name":"Le Vau Piard",
    "wof:placetype":"locality"
},
  "geometry": {"coordinates":[-2.12147,48.61018],"type":"Point"}
}