{
  "type": "Feature",
  "properties": {
    "gn:admin1_code":"84",
    "gn:admin2_code":"03",
    "gn:admin3_code":"032",
    "gn:admin4_code":"03115",
    "gn:asciiname":"Taxat",
    "gn:country_code":"FR",
    "gn:dem":302,
    "gn:feature_class":"P",
    "gn:feature_code":"PPL",
    "gn:name":"Taxat",
    "gn:population":0,
    "gn:timezone":"Europe/Paris",
    "iso:country":"FR",
    "wof:name":"Taxat",
    "wof:placetype":"locality"
},
  "geometry": {"coordinates":[3.17804,46.26409],"type":"Point"}
}