{
  "type": "Feature",
  "properties": {
    "gn:admin1_code":"84",
    "gn:admin2_code":"63",
    "gn:admin3_code":"634",
    "gn:admin4_code":"63110",
    "gn:asciiname":"Claveix",
    "gn:country_code":"FR",
    "gn:dem":828,
    "gn:feature_class":"P",
    "gn:feature_code":"PPL",
    "gn:name":"Claveix",
    "gn:population":0,
    "gn:timezone":"Europe/Paris",
    "iso:country":"FR",
    "name:und_x_variant":[
        "Le Claveix",
        "Claveix"
    ],
    "wof:name":"Claveix",
    "wof:placetype":"locality"
},
  "geometry": {"coordinates":[2.74634,45.8027],"type":"Point"}
}