{
  "type": "Feature",
  "properties": {
    "gn:admin1_code":"27",
    "gn:admin2_code":"58",
    "gn:admin3_code":"582",
    "gn:admin4_code":"58181.0",
    "gn:asciiname":"Chazy",
    "gn:country_code":"FR",
    "gn:dem":287,
    "gn:feature_class":"P",
    "gn:feature_code":"PPL",
    "gn:name":"Chazy",
    "gn:population":0,
    "gn:timezone":"Europe/Paris",
    "iso:country":"FR",
    "wof:name":"Chazy",
    "wof:placetype":"locality"
},
  "geometry": {"coordinates":[3.5412,47.28881],"type":"Point"}
}