{
  "type": "Feature",
  "properties": {
    "gn:admin1_code":"24",
    "gn:admin2_code":"45",
    "gn:admin3_code":"451",
    "gn:admin4_code":"45213",
    "gn:asciiname":"Buges",
    "gn:country_code":"FR",
    "gn:dem":133,
    "gn:feature_class":"P",
    "gn:feature_code":"PPL",
    "gn:name":"Buges",
    "gn:population":0,
    "gn:timezone":"Europe/Paris",
    "iso:country":"FR",
    "wof:name":"Buges",
    "wof:placetype":"locality"
},
  "geometry": {"coordinates":[2.58426,47.8326],"type":"Point"}
}