{
  "type": "Feature",
  "properties": {
    "gn:admin1_code":"52",
    "gn:admin2_code":"49",
    "gn:admin3_code":"492",
    "gn:admin4_code":"49381",
    "gn:asciiname":"La Brosse",
    "gn:country_code":"FR",
    "gn:dem":181,
    "gn:feature_class":"P",
    "gn:feature_code":"PPL",
    "gn:name":"La Brosse",
    "gn:population":0,
    "gn:timezone":"Europe/Paris",
    "iso:country":"FR",
    "wof:name":"La Brosse",
    "wof:placetype":"locality"
},
  "geometry": {"coordinates":[-0.6975,47.02941],"type":"Point"}
}