{
  "type": "Feature",
  "properties": {
    "gn:admin1_code":"84",
    "gn:admin2_code":"43",
    "gn:admin3_code":"431",
    "gn:admin4_code":"43107",
    "gn:asciiname":"Vialard",
    "gn:country_code":"FR",
    "gn:dem":757,
    "gn:feature_class":"P",
    "gn:feature_code":"PPL",
    "gn:name":"Vialard",
    "gn:population":0,
    "gn:timezone":"Europe/Paris",
    "iso:country":"FR",
    "wof:name":"Vialard",
    "wof:placetype":"locality"
},
  "geometry": {"coordinates":[3.61717,45.21684000000001],"type":"Point"}
}