{
  "type": "Feature",
  "properties": {
    "iso:country":"FR",
    "name:eng_x_preferred":[
        "Bords de Seine"
    ],
    "name:fra_x_preferred":[
        "Bords de Seine"
    ],
    "wof:name":"Bords de Seine",
    "wof:placetype":"neighbourhood"
},
  "geometry": {"coordinates":[2.42544315668327,48.74756452778798],"type":"Point"}
}