{
  "type": "Feature",
  "properties": {
    "iso:country":"FR",
    "name:eng_x_preferred":[
        "Alfort"
    ],
    "name:fra_x_preferred":[
        "Alfort"
    ],
    "wof:name":"Alfort",
    "wof:placetype":"neighbourhood"
},
  "geometry": {"coordinates":[2.42472790058608,48.81340720877348],"type":"Point"}
}