{
  "type": "Feature",
  "properties": {
    "gn:admin1_code":"84",
    "gn:admin2_code":"73",
    "gn:admin3_code":"731",
    "gn:admin4_code":"73150.0",
    "gn:asciiname":"La Cote-d'Aime",
    "gn:country_code":"FR",
    "gn:dem":982,
    "gn:feature_class":"P",
    "gn:feature_code":"PPL",
    "gn:name":"La C\u00f4te-d\u2019Aime",
    "gn:population":0,
    "gn:timezone":"Europe/Paris",
    "iso:country":"FR",
    "name:und_x_variant":[
        "La C\u00f4te",
        "La C\u00f4te-d\u2019Aime"
    ],
    "wof:name":"La Cote-d'Aime",
    "wof:placetype":"locality"
},
  "geometry": {"coordinates":[6.66843,45.56838],"type":"Point"}
}