{
  "type": "Feature",
  "properties": {
    "gn:admin1_code":"84",
    "gn:admin2_code":"03",
    "gn:admin3_code":"031",
    "gn:admin4_code":"03313",
    "gn:asciiname":"Les Bordes",
    "gn:country_code":"FR",
    "gn:dem":349,
    "gn:feature_class":"P",
    "gn:feature_code":"PPL",
    "gn:name":"Les Bordes",
    "gn:population":0,
    "gn:timezone":"Europe/Paris",
    "iso:country":"FR",
    "wof:name":"Les Bordes",
    "wof:placetype":"locality"
},
  "geometry": {"coordinates":[2.79418,46.57133],"type":"Point"}
}