{
  "type": "Feature",
  "properties": {
    "gn:admin1_code":"93",
    "gn:admin2_code":"04",
    "gn:admin3_code":"043",
    "gn:admin4_code":"04017",
    "gn:asciiname":"Garnier",
    "gn:country_code":"FR",
    "gn:dem":1649,
    "gn:feature_class":"P",
    "gn:feature_code":"PPL",
    "gn:name":"Garnier",
    "gn:population":0,
    "gn:timezone":"Europe/Paris",
    "iso:country":"FR",
    "wof:name":"Garnier",
    "wof:placetype":"locality"
},
  "geometry": {"coordinates":[6.28333,44.31667],"type":"Point"}
}