{
  "type": "Feature",
  "properties": {
    "gn:admin1_code":"93",
    "gn:admin2_code":"04",
    "gn:admin3_code":"043",
    "gn:admin4_code":"04017",
    "gn:asciiname":"Garnier",
    "gn:country_code":"FR",
    "gn:dem":1649,
    "gn:feature_class":"P",
    "gn:feature_code":"PPL",
    "gn:name":"Garnier",
    "gn:population":0,
    "gn:timezone":"Europe/Paris",
    "iso:country":"FR",
    "name:bul_x_preferred":[
        "\u0413\u0430\u0440\u043d\u0438\u0435"
    ],
    "name:deu_x_preferred":[
        "Garnier"
    ],
    "name:fas_x_preferred":[
        "\u06af\u0627\u0631\u0646\u06cc\u0647"
    ],
    "name:fra_x_preferred":[
        "Garnier"
    ],
    "name:ita_x_preferred":[
        "Garnier"
    ],
    "name:msa_x_preferred":[
        "Garnier"
    ],
    "name:nld_x_preferred":[
        "Garnier"
    ],
    "name:slk_x_preferred":[
        "Garnier"
    ],
    "name:tha_x_preferred":[
        "\u0e01\u0e32\u0e23\u0e4c\u0e19\u0e34\u0e40\u0e22\u0e48"
    ],
    "name:tur_x_preferred":[
        "Garnier"
    ],
    "wof:name":"Garnier",
    "wof:placetype":"locality"
},
  "geometry": {"coordinates":[6.28333,44.31667],"type":"Point"}
}