{
  "type": "Feature",
  "properties": {
    "gn:admin1_code":"93",
    "gn:admin2_code":"13",
    "gn:admin3_code":"133",
    "gn:admin4_code":"13055",
    "gn:asciiname":"Notre-Dame",
    "gn:country_code":"FR",
    "gn:dem":198,
    "gn:feature_class":"P",
    "gn:feature_code":"PPL",
    "gn:name":"Notre-Dame",
    "gn:population":0,
    "gn:timezone":"Europe/Paris",
    "iso:country":"FR",
    "wof:name":"Notre-Dame",
    "wof:placetype":"locality"
},
  "geometry": {"coordinates":[5.36667,43.38333],"type":"Point"}
}