{
  "type": "Feature",
  "properties": {
    "gn:admin1_code":"44",
    "gn:admin2_code":"52",
    "gn:admin3_code":"521",
    "gn:admin4_code":"52031",
    "gn:asciiname":"Saint-Martin-sur-la-Renne",
    "gn:country_code":"FR",
    "gn:dem":238,
    "gn:feature_class":"P",
    "gn:feature_code":"PPL",
    "gn:name":"Saint-Martin-sur-la-Renne",
    "gn:population":0,
    "gn:timezone":"Europe/Paris",
    "iso:country":"FR",
    "name:und_x_variant":[
        "Saint Martin-les-Juzennecourt",
        "Saint Martin",
        "Saint-Martin-sur-la-Renne"
    ],
    "wof:name":"Saint-Martin-sur-la-Renne",
    "wof:placetype":"locality"
},
  "geometry": {"coordinates":[4.95387,48.14512],"type":"Point"}
}