{
  "type": "Feature",
  "properties": {
    "gn:admin1_code":"28",
    "gn:admin2_code":"76",
    "gn:admin3_code":"761",
    "gn:admin4_code":"76744",
    "gn:asciiname":"Villers-sous-Foucarmont",
    "gn:country_code":"FR",
    "gn:dem":126,
    "gn:feature_class":"P",
    "gn:feature_code":"PPL",
    "gn:name":"Villers-sous-Foucarmont",
    "gn:population":0,
    "gn:timezone":"Europe/Paris",
    "iso:country":"FR",
    "name:und_x_variant":[
        "Villers",
        "Villers-sous-Foucarmont"
    ],
    "wof:name":"Villers-sous-Foucarmont",
    "wof:placetype":"locality"
},
  "geometry": {"coordinates":[1.56398,49.83969],"type":"Point"}
}