{
  "type": "Feature",
  "properties": {
    "gn:admin1_code":"84",
    "gn:admin2_code":"03",
    "gn:admin3_code":"032",
    "gn:admin4_code":"3036.0",
    "gn:asciiname":"Pou",
    "gn:country_code":"FR",
    "gn:dem":242,
    "gn:feature_class":"P",
    "gn:feature_code":"PPL",
    "gn:name":"Pou",
    "gn:population":0,
    "gn:timezone":"Europe/Paris",
    "iso:country":"FR",
    "wof:name":"Pou",
    "wof:placetype":"locality"
},
  "geometry": {"coordinates":[3.09009,46.5938],"type":"Point"}
}