{
  "type": "Feature",
  "properties": {
    "iso:country":"FR",
    "name:eng_x_preferred":[
        "Les Mousseaux"
    ],
    "name:fra_x_preferred":[
        "Les Mousseaux"
    ],
    "wof:name":"Les Mousseaux",
    "wof:placetype":"neighbourhood"
},
  "geometry": {"coordinates":[2.54828532833162,48.96517473619725],"type":"Point"}
}