{
  "type": "Feature",
  "properties": {
    "gn:admin1_code":"44",
    "gn:admin2_code":"52",
    "gn:admin3_code":"522",
    "gn:admin4_code":"52094",
    "gn:asciiname":"Musseau",
    "gn:country_code":"FR",
    "gn:dem":395,
    "gn:feature_class":"P",
    "gn:feature_code":"PPL",
    "gn:name":"Musseau",
    "gn:population":0,
    "gn:timezone":"Europe/Paris",
    "iso:country":"FR",
    "wof:name":"Musseau",
    "wof:placetype":"locality"
},
  "geometry": {"coordinates":[5.1124,47.70812],"type":"Point"}
}