{
  "type": "Feature",
  "properties": {
    "gn:admin1_code":"44",
    "gn:admin2_code":"52",
    "gn:admin3_code":"523",
    "gn:admin4_code":"52288",
    "gn:asciiname":"Laneuville-aux-Bois",
    "gn:country_code":"FR",
    "gn:dem":344,
    "gn:feature_class":"P",
    "gn:feature_code":"PPL",
    "gn:name":"Laneuville-aux-Bois",
    "gn:population":0,
    "gn:timezone":"Europe/Paris",
    "iso:country":"FR",
    "name:und_x_variant":[
        "Laneuville",
        "Laneuville-aux-Bois"
    ],
    "wof:name":"Laneuville-aux-Bois",
    "wof:placetype":"locality"
},
  "geometry": {"coordinates":[5.42146,48.4165],"type":"Point"}
}