{
  "type": "Feature",
  "properties": {
    "gn:admin1_code":"28",
    "gn:admin2_code":"14",
    "gn:admin3_code":"142",
    "gn:admin4_code":"14005",
    "gn:asciiname":"Fierville-Bray",
    "gn:cc2":"FR",
    "gn:country_code":"FR",
    "gn:dem":47,
    "gn:feature_class":"P",
    "gn:feature_code":"PPL",
    "gn:name":"Fierville-Bray",
    "gn:population":0,
    "gn:timezone":"Europe/Paris",
    "iso:country":"FR",
    "name:bre_x_preferred":[
        "Fierville-Bray"
    ],
    "name:cat_x_preferred":[
        "Fierville-Bray"
    ],
    "name:ceb_x_preferred":[
        "Fierville-Bray"
    ],
    "name:deu_x_preferred":[
        "Fierville-Bray"
    ],
    "name:eus_x_preferred":[
        "Fierville-Bray"
    ],
    "name:fra_x_preferred":[
        "Fierville-Bray"
    ],
    "name:hun_x_preferred":[
        "Fierville-Bray"
    ],
    "name:hye_x_preferred":[
        "\u0556\u056b\u0565\u057c\u057e\u056b\u056c \u0532\u0580\u0565"
    ],
    "name:ind_x_preferred":[
        "Fierville-Bray"
    ],
    "name:ita_x_preferred":[
        "Fierville-Bray"
    ],
    "name:jpn_x_preferred":[
        "\u30d5\u30a3\u30a8\u30f4\u30a3\u30eb\uff1d\u30d6\u30ec\u30a4"
    ],
    "name:kaz_x_preferred":[
        "\u0424\u044c\u0435\u0440\u0432\u0438\u043b\u044c-\u0411\u0440\u0435"
    ],
    "name:lat_x_preferred":[
        "Fierville-Bray"
    ],
    "name:msa_x_preferred":[
        "Fierville-Bray"
    ],
    "name:nld_x_preferred":[
        "Fierville-Bray"
    ],
    "name:oci_x_preferred":[
        "Fierville-Bray"
    ],
    "name:pms_x_preferred":[
        "Fierville-Bray"
    ],
    "name:pol_x_preferred":[
        "Fierville-Bray"
    ],
    "name:por_x_preferred":[
        "Fierville-Bray"
    ],
    "name:ron_x_preferred":[
        "Fierville-Bray"
    ],
    "name:rus_x_preferred":[
        "\u0424\u044c\u0435\u0440\u0432\u0438\u043b\u044c-\u0411\u0440\u0435"
    ],
    "name:slk_x_preferred":[
        "Fierville-Bray"
    ],
    "name:spa_x_preferred":[
        "Fierville-Bray"
    ],
    "name:swe_x_preferred":[
        "Fierville-Bray"
    ],
    "name:ukr_x_preferred":[
        "\u0424'\u0454\u0440\u0432\u0456\u043b\u044c-\u0411\u0440\u0435"
    ],
    "name:und_x_variant":[
        "Fierville",
        "Fierville-la-Campagne"
    ],
    "name:uzb_x_preferred":[
        "Fierville-Bray"
    ],
    "name:vie_x_preferred":[
        "Fierville-Bray"
    ],
    "name:vol_x_preferred":[
        "Fierville-Bray"
    ],
    "name:war_x_preferred":[
        "Fierville-Bray"
    ],
    "name:zho_x_preferred":[
        "\u83f2\u8036\u5c14\u7ef4\u5c14\u5e03\u8d56"
    ],
    "wof:name":"Fierville-Bray",
    "wof:placetype":"locality"
},
  "geometry": {"coordinates":[-0.18333,49.06667],"type":"Point"}
}