{
  "type": "Feature",
  "properties": {
    "gn:admin1_code":"28",
    "gn:admin2_code":"14",
    "gn:admin3_code":"142",
    "gn:admin4_code":"14005",
    "gn:asciiname":"Fierville-Bray",
    "gn:cc2":"FR",
    "gn:country_code":"FR",
    "gn:dem":47,
    "gn:feature_class":"P",
    "gn:feature_code":"PPL",
    "gn:name":"Fierville-Bray",
    "gn:population":0,
    "gn:timezone":"Europe/Paris",
    "iso:country":"FR",
    "name:und_x_variant":[
        "Fierville",
        "Fierville-la-Campagne"
    ],
    "wof:name":"Fierville-Bray",
    "wof:placetype":"locality"
},
  "geometry": {"coordinates":[-0.18333,49.06667],"type":"Point"}
}