{
  "type": "Feature",
  "properties": {
    "gn:admin1_code":"53",
    "gn:admin2_code":"56",
    "gn:admin3_code":"562",
    "gn:admin4_code":"56041",
    "gn:asciiname":"Kerbedic",
    "gn:country_code":"FR",
    "gn:dem":175,
    "gn:feature_class":"P",
    "gn:feature_code":"PPL",
    "gn:name":"Kerb\u00e9dic",
    "gn:population":0,
    "gn:timezone":"Europe/Paris",
    "iso:country":"FR",
    "wof:name":"Kerbedic",
    "wof:placetype":"locality"
},
  "geometry": {"coordinates":[-3.06743,48.09853],"type":"Point"}
}