{
  "type": "Feature",
  "properties": {
    "gn:admin1_code":"93",
    "gn:admin2_code":"04",
    "gn:admin3_code":"043",
    "gn:admin4_code":"04155",
    "gn:asciiname":"Blegiers",
    "gn:country_code":"FR",
    "gn:dem":921,
    "gn:feature_class":"P",
    "gn:feature_code":"PPL",
    "gn:name":"Bl\u00e9giers",
    "gn:population":0,
    "gn:timezone":"Europe/Paris",
    "iso:country":"FR",
    "name:und_x_variant":[
        "Bl\u00e9giers"
    ],
    "wof:name":"Blegiers",
    "wof:placetype":"locality"
},
  "geometry": {"coordinates":[6.41824,44.17918],"type":"Point"}
}