{
  "type": "Feature",
  "properties": {
    "gn:admin1_code":"44",
    "gn:admin2_code":"57",
    "gn:admin3_code":"576",
    "gn:admin4_code":"57541",
    "gn:asciiname":"Philippsbourg",
    "gn:country_code":"FR",
    "gn:dem":230,
    "gn:feature_class":"P",
    "gn:feature_code":"PPL",
    "gn:name":"Philippsbourg",
    "gn:population":0,
    "gn:timezone":"Europe/Paris",
    "iso:country":"FR",
    "name:als_x_preferred":[
        "Philippsburg"
    ],
    "name:cat_x_preferred":[
        "Philippsbourg"
    ],
    "name:ceb_x_preferred":[
        "Philippsbourg"
    ],
    "name:deu_x_preferred":[
        "Philippsbourg"
    ],
    "name:eus_x_preferred":[
        "Philippsbourg"
    ],
    "name:fra_x_preferred":[
        "Philippsbourg"
    ],
    "name:hun_x_preferred":[
        "Philippsbourg"
    ],
    "name:ita_x_preferred":[
        "Philippsbourg"
    ],
    "name:kaz_x_preferred":[
        "\u0424\u0438\u043b\u0438\u043f\u043f\u0441\u0431\u0443\u0440"
    ],
    "name:lat_x_preferred":[
        "Philippsbourg"
    ],
    "name:ltz_x_preferred":[
        "Philippsbourg"
    ],
    "name:msa_x_preferred":[
        "Philippsbourg"
    ],
    "name:nld_x_preferred":[
        "Philippsbourg"
    ],
    "name:oci_x_preferred":[
        "Philippsbourg"
    ],
    "name:pfl_x_preferred":[
        "Philippsbourg"
    ],
    "name:pms_x_preferred":[
        "Philippsbourg"
    ],
    "name:pol_x_preferred":[
        "Philippsbourg"
    ],
    "name:por_x_preferred":[
        "Philippsbourg"
    ],
    "name:slk_x_preferred":[
        "Philippsbourg"
    ],
    "name:spa_x_preferred":[
        "Philippsbourg"
    ],
    "name:swe_x_preferred":[
        "Philippsbourg"
    ],
    "name:tur_x_preferred":[
        "Philippsbourg"
    ],
    "name:ukr_x_preferred":[
        "\u0424\u0456\u043b\u0456\u043f\u043f\u0441\u0431\u0443\u0440"
    ],
    "name:uzb_x_preferred":[
        "Philippsbourg"
    ],
    "name:vie_x_preferred":[
        "Philippsbourg"
    ],
    "name:war_x_preferred":[
        "Philippsbourg"
    ],
    "name:zho_x_preferred":[
        "\u83f2\u5229\u666e\u65af\u5e03\u5c14"
    ],
    "wof:name":"Philippsbourg",
    "wof:placetype":"locality"
},
  "geometry": {"coordinates":[7.56727,48.9834],"type":"Point"}
}