{
  "type": "Feature",
  "properties": {
    "frgov:code_epci":"200069441",
    "frgov:insee_arr":"6",
    "frgov:insee_com":"57541",
    "frgov:insee_dep":"57",
    "frgov:insee_reg":"44",
    "frgov:nom_com":"Philippsbourg",
    "frgov:nom_com_m":"PHILIPPSBOURG",
    "frgov:nom_dep":"MOSELLE",
    "frgov:nom_reg":"GRAND EST",
    "frgov:statut":"Commune simple",
    "gn:admin1_code":"44",
    "gn:admin2_code":"57",
    "gn:admin3_code":"576",
    "gn:admin4_code":"57541",
    "gn:asciiname":"Philippsbourg",
    "gn:country_code":"FR",
    "gn:dem":230,
    "gn:feature_class":"P",
    "gn:feature_code":"PPL",
    "gn:name":"Philippsbourg",
    "gn:population":0,
    "gn:timezone":"Europe/Paris",
    "iso:country":"FR",
    "name:als_x_preferred":[
        "Philippsburg"
    ],
    "name:cat_x_preferred":[
        "Philippsbourg"
    ],
    "name:ceb_x_preferred":[
        "Philippsbourg"
    ],
    "name:deu_x_preferred":[
        "Philippsbourg"
    ],
    "name:eus_x_preferred":[
        "Philippsbourg"
    ],
    "name:fra_x_preferred":[
        "Philippsbourg"
    ],
    "name:hun_x_preferred":[
        "Philippsbourg"
    ],
    "name:ita_x_preferred":[
        "Philippsbourg"
    ],
    "name:kaz_x_preferred":[
        "\u0424\u0438\u043b\u0438\u043f\u043f\u0441\u0431\u0443\u0440"
    ],
    "name:lat_x_preferred":[
        "Philippsbourg"
    ],
    "name:ltz_x_preferred":[
        "Philippsbourg"
    ],
    "name:msa_x_preferred":[
        "Philippsbourg"
    ],
    "name:nld_x_preferred":[
        "Philippsbourg"
    ],
    "name:oci_x_preferred":[
        "Philippsbourg"
    ],
    "name:pfl_x_preferred":[
        "Philippsbourg"
    ],
    "name:pms_x_preferred":[
        "Philippsbourg"
    ],
    "name:pol_x_preferred":[
        "Philippsbourg"
    ],
    "name:por_x_preferred":[
        "Philippsbourg"
    ],
    "name:slk_x_preferred":[
        "Philippsbourg"
    ],
    "name:spa_x_preferred":[
        "Philippsbourg"
    ],
    "name:swe_x_preferred":[
        "Philippsbourg"
    ],
    "name:tur_x_preferred":[
        "Philippsbourg"
    ],
    "name:ukr_x_preferred":[
        "\u0424\u0456\u043b\u0456\u043f\u043f\u0441\u0431\u0443\u0440"
    ],
    "name:und_x_variant":[
        "Philippsburg",
        "Philippsbourg"
    ],
    "name:uzb_x_preferred":[
        "Philippsbourg"
    ],
    "name:vie_x_preferred":[
        "Philippsbourg"
    ],
    "name:war_x_preferred":[
        "Philippsbourg"
    ],
    "name:zho_x_preferred":[
        "\u83f2\u5229\u666e\u65af\u5e03\u5c14"
    ],
    "qs:a0":"France",
    "qs:a1":"MOSELLE",
    "qs:a1_lc":"57",
    "qs:a1r":"LORRAINE",
    "qs:a1r_lc":"41",
    "qs:a2_lc":"02",
    "qs:a2r_lc":"6",
    "qs:adm0":"France",
    "qs:adm0_a3":"FRA",
    "qs:la":"PHILIPPSBOURG",
    "qs:la_lc":"57541",
    "qs:level":"localadmin",
    "qs:type":"Commune simple",
    "wof:coterminous":[
        404347999
    ],
    "wof:name":"Philippsbourg",
    "wof:placetype":"locality",
    "wof:placetype_local":"Commune simple"
},
  "geometry": {"coordinates":[7.56727,48.9834],"type":"Point"}
}