{
  "type": "Feature",
  "properties": {
    "gn:admin1_code":"93",
    "gn:admin2_code":"84",
    "gn:admin3_code":"843",
    "gn:admin4_code":"84079",
    "gn:asciiname":"Flaoussiers",
    "gn:country_code":"FR",
    "gn:dem":812,
    "gn:feature_class":"P",
    "gn:feature_code":"PPL",
    "gn:name":"Flaoussiers",
    "gn:population":0,
    "gn:timezone":"Europe/Paris",
    "iso:country":"FR",
    "name:und_x_variant":[
        "Flauossier",
        "Flaoussiers"
    ],
    "wof:name":"Flaoussiers",
    "wof:placetype":"locality"
},
  "geometry": {"coordinates":[5.3372,44.05604],"type":"Point"}
}