{
  "type": "Feature",
  "properties": {
    "gn:admin1_code":"44",
    "gn:admin2_code":"54",
    "gn:admin3_code":"541",
    "gn:admin4_code":"54149",
    "gn:asciiname":"Nouveau Crusnes",
    "gn:cc2":"FR",
    "gn:country_code":"FR",
    "gn:dem":406,
    "gn:feature_class":"P",
    "gn:feature_code":"PPL",
    "gn:name":"Nouveau Crusnes",
    "gn:population":0,
    "gn:timezone":"Europe/Paris",
    "iso:country":"FR",
    "name:und_x_variant":[
        "Le Nouveau Crusnes",
        "Nouveau Crusnes"
    ],
    "wof:name":"Nouveau Crusnes",
    "wof:placetype":"locality"
},
  "geometry": {"coordinates":[5.93333,49.43333],"type":"Point"}
}