{
  "type": "Feature",
  "properties": {
    "gn:admin1_code":"28",
    "gn:admin2_code":"76",
    "gn:admin3_code":"761",
    "gn:admin4_code":"76295",
    "gn:asciiname":"Mal Assis",
    "gn:country_code":"FR",
    "gn:dem":222,
    "gn:feature_class":"P",
    "gn:feature_code":"PPL",
    "gn:name":"Mal Assis",
    "gn:population":0,
    "gn:timezone":"Europe/Paris",
    "iso:country":"FR",
    "wof:name":"Mal Assis",
    "wof:placetype":"locality"
},
  "geometry": {"coordinates":[1.63934,49.63729],"type":"Point"}
}