{
  "type": "Feature",
  "properties": {
    "gn:admin1_code":"32",
    "gn:admin2_code":"62",
    "gn:admin3_code":"624",
    "gn:admin4_code":"62690.0",
    "gn:asciiname":"Fond-de-Val",
    "gn:country_code":"FR",
    "gn:dem":29,
    "gn:feature_class":"P",
    "gn:feature_code":"PPL",
    "gn:name":"Fond-de-Val",
    "gn:population":0,
    "gn:timezone":"Europe/Paris",
    "iso:country":"FR",
    "wof:name":"Fond-de-Val",
    "wof:placetype":"locality"
},
  "geometry": {"coordinates":[1.97012,50.30552],"type":"Point"}
}