{
  "type": "Feature",
  "properties": {
    "gn:admin1_code":"84",
    "gn:admin2_code":"63",
    "gn:admin3_code":"632",
    "gn:admin4_code":"63026",
    "gn:asciiname":"Fontclairant",
    "gn:country_code":"FR",
    "gn:dem":942,
    "gn:feature_class":"P",
    "gn:feature_code":"PPL",
    "gn:name":"Fontclairant",
    "gn:population":0,
    "gn:timezone":"Europe/Paris",
    "iso:country":"FR",
    "wof:name":"Fontclairant",
    "wof:placetype":"locality"
},
  "geometry": {"coordinates":[2.96395,45.66848],"type":"Point"}
}