{
  "type": "Feature",
  "properties": {
    "gn:admin1_code":"44",
    "gn:admin2_code":"51",
    "gn:admin3_code":"512",
    "gn:admin4_code":"51235",
    "gn:asciiname":"Le Chatelot",
    "gn:country_code":"FR",
    "gn:dem":212,
    "gn:feature_class":"P",
    "gn:feature_code":"PPL",
    "gn:name":"Le Ch\u00e2telot",
    "gn:population":0,
    "gn:timezone":"Europe/Paris",
    "iso:country":"FR",
    "wof:name":"Le Chatelot",
    "wof:placetype":"locality"
},
  "geometry": {"coordinates":[3.61844,48.772],"type":"Point"}
}