{
  "type": "Feature",
  "properties": {
    "frgov:code_epci":"200040905",
    "frgov:insee_arr":"1",
    "frgov:insee_com":"81249",
    "frgov:insee_dep":"81",
    "frgov:insee_reg":"76",
    "frgov:nom_com":"Sainte-Gemme",
    "frgov:nom_com_m":"SAINTE-GEMME",
    "frgov:nom_dep":"TARN",
    "frgov:nom_reg":"OCCITANIE",
    "frgov:statut":"Commune simple",
    "gn:admin1_code":"76",
    "gn:admin2_code":"81",
    "gn:admin3_code":"811",
    "gn:admin4_code":"81249",
    "gn:asciiname":"Sainte-Gemme",
    "gn:country_code":"FR",
    "gn:dem":360,
    "gn:feature_class":"P",
    "gn:feature_code":"PPL",
    "gn:name":"Sainte-Gemme",
    "gn:population":741,
    "gn:timezone":"Europe/Paris",
    "iso:country":"FR",
    "name:ceb_x_preferred":[
        "Sainte-Gemme"
    ],
    "name:deu_x_preferred":[
        "Sainte-Gemme"
    ],
    "name:epo_x_preferred":[
        "Sainte-Gemme"
    ],
    "name:fra_x_preferred":[
        "Sainte-Gemme"
    ],
    "name:ita_x_preferred":[
        "Sainte-Gemme"
    ],
    "name:nds_x_preferred":[
        "Sainte-Gemme"
    ],
    "name:nld_x_preferred":[
        "Sainte-Gemme"
    ],
    "name:oci_x_preferred":[
        "Sainte-Gemme"
    ],
    "name:pms_x_preferred":[
        "Sainte-Gemme"
    ],
    "name:pol_x_preferred":[
        "Sainte-Gemme"
    ],
    "name:por_x_preferred":[
        "Sainte-Gemme"
    ],
    "name:rus_x_preferred":[
        "\u0421\u0435\u043d\u0442-\u0416\u0435\u043c"
    ],
    "name:slk_x_preferred":[
        "Sainte-Gemme"
    ],
    "name:spa_x_preferred":[
        "Sainte-Gemme"
    ],
    "name:swe_x_preferred":[
        "Sainte-Gemme"
    ],
    "name:ukr_x_preferred":[
        "\u0421\u0435\u043d\u0442-\u0416\u0435\u043c\u043c"
    ],
    "name:und_x_variant":[
        "Sainte-Gemme-l\u00e8s-Farguettes",
        "Sainte-Gemme"
    ],
    "qs:a0":"France",
    "qs:a1":"TARN",
    "qs:a1_lc":"81",
    "qs:a1r":"MIDI-PYRENEES",
    "qs:a1r_lc":"73",
    "qs:a2_lc":"23",
    "qs:a2r_lc":"1",
    "qs:adm0":"France",
    "qs:adm0_a3":"FRA",
    "qs:la":"SAINTE-GEMME",
    "qs:la_lc":"81249",
    "qs:level":"localadmin",
    "qs:type":"Commune simple",
    "wof:coterminous":[
        404363887
    ],
    "wof:name":"Sainte-Gemme",
    "wof:placetype":"locality",
    "wof:placetype_local":"Commune simple",
    "wof:population":741
},
  "geometry": {"coordinates":[2.20121,44.08929],"type":"Point"}
}