{
  "type": "Feature",
  "properties": {
    "gn:admin1_code":"28",
    "gn:admin2_code":"61",
    "gn:admin3_code":"612",
    "gn:admin4_code":"61138",
    "gn:asciiname":"Le Bouillonnay",
    "gn:country_code":"FR",
    "gn:dem":239,
    "gn:feature_class":"P",
    "gn:feature_code":"PPL",
    "gn:name":"Le Bouillonnay",
    "gn:population":0,
    "gn:timezone":"Europe/Paris",
    "iso:country":"FR",
    "wof:name":"Le Bouillonnay",
    "wof:placetype":"locality"
},
  "geometry": {"coordinates":[0.27423,48.74979],"type":"Point"}
}