{
  "type": "Feature",
  "properties": {
    "gn:admin1_code":"75",
    "gn:admin2_code":"24",
    "gn:admin3_code":"244",
    "gn:admin4_code":"24324",
    "gn:asciiname":"Lala",
    "gn:country_code":"FR",
    "gn:dem":244,
    "gn:feature_class":"P",
    "gn:feature_code":"PPL",
    "gn:name":"Lala",
    "gn:population":0,
    "gn:timezone":"Europe/Paris",
    "iso:country":"FR",
    "name:bak_x_preferred":[
        "\u041b\u04d9\u043b\u04d9"
    ],
    "name:ceb_x_preferred":[
        "Lala"
    ],
    "name:deu_x_preferred":[
        "Lala"
    ],
    "name:fra_x_preferred":[
        "Lala"
    ],
    "name:ind_x_preferred":[
        "Lala"
    ],
    "name:ita_x_preferred":[
        "Lala"
    ],
    "name:nld_x_preferred":[
        "Lala"
    ],
    "name:rus_x_preferred":[
        "\u041b\u044f\u043b\u044f"
    ],
    "name:spa_x_preferred":[
        "Lala"
    ],
    "name:swe_x_preferred":[
        "Lala"
    ],
    "wof:name":"Lala",
    "wof:placetype":"locality"
},
  "geometry": {"coordinates":[1.19557,45.1643],"type":"Point"}
}