{
  "type": "Feature",
  "properties": {
    "gn:admin1_code":"76",
    "gn:admin2_code":"30",
    "gn:admin3_code":"303",
    "gn:admin4_code":"30335",
    "gn:asciiname":"Vabres",
    "gn:country_code":"FR",
    "gn:dem":318,
    "gn:feature_class":"P",
    "gn:feature_code":"PPL",
    "gn:name":"Vabres",
    "gn:population":110,
    "gn:timezone":"Europe/Paris",
    "iso:country":"FR",
    "name:ceb_x_preferred":[
        "Vabres"
    ],
    "name:deu_x_preferred":[
        "Vabres"
    ],
    "name:fra_x_preferred":[
        "Vabres"
    ],
    "name:ita_x_preferred":[
        "Vabres"
    ],
    "name:lmo_x_preferred":[
        "Vabres"
    ],
    "name:nds_x_preferred":[
        "Vabres"
    ],
    "name:nld_x_preferred":[
        "Vabres"
    ],
    "name:oci_x_preferred":[
        "Tr\u00e8ve"
    ],
    "name:pms_x_preferred":[
        "Vabres"
    ],
    "name:pol_x_preferred":[
        "Vabres"
    ],
    "name:por_x_preferred":[
        "Vabres"
    ],
    "name:rus_x_preferred":[
        "\u0412\u0430\u0431\u0440"
    ],
    "name:scn_x_preferred":[
        "Vabres"
    ],
    "name:slk_x_preferred":[
        "Vabres"
    ],
    "name:spa_x_preferred":[
        "Vabres"
    ],
    "name:swe_x_preferred":[
        "Vabres"
    ],
    "name:ukr_x_preferred":[
        "\u0412\u0430\u0431\u0440"
    ],
    "wof:name":"Vabres",
    "wof:placetype":"locality",
    "wof:population":110
},
  "geometry": {"coordinates":[3.89154,44.03068],"type":"Point"}
}