{
  "type": "Feature",
  "properties": {
    "gn:admin1_code":"76",
    "gn:admin2_code":"30",
    "gn:admin3_code":"303",
    "gn:admin4_code":"30335",
    "gn:asciiname":"Vabres",
    "gn:country_code":"FR",
    "gn:dem":318,
    "gn:feature_class":"P",
    "gn:feature_code":"PPL",
    "gn:name":"Vabres",
    "gn:population":110,
    "gn:timezone":"Europe/Paris",
    "iso:country":"FR",
    "wof:name":"Vabres",
    "wof:placetype":"locality",
    "wof:population":110
},
  "geometry": {"coordinates":[3.89154,44.03068],"type":"Point"}
}