{
  "type": "Feature",
  "properties": {
    "gn:admin1_code":"27",
    "gn:admin2_code":"21",
    "gn:admin3_code":"211",
    "gn:admin4_code":"21194",
    "gn:asciiname":"Moux",
    "gn:country_code":"FR",
    "gn:dem":213,
    "gn:feature_class":"P",
    "gn:feature_code":"PPL",
    "gn:name":"Moux",
    "gn:population":0,
    "gn:timezone":"Europe/Paris",
    "iso:country":"FR",
    "wof:name":"Moux",
    "wof:placetype":"locality"
},
  "geometry": {"coordinates":[4.96287,47.07402],"type":"Point"}
}