{
  "type": "Feature",
  "properties": {
    "gn:admin1_code":"27",
    "gn:admin2_code":"21",
    "gn:admin3_code":"211",
    "gn:admin4_code":"21194",
    "gn:asciiname":"Moux",
    "gn:country_code":"FR",
    "gn:dem":213,
    "gn:feature_class":"P",
    "gn:feature_code":"PPL",
    "gn:name":"Moux",
    "gn:population":0,
    "gn:timezone":"Europe/Paris",
    "iso:country":"FR",
    "name:cat_x_preferred":[
        "Mos"
    ],
    "name:ceb_x_preferred":[
        "Moux"
    ],
    "name:deu_x_preferred":[
        "Moux"
    ],
    "name:eus_x_preferred":[
        "Moux"
    ],
    "name:fra_x_preferred":[
        "Moux"
    ],
    "name:hun_x_preferred":[
        "Moux"
    ],
    "name:hye_x_preferred":[
        "\u0544\u0578\u0582"
    ],
    "name:ita_x_preferred":[
        "Moux"
    ],
    "name:kaz_x_preferred":[
        "\u041c\u0443"
    ],
    "name:lat_x_preferred":[
        "Moux"
    ],
    "name:lmo_x_preferred":[
        "Moux"
    ],
    "name:mlg_x_preferred":[
        "Moux"
    ],
    "name:msa_x_preferred":[
        "Moux"
    ],
    "name:nld_x_preferred":[
        "Moux"
    ],
    "name:oci_x_preferred":[
        "Mos"
    ],
    "name:pms_x_preferred":[
        "Moux"
    ],
    "name:pol_x_preferred":[
        "Moux"
    ],
    "name:por_x_preferred":[
        "Moux"
    ],
    "name:ron_x_preferred":[
        "Moux"
    ],
    "name:rus_x_preferred":[
        "\u041c\u0443"
    ],
    "name:slk_x_preferred":[
        "Moux"
    ],
    "name:spa_x_preferred":[
        "Moux"
    ],
    "name:swe_x_preferred":[
        "Moux"
    ],
    "name:ukr_x_preferred":[
        "\u041c\u0443"
    ],
    "name:vie_x_preferred":[
        "Moux"
    ],
    "name:vol_x_preferred":[
        "Moux"
    ],
    "name:war_x_preferred":[
        "Moux"
    ],
    "name:zho_x_preferred":[
        "\u7a46"
    ],
    "wof:name":"Moux",
    "wof:placetype":"locality"
},
  "geometry": {"coordinates":[4.96287,47.07402],"type":"Point"}
}