{
  "type": "Feature",
  "properties": {
    "gn:admin1_code":"84",
    "gn:admin2_code":"26",
    "gn:admin3_code":"261",
    "gn:admin4_code":"26282",
    "gn:asciiname":"Les Planaux",
    "gn:country_code":"FR",
    "gn:dem":560,
    "gn:feature_class":"P",
    "gn:feature_code":"PPL",
    "gn:name":"Les Planaux",
    "gn:population":0,
    "gn:timezone":"Europe/Paris",
    "iso:country":"FR",
    "wof:name":"Les Planaux",
    "wof:placetype":"locality"
},
  "geometry": {"coordinates":[5.40555,44.79297],"type":"Point"}
}