{
  "type": "Feature",
  "properties": {
    "frgov:code_epci":"200067593",
    "frgov:insee_arr":"1",
    "frgov:insee_com":"23164",
    "frgov:insee_dep":"23",
    "frgov:insee_reg":"75",
    "frgov:nom_com":"Rougnat",
    "frgov:nom_com_m":"ROUGNAT",
    "frgov:nom_dep":"CREUSE",
    "frgov:nom_reg":"NOUVELLE-AQUITAINE",
    "frgov:statut":"Commune simple",
    "gn:admin1_code":"75",
    "gn:admin2_code":"23",
    "gn:admin3_code":"231",
    "gn:admin4_code":"23164",
    "gn:asciiname":"Rougnat",
    "gn:country_code":"FR",
    "gn:dem":561,
    "gn:feature_class":"P",
    "gn:feature_code":"PPL",
    "gn:name":"Rougnat",
    "gn:population":0,
    "gn:timezone":"Europe/Paris",
    "iso:country":"FR",
    "name:bar_x_preferred":[
        "Rougnat"
    ],
    "name:cat_x_preferred":[
        "Ronhac"
    ],
    "name:ceb_x_preferred":[
        "Rougnat"
    ],
    "name:deu_x_preferred":[
        "Rougnat"
    ],
    "name:epo_x_preferred":[
        "Rougnat"
    ],
    "name:eus_x_preferred":[
        "Rougnat"
    ],
    "name:fra_x_preferred":[
        "Rougnat"
    ],
    "name:hun_x_preferred":[
        "Rougnat"
    ],
    "name:ind_x_preferred":[
        "Rougnat"
    ],
    "name:ita_x_preferred":[
        "Rougnat"
    ],
    "name:kaz_x_preferred":[
        "\u0420\u0443\u043d\u044c\u044f"
    ],
    "name:lat_x_preferred":[
        "Rougnat"
    ],
    "name:mlg_x_preferred":[
        "Rougnat"
    ],
    "name:msa_x_preferred":[
        "Rougnat"
    ],
    "name:nld_x_preferred":[
        "Rougnat"
    ],
    "name:oci_x_preferred":[
        "Ronhac"
    ],
    "name:pms_x_preferred":[
        "Rougnat"
    ],
    "name:pol_x_preferred":[
        "Rougnat"
    ],
    "name:por_x_preferred":[
        "Rougnat"
    ],
    "name:ron_x_preferred":[
        "Rougnat"
    ],
    "name:rus_x_preferred":[
        "\u0420\u0443\u043d\u044c\u044f"
    ],
    "name:slk_x_preferred":[
        "Rougnat"
    ],
    "name:spa_x_preferred":[
        "Rougnat"
    ],
    "name:swe_x_preferred":[
        "Rougnat"
    ],
    "name:ukr_x_preferred":[
        "\u0420\u0443\u043d\u044c\u044f"
    ],
    "name:uzb_x_preferred":[
        "Rougnat"
    ],
    "name:vie_x_preferred":[
        "Rougnat"
    ],
    "name:vol_x_preferred":[
        "Rougnat"
    ],
    "name:war_x_preferred":[
        "Rougnat"
    ],
    "name:zho_x_preferred":[
        "\u9c81\u5c3c\u4e9a"
    ],
    "qs:a0":"France",
    "qs:a1":"CREUSE",
    "qs:a1_lc":"23",
    "qs:a1r":"LIMOUSIN",
    "qs:a1r_lc":"74",
    "qs:a2_lc":"03",
    "qs:a2r_lc":"1",
    "qs:adm0":"France",
    "qs:adm0_a3":"FRA",
    "qs:la":"ROUGNAT",
    "qs:la_lc":"23164",
    "qs:level":"localadmin",
    "qs:type":"Commune simple",
    "wof:coterminous":[
        404382827
    ],
    "wof:name":"Rougnat",
    "wof:placetype":"locality",
    "wof:placetype_local":"Commune simple"
},
  "geometry": {"coordinates":[2.50111,46.054],"type":"Point"}
}