{
  "type": "Feature",
  "properties": {
    "gn:admin1_code":"75",
    "gn:admin2_code":"23",
    "gn:admin3_code":"231",
    "gn:admin4_code":"23164",
    "gn:asciiname":"Rougnat",
    "gn:country_code":"FR",
    "gn:dem":561,
    "gn:feature_class":"P",
    "gn:feature_code":"PPL",
    "gn:name":"Rougnat",
    "gn:population":0,
    "gn:timezone":"Europe/Paris",
    "iso:country":"FR",
    "name:cat_x_preferred":[
        "Ronhac"
    ],
    "name:kaz_x_preferred":[
        "\u0420\u0443\u043d\u044c\u044f"
    ],
    "name:oci_x_preferred":[
        "Ronhac"
    ],
    "name:rus_x_preferred":[
        "\u0420\u0443\u043d\u044c\u044f"
    ],
    "name:ukr_x_preferred":[
        "\u0420\u0443\u043d\u044c\u044f"
    ],
    "name:zho_x_preferred":[
        "\u9c81\u5c3c\u4e9a"
    ],
    "wof:name":"Rougnat",
    "wof:placetype":"locality"
},
  "geometry": {"coordinates":[2.50111,46.054],"type":"Point"}
}