{
  "type": "Feature",
  "properties": {
    "gn:admin1_code":"84",
    "gn:admin2_code":"01",
    "gn:admin3_code":"011",
    "gn:admin4_code":"01073",
    "gn:asciiname":"Grammont",
    "gn:country_code":"FR",
    "gn:dem":363,
    "gn:feature_class":"P",
    "gn:feature_code":"PPL",
    "gn:name":"Grammont",
    "gn:population":0,
    "gn:timezone":"Europe/Paris",
    "iso:country":"FR",
    "name:ceb_x_preferred":[
        "Grammont"
    ],
    "name:deu_x_preferred":[
        "Grammont"
    ],
    "name:fra_x_preferred":[
        "Grammont"
    ],
    "name:nld_x_preferred":[
        "Grammont"
    ],
    "name:rus_x_preferred":[
        "\u0413\u0440\u0430\u043c\u043e\u043d"
    ],
    "name:swe_x_preferred":[
        "Grammont"
    ],
    "name:vol_x_preferred":[
        "Grammont"
    ],
    "wof:name":"Grammont",
    "wof:placetype":"locality"
},
  "geometry": {"coordinates":[5.70161,45.83411],"type":"Point"}
}