{
  "type": "Feature",
  "properties": {
    "frgov:code_epci":"200070571",
    "frgov:insee_arr":"3",
    "frgov:insee_com":"18124",
    "frgov:insee_dep":"18",
    "frgov:insee_reg":"24",
    "frgov:nom_com":"Lazenay",
    "frgov:nom_com_m":"LAZENAY",
    "frgov:nom_dep":"CHER",
    "frgov:nom_reg":"CENTRE-VAL DE LOIRE",
    "frgov:statut":"Commune simple",
    "gn:admin1_code":"24",
    "gn:admin2_code":"18",
    "gn:admin3_code":"183",
    "gn:admin4_code":"18124",
    "gn:asciiname":"Lazenay",
    "gn:country_code":"FR",
    "gn:dem":118,
    "gn:feature_class":"P",
    "gn:feature_code":"PPL",
    "gn:name":"Lazenay",
    "gn:population":0,
    "gn:timezone":"Europe/Paris",
    "iso:country":"FR",
    "name:cat_x_preferred":[
        "Lazenay"
    ],
    "name:ceb_x_preferred":[
        "Lazenay"
    ],
    "name:deu_x_preferred":[
        "Lazenay"
    ],
    "name:eus_x_preferred":[
        "Lazenay"
    ],
    "name:fra_x_preferred":[
        "Lazenay"
    ],
    "name:hun_x_preferred":[
        "Lazenay"
    ],
    "name:ita_x_preferred":[
        "Lazenay"
    ],
    "name:lat_x_preferred":[
        "Lazenay"
    ],
    "name:msa_x_preferred":[
        "Lazenay"
    ],
    "name:nld_x_preferred":[
        "Lazenay"
    ],
    "name:oci_x_preferred":[
        "Lazenay"
    ],
    "name:pms_x_preferred":[
        "Lazenay"
    ],
    "name:pol_x_preferred":[
        "Lazenay"
    ],
    "name:por_x_preferred":[
        "Lazenay"
    ],
    "name:ron_x_preferred":[
        "Lazenay"
    ],
    "name:rus_x_preferred":[
        "\u041b\u0430\u0437\u0435\u043d\u0435"
    ],
    "name:slk_x_preferred":[
        "Lazenay"
    ],
    "name:spa_x_preferred":[
        "Lazenay"
    ],
    "name:swe_x_preferred":[
        "Lazenay"
    ],
    "name:ukr_x_preferred":[
        "\u041b\u0430\u0437\u0435\u043d\u0435"
    ],
    "name:uzb_x_preferred":[
        "Lazenay"
    ],
    "name:vie_x_preferred":[
        "Lazenay"
    ],
    "name:vol_x_preferred":[
        "Lazenay"
    ],
    "name:war_x_preferred":[
        "Lazenay"
    ],
    "name:zho_x_preferred":[
        "\u62c9\u6cfd\u5948"
    ],
    "qs:a0":"France",
    "qs:a1":"CHER",
    "qs:a1_lc":"18",
    "qs:a1r":"CENTRE",
    "qs:a1r_lc":"24",
    "qs:a2_lc":"19",
    "qs:a2r_lc":"3",
    "qs:adm0":"France",
    "qs:adm0_a3":"FRA",
    "qs:la":"LAZENAY",
    "qs:la_lc":"18124",
    "qs:level":"localadmin",
    "qs:type":"Commune simple",
    "wof:coterminous":[
        404381837
    ],
    "wof:name":"Lazenay",
    "wof:placetype":"locality",
    "wof:placetype_local":"Commune simple"
},
  "geometry": {"coordinates":[2.06002,47.0717],"type":"Point"}
}