{
  "type": "Feature",
  "properties": {
    "gn:admin1_code":"24",
    "gn:admin2_code":"18",
    "gn:admin3_code":"183",
    "gn:admin4_code":"18124",
    "gn:asciiname":"Lazenay",
    "gn:country_code":"FR",
    "gn:dem":118,
    "gn:feature_class":"P",
    "gn:feature_code":"PPL",
    "gn:name":"Lazenay",
    "gn:population":0,
    "gn:timezone":"Europe/Paris",
    "iso:country":"FR",
    "name:cat_x_preferred":[
        "Lazenay"
    ],
    "name:ceb_x_preferred":[
        "Lazenay"
    ],
    "name:deu_x_preferred":[
        "Lazenay"
    ],
    "name:eus_x_preferred":[
        "Lazenay"
    ],
    "name:fra_x_preferred":[
        "Lazenay"
    ],
    "name:hun_x_preferred":[
        "Lazenay"
    ],
    "name:ita_x_preferred":[
        "Lazenay"
    ],
    "name:lat_x_preferred":[
        "Lazenay"
    ],
    "name:msa_x_preferred":[
        "Lazenay"
    ],
    "name:nld_x_preferred":[
        "Lazenay"
    ],
    "name:oci_x_preferred":[
        "Lazenay"
    ],
    "name:pms_x_preferred":[
        "Lazenay"
    ],
    "name:pol_x_preferred":[
        "Lazenay"
    ],
    "name:por_x_preferred":[
        "Lazenay"
    ],
    "name:ron_x_preferred":[
        "Lazenay"
    ],
    "name:rus_x_preferred":[
        "\u041b\u0430\u0437\u0435\u043d\u0435"
    ],
    "name:slk_x_preferred":[
        "Lazenay"
    ],
    "name:spa_x_preferred":[
        "Lazenay"
    ],
    "name:swe_x_preferred":[
        "Lazenay"
    ],
    "name:ukr_x_preferred":[
        "\u041b\u0430\u0437\u0435\u043d\u0435"
    ],
    "name:uzb_x_preferred":[
        "Lazenay"
    ],
    "name:vie_x_preferred":[
        "Lazenay"
    ],
    "name:vol_x_preferred":[
        "Lazenay"
    ],
    "name:war_x_preferred":[
        "Lazenay"
    ],
    "name:zho_x_preferred":[
        "\u62c9\u6cfd\u5948"
    ],
    "wof:name":"Lazenay",
    "wof:placetype":"locality"
},
  "geometry": {"coordinates":[2.06002,47.0717],"type":"Point"}
}