{
  "type": "Feature",
  "properties": {
    "iso:country":"FR",
    "name:ceb_x_preferred":[
        "Morlaix \u2013 Ploujean Airport"
    ],
    "name:deu_x_preferred":[
        "Flughafen Morlaix\u2013Ploujean"
    ],
    "name:eng_x_preferred":[
        "Morlaix \u2013 Ploujean Airport"
    ],
    "name:fas_x_preferred":[
        "\u0641\u0631\u0648\u062f\u06af\u0627\u0647 \u0645\u0631\u0644\u0647 \u067e\u0644\u0648\u0698\u0627\u0646"
    ],
    "name:fas_x_variant":[
        "\u0641\u0631\u0648\u062f\u06af\u0627\u0647 \u0645\u0648\u0631\u0644\u06cc\u06a9\u0633 \u2013 \u067e\u0644\u0648\u062c\u06cc\u0646"
    ],
    "name:fra_x_preferred":[
        "A\u00e9roport de Morlaix Ploujean"
    ],
    "name:hun_x_preferred":[
        "Morlaix\u2013Ploujean rep\u00fcl\u0151t\u00e9r"
    ],
    "name:msa_x_preferred":[
        "Lapangan Terbang Ploujean"
    ],
    "name:ron_x_preferred":[
        "Aeroportul Morlaix \u2013 Ploujean"
    ],
    "name:tgk_x_preferred":[
        "\u0424\u0443\u0440\u0443\u0434\u0433\u043e\u04b3\u0438 \u043c\u0443\u0440\u043b\u0438\u043a\u0441 \u2013 \u043f\u043b\u0443\u04b7\u0438\u043d"
    ],
    "oa:elevation_ft":"272",
    "oa:type":"medium_airport",
    "woe:hierarchy":{
        "country_id":23424819,
        "county_id":12591797,
        "localadmin_id":12638580,
        "planet_id":1,
        "state_id":7153313
    },
    "wof:name":"Ploujean Airport",
    "wof:placetype":"campus"
},
  "geometry": {"coordinates":[-3.8166666666667,48.600833333333],"type":"Point"}
}