{
  "type": "Feature",
  "properties": {
    "gn:admin1_code":"75",
    "gn:admin2_code":"40",
    "gn:admin3_code":"401",
    "gn:admin4_code":"40283",
    "gn:asciiname":"Buglose",
    "gn:country_code":"FR",
    "gn:dem":36,
    "gn:feature_class":"P",
    "gn:feature_code":"PPL",
    "gn:name":"Buglose",
    "gn:population":0,
    "gn:timezone":"Europe/Paris",
    "iso:country":"FR",
    "wof:name":"Buglose",
    "wof:placetype":"locality"
},
  "geometry": {"coordinates":[-0.99289,43.78274],"type":"Point"}
}