{
  "type": "Feature",
  "properties": {
    "gn:country":"FR",
    "gn:fcode":"PPL",
    "gn:population":2022,
    "iso:country":"FR",
    "name:cat_x_preferred":[
        "Sent Lo\u00eds de Montferrand"
    ],
    "name:kaz_x_preferred":[
        "\u0421\u0435\u043d-\u041b\u0443\u0438-\u0434\u0435-\u041c\u043e\u043d\u0444\u0435\u0440\u0440\u0430\u043d"
    ],
    "name:oci_x_preferred":[
        "Sent Lo\u00eds de Mont Ferrand"
    ],
    "name:ukr_x_preferred":[
        "\u0421\u0435\u043d-\u041b\u0443\u0457-\u0434\u0435-\u041c\u043e\u043d\u0444\u0435\u0440\u0440\u0430\u043d"
    ],
    "name:und_x_variant":[
        "Saint-Louis"
    ],
    "name:urd_x_preferred":[
        "\u0633\u06cc\u0646\u0679-\u0644\u0648\u0626\u06cc\u0633-\u062f\u06d2-\u0645\u0648\u0646\u062a\u0641\u0631\u0631\u0627\u0646\u0688"
    ],
    "name:zho_x_preferred":[
        "\u5723\u5362\u4f0a\u5fb7\u8499\u7279\u5f17\u5c14\u6717"
    ],
    "qs_pg:aaroncc":"FR",
    "qs_pg:gn_country":"FR",
    "qs_pg:gn_fcode":"PPL",
    "qs_pg:gn_pop":2022,
    "qs_pg:name":"St.-Louis-de-Montferrand",
    "qs_pg:name_adm0":"France",
    "qs_pg:name_adm1":"Aquitaine",
    "qs_pg:photos_9r":0,
    "qs_pg:photos_sr":0,
    "qs_pg:pop_sr":4,
    "qs_pg:qs_pg_placetype":"neighbourhood",
    "qs_pg:qs_pg_placetype_gp":"Suburb",
    "qs_pg:woe_adm0":23424819,
    "woe:adm0_id":23424819,
    "woe:name_adm0":"France",
    "woe:name_adm1":"Aquitaine",
    "woe:placetype":"Suburb",
    "wof:name":"St.-Louis-de-Montferrand",
    "wof:placetype":"neighbourhood",
    "wof:population":2022
},
  "geometry": {"coordinates":[-0.53543,44.95],"type":"Point"}
}