{
  "type": "Feature",
  "properties": {
    "gn:admin1_code":"84",
    "gn:admin2_code":"63",
    "gn:admin3_code":"632",
    "gn:admin4_code":"63071",
    "gn:asciiname":"Allagnat",
    "gn:country_code":"FR",
    "gn:dem":908,
    "gn:feature_class":"P",
    "gn:feature_code":"PPL",
    "gn:name":"Allagnat",
    "gn:population":0,
    "gn:timezone":"Europe/Paris",
    "iso:country":"FR",
    "wof:name":"Allagnat",
    "wof:placetype":"locality"
},
  "geometry": {"coordinates":[2.91548,45.75126],"type":"Point"}
}