{
  "type": "Feature",
  "properties": {
    "gn:admin1_code":"84",
    "gn:admin2_code":"38",
    "gn:admin3_code":"381",
    "gn:admin4_code":"38456",
    "gn:asciiname":"Masserange",
    "gn:country_code":"FR",
    "gn:dem":907,
    "gn:feature_class":"P",
    "gn:feature_code":"PPL",
    "gn:name":"Masserange",
    "gn:population":0,
    "gn:timezone":"Europe/Paris",
    "iso:country":"FR",
    "wof:name":"Masserange",
    "wof:placetype":"locality"
},
  "geometry": {"coordinates":[5.78766,44.86113],"type":"Point"}
}