{
  "type": "Feature",
  "properties": {
    "gn:admin1_code":"53",
    "gn:admin2_code":"22",
    "gn:admin3_code":"224",
    "gn:admin4_code":"22222",
    "gn:asciiname":"Beaugouyan",
    "gn:country_code":"FR",
    "gn:dem":98,
    "gn:feature_class":"P",
    "gn:feature_code":"PPL",
    "gn:name":"Beaugouyan",
    "gn:population":0,
    "gn:timezone":"Europe/Paris",
    "iso:country":"FR",
    "wof:name":"Beaugouyan",
    "wof:placetype":"locality"
},
  "geometry": {"coordinates":[-2.90383,48.64767],"type":"Point"}
}