{
  "type": "Feature",
  "properties": {
    "gn:gn_country":"FR",
    "gn:gn_fcode":"PPL",
    "gn:gn_pop":0,
    "iso:country":"FR",
    "name:unk_x_variant":[
        "Saint-Aubin"
    ],
    "qs_pg:aaroncc":"FR",
    "qs_pg:gn_country":"FR",
    "qs_pg:gn_fcode":"PPL",
    "qs_pg:gn_pop":0,
    "qs_pg:name":"St.-Aubin-sur-Algot",
    "qs_pg:name_adm0":"France",
    "qs_pg:name_adm1":"Basse-Normandie",
    "qs_pg:photos_9k":1,
    "qs_pg:photos_9r":1,
    "qs_pg:photos_all":2,
    "qs_pg:photos_sr":0,
    "qs_pg:pop_sr":0,
    "qs_pg:qs_pg_placetype":"locality",
    "qs_pg:qs_pg_placetype_gp":"Town",
    "qs_pg:woe_adm0":23424819,
    "woe:adm0_id":23424819,
    "woe:name_adm0":"France",
    "woe:name_adm1":"Basse-Normandie",
    "woe:placetype":"Town",
    "wof:name":"St.-Aubin-sur-Algot",
    "wof:placetype":"neighbourhood"
},
  "geometry": {"coordinates":[0.08864,49.1301],"type":"Point"}
}