{
  "type": "Feature",
  "properties": {
    "gn:admin1_code":"44",
    "gn:admin2_code":"54",
    "gn:admin3_code":"541",
    "gn:admin4_code":"54178",
    "gn:asciiname":"Epiez-sur-Chiers",
    "gn:country_code":"FR",
    "gn:dem":198,
    "gn:feature_class":"P",
    "gn:feature_code":"PPL",
    "gn:name":"\u00c9piez-sur-Chiers",
    "gn:population":0,
    "gn:timezone":"Europe/Paris",
    "iso:country":"FR",
    "name:und_x_variant":[
        "\u00c9piez",
        "\u00c9piez-sur-Chiers"
    ],
    "wof:name":"Epiez-sur-Chiers",
    "wof:placetype":"locality"
},
  "geometry": {"coordinates":[5.50386,49.49155],"type":"Point"}
}