{
  "type": "Feature",
  "properties": {
    "gn:admin1_code":"84",
    "gn:admin2_code":"63",
    "gn:admin3_code":"632",
    "gn:admin4_code":"63026",
    "gn:asciiname":"Ponteix",
    "gn:country_code":"FR",
    "gn:dem":744,
    "gn:feature_class":"P",
    "gn:feature_code":"PPL",
    "gn:name":"Ponteix",
    "gn:population":0,
    "gn:timezone":"Europe/Paris",
    "iso:country":"FR",
    "name:fas_x_preferred":[
        "\u067e\u0627\u0646\u062a\u06cc\u06a9\u0633"
    ],
    "name:fra_x_preferred":[
        "Ponteix"
    ],
    "name:nld_x_preferred":[
        "Ponteix"
    ],
    "name:oci_x_preferred":[
        "Ponteix"
    ],
    "name:pol_x_preferred":[
        "Ponteix"
    ],
    "wof:name":"Ponteix",
    "wof:placetype":"locality"
},
  "geometry": {"coordinates":[3.02235,45.66273],"type":"Point"}
}