{
  "type": "Feature",
  "properties": {
    "gn:admin1_code":"76",
    "gn:admin2_code":"30",
    "gn:admin3_code":"303",
    "gn:admin4_code":"30325",
    "gn:asciiname":"Pinoch",
    "gn:country_code":"FR",
    "gn:dem":529,
    "gn:feature_class":"P",
    "gn:feature_code":"PPL",
    "gn:name":"Pinoch",
    "gn:population":0,
    "gn:timezone":"Europe/Paris",
    "iso:country":"FR",
    "wof:name":"Pinoch",
    "wof:placetype":"locality"
},
  "geometry": {"coordinates":[3.69834,44.00046],"type":"Point"}
}