{
  "type": "Feature",
  "properties": {
    "gn:admin1_code":"53",
    "gn:admin2_code":"29",
    "gn:admin3_code":"292",
    "gn:admin4_code":"29041",
    "gn:asciiname":"Keresquant",
    "gn:country_code":"FR",
    "gn:dem":139,
    "gn:feature_class":"P",
    "gn:feature_code":"PPL",
    "gn:name":"Keresquant",
    "gn:population":0,
    "gn:timezone":"Europe/Paris",
    "iso:country":"FR",
    "wof:name":"Keresquant",
    "wof:placetype":"locality"
},
  "geometry": {"coordinates":[-3.88122,48.06445],"type":"Point"}
}