{
  "type": "Feature",
  "properties": {
    "gn:admin1_code":"94",
    "gn:admin2_code":"2A",
    "gn:admin3_code":"2A1",
    "gn:admin4_code":"2A090",
    "gn:asciiname":"Cerasa",
    "gn:country_code":"FR",
    "gn:dem":600,
    "gn:feature_class":"P",
    "gn:feature_code":"PPL",
    "gn:name":"Cerasa",
    "gn:population":0,
    "gn:timezone":"Europe/Paris",
    "iso:country":"FR",
    "name:deu_x_preferred":[
        "Titularbistum Cerasa"
    ],
    "wof:name":"Cerasa",
    "wof:placetype":"locality"
},
  "geometry": {"coordinates":[8.75107,42.12876],"type":"Point"}
}