{
  "type": "Feature",
  "properties": {
    "gn:admin1_code":"75",
    "gn:admin2_code":"23",
    "gn:admin3_code":"232",
    "gn:admin4_code":"23056",
    "gn:asciiname":"Villemontheix",
    "gn:cc2":"FR",
    "gn:country_code":"FR",
    "gn:dem":575,
    "gn:feature_class":"P",
    "gn:feature_code":"PPL",
    "gn:name":"Villemontheix",
    "gn:population":0,
    "gn:timezone":"Europe/Paris",
    "iso:country":"FR",
    "name:und_x_variant":[
        "Villemontheil",
        "Villemontheix"
    ],
    "wof:name":"Villemontheix",
    "wof:placetype":"locality"
},
  "geometry": {"coordinates":[1.66667,45.98333],"type":"Point"}
}