{
  "type": "Feature",
  "properties": {
    "gn:admin1_code":"32",
    "gn:admin2_code":"62",
    "gn:admin3_code":"624",
    "gn:admin4_code":"62844",
    "gn:asciiname":"Gournay",
    "gn:country_code":"FR",
    "gn:dem":150,
    "gn:feature_class":"P",
    "gn:feature_code":"PPL",
    "gn:name":"Gournay",
    "gn:population":0,
    "gn:timezone":"Europe/Paris",
    "iso:country":"FR",
    "wof:name":"Gournay",
    "wof:placetype":"locality"
},
  "geometry": {"coordinates":[2.06449,50.55279],"type":"Point"}
}