{
  "type": "Feature",
  "properties": {
    "gn:admin1_code":"76",
    "gn:admin2_code":"09",
    "gn:admin3_code":"093",
    "gn:admin4_code":"09129",
    "gn:asciiname":"Galey",
    "gn:country_code":"FR",
    "gn:dem":823,
    "gn:feature_class":"P",
    "gn:feature_code":"PPL",
    "gn:name":"Galey",
    "gn:population":0,
    "gn:timezone":"Europe/Paris",
    "iso:country":"FR",
    "wof:name":"Galey",
    "wof:placetype":"locality"
},
  "geometry": {"coordinates":[0.91473,42.93669000000001],"type":"Point"}
}