{
  "type": "Feature",
  "properties": {
    "gn:admin1_code":"76",
    "gn:admin2_code":"09",
    "gn:admin3_code":"093",
    "gn:admin4_code":"09129",
    "gn:asciiname":"Galey",
    "gn:country_code":"FR",
    "gn:dem":823,
    "gn:feature_class":"P",
    "gn:feature_code":"PPL",
    "gn:name":"Galey",
    "gn:population":0,
    "gn:timezone":"Europe/Paris",
    "iso:country":"FR",
    "name:bug_x_preferred":[
        "Galey"
    ],
    "name:cat_x_preferred":[
        "Gal\u00e8i"
    ],
    "name:ceb_x_preferred":[
        "Galey"
    ],
    "name:deu_x_preferred":[
        "Galey"
    ],
    "name:eus_x_preferred":[
        "Galey"
    ],
    "name:fra_x_preferred":[
        "Galey"
    ],
    "name:hun_x_preferred":[
        "Galey"
    ],
    "name:hye_x_preferred":[
        "\u0533\u0561\u056c\u0565"
    ],
    "name:ita_x_preferred":[
        "Galey"
    ],
    "name:lat_x_preferred":[
        "Galey"
    ],
    "name:mlg_x_preferred":[
        "Galey"
    ],
    "name:msa_x_preferred":[
        "Galey"
    ],
    "name:nld_x_preferred":[
        "Galey"
    ],
    "name:oci_x_preferred":[
        "Gal\u00e8i"
    ],
    "name:pol_x_preferred":[
        "Galey"
    ],
    "name:por_x_preferred":[
        "Galey"
    ],
    "name:ron_x_preferred":[
        "Galey"
    ],
    "name:rus_x_preferred":[
        "\u0413\u0430\u043b\u0435"
    ],
    "name:slk_x_preferred":[
        "Galey"
    ],
    "name:spa_x_preferred":[
        "Galey"
    ],
    "name:swe_x_preferred":[
        "Galey"
    ],
    "name:ukr_x_preferred":[
        "\u0413\u0430\u043b\u0435"
    ],
    "name:vie_x_preferred":[
        "Galey"
    ],
    "name:vol_x_preferred":[
        "Galey"
    ],
    "name:war_x_preferred":[
        "Galey"
    ],
    "name:zho_x_preferred":[
        "\u52a0\u83b1"
    ],
    "wof:name":"Galey",
    "wof:placetype":"locality"
},
  "geometry": {"coordinates":[0.91473,42.93669000000001],"type":"Point"}
}