{
  "type": "Feature",
  "properties": {
    "gn:admin1_code":"75",
    "gn:admin2_code":"86",
    "gn:admin3_code":"862",
    "gn:admin4_code":"86097",
    "gn:asciiname":"Les Sables",
    "gn:country_code":"FR",
    "gn:dem":126,
    "gn:feature_class":"P",
    "gn:feature_code":"PPL",
    "gn:name":"Les Sables",
    "gn:population":0,
    "gn:timezone":"Europe/Paris",
    "iso:country":"FR",
    "wof:name":"Les Sables",
    "wof:placetype":"locality"
},
  "geometry": {"coordinates":[0.43403,46.33472],"type":"Point"}
}