{
  "type": "Feature",
  "properties": {
    "gn:admin1_code":"53",
    "gn:admin2_code":"22",
    "gn:admin3_code":"224",
    "gn:admin4_code":"22136",
    "gn:asciiname":"Limpiguet",
    "gn:country_code":"FR",
    "gn:dem":184,
    "gn:feature_class":"P",
    "gn:feature_code":"PPL",
    "gn:name":"Limpiguet",
    "gn:population":0,
    "gn:timezone":"Europe/Paris",
    "iso:country":"FR",
    "wof:name":"Limpiguet",
    "wof:placetype":"locality"
},
  "geometry": {"coordinates":[-2.76414,48.20048],"type":"Point"}
}