{
  "type": "Feature",
  "properties": {
    "gn:admin1_code":"24",
    "gn:admin2_code":"18",
    "gn:admin3_code":"182",
    "gn:admin4_code":"18031",
    "gn:asciiname":"Buciere",
    "gn:country_code":"FR",
    "gn:dem":233,
    "gn:feature_class":"P",
    "gn:feature_code":"PPL",
    "gn:name":"Buci\u00e8re",
    "gn:population":0,
    "gn:timezone":"Europe/Paris",
    "iso:country":"FR",
    "wof:name":"Buciere",
    "wof:placetype":"locality"
},
  "geometry": {"coordinates":[2.74479,46.86792],"type":"Point"}
}