{
  "type": "Feature",
  "properties": {
    "gn:admin1_code":"76",
    "gn:admin2_code":"12",
    "gn:admin3_code":"121",
    "gn:admin4_code":"12160",
    "gn:asciiname":"Liaucous",
    "gn:country_code":"FR",
    "gn:dem":516,
    "gn:feature_class":"P",
    "gn:feature_code":"PPL",
    "gn:name":"Liaucous",
    "gn:population":0,
    "gn:timezone":"Europe/Paris",
    "iso:country":"FR",
    "wof:name":"Liaucous",
    "wof:placetype":"locality"
},
  "geometry": {"coordinates":[3.1949,44.20223],"type":"Point"}
}