{
  "type": "Feature",
  "properties": {
    "iso:country":"FR",
    "name:eng_x_preferred":[
        "Val-de-Bievre"
    ],
    "name:fra_x_preferred":[
        "Val-de-Bi\u00e8vre"
    ],
    "wof:name":"Val-de-Bievre",
    "wof:placetype":"neighbourhood"
},
  "geometry": {"coordinates":[2.34327566170581,48.81078958882327],"type":"Point"}
}