{
  "type": "Feature",
  "properties": {
    "gn:admin1_code":"75",
    "gn:admin2_code":"19",
    "gn:admin3_code":"193",
    "gn:admin4_code":"19008",
    "gn:asciiname":"Besses",
    "gn:country_code":"FR",
    "gn:dem":658,
    "gn:feature_class":"P",
    "gn:feature_code":"PPL",
    "gn:name":"Besses",
    "gn:population":0,
    "gn:timezone":"Europe/Paris",
    "iso:country":"FR",
    "wof:name":"Besses",
    "wof:placetype":"locality"
},
  "geometry": {"coordinates":[2.11713,45.50776],"type":"Point"}
}