{
  "type": "Feature",
  "properties": {
    "gn:admin1_code":"75",
    "gn:admin2_code":"19",
    "gn:admin3_code":"192",
    "gn:admin4_code":"19125",
    "gn:asciiname":"Chiniac",
    "gn:country_code":"FR",
    "gn:dem":578,
    "gn:feature_class":"P",
    "gn:feature_code":"PPL",
    "gn:name":"Chiniac",
    "gn:population":0,
    "gn:timezone":"Europe/Paris",
    "iso:country":"FR",
    "wof:name":"Chiniac",
    "wof:placetype":"locality"
},
  "geometry": {"coordinates":[2.03717,45.27692],"type":"Point"}
}