{
  "type": "Feature",
  "properties": {
    "gn:admin1_code":"84",
    "gn:admin2_code":"63",
    "gn:admin3_code":"632",
    "gn:admin4_code":"63257.0",
    "gn:asciiname":"La Gardette",
    "gn:country_code":"FR",
    "gn:dem":784,
    "gn:feature_class":"P",
    "gn:feature_code":"PPL",
    "gn:name":"La Gardette",
    "gn:population":0,
    "gn:timezone":"Europe/Paris",
    "iso:country":"FR",
    "wof:name":"La Gardette",
    "wof:placetype":"locality"
},
  "geometry": {"coordinates":[2.87219,45.76777],"type":"Point"}
}