{
  "type": "Feature",
  "properties": {
    "gn:admin1_code":"24",
    "gn:admin2_code":"28",
    "gn:admin3_code":"281",
    "gn:admin4_code":"28406",
    "gn:asciiname":"Toutlifaut",
    "gn:country_code":"FR",
    "gn:dem":127,
    "gn:feature_class":"P",
    "gn:feature_code":"PPL",
    "gn:name":"Toutlifaut",
    "gn:population":0,
    "gn:timezone":"Europe/Paris",
    "iso:country":"FR",
    "wof:name":"Toutlifaut",
    "wof:placetype":"locality"
},
  "geometry": {"coordinates":[1.72237,48.17402],"type":"Point"}
}