{
  "type": "Feature",
  "properties": {
    "gn:admin1_code":"24",
    "gn:admin2_code":"18",
    "gn:admin3_code":"183",
    "gn:admin4_code":"18165",
    "gn:asciiname":"Le Grand Jeu",
    "gn:country_code":"FR",
    "gn:dem":167,
    "gn:feature_class":"P",
    "gn:feature_code":"PPL",
    "gn:name":"Le Grand Jeu",
    "gn:population":0,
    "gn:timezone":"Europe/Paris",
    "iso:country":"FR",
    "name:deu_x_preferred":[
        "Le Grand Jeu"
    ],
    "name:fra_x_preferred":[
        "Le Grand Jeu"
    ],
    "name:nld_x_preferred":[
        "Le Grand Jeu"
    ],
    "wof:name":"Le Grand Jeu",
    "wof:placetype":"locality"
},
  "geometry": {"coordinates":[2.28076,47.34791],"type":"Point"}
}