{
  "type": "Feature",
  "properties": {
    "gn:admin1_code":"84",
    "gn:admin2_code":"63",
    "gn:admin3_code":"631",
    "gn:admin4_code":"63105",
    "gn:asciiname":"Chaumont-le-Bourg",
    "gn:country_code":"FR",
    "gn:dem":618,
    "gn:feature_class":"P",
    "gn:feature_code":"PPL",
    "gn:name":"Chaumont-le-Bourg",
    "gn:population":0,
    "gn:timezone":"Europe/Paris",
    "iso:country":"FR",
    "name:cat_x_preferred":[
        "Chaumont"
    ],
    "name:ceb_x_preferred":[
        "Chaumont-le-Bourg"
    ],
    "name:deu_x_preferred":[
        "Chaumont-le-Bourg"
    ],
    "name:eus_x_preferred":[
        "Chaumont-le-Bourg"
    ],
    "name:fra_x_preferred":[
        "Chaumont-le-Bourg"
    ],
    "name:hun_x_preferred":[
        "Chaumont-le-Bourg"
    ],
    "name:ita_x_preferred":[
        "Chaumont-le-Bourg"
    ],
    "name:kaz_x_preferred":[
        "\u0428\u043e\u043c\u043e\u043d-\u043b\u0435-\u0411\u0443\u0440"
    ],
    "name:lat_x_preferred":[
        "Chaumont-le-Bourg"
    ],
    "name:mlg_x_preferred":[
        "Chaumont-le-Bourg"
    ],
    "name:msa_x_preferred":[
        "Chaumont-le-Bourg"
    ],
    "name:nld_x_preferred":[
        "Chaumont-le-Bourg"
    ],
    "name:oci_x_preferred":[
        "Chaumont-le-Bourg"
    ],
    "name:pms_x_preferred":[
        "Chaumont-le-Bourg"
    ],
    "name:pol_x_preferred":[
        "Chaumont-le-Bourg"
    ],
    "name:por_x_preferred":[
        "Chaumont-le-Bourg"
    ],
    "name:ron_x_preferred":[
        "Chaumont-le-Bourg"
    ],
    "name:slk_x_preferred":[
        "Chaumont-le-Bourg"
    ],
    "name:spa_x_preferred":[
        "Chaumont-le-Bourg"
    ],
    "name:swe_x_preferred":[
        "Chaumont-le-Bourg"
    ],
    "name:ukr_x_preferred":[
        "\u0428\u043e\u043c\u043e\u043d-\u043b\u0435-\u0411\u0443\u0440"
    ],
    "name:uzb_x_preferred":[
        "Chaumont-le-Bourg"
    ],
    "name:vie_x_preferred":[
        "Chaumont-le-Bourg"
    ],
    "name:vol_x_preferred":[
        "Chaumont-le-Bourg"
    ],
    "name:war_x_preferred":[
        "Chaumont-le-Bourg"
    ],
    "name:zho_x_preferred":[
        "\u7ecd\u8499\u52d2\u5e03\u5c14"
    ],
    "wof:name":"Chaumont-le-Bourg",
    "wof:placetype":"locality"
},
  "geometry": {"coordinates":[3.7718,45.45],"type":"Point"}
}