{
  "type": "Feature",
  "properties": {
    "gn:admin1_code":"84",
    "gn:admin2_code":"63",
    "gn:admin3_code":"631",
    "gn:admin4_code":"63105",
    "gn:asciiname":"Chaumont-le-Bourg",
    "gn:country_code":"FR",
    "gn:dem":618,
    "gn:feature_class":"P",
    "gn:feature_code":"PPL",
    "gn:name":"Chaumont-le-Bourg",
    "gn:population":0,
    "gn:timezone":"Europe/Paris",
    "iso:country":"FR",
    "wof:name":"Chaumont-le-Bourg",
    "wof:placetype":"locality"
},
  "geometry": {"coordinates":[3.7718,45.45],"type":"Point"}
}