{
  "type": "Feature",
  "properties": {
    "iso:country":"FR",
    "name:eng_x_preferred":[
        "Becon Bac Flachat"
    ],
    "name:fra_x_preferred":[
        "B\u00e9con Bac Flachat"
    ],
    "wof:name":"Becon Bac Flachat",
    "wof:placetype":"neighbourhood"
},
  "geometry": {"coordinates":[2.27685052245938,48.90986515240135],"type":"Point"}
}