{
  "type": "Feature",
  "properties": {
    "gn:admin1_code":"11",
    "gn:admin2_code":"78",
    "gn:admin3_code":"782",
    "gn:admin4_code":"78478.0",
    "gn:asciiname":"Villiers-les-Oudets",
    "gn:country_code":"FR",
    "gn:dem":155,
    "gn:feature_class":"P",
    "gn:feature_code":"PPL",
    "gn:name":"Villiers-les-Oudets",
    "gn:population":0,
    "gn:timezone":"Europe/Paris",
    "iso:country":"FR",
    "wof:name":"Villiers-les-Oudets",
    "wof:placetype":"locality"
},
  "geometry": {"coordinates":[1.87528,48.45123],"type":"Point"}
}