{
  "type": "Feature",
  "properties": {
    "gn:admin1_code":"75",
    "gn:admin2_code":"24",
    "gn:admin3_code":"244",
    "gn:admin4_code":"24547",
    "gn:asciiname":"La Talerie",
    "gn:country_code":"FR",
    "gn:dem":261,
    "gn:feature_class":"P",
    "gn:feature_code":"PPL",
    "gn:name":"La Talerie",
    "gn:population":0,
    "gn:timezone":"Europe/Paris",
    "iso:country":"FR",
    "name:und_x_variant":[
        "La Tallerie",
        "La Talerie"
    ],
    "wof:name":"La Talerie",
    "wof:placetype":"locality"
},
  "geometry": {"coordinates":[1.28281,45.12051],"type":"Point"}
}