{
  "type": "Feature",
  "properties": {
    "gn:admin1_code":"44",
    "gn:admin2_code":"88",
    "gn:admin3_code":"883",
    "gn:admin4_code":"88213",
    "gn:asciiname":"La Grande-Fosse",
    "gn:country_code":"FR",
    "gn:dem":619,
    "gn:feature_class":"P",
    "gn:feature_code":"PPL",
    "gn:name":"La Grande-Fosse",
    "gn:population":0,
    "gn:timezone":"Europe/Paris",
    "iso:country":"FR",
    "wof:name":"La Grande-Fosse",
    "wof:placetype":"locality"
},
  "geometry": {"coordinates":[7.06962,48.33936],"type":"Point"}
}