{
  "type": "Feature",
  "properties": {
    "gn:admin1_code":"44",
    "gn:admin2_code":"88",
    "gn:admin3_code":"883",
    "gn:admin4_code":"88213",
    "gn:asciiname":"La Grande-Fosse",
    "gn:country_code":"FR",
    "gn:dem":619,
    "gn:feature_class":"P",
    "gn:feature_code":"PPL",
    "gn:name":"La Grande-Fosse",
    "gn:population":0,
    "gn:timezone":"Europe/Paris",
    "iso:country":"FR",
    "name:bug_x_preferred":[
        "La Grande-Fosse"
    ],
    "name:cat_x_preferred":[
        "La Grande-Fosse"
    ],
    "name:ceb_x_preferred":[
        "La Grande-Fosse"
    ],
    "name:deu_x_preferred":[
        "La Grande-Fosse"
    ],
    "name:eus_x_preferred":[
        "La Grande-Fosse"
    ],
    "name:fra_x_preferred":[
        "La Grande-Fosse"
    ],
    "name:hun_x_preferred":[
        "La Grande-Fosse"
    ],
    "name:ind_x_preferred":[
        "La Grande-Fosse"
    ],
    "name:ita_x_preferred":[
        "La Grande-Fosse"
    ],
    "name:kaz_x_preferred":[
        "\u041b\u0430-\u0413\u0440\u0430\u043d\u0434-\u0424\u043e\u0441\u0441"
    ],
    "name:ltz_x_preferred":[
        "La Grande-Fosse"
    ],
    "name:msa_x_preferred":[
        "La Grande-Fosse"
    ],
    "name:nld_x_preferred":[
        "La Grande-Fosse"
    ],
    "name:oci_x_preferred":[
        "La Grande-Fosse"
    ],
    "name:pms_x_preferred":[
        "La Grande-Fosse"
    ],
    "name:pol_x_preferred":[
        "La Grande-Fosse"
    ],
    "name:por_x_preferred":[
        "La Grande-Fosse"
    ],
    "name:slk_x_preferred":[
        "La Grande-Fosse"
    ],
    "name:spa_x_preferred":[
        "La Grande-Fosse"
    ],
    "name:swe_x_preferred":[
        "La Grande-Fosse"
    ],
    "name:ukr_x_preferred":[
        "\u041b\u0430-\u0413\u0440\u0430\u043d\u0434-\u0424\u043e\u0441\u0441"
    ],
    "name:urd_x_preferred":[
        "\u0644\u0627 \u06af\u0631\u0627\u0646\u062f\u06cc-\u0641\u0648\u0633\u06cc"
    ],
    "name:uzb_x_preferred":[
        "La Grande-Fosse"
    ],
    "name:vie_x_preferred":[
        "La Grande-Fosse"
    ],
    "name:vol_x_preferred":[
        "La Grande-Fosse"
    ],
    "name:war_x_preferred":[
        "La Grande-Fosse"
    ],
    "name:zho_x_preferred":[
        "\u62c9\u683c\u6717\u5fb7\u798f\u585e"
    ],
    "wof:name":"La Grande-Fosse",
    "wof:placetype":"locality"
},
  "geometry": {"coordinates":[7.06962,48.33936],"type":"Point"}
}