{
  "type": "Feature",
  "properties": {
    "gn:admin1_code":"75",
    "gn:admin2_code":"79",
    "gn:admin3_code":"792",
    "gn:admin4_code":"79061",
    "gn:asciiname":"Verrines-sous-Celles",
    "gn:country_code":"FR",
    "gn:dem":87,
    "gn:feature_class":"P",
    "gn:feature_code":"PPL",
    "gn:name":"Verrines-sous-Celles",
    "gn:population":0,
    "gn:timezone":"Europe/Paris",
    "iso:country":"FR",
    "name:und_x_variant":[
        "Verrines",
        "Verrines-sous-Celles"
    ],
    "wof:name":"Verrines-sous-Celles",
    "wof:placetype":"locality"
},
  "geometry": {"coordinates":[-0.22914,46.22943],"type":"Point"}
}