{
  "type": "Feature",
  "properties": {
    "gn:admin1_code":"84",
    "gn:admin2_code":"63",
    "gn:admin3_code":"631",
    "gn:admin4_code":"63137",
    "gn:asciiname":"Pierre",
    "gn:country_code":"FR",
    "gn:dem":956,
    "gn:feature_class":"P",
    "gn:feature_code":"PPL",
    "gn:name":"Pierre",
    "gn:population":0,
    "gn:timezone":"Europe/Paris",
    "iso:country":"FR",
    "name:bre_x_preferred":[
        "Pierre"
    ],
    "name:deu_x_preferred":[
        "Pierre"
    ],
    "name:fas_x_preferred":[
        "\u067e\u06cc\u0631"
    ],
    "name:fra_x_preferred":[
        "Pierre"
    ],
    "name:ind_x_preferred":[
        "Pierre"
    ],
    "name:jpn_x_preferred":[
        "\u30d4\u30a8\u30fc\u30eb"
    ],
    "name:kor_x_preferred":[
        "\ud53c\uc5d0\ub974"
    ],
    "name:nld_x_preferred":[
        "Pierre"
    ],
    "name:nor_x_preferred":[
        "Pierre"
    ],
    "name:por_x_preferred":[
        "Pierre"
    ],
    "name:swe_x_preferred":[
        "Pierre"
    ],
    "wof:name":"Pierre",
    "wof:placetype":"locality"
},
  "geometry": {"coordinates":[3.62298,45.39762],"type":"Point"}
}