{
  "type": "Feature",
  "properties": {
    "gn:admin1_code":"84",
    "gn:admin2_code":"63",
    "gn:admin3_code":"631",
    "gn:admin4_code":"63137",
    "gn:asciiname":"Pierre",
    "gn:country_code":"FR",
    "gn:dem":956,
    "gn:feature_class":"P",
    "gn:feature_code":"PPL",
    "gn:name":"Pierre",
    "gn:population":0,
    "gn:timezone":"Europe/Paris",
    "iso:country":"FR",
    "wof:name":"Pierre",
    "wof:placetype":"locality"
},
  "geometry": {"coordinates":[3.62298,45.39762],"type":"Point"}
}