{
  "type": "Feature",
  "properties": {
    "gn:gn_country":"FR",
    "gn:gn_fcode":"PPL",
    "gn:gn_pop":952,
    "gn:population":952,
    "iso:country":"FR",
    "qs_pg:aaroncc":"FR",
    "qs_pg:gn_country":"FR",
    "qs_pg:gn_fcode":"PPL",
    "qs_pg:gn_pop":952,
    "qs_pg:name":"G\u00e2telles",
    "qs_pg:name_adm0":"France",
    "qs_pg:name_adm1":"Centre",
    "qs_pg:photos_9r":0,
    "qs_pg:photos_sr":0,
    "qs_pg:pop_sr":2,
    "qs_pg:qs_pg_placetype":"locality",
    "qs_pg:qs_pg_placetype_gp":"Town",
    "qs_pg:woe_adm0":23424819,
    "woe:adm0_id":23424819,
    "woe:name_adm0":"France",
    "woe:name_adm1":"Centre",
    "woe:placetype":"Town",
    "wof:name":"G\u00e2telles",
    "wof:placetype":"neighbourhood",
    "wof:population":952
},
  "geometry": {"coordinates":[1.28738,48.54352],"type":"Point"}
}