{
  "type": "Feature",
  "properties": {
    "gn:admin1_code":"27",
    "gn:admin2_code":"89",
    "gn:admin3_code":"892",
    "gn:admin4_code":"89044",
    "gn:asciiname":"Les Herodats",
    "gn:country_code":"FR",
    "gn:dem":259,
    "gn:feature_class":"P",
    "gn:feature_code":"PPL",
    "gn:name":"Les H\u00e9rodats",
    "gn:population":0,
    "gn:timezone":"Europe/Paris",
    "iso:country":"FR",
    "wof:name":"Les Herodats",
    "wof:placetype":"locality"
},
  "geometry": {"coordinates":[3.75547,47.52548],"type":"Point"}
}