{
  "type": "Feature",
  "properties": {
    "gn:admin1_code":"84",
    "gn:admin2_code":"07",
    "gn:admin3_code":"073",
    "gn:admin4_code":"07192",
    "gn:asciiname":"Binas",
    "gn:country_code":"FR",
    "gn:dem":719,
    "gn:feature_class":"P",
    "gn:feature_code":"PPL",
    "gn:name":"Binas",
    "gn:population":0,
    "gn:timezone":"Europe/Paris",
    "iso:country":"FR",
    "wof:name":"Binas",
    "wof:placetype":"locality"
},
  "geometry": {"coordinates":[4.43333,45.06667],"type":"Point"}
}