{
  "type": "Feature",
  "properties": {
    "gn:admin1_code":"84",
    "gn:admin2_code":"07",
    "gn:admin3_code":"073",
    "gn:admin4_code":"07192",
    "gn:asciiname":"Binas",
    "gn:country_code":"FR",
    "gn:dem":719,
    "gn:feature_class":"P",
    "gn:feature_code":"PPL",
    "gn:name":"Binas",
    "gn:population":0,
    "gn:timezone":"Europe/Paris",
    "iso:country":"FR",
    "name:cat_x_preferred":[
        "Binas"
    ],
    "name:ceb_x_preferred":[
        "Binas"
    ],
    "name:deu_x_preferred":[
        "Binas"
    ],
    "name:eus_x_preferred":[
        "Binas"
    ],
    "name:fra_x_preferred":[
        "Binas"
    ],
    "name:hun_x_preferred":[
        "Binas"
    ],
    "name:ita_x_preferred":[
        "Binas"
    ],
    "name:lat_x_preferred":[
        "Binas"
    ],
    "name:msa_x_preferred":[
        "Binas"
    ],
    "name:nld_x_preferred":[
        "Binas"
    ],
    "name:oci_x_preferred":[
        "Binas"
    ],
    "name:pms_x_preferred":[
        "Binas"
    ],
    "name:pol_x_preferred":[
        "Binas"
    ],
    "name:por_x_preferred":[
        "Binas"
    ],
    "name:ron_x_preferred":[
        "Binas"
    ],
    "name:slk_x_preferred":[
        "Binas"
    ],
    "name:spa_x_preferred":[
        "Binas"
    ],
    "name:srp_x_preferred":[
        "\u0411\u0438\u043d\u0430"
    ],
    "name:swe_x_preferred":[
        "Binas"
    ],
    "name:ukr_x_preferred":[
        "\u0411\u0456\u043d\u0430"
    ],
    "name:uzb_x_preferred":[
        "Binas"
    ],
    "name:vie_x_preferred":[
        "Binas"
    ],
    "name:vol_x_preferred":[
        "Binas"
    ],
    "name:war_x_preferred":[
        "Binas"
    ],
    "wof:name":"Binas",
    "wof:placetype":"locality"
},
  "geometry": {"coordinates":[4.43333,45.06667],"type":"Point"}
}