{
  "type": "Feature",
  "properties": {
    "gn:admin1_code":"27",
    "gn:admin2_code":"21",
    "gn:admin3_code":"213",
    "gn:admin4_code":"21425",
    "gn:asciiname":"La Mairie",
    "gn:country_code":"FR",
    "gn:dem":344,
    "gn:feature_class":"P",
    "gn:feature_code":"PPL",
    "gn:name":"La Mairie",
    "gn:population":0,
    "gn:timezone":"Europe/Paris",
    "iso:country":"FR",
    "wof:name":"La Mairie",
    "wof:placetype":"locality"
},
  "geometry": {"coordinates":[4.34497,47.66154],"type":"Point"}
}