{
  "type": "Feature",
  "properties": {
    "iso:country":"FR",
    "name:eng_x_preferred":[
        "Villeneuve"
    ],
    "name:fra_x_preferred":[
        "Villeneuve"
    ],
    "wof:name":"Villeneuve",
    "wof:placetype":"neighbourhood"
},
  "geometry": {"coordinates":[-1.68016720411265,48.09829369139483],"type":"Point"}
}