{
  "type": "Feature",
  "properties": {
    "gn:admin1_code":"53",
    "gn:admin2_code":"56",
    "gn:admin3_code":"561",
    "gn:admin4_code":"56185",
    "gn:asciiname":"Kervegant",
    "gn:country_code":"FR",
    "gn:dem":39,
    "gn:feature_class":"P",
    "gn:feature_code":"PPL",
    "gn:name":"Kerv\u00e9gant",
    "gn:population":0,
    "gn:timezone":"Europe/Paris",
    "iso:country":"FR",
    "wof:name":"Kervegant",
    "wof:placetype":"locality"
},
  "geometry": {"coordinates":[-3.38878,47.78701],"type":"Point"}
}