{
  "type": "Feature",
  "properties": {
    "gn:admin1_code":"84",
    "gn:admin2_code":"38",
    "gn:admin3_code":"381",
    "gn:admin4_code":"38514.0",
    "gn:asciiname":"Chateau Mea",
    "gn:country_code":"FR",
    "gn:dem":904,
    "gn:feature_class":"P",
    "gn:feature_code":"PPL",
    "gn:name":"Ch\u00e2teau M\u00e9a",
    "gn:population":0,
    "gn:timezone":"Europe/Paris",
    "iso:country":"FR",
    "wof:name":"Chateau Mea",
    "wof:placetype":"locality"
},
  "geometry": {"coordinates":[5.76456,44.74068],"type":"Point"}
}