{
  "type": "Feature",
  "properties": {
    "gn:admin1_code":"84",
    "gn:admin2_code":"03",
    "gn:admin3_code":"031",
    "gn:admin4_code":"03211",
    "gn:asciiname":"Ouches",
    "gn:country_code":"FR",
    "gn:dem":279,
    "gn:feature_class":"P",
    "gn:feature_code":"PPL",
    "gn:name":"Ouches",
    "gn:population":0,
    "gn:timezone":"Europe/Paris",
    "iso:country":"FR",
    "wof:name":"Ouches",
    "wof:placetype":"locality"
},
  "geometry": {"coordinates":[2.55,46.31667],"type":"Point"}
}