{
  "type": "Feature",
  "properties": {
    "gn:admin1_code":"84",
    "gn:admin2_code":"03",
    "gn:admin3_code":"031",
    "gn:admin4_code":"03211",
    "gn:asciiname":"Ouches",
    "gn:country_code":"FR",
    "gn:dem":279,
    "gn:feature_class":"P",
    "gn:feature_code":"PPL",
    "gn:name":"Ouches",
    "gn:population":0,
    "gn:timezone":"Europe/Paris",
    "iso:country":"FR",
    "name:cat_x_preferred":[
        "Ouches"
    ],
    "name:ceb_x_preferred":[
        "Ouches"
    ],
    "name:deu_x_preferred":[
        "Ouches"
    ],
    "name:eus_x_preferred":[
        "Ouches"
    ],
    "name:fra_x_preferred":[
        "Ouches"
    ],
    "name:frp_x_preferred":[
        "Ouches"
    ],
    "name:hun_x_preferred":[
        "Ouches"
    ],
    "name:ita_x_preferred":[
        "Ouches"
    ],
    "name:lat_x_preferred":[
        "Olchii"
    ],
    "name:lmo_x_preferred":[
        "Ouches"
    ],
    "name:mlg_x_preferred":[
        "Ouches"
    ],
    "name:msa_x_preferred":[
        "Ouches"
    ],
    "name:nld_x_preferred":[
        "Ouches"
    ],
    "name:oci_x_preferred":[
        "Ouches"
    ],
    "name:pms_x_preferred":[
        "Ouches"
    ],
    "name:pol_x_preferred":[
        "Ouches"
    ],
    "name:por_x_preferred":[
        "Ouches"
    ],
    "name:ron_x_preferred":[
        "Ouches"
    ],
    "name:slk_x_preferred":[
        "Ouches"
    ],
    "name:spa_x_preferred":[
        "Ouches"
    ],
    "name:swe_x_preferred":[
        "Ouches"
    ],
    "name:uzb_x_preferred":[
        "Ouches"
    ],
    "name:vie_x_preferred":[
        "Ouches"
    ],
    "name:vol_x_preferred":[
        "Ouches"
    ],
    "name:war_x_preferred":[
        "Ouches"
    ],
    "name:zho_x_preferred":[
        "\u4e4c\u8c22"
    ],
    "wof:name":"Ouches",
    "wof:placetype":"locality"
},
  "geometry": {"coordinates":[2.55,46.31667],"type":"Point"}
}