{
  "type": "Feature",
  "properties": {
    "gn:admin1_code":"11",
    "gn:admin2_code":"77",
    "gn:admin3_code":"774",
    "gn:admin4_code":"77458",
    "gn:asciiname":"Fonteneilles",
    "gn:country_code":"FR",
    "gn:dem":101,
    "gn:feature_class":"P",
    "gn:feature_code":"PPL",
    "gn:name":"Fonteneilles",
    "gn:population":0,
    "gn:timezone":"Europe/Paris",
    "iso:country":"FR",
    "wof:name":"Fonteneilles",
    "wof:placetype":"locality"
},
  "geometry": {"coordinates":[2.75456,48.18881],"type":"Point"}
}