{
  "type": "Feature",
  "properties": {
    "iso:country":"FR",
    "name:eng_x_preferred":[
        "Petit Drancy"
    ],
    "name:fra_x_preferred":[
        "Petit Drancy"
    ],
    "name:fra_x_variant":[
        "Le Petit Drancy"
    ],
    "wof:name":"Petit Drancy",
    "wof:placetype":"neighbourhood"
},
  "geometry": {"coordinates":[2.43543222131743,48.91781878391097],"type":"Point"}
}