{
  "type": "Feature",
  "properties": {
    "gn:admin1_code":"24",
    "gn:admin2_code":"28",
    "gn:admin3_code":"282",
    "gn:admin4_code":"28259.0",
    "gn:asciiname":"Dampierre",
    "gn:country_code":"FR",
    "gn:dem":134,
    "gn:feature_class":"P",
    "gn:feature_code":"PPL",
    "gn:name":"Dampierre",
    "gn:population":0,
    "gn:timezone":"Europe/Paris",
    "iso:country":"FR",
    "name:bre_x_preferred":[
        "Dampierre"
    ],
    "name:cat_x_preferred":[
        "Dampierre"
    ],
    "name:ceb_x_preferred":[
        "Dampierre"
    ],
    "name:ces_x_preferred":[
        "Dampierre"
    ],
    "name:deu_x_preferred":[
        "Dampierre"
    ],
    "name:fra_x_preferred":[
        "Dampierre"
    ],
    "name:ind_x_preferred":[
        "Dampierre"
    ],
    "name:ita_x_preferred":[
        "Dampierre"
    ],
    "name:nds_x_preferred":[
        "Dampierre"
    ],
    "name:nld_x_preferred":[
        "Dampierre"
    ],
    "name:oci_x_preferred":[
        "Dampierre"
    ],
    "name:pms_x_preferred":[
        "Dampierre"
    ],
    "name:pol_x_preferred":[
        "Dampierre"
    ],
    "name:por_x_preferred":[
        "Dampierre"
    ],
    "name:rus_x_preferred":[
        "\u0414\u0430\u043c\u043f\u044c\u0435\u0440"
    ],
    "name:slk_x_preferred":[
        "Dampierre"
    ],
    "name:spa_x_preferred":[
        "Dampierre"
    ],
    "name:srp_x_preferred":[
        "\u0414\u0430\u043c\u043f\u0458\u0435\u0440"
    ],
    "name:swe_x_preferred":[
        "Dampierre"
    ],
    "name:ukr_x_preferred":[
        "\u0414\u0430\u043c\u043f'\u0454\u0440\u0440"
    ],
    "wof:name":"Dampierre",
    "wof:placetype":"locality"
},
  "geometry": {"coordinates":[1.42891,48.24326],"type":"Point"}
}