{
  "type": "Feature",
  "properties": {
    "gn:admin1_code":"75",
    "gn:admin2_code":"47",
    "gn:admin3_code":"473",
    "gn:admin4_code":"47106",
    "gn:asciiname":"Condat",
    "gn:country_code":"FR",
    "gn:dem":70,
    "gn:feature_class":"P",
    "gn:feature_code":"PPL",
    "gn:name":"Condat",
    "gn:population":0,
    "gn:timezone":"Europe/Paris",
    "iso:country":"FR",
    "wof:name":"Condat",
    "wof:placetype":"locality"
},
  "geometry": {"coordinates":[0.98736,44.49429],"type":"Point"}
}