{
  "type": "Feature",
  "properties": {
    "gn:admin1_code":"32",
    "gn:admin2_code":"62",
    "gn:admin3_code":"627",
    "gn:admin4_code":"62793",
    "gn:asciiname":"Grand Servins",
    "gn:country_code":"FR",
    "gn:dem":161,
    "gn:feature_class":"P",
    "gn:feature_code":"PPL",
    "gn:name":"Grand Servins",
    "gn:population":0,
    "gn:timezone":"Europe/Paris",
    "iso:country":"FR",
    "wof:name":"Grand Servins",
    "wof:placetype":"locality"
},
  "geometry": {"coordinates":[2.63225,50.40693],"type":"Point"}
}