{
  "type": "Feature",
  "properties": {
    "gn:admin1_code":"84",
    "gn:admin2_code":"15",
    "gn:admin3_code":"153",
    "gn:admin4_code":"15127",
    "gn:asciiname":"Tremoulet",
    "gn:country_code":"FR",
    "gn:dem":843,
    "gn:feature_class":"P",
    "gn:feature_code":"PPL",
    "gn:name":"Tr\u00e9moulet",
    "gn:population":0,
    "gn:timezone":"Europe/Paris",
    "iso:country":"FR",
    "wof:name":"Tremoulet",
    "wof:placetype":"locality"
},
  "geometry": {"coordinates":[3.12377,45.24067],"type":"Point"}
}