{
  "type": "Feature",
  "properties": {
    "iso:country":"FR",
    "wof:name":"Montchat",
    "wof:placetype":"neighbourhood"
},
  "geometry": {"coordinates":[4.887312,45.74939],"type":"Point"}
}