{
  "type": "Feature",
  "properties": {
    "iso:country":"FR",
    "wof:name":"\nMontchat",
    "wof:placetype":"neighbourhood"
},
  "geometry": {"coordinates":[4.88731203534488,45.74939042515692],"type":"Point"}
}