{
  "type": "Feature",
  "properties": {
    "gn:admin1_code":"44",
    "gn:admin2_code":"10",
    "gn:admin3_code":"103",
    "gn:admin4_code":"10191",
    "gn:asciiname":"La Valotte",
    "gn:country_code":"FR",
    "gn:dem":102,
    "gn:feature_class":"P",
    "gn:feature_code":"PPL",
    "gn:name":"La Valotte",
    "gn:population":0,
    "gn:timezone":"Europe/Paris",
    "iso:country":"FR",
    "wof:name":"La Valotte",
    "wof:placetype":"locality"
},
  "geometry": {"coordinates":[4.07866,48.33245],"type":"Point"}
}