{
  "type": "Feature",
  "properties": {
    "gn:admin1_code":"11",
    "gn:admin2_code":"77",
    "gn:admin3_code":"774",
    "gn:admin4_code":"77011",
    "gn:asciiname":"Morville",
    "gn:country_code":"FR",
    "gn:dem":111,
    "gn:feature_class":"P",
    "gn:feature_code":"PPL",
    "gn:name":"Morville",
    "gn:population":0,
    "gn:timezone":"Europe/Paris",
    "iso:country":"FR",
    "name:ceb_x_preferred":[
        "Morville"
    ],
    "name:deu_x_preferred":[
        "Morville"
    ],
    "name:fra_x_preferred":[
        "Morville"
    ],
    "name:hun_x_preferred":[
        "Morville"
    ],
    "name:ita_x_preferred":[
        "Morville"
    ],
    "name:nds_x_preferred":[
        "Morville"
    ],
    "name:nld_x_preferred":[
        "Morville"
    ],
    "name:pms_x_preferred":[
        "Morville"
    ],
    "name:pol_x_preferred":[
        "Morville"
    ],
    "name:por_x_preferred":[
        "Morville"
    ],
    "name:rus_x_preferred":[
        "\u041c\u043e\u0440\u0432\u0438\u043b\u044c"
    ],
    "name:slk_x_preferred":[
        "Morville"
    ],
    "name:spa_x_preferred":[
        "Morville"
    ],
    "name:swe_x_preferred":[
        "Morville"
    ],
    "name:ukr_x_preferred":[
        "\u041c\u043e\u0440\u0432\u0456\u043b\u044c"
    ],
    "wof:name":"Morville",
    "wof:placetype":"locality"
},
  "geometry": {"coordinates":[2.61046,48.2033],"type":"Point"}
}