{
  "type": "Feature",
  "properties": {
    "gn:admin1_code":"27",
    "gn:admin2_code":"58",
    "gn:admin3_code":"583",
    "gn:admin4_code":"58057",
    "gn:asciiname":"Mussy",
    "gn:country_code":"FR",
    "gn:dem":209,
    "gn:feature_class":"P",
    "gn:feature_code":"PPL",
    "gn:name":"Mussy",
    "gn:population":0,
    "gn:timezone":"Europe/Paris",
    "iso:country":"FR",
    "wof:name":"Mussy",
    "wof:placetype":"locality"
},
  "geometry": {"coordinates":[3.1721,46.74952],"type":"Point"}
}