{
  "type": "Feature",
  "properties": {
    "gn:admin1_code":"75",
    "gn:admin2_code":"87",
    "gn:admin3_code":"871",
    "gn:admin4_code":"87041",
    "gn:asciiname":"Le Montillon",
    "gn:country_code":"FR",
    "gn:dem":288,
    "gn:feature_class":"P",
    "gn:feature_code":"PPL",
    "gn:name":"Le Montillon",
    "gn:population":0,
    "gn:timezone":"Europe/Paris",
    "iso:country":"FR",
    "wof:name":"Le Montillon",
    "wof:placetype":"locality"
},
  "geometry": {"coordinates":[1.23893,46.11194],"type":"Point"}
}