{
  "type": "Feature",
  "properties": {
    "gn:admin1_code":"53",
    "gn:admin2_code":"35",
    "gn:admin3_code":"352",
    "gn:admin4_code":"35236",
    "gn:asciiname":"Mussain",
    "gn:country_code":"FR",
    "gn:dem":19,
    "gn:feature_class":"P",
    "gn:feature_code":"PPL",
    "gn:name":"Mussain",
    "gn:population":0,
    "gn:timezone":"Europe/Paris",
    "iso:country":"FR",
    "wof:name":"Mussain",
    "wof:placetype":"locality"
},
  "geometry": {"coordinates":[-2.0879,47.67438],"type":"Point"}
}