{
  "type": "Feature",
  "properties": {
    "iso:country":"FR",
    "name:eng_x_preferred":[
        "Gresillons"
    ],
    "name:fra_x_preferred":[
        "Gr\u00e9sillons"
    ],
    "wof:name":"Gresillons",
    "wof:placetype":"neighbourhood"
},
  "geometry": {"coordinates":[2.30550368171269,48.918020701624],"type":"Point"}
}