{
  "type": "Feature",
  "properties": {
    "iso:country":"FR",
    "name:eng_x_preferred":[
        "Front-de-Seine"
    ],
    "name:fra_x_preferred":[
        "Front-de-Seine"
    ],
    "wof:name":"Front-de-Seine",
    "wof:placetype":"neighbourhood"
},
  "geometry": {"coordinates":[2.28308755562685,48.89839342277307],"type":"Point"}
}