{
  "type": "Feature",
  "properties": {
    "gn:admin1_code":"44",
    "gn:admin2_code":"52",
    "gn:admin3_code":"523",
    "gn:admin4_code":"52288",
    "gn:asciiname":"Harmeville",
    "gn:country_code":"FR",
    "gn:dem":320,
    "gn:feature_class":"P",
    "gn:feature_code":"PPL",
    "gn:name":"Harm\u00e9ville",
    "gn:population":0,
    "gn:timezone":"Europe/Paris",
    "iso:country":"FR",
    "name:und_x_variant":[
        "Harm\u00e9ville"
    ],
    "wof:name":"Harmeville",
    "wof:placetype":"locality"
},
  "geometry": {"coordinates":[5.33759,48.44198],"type":"Point"}
}