{
  "type": "Feature",
  "properties": {
    "gn:admin1_code":"28",
    "gn:admin2_code":"27",
    "gn:admin3_code":"273",
    "gn:admin4_code":"27112",
    "gn:asciiname":"Cintray",
    "gn:country_code":"FR",
    "gn:dem":171,
    "gn:feature_class":"P",
    "gn:feature_code":"PPL",
    "gn:name":"Cintray",
    "gn:population":393,
    "gn:timezone":"Europe/Paris",
    "iso:country":"FR",
    "name:ceb_x_preferred":[
        "Cintray"
    ],
    "name:deu_x_preferred":[
        "Cintray"
    ],
    "name:fra_x_preferred":[
        "Cintray"
    ],
    "name:ita_x_preferred":[
        "Cintray"
    ],
    "name:nds_x_preferred":[
        "Cintray"
    ],
    "name:nld_x_preferred":[
        "Cintray"
    ],
    "name:oci_x_preferred":[
        "Cintray"
    ],
    "name:pms_x_preferred":[
        "Cintray"
    ],
    "name:pol_x_preferred":[
        "Cintray"
    ],
    "name:slk_x_preferred":[
        "Cintray"
    ],
    "name:spa_x_preferred":[
        "Cintray"
    ],
    "name:srp_x_preferred":[
        "\u0421\u0438\u043d\u0442\u0440\u0435"
    ],
    "name:swe_x_preferred":[
        "Cintray"
    ],
    "wof:name":"Cintray",
    "wof:placetype":"locality",
    "wof:population":393
},
  "geometry": {"coordinates":[0.89368,48.79483],"type":"Point"}
}