{
  "type": "Feature",
  "properties": {
    "gn:admin1_code":"28",
    "gn:admin2_code":"27",
    "gn:admin3_code":"273",
    "gn:admin4_code":"27112",
    "gn:asciiname":"Cintray",
    "gn:country_code":"FR",
    "gn:dem":171,
    "gn:feature_class":"P",
    "gn:feature_code":"PPL",
    "gn:name":"Cintray",
    "gn:population":393,
    "gn:timezone":"Europe/Paris",
    "iso:country":"FR",
    "wof:name":"Cintray",
    "wof:placetype":"locality",
    "wof:population":393
},
  "geometry": {"coordinates":[0.89368,48.79483],"type":"Point"}
}