{
  "type": "Feature",
  "properties": {
    "gn:admin1_code":"93",
    "gn:admin2_code":"04",
    "gn:admin3_code":"042",
    "gn:admin4_code":"04218",
    "gn:asciiname":"Chateau-Garnier",
    "gn:country_code":"FR",
    "gn:dem":1100,
    "gn:feature_class":"P",
    "gn:feature_code":"PPL",
    "gn:name":"Ch\u00e2teau-Garnier",
    "gn:population":0,
    "gn:timezone":"Europe/Paris",
    "iso:country":"FR",
    "wof:name":"Chateau-Garnier",
    "wof:placetype":"locality"
},
  "geometry": {"coordinates":[6.48039,44.08655],"type":"Point"}
}