{
  "type": "Feature",
  "properties": {
    "gn:admin1_code":"75",
    "gn:admin2_code":"40",
    "gn:admin3_code":"402",
    "gn:admin4_code":"40171",
    "gn:asciiname":"Mano",
    "gn:country_code":"FR",
    "gn:dem":63,
    "gn:feature_class":"P",
    "gn:feature_code":"PPL",
    "gn:name":"Mano",
    "gn:population":0,
    "gn:timezone":"Europe/Paris",
    "iso:country":"FR",
    "name:ceb_x_preferred":[
        "Mano"
    ],
    "name:deu_x_preferred":[
        "Mano"
    ],
    "name:fra_x_preferred":[
        "Mano"
    ],
    "name:ita_x_preferred":[
        "Mano"
    ],
    "name:nld_x_preferred":[
        "Mano"
    ],
    "name:pol_x_preferred":[
        "Mano"
    ],
    "name:rus_x_preferred":[
        "\u041c\u0430\u043d\u043e"
    ],
    "name:spa_x_preferred":[
        "Mano"
    ],
    "name:swe_x_preferred":[
        "Mano"
    ],
    "name:tur_x_preferred":[
        "Mano"
    ],
    "wof:name":"Mano",
    "wof:placetype":"locality"
},
  "geometry": {"coordinates":[-0.66667,44.41667],"type":"Point"}
}