{
  "type": "Feature",
  "properties": {
    "frgov:code_epci":"200069656",
    "frgov:insee_arr":"2",
    "frgov:insee_com":"40171",
    "frgov:insee_dep":"40",
    "frgov:insee_reg":"75",
    "frgov:nom_com":"Mano",
    "frgov:nom_com_m":"MANO",
    "frgov:nom_dep":"LANDES",
    "frgov:nom_reg":"NOUVELLE-AQUITAINE",
    "frgov:statut":"Commune simple",
    "gn:admin1_code":"75",
    "gn:admin2_code":"40",
    "gn:admin3_code":"402",
    "gn:admin4_code":"40171",
    "gn:asciiname":"Mano",
    "gn:country_code":"FR",
    "gn:dem":63,
    "gn:feature_class":"P",
    "gn:feature_code":"PPL",
    "gn:name":"Mano",
    "gn:population":0,
    "gn:timezone":"Europe/Paris",
    "iso:country":"FR",
    "name:ceb_x_preferred":[
        "Mano"
    ],
    "name:deu_x_preferred":[
        "Mano"
    ],
    "name:fra_x_preferred":[
        "Mano"
    ],
    "name:ita_x_preferred":[
        "Mano"
    ],
    "name:nld_x_preferred":[
        "Mano"
    ],
    "name:pol_x_preferred":[
        "Mano"
    ],
    "name:rus_x_preferred":[
        "\u041c\u0430\u043d\u043e"
    ],
    "name:spa_x_preferred":[
        "Mano"
    ],
    "name:swe_x_preferred":[
        "Mano"
    ],
    "name:tur_x_preferred":[
        "Mano"
    ],
    "qs:a0":"France",
    "qs:a1":"LANDES",
    "qs:a1_lc":"40",
    "qs:a1r":"AQUITAINE",
    "qs:a1r_lc":"72",
    "qs:a2_lc":"17",
    "qs:a2r_lc":"2",
    "qs:adm0":"France",
    "qs:adm0_a3":"FRA",
    "qs:la":"MANO",
    "qs:la_lc":"40171",
    "qs:level":"localadmin",
    "qs:type":"Commune simple",
    "wof:coterminous":[
        404404421
    ],
    "wof:name":"Mano",
    "wof:placetype":"locality",
    "wof:placetype_local":"Commune simple"
},
  "geometry": {"coordinates":[-0.66667,44.41667],"type":"Point"}
}