{
  "type": "Feature",
  "properties": {
    "gn:admin1_code":"75",
    "gn:admin2_code":"86",
    "gn:admin3_code":"861",
    "gn:admin4_code":"86245",
    "gn:asciiname":"Saint-Sauveur",
    "gn:country_code":"FR",
    "gn:dem":103,
    "gn:feature_class":"P",
    "gn:feature_code":"PPL",
    "gn:name":"Saint-Sauveur",
    "gn:population":1019,
    "gn:timezone":"Europe/Paris",
    "iso:country":"FR",
    "name:cat_x_preferred":[
        "Saint-Sauveur"
    ],
    "name:ceb_x_preferred":[
        "Saint-Sauveur"
    ],
    "name:deu_x_preferred":[
        "Saint-Sauveur"
    ],
    "name:fra_x_preferred":[
        "Saint-Sauveur"
    ],
    "name:ita_x_preferred":[
        "Saint-Sauveur"
    ],
    "name:jpn_x_preferred":[
        "\u30b5\u30f3\u30fb\u30bd\u30f4\u30fc\u30eb"
    ],
    "name:nds_x_preferred":[
        "Saint-Sauveur"
    ],
    "name:nld_x_preferred":[
        "Saint-Sauveur"
    ],
    "name:oci_x_preferred":[
        "Saint-Sauveur"
    ],
    "name:pms_x_preferred":[
        "Saint-Sauveur"
    ],
    "name:pol_x_preferred":[
        "Saint-Sauveur"
    ],
    "name:por_x_preferred":[
        "Saint-Sauveur"
    ],
    "name:rus_x_preferred":[
        "\u0421\u0435\u043d-\u0421\u043e\u0432\u0451\u0440"
    ],
    "name:slk_x_preferred":[
        "Saint-Sauveur"
    ],
    "name:spa_x_preferred":[
        "Saint-Sauveur"
    ],
    "name:swe_x_preferred":[
        "Saint-Sauveur"
    ],
    "name:ukr_x_preferred":[
        "\u0421\u0435\u043d-\u0421\u043e\u0432\u0435\u0440"
    ],
    "wof:name":"Saint-Sauveur",
    "wof:placetype":"locality",
    "wof:population":1019
},
  "geometry": {"coordinates":[0.62277,46.80841],"type":"Point"}
}