{
  "type": "Feature",
  "properties": {
    "gn:admin1_code":"93",
    "gn:admin2_code":"83",
    "gn:admin3_code":"831",
    "gn:admin4_code":"83061",
    "gn:asciiname":"Frejus-Plage",
    "gn:country_code":"FR",
    "gn:dem":-9999,
    "gn:feature_class":"P",
    "gn:feature_code":"PPL",
    "gn:name":"Fr\u00e9jus-Plage",
    "gn:population":0,
    "gn:timezone":"Europe/Paris",
    "iso:country":"FR",
    "wof:name":"Frejus-Plage",
    "wof:placetype":"locality"
},
  "geometry": {"coordinates":[6.74506,43.41872],"type":"Point"}
}