{
  "type": "Feature",
  "properties": {
    "gn:admin1_code":"44",
    "gn:admin2_code":"51",
    "gn:admin3_code":"514",
    "gn:admin4_code":"51463",
    "gn:asciiname":"Henruel",
    "gn:country_code":"FR",
    "gn:dem":118,
    "gn:feature_class":"P",
    "gn:feature_code":"PPL",
    "gn:name":"Henruel",
    "gn:population":0,
    "gn:timezone":"Europe/Paris",
    "iso:country":"FR",
    "wof:name":"Henruel",
    "wof:placetype":"locality"
},
  "geometry": {"coordinates":[4.55992,48.64672],"type":"Point"}
}