{
  "type": "Feature",
  "properties": {
    "gn:admin1_code":"27",
    "gn:admin2_code":"89",
    "gn:admin3_code":"893",
    "gn:admin4_code":"89443",
    "gn:asciiname":"Val Peronne",
    "gn:country_code":"FR",
    "gn:dem":152,
    "gn:feature_class":"P",
    "gn:feature_code":"PPL",
    "gn:name":"Val P\u00e9ronne",
    "gn:population":0,
    "gn:timezone":"Europe/Paris",
    "iso:country":"FR",
    "wof:name":"Val Peronne",
    "wof:placetype":"locality"
},
  "geometry": {"coordinates":[3.34857,48.13355],"type":"Point"}
}