{
  "type": "Feature",
  "properties": {
    "gn:admin1_code":"84",
    "gn:admin2_code":"42",
    "gn:admin3_code":"421",
    "gn:admin4_code":"42266",
    "gn:asciiname":"Geneviecq",
    "gn:country_code":"FR",
    "gn:dem":670,
    "gn:feature_class":"P",
    "gn:feature_code":"PPL",
    "gn:name":"Geneviecq",
    "gn:population":0,
    "gn:timezone":"Europe/Paris",
    "iso:country":"FR",
    "wof:name":"Geneviecq",
    "wof:placetype":"locality"
},
  "geometry": {"coordinates":[4.10543,45.40865],"type":"Point"}
}