{
  "type": "Feature",
  "properties": {
    "gn:admin1_code":"75",
    "gn:admin2_code":"47",
    "gn:admin3_code":"473",
    "gn:admin4_code":"47311",
    "gn:asciiname":"Maures",
    "gn:country_code":"FR",
    "gn:dem":176,
    "gn:feature_class":"P",
    "gn:feature_code":"PPL",
    "gn:name":"Maur\u00e8s",
    "gn:population":0,
    "gn:timezone":"Europe/Paris",
    "iso:country":"FR",
    "wof:name":"Maures",
    "wof:placetype":"locality"
},
  "geometry": {"coordinates":[0.80398,44.69009000000001],"type":"Point"}
}