{
  "type": "Feature",
  "properties": {
    "gn:admin1_code":"24",
    "gn:admin2_code":"36",
    "gn:admin3_code":"363",
    "gn:admin4_code":"36060",
    "gn:asciiname":"Les Bergeres",
    "gn:country_code":"FR",
    "gn:dem":408,
    "gn:feature_class":"P",
    "gn:feature_code":"PPL",
    "gn:name":"Les Berg\u00e8res",
    "gn:population":0,
    "gn:timezone":"Europe/Paris",
    "iso:country":"FR",
    "wof:name":"Les Bergeres",
    "wof:placetype":"locality"
},
  "geometry": {"coordinates":[1.96115,46.45933],"type":"Point"}
}