{
  "type": "Feature",
  "properties": {
    "gn:admin1_code":"24",
    "gn:admin2_code":"41",
    "gn:admin3_code":"413",
    "gn:admin4_code":"41241",
    "gn:asciiname":"La Bediniere",
    "gn:country_code":"FR",
    "gn:dem":110,
    "gn:feature_class":"P",
    "gn:feature_code":"PPL",
    "gn:name":"La B\u00e9dini\u00e8re",
    "gn:population":0,
    "gn:timezone":"Europe/Paris",
    "iso:country":"FR",
    "wof:name":"La Bediniere",
    "wof:placetype":"locality"
},
  "geometry": {"coordinates":[1.92712,47.3581],"type":"Point"}
}