{
  "type": "Feature",
  "properties": {
    "gn:admin1_code":"75",
    "gn:admin2_code":"24",
    "gn:admin3_code":"243",
    "gn:admin4_code":"24055",
    "gn:asciiname":"La Bertinie",
    "gn:country_code":"FR",
    "gn:dem":141,
    "gn:feature_class":"P",
    "gn:feature_code":"PPL",
    "gn:name":"La Bertinie",
    "gn:population":0,
    "gn:timezone":"Europe/Paris",
    "iso:country":"FR",
    "wof:name":"La Bertinie",
    "wof:placetype":"locality"
},
  "geometry": {"coordinates":[0.58039,45.28746],"type":"Point"}
}