{
  "type": "Feature",
  "properties": {
    "gn:admin1_code":"27",
    "gn:admin2_code":"39",
    "gn:admin3_code":"391",
    "gn:admin4_code":"39464",
    "gn:asciiname":"Romain",
    "gn:country_code":"FR",
    "gn:dem":283,
    "gn:feature_class":"P",
    "gn:feature_code":"PPL",
    "gn:name":"Romain",
    "gn:population":143,
    "gn:timezone":"Europe/Paris",
    "iso:country":"FR",
    "name:ceb_x_preferred":[
        "Romain"
    ],
    "name:deu_x_preferred":[
        "Romain"
    ],
    "name:fra_x_preferred":[
        "Romain"
    ],
    "name:ita_x_preferred":[
        "Romain"
    ],
    "name:nds_x_preferred":[
        "Romain"
    ],
    "name:nld_x_preferred":[
        "Romain"
    ],
    "name:oci_x_preferred":[
        "Romain"
    ],
    "name:pms_x_preferred":[
        "Romain"
    ],
    "name:pol_x_preferred":[
        "Romain"
    ],
    "name:por_x_preferred":[
        "Romain"
    ],
    "name:rus_x_preferred":[
        "\u0420\u043e\u043c\u0435\u043d"
    ],
    "name:slk_x_preferred":[
        "Romain"
    ],
    "name:spa_x_preferred":[
        "Romain"
    ],
    "name:swe_x_preferred":[
        "Romain"
    ],
    "name:ukr_x_preferred":[
        "\u0420\u043e\u043c\u0435\u043d"
    ],
    "wof:name":"Romain",
    "wof:placetype":"locality",
    "wof:population":143
},
  "geometry": {"coordinates":[5.72022,47.21324],"type":"Point"}
}