{
  "type": "Feature",
  "properties": {
    "gn:admin1_code":"27",
    "gn:admin2_code":"39",
    "gn:admin3_code":"391",
    "gn:admin4_code":"39464",
    "gn:asciiname":"Romain",
    "gn:country_code":"FR",
    "gn:dem":283,
    "gn:feature_class":"P",
    "gn:feature_code":"PPL",
    "gn:name":"Romain",
    "gn:population":143,
    "gn:timezone":"Europe/Paris",
    "iso:country":"FR",
    "wof:name":"Romain",
    "wof:placetype":"locality",
    "wof:population":143
},
  "geometry": {"coordinates":[5.72022,47.21324],"type":"Point"}
}