{
  "type": "Feature",
  "properties": {
    "frgov:code_epci":"243900560",
    "frgov:insee_arr":"1",
    "frgov:insee_com":"39464",
    "frgov:insee_dep":"39",
    "frgov:insee_reg":"27",
    "frgov:nom_com":"Romain",
    "frgov:nom_com_m":"ROMAIN",
    "frgov:nom_dep":"JURA",
    "frgov:nom_reg":"BOURGOGNE-FRANCHE-COMTE",
    "frgov:statut":"Commune simple",
    "gn:admin1_code":"27",
    "gn:admin2_code":"39",
    "gn:admin3_code":"391",
    "gn:admin4_code":"39464",
    "gn:asciiname":"Romain",
    "gn:country_code":"FR",
    "gn:dem":283,
    "gn:feature_class":"P",
    "gn:feature_code":"PPL",
    "gn:name":"Romain",
    "gn:population":143,
    "gn:timezone":"Europe/Paris",
    "iso:country":"FR",
    "name:ceb_x_preferred":[
        "Romain"
    ],
    "name:deu_x_preferred":[
        "Romain"
    ],
    "name:fra_x_preferred":[
        "Romain"
    ],
    "name:ita_x_preferred":[
        "Romain"
    ],
    "name:nds_x_preferred":[
        "Romain"
    ],
    "name:nld_x_preferred":[
        "Romain"
    ],
    "name:oci_x_preferred":[
        "Romain"
    ],
    "name:pms_x_preferred":[
        "Romain"
    ],
    "name:pol_x_preferred":[
        "Romain"
    ],
    "name:por_x_preferred":[
        "Romain"
    ],
    "name:rus_x_preferred":[
        "\u0420\u043e\u043c\u0435\u043d"
    ],
    "name:slk_x_preferred":[
        "Romain"
    ],
    "name:spa_x_preferred":[
        "Romain"
    ],
    "name:swe_x_preferred":[
        "Romain"
    ],
    "name:ukr_x_preferred":[
        "\u0420\u043e\u043c\u0435\u043d"
    ],
    "qs:a0":"France",
    "qs:a1":"JURA",
    "qs:a1_lc":"39",
    "qs:a1r":"FRANCHE-COMTE",
    "qs:a1r_lc":"43",
    "qs:a2_lc":"14",
    "qs:a2r_lc":"1",
    "qs:adm0":"France",
    "qs:adm0_a3":"FRA",
    "qs:la":"ROMAIN",
    "qs:la_lc":"39464",
    "qs:level":"localadmin",
    "qs:type":"Commune simple",
    "wof:coterminous":[
        404376539
    ],
    "wof:name":"Romain",
    "wof:placetype":"locality",
    "wof:placetype_local":"Commune simple",
    "wof:population":143
},
  "geometry": {"coordinates":[5.72022,47.21324],"type":"Point"}
}