{
  "type": "Feature",
  "properties": {
    "gn:admin1_code":"32",
    "gn:admin2_code":"80",
    "gn:admin3_code":"801",
    "gn:admin4_code":"80444",
    "gn:asciiname":"Limercourt",
    "gn:country_code":"FR",
    "gn:dem":55,
    "gn:feature_class":"P",
    "gn:feature_code":"PPL",
    "gn:name":"Limercourt",
    "gn:population":0,
    "gn:timezone":"Europe/Paris",
    "iso:country":"FR",
    "wof:name":"Limercourt",
    "wof:placetype":"locality"
},
  "geometry": {"coordinates":[1.7934,50.04104],"type":"Point"}
}