{
  "type": "Feature",
  "properties": {
    "iso:country":"FR",
    "name:fra_x_preferred":[
        "Magnan"
    ],
    "name:unk_x_variant":[
        "Magnan"
    ],
    "qs:gn_adm0_cc":"FR",
    "qs:gn_local":2990440,
    "qs:gn_nam_loc":"Nice, Nice, Alpes-Maritimes, Provence-Alpes-C\u00f4te d'Azur, FR",
    "qs:gn_namadm1":"B8",
    "qs:local_max":21708,
    "qs:local_sum":39512,
    "qs:localhoods":6,
    "qs:name":"Magnan",
    "qs:name_adm0":"France",
    "qs:name_adm1":"Provence-Alpes-C\u00f4te d'Azur",
    "qs:name_adm2":"Alpes-Maritimes",
    "qs:name_lau":"Nice",
    "qs:name_local":"Nice",
    "qs:photo_max":6194,
    "qs:photo_sum":21708,
    "qs:placetype":"Suburb",
    "qs:quad_count":74,
    "qs:woe_adm0":23424819,
    "qs:woe_adm1":7153328,
    "qs:woe_adm2":12591800,
    "qs:woe_lau":22755881,
    "qs:woe_local":614274,
    "qs:woe_ver":"7.10.0",
    "wd:wordcount":23,
    "wof:lang":[
        "fre"
    ],
    "wof:name":"Magnan",
    "wof:placetype":"neighbourhood"
},
  "geometry": {"coordinates":[7.266032,43.69548],"type":"Point"}
}