{
  "type": "Feature",
  "properties": {
    "gn:admin1_code":"75",
    "gn:admin2_code":"23",
    "gn:admin3_code":"232",
    "gn:admin4_code":"23240",
    "gn:asciiname":"La Roche",
    "gn:country_code":"FR",
    "gn:dem":452,
    "gn:feature_class":"P",
    "gn:feature_code":"PPL",
    "gn:name":"La Roche",
    "gn:population":0,
    "gn:timezone":"Europe/Paris",
    "iso:country":"FR",
    "wof:name":"La Roche",
    "wof:placetype":"locality"
},
  "geometry": {"coordinates":[2.20585,46.3237],"type":"Point"}
}