{
  "type": "Feature",
  "properties": {
    "gn:admin1_code":"76",
    "gn:admin2_code":"30",
    "gn:admin3_code":"302",
    "gn:admin4_code":"30182",
    "gn:asciiname":"Montpezat",
    "gn:country_code":"FR",
    "gn:dem":149,
    "gn:feature_class":"P",
    "gn:feature_code":"PPL",
    "gn:name":"Montpezat",
    "gn:population":999,
    "gn:timezone":"Europe/Paris",
    "iso:country":"FR",
    "wof:name":"Montpezat",
    "wof:placetype":"locality",
    "wof:population":999
},
  "geometry": {"coordinates":[4.1583,43.85106],"type":"Point"}
}