{
  "type": "Feature",
  "properties": {
    "gn:admin1_code":"84",
    "gn:admin2_code":"03",
    "gn:admin3_code":"032",
    "gn:admin4_code":"03099",
    "gn:asciiname":"Monteaux",
    "gn:country_code":"FR",
    "gn:dem":440,
    "gn:feature_class":"P",
    "gn:feature_code":"PPL",
    "gn:name":"Monteaux",
    "gn:population":0,
    "gn:timezone":"Europe/Paris",
    "iso:country":"FR",
    "name:cat_x_preferred":[
        "Monteaux"
    ],
    "name:ceb_x_preferred":[
        "Monteaux"
    ],
    "name:deu_x_preferred":[
        "Monteaux"
    ],
    "name:eus_x_preferred":[
        "Monteaux"
    ],
    "name:fra_x_preferred":[
        "Monteaux"
    ],
    "name:hun_x_preferred":[
        "Monteaux"
    ],
    "name:ita_x_preferred":[
        "Monteaux"
    ],
    "name:lat_x_preferred":[
        "Monteaux"
    ],
    "name:mlg_x_preferred":[
        "Monteaux"
    ],
    "name:msa_x_preferred":[
        "Monteaux"
    ],
    "name:nld_x_preferred":[
        "Monteaux"
    ],
    "name:oci_x_preferred":[
        "Monteaux"
    ],
    "name:pms_x_preferred":[
        "Monteaux"
    ],
    "name:pol_x_preferred":[
        "Monteaux"
    ],
    "name:por_x_preferred":[
        "Monteaux"
    ],
    "name:ron_x_preferred":[
        "Monteaux"
    ],
    "name:slk_x_preferred":[
        "Monteaux"
    ],
    "name:spa_x_preferred":[
        "Monteaux"
    ],
    "name:swe_x_preferred":[
        "Monteaux"
    ],
    "name:ukr_x_preferred":[
        "\u041c\u043e\u043d\u0442\u043e"
    ],
    "name:uzb_x_preferred":[
        "Monteaux"
    ],
    "name:vie_x_preferred":[
        "Monteaux"
    ],
    "name:vol_x_preferred":[
        "Monteaux"
    ],
    "name:war_x_preferred":[
        "Monteaux"
    ],
    "name:zho_x_preferred":[
        "\u8499\u6258"
    ],
    "wof:name":"Monteaux",
    "wof:placetype":"locality"
},
  "geometry": {"coordinates":[3.05458,46.35934],"type":"Point"}
}