{
  "type": "Feature",
  "properties": {
    "gn:admin1_code":"84",
    "gn:admin2_code":"63",
    "gn:admin3_code":"631",
    "gn:admin4_code":"63158",
    "gn:asciiname":"Ardennes",
    "gn:country_code":"FR",
    "gn:dem":1048,
    "gn:feature_class":"P",
    "gn:feature_code":"PPL",
    "gn:name":"Ardennes",
    "gn:population":0,
    "gn:timezone":"Europe/Paris",
    "iso:country":"FR",
    "wof:name":"Ardennes",
    "wof:placetype":"locality"
},
  "geometry": {"coordinates":[3.53642,45.43678],"type":"Point"}
}