{
  "type": "Feature",
  "properties": {
    "gn:admin1_code":"52",
    "gn:admin2_code":"85",
    "gn:admin3_code":"852",
    "gn:admin4_code":"85051",
    "gn:asciiname":"Saint-Philbert-du-Pont-Charrault",
    "gn:country_code":"FR",
    "gn:dem":84,
    "gn:feature_class":"P",
    "gn:feature_code":"PPL",
    "gn:name":"Saint-Philbert-du-Pont-Charrault",
    "gn:population":0,
    "gn:timezone":"Europe/Paris",
    "iso:country":"FR",
    "name:und_x_variant":[
        "Saint-Philbert",
        "Saint-Philbert-du-Pont-Charrault"
    ],
    "wof:name":"Saint-Philbert-du-Pont-Charrault",
    "wof:placetype":"locality"
},
  "geometry": {"coordinates":[-0.99165,46.65666],"type":"Point"}
}