{
  "type": "Feature",
  "properties": {
    "gn:admin1_code":"27",
    "gn:admin2_code":"89",
    "gn:admin3_code":"891",
    "gn:admin4_code":"89405",
    "gn:asciiname":"Aubigny",
    "gn:country_code":"FR",
    "gn:dem":262,
    "gn:feature_class":"P",
    "gn:feature_code":"PPL",
    "gn:name":"Aubigny",
    "gn:population":0,
    "gn:timezone":"Europe/Paris",
    "iso:country":"FR",
    "wof:name":"Aubigny",
    "wof:placetype":"locality"
},
  "geometry": {"coordinates":[3.42465,47.5981],"type":"Point"}
}