{
  "type": "Feature",
  "properties": {
    "gn:admin1_code":"27",
    "gn:admin2_code":"89",
    "gn:admin3_code":"891",
    "gn:admin4_code":"89405",
    "gn:asciiname":"Aubigny",
    "gn:country_code":"FR",
    "gn:dem":262,
    "gn:feature_class":"P",
    "gn:feature_code":"PPL",
    "gn:name":"Aubigny",
    "gn:population":0,
    "gn:timezone":"Europe/Paris",
    "iso:country":"FR",
    "name:bre_x_preferred":[
        "Aubigny"
    ],
    "name:cat_x_preferred":[
        "Aubigny"
    ],
    "name:ceb_x_preferred":[
        "Aubigny"
    ],
    "name:deu_x_preferred":[
        "Aubigny"
    ],
    "name:epo_x_preferred":[
        "Aubigny"
    ],
    "name:fra_x_preferred":[
        "Aubigny"
    ],
    "name:ind_x_preferred":[
        "Aubigny"
    ],
    "name:ita_x_preferred":[
        "Aubigny"
    ],
    "name:jpn_x_preferred":[
        "\u30aa\u30fc\u30d3\u30cb\u30fc"
    ],
    "name:ltz_x_preferred":[
        "Aubigny"
    ],
    "name:nds_x_preferred":[
        "Aubigny"
    ],
    "name:nld_x_preferred":[
        "Aubigny"
    ],
    "name:oci_x_preferred":[
        "Aubigny"
    ],
    "name:pms_x_preferred":[
        "Aubigny"
    ],
    "name:pol_x_preferred":[
        "Aubigny"
    ],
    "name:por_x_preferred":[
        "Aubigny"
    ],
    "name:ron_x_preferred":[
        "Aubigny"
    ],
    "name:rus_x_preferred":[
        "\u041e\u0431\u0438\u043d\u044c\u0438"
    ],
    "name:slk_x_preferred":[
        "Aubigny"
    ],
    "name:spa_x_preferred":[
        "Aubigny"
    ],
    "name:swe_x_preferred":[
        "Aubigny"
    ],
    "name:szl_x_preferred":[
        "Aubigny"
    ],
    "name:ukr_x_preferred":[
        "\u041e\u0431\u0456\u043d\u044c\u0457"
    ],
    "wof:name":"Aubigny",
    "wof:placetype":"locality"
},
  "geometry": {"coordinates":[3.42465,47.5981],"type":"Point"}
}