{
  "type": "Feature",
  "properties": {
    "gn:admin1_code":"75",
    "gn:admin2_code":"24",
    "gn:admin3_code":"242",
    "gn:admin4_code":"24398",
    "gn:asciiname":"La Caujonnet",
    "gn:country_code":"FR",
    "gn:dem":288,
    "gn:feature_class":"P",
    "gn:feature_code":"PPL",
    "gn:name":"La Caujonnet",
    "gn:population":0,
    "gn:timezone":"Europe/Paris",
    "iso:country":"FR",
    "name:und_x_variant":[
        "Les Coujammers",
        "Lacoujammet",
        "Lacaujamet",
        "La Caujonnet"
    ],
    "wof:name":"La Caujonnet",
    "wof:placetype":"locality"
},
  "geometry": {"coordinates":[0.67181,45.62978],"type":"Point"}
}