{
  "type": "Feature",
  "properties": {
    "gn:admin1_code":"75",
    "gn:admin2_code":"19",
    "gn:admin3_code":"193",
    "gn:admin4_code":"19252",
    "gn:asciiname":"Sauliac",
    "gn:country_code":"FR",
    "gn:dem":643,
    "gn:feature_class":"P",
    "gn:feature_code":"PPL",
    "gn:name":"Sauliac",
    "gn:population":0,
    "gn:timezone":"Europe/Paris",
    "iso:country":"FR",
    "wof:name":"Sauliac",
    "wof:placetype":"locality"
},
  "geometry": {"coordinates":[2.47184,45.42457],"type":"Point"}
}