{
  "type": "Feature",
  "properties": {
    "gn:admin1_code":"44",
    "gn:admin2_code":"51",
    "gn:admin3_code":"514",
    "gn:admin4_code":"51567",
    "gn:asciiname":"Faremont",
    "gn:country_code":"FR",
    "gn:dem":121,
    "gn:feature_class":"P",
    "gn:feature_code":"PPL",
    "gn:name":"Far\u00e9mont",
    "gn:population":0,
    "gn:timezone":"Europe/Paris",
    "iso:country":"FR",
    "wof:name":"Faremont",
    "wof:placetype":"locality"
},
  "geometry": {"coordinates":[4.72237,48.68982000000001],"type":"Point"}
}