{
  "type": "Feature",
  "properties": {
    "gn:admin1_code":"75",
    "gn:admin2_code":"87",
    "gn:admin3_code":"872",
    "gn:admin4_code":"87088",
    "gn:asciiname":"Rouffignac",
    "gn:country_code":"FR",
    "gn:dem":424,
    "gn:feature_class":"P",
    "gn:feature_code":"PPL",
    "gn:name":"Rouffignac",
    "gn:population":0,
    "gn:timezone":"Europe/Paris",
    "iso:country":"FR",
    "name:cat_x_preferred":[
        "Rouffignac"
    ],
    "name:ceb_x_preferred":[
        "Rouffignac"
    ],
    "name:deu_x_preferred":[
        "Rouffignac"
    ],
    "name:epo_x_preferred":[
        "Rouffignac"
    ],
    "name:eus_x_preferred":[
        "Rouffignac"
    ],
    "name:fra_x_preferred":[
        "Rouffignac"
    ],
    "name:hun_x_preferred":[
        "Rouffignac"
    ],
    "name:hye_x_preferred":[
        "\u054c\u0578\u0582\u0586\u056b\u0576\u0575\u0561\u056f"
    ],
    "name:ita_x_preferred":[
        "Rouffignac"
    ],
    "name:lat_x_preferred":[
        "Rouffignac"
    ],
    "name:mlg_x_preferred":[
        "Rouffignac"
    ],
    "name:msa_x_preferred":[
        "Rouffignac"
    ],
    "name:nld_x_preferred":[
        "Rouffignac"
    ],
    "name:oci_x_preferred":[
        "Rouffignac"
    ],
    "name:pms_x_preferred":[
        "Rouffignac"
    ],
    "name:pol_x_preferred":[
        "Rouffignac"
    ],
    "name:por_x_preferred":[
        "Rouffignac"
    ],
    "name:ron_x_preferred":[
        "Rouffignac"
    ],
    "name:rus_x_preferred":[
        "\u0420\u0443\u0444\u0444\u0438\u043d\u044c\u044f\u043a"
    ],
    "name:slk_x_preferred":[
        "Rouffignac"
    ],
    "name:spa_x_preferred":[
        "Rouffignac"
    ],
    "name:swe_x_preferred":[
        "Rouffignac"
    ],
    "name:ukr_x_preferred":[
        "\u0420\u0443\u0444\u0444\u0456\u043d\u044c\u044f\u043a"
    ],
    "name:vie_x_preferred":[
        "Rouffignac"
    ],
    "name:vol_x_preferred":[
        "Rouffignac"
    ],
    "name:war_x_preferred":[
        "Rouffignac"
    ],
    "name:zho_x_preferred":[
        "\u9c81\u83f2\u5c3c\u4e9a\u514b"
    ],
    "wof:name":"Rouffignac",
    "wof:placetype":"locality"
},
  "geometry": {"coordinates":[1.43177,45.59275],"type":"Point"}
}