{
  "type": "Feature",
  "properties": {
    "iso:country":"FR",
    "name:eng_x_preferred":[
        "Les Bas-Heurts"
    ],
    "name:fra_x_preferred":[
        "Les Bas-Heurts"
    ],
    "wof:name":"Les Bas-Heurts",
    "wof:placetype":"neighbourhood"
},
  "geometry": {"coordinates":[2.5394781341897,48.84332476780781],"type":"Point"}
}