{
  "type": "Feature",
  "properties": {
    "gn:admin1_code":"44",
    "gn:admin2_code":"51",
    "gn:admin3_code":"512",
    "gn:admin4_code":"51116",
    "gn:asciiname":"Champguyon-Bas",
    "gn:country_code":"FR",
    "gn:dem":180,
    "gn:feature_class":"P",
    "gn:feature_code":"PPL",
    "gn:name":"Champguyon-Bas",
    "gn:population":0,
    "gn:timezone":"Europe/Paris",
    "iso:country":"FR",
    "wof:name":"Champguyon-Bas",
    "wof:placetype":"locality"
},
  "geometry": {"coordinates":[3.55,48.76667],"type":"Point"}
}