{
  "type": "Feature",
  "properties": {
    "gn:admin1_code":"52",
    "gn:admin2_code":"85",
    "gn:admin3_code":"852",
    "gn:admin4_code":"85036",
    "gn:asciiname":"La Claye",
    "gn:country_code":"FR",
    "gn:dem":10,
    "gn:feature_class":"P",
    "gn:feature_code":"PPL",
    "gn:name":"La Claye",
    "gn:population":0,
    "gn:timezone":"Europe/Paris",
    "iso:country":"FR",
    "wof:name":"La Claye",
    "wof:placetype":"locality"
},
  "geometry": {"coordinates":[-1.28439,46.47834],"type":"Point"}
}