{
  "type": "Feature",
  "properties": {
    "gn:admin1_code":"27",
    "gn:admin2_code":"58",
    "gn:admin3_code":"583",
    "gn:admin4_code":"58151",
    "gn:asciiname":"Les Fromajots",
    "gn:country_code":"FR",
    "gn:dem":262,
    "gn:feature_class":"P",
    "gn:feature_code":"PPL",
    "gn:name":"Les Fromajots",
    "gn:population":0,
    "gn:timezone":"Europe/Paris",
    "iso:country":"FR",
    "name:und_x_variant":[
        "Les Fromageots",
        "Les Fromajots"
    ],
    "wof:name":"Les Fromajots",
    "wof:placetype":"locality"
},
  "geometry": {"coordinates":[3.46292,46.91033],"type":"Point"}
}