{
  "type": "Feature",
  "properties": {
    "gn:admin1_code":"84",
    "gn:admin2_code":"38",
    "gn:admin3_code":"381",
    "gn:admin4_code":"38547",
    "gn:asciiname":"Brignoud",
    "gn:country_code":"FR",
    "gn:dem":243,
    "gn:feature_class":"P",
    "gn:feature_code":"PPL",
    "gn:name":"Brignoud",
    "gn:population":0,
    "gn:timezone":"Europe/Paris",
    "iso:country":"FR",
    "wof:name":"Brignoud",
    "wof:placetype":"locality"
},
  "geometry": {"coordinates":[5.90841,45.25821],"type":"Point"}
}