{
  "type": "Feature",
  "properties": {
    "gn:admin1_code":"53",
    "gn:admin2_code":"29",
    "gn:admin3_code":"293",
    "gn:admin4_code":"29277",
    "gn:asciiname":"Roc'h Cleguer",
    "gn:country_code":"FR",
    "gn:dem":123,
    "gn:feature_class":"P",
    "gn:feature_code":"PPL",
    "gn:name":"Roc\u2019h Cl\u00e9guer",
    "gn:population":0,
    "gn:timezone":"Europe/Paris",
    "iso:country":"FR",
    "wof:name":"Roc'h Cleguer",
    "wof:placetype":"locality"
},
  "geometry": {"coordinates":[-4.03333,48.41667],"type":"Point"}
}