{
  "type": "Feature",
  "properties": {
    "gn:admin1_code":"84",
    "gn:admin2_code":"03",
    "gn:admin3_code":"031",
    "gn:admin4_code":"03037",
    "gn:asciiname":"Verneuil",
    "gn:country_code":"FR",
    "gn:dem":229,
    "gn:feature_class":"P",
    "gn:feature_code":"PPL",
    "gn:name":"Verneuil",
    "gn:population":0,
    "gn:timezone":"Europe/Paris",
    "iso:country":"FR",
    "wof:name":"Verneuil",
    "wof:placetype":"locality"
},
  "geometry": {"coordinates":[2.63397,46.68387],"type":"Point"}
}