{
  "type": "Feature",
  "properties": {
    "gn:admin1_code":"84",
    "gn:admin2_code":"03",
    "gn:admin3_code":"031",
    "gn:admin4_code":"03037",
    "gn:asciiname":"Verneuil",
    "gn:country_code":"FR",
    "gn:dem":229,
    "gn:feature_class":"P",
    "gn:feature_code":"PPL",
    "gn:name":"Verneuil",
    "gn:population":0,
    "gn:timezone":"Europe/Paris",
    "iso:country":"FR",
    "name:cat_x_preferred":[
        "Verneuil"
    ],
    "name:ceb_x_preferred":[
        "Verneuil"
    ],
    "name:deu_x_preferred":[
        "Verneuil"
    ],
    "name:fra_x_preferred":[
        "Verneuil"
    ],
    "name:ita_x_preferred":[
        "Verneuil"
    ],
    "name:nds_x_preferred":[
        "Verneuil"
    ],
    "name:nld_x_preferred":[
        "Verneuil"
    ],
    "name:oci_x_preferred":[
        "Verneuil"
    ],
    "name:pms_x_preferred":[
        "Verneuil"
    ],
    "name:pol_x_preferred":[
        "Verneuil"
    ],
    "name:por_x_preferred":[
        "Verneuil"
    ],
    "name:rus_x_preferred":[
        "\u0412\u0435\u0440\u043d\u0451\u0439"
    ],
    "name:slk_x_preferred":[
        "Verneuil"
    ],
    "name:spa_x_preferred":[
        "Verneuil"
    ],
    "name:ukr_x_preferred":[
        "\u0412\u0435\u0440\u043d\u0435\u0439"
    ],
    "wof:name":"Verneuil",
    "wof:placetype":"locality"
},
  "geometry": {"coordinates":[2.63397,46.68387],"type":"Point"}
}