{
  "type": "Feature",
  "properties": {
    "gn:admin1_code":"53",
    "gn:admin2_code":"56",
    "gn:admin3_code":"561",
    "gn:admin4_code":"56162",
    "gn:asciiname":"Kervernois",
    "gn:country_code":"FR",
    "gn:dem":23,
    "gn:feature_class":"P",
    "gn:feature_code":"PPL",
    "gn:name":"Kerverno\u00efs",
    "gn:population":0,
    "gn:timezone":"Europe/Paris",
    "iso:country":"FR",
    "wof:name":"Kervernois",
    "wof:placetype":"locality"
},
  "geometry": {"coordinates":[-3.45357,47.71572000000001],"type":"Point"}
}