{
  "type": "Feature",
  "properties": {
    "gn:admin1_code":"44",
    "gn:admin2_code":"52",
    "gn:admin3_code":"521",
    "gn:admin4_code":"52365",
    "gn:asciiname":"Orges",
    "gn:country_code":"FR",
    "gn:dem":214,
    "gn:feature_class":"P",
    "gn:feature_code":"PPL",
    "gn:name":"Orges",
    "gn:population":375,
    "gn:timezone":"Europe/Paris",
    "iso:country":"FR",
    "wof:name":"Orges",
    "wof:placetype":"locality",
    "wof:population":375
},
  "geometry": {"coordinates":[4.92622,48.08073],"type":"Point"}
}