{
  "type": "Feature",
  "properties": {
    "frgov:code_epci":"245200597",
    "frgov:insee_arr":"1",
    "frgov:insee_com":"52365",
    "frgov:insee_dep":"52",
    "frgov:insee_reg":"44",
    "frgov:nom_com":"Orges",
    "frgov:nom_com_m":"ORGES",
    "frgov:nom_dep":"HAUTE-MARNE",
    "frgov:nom_reg":"GRAND EST",
    "frgov:statut":"Commune simple",
    "gn:admin1_code":"44",
    "gn:admin2_code":"52",
    "gn:admin3_code":"521",
    "gn:admin4_code":"52365",
    "gn:asciiname":"Orges",
    "gn:country_code":"FR",
    "gn:dem":214,
    "gn:feature_class":"P",
    "gn:feature_code":"PPL",
    "gn:name":"Orges",
    "gn:population":375,
    "gn:timezone":"Europe/Paris",
    "iso:country":"FR",
    "name:fra_x_preferred":[
        "Orges"
    ],
    "qs:a0":"France",
    "qs:a1":"HAUTE-MARNE",
    "qs:a1_lc":"52",
    "qs:a1r":"CHAMPAGNE-ARDENNE",
    "qs:a1r_lc":"21",
    "qs:a2_lc":"06",
    "qs:a2r_lc":"1",
    "qs:adm0":"France",
    "qs:adm0_a3":"FRA",
    "qs:la":"ORGES",
    "qs:la_lc":"52365",
    "qs:level":"localadmin",
    "qs:type":"Commune simple",
    "wof:coterminous":[
        404415725
    ],
    "wof:name":"Orges",
    "wof:placetype":"locality",
    "wof:placetype_local":"Commune simple",
    "wof:population":375
},
  "geometry": {"coordinates":[4.92622,48.08073],"type":"Point"}
}