{
  "type": "Feature",
  "properties": {
    "gn:admin1_code":"84",
    "gn:admin2_code":"69",
    "gn:admin3_code":"691",
    "gn:admin4_code":"69249",
    "gn:asciiname":"Les Julins",
    "gn:country_code":"FR",
    "gn:dem":415,
    "gn:feature_class":"P",
    "gn:feature_code":"PPL",
    "gn:name":"Les Julins",
    "gn:population":0,
    "gn:timezone":"Europe/Paris",
    "iso:country":"FR",
    "name:und_x_variant":[
        "Julin",
        "Les Julins"
    ],
    "wof:name":"Les Julins",
    "wof:placetype":"locality"
},
  "geometry": {"coordinates":[4.61626,45.68768],"type":"Point"}
}