{
  "type": "Feature",
  "properties": {
    "gn:admin1_code":"27",
    "gn:admin2_code":"21",
    "gn:admin3_code":"211",
    "gn:admin4_code":"21054.0",
    "gn:asciiname":"Faubourg-Saint-Martin",
    "gn:country_code":"FR",
    "gn:dem":218,
    "gn:feature_class":"P",
    "gn:feature_code":"PPL",
    "gn:name":"Faubourg-Saint-Martin",
    "gn:population":0,
    "gn:timezone":"Europe/Paris",
    "iso:country":"FR",
    "wof:name":"Faubourg-Saint-Martin",
    "wof:placetype":"locality"
},
  "geometry": {"coordinates":[4.83262,47.02881],"type":"Point"}
}