{
  "type": "Feature",
  "properties": {
    "gn:admin1_code":"27",
    "gn:admin2_code":"25",
    "gn:admin3_code":"253",
    "gn:admin4_code":"25600",
    "gn:asciiname":"Vennes",
    "gn:country_code":"FR",
    "gn:dem":794,
    "gn:feature_class":"P",
    "gn:feature_code":"PPL",
    "gn:name":"Vennes",
    "gn:population":0,
    "gn:timezone":"Europe/Paris",
    "iso:country":"FR",
    "name:cat_x_preferred":[
        "Vennes"
    ],
    "name:ceb_x_preferred":[
        "Vennes"
    ],
    "name:deu_x_preferred":[
        "Vennes"
    ],
    "name:eus_x_preferred":[
        "Vennes"
    ],
    "name:fra_x_preferred":[
        "Vennes"
    ],
    "name:hun_x_preferred":[
        "Vennes"
    ],
    "name:ita_x_preferred":[
        "Vennes"
    ],
    "name:lat_x_preferred":[
        "Vennes"
    ],
    "name:msa_x_preferred":[
        "Vennes"
    ],
    "name:nld_x_preferred":[
        "Vennes"
    ],
    "name:oci_x_preferred":[
        "Vennes"
    ],
    "name:pms_x_preferred":[
        "Vennes"
    ],
    "name:pol_x_preferred":[
        "Vennes"
    ],
    "name:por_x_preferred":[
        "Vennes"
    ],
    "name:slk_x_preferred":[
        "Vennes"
    ],
    "name:spa_x_preferred":[
        "Vennes"
    ],
    "name:swe_x_preferred":[
        "Vennes"
    ],
    "name:ukr_x_preferred":[
        "\u0412\u0435\u043d\u043d"
    ],
    "name:uzb_x_preferred":[
        "Vennes"
    ],
    "name:vie_x_preferred":[
        "Vennes"
    ],
    "name:vol_x_preferred":[
        "Vennes"
    ],
    "name:war_x_preferred":[
        "Vennes"
    ],
    "name:zho_x_preferred":[
        "\u97e6\u5185"
    ],
    "wof:name":"Vennes",
    "wof:placetype":"locality"
},
  "geometry": {"coordinates":[6.5474,47.1528],"type":"Point"}
}