{
  "type": "Feature",
  "properties": {
    "frgov:code_epci":"242504181",
    "frgov:insee_arr":"3",
    "frgov:insee_com":"25600",
    "frgov:insee_dep":"25",
    "frgov:insee_reg":"27",
    "frgov:nom_com":"Vennes",
    "frgov:nom_com_m":"VENNES",
    "frgov:nom_dep":"DOUBS",
    "frgov:nom_reg":"BOURGOGNE-FRANCHE-COMTE",
    "frgov:statut":"Commune simple",
    "gn:admin1_code":"27",
    "gn:admin2_code":"25",
    "gn:admin3_code":"253",
    "gn:admin4_code":"25600",
    "gn:asciiname":"Vennes",
    "gn:country_code":"FR",
    "gn:dem":794,
    "gn:feature_class":"P",
    "gn:feature_code":"PPL",
    "gn:name":"Vennes",
    "gn:population":0,
    "gn:timezone":"Europe/Paris",
    "iso:country":"FR",
    "name:cat_x_preferred":[
        "Vennes"
    ],
    "name:ceb_x_preferred":[
        "Vennes"
    ],
    "name:deu_x_preferred":[
        "Vennes"
    ],
    "name:eus_x_preferred":[
        "Vennes"
    ],
    "name:fra_x_preferred":[
        "Vennes"
    ],
    "name:hun_x_preferred":[
        "Vennes"
    ],
    "name:ita_x_preferred":[
        "Vennes"
    ],
    "name:lat_x_preferred":[
        "Vennes"
    ],
    "name:msa_x_preferred":[
        "Vennes"
    ],
    "name:nld_x_preferred":[
        "Vennes"
    ],
    "name:oci_x_preferred":[
        "Vennes"
    ],
    "name:pms_x_preferred":[
        "Vennes"
    ],
    "name:pol_x_preferred":[
        "Vennes"
    ],
    "name:por_x_preferred":[
        "Vennes"
    ],
    "name:slk_x_preferred":[
        "Vennes"
    ],
    "name:spa_x_preferred":[
        "Vennes"
    ],
    "name:swe_x_preferred":[
        "Vennes"
    ],
    "name:ukr_x_preferred":[
        "\u0412\u0435\u043d\u043d"
    ],
    "name:uzb_x_preferred":[
        "Vennes"
    ],
    "name:vie_x_preferred":[
        "Vennes"
    ],
    "name:vol_x_preferred":[
        "Vennes"
    ],
    "name:war_x_preferred":[
        "Vennes"
    ],
    "name:zho_x_preferred":[
        "\u97e6\u5185"
    ],
    "qs:a0":"France",
    "qs:a1":"DOUBS",
    "qs:a1_lc":"25",
    "qs:a1r":"FRANCHE-COMTE",
    "qs:a1r_lc":"43",
    "qs:a2_lc":"19",
    "qs:a2r_lc":"3",
    "qs:adm0":"France",
    "qs:adm0_a3":"FRA",
    "qs:la":"VENNES",
    "qs:la_lc":"25600",
    "qs:level":"localadmin",
    "qs:type":"Commune simple",
    "wof:coterminous":[
        404402891
    ],
    "wof:name":"Vennes",
    "wof:placetype":"locality",
    "wof:placetype_local":"Commune simple"
},
  "geometry": {"coordinates":[6.5474,47.1528],"type":"Point"}
}