{
  "type": "Feature",
  "properties": {
    "gn:admin1_code":"32",
    "gn:admin2_code":"62",
    "gn:admin3_code":"625",
    "gn:admin4_code":"62008.0",
    "gn:asciiname":"Le Val d'Acquin",
    "gn:country_code":"FR",
    "gn:dem":106,
    "gn:feature_class":"P",
    "gn:feature_code":"PPL",
    "gn:name":"Le Val d\u2019Acquin",
    "gn:population":0,
    "gn:timezone":"Europe/Paris",
    "iso:country":"FR",
    "wof:name":"Le Val d'Acquin",
    "wof:placetype":"locality"
},
  "geometry": {"coordinates":[2.06512,50.72651],"type":"Point"}
}