{
  "type": "Feature",
  "properties": {
    "iso:country":"FR",
    "name:fra_x_variant":[
        "Saint-Ambroise"
    ],
    "wof:name":"Saint-Ambroise",
    "wof:placetype":"neighbourhood"
},
  "geometry": {"coordinates":[2.376117,48.862443],"type":"Point"}
}