{
  "type": "Feature",
  "properties": {
    "gn:admin1_code":"84",
    "gn:admin2_code":"63",
    "gn:admin3_code":"631",
    "gn:admin4_code":"63086",
    "gn:asciiname":"Montmy",
    "gn:country_code":"FR",
    "gn:dem":882,
    "gn:feature_class":"P",
    "gn:feature_code":"PPL",
    "gn:name":"Montmy",
    "gn:population":0,
    "gn:timezone":"Europe/Paris",
    "iso:country":"FR",
    "wof:name":"Montmy",
    "wof:placetype":"locality"
},
  "geometry": {"coordinates":[3.61667,45.63333],"type":"Point"}
}