{
  "type": "Feature",
  "properties": {
    "gn:admin1_code":"27",
    "gn:admin2_code":"58",
    "gn:admin3_code":"584",
    "gn:admin4_code":"58270.0",
    "gn:asciiname":"Les Bouillons",
    "gn:country_code":"FR",
    "gn:dem":249,
    "gn:feature_class":"P",
    "gn:feature_code":"PPL",
    "gn:name":"Les Bouillons",
    "gn:population":0,
    "gn:timezone":"Europe/Paris",
    "iso:country":"FR",
    "name:und_x_variant":[
        "Les Bouillon",
        "Les Bouillons"
    ],
    "wof:name":"Les Bouillons",
    "wof:placetype":"locality"
},
  "geometry": {"coordinates":[3.02419,47.47171],"type":"Point"}
}