{
  "type": "Feature",
  "properties": {
    "gn:admin1_code":"84",
    "gn:admin2_code":"73",
    "gn:admin3_code":"732",
    "gn:admin4_code":"73164",
    "gn:asciiname":"La Chapelle",
    "gn:country_code":"FR",
    "gn:dem":759,
    "gn:feature_class":"P",
    "gn:feature_code":"PPL",
    "gn:name":"La Chapelle",
    "gn:population":0,
    "gn:timezone":"Europe/Paris",
    "iso:country":"FR",
    "wof:name":"La Chapelle",
    "wof:placetype":"locality"
},
  "geometry": {"coordinates":[5.99225,45.7148],"type":"Point"}
}