{
  "type": "Feature",
  "properties": {
    "gn:gn_country":"FR",
    "gn:gn_fcode":"PPL",
    "gn:gn_pop":77,
    "gn:population":77,
    "iso:country":"FR",
    "name:bre_x_preferred":[
        "Louvi\u00e8res"
    ],
    "name:ceb_x_preferred":[
        "Louvi\u00e8res"
    ],
    "name:deu_x_preferred":[
        "Louvi\u00e8res"
    ],
    "name:fra_x_preferred":[
        "Louvi\u00e8res"
    ],
    "name:ind_x_preferred":[
        "Louvi\u00e8res"
    ],
    "name:ita_x_preferred":[
        "Louvi\u00e8res"
    ],
    "name:nds_x_preferred":[
        "Louvi\u00e8res"
    ],
    "name:nld_x_preferred":[
        "Louvi\u00e8res"
    ],
    "name:oci_x_preferred":[
        "Louvi\u00e8res"
    ],
    "name:pms_x_preferred":[
        "Louvi\u00e8res"
    ],
    "name:pol_x_preferred":[
        "Louvi\u00e8res"
    ],
    "name:por_x_preferred":[
        "Louvi\u00e8res"
    ],
    "name:rus_x_preferred":[
        "\u041b\u0443\u0432\u044c\u0435\u0440"
    ],
    "name:slk_x_preferred":[
        "Louvi\u00e8res"
    ],
    "name:spa_x_preferred":[
        "Louvi\u00e8res"
    ],
    "name:swe_x_preferred":[
        "Louvi\u00e8res"
    ],
    "name:ukr_x_preferred":[
        "\u041b\u0443\u0432'\u0454\u0440"
    ],
    "qs_pg:aaroncc":"FR",
    "qs_pg:gn_country":"FR",
    "qs_pg:gn_fcode":"PPL",
    "qs_pg:gn_pop":77,
    "qs_pg:name":"Louvi\u00e8res",
    "qs_pg:name_adm0":"France",
    "qs_pg:name_adm1":"Basse-Normandie",
    "qs_pg:photos_9r":0,
    "qs_pg:photos_sr":0,
    "qs_pg:pop_sr":1,
    "qs_pg:qs_pg_placetype":"locality",
    "qs_pg:qs_pg_placetype_gp":"Town",
    "qs_pg:woe_adm0":23424819,
    "woe:adm0_id":23424819,
    "woe:name_adm0":"France",
    "woe:name_adm1":"Basse-Normandie",
    "woe:placetype":"Town",
    "wof:name":"Louvi\u00e8res",
    "wof:placetype":"neighbourhood",
    "wof:population":77
},
  "geometry": {"coordinates":[0.08333,49.36667],"type":"Point"}
}