{
  "type": "Feature",
  "properties": {
    "gn:admin1_code":"84",
    "gn:admin2_code":"15",
    "gn:admin3_code":"153",
    "gn:admin4_code":"15259",
    "gn:asciiname":"Le Pradal",
    "gn:country_code":"FR",
    "gn:dem":996,
    "gn:feature_class":"P",
    "gn:feature_code":"PPL",
    "gn:name":"Le Pradal",
    "gn:population":0,
    "gn:timezone":"Europe/Paris",
    "iso:country":"FR",
    "name:cat_x_preferred":[
        "Lo Pradal"
    ],
    "name:ceb_x_preferred":[
        "Le Pradal"
    ],
    "name:deu_x_preferred":[
        "Le Pradal"
    ],
    "name:eus_x_preferred":[
        "Le Pradal"
    ],
    "name:fas_x_preferred":[
        "\u0644 \u067e\u0631\u0627\u062f\u0627\u0644"
    ],
    "name:fra_x_preferred":[
        "Le Pradal"
    ],
    "name:hun_x_preferred":[
        "Le Pradal"
    ],
    "name:ita_x_preferred":[
        "Le Pradal"
    ],
    "name:kaz_x_preferred":[
        "\u041b\u0435-\u041f\u0440\u0430\u0434\u0430\u043b\u044c"
    ],
    "name:lat_x_preferred":[
        "Le Pradal"
    ],
    "name:lmo_x_preferred":[
        "Le Pradal"
    ],
    "name:mlg_x_preferred":[
        "Le Pradal"
    ],
    "name:msa_x_preferred":[
        "Le Pradal"
    ],
    "name:nld_x_preferred":[
        "Le Pradal"
    ],
    "name:oci_x_preferred":[
        "Lo Pradal"
    ],
    "name:pms_x_preferred":[
        "Le Pradal"
    ],
    "name:pol_x_preferred":[
        "Le Pradal"
    ],
    "name:por_x_preferred":[
        "Le Pradal"
    ],
    "name:ron_x_preferred":[
        "Le Pradal"
    ],
    "name:slk_x_preferred":[
        "Le Pradal"
    ],
    "name:spa_x_preferred":[
        "Le Pradal"
    ],
    "name:swe_x_preferred":[
        "Le Pradal"
    ],
    "name:ukr_x_preferred":[
        "\u041b\u0435-\u041f\u0440\u0430\u0434\u0430\u043b\u044c"
    ],
    "name:vie_x_preferred":[
        "Le Pradal"
    ],
    "name:vol_x_preferred":[
        "Le Pradal"
    ],
    "name:war_x_preferred":[
        "Le Pradal"
    ],
    "name:zho_x_preferred":[
        "\u52d2\u666e\u62c9\u8fbe"
    ],
    "wof:name":"Le Pradal",
    "wof:placetype":"locality"
},
  "geometry": {"coordinates":[3.16387,45.11908],"type":"Point"}
}