{
  "type": "Feature",
  "properties": {
    "gn:admin1_code":"76",
    "gn:admin2_code":"12",
    "gn:admin3_code":"123",
    "gn:admin4_code":"12305",
    "gn:asciiname":"Le Crouzet",
    "gn:country_code":"FR",
    "gn:dem":247,
    "gn:feature_class":"P",
    "gn:feature_code":"PPL",
    "gn:name":"Le Crouzet",
    "gn:population":0,
    "gn:timezone":"Europe/Paris",
    "iso:country":"FR",
    "wof:name":"Le Crouzet",
    "wof:placetype":"locality"
},
  "geometry": {"coordinates":[2.22877,44.54766],"type":"Point"}
}