{
  "type": "Feature",
  "properties": {
    "gn:admin1_code":"76",
    "gn:admin2_code":"12",
    "gn:admin3_code":"123",
    "gn:admin4_code":"12305",
    "gn:asciiname":"Le Crouzet",
    "gn:country_code":"FR",
    "gn:dem":247,
    "gn:feature_class":"P",
    "gn:feature_code":"PPL",
    "gn:name":"Le Crouzet",
    "gn:population":0,
    "gn:timezone":"Europe/Paris",
    "iso:country":"FR",
    "name:cat_x_preferred":[
        "Le Crouzet"
    ],
    "name:ceb_x_preferred":[
        "Le Crouzet"
    ],
    "name:deu_x_preferred":[
        "Le Crouzet"
    ],
    "name:eus_x_preferred":[
        "Le Crouzet"
    ],
    "name:fra_x_preferred":[
        "Le Crouzet"
    ],
    "name:hun_x_preferred":[
        "Le Crouzet"
    ],
    "name:ita_x_preferred":[
        "Le Crouzet"
    ],
    "name:lat_x_preferred":[
        "Le Crouzet"
    ],
    "name:msa_x_preferred":[
        "Le Crouzet"
    ],
    "name:nld_x_preferred":[
        "Le Crouzet"
    ],
    "name:oci_x_preferred":[
        "Le Crouzet"
    ],
    "name:pms_x_preferred":[
        "Le Crouzet"
    ],
    "name:pol_x_preferred":[
        "Le Crouzet"
    ],
    "name:por_x_preferred":[
        "Le Crouzet"
    ],
    "name:slk_x_preferred":[
        "Le Crouzet"
    ],
    "name:spa_x_preferred":[
        "Le Crouzet"
    ],
    "name:srp_x_preferred":[
        "\u041a\u0440\u0443\u0437\u0435"
    ],
    "name:swe_x_preferred":[
        "Le Crouzet"
    ],
    "name:ukr_x_preferred":[
        "\u041b\u0435-\u041a\u0440\u0443\u0437\u0435"
    ],
    "name:uzb_x_preferred":[
        "Le Crouzet"
    ],
    "name:vie_x_preferred":[
        "Le Crouzet"
    ],
    "name:vol_x_preferred":[
        "Le Crouzet"
    ],
    "name:war_x_preferred":[
        "Le Crouzet"
    ],
    "name:zho_x_preferred":[
        "\u52d2\u514b\u9c81\u6cfd"
    ],
    "wof:name":"Le Crouzet",
    "wof:placetype":"locality"
},
  "geometry": {"coordinates":[2.22877,44.54766],"type":"Point"}
}