{
  "type": "Feature",
  "properties": {
    "iso:country":"FR",
    "wof:name":"La Pointe Rouge",
    "wof:placetype":"neighbourhood"
},
  "geometry": {"coordinates":[5.37942153651177,43.23837821863339],"type":"Point"}
}