{
  "type": "Feature",
  "properties": {
    "gn:admin1_code":"75",
    "gn:admin2_code":"23",
    "gn:admin3_code":"231",
    "gn:admin4_code":"23114",
    "gn:asciiname":"Rierette",
    "gn:country_code":"FR",
    "gn:dem":417,
    "gn:feature_class":"P",
    "gn:feature_code":"PPL",
    "gn:name":"Ri\u00e8rette",
    "gn:population":0,
    "gn:timezone":"Europe/Paris",
    "iso:country":"FR",
    "wof:name":"Rierette",
    "wof:placetype":"locality"
},
  "geometry": {"coordinates":[2.37354,46.17548],"type":"Point"}
}