{
  "type": "Feature",
  "properties": {
    "gn:admin1_code":"84",
    "gn:admin2_code":"63",
    "gn:admin3_code":"633",
    "gn:admin4_code":"63144",
    "gn:asciiname":"Espinat",
    "gn:country_code":"FR",
    "gn:dem":1148,
    "gn:feature_class":"P",
    "gn:feature_code":"PPL",
    "gn:name":"Espinat",
    "gn:population":0,
    "gn:timezone":"Europe/Paris",
    "iso:country":"FR",
    "wof:name":"Espinat",
    "wof:placetype":"locality"
},
  "geometry": {"coordinates":[2.86553,45.42],"type":"Point"}
}