{
  "type": "Feature",
  "properties": {
    "gn:admin1_code":"76",
    "gn:admin2_code":"30",
    "gn:admin3_code":"303",
    "gn:admin4_code":"30065",
    "gn:asciiname":"Canaules-et-Argentieres",
    "gn:country_code":"FR",
    "gn:dem":107,
    "gn:feature_class":"P",
    "gn:feature_code":"PPL",
    "gn:name":"Canaules-et-Argenti\u00e8res",
    "gn:population":368,
    "gn:timezone":"Europe/Paris",
    "iso:country":"FR",
    "name:und_x_variant":[
        "Canaules-et Argenti\u00e8re",
        "Canaules-et-Argenti\u00e8res"
    ],
    "wof:name":"Canaules-et-Argentieres",
    "wof:placetype":"locality",
    "wof:population":368
},
  "geometry": {"coordinates":[4.05207,43.98111],"type":"Point"}
}