{
  "type": "Feature",
  "properties": {
    "gn:admin1_code":"76",
    "gn:admin2_code":"46",
    "gn:admin3_code":"462",
    "gn:admin4_code":"46177",
    "gn:asciiname":"Siran",
    "gn:country_code":"FR",
    "gn:dem":341,
    "gn:feature_class":"P",
    "gn:feature_code":"PPL",
    "gn:name":"Siran",
    "gn:population":0,
    "gn:timezone":"Europe/Paris",
    "iso:country":"FR",
    "name:cat_x_preferred":[
        "Siran"
    ],
    "name:ceb_x_preferred":[
        "Siran"
    ],
    "name:deu_x_preferred":[
        "Siran"
    ],
    "name:fra_x_preferred":[
        "Siran"
    ],
    "name:ita_x_preferred":[
        "Siran"
    ],
    "name:jpn_x_preferred":[
        "\u30b7\u30e9\u30f3"
    ],
    "name:nds_x_preferred":[
        "Siran"
    ],
    "name:nld_x_preferred":[
        "Siran"
    ],
    "name:pms_x_preferred":[
        "Siran"
    ],
    "name:pol_x_preferred":[
        "Siran"
    ],
    "name:por_x_preferred":[
        "Siran"
    ],
    "name:rus_x_preferred":[
        "\u0421\u0438\u0440\u0430\u043d"
    ],
    "name:scn_x_preferred":[
        "Siran"
    ],
    "name:slk_x_preferred":[
        "Siran"
    ],
    "name:spa_x_preferred":[
        "Siran"
    ],
    "name:swe_x_preferred":[
        "Siran"
    ],
    "name:ukr_x_preferred":[
        "\u0421\u0456\u0440\u0430\u043d"
    ],
    "wof:name":"Siran",
    "wof:placetype":"locality"
},
  "geometry": {"coordinates":[1.80948,44.84505],"type":"Point"}
}