{
  "type": "Feature",
  "properties": {
    "gn:admin1_code":"53",
    "gn:admin2_code":"29",
    "gn:admin3_code":"294",
    "gn:admin4_code":"29214",
    "gn:asciiname":"Kerguen",
    "gn:country_code":"FR",
    "gn:dem":10,
    "gn:feature_class":"P",
    "gn:feature_code":"PPL",
    "gn:name":"Kerguen",
    "gn:population":0,
    "gn:timezone":"Europe/Paris",
    "iso:country":"FR",
    "wof:name":"Kerguen",
    "wof:placetype":"locality"
},
  "geometry": {"coordinates":[-4.37792,47.9265],"type":"Point"}
}