{
  "type": "Feature",
  "properties": {
    "gn:admin1_code":"76",
    "gn:admin2_code":"30",
    "gn:admin3_code":"302",
    "gn:admin4_code":"30189",
    "gn:asciiname":"Courbessac",
    "gn:country_code":"FR",
    "gn:dem":74,
    "gn:feature_class":"P",
    "gn:feature_code":"PPL",
    "gn:name":"Courbessac",
    "gn:population":0,
    "gn:timezone":"Europe/Paris",
    "iso:country":"FR",
    "wof:name":"Courbessac",
    "wof:placetype":"locality"
},
  "geometry": {"coordinates":[4.40286,43.86059],"type":"Point"}
}