{
  "type": "Feature",
  "properties": {
    "gn:admin1_code":"84",
    "gn:admin2_code":"38",
    "gn:admin3_code":"381",
    "gn:admin4_code":"38023",
    "gn:asciiname":"Mageline",
    "gn:country_code":"FR",
    "gn:dem":550,
    "gn:feature_class":"P",
    "gn:feature_code":"PPL",
    "gn:name":"Mageline",
    "gn:population":0,
    "gn:timezone":"Europe/Paris",
    "iso:country":"FR",
    "wof:name":"Mageline",
    "wof:placetype":"locality"
},
  "geometry": {"coordinates":[5.67244,44.97305],"type":"Point"}
}