{
  "type": "Feature",
  "properties": {
    "gn:admin1_code":"84",
    "gn:admin2_code":"43",
    "gn:admin3_code":"433",
    "gn:admin4_code":"43246",
    "gn:asciiname":"Pravel",
    "gn:country_code":"FR",
    "gn:dem":779,
    "gn:feature_class":"P",
    "gn:feature_code":"PPL",
    "gn:name":"Pravel",
    "gn:population":0,
    "gn:timezone":"Europe/Paris",
    "iso:country":"FR",
    "wof:name":"Pravel",
    "wof:placetype":"locality"
},
  "geometry": {"coordinates":[4.02435,45.27838],"type":"Point"}
}