{
  "type": "Feature",
  "properties": {
    "gn:admin1_code":"84",
    "gn:admin2_code":"63",
    "gn:admin3_code":"633",
    "gn:admin4_code":"63261",
    "gn:asciiname":"Nave",
    "gn:country_code":"FR",
    "gn:dem":490,
    "gn:feature_class":"P",
    "gn:feature_code":"PPL",
    "gn:name":"Nave",
    "gn:population":0,
    "gn:timezone":"Europe/Paris",
    "iso:country":"FR",
    "wof:name":"Nave",
    "wof:placetype":"locality"
},
  "geometry": {"coordinates":[3.26994,45.57818],"type":"Point"}
}