{
  "type": "Feature",
  "properties": {
    "gn:admin1_code":"11",
    "gn:admin2_code":"95",
    "gn:admin3_code":"953",
    "gn:admin4_code":"95355.0",
    "gn:asciiname":"Arthieul",
    "gn:country_code":"FR",
    "gn:dem":100,
    "gn:feature_class":"P",
    "gn:feature_code":"PPL",
    "gn:name":"Arthieul",
    "gn:population":0,
    "gn:timezone":"Europe/Paris",
    "iso:country":"FR",
    "wof:name":"Arthieul",
    "wof:placetype":"locality"
},
  "geometry": {"coordinates":[1.80647,49.1524],"type":"Point"}
}