{
  "type": "Feature",
  "properties": {
    "gn:admin1_code":"93",
    "gn:admin2_code":"04",
    "gn:admin3_code":"043",
    "gn:admin4_code":"04059",
    "gn:asciiname":"Sauzeries Hautes",
    "gn:country_code":"FR",
    "gn:dem":953,
    "gn:feature_class":"P",
    "gn:feature_code":"PPL",
    "gn:name":"Sauzeries Hautes",
    "gn:population":0,
    "gn:timezone":"Europe/Paris",
    "iso:country":"FR",
    "wof:name":"Sauzeries Hautes",
    "wof:placetype":"locality"
},
  "geometry": {"coordinates":[6.3612,44.05266],"type":"Point"}
}