{
  "type": "Feature",
  "properties": {
    "gn:admin1_code":"84",
    "gn:admin2_code":"74",
    "gn:admin3_code":"742",
    "gn:admin4_code":"74256",
    "gn:asciiname":"Mernex",
    "gn:country_code":"FR",
    "gn:dem":670,
    "gn:feature_class":"P",
    "gn:feature_code":"PPL",
    "gn:name":"Mernex",
    "gn:population":0,
    "gn:timezone":"Europe/Paris",
    "iso:country":"FR",
    "wof:name":"Mernex",
    "wof:placetype":"locality"
},
  "geometry": {"coordinates":[6.62068,45.94094000000001],"type":"Point"}
}