{
  "type": "Feature",
  "properties": {
    "gn:gn_country":"FR",
    "gn:gn_fcode":"PPL",
    "gn:gn_pop":0,
    "iso:country":"FR",
    "name:cat_x_preferred":[
        "Pra-Loup"
    ],
    "name:deu_x_preferred":[
        "Pra-Loup"
    ],
    "name:eng_x_preferred":[
        "Pra Loup"
    ],
    "name:fra_x_preferred":[
        "Pra-Loup"
    ],
    "name:ita_x_preferred":[
        "Pra Loup"
    ],
    "name:jpn_x_preferred":[
        "\u30d7\u30e9\uff1d\u30eb"
    ],
    "name:ltz_x_preferred":[
        "Pra-Loup"
    ],
    "name:nld_x_preferred":[
        "Pra Loup"
    ],
    "name:nob_x_preferred":[
        "Pra Loup"
    ],
    "name:pol_x_preferred":[
        "Pra Loup"
    ],
    "name:swe_x_preferred":[
        "Pra Loup"
    ],
    "qs_pg:aaroncc":"FR",
    "qs_pg:gn_country":"FR",
    "qs_pg:gn_fcode":"PPL",
    "qs_pg:gn_pop":0,
    "qs_pg:name":"Pra-Loup",
    "qs_pg:name_adm0":"France",
    "qs_pg:name_adm1":"Provence-Alpes-C\u00f4te d'Azur",
    "qs_pg:photos":173,
    "qs_pg:photos_1k":35,
    "qs_pg:photos_9k":1,
    "qs_pg:photos_9r":4,
    "qs_pg:photos_all":173,
    "qs_pg:photos_sr":4,
    "qs_pg:pop_sr":0,
    "qs_pg:qs_pg_placetype":"locality",
    "qs_pg:qs_pg_placetype_gp":"Town",
    "qs_pg:woe_adm0":23424819,
    "woe:adm0_id":23424819,
    "woe:name_adm0":"France",
    "woe:name_adm1":"Provence-Alpes-C\u00f4te d'Azur",
    "woe:placetype":"Town",
    "wof:name":"Pra-Loup",
    "wof:placetype":"neighbourhood"
},
  "geometry": {"coordinates":[6.60476,44.37043],"type":"Point"}
}