{
  "type": "Feature",
  "properties": {
    "gn:admin1_code":"84",
    "gn:admin2_code":"38",
    "gn:admin3_code":"382",
    "gn:admin4_code":"38297",
    "gn:asciiname":"Concharbin",
    "gn:country_code":"FR",
    "gn:dem":278,
    "gn:feature_class":"P",
    "gn:feature_code":"PPL",
    "gn:name":"Concharbin",
    "gn:population":0,
    "gn:timezone":"Europe/Paris",
    "iso:country":"FR",
    "wof:name":"Concharbin",
    "wof:placetype":"locality"
},
  "geometry": {"coordinates":[5.46387,45.71697],"type":"Point"}
}