{
  "type": "Feature",
  "properties": {
    "gn:admin1_code":"84",
    "gn:admin2_code":"43",
    "gn:admin3_code":"432",
    "gn:admin4_code":"43138.0",
    "gn:asciiname":"Les Ignes",
    "gn:country_code":"FR",
    "gn:dem":1005,
    "gn:feature_class":"P",
    "gn:feature_code":"PPL",
    "gn:name":"Les Ignes",
    "gn:population":0,
    "gn:timezone":"Europe/Paris",
    "iso:country":"FR",
    "wof:name":"Les Ignes",
    "wof:placetype":"locality"
},
  "geometry": {"coordinates":[3.69549,45.22589],"type":"Point"}
}