{
  "type": "Feature",
  "properties": {
    "gn:admin1_code":"53",
    "gn:admin2_code":"22",
    "gn:admin3_code":"224",
    "gn:admin4_code":"22074",
    "gn:asciiname":"Saint-Damant",
    "gn:country_code":"FR",
    "gn:dem":230,
    "gn:feature_class":"P",
    "gn:feature_code":"PPL",
    "gn:name":"Saint-Damant",
    "gn:population":0,
    "gn:timezone":"Europe/Paris",
    "iso:country":"FR",
    "name:und_x_variant":[
        "Saint-Daman",
        "Saint-Damant"
    ],
    "wof:name":"Saint-Damant",
    "wof:placetype":"locality"
},
  "geometry": {"coordinates":[-3.04567,48.35066],"type":"Point"}
}