{
  "type": "Feature",
  "properties": {
    "gn:admin1_code":"52",
    "gn:admin2_code":"49",
    "gn:admin3_code":"491",
    "gn:admin4_code":"49050",
    "gn:asciiname":"Les Brosses",
    "gn:country_code":"FR",
    "gn:dem":61,
    "gn:feature_class":"P",
    "gn:feature_code":"PPL",
    "gn:name":"Les Brosses",
    "gn:population":0,
    "gn:timezone":"Europe/Paris",
    "iso:country":"FR",
    "wof:name":"Les Brosses",
    "wof:placetype":"locality"
},
  "geometry": {"coordinates":[-0.38631,47.31361],"type":"Point"}
}