{
  "type": "Feature",
  "properties": {
    "gn:admin1_code":"44",
    "gn:admin2_code":"52",
    "gn:admin3_code":"523",
    "gn:admin4_code":"52497",
    "gn:asciiname":"Avrainville",
    "gn:country_code":"FR",
    "gn:dem":246,
    "gn:feature_class":"P",
    "gn:feature_code":"PPL",
    "gn:name":"Avrainville",
    "gn:population":0,
    "gn:timezone":"Europe/Paris",
    "iso:country":"FR",
    "name:ceb_x_preferred":[
        "Avrainville"
    ],
    "name:ces_x_preferred":[
        "Avrainville"
    ],
    "name:deu_x_preferred":[
        "Avrainville"
    ],
    "name:fra_x_preferred":[
        "Avrainville"
    ],
    "name:ita_x_preferred":[
        "Avrainville"
    ],
    "name:ltz_x_preferred":[
        "Avrainville"
    ],
    "name:nds_x_preferred":[
        "Avrainville"
    ],
    "name:nld_x_preferred":[
        "Avrainville"
    ],
    "name:pol_x_preferred":[
        "Avrainville"
    ],
    "name:por_x_preferred":[
        "Avrainville"
    ],
    "name:rus_x_preferred":[
        "\u0410\u0432\u0440\u0435\u043d\u0432\u0438\u043b\u044c"
    ],
    "name:slk_x_preferred":[
        "Avrainville"
    ],
    "name:spa_x_preferred":[
        "Avrainville"
    ],
    "name:srp_x_preferred":[
        "\u0410\u0432\u0440\u0435\u043d\u0432\u0438\u043b"
    ],
    "name:swe_x_preferred":[
        "Avrainville"
    ],
    "name:ukr_x_preferred":[
        "\u0410\u0432\u0440\u0435\u043d\u0432\u0456\u043b\u044c"
    ],
    "wof:name":"Avrainville",
    "wof:placetype":"locality"
},
  "geometry": {"coordinates":[5.04776,48.5316],"type":"Point"}
}