{
  "type": "Feature",
  "properties": {
    "gn:admin1_code":"75",
    "gn:admin2_code":"23",
    "gn:admin3_code":"232",
    "gn:admin4_code":"23089",
    "gn:asciiname":"Moulizoux",
    "gn:country_code":"FR",
    "gn:dem":329,
    "gn:feature_class":"P",
    "gn:feature_code":"PPL",
    "gn:name":"Moulizoux",
    "gn:population":0,
    "gn:timezone":"Europe/Paris",
    "iso:country":"FR",
    "wof:name":"Moulizoux",
    "wof:placetype":"locality"
},
  "geometry": {"coordinates":[2.00503,46.37107],"type":"Point"}
}