{
  "type": "Feature",
  "properties": {
    "gn:admin1_code":"84",
    "gn:admin2_code":"43",
    "gn:admin3_code":"431",
    "gn:admin4_code":"43237",
    "gn:asciiname":"Les Salles",
    "gn:country_code":"FR",
    "gn:dem":968,
    "gn:feature_class":"P",
    "gn:feature_code":"PPL",
    "gn:name":"Les Salles",
    "gn:population":0,
    "gn:timezone":"Europe/Paris",
    "iso:country":"FR",
    "name:cat_x_preferred":[
        "Les Salles"
    ],
    "name:ceb_x_preferred":[
        "Les Salles"
    ],
    "name:deu_x_preferred":[
        "Les Salles"
    ],
    "name:eus_x_preferred":[
        "Les Salles"
    ],
    "name:fas_x_preferred":[
        "\u0644\u0632 \u0633\u0627\u0644\u0633"
    ],
    "name:fra_x_preferred":[
        "Les Salles"
    ],
    "name:hun_x_preferred":[
        "Les Salles"
    ],
    "name:ita_x_preferred":[
        "Les Salles"
    ],
    "name:lat_x_preferred":[
        "Les Salles"
    ],
    "name:lmo_x_preferred":[
        "Les Salles"
    ],
    "name:msa_x_preferred":[
        "Les Salles"
    ],
    "name:nld_x_preferred":[
        "Les Salles"
    ],
    "name:oci_x_preferred":[
        "Les Salles"
    ],
    "name:pms_x_preferred":[
        "Les Salles"
    ],
    "name:pol_x_preferred":[
        "Les Salles"
    ],
    "name:por_x_preferred":[
        "Les Salles"
    ],
    "name:ron_x_preferred":[
        "Les Salles"
    ],
    "name:slk_x_preferred":[
        "Les Salles"
    ],
    "name:spa_x_preferred":[
        "Les Salles"
    ],
    "name:swe_x_preferred":[
        "Les Salles"
    ],
    "name:ukr_x_preferred":[
        "\u041b\u0435-\u0421\u0430\u043b\u044c"
    ],
    "name:uzb_x_preferred":[
        "Les Salles"
    ],
    "name:vie_x_preferred":[
        "Les Salles"
    ],
    "name:vol_x_preferred":[
        "Les Salles"
    ],
    "name:war_x_preferred":[
        "Les Salles"
    ],
    "name:zho_x_preferred":[
        "\u83b1\u8428\u52d2"
    ],
    "wof:name":"Les Salles",
    "wof:placetype":"locality"
},
  "geometry": {"coordinates":[3.6751,45.29488],"type":"Point"}
}