{
  "type": "Feature",
  "properties": {
    "gn:admin1_code":"84",
    "gn:admin2_code":"43",
    "gn:admin3_code":"431",
    "gn:admin4_code":"43237",
    "gn:asciiname":"Les Salles",
    "gn:country_code":"FR",
    "gn:dem":968,
    "gn:feature_class":"P",
    "gn:feature_code":"PPL",
    "gn:name":"Les Salles",
    "gn:population":0,
    "gn:timezone":"Europe/Paris",
    "iso:country":"FR",
    "wof:name":"Les Salles",
    "wof:placetype":"locality"
},
  "geometry": {"coordinates":[3.6751,45.29488],"type":"Point"}
}