{
  "type": "Feature",
  "properties": {
    "iso:country":"FR",
    "name:cat_x_preferred":[
        "Petit-Montrouge"
    ],
    "name:ces_x_preferred":[
        "Quartier du Petit-Montrouge"
    ],
    "name:deu_x_preferred":[
        "Petit-Montrouge"
    ],
    "name:eng_x_preferred":[
        "Petit-Montrouge"
    ],
    "name:eus_x_preferred":[
        "Petit-Montrouge"
    ],
    "name:fra_x_preferred":[
        "Quartier du Petit-Montrouge"
    ],
    "name:fra_x_variant":[
        "Petit-Montrouge"
    ],
    "name:ltz_x_preferred":[
        "Petit-Montrouge"
    ],
    "name:nld_x_preferred":[
        "Petit-Montrouge"
    ],
    "name:slk_x_preferred":[
        "Quartier du Petit-Montrouge"
    ],
    "wd:wordcount":956,
    "wof:name":"Petit-Montrouge",
    "wof:placetype":"neighbourhood"
},
  "geometry": {"coordinates":[2.326435,48.825973],"type":"Point"}
}