{
  "type": "Feature",
  "properties": {
    "gn:admin1_code":"53",
    "gn:admin2_code":"35",
    "gn:admin3_code":"352",
    "gn:admin4_code":"35294",
    "gn:asciiname":"La Couplais",
    "gn:country_code":"FR",
    "gn:dem":29,
    "gn:feature_class":"P",
    "gn:feature_code":"PPL",
    "gn:name":"La Couplais",
    "gn:population":0,
    "gn:timezone":"Europe/Paris",
    "iso:country":"FR",
    "wof:name":"La Couplais",
    "wof:placetype":"locality"
},
  "geometry": {"coordinates":[-1.99363,47.70332],"type":"Point"}
}