{
  "type": "Feature",
  "properties": {
    "gn:admin1_code":"94",
    "gn:admin2_code":"2A",
    "gn:admin3_code":"2A4",
    "gn:admin4_code":"2A247",
    "gn:asciiname":"Piccovaggia",
    "gn:country_code":"FR",
    "gn:dem":32,
    "gn:feature_class":"P",
    "gn:feature_code":"PPL",
    "gn:name":"Piccovaggia",
    "gn:population":0,
    "gn:timezone":"Europe/Paris",
    "iso:country":"FR",
    "wof:name":"Piccovaggia",
    "wof:placetype":"locality"
},
  "geometry": {"coordinates":[9.34032,41.58155],"type":"Point"}
}