{
  "type": "Feature",
  "properties": {
    "gn:admin1_code":"84",
    "gn:admin2_code":"73",
    "gn:admin3_code":"732",
    "gn:admin4_code":"73324",
    "gn:asciiname":"La Batie",
    "gn:country_code":"FR",
    "gn:dem":545,
    "gn:feature_class":"P",
    "gn:feature_code":"PPL",
    "gn:name":"La B\u00e2tie",
    "gn:population":0,
    "gn:timezone":"Europe/Paris",
    "iso:country":"FR",
    "name:und_x_variant":[
        "La Bathie",
        "La B\u00e2tie"
    ],
    "wof:name":"La Batie",
    "wof:placetype":"locality"
},
  "geometry": {"coordinates":[6.07999,45.46716],"type":"Point"}
}