{
  "type": "Feature",
  "properties": {
    "gn:admin1_code":"24",
    "gn:admin2_code":"18",
    "gn:admin3_code":"183",
    "gn:admin4_code":"18279.0",
    "gn:asciiname":"Vierzon-Bourgneuf",
    "gn:country_code":"FR",
    "gn:dem":122,
    "gn:feature_class":"P",
    "gn:feature_code":"PPL",
    "gn:name":"Vierzon-Bourgneuf",
    "gn:population":0,
    "gn:timezone":"Europe/Paris",
    "iso:country":"FR",
    "wof:name":"Vierzon-Bourgneuf",
    "wof:placetype":"locality"
},
  "geometry": {"coordinates":[2.06419,47.22485],"type":"Point"}
}