{
  "type": "Feature",
  "properties": {
    "gn:admin1_code":"75",
    "gn:admin2_code":"24",
    "gn:admin3_code":"241",
    "gn:admin4_code":"24338",
    "gn:asciiname":"Vicq",
    "gn:country_code":"FR",
    "gn:dem":193,
    "gn:feature_class":"P",
    "gn:feature_code":"PPL",
    "gn:name":"Vicq",
    "gn:population":0,
    "gn:timezone":"Europe/Paris",
    "iso:country":"FR",
    "wof:name":"Vicq",
    "wof:placetype":"locality"
},
  "geometry": {"coordinates":[0.74621,44.89875],"type":"Point"}
}