{
  "type": "Feature",
  "properties": {
    "gn:admin1_code":"76",
    "gn:admin2_code":"65",
    "gn:admin3_code":"652",
    "gn:admin4_code":"65157",
    "gn:asciiname":"Ens",
    "gn:country_code":"FR",
    "gn:dem":1197,
    "gn:feature_class":"P",
    "gn:feature_code":"PPL",
    "gn:name":"Ens",
    "gn:population":16,
    "gn:timezone":"Europe/Paris",
    "iso:country":"FR",
    "name:arg_x_preferred":[
        "Ens"
    ],
    "name:ceb_x_preferred":[
        "Ens"
    ],
    "name:nld_x_preferred":[
        "Ens"
    ],
    "name:pol_x_preferred":[
        "Ens"
    ],
    "name:por_x_preferred":[
        "Ens"
    ],
    "name:swe_x_preferred":[
        "Ens"
    ],
    "wof:name":"Ens",
    "wof:placetype":"locality",
    "wof:population":16
},
  "geometry": {"coordinates":[0.34075,42.80686],"type":"Point"}
}