{
  "type": "Feature",
  "properties": {
    "frgov:code_epci":"246500573",
    "frgov:insee_arr":"2",
    "frgov:insee_com":"65157",
    "frgov:insee_dep":"65",
    "frgov:insee_reg":"76",
    "frgov:nom_com":"Ens",
    "frgov:nom_com_m":"ENS",
    "frgov:nom_dep":"HAUTES-PYRENEES",
    "frgov:nom_reg":"OCCITANIE",
    "frgov:statut":"Commune simple",
    "gn:admin1_code":"76",
    "gn:admin2_code":"65",
    "gn:admin3_code":"652",
    "gn:admin4_code":"65157",
    "gn:asciiname":"Ens",
    "gn:country_code":"FR",
    "gn:dem":1197,
    "gn:feature_class":"P",
    "gn:feature_code":"PPL",
    "gn:name":"Ens",
    "gn:population":16,
    "gn:timezone":"Europe/Paris",
    "iso:country":"FR",
    "name:arg_x_preferred":[
        "Ens"
    ],
    "name:ceb_x_preferred":[
        "Ens"
    ],
    "name:fra_x_preferred":[
        "Ens"
    ],
    "name:nld_x_preferred":[
        "Ens"
    ],
    "name:pol_x_preferred":[
        "Ens"
    ],
    "name:por_x_preferred":[
        "Ens"
    ],
    "name:rus_x_preferred":[
        "\u0410\u043d"
    ],
    "name:swe_x_preferred":[
        "Ens"
    ],
    "name:ukr_x_preferred":[
        "\u0410\u043d"
    ],
    "name:zho_x_preferred":[
        "\u6602\u9547"
    ],
    "qs:a0":"France",
    "qs:a1":"HAUTES-PYRENEES",
    "qs:a1_lc":"65",
    "qs:a1r":"MIDI-PYRENEES",
    "qs:a1r_lc":"73",
    "qs:a2_lc":"26",
    "qs:a2r_lc":"2",
    "qs:adm0":"France",
    "qs:adm0_a3":"FRA",
    "qs:la":"ENS",
    "qs:la_lc":"65157",
    "qs:level":"localadmin",
    "qs:type":"Commune simple",
    "wof:coterminous":[
        404386503
    ],
    "wof:name":"Ens",
    "wof:placetype":"locality",
    "wof:placetype_local":"Commune simple",
    "wof:population":16
},
  "geometry": {"coordinates":[0.34075,42.80686],"type":"Point"}
}