{
  "type": "Feature",
  "properties": {
    "gn:admin1_code":"52",
    "gn:admin2_code":"44",
    "gn:admin3_code":"441",
    "gn:admin4_code":"44205",
    "gn:asciiname":"Les Masures",
    "gn:country_code":"FR",
    "gn:dem":19,
    "gn:feature_class":"P",
    "gn:feature_code":"PPL",
    "gn:name":"Les Masures",
    "gn:population":0,
    "gn:timezone":"Europe/Paris",
    "iso:country":"FR",
    "name:und_x_variant":[
        "Les Mazures",
        "Les Masures"
    ],
    "wof:name":"Les Masures",
    "wof:placetype":"locality"
},
  "geometry": {"coordinates":[-1.41857,47.43357],"type":"Point"}
}