{
  "type": "Feature",
  "properties": {
    "gn:admin1_code":"84",
    "gn:admin2_code":"43",
    "gn:admin3_code":"432",
    "gn:admin4_code":"43168",
    "gn:asciiname":"Freycenet",
    "gn:country_code":"FR",
    "gn:dem":1094,
    "gn:feature_class":"P",
    "gn:feature_code":"PPL",
    "gn:name":"Freycenet",
    "gn:population":0,
    "gn:timezone":"Europe/Paris",
    "iso:country":"FR",
    "wof:name":"Freycenet",
    "wof:placetype":"locality"
},
  "geometry": {"coordinates":[3.91639,44.82767],"type":"Point"}
}