{
  "type": "Feature",
  "properties": {
    "gn:admin1_code":"75",
    "gn:admin2_code":"33",
    "gn:admin3_code":"334",
    "gn:admin4_code":"33146",
    "gn:asciiname":"Martins",
    "gn:country_code":"FR",
    "gn:dem":7,
    "gn:feature_class":"P",
    "gn:feature_code":"PPL",
    "gn:name":"Martins",
    "gn:population":0,
    "gn:timezone":"Europe/Paris",
    "iso:country":"FR",
    "name:ceb_x_preferred":[
        "Martins"
    ],
    "name:deu_x_preferred":[
        "Martins"
    ],
    "name:fas_x_preferred":[
        "\u0645\u0627\u0631\u062a\u06cc\u0646\u0633"
    ],
    "name:fin_x_preferred":[
        "Martins"
    ],
    "name:fra_x_preferred":[
        "Martins"
    ],
    "name:ita_x_preferred":[
        "Martins"
    ],
    "name:lav_x_preferred":[
        "Martins"
    ],
    "name:por_x_preferred":[
        "Martins"
    ],
    "name:rus_x_preferred":[
        "\u041c\u0430\u0440\u0442\u0438\u043d\u0448"
    ],
    "name:swe_x_preferred":[
        "Martins"
    ],
    "name:ukr_x_preferred":[
        "\u041c\u0430\u0440\u0442\u0456\u043d\u0448"
    ],
    "wof:name":"Martins",
    "wof:placetype":"locality"
},
  "geometry": {"coordinates":[-0.72291,45.1033],"type":"Point"}
}