{
  "type": "Feature",
  "properties": {
    "gn:admin1_code":"84",
    "gn:admin2_code":"43",
    "gn:admin3_code":"432",
    "gn:admin4_code":"43233",
    "gn:asciiname":"Vourzac",
    "gn:country_code":"FR",
    "gn:dem":843,
    "gn:feature_class":"P",
    "gn:feature_code":"PPL",
    "gn:name":"Vourzac",
    "gn:population":0,
    "gn:timezone":"Europe/Paris",
    "iso:country":"FR",
    "wof:name":"Vourzac",
    "wof:placetype":"locality"
},
  "geometry": {"coordinates":[3.80218,45.03764],"type":"Point"}
}