{
  "type": "Feature",
  "properties": {
    "gn:admin1_code":"84",
    "gn:admin2_code":"43",
    "gn:admin3_code":"433",
    "gn:admin4_code":"43163",
    "gn:asciiname":"Clavas",
    "gn:country_code":"FR",
    "gn:dem":1094,
    "gn:feature_class":"P",
    "gn:feature_code":"PPL",
    "gn:name":"Clavas",
    "gn:population":0,
    "gn:timezone":"Europe/Paris",
    "iso:country":"FR",
    "wof:name":"Clavas",
    "wof:placetype":"locality"
},
  "geometry": {"coordinates":[4.46714,45.22171],"type":"Point"}
}