{
  "type": "Feature",
  "properties": {
    "gn:admin1_code":"76",
    "gn:admin2_code":"12",
    "gn:admin3_code":"122",
    "gn:admin4_code":"12254",
    "gn:asciiname":"Solsac",
    "gn:country_code":"FR",
    "gn:dem":501,
    "gn:feature_class":"P",
    "gn:feature_code":"PPL",
    "gn:name":"Solsac",
    "gn:population":0,
    "gn:timezone":"Europe/Paris",
    "iso:country":"FR",
    "wof:name":"Solsac",
    "wof:placetype":"locality"
},
  "geometry": {"coordinates":[2.5079,44.47777],"type":"Point"}
}