{
  "type": "Feature",
  "properties": {
    "gn:admin1_code":"53",
    "gn:admin2_code":"29",
    "gn:admin3_code":"293",
    "gn:admin4_code":"29202",
    "gn:asciiname":"Le Mengleuz",
    "gn:country_code":"FR",
    "gn:dem":258,
    "gn:feature_class":"P",
    "gn:feature_code":"PPL",
    "gn:name":"Le Mengleuz",
    "gn:population":0,
    "gn:timezone":"Europe/Paris",
    "iso:country":"FR",
    "wof:name":"Le Mengleuz",
    "wof:placetype":"locality"
},
  "geometry": {"coordinates":[-3.85366,48.455],"type":"Point"}
}