{
  "type": "Feature",
  "properties": {
    "gn:admin1_code":"24",
    "gn:admin2_code":"18",
    "gn:admin3_code":"181",
    "gn:admin4_code":"18271",
    "gn:asciiname":"La Breuille",
    "gn:country_code":"FR",
    "gn:dem":169,
    "gn:feature_class":"P",
    "gn:feature_code":"PPL",
    "gn:name":"La Breuille",
    "gn:population":0,
    "gn:timezone":"Europe/Paris",
    "iso:country":"FR",
    "wof:name":"La Breuille",
    "wof:placetype":"locality"
},
  "geometry": {"coordinates":[2.40543,47.16286],"type":"Point"}
}