{
  "type": "Feature",
  "properties": {
    "gn:admin1_code":"75",
    "gn:admin2_code":"87",
    "gn:admin3_code":"872",
    "gn:admin4_code":"87117",
    "gn:asciiname":"Champseau",
    "gn:country_code":"FR",
    "gn:dem":411,
    "gn:feature_class":"P",
    "gn:feature_code":"PPL",
    "gn:name":"Champseau",
    "gn:population":0,
    "gn:timezone":"Europe/Paris",
    "iso:country":"FR",
    "wof:name":"Champseau",
    "wof:placetype":"locality"
},
  "geometry": {"coordinates":[1.76667,45.83333],"type":"Point"}
}