{
  "type": "Feature",
  "properties": {
    "gn:admin1_code":"75",
    "gn:admin2_code":"23",
    "gn:admin3_code":"231",
    "gn:admin4_code":"23178",
    "gn:asciiname":"Noudiere",
    "gn:country_code":"FR",
    "gn:dem":774,
    "gn:feature_class":"P",
    "gn:feature_code":"PPL",
    "gn:name":"Noudi\u00e8re",
    "gn:population":0,
    "gn:timezone":"Europe/Paris",
    "iso:country":"FR",
    "wof:name":"Noudiere",
    "wof:placetype":"locality"
},
  "geometry": {"coordinates":[2.34426,45.786],"type":"Point"}
}