{
  "type": "Feature",
  "properties": {
    "gn:admin1_code":"24",
    "gn:admin2_code":"28",
    "gn:admin3_code":"281",
    "gn:admin4_code":"28196",
    "gn:asciiname":"Le Petit Grande Bois",
    "gn:country_code":"FR",
    "gn:dem":193,
    "gn:feature_class":"P",
    "gn:feature_code":"PPL",
    "gn:name":"Le Petit Grande Bois",
    "gn:population":0,
    "gn:timezone":"Europe/Paris",
    "iso:country":"FR",
    "wof:name":"Le Petit Grande Bois",
    "wof:placetype":"locality"
},
  "geometry": {"coordinates":[1.16664,48.30735],"type":"Point"}
}