{
  "type": "Feature",
  "properties": {
    "gn:admin1_code":"53",
    "gn:admin2_code":"29",
    "gn:admin3_code":"292",
    "gn:admin4_code":"29018",
    "gn:asciiname":"Plouenez",
    "gn:country_code":"FR",
    "gn:dem":223,
    "gn:feature_class":"P",
    "gn:feature_code":"PPL",
    "gn:name":"Plou\u00e9nez",
    "gn:population":0,
    "gn:timezone":"Europe/Paris",
    "iso:country":"FR",
    "wof:name":"Plouenez",
    "wof:placetype":"locality"
},
  "geometry": {"coordinates":[-3.81667,48.35],"type":"Point"}
}