{
  "type": "Feature",
  "properties": {
    "gn:admin1_code":"76",
    "gn:admin2_code":"30",
    "gn:admin3_code":"303",
    "gn:admin4_code":"30198",
    "gn:asciiname":"Saint-Marcel-de-Fontfouillouse",
    "gn:country_code":"FR",
    "gn:dem":574,
    "gn:feature_class":"P",
    "gn:feature_code":"PPL",
    "gn:name":"Saint-Marcel-de-Fontfouillouse",
    "gn:population":0,
    "gn:timezone":"Europe/Paris",
    "iso:country":"FR",
    "name:und_x_variant":[
        "Saint-Marcel-de Fonsfouillouse",
        "Saint-Marcel-de-Fontfouillouse"
    ],
    "wof:name":"Saint-Marcel-de-Fontfouillouse",
    "wof:placetype":"locality"
},
  "geometry": {"coordinates":[3.71139,44.12515],"type":"Point"}
}