{
  "type": "Feature",
  "properties": {
    "gn:admin1_code":"24",
    "gn:admin2_code":"28",
    "gn:admin3_code":"283",
    "gn:admin4_code":"28231.0",
    "gn:asciiname":"Montmureau",
    "gn:country_code":"FR",
    "gn:dem":197,
    "gn:feature_class":"P",
    "gn:feature_code":"PPL",
    "gn:name":"Montmureau",
    "gn:population":0,
    "gn:timezone":"Europe/Paris",
    "iso:country":"FR",
    "wof:name":"Montmureau",
    "wof:placetype":"locality"
},
  "geometry": {"coordinates":[0.99289,48.64794000000001],"type":"Point"}
}