{
  "type": "Feature",
  "properties": {
    "gn:admin1_code":"11",
    "gn:admin2_code":"77",
    "gn:admin3_code":"774",
    "gn:admin4_code":"77011",
    "gn:asciiname":"Busseau",
    "gn:country_code":"FR",
    "gn:dem":104,
    "gn:feature_class":"P",
    "gn:feature_code":"PPL",
    "gn:name":"Busseau",
    "gn:population":0,
    "gn:timezone":"Europe/Paris",
    "iso:country":"FR",
    "wof:name":"Busseau",
    "wof:placetype":"locality"
},
  "geometry": {"coordinates":[2.59146,48.18853],"type":"Point"}
}