{
  "type": "Feature",
  "properties": {
    "gn:admin1_code":"28",
    "gn:admin2_code":"61",
    "gn:admin3_code":"613",
    "gn:admin4_code":"61061",
    "gn:asciiname":"La Fosse",
    "gn:country_code":"FR",
    "gn:dem":201,
    "gn:feature_class":"P",
    "gn:feature_code":"PPL",
    "gn:name":"La Fosse",
    "gn:population":0,
    "gn:timezone":"Europe/Paris",
    "iso:country":"FR",
    "wof:name":"La Fosse",
    "wof:placetype":"locality"
},
  "geometry": {"coordinates":[0.92175,48.42577],"type":"Point"}
}