{
  "type": "Feature",
  "properties": {
    "iso:country":"FR",
    "name:ceb_x_preferred":[
        "Jonzac-Neulles"
    ],
    "name:eng_x_preferred":[
        "Jonzac - Neulles Airport"
    ],
    "name:msa_x_preferred":[
        "Lapangan Terbang Neulles"
    ],
    "oa:elevation_ft":"128",
    "oa:type":"small_airport",
    "woe:hierarchy":{
        "country_id":23424819,
        "county_id":12597189,
        "localadmin_id":12663069,
        "planet_id":1,
        "state_id":7153327
    },
    "wof:name":"A\u00e9rodrome de Jonzac-neuilles",
    "wof:placetype":"campus"
},
  "geometry": {"coordinates":[-0.42306,45.4831],"type":"Point"}
}