{
  "type": "Feature",
  "properties": {
    "gn:admin1_code":"84",
    "gn:admin2_code":"73",
    "gn:admin3_code":"732",
    "gn:admin4_code":"73316",
    "gn:asciiname":"Le Mollaret",
    "gn:country_code":"FR",
    "gn:dem":319,
    "gn:feature_class":"P",
    "gn:feature_code":"PPL",
    "gn:name":"Le Mollaret",
    "gn:population":0,
    "gn:timezone":"Europe/Paris",
    "iso:country":"FR",
    "wof:name":"Le Mollaret",
    "wof:placetype":"locality"
},
  "geometry": {"coordinates":[6.14063,45.48872],"type":"Point"}
}