{
  "type": "Feature",
  "properties": {
    "gn:country":"FR",
    "gn:fcode":"PPL",
    "gn:population":0,
    "iso:country":"FR",
    "name:bug_x_preferred":[
        "La Grave"
    ],
    "name:cat_x_preferred":[
        "La Grava"
    ],
    "name:ceb_x_preferred":[
        "La Grave"
    ],
    "name:deu_x_preferred":[
        "La Grave"
    ],
    "name:eus_x_preferred":[
        "La Grave"
    ],
    "name:fas_x_preferred":[
        "\u0644\u0627 \u06af\u0631\u0627\u0648"
    ],
    "name:fin_x_preferred":[
        "La Grave"
    ],
    "name:fra_x_preferred":[
        "La Grave"
    ],
    "name:hun_x_preferred":[
        "La Grave"
    ],
    "name:ita_x_preferred":[
        "La Grave"
    ],
    "name:lat_x_preferred":[
        "La Grave"
    ],
    "name:lmo_x_preferred":[
        "La Grave"
    ],
    "name:ltz_x_preferred":[
        "La Grave"
    ],
    "name:msa_x_preferred":[
        "La Grave"
    ],
    "name:nld_x_preferred":[
        "La Grave"
    ],
    "name:oci_x_preferred":[
        "La Grava"
    ],
    "name:pms_x_preferred":[
        "La Grave"
    ],
    "name:pol_x_preferred":[
        "La Grave"
    ],
    "name:por_x_preferred":[
        "La Grave"
    ],
    "name:ron_x_preferred":[
        "La Grave"
    ],
    "name:rus_x_preferred":[
        "\u041b\u0430-\u0413\u0440\u0430\u0432"
    ],
    "name:slk_x_preferred":[
        "La Grave"
    ],
    "name:slv_x_preferred":[
        "La Grave"
    ],
    "name:spa_x_preferred":[
        "La Grave"
    ],
    "name:sqi_x_preferred":[
        "La Grave"
    ],
    "name:swe_x_preferred":[
        "La Grave"
    ],
    "name:ukr_x_preferred":[
        "\u041b\u0430-\u0413\u0440\u0430\u0432"
    ],
    "name:und_x_variant":[
        "Grave-de-Peille"
    ],
    "name:urd_x_preferred":[
        "\u0644\u0627 \u06af\u0631\u0627\u0648\u06cc"
    ],
    "name:vie_x_preferred":[
        "La Grave"
    ],
    "name:vol_x_preferred":[
        "La Grave"
    ],
    "name:war_x_preferred":[
        "La Grave"
    ],
    "name:zho_x_preferred":[
        "\u62c9\u683c\u62c9\u592b"
    ],
    "qs_pg:aaroncc":"FR",
    "qs_pg:gn_country":"FR",
    "qs_pg:gn_fcode":"PPL",
    "qs_pg:gn_pop":0,
    "qs_pg:name":"La Grave",
    "qs_pg:name_adm0":"France",
    "qs_pg:name_adm1":"Provence-Alpes-C\u00f4te d'Azur",
    "qs_pg:photos":44,
    "qs_pg:photos_1k":9,
    "qs_pg:photos_9k":1,
    "qs_pg:photos_9r":2,
    "qs_pg:photos_all":44,
    "qs_pg:photos_sr":2,
    "qs_pg:pop_sr":0,
    "qs_pg:qs_pg_placetype":"locality",
    "qs_pg:qs_pg_placetype_gp":"Town",
    "qs_pg:woe_adm0":23424819,
    "woe:adm0_id":23424819,
    "woe:name_adm0":"France",
    "woe:name_adm1":"Provence-Alpes-C\u00f4te d'Azur",
    "woe:placetype":"Town",
    "wof:name":"La Grave",
    "wof:placetype":"neighbourhood"
},
  "geometry": {"coordinates":[7.37835,43.7934],"type":"Point"}
}