{
  "type": "Feature",
  "properties": {
    "gn:admin1_code":"75",
    "gn:admin2_code":"79",
    "gn:admin3_code":"793",
    "gn:admin4_code":"79260",
    "gn:asciiname":"Douron",
    "gn:country_code":"FR",
    "gn:dem":121,
    "gn:feature_class":"P",
    "gn:feature_code":"PPL",
    "gn:name":"Douron",
    "gn:population":0,
    "gn:timezone":"Europe/Paris",
    "iso:country":"FR",
    "wof:name":"Douron",
    "wof:placetype":"locality"
},
  "geometry": {"coordinates":[-0.08192,46.85565],"type":"Point"}
}