{
  "type": "Feature",
  "properties": {
    "gn:admin1_code":"11",
    "gn:admin2_code":"77",
    "gn:admin3_code":"774",
    "gn:admin4_code":"77016",
    "gn:asciiname":"Glandelles",
    "gn:country_code":"FR",
    "gn:dem":68,
    "gn:feature_class":"P",
    "gn:feature_code":"PPL",
    "gn:name":"Glandelles",
    "gn:population":0,
    "gn:timezone":"Europe/Paris",
    "iso:country":"FR",
    "wof:name":"Glandelles",
    "wof:placetype":"locality"
},
  "geometry": {"coordinates":[2.7152,48.21383],"type":"Point"}
}