{
  "type": "Feature",
  "properties": {
    "gn:admin1_code":"44",
    "gn:admin2_code":"08",
    "gn:admin3_code":"081",
    "gn:admin4_code":"08105",
    "gn:asciiname":"Etion",
    "gn:country_code":"FR",
    "gn:dem":186,
    "gn:feature_class":"P",
    "gn:feature_code":"PPL",
    "gn:name":"\u00c9tion",
    "gn:population":0,
    "gn:timezone":"Europe/Paris",
    "iso:country":"FR",
    "wof:name":"Etion",
    "wof:placetype":"locality"
},
  "geometry": {"coordinates":[4.69317,49.78761],"type":"Point"}
}