{
  "type": "Feature",
  "properties": {
    "gn:admin1_code":"75",
    "gn:admin2_code":"16",
    "gn:admin3_code":"163",
    "gn:admin4_code":"16173",
    "gn:asciiname":"Juille",
    "gn:country_code":"FR",
    "gn:dem":87,
    "gn:feature_class":"P",
    "gn:feature_code":"PPL",
    "gn:name":"Juill\u00e9",
    "gn:population":0,
    "gn:timezone":"Europe/Paris",
    "iso:country":"FR",
    "name:und_x_variant":[
        "Juill\u00e9"
    ],
    "wof:name":"Juille",
    "wof:placetype":"locality"
},
  "geometry": {"coordinates":[0.14388,45.92972],"type":"Point"}
}