{
  "type": "Feature",
  "properties": {
    "gn:admin1_code":"75",
    "gn:admin2_code":"16",
    "gn:admin3_code":"161",
    "gn:admin4_code":"16223",
    "gn:asciiname":"Chez Vincent",
    "gn:country_code":"FR",
    "gn:dem":197,
    "gn:feature_class":"P",
    "gn:feature_code":"PPL",
    "gn:name":"Chez Vincent",
    "gn:population":0,
    "gn:timezone":"Europe/Paris",
    "iso:country":"FR",
    "wof:name":"Chez Vincent",
    "wof:placetype":"locality"
},
  "geometry": {"coordinates":[0.50262,45.6269],"type":"Point"}
}