{
  "type": "Feature",
  "properties": {
    "gn:admin1_code":"93",
    "gn:admin2_code":"05",
    "gn:admin3_code":"052",
    "gn:admin4_code":"05061",
    "gn:asciiname":"Les Fauvins",
    "gn:country_code":"FR",
    "gn:dem":780,
    "gn:feature_class":"P",
    "gn:feature_code":"PPL",
    "gn:name":"Les Fauvins",
    "gn:population":0,
    "gn:timezone":"Europe/Paris",
    "iso:country":"FR",
    "wof:name":"Les Fauvins",
    "wof:placetype":"locality"
},
  "geometry": {"coordinates":[6.11412,44.56257],"type":"Point"}
}