{
  "type": "Feature",
  "properties": {
    "gn:admin1_code":"84",
    "gn:admin2_code":"74",
    "gn:admin3_code":"744",
    "gn:admin4_code":"74218",
    "gn:asciiname":"Amphion-les-Bains",
    "gn:country_code":"FR",
    "gn:dem":376,
    "gn:feature_class":"P",
    "gn:feature_code":"PPL",
    "gn:name":"Amphion-les-Bains",
    "gn:population":0,
    "gn:timezone":"Europe/Paris",
    "iso:country":"FR",
    "wof:name":"Amphion-les-Bains",
    "wof:placetype":"locality"
},
  "geometry": {"coordinates":[6.52931,46.39679],"type":"Point"}
}