{
  "type": "Feature",
  "properties": {
    "gn:admin1_code":"84",
    "gn:admin2_code":"73",
    "gn:admin3_code":"731",
    "gn:admin4_code":"73206",
    "gn:asciiname":"Les Granges",
    "gn:country_code":"FR",
    "gn:dem":1445,
    "gn:feature_class":"P",
    "gn:feature_code":"PPL",
    "gn:name":"Les Granges",
    "gn:population":0,
    "gn:timezone":"Europe/Paris",
    "iso:country":"FR",
    "name:cat_x_preferred":[
        "Les Granges"
    ],
    "name:ceb_x_preferred":[
        "Les Granges"
    ],
    "name:eus_x_preferred":[
        "Les Granges"
    ],
    "name:fra_x_preferred":[
        "Les Granges"
    ],
    "name:hun_x_preferred":[
        "Les Granges"
    ],
    "name:hye_x_preferred":[
        "\u053c\u0565 \u0533\u0580\u0561\u0576\u056a"
    ],
    "name:ita_x_preferred":[
        "Les Granges"
    ],
    "name:lat_x_preferred":[
        "Les Granges"
    ],
    "name:msa_x_preferred":[
        "Les Granges"
    ],
    "name:nld_x_preferred":[
        "Les Granges"
    ],
    "name:oci_x_preferred":[
        "Les Granges"
    ],
    "name:pms_x_preferred":[
        "Les Granges"
    ],
    "name:pol_x_preferred":[
        "Les Granges"
    ],
    "name:por_x_preferred":[
        "Les Granges"
    ],
    "name:ron_x_preferred":[
        "Les Granges"
    ],
    "name:rus_x_preferred":[
        "\u041b\u0435-\u0413\u0440\u0430\u043d\u0436"
    ],
    "name:slk_x_preferred":[
        "Les Granges"
    ],
    "name:spa_x_preferred":[
        "Les Granges"
    ],
    "name:swe_x_preferred":[
        "Les Granges"
    ],
    "name:ukr_x_preferred":[
        "\u041b\u0435-\u0413\u0440\u0430\u043d\u0436"
    ],
    "name:vie_x_preferred":[
        "Les Granges"
    ],
    "name:vol_x_preferred":[
        "Les Granges"
    ],
    "name:war_x_preferred":[
        "Les Granges"
    ],
    "name:zho_x_preferred":[
        "\u96f7\u683c\u6717\u65e5"
    ],
    "wof:name":"Les Granges",
    "wof:placetype":"locality"
},
  "geometry": {"coordinates":[6.71639,45.39041],"type":"Point"}
}