{
  "type": "Feature",
  "properties": {
    "gn:admin1_code":"84",
    "gn:admin2_code":"73",
    "gn:admin3_code":"731",
    "gn:admin4_code":"73206",
    "gn:asciiname":"Les Granges",
    "gn:country_code":"FR",
    "gn:dem":1445,
    "gn:feature_class":"P",
    "gn:feature_code":"PPL",
    "gn:name":"Les Granges",
    "gn:population":0,
    "gn:timezone":"Europe/Paris",
    "iso:country":"FR",
    "wof:name":"Les Granges",
    "wof:placetype":"locality"
},
  "geometry": {"coordinates":[6.71639,45.39041],"type":"Point"}
}