{
  "type": "Feature",
  "properties": {
    "gn:admin1_code":"53",
    "gn:admin2_code":"56",
    "gn:admin3_code":"563",
    "gn:admin4_code":"56033",
    "gn:asciiname":"Vieux Bourg",
    "gn:country_code":"FR",
    "gn:dem":50,
    "gn:feature_class":"P",
    "gn:feature_code":"PPL",
    "gn:name":"Vieux Bourg",
    "gn:population":0,
    "gn:timezone":"Europe/Paris",
    "iso:country":"FR",
    "name:und_x_variant":[
        "Tr\u00e9al",
        "Vieux Bourg"
    ],
    "wof:name":"Vieux Bourg",
    "wof:placetype":"locality"
},
  "geometry": {"coordinates":[-2.20785,47.84472],"type":"Point"}
}