{
  "type": "Feature",
  "properties": {
    "gn:admin1_code":"53",
    "gn:admin2_code":"29",
    "gn:admin3_code":"294",
    "gn:admin4_code":"29046",
    "gn:asciiname":"Lesperbe",
    "gn:country_code":"FR",
    "gn:dem":50,
    "gn:feature_class":"P",
    "gn:feature_code":"PPL",
    "gn:name":"Lesperb\u00e9",
    "gn:population":0,
    "gn:timezone":"Europe/Paris",
    "iso:country":"FR",
    "wof:name":"Lesperbe",
    "wof:placetype":"locality"
},
  "geometry": {"coordinates":[-4.31036,48.05885],"type":"Point"}
}