{
  "type": "Feature",
  "properties": {
    "frgov:code_epci":"200067031",
    "frgov:insee_arr":"3",
    "frgov:insee_com":"50182",
    "frgov:insee_dep":"50",
    "frgov:insee_reg":"28",
    "frgov:nom_com":"La Feuillie",
    "frgov:nom_com_m":"LA FEUILLIE",
    "frgov:nom_dep":"MANCHE",
    "frgov:nom_reg":"NORMANDIE",
    "frgov:statut":"Commune simple",
    "gn:admin1_code":"28",
    "gn:admin2_code":"50",
    "gn:admin3_code":"503",
    "gn:admin4_code":"50182",
    "gn:asciiname":"La Feuillie",
    "gn:country_code":"FR",
    "gn:dem":21,
    "gn:feature_class":"P",
    "gn:feature_code":"PPL",
    "gn:name":"La Feuillie",
    "gn:population":267,
    "gn:timezone":"Europe/Paris",
    "iso:country":"FR",
    "name:ceb_x_preferred":[
        "La Feuillie"
    ],
    "name:deu_x_preferred":[
        "La Feuillie"
    ],
    "name:fra_x_preferred":[
        "La Feuillie"
    ],
    "name:ita_x_preferred":[
        "La Feuillie"
    ],
    "name:kaz_x_preferred":[
        "\u041b\u0430-\u0424\u0435\u0438"
    ],
    "name:nds_x_preferred":[
        "La Feuillie"
    ],
    "name:nld_x_preferred":[
        "La Feuillie"
    ],
    "name:pms_x_preferred":[
        "La Feuillie"
    ],
    "name:pol_x_preferred":[
        "La Feuillie"
    ],
    "name:por_x_preferred":[
        "La Feuillie"
    ],
    "name:scn_x_preferred":[
        "La Feuillie"
    ],
    "name:slk_x_preferred":[
        "La Feuillie"
    ],
    "name:spa_x_preferred":[
        "La Feuillie"
    ],
    "name:swe_x_preferred":[
        "La Feuillie"
    ],
    "name:ukr_x_preferred":[
        "\u041b\u0430-\u0424\u0435\u0457"
    ],
    "name:urd_x_preferred":[
        "\u0644\u0627 \u0641\u06cc\u0648\u06cc\u0644\u06cc\u060c \u0645\u0627\u0646\u0634\u06cc"
    ],
    "name:zho_x_preferred":[
        "\u62c9\u5f17\u4f0a\u5229\u8036"
    ],
    "qs:a0":"France",
    "qs:a1":"MANCHE",
    "qs:a1_lc":"50",
    "qs:a1r":"BASSE-NORMANDIE",
    "qs:a1r_lc":"25",
    "qs:a2_lc":"20",
    "qs:a2r_lc":"3",
    "qs:adm0":"France",
    "qs:adm0_a3":"FRA",
    "qs:la":"LA FEUILLIE",
    "qs:la_lc":"50182",
    "qs:level":"localadmin",
    "qs:type":"Commune simple",
    "wof:coterminous":[
        404391929
    ],
    "wof:name":"La Feuillie",
    "wof:placetype":"locality",
    "wof:placetype_local":"Commune simple",
    "wof:population":267
},
  "geometry": {"coordinates":[-1.47845,49.17666],"type":"Point"}
}