{
  "type": "Feature",
  "properties": {
    "gn:admin1_code":"28",
    "gn:admin2_code":"50",
    "gn:admin3_code":"503",
    "gn:admin4_code":"50182",
    "gn:asciiname":"La Feuillie",
    "gn:country_code":"FR",
    "gn:dem":21,
    "gn:feature_class":"P",
    "gn:feature_code":"PPL",
    "gn:name":"La Feuillie",
    "gn:population":267,
    "gn:timezone":"Europe/Paris",
    "iso:country":"FR",
    "wof:name":"La Feuillie",
    "wof:placetype":"locality",
    "wof:population":267
},
  "geometry": {"coordinates":[-1.47845,49.17666],"type":"Point"}
}