{
  "type": "Feature",
  "properties": {
    "gn:admin1_code":"28",
    "gn:admin2_code":"50",
    "gn:admin3_code":"503",
    "gn:admin4_code":"50182",
    "gn:asciiname":"La Feuillie",
    "gn:country_code":"FR",
    "gn:dem":21,
    "gn:feature_class":"P",
    "gn:feature_code":"PPL",
    "gn:name":"La Feuillie",
    "gn:population":267,
    "gn:timezone":"Europe/Paris",
    "iso:country":"FR",
    "name:ceb_x_preferred":[
        "La Feuillie"
    ],
    "name:deu_x_preferred":[
        "La Feuillie"
    ],
    "name:fra_x_preferred":[
        "La Feuillie"
    ],
    "name:ita_x_preferred":[
        "La Feuillie"
    ],
    "name:nds_x_preferred":[
        "La Feuillie"
    ],
    "name:nld_x_preferred":[
        "La Feuillie"
    ],
    "name:pms_x_preferred":[
        "La Feuillie"
    ],
    "name:pol_x_preferred":[
        "La Feuillie"
    ],
    "name:por_x_preferred":[
        "La Feuillie"
    ],
    "name:scn_x_preferred":[
        "La Feuillie"
    ],
    "name:slk_x_preferred":[
        "La Feuillie"
    ],
    "name:spa_x_preferred":[
        "La Feuillie"
    ],
    "name:swe_x_preferred":[
        "La Feuillie"
    ],
    "name:ukr_x_preferred":[
        "\u041b\u0430-\u0424\u0435\u0457"
    ],
    "wof:name":"La Feuillie",
    "wof:placetype":"locality",
    "wof:population":267
},
  "geometry": {"coordinates":[-1.47845,49.17666],"type":"Point"}
}