{
  "type": "Feature",
  "properties": {
    "gn:gn_country":"FR",
    "gn:gn_fcode":"PPL",
    "gn:gn_pop":273,
    "gn:population":273,
    "iso:country":"FR",
    "name:unk_x_variant":[
        "Beauvoir"
    ],
    "qs_pg:aaroncc":"FR",
    "qs_pg:gn_country":"FR",
    "qs_pg:gn_fcode":"PPL",
    "qs_pg:gn_pop":273,
    "qs_pg:name":"Beauvoir-sur-Sarce",
    "qs_pg:name_adm0":"France",
    "qs_pg:name_adm1":"Champagne-Ardenne",
    "qs_pg:photos_9r":0,
    "qs_pg:photos_sr":0,
    "qs_pg:pop_sr":2,
    "qs_pg:qs_pg_placetype":"locality",
    "qs_pg:qs_pg_placetype_gp":"Town",
    "qs_pg:woe_adm0":23424819,
    "woe:adm0_id":23424819,
    "woe:name_adm0":"France",
    "woe:name_adm1":"Champagne-Ardenne",
    "woe:placetype":"Town",
    "wof:name":"Beauvoir-sur-Sarce",
    "wof:placetype":"neighbourhood",
    "wof:population":273
},
  "geometry": {"coordinates":[4.29681,47.96586],"type":"Point"}
}