{
  "type": "Feature",
  "properties": {
    "gn:admin1_code":"11",
    "gn:admin2_code":"77",
    "gn:admin3_code":"772",
    "gn:admin4_code":"77381",
    "gn:asciiname":"La Fermete",
    "gn:country_code":"FR",
    "gn:dem":111,
    "gn:feature_class":"P",
    "gn:feature_code":"PPL",
    "gn:name":"La Fermet\u00e9",
    "gn:population":0,
    "gn:timezone":"Europe/Paris",
    "iso:country":"FR",
    "wof:name":"La Fermete",
    "wof:placetype":"locality"
},
  "geometry": {"coordinates":[2.94823,48.6208],"type":"Point"}
}