{
  "type": "Feature",
  "properties": {
    "gn:admin1_code":"27",
    "gn:admin2_code":"58",
    "gn:admin3_code":"582",
    "gn:admin4_code":"58109",
    "gn:asciiname":"Chateau-du-Bois",
    "gn:country_code":"FR",
    "gn:dem":242,
    "gn:feature_class":"P",
    "gn:feature_code":"PPL",
    "gn:name":"Ch\u00e2teau-du-Bois",
    "gn:population":0,
    "gn:timezone":"Europe/Paris",
    "iso:country":"FR",
    "wof:name":"Chateau-du-Bois",
    "wof:placetype":"locality"
},
  "geometry": {"coordinates":[3.31286,47.47834],"type":"Point"}
}