{
  "type": "Feature",
  "properties": {
    "gn:admin1_code":"76",
    "gn:admin2_code":"46",
    "gn:admin3_code":"462",
    "gn:admin4_code":"46102",
    "gn:asciiname":"Arelies",
    "gn:cc2":"FR",
    "gn:country_code":"FR",
    "gn:dem":325,
    "gn:feature_class":"P",
    "gn:feature_code":"PPL",
    "gn:name":"Arelies",
    "gn:population":0,
    "gn:timezone":"Europe/Paris",
    "iso:country":"FR",
    "name:und_x_variant":[
        "Arelles",
        "Arelies"
    ],
    "wof:name":"Arelies",
    "wof:placetype":"locality"
},
  "geometry": {"coordinates":[2.01667,44.58333],"type":"Point"}
}