{
  "type": "Feature",
  "properties": {
    "iso:country":"FR",
    "wof:name":"Le Busca",
    "wof:placetype":"neighbourhood"
},
  "geometry": {"coordinates":[1.45151969907922,43.59028028482116],"type":"Point"}
}