{
  "type": "Feature",
  "properties": {
    "gn:admin1_code":"93",
    "gn:admin2_code":"04",
    "gn:admin3_code":"044",
    "gn:admin4_code":"04013",
    "gn:asciiname":"Le Forest",
    "gn:country_code":"FR",
    "gn:dem":505,
    "gn:feature_class":"P",
    "gn:feature_code":"PPL",
    "gn:name":"Le Forest",
    "gn:population":0,
    "gn:timezone":"Europe/Paris",
    "iso:country":"FR",
    "name:und_x_variant":[
        "La Forest",
        "La For\u00eat",
        "Le Forest"
    ],
    "wof:name":"Le Forest",
    "wof:placetype":"locality"
},
  "geometry": {"coordinates":[5.95541,44.12085],"type":"Point"}
}