{
  "type": "Feature",
  "properties": {
    "iso:country":"FR",
    "name:eng_x_preferred":[
        "Quartier de Plaisance"
    ],
    "name:fra_x_preferred":[
        "Quartier de Plaisance"
    ],
    "wof:name":"Quartier de Plaisance",
    "wof:placetype":"neighbourhood"
},
  "geometry": {"coordinates":[2.31626646600854,48.83073722266589],"type":"Point"}
}