{
  "type": "Feature",
  "properties": {
    "gn:admin1_code":"76",
    "gn:admin2_code":"46",
    "gn:admin3_code":"462",
    "gn:admin4_code":"46163",
    "gn:asciiname":"Le Sol",
    "gn:country_code":"FR",
    "gn:dem":286,
    "gn:feature_class":"P",
    "gn:feature_code":"PPL",
    "gn:name":"Le Sol",
    "gn:population":0,
    "gn:timezone":"Europe/Paris",
    "iso:country":"FR",
    "wof:name":"Le Sol",
    "wof:placetype":"locality"
},
  "geometry": {"coordinates":[1.94151,44.94875],"type":"Point"}
}