{
  "type": "Feature",
  "properties": {
    "gn:admin1_code":"84",
    "gn:admin2_code":"74",
    "gn:admin3_code":"743",
    "gn:admin4_code":"74040",
    "gn:asciiname":"Loex",
    "gn:country_code":"FR",
    "gn:dem":517,
    "gn:feature_class":"P",
    "gn:feature_code":"PPL",
    "gn:name":"Lo\u00ebx",
    "gn:population":0,
    "gn:timezone":"Europe/Paris",
    "iso:country":"FR",
    "wof:name":"Loex",
    "wof:placetype":"locality"
},
  "geometry": {"coordinates":[6.30615,46.16675],"type":"Point"}
}