{
  "type": "Feature",
  "properties": {
    "iso:country":"FR",
    "name:fra_x_preferred":[
        "Ainay"
    ],
    "wof:name":"Ainay",
    "wof:placetype":"neighbourhood"
},
  "geometry": {"coordinates":[4.82846681938147,45.7529291351409],"type":"Point"}
}