{
  "type": "Feature",
  "properties": {
    "gn:admin1_code":"76",
    "gn:admin2_code":"12",
    "gn:admin3_code":"122",
    "gn:admin4_code":"12187",
    "gn:asciiname":"Born",
    "gn:country_code":"FR",
    "gn:dem":1036,
    "gn:feature_class":"P",
    "gn:feature_code":"PPL",
    "gn:name":"Born",
    "gn:population":0,
    "gn:timezone":"Europe/Paris",
    "iso:country":"FR",
    "wof:name":"Born",
    "wof:placetype":"locality"
},
  "geometry": {"coordinates":[2.99205,44.54872],"type":"Point"}
}