{
  "type": "Feature",
  "properties": {
    "gn:admin1_code":"76",
    "gn:admin2_code":"12",
    "gn:admin3_code":"122",
    "gn:admin4_code":"12187",
    "gn:asciiname":"Born",
    "gn:country_code":"FR",
    "gn:dem":1036,
    "gn:feature_class":"P",
    "gn:feature_code":"PPL",
    "gn:name":"Born",
    "gn:population":0,
    "gn:timezone":"Europe/Paris",
    "iso:country":"FR",
    "name:cat_x_preferred":[
        "Born"
    ],
    "name:ceb_x_preferred":[
        "Born"
    ],
    "name:ces_x_preferred":[
        "Born"
    ],
    "name:deu_x_preferred":[
        "Born"
    ],
    "name:fin_x_preferred":[
        "Born"
    ],
    "name:fra_x_preferred":[
        "Born"
    ],
    "name:ita_x_preferred":[
        "Born"
    ],
    "name:lim_x_preferred":[
        "Born"
    ],
    "name:nds_x_preferred":[
        "Born"
    ],
    "name:nld_x_preferred":[
        "Born"
    ],
    "name:pol_x_preferred":[
        "Born"
    ],
    "name:rus_x_preferred":[
        "\u0411\u043e\u0440\u043d"
    ],
    "name:scn_x_preferred":[
        "Born"
    ],
    "name:srp_x_preferred":[
        "\u0411\u043e\u0440\u043d"
    ],
    "name:swe_x_preferred":[
        "Born"
    ],
    "name:ukr_x_preferred":[
        "\u0411\u043e\u0440\u043d"
    ],
    "wof:name":"Born",
    "wof:placetype":"locality"
},
  "geometry": {"coordinates":[2.99205,44.54872],"type":"Point"}
}