{
  "type": "Feature",
  "properties": {
    "gn:admin1_code":"75",
    "gn:admin2_code":"86",
    "gn:admin3_code":"863",
    "gn:admin4_code":"86031",
    "gn:asciiname":"Les Bouneaux",
    "gn:country_code":"FR",
    "gn:dem":62,
    "gn:feature_class":"P",
    "gn:feature_code":"PPL",
    "gn:name":"Les Bouneaux",
    "gn:population":0,
    "gn:timezone":"Europe/Paris",
    "iso:country":"FR",
    "wof:name":"Les Bouneaux",
    "wof:placetype":"locality"
},
  "geometry": {"coordinates":[0.60007,46.60866],"type":"Point"}
}