{
  "type": "Feature",
  "properties": {
    "gn:admin1_code":"44",
    "gn:admin2_code":"52",
    "gn:admin3_code":"522",
    "gn:admin4_code":"52242",
    "gn:asciiname":"Haute-Amance",
    "gn:country_code":"FR",
    "gn:dem":280,
    "gn:feature_class":"P",
    "gn:feature_code":"PPL",
    "gn:name":"Haute-Amance",
    "gn:population":994,
    "gn:timezone":"Europe/Paris",
    "iso:country":"FR",
    "name:und_x_variant":[
        "Hortes"
    ],
    "wof:name":"Haute-Amance",
    "wof:placetype":"locality",
    "wof:population":994
},
  "geometry": {"coordinates":[5.55,47.83333],"type":"Point"}
}