{
  "type": "Feature",
  "properties": {
    "gn:admin1_code":"44",
    "gn:admin2_code":"52",
    "gn:admin3_code":"522",
    "gn:admin4_code":"52242",
    "gn:asciiname":"Haute-Amance",
    "gn:country_code":"FR",
    "gn:dem":280,
    "gn:feature_class":"P",
    "gn:feature_code":"PPL",
    "gn:name":"Haute-Amance",
    "gn:population":994,
    "gn:timezone":"Europe/Paris",
    "iso:country":"FR",
    "name:bug_x_preferred":[
        "Haute-Amance"
    ],
    "name:cat_x_preferred":[
        "Haute-Amance"
    ],
    "name:ceb_x_preferred":[
        "Haute-Amance"
    ],
    "name:deu_x_preferred":[
        "Haute-Amance"
    ],
    "name:eus_x_preferred":[
        "Haute-Amance"
    ],
    "name:fra_x_preferred":[
        "Haute-Amance"
    ],
    "name:hun_x_preferred":[
        "Haute-Amance"
    ],
    "name:ind_x_preferred":[
        "Haute-Amance"
    ],
    "name:ita_x_preferred":[
        "Haute-Amance"
    ],
    "name:lat_x_preferred":[
        "Haute-Amance"
    ],
    "name:mlg_x_preferred":[
        "Haute-Amance"
    ],
    "name:msa_x_preferred":[
        "Haute-Amance"
    ],
    "name:nld_x_preferred":[
        "Haute-Amance"
    ],
    "name:oci_x_preferred":[
        "Haute-Amance"
    ],
    "name:pms_x_preferred":[
        "Haute-Amance"
    ],
    "name:pol_x_preferred":[
        "Haute-Amance"
    ],
    "name:por_x_preferred":[
        "Haute-Amance"
    ],
    "name:ron_x_preferred":[
        "Haute-Amance"
    ],
    "name:slk_x_preferred":[
        "Haute-Amance"
    ],
    "name:spa_x_preferred":[
        "Haute-Amance"
    ],
    "name:srp_x_preferred":[
        "\u041e\u0442 \u0410\u043c\u0430\u043d\u0441"
    ],
    "name:swe_x_preferred":[
        "Haute-Amance"
    ],
    "name:ukr_x_preferred":[
        "\u041e\u0442-\u0410\u043c\u0430\u043d\u0441"
    ],
    "name:und_x_variant":[
        "Hortes"
    ],
    "name:vie_x_preferred":[
        "Haute-Amance"
    ],
    "name:vol_x_preferred":[
        "Haute-Amance"
    ],
    "name:war_x_preferred":[
        "Haute-Amance"
    ],
    "name:zho_x_preferred":[
        "\u5965\u7279\u963f\u8292\u514b"
    ],
    "wof:name":"Haute-Amance",
    "wof:placetype":"locality",
    "wof:population":994
},
  "geometry": {"coordinates":[5.55,47.83333],"type":"Point"}
}