{
  "type": "Feature",
  "properties": {
    "gn:admin1_code":"11",
    "gn:admin2_code":"91",
    "gn:admin3_code":"913",
    "gn:admin4_code":"91560.0",
    "gn:asciiname":"Villeziers",
    "gn:country_code":"FR",
    "gn:dem":153,
    "gn:feature_class":"P",
    "gn:feature_code":"PPL",
    "gn:name":"Villeziers",
    "gn:population":0,
    "gn:timezone":"Europe/Paris",
    "iso:country":"FR",
    "wof:name":"Villeziers",
    "wof:placetype":"locality"
},
  "geometry": {"coordinates":[2.1704,48.67325],"type":"Point"}
}