{
  "type": "Feature",
  "properties": {
    "gn:admin1_code":"84",
    "gn:admin2_code":"03",
    "gn:admin3_code":"032",
    "gn:admin4_code":"3238.0",
    "gn:asciiname":"Les Carterons",
    "gn:country_code":"FR",
    "gn:dem":373,
    "gn:feature_class":"P",
    "gn:feature_code":"PPL",
    "gn:name":"Les Carterons",
    "gn:population":0,
    "gn:timezone":"Europe/Paris",
    "iso:country":"FR",
    "wof:name":"Les Carterons",
    "wof:placetype":"locality"
},
  "geometry": {"coordinates":[3.01429,46.47028],"type":"Point"}
}