{
  "type": "Feature",
  "properties": {
    "frgov:code_epci":"200067429",
    "frgov:insee_arr":"2",
    "frgov:insee_com":"58090",
    "frgov:insee_dep":"58",
    "frgov:insee_reg":"27",
    "frgov:nom_com":"Courcelles",
    "frgov:nom_com_m":"COURCELLES",
    "frgov:nom_dep":"NIEVRE",
    "frgov:nom_reg":"BOURGOGNE-FRANCHE-COMTE",
    "frgov:statut":"Commune simple",
    "gn:admin1_code":"27",
    "gn:admin2_code":"58",
    "gn:admin3_code":"582",
    "gn:admin4_code":"58090",
    "gn:asciiname":"Courcelles",
    "gn:country_code":"FR",
    "gn:dem":196,
    "gn:feature_class":"P",
    "gn:feature_code":"PPL",
    "gn:name":"Courcelles",
    "gn:population":0,
    "gn:timezone":"Europe/Paris",
    "iso:country":"FR",
    "name:cat_x_preferred":[
        "Courcelles"
    ],
    "name:ceb_x_preferred":[
        "Courcelles"
    ],
    "name:ces_x_preferred":[
        "Courcelles"
    ],
    "name:deu_x_preferred":[
        "Courcelles"
    ],
    "name:epo_x_preferred":[
        "Courcelles"
    ],
    "name:fra_x_preferred":[
        "Courcelles"
    ],
    "name:ita_x_preferred":[
        "Courcelles"
    ],
    "name:nds_x_preferred":[
        "Courcelles"
    ],
    "name:nld_x_preferred":[
        "Courcelles"
    ],
    "name:pms_x_preferred":[
        "Courcelles"
    ],
    "name:pol_x_preferred":[
        "Courcelles"
    ],
    "name:por_x_preferred":[
        "Courcelles"
    ],
    "name:rus_x_preferred":[
        "\u041a\u0443\u0440\u0441\u0435\u043b\u044c"
    ],
    "name:slk_x_preferred":[
        "Courcelles"
    ],
    "name:spa_x_preferred":[
        "Courcelles"
    ],
    "name:swe_x_preferred":[
        "Courcelles"
    ],
    "name:ukr_x_preferred":[
        "\u041a\u0443\u0440\u0441\u0435\u043b\u044c"
    ],
    "qs:a0":"France",
    "qs:a1":"NIEVRE",
    "qs:a1_lc":"58",
    "qs:a1r":"BOURGOGNE",
    "qs:a1r_lc":"26",
    "qs:a2_lc":"25",
    "qs:a2r_lc":"2",
    "qs:adm0":"France",
    "qs:adm0_a3":"FRA",
    "qs:la":"COURCELLES",
    "qs:la_lc":"58090",
    "qs:level":"localadmin",
    "qs:type":"Commune simple",
    "wof:coterminous":[
        404387785
    ],
    "wof:name":"Courcelles",
    "wof:placetype":"locality",
    "wof:placetype_local":"Commune simple"
},
  "geometry": {"coordinates":[3.39914,47.39667],"type":"Point"}
}