{
  "type": "Feature",
  "properties": {
    "gn:admin1_code":"27",
    "gn:admin2_code":"58",
    "gn:admin3_code":"582",
    "gn:admin4_code":"58090",
    "gn:asciiname":"Courcelles",
    "gn:country_code":"FR",
    "gn:dem":196,
    "gn:feature_class":"P",
    "gn:feature_code":"PPL",
    "gn:name":"Courcelles",
    "gn:population":0,
    "gn:timezone":"Europe/Paris",
    "iso:country":"FR",
    "name:cat_x_preferred":[
        "Courcelles"
    ],
    "name:ceb_x_preferred":[
        "Courcelles"
    ],
    "name:ces_x_preferred":[
        "Courcelles"
    ],
    "name:deu_x_preferred":[
        "Courcelles"
    ],
    "name:epo_x_preferred":[
        "Courcelles"
    ],
    "name:fra_x_preferred":[
        "Courcelles"
    ],
    "name:ita_x_preferred":[
        "Courcelles"
    ],
    "name:nds_x_preferred":[
        "Courcelles"
    ],
    "name:nld_x_preferred":[
        "Courcelles"
    ],
    "name:pms_x_preferred":[
        "Courcelles"
    ],
    "name:pol_x_preferred":[
        "Courcelles"
    ],
    "name:por_x_preferred":[
        "Courcelles"
    ],
    "name:rus_x_preferred":[
        "\u041a\u0443\u0440\u0441\u0435\u043b\u044c"
    ],
    "name:slk_x_preferred":[
        "Courcelles"
    ],
    "name:spa_x_preferred":[
        "Courcelles"
    ],
    "name:swe_x_preferred":[
        "Courcelles"
    ],
    "name:ukr_x_preferred":[
        "\u041a\u0443\u0440\u0441\u0435\u043b\u044c"
    ],
    "wof:name":"Courcelles",
    "wof:placetype":"locality"
},
  "geometry": {"coordinates":[3.39914,47.39667],"type":"Point"}
}