{
  "type": "Feature",
  "properties": {
    "gn:admin1_code":"44",
    "gn:admin2_code":"08",
    "gn:admin3_code":"084",
    "gn:admin4_code":"08351",
    "gn:asciiname":"Quilly",
    "gn:country_code":"FR",
    "gn:dem":107,
    "gn:feature_class":"P",
    "gn:feature_code":"PPL",
    "gn:name":"Quilly",
    "gn:population":65,
    "gn:timezone":"Europe/Paris",
    "iso:country":"FR",
    "name:bre_x_preferred":[
        "Quilly"
    ],
    "name:ceb_x_preferred":[
        "Quilly"
    ],
    "name:deu_x_preferred":[
        "Quilly"
    ],
    "name:fra_x_preferred":[
        "Quilly"
    ],
    "name:ita_x_preferred":[
        "Quilly"
    ],
    "name:ltz_x_preferred":[
        "Quilly"
    ],
    "name:nds_x_preferred":[
        "Quilly"
    ],
    "name:nld_x_preferred":[
        "Quilly"
    ],
    "name:pms_x_preferred":[
        "Quilly"
    ],
    "name:pol_x_preferred":[
        "Quilly"
    ],
    "name:por_x_preferred":[
        "Quilly"
    ],
    "name:rus_x_preferred":[
        "\u041a\u0438\u0439\u0438"
    ],
    "name:slk_x_preferred":[
        "Quilly"
    ],
    "name:spa_x_preferred":[
        "Quilly"
    ],
    "name:sqi_x_preferred":[
        "Quilly"
    ],
    "name:swe_x_preferred":[
        "Quilly"
    ],
    "name:ukr_x_preferred":[
        "\u041a\u0456\u0457"
    ],
    "wof:name":"Quilly",
    "wof:placetype":"locality",
    "wof:population":65
},
  "geometry": {"coordinates":[4.59931,49.40766],"type":"Point"}
}