{
  "type": "Feature",
  "properties": {
    "frgov:code_epci":"240800920",
    "frgov:insee_arr":"4",
    "frgov:insee_com":"08351",
    "frgov:insee_dep":"08",
    "frgov:insee_reg":"44",
    "frgov:nom_com":"Quilly",
    "frgov:nom_com_m":"QUILLY",
    "frgov:nom_dep":"ARDENNES",
    "frgov:nom_reg":"GRAND EST",
    "frgov:statut":"Commune simple",
    "gn:admin1_code":"44",
    "gn:admin2_code":"08",
    "gn:admin3_code":"084",
    "gn:admin4_code":"08351",
    "gn:asciiname":"Quilly",
    "gn:country_code":"FR",
    "gn:dem":107,
    "gn:feature_class":"P",
    "gn:feature_code":"PPL",
    "gn:name":"Quilly",
    "gn:population":65,
    "gn:timezone":"Europe/Paris",
    "iso:country":"FR",
    "name:bre_x_preferred":[
        "Quilly"
    ],
    "name:ceb_x_preferred":[
        "Quilly"
    ],
    "name:deu_x_preferred":[
        "Quilly"
    ],
    "name:fra_x_preferred":[
        "Quilly"
    ],
    "name:ita_x_preferred":[
        "Quilly"
    ],
    "name:ltz_x_preferred":[
        "Quilly"
    ],
    "name:nds_x_preferred":[
        "Quilly"
    ],
    "name:nld_x_preferred":[
        "Quilly"
    ],
    "name:pms_x_preferred":[
        "Quilly"
    ],
    "name:pol_x_preferred":[
        "Quilly"
    ],
    "name:por_x_preferred":[
        "Quilly"
    ],
    "name:rus_x_preferred":[
        "\u041a\u0438\u0439\u0438"
    ],
    "name:slk_x_preferred":[
        "Quilly"
    ],
    "name:spa_x_preferred":[
        "Quilly"
    ],
    "name:sqi_x_preferred":[
        "Quilly"
    ],
    "name:swe_x_preferred":[
        "Quilly"
    ],
    "name:ukr_x_preferred":[
        "\u041a\u0456\u0457"
    ],
    "qs:a0":"France",
    "qs:a1":"ARDENNES",
    "qs:a1_lc":"08",
    "qs:a1r":"CHAMPAGNE-ARDENNE",
    "qs:a1r_lc":"21",
    "qs:a2_lc":"14",
    "qs:a2r_lc":"4",
    "qs:adm0":"France",
    "qs:adm0_a3":"FRA",
    "qs:la":"QUILLY",
    "qs:la_lc":"08351",
    "qs:level":"localadmin",
    "qs:type":"Commune simple",
    "wof:coterminous":[
        404385169
    ],
    "wof:name":"Quilly",
    "wof:placetype":"locality",
    "wof:placetype_local":"Commune simple",
    "wof:population":65
},
  "geometry": {"coordinates":[4.59931,49.40766],"type":"Point"}
}