{
  "type": "Feature",
  "properties": {
    "gn:admin1_code":"44",
    "gn:admin2_code":"08",
    "gn:admin3_code":"084",
    "gn:admin4_code":"08351",
    "gn:asciiname":"Quilly",
    "gn:country_code":"FR",
    "gn:dem":107,
    "gn:feature_class":"P",
    "gn:feature_code":"PPL",
    "gn:name":"Quilly",
    "gn:population":65,
    "gn:timezone":"Europe/Paris",
    "iso:country":"FR",
    "wof:name":"Quilly",
    "wof:placetype":"locality",
    "wof:population":65
},
  "geometry": {"coordinates":[4.59931,49.40766],"type":"Point"}
}