{
  "type": "Feature",
  "properties": {
    "gn:admin1_code":"75",
    "gn:admin2_code":"23",
    "gn:admin3_code":"231",
    "gn:admin4_code":"23221",
    "gn:asciiname":"Les Massoneches",
    "gn:country_code":"FR",
    "gn:dem":755,
    "gn:feature_class":"P",
    "gn:feature_code":"PPL",
    "gn:name":"Les Masson\u00e8ches",
    "gn:population":0,
    "gn:timezone":"Europe/Paris",
    "iso:country":"FR",
    "wof:name":"Les Massoneches",
    "wof:placetype":"locality"
},
  "geometry": {"coordinates":[2.45313,45.75051],"type":"Point"}
}