{
  "type": "Feature",
  "properties": {
    "gn:admin1_code":"28",
    "gn:admin2_code":"76",
    "gn:admin3_code":"763",
    "gn:admin4_code":"76123",
    "gn:asciiname":"La Haie-Gonnor",
    "gn:country_code":"FR",
    "gn:dem":174,
    "gn:feature_class":"P",
    "gn:feature_code":"PPL",
    "gn:name":"La Haie-Gonnor",
    "gn:population":0,
    "gn:timezone":"Europe/Paris",
    "iso:country":"FR",
    "wof:name":"La Haie-Gonnor",
    "wof:placetype":"locality"
},
  "geometry": {"coordinates":[1.13899,49.53306],"type":"Point"}
}