{
  "type": "Feature",
  "properties": {
    "gn:admin1_code":"84",
    "gn:admin2_code":"03",
    "gn:admin3_code":"031",
    "gn:admin4_code":"03315",
    "gn:asciiname":"Neuville",
    "gn:country_code":"FR",
    "gn:dem":240,
    "gn:feature_class":"P",
    "gn:feature_code":"PPL",
    "gn:name":"Neuville",
    "gn:population":0,
    "gn:timezone":"Europe/Paris",
    "iso:country":"FR",
    "wof:name":"Neuville",
    "wof:placetype":"locality"
},
  "geometry": {"coordinates":[2.8261,46.41857],"type":"Point"}
}