{
  "type": "Feature",
  "properties": {
    "gn:admin1_code":"84",
    "gn:admin2_code":"03",
    "gn:admin3_code":"031",
    "gn:admin4_code":"03315",
    "gn:asciiname":"Neuville",
    "gn:country_code":"FR",
    "gn:dem":240,
    "gn:feature_class":"P",
    "gn:feature_code":"PPL",
    "gn:name":"Neuville",
    "gn:population":0,
    "gn:timezone":"Europe/Paris",
    "iso:country":"FR",
    "name:bre_x_preferred":[
        "Neuville"
    ],
    "name:cat_x_preferred":[
        "Neuville"
    ],
    "name:ceb_x_preferred":[
        "Neuville"
    ],
    "name:deu_x_preferred":[
        "Neuville"
    ],
    "name:fas_x_preferred":[
        "\u0646\u0648\u0648\u06cc\u0644"
    ],
    "name:fra_x_preferred":[
        "Neuville"
    ],
    "name:ita_x_preferred":[
        "Neuville"
    ],
    "name:nds_x_preferred":[
        "Neuville"
    ],
    "name:nld_x_preferred":[
        "Neuville"
    ],
    "name:pms_x_preferred":[
        "Neuville"
    ],
    "name:pol_x_preferred":[
        "Neuville"
    ],
    "name:por_x_preferred":[
        "Neuville"
    ],
    "name:rus_x_preferred":[
        "\u041d\u0451\u0432\u0438\u043b\u044c"
    ],
    "name:slk_x_preferred":[
        "Neuville"
    ],
    "name:spa_x_preferred":[
        "Neuville"
    ],
    "name:sqi_x_preferred":[
        "Neuville"
    ],
    "name:swe_x_preferred":[
        "Neuville"
    ],
    "name:ukr_x_preferred":[
        "\u041d\u0435\u0432\u0456\u043b\u044c"
    ],
    "wof:name":"Neuville",
    "wof:placetype":"locality"
},
  "geometry": {"coordinates":[2.8261,46.41857],"type":"Point"}
}