{
  "type": "Feature",
  "properties": {
    "gn:admin1_code":"27",
    "gn:admin2_code":"70",
    "gn:admin3_code":"702",
    "gn:admin4_code":"70197",
    "gn:asciiname":"Trevey",
    "gn:country_code":"FR",
    "gn:dem":290,
    "gn:feature_class":"P",
    "gn:feature_code":"PPL",
    "gn:name":"Trevey",
    "gn:population":0,
    "gn:timezone":"Europe/Paris",
    "iso:country":"FR",
    "wof:name":"Trevey",
    "wof:placetype":"locality"
},
  "geometry": {"coordinates":[6.25319,47.51714000000001],"type":"Point"}
}