{
  "type": "Feature",
  "properties": {
    "frgov:code_epci":"200029734",
    "frgov:insee_arr":"2",
    "frgov:insee_com":"16357",
    "frgov:insee_dep":"16",
    "frgov:insee_reg":"75",
    "frgov:nom_com":"Saint-Vallier",
    "frgov:nom_com_m":"SAINT-VALLIER",
    "frgov:nom_dep":"CHARENTE",
    "frgov:nom_reg":"NOUVELLE-AQUITAINE",
    "frgov:statut":"Commune simple",
    "gn:admin1_code":"75",
    "gn:admin2_code":"16",
    "gn:admin3_code":"162",
    "gn:admin4_code":"16357",
    "gn:asciiname":"Saint-Vallier",
    "gn:country_code":"FR",
    "gn:dem":123,
    "gn:feature_class":"P",
    "gn:feature_code":"PPL",
    "gn:name":"Saint-Vallier",
    "gn:population":170,
    "gn:timezone":"Europe/Paris",
    "iso:country":"FR",
    "name:cat_x_preferred":[
        "Saint-Vallier"
    ],
    "name:ceb_x_preferred":[
        "Saint-Vallier"
    ],
    "name:deu_x_preferred":[
        "Saint-Vallier"
    ],
    "name:fra_x_preferred":[
        "Saint-Vallier"
    ],
    "name:ita_x_preferred":[
        "Saint-Vallier"
    ],
    "name:nds_x_preferred":[
        "Saint-Vallier"
    ],
    "name:nld_x_preferred":[
        "Saint-Vallier"
    ],
    "name:pms_x_preferred":[
        "Saint-Vallier"
    ],
    "name:pol_x_preferred":[
        "Saint-Vallier"
    ],
    "name:por_x_preferred":[
        "Saint-Vallier"
    ],
    "name:rus_x_preferred":[
        "\u0421\u0435\u043d-\u0412\u0430\u043b\u044c\u0435"
    ],
    "name:scn_x_preferred":[
        "Saint-Vallier"
    ],
    "name:slk_x_preferred":[
        "Saint-Vallier"
    ],
    "name:spa_x_preferred":[
        "Saint-Vallier"
    ],
    "name:swe_x_preferred":[
        "Saint-Vallier"
    ],
    "name:ukr_x_preferred":[
        "\u0421\u0435\u043d-\u0412\u0430\u043b\u044c\u0454"
    ],
    "qs:a0":"France",
    "qs:a1":"CHARENTE",
    "qs:a1_lc":"16",
    "qs:a1r":"POITOU-CHARENTES",
    "qs:a1r_lc":"54",
    "qs:a2_lc":"08",
    "qs:a2r_lc":"2",
    "qs:adm0":"France",
    "qs:adm0_a3":"FRA",
    "qs:la":"SAINT-VALLIER",
    "qs:la_lc":"16357",
    "qs:level":"localadmin",
    "qs:type":"Commune simple",
    "wof:coterminous":[
        404356013
    ],
    "wof:name":"Saint-Vallier",
    "wof:placetype":"locality",
    "wof:placetype_local":"Commune simple",
    "wof:population":170
},
  "geometry": {"coordinates":[-0.05,45.3],"type":"Point"}
}