{
  "type": "Feature",
  "properties": {
    "gn:admin1_code":"11",
    "gn:admin2_code":"77",
    "gn:admin3_code":"773",
    "gn:admin4_code":"77031",
    "gn:asciiname":"Pompierre",
    "gn:country_code":"FR",
    "gn:dem":91,
    "gn:feature_class":"P",
    "gn:feature_code":"PPL",
    "gn:name":"Pompierre",
    "gn:population":0,
    "gn:timezone":"Europe/Paris",
    "iso:country":"FR",
    "name:bug_x_preferred":[
        "Pompierre"
    ],
    "name:cat_x_preferred":[
        "Pompierre"
    ],
    "name:ceb_x_preferred":[
        "Pompierre"
    ],
    "name:deu_x_preferred":[
        "Pompierre"
    ],
    "name:eus_x_preferred":[
        "Pompierre"
    ],
    "name:fra_x_preferred":[
        "Pompierre"
    ],
    "name:hun_x_preferred":[
        "Pompierre"
    ],
    "name:ind_x_preferred":[
        "Pompierre"
    ],
    "name:ita_x_preferred":[
        "Pompierre"
    ],
    "name:kaz_x_preferred":[
        "\u041f\u043e\u043c\u043f\u044c\u0435\u0440\u0440"
    ],
    "name:ltz_x_preferred":[
        "Pompierre"
    ],
    "name:mlg_x_preferred":[
        "Pompierre"
    ],
    "name:msa_x_preferred":[
        "Pompierre"
    ],
    "name:nld_x_preferred":[
        "Pompierre"
    ],
    "name:oci_x_preferred":[
        "Pompierre"
    ],
    "name:pol_x_preferred":[
        "Pompierre"
    ],
    "name:slk_x_preferred":[
        "Pompierre"
    ],
    "name:spa_x_preferred":[
        "Pompierre"
    ],
    "name:swe_x_preferred":[
        "Pompierre"
    ],
    "name:ukr_x_preferred":[
        "\u041f\u043e\u043c\u043f'\u0454\u0440\u0440"
    ],
    "name:uzb_x_preferred":[
        "Pompierre"
    ],
    "name:vie_x_preferred":[
        "Pompierre"
    ],
    "name:vol_x_preferred":[
        "Pompierre"
    ],
    "name:war_x_preferred":[
        "Pompierre"
    ],
    "name:zho_x_preferred":[
        "\u84ec\u76ae\u57c3\u5c14"
    ],
    "wof:name":"Pompierre",
    "wof:placetype":"locality"
},
  "geometry": {"coordinates":[2.92223,48.65848],"type":"Point"}
}