{
  "type": "Feature",
  "properties": {
    "gn:admin1_code":"27",
    "gn:admin2_code":"21",
    "gn:admin3_code":"212",
    "gn:admin4_code":"21158.0",
    "gn:asciiname":"Courchamp",
    "gn:country_code":"FR",
    "gn:dem":258,
    "gn:feature_class":"P",
    "gn:feature_code":"PPL",
    "gn:name":"Courchamp",
    "gn:population":0,
    "gn:timezone":"Europe/Paris",
    "iso:country":"FR",
    "wof:name":"Courchamp",
    "wof:placetype":"locality"
},
  "geometry": {"coordinates":[5.37417,47.59801],"type":"Point"}
}