{
  "type": "Feature",
  "properties": {
    "gn:admin1_code":"27",
    "gn:admin2_code":"21",
    "gn:admin3_code":"212",
    "gn:admin4_code":"21158.0",
    "gn:asciiname":"Courchamp",
    "gn:country_code":"FR",
    "gn:dem":258,
    "gn:feature_class":"P",
    "gn:feature_code":"PPL",
    "gn:name":"Courchamp",
    "gn:population":0,
    "gn:timezone":"Europe/Paris",
    "iso:country":"FR",
    "name:cat_x_preferred":[
        "Courchamp"
    ],
    "name:ceb_x_preferred":[
        "Courchamp"
    ],
    "name:deu_x_preferred":[
        "Courchamp"
    ],
    "name:eus_x_preferred":[
        "Courchamp"
    ],
    "name:fra_x_preferred":[
        "Courchamp"
    ],
    "name:hun_x_preferred":[
        "Courchamp"
    ],
    "name:ind_x_preferred":[
        "Courchamp"
    ],
    "name:ita_x_preferred":[
        "Courchamp"
    ],
    "name:kaz_x_preferred":[
        "\u041a\u0443\u0440\u0448\u0430\u043c"
    ],
    "name:lat_x_preferred":[
        "Courchamp"
    ],
    "name:msa_x_preferred":[
        "Courchamp"
    ],
    "name:nld_x_preferred":[
        "Courchamp"
    ],
    "name:oci_x_preferred":[
        "Courchamp"
    ],
    "name:pms_x_preferred":[
        "Courchamp"
    ],
    "name:pol_x_preferred":[
        "Courchamp"
    ],
    "name:por_x_preferred":[
        "Courchamp"
    ],
    "name:slk_x_preferred":[
        "Courchamp"
    ],
    "name:spa_x_preferred":[
        "Courchamp"
    ],
    "name:srp_x_preferred":[
        "\u041a\u0443\u0440\u0448\u0430\u043d"
    ],
    "name:swe_x_preferred":[
        "Courchamp"
    ],
    "name:ukr_x_preferred":[
        "\u041a\u0443\u0440\u0448\u0430\u043c"
    ],
    "name:vie_x_preferred":[
        "Courchamp"
    ],
    "name:vol_x_preferred":[
        "Courchamp"
    ],
    "name:war_x_preferred":[
        "Courchamp"
    ],
    "wof:name":"Courchamp",
    "wof:placetype":"locality"
},
  "geometry": {"coordinates":[5.37417,47.59801],"type":"Point"}
}