{
  "type": "Feature",
  "properties": {
    "iso:country":"FR",
    "name:eng_x_preferred":[
        "Cite Jardin"
    ],
    "name:fra_x_preferred":[
        "Cit\u00e9 Jardin"
    ],
    "name:fra_x_variant":[
        "Cit\u00e9-Jardin Haute"
    ],
    "wof:name":"Cite Jardin",
    "wof:placetype":"neighbourhood"
},
  "geometry": {"coordinates":[2.25929813783441,48.77551170189644],"type":"Point"}
}