{
  "type": "Feature",
  "properties": {
    "gn:admin1_code":"84",
    "gn:admin2_code":"43",
    "gn:admin3_code":"431",
    "gn:admin4_code":"43188",
    "gn:asciiname":"Saint-Georges-d'Aurac",
    "gn:country_code":"FR",
    "gn:dem":626,
    "gn:feature_class":"P",
    "gn:feature_code":"PPL",
    "gn:name":"Saint-Georges-d\u2019Aurac",
    "gn:population":0,
    "gn:timezone":"Europe/Paris",
    "iso:country":"FR",
    "name:bug_x_preferred":[
        "Saint-Georges-d'Aurac"
    ],
    "name:ceb_x_preferred":[
        "Saint-Georges-d'Aurac"
    ],
    "name:deu_x_preferred":[
        "Saint-Georges-d\u2019Aurac"
    ],
    "name:eus_x_preferred":[
        "Saint-Georges-d'Aurac"
    ],
    "name:fra_x_preferred":[
        "Saint-Georges-d'Aurac"
    ],
    "name:hun_x_preferred":[
        "Saint-Georges-d\u2019Aurac"
    ],
    "name:ita_x_preferred":[
        "Saint-Georges-d'Aurac"
    ],
    "name:kaz_x_preferred":[
        "\u0421\u0435\u043d-\u0416\u043e\u0440\u0436-\u0434'\u041e\u0440\u0430\u043a"
    ],
    "name:lat_x_preferred":[
        "Saint-Georges-d'Aurac"
    ],
    "name:ltz_x_preferred":[
        "Saint-Georges-d'Aurac"
    ],
    "name:msa_x_preferred":[
        "Saint-Georges-d'Aurac"
    ],
    "name:nld_x_preferred":[
        "Saint-Georges-d'Aurac"
    ],
    "name:pms_x_preferred":[
        "Saint-Georges-d'Aurac"
    ],
    "name:pol_x_preferred":[
        "Saint-Georges-d\u2019Aurac"
    ],
    "name:por_x_preferred":[
        "Saint-Georges-d'Aurac"
    ],
    "name:ron_x_preferred":[
        "Saint-Georges-d'Aurac"
    ],
    "name:slk_x_preferred":[
        "Saint-Georges-d\u2019Aurac"
    ],
    "name:spa_x_preferred":[
        "Saint-Georges-d'Aurac"
    ],
    "name:swe_x_preferred":[
        "Saint-Georges-d'Aurac"
    ],
    "name:ukr_x_preferred":[
        "\u0421\u0435\u043d-\u0416\u043e\u0440\u0436-\u0434'\u041e\u0440\u0430\u043a"
    ],
    "name:und_x_variant":[
        "Saint-Georges"
    ],
    "name:urd_x_preferred":[
        "\u0633\u06cc\u0646\u0679-\u06af\u06cc\u0648\u0631\u06af\u0633-\u062f\u0648\u0631\u06a9"
    ],
    "name:uzb_x_preferred":[
        "Saint-Georges-d'Aurac"
    ],
    "name:vie_x_preferred":[
        "Saint-Georges-d'Aurac"
    ],
    "name:vol_x_preferred":[
        "Saint-Georges-d'Aurac"
    ],
    "name:war_x_preferred":[
        "Saint-Georges-d'Aurac"
    ],
    "name:zho_x_preferred":[
        "\u5723\u4e54\u6cbb\u591a\u62c9\u514b"
    ],
    "wof:name":"Saint-Georges-d'Aurac",
    "wof:placetype":"locality"
},
  "geometry": {"coordinates":[3.54043,45.15692],"type":"Point"}
}