{
  "type": "Feature",
  "properties": {
    "gn:admin1_code":"84",
    "gn:admin2_code":"43",
    "gn:admin3_code":"431",
    "gn:admin4_code":"43188",
    "gn:asciiname":"Saint-Georges-d'Aurac",
    "gn:country_code":"FR",
    "gn:dem":626,
    "gn:feature_class":"P",
    "gn:feature_code":"PPL",
    "gn:name":"Saint-Georges-d\u2019Aurac",
    "gn:population":0,
    "gn:timezone":"Europe/Paris",
    "iso:country":"FR",
    "name:und_x_variant":[
        "Saint-Georges",
        "Saint-Georges-d\u2019Aurac"
    ],
    "wof:name":"Saint-Georges-d'Aurac",
    "wof:placetype":"locality"
},
  "geometry": {"coordinates":[3.54043,45.15692],"type":"Point"}
}