{
  "type": "Feature",
  "properties": {
    "gn:admin1_code":"84",
    "gn:admin2_code":"03",
    "gn:admin3_code":"031",
    "gn:admin4_code":"03282",
    "gn:asciiname":"Grand Fy",
    "gn:country_code":"FR",
    "gn:dem":328,
    "gn:feature_class":"P",
    "gn:feature_code":"PPL",
    "gn:name":"Grand Fy",
    "gn:population":0,
    "gn:timezone":"Europe/Paris",
    "iso:country":"FR",
    "wof:name":"Grand Fy",
    "wof:placetype":"locality"
},
  "geometry": {"coordinates":[2.888,46.5618],"type":"Point"}
}