{
  "type": "Feature",
  "properties": {
    "gn:admin1_code":"28",
    "gn:admin2_code":"76",
    "gn:admin3_code":"763",
    "gn:admin4_code":"76289.0",
    "gn:asciiname":"Freville",
    "gn:country_code":"FR",
    "gn:dem":136,
    "gn:feature_class":"P",
    "gn:feature_code":"PPL",
    "gn:name":"Fr\u00e9ville",
    "gn:population":0,
    "gn:timezone":"Europe/Paris",
    "iso:country":"FR",
    "name:und_x_variant":[
        "Fr\u00e9ville"
    ],
    "wof:name":"Freville",
    "wof:placetype":"locality"
},
  "geometry": {"coordinates":[0.83264,49.5678],"type":"Point"}
}