{
  "type": "Feature",
  "properties": {
    "gn:admin1_code":"84",
    "gn:admin2_code":"43",
    "gn:admin3_code":"432",
    "gn:admin4_code":"43189",
    "gn:asciiname":"Piassac",
    "gn:country_code":"FR",
    "gn:dem":861,
    "gn:feature_class":"P",
    "gn:feature_code":"PPL",
    "gn:name":"Piassac",
    "gn:population":0,
    "gn:timezone":"Europe/Paris",
    "iso:country":"FR",
    "wof:name":"Piassac",
    "wof:placetype":"locality"
},
  "geometry": {"coordinates":[3.89641,45.31196],"type":"Point"}
}