{
  "type": "Feature",
  "properties": {
    "gn:admin1_code":"75",
    "gn:admin2_code":"24",
    "gn:admin3_code":"243",
    "gn:admin4_code":"24312",
    "gn:asciiname":"La Cote",
    "gn:country_code":"FR",
    "gn:dem":217,
    "gn:feature_class":"P",
    "gn:feature_code":"PPL",
    "gn:name":"La Cote",
    "gn:population":0,
    "gn:timezone":"Europe/Paris",
    "iso:country":"FR",
    "wof:name":"La Cote",
    "wof:placetype":"locality"
},
  "geometry": {"coordinates":[0.80754,45.11095],"type":"Point"}
}