{
  "type": "Feature",
  "properties": {
    "gn:admin1_code":"28",
    "gn:admin2_code":"14",
    "gn:admin3_code":"141",
    "gn:admin4_code":"14138",
    "gn:asciiname":"Cartigny-l'Epinay",
    "gn:country_code":"FR",
    "gn:dem":19,
    "gn:feature_class":"P",
    "gn:feature_code":"PPL",
    "gn:name":"Cartigny-l\u2019\u00c9pinay",
    "gn:population":0,
    "gn:timezone":"Europe/Paris",
    "iso:country":"FR",
    "name:und_x_variant":[
        "Cartigny",
        "Cartigny-l\u2019\u00c9pinay"
    ],
    "wof:name":"Cartigny-l'Epinay",
    "wof:placetype":"locality"
},
  "geometry": {"coordinates":[-1.01047,49.23916],"type":"Point"}
}