{
  "type": "Feature",
  "properties": {
    "gn:admin1_code":"28",
    "gn:admin2_code":"14",
    "gn:admin3_code":"141",
    "gn:admin4_code":"14138",
    "gn:asciiname":"Cartigny-l'Epinay",
    "gn:country_code":"FR",
    "gn:dem":19,
    "gn:feature_class":"P",
    "gn:feature_code":"PPL",
    "gn:name":"Cartigny-l\u2019\u00c9pinay",
    "gn:population":0,
    "gn:timezone":"Europe/Paris",
    "iso:country":"FR",
    "name:bre_x_preferred":[
        "Cartigny-l'\u00c9pinay"
    ],
    "name:cat_x_preferred":[
        "Cartigny-l'\u00c9pinay"
    ],
    "name:ceb_x_preferred":[
        "Cartigny-l'\u00c9pinay"
    ],
    "name:deu_x_preferred":[
        "Cartigny-l\u2019\u00c9pinay"
    ],
    "name:eus_x_preferred":[
        "Cartigny-l'\u00c9pinay"
    ],
    "name:fra_x_preferred":[
        "Cartigny-l'\u00c9pinay"
    ],
    "name:hun_x_preferred":[
        "Cartigny-l\u2019\u00c9pinay"
    ],
    "name:hye_x_preferred":[
        "\u053f\u0561\u0580\u057f\u056b\u0576\u056b \u056c'\u0537\u057a\u056b\u0576\u0565"
    ],
    "name:ind_x_preferred":[
        "Cartigny-l'\u00c9pinay"
    ],
    "name:ita_x_preferred":[
        "Cartigny-l'\u00c9pinay"
    ],
    "name:kaz_x_preferred":[
        "\u041a\u0430\u0440\u0442\u0438\u043d\u044c\u0438-\u043b'\u0415\u043f\u0438\u043d\u0435"
    ],
    "name:lat_x_preferred":[
        "Cartigny-l'\u00c9pinay"
    ],
    "name:msa_x_preferred":[
        "Cartigny-l'\u00c9pinay"
    ],
    "name:nld_x_preferred":[
        "Cartigny-l'\u00c9pinay"
    ],
    "name:oci_x_preferred":[
        "Cartigny-l'\u00c9pinay"
    ],
    "name:pam_x_preferred":[
        "Cartigny-l'\u00c9pinay"
    ],
    "name:pms_x_preferred":[
        "Cartigny-l'\u00c9pinay"
    ],
    "name:pol_x_preferred":[
        "Cartigny-l\u2019\u00c9pinay"
    ],
    "name:por_x_preferred":[
        "Cartigny-l'\u00c9pinay"
    ],
    "name:ron_x_preferred":[
        "Cartigny-l'\u00c9pinay"
    ],
    "name:rus_x_preferred":[
        "\u041a\u0430\u0440\u0442\u0438\u043d\u044c\u0438-\u043b\u2019\u042d\u043f\u0438\u043d\u0435"
    ],
    "name:slk_x_preferred":[
        "Cartigny-l\u2019\u00c9pinay"
    ],
    "name:spa_x_preferred":[
        "Cartigny-l'\u00c9pinay"
    ],
    "name:srp_x_preferred":[
        "\u041a\u0430\u0440\u0442\u0438\u045a\u0438 \u043b'\u0415\u043f\u0438\u043d\u0435"
    ],
    "name:swe_x_preferred":[
        "Cartigny-l'\u00c9pinay"
    ],
    "name:ukr_x_preferred":[
        "\u041a\u0430\u0440\u0442\u0456\u043d\u044c\u0457-\u043b'\u0415\u043f\u0456\u043d\u0435"
    ],
    "name:und_x_variant":[
        "Cartigny",
        "Cartigny-l\u2019\u00c9pinay"
    ],
    "name:uzb_x_preferred":[
        "Cartigny-l'\u00c9pinay"
    ],
    "name:vie_x_preferred":[
        "Cartigny-l'\u00c9pinay"
    ],
    "name:vol_x_preferred":[
        "Cartigny-l'\u00c9pinay"
    ],
    "name:war_x_preferred":[
        "Cartigny-l'\u00c9pinay"
    ],
    "name:zho_x_preferred":[
        "\u5361\u5c14\u8482\u5c3c\u83b1\u76ae\u5948"
    ],
    "wof:name":"Cartigny-l'Epinay",
    "wof:placetype":"locality"
},
  "geometry": {"coordinates":[-1.01047,49.23916],"type":"Point"}
}