{
  "type": "Feature",
  "properties": {
    "gn:admin1_code":"27",
    "gn:admin2_code":"58",
    "gn:admin3_code":"584",
    "gn:admin4_code":"58256",
    "gn:asciiname":"Moussard",
    "gn:country_code":"FR",
    "gn:dem":201,
    "gn:feature_class":"P",
    "gn:feature_code":"PPL",
    "gn:name":"Moussard",
    "gn:population":0,
    "gn:timezone":"Europe/Paris",
    "iso:country":"FR",
    "wof:name":"Moussard",
    "wof:placetype":"locality"
},
  "geometry": {"coordinates":[2.96486,47.34534],"type":"Point"}
}