{
  "type": "Feature",
  "properties": {
    "gn:admin1_code":"27",
    "gn:admin2_code":"89",
    "gn:admin3_code":"893",
    "gn:admin4_code":"89464",
    "gn:asciiname":"Talouan",
    "gn:country_code":"FR",
    "gn:dem":103,
    "gn:feature_class":"P",
    "gn:feature_code":"PPL",
    "gn:name":"Talouan",
    "gn:population":0,
    "gn:timezone":"Europe/Paris",
    "iso:country":"FR",
    "wof:name":"Talouan",
    "wof:placetype":"locality"
},
  "geometry": {"coordinates":[3.34791,48.09413],"type":"Point"}
}