{
  "type": "Feature",
  "properties": {
    "gn:admin1_code":"93",
    "gn:admin2_code":"06",
    "gn:admin3_code":"062",
    "gn:admin4_code":"06074",
    "gn:asciiname":"Saint-Colomban",
    "gn:country_code":"FR",
    "gn:dem":701,
    "gn:feature_class":"P",
    "gn:feature_code":"PPL",
    "gn:name":"Saint-Colomban",
    "gn:population":0,
    "gn:timezone":"Europe/Paris",
    "iso:country":"FR",
    "name:bre_x_preferred":[
        "Sant-Koulman"
    ],
    "name:cat_x_preferred":[
        "Saint-Colomban"
    ],
    "name:ceb_x_preferred":[
        "Saint-Colomban"
    ],
    "name:cym_x_preferred":[
        "Sant-Koulman"
    ],
    "name:deu_x_preferred":[
        "Saint-Colomban"
    ],
    "name:eus_x_preferred":[
        "Saint-Colomban"
    ],
    "name:fas_x_preferred":[
        "\u0633\u0646-\u06a9\u0648\u0644\u0648\u0645\u0628\u0627\u0646"
    ],
    "name:fra_x_preferred":[
        "Saint-Colomban"
    ],
    "name:hun_x_preferred":[
        "Saint-Colomban"
    ],
    "name:ita_x_preferred":[
        "Saint-Colomban"
    ],
    "name:lat_x_preferred":[
        "Saint-Colomban"
    ],
    "name:mlg_x_preferred":[
        "Saint-Colomban"
    ],
    "name:msa_x_preferred":[
        "Saint-Colomban"
    ],
    "name:nld_x_preferred":[
        "Saint-Colomban"
    ],
    "name:oci_x_preferred":[
        "Sant-Koulman"
    ],
    "name:pms_x_preferred":[
        "Saint-Colomban"
    ],
    "name:pol_x_preferred":[
        "Saint-Colomban"
    ],
    "name:por_x_preferred":[
        "Saint-Colomban"
    ],
    "name:ron_x_preferred":[
        "Saint-Colomban"
    ],
    "name:slk_x_preferred":[
        "Saint-Colomban"
    ],
    "name:spa_x_preferred":[
        "Saint-Colomban"
    ],
    "name:swe_x_preferred":[
        "Saint-Colomban"
    ],
    "name:ukr_x_preferred":[
        "\u0421\u0435\u043d-\u041a\u043e\u043b\u043e\u043c\u0431\u0430\u043d"
    ],
    "name:urd_x_preferred":[
        "\u0633\u06cc\u0646\u0679-\u06a9\u0648\u0644\u0648\u0645\u0628\u0627\u0646"
    ],
    "name:vie_x_preferred":[
        "Saint-Colomban"
    ],
    "name:vol_x_preferred":[
        "Saint-Colomban"
    ],
    "name:war_x_preferred":[
        "Saint-Colomban"
    ],
    "name:zho_x_preferred":[
        "\u5723\u79d1\u9686\u90a6"
    ],
    "wof:name":"Saint-Colomban",
    "wof:placetype":"locality"
},
  "geometry": {"coordinates":[7.32371,43.9542],"type":"Point"}
}