{
  "type": "Feature",
  "properties": {
    "gn:admin1_code":"93",
    "gn:admin2_code":"06",
    "gn:admin3_code":"062",
    "gn:admin4_code":"06074",
    "gn:asciiname":"Saint-Colomban",
    "gn:country_code":"FR",
    "gn:dem":701,
    "gn:feature_class":"P",
    "gn:feature_code":"PPL",
    "gn:name":"Saint-Colomban",
    "gn:population":0,
    "gn:timezone":"Europe/Paris",
    "iso:country":"FR",
    "wof:name":"Saint-Colomban",
    "wof:placetype":"locality"
},
  "geometry": {"coordinates":[7.32371,43.9542],"type":"Point"}
}