{
  "type": "Feature",
  "properties": {
    "gn:admin1_code":"32",
    "gn:admin2_code":"62",
    "gn:admin3_code":"622",
    "gn:admin4_code":"62373.0",
    "gn:asciiname":"Givenchy-les-la-Bassee",
    "gn:cc2":"FR",
    "gn:country_code":"FR",
    "gn:dem":27,
    "gn:feature_class":"P",
    "gn:feature_code":"PPL",
    "gn:name":"Givenchy-l\u00e8s-la-Bass\u00e9e",
    "gn:population":0,
    "gn:timezone":"Europe/Paris",
    "iso:country":"FR",
    "name:und_x_variant":[
        "Givenchy"
    ],
    "wof:name":"Givenchy-les-la-Bassee",
    "wof:placetype":"locality"
},
  "geometry": {"coordinates":[2.76667,50.53333],"type":"Point"}
}