{
  "type": "Feature",
  "properties": {
    "gn:admin1_code":"53",
    "gn:admin2_code":"22",
    "gn:admin3_code":"224",
    "gn:admin4_code":"22054",
    "gn:asciiname":"Le Val",
    "gn:country_code":"FR",
    "gn:dem":29,
    "gn:feature_class":"P",
    "gn:feature_code":"PPL",
    "gn:name":"Le Val",
    "gn:population":0,
    "gn:timezone":"Europe/Paris",
    "iso:country":"FR",
    "name:fra_x_preferred":[
        "Le Val"
    ],
    "name:nld_x_preferred":[
        "Le Val"
    ],
    "name:pol_x_preferred":[
        "Le Val"
    ],
    "name:spa_x_preferred":[
        "Le Val"
    ],
    "wof:name":"Le Val",
    "wof:placetype":"locality"
},
  "geometry": {"coordinates":[-2.45202,48.63215],"type":"Point"}
}