{
  "type": "Feature",
  "properties": {
    "gn:admin1_code":"44",
    "gn:admin2_code":"51",
    "gn:admin3_code":"514",
    "gn:admin4_code":"51539",
    "gn:asciiname":"Sogny-en-l'Angle",
    "gn:country_code":"FR",
    "gn:dem":114,
    "gn:feature_class":"P",
    "gn:feature_code":"PPL",
    "gn:name":"Sogny-en-l\u2019Angle",
    "gn:population":0,
    "gn:timezone":"Europe/Paris",
    "iso:country":"FR",
    "name:cat_x_preferred":[
        "Sogny-en-l'Angle"
    ],
    "name:ceb_x_preferred":[
        "Sogny-en-l'Angle"
    ],
    "name:deu_x_preferred":[
        "Sogny-en-l\u2019Angle"
    ],
    "name:eus_x_preferred":[
        "Sogny-en-l'Angle"
    ],
    "name:fra_x_preferred":[
        "Sogny-en-l'Angle"
    ],
    "name:hun_x_preferred":[
        "Sogny-en-l\u2019Angle"
    ],
    "name:ita_x_preferred":[
        "Sogny-en-l'Angle"
    ],
    "name:lat_x_preferred":[
        "Sogny-en-l'Angle"
    ],
    "name:mlg_x_preferred":[
        "Sogny-en-l'Angle"
    ],
    "name:msa_x_preferred":[
        "Sogny-en-l'Angle"
    ],
    "name:nld_x_preferred":[
        "Sogny-en-l'Angle"
    ],
    "name:oci_x_preferred":[
        "Sogny-en-l'Angle"
    ],
    "name:pol_x_preferred":[
        "Sogny-en-l\u2019Angle"
    ],
    "name:ron_x_preferred":[
        "Sogny-en-l'Angle"
    ],
    "name:slk_x_preferred":[
        "Sogny-en-l\u2019Angle"
    ],
    "name:spa_x_preferred":[
        "Sogny-en-l'Angle"
    ],
    "name:swe_x_preferred":[
        "Sogny-en-l'Angle"
    ],
    "name:ukr_x_preferred":[
        "\u0421\u043e\u043d\u044c\u0457-\u0430\u043d-\u043b'\u0410\u043d\u0433\u043b\u044c"
    ],
    "name:und_x_variant":[
        "Sogny",
        "Sogny-en-l\u2019Angle"
    ],
    "name:vie_x_preferred":[
        "Sogny-en-l'Angle"
    ],
    "name:vol_x_preferred":[
        "Sogny-en-l'Angle"
    ],
    "name:war_x_preferred":[
        "Sogny-en-l'Angle"
    ],
    "name:zho_x_preferred":[
        "\u6717\u683c\u5c14\u5730\u533a\u7d22\u5c3c"
    ],
    "wof:name":"Sogny-en-l'Angle",
    "wof:placetype":"locality"
},
  "geometry": {"coordinates":[4.80329,48.8122],"type":"Point"}
}