{
  "type": "Feature",
  "properties": {
    "gn:admin1_code":"44",
    "gn:admin2_code":"51",
    "gn:admin3_code":"514",
    "gn:admin4_code":"51539",
    "gn:asciiname":"Sogny-en-l'Angle",
    "gn:country_code":"FR",
    "gn:dem":114,
    "gn:feature_class":"P",
    "gn:feature_code":"PPL",
    "gn:name":"Sogny-en-l\u2019Angle",
    "gn:population":0,
    "gn:timezone":"Europe/Paris",
    "iso:country":"FR",
    "name:und_x_variant":[
        "Sogny",
        "Sogny-en-l\u2019Angle"
    ],
    "wof:name":"Sogny-en-l'Angle",
    "wof:placetype":"locality"
},
  "geometry": {"coordinates":[4.80329,48.8122],"type":"Point"}
}