{
  "type": "Feature",
  "properties": {
    "gn:admin1_code":"84",
    "gn:admin2_code":"43",
    "gn:admin3_code":"433",
    "gn:admin4_code":"43127",
    "gn:asciiname":"Mayol",
    "gn:country_code":"FR",
    "gn:dem":560,
    "gn:feature_class":"P",
    "gn:feature_code":"PPL",
    "gn:name":"Mayol",
    "gn:population":0,
    "gn:timezone":"Europe/Paris",
    "iso:country":"FR",
    "name:deu_x_preferred":[
        "Mayol"
    ],
    "name:fra_x_preferred":[
        "Mayol"
    ],
    "name:jpn_x_preferred":[
        "\u30de\u30a4\u30e8\u30fc\u30eb"
    ],
    "name:rus_x_preferred":[
        "\u041c\u0430\u0439\u043e\u043b\u044c"
    ],
    "name:ukr_x_preferred":[
        "\u041c\u0430\u0439\u043e\u043b\u044c"
    ],
    "wof:name":"Mayol",
    "wof:placetype":"locality"
},
  "geometry": {"coordinates":[4.17992,45.34175],"type":"Point"}
}