{
  "type": "Feature",
  "properties": {
    "gn:admin1_code":"76",
    "gn:admin2_code":"12",
    "gn:admin3_code":"122",
    "gn:admin4_code":"12223",
    "gn:asciiname":"Orlhaguet",
    "gn:country_code":"FR",
    "gn:dem":814,
    "gn:feature_class":"P",
    "gn:feature_code":"PPL",
    "gn:name":"Orlhaguet",
    "gn:population":0,
    "gn:timezone":"Europe/Paris",
    "iso:country":"FR",
    "wof:name":"Orlhaguet",
    "wof:placetype":"locality"
},
  "geometry": {"coordinates":[2.75738,44.81656],"type":"Point"}
}