{
  "type": "Feature",
  "properties": {
    "iso:country":"FR",
    "name:fra_x_preferred":[
        "Moscou"
    ],
    "qs:gn_adm0_cc":"FR",
    "qs:gn_fcode":"PPLX",
    "qs:gn_local":2972315,
    "qs:gn_nam_loc":"Toulouse, Toulouse, Haute Garonne, Midi-Pyr\u00e9n\u00e9es, FR",
    "qs:gn_namadm1":"B3",
    "qs:gn_name":"Moscou",
    "qs:local_max":24044,
    "qs:local_sum":37308,
    "qs:localhoods":9,
    "qs:name":"Moscou",
    "qs:name_adm0":"France",
    "qs:name_adm1":"Midi-Pyr\u00e9n\u00e9es",
    "qs:name_adm2":"Haute-Garonne",
    "qs:name_lau":"Toulouse",
    "qs:name_local":"Toulouse",
    "qs:photo_max":204,
    "qs:photo_sum":2217,
    "qs:placetype":"Suburb",
    "qs:quad_count":80,
    "qs:woe_adm0":23424819,
    "qs:woe_adm1":7153323,
    "qs:woe_adm2":12597186,
    "qs:woe_lau":12657325,
    "qs:woe_local":628886,
    "qs:woe_ver":"7.10.0",
    "wof:lang":[
        "fre"
    ],
    "wof:name":"Moscou",
    "wof:placetype":"neighbourhood"
},
  "geometry": {"coordinates":[1.475527,43.599392],"type":"Point"}
}