{
  "type": "Feature",
  "properties": {
    "gn:admin1_code":"27",
    "gn:admin2_code":"89",
    "gn:admin3_code":"892",
    "gn:admin4_code":"89266",
    "gn:asciiname":"Vaux Donjon",
    "gn:country_code":"FR",
    "gn:dem":166,
    "gn:feature_class":"P",
    "gn:feature_code":"PPL",
    "gn:name":"Vaux Donjon",
    "gn:population":0,
    "gn:timezone":"Europe/Paris",
    "iso:country":"FR",
    "wof:name":"Vaux Donjon",
    "wof:placetype":"locality"
},
  "geometry": {"coordinates":[3.74976,47.51155],"type":"Point"}
}