{
  "type": "Feature",
  "properties": {
    "gn:admin1_code":"93",
    "gn:admin2_code":"06",
    "gn:admin3_code":"061",
    "gn:admin4_code":"06105",
    "gn:asciiname":"Le Chateau",
    "gn:country_code":"FR",
    "gn:dem":227,
    "gn:feature_class":"P",
    "gn:feature_code":"PPL",
    "gn:name":"Le Ch\u00e2teau",
    "gn:population":0,
    "gn:timezone":"Europe/Paris",
    "iso:country":"FR",
    "wof:name":"Le Chateau",
    "wof:placetype":"locality"
},
  "geometry": {"coordinates":[7.03683,43.67773],"type":"Point"}
}