{
  "type": "Feature",
  "properties": {
    "gn:admin1_code":"84",
    "gn:admin2_code":"15",
    "gn:admin3_code":"151",
    "gn:admin4_code":"15267",
    "gn:asciiname":"Espinat",
    "gn:country_code":"FR",
    "gn:dem":577,
    "gn:feature_class":"P",
    "gn:feature_code":"PPL",
    "gn:name":"Espinat",
    "gn:population":0,
    "gn:timezone":"Europe/Paris",
    "iso:country":"FR",
    "wof:name":"Espinat",
    "wof:placetype":"locality"
},
  "geometry": {"coordinates":[2.3811,44.9335],"type":"Point"}
}