{
  "type": "Feature",
  "properties": {
    "gn:admin1_code":"52",
    "gn:admin2_code":"44",
    "gn:admin3_code":"442",
    "gn:admin4_code":"44217",
    "gn:asciiname":"La Gandiniere",
    "gn:country_code":"FR",
    "gn:dem":76,
    "gn:feature_class":"P",
    "gn:feature_code":"PPL",
    "gn:name":"La Gandini\u00e8re",
    "gn:population":0,
    "gn:timezone":"Europe/Paris",
    "iso:country":"FR",
    "wof:name":"La Gandiniere",
    "wof:placetype":"locality"
},
  "geometry": {"coordinates":[-1.71095,47.30119000000001],"type":"Point"}
}