{
  "type": "Feature",
  "properties": {
    "gn:admin1_code":"94",
    "gn:admin2_code":"2B",
    "gn:admin3_code":"2B3",
    "gn:admin4_code":"2B337",
    "gn:asciiname":"Casapitti",
    "gn:country_code":"FR",
    "gn:dem":749,
    "gn:feature_class":"P",
    "gn:feature_code":"PPL",
    "gn:name":"Casapitti",
    "gn:population":0,
    "gn:timezone":"Europe/Paris",
    "iso:country":"FR",
    "name:und_x_variant":[
        "Casabiti",
        "Casapitti"
    ],
    "wof:name":"Casapitti",
    "wof:placetype":"locality"
},
  "geometry": {"coordinates":[9.28691,42.44784],"type":"Point"}
}