{
  "type": "Feature",
  "properties": {
    "gn:admin1_code":"24",
    "gn:admin2_code":"28",
    "gn:admin3_code":"282",
    "gn:admin4_code":"28205",
    "gn:asciiname":"Les Gaulardieres",
    "gn:country_code":"FR",
    "gn:dem":156,
    "gn:feature_class":"P",
    "gn:feature_code":"PPL",
    "gn:name":"Les Gaulardi\u00e8res",
    "gn:population":0,
    "gn:timezone":"Europe/Paris",
    "iso:country":"FR",
    "name:und_x_variant":[
        "Les Goislardi\u00e8res",
        "Les Gaulardi\u00e8res"
    ],
    "wof:name":"Les Gaulardieres",
    "wof:placetype":"locality"
},
  "geometry": {"coordinates":[1.24967,48.10641],"type":"Point"}
}