{
  "type": "Feature",
  "properties": {
    "gn:admin1_code":"28",
    "gn:admin2_code":"14",
    "gn:admin3_code":"143",
    "gn:admin4_code":"14431.0",
    "gn:asciiname":"Sainte-Marie-aux-Anglais",
    "gn:country_code":"FR",
    "gn:dem":63,
    "gn:feature_class":"P",
    "gn:feature_code":"PPL",
    "gn:name":"Sainte-Marie-aux-Anglais",
    "gn:population":0,
    "gn:timezone":"Europe/Paris",
    "iso:country":"FR",
    "name:und_x_variant":[
        "Sainte-Marie",
        "Sainte-Marie-aux-Anglais"
    ],
    "wof:name":"Sainte-Marie-aux-Anglais",
    "wof:placetype":"locality"
},
  "geometry": {"coordinates":[0.01112,49.07279000000001],"type":"Point"}
}