{
  "type": "Feature",
  "properties": {
    "gn:admin1_code":"27",
    "gn:admin2_code":"21",
    "gn:admin3_code":"213",
    "gn:admin4_code":"21451",
    "gn:asciiname":"Massoult",
    "gn:country_code":"FR",
    "gn:dem":291,
    "gn:feature_class":"P",
    "gn:feature_code":"PPL",
    "gn:name":"Massoult",
    "gn:population":0,
    "gn:timezone":"Europe/Paris",
    "iso:country":"FR",
    "wof:name":"Massoult",
    "wof:placetype":"locality"
},
  "geometry": {"coordinates":[4.4493,47.7888],"type":"Point"}
}