{
  "type": "Feature",
  "properties": {
    "gn:admin1_code":"75",
    "gn:admin2_code":"24",
    "gn:admin3_code":"241",
    "gn:admin4_code":"24492",
    "gn:asciiname":"Rocquepine",
    "gn:country_code":"FR",
    "gn:dem":83,
    "gn:feature_class":"P",
    "gn:feature_code":"PPL",
    "gn:name":"Rocquepine",
    "gn:population":0,
    "gn:timezone":"Europe/Paris",
    "iso:country":"FR",
    "name:und_x_variant":[
        "Roquepine",
        "Rocquepine"
    ],
    "wof:name":"Rocquepine",
    "wof:placetype":"locality"
},
  "geometry": {"coordinates":[0.67834,44.68982000000001],"type":"Point"}
}