{
  "type": "Feature",
  "properties": {
    "gn:admin1_code":"24",
    "gn:admin2_code":"45",
    "gn:admin3_code":"453",
    "gn:admin4_code":"45080",
    "gn:asciiname":"Gironville",
    "gn:country_code":"FR",
    "gn:dem":126,
    "gn:feature_class":"P",
    "gn:feature_code":"PPL",
    "gn:name":"Gironville",
    "gn:population":0,
    "gn:timezone":"Europe/Paris",
    "iso:country":"FR",
    "wof:name":"Gironville",
    "wof:placetype":"locality"
},
  "geometry": {"coordinates":[2.09276,48.24579],"type":"Point"}
}