{
  "type": "Feature",
  "properties": {
    "gn:admin1_code":"24",
    "gn:admin2_code":"45",
    "gn:admin3_code":"453",
    "gn:admin4_code":"45080",
    "gn:asciiname":"Gironville",
    "gn:country_code":"FR",
    "gn:dem":126,
    "gn:feature_class":"P",
    "gn:feature_code":"PPL",
    "gn:name":"Gironville",
    "gn:population":0,
    "gn:timezone":"Europe/Paris",
    "iso:country":"FR",
    "name:ceb_x_preferred":[
        "Gironville"
    ],
    "name:deu_x_preferred":[
        "Gironville"
    ],
    "name:eus_x_preferred":[
        "Gironville"
    ],
    "name:fra_x_preferred":[
        "Gironville"
    ],
    "name:hun_x_preferred":[
        "Gironville"
    ],
    "name:ind_x_preferred":[
        "Gironville"
    ],
    "name:ita_x_preferred":[
        "Gironville"
    ],
    "name:kaz_x_preferred":[
        "\u0416\u0438\u0440\u043e\u043d\u0432\u0438\u043b\u044c"
    ],
    "name:lat_x_preferred":[
        "Gironville"
    ],
    "name:msa_x_preferred":[
        "Gironville"
    ],
    "name:nld_x_preferred":[
        "Gironville"
    ],
    "name:oci_x_preferred":[
        "Gironville"
    ],
    "name:pms_x_preferred":[
        "Gironville"
    ],
    "name:pol_x_preferred":[
        "Gironville"
    ],
    "name:por_x_preferred":[
        "Gironville"
    ],
    "name:slk_x_preferred":[
        "Gironville"
    ],
    "name:spa_x_preferred":[
        "Gironville"
    ],
    "name:srp_x_preferred":[
        "\u0416\u0438\u0440\u043e\u043d\u0432\u0438\u043b"
    ],
    "name:swe_x_preferred":[
        "Gironville"
    ],
    "name:ukr_x_preferred":[
        "\u0416\u0438\u0440\u043e\u043d\u0432\u0456\u043b\u044c"
    ],
    "name:vie_x_preferred":[
        "Gironville"
    ],
    "name:vol_x_preferred":[
        "Gironville"
    ],
    "name:war_x_preferred":[
        "Gironville"
    ],
    "wof:name":"Gironville",
    "wof:placetype":"locality"
},
  "geometry": {"coordinates":[2.09276,48.24579],"type":"Point"}
}