{
  "type": "Feature",
  "properties": {
    "gn:admin1_code":"27",
    "gn:admin2_code":"71",
    "gn:admin3_code":"714",
    "gn:admin4_code":"71079.0",
    "gn:asciiname":"Louvarel",
    "gn:country_code":"FR",
    "gn:dem":203,
    "gn:feature_class":"P",
    "gn:feature_code":"PPL",
    "gn:name":"Louvarel",
    "gn:population":0,
    "gn:timezone":"Europe/Paris",
    "iso:country":"FR",
    "wof:name":"Louvarel",
    "wof:placetype":"locality"
},
  "geometry": {"coordinates":[5.32571,46.49609],"type":"Point"}
}