{
  "type": "Feature",
  "properties": {
    "gn:admin1_code":"27",
    "gn:admin2_code":"58",
    "gn:admin3_code":"582",
    "gn:admin4_code":"58165",
    "gn:asciiname":"Champagne",
    "gn:country_code":"FR",
    "gn:dem":231,
    "gn:feature_class":"P",
    "gn:feature_code":"PPL",
    "gn:name":"Champagne",
    "gn:population":0,
    "gn:timezone":"Europe/Paris",
    "iso:country":"FR",
    "wof:name":"Champagne",
    "wof:placetype":"locality"
},
  "geometry": {"coordinates":[3.62405,47.38202],"type":"Point"}
}