{
  "type": "Feature",
  "properties": {
    "gn:admin1_code":"84",
    "gn:admin2_code":"73",
    "gn:admin3_code":"733",
    "gn:admin4_code":"73278.0",
    "gn:asciiname":"La Girard",
    "gn:country_code":"FR",
    "gn:dem":445,
    "gn:feature_class":"P",
    "gn:feature_code":"PPL",
    "gn:name":"La Girard",
    "gn:population":0,
    "gn:timezone":"Europe/Paris",
    "iso:country":"FR",
    "wof:name":"La Girard",
    "wof:placetype":"locality"
},
  "geometry": {"coordinates":[6.26888,45.38401],"type":"Point"}
}