{
  "type": "Feature",
  "properties": {
    "gn:admin1_code":"52",
    "gn:admin2_code":"53",
    "gn:admin3_code":"532",
    "gn:admin4_code":"53220",
    "gn:asciiname":"La Forge",
    "gn:country_code":"FR",
    "gn:dem":94,
    "gn:feature_class":"P",
    "gn:feature_code":"PPL",
    "gn:name":"La Forge",
    "gn:population":0,
    "gn:timezone":"Europe/Paris",
    "iso:country":"FR",
    "name:deu_x_preferred":[
        "La Forge"
    ],
    "name:fra_x_preferred":[
        "La Forge"
    ],
    "wof:name":"La Forge",
    "wof:placetype":"locality"
},
  "geometry": {"coordinates":[-0.53333,48.03333],"type":"Point"}
}