{
  "type": "Feature",
  "properties": {
    "iso:country":"FR",
    "name:fra_x_preferred":[
        "Les M\u00e9dicins"
    ],
    "wof:name":"Les Medicins",
    "wof:placetype":"neighbourhood"
},
  "geometry": {"coordinates":[5.45495258037474,43.35814832013296],"type":"Point"}
}