{
  "type": "Feature",
  "properties": {
    "gn:admin1_code":"76",
    "gn:admin2_code":"48",
    "gn:admin3_code":"482",
    "gn:admin4_code":"48013",
    "gn:asciiname":"Bories Basses",
    "gn:country_code":"FR",
    "gn:dem":798,
    "gn:feature_class":"P",
    "gn:feature_code":"PPL",
    "gn:name":"Bories Basses",
    "gn:population":0,
    "gn:timezone":"Europe/Paris",
    "iso:country":"FR",
    "wof:name":"Bories Basses",
    "wof:placetype":"locality"
},
  "geometry": {"coordinates":[3.53086,44.52868],"type":"Point"}
}