{
  "type": "Feature",
  "properties": {
    "gn:admin1_code":"84",
    "gn:admin2_code":"43",
    "gn:admin3_code":"431",
    "gn:admin4_code":"43067",
    "gn:asciiname":"Boisseuges",
    "gn:country_code":"FR",
    "gn:dem":691,
    "gn:feature_class":"P",
    "gn:feature_code":"PPL",
    "gn:name":"Boisseuges",
    "gn:population":0,
    "gn:timezone":"Europe/Paris",
    "iso:country":"FR",
    "name:und_x_variant":[
        "Boisseuge",
        "Boisseuges"
    ],
    "wof:name":"Boisseuges",
    "wof:placetype":"locality"
},
  "geometry": {"coordinates":[3.57276,45.15054],"type":"Point"}
}