{
  "type": "Feature",
  "properties": {
    "gn:admin1_code":"53",
    "gn:admin2_code":"35",
    "gn:admin3_code":"353",
    "gn:admin4_code":"35047",
    "gn:asciiname":"Matival",
    "gn:country_code":"FR",
    "gn:dem":33,
    "gn:feature_class":"P",
    "gn:feature_code":"PPL",
    "gn:name":"Matival",
    "gn:population":0,
    "gn:timezone":"Europe/Paris",
    "iso:country":"FR",
    "wof:name":"Matival",
    "wof:placetype":"locality"
},
  "geometry": {"coordinates":[-1.73333,48.05],"type":"Point"}
}