{
  "type": "Feature",
  "properties": {
    "gn:admin1_code":"24",
    "gn:admin2_code":"18",
    "gn:admin3_code":"182",
    "gn:admin4_code":"18252.0",
    "gn:asciiname":"Rancier",
    "gn:country_code":"FR",
    "gn:dem":363,
    "gn:feature_class":"P",
    "gn:feature_code":"PPL",
    "gn:name":"Rancier",
    "gn:population":0,
    "gn:timezone":"Europe/Paris",
    "iso:country":"FR",
    "wof:name":"Rancier",
    "wof:placetype":"locality"
},
  "geometry": {"coordinates":[2.29695,46.51218],"type":"Point"}
}