{
  "type": "Feature",
  "properties": {
    "gn:admin1_code":"32",
    "gn:admin2_code":"62",
    "gn:admin3_code":"623",
    "gn:admin4_code":"62054",
    "gn:asciiname":"Onglevert",
    "gn:country_code":"FR",
    "gn:dem":86,
    "gn:feature_class":"P",
    "gn:feature_code":"PPL",
    "gn:name":"Onglevert",
    "gn:population":0,
    "gn:timezone":"Europe/Paris",
    "iso:country":"FR",
    "wof:name":"Onglevert",
    "wof:placetype":"locality"
},
  "geometry": {"coordinates":[1.62125,50.84148],"type":"Point"}
}