{
  "type": "Feature",
  "properties": {
    "gn:admin1_code":"75",
    "gn:admin2_code":"87",
    "gn:admin3_code":"872",
    "gn:admin4_code":"87186",
    "gn:asciiname":"Cursac",
    "gn:cc2":"FR",
    "gn:country_code":"FR",
    "gn:dem":372,
    "gn:feature_class":"P",
    "gn:feature_code":"PPL",
    "gn:name":"Cursac",
    "gn:population":0,
    "gn:timezone":"Europe/Paris",
    "iso:country":"FR",
    "name:und_x_variant":[
        "Curzac",
        "Cursac"
    ],
    "wof:name":"Cursac",
    "wof:placetype":"locality"
},
  "geometry": {"coordinates":[1.53333,45.63333],"type":"Point"}
}