{
  "type": "Feature",
  "properties": {
    "gn:admin1_code":"28",
    "gn:admin2_code":"27",
    "gn:admin3_code":"273",
    "gn:admin4_code":"27198",
    "gn:asciiname":"Conde-sur-Iton",
    "gn:cc2":"FR",
    "gn:country_code":"FR",
    "gn:dem":153,
    "gn:feature_class":"P",
    "gn:feature_code":"PPL",
    "gn:name":"Cond\u00e9-sur-Iton",
    "gn:population":0,
    "gn:timezone":"Europe/Paris",
    "iso:country":"FR",
    "name:und_x_variant":[
        "Cond\u00e9"
    ],
    "wof:name":"Conde-sur-Iton",
    "wof:placetype":"locality"
},
  "geometry": {"coordinates":[0.96667,48.83333],"type":"Point"}
}