{
  "type": "Feature",
  "properties": {
    "gn:admin1_code":"44",
    "gn:admin2_code":"52",
    "gn:admin3_code":"523",
    "gn:admin4_code":"52456",
    "gn:asciiname":"Maconcourt",
    "gn:country_code":"FR",
    "gn:dem":281,
    "gn:feature_class":"P",
    "gn:feature_code":"PPL",
    "gn:name":"Maconcourt",
    "gn:population":0,
    "gn:timezone":"Europe/Paris",
    "iso:country":"FR",
    "name:bug_x_preferred":[
        "Maconcourt"
    ],
    "name:cat_x_preferred":[
        "Maconcourt"
    ],
    "name:ceb_x_preferred":[
        "Maconcourt"
    ],
    "name:deu_x_preferred":[
        "Maconcourt"
    ],
    "name:eus_x_preferred":[
        "Maconcourt"
    ],
    "name:fra_x_preferred":[
        "Maconcourt"
    ],
    "name:hun_x_preferred":[
        "Maconcourt"
    ],
    "name:ind_x_preferred":[
        "Maconcourt"
    ],
    "name:ita_x_preferred":[
        "Maconcourt"
    ],
    "name:kaz_x_preferred":[
        "\u041c\u0430\u043a\u043e\u043d\u043a\u0443\u0440"
    ],
    "name:mlg_x_preferred":[
        "Maconcourt"
    ],
    "name:msa_x_preferred":[
        "Maconcourt"
    ],
    "name:nld_x_preferred":[
        "Maconcourt"
    ],
    "name:oci_x_preferred":[
        "Maconcourt"
    ],
    "name:pms_x_preferred":[
        "Maconcourt"
    ],
    "name:pol_x_preferred":[
        "Maconcourt"
    ],
    "name:por_x_preferred":[
        "Maconcourt"
    ],
    "name:slk_x_preferred":[
        "Maconcourt"
    ],
    "name:spa_x_preferred":[
        "Maconcourt"
    ],
    "name:swe_x_preferred":[
        "Maconcourt"
    ],
    "name:ukr_x_preferred":[
        "\u041c\u0430\u043a\u043e\u043d\u043a\u0443\u0440"
    ],
    "name:urd_x_preferred":[
        "\u0645\u06cc\u06a9\u0648\u0646\u06a9\u0648\u0631\u0679"
    ],
    "name:uzb_x_preferred":[
        "Maconcourt"
    ],
    "name:vie_x_preferred":[
        "Maconcourt"
    ],
    "name:vol_x_preferred":[
        "Maconcourt"
    ],
    "name:war_x_preferred":[
        "Maconcourt"
    ],
    "name:zho_x_preferred":[
        "\u9a6c\u5b54\u5e93\u5c14"
    ],
    "wof:name":"Maconcourt",
    "wof:placetype":"locality"
},
  "geometry": {"coordinates":[5.24077,48.38494],"type":"Point"}
}