{
  "type": "Feature",
  "properties": {
    "gn:admin1_code":"44",
    "gn:admin2_code":"52",
    "gn:admin3_code":"523",
    "gn:admin4_code":"52456",
    "gn:asciiname":"Maconcourt",
    "gn:country_code":"FR",
    "gn:dem":281,
    "gn:feature_class":"P",
    "gn:feature_code":"PPL",
    "gn:name":"Maconcourt",
    "gn:population":0,
    "gn:timezone":"Europe/Paris",
    "iso:country":"FR",
    "wof:name":"Maconcourt",
    "wof:placetype":"locality"
},
  "geometry": {"coordinates":[5.24077,48.38494],"type":"Point"}
}