{
  "type": "Feature",
  "properties": {
    "gn:admin1_code":"75",
    "gn:admin2_code":"19",
    "gn:admin3_code":"192",
    "gn:admin4_code":"19034",
    "gn:asciiname":"Saint-Mathurin-Leobazel",
    "gn:country_code":"FR",
    "gn:dem":546,
    "gn:feature_class":"P",
    "gn:feature_code":"PPL",
    "gn:name":"Saint-Mathurin-L\u00e9obazel",
    "gn:population":0,
    "gn:timezone":"Europe/Paris",
    "iso:country":"FR",
    "name:und_x_variant":[
        "Saint-Mathurin",
        "Saint-Mathurin-L\u00e9obazel"
    ],
    "wof:name":"Saint-Mathurin-Leobazel",
    "wof:placetype":"locality"
},
  "geometry": {"coordinates":[2.01459,45.01823],"type":"Point"}
}