{
  "type": "Feature",
  "properties": {
    "gn:admin1_code":"75",
    "gn:admin2_code":"86",
    "gn:admin3_code":"862",
    "gn:admin4_code":"86120",
    "gn:asciiname":"Saint-Remy-en-Montmorillon",
    "gn:country_code":"FR",
    "gn:dem":208,
    "gn:feature_class":"P",
    "gn:feature_code":"PPL",
    "gn:name":"Saint-R\u00e9my-en-Montmorillon",
    "gn:population":0,
    "gn:timezone":"Europe/Paris",
    "iso:country":"FR",
    "name:und_x_variant":[
        "Saint-Remy",
        "Saint-R\u00e9my-en-Montmorillon"
    ],
    "wof:name":"Saint-Remy-en-Montmorillon",
    "wof:placetype":"locality"
},
  "geometry": {"coordinates":[0.89774,46.29213],"type":"Point"}
}