{
  "type": "Feature",
  "properties": {
    "gn:admin1_code":"84",
    "gn:admin2_code":"69",
    "gn:admin3_code":"692",
    "gn:admin4_code":"69026",
    "gn:asciiname":"Le Breuil",
    "gn:country_code":"FR",
    "gn:dem":252,
    "gn:feature_class":"P",
    "gn:feature_code":"PPL",
    "gn:name":"Le Breuil",
    "gn:population":385,
    "gn:timezone":"Europe/Paris",
    "iso:country":"FR",
    "wof:name":"Le Breuil",
    "wof:placetype":"locality",
    "wof:population":385
},
  "geometry": {"coordinates":[4.58687,45.89379],"type":"Point"}
}