{
  "type": "Feature",
  "properties": {
    "frgov:code_epci":"200040574",
    "frgov:insee_arr":"2",
    "frgov:insee_com":"69026",
    "frgov:insee_dep":"69",
    "frgov:insee_reg":"84",
    "frgov:nom_com":"Le Breuil",
    "frgov:nom_com_m":"LE BREUIL",
    "frgov:nom_dep":"RHONE",
    "frgov:nom_reg":"AUVERGNE-RHONE-ALPES",
    "frgov:statut":"Commune simple",
    "gn:admin1_code":"84",
    "gn:admin2_code":"69",
    "gn:admin3_code":"692",
    "gn:admin4_code":"69026",
    "gn:asciiname":"Le Breuil",
    "gn:country_code":"FR",
    "gn:dem":252,
    "gn:feature_class":"P",
    "gn:feature_code":"PPL",
    "gn:name":"Le Breuil",
    "gn:population":385,
    "gn:timezone":"Europe/Paris",
    "iso:country":"FR",
    "name:ceb_x_preferred":[
        "Le Breuil"
    ],
    "name:deu_x_preferred":[
        "Le Breuil"
    ],
    "name:fra_x_preferred":[
        "Le Breuil"
    ],
    "name:hbs_x_preferred":[
        "Breuil"
    ],
    "name:ita_x_preferred":[
        "Le Breuil"
    ],
    "name:lmo_x_preferred":[
        "Le Breuil"
    ],
    "name:nds_x_preferred":[
        "Le Breuil"
    ],
    "name:nld_x_preferred":[
        "Le Breuil"
    ],
    "name:pms_x_preferred":[
        "Le Breuil"
    ],
    "name:pol_x_preferred":[
        "Le Breuil"
    ],
    "name:por_x_preferred":[
        "Le Breuil"
    ],
    "name:rus_x_preferred":[
        "\u041b\u0435-\u0411\u0440\u0451\u0439"
    ],
    "name:slk_x_preferred":[
        "Le Breuil"
    ],
    "name:spa_x_preferred":[
        "Le Breuil"
    ],
    "name:sqi_x_preferred":[
        "Le Breuil"
    ],
    "name:srp_x_preferred":[
        "\u0411\u0440\u0435\u0458"
    ],
    "name:swe_x_preferred":[
        "Le Breuil"
    ],
    "name:ukr_x_preferred":[
        "\u041b\u0435-\u0411\u0440\u0435\u0439"
    ],
    "qs:a0":"France",
    "qs:a1":"RHONE",
    "qs:a1_lc":"69",
    "qs:a1r":"RHONE-ALPES",
    "qs:a1r_lc":"82",
    "qs:a2_lc":"06",
    "qs:a2r_lc":"2",
    "qs:adm0":"France",
    "qs:adm0_a3":"FRA",
    "qs:la":"LE BREUIL",
    "qs:la_lc":"69026",
    "qs:level":"localadmin",
    "qs:type":"Commune simple",
    "wof:coterminous":[
        404370867
    ],
    "wof:name":"Le Breuil",
    "wof:placetype":"locality",
    "wof:placetype_local":"Commune simple",
    "wof:population":385
},
  "geometry": {"coordinates":[4.58687,45.89379],"type":"Point"}
}