{
  "type": "Feature",
  "properties": {
    "gn:admin1_code":"84",
    "gn:admin2_code":"43",
    "gn:admin3_code":"431",
    "gn:admin4_code":"43220",
    "gn:asciiname":"La Bastide",
    "gn:country_code":"FR",
    "gn:dem":932,
    "gn:feature_class":"P",
    "gn:feature_code":"PPL",
    "gn:name":"La Bastide",
    "gn:population":0,
    "gn:timezone":"Europe/Paris",
    "iso:country":"FR",
    "name:bre_x_preferred":[
        "La Bastide"
    ],
    "name:ceb_x_preferred":[
        "La Bastide"
    ],
    "name:deu_x_preferred":[
        "La Bastide"
    ],
    "name:eus_x_preferred":[
        "La Bastide"
    ],
    "name:fra_x_preferred":[
        "La Bastide"
    ],
    "name:ita_x_preferred":[
        "La Bastide"
    ],
    "name:lmo_x_preferred":[
        "La Bastide"
    ],
    "name:nds_x_preferred":[
        "La Bastide"
    ],
    "name:nld_x_preferred":[
        "La Bastide"
    ],
    "name:por_x_preferred":[
        "La Bastide"
    ],
    "name:rus_x_preferred":[
        "\u041b\u0430-\u0411\u0430\u0441\u0442\u0438\u0434"
    ],
    "name:scn_x_preferred":[
        "La Bastide"
    ],
    "name:slk_x_preferred":[
        "La Bastide"
    ],
    "name:spa_x_preferred":[
        "La Bastide"
    ],
    "name:swe_x_preferred":[
        "La Bastide"
    ],
    "name:ukr_x_preferred":[
        "\u041b\u0430-\u0411\u0430\u0441\u0442\u0456\u0434"
    ],
    "wof:name":"La Bastide",
    "wof:placetype":"locality"
},
  "geometry": {"coordinates":[3.65577,44.92646],"type":"Point"}
}