{
  "type": "Feature",
  "properties": {
    "gn:admin1_code":"75",
    "gn:admin2_code":"47",
    "gn:admin3_code":"472",
    "gn:admin4_code":"47122",
    "gn:asciiname":"Pierre-Bernat",
    "gn:country_code":"FR",
    "gn:dem":98,
    "gn:feature_class":"P",
    "gn:feature_code":"PPL",
    "gn:name":"Pierre-Bernat",
    "gn:population":0,
    "gn:timezone":"Europe/Paris",
    "iso:country":"FR",
    "wof:name":"Pierre-Bernat",
    "wof:placetype":"locality"
},
  "geometry": {"coordinates":[0.37139,44.49703],"type":"Point"}
}