{
  "type": "Feature",
  "properties": {
    "iso:country":"FR",
    "name:eng_x_preferred":[
        "Pont-Yblon"
    ],
    "name:fra_x_preferred":[
        "Pont-Yblon"
    ],
    "wof:name":"Pont-Yblon",
    "wof:placetype":"neighbourhood"
},
  "geometry": {"coordinates":[2.43963792716889,48.9511417644513],"type":"Point"}
}