{
  "type": "Feature",
  "properties": {
    "gn:admin1_code":"84",
    "gn:admin2_code":"07",
    "gn:admin3_code":"073",
    "gn:admin4_code":"07274",
    "gn:asciiname":"Saint-Maurice-en-Chalencon",
    "gn:country_code":"FR",
    "gn:dem":653,
    "gn:feature_class":"P",
    "gn:feature_code":"PPL",
    "gn:name":"Saint-Maurice-en-Chalencon",
    "gn:population":0,
    "gn:timezone":"Europe/Paris",
    "iso:country":"FR",
    "name:bug_x_preferred":[
        "Saint-Maurice-en-Chalencon"
    ],
    "name:ceb_x_preferred":[
        "Saint-Maurice-en-Chalencon"
    ],
    "name:deu_x_preferred":[
        "Saint-Maurice-en-Chalencon"
    ],
    "name:eus_x_preferred":[
        "Saint-Maurice-en-Chalencon"
    ],
    "name:fra_x_preferred":[
        "Saint-Maurice-en-Chalencon"
    ],
    "name:hun_x_preferred":[
        "Saint-Maurice-en-Chalencon"
    ],
    "name:ita_x_preferred":[
        "Saint-Maurice-en-Chalencon"
    ],
    "name:lat_x_preferred":[
        "Saint-Maurice-en-Chalencon"
    ],
    "name:lmo_x_preferred":[
        "Saint-Maurice-en-Chalencon"
    ],
    "name:mlg_x_preferred":[
        "Saint-Maurice-en-Chalencon"
    ],
    "name:msa_x_preferred":[
        "Saint-Maurice-en-Chalencon"
    ],
    "name:nld_x_preferred":[
        "Saint-Maurice-en-Chalencon"
    ],
    "name:pms_x_preferred":[
        "Saint-Maurice-en-Chalencon"
    ],
    "name:pol_x_preferred":[
        "Saint-Maurice-en-Chalencon"
    ],
    "name:por_x_preferred":[
        "Saint-Maurice-en-Chalencon"
    ],
    "name:ron_x_preferred":[
        "Saint-Maurice-en-Chalencon"
    ],
    "name:rus_x_preferred":[
        "\u0421\u0435\u043d-\u041c\u043e\u0440\u0438\u0441-\u0430\u043d-\u0428\u0430\u043b\u0430\u043d\u043a\u043e\u043d"
    ],
    "name:slk_x_preferred":[
        "Saint-Maurice-en-Chalencon"
    ],
    "name:spa_x_preferred":[
        "Saint-Maurice-en-Chalencon"
    ],
    "name:sqi_x_preferred":[
        "Saint-Maurice-en-Chalencon"
    ],
    "name:swe_x_preferred":[
        "Saint-Maurice-en-Chalencon"
    ],
    "name:ukr_x_preferred":[
        "\u0421\u0435\u043d-\u041c\u043e\u0440\u0438\u0441-\u0430\u043d-\u0428\u0430\u043b\u0430\u043d\u043a\u043e\u043d"
    ],
    "name:urd_x_preferred":[
        "\u0633\u06cc\u0646\u0679-\u0645\u0648\u0631\u06cc\u0633-\u0627\u06cc\u0646 -\u0686\u0644\u0646\u06a9\u0648\u0646"
    ],
    "name:uzb_x_preferred":[
        "Saint-Maurice-en-Chalencon"
    ],
    "name:vie_x_preferred":[
        "Saint-Maurice-en-Chalencon"
    ],
    "name:vol_x_preferred":[
        "Saint-Maurice-en-Chalencon"
    ],
    "name:war_x_preferred":[
        "Saint-Maurice-en-Chalencon"
    ],
    "name:zho_x_preferred":[
        "\u6c99\u6717\u5b54\u5730\u533a\u5723\u83ab\u91cc\u514b"
    ],
    "wof:name":"Saint-Maurice-en-Chalencon",
    "wof:placetype":"locality"
},
  "geometry": {"coordinates":[4.59098,44.84902],"type":"Point"}
}