{
  "type": "Feature",
  "properties": {
    "gn:admin1_code":"84",
    "gn:admin2_code":"07",
    "gn:admin3_code":"073",
    "gn:admin4_code":"07274",
    "gn:asciiname":"Saint-Maurice-en-Chalencon",
    "gn:country_code":"FR",
    "gn:dem":653,
    "gn:feature_class":"P",
    "gn:feature_code":"PPL",
    "gn:name":"Saint-Maurice-en-Chalencon",
    "gn:population":0,
    "gn:timezone":"Europe/Paris",
    "iso:country":"FR",
    "wof:name":"Saint-Maurice-en-Chalencon",
    "wof:placetype":"locality"
},
  "geometry": {"coordinates":[4.59098,44.84902],"type":"Point"}
}