{
  "type": "Feature",
  "properties": {
    "gn:admin1_code":"32",
    "gn:admin2_code":"80",
    "gn:admin3_code":"801",
    "gn:admin4_code":"80343",
    "gn:asciiname":"Witaineglise",
    "gn:country_code":"FR",
    "gn:dem":136,
    "gn:feature_class":"P",
    "gn:feature_code":"PPL",
    "gn:name":"Witain\u00e9glise",
    "gn:population":0,
    "gn:timezone":"Europe/Paris",
    "iso:country":"FR",
    "wof:name":"Witaineglise",
    "wof:placetype":"locality"
},
  "geometry": {"coordinates":[1.68333,49.95306],"type":"Point"}
}