{
  "type": "Feature",
  "properties": {
    "gn:admin1_code":"24",
    "gn:admin2_code":"28",
    "gn:admin3_code":"283",
    "gn:admin4_code":"28393",
    "gn:asciiname":"Saint-Cheron-des-Champs",
    "gn:country_code":"FR",
    "gn:dem":161,
    "gn:feature_class":"P",
    "gn:feature_code":"PPL",
    "gn:name":"Saint-Ch\u00e9ron-des-Champs",
    "gn:population":0,
    "gn:timezone":"Europe/Paris",
    "iso:country":"FR",
    "name:und_x_variant":[
        "Saint-Ch\u00e9ron",
        "Saint-Ch\u00e9ron-des-Champs"
    ],
    "wof:name":"Saint-Cheron-des-Champs",
    "wof:placetype":"locality"
},
  "geometry": {"coordinates":[1.45078,48.57441],"type":"Point"}
}