{
  "type": "Feature",
  "properties": {
    "gn:admin1_code":"75",
    "gn:admin2_code":"24",
    "gn:admin3_code":"244",
    "gn:admin4_code":"24263",
    "gn:asciiname":"Cabirat",
    "gn:country_code":"FR",
    "gn:dem":241,
    "gn:feature_class":"P",
    "gn:feature_code":"PPL",
    "gn:name":"Cabirat",
    "gn:population":0,
    "gn:timezone":"Europe/Paris",
    "iso:country":"FR",
    "wof:name":"Cabirat",
    "wof:placetype":"locality"
},
  "geometry": {"coordinates":[1.00505,44.69432000000001],"type":"Point"}
}