{
  "type": "Feature",
  "properties": {
    "gn:admin1_code":"11",
    "gn:admin2_code":"77",
    "gn:admin3_code":"773",
    "gn:admin4_code":"77325",
    "gn:asciiname":"Grand Peugny",
    "gn:country_code":"FR",
    "gn:dem":54,
    "gn:feature_class":"P",
    "gn:feature_code":"PPL",
    "gn:name":"Grand Peugny",
    "gn:population":0,
    "gn:timezone":"Europe/Paris",
    "iso:country":"FR",
    "wof:name":"Grand Peugny",
    "wof:placetype":"locality"
},
  "geometry": {"coordinates":[3.25786,48.42916],"type":"Point"}
}