{
  "type": "Feature",
  "properties": {
    "gn:admin1_code":"93",
    "gn:admin2_code":"06",
    "gn:admin3_code":"062",
    "gn:admin4_code":"06083",
    "gn:asciiname":"Monti",
    "gn:country_code":"FR",
    "gn:dem":191,
    "gn:feature_class":"P",
    "gn:feature_code":"PPL",
    "gn:name":"Monti",
    "gn:population":0,
    "gn:timezone":"Europe/Paris",
    "iso:country":"FR",
    "name:ceb_x_preferred":[
        "Monti"
    ],
    "name:ces_x_preferred":[
        "Monti"
    ],
    "name:deu_x_preferred":[
        "Monti"
    ],
    "name:epo_x_preferred":[
        "Monti"
    ],
    "name:fra_x_preferred":[
        "Monti"
    ],
    "name:heb_x_preferred":[
        "\u05de\u05d5\u05e0\u05d8\u05d9"
    ],
    "name:ita_x_preferred":[
        "Monti"
    ],
    "name:jpn_x_preferred":[
        "\u30e2\u30f3\u30c6\u30a3"
    ],
    "name:nld_x_preferred":[
        "Monti"
    ],
    "name:nor_x_preferred":[
        "Monti"
    ],
    "name:pms_x_preferred":[
        "Monti"
    ],
    "name:pol_x_preferred":[
        "Monti"
    ],
    "name:rus_x_preferred":[
        "\u041c\u043e\u043d\u0442\u0438"
    ],
    "name:spa_x_preferred":[
        "Monti"
    ],
    "name:srp_x_preferred":[
        "Monti"
    ],
    "name:swe_x_preferred":[
        "Monti"
    ],
    "name:ukr_x_preferred":[
        "\u041c\u043e\u043d\u0442\u0456"
    ],
    "name:vol_x_preferred":[
        "Monti"
    ],
    "wof:name":"Monti",
    "wof:placetype":"locality"
},
  "geometry": {"coordinates":[7.48509,43.80902],"type":"Point"}
}