{
  "type": "Feature",
  "properties": {
    "gn:admin1_code":"75",
    "gn:admin2_code":"86",
    "gn:admin3_code":"862",
    "gn:admin4_code":"86273",
    "gn:asciiname":"Saint-Pierre",
    "gn:country_code":"FR",
    "gn:dem":139,
    "gn:feature_class":"P",
    "gn:feature_code":"PPL",
    "gn:name":"Saint-Pierre",
    "gn:population":0,
    "gn:timezone":"Europe/Paris",
    "iso:country":"FR",
    "name:azb_x_preferred":[
        "\u0633\u0646-\u067e\u06cc\u0631"
    ],
    "name:bre_x_preferred":[
        "Saint-Pierre"
    ],
    "name:cat_x_preferred":[
        "Saint-Pierre"
    ],
    "name:ceb_x_preferred":[
        "Saint-Pierre"
    ],
    "name:ces_x_preferred":[
        "Saint-Pierre"
    ],
    "name:cos_x_preferred":[
        "San Petru"
    ],
    "name:cym_x_preferred":[
        "Saint-Pierre"
    ],
    "name:deu_x_preferred":[
        "Saint-Pierre"
    ],
    "name:epo_x_preferred":[
        "Saint-Pierre"
    ],
    "name:eus_x_preferred":[
        "Saint-Pierre"
    ],
    "name:fas_x_preferred":[
        "\u0633\u0646-\u067e\u06cc\u0631"
    ],
    "name:fin_x_preferred":[
        "Saint-Pierre"
    ],
    "name:fra_x_preferred":[
        "Saint-Pierre"
    ],
    "name:ita_x_preferred":[
        "Saint-Pierre"
    ],
    "name:jpn_x_preferred":[
        "\u30b5\u30f3\uff1d\u30d4\u30a8\u30fc\u30eb"
    ],
    "name:kor_x_preferred":[
        "\uc0dd\ud53c\uc5d0\ub974"
    ],
    "name:lit_x_preferred":[
        "Sen Pjeras"
    ],
    "name:nds_x_preferred":[
        "Saint-Pierre"
    ],
    "name:nld_x_preferred":[
        "Saint-Pierre"
    ],
    "name:nor_x_preferred":[
        "Saint-Pierre"
    ],
    "name:pms_x_preferred":[
        "Saint-Pierre"
    ],
    "name:pol_x_preferred":[
        "Saint-Pierre"
    ],
    "name:por_x_preferred":[
        "Saint-Pierre"
    ],
    "name:rus_x_preferred":[
        "\u0421\u0435\u043d-\u041f\u044c\u0435\u0440"
    ],
    "name:scn_x_preferred":[
        "San Petru"
    ],
    "name:slk_x_preferred":[
        "Saint-Pierre"
    ],
    "name:spa_x_preferred":[
        "Saint-Pierre"
    ],
    "name:srp_x_preferred":[
        "\u0421\u0435\u043d \u041f\u0458\u0435\u0440"
    ],
    "name:swe_x_preferred":[
        "Saint-Pierre"
    ],
    "name:ukr_x_preferred":[
        "\u0421\u0435\u043d-\u041f'\u0454\u0440"
    ],
    "name:wln_x_preferred":[
        "Sint-Pire"
    ],
    "name:zho_x_preferred":[
        "\u5723\u76ae\u57c3\u5c14"
    ],
    "wof:name":"Saint-Pierre",
    "wof:placetype":"locality"
},
  "geometry": {"coordinates":[1.05666,46.46458],"type":"Point"}
}