{
  "type": "Feature",
  "properties": {
    "gn:admin1_code":"75",
    "gn:admin2_code":"86",
    "gn:admin3_code":"862",
    "gn:admin4_code":"86273",
    "gn:asciiname":"Saint-Pierre",
    "gn:country_code":"FR",
    "gn:dem":139,
    "gn:feature_class":"P",
    "gn:feature_code":"PPL",
    "gn:name":"Saint-Pierre",
    "gn:population":0,
    "gn:timezone":"Europe/Paris",
    "iso:country":"FR",
    "wof:name":"Saint-Pierre",
    "wof:placetype":"locality"
},
  "geometry": {"coordinates":[1.05666,46.46458],"type":"Point"}
}