{
  "type": "Feature",
  "properties": {
    "gn:country":"FR",
    "gn:fcode":"PPL",
    "gn:population":0,
    "iso:country":"FR",
    "name:deu_x_preferred":[
        "Plascassier"
    ],
    "name:eng_x_preferred":[
        "Plascassier"
    ],
    "name:fra_x_preferred":[
        "Plascassier"
    ],
    "name:fra_x_variant":[
        "Puteau"
    ],
    "name:nld_x_preferred":[
        "Plascassier"
    ],
    "name:spa_x_preferred":[
        "Plascassier"
    ],
    "name:swe_x_preferred":[
        "Plascassier"
    ],
    "qs_pg:aaroncc":"FR",
    "qs_pg:gn_country":"FR",
    "qs_pg:gn_fcode":"PPL",
    "qs_pg:gn_pop":0,
    "qs_pg:name":"Plascassier",
    "qs_pg:name_adm0":"France",
    "qs_pg:name_adm1":"Provence-Alpes-C\u00f4te d'Azur",
    "qs_pg:photos":78,
    "qs_pg:photos_1k":16,
    "qs_pg:photos_9k":1,
    "qs_pg:photos_9r":3,
    "qs_pg:photos_all":78,
    "qs_pg:photos_sr":3,
    "qs_pg:pop_sr":0,
    "qs_pg:qs_pg_placetype":"locality",
    "qs_pg:qs_pg_placetype_gp":"Town",
    "qs_pg:woe_adm0":23424819,
    "woe:adm0_id":23424819,
    "woe:name_adm0":"France",
    "woe:name_adm1":"Provence-Alpes-C\u00f4te d'Azur",
    "woe:placetype":"Town",
    "wof:name":"Plascassier",
    "wof:placetype":"neighbourhood"
},
  "geometry": {"coordinates":[6.98333,43.65],"type":"Point"}
}