{
  "type": "Feature",
  "properties": {
    "gn:admin1_code":"94",
    "gn:admin2_code":"2A",
    "gn:admin3_code":"2A4",
    "gn:admin4_code":"2A189",
    "gn:asciiname":"Cappicciolo",
    "gn:country_code":"FR",
    "gn:dem":37,
    "gn:feature_class":"P",
    "gn:feature_code":"PPL",
    "gn:name":"Cappicciolo",
    "gn:population":0,
    "gn:timezone":"Europe/Paris",
    "iso:country":"FR",
    "wof:name":"Cappicciolo",
    "wof:placetype":"locality"
},
  "geometry": {"coordinates":[8.87143,41.69726],"type":"Point"}
}