{
  "type": "Feature",
  "properties": {
    "gn:admin1_code":"76",
    "gn:admin2_code":"12",
    "gn:admin3_code":"121",
    "gn:admin4_code":"12220",
    "gn:asciiname":"Mas Trinquie",
    "gn:country_code":"FR",
    "gn:dem":737,
    "gn:feature_class":"P",
    "gn:feature_code":"PPL",
    "gn:name":"Mas Trinqui\u00e9",
    "gn:population":0,
    "gn:timezone":"Europe/Paris",
    "iso:country":"FR",
    "wof:name":"Mas Trinquie",
    "wof:placetype":"locality"
},
  "geometry": {"coordinates":[3.18646,43.95813],"type":"Point"}
}