{
  "type": "Feature",
  "properties": {
    "gn:admin1_code":"84",
    "gn:admin2_code":"43",
    "gn:admin3_code":"432",
    "gn:admin4_code":"43113",
    "gn:asciiname":"La Collang",
    "gn:country_code":"FR",
    "gn:dem":860,
    "gn:feature_class":"P",
    "gn:feature_code":"PPL",
    "gn:name":"La Collang",
    "gn:population":0,
    "gn:timezone":"Europe/Paris",
    "iso:country":"FR",
    "name:und_x_variant":[
        "La Collange",
        "La Collang"
    ],
    "wof:name":"La Collang",
    "wof:placetype":"locality"
},
  "geometry": {"coordinates":[3.98534,44.98038],"type":"Point"}
}