{
  "type": "Feature",
  "properties": {
    "gn:admin1_code":"84",
    "gn:admin2_code":"63",
    "gn:admin3_code":"634",
    "gn:admin4_code":"63208",
    "gn:asciiname":"Salpaleine",
    "gn:country_code":"FR",
    "gn:dem":479,
    "gn:feature_class":"P",
    "gn:feature_code":"PPL",
    "gn:name":"Salpaleine",
    "gn:population":0,
    "gn:timezone":"Europe/Paris",
    "iso:country":"FR",
    "wof:name":"Salpaleine",
    "wof:placetype":"locality"
},
  "geometry": {"coordinates":[3.02811,46.09093],"type":"Point"}
}