{
  "type": "Feature",
  "properties": {
    "gn:admin1_code":"94",
    "gn:admin2_code":"2A",
    "gn:admin3_code":"2A4",
    "gn:admin4_code":"2A362",
    "gn:asciiname":"Vardiola",
    "gn:country_code":"FR",
    "gn:dem":28,
    "gn:feature_class":"P",
    "gn:feature_code":"PPL",
    "gn:name":"Vardiola",
    "gn:population":0,
    "gn:timezone":"Europe/Paris",
    "iso:country":"FR",
    "wof:name":"Vardiola",
    "wof:placetype":"locality"
},
  "geometry": {"coordinates":[9.38612,41.69371],"type":"Point"}
}