{
  "type": "Feature",
  "properties": {
    "gn:admin1_code":"11",
    "gn:admin2_code":"77",
    "gn:admin3_code":"773",
    "gn:admin4_code":"77289",
    "gn:asciiname":"Maulny",
    "gn:country_code":"FR",
    "gn:dem":75,
    "gn:feature_class":"P",
    "gn:feature_code":"PPL",
    "gn:name":"Maulny",
    "gn:population":0,
    "gn:timezone":"Europe/Paris",
    "iso:country":"FR",
    "wof:name":"Maulny",
    "wof:placetype":"locality"
},
  "geometry": {"coordinates":[3.3916,48.50763],"type":"Point"}
}