{
  "type": "Feature",
  "properties": {
    "gn:admin1_code":"76",
    "gn:admin2_code":"30",
    "gn:admin3_code":"301",
    "gn:admin4_code":"30270",
    "gn:asciiname":"La Barriere",
    "gn:country_code":"FR",
    "gn:dem":250,
    "gn:feature_class":"P",
    "gn:feature_code":"PPL",
    "gn:name":"La Barri\u00e9re",
    "gn:population":0,
    "gn:timezone":"Europe/Paris",
    "iso:country":"FR",
    "wof:name":"La Barriere",
    "wof:placetype":"locality"
},
  "geometry": {"coordinates":[4.03333,44.11667],"type":"Point"}
}