{
  "type": "Feature",
  "properties": {
    "gn:admin1_code":"75",
    "gn:admin2_code":"86",
    "gn:admin3_code":"861",
    "gn:admin4_code":"86032",
    "gn:asciiname":"Les Piqueteries",
    "gn:country_code":"FR",
    "gn:dem":74,
    "gn:feature_class":"P",
    "gn:feature_code":"PPL",
    "gn:name":"Les Piqueteries",
    "gn:population":0,
    "gn:timezone":"Europe/Paris",
    "iso:country":"FR",
    "name:und_x_variant":[
        "Les Riqueteries",
        "Les Piqueteries"
    ],
    "wof:name":"Les Piqueteries",
    "wof:placetype":"locality"
},
  "geometry": {"coordinates":[0.53974,46.68951],"type":"Point"}
}