{
  "type": "Feature",
  "properties": {
    "gn:admin1_code":"27",
    "gn:admin2_code":"71",
    "gn:admin3_code":"711",
    "gn:admin4_code":"71103.0",
    "gn:asciiname":"Charmoy-la-Ville",
    "gn:country_code":"FR",
    "gn:dem":358,
    "gn:feature_class":"P",
    "gn:feature_code":"PPL",
    "gn:name":"Charmoy-la-Ville",
    "gn:population":0,
    "gn:timezone":"Europe/Paris",
    "iso:country":"FR",
    "wof:name":"Charmoy-la-Ville",
    "wof:placetype":"locality"
},
  "geometry": {"coordinates":[4.32881,46.77642],"type":"Point"}
}