{
  "type": "Feature",
  "properties": {
    "iso:country":"FR",
    "name:eng_x_preferred":[
        "Plant"
    ],
    "name:fra_x_preferred":[
        "Plant"
    ],
    "name:fra_x_variant":[
        "Le Plant"
    ],
    "wof:name":"Plant",
    "wof:placetype":"neighbourhood"
},
  "geometry": {"coordinates":[2.49871399127917,48.82103692060412],"type":"Point"}
}