{
  "type": "Feature",
  "properties": {
    "gn:admin1_code":"75",
    "gn:admin2_code":"19",
    "gn:admin3_code":"191",
    "gn:admin4_code":"19093",
    "gn:asciiname":"La Brande",
    "gn:country_code":"FR",
    "gn:dem":300,
    "gn:feature_class":"P",
    "gn:feature_code":"PPL",
    "gn:name":"La Brande",
    "gn:population":0,
    "gn:timezone":"Europe/Paris",
    "iso:country":"FR",
    "wof:name":"La Brande",
    "wof:placetype":"locality"
},
  "geometry": {"coordinates":[1.551,45.10006],"type":"Point"}
}