{
  "type": "Feature",
  "properties": {
    "gn:admin1_code":"24",
    "gn:admin2_code":"45",
    "gn:admin3_code":"453",
    "gn:admin4_code":"45214",
    "gn:asciiname":"Montigny",
    "gn:country_code":"FR",
    "gn:dem":128,
    "gn:feature_class":"P",
    "gn:feature_code":"PPL",
    "gn:name":"Montigny",
    "gn:population":277,
    "gn:timezone":"Europe/Paris",
    "iso:country":"FR",
    "wof:name":"Montigny",
    "wof:placetype":"locality",
    "wof:population":277
},
  "geometry": {"coordinates":[2.11487,48.11356],"type":"Point"}
}