{
  "type": "Feature",
  "properties": {
    "frgov:code_epci":"244500484",
    "frgov:insee_arr":"2",
    "frgov:insee_com":"45214",
    "frgov:insee_dep":"45",
    "frgov:insee_reg":"24",
    "frgov:nom_com":"Montigny",
    "frgov:nom_com_m":"MONTIGNY",
    "frgov:nom_dep":"LOIRET",
    "frgov:nom_reg":"CENTRE-VAL DE LOIRE",
    "frgov:statut":"Commune simple",
    "gn:admin1_code":"24",
    "gn:admin2_code":"45",
    "gn:admin3_code":"453",
    "gn:admin4_code":"45214",
    "gn:asciiname":"Montigny",
    "gn:country_code":"FR",
    "gn:dem":128,
    "gn:feature_class":"P",
    "gn:feature_code":"PPL",
    "gn:name":"Montigny",
    "gn:population":277,
    "gn:timezone":"Europe/Paris",
    "iso:country":"FR",
    "name:bre_x_preferred":[
        "Montigny"
    ],
    "name:cat_x_preferred":[
        "Montigny"
    ],
    "name:ceb_x_preferred":[
        "Montigny"
    ],
    "name:ces_x_preferred":[
        "Montigny"
    ],
    "name:deu_x_preferred":[
        "Montigny"
    ],
    "name:epo_x_preferred":[
        "Montigny"
    ],
    "name:fas_x_preferred":[
        "\u0645\u0648\u0646\u062a\u06cc\u0646\u06cc\u0647"
    ],
    "name:fra_x_preferred":[
        "Montigny"
    ],
    "name:hun_x_preferred":[
        "Montigny"
    ],
    "name:ita_x_preferred":[
        "Montigny"
    ],
    "name:jpn_x_preferred":[
        "\u30e2\u30f3\u30c6\u30a3\u30cb\u30fc"
    ],
    "name:nds_x_preferred":[
        "Montigny"
    ],
    "name:nld_x_preferred":[
        "Montigny"
    ],
    "name:oci_x_preferred":[
        "Montigny"
    ],
    "name:pms_x_preferred":[
        "Montigny"
    ],
    "name:pol_x_preferred":[
        "Montigny"
    ],
    "name:por_x_preferred":[
        "Montigny"
    ],
    "name:rus_x_preferred":[
        "\u041c\u043e\u043d\u0442\u0438\u043d\u044c\u0438"
    ],
    "name:sco_x_preferred":[
        "Montigny"
    ],
    "name:slk_x_preferred":[
        "Montigny"
    ],
    "name:spa_x_preferred":[
        "Montigny"
    ],
    "name:swe_x_preferred":[
        "Montigny"
    ],
    "name:ukr_x_preferred":[
        "\u041c\u043e\u043d\u0442\u0456\u043d\u044c\u0457"
    ],
    "name:zho_x_preferred":[
        "\u8499\u8482\u5c3c"
    ],
    "qs:a0":"France",
    "qs:a1":"LOIRET",
    "qs:a1_lc":"45",
    "qs:a1r":"CENTRE",
    "qs:a1r_lc":"24",
    "qs:a2_lc":"26",
    "qs:a2r_lc":"3",
    "qs:adm0":"France",
    "qs:adm0_a3":"FRA",
    "qs:la":"MONTIGNY",
    "qs:la_lc":"45214",
    "qs:level":"localadmin",
    "qs:type":"Commune simple",
    "wof:coterminous":[
        404379295
    ],
    "wof:name":"Montigny",
    "wof:placetype":"locality",
    "wof:placetype_local":"Commune simple",
    "wof:population":277
},
  "geometry": {"coordinates":[2.11487,48.11356],"type":"Point"}
}