{
  "type": "Feature",
  "properties": {
    "gn:admin1_code":"27",
    "gn:admin2_code":"89",
    "gn:admin3_code":"893",
    "gn:admin4_code":"89195",
    "gn:asciiname":"Les Epenards",
    "gn:country_code":"FR",
    "gn:dem":89,
    "gn:feature_class":"P",
    "gn:feature_code":"PPL",
    "gn:name":"Les \u00c9penards",
    "gn:population":0,
    "gn:timezone":"Europe/Paris",
    "iso:country":"FR",
    "wof:name":"Les Epenards",
    "wof:placetype":"locality"
},
  "geometry": {"coordinates":[3.26603,48.14559000000001],"type":"Point"}
}