{
  "type": "Feature",
  "properties": {
    "gn:admin1_code":"11",
    "gn:admin2_code":"77",
    "gn:admin3_code":"773",
    "gn:admin4_code":"77113",
    "gn:asciiname":"Les Petits Courbons",
    "gn:country_code":"FR",
    "gn:dem":154,
    "gn:feature_class":"P",
    "gn:feature_code":"PPL",
    "gn:name":"Les Petits Courbons",
    "gn:population":0,
    "gn:timezone":"Europe/Paris",
    "iso:country":"FR",
    "wof:name":"Les Petits Courbons",
    "wof:placetype":"locality"
},
  "geometry": {"coordinates":[3.21567,48.73343],"type":"Point"}
}