{
  "type": "Feature",
  "properties": {
    "gn:admin1_code":"24",
    "gn:admin2_code":"28",
    "gn:admin3_code":"283",
    "gn:admin4_code":"28404",
    "gn:asciiname":"Nuisement",
    "gn:country_code":"FR",
    "gn:dem":133,
    "gn:feature_class":"P",
    "gn:feature_code":"PPL",
    "gn:name":"Nuisement",
    "gn:population":0,
    "gn:timezone":"Europe/Paris",
    "iso:country":"FR",
    "wof:name":"Nuisement",
    "wof:placetype":"locality"
},
  "geometry": {"coordinates":[1.38201,48.71556],"type":"Point"}
}