{
  "type": "Feature",
  "properties": {
    "gn:admin1_code":"11",
    "gn:admin2_code":"91",
    "gn:admin3_code":"913",
    "gn:admin4_code":"91249",
    "gn:asciiname":"Le Bajolet",
    "gn:country_code":"FR",
    "gn:dem":116,
    "gn:feature_class":"P",
    "gn:feature_code":"PPL",
    "gn:name":"Le Bajolet",
    "gn:population":0,
    "gn:timezone":"Europe/Paris",
    "iso:country":"FR",
    "name:und_x_variant":[
        "Bajolet",
        "Le Bajolet"
    ],
    "wof:name":"Le Bajolet",
    "wof:placetype":"locality"
},
  "geometry": {"coordinates":[2.0693,48.60581],"type":"Point"}
}