{
  "type": "Feature",
  "properties": {
    "gn:admin1_code":"84",
    "gn:admin2_code":"03",
    "gn:admin3_code":"033",
    "gn:admin4_code":"03235",
    "gn:asciiname":"Les Places",
    "gn:country_code":"FR",
    "gn:dem":277,
    "gn:feature_class":"P",
    "gn:feature_code":"PPL",
    "gn:name":"Les Places",
    "gn:population":0,
    "gn:timezone":"Europe/Paris",
    "iso:country":"FR",
    "wof:name":"Les Places",
    "wof:placetype":"locality"
},
  "geometry": {"coordinates":[3.47915,46.28824],"type":"Point"}
}