{
  "type": "Feature",
  "properties": {
    "gn:admin1_code":"75",
    "gn:admin2_code":"24",
    "gn:admin3_code":"241",
    "gn:admin4_code":"24260",
    "gn:asciiname":"Millac",
    "gn:country_code":"FR",
    "gn:dem":161,
    "gn:feature_class":"P",
    "gn:feature_code":"PPL",
    "gn:name":"Millac",
    "gn:population":0,
    "gn:timezone":"Europe/Paris",
    "iso:country":"FR",
    "name:cat_x_preferred":[
        "Milhac"
    ],
    "name:ceb_x_preferred":[
        "Millac"
    ],
    "name:deu_x_preferred":[
        "Millac"
    ],
    "name:eus_x_preferred":[
        "Millac"
    ],
    "name:fra_x_preferred":[
        "Millac"
    ],
    "name:hun_x_preferred":[
        "Millac"
    ],
    "name:ita_x_preferred":[
        "Millac"
    ],
    "name:lat_x_preferred":[
        "Millac"
    ],
    "name:mlg_x_preferred":[
        "Millac"
    ],
    "name:msa_x_preferred":[
        "Millac"
    ],
    "name:nld_x_preferred":[
        "Millac"
    ],
    "name:oci_x_preferred":[
        "Milhac"
    ],
    "name:pms_x_preferred":[
        "Millac"
    ],
    "name:pol_x_preferred":[
        "Millac"
    ],
    "name:por_x_preferred":[
        "Millac"
    ],
    "name:ron_x_preferred":[
        "Millac"
    ],
    "name:slk_x_preferred":[
        "Millac"
    ],
    "name:spa_x_preferred":[
        "Millac"
    ],
    "name:swe_x_preferred":[
        "Millac"
    ],
    "name:ukr_x_preferred":[
        "\u041c\u0456\u044f\u043a"
    ],
    "name:vie_x_preferred":[
        "Millac"
    ],
    "name:vol_x_preferred":[
        "Millac"
    ],
    "name:war_x_preferred":[
        "Millac"
    ],
    "name:zho_x_preferred":[
        "\u7c73\u62c9\u514b"
    ],
    "wof:name":"Millac",
    "wof:placetype":"locality"
},
  "geometry": {"coordinates":[0.79375,44.88666],"type":"Point"}
}