{
  "type": "Feature",
  "properties": {
    "gn:admin1_code":"27",
    "gn:admin2_code":"89",
    "gn:admin3_code":"891",
    "gn:admin4_code":"89439",
    "gn:asciiname":"Rebourseaux",
    "gn:country_code":"FR",
    "gn:dem":134,
    "gn:feature_class":"P",
    "gn:feature_code":"PPL",
    "gn:name":"Rebourseaux",
    "gn:population":0,
    "gn:timezone":"Europe/Paris",
    "iso:country":"FR",
    "wof:name":"Rebourseaux",
    "wof:placetype":"locality"
},
  "geometry": {"coordinates":[3.68872,47.95573],"type":"Point"}
}