{
  "type": "Feature",
  "properties": {
    "gn:admin1_code":"27",
    "gn:admin2_code":"58",
    "gn:admin3_code":"584",
    "gn:admin4_code":"58218.0",
    "gn:asciiname":"Cervenon",
    "gn:country_code":"FR",
    "gn:dem":277,
    "gn:feature_class":"P",
    "gn:feature_code":"PPL",
    "gn:name":"Cervenon",
    "gn:population":0,
    "gn:timezone":"Europe/Paris",
    "iso:country":"FR",
    "wof:name":"Cervenon",
    "wof:placetype":"locality"
},
  "geometry": {"coordinates":[3.34762,47.15676],"type":"Point"}
}