{
  "type": "Feature",
  "properties": {
    "gn:admin1_code":"44",
    "gn:admin2_code":"08",
    "gn:admin3_code":"081",
    "gn:admin4_code":"08370",
    "gn:asciiname":"Servion",
    "gn:country_code":"FR",
    "gn:dem":182,
    "gn:feature_class":"P",
    "gn:feature_code":"PPL",
    "gn:name":"Servion",
    "gn:population":0,
    "gn:timezone":"Europe/Paris",
    "iso:country":"FR",
    "name:als_x_preferred":[
        "Servion"
    ],
    "name:cat_x_preferred":[
        "Servion"
    ],
    "name:ceb_x_preferred":[
        "Servion"
    ],
    "name:deu_x_preferred":[
        "Servion"
    ],
    "name:epo_x_preferred":[
        "Servion"
    ],
    "name:eus_x_preferred":[
        "Servion"
    ],
    "name:fra_x_preferred":[
        "Servion"
    ],
    "name:ita_x_preferred":[
        "Servion"
    ],
    "name:lmo_x_preferred":[
        "Servion"
    ],
    "name:msa_x_preferred":[
        "Servion"
    ],
    "name:nld_x_preferred":[
        "Servion"
    ],
    "name:nno_x_preferred":[
        "Servion"
    ],
    "name:roh_x_preferred":[
        "Servion"
    ],
    "name:spa_x_preferred":[
        "Servion"
    ],
    "name:sqi_x_preferred":[
        "Servion"
    ],
    "name:swe_x_preferred":[
        "Servion"
    ],
    "name:vol_x_preferred":[
        "Servion"
    ],
    "name:war_x_preferred":[
        "Servion"
    ],
    "name:zho_x_preferred":[
        "\u585e\u5c14\u7ef4\u7fc1"
    ],
    "wof:name":"Servion",
    "wof:placetype":"locality"
},
  "geometry": {"coordinates":[4.50082,49.78404000000001],"type":"Point"}
}