{
  "type": "Feature",
  "properties": {
    "gn:admin1_code":"44",
    "gn:admin2_code":"08",
    "gn:admin3_code":"081",
    "gn:admin4_code":"08370",
    "gn:asciiname":"Servion",
    "gn:country_code":"FR",
    "gn:dem":182,
    "gn:feature_class":"P",
    "gn:feature_code":"PPL",
    "gn:name":"Servion",
    "gn:population":0,
    "gn:timezone":"Europe/Paris",
    "iso:country":"FR",
    "wof:name":"Servion",
    "wof:placetype":"locality"
},
  "geometry": {"coordinates":[4.50082,49.78404000000001],"type":"Point"}
}