{
  "type": "Feature",
  "properties": {
    "gn:admin1_code":"44",
    "gn:admin2_code":"08",
    "gn:admin3_code":"081",
    "gn:admin4_code":"08448",
    "gn:asciiname":"Nohan",
    "gn:country_code":"FR",
    "gn:dem":157,
    "gn:feature_class":"P",
    "gn:feature_code":"PPL",
    "gn:name":"Nohan",
    "gn:population":0,
    "gn:timezone":"Europe/Paris",
    "iso:country":"FR",
    "wof:name":"Nohan",
    "wof:placetype":"locality"
},
  "geometry": {"coordinates":[4.82111,49.88595],"type":"Point"}
}