{
  "type": "Feature",
  "properties": {
    "gn:admin1_code":"27",
    "gn:admin2_code":"89",
    "gn:admin3_code":"892",
    "gn:admin4_code":"89279.0",
    "gn:asciiname":"Puits-de-Bon",
    "gn:country_code":"FR",
    "gn:dem":269,
    "gn:feature_class":"P",
    "gn:feature_code":"PPL",
    "gn:name":"Puits-de-Bon",
    "gn:population":0,
    "gn:timezone":"Europe/Paris",
    "iso:country":"FR",
    "wof:name":"Puits-de-Bon",
    "wof:placetype":"locality"
},
  "geometry": {"coordinates":[3.95065,47.67957],"type":"Point"}
}