{
  "type": "Feature",
  "properties": {
    "gn:admin1_code":"53",
    "gn:admin2_code":"29",
    "gn:admin3_code":"294",
    "gn:admin4_code":"29028",
    "gn:asciiname":"Kersaudy",
    "gn:country_code":"FR",
    "gn:dem":54,
    "gn:feature_class":"P",
    "gn:feature_code":"PPL",
    "gn:name":"Kersaudy",
    "gn:population":0,
    "gn:timezone":"Europe/Paris",
    "iso:country":"FR",
    "wof:name":"Kersaudy",
    "wof:placetype":"locality"
},
  "geometry": {"coordinates":[-4.68333,48.05],"type":"Point"}
}