{
  "type": "Feature",
  "properties": {
    "iso:country":"FR",
    "name:eng_x_preferred":[
        "Hector Berlioz-Pablo Picasso"
    ],
    "name:fra_x_preferred":[
        "Hector Berlioz-Pablo Picasso"
    ],
    "wof:name":"Hector Berlioz-Pablo Picasso",
    "wof:placetype":"neighbourhood"
},
  "geometry": {"coordinates":[2.45334699496642,48.90554410698107],"type":"Point"}
}