{
  "type": "Feature",
  "properties": {
    "gn:admin1_code":"75",
    "gn:admin2_code":"86",
    "gn:admin3_code":"861",
    "gn:admin4_code":"86225",
    "gn:asciiname":"Frontenay-sur-Dive",
    "gn:country_code":"FR",
    "gn:dem":87,
    "gn:feature_class":"P",
    "gn:feature_code":"PPL",
    "gn:name":"Frontenay-sur-Dive",
    "gn:population":0,
    "gn:timezone":"Europe/Paris",
    "iso:country":"FR",
    "name:und_x_variant":[
        "Frontenay",
        "Frontenay-sur-Dives",
        "Frontenay-sur-Dive"
    ],
    "wof:name":"Frontenay-sur-Dive",
    "wof:placetype":"locality"
},
  "geometry": {"coordinates":[0.05425,46.8459],"type":"Point"}
}