{
  "type": "Feature",
  "properties": {
    "gn:admin1_code":"76",
    "gn:admin2_code":"12",
    "gn:admin3_code":"121",
    "gn:admin4_code":"12082",
    "gn:asciiname":"Belvezet",
    "gn:cc2":"FR",
    "gn:country_code":"FR",
    "gn:dem":810,
    "gn:feature_class":"P",
    "gn:feature_code":"PPL",
    "gn:name":"Belvezet",
    "gn:population":0,
    "gn:timezone":"Europe/Paris",
    "iso:country":"FR",
    "name:cat_x_preferred":[
        "B\u00e8lveser"
    ],
    "name:ceb_x_preferred":[
        "Belvezet"
    ],
    "name:deu_x_preferred":[
        "Belvezet"
    ],
    "name:eus_x_preferred":[
        "B\u00e8lveser"
    ],
    "name:fra_x_preferred":[
        "Belvezet"
    ],
    "name:hun_x_preferred":[
        "Belvezet"
    ],
    "name:ita_x_preferred":[
        "Belvezet"
    ],
    "name:kaz_x_preferred":[
        "\u0411\u0435\u043b\u044c\u0432\u0435\u0437\u0435"
    ],
    "name:lat_x_preferred":[
        "Belvezet"
    ],
    "name:lmo_x_preferred":[
        "Belvezet"
    ],
    "name:msa_x_preferred":[
        "Belvezet"
    ],
    "name:nld_x_preferred":[
        "Belvezet"
    ],
    "name:oci_x_preferred":[
        "B\u00e8lveser"
    ],
    "name:pms_x_preferred":[
        "Belvezet"
    ],
    "name:pol_x_preferred":[
        "Belvezet"
    ],
    "name:por_x_preferred":[
        "Belvezet"
    ],
    "name:ron_x_preferred":[
        "Belvezet"
    ],
    "name:slk_x_preferred":[
        "Belvezet"
    ],
    "name:spa_x_preferred":[
        "Belvezet"
    ],
    "name:sqi_x_preferred":[
        "Belvezet"
    ],
    "name:srp_x_preferred":[
        "\u0411\u0435\u043b\u0432\u0435\u0437\u0435"
    ],
    "name:swe_x_preferred":[
        "Belvezet"
    ],
    "name:ukr_x_preferred":[
        "\u0411\u0435\u043b\u044c\u0432\u0435\u0437\u0435"
    ],
    "name:und_x_variant":[
        "Belvezer"
    ],
    "name:vie_x_preferred":[
        "Belvezet"
    ],
    "name:vol_x_preferred":[
        "Belvezet"
    ],
    "name:war_x_preferred":[
        "Belvezet"
    ],
    "name:zho_x_preferred":[
        "\u8d1d\u5c14\u97e6\u6cfd"
    ],
    "wof:name":"Belvezet",
    "wof:placetype":"locality"
},
  "geometry": {"coordinates":[3.28405,43.94216],"type":"Point"}
}