{
  "type": "Feature",
  "properties": {
    "gn:admin1_code":"27",
    "gn:admin2_code":"58",
    "gn:admin3_code":"582",
    "gn:admin4_code":"58132",
    "gn:asciiname":"La Brosse",
    "gn:country_code":"FR",
    "gn:dem":254,
    "gn:feature_class":"P",
    "gn:feature_code":"PPL",
    "gn:name":"La Brosse",
    "gn:population":0,
    "gn:timezone":"Europe/Paris",
    "iso:country":"FR",
    "name:deu_x_preferred":[
        "La Brosse"
    ],
    "name:fra_x_preferred":[
        "La Brosse"
    ],
    "wof:name":"La Brosse",
    "wof:placetype":"locality"
},
  "geometry": {"coordinates":[3.57333,47.22143],"type":"Point"}
}