{
  "type": "Feature",
  "properties": {
    "gn:admin1_code":"75",
    "gn:admin2_code":"86",
    "gn:admin3_code":"861",
    "gn:admin4_code":"86111",
    "gn:asciiname":"Varenne",
    "gn:country_code":"FR",
    "gn:dem":87,
    "gn:feature_class":"P",
    "gn:feature_code":"PPL",
    "gn:name":"Varenne",
    "gn:population":0,
    "gn:timezone":"Europe/Paris",
    "iso:country":"FR",
    "name:fin_x_preferred":[
        "Varenne"
    ],
    "name:fra_x_preferred":[
        "Varenne"
    ],
    "name:ita_x_preferred":[
        "Varenne"
    ],
    "name:jpn_x_preferred":[
        "\u30f4\u30a1\u30ec\u30f3\u30cc"
    ],
    "name:swe_x_preferred":[
        "Varenne"
    ],
    "wof:name":"Varenne",
    "wof:placetype":"locality"
},
  "geometry": {"coordinates":[0.56667,46.85],"type":"Point"}
}