{
  "type": "Feature",
  "properties": {
    "gn:admin1_code":"44",
    "gn:admin2_code":"52",
    "gn:admin3_code":"521",
    "gn:admin4_code":"52211",
    "gn:asciiname":"Buxieres-les-Froncles",
    "gn:country_code":"FR",
    "gn:dem":239,
    "gn:feature_class":"P",
    "gn:feature_code":"PPL",
    "gn:name":"Buxi\u00e8res-l\u00e8s-Froncles",
    "gn:population":0,
    "gn:timezone":"Europe/Paris",
    "iso:country":"FR",
    "name:und_x_variant":[
        "Buxi\u00e8res",
        "Buxi\u00e8res-l\u00e8s-Froncles"
    ],
    "wof:name":"Buxieres-les-Froncles",
    "wof:placetype":"locality"
},
  "geometry": {"coordinates":[5.14931,48.29226],"type":"Point"}
}