{
  "type": "Feature",
  "properties": {
    "frgov:code_epci":"200034031",
    "frgov:insee_arr":"1",
    "frgov:insee_com":"81295",
    "frgov:insee_dep":"81",
    "frgov:insee_reg":"76",
    "frgov:nom_com":"Teillet",
    "frgov:nom_com_m":"TEILLET",
    "frgov:nom_dep":"TARN",
    "frgov:nom_reg":"OCCITANIE",
    "frgov:statut":"Commune simple",
    "gn:admin1_code":"76",
    "gn:admin2_code":"81",
    "gn:admin3_code":"811",
    "gn:admin4_code":"81295",
    "gn:asciiname":"Teillet",
    "gn:country_code":"FR",
    "gn:dem":491,
    "gn:feature_class":"P",
    "gn:feature_code":"PPL",
    "gn:name":"Teillet",
    "gn:population":0,
    "gn:timezone":"Europe/Paris",
    "iso:country":"FR",
    "name:cat_x_preferred":[
        "Telhet"
    ],
    "name:ceb_x_preferred":[
        "Teillet"
    ],
    "name:deu_x_preferred":[
        "Teillet"
    ],
    "name:eus_x_preferred":[
        "Teillet"
    ],
    "name:fra_x_preferred":[
        "Teillet"
    ],
    "name:hun_x_preferred":[
        "Teillet"
    ],
    "name:ita_x_preferred":[
        "Teillet"
    ],
    "name:lat_x_preferred":[
        "Teillet"
    ],
    "name:msa_x_preferred":[
        "Teillet"
    ],
    "name:nld_x_preferred":[
        "Teillet"
    ],
    "name:oci_x_preferred":[
        "Telhet"
    ],
    "name:pms_x_preferred":[
        "Teillet"
    ],
    "name:pol_x_preferred":[
        "Teillet"
    ],
    "name:por_x_preferred":[
        "Teillet"
    ],
    "name:ron_x_preferred":[
        "Teillet"
    ],
    "name:rus_x_preferred":[
        "\u0422\u0435\u0439\u0435"
    ],
    "name:slk_x_preferred":[
        "Teillet"
    ],
    "name:spa_x_preferred":[
        "Teillet"
    ],
    "name:swe_x_preferred":[
        "Teillet"
    ],
    "name:ukr_x_preferred":[
        "\u0422\u0435\u0454"
    ],
    "name:vie_x_preferred":[
        "Teillet"
    ],
    "name:vol_x_preferred":[
        "Teillet"
    ],
    "name:war_x_preferred":[
        "Teillet"
    ],
    "name:zho_x_preferred":[
        "\u6cf0\u8036"
    ],
    "qs:a0":"France",
    "qs:a1":"TARN",
    "qs:a1_lc":"81",
    "qs:a1r":"MIDI-PYRENEES",
    "qs:a1r_lc":"73",
    "qs:a2_lc":"01",
    "qs:a2r_lc":"1",
    "qs:adm0":"France",
    "qs:adm0_a3":"FRA",
    "qs:la":"TEILLET",
    "qs:la_lc":"81295",
    "qs:level":"localadmin",
    "qs:type":"Commune simple",
    "wof:coterminous":[
        404358619
    ],
    "wof:name":"Teillet",
    "wof:placetype":"locality",
    "wof:placetype_local":"Commune simple"
},
  "geometry": {"coordinates":[2.34,43.83528],"type":"Point"}
}