{
  "type": "Feature",
  "properties": {
    "gn:admin1_code":"84",
    "gn:admin2_code":"63",
    "gn:admin3_code":"633",
    "gn:admin4_code":"63335",
    "gn:asciiname":"Bessolle",
    "gn:country_code":"FR",
    "gn:dem":768,
    "gn:feature_class":"P",
    "gn:feature_code":"PPL",
    "gn:name":"Bessolle",
    "gn:population":0,
    "gn:timezone":"Europe/Paris",
    "iso:country":"FR",
    "wof:name":"Bessolle",
    "wof:placetype":"locality"
},
  "geometry": {"coordinates":[3.01916,45.52363],"type":"Point"}
}