{
  "type": "Feature",
  "properties": {
    "gn:admin1_code":"84",
    "gn:admin2_code":"07",
    "gn:admin3_code":"073",
    "gn:admin4_code":"07085",
    "gn:asciiname":"Bouteyron",
    "gn:country_code":"FR",
    "gn:dem":924,
    "gn:feature_class":"P",
    "gn:feature_code":"PPL",
    "gn:name":"Bouteyron",
    "gn:population":0,
    "gn:timezone":"Europe/Paris",
    "iso:country":"FR",
    "wof:name":"Bouteyron",
    "wof:placetype":"locality"
},
  "geometry": {"coordinates":[4.58333,45.05],"type":"Point"}
}