{
  "type": "Feature",
  "properties": {
    "gn:admin1_code":"84",
    "gn:admin2_code":"74",
    "gn:admin3_code":"741",
    "gn:admin4_code":"74283",
    "gn:asciiname":"Le Pezay",
    "gn:country_code":"FR",
    "gn:dem":649,
    "gn:feature_class":"P",
    "gn:feature_code":"PPL",
    "gn:name":"Le Pezay",
    "gn:population":0,
    "gn:timezone":"Europe/Paris",
    "iso:country":"FR",
    "name:und_x_variant":[
        "Pessay",
        "Le Pesay",
        "Le Pezay"
    ],
    "wof:name":"Le Pezay",
    "wof:placetype":"locality"
},
  "geometry": {"coordinates":[5.97046,45.9507],"type":"Point"}
}