{
  "type": "Feature",
  "properties": {
    "gn:admin1_code":"84",
    "gn:admin2_code":"03",
    "gn:admin3_code":"031",
    "gn:admin4_code":"3047.0",
    "gn:asciiname":"Merlon",
    "gn:country_code":"FR",
    "gn:dem":466,
    "gn:feature_class":"P",
    "gn:feature_code":"PPL",
    "gn:name":"Merlon",
    "gn:population":0,
    "gn:timezone":"Europe/Paris",
    "iso:country":"FR",
    "name:ara_x_preferred":[
        "\u062b\u0644\u0645\u0629"
    ],
    "name:bel_x_preferred":[
        "\u0417\u0443\u0431\u0435\u0446"
    ],
    "name:bul_x_preferred":[
        "\u0417\u044a\u0431\u0435\u0446"
    ],
    "name:cat_x_preferred":[
        "Merlet"
    ],
    "name:deu_x_preferred":[
        "Zinne"
    ],
    "name:eus_x_preferred":[
        "Almena"
    ],
    "name:fas_x_preferred":[
        "\u0634\u0631\u0641\u0647"
    ],
    "name:fra_x_preferred":[
        "Merlon"
    ],
    "name:gle_x_preferred":[
        "Meiril"
    ],
    "name:glg_x_preferred":[
        "Amea"
    ],
    "name:ita_x_preferred":[
        "Merlo"
    ],
    "name:lav_x_preferred":[
        "Dzegu\u013ci"
    ],
    "name:lim_x_preferred":[
        "Kanteel"
    ],
    "name:nld_x_preferred":[
        "Kanteel"
    ],
    "name:por_x_preferred":[
        "Merl\u00e3o"
    ],
    "name:ron_x_preferred":[
        "Merlon"
    ],
    "name:rus_x_preferred":[
        "\u0417\u0443\u0431\u0435\u0446"
    ],
    "name:slv_x_preferred":[
        "Cina"
    ],
    "name:spa_x_preferred":[
        "Almena"
    ],
    "name:tha_x_preferred":[
        "\u0e43\u0e1a\u0e2a\u0e2d"
    ],
    "name:ukr_x_preferred":[
        "\u041c\u0435\u0440\u043b\u043e\u043d"
    ],
    "wof:name":"Merlon",
    "wof:placetype":"locality"
},
  "geometry": {"coordinates":[2.76957,46.25384],"type":"Point"}
}