{
  "type": "Feature",
  "properties": {
    "gn:admin1_code":"75",
    "gn:admin2_code":"79",
    "gn:admin3_code":"793",
    "gn:admin4_code":"79005",
    "gn:asciiname":"Borcq-sur-Airvault",
    "gn:country_code":"FR",
    "gn:dem":131,
    "gn:feature_class":"P",
    "gn:feature_code":"PPL",
    "gn:name":"Borcq-sur-Airvault",
    "gn:population":0,
    "gn:timezone":"Europe/Paris",
    "iso:country":"FR",
    "name:und_x_variant":[
        "Borcq",
        "Borcq-sur-Airvault"
    ],
    "wof:name":"Borcq-sur-Airvault",
    "wof:placetype":"locality"
},
  "geometry": {"coordinates":[-0.08875,46.83004],"type":"Point"}
}