{
  "type": "Feature",
  "properties": {
    "gn:admin1_code":"44",
    "gn:admin2_code":"54",
    "gn:admin3_code":"541",
    "gn:admin4_code":"54363",
    "gn:asciiname":"Boudrezy",
    "gn:country_code":"FR",
    "gn:dem":325,
    "gn:feature_class":"P",
    "gn:feature_code":"PPL",
    "gn:name":"Boudrezy",
    "gn:population":0,
    "gn:timezone":"Europe/Paris",
    "iso:country":"FR",
    "wof:name":"Boudrezy",
    "wof:placetype":"locality"
},
  "geometry": {"coordinates":[5.81384,49.36975],"type":"Point"}
}