{
  "type": "Feature",
  "properties": {
    "gn:admin1_code":"75",
    "gn:admin2_code":"24",
    "gn:admin3_code":"244",
    "gn:admin4_code":"24301",
    "gn:asciiname":"Rouves",
    "gn:country_code":"FR",
    "gn:dem":278,
    "gn:feature_class":"P",
    "gn:feature_code":"PPL",
    "gn:name":"Rouves",
    "gn:population":0,
    "gn:timezone":"Europe/Paris",
    "iso:country":"FR",
    "name:cat_x_preferred":[
        "Rouves"
    ],
    "name:ceb_x_preferred":[
        "Rouves"
    ],
    "name:deu_x_preferred":[
        "Rouves"
    ],
    "name:eus_x_preferred":[
        "Rouves"
    ],
    "name:fra_x_preferred":[
        "Rouves"
    ],
    "name:hun_x_preferred":[
        "Rouves"
    ],
    "name:ita_x_preferred":[
        "Rouves"
    ],
    "name:kaz_x_preferred":[
        "\u0420\u0443\u0432"
    ],
    "name:lat_x_preferred":[
        "Rouves"
    ],
    "name:ltz_x_preferred":[
        "Rouves"
    ],
    "name:mlg_x_preferred":[
        "Rouves"
    ],
    "name:msa_x_preferred":[
        "Rouves"
    ],
    "name:nld_x_preferred":[
        "Rouves"
    ],
    "name:oci_x_preferred":[
        "Rouves"
    ],
    "name:pms_x_preferred":[
        "Rouves"
    ],
    "name:pol_x_preferred":[
        "Rouves"
    ],
    "name:por_x_preferred":[
        "Rouves"
    ],
    "name:rus_x_preferred":[
        "\u0420\u0443\u0432"
    ],
    "name:slk_x_preferred":[
        "Rouves"
    ],
    "name:spa_x_preferred":[
        "Rouves"
    ],
    "name:swe_x_preferred":[
        "Rouves"
    ],
    "name:ukr_x_preferred":[
        "\u0420\u0443\u0432"
    ],
    "name:uzb_x_preferred":[
        "Rouves"
    ],
    "name:vie_x_preferred":[
        "Rouves"
    ],
    "name:vol_x_preferred":[
        "Rouves"
    ],
    "name:war_x_preferred":[
        "Rouves"
    ],
    "name:zho_x_preferred":[
        "\u9c81\u97e6"
    ],
    "wof:name":"Rouves",
    "wof:placetype":"locality"
},
  "geometry": {"coordinates":[1.39759,45.04846],"type":"Point"}
}