{
  "type": "Feature",
  "properties": {
    "gn:admin1_code":"24",
    "gn:admin2_code":"28",
    "gn:admin3_code":"284",
    "gn:admin4_code":"28240",
    "gn:asciiname":"Le Haut Bois",
    "gn:country_code":"FR",
    "gn:dem":217,
    "gn:feature_class":"P",
    "gn:feature_code":"PPL",
    "gn:name":"Le Haut Bois",
    "gn:population":0,
    "gn:timezone":"Europe/Paris",
    "iso:country":"FR",
    "wof:name":"Le Haut Bois",
    "wof:placetype":"locality"
},
  "geometry": {"coordinates":[0.97053,48.47764],"type":"Point"}
}