{
  "type": "Feature",
  "properties": {
    "gn:admin1_code":"24",
    "gn:admin2_code":"37",
    "gn:admin3_code":"371",
    "gn:admin4_code":"37216.0",
    "gn:asciiname":"La Grande Maison",
    "gn:country_code":"FR",
    "gn:dem":86,
    "gn:feature_class":"P",
    "gn:feature_code":"PPL",
    "gn:name":"La Grande Maison",
    "gn:population":0,
    "gn:timezone":"Europe/Paris",
    "iso:country":"FR",
    "wof:name":"La Grande Maison",
    "wof:placetype":"locality"
},
  "geometry": {"coordinates":[0.57905,47.1642],"type":"Point"}
}