{
  "type": "Feature",
  "properties": {
    "gn:admin1_code":"27",
    "gn:admin2_code":"58",
    "gn:admin3_code":"584",
    "gn:admin4_code":"58122.0",
    "gn:asciiname":"Le Puizac",
    "gn:country_code":"FR",
    "gn:dem":186,
    "gn:feature_class":"P",
    "gn:feature_code":"PPL",
    "gn:name":"Le Puizac",
    "gn:population":0,
    "gn:timezone":"Europe/Paris",
    "iso:country":"FR",
    "name:und_x_variant":[
        "Le Puisac",
        "Le Puizac"
    ],
    "wof:name":"Le Puizac",
    "wof:placetype":"locality"
},
  "geometry": {"coordinates":[3.018,47.28809],"type":"Point"}
}