{
  "type": "Feature",
  "properties": {
    "gn:admin1_code":"76",
    "gn:admin2_code":"32",
    "gn:admin3_code":"321",
    "gn:admin4_code":"32327",
    "gn:asciiname":"Pouy-Loubrin",
    "gn:country_code":"FR",
    "gn:dem":288,
    "gn:feature_class":"P",
    "gn:feature_code":"PPL",
    "gn:name":"Pouy-Loubrin",
    "gn:population":0,
    "gn:timezone":"Europe/Paris",
    "iso:country":"FR",
    "name:arg_x_preferred":[
        "Poilobrin"
    ],
    "name:bug_x_preferred":[
        "Pouy-Loubrin"
    ],
    "name:cat_x_preferred":[
        "Poilobrin"
    ],
    "name:ceb_x_preferred":[
        "Pouy-Loubrin"
    ],
    "name:eus_x_preferred":[
        "Pouy-Loubrin"
    ],
    "name:fra_x_preferred":[
        "Pouy-Loubrin"
    ],
    "name:hun_x_preferred":[
        "Pouy-Loubrin"
    ],
    "name:ind_x_preferred":[
        "Pouy-Loubrin"
    ],
    "name:ita_x_preferred":[
        "Pouy-Loubrin"
    ],
    "name:lat_x_preferred":[
        "Pouy-Loubrin"
    ],
    "name:mlg_x_preferred":[
        "Pouy-Loubrin"
    ],
    "name:msa_x_preferred":[
        "Pouy-Loubrin"
    ],
    "name:nld_x_preferred":[
        "Pouy-Loubrin"
    ],
    "name:oci_x_preferred":[
        "Poilobrin"
    ],
    "name:pms_x_preferred":[
        "Pouy-Loubrin"
    ],
    "name:pol_x_preferred":[
        "Pouy-Loubrin"
    ],
    "name:por_x_preferred":[
        "Pouy-Loubrin"
    ],
    "name:ron_x_preferred":[
        "Pouy-Loubrin"
    ],
    "name:rus_x_preferred":[
        "\u041f\u0443\u0438-\u041b\u0443\u0431\u0440\u0435\u043d"
    ],
    "name:slk_x_preferred":[
        "Pouy-Loubrin"
    ],
    "name:spa_x_preferred":[
        "Pouy-Loubrin"
    ],
    "name:swe_x_preferred":[
        "Pouy-Loubrin"
    ],
    "name:ukr_x_preferred":[
        "\u041f\u0443\u0457-\u041b\u0443\u0431\u0440\u0435\u043d"
    ],
    "name:vie_x_preferred":[
        "Pouy-Loubrin"
    ],
    "name:vol_x_preferred":[
        "Pouy-Loubrin"
    ],
    "name:war_x_preferred":[
        "Pouy-Loubrin"
    ],
    "name:zho_x_preferred":[
        "\u666e\u4f0a\u5362\u5e03\u5170"
    ],
    "wof:name":"Pouy-Loubrin",
    "wof:placetype":"locality"
},
  "geometry": {"coordinates":[0.61667,43.46667],"type":"Point"}
}