{
  "type": "Feature",
  "properties": {
    "gn:admin1_code":"76",
    "gn:admin2_code":"32",
    "gn:admin3_code":"321",
    "gn:admin4_code":"32327",
    "gn:asciiname":"Pouy-Loubrin",
    "gn:country_code":"FR",
    "gn:dem":288,
    "gn:feature_class":"P",
    "gn:feature_code":"PPL",
    "gn:name":"Pouy-Loubrin",
    "gn:population":0,
    "gn:timezone":"Europe/Paris",
    "iso:country":"FR",
    "wof:name":"Pouy-Loubrin",
    "wof:placetype":"locality"
},
  "geometry": {"coordinates":[0.61667,43.46667],"type":"Point"}
}