{
  "type": "Feature",
  "properties": {
    "gn:admin1_code":"76",
    "gn:admin2_code":"46",
    "gn:admin3_code":"462",
    "gn:admin4_code":"46177",
    "gn:asciiname":"Rouquet",
    "gn:country_code":"FR",
    "gn:dem":387,
    "gn:feature_class":"P",
    "gn:feature_code":"PPL",
    "gn:name":"Rouquet",
    "gn:population":0,
    "gn:timezone":"Europe/Paris",
    "iso:country":"FR",
    "wof:name":"Rouquet",
    "wof:placetype":"locality"
},
  "geometry": {"coordinates":[1.78611,44.85249],"type":"Point"}
}