{
  "type": "Feature",
  "properties": {
    "gn:admin1_code":"75",
    "gn:admin2_code":"33",
    "gn:admin3_code":"333",
    "gn:admin4_code":"33139",
    "gn:asciiname":"Coutures",
    "gn:country_code":"FR",
    "gn:dem":37,
    "gn:feature_class":"P",
    "gn:feature_code":"PPL",
    "gn:name":"Coutures",
    "gn:population":73,
    "gn:timezone":"Europe/Paris",
    "iso:country":"FR",
    "name:und_x_variant":[
        "Coutures-sur-le-Dropt",
        "Coutures"
    ],
    "wof:name":"Coutures",
    "wof:placetype":"locality",
    "wof:population":73
},
  "geometry": {"coordinates":[0.0293,44.64433],"type":"Point"}
}