{
  "type": "Feature",
  "properties": {
    "frgov:code_epci":"200069599",
    "frgov:insee_arr":"3",
    "frgov:insee_com":"33139",
    "frgov:insee_dep":"33",
    "frgov:insee_reg":"75",
    "frgov:nom_com":"Coutures",
    "frgov:nom_com_m":"COUTURES",
    "frgov:nom_dep":"GIRONDE",
    "frgov:nom_reg":"NOUVELLE-AQUITAINE",
    "frgov:statut":"Commune simple",
    "gn:admin1_code":"75",
    "gn:admin2_code":"33",
    "gn:admin3_code":"333",
    "gn:admin4_code":"33139",
    "gn:asciiname":"Coutures",
    "gn:country_code":"FR",
    "gn:dem":37,
    "gn:feature_class":"P",
    "gn:feature_code":"PPL",
    "gn:name":"Coutures",
    "gn:population":73,
    "gn:timezone":"Europe/Paris",
    "iso:country":"FR",
    "name:cat_x_preferred":[
        "Coturas"
    ],
    "name:ceb_x_preferred":[
        "Coutures"
    ],
    "name:deu_x_preferred":[
        "Coutures"
    ],
    "name:fra_x_preferred":[
        "Coutures"
    ],
    "name:ita_x_preferred":[
        "Coutures"
    ],
    "name:kaz_x_preferred":[
        "\u041a\u0443\u0442\u044e\u0440"
    ],
    "name:nds_x_preferred":[
        "Coutures"
    ],
    "name:nld_x_preferred":[
        "Coutures"
    ],
    "name:oci_x_preferred":[
        "C\u00f2uturas"
    ],
    "name:pms_x_preferred":[
        "Coutures"
    ],
    "name:pol_x_preferred":[
        "Coutures"
    ],
    "name:rus_x_preferred":[
        "\u041a\u0443\u0442\u044e\u0440"
    ],
    "name:slk_x_preferred":[
        "Coutures"
    ],
    "name:spa_x_preferred":[
        "Coutures"
    ],
    "name:srp_x_preferred":[
        "\u041a\u0443\u0442\u0438\u0440"
    ],
    "name:swe_x_preferred":[
        "Coutures"
    ],
    "name:ukr_x_preferred":[
        "\u041a\u0443\u0442\u044e\u0440"
    ],
    "name:und_x_variant":[
        "Coutures-sur-le-Dropt",
        "Coutures"
    ],
    "name:zho_x_preferred":[
        "\u5e93\u8482\u96f7"
    ],
    "qs:a0":"France",
    "qs:a1":"GIRONDE",
    "qs:a1_lc":"33",
    "qs:a1r":"AQUITAINE",
    "qs:a1r_lc":"72",
    "qs:a2_lc":"32",
    "qs:a2r_lc":"3",
    "qs:adm0":"France",
    "qs:adm0_a3":"FRA",
    "qs:la":"COUTURES",
    "qs:la_lc":"33139",
    "qs:level":"localadmin",
    "qs:type":"Commune simple",
    "wof:coterminous":[
        404410033
    ],
    "wof:name":"Coutures",
    "wof:placetype":"locality",
    "wof:placetype_local":"Commune simple",
    "wof:population":73
},
  "geometry": {"coordinates":[0.0293,44.64433],"type":"Point"}
}