{
  "type": "Feature",
  "properties": {
    "gn:admin1_code":"75",
    "gn:admin2_code":"33",
    "gn:admin3_code":"333",
    "gn:admin4_code":"33139",
    "gn:asciiname":"Coutures",
    "gn:country_code":"FR",
    "gn:dem":37,
    "gn:feature_class":"P",
    "gn:feature_code":"PPL",
    "gn:name":"Coutures",
    "gn:population":73,
    "gn:timezone":"Europe/Paris",
    "iso:country":"FR",
    "name:ceb_x_preferred":[
        "Coutures"
    ],
    "name:deu_x_preferred":[
        "Coutures"
    ],
    "name:fra_x_preferred":[
        "Coutures"
    ],
    "name:ita_x_preferred":[
        "Coutures"
    ],
    "name:nds_x_preferred":[
        "Coutures"
    ],
    "name:nld_x_preferred":[
        "Coutures"
    ],
    "name:pms_x_preferred":[
        "Coutures"
    ],
    "name:pol_x_preferred":[
        "Coutures"
    ],
    "name:rus_x_preferred":[
        "\u041a\u0443\u0442\u044e\u0440"
    ],
    "name:slk_x_preferred":[
        "Coutures"
    ],
    "name:spa_x_preferred":[
        "Coutures"
    ],
    "name:srp_x_preferred":[
        "\u041a\u0443\u0442\u0438\u0440"
    ],
    "name:swe_x_preferred":[
        "Coutures"
    ],
    "name:ukr_x_preferred":[
        "\u041a\u0443\u0442\u044e\u0440"
    ],
    "name:und_x_variant":[
        "Coutures-sur-le-Dropt",
        "Coutures"
    ],
    "wof:name":"Coutures",
    "wof:placetype":"locality",
    "wof:population":73
},
  "geometry": {"coordinates":[0.0293,44.64433],"type":"Point"}
}