{
  "type": "Feature",
  "properties": {
    "gn:admin1_code":"84",
    "gn:admin2_code":"73",
    "gn:admin3_code":"733",
    "gn:admin4_code":"73259",
    "gn:asciiname":"Saint-Martin-sur-la-Chambre",
    "gn:cc2":"FR",
    "gn:country_code":"FR",
    "gn:dem":607,
    "gn:feature_class":"P",
    "gn:feature_code":"PPL",
    "gn:name":"Saint-Martin-sur-la-Chambre",
    "gn:population":0,
    "gn:timezone":"Europe/Paris",
    "iso:country":"FR",
    "name:cat_x_preferred":[
        "Saint-Martin-sur-la-Chambre"
    ],
    "name:ceb_x_preferred":[
        "Saint-Martin-sur-la-Chambre"
    ],
    "name:deu_x_preferred":[
        "Saint-Martin-sur-la-Chambre"
    ],
    "name:eus_x_preferred":[
        "Saint-Martin-sur-la-Chambre"
    ],
    "name:fra_x_preferred":[
        "Saint-Martin-sur-la-Chambre"
    ],
    "name:frp_x_preferred":[
        "Sent-Martin-sus-la-Chambra"
    ],
    "name:hun_x_preferred":[
        "Saint-Martin-sur-la-Chambre"
    ],
    "name:ita_x_preferred":[
        "Saint-Martin-sur-la-Chambre"
    ],
    "name:lat_x_preferred":[
        "Saint-Martin-sur-la-Chambre"
    ],
    "name:lmo_x_preferred":[
        "Saint-Martin-sur-la-Chambre"
    ],
    "name:msa_x_preferred":[
        "Saint-Martin-sur-la-Chambre"
    ],
    "name:nld_x_preferred":[
        "Saint-Martin-sur-la-Chambre"
    ],
    "name:oci_x_preferred":[
        "Saint-Martin-sur-la-Chambre"
    ],
    "name:pms_x_preferred":[
        "Saint-Martin-sur-la-Chambre"
    ],
    "name:pol_x_preferred":[
        "Saint-Martin-sur-la-Chambre"
    ],
    "name:por_x_preferred":[
        "Saint-Martin-sur-la-Chambre"
    ],
    "name:ron_x_preferred":[
        "Saint-Martin-sur-la-Chambre"
    ],
    "name:slk_x_preferred":[
        "Saint-Martin-sur-la-Chambre"
    ],
    "name:spa_x_preferred":[
        "Saint-Martin-sur-la-Chambre"
    ],
    "name:swe_x_preferred":[
        "Saint-Martin-sur-la-Chambre"
    ],
    "name:ukr_x_preferred":[
        "\u0421\u0435\u043d-\u041c\u0430\u0440\u0442\u0435\u043d-\u0441\u044e\u0440-\u043b\u0430-\u0428\u0430\u043c\u0431\u0440"
    ],
    "name:und_x_variant":[
        "Saint Martin"
    ],
    "name:urd_x_preferred":[
        "\u0633\u06cc\u0646\u0679-\u0645\u0627\u0631\u0679\u0646-\u0633\u0631-\u0644\u0627-\u0686\u0645\u0628\u0631\u06d2"
    ],
    "name:uzb_x_preferred":[
        "Saint-Martin-sur-la-Chambre"
    ],
    "name:vie_x_preferred":[
        "Saint-Martin-sur-la-Chambre"
    ],
    "name:vol_x_preferred":[
        "Saint-Martin-sur-la-Chambre"
    ],
    "name:war_x_preferred":[
        "Saint-Martin-sur-la-Chambre"
    ],
    "wof:name":"Saint-Martin-sur-la-Chambre",
    "wof:placetype":"locality"
},
  "geometry": {"coordinates":[6.31667,45.36667],"type":"Point"}
}