{
  "type": "Feature",
  "properties": {
    "gn:admin1_code":"84",
    "gn:admin2_code":"73",
    "gn:admin3_code":"733",
    "gn:admin4_code":"73259",
    "gn:asciiname":"Saint-Martin-sur-la-Chambre",
    "gn:cc2":"FR",
    "gn:country_code":"FR",
    "gn:dem":607,
    "gn:feature_class":"P",
    "gn:feature_code":"PPL",
    "gn:name":"Saint-Martin-sur-la-Chambre",
    "gn:population":0,
    "gn:timezone":"Europe/Paris",
    "iso:country":"FR",
    "name:und_x_variant":[
        "Saint Martin"
    ],
    "wof:name":"Saint-Martin-sur-la-Chambre",
    "wof:placetype":"locality"
},
  "geometry": {"coordinates":[6.31667,45.36667],"type":"Point"}
}