{
  "type": "Feature",
  "properties": {
    "gn:admin1_code":"27",
    "gn:admin2_code":"89",
    "gn:admin3_code":"891",
    "gn:admin4_code":"89163",
    "gn:asciiname":"Couilly",
    "gn:country_code":"FR",
    "gn:dem":219,
    "gn:feature_class":"P",
    "gn:feature_code":"PPL",
    "gn:name":"Couilly",
    "gn:population":0,
    "gn:timezone":"Europe/Paris",
    "iso:country":"FR",
    "wof:name":"Couilly",
    "wof:placetype":"locality"
},
  "geometry": {"coordinates":[3.2799,47.8847],"type":"Point"}
}