{
  "type": "Feature",
  "properties": {
    "gn:admin1_code":"24",
    "gn:admin2_code":"45",
    "gn:admin3_code":"451",
    "gn:admin4_code":"45245",
    "gn:asciiname":"Le Grand Chaloy",
    "gn:country_code":"FR",
    "gn:dem":169,
    "gn:feature_class":"P",
    "gn:feature_code":"PPL",
    "gn:name":"Le Grand Chaloy",
    "gn:population":0,
    "gn:timezone":"Europe/Paris",
    "iso:country":"FR",
    "wof:name":"Le Grand Chaloy",
    "wof:placetype":"locality"
},
  "geometry": {"coordinates":[2.85704,47.70829000000001],"type":"Point"}
}