{
  "type": "Feature",
  "properties": {
    "gn:admin1_code":"76",
    "gn:admin2_code":"81",
    "gn:admin3_code":"812",
    "gn:admin4_code":"81182",
    "gn:asciiname":"Bellegarde",
    "gn:country_code":"FR",
    "gn:dem":601,
    "gn:feature_class":"P",
    "gn:feature_code":"PPL",
    "gn:name":"Bellegarde",
    "gn:population":0,
    "gn:timezone":"Europe/Paris",
    "iso:country":"FR",
    "wof:name":"Bellegarde",
    "wof:placetype":"locality"
},
  "geometry": {"coordinates":[2.37946,43.71567],"type":"Point"}
}