{
  "type": "Feature",
  "properties": {
    "gn:admin1_code":"84",
    "gn:admin2_code":"69",
    "gn:admin3_code":"691",
    "gn:admin4_code":"69277",
    "gn:asciiname":"Vurey",
    "gn:country_code":"FR",
    "gn:dem":219,
    "gn:feature_class":"P",
    "gn:feature_code":"PPL",
    "gn:name":"Vurey",
    "gn:population":0,
    "gn:timezone":"Europe/Paris",
    "iso:country":"FR",
    "wof:name":"Vurey",
    "wof:placetype":"locality"
},
  "geometry": {"coordinates":[5.00454,45.72148],"type":"Point"}
}