{
  "type": "Feature",
  "properties": {
    "gn:admin1_code":"76",
    "gn:admin2_code":"46",
    "gn:admin3_code":"463",
    "gn:admin4_code":"46127",
    "gn:asciiname":"Costeraste",
    "gn:country_code":"FR",
    "gn:dem":214,
    "gn:feature_class":"P",
    "gn:feature_code":"PPL",
    "gn:name":"Costeraste",
    "gn:population":0,
    "gn:timezone":"Europe/Paris",
    "iso:country":"FR",
    "wof:name":"Costeraste",
    "wof:placetype":"locality"
},
  "geometry": {"coordinates":[1.351,44.70823],"type":"Point"}
}