{
  "type": "Feature",
  "properties": {
    "gn:admin1_code":"84",
    "gn:admin2_code":"63",
    "gn:admin3_code":"631",
    "gn:admin4_code":"63309",
    "gn:asciiname":"Espinasse",
    "gn:country_code":"FR",
    "gn:dem":914,
    "gn:feature_class":"P",
    "gn:feature_code":"PPL",
    "gn:name":"Espinasse",
    "gn:population":0,
    "gn:timezone":"Europe/Paris",
    "iso:country":"FR",
    "name:ceb_x_preferred":[
        "Espinasse"
    ],
    "name:deu_x_preferred":[
        "Espinasse"
    ],
    "name:fra_x_preferred":[
        "Espinasse"
    ],
    "name:ita_x_preferred":[
        "Espinasse"
    ],
    "name:nds_x_preferred":[
        "Espinasse"
    ],
    "name:nld_x_preferred":[
        "Espinasse"
    ],
    "name:oci_x_preferred":[
        "Espinassa"
    ],
    "name:pms_x_preferred":[
        "Espinasse"
    ],
    "name:pol_x_preferred":[
        "Espinasse"
    ],
    "name:por_x_preferred":[
        "Espinasse"
    ],
    "name:rus_x_preferred":[
        "\u042d\u0441\u043f\u0438\u043d\u0430\u0441"
    ],
    "name:slk_x_preferred":[
        "Espinasse"
    ],
    "name:spa_x_preferred":[
        "Espinasse"
    ],
    "name:swe_x_preferred":[
        "Espinasse"
    ],
    "name:ukr_x_preferred":[
        "\u0415\u0441\u043f\u0456\u043d\u0430\u0441\u0441"
    ],
    "wof:name":"Espinasse",
    "wof:placetype":"locality"
},
  "geometry": {"coordinates":[3.92101,45.44551],"type":"Point"}
}