{
  "type": "Feature",
  "properties": {
    "gn:admin1_code":"84",
    "gn:admin2_code":"63",
    "gn:admin3_code":"631",
    "gn:admin4_code":"63309",
    "gn:asciiname":"Espinasse",
    "gn:country_code":"FR",
    "gn:dem":914,
    "gn:feature_class":"P",
    "gn:feature_code":"PPL",
    "gn:name":"Espinasse",
    "gn:population":0,
    "gn:timezone":"Europe/Paris",
    "iso:country":"FR",
    "wof:name":"Espinasse",
    "wof:placetype":"locality"
},
  "geometry": {"coordinates":[3.92101,45.44551],"type":"Point"}
}