{
  "type": "Feature",
  "properties": {
    "gn:admin1_code":"93",
    "gn:admin2_code":"84",
    "gn:admin3_code":"841",
    "gn:admin4_code":"84144",
    "gn:asciiname":"Saint-Amas",
    "gn:country_code":"FR",
    "gn:dem":524,
    "gn:feature_class":"P",
    "gn:feature_code":"PPL",
    "gn:name":"Saint-Amas",
    "gn:population":0,
    "gn:timezone":"Europe/Paris",
    "iso:country":"FR",
    "wof:name":"Saint-Amas",
    "wof:placetype":"locality"
},
  "geometry": {"coordinates":[5.51593,43.89712],"type":"Point"}
}