{
  "type": "Feature",
  "properties": {
    "gn:admin1_code":"24",
    "gn:admin2_code":"28",
    "gn:admin3_code":"283",
    "gn:admin4_code":"28056",
    "gn:asciiname":"Les Joncs",
    "gn:country_code":"FR",
    "gn:dem":135,
    "gn:feature_class":"P",
    "gn:feature_code":"PPL",
    "gn:name":"Les Joncs",
    "gn:population":0,
    "gn:timezone":"Europe/Paris",
    "iso:country":"FR",
    "wof:name":"Les Joncs",
    "wof:placetype":"locality"
},
  "geometry": {"coordinates":[1.58489,48.7234],"type":"Point"}
}