{
  "type": "Feature",
  "properties": {
    "gn:admin1_code":"84",
    "gn:admin2_code":"03",
    "gn:admin3_code":"031",
    "gn:admin4_code":"03303",
    "gn:asciiname":"Parcais Petit",
    "gn:country_code":"FR",
    "gn:dem":273,
    "gn:feature_class":"P",
    "gn:feature_code":"PPL",
    "gn:name":"Parcais Petit",
    "gn:population":0,
    "gn:timezone":"Europe/Paris",
    "iso:country":"FR",
    "wof:name":"Parcais Petit",
    "wof:placetype":"locality"
},
  "geometry": {"coordinates":[2.77458,46.44734],"type":"Point"}
}