{
  "type": "Feature",
  "properties": {
    "gn:admin1_code":"52",
    "gn:admin2_code":"44",
    "gn:admin3_code":"443",
    "gn:admin4_code":"44068",
    "gn:asciiname":"Le Bignon",
    "gn:country_code":"FR",
    "gn:dem":11,
    "gn:feature_class":"P",
    "gn:feature_code":"PPL",
    "gn:name":"Le Bignon",
    "gn:population":0,
    "gn:timezone":"Europe/Paris",
    "iso:country":"FR",
    "wof:name":"Le Bignon",
    "wof:placetype":"locality"
},
  "geometry": {"coordinates":[-1.96405,47.47393],"type":"Point"}
}