{
  "type": "Feature",
  "properties": {
    "iso:country":"FR",
    "name:eng_x_preferred":[
        "Port-Marianne"
    ],
    "name:fra_x_preferred":[
        "Port-Marianne"
    ],
    "name:fra_x_variant":[
        "Port Marianne"
    ],
    "wof:name":"Port-Marianne",
    "wof:placetype":"neighbourhood"
},
  "geometry": {"coordinates":[3.91206606194498,43.6047235970942],"type":"Point"}
}