{
  "type": "Feature",
  "properties": {
    "gn:admin1_code":"93",
    "gn:admin2_code":"84",
    "gn:admin3_code":"841",
    "gn:admin4_code":"84014",
    "gn:asciiname":"La Ringuiere",
    "gn:country_code":"FR",
    "gn:dem":499,
    "gn:feature_class":"P",
    "gn:feature_code":"PPL",
    "gn:name":"La Ringui\u00e8re",
    "gn:population":0,
    "gn:timezone":"Europe/Paris",
    "iso:country":"FR",
    "name:und_x_variant":[
        "La Renguiere",
        "La Ringui\u00e8re"
    ],
    "wof:name":"La Ringuiere",
    "wof:placetype":"locality"
},
  "geometry": {"coordinates":[5.65207,43.76371],"type":"Point"}
}