{
  "type": "Feature",
  "properties": {
    "gn:admin1_code":"75",
    "gn:admin2_code":"87",
    "gn:admin3_code":"872",
    "gn:admin4_code":"87049",
    "gn:asciiname":"Pierre Fiche",
    "gn:country_code":"FR",
    "gn:dem":397,
    "gn:feature_class":"P",
    "gn:feature_code":"PPL",
    "gn:name":"Pierre Fiche",
    "gn:population":0,
    "gn:timezone":"Europe/Paris",
    "iso:country":"FR",
    "wof:name":"Pierre Fiche",
    "wof:placetype":"locality"
},
  "geometry": {"coordinates":[1.36169,45.52274],"type":"Point"}
}