{
  "type": "Feature",
  "properties": {
    "gn:admin1_code":"28",
    "gn:admin2_code":"61",
    "gn:admin3_code":"613",
    "gn:admin4_code":"61118",
    "gn:asciiname":"La Fortiniere",
    "gn:country_code":"FR",
    "gn:dem":163,
    "gn:feature_class":"P",
    "gn:feature_code":"PPL",
    "gn:name":"La Fortini\u00e8re",
    "gn:population":0,
    "gn:timezone":"Europe/Paris",
    "iso:country":"FR",
    "wof:name":"La Fortiniere",
    "wof:placetype":"locality"
},
  "geometry": {"coordinates":[0.63333,48.46667],"type":"Point"}
}