{
  "type": "Feature",
  "properties": {
    "gn:admin1_code":"32",
    "gn:admin2_code":"80",
    "gn:admin3_code":"801",
    "gn:admin4_code":"80104",
    "gn:asciiname":"Biencourt",
    "gn:country_code":"FR",
    "gn:dem":117,
    "gn:feature_class":"P",
    "gn:feature_code":"PPL",
    "gn:name":"Biencourt",
    "gn:population":0,
    "gn:timezone":"Europe/Paris",
    "iso:country":"FR",
    "name:bug_x_preferred":[
        "Biencourt"
    ],
    "name:cat_x_preferred":[
        "Biencourt"
    ],
    "name:ceb_x_preferred":[
        "Biencourt"
    ],
    "name:deu_x_preferred":[
        "Biencourt"
    ],
    "name:eus_x_preferred":[
        "Biencourt"
    ],
    "name:fas_x_preferred":[
        "\u0628\u06cc\u0646\u06a9\u0648\u0631"
    ],
    "name:fra_x_preferred":[
        "Biencourt"
    ],
    "name:hun_x_preferred":[
        "Biencourt"
    ],
    "name:hye_x_preferred":[
        "\u0532\u056b\u0565\u0576\u056f\u0578\u0582\u0580"
    ],
    "name:ita_x_preferred":[
        "Biencourt"
    ],
    "name:lat_x_preferred":[
        "Biencourt"
    ],
    "name:mlg_x_preferred":[
        "Biencourt"
    ],
    "name:msa_x_preferred":[
        "Biencourt"
    ],
    "name:nld_x_preferred":[
        "Biencourt"
    ],
    "name:oci_x_preferred":[
        "Biencourt"
    ],
    "name:pcd_x_preferred":[
        "Biencourt"
    ],
    "name:pms_x_preferred":[
        "Biencourt"
    ],
    "name:pol_x_preferred":[
        "Biencourt"
    ],
    "name:por_x_preferred":[
        "Biencourt"
    ],
    "name:slk_x_preferred":[
        "Biencourt"
    ],
    "name:spa_x_preferred":[
        "Biencourt"
    ],
    "name:srp_x_preferred":[
        "\u0411\u0458\u0435\u043d\u043a\u0443\u0440"
    ],
    "name:swe_x_preferred":[
        "Biencourt"
    ],
    "name:ukr_x_preferred":[
        "\u0411'\u044f\u043d\u043a\u0443\u0440"
    ],
    "name:uzb_x_preferred":[
        "Biencourt"
    ],
    "name:vie_x_preferred":[
        "Biencourt"
    ],
    "name:vol_x_preferred":[
        "Biencourt"
    ],
    "name:war_x_preferred":[
        "Biencourt"
    ],
    "name:zho_x_preferred":[
        "\u6bd4\u5b89\u5e93\u5c14"
    ],
    "wof:name":"Biencourt",
    "wof:placetype":"locality"
},
  "geometry": {"coordinates":[1.69132,49.97413],"type":"Point"}
}