{
  "type": "Feature",
  "properties": {
    "gn:admin1_code":"44",
    "gn:admin2_code":"52",
    "gn:admin3_code":"523",
    "gn:admin4_code":"52088",
    "gn:asciiname":"Sauvage-Magny",
    "gn:country_code":"FR",
    "gn:dem":133,
    "gn:feature_class":"P",
    "gn:feature_code":"PPL",
    "gn:name":"Sauvage-Magny",
    "gn:population":0,
    "gn:timezone":"Europe/Paris",
    "iso:country":"FR",
    "wof:name":"Sauvage-Magny",
    "wof:placetype":"locality"
},
  "geometry": {"coordinates":[4.73853,48.4121],"type":"Point"}
}