{
  "type": "Feature",
  "properties": {
    "gn:admin1_code":"52",
    "gn:admin2_code":"53",
    "gn:admin3_code":"532",
    "gn:admin4_code":"53086",
    "gn:asciiname":"Le Breil",
    "gn:country_code":"FR",
    "gn:dem":141,
    "gn:feature_class":"P",
    "gn:feature_code":"PPL",
    "gn:name":"Le Breil",
    "gn:population":0,
    "gn:timezone":"Europe/Paris",
    "iso:country":"FR",
    "wof:name":"Le Breil",
    "wof:placetype":"locality"
},
  "geometry": {"coordinates":[-1.06354,48.20103],"type":"Point"}
}