{
  "type": "Feature",
  "properties": {
    "gn:admin1_code":"84",
    "gn:admin2_code":"03",
    "gn:admin3_code":"033",
    "gn:admin4_code":"03110",
    "gn:asciiname":"Les Thevenins",
    "gn:country_code":"FR",
    "gn:dem":329,
    "gn:feature_class":"P",
    "gn:feature_code":"PPL",
    "gn:name":"Les Th\u00e9venins",
    "gn:population":0,
    "gn:timezone":"Europe/Paris",
    "iso:country":"FR",
    "wof:name":"Les Thevenins",
    "wof:placetype":"locality"
},
  "geometry": {"coordinates":[3.35696,46.1419],"type":"Point"}
}