{
  "type": "Feature",
  "properties": {
    "gn:admin1_code":"24",
    "gn:admin2_code":"45",
    "gn:admin3_code":"453",
    "gn:admin4_code":"45191",
    "gn:asciiname":"Mainvilliers",
    "gn:country_code":"FR",
    "gn:dem":126,
    "gn:feature_class":"P",
    "gn:feature_code":"PPL",
    "gn:name":"Mainvilliers",
    "gn:population":252,
    "gn:timezone":"Europe/Paris",
    "iso:country":"FR",
    "wof:name":"Mainvilliers",
    "wof:placetype":"locality",
    "wof:population":252
},
  "geometry": {"coordinates":[2.28157,48.30055],"type":"Point"}
}