{
  "type": "Feature",
  "properties": {
    "gn:admin1_code":"11",
    "gn:admin2_code":"77",
    "gn:admin3_code":"771",
    "gn:admin4_code":"77129",
    "gn:asciiname":"Vaux-sous-Coulombs",
    "gn:country_code":"FR",
    "gn:dem":109,
    "gn:feature_class":"P",
    "gn:feature_code":"PPL",
    "gn:name":"Vaux-sous-Coulombs",
    "gn:population":0,
    "gn:timezone":"Europe/Paris",
    "iso:country":"FR",
    "name:und_x_variant":[
        "Vaux",
        "Vaux-sous-Coulombs"
    ],
    "wof:name":"Vaux-sous-Coulombs",
    "wof:placetype":"locality"
},
  "geometry": {"coordinates":[3.13409,49.10228],"type":"Point"}
}