{
  "type": "Feature",
  "properties": {
    "gn:admin1_code":"24",
    "gn:admin2_code":"18",
    "gn:admin3_code":"181",
    "gn:admin4_code":"18179",
    "gn:asciiname":"Lizy",
    "gn:country_code":"FR",
    "gn:dem":164,
    "gn:feature_class":"P",
    "gn:feature_code":"PPL",
    "gn:name":"Lizy",
    "gn:population":0,
    "gn:timezone":"Europe/Paris",
    "iso:country":"FR",
    "name:bug_x_preferred":[
        "Lizy"
    ],
    "name:cat_x_preferred":[
        "Lizy"
    ],
    "name:ceb_x_preferred":[
        "Lizy"
    ],
    "name:deu_x_preferred":[
        "Lizy"
    ],
    "name:eus_x_preferred":[
        "Lizy"
    ],
    "name:fra_x_preferred":[
        "Lizy"
    ],
    "name:hun_x_preferred":[
        "Lizy"
    ],
    "name:hye_x_preferred":[
        "\u053c\u056b\u0566\u056b"
    ],
    "name:ind_x_preferred":[
        "Lizy"
    ],
    "name:ita_x_preferred":[
        "Lizy"
    ],
    "name:lat_x_preferred":[
        "Lizy"
    ],
    "name:mlg_x_preferred":[
        "Lizy"
    ],
    "name:msa_x_preferred":[
        "Lizy"
    ],
    "name:nld_x_preferred":[
        "Lizy"
    ],
    "name:oci_x_preferred":[
        "Lizy"
    ],
    "name:pms_x_preferred":[
        "Lizy"
    ],
    "name:pol_x_preferred":[
        "Lizy"
    ],
    "name:por_x_preferred":[
        "Lizy"
    ],
    "name:ron_x_preferred":[
        "Lizy"
    ],
    "name:rus_x_preferred":[
        "\u041b\u0438\u0437\u0438"
    ],
    "name:slk_x_preferred":[
        "Lizy"
    ],
    "name:spa_x_preferred":[
        "Lizy"
    ],
    "name:sqi_x_preferred":[
        "Lizy"
    ],
    "name:swe_x_preferred":[
        "Lizy"
    ],
    "name:ukr_x_preferred":[
        "\u041b\u0456\u0437\u0456"
    ],
    "name:uzb_x_preferred":[
        "Lizy"
    ],
    "name:vie_x_preferred":[
        "Lizy"
    ],
    "name:vol_x_preferred":[
        "Lizy"
    ],
    "name:war_x_preferred":[
        "Lizy"
    ],
    "name:zea_x_preferred":[
        "Lizy"
    ],
    "wof:name":"Lizy",
    "wof:placetype":"locality"
},
  "geometry": {"coordinates":[2.44258,47.15763],"type":"Point"}
}