{
  "type": "Feature",
  "properties": {
    "gn:admin1_code":"24",
    "gn:admin2_code":"18",
    "gn:admin3_code":"181",
    "gn:admin4_code":"18179",
    "gn:asciiname":"Lizy",
    "gn:country_code":"FR",
    "gn:dem":164,
    "gn:feature_class":"P",
    "gn:feature_code":"PPL",
    "gn:name":"Lizy",
    "gn:population":0,
    "gn:timezone":"Europe/Paris",
    "iso:country":"FR",
    "wof:name":"Lizy",
    "wof:placetype":"locality"
},
  "geometry": {"coordinates":[2.44258,47.15763],"type":"Point"}
}