{
  "type": "Feature",
  "properties": {
    "gn:admin1_code":"52",
    "gn:admin2_code":"44",
    "gn:admin3_code":"442",
    "gn:admin4_code":"44114",
    "gn:asciiname":"Le Doucet",
    "gn:country_code":"FR",
    "gn:dem":62,
    "gn:feature_class":"P",
    "gn:feature_code":"PPL",
    "gn:name":"Le Doucet",
    "gn:population":0,
    "gn:timezone":"Europe/Paris",
    "iso:country":"FR",
    "wof:name":"Le Doucet",
    "wof:placetype":"locality"
},
  "geometry": {"coordinates":[-1.63345,47.2775],"type":"Point"}
}