{
  "type": "Feature",
  "properties": {
    "gn:admin1_code":"27",
    "gn:admin2_code":"25",
    "gn:admin3_code":"251",
    "gn:admin4_code":"25223",
    "gn:asciiname":"Doulaize",
    "gn:country_code":"FR",
    "gn:dem":398,
    "gn:feature_class":"P",
    "gn:feature_code":"PPL",
    "gn:name":"Doulaize",
    "gn:population":0,
    "gn:timezone":"Europe/Paris",
    "iso:country":"FR",
    "wof:name":"Doulaize",
    "wof:placetype":"locality"
},
  "geometry": {"coordinates":[5.98241,47.03807000000001],"type":"Point"}
}