{
  "type": "Feature",
  "properties": {
    "gn:admin1_code":"11",
    "gn:admin2_code":"78",
    "gn:admin3_code":"782",
    "gn:admin4_code":"78407.0",
    "gn:asciiname":"Vacheresse",
    "gn:country_code":"FR",
    "gn:dem":128,
    "gn:feature_class":"P",
    "gn:feature_code":"PPL",
    "gn:name":"Vacheresse",
    "gn:population":0,
    "gn:timezone":"Europe/Paris",
    "iso:country":"FR",
    "name:cat_x_preferred":[
        "Vacheresse"
    ],
    "name:ceb_x_preferred":[
        "Vacheresse"
    ],
    "name:deu_x_preferred":[
        "Vacheresse"
    ],
    "name:eus_x_preferred":[
        "Vacheresse"
    ],
    "name:fra_x_preferred":[
        "Vacheresse"
    ],
    "name:hun_x_preferred":[
        "Vacheresse"
    ],
    "name:ind_x_preferred":[
        "Vacheresse"
    ],
    "name:ita_x_preferred":[
        "Vacheresse"
    ],
    "name:lat_x_preferred":[
        "Vaccaritia"
    ],
    "name:lmo_x_preferred":[
        "Vacheresse"
    ],
    "name:mlg_x_preferred":[
        "Vacheresse"
    ],
    "name:msa_x_preferred":[
        "Vacheresse"
    ],
    "name:nld_x_preferred":[
        "Vacheresse"
    ],
    "name:oci_x_preferred":[
        "Vacheresse"
    ],
    "name:pms_x_preferred":[
        "Vacheresse"
    ],
    "name:pol_x_preferred":[
        "Vacheresse"
    ],
    "name:por_x_preferred":[
        "Vacheresse"
    ],
    "name:ron_x_preferred":[
        "Vacheresse"
    ],
    "name:slk_x_preferred":[
        "Vacheresse"
    ],
    "name:spa_x_preferred":[
        "Vacheresse"
    ],
    "name:swe_x_preferred":[
        "Vacheresse"
    ],
    "name:ukr_x_preferred":[
        "\u0412\u0430\u0448\u0435\u0440\u0435\u0441\u0441"
    ],
    "name:uzb_x_preferred":[
        "Vacheresse"
    ],
    "name:vie_x_preferred":[
        "Vacheresse"
    ],
    "name:vol_x_preferred":[
        "Vacheresse"
    ],
    "name:war_x_preferred":[
        "Vacheresse"
    ],
    "wof:name":"Vacheresse",
    "wof:placetype":"locality"
},
  "geometry": {"coordinates":[1.62112,48.66416],"type":"Point"}
}