{
  "type": "Feature",
  "properties": {
    "gn:admin1_code":"93",
    "gn:admin2_code":"13",
    "gn:admin3_code":"131",
    "gn:admin4_code":"13001",
    "gn:asciiname":"Pont de l'Arc",
    "gn:country_code":"FR",
    "gn:dem":144,
    "gn:feature_class":"P",
    "gn:feature_code":"PPL",
    "gn:name":"Pont de l\u2019Arc",
    "gn:population":0,
    "gn:timezone":"Europe/Paris",
    "iso:country":"FR",
    "wof:name":"Pont de l'Arc",
    "wof:placetype":"locality"
},
  "geometry": {"coordinates":[5.44072,43.50838],"type":"Point"}
}