{
  "type": "Feature",
  "properties": {
    "gn:admin1_code":"76",
    "gn:admin2_code":"11",
    "gn:admin3_code":"112",
    "gn:admin4_code":"11091",
    "gn:asciiname":"Le Cazal-Sainte-Marie",
    "gn:country_code":"FR",
    "gn:dem":377,
    "gn:feature_class":"P",
    "gn:feature_code":"PPL",
    "gn:name":"Le Cazal-Sainte-Marie",
    "gn:population":0,
    "gn:timezone":"Europe/Paris",
    "iso:country":"FR",
    "name:und_x_variant":[
        "Cazal-Sainte-Marie",
        "Le Cazal-Sainte-Marie"
    ],
    "wof:name":"Le Cazal-Sainte-Marie",
    "wof:placetype":"locality"
},
  "geometry": {"coordinates":[2.00308,42.97283],"type":"Point"}
}