{
  "type": "Feature",
  "properties": {
    "gn:gn_country":"FR",
    "gn:gn_fcode":"PPL",
    "gn:gn_pop":0,
    "iso:country":"FR",
    "qs_pg:aaroncc":"FR",
    "qs_pg:gn_country":"FR",
    "qs_pg:gn_fcode":"PPL",
    "qs_pg:gn_pop":0,
    "qs_pg:name":"Condamine",
    "qs_pg:name_adm0":"France",
    "qs_pg:name_adm1":"Rh\u00f4ne-Alpes",
    "qs_pg:photos":273,
    "qs_pg:photos_1k":55,
    "qs_pg:photos_9k":1,
    "qs_pg:photos_9r":4,
    "qs_pg:photos_all":273,
    "qs_pg:photos_sr":5,
    "qs_pg:pop_sr":0,
    "qs_pg:qs_pg_placetype":"locality",
    "qs_pg:qs_pg_placetype_gp":"Town",
    "qs_pg:woe_adm0":23424819,
    "woe:adm0_id":23424819,
    "woe:name_adm0":"France",
    "woe:name_adm1":"Rh\u00f4ne-Alpes",
    "woe:placetype":"Town",
    "wof:name":"Condamine",
    "wof:placetype":"neighbourhood"
},
  "geometry": {"coordinates":[4.26028,45.45561],"type":"Point"}
}