{
  "type": "Feature",
  "properties": {
    "gn:admin1_code":"84",
    "gn:admin2_code":"74",
    "gn:admin3_code":"742",
    "gn:admin4_code":"74212",
    "gn:asciiname":"L'Essert",
    "gn:country_code":"FR",
    "gn:dem":768,
    "gn:feature_class":"P",
    "gn:feature_code":"PPL",
    "gn:name":"L\u2019Essert",
    "gn:population":0,
    "gn:timezone":"Europe/Paris",
    "iso:country":"FR",
    "wof:name":"L'Essert",
    "wof:placetype":"locality"
},
  "geometry": {"coordinates":[6.38929,45.98818],"type":"Point"}
}