{
  "type": "Feature",
  "properties": {
    "gn:admin1_code":"24",
    "gn:admin2_code":"41",
    "gn:admin3_code":"413",
    "gn:admin4_code":"41249",
    "gn:asciiname":"La Pree",
    "gn:country_code":"FR",
    "gn:dem":125,
    "gn:feature_class":"P",
    "gn:feature_code":"PPL",
    "gn:name":"La Pr\u00e9e",
    "gn:population":0,
    "gn:timezone":"Europe/Paris",
    "iso:country":"FR",
    "wof:name":"La Pree",
    "wof:placetype":"locality"
},
  "geometry": {"coordinates":[2.13286,47.44438],"type":"Point"}
}