{
  "type": "Feature",
  "properties": {
    "gn:admin1_code":"75",
    "gn:admin2_code":"19",
    "gn:admin3_code":"192",
    "gn:admin4_code":"19004",
    "gn:asciiname":"Chantarel",
    "gn:country_code":"FR",
    "gn:dem":449,
    "gn:feature_class":"P",
    "gn:feature_code":"PPL",
    "gn:name":"Chantarel",
    "gn:population":0,
    "gn:timezone":"Europe/Paris",
    "iso:country":"FR",
    "wof:name":"Chantarel",
    "wof:placetype":"locality"
},
  "geometry": {"coordinates":[1.78729,45.16383],"type":"Point"}
}