{
  "type": "Feature",
  "properties": {
    "gn:admin1_code":"84",
    "gn:admin2_code":"43",
    "gn:admin3_code":"431",
    "gn:admin4_code":"43001",
    "gn:asciiname":"Isseuges",
    "gn:country_code":"FR",
    "gn:dem":712,
    "gn:feature_class":"P",
    "gn:feature_code":"PPL",
    "gn:name":"Isseuges",
    "gn:population":0,
    "gn:timezone":"Europe/Paris",
    "iso:country":"FR",
    "name:und_x_variant":[
        "Isseuge",
        "Isseuges"
    ],
    "wof:name":"Isseuges",
    "wof:placetype":"locality"
},
  "geometry": {"coordinates":[3.46895,45.3448],"type":"Point"}
}