{
  "type": "Feature",
  "properties": {
    "gn:admin1_code":"76",
    "gn:admin2_code":"11",
    "gn:admin3_code":"111",
    "gn:admin4_code":"11243",
    "gn:asciiname":"Montferrand",
    "gn:country_code":"FR",
    "gn:dem":263,
    "gn:feature_class":"P",
    "gn:feature_code":"PPL",
    "gn:name":"Montferrand",
    "gn:population":469,
    "gn:timezone":"Europe/Paris",
    "iso:country":"FR",
    "name:deu_x_preferred":[
        "Montferrand"
    ],
    "name:fra_x_preferred":[
        "Montferrand"
    ],
    "name:oci_x_preferred":[
        "Montferrand"
    ],
    "name:rus_x_preferred":[
        "\u041c\u043e\u043d\u0444\u0435\u0440\u0440\u0430\u043d"
    ],
    "name:swe_x_preferred":[
        "Montferrand"
    ],
    "wof:name":"Montferrand",
    "wof:placetype":"locality",
    "wof:population":469
},
  "geometry": {"coordinates":[1.81979,43.3643],"type":"Point"}
}