{
  "type": "Feature",
  "properties": {
    "frgov:code_epci":"200035855",
    "frgov:insee_arr":"1",
    "frgov:insee_com":"11243",
    "frgov:insee_dep":"11",
    "frgov:insee_reg":"76",
    "frgov:nom_com":"Montferrand",
    "frgov:nom_com_m":"MONTFERRAND",
    "frgov:nom_dep":"AUDE",
    "frgov:nom_reg":"OCCITANIE",
    "frgov:statut":"Commune simple",
    "gn:admin1_code":"76",
    "gn:admin2_code":"11",
    "gn:admin3_code":"111",
    "gn:admin4_code":"11243",
    "gn:asciiname":"Montferrand",
    "gn:country_code":"FR",
    "gn:dem":263,
    "gn:feature_class":"P",
    "gn:feature_code":"PPL",
    "gn:name":"Montferrand",
    "gn:population":469,
    "gn:timezone":"Europe/Paris",
    "iso:country":"FR",
    "name:deu_x_preferred":[
        "Montferrand"
    ],
    "name:fra_x_preferred":[
        "Montferrand"
    ],
    "name:kaz_x_preferred":[
        "\u041c\u043e\u043d\u0444\u0435\u0440\u0440\u0430\u043d"
    ],
    "name:oci_x_preferred":[
        "Montferrand"
    ],
    "name:rus_x_preferred":[
        "\u041c\u043e\u043d\u0444\u0435\u0440\u0440\u0430\u043d"
    ],
    "name:swe_x_preferred":[
        "Montferrand"
    ],
    "name:ukr_x_preferred":[
        "\u041c\u043e\u043d\u0444\u0435\u0440\u0440\u0430\u043d"
    ],
    "name:zho_x_preferred":[
        "\u8499\u7279\u5f17\u5c14\u6717"
    ],
    "qs:a0":"France",
    "qs:a1":"AUDE",
    "qs:a1_lc":"11",
    "qs:a1r":"LANGUEDOC-ROUSSILLON",
    "qs:a1r_lc":"91",
    "qs:a2_lc":"10",
    "qs:a2r_lc":"1",
    "qs:adm0":"France",
    "qs:adm0_a3":"FRA",
    "qs:la":"MONTFERRAND",
    "qs:la_lc":"11243",
    "qs:level":"localadmin",
    "qs:type":"Commune simple",
    "wof:coterminous":[
        404390767
    ],
    "wof:name":"Montferrand",
    "wof:placetype":"locality",
    "wof:placetype_local":"Commune simple",
    "wof:population":469
},
  "geometry": {"coordinates":[1.81979,43.3643],"type":"Point"}
}