{
  "type": "Feature",
  "properties": {
    "gn:admin1_code":"75",
    "gn:admin2_code":"24",
    "gn:admin3_code":"241",
    "gn:admin4_code":"24331",
    "gn:asciiname":"Malveyrein",
    "gn:country_code":"FR",
    "gn:dem":115,
    "gn:feature_class":"P",
    "gn:feature_code":"PPL",
    "gn:name":"Malveyrein",
    "gn:population":0,
    "gn:timezone":"Europe/Paris",
    "iso:country":"FR",
    "name:und_x_variant":[
        "Malveyrien",
        "Malveyrein"
    ],
    "wof:name":"Malveyrein",
    "wof:placetype":"locality"
},
  "geometry": {"coordinates":[0.39541,44.79857],"type":"Point"}
}