{
  "type": "Feature",
  "properties": {
    "gn:admin1_code":"53",
    "gn:admin2_code":"35",
    "gn:admin3_code":"354",
    "gn:admin4_code":"35228",
    "gn:asciiname":"Jouvente",
    "gn:country_code":"FR",
    "gn:dem":34,
    "gn:feature_class":"P",
    "gn:feature_code":"PPL",
    "gn:name":"Jouvente",
    "gn:population":0,
    "gn:timezone":"Europe/Paris",
    "iso:country":"FR",
    "wof:name":"Jouvente",
    "wof:placetype":"locality"
},
  "geometry": {"coordinates":[-2.01987,48.59329],"type":"Point"}
}