{
  "type": "Feature",
  "properties": {
    "gn:admin1_code":"53",
    "gn:admin2_code":"56",
    "gn:admin3_code":"562",
    "gn:admin4_code":"56246",
    "gn:asciiname":"Saint-Michel",
    "gn:country_code":"FR",
    "gn:dem":59,
    "gn:feature_class":"P",
    "gn:feature_code":"PPL",
    "gn:name":"Saint-Michel",
    "gn:population":0,
    "gn:timezone":"Europe/Paris",
    "iso:country":"FR",
    "name:bre_x_preferred":[
        "Saint-Michel"
    ],
    "name:cat_x_preferred":[
        "Saint-Michel"
    ],
    "name:ceb_x_preferred":[
        "Saint-Michel"
    ],
    "name:ces_x_preferred":[
        "Saint-Michel"
    ],
    "name:deu_x_preferred":[
        "Saint-Michel"
    ],
    "name:eus_x_preferred":[
        "Saint-Michel"
    ],
    "name:fra_x_preferred":[
        "Saint-Michel"
    ],
    "name:heb_x_preferred":[
        "\u05e1\u05df-\u05de\u05d9\u05e9\u05dc"
    ],
    "name:ita_x_preferred":[
        "Saint-Michel"
    ],
    "name:jpn_x_preferred":[
        "\u30b5\u30f3\u30fb\u30df\u30b7\u30a7\u30eb"
    ],
    "name:kor_x_preferred":[
        "\uc0dd\ubbf8\uc178"
    ],
    "name:lmo_x_preferred":[
        "Saint-Michel"
    ],
    "name:nds_x_preferred":[
        "Saint-Michel"
    ],
    "name:nld_x_preferred":[
        "Saint-Michel"
    ],
    "name:pms_x_preferred":[
        "Saint-Michel"
    ],
    "name:pol_x_preferred":[
        "Saint-Michel"
    ],
    "name:por_x_preferred":[
        "Saint-Michel"
    ],
    "name:rus_x_preferred":[
        "\u0421\u0435\u043d-\u041c\u0438\u0448\u0435\u043b\u044c"
    ],
    "name:sco_x_preferred":[
        "Saint-Michel"
    ],
    "name:slk_x_preferred":[
        "Saint-Michel"
    ],
    "name:slv_x_preferred":[
        "Saint-Michel"
    ],
    "name:spa_x_preferred":[
        "Saint-Michel"
    ],
    "name:swe_x_preferred":[
        "Saint-Michel"
    ],
    "name:ukr_x_preferred":[
        "\u0421\u0435\u043d-\u041c\u0456\u0448\u0435\u043b\u044c"
    ],
    "wof:name":"Saint-Michel",
    "wof:placetype":"locality"
},
  "geometry": {"coordinates":[-2.96875,48.04125],"type":"Point"}
}