{
  "type": "Feature",
  "properties": {
    "gn:admin1_code":"53",
    "gn:admin2_code":"56",
    "gn:admin3_code":"562",
    "gn:admin4_code":"56246",
    "gn:asciiname":"Saint-Michel",
    "gn:country_code":"FR",
    "gn:dem":59,
    "gn:feature_class":"P",
    "gn:feature_code":"PPL",
    "gn:name":"Saint-Michel",
    "gn:population":0,
    "gn:timezone":"Europe/Paris",
    "iso:country":"FR",
    "wof:name":"Saint-Michel",
    "wof:placetype":"locality"
},
  "geometry": {"coordinates":[-2.96875,48.04125],"type":"Point"}
}