{
  "type": "Feature",
  "properties": {
    "gn:admin1_code":"28",
    "gn:admin2_code":"61",
    "gn:admin3_code":"613",
    "gn:admin4_code":"61327",
    "gn:asciiname":"Voirie",
    "gn:country_code":"FR",
    "gn:dem":179,
    "gn:feature_class":"P",
    "gn:feature_code":"PPL",
    "gn:name":"Voirie",
    "gn:population":0,
    "gn:timezone":"Europe/Paris",
    "iso:country":"FR",
    "wof:name":"Voirie",
    "wof:placetype":"locality"
},
  "geometry": {"coordinates":[0.44344,48.45466],"type":"Point"}
}