{
  "type": "Feature",
  "properties": {
    "gn:admin1_code":"75",
    "gn:admin2_code":"19",
    "gn:admin3_code":"193",
    "gn:admin4_code":"19265",
    "gn:asciiname":"Javeaux",
    "gn:country_code":"FR",
    "gn:dem":798,
    "gn:feature_class":"P",
    "gn:feature_code":"PPL",
    "gn:name":"Javeaux",
    "gn:population":0,
    "gn:timezone":"Europe/Paris",
    "iso:country":"FR",
    "wof:name":"Javeaux",
    "wof:placetype":"locality"
},
  "geometry": {"coordinates":[1.95127,45.66984],"type":"Point"}
}