{
  "type": "Feature",
  "properties": {
    "gn:admin1_code":"76",
    "gn:admin2_code":"30",
    "gn:admin3_code":"303",
    "gn:admin4_code":"30108",
    "gn:asciiname":"Saint-Martin-de-Corconac",
    "gn:country_code":"FR",
    "gn:dem":356,
    "gn:feature_class":"P",
    "gn:feature_code":"PPL",
    "gn:name":"Saint-Martin-de-Corconac",
    "gn:population":0,
    "gn:timezone":"Europe/Paris",
    "iso:country":"FR",
    "name:und_x_variant":[
        "Saint-Martin",
        "Saint-Martin-de-Corconac"
    ],
    "wof:name":"Saint-Martin-de-Corconac",
    "wof:placetype":"locality"
},
  "geometry": {"coordinates":[3.79942,44.10152],"type":"Point"}
}