{
  "type": "Feature",
  "properties": {
    "gn:admin1_code":"52",
    "gn:admin2_code":"72",
    "gn:admin3_code":"723",
    "gn:admin4_code":"72101",
    "gn:asciiname":"La Douardiere",
    "gn:country_code":"FR",
    "gn:dem":97,
    "gn:feature_class":"P",
    "gn:feature_code":"PPL",
    "gn:name":"La Douardi\u00e8re",
    "gn:population":0,
    "gn:timezone":"Europe/Paris",
    "iso:country":"FR",
    "name:und_x_variant":[
        "La Bouvardi\u00e8re",
        "La Douardi\u00e8re"
    ],
    "wof:name":"La Douardiere",
    "wof:placetype":"locality"
},
  "geometry": {"coordinates":[0.36085,48.18153],"type":"Point"}
}