{
  "type": "Feature",
  "properties": {
    "gn:admin1_code":"28",
    "gn:admin2_code":"61",
    "gn:admin3_code":"611",
    "gn:admin4_code":"61331",
    "gn:asciiname":"Le Val-Ruse",
    "gn:country_code":"FR",
    "gn:dem":183,
    "gn:feature_class":"P",
    "gn:feature_code":"PPL",
    "gn:name":"Le Val-Rus\u00e9",
    "gn:population":0,
    "gn:timezone":"Europe/Paris",
    "iso:country":"FR",
    "wof:name":"Le Val-Ruse",
    "wof:placetype":"locality"
},
  "geometry": {"coordinates":[0.41667,48.61667],"type":"Point"}
}