{
  "type": "Feature",
  "properties": {
    "gn:admin1_code":"24",
    "gn:admin2_code":"18",
    "gn:admin3_code":"181",
    "gn:admin4_code":"18206",
    "gn:asciiname":"Breuilly",
    "gn:country_code":"FR",
    "gn:dem":179,
    "gn:feature_class":"P",
    "gn:feature_code":"PPL",
    "gn:name":"Breuilly",
    "gn:population":0,
    "gn:timezone":"Europe/Paris",
    "iso:country":"FR",
    "wof:name":"Breuilly",
    "wof:placetype":"locality"
},
  "geometry": {"coordinates":[2.34905,47.16153],"type":"Point"}
}