{
  "type": "Feature",
  "properties": {
    "gn:admin1_code":"52",
    "gn:admin2_code":"72",
    "gn:admin3_code":"722",
    "gn:admin4_code":"72088",
    "gn:asciiname":"La Senerie",
    "gn:country_code":"FR",
    "gn:dem":65,
    "gn:feature_class":"P",
    "gn:feature_code":"PPL",
    "gn:name":"La S\u00e9nerie",
    "gn:population":0,
    "gn:timezone":"Europe/Paris",
    "iso:country":"FR",
    "wof:name":"La Senerie",
    "wof:placetype":"locality"
},
  "geometry": {"coordinates":[0.267,48.22421],"type":"Point"}
}