{
  "type": "Feature",
  "properties": {
    "gn:admin1_code":"53",
    "gn:admin2_code":"56",
    "gn:admin3_code":"563",
    "gn:admin4_code":"56194",
    "gn:asciiname":"Auquefer",
    "gn:country_code":"FR",
    "gn:dem":21,
    "gn:feature_class":"P",
    "gn:feature_code":"PPL",
    "gn:name":"Auquefer",
    "gn:population":0,
    "gn:timezone":"Europe/Paris",
    "iso:country":"FR",
    "name:und_x_variant":[
        "Aucfer",
        "Auquefer"
    ],
    "wof:name":"Auquefer",
    "wof:placetype":"locality"
},
  "geometry": {"coordinates":[-2.10504,47.63247],"type":"Point"}
}