{
  "type": "Feature",
  "properties": {
    "gn:admin1_code":"24",
    "gn:admin2_code":"45",
    "gn:admin3_code":"452",
    "gn:admin4_code":"45270",
    "gn:asciiname":"Fleury",
    "gn:country_code":"FR",
    "gn:dem":111,
    "gn:feature_class":"P",
    "gn:feature_code":"PPL",
    "gn:name":"Fleury",
    "gn:population":0,
    "gn:timezone":"Europe/Paris",
    "iso:country":"FR",
    "name:ces_x_preferred":[
        "Kl\u00e1\u0161ter Saint-Beno\u00eet-sur-Loire"
    ],
    "name:deu_x_preferred":[
        "Fleury"
    ],
    "name:epo_x_preferred":[
        "Abatejo Fleury"
    ],
    "name:eus_x_preferred":[
        "Fleury abadia"
    ],
    "name:pol_x_preferred":[
        "Opactwo Fleury"
    ],
    "name:rus_x_preferred":[
        "\u0410\u0431\u0431\u0430\u0442\u0441\u0442\u0432\u043e \u0424\u043b\u0451\u0440\u0438"
    ],
    "name:slk_x_preferred":[
        "Kl\u00e1\u0161tor Saint-Beno\u00eet-sur-Loire"
    ],
    "name:tha_x_preferred":[
        "\u0e2d\u0e32\u0e23\u0e32\u0e21\u0e41\u0e0b\u0e47\u0e07-\u0e40\u0e1a\u0e2d\u0e19\u0e31\u0e27-\u0e0b\u0e39\u0e23\u0e4c-\u0e25\u0e31\u0e27\u0e23\u0e4c"
    ],
    "name:zho_x_preferred":[
        "\u5f17\u52d2\u91cc\u4fee\u9053\u9662"
    ],
    "wof:name":"Fleury",
    "wof:placetype":"locality"
},
  "geometry": {"coordinates":[2.31321,47.80281],"type":"Point"}
}