{
  "type": "Feature",
  "properties": {
    "gn:admin1_code":"84",
    "gn:admin2_code":"69",
    "gn:admin3_code":"691",
    "gn:admin4_code":"69297",
    "gn:asciiname":"Flevieu",
    "gn:country_code":"FR",
    "gn:dem":205,
    "gn:feature_class":"P",
    "gn:feature_code":"PPL",
    "gn:name":"Flevieu",
    "gn:population":0,
    "gn:timezone":"Europe/Paris",
    "iso:country":"FR",
    "wof:name":"Flevieu",
    "wof:placetype":"locality"
},
  "geometry": {"coordinates":[4.79907,45.59681],"type":"Point"}
}