{
  "type": "Feature",
  "properties": {
    "gn:country":"FR",
    "gn:fcode":"PPL",
    "gn:population":0,
    "iso:country":"FR",
    "qs_pg:aaroncc":"FR",
    "qs_pg:gn_country":"FR",
    "qs_pg:gn_fcode":"PPL",
    "qs_pg:gn_pop":0,
    "qs_pg:name":"Le Pouldu",
    "qs_pg:name_adm0":"France",
    "qs_pg:name_adm1":"Bretagne",
    "qs_pg:photos":531,
    "qs_pg:photos_1k":108,
    "qs_pg:photos_9k":2,
    "qs_pg:photos_9r":5,
    "qs_pg:photos_all":531,
    "qs_pg:photos_sr":7,
    "qs_pg:pop_sr":0,
    "qs_pg:qs_pg_placetype":"locality",
    "qs_pg:qs_pg_placetype_gp":"Town",
    "qs_pg:woe_adm0":23424819,
    "woe:adm0_id":23424819,
    "woe:name_adm0":"France",
    "woe:name_adm1":"Bretagne",
    "woe:placetype":"Town",
    "wof:name":"Le Pouldu",
    "wof:placetype":"neighbourhood"
},
  "geometry": {"coordinates":[-3.54358,47.76787],"type":"Point"}
}