{
  "type": "Feature",
  "properties": {
    "gn:admin1_code":"24",
    "gn:admin2_code":"45",
    "gn:admin3_code":"451",
    "gn:admin4_code":"45094.0",
    "gn:asciiname":"Les Cottencins",
    "gn:cc2":"FR",
    "gn:country_code":"FR",
    "gn:dem":120,
    "gn:feature_class":"P",
    "gn:feature_code":"PPL",
    "gn:name":"Les Cottencins",
    "gn:population":0,
    "gn:timezone":"Europe/Paris",
    "iso:country":"FR",
    "name:und_x_variant":[
        "Les Cottancins",
        "Les Cottencins"
    ],
    "wof:name":"Les Cottencins",
    "wof:placetype":"locality"
},
  "geometry": {"coordinates":[2.8882,48.14582],"type":"Point"}
}