{
  "type": "Feature",
  "properties": {
    "gn:admin1_code":"84",
    "gn:admin2_code":"07",
    "gn:admin3_code":"073",
    "gn:admin4_code":"7250.0",
    "gn:asciiname":"Saint-Jeure-d'Ay",
    "gn:country_code":"FR",
    "gn:dem":469,
    "gn:feature_class":"P",
    "gn:feature_code":"PPL",
    "gn:name":"Saint-Jeure-d\u2019Ay",
    "gn:population":0,
    "gn:timezone":"Europe/Paris",
    "iso:country":"FR",
    "name:und_x_variant":[
        "Saint-Jeure",
        "Saint-Jeure-d\u2019Ay"
    ],
    "wof:name":"Saint-Jeure-d'Ay",
    "wof:placetype":"locality"
},
  "geometry": {"coordinates":[4.70611,45.14736],"type":"Point"}
}