{
  "type": "Feature",
  "properties": {
    "gn:admin1_code":"84",
    "gn:admin2_code":"07",
    "gn:admin3_code":"073",
    "gn:admin4_code":"7250.0",
    "gn:asciiname":"Saint-Jeure-d'Ay",
    "gn:country_code":"FR",
    "gn:dem":469,
    "gn:feature_class":"P",
    "gn:feature_code":"PPL",
    "gn:name":"Saint-Jeure-d\u2019Ay",
    "gn:population":0,
    "gn:timezone":"Europe/Paris",
    "iso:country":"FR",
    "name:bug_x_preferred":[
        "Saint-Jeure-d'Ay"
    ],
    "name:ceb_x_preferred":[
        "Saint-Jeure-d'Ay"
    ],
    "name:deu_x_preferred":[
        "Saint-Jeure-d\u2019Ay"
    ],
    "name:eus_x_preferred":[
        "Saint-Jeure-d'Ay"
    ],
    "name:fra_x_preferred":[
        "Saint-Jeure-d'Ay"
    ],
    "name:hun_x_preferred":[
        "Saint-Jeure-d\u2019Ay"
    ],
    "name:ita_x_preferred":[
        "Saint-Jeure-d'Ay"
    ],
    "name:lat_x_preferred":[
        "Saint-Jeure-d'Ay"
    ],
    "name:lmo_x_preferred":[
        "Saint-Jeure-d'Ay"
    ],
    "name:mlg_x_preferred":[
        "Saint-Jeure-d'Ay"
    ],
    "name:msa_x_preferred":[
        "Saint-Jeure-d'Ay"
    ],
    "name:nld_x_preferred":[
        "Saint-Jeure-d'Ay"
    ],
    "name:pms_x_preferred":[
        "Saint-Jeure-d'Ay"
    ],
    "name:pol_x_preferred":[
        "Saint-Jeure-d\u2019Ay"
    ],
    "name:por_x_preferred":[
        "Saint-Jeure-d'Ay"
    ],
    "name:ron_x_preferred":[
        "Saint-Jeure-d'Ay"
    ],
    "name:rus_x_preferred":[
        "\u0421\u0435\u043d-\u0416\u0451\u0440-\u0434\u2019\u042d"
    ],
    "name:slk_x_preferred":[
        "Saint-Jeure-d\u2019Ay"
    ],
    "name:spa_x_preferred":[
        "Saint-Jeure-d'Ay"
    ],
    "name:sqi_x_preferred":[
        "Saint-Jeure-d'Ay"
    ],
    "name:swe_x_preferred":[
        "Saint-Jeure-d'Ay"
    ],
    "name:ukr_x_preferred":[
        "\u0421\u0435\u043d-\u0416\u0435\u0440-\u0434'\u0415"
    ],
    "name:und_x_variant":[
        "Saint-Jeure"
    ],
    "name:urd_x_preferred":[
        "\u0633\u06cc\u0646\u0679-\u062c\u0648\u0691\u06d2-\u062f\u06d2"
    ],
    "name:uzb_x_preferred":[
        "Saint-Jeure-d'Ay"
    ],
    "name:vie_x_preferred":[
        "Saint-Jeure-d'Ay"
    ],
    "name:vol_x_preferred":[
        "Saint-Jeure-d'Ay"
    ],
    "name:war_x_preferred":[
        "Saint-Jeure-d'Ay"
    ],
    "name:zho_x_preferred":[
        "\u5723\u70ed\u5c14\u4ee3"
    ],
    "wof:name":"Saint-Jeure-d'Ay",
    "wof:placetype":"locality"
},
  "geometry": {"coordinates":[4.70611,45.14736],"type":"Point"}
}