{
  "type": "Feature",
  "properties": {
    "gn:admin1_code":"84",
    "gn:admin2_code":"63",
    "gn:admin3_code":"631",
    "gn:admin4_code":"63179.0",
    "gn:asciiname":"Les Chassaings",
    "gn:country_code":"FR",
    "gn:dem":640,
    "gn:feature_class":"P",
    "gn:feature_code":"PPL",
    "gn:name":"Les Chassaings",
    "gn:population":0,
    "gn:timezone":"Europe/Paris",
    "iso:country":"FR",
    "wof:name":"Les Chassaings",
    "wof:placetype":"locality"
},
  "geometry": {"coordinates":[3.73333,45.63333],"type":"Point"}
}