{
  "type": "Feature",
  "properties": {
    "gn:admin1_code":"84",
    "gn:admin2_code":"03",
    "gn:admin3_code":"032",
    "gn:admin4_code":"03238",
    "gn:asciiname":"Buchatiere",
    "gn:country_code":"FR",
    "gn:dem":330,
    "gn:feature_class":"P",
    "gn:feature_code":"PPL",
    "gn:name":"Buchati\u00e8re",
    "gn:population":0,
    "gn:timezone":"Europe/Paris",
    "iso:country":"FR",
    "wof:name":"Buchatiere",
    "wof:placetype":"locality"
},
  "geometry": {"coordinates":[3.01077,46.47856],"type":"Point"}
}