{
  "type": "Feature",
  "properties": {
    "gn:admin1_code":"84",
    "gn:admin2_code":"43",
    "gn:admin3_code":"431",
    "gn:admin4_code":"43262",
    "gn:asciiname":"Vedrines",
    "gn:country_code":"FR",
    "gn:dem":564,
    "gn:feature_class":"P",
    "gn:feature_code":"PPL",
    "gn:name":"V\u00e9drines",
    "gn:population":0,
    "gn:timezone":"Europe/Paris",
    "iso:country":"FR",
    "wof:name":"Vedrines",
    "wof:placetype":"locality"
},
  "geometry": {"coordinates":[3.38915,45.24576],"type":"Point"}
}