{
  "type": "Feature",
  "properties": {
    "gn:admin1_code":"75",
    "gn:admin2_code":"23",
    "gn:admin3_code":"231",
    "gn:admin4_code":"23080",
    "gn:asciiname":"Maugenoueix",
    "gn:country_code":"FR",
    "gn:dem":838,
    "gn:feature_class":"P",
    "gn:feature_code":"PPL",
    "gn:name":"Maugenoueix",
    "gn:population":0,
    "gn:timezone":"Europe/Paris",
    "iso:country":"FR",
    "wof:name":"Maugenoueix",
    "wof:placetype":"locality"
},
  "geometry": {"coordinates":[2.13333,45.76667],"type":"Point"}
}