{
  "type": "Feature",
  "properties": {
    "frgov:code_epci":"200042703",
    "frgov:insee_arr":"5",
    "frgov:insee_com":"51228",
    "frgov:insee_dep":"51",
    "frgov:insee_reg":"44",
    "frgov:nom_com":"\u00c9lise-Daucourt",
    "frgov:nom_com_m":"ELISE-DAUCOURT",
    "frgov:nom_dep":"MARNE",
    "frgov:nom_reg":"GRAND EST",
    "frgov:statut":"Commune simple",
    "gn:admin1_code":"44",
    "gn:admin2_code":"51",
    "gn:admin3_code":"515",
    "gn:admin4_code":"51228",
    "gn:asciiname":"Elise-Daucourt",
    "gn:country_code":"FR",
    "gn:dem":171,
    "gn:feature_class":"P",
    "gn:feature_code":"PPL",
    "gn:name":"\u00c9lise-Daucourt",
    "gn:population":0,
    "gn:timezone":"Europe/Paris",
    "iso:country":"FR",
    "name:fra_x_preferred":[
        "\u00c9lise-Daucourt"
    ],
    "qs:a0":"France",
    "qs:a1":"MARNE",
    "qs:a1_lc":"51",
    "qs:a1r":"CHAMPAGNE-ARDENNE",
    "qs:a1r_lc":"21",
    "qs:a2_lc":"23",
    "qs:a2r_lc":"5",
    "qs:adm0":"France",
    "qs:adm0_a3":"FRA",
    "qs:la":"ELISE-DAUCOURT",
    "qs:la_lc":"51228",
    "qs:level":"localadmin",
    "qs:type":"Commune simple",
    "wof:coterminous":[
        404372829
    ],
    "wof:name":"Elise-Daucourt",
    "wof:placetype":"locality",
    "wof:placetype_local":"Commune simple"
},
  "geometry": {"coordinates":[4.86667,49.05],"type":"Point"}
}