{
  "type": "Feature",
  "properties": {
    "gn:admin1_code":"44",
    "gn:admin2_code":"51",
    "gn:admin3_code":"515",
    "gn:admin4_code":"51228",
    "gn:asciiname":"Elise-Daucourt",
    "gn:country_code":"FR",
    "gn:dem":171,
    "gn:feature_class":"P",
    "gn:feature_code":"PPL",
    "gn:name":"\u00c9lise-Daucourt",
    "gn:population":0,
    "gn:timezone":"Europe/Paris",
    "iso:country":"FR",
    "wof:name":"Elise-Daucourt",
    "wof:placetype":"locality"
},
  "geometry": {"coordinates":[4.86667,49.05],"type":"Point"}
}