{
  "type": "Feature",
  "properties": {
    "gn:admin1_code":"84",
    "gn:admin2_code":"63",
    "gn:admin3_code":"633",
    "gn:admin4_code":"63335",
    "gn:asciiname":"Bas",
    "gn:country_code":"FR",
    "gn:dem":723,
    "gn:feature_class":"P",
    "gn:feature_code":"PPL",
    "gn:name":"Bas",
    "gn:population":0,
    "gn:timezone":"Europe/Paris",
    "iso:country":"FR",
    "name:bel_x_preferred":[
        "\u0411\u0430\u0441"
    ],
    "name:bos_x_preferred":[
        "Bas"
    ],
    "name:bul_x_preferred":[
        "\u0411\u0430\u0441"
    ],
    "name:cat_x_preferred":[
        "Bas"
    ],
    "name:ceb_x_preferred":[
        "Bas"
    ],
    "name:dan_x_preferred":[
        "Bas"
    ],
    "name:deu_x_preferred":[
        "Bas"
    ],
    "name:hrv_x_preferred":[
        "Bas"
    ],
    "name:jpn_x_preferred":[
        "\u30d9\u30fc\u30b9"
    ],
    "name:nld_x_preferred":[
        "Bas"
    ],
    "name:pol_x_preferred":[
        "Bas"
    ],
    "name:por_x_preferred":[
        "Bas"
    ],
    "name:ron_x_preferred":[
        "Bas"
    ],
    "name:slk_x_preferred":[
        "Bas"
    ],
    "name:slv_x_preferred":[
        "Bas"
    ],
    "name:swe_x_preferred":[
        "Bas"
    ],
    "name:tur_x_preferred":[
        "Bas"
    ],
    "wof:name":"Bas",
    "wof:placetype":"locality"
},
  "geometry": {"coordinates":[3.03333,45.55],"type":"Point"}
}