{
  "type": "Feature",
  "properties": {
    "gn:admin1_code":"84",
    "gn:admin2_code":"07",
    "gn:admin3_code":"073",
    "gn:admin4_code":"07084",
    "gn:asciiname":"Les Bardons",
    "gn:country_code":"FR",
    "gn:dem":426,
    "gn:feature_class":"P",
    "gn:feature_code":"PPL",
    "gn:name":"Les Bardons",
    "gn:population":0,
    "gn:timezone":"Europe/Paris",
    "iso:country":"FR",
    "wof:name":"Les Bardons",
    "wof:placetype":"locality"
},
  "geometry": {"coordinates":[4.75928,45.16883],"type":"Point"}
}