{
  "type": "Feature",
  "properties": {
    "gn:admin1_code":"75",
    "gn:admin2_code":"24",
    "gn:admin3_code":"244",
    "gn:admin4_code":"24386",
    "gn:asciiname":"Saint-Cernin-de-l'Herm",
    "gn:country_code":"FR",
    "gn:dem":177,
    "gn:feature_class":"P",
    "gn:feature_code":"PPL",
    "gn:name":"Saint-Cernin-de-l\u2019Herm",
    "gn:population":0,
    "gn:timezone":"Europe/Paris",
    "iso:country":"FR",
    "name:bug_x_preferred":[
        "Saint-Cernin-de-l'Herm"
    ],
    "name:ceb_x_preferred":[
        "Saint-Cernin-de-l'Herm"
    ],
    "name:deu_x_preferred":[
        "Saint-Cernin-de-l\u2019Herm"
    ],
    "name:eus_x_preferred":[
        "Saint-Cernin-de-l'Herm"
    ],
    "name:fra_x_preferred":[
        "Saint-Cernin-de-l'Herm"
    ],
    "name:hun_x_preferred":[
        "Saint-Cernin-de-l\u2019Herm"
    ],
    "name:ita_x_preferred":[
        "Saint-Cernin-de-l'Herm"
    ],
    "name:kaz_x_preferred":[
        "\u0421\u0435\u043d-\u0421\u0435\u0440\u043d\u0435\u043d-\u0434\u0435-\u043b'\u0415\u0440\u043c"
    ],
    "name:lat_x_preferred":[
        "Saint-Cernin-de-l'Herm"
    ],
    "name:mlg_x_preferred":[
        "Saint-Cernin-de-l'Herm"
    ],
    "name:msa_x_preferred":[
        "Saint-Cernin-de-l'Herm"
    ],
    "name:nld_x_preferred":[
        "Saint-Cernin-de-l'Herm"
    ],
    "name:pms_x_preferred":[
        "Saint-Cernin-de-l'Herm"
    ],
    "name:pol_x_preferred":[
        "Saint-Cernin-de-l\u2019Herm"
    ],
    "name:por_x_preferred":[
        "Saint-Cernin-de-l'Herm"
    ],
    "name:ron_x_preferred":[
        "Saint-Cernin-de-l'Herm"
    ],
    "name:slk_x_preferred":[
        "Saint-Cernin-de-l\u2019Herm"
    ],
    "name:spa_x_preferred":[
        "Saint-Cernin-de-l'Herm"
    ],
    "name:swe_x_preferred":[
        "Saint-Cernin-de-l'Herm"
    ],
    "name:ukr_x_preferred":[
        "\u0421\u0435\u043d-\u0421\u0435\u0440\u043d\u0435\u043d-\u0434\u0435-\u043b'\u0415\u0440\u043c"
    ],
    "name:und_x_variant":[
        "Saint-Cernin",
        "Saint-Cernin-de-l\u2019Herm"
    ],
    "name:urd_x_preferred":[
        "\u0633\u06cc\u0646\u0679-\u06a9\u0631\u0646\u06cc\u06ba -\u062f\u06d2-\u0644\u062d\u0631\u0645"
    ],
    "name:uzb_x_preferred":[
        "Saint-Cernin-de-l'Herm"
    ],
    "name:vie_x_preferred":[
        "Saint-Cernin-de-l'Herm"
    ],
    "name:vol_x_preferred":[
        "Saint-Cernin-de-l'Herm"
    ],
    "name:war_x_preferred":[
        "Saint-Cernin-de-l'Herm"
    ],
    "name:zho_x_preferred":[
        "\u5723\u585e\u5c14\u5357\u5fb7\u8036\u5c14\u59c6"
    ],
    "wof:name":"Saint-Cernin-de-l'Herm",
    "wof:placetype":"locality"
},
  "geometry": {"coordinates":[1.0318,44.63924],"type":"Point"}
}