{
  "type": "Feature",
  "properties": {
    "gn:admin1_code":"75",
    "gn:admin2_code":"24",
    "gn:admin3_code":"244",
    "gn:admin4_code":"24386",
    "gn:asciiname":"Saint-Cernin-de-l'Herm",
    "gn:country_code":"FR",
    "gn:dem":177,
    "gn:feature_class":"P",
    "gn:feature_code":"PPL",
    "gn:name":"Saint-Cernin-de-l\u2019Herm",
    "gn:population":0,
    "gn:timezone":"Europe/Paris",
    "iso:country":"FR",
    "name:und_x_variant":[
        "Saint-Cernin",
        "Saint-Cernin-de-l\u2019Herm"
    ],
    "wof:name":"Saint-Cernin-de-l'Herm",
    "wof:placetype":"locality"
},
  "geometry": {"coordinates":[1.0318,44.63924],"type":"Point"}
}