{
  "type": "Feature",
  "properties": {
    "gn:admin1_code":"27",
    "gn:admin2_code":"21",
    "gn:admin3_code":"212",
    "gn:admin4_code":"21016",
    "gn:asciiname":"Fouchanges",
    "gn:country_code":"FR",
    "gn:dem":239,
    "gn:feature_class":"P",
    "gn:feature_code":"PPL",
    "gn:name":"Fouchanges",
    "gn:population":0,
    "gn:timezone":"Europe/Paris",
    "iso:country":"FR",
    "wof:name":"Fouchanges",
    "wof:placetype":"locality"
},
  "geometry": {"coordinates":[5.19639,47.39727],"type":"Point"}
}