{
  "type": "Feature",
  "properties": {
    "gn:admin1_code":"93",
    "gn:admin2_code":"04",
    "gn:admin3_code":"044",
    "gn:admin4_code":"04049",
    "gn:asciiname":"Saint-Auban",
    "gn:country_code":"FR",
    "gn:dem":466,
    "gn:feature_class":"P",
    "gn:feature_code":"PPL",
    "gn:name":"Saint-Auban",
    "gn:population":0,
    "gn:timezone":"Europe/Paris",
    "iso:country":"FR",
    "name:und_x_variant":[
        "Saint Aubon",
        "Saint-Auban"
    ],
    "wof:name":"Saint-Auban",
    "wof:placetype":"locality"
},
  "geometry": {"coordinates":[5.9921,44.07174000000001],"type":"Point"}
}