{
  "type": "Feature",
  "properties": {
    "gn:admin1_code":"93",
    "gn:admin2_code":"04",
    "gn:admin3_code":"044",
    "gn:admin4_code":"04049",
    "gn:asciiname":"Saint-Auban",
    "gn:country_code":"FR",
    "gn:dem":466,
    "gn:feature_class":"P",
    "gn:feature_code":"PPL",
    "gn:name":"Saint-Auban",
    "gn:population":0,
    "gn:timezone":"Europe/Paris",
    "iso:country":"FR",
    "name:ara_x_preferred":[
        "\u0633\u0627\u0646 \u0623\u0648\u0628\u0627\u0646"
    ],
    "name:bug_x_preferred":[
        "Saint-Auban"
    ],
    "name:cat_x_preferred":[
        "Sant Auban"
    ],
    "name:ceb_x_preferred":[
        "Saint-Auban"
    ],
    "name:deu_x_preferred":[
        "Saint-Auban"
    ],
    "name:eus_x_preferred":[
        "Saint-Auban"
    ],
    "name:fra_x_preferred":[
        "Saint-Auban"
    ],
    "name:hun_x_preferred":[
        "Saint-Auban"
    ],
    "name:hye_x_preferred":[
        "\u054d\u0565\u0576\u057f \u0555\u0562\u0561\u0576"
    ],
    "name:ind_x_preferred":[
        "Saint-Auban"
    ],
    "name:ita_x_preferred":[
        "Saint-Auban"
    ],
    "name:lat_x_preferred":[
        "Saint-Auban"
    ],
    "name:lmo_x_preferred":[
        "Saint-Auban"
    ],
    "name:msa_x_preferred":[
        "Saint-Auban"
    ],
    "name:nld_x_preferred":[
        "Saint-Auban"
    ],
    "name:oci_x_preferred":[
        "Sant Auban"
    ],
    "name:pms_x_preferred":[
        "Saint-Auban"
    ],
    "name:pol_x_preferred":[
        "Saint-Auban"
    ],
    "name:por_x_preferred":[
        "Saint-Auban"
    ],
    "name:ron_x_preferred":[
        "Saint-Auban"
    ],
    "name:rus_x_preferred":[
        "\u0421\u0435\u043d\u0442-\u041e\u0431\u0430\u043d"
    ],
    "name:slk_x_preferred":[
        "Saint-Auban"
    ],
    "name:slv_x_preferred":[
        "Saint-Auban"
    ],
    "name:spa_x_preferred":[
        "Saint-Auban"
    ],
    "name:sqi_x_preferred":[
        "Saint-Auban"
    ],
    "name:swe_x_preferred":[
        "Saint-Auban"
    ],
    "name:ukr_x_preferred":[
        "\u0421\u0435\u043d\u0442-\u041e\u0431\u0430\u043d"
    ],
    "name:und_x_variant":[
        "Saint Aubon",
        "Saint-Auban"
    ],
    "name:urd_x_preferred":[
        "\u0633\u06cc\u0646\u0679-\u0627\u0628\u0646"
    ],
    "name:vie_x_preferred":[
        "Saint-Auban"
    ],
    "name:vol_x_preferred":[
        "Saint-Auban"
    ],
    "name:war_x_preferred":[
        "Saint-Auban"
    ],
    "name:zho_x_preferred":[
        "\u5723\u6b27\u90a6"
    ],
    "wof:name":"Saint-Auban",
    "wof:placetype":"locality"
},
  "geometry": {"coordinates":[5.9921,44.07174000000001],"type":"Point"}
}