{
  "type": "Feature",
  "properties": {
    "gn:admin1_code":"84",
    "gn:admin2_code":"73",
    "gn:admin3_code":"732",
    "gn:admin4_code":"73200",
    "gn:asciiname":"Le Puiset",
    "gn:country_code":"FR",
    "gn:dem":354,
    "gn:feature_class":"P",
    "gn:feature_code":"PPL",
    "gn:name":"Le Puiset",
    "gn:population":0,
    "gn:timezone":"Europe/Paris",
    "iso:country":"FR",
    "name:bug_x_preferred":[
        "Le Puiset"
    ],
    "name:cat_x_preferred":[
        "Le Puiset"
    ],
    "name:ceb_x_preferred":[
        "Le Puiset"
    ],
    "name:deu_x_preferred":[
        "Le Puiset"
    ],
    "name:eus_x_preferred":[
        "Le Puiset"
    ],
    "name:fra_x_preferred":[
        "Le Puiset"
    ],
    "name:hun_x_preferred":[
        "Le Puiset"
    ],
    "name:ita_x_preferred":[
        "Le Puiset"
    ],
    "name:lat_x_preferred":[
        "Le Puiset"
    ],
    "name:msa_x_preferred":[
        "Le Puiset"
    ],
    "name:nld_x_preferred":[
        "Le Puiset"
    ],
    "name:oci_x_preferred":[
        "Le Puiset"
    ],
    "name:pms_x_preferred":[
        "Puiset"
    ],
    "name:pol_x_preferred":[
        "Le Puiset"
    ],
    "name:por_x_preferred":[
        "Le Puiset"
    ],
    "name:ron_x_preferred":[
        "Le Puiset"
    ],
    "name:slk_x_preferred":[
        "Le Puiset"
    ],
    "name:spa_x_preferred":[
        "Le Puiset"
    ],
    "name:swe_x_preferred":[
        "Le Puiset"
    ],
    "name:ukr_x_preferred":[
        "\u041b\u0435-\u041f\u044e\u0457\u0437\u0435"
    ],
    "name:uzb_x_preferred":[
        "Le Puiset"
    ],
    "name:vie_x_preferred":[
        "Le Puiset"
    ],
    "name:vol_x_preferred":[
        "Le Puiset"
    ],
    "name:war_x_preferred":[
        "Le Puiset"
    ],
    "name:zho_x_preferred":[
        "\u52d2\u76ae\u4f0a\u585e"
    ],
    "wof:name":"Le Puiset",
    "wof:placetype":"locality"
},
  "geometry": {"coordinates":[6.10445,45.50893],"type":"Point"}
}