{
  "type": "Feature",
  "properties": {
    "iso:country":"FR",
    "name:eng_x_preferred":[
        "Paul Eluard"
    ],
    "name:fer_x_variant":[
        "Cit\u00e9 Paul Eluard"
    ],
    "name:fra_x_preferred":[
        "Paul Eluard"
    ],
    "wof:name":"Paul Eluard",
    "wof:placetype":"neighbourhood"
},
  "geometry": {"coordinates":[2.44396283497132,48.90825203710616],"type":"Point"}
}