{
  "type": "Feature",
  "properties": {
    "gn:admin1_code":"28",
    "gn:admin2_code":"27",
    "gn:admin3_code":"271",
    "gn:admin4_code":"27329",
    "gn:asciiname":"L'Epinay",
    "gn:country_code":"FR",
    "gn:dem":148,
    "gn:feature_class":"P",
    "gn:feature_code":"PPL",
    "gn:name":"L\u2019\u00c9pinay",
    "gn:population":0,
    "gn:timezone":"Europe/Paris",
    "iso:country":"FR",
    "wof:name":"L'Epinay",
    "wof:placetype":"locality"
},
  "geometry": {"coordinates":[1.45671,49.19904],"type":"Point"}
}