{
  "type": "Feature",
  "properties": {
    "gn:admin1_code":"24",
    "gn:admin2_code":"36",
    "gn:admin3_code":"361",
    "gn:admin4_code":"36096",
    "gn:asciiname":"Gabriau",
    "gn:country_code":"FR",
    "gn:dem":89,
    "gn:feature_class":"P",
    "gn:feature_code":"PPL",
    "gn:name":"Gabriau",
    "gn:population":0,
    "gn:timezone":"Europe/Paris",
    "iso:country":"FR",
    "wof:name":"Gabriau",
    "wof:placetype":"locality"
},
  "geometry": {"coordinates":[1.1549,46.76293],"type":"Point"}
}