{
  "type": "Feature",
  "properties": {
    "gn:admin1_code":"53",
    "gn:admin2_code":"22",
    "gn:admin3_code":"221",
    "gn:admin4_code":"22190",
    "gn:asciiname":"La Rougerais",
    "gn:country_code":"FR",
    "gn:dem":71,
    "gn:feature_class":"P",
    "gn:feature_code":"PPL",
    "gn:name":"La Rougerais",
    "gn:population":0,
    "gn:timezone":"Europe/Paris",
    "iso:country":"FR",
    "wof:name":"La Rougerais",
    "wof:placetype":"locality"
},
  "geometry": {"coordinates":[-2.08776,48.52748],"type":"Point"}
}