{
  "type": "Feature",
  "properties": {
    "gn:admin1_code":"76",
    "gn:admin2_code":"31",
    "gn:admin3_code":"312",
    "gn:admin4_code":"31302",
    "gn:asciiname":"Lodes",
    "gn:country_code":"FR",
    "gn:dem":408,
    "gn:feature_class":"P",
    "gn:feature_code":"PPL",
    "gn:name":"Lodes",
    "gn:population":285,
    "gn:timezone":"Europe/Paris",
    "iso:country":"FR",
    "name:arg_x_preferred":[
        "L\u00f2das"
    ],
    "name:bug_x_preferred":[
        "Lodes"
    ],
    "name:cat_x_preferred":[
        "L\u00f2das"
    ],
    "name:ceb_x_preferred":[
        "Lodes"
    ],
    "name:deu_x_preferred":[
        "Lodes"
    ],
    "name:eus_x_preferred":[
        "Lodes"
    ],
    "name:fra_x_preferred":[
        "Lodes"
    ],
    "name:hun_x_preferred":[
        "Lodes"
    ],
    "name:ita_x_preferred":[
        "Lodes"
    ],
    "name:lat_x_preferred":[
        "Lodes"
    ],
    "name:msa_x_preferred":[
        "Lodes"
    ],
    "name:nld_x_preferred":[
        "Lodes"
    ],
    "name:oci_x_preferred":[
        "L\u00f2das"
    ],
    "name:pol_x_preferred":[
        "Lodes"
    ],
    "name:ron_x_preferred":[
        "Lodes"
    ],
    "name:rus_x_preferred":[
        "\u041b\u043e\u0434"
    ],
    "name:slk_x_preferred":[
        "Lodes"
    ],
    "name:spa_x_preferred":[
        "Lodes"
    ],
    "name:swe_x_preferred":[
        "Lodes"
    ],
    "name:ukr_x_preferred":[
        "\u041b\u043e\u0434"
    ],
    "name:vie_x_preferred":[
        "Lodes"
    ],
    "name:vol_x_preferred":[
        "Lodes"
    ],
    "name:war_x_preferred":[
        "Lodes"
    ],
    "wof:name":"Lodes",
    "wof:placetype":"locality",
    "wof:population":285
},
  "geometry": {"coordinates":[0.67661,43.16982],"type":"Point"}
}