{
  "type": "Feature",
  "properties": {
    "gn:admin1_code":"84",
    "gn:admin2_code":"63",
    "gn:admin3_code":"632",
    "gn:admin4_code":"63451",
    "gn:asciiname":"Neuville",
    "gn:country_code":"FR",
    "gn:dem":957,
    "gn:feature_class":"P",
    "gn:feature_code":"PPL",
    "gn:name":"Neuville",
    "gn:population":0,
    "gn:timezone":"Europe/Paris",
    "iso:country":"FR",
    "wof:name":"Neuville",
    "wof:placetype":"locality"
},
  "geometry": {"coordinates":[2.88472,45.68776],"type":"Point"}
}